{
  "type": "FeatureCollection",
  "title": "Puente Melchor Roman villa",
  "id": "102500043",
  "bbox": [
    -6.1627413,
    36.5215031,
    -6.1627413,
    36.5215031
  ],
  "description": "A Roman villa with mosaic decoration located in an archaeological area of Puente Melchor, in Puerto Real, Cádiz, Spain.",
  "features": [
    {
      "type": "Feature",
      "geometry": {
        "type": "Point",
        "coordinates": [
          -6.1627413,
          36.5215031
        ]
      },
      "properties": {
        "description": "representative point"
      }
    },
    {
      "geometry": {
        "type": "Point",
        "coordinates": [
          -6.1627413,
          36.5215031
        ]
      },
      "id": "osm-location",
      "type": "Feature",
      "properties": {
        "description": "Representative location of the archaeological area based on OpenStreetMap.",
        "location_precision": "precise",
        "title": "OSM location of Yacimiento del Puente Melchor",
        "link": "http://pleiades.stoa.org/places/102500043/osm-location"
      }
    }
  ]
}