{
  "type": "FeatureCollection",
  "title": "Susegana bridge",
  "id": "102937425",
  "bbox": [
    12.185556,
    45.8340171,
    12.2206508,
    45.857778
  ],
  "description": "A Roman bridge along the Via Claudia Augusta.",
  "connectsWith": [
    "688514720"
  ],
  "features": [
    {
      "type": "Feature",
      "geometry": {
        "type": "Point",
        "coordinates": [
          12.2031034,
          45.84589755
        ]
      },
      "properties": {
        "description": "representative point"
      }
    },
    {
      "geometry": {
        "type": "Point",
        "coordinates": [
          12.185556,
          45.857778
        ]
      },
      "id": "location-of-roman-bridge",
      "type": "Feature",
      "properties": {
        "description": "coordinates after GeoHack.",
        "location_precision": "precise",
        "title": "Imagery location of Brücke von Susegana",
        "link": "http://pleiades.stoa.org/places/102937425/location-of-roman-bridge"
      }
    },
    {
      "geometry": {
        "type": "Point",
        "coordinates": [
          12.2206508,
          45.8340171
        ]
      },
      "id": "osm-location-of-colfosco",
      "type": "Feature",
      "properties": {
        "description": "Representative location based on OpenStreetMap.",
        "location_precision": "precise",
        "title": "OSM location of Colfosco",
        "link": "http://pleiades.stoa.org/places/102937425/osm-location-of-colfosco"
      }
    }
  ]
}