{
  "type": "FeatureCollection",
  "title": "Ṣanʿāʾ",
  "id": "104811110",
  "bbox": [
    44.2005197,
    15.342101,
    44.2005197,
    15.342101
  ],
  "description": "Ṣanʿāʾ is the largest city in Yemen. Its \"Old City\" was listed as a UNESCO World Heritage Site in 1986.",
  "names": [
    "Ṣanʿāʾ",
    "Sanʿāʾ",
    "Sanaa",
    "Sanʿaʾ"
  ],
  "features": [
    {
      "type": "Feature",
      "geometry": {
        "type": "Point",
        "coordinates": [
          44.2005197,
          15.342101
        ]
      },
      "properties": {
        "description": "representative point"
      }
    },
    {
      "geometry": {
        "type": "Point",
        "coordinates": [
          44.2005197,
          15.342101
        ]
      },
      "id": "osm-location-of-sanaa",
      "type": "Feature",
      "properties": {
        "description": "Location based on OpenStreetMap",
        "location_precision": "precise",
        "title": "OSM location of Sana'a",
        "link": "http://pleiades.stoa.org/places/104811110/osm-location-of-sanaa"
      }
    }
  ]
}