{
  "type": "FeatureCollection",
  "title": "Greppe S. Angelo necropolis",
  "id": "105341156",
  "bbox": [
    12.1086465,
    41.9965645,
    12.1086465,
    41.9965645
  ],
  "description": "A rock-cut necropolis of Caere that is noted as the findspot of the Sarpedon krater of the artist Euphronios.",
  "connectsWith": [
    "422859"
  ],
  "names": [
    "Greppe S . Angelo necropolis"
  ],
  "features": [
    {
      "type": "Feature",
      "geometry": {
        "type": "Point",
        "coordinates": [
          12.1086465,
          41.9965645
        ]
      },
      "properties": {
        "description": "representative point"
      }
    },
    {
      "geometry": {
        "type": "Point",
        "coordinates": [
          12.1086465,
          41.9965645
        ]
      },
      "id": "osm-location-of-necropoli-rupestre-di-greppe-s",
      "type": "Feature",
      "properties": {
        "description": "Representative location based on OpenStreetMap",
        "location_precision": "precise",
        "title": "OSM location of Necropoli rupestre di Greppe S. Angelo",
        "link": "http://pleiades.stoa.org/places/105341156/osm-location-of-necropoli-rupestre-di-greppe-s"
      }
    }
  ]
}