{
  "type": "FeatureCollection",
  "title": "Cursus Barrows (Burial Mounds) ",
  "id": "105470541",
  "bbox": [
    -1.831788,
    51.184148,
    -1.831788,
    51.184148
  ],
  "description": " A grouping of burial mounds (named Cursus Barrows) located very close to Stonehenge. ",
  "connectsWith": [
    "509089189"
  ],
  "features": [
    {
      "type": "Feature",
      "geometry": {
        "type": "Point",
        "coordinates": [
          -1.831788,
          51.184148
        ]
      },
      "properties": {
        "description": "representative point"
      }
    },
    {
      "geometry": {
        "type": "Point",
        "coordinates": [
          -1.831788,
          51.184148
        ]
      },
      "id": "burial-mounds",
      "type": "Feature",
      "properties": {
        "description": "Location includes all 5 mounds. ",
        "location_precision": "precise",
        "title": "Burial Mounds",
        "link": "http://pleiades.stoa.org/places/105470541/burial-mounds"
      }
    }
  ]
}