{
  "type": "FeatureCollection",
  "title": "Cursus Barrows (Burial Mounds)",
  "id": "105470541",
  "description": "A grouping of burial mounds (named Cursus Barrows) located very closely to Stonehenge.",
  "bbox": [
    -1.831788,
    51.184148,
    -1.831788,
    51.184148
  ],
  "reprPoint": [
    -1.831788,
    51.184148
  ],
  "features": [
    {
      "geometry": {
        "type": "Point",
        "coordinates": [
          -1.831788,
          51.184148
        ]
      },
      "id": "burial-mounds",
      "type": "Feature",
      "properties": {
        "description": "Location includes all 5 mounds.",
        "location_precision": "precise",
        "title": "Burial Mounds",
        "link": "http://pleiades.stoa.org/places/105470541/burial-mounds"
      }
    }
  ]
}