{
  "type": "FeatureCollection",
  "title": "Elar",
  "id": "106515916",
  "bbox": [
    44.6168,
    40.2681,
    44.6168,
    40.2681
  ],
  "description": "Site for rock inscription (now fragmented and removed) by the road from Yerevan to Lake Sevan.",
  "names": [
    "Elar"
  ],
  "features": [
    {
      "type": "Feature",
      "geometry": {
        "type": "Point",
        "coordinates": [
          44.6168,
          40.2681
        ]
      },
      "properties": {
        "description": "representative point"
      }
    },
    {
      "geometry": {
        "type": "Point",
        "coordinates": [
          44.6168,
          40.2681
        ]
      },
      "id": "cigs-locaiton-of-elar",
      "type": "Feature",
      "properties": {
        "description": null,
        "location_precision": "precise",
        "title": "CIGS locaiton of Elar",
        "link": "http://pleiades.stoa.org/places/106515916/cigs-locaiton-of-elar"
      }
    }
  ]
}