{
  "type": "FeatureCollection",
  "title": "Tumulo di Montecalvario",
  "id": "107397415",
  "bbox": [
    11.2836616,
    43.4727707,
    11.2836616,
    43.4727707
  ],
  "description": "An Etruscan tomb located at Castellina in Chianti in Italy.",
  "connectsWith": [
    "413067"
  ],
  "names": [
    "Tumulo di Montecalvario"
  ],
  "features": [
    {
      "type": "Feature",
      "geometry": {
        "type": "Point",
        "coordinates": [
          11.2836616,
          43.4727707
        ]
      },
      "properties": {
        "description": "representative point"
      }
    },
    {
      "geometry": {
        "type": "Point",
        "coordinates": [
          11.2836616,
          43.4727707
        ]
      },
      "id": "location-of-tumulus-of-montecalvario",
      "type": "Feature",
      "properties": {
        "description": "Representative location based on OpenStreetMap.",
        "location_precision": "precise",
        "title": "OSM location of Tumulo di Montecalvario",
        "link": "http://pleiades.stoa.org/places/107397415/location-of-tumulus-of-montecalvario"
      }
    }
  ]
}