{
  "type": "FeatureCollection",
  "title": "Augustobona",
  "id": "108775",
  "bbox": [
    4.074806,
    48.297473,
    4.074806,
    48.297473
  ],
  "description": "Augustobona Tricassium stood at a key highway hub on the Via Agrippa.",
  "connectsWith": [
    "109392"
  ],
  "names": [
    "Augustobona",
    "Troyes"
  ],
  "features": [
    {
      "type": "Feature",
      "geometry": {
        "type": "Point",
        "coordinates": [
          4.074806,
          48.297473
        ]
      },
      "properties": {
        "description": "representative point"
      }
    },
    {
      "geometry": {
        "type": "Point",
        "coordinates": [
          4.074806,
          48.297473
        ]
      },
      "id": "darmc-location-11578",
      "type": "Feature",
      "properties": {
        "description": "1:1 million scale representative point location digitized from the Barrington Atlas of the Greek and Roman World by the Digital Atlas of Roman and Medieval Civilizations project at Harvard University.",
        "location_precision": "precise",
        "title": "DARMC location 11578",
        "link": "http://pleiades.stoa.org/places/108775/darmc-location-11578"
      }
    }
  ]
}