{
  "type": "FeatureCollection",
  "title": "Argentovaria?",
  "id": "108755",
  "bbox": [
    7.545189,
    48.038597,
    7.546367,
    48.06394
  ],
  "description": "An ancient place, cited: BAtlas 11 H4 Argentovaria?",
  "names": [
    "Argentovaria"
  ],
  "features": [
    {
      "type": "Feature",
      "geometry": {
        "type": "Point",
        "coordinates": [
          7.545778,
          48.0512685
        ]
      },
      "properties": {
        "description": "representative point"
      }
    },
    {
      "geometry": {
        "type": "Point",
        "coordinates": [
          7.545189,
          48.038597
        ]
      },
      "id": "darmc-location-11481",
      "type": "Feature",
      "properties": {
        "description": "1:1 million scale representative point location digitized from the Barrington Atlas of the Greek and Roman World by the Digital Atlas of Roman and Medieval Civilizations project at Harvard University.",
        "location_precision": "precise",
        "title": "DARMC location 11481",
        "link": "http://pleiades.stoa.org/places/108755/darmc-location-11481"
      }
    },
    {
      "geometry": {
        "type": "Point",
        "coordinates": [
          7.546367,
          48.06394
        ]
      },
      "id": "dare-location",
      "type": "Feature",
      "properties": {
        "description": "Representative point location, village precision",
        "location_precision": "precise",
        "title": "DARE Location",
        "link": "http://pleiades.stoa.org/places/108755/dare-location"
      }
    }
  ]
}