{
  "type": "FeatureCollection",
  "title": "Atuatuca",
  "id": "108765",
  "bbox": [
    5.4639172,
    50.7806267,
    5.4639172,
    50.7806267
  ],
  "description": "Atuatuca (modern Tongeren, Belgium) was also known as Aduatuca Tungrorum or Atuatuca Tongrorum and served as the capital of the Civitas Tungrorum.",
  "connectsWith": [
    "981524",
    "108952"
  ],
  "names": [
    "Atuatuca",
    "Tongeren",
    "Tongres",
    "Atuatuca Tungrorum",
    "Atuatuca",
    "Tongeren"
  ],
  "features": [
    {
      "type": "Feature",
      "geometry": {
        "type": "Point",
        "coordinates": [
          5.4639172,
          50.7806267
        ]
      },
      "properties": {
        "description": "representative point"
      }
    },
    {
      "geometry": {
        "type": "Point",
        "coordinates": [
          5.4639172,
          50.7806267
        ]
      },
      "id": "osm-location-of-modern-tongeren",
      "type": "Feature",
      "properties": {
        "description": "Location based on OpenStreetMap",
        "location_precision": "precise",
        "title": "OSM Location of modern Tongeren",
        "link": "http://pleiades.stoa.org/places/108765/osm-location-of-modern-tongeren"
      }
    }
  ]
}