{
  "type": "FeatureCollection",
  "title": "Atuatuca",
  "id": "108765",
  "description": "An ancient place, cited: BAtlas 11 F2 Atuatuca",
  "bbox": [
    5.464831,
    50.780857,
    5.464831,
    50.780857
  ],
  "reprPoint": [
    5.464831,
    50.780857
  ],
  "names": [
    "Tongeren",
    "Atuatuca"
  ],
  "features": [
    {
      "geometry": {
        "type": "Point",
        "coordinates": [
          5.464831,
          50.780857
        ]
      },
      "id": "darmc-location-11563",
      "type": "Feature",
      "properties": {
        "description": "1M scale point location",
        "location_precision": "precise",
        "title": "DARMC location 11563",
        "link": "http://pleiades.stoa.org/places/108765/darmc-location-11563"
      }
    }
  ]
}