{
  "type": "FeatureCollection",
  "title": "Augustobona",
  "id": "108775",
  "description": "Augustobona Tricassium stood at a key highway hub on the Via Agrippa.",
  "bbox": [
    4.074806,
    48.297473,
    4.074806,
    48.297473
  ],
  "reprPoint": [
    4.074806,
    48.297473
  ],
  "names": [
    "Troyes",
    "Augustobona"
  ],
  "features": [
    {
      "geometry": {
        "type": "Point",
        "coordinates": [
          4.074806,
          48.297473
        ]
      },
      "id": "darmc-location-11578",
      "type": "Feature",
      "properties": {
        "description": "1M scale point location",
        "location_precision": "precise",
        "title": "DARMC location 11578",
        "link": "http://pleiades.stoa.org/places/108775/darmc-location-11578"
      }
    }
  ]
}