{
  "type": "FeatureCollection",
  "title": "Atuatuca",
  "id": "108765",
  "description": "Atuatuca (modern Tongeren, Belgium) was also known as Aduatuca Tungrorum or Atuatuca Tongrorum and served as the capital of the Civitas Tungrorum.",
  "bbox": [
    5.464831,
    50.780857,
    5.464831,
    50.780857
  ],
  "connectsWith": [
    "2a0f22af24f9196d6a765c346f0e8587",
    "78a13fc53cb1749032a6bc31d6010675"
  ],
  "reprPoint": [
    5.464831,
    50.780857
  ],
  "names": [
    "Atuatuca",
    "Tongeren",
    "Tongres",
    "Atuatuca Tungrorum",
    "Atuatuca",
    "Tongeren"
  ],
  "features": [
    {
      "geometry": {
        "type": "Point",
        "coordinates": [
          5.464831,
          50.780857
        ]
      },
      "id": "darmc-location-11563",
      "type": "Feature",
      "properties": {
        "description": "1M scale point location",
        "location_precision": "precise",
        "title": "DARMC location 11563",
        "link": "http://pleiades.stoa.org/places/108765/darmc-location-11563"
      }
    },
    {
      "geometry": {
        "type": "Point",
        "coordinates": [
          5.464831,
          50.780857
        ]
      },
      "id": "copy_of_darmc-location-11563",
      "type": "Feature",
      "properties": {
        "description": "1M scale point location",
        "location_precision": "precise",
        "title": "DARMC location 11563",
        "link": "http://pleiades.stoa.org/places/108765/copy_of_darmc-location-11563"
      }
    }
  ]
}