{
  "type": "FeatureCollection",
  "title": "Ad Duodecimum",
  "id": "108725",
  "bbox": [
    6.389796,
    48.888911,
    6.389796,
    48.888911
  ],
  "description": "An ancient place, cited: BAtlas 11 G4 Ad Duodecimum",
  "names": [
    "Ad Duodecimum"
  ],
  "features": [
    {
      "type": "Feature",
      "geometry": {
        "type": "Point",
        "coordinates": [
          6.389796,
          48.888911
        ]
      },
      "properties": {
        "description": "representative point"
      }
    },
    {
      "geometry": {
        "type": "Point",
        "coordinates": [
          6.389796,
          48.888911
        ]
      },
      "id": "center-point-of-commune-delme",
      "type": "Feature",
      "properties": {
        "description": null,
        "location_precision": "precise",
        "title": "Center point of commune Delme",
        "link": "http://pleiades.stoa.org/places/108725/center-point-of-commune-delme"
      }
    }
  ]
}