{
  "type": "FeatureCollection",
  "title": "Audun-le-Tiche",
  "id": "108767",
  "description": "An ancient place, cited: BAtlas 11 F3 Audun-le-Tiche",
  "bbox": [
    5.957315,
    49.471276,
    5.957315,
    49.471276
  ],
  "reprPoint": [
    5.957315,
    49.471276
  ],
  "features": [
    {
      "geometry": {
        "type": "Point",
        "coordinates": [
          5.957315,
          49.471276
        ]
      },
      "id": "darmc-location-21567",
      "type": "Feature",
      "properties": {
        "description": "1M scale point location",
        "location_precision": "precise",
        "title": "DARMC location 21567",
        "link": "http://pleiades.stoa.org/places/108767/darmc-location-21567"
      }
    }
  ]
}