{
  "type": "FeatureCollection",
  "title": "Chapelle-lez-Herlaimont",
  "id": "108877",
  "description": "An ancient place, cited: BAtlas 11 E2 Chapelle-lez-Herlaimont",
  "bbox": [
    4.284002,
    50.467958,
    4.284002,
    50.467958
  ],
  "reprPoint": [
    4.284002,
    50.467958
  ],
  "features": [
    {
      "geometry": {
        "type": "Point",
        "coordinates": [
          4.284002,
          50.467958
        ]
      },
      "id": "darmc-location-19803",
      "type": "Feature",
      "properties": {
        "description": "1M scale point location",
        "location_precision": "precise",
        "title": "DARMC location 19803",
        "link": "http://pleiades.stoa.org/places/108877/darmc-location-19803"
      }
    }
  ]
}