{
  "type": "FeatureCollection",
  "title": "Bergheim-Quadrath",
  "id": "108805",
  "description": "An ancient place, cited: BAtlas 11 G2 Bergheim-Quadrath",
  "bbox": [
    6.685073,
    50.933252,
    6.685073,
    50.933252
  ],
  "reprPoint": [
    6.685073,
    50.933252
  ],
  "features": [
    {
      "geometry": {
        "type": "Point",
        "coordinates": [
          6.685073,
          50.933252
        ]
      },
      "id": "darmc-location-19784",
      "type": "Feature",
      "properties": {
        "description": "1M scale point location",
        "location_precision": "precise",
        "title": "DARMC location 19784",
        "link": "http://pleiades.stoa.org/places/108805/darmc-location-19784"
      }
    }
  ]
}