{
  "type": "FeatureCollection",
  "title": "Brühl-Villenhaus",
  "id": "108831",
  "bbox": [
    6.90154,
    50.826129,
    6.90154,
    50.826129
  ],
  "description": "An ancient place, cited: BAtlas 11 G2 Brühl-Villenhaus",
  "features": [
    {
      "type": "Feature",
      "geometry": {
        "type": "Point",
        "coordinates": [
          6.90154,
          50.826129
        ]
      },
      "properties": {
        "description": "representative point"
      }
    },
    {
      "geometry": {
        "type": "Point",
        "coordinates": [
          6.90154,
          50.826129
        ]
      },
      "id": "darmc-location-19793",
      "type": "Feature",
      "properties": {
        "description": "1M scale point location",
        "location_precision": "precise",
        "title": "DARMC location 19793",
        "link": "http://pleiades.stoa.org/places/108831/darmc-location-19793"
      }
    }
  ]
}