{
  "type": "FeatureCollection",
  "title": "Ceuclum",
  "id": "108875",
  "description": "Vicus on the Meuse river along the road from Noviomagus to Atua(tu)ca.",
  "bbox": [
    5.878781,
    51.729444,
    5.878781,
    51.729444
  ],
  "connectsWith": [
    "109180"
  ],
  "reprPoint": [
    5.878781,
    51.729444
  ],
  "names": [
    "Cuijk",
    "Ceuclum"
  ],
  "features": [
    {
      "geometry": {
        "type": "Point",
        "coordinates": [
          5.878781,
          51.729444
        ]
      },
      "id": "darmc-location-7560",
      "type": "Feature",
      "properties": {
        "description": "1M scale point location",
        "location_precision": "precise",
        "title": "DARMC location 7560",
        "link": "http://pleiades.stoa.org/places/108875/darmc-location-7560"
      }
    }
  ]
}