{
  "type": "FeatureCollection",
  "title": "La Cheppe",
  "id": "108889",
  "description": "An ancient place, cited: BAtlas 11 E3 La Cheppe",
  "bbox": [
    4.48786,
    49.049743,
    4.48786,
    49.049743
  ],
  "reprPoint": [
    4.48786,
    49.049743
  ],
  "features": [
    {
      "geometry": {
        "type": "Point",
        "coordinates": [
          4.48786,
          49.049743
        ]
      },
      "id": "center-point-of-the-site-camp-dattila-commune-la-cheppe",
      "type": "Feature",
      "properties": {
        "description": null,
        "location_precision": "precise",
        "title": "Center point of the site Camp d'Attila, commune La Cheppe",
        "link": "http://pleiades.stoa.org/places/108889/center-point-of-the-site-camp-dattila-commune-la-cheppe"
      }
    }
  ]
}