{
  "type": "FeatureCollection",
  "title": "Ciney",
  "id": "108891",
  "description": "An ancient place, cited: BAtlas 11 F2 Ciney",
  "bbox": [
    5.100321,
    50.296196,
    5.100321,
    50.296196
  ],
  "reprPoint": [
    5.100321,
    50.296196
  ],
  "features": [
    {
      "geometry": {
        "type": "Point",
        "coordinates": [
          5.100321,
          50.296196
        ]
      },
      "id": "darmc-location-12036",
      "type": "Feature",
      "properties": {
        "description": "1M scale point location",
        "location_precision": "precise",
        "title": "DARMC location 12036",
        "link": "http://pleiades.stoa.org/places/108891/darmc-location-12036"
      }
    }
  ]
}