{
  "type": "FeatureCollection",
  "title": "Burginatium",
  "id": "108837",
  "description": "An ancient place, cited: BAtlas 11 G1 Burginatium",
  "bbox": [
    6.318889,
    51.713889,
    6.318889,
    51.713889
  ],
  "reprPoint": [
    6.318889,
    51.713889
  ],
  "names": [
    "Burginatium"
  ],
  "features": [
    {
      "geometry": {
        "type": "Point",
        "coordinates": [
          6.29298,
          51.73979
        ]
      },
      "id": "darmc-location-7479",
      "type": "Feature",
      "properties": {
        "description": "1M scale point location",
        "location_precision": "precise",
        "title": "DARMC location 7479",
        "link": "http://pleiades.stoa.org/places/108837/darmc-location-7479"
      }
    },
    {
      "geometry": {
        "type": "Point",
        "coordinates": [
          6.318889,
          51.713889
        ]
      },
      "id": "dare-location",
      "type": "Feature",
      "properties": {
        "description": "Representative point location, site precision",
        "location_precision": "precise",
        "title": "DARE Location",
        "link": "http://pleiades.stoa.org/places/108837/dare-location"
      }
    }
  ]
}