{
  "type": "FeatureCollection",
  "title": "Blickweiler",
  "id": "108814",
  "bbox": [
    7.25178,
    49.212748,
    7.25178,
    49.212748
  ],
  "description": "An ancient place, cited: BAtlas 11 H3 Blickweiler",
  "features": [
    {
      "type": "Feature",
      "geometry": {
        "type": "Point",
        "coordinates": [
          7.25178,
          49.212748
        ]
      },
      "properties": {
        "description": "representative point"
      }
    },
    {
      "geometry": {
        "type": "Point",
        "coordinates": [
          7.25178,
          49.212748
        ]
      },
      "id": "darmc-location-11778",
      "type": "Feature",
      "properties": {
        "description": "1M scale point location",
        "location_precision": "precise",
        "title": "DARMC location 11778",
        "link": "http://pleiades.stoa.org/places/108814/darmc-location-11778"
      }
    }
  ]
}