{
  "type": "FeatureCollection",
  "title": "Damery",
  "id": "108919",
  "bbox": [
    3.875878,
    49.071315,
    3.875878,
    49.071315
  ],
  "description": "An ancient place, cited: BAtlas 11 D3 Damery",
  "features": [
    {
      "type": "Feature",
      "geometry": {
        "type": "Point",
        "coordinates": [
          3.875878,
          49.071315
        ]
      },
      "properties": {
        "description": "representative point"
      }
    },
    {
      "geometry": {
        "type": "Point",
        "coordinates": [
          3.875878,
          49.071315
        ]
      },
      "id": "darmc-location-12143",
      "type": "Feature",
      "properties": {
        "description": "1M scale point location",
        "location_precision": "precise",
        "title": "DARMC location 12143",
        "link": "http://pleiades.stoa.org/places/108919/darmc-location-12143"
      }
    }
  ]
}