{
  "type": "FeatureCollection",
  "title": "Famechon",
  "id": "108976",
  "description": "An ancient place, cited: BAtlas 11 C3 Famechon",
  "bbox": [
    2.040574,
    49.758897,
    2.041351,
    49.759727
  ],
  "reprPoint": [
    2.0409625,
    49.759312
  ],
  "features": [
    {
      "geometry": {
        "type": "Point",
        "coordinates": [
          2.040574,
          49.758897
        ]
      },
      "id": "darmc-location-17416",
      "type": "Feature",
      "properties": {
        "description": "1M scale point location",
        "location_precision": "precise",
        "title": "DARMC location 17416",
        "link": "http://pleiades.stoa.org/places/108976/darmc-location-17416"
      }
    },
    {
      "geometry": {
        "type": "Point",
        "coordinates": [
          2.041351,
          49.759727
        ]
      },
      "id": "dare-location",
      "type": "Feature",
      "properties": {
        "description": "Representative point location, village precision",
        "location_precision": "precise",
        "title": "DARE Location",
        "link": "http://pleiades.stoa.org/places/108976/dare-location"
      }
    }
  ]
}