{
  "type": "FeatureCollection",
  "title": "Decem Pagi",
  "id": "108921",
  "description": "An ancient place, cited: BAtlas 11 G4 Decem Pagi",
  "bbox": [
    6.75762,
    48.78451,
    6.75762,
    48.78451
  ],
  "reprPoint": [
    6.75762,
    48.78451
  ],
  "names": [
    "Tarquimpol",
    "Decem Pagi"
  ],
  "features": [
    {
      "geometry": {
        "type": "Point",
        "coordinates": [
          6.75762,
          48.78451
        ]
      },
      "id": "darmc-location-12168",
      "type": "Feature",
      "properties": {
        "description": "1M scale point location",
        "location_precision": "precise",
        "title": "DARMC location 12168",
        "link": "http://pleiades.stoa.org/places/108921/darmc-location-12168"
      }
    }
  ]
}