{
  "type": "FeatureCollection",
  "title": "Contra Aginnum",
  "id": "108905",
  "description": "An ancient place, cited: BAtlas 11 D3 Contra Aginnum",
  "bbox": [
    3.279702,
    49.628457,
    3.279702,
    49.628457
  ],
  "reprPoint": [
    3.279702,
    49.628457
  ],
  "names": [
    "Contra Aginnum"
  ],
  "features": [
    {
      "geometry": {
        "type": "Point",
        "coordinates": [
          3.279702,
          49.628457
        ]
      },
      "id": "darmc-location-12082",
      "type": "Feature",
      "properties": {
        "description": "1M scale point location",
        "location_precision": "precise",
        "title": "DARMC location 12082",
        "link": "http://pleiades.stoa.org/places/108905/darmc-location-12082"
      }
    }
  ]
}