{
  "type": "FeatureCollection",
  "title": "Eschweiler Hof",
  "id": "108966",
  "description": "An ancient place, cited: BAtlas 11 H3 Eschweiler Hof",
  "bbox": [
    7.206719,
    49.300419,
    7.206719,
    49.300419
  ],
  "reprPoint": [
    7.206719,
    49.300419
  ],
  "features": [
    {
      "geometry": {
        "type": "Point",
        "coordinates": [
          7.206719,
          49.300419
        ]
      },
      "id": "darmc-location-12385",
      "type": "Feature",
      "properties": {
        "description": "1M scale point location",
        "location_precision": "precise",
        "title": "DARMC location 12385",
        "link": "http://pleiades.stoa.org/places/108966/darmc-location-12385"
      }
    }
  ]
}