{
  "type": "FeatureCollection",
  "title": "Dinglingen",
  "id": "108926",
  "bbox": [
    7.83463,
    48.340004,
    7.83463,
    48.340004
  ],
  "description": "An ancient place, cited: BAtlas 11 H4 Dinglingen",
  "features": [
    {
      "type": "Feature",
      "geometry": {
        "type": "Point",
        "coordinates": [
          7.83463,
          48.340004
        ]
      },
      "properties": {
        "description": "representative point"
      }
    },
    {
      "geometry": {
        "type": "Point",
        "coordinates": [
          7.83463,
          48.340004
        ]
      },
      "id": "darmc-location-12206",
      "type": "Feature",
      "properties": {
        "description": "1M scale point location",
        "location_precision": "precise",
        "title": "DARMC location 12206",
        "link": "http://pleiades.stoa.org/places/108926/darmc-location-12206"
      }
    }
  ]
}