{
  "type": "FeatureCollection",
  "title": "Elewijt",
  "id": "108958",
  "description": "An ancient place, cited: BAtlas 11 E2 Elewijt",
  "bbox": [
    4.496974,
    50.960071,
    4.496974,
    50.960071
  ],
  "reprPoint": [
    4.496974,
    50.960071
  ],
  "names": [
    "Elewijt"
  ],
  "features": [
    {
      "geometry": {
        "type": "Point",
        "coordinates": [
          4.496974,
          50.960071
        ]
      },
      "id": "darmc-location-7713",
      "type": "Feature",
      "properties": {
        "description": "1M scale point location",
        "location_precision": "precise",
        "title": "DARMC location 7713",
        "link": "http://pleiades.stoa.org/places/108958/darmc-location-7713"
      }
    }
  ]
}