{
  "type": "FeatureCollection",
  "title": "Contrua?",
  "id": "108906",
  "bbox": [
    7.459608,
    50.308279,
    7.459608,
    50.308279
  ],
  "description": "An ancient place, cited: BAtlas 11 H2 Contrua?",
  "names": [
    "Contrua"
  ],
  "features": [
    {
      "type": "Feature",
      "geometry": {
        "type": "Point",
        "coordinates": [
          7.459608,
          50.308279
        ]
      },
      "properties": {
        "description": "representative point"
      }
    },
    {
      "geometry": {
        "type": "Point",
        "coordinates": [
          7.459608,
          50.308279
        ]
      },
      "id": "darmc-location-12087",
      "type": "Feature",
      "properties": {
        "description": "1M scale point location",
        "location_precision": "precise",
        "title": "DARMC location 12087",
        "link": "http://pleiades.stoa.org/places/108906/darmc-location-12087"
      }
    }
  ]
}