{
  "type": "FeatureCollection",
  "title": "Dorsten-Holsterhausen",
  "id": "108931",
  "bbox": [
    6.935278,
    51.673889,
    6.955789,
    51.682122
  ],
  "description": "An ancient place, cited: BAtlas 11 G1 Dorsten-Holsterhausen",
  "features": [
    {
      "type": "Feature",
      "geometry": {
        "type": "Point",
        "coordinates": [
          6.9455335,
          51.6780055
        ]
      },
      "properties": {
        "description": "representative point"
      }
    },
    {
      "geometry": {
        "type": "Point",
        "coordinates": [
          6.955789,
          51.682122
        ]
      },
      "id": "darmc-location-17678",
      "type": "Feature",
      "properties": {
        "description": "1M scale point location",
        "location_precision": "precise",
        "title": "DARMC location 17678",
        "link": "http://pleiades.stoa.org/places/108931/darmc-location-17678"
      }
    },
    {
      "geometry": {
        "type": "Point",
        "coordinates": [
          6.935278,
          51.673889
        ]
      },
      "id": "dare-location",
      "type": "Feature",
      "properties": {
        "description": "Representative point location, site precision",
        "location_precision": "precise",
        "title": "DARE Location",
        "link": "http://pleiades.stoa.org/places/108931/dare-location"
      }
    }
  ]
}