{
  "type": "FeatureCollection",
  "title": "Fluy",
  "id": "108987",
  "description": "An ancient place, cited: BAtlas 11 C3 Fluy",
  "bbox": [
    2.099259,
    49.854813,
    2.100046,
    49.858499
  ],
  "reprPoint": [
    2.0996525,
    49.856656
  ],
  "features": [
    {
      "geometry": {
        "type": "Point",
        "coordinates": [
          2.099259,
          49.858499
        ]
      },
      "id": "darmc-location-15958",
      "type": "Feature",
      "properties": {
        "description": "1M scale point location",
        "location_precision": "precise",
        "title": "DARMC location 15958",
        "link": "http://pleiades.stoa.org/places/108987/darmc-location-15958"
      }
    },
    {
      "geometry": {
        "type": "Point",
        "coordinates": [
          2.100046,
          49.854813
        ]
      },
      "id": "dare-location",
      "type": "Feature",
      "properties": {
        "description": "Representative point location, site precision",
        "location_precision": "precise",
        "title": "DARE Location",
        "link": "http://pleiades.stoa.org/places/108987/dare-location"
      }
    }
  ]
}