{
  "type": "FeatureCollection",
  "title": "Ermont",
  "id": "108964",
  "bbox": [
    2.257933,
    48.988024,
    2.257933,
    48.988024
  ],
  "description": "An ancient place, cited: BAtlas 11 C4 Ermont",
  "features": [
    {
      "type": "Feature",
      "geometry": {
        "type": "Point",
        "coordinates": [
          2.257933,
          48.988024
        ]
      },
      "properties": {
        "description": "representative point"
      }
    },
    {
      "geometry": {
        "type": "Point",
        "coordinates": [
          2.257933,
          48.988024
        ]
      },
      "id": "darmc-location-12376",
      "type": "Feature",
      "properties": {
        "description": "1M scale point location",
        "location_precision": "precise",
        "title": "DARMC location 12376",
        "link": "http://pleiades.stoa.org/places/108964/darmc-location-12376"
      }
    }
  ]
}