{
  "type": "FeatureCollection",
  "title": "Ems",
  "id": "108961",
  "description": "An ancient place, cited: BAtlas 11 H2 Ems",
  "bbox": [
    7.712449,
    50.335922,
    7.713,
    50.336491
  ],
  "reprPoint": [
    7.7127245,
    50.3362065
  ],
  "features": [
    {
      "geometry": {
        "type": "Point",
        "coordinates": [
          7.712449,
          50.336491
        ]
      },
      "id": "darmc-location-7719",
      "type": "Feature",
      "properties": {
        "description": "1M scale point location",
        "location_precision": "precise",
        "title": "DARMC location 7719",
        "link": "http://pleiades.stoa.org/places/108961/darmc-location-7719"
      }
    },
    {
      "geometry": {
        "type": "Point",
        "coordinates": [
          7.713,
          50.335922
        ]
      },
      "id": "dare-location",
      "type": "Feature",
      "properties": {
        "description": "Representative point location, site precision",
        "location_precision": "precise",
        "title": "DARE Location",
        "link": "http://pleiades.stoa.org/places/108961/dare-location"
      }
    }
  ]
}