{
  "type": "FeatureCollection",
  "title": "Destelbergen-Gand",
  "id": "108923",
  "description": "An ancient place, cited: BAtlas 11 D1 Destelbergen-Gand",
  "bbox": [
    3.798867,
    51.056051,
    3.798867,
    51.056051
  ],
  "reprPoint": [
    3.798867,
    51.056051
  ],
  "features": [
    {
      "geometry": {
        "type": "Point",
        "coordinates": [
          3.798867,
          51.056051
        ]
      },
      "id": "darmc-location-22189",
      "type": "Feature",
      "properties": {
        "description": "1M scale point location",
        "location_precision": "precise",
        "title": "DARMC location 22189",
        "link": "http://pleiades.stoa.org/places/108923/darmc-location-22189"
      }
    }
  ]
}