{
  "type": "FeatureCollection",
  "title": "Feresne?",
  "id": "108980",
  "description": "An ancient place, cited: BAtlas 11 F1 Feresne?",
  "bbox": [
    5.743404,
    51.020617,
    5.743404,
    51.020617
  ],
  "reprPoint": [
    5.743404,
    51.020617
  ],
  "names": [
    "Feresne"
  ],
  "features": [
    {
      "geometry": {
        "type": "Point",
        "coordinates": [
          5.743404,
          51.020617
        ]
      },
      "id": "darmc-location-7753",
      "type": "Feature",
      "properties": {
        "description": "1M scale point location",
        "location_precision": "precise",
        "title": "DARMC location 7753",
        "link": "http://pleiades.stoa.org/places/108980/darmc-location-7753"
      }
    }
  ]
}