{
  "type": "FeatureCollection",
  "title": "Deneuvre",
  "id": "108922",
  "description": "An ancient place, cited: BAtlas 11 G4 Deneuvre",
  "bbox": [
    6.734743,
    48.441735,
    6.73517,
    48.446581
  ],
  "reprPoint": [
    6.7349565,
    48.444158
  ],
  "features": [
    {
      "geometry": {
        "type": "Point",
        "coordinates": [
          6.734743,
          48.446581
        ]
      },
      "id": "darmc-location-15941",
      "type": "Feature",
      "properties": {
        "description": "1M scale point location",
        "location_precision": "precise",
        "title": "DARMC location 15941",
        "link": "http://pleiades.stoa.org/places/108922/darmc-location-15941"
      }
    },
    {
      "geometry": {
        "type": "Point",
        "coordinates": [
          6.73517,
          48.441735
        ]
      },
      "id": "dare-location",
      "type": "Feature",
      "properties": {
        "description": "Representative point location, site precision",
        "location_precision": "precise",
        "title": "DARE Location",
        "link": "http://pleiades.stoa.org/places/108922/dare-location"
      }
    }
  ]
}