{
  "type": "FeatureCollection",
  "title": "Condécourt-Gaillon",
  "id": "108901",
  "bbox": [
    1.891902,
    49.023652,
    1.891902,
    49.023652
  ],
  "description": "An ancient place, cited: BAtlas 11 B3 Condécourt-Gaillon",
  "features": [
    {
      "type": "Feature",
      "geometry": {
        "type": "Point",
        "coordinates": [
          1.891902,
          49.023652
        ]
      },
      "properties": {
        "description": "representative point"
      }
    },
    {
      "geometry": {
        "type": "Point",
        "coordinates": [
          1.891902,
          49.023652
        ]
      },
      "id": "darmc-location-22077",
      "type": "Feature",
      "properties": {
        "description": "1M scale point location",
        "location_precision": "precise",
        "title": "DARMC location 22077",
        "link": "http://pleiades.stoa.org/places/108901/darmc-location-22077"
      }
    }
  ]
}