{
  "type": "FeatureCollection",
  "title": "Epiais-Rhus",
  "id": "108962",
  "description": "An ancient place, cited: BAtlas 11 C3 Epiais-Rhus",
  "bbox": [
    2.085254,
    49.133663,
    2.085254,
    49.133663
  ],
  "reprPoint": [
    2.085254,
    49.133663
  ],
  "names": [
    "Les Terres Noires"
  ],
  "features": [
    {
      "geometry": {
        "type": "Point",
        "coordinates": [
          2.085254,
          49.133663
        ]
      },
      "id": "dare-location",
      "type": "Feature",
      "properties": {
        "description": "Representative point location, village precision",
        "location_precision": "precise",
        "title": "DARE Location",
        "link": "http://pleiades.stoa.org/places/108962/dare-location"
      }
    },
    {
      "geometry": {
        "type": "Point",
        "coordinates": [
          2.061123,
          49.120298
        ]
      },
      "id": "darmc-location-25952",
      "type": "Feature",
      "properties": {
        "description": "1M scale point location",
        "location_precision": "precise",
        "title": "DARMC location 25952",
        "link": "http://pleiades.stoa.org/places/108962/darmc-location-25952"
      }
    }
  ]
}