{
  "type": "FeatureCollection",
  "title": "Hermeskeil",
  "id": "109042",
  "description": "An ancient place, cited: BAtlas 11 G3 Hermeskeil",
  "bbox": [
    7.00164,
    49.621182,
    7.00164,
    49.621182
  ],
  "reprPoint": [
    7.00164,
    49.621182
  ],
  "features": [
    {
      "geometry": {
        "type": "Point",
        "coordinates": [
          7.00164,
          49.621182
        ]
      },
      "id": "center-point-of-oppidum-otzenhausen",
      "type": "Feature",
      "properties": {
        "description": "The fortification called Hunnenring covers an area of more than 18 ha and is located on the mountain Dollberg, north of Otzenhausen, Gemeinde Nonnweiler, Saarland.",
        "location_precision": "precise",
        "title": "Center point of oppidum Otzenhausen",
        "link": "http://pleiades.stoa.org/places/109042/center-point-of-oppidum-otzenhausen"
      }
    }
  ]
}