{
  "type": "FeatureCollection",
  "title": "Iversheim",
  "id": "109070",
  "bbox": [
    6.773858,
    50.5881818,
    6.773858,
    50.5881818
  ],
  "description": "A Roman site used for the extraction and preparation of lime. At least six lime kilns have been identified at the site. These were operated by Roman legionaries of the Legio XXX Ulpia Victrix and Legio I Minervia from ca. A.D. 150 to 300.",
  "names": [
    "Römische Kalkbrennerei Iversheim"
  ],
  "features": [
    {
      "type": "Feature",
      "geometry": {
        "type": "Point",
        "coordinates": [
          6.773858,
          50.5881818
        ]
      },
      "properties": {
        "description": "representative point"
      }
    },
    {
      "geometry": {
        "type": "Point",
        "coordinates": [
          6.773858,
          50.5881818
        ]
      },
      "id": "osm-location-of-rapmische-kalkbrennerei",
      "type": "Feature",
      "properties": {
        "description": "Representative location based on OpenStreetMap.",
        "location_precision": "precise",
        "title": "OSM location of Römische Kalkbrennerei",
        "link": "http://pleiades.stoa.org/places/109070/osm-location-of-rapmische-kalkbrennerei"
      }
    }
  ]
}