{
  "type": "FeatureCollection",
  "title": "Hermoniacum",
  "id": "109043",
  "bbox": [
    3.529921,
    50.249015,
    3.529921,
    50.249015
  ],
  "description": "An ancient place, cited: BAtlas 11 D2 Hermoniacum",
  "names": [
    "Hermoniacum"
  ],
  "features": [
    {
      "type": "Feature",
      "geometry": {
        "type": "Point",
        "coordinates": [
          3.529921,
          50.249015
        ]
      },
      "properties": {
        "description": "representative point"
      }
    },
    {
      "geometry": {
        "type": "Point",
        "coordinates": [
          3.529921,
          50.249015
        ]
      },
      "id": "darmc-location-12747",
      "type": "Feature",
      "properties": {
        "description": "1M scale point location",
        "location_precision": "precise",
        "title": "DARMC location 12747",
        "link": "http://pleiades.stoa.org/places/109043/darmc-location-12747"
      }
    }
  ]
}