{
  "type": "FeatureCollection",
  "title": "Heidekringen",
  "id": "109037",
  "description": "An ancient place, cited: BAtlas 11 I2 Heidekringen",
  "bbox": [
    8.185205,
    50.148031,
    8.196058,
    50.155993
  ],
  "reprPoint": [
    8.1906315,
    50.152012
  ],
  "features": [
    {
      "geometry": {
        "type": "Point",
        "coordinates": [
          8.185205,
          50.155993
        ]
      },
      "id": "darmc-location-7311",
      "type": "Feature",
      "properties": {
        "description": "1M scale point location",
        "location_precision": "precise",
        "title": "DARMC location 7311",
        "link": "http://pleiades.stoa.org/places/109037/darmc-location-7311"
      }
    },
    {
      "geometry": {
        "type": "Point",
        "coordinates": [
          8.196058,
          50.148031
        ]
      },
      "id": "dare-location",
      "type": "Feature",
      "properties": {
        "description": "Representative point location, site precision",
        "location_precision": "precise",
        "title": "DARE Location",
        "link": "http://pleiades.stoa.org/places/109037/dare-location"
      }
    }
  ]
}