{
  "type": "FeatureCollection",
  "title": "Igel",
  "id": "109063",
  "description": "An ancient place, cited: BAtlas 11 G3 Igel",
  "bbox": [
    6.53216203596,
    49.7162731779,
    6.53216203596,
    49.7162731779
  ],
  "connectsWith": [
    "109182"
  ],
  "reprPoint": [
    6.53216203596,
    49.7162731779
  ],
  "names": [
    "Igel"
  ],
  "features": [
    {
      "geometry": {
        "type": "Point",
        "coordinates": [
          6.548162,
          49.708897
        ]
      },
      "id": "darmc-location-16012",
      "type": "Feature",
      "properties": {
        "description": "1M scale point location",
        "location_precision": "precise",
        "title": "DARMC location 16012",
        "link": "http://pleiades.stoa.org/places/109063/darmc-location-16012"
      }
    },
    {
      "geometry": {
        "type": "Point",
        "coordinates": [
          6.53216203596,
          49.7162731779
        ]
      },
      "id": "dare-location",
      "type": "Feature",
      "properties": {
        "description": "Representative point location, site precision",
        "location_precision": "precise",
        "title": "DARE Location",
        "link": "http://pleiades.stoa.org/places/109063/dare-location"
      }
    }
  ]
}