{
  "type": "FeatureCollection",
  "title": "Heumen-Heumensoord",
  "id": "109045",
  "bbox": [
    5.842918,
    51.764232,
    5.842918,
    51.764232
  ],
  "description": "An ancient place, cited: BAtlas 11 F1 Heumen-Heumensoord",
  "features": [
    {
      "type": "Feature",
      "geometry": {
        "type": "Point",
        "coordinates": [
          5.842918,
          51.764232
        ]
      },
      "properties": {
        "description": "representative point"
      }
    },
    {
      "geometry": {
        "type": "Point",
        "coordinates": [
          5.842918,
          51.764232
        ]
      },
      "id": "darmc-location-17784",
      "type": "Feature",
      "properties": {
        "description": "1M scale point location",
        "location_precision": "precise",
        "title": "DARMC location 17784",
        "link": "http://pleiades.stoa.org/places/109045/darmc-location-17784"
      }
    }
  ]
}