{
  "type": "FeatureCollection",
  "title": "Kapersburg",
  "id": "109074",
  "description": "An ancient place, cited: BAtlas 11 I2 Kapersburg",
  "bbox": [
    8.635664,
    50.313042,
    8.636088,
    50.313122
  ],
  "reprPoint": [
    8.635876,
    50.313082
  ],
  "features": [
    {
      "geometry": {
        "type": "Point",
        "coordinates": [
          8.636088,
          50.313122
        ]
      },
      "id": "darmc-location-7868",
      "type": "Feature",
      "properties": {
        "description": "1M scale point location",
        "location_precision": "precise",
        "title": "DARMC location 7868",
        "link": "http://pleiades.stoa.org/places/109074/darmc-location-7868"
      }
    },
    {
      "geometry": {
        "type": "Point",
        "coordinates": [
          8.635664,
          50.313042
        ]
      },
      "id": "dare-location",
      "type": "Feature",
      "properties": {
        "description": "Representative point location, site precision",
        "location_precision": "precise",
        "title": "DARE Location",
        "link": "http://pleiades.stoa.org/places/109074/dare-location"
      }
    }
  ]
}