{
  "type": "FeatureCollection",
  "title": "Korschenbroich-Liedberg",
  "id": "109088",
  "description": "An ancient place, cited: BAtlas 11 G1 Korschenbroich-Liedberg",
  "bbox": [
    6.541797,
    51.166237,
    6.541797,
    51.166237
  ],
  "reprPoint": [
    6.541797,
    51.166237
  ],
  "features": [
    {
      "geometry": {
        "type": "Point",
        "coordinates": [
          6.541797,
          51.166237
        ]
      },
      "id": "darmc-location-19242",
      "type": "Feature",
      "properties": {
        "description": "1M scale point location",
        "location_precision": "precise",
        "title": "DARMC location 19242",
        "link": "http://pleiades.stoa.org/places/109088/darmc-location-19242"
      }
    }
  ]
}