{
  "type": "FeatureCollection",
  "title": "Les Vaux de la Celle",
  "id": "109004",
  "bbox": [
    1.7710257,
    49.1203993,
    1.7710257,
    49.1203993
  ],
  "description": "An ancient Gallo-Roman sanctuary near modern Genainville (France), with excavated remains of a temple, nymphaeum, and theater: BAtlas 11 B3 Génainville (sic)",
  "names": [
    "Les Vaux de la Celle"
  ],
  "features": [
    {
      "type": "Feature",
      "geometry": {
        "type": "Point",
        "coordinates": [
          1.7710257,
          49.1203993
        ]
      },
      "properties": {
        "description": "representative point"
      }
    },
    {
      "geometry": {
        "type": "Point",
        "coordinates": [
          1.7710257,
          49.1203993
        ]
      },
      "id": "osm-location-of-vestiges-gallo-romains",
      "type": "Feature",
      "properties": {
        "description": "Representative location based on OpenStreetMap",
        "location_precision": "precise",
        "title": "OSM location of Vestiges gallo-romains",
        "link": "http://pleiades.stoa.org/places/109004/osm-location-of-vestiges-gallo-romains"
      }
    }
  ]
}