{
  "type": "FeatureCollection",
  "title": "Iversheim",
  "id": "109070",
  "description": "An ancient place, cited: BAtlas 11 G2 Iversheim",
  "bbox": [
    6.769845,
    50.582035,
    6.769845,
    50.582035
  ],
  "reprPoint": [
    6.769845,
    50.582035
  ],
  "features": [
    {
      "geometry": {
        "type": "Point",
        "coordinates": [
          6.769845,
          50.582035
        ]
      },
      "id": "darmc-location-9235",
      "type": "Feature",
      "properties": {
        "description": "1M scale point location",
        "location_precision": "precise",
        "title": "DARMC location 9235",
        "link": "http://pleiades.stoa.org/places/109070/darmc-location-9235"
      }
    }
  ]
}