{
  "type": "FeatureCollection",
  "title": "Kruishoutem",
  "id": "109093",
  "bbox": [
    3.528018,
    50.904532,
    3.528018,
    50.904532
  ],
  "description": "An ancient settlement (name unknown) located at modern Kruishoutem in Belgium.",
  "names": [
    "Kruishoutem"
  ],
  "features": [
    {
      "type": "Feature",
      "geometry": {
        "type": "Point",
        "coordinates": [
          3.528018,
          50.904532
        ]
      },
      "properties": {
        "description": "representative point"
      }
    },
    {
      "geometry": {
        "type": "Point",
        "coordinates": [
          3.528018,
          50.904532
        ]
      },
      "id": "darmc-location-13321",
      "type": "Feature",
      "properties": {
        "description": "1M scale point location",
        "location_precision": "precise",
        "title": "DARMC location 13321",
        "link": "http://pleiades.stoa.org/places/109093/darmc-location-13321"
      }
    }
  ]
}