{
  "type": "FeatureCollection",
  "title": "Imsbach",
  "id": "109064",
  "description": "An ancient place, cited: BAtlas 11 H3 Imsbach",
  "bbox": [
    7.879448,
    49.582328,
    7.879448,
    49.582328
  ],
  "reprPoint": [
    7.879448,
    49.582328
  ],
  "features": [
    {
      "geometry": {
        "type": "Point",
        "coordinates": [
          7.879448,
          49.582328
        ]
      },
      "id": "darmc-location-9232",
      "type": "Feature",
      "properties": {
        "description": "1M scale point location",
        "location_precision": "precise",
        "title": "DARMC location 9232",
        "link": "http://pleiades.stoa.org/places/109064/darmc-location-9232"
      }
    }
  ]
}