{
  "type": "FeatureCollection",
  "title": "Igel",
  "id": "109063",
  "bbox": [
    6.53216203596,
    49.7162731779,
    6.53216203596,
    49.7162731779
  ],
  "description": "The village of Igel is known for its funerary monument of the Secundinii dating ca. A.D. 250.",
  "connectsWith": [
    "109182"
  ],
  "names": [
    "Igel"
  ],
  "features": [
    {
      "type": "Feature",
      "geometry": {
        "type": "Point",
        "coordinates": [
          6.53216203596,
          49.7162731779
        ]
      },
      "properties": {
        "description": "representative point"
      }
    },
    {
      "geometry": {
        "type": "Point",
        "coordinates": [
          6.53216203596,
          49.7162731779
        ]
      },
      "id": "dare-location",
      "type": "Feature",
      "properties": {
        "description": "Representative point location, site precision",
        "location_precision": "precise",
        "title": "DARE Location",
        "link": "http://pleiades.stoa.org/places/109063/dare-location"
      }
    }
  ]
}