{
  "type": "FeatureCollection",
  "title": "Les Vaux de la Celle",
  "id": "109004",
  "description": "An ancient Gallo-Roman sanctuary near modern Genainville (France), with excavated remains of a temple, nymphaeum, and theater: BAtlas 11 B3 Génainville (sic)",
  "bbox": [
    1.771454,
    49.120178,
    1.771454,
    49.120178
  ],
  "reprPoint": [
    1.771454,
    49.120178
  ],
  "names": [
    "Les Vaux de la Celle"
  ],
  "features": [
    {
      "geometry": {
        "type": "Point",
        "coordinates": [
          1.771454,
          49.120178
        ]
      },
      "id": "archaeological-site-les-vaux-de-la-celle",
      "type": "Feature",
      "properties": {
        "description": "The site Les Vaux de la Celle is located in the commune Genainville, département Val-d'Oise.",
        "location_precision": "precise",
        "title": "Archaeological site Les Vaux de la Celle",
        "link": "http://pleiades.stoa.org/places/109004/archaeological-site-les-vaux-de-la-celle"
      }
    }
  ]
}