{
  "type": "FeatureCollection",
  "title": "Igel",
  "id": "109063",
  "bbox": [
    6.5494716,
    49.7091434,
    6.5494716,
    49.7091434
  ],
  "description": "The village of Igel is known for its funerary monument of the Secundinii dating ca. A.D. 250.",
  "connectsWith": [
    "109182"
  ],
  "names": [
    "Igel"
  ],
  "features": [
    {
      "type": "Feature",
      "geometry": {
        "type": "Point",
        "coordinates": [
          6.5494716,
          49.7091434
        ]
      },
      "properties": {
        "description": "representative point"
      }
    },
    {
      "geometry": {
        "type": "Point",
        "coordinates": [
          6.5494716,
          49.7091434
        ]
      },
      "id": "osm-location-of-igeler-sa-ule",
      "type": "Feature",
      "properties": {
        "description": "Representative location based on OpenStreetMap.",
        "location_precision": "precise",
        "title": "OSM location of Igeler Säule",
        "link": "http://pleiades.stoa.org/places/109063/osm-location-of-igeler-sa-ule"
      }
    }
  ]
}