{
  "type": "FeatureCollection",
  "title": "Igel",
  "id": "109063",
  "description": "The village of Igel is known for its funerary monument of the Secundinii dating ca. A.D. 250.",
  "bbox": [
    6.53216203596,
    49.708897,
    6.548162,
    49.7162731779
  ],
  "connectsWith": [
    "529d15ba3b38c28ecdeb36a6a68e5a34"
  ],
  "reprPoint": [
    6.54016201798,
    49.712585089
  ],
  "names": [
    "Igel"
  ],
  "features": [
    {
      "geometry": {
        "type": "Point",
        "coordinates": [
          6.548162,
          49.708897
        ]
      },
      "id": "darmc-location-16012",
      "type": "Feature",
      "properties": {
        "description": "1M scale point location",
        "location_precision": "precise",
        "title": "DARMC location 16012",
        "link": "http://pleiades.stoa.org/places/109063/darmc-location-16012"
      }
    },
    {
      "geometry": {
        "type": "Point",
        "coordinates": [
          6.53216203596,
          49.7162731779
        ]
      },
      "id": "dare-location",
      "type": "Feature",
      "properties": {
        "description": "Representative point location, site precision",
        "location_precision": "precise",
        "title": "DARE Location",
        "link": "http://pleiades.stoa.org/places/109063/dare-location"
      }
    }
  ]
}