{
  "type": "FeatureCollection",
  "title": "Grubbenvorst-Lottum",
  "id": "109022",
  "bbox": [
    6.162546,
    51.461641,
    6.162546,
    51.461641
  ],
  "description": "An ancient place, cited: BAtlas 11 G1 Grubbenvorst-Lottum",
  "features": [
    {
      "type": "Feature",
      "geometry": {
        "type": "Point",
        "coordinates": [
          6.162546,
          51.461641
        ]
      },
      "properties": {
        "description": "representative point"
      }
    },
    {
      "geometry": {
        "type": "Point",
        "coordinates": [
          6.162546,
          51.461641
        ]
      },
      "id": "darmc-location-16877",
      "type": "Feature",
      "properties": {
        "description": "1M scale point location",
        "location_precision": "precise",
        "title": "DARMC location 16877",
        "link": "http://pleiades.stoa.org/places/109022/darmc-location-16877"
      }
    }
  ]
}