{
  "type": "FeatureCollection",
  "title": "Helmlingen",
  "id": "109040",
  "description": "An ancient place, cited: BAtlas 11 H4 Helmlingen",
  "bbox": [
    7.966668,
    48.708676,
    7.966668,
    48.708676
  ],
  "reprPoint": [
    7.966668,
    48.708676
  ],
  "features": [
    {
      "geometry": {
        "type": "Point",
        "coordinates": [
          7.966668,
          48.708676
        ]
      },
      "id": "darmc-location-12699",
      "type": "Feature",
      "properties": {
        "description": "1M scale point location",
        "location_precision": "precise",
        "title": "DARMC location 12699",
        "link": "http://pleiades.stoa.org/places/109040/darmc-location-12699"
      }
    }
  ]
}