{
  "type": "FeatureCollection",
  "title": "Helvetum/Ellelum",
  "id": "109041",
  "bbox": [
    7.616824,
    48.372887,
    7.616824,
    48.372887
  ],
  "description": "An ancient place, cited: BAtlas 11 H4 Helvetum/Ellelum",
  "names": [
    "Helvetum",
    "Ellelum"
  ],
  "features": [
    {
      "type": "Feature",
      "geometry": {
        "type": "Point",
        "coordinates": [
          7.616824,
          48.372887
        ]
      },
      "properties": {
        "description": "representative point"
      }
    },
    {
      "geometry": {
        "type": "Point",
        "coordinates": [
          7.616824,
          48.372887
        ]
      },
      "id": "center-point-of-location-ehl-commune-benfeld",
      "type": "Feature",
      "properties": {
        "description": null,
        "location_precision": "precise",
        "title": "Center point of location Ehl, commune Benfeld",
        "link": "http://pleiades.stoa.org/places/109041/center-point-of-location-ehl-commune-benfeld"
      }
    }
  ]
}