{
  "type": "FeatureCollection",
  "title": "Mézières-en-Santerre",
  "id": "109164",
  "description": "An ancient place, cited: BAtlas 11 C3 Mézières-en-Santerre",
  "bbox": [
    2.553563,
    49.7727281091,
    2.55771322754,
    49.787248
  ],
  "reprPoint": [
    2.55563811377,
    49.7799880546
  ],
  "features": [
    {
      "geometry": {
        "type": "Point",
        "coordinates": [
          2.5577132275391,
          49.772728109146
        ]
      },
      "id": "dare-location",
      "type": "Feature",
      "properties": {
        "description": "Representative point location, village precision",
        "location_precision": "precise",
        "title": "DARE Location",
        "link": "http://pleiades.stoa.org/places/109164/dare-location"
      }
    },
    {
      "geometry": {
        "type": "Point",
        "coordinates": [
          2.553563,
          49.787248
        ]
      },
      "id": "darmc-location-27529",
      "type": "Feature",
      "properties": {
        "description": "1M scale point location",
        "location_precision": "precise",
        "title": "DARMC location 27529",
        "link": "http://pleiades.stoa.org/places/109164/darmc-location-27529"
      }
    }
  ]
}