{
  "type": "FeatureCollection",
  "title": "Lutetia",
  "id": "109126",
  "bbox": [
    2.342384,
    48.852964,
    2.349952,
    48.855847
  ],
  "description": "Lutetia (modern Paris) was the capital of the Parisii, a tribe of ancient Gaul.",
  "connectsWith": [
    "109341",
    "109242"
  ],
  "names": [
    "Lutetia",
    "Lutecia",
    "Luticia",
    "Paris",
    "Loutokotia",
    "Lutetia Parisiorum",
    "Luteci",
    "Luticia Parisiorum",
    "Lutecia Parisiorum",
    "Leukotekia polis",
    "Lutèce",
    "Lutecia",
    "Lutezia"
  ],
  "features": [
    {
      "type": "Feature",
      "geometry": {
        "type": "Point",
        "coordinates": [
          2.346168,
          48.8544055
        ]
      },
      "properties": {
        "description": "representative point"
      }
    },
    {
      "geometry": {
        "type": "Point",
        "coordinates": [
          2.342384,
          48.855847
        ]
      },
      "id": "darmc-location-13544",
      "type": "Feature",
      "properties": {
        "description": "1:1 million scale representative point location digitized from the Barrington Atlas of the Greek and Roman World by the Digital Atlas of Roman and Medieval Civilizations project at Harvard University.",
        "location_precision": "precise",
        "title": "DARMC location 13544",
        "link": "http://pleiades.stoa.org/places/109126/darmc-location-13544"
      }
    },
    {
      "geometry": {
        "type": "Point",
        "coordinates": [
          2.349952,
          48.852964
        ]
      },
      "id": "dare-location",
      "type": "Feature",
      "properties": {
        "description": "Representative point location, site precision",
        "location_precision": "precise",
        "title": "DARE Location",
        "link": "http://pleiades.stoa.org/places/109126/dare-location"
      }
    }
  ]
}