{
  "type": "FeatureCollection",
  "title": "Mauchamp",
  "id": "109149",
  "description": "An ancient place, cited: BAtlas 11 D3 Mauchamp",
  "bbox": [
    3.926362,
    49.41798,
    3.930695,
    49.423401
  ],
  "reprPoint": [
    3.9285285,
    49.4206905
  ],
  "features": [
    {
      "geometry": {
        "type": "Point",
        "coordinates": [
          3.930695,
          49.423401
        ]
      },
      "id": "darmc-location-8095",
      "type": "Feature",
      "properties": {
        "description": "1M scale point location",
        "location_precision": "precise",
        "title": "DARMC location 8095",
        "link": "http://pleiades.stoa.org/places/109149/darmc-location-8095"
      }
    },
    {
      "geometry": {
        "type": "Point",
        "coordinates": [
          3.926362,
          49.41798
        ]
      },
      "id": "dare-location",
      "type": "Feature",
      "properties": {
        "description": "Representative point location, village precision",
        "location_precision": "precise",
        "title": "DARE Location",
        "link": "http://pleiades.stoa.org/places/109149/dare-location"
      }
    }
  ]
}