{
  "type": "FeatureCollection",
  "title": "Marcis?",
  "id": "109140",
  "bbox": [
    1.70763,
    50.810751,
    1.70763,
    50.810751
  ],
  "description": "An ancient place, cited: BAtlas 11 B2 Marcis?",
  "names": [
    "Marcis"
  ],
  "features": [
    {
      "type": "Feature",
      "geometry": {
        "type": "Point",
        "coordinates": [
          1.70763,
          50.810751
        ]
      },
      "properties": {
        "description": "representative point"
      }
    },
    {
      "geometry": {
        "type": "Point",
        "coordinates": [
          1.70763,
          50.810751
        ]
      },
      "id": "darmc-location-4687",
      "type": "Feature",
      "properties": {
        "description": "1M scale point location",
        "location_precision": "precise",
        "title": "DARMC location 4687",
        "link": "http://pleiades.stoa.org/places/109140/darmc-location-4687"
      }
    }
  ]
}