{
  "type": "FeatureCollection",
  "title": "Morienval",
  "id": "109176",
  "description": "An ancient place, cited: BAtlas 11 C3 Morienval",
  "bbox": [
    2.917544,
    49.295031,
    2.917544,
    49.295031
  ],
  "reprPoint": [
    2.917544,
    49.295031
  ],
  "features": [
    {
      "geometry": {
        "type": "Point",
        "coordinates": [
          2.917544,
          49.295031
        ]
      },
      "id": "darmc-location-13799",
      "type": "Feature",
      "properties": {
        "description": "1M scale point location",
        "location_precision": "precise",
        "title": "DARMC location 13799",
        "link": "http://pleiades.stoa.org/places/109176/darmc-location-13799"
      }
    }
  ]
}