{
  "type": "FeatureCollection",
  "title": "Laugona? fl.",
  "id": "109102",
  "description": "An ancient place, cited: BAtlas 11 H2 Laugona? fl.",
  "bbox": [
    7.6130817,
    50.3079954,
    7.6130817,
    50.3079954
  ],
  "reprPoint": [
    7.6130817,
    50.3079954
  ],
  "names": [
    "Laugona"
  ],
  "features": [
    {
      "geometry": {
        "type": "Point",
        "coordinates": [
          7.6130817,
          50.3079954
        ]
      },
      "id": "location-of-lahn-river",
      "type": "Feature",
      "properties": {
        "description": "Location based on OpenStreetMap",
        "location_precision": "precise",
        "title": "location of Lahn river",
        "link": "http://pleiades.stoa.org/places/109102/location-of-lahn-river"
      }
    }
  ]
}