{
  "type": "FeatureCollection",
  "title": "Marchélepot",
  "id": "109139",
  "bbox": [
    2.864513,
    49.833629,
    2.864513,
    49.833629
  ],
  "description": "An ancient place, cited: BAtlas 11 C3 Marchélepot",
  "features": [
    {
      "type": "Feature",
      "geometry": {
        "type": "Point",
        "coordinates": [
          2.864513,
          49.833629
        ]
      },
      "properties": {
        "description": "representative point"
      }
    },
    {
      "geometry": {
        "type": "Point",
        "coordinates": [
          2.864513,
          49.833629
        ]
      },
      "id": "darmc-location-17519",
      "type": "Feature",
      "properties": {
        "description": "1M scale point location",
        "location_precision": "precise",
        "title": "DARMC location 17519",
        "link": "http://pleiades.stoa.org/places/109139/darmc-location-17519"
      }
    }
  ]
}