{
  "type": "FeatureCollection",
  "title": "Moenus fl.",
  "id": "109168",
  "description": "An ancient place, cited: BAtlas 11 I2 Moenus fl.",
  "bbox": [
    8.3337876,
    49.9998475,
    8.3337876,
    49.9998475
  ],
  "reprPoint": [
    8.3337876,
    49.9998475
  ],
  "names": [
    "Moenus"
  ],
  "features": [
    {
      "geometry": {
        "type": "Point",
        "coordinates": [
          8.3337876,
          49.9998475
        ]
      },
      "id": "location-of-Moenus-fl",
      "type": "Feature",
      "properties": {
        "description": "Location based on OpenStreetMap",
        "location_precision": "precise",
        "title": "location of Moenus fl.",
        "link": "http://pleiades.stoa.org/places/109168/location-of-Moenus-fl"
      }
    }
  ]
}