{
  "type": "FeatureCollection",
  "title": "Maubeuge",
  "id": "109148",
  "description": "An ancient place, cited: BAtlas 11 D2 Maubeuge",
  "bbox": [
    3.971892,
    50.277672,
    3.971892,
    50.277672
  ],
  "reprPoint": [
    3.971892,
    50.277672
  ],
  "names": [
    "Maubeuge"
  ],
  "features": [
    {
      "geometry": {
        "type": "Point",
        "coordinates": [
          3.971892,
          50.277672
        ]
      },
      "id": "darmc-location-17522",
      "type": "Feature",
      "properties": {
        "description": "1M scale point location",
        "location_precision": "precise",
        "title": "DARMC location 17522",
        "link": "http://pleiades.stoa.org/places/109148/darmc-location-17522"
      }
    }
  ]
}