{
  "type": "FeatureCollection",
  "title": "Mederiacum",
  "id": "109152",
  "description": "An ancient place, cited: BAtlas 11 G1 Mederiacum",
  "bbox": [
    6.018727,
    51.157771,
    6.018727,
    51.157771
  ],
  "reprPoint": [
    6.018727,
    51.157771
  ],
  "names": [
    "Mederiacum"
  ],
  "features": [
    {
      "geometry": {
        "type": "Point",
        "coordinates": [
          6.018727,
          51.157771
        ]
      },
      "id": "darmc-location-13669",
      "type": "Feature",
      "properties": {
        "description": "1M scale point location",
        "location_precision": "precise",
        "title": "DARMC location 13669",
        "link": "http://pleiades.stoa.org/places/109152/darmc-location-13669"
      }
    }
  ]
}