{
  "type": "FeatureCollection",
  "title": "Lutetia",
  "id": "109126",
  "description": "Lutetia (modern Paris) was the capital of the Parisii, a tribe of ancient Gaul.",
  "bbox": [
    2.349952,
    48.852964,
    2.349952,
    48.852964
  ],
  "connectsWith": [
    "109341",
    "109242"
  ],
  "reprPoint": [
    2.349952,
    48.852964
  ],
  "names": [
    "Paris",
    "Loutokotia",
    "Luteci",
    "Lutetia Parisiorum",
    "Lutetia",
    "Lutecia",
    "Luticia"
  ],
  "features": [
    {
      "geometry": {
        "type": "Point",
        "coordinates": [
          2.3525032,
          48.8451662
        ]
      },
      "id": "location-of-arenes-de-lutece",
      "type": "Feature",
      "properties": {
        "description": "Location based on OpenStreetMap",
        "location_precision": "precise",
        "title": "location of Arènes de Lutèce",
        "link": "http://pleiades.stoa.org/places/109126/location-of-arenes-de-lutece"
      }
    },
    {
      "geometry": {
        "type": "Point",
        "coordinates": [
          2.3432743,
          48.8506016
        ]
      },
      "id": "location-of-thermes-de-cluny",
      "type": "Feature",
      "properties": {
        "description": "A Gallo-Roman bath complex of the third century AD. Location based on OpenStreetMap.",
        "location_precision": "precise",
        "title": "location of Thermes de Cluny",
        "link": "http://pleiades.stoa.org/places/109126/location-of-thermes-de-cluny"
      }
    },
    {
      "geometry": {
        "type": "Point",
        "coordinates": [
          2.342384,
          48.855847
        ]
      },
      "id": "darmc-location-13544",
      "type": "Feature",
      "properties": {
        "description": "1M scale point location",
        "location_precision": "precise",
        "title": "DARMC location 13544",
        "link": "http://pleiades.stoa.org/places/109126/darmc-location-13544"
      }
    },
    {
      "geometry": {
        "type": "Point",
        "coordinates": [
          2.349952,
          48.852964
        ]
      },
      "id": "dare-location",
      "type": "Feature",
      "properties": {
        "description": "Representative point location, site precision",
        "location_precision": "precise",
        "title": "DARE Location",
        "link": "http://pleiades.stoa.org/places/109126/dare-location"
      }
    }
  ]
}