{
  "type": "FeatureCollection",
  "title": "Mérouville",
  "id": "109158",
  "description": "An ancient place, cited: BAtlas 11 B4 Mérouville",
  "bbox": [
    1.898655,
    48.296,
    1.898655,
    48.296
  ],
  "reprPoint": [
    1.898655,
    48.296
  ],
  "features": [
    {
      "geometry": {
        "type": "Point",
        "coordinates": [
          1.898655,
          48.296
        ]
      },
      "id": "darmc-location-13708",
      "type": "Feature",
      "properties": {
        "description": "1M scale point location",
        "location_precision": "precise",
        "title": "DARMC location 13708",
        "link": "http://pleiades.stoa.org/places/109158/darmc-location-13708"
      }
    }
  ]
}