{
  "type": "FeatureCollection",
  "title": "Pierrefonds",
  "id": "109247",
  "bbox": [
    2.9899049,
    49.360498,
    2.9899049,
    49.360498
  ],
  "description": "A Gallo-Roman vicus.",
  "names": [
    "Pierrefonds"
  ],
  "features": [
    {
      "type": "Feature",
      "geometry": {
        "type": "Point",
        "coordinates": [
          2.9899049,
          49.360498
        ]
      },
      "properties": {
        "description": "representative point"
      }
    },
    {
      "geometry": {
        "type": "Point",
        "coordinates": [
          2.9899049,
          49.360498
        ]
      },
      "id": "dare-location",
      "type": "Feature",
      "properties": {
        "description": "Representative point location, site precision",
        "location_precision": "precise",
        "title": "DARE Location",
        "link": "http://pleiades.stoa.org/places/109247/dare-location"
      }
    }
  ]
}