{
  "type": "FeatureCollection",
  "title": "Palaiseau",
  "id": "109239",
  "description": "An ancient place, cited: BAtlas 11 C4 Palaiseau",
  "bbox": [
    2.233534,
    48.718875,
    2.233534,
    48.718875
  ],
  "reprPoint": [
    2.233534,
    48.718875
  ],
  "features": [
    {
      "geometry": {
        "type": "Point",
        "coordinates": [
          2.233534,
          48.718875
        ]
      },
      "id": "darmc-location-14092",
      "type": "Feature",
      "properties": {
        "description": "1M scale point location",
        "location_precision": "precise",
        "title": "DARMC location 14092",
        "link": "http://pleiades.stoa.org/places/109239/darmc-location-14092"
      }
    }
  ]
}