{
  "type": "FeatureCollection",
  "title": "Ophoven",
  "id": "109231",
  "description": "Ophoven is the site of a Gallo-Roman vicus located along the left bank of the Meuse river between Tongres and Nijmegen.",
  "bbox": [
    5.802235,
    51.12606,
    5.802235,
    51.12606
  ],
  "reprPoint": [
    5.802235,
    51.12606
  ],
  "names": [
    "Geistingen"
  ],
  "features": [
    {
      "geometry": {
        "type": "Point",
        "coordinates": [
          5.802235,
          51.12606
        ]
      },
      "id": "darmc-location-14022",
      "type": "Feature",
      "properties": {
        "description": "1M scale point location",
        "location_precision": "precise",
        "title": "DARMC location 14022",
        "link": "http://pleiades.stoa.org/places/109231/darmc-location-14022"
      }
    }
  ]
}