{
  "type": "FeatureCollection",
  "title": "Pîtres",
  "id": "109249",
  "bbox": [
    1.222467,
    49.317793,
    1.222467,
    49.317793
  ],
  "description": "An ancient place, cited: BAtlas 11 B3 Pîtres",
  "names": [
    "Pîtres"
  ],
  "features": [
    {
      "type": "Feature",
      "geometry": {
        "type": "Point",
        "coordinates": [
          1.222467,
          49.317793
        ]
      },
      "properties": {
        "description": "representative point"
      }
    },
    {
      "geometry": {
        "type": "Point",
        "coordinates": [
          1.222467,
          49.317793
        ]
      },
      "id": "darmc-location-16143",
      "type": "Feature",
      "properties": {
        "description": "1M scale point location",
        "location_precision": "precise",
        "title": "DARMC location 16143",
        "link": "http://pleiades.stoa.org/places/109249/darmc-location-16143"
      }
    }
  ]
}