{
  "type": "FeatureCollection",
  "title": "Tempelbezirk Pesch",
  "id": "109214",
  "bbox": [
    6.702819,
    50.533588,
    6.7030087,
    50.5336203
  ],
  "description": "A Gallo-Roman temple complex dated to the 1st-4th centuries CE.",
  "features": [
    {
      "type": "Feature",
      "geometry": {
        "type": "Point",
        "coordinates": [
          6.70291385,
          50.53360415
        ]
      },
      "properties": {
        "description": "representative point"
      }
    },
    {
      "geometry": {
        "type": "Point",
        "coordinates": [
          6.7030087,
          50.5336203
        ]
      },
      "id": "dare-location",
      "type": "Feature",
      "properties": {
        "description": "Representative point location, site precision",
        "location_precision": "precise",
        "title": "DARE Location",
        "link": "http://pleiades.stoa.org/places/109214/dare-location"
      }
    },
    {
      "geometry": {
        "type": "Point",
        "coordinates": [
          6.702819,
          50.533588
        ]
      },
      "id": "osm-location-of-tempelbezirk-pesch",
      "type": "Feature",
      "properties": {
        "description": "Representative location based on OpenStreetMap.",
        "location_precision": "precise",
        "title": "OSM location of Tempelbezirk Pesch",
        "link": "http://pleiades.stoa.org/places/109214/osm-location-of-tempelbezirk-pesch"
      }
    }
  ]
}