{
  "type": "FeatureCollection",
  "title": "Pont-sur-Sambre",
  "id": "109257",
  "bbox": [
    3.848302,
    50.226987,
    3.848302,
    50.226987
  ],
  "description": "An ancient place, cited: BAtlas 11 D2 Pont-sur-Sambre",
  "features": [
    {
      "type": "Feature",
      "geometry": {
        "type": "Point",
        "coordinates": [
          3.848302,
          50.226987
        ]
      },
      "properties": {
        "description": "representative point"
      }
    },
    {
      "geometry": {
        "type": "Point",
        "coordinates": [
          3.848302,
          50.226987
        ]
      },
      "id": "darmc-location-24367",
      "type": "Feature",
      "properties": {
        "description": "1M scale point location",
        "location_precision": "precise",
        "title": "DARMC location 24367",
        "link": "http://pleiades.stoa.org/places/109257/darmc-location-24367"
      }
    }
  ]
}