{
  "type": "FeatureCollection",
  "title": "Nöthen",
  "id": "109214",
  "description": "An ancient place, cited: BAtlas 11 G2 Nöthen",
  "bbox": [
    6.7030087,
    50.5336203,
    6.722114,
    50.548544
  ],
  "reprPoint": [
    6.71256135,
    50.54108215
  ],
  "features": [
    {
      "geometry": {
        "type": "Point",
        "coordinates": [
          6.722114,
          50.548544
        ]
      },
      "id": "darmc-location-16115",
      "type": "Feature",
      "properties": {
        "description": "1M scale point location",
        "location_precision": "precise",
        "title": "DARMC location 16115",
        "link": "http://pleiades.stoa.org/places/109214/darmc-location-16115"
      }
    },
    {
      "geometry": {
        "type": "Point",
        "coordinates": [
          6.7030087,
          50.5336203
        ]
      },
      "id": "dare-location",
      "type": "Feature",
      "properties": {
        "description": "Representative point location, site precision",
        "location_precision": "precise",
        "title": "DARE Location",
        "link": "http://pleiades.stoa.org/places/109214/dare-location"
      }
    }
  ]
}