{
  "type": "FeatureCollection",
  "title": "Oberweis",
  "id": "109230",
  "description": "An ancient place, cited: BAtlas 11 G3 Oberweis",
  "bbox": [
    6.42091087205,
    49.962928,
    6.421189,
    49.9672083944
  ],
  "reprPoint": [
    6.42104993602,
    49.9650681972
  ],
  "features": [
    {
      "geometry": {
        "type": "Point",
        "coordinates": [
          6.421189,
          49.962928
        ]
      },
      "id": "darmc-location-17542",
      "type": "Feature",
      "properties": {
        "description": "1M scale point location",
        "location_precision": "precise",
        "title": "DARMC location 17542",
        "link": "http://pleiades.stoa.org/places/109230/darmc-location-17542"
      }
    },
    {
      "geometry": {
        "type": "Point",
        "coordinates": [
          6.42091087205,
          49.9672083944
        ]
      },
      "id": "dare-location",
      "type": "Feature",
      "properties": {
        "description": "Representative point location, site precision",
        "location_precision": "precise",
        "title": "DARE Location",
        "link": "http://pleiades.stoa.org/places/109230/dare-location"
      }
    }
  ]
}