{
  "type": "FeatureCollection",
  "title": "Gallo-Roman vicus at Pierrefonds",
  "id": "109247",
  "bbox": [
    2.9899049,
    49.3604353,
    2.9901883,
    49.360498
  ],
  "description": "An extensive (50+ hectares) ancient settlement located in the modern French commune of Pierrefonds, lying between Pierrefonds itself and Mont Berny to the northeast. Variously referred to in the modern literature as \"Pierrefonds\", \"La Ville des Gaules\", \"Mont Berny\", or \"Saint-Étienne-Roilaye\" (another nearby modern town), the ancient name of the vicus is unknown.",
  "names": [
    "Ruines gallo-romaines du Mont-Berny dans la forêt de Compiègne",
    "La Ville des Gaules",
    "Saint Etienne Roilaye",
    "Pierrefonds"
  ],
  "features": [
    {
      "type": "Feature",
      "geometry": {
        "type": "Point",
        "coordinates": [
          2.9900466,
          49.36046665
        ]
      },
      "properties": {
        "description": "representative point"
      }
    },
    {
      "geometry": {
        "type": "Point",
        "coordinates": [
          2.9899049,
          49.360498
        ]
      },
      "id": "dare-location",
      "type": "Feature",
      "properties": {
        "description": "Representative point location, site precision",
        "location_precision": "precise",
        "title": "DARE Location",
        "link": "http://pleiades.stoa.org/places/109247/dare-location"
      }
    },
    {
      "geometry": {
        "type": "Point",
        "coordinates": [
          2.9901883,
          49.3604353
        ]
      },
      "id": "osm-location-of-la-ville-des-gaules",
      "type": "Feature",
      "properties": {
        "description": "Representative location based on OpenStreetMap.",
        "location_precision": "precise",
        "title": "OSM location of La Ville des Gaules",
        "link": "http://pleiades.stoa.org/places/109247/osm-location-of-la-ville-des-gaules"
      }
    }
  ]
}