{
  "type": "FeatureCollection",
  "title": "Neupotz",
  "id": "109200",
  "description": "An ancient place, cited: BAtlas 11 I3 Neupotz",
  "bbox": [
    8.317387,
    49.117657,
    8.317387,
    49.117657
  ],
  "reprPoint": [
    8.317387,
    49.117657
  ],
  "features": [
    {
      "geometry": {
        "type": "Point",
        "coordinates": [
          8.317387,
          49.117657
        ]
      },
      "id": "darmc-location-13916",
      "type": "Feature",
      "properties": {
        "description": "1M scale point location",
        "location_precision": "precise",
        "title": "DARMC location 13916",
        "link": "http://pleiades.stoa.org/places/109200/darmc-location-13916"
      }
    }
  ]
}