{
  "type": "FeatureCollection",
  "title": "Pontes",
  "id": "109255",
  "bbox": [
    1.8933262,
    50.3100243,
    1.8933262,
    50.3100243
  ],
  "description": "A place mentioned in the Antonine Itinerary (Pontibus). Scholars tentatively associate it with modern Ponches-Estruval in France's Somme department.",
  "names": [
    "Pontes"
  ],
  "features": [
    {
      "type": "Feature",
      "geometry": {
        "type": "Point",
        "coordinates": [
          1.8933262,
          50.3100243
        ]
      },
      "properties": {
        "description": "representative point"
      }
    },
    {
      "geometry": {
        "type": "Point",
        "coordinates": [
          1.8933262,
          50.3100243
        ]
      },
      "id": "osm-location",
      "type": "Feature",
      "properties": {
        "description": "Location based on OpenStreetMap",
        "location_precision": "precise",
        "title": "OSM location of modern Ponches-Estruval",
        "link": "http://pleiades.stoa.org/places/109255/osm-location"
      }
    }
  ]
}