{
  "type": "FeatureCollection",
  "title": "Ratumagus Silvanectum?",
  "id": "109271",
  "description": "An ancient place, cited: BAtlas 11 C3 Ratumagus Silvanectum?",
  "bbox": [
    2.243977,
    49.354659,
    2.243977,
    49.354659
  ],
  "reprPoint": [
    2.243977,
    49.354659
  ],
  "names": [
    "Ratumagus Silvanectum",
    "Ratum(...)"
  ],
  "features": [
    {
      "geometry": {
        "type": "Point",
        "coordinates": [
          2.243977,
          49.354659
        ]
      },
      "id": "darmc-location-14477",
      "type": "Feature",
      "properties": {
        "description": "1M scale point location",
        "location_precision": "precise",
        "title": "DARMC location 14477",
        "link": "http://pleiades.stoa.org/places/109271/darmc-location-14477"
      }
    }
  ]
}