{
  "type": "FeatureCollection",
  "title": "Rouvroy-les-Merles",
  "id": "109289",
  "description": "An ancient place, cited: BAtlas 11 C3 Rouvroy-les-Merles",
  "bbox": [
    2.358426,
    49.647764,
    2.3663599,
    49.656014
  ],
  "reprPoint": [
    2.36239295,
    49.651889
  ],
  "features": [
    {
      "geometry": {
        "type": "Point",
        "coordinates": [
          2.3663599,
          49.656014
        ]
      },
      "id": "dare-location",
      "type": "Feature",
      "properties": {
        "description": "Representative point location, village precision",
        "location_precision": "precise",
        "title": "DARE Location",
        "link": "http://pleiades.stoa.org/places/109289/dare-location"
      }
    },
    {
      "geometry": {
        "type": "Point",
        "coordinates": [
          2.358426,
          49.647764
        ]
      },
      "id": "darmc-location-26175",
      "type": "Feature",
      "properties": {
        "description": "1M scale point location",
        "location_precision": "precise",
        "title": "DARMC location 26175",
        "link": "http://pleiades.stoa.org/places/109289/darmc-location-26175"
      }
    }
  ]
}