{
  "type": "FeatureCollection",
  "title": "Pierrefonds",
  "id": "109247",
  "description": "An ancient place, cited: BAtlas 11 D3 Pierrefonds",
  "bbox": [
    2.9899049,
    49.352213,
    3.017469,
    49.360498
  ],
  "reprPoint": [
    3.00368695,
    49.3563555
  ],
  "names": [
    "Pierrefonds"
  ],
  "features": [
    {
      "geometry": {
        "type": "Point",
        "coordinates": [
          2.9899049,
          49.360498
        ]
      },
      "id": "dare-location",
      "type": "Feature",
      "properties": {
        "description": "Representative point location, site precision",
        "location_precision": "precise",
        "title": "DARE Location",
        "link": "http://pleiades.stoa.org/places/109247/dare-location"
      }
    },
    {
      "geometry": {
        "type": "Point",
        "coordinates": [
          3.017469,
          49.352213
        ]
      },
      "id": "darmc-location-22431",
      "type": "Feature",
      "properties": {
        "description": "1M scale point location",
        "location_precision": "precise",
        "title": "DARMC location 22431",
        "link": "http://pleiades.stoa.org/places/109247/darmc-location-22431"
      }
    }
  ]
}