{
  "type": "FeatureCollection",
  "title": "St-André-sur-Cailly",
  "id": "109304",
  "description": "An ancient place, cited: BAtlas 11 B3 St-André-sur-Cailly",
  "bbox": [
    1.212792,
    49.547341,
    1.219344,
    49.557165
  ],
  "reprPoint": [
    1.216068,
    49.552253
  ],
  "features": [
    {
      "geometry": {
        "type": "Point",
        "coordinates": [
          1.212792,
          49.557165
        ]
      },
      "id": "dare-location",
      "type": "Feature",
      "properties": {
        "description": "Representative point location, site precision",
        "location_precision": "precise",
        "title": "DARE Location",
        "link": "http://pleiades.stoa.org/places/109304/dare-location"
      }
    },
    {
      "geometry": {
        "type": "Point",
        "coordinates": [
          1.219344,
          49.547341
        ]
      },
      "id": "darmc-location-26209",
      "type": "Feature",
      "properties": {
        "description": "1M scale point location",
        "location_precision": "precise",
        "title": "DARMC location 26209",
        "link": "http://pleiades.stoa.org/places/109304/darmc-location-26209"
      }
    }
  ]
}