{
  "type": "FeatureCollection",
  "title": "Treignes",
  "id": "109387",
  "description": "An ancient place, cited: BAtlas 11 E2 Treignes",
  "bbox": [
    4.663961,
    50.08768,
    4.669162,
    50.092722
  ],
  "reprPoint": [
    4.6665615,
    50.090201
  ],
  "features": [
    {
      "geometry": {
        "type": "Point",
        "coordinates": [
          4.669162,
          50.092722
        ]
      },
      "id": "darmc-location-17628",
      "type": "Feature",
      "properties": {
        "description": "1M scale point location",
        "location_precision": "precise",
        "title": "DARMC location 17628",
        "link": "http://pleiades.stoa.org/places/109387/darmc-location-17628"
      }
    },
    {
      "geometry": {
        "type": "Point",
        "coordinates": [
          4.663961,
          50.08768
        ]
      },
      "id": "dare-location",
      "type": "Feature",
      "properties": {
        "description": "Representative point location, site precision",
        "location_precision": "precise",
        "title": "DARE Location",
        "link": "http://pleiades.stoa.org/places/109387/dare-location"
      }
    }
  ]
}