{
  "type": "FeatureCollection",
  "title": "Trebur",
  "id": "109388",
  "description": "An ancient place, cited: BAtlas 11 I3 Trebur",
  "bbox": [
    8.37,
    49.87,
    8.409341,
    49.924264
  ],
  "reprPoint": [
    8.3896705,
    49.897132
  ],
  "features": [
    {
      "geometry": {
        "type": "Point",
        "coordinates": [
          8.409341,
          49.924264
        ]
      },
      "id": "darmc-location-15248",
      "type": "Feature",
      "properties": {
        "description": "1M scale point location",
        "location_precision": "precise",
        "title": "DARMC location 15248",
        "link": "http://pleiades.stoa.org/places/109388/darmc-location-15248"
      }
    },
    {
      "geometry": {
        "type": "Point",
        "coordinates": [
          8.37,
          49.87
        ]
      },
      "id": "dare-location",
      "type": "Feature",
      "properties": {
        "description": "Representative point location, village precision",
        "location_precision": "precise",
        "title": "DARE Location",
        "link": "http://pleiades.stoa.org/places/109388/dare-location"
      }
    }
  ]
}