{
  "type": "FeatureCollection",
  "title": "Souzy",
  "id": "109350",
  "bbox": [
    2.147934,
    48.529222,
    2.147934,
    48.529222
  ],
  "description": "An ancient place, cited: BAtlas 11 C4 Souzy",
  "features": [
    {
      "type": "Feature",
      "geometry": {
        "type": "Point",
        "coordinates": [
          2.147934,
          48.529222
        ]
      },
      "properties": {
        "description": "representative point"
      }
    },
    {
      "geometry": {
        "type": "Point",
        "coordinates": [
          2.147934,
          48.529222
        ]
      },
      "id": "darmc-location-17607",
      "type": "Feature",
      "properties": {
        "description": "1M scale point location",
        "location_precision": "precise",
        "title": "DARMC location 17607",
        "link": "http://pleiades.stoa.org/places/109350/darmc-location-17607"
      }
    }
  ]
}