{
  "type": "FeatureCollection",
  "title": "Teucera",
  "id": "109372",
  "description": "An ancient place, cited: BAtlas 11 C2 Teucera",
  "bbox": [
    2.4532,
    50.127518,
    2.4532,
    50.127518
  ],
  "reprPoint": [
    2.4532,
    50.127518
  ],
  "names": [
    "Teucera"
  ],
  "features": [
    {
      "geometry": {
        "type": "Point",
        "coordinates": [
          2.4532,
          50.127518
        ]
      },
      "id": "darmc-location-15093",
      "type": "Feature",
      "properties": {
        "description": "1M scale point location",
        "location_precision": "precise",
        "title": "DARMC location 15093",
        "link": "http://pleiades.stoa.org/places/109372/darmc-location-15093"
      }
    }
  ]
}