{
  "type": "FeatureCollection",
  "title": "Samarobriva Ambianorum",
  "id": "109321",
  "description": "An ancient place, cited: BAtlas 11 C3 Samarobriva Ambianorum",
  "bbox": [
    2.293832,
    49.892624,
    2.302064,
    49.894591
  ],
  "reprPoint": [
    2.297948,
    49.8936075
  ],
  "names": [
    "Samarobriva Ambianorum",
    "Amiens"
  ],
  "features": [
    {
      "geometry": {
        "type": "Point",
        "coordinates": [
          2.293832,
          49.892624
        ]
      },
      "id": "darmc-location-14589",
      "type": "Feature",
      "properties": {
        "description": "1M scale point location",
        "location_precision": "precise",
        "title": "DARMC location 14589",
        "link": "http://pleiades.stoa.org/places/109321/darmc-location-14589"
      }
    },
    {
      "geometry": {
        "type": "Point",
        "coordinates": [
          2.302064,
          49.894591
        ]
      },
      "id": "dare-location",
      "type": "Feature",
      "properties": {
        "description": "Representative point location, site precision",
        "location_precision": "precise",
        "title": "DARE Location",
        "link": "http://pleiades.stoa.org/places/109321/dare-location"
      }
    }
  ]
}