{
  "type": "FeatureCollection",
  "title": "Songeons",
  "id": "109349",
  "description": "An ancient place, cited: BAtlas 11 B3 Songeons",
  "bbox": [
    1.83547590991,
    49.547677,
    1.852873,
    49.5646384113
  ],
  "reprPoint": [
    1.84417445496,
    49.5561577057
  ],
  "features": [
    {
      "geometry": {
        "type": "Point",
        "coordinates": [
          1.852873,
          49.547677
        ]
      },
      "id": "darmc-location-16199",
      "type": "Feature",
      "properties": {
        "description": "1M scale point location",
        "location_precision": "precise",
        "title": "DARMC location 16199",
        "link": "http://pleiades.stoa.org/places/109349/darmc-location-16199"
      }
    },
    {
      "geometry": {
        "type": "Point",
        "coordinates": [
          1.83547590991,
          49.5646384113
        ]
      },
      "id": "dare-location",
      "type": "Feature",
      "properties": {
        "description": "Representative point location, village precision",
        "location_precision": "precise",
        "title": "DARE Location",
        "link": "http://pleiades.stoa.org/places/109349/dare-location"
      }
    }
  ]
}