{
  "type": "FeatureCollection",
  "title": "Seclin",
  "id": "109334",
  "description": "An ancient place, cited: BAtlas 11 D2 Seclin",
  "bbox": [
    3.0304,
    50.550731,
    3.0304,
    50.550731
  ],
  "reprPoint": [
    3.0304,
    50.550731
  ],
  "features": [
    {
      "geometry": {
        "type": "Point",
        "coordinates": [
          3.0304,
          50.550731
        ]
      },
      "id": "darmc-location-14648",
      "type": "Feature",
      "properties": {
        "description": "1M scale point location",
        "location_precision": "precise",
        "title": "DARMC location 14648",
        "link": "http://pleiades.stoa.org/places/109334/darmc-location-14648"
      }
    }
  ]
}