{
  "type": "FeatureCollection",
  "title": "Stolberg-Breinigerberg",
  "id": "109353",
  "bbox": [
    6.238748,
    50.737185,
    6.238748,
    50.737185
  ],
  "description": "An ancient place, cited: BAtlas 11 G2 Stolberg-Breinigerberg",
  "features": [
    {
      "type": "Feature",
      "geometry": {
        "type": "Point",
        "coordinates": [
          6.238748,
          50.737185
        ]
      },
      "properties": {
        "description": "representative point"
      }
    },
    {
      "geometry": {
        "type": "Point",
        "coordinates": [
          6.238748,
          50.737185
        ]
      },
      "id": "darmc-location-16089",
      "type": "Feature",
      "properties": {
        "description": "1M scale point location",
        "location_precision": "precise",
        "title": "DARMC location 16089",
        "link": "http://pleiades.stoa.org/places/109353/darmc-location-16089"
      }
    }
  ]
}