{
  "type": "FeatureCollection",
  "title": "Sceaux-sur-Huisne",
  "id": "109331",
  "description": "An ancient place, cited: BAtlas 11 A4 Sceaux-sur-Huisne",
  "bbox": [
    0.583693,
    48.103605,
    0.583693,
    48.103605
  ],
  "reprPoint": [
    0.583693,
    48.103605
  ],
  "features": [
    {
      "geometry": {
        "type": "Point",
        "coordinates": [
          0.583693,
          48.103605
        ]
      },
      "id": "darmc-location-27589",
      "type": "Feature",
      "properties": {
        "description": "1M scale point location",
        "location_precision": "precise",
        "title": "DARMC location 27589",
        "link": "http://pleiades.stoa.org/places/109331/darmc-location-27589"
      }
    }
  ]
}