{
  "type": "FeatureCollection",
  "title": "St-Germain-les-Corbeil",
  "id": "109308",
  "description": "An ancient place, cited: BAtlas 11 C4 St-Germain-les-Corbeil",
  "bbox": [
    2.490094,
    48.620171,
    2.490094,
    48.620171
  ],
  "reprPoint": [
    2.490094,
    48.620171
  ],
  "features": [
    {
      "geometry": {
        "type": "Point",
        "coordinates": [
          2.490094,
          48.620171
        ]
      },
      "id": "darmc-location-27611",
      "type": "Feature",
      "properties": {
        "description": "1M scale point location",
        "location_precision": "precise",
        "title": "DARMC location 27611",
        "link": "http://pleiades.stoa.org/places/109308/darmc-location-27611"
      }
    }
  ]
}