{
  "type": "FeatureCollection",
  "title": "St-André-sur-Cailly",
  "id": "109304",
  "bbox": [
    1.212792,
    49.557165,
    1.212792,
    49.557165
  ],
  "description": "An ancient place, cited: BAtlas 11 B3 St-André-sur-Cailly",
  "features": [
    {
      "type": "Feature",
      "geometry": {
        "type": "Point",
        "coordinates": [
          1.212792,
          49.557165
        ]
      },
      "properties": {
        "description": "representative point"
      }
    },
    {
      "geometry": {
        "type": "Point",
        "coordinates": [
          1.212792,
          49.557165
        ]
      },
      "id": "dare-location",
      "type": "Feature",
      "properties": {
        "description": "Representative point location, site precision",
        "location_precision": "precise",
        "title": "DARE Location",
        "link": "http://pleiades.stoa.org/places/109304/dare-location"
      }
    }
  ]
}