{
  "type": "FeatureCollection",
  "title": "Traiectus?",
  "id": "109386",
  "description": "An ancient place, cited: BAtlas 11 F2 Traiectus?",
  "bbox": [
    5.68721,
    50.84841,
    5.693799,
    50.84975
  ],
  "reprPoint": [
    5.6905045,
    50.84908
  ],
  "names": [
    "Maastricht",
    "Traiectus"
  ],
  "features": [
    {
      "geometry": {
        "type": "Point",
        "coordinates": [
          5.68721,
          50.84975
        ]
      },
      "id": "darmc-location-5251",
      "type": "Feature",
      "properties": {
        "description": "1M scale point location",
        "location_precision": "precise",
        "title": "DARMC location 5251",
        "link": "http://pleiades.stoa.org/places/109386/darmc-location-5251"
      }
    },
    {
      "geometry": {
        "type": "Point",
        "coordinates": [
          5.693799,
          50.84841
        ]
      },
      "id": "dare-location",
      "type": "Feature",
      "properties": {
        "description": "Representative point location, site precision",
        "location_precision": "precise",
        "title": "DARE Location",
        "link": "http://pleiades.stoa.org/places/109386/dare-location"
      }
    }
  ]
}