{
  "type": "FeatureCollection",
  "title": "Samarobriva Ambianorum",
  "id": "109321",
  "bbox": [
    2.293832,
    49.892624,
    2.302064,
    49.894591
  ],
  "description": "A city of Gallia Belgica located on the Somme that is mentioned in Caesar's commentaries.",
  "connectsWith": [
    "108740",
    "109320"
  ],
  "names": [
    "Samarobriva Ambianorum",
    "Amiens",
    "Sammarobriva"
  ],
  "features": [
    {
      "type": "Feature",
      "geometry": {
        "type": "Point",
        "coordinates": [
          2.297948,
          49.8936075
        ]
      },
      "properties": {
        "description": "representative point"
      }
    },
    {
      "geometry": {
        "type": "Point",
        "coordinates": [
          2.293832,
          49.892624
        ]
      },
      "id": "darmc-location-14589",
      "type": "Feature",
      "properties": {
        "description": "1:1 million scale representative point location digitized from the Barrington Atlas of the Greek and Roman World by the Digital Atlas of Roman and Medieval Civilizations project at Harvard University.",
        "location_precision": "precise",
        "title": "DARMC location 14589",
        "link": "http://pleiades.stoa.org/places/109321/darmc-location-14589"
      }
    },
    {
      "geometry": {
        "type": "Point",
        "coordinates": [
          2.302064,
          49.894591
        ]
      },
      "id": "dare-location",
      "type": "Feature",
      "properties": {
        "description": "Representative point location, site precision",
        "location_precision": "precise",
        "title": "DARE Location",
        "link": "http://pleiades.stoa.org/places/109321/dare-location"
      }
    }
  ]
}