{
  "type": "FeatureCollection",
  "title": "Speicher",
  "id": "109351",
  "description": "An ancient place, cited: BAtlas 11 G3 Speicher",
  "bbox": [
    6.637343,
    49.9352682401,
    6.63770497188,
    49.936129
  ],
  "reprPoint": [
    6.63752398594,
    49.9356986201
  ],
  "features": [
    {
      "geometry": {
        "type": "Point",
        "coordinates": [
          6.637343,
          49.936129
        ]
      },
      "id": "darmc-location-14846",
      "type": "Feature",
      "properties": {
        "description": "1M scale point location",
        "location_precision": "precise",
        "title": "DARMC location 14846",
        "link": "http://pleiades.stoa.org/places/109351/darmc-location-14846"
      }
    },
    {
      "geometry": {
        "type": "Point",
        "coordinates": [
          6.63770497188,
          49.9352682401
        ]
      },
      "id": "dare-location",
      "type": "Feature",
      "properties": {
        "description": "Representative point location, site precision",
        "location_precision": "precise",
        "title": "DARE Location",
        "link": "http://pleiades.stoa.org/places/109351/dare-location"
      }
    }
  ]
}