{
  "type": "FeatureCollection",
  "title": "Carzield",
  "id": "109408874",
  "bbox": [
    -3.61866,
    55.11979,
    -3.61866,
    55.11979
  ],
  "description": "An Antonine cavalry fort covering ca. 2.6 ha that was excavated by E. Birley and I. A. Richmond in 1939.",
  "features": [
    {
      "type": "Feature",
      "geometry": {
        "type": "Point",
        "coordinates": [
          -3.61866,
          55.11979
        ]
      },
      "properties": {
        "description": "representative point"
      }
    },
    {
      "geometry": {
        "type": "Point",
        "coordinates": [
          -3.61866,
          55.11979
        ]
      },
      "id": "imagery-location-of-roman-fortlet",
      "type": "Feature",
      "properties": {
        "description": "Representative location and chronology based on Canmore.",
        "location_precision": "precise",
        "title": "Canmore location of Roman fortlet",
        "link": "http://pleiades.stoa.org/places/109408874/imagery-location-of-roman-fortlet"
      }
    }
  ]
}