{
  "type": "FeatureCollection",
  "title": "Vicus Iulius",
  "id": "109428",
  "bbox": [
    8.369585,
    49.218856,
    8.369585,
    49.218856
  ],
  "description": "An ancient place, cited: BAtlas 11 I3 Vicus Iulius",
  "names": [
    "Vicus Iulius"
  ],
  "features": [
    {
      "type": "Feature",
      "geometry": {
        "type": "Point",
        "coordinates": [
          8.369585,
          49.218856
        ]
      },
      "properties": {
        "description": "representative point"
      }
    },
    {
      "geometry": {
        "type": "Point",
        "coordinates": [
          8.369585,
          49.218856
        ]
      },
      "id": "darmc-location-10258",
      "type": "Feature",
      "properties": {
        "description": "1M scale point location",
        "location_precision": "precise",
        "title": "DARMC location 10258",
        "link": "http://pleiades.stoa.org/places/109428/darmc-location-10258"
      }
    }
  ]
}