{
  "type": "FeatureCollection",
  "title": "Unnamed Roman bridge at Trier",
  "id": "110234",
  "bbox": [
    6.626667,
    49.751944,
    6.626667,
    49.751944
  ],
  "description": "BAtlas 11 G3 unnamed bridge (Col. Augusta Treverorum)",
  "connectsWith": [
    "108894"
  ],
  "features": [
    {
      "type": "Feature",
      "geometry": {
        "type": "Point",
        "coordinates": [
          6.626667,
          49.751944
        ]
      },
      "properties": {
        "description": "representative point"
      }
    },
    {
      "geometry": {
        "type": "Point",
        "coordinates": [
          6.626667,
          49.751944
        ]
      },
      "id": "midpoint-of-roman-bridge",
      "type": "Feature",
      "properties": {
        "description": null,
        "location_precision": "precise",
        "title": "Midpoint of Roman bridge",
        "link": "http://pleiades.stoa.org/places/110234/midpoint-of-roman-bridge"
      }
    }
  ]
}