{
  "type": "FeatureCollection",
  "title": "Baptistery of Butrint",
  "id": "11257637",
  "bbox": [
    20.022861,
    39.745551,
    20.0229272,
    39.7455751
  ],
  "description": "The Baptistery of Butrint is a round structure, with a diameter of 14.5 meters. It was built in the sixth century A.D. and was excavated in May 1928 by Luigi Maria Ugolini.",
  "connectsWith": [
    "530824"
  ],
  "features": [
    {
      "type": "Feature",
      "geometry": {
        "type": "Point",
        "coordinates": [
          20.0228941,
          39.74556305
        ]
      },
      "properties": {
        "description": "representative point"
      }
    },
    {
      "geometry": {
        "type": "Point",
        "coordinates": [
          20.022861,
          39.745551
        ]
      },
      "id": "centerpoint-of-the-baptistry-at-butrint",
      "type": "Feature",
      "properties": {
        "description": "Coordinates obtained by eye in Google Earth in September 2012 at an eye altitude of 155m. Dates after PECS.",
        "location_precision": "precise",
        "title": "Centerpoint of the Baptistry at Butrint",
        "link": "http://pleiades.stoa.org/places/11257637/centerpoint-of-the-baptistry-at-butrint"
      }
    },
    {
      "geometry": {
        "type": "Point",
        "coordinates": [
          20.0229272,
          39.7455751
        ]
      },
      "id": "osm-location-of-baptistery-of-butrint",
      "type": "Feature",
      "properties": {
        "description": "Representative location based on OpenStreetMap",
        "location_precision": "precise",
        "title": "OSM location of Baptistery of Butrint",
        "link": "http://pleiades.stoa.org/places/11257637/osm-location-of-baptistery-of-butrint"
      }
    }
  ]
}