{
  "type": "FeatureCollection",
  "title": "Untitled",
  "id": "113268",
  "bbox": [
    3.234282,
    49.253801,
    4.033901,
    50.175165
  ],
  "description": "Camaracum → Augusta Suessionum → Durocortorum",
  "features": [
    {
      "type": "Feature",
      "geometry": {
        "type": "Point",
        "coordinates": [
          3.531112,
          49.6033188333
        ]
      },
      "properties": {
        "description": "representative point"
      }
    }
  ]
}