{
  "type": "FeatureCollection",
  "title": "Petromantulum?/Petromantalum?/Petrum Viaco",
  "id": "114789",
  "description": "An ancient settlement or road station, attested by the Antonine Itineraries and the Peutinger Map, whose precise location is uncertain (BAtlas 11 unlocated Petromantulum/Petrum Viaco).",
  "bbox": [
    1.771454,
    49.120178,
    1.771454,
    49.120178
  ],
  "connectsWith": [
    "c051db9f0be0106f1e577066f0af2e36"
  ],
  "reprPoint": [
    1.771454,
    49.120178
  ],
  "names": [
    "Petromantulum",
    "Petrum Viaco"
  ],
  "features": [
    {
      "id": "undetermined",
      "type": "Feature",
      "properties": {
        "description": null,
        "location_precision": "unlocated",
        "title": "Undetermined location",
        "link": "http://pleiades.stoa.org/places/114789/undetermined"
      }
    },
    {
      "geometry": {
        "type": "Point",
        "coordinates": [
          1.771454,
          49.120178
        ]
      },
      "id": "archaeological-site-les-vaux-de-la-celle",
      "type": "Feature",
      "properties": {
        "description": "The site Les Vaux de la Celle is located in the commune Genainville, département Val-d'Oise.",
        "location_precision": "precise",
        "title": "Archaeological site Les Vaux de la Celle",
        "link": "http://pleiades.stoa.org/places/114789/archaeological-site-les-vaux-de-la-celle"
      }
    }
  ]
}