{
  "type": "FeatureCollection",
  "title": "Ad Fines",
  "id": "114762",
  "bbox": [
    5.3859057,
    48.6319439,
    5.895105,
    48.68345
  ],
  "description": "An ancient place, cited: BAtlas 11 unlocated Ad Fines",
  "connectsWith": [
    "109190",
    "109396"
  ],
  "names": [
    "Ad Fines"
  ],
  "features": [
    {
      "type": "Feature",
      "geometry": {
        "type": "Point",
        "coordinates": [
          5.6406908248,
          48.6559232084
        ]
      },
      "properties": {
        "description": "representative point"
      }
    },
    {
      "geometry": null,
      "id": "undetermined",
      "type": "Feature",
      "properties": {
        "description": null,
        "location_precision": "unlocated",
        "title": "Undetermined location",
        "link": "http://pleiades.stoa.org/places/114762/undetermined"
      }
    }
  ]
}