{
  "type": "FeatureCollection",
  "title": "Petromantulum?/Petromantalum?/Petrum Viaco",
  "id": "114789",
  "bbox": [
    1.7710257,
    49.1203993,
    1.7710257,
    49.1203993
  ],
  "description": "An ancient settlement or road station, attested by both the Antonine Itineraries and the Peutinger Map, whose precise location is uncertain (BAtlas 11 unlocated Petromantulum/Petrum Viaco).",
  "connectsWith": [
    "109004"
  ],
  "names": [
    "Petromantulum",
    "Petrum Viaco"
  ],
  "features": [
    {
      "type": "Feature",
      "geometry": {
        "type": "Point",
        "coordinates": [
          1.7710257,
          49.1203993
        ]
      },
      "properties": {
        "description": "representative point"
      }
    }
  ]
}