{
  "type": "FeatureCollection",
  "title": "Uchkakar",
  "id": "115395944",
  "bbox": [
    52.2996437,
    58.2264921,
    52.2996437,
    58.2264921
  ],
  "description": "Fortified settlement on the banks of the Cheptsa River, inhabited from the 9th-13th centuries CE and associated with the Cheptsa culture",
  "features": [
    {
      "type": "Feature",
      "geometry": {
        "type": "Point",
        "coordinates": [
          52.2996437,
          58.2264921
        ]
      },
      "properties": {
        "description": "representative point"
      }
    },
    {
      "geometry": {
        "type": "Point",
        "coordinates": [
          52.2996437,
          58.2264921
        ]
      },
      "id": "uchkakar",
      "type": "Feature",
      "properties": {
        "description": "Point representing the visible remains of the hillfort at Uchkakar, derived from an OpenStreetMap Node after Zhurbin et al. 2018.",
        "location_precision": "precise",
        "title": "OSM location of Uchkakar",
        "link": "http://pleiades.stoa.org/places/115395944/uchkakar"
      }
    }
  ]
}