{
  "type": "FeatureCollection",
  "title": "Ad Ponte(m) Ises",
  "id": "118545",
  "bbox": [
    15.050087,
    48.146408,
    15.050087,
    48.146408
  ],
  "description": "An ancient place, cited: BAtlas 12 I4 Ad Ponte(m) Ises",
  "names": [
    "Ad Pontem Ises",
    "Ad Ponte Ises"
  ],
  "features": [
    {
      "type": "Feature",
      "geometry": {
        "type": "Point",
        "coordinates": [
          15.050087,
          48.146408
        ]
      },
      "properties": {
        "description": "representative point"
      }
    },
    {
      "geometry": {
        "type": "Point",
        "coordinates": [
          15.050087,
          48.146408
        ]
      },
      "id": "darmc-location-8662",
      "type": "Feature",
      "properties": {
        "description": "1M scale point location",
        "location_precision": "precise",
        "title": "DARMC location 8662",
        "link": "http://pleiades.stoa.org/places/118545/darmc-location-8662"
      }
    }
  ]
}