{
  "type": "FeatureCollection",
  "title": "Ad Iuvense?",
  "id": "118541",
  "bbox": [
    14.715782,
    48.166667,
    14.716667,
    48.167341
  ],
  "description": "An ancient place, cited: BAtlas 12 H4 Ad Iuvense?",
  "names": [
    "Ad Iuvense"
  ],
  "features": [
    {
      "type": "Feature",
      "geometry": {
        "type": "Point",
        "coordinates": [
          14.7162245,
          48.167004
        ]
      },
      "properties": {
        "description": "representative point"
      }
    },
    {
      "geometry": {
        "type": "Point",
        "coordinates": [
          14.715782,
          48.167341
        ]
      },
      "id": "darmc-location-17026",
      "type": "Feature",
      "properties": {
        "description": "1M scale point location",
        "location_precision": "precise",
        "title": "DARMC location 17026",
        "link": "http://pleiades.stoa.org/places/118541/darmc-location-17026"
      }
    },
    {
      "geometry": {
        "type": "Point",
        "coordinates": [
          14.716667,
          48.166667
        ]
      },
      "id": "dare-location",
      "type": "Feature",
      "properties": {
        "description": "Representative point location, site precision",
        "location_precision": "precise",
        "title": "DARE Location",
        "link": "http://pleiades.stoa.org/places/118541/dare-location"
      }
    }
  ]
}