{
  "type": "FeatureCollection",
  "title": "Bergtheim",
  "id": "118596",
  "description": "An ancient place, cited: BAtlas 12 D3 Bergtheim",
  "bbox": [
    10.067673,
    49.898331,
    10.067673,
    49.898331
  ],
  "reprPoint": [
    10.067673,
    49.898331
  ],
  "features": [
    {
      "geometry": {
        "type": "Point",
        "coordinates": [
          10.067673,
          49.898331
        ]
      },
      "id": "darmc-location-11706",
      "type": "Feature",
      "properties": {
        "description": "1M scale point location",
        "location_precision": "precise",
        "title": "DARMC location 11706",
        "link": "http://pleiades.stoa.org/places/118596/darmc-location-11706"
      }
    }
  ]
}