{
  "type": "FeatureCollection",
  "title": "Friedberg",
  "id": "118681",
  "description": "An ancient place, cited: BAtlas 12 B2 Friedberg",
  "bbox": [
    8.753676,
    50.336719,
    8.753676,
    50.336719
  ],
  "reprPoint": [
    8.753676,
    50.336719
  ],
  "features": [
    {
      "geometry": {
        "type": "Point",
        "coordinates": [
          8.753676,
          50.336719
        ]
      },
      "id": "darmc-location-7762",
      "type": "Feature",
      "properties": {
        "description": "1M scale point location",
        "location_precision": "precise",
        "title": "DARMC location 7762",
        "link": "http://pleiades.stoa.org/places/118681/darmc-location-7762"
      }
    }
  ]
}