{
  "type": "FeatureCollection",
  "title": "Emerkingen",
  "id": "118665",
  "bbox": [
    9.648333,
    48.211966,
    9.656127,
    48.218611
  ],
  "description": "An ancient place, cited: BAtlas 12 C4 Emerkingen",
  "features": [
    {
      "type": "Feature",
      "geometry": {
        "type": "Point",
        "coordinates": [
          9.65223,
          48.2152885
        ]
      },
      "properties": {
        "description": "representative point"
      }
    },
    {
      "geometry": {
        "type": "Point",
        "coordinates": [
          9.656127,
          48.211966
        ]
      },
      "id": "darmc-location-7718",
      "type": "Feature",
      "properties": {
        "description": "1M scale point location",
        "location_precision": "precise",
        "title": "DARMC location 7718",
        "link": "http://pleiades.stoa.org/places/118665/darmc-location-7718"
      }
    },
    {
      "geometry": {
        "type": "Point",
        "coordinates": [
          9.648333,
          48.218611
        ]
      },
      "id": "dare-location",
      "type": "Feature",
      "properties": {
        "description": "Representative point location, site precision",
        "location_precision": "precise",
        "title": "DARE Location",
        "link": "http://pleiades.stoa.org/places/118665/dare-location"
      }
    }
  ]
}