{
  "type": "FeatureCollection",
  "title": "Finsterlohr",
  "id": "118676",
  "description": "An ancient place, cited: BAtlas 12 D3 Finsterlohr",
  "bbox": [
    10.121086,
    49.437202,
    10.121086,
    49.437202
  ],
  "reprPoint": [
    10.121086,
    49.437202
  ],
  "features": [
    {
      "geometry": {
        "type": "Point",
        "coordinates": [
          10.121086,
          49.437202
        ]
      },
      "id": "dare-location",
      "type": "Feature",
      "properties": {
        "description": "Representative point location, site precision",
        "location_precision": "precise",
        "title": "DARE Location",
        "link": "http://pleiades.stoa.org/places/118676/dare-location"
      }
    }
  ]
}