{
  "type": "FeatureCollection",
  "title": "Buch",
  "id": "118614",
  "description": "An ancient place, cited: BAtlas 12 D4 Buch",
  "bbox": [
    10.133905,
    48.907784,
    10.145156,
    48.909717
  ],
  "reprPoint": [
    10.1395305,
    48.9087505
  ],
  "features": [
    {
      "geometry": {
        "type": "Point",
        "coordinates": [
          10.133905,
          48.907784
        ]
      },
      "id": "darmc-location-7471",
      "type": "Feature",
      "properties": {
        "description": "1M scale point location",
        "location_precision": "precise",
        "title": "DARMC location 7471",
        "link": "http://pleiades.stoa.org/places/118614/darmc-location-7471"
      }
    },
    {
      "geometry": {
        "type": "Point",
        "coordinates": [
          10.145156,
          48.909717
        ]
      },
      "id": "dare-location",
      "type": "Feature",
      "properties": {
        "description": "Representative point location, site precision",
        "location_precision": "precise",
        "title": "DARE Location",
        "link": "http://pleiades.stoa.org/places/118614/dare-location"
      }
    }
  ]
}