{
  "type": "FeatureCollection",
  "title": "Freystadt",
  "id": "118680",
  "bbox": [
    11.328034,
    49.199321,
    11.328034,
    49.199321
  ],
  "description": "An ancient place, cited: BAtlas 12 E3 Freystadt",
  "features": [
    {
      "type": "Feature",
      "geometry": {
        "type": "Point",
        "coordinates": [
          11.328034,
          49.199321
        ]
      },
      "properties": {
        "description": "representative point"
      }
    },
    {
      "geometry": {
        "type": "Point",
        "coordinates": [
          11.328034,
          49.199321
        ]
      },
      "id": "darmc-location-12453",
      "type": "Feature",
      "properties": {
        "description": "1M scale point location",
        "location_precision": "precise",
        "title": "DARMC location 12453",
        "link": "http://pleiades.stoa.org/places/118680/darmc-location-12453"
      }
    }
  ]
}