{
  "type": "FeatureCollection",
  "title": "Finsterlohr",
  "id": "118676",
  "description": "An ancient place, cited: BAtlas 12 D3 Finsterlohr",
  "bbox": [
    10.094829,
    49.434977,
    10.121086,
    49.437202
  ],
  "reprPoint": [
    10.1079575,
    49.4360895
  ],
  "features": [
    {
      "geometry": {
        "type": "Point",
        "coordinates": [
          10.094829,
          49.434977
        ]
      },
      "id": "darmc-location-12432",
      "type": "Feature",
      "properties": {
        "description": "1M scale point location",
        "location_precision": "precise",
        "title": "DARMC location 12432",
        "link": "http://pleiades.stoa.org/places/118676/darmc-location-12432"
      }
    },
    {
      "geometry": {
        "type": "Point",
        "coordinates": [
          10.121086,
          49.437202
        ]
      },
      "id": "dare-location",
      "type": "Feature",
      "properties": {
        "description": "Representative point location, site precision",
        "location_precision": "precise",
        "title": "DARE Location",
        "link": "http://pleiades.stoa.org/places/118676/dare-location"
      }
    }
  ]
}