{
  "type": "FeatureCollection",
  "title": "Gera",
  "id": "118694",
  "description": "An ancient place, cited: BAtlas 12 F2 Gera",
  "bbox": [
    12.076946,
    50.90186,
    12.076946,
    50.90186
  ],
  "reprPoint": [
    12.076946,
    50.90186
  ],
  "features": [
    {
      "geometry": {
        "type": "Point",
        "coordinates": [
          12.076946,
          50.90186
        ]
      },
      "id": "darmc-location-12523",
      "type": "Feature",
      "properties": {
        "description": "1M scale point location",
        "location_precision": "precise",
        "title": "DARMC location 12523",
        "link": "http://pleiades.stoa.org/places/118694/darmc-location-12523"
      }
    }
  ]
}