{
  "type": "FeatureCollection",
  "title": "Dittigheim",
  "id": "118646",
  "description": "An ancient place, cited: BAtlas 12 C3 Dittigheim",
  "bbox": [
    9.674325,
    49.610885,
    9.674325,
    49.610885
  ],
  "reprPoint": [
    9.674325,
    49.610885
  ],
  "features": [
    {
      "geometry": {
        "type": "Point",
        "coordinates": [
          9.674325,
          49.610885
        ]
      },
      "id": "darmc-location-12214",
      "type": "Feature",
      "properties": {
        "description": "1M scale point location",
        "location_precision": "precise",
        "title": "DARMC location 12214",
        "link": "http://pleiades.stoa.org/places/118646/darmc-location-12214"
      }
    }
  ]
}