{
  "type": "FeatureCollection",
  "title": "Burladingen",
  "id": "118618",
  "description": "An ancient place, cited: BAtlas 12 C4 Burladingen",
  "bbox": [
    9.115248,
    48.289167,
    9.115248,
    48.289167
  ],
  "reprPoint": [
    9.115248,
    48.289167
  ],
  "features": [
    {
      "geometry": {
        "type": "Point",
        "coordinates": [
          9.115248,
          48.289167
        ]
      },
      "id": "darmc-location-7483",
      "type": "Feature",
      "properties": {
        "description": "1M scale point location",
        "location_precision": "precise",
        "title": "DARMC location 7483",
        "link": "http://pleiades.stoa.org/places/118618/darmc-location-7483"
      }
    }
  ]
}