{
  "type": "FeatureCollection",
  "title": "Celeusum",
  "id": "118628",
  "description": "An ancient place, cited: BAtlas 12 E4 Celeusum",
  "bbox": [
    11.68892,
    48.808048,
    11.68892,
    48.808048
  ],
  "reprPoint": [
    11.68892,
    48.808048
  ],
  "names": [
    "Celeusum"
  ],
  "features": [
    {
      "geometry": {
        "type": "Point",
        "coordinates": [
          11.68892,
          48.808048
        ]
      },
      "id": "darmc-location-7552",
      "type": "Feature",
      "properties": {
        "description": "1M scale point location",
        "location_precision": "precise",
        "title": "DARMC location 7552",
        "link": "http://pleiades.stoa.org/places/118628/darmc-location-7552"
      }
    }
  ]
}