{
  "type": "FeatureCollection",
  "title": "Dobřichov",
  "id": "118647",
  "description": "An ancient place, cited: BAtlas 12 I2 Dobřichov",
  "bbox": [
    15.032019,
    50.079289,
    15.032019,
    50.079289
  ],
  "reprPoint": [
    15.032019,
    50.079289
  ],
  "features": [
    {
      "geometry": {
        "type": "Point",
        "coordinates": [
          15.032019,
          50.079289
        ]
      },
      "id": "darmc-location-12222",
      "type": "Feature",
      "properties": {
        "description": "1M scale point location",
        "location_precision": "precise",
        "title": "DARMC location 12222",
        "link": "http://pleiades.stoa.org/places/118647/darmc-location-12222"
      }
    }
  ]
}