{
  "type": "FeatureCollection",
  "title": "Hassleben",
  "id": "118727",
  "description": "An ancient place, cited: BAtlas 12 D1 Hassleben",
  "bbox": [
    10.993579,
    51.107945,
    10.993597,
    51.108067
  ],
  "reprPoint": [
    10.993588,
    51.108006
  ],
  "features": [
    {
      "geometry": {
        "type": "Point",
        "coordinates": [
          10.993597,
          51.107945
        ]
      },
      "id": "darmc-location-23667",
      "type": "Feature",
      "properties": {
        "description": "Point location",
        "location_precision": "precise",
        "title": "DARMC location 23667",
        "link": "http://pleiades.stoa.org/places/118727/darmc-location-23667"
      }
    },
    {
      "geometry": {
        "type": "Point",
        "coordinates": [
          10.993579,
          51.108067
        ]
      },
      "id": "darmc-location-12679",
      "type": "Feature",
      "properties": {
        "description": "1M scale point location",
        "location_precision": "precise",
        "title": "DARMC location 12679",
        "link": "http://pleiades.stoa.org/places/118727/darmc-location-12679"
      }
    }
  ]
}