{
  "type": "FeatureCollection",
  "title": "Heuneburg",
  "id": "118742",
  "description": "An ancient place, cited: BAtlas 12 C4 Heuneburg",
  "bbox": [
    9.412566,
    48.094667,
    9.412566,
    48.094667
  ],
  "reprPoint": [
    9.412566,
    48.094667
  ],
  "features": [
    {
      "geometry": {
        "type": "Point",
        "coordinates": [
          9.412566,
          48.094667
        ]
      },
      "id": "darmc-location-12754",
      "type": "Feature",
      "properties": {
        "description": "1M scale point location",
        "location_precision": "precise",
        "title": "DARMC location 12754",
        "link": "http://pleiades.stoa.org/places/118742/darmc-location-12754"
      }
    }
  ]
}