{
  "type": "FeatureCollection",
  "title": "Ivarus? (river)",
  "id": "118766",
  "description": "An ancient place, cited: BAtlas 12 F4 Ivarus? fl.",
  "bbox": [
    12.751898,
    48.1131796,
    12.751898,
    48.1131796
  ],
  "reprPoint": [
    12.751898,
    48.1131796
  ],
  "names": [
    "Ivarus",
    "Iovarus"
  ],
  "features": [
    {
      "geometry": {
        "type": "Point",
        "coordinates": [
          12.751898,
          48.1131796
        ]
      },
      "id": "osm-location",
      "type": "Feature",
      "properties": {
        "description": "Representative modern location based on OpenStreetMap.",
        "location_precision": "precise",
        "title": "OSM location of Salzach (river)",
        "link": "http://pleiades.stoa.org/places/118766/osm-location"
      }
    }
  ]
}