{
  "type": "FeatureCollection",
  "title": "Kyjice",
  "id": "118794",
  "description": "An ancient place, cited: BAtlas 12 G2 Kyjice",
  "bbox": [
    13.485903,
    50.509549,
    13.485903,
    50.509549
  ],
  "reprPoint": [
    13.485903,
    50.509549
  ],
  "features": [
    {
      "geometry": {
        "type": "Point",
        "coordinates": [
          13.485903,
          50.509549
        ]
      },
      "id": "darmc-location-13347",
      "type": "Feature",
      "properties": {
        "description": "1M scale point location",
        "location_precision": "precise",
        "title": "DARMC location 13347",
        "link": "http://pleiades.stoa.org/places/118794/darmc-location-13347"
      }
    }
  ]
}