{
  "type": "FeatureCollection",
  "title": "Kleinzerbst",
  "id": "118784",
  "description": "An ancient place, cited: BAtlas 12 F1 Kleinzerbst",
  "bbox": [
    12.04767,
    51.856291,
    12.04767,
    51.856291
  ],
  "reprPoint": [
    12.04767,
    51.856291
  ],
  "features": [
    {
      "geometry": {
        "type": "Point",
        "coordinates": [
          12.04767,
          51.856291
        ]
      },
      "id": "darmc-location-23653",
      "type": "Feature",
      "properties": {
        "description": "Point location",
        "location_precision": "precise",
        "title": "DARMC location 23653",
        "link": "http://pleiades.stoa.org/places/118784/darmc-location-23653"
      }
    }
  ]
}