{
  "type": "FeatureCollection",
  "title": "Hanau",
  "id": "118726",
  "description": "An ancient place, cited: BAtlas 12 B2 Hanau",
  "bbox": [
    8.895286,
    50.128857,
    8.915114,
    50.135405
  ],
  "reprPoint": [
    8.9052,
    50.132131
  ],
  "features": [
    {
      "geometry": {
        "type": "Point",
        "coordinates": [
          8.895286,
          50.128857
        ]
      },
      "id": "dare-location",
      "type": "Feature",
      "properties": {
        "description": "Representative point location, site precision",
        "location_precision": "precise",
        "title": "DARE Location",
        "link": "http://pleiades.stoa.org/places/118726/dare-location"
      }
    },
    {
      "geometry": {
        "type": "Point",
        "coordinates": [
          8.915114,
          50.135405
        ]
      },
      "id": "darmc-location-7303",
      "type": "Feature",
      "properties": {
        "description": "1M scale point location",
        "location_precision": "precise",
        "title": "DARMC location 7303",
        "link": "http://pleiades.stoa.org/places/118726/darmc-location-7303"
      }
    }
  ]
}