{
  "type": "FeatureCollection",
  "title": "*Grinario",
  "id": "118706",
  "bbox": [
    9.360069,
    48.677292,
    9.360069,
    48.677292
  ],
  "description": "An ancient place, cited: BAtlas 12 C4 *Grinario",
  "names": [
    "Grinario"
  ],
  "features": [
    {
      "type": "Feature",
      "geometry": {
        "type": "Point",
        "coordinates": [
          9.360069,
          48.677292
        ]
      },
      "properties": {
        "description": "representative point"
      }
    },
    {
      "geometry": {
        "type": "Point",
        "coordinates": [
          9.360069,
          48.677292
        ]
      },
      "id": "dare-location",
      "type": "Feature",
      "properties": {
        "description": "Representative point location, site precision",
        "location_precision": "precise",
        "title": "DARE Location",
        "link": "http://pleiades.stoa.org/places/118706/dare-location"
      }
    }
  ]
}