{
  "type": "FeatureCollection",
  "title": "Hainhaus",
  "id": "118724",
  "description": "An ancient place, cited: BAtlas 12 C3 Hainhaus",
  "bbox": [
    9.083194,
    49.732778,
    9.083646,
    49.733467
  ],
  "reprPoint": [
    9.08342,
    49.7331225
  ],
  "features": [
    {
      "geometry": {
        "type": "Point",
        "coordinates": [
          9.083194,
          49.732778
        ]
      },
      "id": "dare-location",
      "type": "Feature",
      "properties": {
        "description": "Representative point location, site precision",
        "location_precision": "precise",
        "title": "DARE Location",
        "link": "http://pleiades.stoa.org/places/118724/dare-location"
      }
    },
    {
      "geometry": {
        "type": "Point",
        "coordinates": [
          9.083646,
          49.733467
        ]
      },
      "id": "darmc-location-6884",
      "type": "Feature",
      "properties": {
        "description": "1M scale point location",
        "location_precision": "precise",
        "title": "DARMC location 6884",
        "link": "http://pleiades.stoa.org/places/118724/darmc-location-6884"
      }
    }
  ]
}