{
  "type": "FeatureCollection",
  "title": "Heiligenberg",
  "id": "118735",
  "bbox": [
    8.706091,
    49.425815,
    8.706091,
    49.425815
  ],
  "description": "An ancient place, cited: BAtlas 12 B3 Heiligenberg",
  "features": [
    {
      "type": "Feature",
      "geometry": {
        "type": "Point",
        "coordinates": [
          8.706091,
          49.425815
        ]
      },
      "properties": {
        "description": "representative point"
      }
    },
    {
      "geometry": {
        "type": "Point",
        "coordinates": [
          8.706091,
          49.425815
        ]
      },
      "id": "darmc-location-12689",
      "type": "Feature",
      "properties": {
        "description": "1M scale point location",
        "location_precision": "precise",
        "title": "DARMC location 12689",
        "link": "http://pleiades.stoa.org/places/118735/darmc-location-12689"
      }
    }
  ]
}