{
  "type": "FeatureCollection",
  "title": "Kadaň",
  "id": "118773",
  "bbox": [
    13.270739,
    50.376292,
    13.270739,
    50.376292
  ],
  "description": "An ancient place, cited: BAtlas 12 G2 Kadaň",
  "features": [
    {
      "type": "Feature",
      "geometry": {
        "type": "Point",
        "coordinates": [
          13.270739,
          50.376292
        ]
      },
      "properties": {
        "description": "representative point"
      }
    },
    {
      "geometry": {
        "type": "Point",
        "coordinates": [
          13.270739,
          50.376292
        ]
      },
      "id": "darmc-location-12941",
      "type": "Feature",
      "properties": {
        "description": "1M scale point location",
        "location_precision": "precise",
        "title": "DARMC location 12941",
        "link": "http://pleiades.stoa.org/places/118773/darmc-location-12941"
      }
    }
  ]
}