{
  "type": "FeatureCollection",
  "title": "Haddamar I",
  "id": "118721",
  "description": "An ancient place, cited: BAtlas 12 C1 Haddamar I",
  "bbox": [
    9.264062,
    51.160863,
    9.264062,
    51.160863
  ],
  "reprPoint": [
    9.264062,
    51.160863
  ],
  "features": [
    {
      "geometry": {
        "type": "Point",
        "coordinates": [
          9.264062,
          51.160863
        ]
      },
      "id": "darmc-location-12641",
      "type": "Feature",
      "properties": {
        "description": "1M scale point location",
        "location_precision": "precise",
        "title": "DARMC location 12641",
        "link": "http://pleiades.stoa.org/places/118721/darmc-location-12641"
      }
    }
  ]
}