{
  "type": "FeatureCollection",
  "title": "Leuna",
  "id": "118804",
  "description": "An ancient place, cited: BAtlas 12 F1 Leuna",
  "bbox": [
    12.015592,
    51.321777,
    12.015592,
    51.321777
  ],
  "reprPoint": [
    12.015592,
    51.321777
  ],
  "features": [
    {
      "geometry": {
        "type": "Point",
        "coordinates": [
          12.015592,
          51.321777
        ]
      },
      "id": "darmc-location-23674",
      "type": "Feature",
      "properties": {
        "description": "Point location",
        "location_precision": "precise",
        "title": "DARMC location 23674",
        "link": "http://pleiades.stoa.org/places/118804/darmc-location-23674"
      }
    }
  ]
}