{
  "type": "FeatureCollection",
  "title": "Maiersch",
  "id": "118828",
  "description": "An ancient place, cited: BAtlas 12 I4 Maiersch",
  "bbox": [
    15.689122,
    48.576768,
    15.689122,
    48.576768
  ],
  "reprPoint": [
    15.689122,
    48.576768
  ],
  "features": [
    {
      "geometry": {
        "type": "Point",
        "coordinates": [
          15.689122,
          48.576768
        ]
      },
      "id": "darmc-location-13593",
      "type": "Feature",
      "properties": {
        "description": "1M scale point location",
        "location_precision": "precise",
        "title": "DARMC location 13593",
        "link": "http://pleiades.stoa.org/places/118828/darmc-location-13593"
      }
    }
  ]
}