{
  "type": "FeatureCollection",
  "title": "Lentia",
  "id": "118803",
  "description": "An ancient place, cited: BAtlas 12 H4 Lentia",
  "bbox": [
    14.286293,
    48.303056,
    14.290556,
    48.306072
  ],
  "reprPoint": [
    14.2884245,
    48.304564
  ],
  "names": [
    "Linz",
    "Lentia"
  ],
  "features": [
    {
      "geometry": {
        "type": "Point",
        "coordinates": [
          14.286293,
          48.306072
        ]
      },
      "id": "darmc-location-7900",
      "type": "Feature",
      "properties": {
        "description": "1M scale point location",
        "location_precision": "precise",
        "title": "DARMC location 7900",
        "link": "http://pleiades.stoa.org/places/118803/darmc-location-7900"
      }
    },
    {
      "geometry": {
        "type": "Point",
        "coordinates": [
          14.290556,
          48.303056
        ]
      },
      "id": "dare-location",
      "type": "Feature",
      "properties": {
        "description": "Representative point location, site precision",
        "location_precision": "precise",
        "title": "DARE Location",
        "link": "http://pleiades.stoa.org/places/118803/dare-location"
      }
    }
  ]
}