{
  "type": "FeatureCollection",
  "title": "Miltenberg-Altstadt",
  "id": "118845",
  "description": "An ancient place, cited: BAtlas 12 C3 Miltenberg-Altstadt",
  "bbox": [
    9.2300905,
    49.70264,
    9.256847,
    49.7092365
  ],
  "reprPoint": [
    9.24346875,
    49.70593825
  ],
  "features": [
    {
      "geometry": {
        "type": "Point",
        "coordinates": [
          9.2300905,
          49.7092365
        ]
      },
      "id": "dare-location",
      "type": "Feature",
      "properties": {
        "description": "Representative point location, site precision",
        "location_precision": "precise",
        "title": "DARE Location",
        "link": "http://pleiades.stoa.org/places/118845/dare-location"
      }
    },
    {
      "geometry": {
        "type": "Point",
        "coordinates": [
          9.256847,
          49.70264
        ]
      },
      "id": "darmc-location-18120",
      "type": "Feature",
      "properties": {
        "description": "1M scale point location",
        "location_precision": "precise",
        "title": "DARMC location 18120",
        "link": "http://pleiades.stoa.org/places/118845/darmc-location-18120"
      }
    }
  ]
}