{
  "type": "FeatureCollection",
  "title": "Murrhardt",
  "id": "118854",
  "description": "An ancient place, cited: BAtlas 12 C4 Murrhardt",
  "bbox": [
    9.5815,
    48.977103,
    9.582194,
    48.980025
  ],
  "reprPoint": [
    9.581847,
    48.978564
  ],
  "features": [
    {
      "geometry": {
        "type": "Point",
        "coordinates": [
          9.5815,
          48.980025
        ]
      },
      "id": "darmc-location-8125",
      "type": "Feature",
      "properties": {
        "description": "1M scale point location",
        "location_precision": "precise",
        "title": "DARMC location 8125",
        "link": "http://pleiades.stoa.org/places/118854/darmc-location-8125"
      }
    },
    {
      "geometry": {
        "type": "Point",
        "coordinates": [
          9.582194,
          48.977103
        ]
      },
      "id": "dare-location",
      "type": "Feature",
      "properties": {
        "description": "Representative point location, site precision",
        "location_precision": "precise",
        "title": "DARE Location",
        "link": "http://pleiades.stoa.org/places/118854/dare-location"
      }
    }
  ]
}