{
  "type": "FeatureCollection",
  "title": "Lopodunum",
  "id": "118813",
  "description": "An ancient place, cited: BAtlas 12 B3 Lopodunum",
  "bbox": [
    8.614162,
    49.47416,
    8.614162,
    49.47416
  ],
  "reprPoint": [
    8.614162,
    49.47416
  ],
  "names": [
    "Ladenburg",
    "Lopodunum"
  ],
  "features": [
    {
      "geometry": {
        "type": "Point",
        "coordinates": [
          8.614162,
          49.47416
        ]
      },
      "id": "darmc-location-13524",
      "type": "Feature",
      "properties": {
        "description": "1M scale point location",
        "location_precision": "precise",
        "title": "DARMC location 13524",
        "link": "http://pleiades.stoa.org/places/118813/darmc-location-13524"
      }
    }
  ]
}