{
  "type": "FeatureCollection",
  "title": "Obernburg",
  "id": "118889",
  "description": "An ancient place, cited: BAtlas 12 C3 Obernburg",
  "bbox": [
    9.145972,
    49.841111,
    9.147765,
    49.842283
  ],
  "reprPoint": [
    9.1468685,
    49.841697
  ],
  "features": [
    {
      "geometry": {
        "type": "Point",
        "coordinates": [
          9.147765,
          49.842283
        ]
      },
      "id": "darmc-location-8149",
      "type": "Feature",
      "properties": {
        "description": "1M scale point location",
        "location_precision": "precise",
        "title": "DARMC location 8149",
        "link": "http://pleiades.stoa.org/places/118889/darmc-location-8149"
      }
    },
    {
      "geometry": {
        "type": "Point",
        "coordinates": [
          9.145972,
          49.841111
        ]
      },
      "id": "dare-location",
      "type": "Feature",
      "properties": {
        "description": "Representative point location, site precision",
        "location_precision": "precise",
        "title": "DARE Location",
        "link": "http://pleiades.stoa.org/places/118889/dare-location"
      }
    }
  ]
}