{
  "type": "FeatureCollection",
  "title": "Losodica",
  "id": "118815",
  "bbox": [
    10.602346,
    48.921544,
    10.602346,
    48.921544
  ],
  "description": "An ancient place, cited: BAtlas 12 D4 Losodica",
  "names": [
    "Losodica"
  ],
  "features": [
    {
      "type": "Feature",
      "geometry": {
        "type": "Point",
        "coordinates": [
          10.602346,
          48.921544
        ]
      },
      "properties": {
        "description": "representative point"
      }
    },
    {
      "geometry": {
        "type": "Point",
        "coordinates": [
          10.602346,
          48.921544
        ]
      },
      "id": "darmc-location-7919",
      "type": "Feature",
      "properties": {
        "description": "1M scale point location",
        "location_precision": "precise",
        "title": "DARMC location 7919",
        "link": "http://pleiades.stoa.org/places/118815/darmc-location-7919"
      }
    }
  ]
}