{
  "type": "FeatureCollection",
  "title": "Nebra",
  "id": "118860",
  "description": "An ancient place, cited: BAtlas 12 E1 Nebra",
  "bbox": [
    11.577288,
    51.283321,
    11.58333,
    51.289038
  ],
  "reprPoint": [
    11.580309,
    51.2861795
  ],
  "features": [
    {
      "geometry": {
        "type": "Point",
        "coordinates": [
          11.58333,
          51.283321
        ]
      },
      "id": "darmc-location-23669",
      "type": "Feature",
      "properties": {
        "description": "Point location",
        "location_precision": "precise",
        "title": "DARMC location 23669",
        "link": "http://pleiades.stoa.org/places/118860/darmc-location-23669"
      }
    },
    {
      "geometry": {
        "type": "Point",
        "coordinates": [
          11.577288,
          51.289038
        ]
      },
      "id": "darmc-location-13894",
      "type": "Feature",
      "properties": {
        "description": "1M scale point location",
        "location_precision": "precise",
        "title": "DARMC location 13894",
        "link": "http://pleiades.stoa.org/places/118860/darmc-location-13894"
      }
    }
  ]
}