{
  "type": "FeatureCollection",
  "title": "Pňov",
  "id": "118908",
  "description": "An ancient place, cited: BAtlas 12 I2 Pňov",
  "bbox": [
    15.148262,
    50.085517,
    15.148262,
    50.085517
  ],
  "reprPoint": [
    15.148262,
    50.085517
  ],
  "features": [
    {
      "geometry": {
        "type": "Point",
        "coordinates": [
          15.148262,
          50.085517
        ]
      },
      "id": "darmc-location-14330",
      "type": "Feature",
      "properties": {
        "description": "1M scale point location",
        "location_precision": "precise",
        "title": "DARMC location 14330",
        "link": "http://pleiades.stoa.org/places/118908/darmc-location-14330"
      }
    }
  ]
}