{
  "type": "FeatureCollection",
  "title": "Rederzhausen",
  "id": "118927",
  "description": "An ancient place, cited: BAtlas 12 D4 Rederzhausen",
  "bbox": [
    11.003516,
    48.338717,
    11.003516,
    48.338717
  ],
  "reprPoint": [
    11.003516,
    48.338717
  ],
  "features": [
    {
      "geometry": {
        "type": "Point",
        "coordinates": [
          11.003516,
          48.338717
        ]
      },
      "id": "darmc-location-8236",
      "type": "Feature",
      "properties": {
        "description": "1M scale point location",
        "location_precision": "precise",
        "title": "DARMC location 8236",
        "link": "http://pleiades.stoa.org/places/118927/darmc-location-8236"
      }
    }
  ]
}