{
  "type": "FeatureCollection",
  "title": "Quintana",
  "id": "118919",
  "bbox": [
    13.078749,
    48.668525,
    13.079903,
    48.669403
  ],
  "description": "An ancient place, cited: BAtlas 12 G4 Quintana",
  "names": [
    "Quintana"
  ],
  "features": [
    {
      "type": "Feature",
      "geometry": {
        "type": "Point",
        "coordinates": [
          13.079326,
          48.668964
        ]
      },
      "properties": {
        "description": "representative point"
      }
    },
    {
      "geometry": {
        "type": "Point",
        "coordinates": [
          13.078749,
          48.669403
        ]
      },
      "id": "darmc-location-8223",
      "type": "Feature",
      "properties": {
        "description": "1M scale point location",
        "location_precision": "precise",
        "title": "DARMC location 8223",
        "link": "http://pleiades.stoa.org/places/118919/darmc-location-8223"
      }
    },
    {
      "geometry": {
        "type": "Point",
        "coordinates": [
          13.079903,
          48.668525
        ]
      },
      "id": "dare-location",
      "type": "Feature",
      "properties": {
        "description": "Representative point location, site precision",
        "location_precision": "precise",
        "title": "DARE Location",
        "link": "http://pleiades.stoa.org/places/118919/dare-location"
      }
    }
  ]
}