{
  "type": "FeatureCollection",
  "title": "Phoebiana",
  "id": "118904",
  "description": "An ancient place, cited: BAtlas 12 D4 Phoebiana",
  "bbox": [
    10.409149,
    48.561582,
    10.409149,
    48.561582
  ],
  "reprPoint": [
    10.409149,
    48.561582
  ],
  "names": [
    "Phoebiana"
  ],
  "features": [
    {
      "geometry": {
        "type": "Point",
        "coordinates": [
          10.409149,
          48.561582
        ]
      },
      "id": "darmc-location-14257",
      "type": "Feature",
      "properties": {
        "description": "1M scale point location",
        "location_precision": "precise",
        "title": "DARMC location 14257",
        "link": "http://pleiades.stoa.org/places/118904/darmc-location-14257"
      }
    }
  ]
}