{
  "type": "FeatureCollection",
  "title": "Steinkirchen",
  "id": "118975",
  "bbox": [
    12.837564,
    48.827168,
    12.837564,
    48.827168
  ],
  "description": "An ancient place, cited: BAtlas 12 F4 Steinkirchen",
  "features": [
    {
      "type": "Feature",
      "geometry": {
        "type": "Point",
        "coordinates": [
          12.837564,
          48.827168
        ]
      },
      "properties": {
        "description": "representative point"
      }
    },
    {
      "geometry": {
        "type": "Point",
        "coordinates": [
          12.837564,
          48.827168
        ]
      },
      "id": "darmc-location-8334",
      "type": "Feature",
      "properties": {
        "description": "1M scale point location",
        "location_precision": "precise",
        "title": "DARMC location 8334",
        "link": "http://pleiades.stoa.org/places/118975/darmc-location-8334"
      }
    }
  ]
}