{
  "type": "FeatureCollection",
  "title": "Poláky",
  "id": "118911",
  "description": "An ancient place, cited: BAtlas 12 G2 Poláky",
  "bbox": [
    13.354751,
    50.338053,
    13.354751,
    50.338053
  ],
  "reprPoint": [
    13.354751,
    50.338053
  ],
  "features": [
    {
      "geometry": {
        "type": "Point",
        "coordinates": [
          13.354751,
          50.338053
        ]
      },
      "id": "darmc-location-33677",
      "type": "Feature",
      "properties": {
        "description": "scale point location",
        "location_precision": "precise",
        "title": "DARMC location 33677",
        "link": "http://pleiades.stoa.org/places/118911/darmc-location-33677"
      }
    }
  ]
}