{
  "type": "FeatureCollection",
  "title": "Žalany",
  "id": "119069",
  "bbox": [
    13.905656,
    50.590303,
    13.905656,
    50.590303
  ],
  "description": "An ancient place, cited: BAtlas 12 G2 Žalany",
  "features": [
    {
      "type": "Feature",
      "geometry": {
        "type": "Point",
        "coordinates": [
          13.905656,
          50.590303
        ]
      },
      "properties": {
        "description": "representative point"
      }
    },
    {
      "geometry": {
        "type": "Point",
        "coordinates": [
          13.905656,
          50.590303
        ]
      },
      "id": "darmc-location-15504",
      "type": "Feature",
      "properties": {
        "description": "1M scale point location",
        "location_precision": "precise",
        "title": "DARMC location 15504",
        "link": "http://pleiades.stoa.org/places/119069/darmc-location-15504"
      }
    }
  ]
}