{
  "type": "FeatureCollection",
  "title": "Venaxamodurum",
  "id": "119019",
  "description": "An ancient place, cited: BAtlas 12 E4 Venaxamodurum",
  "bbox": [
    11.184336,
    48.735955,
    11.184336,
    48.735955
  ],
  "reprPoint": [
    11.184336,
    48.735955
  ],
  "names": [
    "Venaxamodurum"
  ],
  "features": [
    {
      "geometry": {
        "type": "Point",
        "coordinates": [
          11.184336,
          48.735955
        ]
      },
      "id": "darmc-location-15367",
      "type": "Feature",
      "properties": {
        "description": "1M scale point location",
        "location_precision": "precise",
        "title": "DARMC location 15367",
        "link": "http://pleiades.stoa.org/places/119019/darmc-location-15367"
      }
    }
  ]
}