{
  "type": "FeatureCollection",
  "title": "Weissenfels",
  "id": "119044",
  "bbox": [
    11.966724,
    51.199825,
    11.966724,
    51.199825
  ],
  "description": "An ancient place, cited: BAtlas 12 E1 Weissenfels",
  "features": [
    {
      "type": "Feature",
      "geometry": {
        "type": "Point",
        "coordinates": [
          11.966724,
          51.199825
        ]
      },
      "properties": {
        "description": "representative point"
      }
    },
    {
      "geometry": {
        "type": "Point",
        "coordinates": [
          11.966724,
          51.199825
        ]
      },
      "id": "darmc-location-23671",
      "type": "Feature",
      "properties": {
        "description": "Point location",
        "location_precision": "precise",
        "title": "DARMC location 23671",
        "link": "http://pleiades.stoa.org/places/119044/darmc-location-23671"
      }
    }
  ]
}