{
  "type": "FeatureCollection",
  "title": "Vrbice",
  "id": "119037",
  "description": "An ancient place, cited: BAtlas 12 G2 Vrbice",
  "bbox": [
    13.52463,
    50.169512,
    13.52463,
    50.169512
  ],
  "reprPoint": [
    13.52463,
    50.169512
  ],
  "features": [
    {
      "geometry": {
        "type": "Point",
        "coordinates": [
          13.52463,
          50.169512
        ]
      },
      "id": "darmc-location-23679",
      "type": "Feature",
      "properties": {
        "description": "Point location",
        "location_precision": "precise",
        "title": "DARMC location 23679",
        "link": "http://pleiades.stoa.org/places/119037/darmc-location-23679"
      }
    }
  ]
}