{
  "type": "FeatureCollection",
  "title": "Ubstadt",
  "id": "119009",
  "bbox": [
    8.632329,
    49.162108,
    8.632329,
    49.162108
  ],
  "description": "An ancient place, cited: BAtlas 12 B3 Ubstadt",
  "features": [
    {
      "type": "Feature",
      "geometry": {
        "type": "Point",
        "coordinates": [
          8.632329,
          49.162108
        ]
      },
      "properties": {
        "description": "representative point"
      }
    },
    {
      "geometry": {
        "type": "Point",
        "coordinates": [
          8.632329,
          49.162108
        ]
      },
      "id": "darmc-location-7201",
      "type": "Feature",
      "properties": {
        "description": "1M scale point location",
        "location_precision": "precise",
        "title": "DARMC location 7201",
        "link": "http://pleiades.stoa.org/places/119009/darmc-location-7201"
      }
    }
  ]
}