{
  "type": "FeatureCollection",
  "title": "Capitolium at Thugga",
  "id": "119729285",
  "bbox": [
    9.2180918,
    36.4227215,
    9.2180918,
    36.4227215
  ],
  "description": "The Capitolium at Thugga dates to the middle of the second century and carries epigraphic dedications to Lucius Verus and Marcus Aurelius dating to the late 160s.",
  "connectsWith": [
    "315223"
  ],
  "features": [
    {
      "type": "Feature",
      "geometry": {
        "type": "Point",
        "coordinates": [
          9.2180918,
          36.4227215
        ]
      },
      "properties": {
        "description": "representative point"
      }
    },
    {
      "geometry": {
        "type": "Point",
        "coordinates": [
          9.2180918,
          36.4227215
        ]
      },
      "id": "location-of-capitolium",
      "type": "Feature",
      "properties": {
        "description": "Location based on OpenStreetMap",
        "location_precision": "precise",
        "title": "OSM location of Capitolium",
        "link": "http://pleiades.stoa.org/places/119729285/location-of-capitolium"
      }
    }
  ]
}