{
  "type": "FeatureCollection",
  "title": "Kirkhill Roman signal station",
  "id": "121620025",
  "bbox": [
    -3.671803,
    56.3503718,
    -3.671803,
    56.3503718
  ],
  "description": "A Roman signal station dating to the Flavian period.",
  "features": [
    {
      "type": "Feature",
      "geometry": {
        "type": "Point",
        "coordinates": [
          -3.671803,
          56.3503718
        ]
      },
      "properties": {
        "description": "representative point"
      }
    },
    {
      "geometry": {
        "type": "Point",
        "coordinates": [
          -3.671803,
          56.3503718
        ]
      },
      "id": "osm-location",
      "type": "Feature",
      "properties": {
        "description": "Representative location based on OpenStreetMap.",
        "location_precision": "precise",
        "title": "OSM location of Kirkhill Roman signal station",
        "link": "http://pleiades.stoa.org/places/121620025/osm-location"
      }
    }
  ]
}