{
  "type": "FeatureCollection",
  "title": "Tell Ba'arura Shargi",
  "id": "123591514",
  "bbox": [
    46.1684,
    30.9786,
    46.1684,
    30.9786
  ],
  "description": "Find place for cuneiform inscription.",
  "features": [
    {
      "type": "Feature",
      "geometry": {
        "type": "Point",
        "coordinates": [
          46.1684,
          30.9786
        ]
      },
      "properties": {
        "description": "representative point"
      }
    },
    {
      "geometry": {
        "type": "Point",
        "coordinates": [
          46.1684,
          30.9786
        ]
      },
      "id": "tell-baarura-shargi",
      "type": "Feature",
      "properties": {
        "description": null,
        "location_precision": "precise",
        "title": "Tell Ba'arura Shargi",
        "link": "http://pleiades.stoa.org/places/123591514/tell-baarura-shargi"
      }
    }
  ]
}