{
  "type": "FeatureCollection",
  "title": "Rutubis",
  "id": "1249",
  "bbox": [
    -8.510524,
    33.254782,
    -8.510524,
    33.254782
  ],
  "description": "An ancient place, cited: BAtlas 1 B4 Rutubis",
  "names": [
    "Rutubis"
  ],
  "features": [
    {
      "type": "Feature",
      "geometry": {
        "type": "Point",
        "coordinates": [
          -8.510524,
          33.254782
        ]
      },
      "properties": {
        "description": "representative point"
      }
    },
    {
      "geometry": {
        "type": "Point",
        "coordinates": [
          -8.510524,
          33.254782
        ]
      },
      "id": "darmc-location-24546",
      "type": "Feature",
      "properties": {
        "description": "5M scale point location",
        "location_precision": "precise",
        "title": "DARMC location 24546",
        "link": "http://pleiades.stoa.org/places/1249/darmc-location-24546"
      }
    }
  ]
}