{
  "type": "FeatureCollection",
  "title": "Gallo-Roman fanum at Lapanouse-de-Cernon",
  "id": "127288246",
  "bbox": [
    3.098374,
    43.9962525,
    3.098374,
    43.9962525
  ],
  "description": "The remains of a possible Gallo-Roman fanum were recovered, including an enclosure surrounding a rectangular structure along with terra sigillata from La Graufesenque.",
  "features": [
    {
      "type": "Feature",
      "geometry": {
        "type": "Point",
        "coordinates": [
          3.098374,
          43.9962525
        ]
      },
      "properties": {
        "description": "representative point"
      }
    },
    {
      "geometry": {
        "type": "Point",
        "coordinates": [
          3.098374,
          43.9962525
        ]
      },
      "id": "osm-location",
      "type": "Feature",
      "properties": {
        "description": "Representative location based on OpenStreetMap.",
        "location_precision": "precise",
        "title": "OSM location of modern Lapanouse-de-Cernon",
        "link": "http://pleiades.stoa.org/places/127288246/osm-location"
      }
    }
  ]
}