{
  "type": "FeatureCollection",
  "title": "Devín",
  "id": "128391",
  "description": "An ancient place, cited: BAtlas 13 C4 Devín",
  "bbox": [
    16.9786220879,
    48.173297,
    16.978816,
    48.1736221791
  ],
  "reprPoint": [
    16.9787190439,
    48.1734595896
  ],
  "features": [
    {
      "geometry": {
        "type": "Point",
        "coordinates": [
          16.97862208789654,
          48.17362217913922
        ]
      },
      "id": "dare-location",
      "type": "Feature",
      "properties": {
        "description": "Representative point location, site precision",
        "location_precision": "precise",
        "title": "DARE Location",
        "link": "http://pleiades.stoa.org/places/128391/dare-location"
      }
    },
    {
      "geometry": {
        "type": "Point",
        "coordinates": [
          16.978816,
          48.173297
        ]
      },
      "id": "darmc-location-12191",
      "type": "Feature",
      "properties": {
        "description": "1M scale point location",
        "location_precision": "precise",
        "title": "DARMC location 12191",
        "link": "http://pleiades.stoa.org/places/128391/darmc-location-12191"
      }
    }
  ]
}