{
  "type": "FeatureCollection",
  "title": "Gajary",
  "id": "128398",
  "description": "An ancient place, cited: BAtlas 13 B4 Gajary",
  "bbox": [
    16.923328,
    48.466148,
    16.923328,
    48.466148
  ],
  "reprPoint": [
    16.923328,
    48.466148
  ],
  "features": [
    {
      "geometry": {
        "type": "Point",
        "coordinates": [
          16.923328,
          48.466148
        ]
      },
      "id": "darmc-location-12469",
      "type": "Feature",
      "properties": {
        "description": "1M scale point location",
        "location_precision": "precise",
        "title": "DARMC location 12469",
        "link": "http://pleiades.stoa.org/places/128398/darmc-location-12469"
      }
    }
  ]
}