{
  "type": "FeatureCollection",
  "title": "Borkovany",
  "id": "128366",
  "bbox": [
    16.81032,
    49.028348,
    16.81032,
    49.028348
  ],
  "description": "An ancient place, cited: BAtlas 13 B3 Borkovany",
  "features": [
    {
      "type": "Feature",
      "geometry": {
        "type": "Point",
        "coordinates": [
          16.81032,
          49.028348
        ]
      },
      "properties": {
        "description": "representative point"
      }
    },
    {
      "geometry": {
        "type": "Point",
        "coordinates": [
          16.81032,
          49.028348
        ]
      },
      "id": "darmc-location-11798",
      "type": "Feature",
      "properties": {
        "description": "1M scale point location",
        "location_precision": "precise",
        "title": "DARMC location 11798",
        "link": "http://pleiades.stoa.org/places/128366/darmc-location-11798"
      }
    }
  ]
}