{
  "type": "FeatureCollection",
  "title": "Blažovice",
  "id": "128363",
  "description": "An ancient place, cited: BAtlas 13 B3 Blažovice",
  "bbox": [
    16.786314,
    49.164684,
    16.786314,
    49.164684
  ],
  "reprPoint": [
    16.786314,
    49.164684
  ],
  "features": [
    {
      "geometry": {
        "type": "Point",
        "coordinates": [
          16.786314,
          49.164684
        ]
      },
      "id": "darmc-location-11776",
      "type": "Feature",
      "properties": {
        "description": "1M scale point location",
        "location_precision": "precise",
        "title": "DARMC location 11776",
        "link": "http://pleiades.stoa.org/places/128363/darmc-location-11776"
      }
    }
  ]
}