{
  "type": "FeatureCollection",
  "title": "Čačov",
  "id": "128374",
  "description": "An ancient place, cited: BAtlas 13 C4 Čačov",
  "bbox": [
    17.331827,
    48.676469,
    17.331827,
    48.676469
  ],
  "reprPoint": [
    17.331827,
    48.676469
  ],
  "features": [
    {
      "geometry": {
        "type": "Point",
        "coordinates": [
          17.331827,
          48.676469
        ]
      },
      "id": "darmc-location-23806",
      "type": "Feature",
      "properties": {
        "description": "Point location",
        "location_precision": "precise",
        "title": "DARMC location 23806",
        "link": "http://pleiades.stoa.org/places/128374/darmc-location-23806"
      }
    }
  ]
}