{
  "type": "FeatureCollection",
  "title": "Branč",
  "id": "128368",
  "description": "An ancient place, cited: BAtlas 13 D4 Branč",
  "bbox": [
    18.147057,
    48.209927,
    18.147057,
    48.209927
  ],
  "reprPoint": [
    18.147057,
    48.209927
  ],
  "features": [
    {
      "geometry": {
        "type": "Point",
        "coordinates": [
          18.147057,
          48.209927
        ]
      },
      "id": "darmc-location-11827",
      "type": "Feature",
      "properties": {
        "description": "1M scale point location",
        "location_precision": "precise",
        "title": "DARMC location 11827",
        "link": "http://pleiades.stoa.org/places/128368/darmc-location-11827"
      }
    }
  ]
}