{
  "type": "FeatureCollection",
  "title": "Dębe",
  "id": "128390",
  "bbox": [
    18.192486,
    51.799035,
    18.192486,
    51.799035
  ],
  "description": "An ancient place, cited: BAtlas 13 D1 Dębe",
  "features": [
    {
      "type": "Feature",
      "geometry": {
        "type": "Point",
        "coordinates": [
          18.192486,
          51.799035
        ]
      },
      "properties": {
        "description": "representative point"
      }
    },
    {
      "geometry": {
        "type": "Point",
        "coordinates": [
          18.192486,
          51.799035
        ]
      },
      "id": "darmc-location-23776",
      "type": "Feature",
      "properties": {
        "description": "Point location",
        "location_precision": "precise",
        "title": "DARMC location 23776",
        "link": "http://pleiades.stoa.org/places/128390/darmc-location-23776"
      }
    }
  ]
}