{
  "type": "FeatureCollection",
  "title": "Braunsberg",
  "id": "128369",
  "description": "An ancient place, cited: BAtlas 13 B4 Braunsberg",
  "bbox": [
    16.956682,
    48.154405,
    16.956682,
    48.154405
  ],
  "reprPoint": [
    16.956682,
    48.154405
  ],
  "features": [
    {
      "geometry": {
        "type": "Point",
        "coordinates": [
          16.956682,
          48.154405
        ]
      },
      "id": "darmc-location-11831",
      "type": "Feature",
      "properties": {
        "description": "1M scale point location",
        "location_precision": "precise",
        "title": "DARMC location 11831",
        "link": "http://pleiades.stoa.org/places/128369/darmc-location-11831"
      }
    }
  ]
}