{
  "type": "FeatureCollection",
  "title": "Křepice",
  "id": "128433",
  "description": "An ancient place, cited: BAtlas 13 B3 Křepice",
  "bbox": [
    16.719762,
    48.999934,
    16.719762,
    48.999934
  ],
  "reprPoint": [
    16.719762,
    48.999934
  ],
  "features": [
    {
      "geometry": {
        "type": "Point",
        "coordinates": [
          16.719762,
          48.999934
        ]
      },
      "id": "darmc-location-13310",
      "type": "Feature",
      "properties": {
        "description": "1M scale point location",
        "location_precision": "precise",
        "title": "DARMC location 13310",
        "link": "http://pleiades.stoa.org/places/128433/darmc-location-13310"
      }
    }
  ]
}