{
  "type": "FeatureCollection",
  "title": "Oblin",
  "id": "128478",
  "description": "An ancient place, cited: BAtlas 13 G1 Oblin",
  "bbox": [
    21.531213,
    51.695182,
    21.531213,
    51.695182
  ],
  "reprPoint": [
    21.531213,
    51.695182
  ],
  "features": [
    {
      "geometry": {
        "type": "Point",
        "coordinates": [
          21.531213,
          51.695182
        ]
      },
      "id": "darmc-location-23820",
      "type": "Feature",
      "properties": {
        "description": "Point location",
        "location_precision": "precise",
        "title": "DARMC location 23820",
        "link": "http://pleiades.stoa.org/places/128478/darmc-location-23820"
      }
    }
  ]
}