{
  "type": "FeatureCollection",
  "title": "Očkov",
  "id": "128479",
  "description": "An ancient place, cited: BAtlas 13 C4 Očkov",
  "bbox": [
    17.764288,
    48.653437,
    17.764288,
    48.653437
  ],
  "reprPoint": [
    17.764288,
    48.653437
  ],
  "features": [
    {
      "geometry": {
        "type": "Point",
        "coordinates": [
          17.764288,
          48.653437
        ]
      },
      "id": "darmc-location-23810",
      "type": "Feature",
      "properties": {
        "description": "Point location",
        "location_precision": "precise",
        "title": "DARMC location 23810",
        "link": "http://pleiades.stoa.org/places/128479/darmc-location-23810"
      }
    }
  ]
}