{
  "type": "FeatureCollection",
  "title": "Ostrovany",
  "id": "128482",
  "bbox": [
    21.11668,
    49.062336,
    21.11668,
    49.062336
  ],
  "description": "An ancient place, cited: BAtlas 13 G3 Ostrovany",
  "features": [
    {
      "type": "Feature",
      "geometry": {
        "type": "Point",
        "coordinates": [
          21.11668,
          49.062336
        ]
      },
      "properties": {
        "description": "representative point"
      }
    },
    {
      "geometry": {
        "type": "Point",
        "coordinates": [
          21.11668,
          49.062336
        ]
      },
      "id": "darmc-location-23824",
      "type": "Feature",
      "properties": {
        "description": "Point location",
        "location_precision": "precise",
        "title": "DARMC location 23824",
        "link": "http://pleiades.stoa.org/places/128482/darmc-location-23824"
      }
    }
  ]
}