{
  "type": "FeatureCollection",
  "title": "Laskiv",
  "id": "128441",
  "description": "An ancient place, cited: BAtlas 13 J2 Laskiv",
  "bbox": [
    24.18884,
    50.788773,
    24.18884,
    50.788773
  ],
  "reprPoint": [
    24.18884,
    50.788773
  ],
  "features": [
    {
      "geometry": {
        "type": "Point",
        "coordinates": [
          24.18884,
          50.788773
        ]
      },
      "id": "darmc-location-15671",
      "type": "Feature",
      "properties": {
        "description": "1M scale point location",
        "location_precision": "precise",
        "title": "DARMC location 15671",
        "link": "http://pleiades.stoa.org/places/128441/darmc-location-15671"
      }
    }
  ]
}