{
  "type": "FeatureCollection",
  "title": "Niechmirów-Mała Wieś",
  "id": "128467",
  "description": "An ancient place, cited: BAtlas 13 D1 Niechmirów-Mała Wieś",
  "bbox": [
    18.762187,
    51.391121,
    18.762187,
    51.391121
  ],
  "reprPoint": [
    18.762187,
    51.391121
  ],
  "features": [
    {
      "geometry": {
        "type": "Point",
        "coordinates": [
          18.762187,
          51.391121
        ]
      },
      "id": "darmc-location-33773",
      "type": "Feature",
      "properties": {
        "description": "scale point location",
        "location_precision": "precise",
        "title": "DARMC location 33773",
        "link": "http://pleiades.stoa.org/places/128467/darmc-location-33773"
      }
    }
  ]
}