{
  "type": "FeatureCollection",
  "title": "Gródek nad Bugiem",
  "id": "128405",
  "bbox": [
    23.948536,
    50.79872,
    23.948536,
    50.79872
  ],
  "description": "An ancient place, cited: BAtlas 13 I2 Gródek nad Bugiem",
  "features": [
    {
      "type": "Feature",
      "geometry": {
        "type": "Point",
        "coordinates": [
          23.948536,
          50.79872
        ]
      },
      "properties": {
        "description": "representative point"
      }
    },
    {
      "geometry": {
        "type": "Point",
        "coordinates": [
          23.948536,
          50.79872
        ]
      },
      "id": "darmc-location-33821",
      "type": "Feature",
      "properties": {
        "description": "representative point location digitized from the Barrington Atlas of the Greek and Roman World by the Digital Atlas of Roman and Medieval Civilizations project at Harvard University.",
        "location_precision": "precise",
        "title": "DARMC location 33821",
        "link": "http://pleiades.stoa.org/places/128405/darmc-location-33821"
      }
    }
  ]
}