{
  "type": "FeatureCollection",
  "title": "Mauerbach",
  "id": "128453",
  "description": "An ancient place, cited: BAtlas 13 B4 Mauerbach",
  "bbox": [
    16.167939,
    48.24547,
    16.167939,
    48.24547
  ],
  "reprPoint": [
    16.167939,
    48.24547
  ],
  "features": [
    {
      "geometry": {
        "type": "Point",
        "coordinates": [
          16.167939,
          48.24547
        ]
      },
      "id": "darmc-location-8096",
      "type": "Feature",
      "properties": {
        "description": "1M scale point location",
        "location_precision": "precise",
        "title": "DARMC location 8096",
        "link": "http://pleiades.stoa.org/places/128453/darmc-location-8096"
      }
    }
  ]
}