{
  "type": "FeatureCollection",
  "title": "Metelin",
  "id": "128455",
  "bbox": [
    23.85935,
    50.749782,
    23.85935,
    50.749782
  ],
  "description": "An ancient place, cited: BAtlas 13 I2 Metelin",
  "features": [
    {
      "type": "Feature",
      "geometry": {
        "type": "Point",
        "coordinates": [
          23.85935,
          50.749782
        ]
      },
      "properties": {
        "description": "representative point"
      }
    },
    {
      "geometry": {
        "type": "Point",
        "coordinates": [
          23.85935,
          50.749782
        ]
      },
      "id": "darmc-location-15672",
      "type": "Feature",
      "properties": {
        "description": "1M scale point location",
        "location_precision": "precise",
        "title": "DARMC location 15672",
        "link": "http://pleiades.stoa.org/places/128455/darmc-location-15672"
      }
    }
  ]
}