{
  "type": "FeatureCollection",
  "title": "Przeworsk-Gać",
  "id": "128497",
  "description": "An ancient place, cited: BAtlas 13 H2 Przeworsk-Gać",
  "bbox": [
    22.493776,
    50.058696,
    22.493776,
    50.058696
  ],
  "reprPoint": [
    22.493776,
    50.058696
  ],
  "features": [
    {
      "geometry": {
        "type": "Point",
        "coordinates": [
          22.493776,
          50.058696
        ]
      },
      "id": "darmc-location-33823",
      "type": "Feature",
      "properties": {
        "description": "scale point location",
        "location_precision": "precise",
        "title": "DARMC location 33823",
        "link": "http://pleiades.stoa.org/places/128497/darmc-location-33823"
      }
    }
  ]
}