{
  "type": "FeatureCollection",
  "title": "Komjatice",
  "id": "128428",
  "description": "An ancient place, cited: BAtlas 13 D4 Komjatice",
  "bbox": [
    18.170175,
    48.157233,
    18.170175,
    48.157233
  ],
  "reprPoint": [
    18.170175,
    48.157233
  ],
  "features": [
    {
      "geometry": {
        "type": "Point",
        "coordinates": [
          18.170175,
          48.157233
        ]
      },
      "id": "darmc-location-13246",
      "type": "Feature",
      "properties": {
        "description": "1M scale point location",
        "location_precision": "precise",
        "title": "DARMC location 13246",
        "link": "http://pleiades.stoa.org/places/128428/darmc-location-13246"
      }
    }
  ]
}