{
  "type": "FeatureCollection",
  "title": "Kraków-Nowa Huta",
  "id": "128432",
  "description": "An ancient place, cited: BAtlas 13 F2 Kraków-Nowa Huta",
  "bbox": [
    19.937627,
    50.059376,
    19.937627,
    50.059376
  ],
  "reprPoint": [
    19.937627,
    50.059376
  ],
  "features": [
    {
      "geometry": {
        "type": "Point",
        "coordinates": [
          19.937627,
          50.059376
        ]
      },
      "id": "darmc-location-23298",
      "type": "Feature",
      "properties": {
        "description": "1M scale point location",
        "location_precision": "precise",
        "title": "DARMC location 23298",
        "link": "http://pleiades.stoa.org/places/128432/darmc-location-23298"
      }
    }
  ]
}