{
  "type": "FeatureCollection",
  "title": "Nietulisko Małe",
  "id": "128469",
  "bbox": [
    21.257289,
    50.970514,
    21.257289,
    50.970514
  ],
  "description": "An ancient place, cited: BAtlas 13 G2 Nietulisko Małe",
  "features": [
    {
      "type": "Feature",
      "geometry": {
        "type": "Point",
        "coordinates": [
          21.257289,
          50.970514
        ]
      },
      "properties": {
        "description": "representative point"
      }
    },
    {
      "geometry": {
        "type": "Point",
        "coordinates": [
          21.257289,
          50.970514
        ]
      },
      "id": "darmc-location-25675",
      "type": "Feature",
      "properties": {
        "description": "1M scale point location",
        "location_precision": "precise",
        "title": "DARMC location 25675",
        "link": "http://pleiades.stoa.org/places/128469/darmc-location-25675"
      }
    }
  ]
}