{
  "type": "FeatureCollection",
  "title": "Šarovce",
  "id": "128507",
  "description": "An ancient place, cited: BAtlas 13 D4 Šarovce",
  "bbox": [
    18.635083,
    48.104855,
    18.635083,
    48.104855
  ],
  "reprPoint": [
    18.635083,
    48.104855
  ],
  "features": [
    {
      "geometry": {
        "type": "Point",
        "coordinates": [
          18.635083,
          48.104855
        ]
      },
      "id": "darmc-location-14614",
      "type": "Feature",
      "properties": {
        "description": "1M scale point location",
        "location_precision": "precise",
        "title": "DARMC location 14614",
        "link": "http://pleiades.stoa.org/places/128507/darmc-location-14614"
      }
    }
  ]
}