{
  "type": "FeatureCollection",
  "title": "Stillfried",
  "id": "128519",
  "bbox": [
    16.84325,
    48.410019,
    16.84325,
    48.410019
  ],
  "description": "An ancient place, cited: BAtlas 13 B4 Stillfried",
  "features": [
    {
      "type": "Feature",
      "geometry": {
        "type": "Point",
        "coordinates": [
          16.84325,
          48.410019
        ]
      },
      "properties": {
        "description": "representative point"
      }
    },
    {
      "geometry": {
        "type": "Point",
        "coordinates": [
          16.84325,
          48.410019
        ]
      },
      "id": "darmc-location-8336",
      "type": "Feature",
      "properties": {
        "description": "1M scale point location",
        "location_precision": "precise",
        "title": "DARMC location 8336",
        "link": "http://pleiades.stoa.org/places/128519/darmc-location-8336"
      }
    }
  ]
}