{
  "type": "FeatureCollection",
  "title": "Uherské Hradiště",
  "id": "128529",
  "description": "An ancient place, cited: BAtlas 13 C3 Uherské Hradiště",
  "bbox": [
    17.459186,
    49.065163,
    17.459186,
    49.065163
  ],
  "reprPoint": [
    17.459186,
    49.065163
  ],
  "features": [
    {
      "geometry": {
        "type": "Point",
        "coordinates": [
          17.459186,
          49.065163
        ]
      },
      "id": "darmc-location-15305",
      "type": "Feature",
      "properties": {
        "description": "1M scale point location",
        "location_precision": "precise",
        "title": "DARMC location 15305",
        "link": "http://pleiades.stoa.org/places/128529/darmc-location-15305"
      }
    }
  ]
}