{
  "type": "FeatureCollection",
  "title": "Stopfenreuth",
  "id": "128521",
  "description": "An ancient place, cited: BAtlas 13 B4 Stopfenreuth",
  "bbox": [
    16.880299,
    48.148655,
    16.883333,
    48.183333
  ],
  "reprPoint": [
    16.881816,
    48.165994
  ],
  "features": [
    {
      "geometry": {
        "type": "Point",
        "coordinates": [
          16.880299,
          48.148655
        ]
      },
      "id": "darmc-location-8339",
      "type": "Feature",
      "properties": {
        "description": "1M scale point location",
        "location_precision": "precise",
        "title": "DARMC location 8339",
        "link": "http://pleiades.stoa.org/places/128521/darmc-location-8339"
      }
    },
    {
      "geometry": {
        "type": "Point",
        "coordinates": [
          16.883333,
          48.183333
        ]
      },
      "id": "dare-location",
      "type": "Feature",
      "properties": {
        "description": "Representative point location, site precision",
        "location_precision": "precise",
        "title": "DARE Location",
        "link": "http://pleiades.stoa.org/places/128521/dare-location"
      }
    }
  ]
}