{
  "type": "FeatureCollection",
  "title": "Zamość",
  "id": "128549",
  "description": "An ancient place, cited: BAtlas 13 I2 Zamość",
  "bbox": [
    23.251993,
    50.723127,
    23.251993,
    50.723127
  ],
  "reprPoint": [
    23.251993,
    50.723127
  ],
  "features": [
    {
      "geometry": {
        "type": "Point",
        "coordinates": [
          23.251993,
          50.723127
        ]
      },
      "id": "darmc-location-15695",
      "type": "Feature",
      "properties": {
        "description": "1M scale point location",
        "location_precision": "precise",
        "title": "DARMC location 15695",
        "link": "http://pleiades.stoa.org/places/128549/darmc-location-15695"
      }
    }
  ]
}