{
  "type": "FeatureCollection",
  "title": "Uherský Brod",
  "id": "128530",
  "description": "An ancient place, cited: BAtlas 13 C3 Uherský Brod",
  "bbox": [
    17.646427,
    49.024606,
    17.646427,
    49.024606
  ],
  "reprPoint": [
    17.646427,
    49.024606
  ],
  "features": [
    {
      "geometry": {
        "type": "Point",
        "coordinates": [
          17.646427,
          49.024606
        ]
      },
      "id": "darmc-location-15306",
      "type": "Feature",
      "properties": {
        "description": "1M scale point location",
        "location_precision": "precise",
        "title": "DARMC location 15306",
        "link": "http://pleiades.stoa.org/places/128530/darmc-location-15306"
      }
    }
  ]
}