{
  "type": "FeatureCollection",
  "title": "Camp celtique de la Bure",
  "id": "133577441",
  "description": null,
  "bbox": [
    6.940044,
    48.326764,
    6.940044,
    48.326764
  ],
  "connectsWith": [
    "109307"
  ],
  "reprPoint": [
    6.940044,
    48.326764
  ],
  "features": [
    {
      "geometry": {
        "type": "Point",
        "coordinates": [
          6.940044,
          48.326764
        ]
      },
      "id": "location-of-the-oppidum",
      "type": "Feature",
      "properties": {
        "description": "Camp celtique de la Bure, commune Saint-Dié-des-Vosges, département Vosges.",
        "location_precision": "precise",
        "title": "Location of the oppidum",
        "link": "http://pleiades.stoa.org/places/133577441/location-of-the-oppidum"
      }
    }
  ]
}