{
  "type": "FeatureCollection",
  "title": "Campus Esquilinus",
  "id": "133574713",
  "bbox": [
    12.486137,
    41.891775,
    12.486137,
    41.891775
  ],
  "description": "A toponym used in the later part of the Roman Republican period to describe the portion of the Esquiline plateau that lay outside the porta Esquilina. Its limits are unknown, although Strabo has it located to the north of the via Labicana.",
  "connectsWith": [
    "423025",
    "679976755"
  ],
  "names": [
    "Campus Esquilinus",
    "to pedion to Esquilinon"
  ],
  "features": [
    {
      "type": "Feature",
      "geometry": {
        "type": "Point",
        "coordinates": [
          12.486137,
          41.891775
        ]
      },
      "properties": {
        "description": "representative point"
      }
    }
  ]
}