{
  "type": "FeatureCollection",
  "title": "Basilica Manastirine",
  "id": "135962387",
  "bbox": [
    16.4825906,
    43.5421187,
    16.4825906,
    43.5421187
  ],
  "description": "An important extra-mural Christian site at Solina. The site includes the basilica and the cemetery of Manastirine, associated with a Christian martyr.",
  "connectsWith": [
    "197488"
  ],
  "features": [
    {
      "type": "Feature",
      "geometry": {
        "type": "Point",
        "coordinates": [
          16.4825906,
          43.5421187
        ]
      },
      "properties": {
        "description": "representative point"
      }
    },
    {
      "geometry": {
        "type": "Point",
        "coordinates": [
          16.4825906,
          43.5421187
        ]
      },
      "id": "location-of-manastirine-basilica",
      "type": "Feature",
      "properties": {
        "description": "Representative location based on OpenStreetMap.",
        "location_precision": "precise",
        "title": "OSM location of Basilica Manastirine",
        "link": "http://pleiades.stoa.org/places/135962387/location-of-manastirine-basilica"
      }
    }
  ]
}