{
  "type": "FeatureCollection",
  "title": "Arthona",
  "id": "138195",
  "bbox": [
    3.140504,
    46.002611,
    3.140504,
    46.002611
  ],
  "description": "An ancient place, cited: BAtlas 14 I2 Arthona",
  "names": [
    "Arthona"
  ],
  "features": [
    {
      "type": "Feature",
      "geometry": {
        "type": "Point",
        "coordinates": [
          3.140504,
          46.002611
        ]
      },
      "properties": {
        "description": "representative point"
      }
    },
    {
      "geometry": {
        "type": "Point",
        "coordinates": [
          3.140504,
          46.002611
        ]
      },
      "id": "darmc-location-11514",
      "type": "Feature",
      "properties": {
        "description": "1M scale point location",
        "location_precision": "precise",
        "title": "DARMC location 11514",
        "link": "http://pleiades.stoa.org/places/138195/darmc-location-11514"
      }
    }
  ]
}