{
  "type": "FeatureCollection",
  "title": "Aron",
  "id": "138193",
  "bbox": [
    2.440556,
    44.926111,
    2.442965,
    44.926721
  ],
  "description": "An ancient place, cited: BAtlas 14 H4 Aron",
  "features": [
    {
      "type": "Feature",
      "geometry": {
        "type": "Point",
        "coordinates": [
          2.4417605,
          44.926416
        ]
      },
      "properties": {
        "description": "representative point"
      }
    },
    {
      "geometry": {
        "type": "Point",
        "coordinates": [
          2.442965,
          44.926721
        ]
      },
      "id": "darmc-location-15888",
      "type": "Feature",
      "properties": {
        "description": "1M scale point location",
        "location_precision": "precise",
        "title": "DARMC location 15888",
        "link": "http://pleiades.stoa.org/places/138193/darmc-location-15888"
      }
    },
    {
      "geometry": {
        "type": "Point",
        "coordinates": [
          2.440556,
          44.926111
        ]
      },
      "id": "dare-location",
      "type": "Feature",
      "properties": {
        "description": "Representative point location, site precision",
        "location_precision": "precise",
        "title": "DARE Location",
        "link": "http://pleiades.stoa.org/places/138193/dare-location"
      }
    }
  ]
}