{
  "type": "FeatureCollection",
  "title": "Burgus",
  "id": "138249",
  "description": "An ancient place, cited: BAtlas 14 E3 Burgus",
  "bbox": [
    -0.559844,
    45.039335,
    -0.559844,
    45.039335
  ],
  "reprPoint": [
    -0.559844,
    45.039335
  ],
  "names": [
    "Burgus"
  ],
  "features": [
    {
      "geometry": {
        "type": "Point",
        "coordinates": [
          -0.559844,
          45.039335
        ]
      },
      "id": "darmc-location-17389",
      "type": "Feature",
      "properties": {
        "description": "1M scale point location",
        "location_precision": "precise",
        "title": "DARMC location 17389",
        "link": "http://pleiades.stoa.org/places/138249/darmc-location-17389"
      }
    }
  ]
}