{
  "type": "FeatureCollection",
  "title": "Blacciacum",
  "id": "138227",
  "bbox": [
    -0.646428,
    45.101808,
    -0.645725,
    45.1021055
  ],
  "description": "An ancient place, cited: BAtlas 14 E3 Blacciacum",
  "names": [
    "Blacciacum",
    "Blassiacum"
  ],
  "features": [
    {
      "type": "Feature",
      "geometry": {
        "type": "Point",
        "coordinates": [
          -0.646151133333,
          45.1019851667
        ]
      },
      "properties": {
        "description": "representative point"
      }
    },
    {
      "geometry": {
        "type": "Point",
        "coordinates": [
          -0.645725,
          45.101808
        ]
      },
      "id": "darmc-location-17383",
      "type": "Feature",
      "properties": {
        "description": "1M scale point location",
        "location_precision": "precise",
        "title": "DARMC location 17383",
        "link": "http://pleiades.stoa.org/places/138227/darmc-location-17383"
      }
    },
    {
      "geometry": {
        "type": "Point",
        "coordinates": [
          -0.646428,
          45.102042
        ]
      },
      "id": "dare-location",
      "type": "Feature",
      "properties": {
        "description": "Representative point location, site precision",
        "location_precision": "precise",
        "title": "DARE Location",
        "link": "http://pleiades.stoa.org/places/138227/dare-location"
      }
    },
    {
      "geometry": {
        "type": "Point",
        "coordinates": [
          -0.6463004,
          45.1021055
        ]
      },
      "id": "osm-location-of-villa-gallo-romaine-de-plassac",
      "type": "Feature",
      "properties": {
        "description": "Representative location based on OpenStreetMap.",
        "location_precision": "precise",
        "title": "OSM location of Villa Gallo-Romaine de Plassac",
        "link": "http://pleiades.stoa.org/places/138227/osm-location-of-villa-gallo-romaine-de-plassac"
      }
    }
  ]
}