{
  "type": "FeatureCollection",
  "title": "Azat-le-Ris",
  "id": "138211",
  "description": "An ancient place, cited: BAtlas 14 G2 Azat-le-Ris",
  "bbox": [
    1.060319,
    46.319257,
    1.060319,
    46.319257
  ],
  "reprPoint": [
    1.060319,
    46.319257
  ],
  "features": [
    {
      "geometry": {
        "type": "Point",
        "coordinates": [
          1.060319,
          46.319257
        ]
      },
      "id": "darmc-location-21605",
      "type": "Feature",
      "properties": {
        "description": "1M scale point location",
        "location_precision": "precise",
        "title": "DARMC location 21605",
        "link": "http://pleiades.stoa.org/places/138211/darmc-location-21605"
      }
    }
  ]
}