{
  "type": "FeatureCollection",
  "title": "Belleroche",
  "id": "138219",
  "bbox": [
    1.40364,
    47.277259,
    1.40364,
    47.277259
  ],
  "description": "An ancient place, cited: BAtlas 14 G1 Belleroche",
  "features": [
    {
      "type": "Feature",
      "geometry": {
        "type": "Point",
        "coordinates": [
          1.40364,
          47.277259
        ]
      },
      "properties": {
        "description": "representative point"
      }
    },
    {
      "geometry": {
        "type": "Point",
        "coordinates": [
          1.40364,
          47.277259
        ]
      },
      "id": "darmc-location-9184",
      "type": "Feature",
      "properties": {
        "description": "1M scale point location",
        "location_precision": "precise",
        "title": "DARMC location 9184",
        "link": "http://pleiades.stoa.org/places/138219/darmc-location-9184"
      }
    }
  ]
}