{
  "type": "FeatureCollection",
  "title": "Chanteau",
  "id": "138288",
  "bbox": [
    1.995574,
    46.051131,
    2.030581,
    46.06357
  ],
  "description": "An ancient place, cited: BAtlas 14 H2 Chanteau",
  "features": [
    {
      "type": "Feature",
      "geometry": {
        "type": "Point",
        "coordinates": [
          2.0130775,
          46.0573505
        ]
      },
      "properties": {
        "description": "representative point"
      }
    },
    {
      "geometry": {
        "type": "Point",
        "coordinates": [
          1.995574,
          46.06357
        ]
      },
      "id": "darmc-location-2782",
      "type": "Feature",
      "properties": {
        "description": "1M scale point location",
        "location_precision": "precise",
        "title": "DARMC location 2782",
        "link": "http://pleiades.stoa.org/places/138288/darmc-location-2782"
      }
    },
    {
      "geometry": {
        "type": "Point",
        "coordinates": [
          2.030581,
          46.051131
        ]
      },
      "id": "darmc-location-6805",
      "type": "Feature",
      "properties": {
        "description": "1M scale point location",
        "location_precision": "precise",
        "title": "DARMC location 6805",
        "link": "http://pleiades.stoa.org/places/138288/darmc-location-6805"
      }
    }
  ]
}