{
  "type": "FeatureCollection",
  "title": "Blatomagus",
  "id": "138229",
  "description": "An ancient place, cited: BAtlas 14 G2 Blatomagus",
  "bbox": [
    1.017002,
    46.043725,
    1.021061,
    46.06122
  ],
  "reprPoint": [
    1.0190315,
    46.0524725
  ],
  "names": [
    "Blatomagus"
  ],
  "features": [
    {
      "geometry": {
        "type": "Point",
        "coordinates": [
          1.017002,
          46.043725
        ]
      },
      "id": "darmc-location-11774",
      "type": "Feature",
      "properties": {
        "description": "1M scale point location",
        "location_precision": "precise",
        "title": "DARMC location 11774",
        "link": "http://pleiades.stoa.org/places/138229/darmc-location-11774"
      }
    },
    {
      "geometry": {
        "type": "Point",
        "coordinates": [
          1.021061,
          46.06122
        ]
      },
      "id": "dare-location",
      "type": "Feature",
      "properties": {
        "description": "Representative point location, village precision",
        "location_precision": "precise",
        "title": "DARE Location",
        "link": "http://pleiades.stoa.org/places/138229/dare-location"
      }
    }
  ]
}