{
  "type": "FeatureCollection",
  "title": "Blacciacum",
  "id": "138227",
  "description": "An ancient place, cited: BAtlas 14 E3 Blacciacum",
  "bbox": [
    -0.646428,
    45.101808,
    -0.645725,
    45.102042
  ],
  "reprPoint": [
    -0.6460765,
    45.101925
  ],
  "names": [
    "Blacciacum",
    "Blassiacum"
  ],
  "features": [
    {
      "geometry": {
        "type": "Point",
        "coordinates": [
          -0.645725,
          45.101808
        ]
      },
      "id": "darmc-location-17383",
      "type": "Feature",
      "properties": {
        "description": "1M scale point location",
        "location_precision": "precise",
        "title": "DARMC location 17383",
        "link": "http://pleiades.stoa.org/places/138227/darmc-location-17383"
      }
    },
    {
      "geometry": {
        "type": "Point",
        "coordinates": [
          -0.646428,
          45.102042
        ]
      },
      "id": "dare-location",
      "type": "Feature",
      "properties": {
        "description": "Representative point location, site precision",
        "location_precision": "precise",
        "title": "DARE Location",
        "link": "http://pleiades.stoa.org/places/138227/dare-location"
      }
    }
  ]
}