{
  "type": "FeatureCollection",
  "title": "Chanceaux-sur-Choisille",
  "id": "138286",
  "bbox": [
    0.702604,
    47.472054,
    0.702604,
    47.472054
  ],
  "description": "An ancient place, cited: BAtlas 14 F1 Chanceaux-sur-Choisille",
  "features": [
    {
      "type": "Feature",
      "geometry": {
        "type": "Point",
        "coordinates": [
          0.702604,
          47.472054
        ]
      },
      "properties": {
        "description": "representative point"
      }
    },
    {
      "geometry": {
        "type": "Point",
        "coordinates": [
          0.702604,
          47.472054
        ]
      },
      "id": "darmc-location-25931",
      "type": "Feature",
      "properties": {
        "description": "1M scale point location",
        "location_precision": "precise",
        "title": "DARMC location 25931",
        "link": "http://pleiades.stoa.org/places/138286/darmc-location-25931"
      }
    }
  ]
}