{
  "type": "FeatureCollection",
  "title": "Boii",
  "id": "138232",
  "description": "An ancient place, cited: BAtlas 14 E4 Boii",
  "bbox": [
    -0.971141,
    44.627926,
    -0.971141,
    44.627926
  ],
  "reprPoint": [
    -0.971141,
    44.627926
  ],
  "names": [
    "Boii"
  ],
  "features": [
    {
      "geometry": {
        "type": "Point",
        "coordinates": [
          -0.971141,
          44.627926
        ]
      },
      "id": "darmc-location-11787",
      "type": "Feature",
      "properties": {
        "description": "1M scale point location",
        "location_precision": "precise",
        "title": "DARMC location 11787",
        "link": "http://pleiades.stoa.org/places/138232/darmc-location-11787"
      }
    }
  ]
}