{
  "type": "FeatureCollection",
  "title": "Canniaco",
  "id": "138265",
  "description": "An ancient place, cited: BAtlas 14 G4 Canniaco",
  "bbox": [
    1.6363,
    44.624611,
    1.6363,
    44.624611
  ],
  "reprPoint": [
    1.6363,
    44.624611
  ],
  "names": [
    "Canniaco"
  ],
  "features": [
    {
      "geometry": {
        "type": "Point",
        "coordinates": [
          1.6363,
          44.624611
        ]
      },
      "id": "darmc-location-16319",
      "type": "Feature",
      "properties": {
        "description": "1M scale point location",
        "location_precision": "precise",
        "title": "DARMC location 16319",
        "link": "http://pleiades.stoa.org/places/138265/darmc-location-16319"
      }
    }
  ]
}