{
  "type": "FeatureCollection",
  "title": "Briggogalus",
  "id": "138238",
  "description": "An ancient place, cited: BAtlas 14 F1 Briggogalus",
  "bbox": [
    0.536795,
    47.14519,
    0.536795,
    47.14519
  ],
  "reprPoint": [
    0.536795,
    47.14519
  ],
  "names": [
    "Briggogalus"
  ],
  "features": [
    {
      "geometry": {
        "type": "Point",
        "coordinates": [
          0.536795,
          47.14519
        ]
      },
      "id": "darmc-location-11839",
      "type": "Feature",
      "properties": {
        "description": "1M scale point location",
        "location_precision": "precise",
        "title": "DARMC location 11839",
        "link": "http://pleiades.stoa.org/places/138238/darmc-location-11839"
      }
    }
  ]
}