{
  "type": "FeatureCollection",
  "title": "Evina",
  "id": "138348",
  "bbox": [
    0.785615,
    47.283781,
    0.785615,
    47.283781
  ],
  "description": "An ancient place, cited: BAtlas 14 F1 Evina",
  "names": [
    "Evina"
  ],
  "features": [
    {
      "type": "Feature",
      "geometry": {
        "type": "Point",
        "coordinates": [
          0.785615,
          47.283781
        ]
      },
      "properties": {
        "description": "representative point"
      }
    },
    {
      "geometry": {
        "type": "Point",
        "coordinates": [
          0.785615,
          47.283781
        ]
      },
      "id": "darmc-location-10050",
      "type": "Feature",
      "properties": {
        "description": "1M scale point location",
        "location_precision": "precise",
        "title": "DARMC location 10050",
        "link": "http://pleiades.stoa.org/places/138348/darmc-location-10050"
      }
    }
  ]
}