{
  "type": "FeatureCollection",
  "title": "Condatis",
  "id": "138307",
  "bbox": [
    -0.241729,
    44.897877,
    -0.241729,
    44.897877
  ],
  "description": "An ancient place, cited: BAtlas 14 E4 Condatis",
  "names": [
    "Condatis"
  ],
  "features": [
    {
      "type": "Feature",
      "geometry": {
        "type": "Point",
        "coordinates": [
          -0.241729,
          44.897877
        ]
      },
      "properties": {
        "description": "representative point"
      }
    },
    {
      "geometry": {
        "type": "Point",
        "coordinates": [
          -0.241729,
          44.897877
        ]
      },
      "id": "center-point-of-condat",
      "type": "Feature",
      "properties": {
        "description": "Condat, commune Libourne, département Gironde",
        "location_precision": "precise",
        "title": "Center point of Condat",
        "link": "http://pleiades.stoa.org/places/138307/center-point-of-condat"
      }
    }
  ]
}