{
  "type": "FeatureCollection",
  "title": "Cossium",
  "id": "138313",
  "description": "An ancient place, cited: BAtlas 14 E4 Cossium",
  "bbox": [
    -0.213375,
    44.431514,
    -0.213375,
    44.431514
  ],
  "reprPoint": [
    -0.213375,
    44.431514
  ],
  "names": [
    "Cossium",
    "Civitas Vasatica",
    "Vasates"
  ],
  "features": [
    {
      "geometry": {
        "type": "Point",
        "coordinates": [
          -0.213375,
          44.431514
        ]
      },
      "id": "darmc-location-12102",
      "type": "Feature",
      "properties": {
        "description": "1M scale point location",
        "location_precision": "precise",
        "title": "DARMC location 12102",
        "link": "http://pleiades.stoa.org/places/138313/darmc-location-12102"
      }
    }
  ]
}