{
  "type": "FeatureCollection",
  "title": "*Iciodorum",
  "id": "138391",
  "description": "An ancient place, cited: BAtlas 14 I3 *Iciodorum",
  "bbox": [
    3.256877,
    45.556613,
    3.256877,
    45.556613
  ],
  "reprPoint": [
    3.256877,
    45.556613
  ],
  "names": [
    "Iciodorum"
  ],
  "features": [
    {
      "geometry": {
        "type": "Point",
        "coordinates": [
          3.256877,
          45.556613
        ]
      },
      "id": "darmc-location-10073",
      "type": "Feature",
      "properties": {
        "description": "1M scale point location",
        "location_precision": "precise",
        "title": "DARMC location 10073",
        "link": "http://pleiades.stoa.org/places/138391/darmc-location-10073"
      }
    }
  ]
}