{
  "type": "FeatureCollection",
  "title": "Issando",
  "id": "138398",
  "description": "An ancient place, cited: BAtlas 14 G3 Issando",
  "bbox": [
    1.36786386933,
    45.208034,
    1.373398,
    45.2098945615
  ],
  "reprPoint": [
    1.37063093466,
    45.2089642807
  ],
  "names": [
    "Issando"
  ],
  "features": [
    {
      "geometry": {
        "type": "Point",
        "coordinates": [
          1.373398,
          45.208034
        ]
      },
      "id": "darmc-location-7835",
      "type": "Feature",
      "properties": {
        "description": "1M scale point location",
        "location_precision": "precise",
        "title": "DARMC location 7835",
        "link": "http://pleiades.stoa.org/places/138398/darmc-location-7835"
      }
    },
    {
      "geometry": {
        "type": "Point",
        "coordinates": [
          1.36786386933,
          45.2098945615
        ]
      },
      "id": "dare-location",
      "type": "Feature",
      "properties": {
        "description": "Representative point location, site precision",
        "location_precision": "precise",
        "title": "DARE Location",
        "link": "http://pleiades.stoa.org/places/138398/dare-location"
      }
    }
  ]
}