{
  "type": "FeatureCollection",
  "title": "Criscencio",
  "id": "138317",
  "bbox": [
    1.145134,
    44.411243,
    1.145134,
    44.411243
  ],
  "description": "An ancient place, cited: BAtlas 14 G4 Criscencio",
  "names": [
    "Criscencio"
  ],
  "features": [
    {
      "type": "Feature",
      "geometry": {
        "type": "Point",
        "coordinates": [
          1.145134,
          44.411243
        ]
      },
      "properties": {
        "description": "representative point"
      }
    },
    {
      "geometry": {
        "type": "Point",
        "coordinates": [
          1.145134,
          44.411243
        ]
      },
      "id": "darmc-location-16362",
      "type": "Feature",
      "properties": {
        "description": "1M scale point location",
        "location_precision": "precise",
        "title": "DARMC location 16362",
        "link": "http://pleiades.stoa.org/places/138317/darmc-location-16362"
      }
    }
  ]
}