{
  "type": "FeatureCollection",
  "title": "Dumnitonus",
  "id": "138333",
  "bbox": [
    -0.782903,
    45.19181,
    -0.782903,
    45.19181
  ],
  "description": "An ancient place, cited: BAtlas 14 E3 Dumnitonus",
  "names": [
    "Dumnitonus"
  ],
  "features": [
    {
      "type": "Feature",
      "geometry": {
        "type": "Point",
        "coordinates": [
          -0.782903,
          45.19181
        ]
      },
      "properties": {
        "description": "representative point"
      }
    },
    {
      "geometry": {
        "type": "Point",
        "coordinates": [
          -0.782903,
          45.19181
        ]
      },
      "id": "darmc-location-16364",
      "type": "Feature",
      "properties": {
        "description": "1M scale point location",
        "location_precision": "precise",
        "title": "DARMC location 16364",
        "link": "http://pleiades.stoa.org/places/138333/darmc-location-16364"
      }
    }
  ]
}