{
  "type": "FeatureCollection",
  "title": "Condate",
  "id": "138304",
  "description": "An ancient place, cited: BAtlas 14 E3 Condate",
  "bbox": [
    -0.328744,
    45.691046,
    -0.328744,
    45.691046
  ],
  "reprPoint": [
    -0.328744,
    45.691046
  ],
  "names": [
    "Condate"
  ],
  "features": [
    {
      "geometry": {
        "type": "Point",
        "coordinates": [
          -0.328744,
          45.691046
        ]
      },
      "id": "center-point-of-commune-cognac",
      "type": "Feature",
      "properties": {
        "description": null,
        "location_precision": "precise",
        "title": "Center point of commune Cognac",
        "link": "http://pleiades.stoa.org/places/138304/center-point-of-commune-cognac"
      }
    }
  ]
}