{
  "type": "FeatureCollection",
  "title": "Espalion",
  "id": "138344",
  "bbox": [
    2.762311,
    44.5219,
    2.762311,
    44.5219
  ],
  "description": "An ancient place, cited: BAtlas 14 H4 Espalion",
  "features": [
    {
      "type": "Feature",
      "geometry": {
        "type": "Point",
        "coordinates": [
          2.762311,
          44.5219
        ]
      },
      "properties": {
        "description": "representative point"
      }
    },
    {
      "geometry": {
        "type": "Point",
        "coordinates": [
          2.762311,
          44.5219
        ]
      },
      "id": "darmc-location-12394",
      "type": "Feature",
      "properties": {
        "description": "1M scale point location",
        "location_precision": "precise",
        "title": "DARMC location 12394",
        "link": "http://pleiades.stoa.org/places/138344/darmc-location-12394"
      }
    }
  ]
}