{
  "type": "FeatureCollection",
  "title": "Cornucio",
  "id": "138311",
  "bbox": [
    1.727775,
    44.463304,
    1.727775,
    44.463304
  ],
  "description": "An ancient place, cited: BAtlas 14 G4 Cornucio",
  "names": [
    "Cornucio"
  ],
  "features": [
    {
      "type": "Feature",
      "geometry": {
        "type": "Point",
        "coordinates": [
          1.727775,
          44.463304
        ]
      },
      "properties": {
        "description": "representative point"
      }
    },
    {
      "geometry": {
        "type": "Point",
        "coordinates": [
          1.727775,
          44.463304
        ]
      },
      "id": "darmc-location-16361",
      "type": "Feature",
      "properties": {
        "description": "1M scale point location",
        "location_precision": "precise",
        "title": "DARMC location 16361",
        "link": "http://pleiades.stoa.org/places/138311/darmc-location-16361"
      }
    }
  ]
}