{
  "type": "FeatureCollection",
  "title": "Gouts-Rossignols",
  "id": "138375",
  "description": "An ancient place, cited: BAtlas 14 F3 Gouts-Rossignols",
  "bbox": [
    0.383857,
    45.412448,
    0.383857,
    45.412448
  ],
  "reprPoint": [
    0.383857,
    45.412448
  ],
  "features": [
    {
      "geometry": {
        "type": "Point",
        "coordinates": [
          0.383857,
          45.412448
        ]
      },
      "id": "darmc-location-18604",
      "type": "Feature",
      "properties": {
        "description": "1M scale point location",
        "location_precision": "precise",
        "title": "DARMC location 18604",
        "link": "http://pleiades.stoa.org/places/138375/darmc-location-18604"
      }
    }
  ]
}