{
  "type": "FeatureCollection",
  "title": "Mornat",
  "id": "138472",
  "description": "An ancient place, cited: BAtlas 14 H2 Mornat",
  "bbox": [
    2.093928,
    46.09626,
    2.093928,
    46.09626
  ],
  "reprPoint": [
    2.093928,
    46.09626
  ],
  "features": [
    {
      "geometry": {
        "type": "Point",
        "coordinates": [
          2.093928,
          46.09626
        ]
      },
      "id": "darmc-location-9038",
      "type": "Feature",
      "properties": {
        "description": "1M scale point location",
        "location_precision": "precise",
        "title": "DARMC location 9038",
        "link": "http://pleiades.stoa.org/places/138472/darmc-location-9038"
      }
    }
  ]
}