{
  "type": "FeatureCollection",
  "title": "Mediolanum",
  "id": "138459",
  "bbox": [
    2.201875,
    46.562103,
    2.201875,
    46.562103
  ],
  "description": "An ancient settlement, located in the modern French commune of Châteaumeillant.",
  "names": [
    "Mediolanum",
    "Stampensis",
    "Châteaumeillant"
  ],
  "features": [
    {
      "type": "Feature",
      "geometry": {
        "type": "Point",
        "coordinates": [
          2.201875,
          46.562103
        ]
      },
      "properties": {
        "description": "representative point"
      }
    },
    {
      "geometry": {
        "type": "Point",
        "coordinates": [
          2.201875,
          46.562103
        ]
      },
      "id": "centerpoint-of-commune-chateaumeillant",
      "type": "Feature",
      "properties": {
        "description": null,
        "location_precision": "precise",
        "title": "Center point of commune Châteaumeillant",
        "link": "http://pleiades.stoa.org/places/138459/centerpoint-of-commune-chateaumeillant"
      }
    }
  ]
}