{
  "type": "FeatureCollection",
  "title": "Les Jumeaux",
  "id": "138403",
  "description": "An ancient place, cited: BAtlas 14 F2 Les Jumeaux",
  "bbox": [
    -0.088519,
    46.811919,
    0.101301,
    46.854485
  ],
  "reprPoint": [
    0.006391,
    46.833202
  ],
  "features": [
    {
      "geometry": {
        "type": "Point",
        "coordinates": [
          0.101301,
          46.854485
        ]
      },
      "id": "center-point-of-the-hamlet-les-jumeaux",
      "type": "Feature",
      "properties": {
        "description": "Center point of the location Les Jumeaux, commune Saint-Jean-de-Sauves, département Vienne",
        "location_precision": "precise",
        "title": "Center point of the location Les Jumeaux",
        "link": "http://pleiades.stoa.org/places/138403/center-point-of-the-hamlet-les-jumeaux"
      }
    }
  ]
}