{
  "type": "FeatureCollection",
  "title": "Lusignan",
  "id": "138434",
  "description": "An ancient place, cited: BAtlas 14 F2 Lusignan",
  "bbox": [
    0.122412,
    46.435068,
    0.122412,
    46.435068
  ],
  "reprPoint": [
    0.122412,
    46.435068
  ],
  "features": [
    {
      "geometry": {
        "type": "Point",
        "coordinates": [
          0.122412,
          46.435068
        ]
      },
      "id": "darmc-location-13542",
      "type": "Feature",
      "properties": {
        "description": "1M scale point location",
        "location_precision": "precise",
        "title": "DARMC location 13542",
        "link": "http://pleiades.stoa.org/places/138434/darmc-location-13542"
      }
    }
  ]
}