{
  "type": "FeatureCollection",
  "title": "Levet",
  "id": "138417",
  "description": "An ancient place, cited: BAtlas 14 H2 Levet",
  "bbox": [
    2.407316,
    46.924185,
    2.407316,
    46.924185
  ],
  "reprPoint": [
    2.407316,
    46.924185
  ],
  "features": [
    {
      "geometry": {
        "type": "Point",
        "coordinates": [
          2.407316,
          46.924185
        ]
      },
      "id": "darmc-location-13481",
      "type": "Feature",
      "properties": {
        "description": "1M scale point location",
        "location_precision": "precise",
        "title": "DARMC location 13481",
        "link": "http://pleiades.stoa.org/places/138417/darmc-location-13481"
      }
    }
  ]
}