{
  "type": "FeatureCollection",
  "title": "Limonum",
  "id": "138422",
  "bbox": [
    0.342633,
    46.580342,
    0.349348,
    46.586951
  ],
  "description": "An ancient place, cited: BAtlas 14 F2 Limonum",
  "connectsWith": [
    "138515"
  ],
  "names": [
    "Limonum",
    "Pictavi",
    "Poitiers"
  ],
  "features": [
    {
      "type": "Feature",
      "geometry": {
        "type": "Point",
        "coordinates": [
          0.3459905,
          46.5836465
        ]
      },
      "properties": {
        "description": "representative point"
      }
    },
    {
      "geometry": {
        "type": "Point",
        "coordinates": [
          0.342633,
          46.586951
        ]
      },
      "id": "darmc-location-13501",
      "type": "Feature",
      "properties": {
        "description": "1:1 million scale representative point location digitized from the Barrington Atlas of the Greek and Roman World by the Digital Atlas of Roman and Medieval Civilizations project at Harvard University.",
        "location_precision": "precise",
        "title": "DARMC location 13501",
        "link": "http://pleiades.stoa.org/places/138422/darmc-location-13501"
      }
    },
    {
      "geometry": {
        "type": "Point",
        "coordinates": [
          0.349348,
          46.580342
        ]
      },
      "id": "dare-location",
      "type": "Feature",
      "properties": {
        "description": "Representative point location, site precision",
        "location_precision": "precise",
        "title": "DARE Location",
        "link": "http://pleiades.stoa.org/places/138422/dare-location"
      }
    }
  ]
}