{
  "type": "FeatureCollection",
  "title": "Limonum",
  "id": "138422",
  "description": "An ancient place, cited: BAtlas 14 F2 Limonum",
  "bbox": [
    0.349348,
    46.580342,
    0.349348,
    46.580342
  ],
  "reprPoint": [
    0.349348,
    46.580342
  ],
  "names": [
    "Poitiers",
    "Limonum",
    "Pictavi"
  ],
  "features": [
    {
      "geometry": {
        "type": "Point",
        "coordinates": [
          0.342633,
          46.586951
        ]
      },
      "id": "darmc-location-13501",
      "type": "Feature",
      "properties": {
        "description": "1M scale point location",
        "location_precision": "precise",
        "title": "DARMC location 13501",
        "link": "http://pleiades.stoa.org/places/138422/darmc-location-13501"
      }
    },
    {
      "geometry": {
        "type": "Point",
        "coordinates": [
          0.349348,
          46.580342
        ]
      },
      "id": "dare-location",
      "type": "Feature",
      "properties": {
        "description": "Representative point location, site precision",
        "location_precision": "precise",
        "title": "DARE Location",
        "link": "http://pleiades.stoa.org/places/138422/dare-location"
      }
    }
  ]
}