{
  "type": "FeatureCollection",
  "title": "Mediolanum",
  "id": "138459",
  "bbox": [
    2.1962014,
    46.5608687,
    2.1962014,
    46.5608687
  ],
  "description": "An ancient settlement, located in the modern French commune of Châteaumeillant.",
  "names": [
    "Mediolanum",
    "Stampensis",
    "Châteaumeillant"
  ],
  "features": [
    {
      "type": "Feature",
      "geometry": {
        "type": "Point",
        "coordinates": [
          2.1962014,
          46.5608687
        ]
      },
      "properties": {
        "description": "representative point"
      }
    },
    {
      "geometry": {
        "type": "Point",
        "coordinates": [
          2.1962014,
          46.5608687
        ]
      },
      "id": "osm-location-of-modern-commune-of-chac",
      "type": "Feature",
      "properties": {
        "description": "Location based on OpenStreetMap",
        "location_precision": "precise",
        "title": "OSM location of modern commune of Châteaumeillant",
        "link": "http://pleiades.stoa.org/places/138459/osm-location-of-modern-commune-of-chac"
      }
    }
  ]
}