{
  "type": "FeatureCollection",
  "title": "Massiac",
  "id": "138453",
  "bbox": [
    3.197007,
    45.250965,
    3.197007,
    45.250965
  ],
  "description": "An ancient place, cited: BAtlas 14 I3 Massiac",
  "features": [
    {
      "type": "Feature",
      "geometry": {
        "type": "Point",
        "coordinates": [
          3.197007,
          45.250965
        ]
      },
      "properties": {
        "description": "representative point"
      }
    },
    {
      "geometry": {
        "type": "Point",
        "coordinates": [
          3.197007,
          45.250965
        ]
      },
      "id": "darmc-location-9265",
      "type": "Feature",
      "properties": {
        "description": "1M scale point location",
        "location_precision": "precise",
        "title": "DARMC location 9265",
        "link": "http://pleiades.stoa.org/places/138453/darmc-location-9265"
      }
    }
  ]
}