{
  "type": "FeatureCollection",
  "title": "Lamnum",
  "id": "138410",
  "description": "An ancient place, cited: BAtlas 14 E3 Lamnum",
  "bbox": [
    -0.551010470461,
    45.5824197001,
    -0.551010470461,
    45.5824197001
  ],
  "reprPoint": [
    -0.551010470461,
    45.5824197001
  ],
  "names": [
    "Lamnum"
  ],
  "features": [
    {
      "geometry": {
        "type": "Point",
        "coordinates": [
          -0.551010470461,
          45.5824197001
        ]
      },
      "id": "dare-location",
      "type": "Feature",
      "properties": {
        "description": "Representative point location, site precision",
        "location_precision": "precise",
        "title": "DARE Location",
        "link": "http://pleiades.stoa.org/places/138410/dare-location"
      }
    }
  ]
}