{
  "type": "FeatureCollection",
  "title": "Navicellis",
  "id": "138481",
  "bbox": [
    0.952891,
    47.43216,
    0.952891,
    47.43216
  ],
  "description": "An ancient place, cited: BAtlas 14 F1 Navicellis",
  "names": [
    "Navicellis"
  ],
  "features": [
    {
      "type": "Feature",
      "geometry": {
        "type": "Point",
        "coordinates": [
          0.952891,
          47.43216
        ]
      },
      "properties": {
        "description": "representative point"
      }
    },
    {
      "geometry": {
        "type": "Point",
        "coordinates": [
          0.952891,
          47.43216
        ]
      },
      "id": "darmc-location-10153",
      "type": "Feature",
      "properties": {
        "description": "1M scale point location",
        "location_precision": "precise",
        "title": "DARMC location 10153",
        "link": "http://pleiades.stoa.org/places/138481/darmc-location-10153"
      }
    }
  ]
}