{
  "type": "FeatureCollection",
  "title": "Musciacas?",
  "id": "138477",
  "bbox": [
    3.353397,
    45.774457,
    3.353397,
    45.774457
  ],
  "description": "An ancient place, cited: BAtlas 14 I3 Musciacas?",
  "names": [
    "Musciacas"
  ],
  "features": [
    {
      "type": "Feature",
      "geometry": {
        "type": "Point",
        "coordinates": [
          3.353397,
          45.774457
        ]
      },
      "properties": {
        "description": "representative point"
      }
    },
    {
      "geometry": {
        "type": "Point",
        "coordinates": [
          3.353397,
          45.774457
        ]
      },
      "id": "darmc-location-6778",
      "type": "Feature",
      "properties": {
        "description": "500K scale point location",
        "location_precision": "precise",
        "title": "DARMC location 6778",
        "link": "http://pleiades.stoa.org/places/138477/darmc-location-6778"
      }
    }
  ]
}