{
  "type": "FeatureCollection",
  "title": "*Melita",
  "id": "138462",
  "description": "An ancient place, cited: BAtlas 14 H3 *Melita",
  "bbox": [
    2.340104,
    45.2554153,
    2.430129,
    45.261957
  ],
  "reprPoint": [
    2.3851165,
    45.25868615
  ],
  "names": [
    "Melita"
  ],
  "features": [
    {
      "geometry": {
        "type": "Point",
        "coordinates": [
          2.430129,
          45.2554153
        ]
      },
      "id": "cneter-point-of-commune-meallet",
      "type": "Feature",
      "properties": {
        "description": null,
        "location_precision": "precise",
        "title": "Center point of commune Méallet",
        "link": "http://pleiades.stoa.org/places/138462/cneter-point-of-commune-meallet"
      }
    }
  ]
}