{
  "type": "FeatureCollection",
  "title": "Lamnum",
  "id": "138410",
  "description": "A road station in Gallia Aquitania, cited in the Tabula Peutingeriana",
  "bbox": [
    -0.551010470461,
    45.5824197001,
    -0.551010470461,
    45.5824197001
  ],
  "reprPoint": [
    -0.551010470461,
    45.5824197001
  ],
  "names": [
    "Lamnum"
  ],
  "features": [
    {
      "geometry": {
        "type": "Point",
        "coordinates": [
          -0.55101,
          45.58242
        ]
      },
      "id": "center-point-of-commune-pons",
      "type": "Feature",
      "properties": {
        "description": "A new identification of Lamnum. Dates after BAtlas.",
        "location_precision": "precise",
        "title": "Center point of archaeological site in commune Pons",
        "link": "http://pleiades.stoa.org/places/138410/center-point-of-commune-pons"
      }
    },
    {
      "geometry": {
        "type": "Point",
        "coordinates": [
          -0.551010470461,
          45.5824197001
        ]
      },
      "id": "dare-location",
      "type": "Feature",
      "properties": {
        "description": "Representative point location, site precision",
        "location_precision": "precise",
        "title": "DARE Location",
        "link": "http://pleiades.stoa.org/places/138410/dare-location"
      }
    }
  ]
}