{
  "type": "FeatureCollection",
  "title": "*Maroialum",
  "id": "138448",
  "description": "An ancient place, cited: BAtlas 14 G1 *Maroialum",
  "bbox": [
    1.319957,
    47.290628,
    1.319957,
    47.290628
  ],
  "reprPoint": [
    1.319957,
    47.290628
  ],
  "names": [
    "Maroialum"
  ],
  "features": [
    {
      "geometry": {
        "type": "Point",
        "coordinates": [
          1.319957,
          47.290628
        ]
      },
      "id": "darmc-location-4798",
      "type": "Feature",
      "properties": {
        "description": "1M scale point location",
        "location_precision": "precise",
        "title": "DARMC location 4798",
        "link": "http://pleiades.stoa.org/places/138448/darmc-location-4798"
      }
    }
  ]
}