{
  "type": "FeatureCollection",
  "title": "Petroliaco",
  "id": "138514",
  "description": "An ancient place, cited: BAtlas 14 G4 Petroliaco",
  "bbox": [
    1.407792,
    44.886978,
    1.407792,
    44.886978
  ],
  "reprPoint": [
    1.407792,
    44.886978
  ],
  "names": [
    "Petroliaco"
  ],
  "features": [
    {
      "geometry": {
        "type": "Point",
        "coordinates": [
          1.407792,
          44.886978
        ]
      },
      "id": "darmc-location-16372",
      "type": "Feature",
      "properties": {
        "description": "1M scale point location",
        "location_precision": "precise",
        "title": "DARMC location 16372",
        "link": "http://pleiades.stoa.org/places/138514/darmc-location-16372"
      }
    }
  ]
}