{
  "type": "FeatureCollection",
  "title": "Ron-de-Gleiso",
  "id": "138542",
  "description": "An ancient place, cited: BAtlas 14 I4 Ron-de-Gleiso",
  "bbox": [
    3.213161,
    44.428389,
    3.213161,
    44.428389
  ],
  "reprPoint": [
    3.213161,
    44.428389
  ],
  "names": [
    "Capelle-Saint-Martin"
  ],
  "features": [
    {
      "geometry": {
        "type": "Point",
        "coordinates": [
          3.213161,
          44.428389
        ]
      },
      "id": "dare-location",
      "type": "Feature",
      "properties": {
        "description": "Representative point location, site precision",
        "location_precision": "precise",
        "title": "DARE Location",
        "link": "http://pleiades.stoa.org/places/138542/dare-location"
      }
    },
    {
      "geometry": {
        "type": "Point",
        "coordinates": [
          3.2177,
          44.426577
        ]
      },
      "id": "darmc-location-24520",
      "type": "Feature",
      "properties": {
        "description": "1M scale point location",
        "location_precision": "precise",
        "title": "DARMC location 24520",
        "link": "http://pleiades.stoa.org/places/138542/darmc-location-24520"
      }
    }
  ]
}