{
  "type": "FeatureCollection",
  "title": "St-Julien-de-Concelles",
  "id": "138558",
  "description": "An ancient place, cited: BAtlas 14 D1 St-Julien-de-Concelles",
  "bbox": [
    -1.385976,
    47.253389,
    -1.385976,
    47.253389
  ],
  "reprPoint": [
    -1.385976,
    47.253389
  ],
  "features": [
    {
      "geometry": {
        "type": "Point",
        "coordinates": [
          -1.385976,
          47.253389
        ]
      },
      "id": "darmc-location-24862",
      "type": "Feature",
      "properties": {
        "description": "1M scale point location",
        "location_precision": "precise",
        "title": "DARMC location 24862",
        "link": "http://pleiades.stoa.org/places/138558/darmc-location-24862"
      }
    }
  ]
}