{
  "type": "FeatureCollection",
  "title": "Royat",
  "id": "138544",
  "description": "An ancient place, cited: BAtlas 14 I3 Royat",
  "bbox": [
    3.049775,
    45.764539,
    3.049775,
    45.764539
  ],
  "reprPoint": [
    3.049775,
    45.764539
  ],
  "names": [
    "Royat"
  ],
  "features": [
    {
      "geometry": {
        "type": "Point",
        "coordinates": [
          3.049775,
          45.764539
        ]
      },
      "id": "darmc-location-14530",
      "type": "Feature",
      "properties": {
        "description": "1M scale point location",
        "location_precision": "precise",
        "title": "DARMC location 14530",
        "link": "http://pleiades.stoa.org/places/138544/darmc-location-14530"
      }
    }
  ]
}