{
  "type": "FeatureCollection",
  "title": "Sarrum",
  "id": "138576",
  "description": "An ancient place, cited: BAtlas 14 F3 Sarrum",
  "bbox": [
    0.18293,
    45.496243,
    0.18293,
    45.496243
  ],
  "reprPoint": [
    0.18293,
    45.496243
  ],
  "names": [
    "Sarrum"
  ],
  "features": [
    {
      "geometry": {
        "type": "Point",
        "coordinates": [
          0.18293,
          45.496243
        ]
      },
      "id": "darmc-location-8696",
      "type": "Feature",
      "properties": {
        "description": "1M scale point location",
        "location_precision": "precise",
        "title": "DARMC location 8696",
        "link": "http://pleiades.stoa.org/places/138576/darmc-location-8696"
      }
    }
  ]
}