{
  "type": "FeatureCollection",
  "title": "Rotomagus?",
  "id": "138543",
  "description": "An ancient place, cited: BAtlas 14 F1 Rotomagus?",
  "bbox": [
    0.57529,
    47.259024,
    0.57529,
    47.259024
  ],
  "reprPoint": [
    0.57529,
    47.259024
  ],
  "names": [
    "Rotomagus"
  ],
  "features": [
    {
      "geometry": {
        "type": "Point",
        "coordinates": [
          0.57529,
          47.259024
        ]
      },
      "id": "darmc-location-24523",
      "type": "Feature",
      "properties": {
        "description": "1M scale point location",
        "location_precision": "precise",
        "title": "DARMC location 24523",
        "link": "http://pleiades.stoa.org/places/138543/darmc-location-24523"
      }
    }
  ]
}