{
  "type": "FeatureCollection",
  "title": "*Solonacum?",
  "id": "138598",
  "bbox": [
    0.971242,
    47.602336,
    0.971242,
    47.602336
  ],
  "description": "An ancient place, cited: BAtlas 14 F1 *Solonacum?",
  "names": [
    "Solonacum"
  ],
  "features": [
    {
      "type": "Feature",
      "geometry": {
        "type": "Point",
        "coordinates": [
          0.971242,
          47.602336
        ]
      },
      "properties": {
        "description": "representative point"
      }
    },
    {
      "geometry": {
        "type": "Point",
        "coordinates": [
          0.971242,
          47.602336
        ]
      },
      "id": "darmc-location-24818",
      "type": "Feature",
      "properties": {
        "description": "1M scale point location",
        "location_precision": "precise",
        "title": "DARMC location 24818",
        "link": "http://pleiades.stoa.org/places/138598/darmc-location-24818"
      }
    }
  ]
}