{
  "type": "FeatureCollection",
  "title": "Puy-Lautard",
  "id": "138527",
  "description": "An ancient place, cited: BAtlas 14 G3 Puy-Lautard",
  "bbox": [
    1.888173,
    45.915971,
    1.888173,
    45.915971
  ],
  "reprPoint": [
    1.888173,
    45.915971
  ],
  "features": [
    {
      "geometry": {
        "type": "Point",
        "coordinates": [
          1.888173,
          45.915971
        ]
      },
      "id": "darmc-location-26154",
      "type": "Feature",
      "properties": {
        "description": "1M scale point location",
        "location_precision": "precise",
        "title": "DARMC location 26154",
        "link": "http://pleiades.stoa.org/places/138527/darmc-location-26154"
      }
    }
  ]
}