{
  "type": "FeatureCollection",
  "title": "Reontio",
  "id": "138536",
  "description": "An ancient place, cited: BAtlas 14 E4 Reontio",
  "bbox": [
    -0.351568,
    44.663554,
    -0.351568,
    44.663554
  ],
  "reprPoint": [
    -0.351568,
    44.663554
  ],
  "names": [
    "Reontio"
  ],
  "features": [
    {
      "geometry": {
        "type": "Point",
        "coordinates": [
          -0.351568,
          44.663554
        ]
      },
      "id": "darmc-location-17573",
      "type": "Feature",
      "properties": {
        "description": "1M scale point location",
        "location_precision": "precise",
        "title": "DARMC location 17573",
        "link": "http://pleiades.stoa.org/places/138536/darmc-location-17573"
      }
    }
  ]
}