{
  "type": "FeatureCollection",
  "title": "Les Poulittes",
  "id": "138521",
  "bbox": [
    1.101979,
    47.79531,
    1.101979,
    47.79531
  ],
  "description": "An ancient place, cited: BAtlas 14 G1 Les Poulittes",
  "features": [
    {
      "type": "Feature",
      "geometry": {
        "type": "Point",
        "coordinates": [
          1.101979,
          47.79531
        ]
      },
      "properties": {
        "description": "representative point"
      }
    },
    {
      "geometry": {
        "type": "Point",
        "coordinates": [
          1.101979,
          47.79531
        ]
      },
      "id": "darmc-location-13468",
      "type": "Feature",
      "properties": {
        "description": "1M scale point location",
        "location_precision": "precise",
        "title": "DARMC location 13468",
        "link": "http://pleiades.stoa.org/places/138521/darmc-location-13468"
      }
    }
  ]
}