{
  "type": "FeatureCollection",
  "title": "Saffré",
  "id": "138548",
  "description": "An ancient place, cited: BAtlas 14 D1 Saffré",
  "bbox": [
    -1.578748,
    47.501522,
    -1.578748,
    47.501522
  ],
  "reprPoint": [
    -1.578748,
    47.501522
  ],
  "features": [
    {
      "geometry": {
        "type": "Point",
        "coordinates": [
          -1.578748,
          47.501522
        ]
      },
      "id": "darmc-location-9067",
      "type": "Feature",
      "properties": {
        "description": "1M scale point location",
        "location_precision": "precise",
        "title": "DARMC location 9067",
        "link": "http://pleiades.stoa.org/places/138548/darmc-location-9067"
      }
    }
  ]
}