{
  "type": "FeatureCollection",
  "title": "Verdes",
  "id": "138645",
  "description": "An ancient place, cited: BAtlas 14 G1 Verdes",
  "bbox": [
    1.426589,
    47.955841,
    1.426589,
    47.955841
  ],
  "reprPoint": [
    1.426589,
    47.955841
  ],
  "features": [
    {
      "geometry": {
        "type": "Point",
        "coordinates": [
          1.426589,
          47.955841
        ]
      },
      "id": "darmc-location-15371",
      "type": "Feature",
      "properties": {
        "description": "1M scale point location",
        "location_precision": "precise",
        "title": "DARMC location 15371",
        "link": "http://pleiades.stoa.org/places/138645/darmc-location-15371"
      }
    }
  ]
}