{
  "type": "FeatureCollection",
  "title": "‘Vorogio’",
  "id": "138666",
  "bbox": [
    3.3982682,
    46.31198,
    3.402605,
    46.3143365
  ],
  "description": "An ancient place, cited: BAtlas 14 I2 ‘Vorogio’",
  "names": [
    "Vorogio"
  ],
  "features": [
    {
      "type": "Feature",
      "geometry": {
        "type": "Point",
        "coordinates": [
          3.4004366,
          46.31315825
        ]
      },
      "properties": {
        "description": "representative point"
      }
    },
    {
      "geometry": {
        "type": "Point",
        "coordinates": [
          3.402605,
          46.31198
        ]
      },
      "id": "darmc-location-9909",
      "type": "Feature",
      "properties": {
        "description": "1M scale point location",
        "location_precision": "precise",
        "title": "DARMC location 9909",
        "link": "http://pleiades.stoa.org/places/138666/darmc-location-9909"
      }
    },
    {
      "geometry": {
        "type": "Point",
        "coordinates": [
          3.3982681999999613,
          46.3143365
        ]
      },
      "id": "dare-location",
      "type": "Feature",
      "properties": {
        "description": "Representative point location, village precision",
        "location_precision": "precise",
        "title": "DARE Location",
        "link": "http://pleiades.stoa.org/places/138666/dare-location"
      }
    }
  ]
}