{
  "type": "FeatureCollection",
  "title": "Vivonne",
  "id": "138663",
  "description": "An ancient place, cited: BAtlas 14 F2 Vivonne",
  "bbox": [
    0.261136,
    46.426072,
    0.261136,
    46.426072
  ],
  "reprPoint": [
    0.261136,
    46.426072
  ],
  "features": [
    {
      "geometry": {
        "type": "Point",
        "coordinates": [
          0.261136,
          46.426072
        ]
      },
      "id": "darmc-location-15423",
      "type": "Feature",
      "properties": {
        "description": "1M scale point location",
        "location_precision": "precise",
        "title": "DARMC location 15423",
        "link": "http://pleiades.stoa.org/places/138663/darmc-location-15423"
      }
    }
  ]
}