{
  "type": "FeatureCollection",
  "title": "Tasciaca?",
  "id": "138608",
  "description": "An ancient place, cited: BAtlas 14 G1 Tasciaca?",
  "bbox": [
    1.301991,
    47.325755,
    1.3026426,
    47.3269725
  ],
  "reprPoint": [
    1.3023168,
    47.32636375
  ],
  "names": [
    "Thésée",
    "Tasciaca"
  ],
  "features": [
    {
      "geometry": {
        "type": "Point",
        "coordinates": [
          1.3026426,
          47.3269725
        ]
      },
      "id": "dare-location",
      "type": "Feature",
      "properties": {
        "description": "Representative point location, site precision",
        "location_precision": "precise",
        "title": "DARE Location",
        "link": "http://pleiades.stoa.org/places/138608/dare-location"
      }
    },
    {
      "geometry": {
        "type": "Point",
        "coordinates": [
          1.301991,
          47.325755
        ]
      },
      "id": "darmc-location-7191",
      "type": "Feature",
      "properties": {
        "description": "1M scale point location",
        "location_precision": "precise",
        "title": "DARMC location 7191",
        "link": "http://pleiades.stoa.org/places/138608/darmc-location-7191"
      }
    }
  ]
}