{
  "type": "FeatureCollection",
  "title": "Vendoeuvres-en-Brenne",
  "id": "138642",
  "bbox": [
    1.354989,
    46.801194,
    1.354989,
    46.801194
  ],
  "description": "An ancient place, cited: BAtlas 14 G2 Vendoeuvres-en-Brenne",
  "names": [
    "Vendoeuvres"
  ],
  "features": [
    {
      "type": "Feature",
      "geometry": {
        "type": "Point",
        "coordinates": [
          1.354989,
          46.801194
        ]
      },
      "properties": {
        "description": "representative point"
      }
    },
    {
      "geometry": {
        "type": "Point",
        "coordinates": [
          1.354989,
          46.801194
        ]
      },
      "id": "darmc-location-25368",
      "type": "Feature",
      "properties": {
        "description": "1M scale point location",
        "location_precision": "precise",
        "title": "DARMC location 25368",
        "link": "http://pleiades.stoa.org/places/138642/darmc-location-25368"
      }
    }
  ]
}