{
  "type": "FeatureCollection",
  "title": "Untitled",
  "id": "139677",
  "bbox": [
    1.646658,
    47.269982,
    1.646658,
    47.269982
  ],
  "description": "An ancient place, cited: BAtlas 14 G1 unnamed bridge (Chabris)",
  "features": [
    {
      "type": "Feature",
      "geometry": {
        "type": "Point",
        "coordinates": [
          1.646658,
          47.269982
        ]
      },
      "properties": {
        "description": "representative point"
      }
    },
    {
      "geometry": {
        "type": "Point",
        "coordinates": [
          1.646658,
          47.269982
        ]
      },
      "id": "darmc-location-13753",
      "type": "Feature",
      "properties": {
        "description": "1M scale point location",
        "location_precision": "precise",
        "title": "DARMC location 13753",
        "link": "http://pleiades.stoa.org/places/139677/darmc-location-13753"
      }
    }
  ]
}