{
  "type": "FeatureCollection",
  "title": "Untitled",
  "id": "139679",
  "bbox": [
    1.399021,
    45.886509,
    1.399021,
    45.886509
  ],
  "description": "An ancient place, cited: BAtlas 14 G3 unnamed bridge (St-Priest-Taurion, NE Augustoritum)",
  "features": [
    {
      "type": "Feature",
      "geometry": {
        "type": "Point",
        "coordinates": [
          1.399021,
          45.886509
        ]
      },
      "properties": {
        "description": "representative point"
      }
    },
    {
      "geometry": {
        "type": "Point",
        "coordinates": [
          1.399021,
          45.886509
        ]
      },
      "id": "center-of-batlas-location",
      "type": "Feature",
      "properties": {
        "description": "A positive identification of the sub-commune location noted in the Barrington Atlas directory",
        "location_precision": "precise",
        "title": "Center point of location",
        "link": "http://pleiades.stoa.org/places/139679/center-of-batlas-location"
      }
    }
  ]
}