{
  "type": "FeatureCollection",
  "title": "Barrington Atlas feature labeled 44",
  "id": "140475",
  "bbox": [
    0.577942,
    46.978499,
    0.577942,
    46.978499
  ],
  "description": "An ancient place, cited: BAtlas 14 F2 no. 44 (Chirons, Cm. Antogny)",
  "features": [
    {
      "type": "Feature",
      "geometry": {
        "type": "Point",
        "coordinates": [
          0.577942,
          46.978499
        ]
      },
      "properties": {
        "description": "representative point"
      }
    },
    {
      "geometry": {
        "type": "Point",
        "coordinates": [
          0.577942,
          46.978499
        ]
      },
      "id": "center-of-batlas-location",
      "type": "Feature",
      "properties": {
        "description": "The center of the commune noted in the Barrington Atlas directory",
        "location_precision": "precise",
        "title": "Center point of location",
        "link": "http://pleiades.stoa.org/places/140475/center-of-batlas-location"
      }
    }
  ]
}