{
  "type": "FeatureCollection",
  "title": "Barrington Atlas feature labeled 20",
  "id": "140451",
  "description": "An ancient place, cited: BAtlas 14 F1 no. 20 (La Boulaye, Cm. Athée-sur-Cher)",
  "bbox": [
    0.921076,
    47.338962,
    0.921076,
    47.338962
  ],
  "reprPoint": [
    0.921076,
    47.338962
  ],
  "features": [
    {
      "geometry": {
        "type": "Point",
        "coordinates": [
          0.921076,
          47.338962
        ]
      },
      "id": "center-of-batlas-location",
      "type": "Feature",
      "properties": {
        "description": "A positive identification of the sub-commune location noted in the Barrington Atlas directory",
        "location_precision": "precise",
        "title": "Center point of location",
        "link": "http://pleiades.stoa.org/places/140451/center-of-batlas-location"
      }
    }
  ]
}