{
  "type": "FeatureCollection",
  "title": "Les Petites Varennes, Pouzay",
  "id": "140447",
  "description": "An ancient place, cited: BAtlas 14 F1 no. 16 (Les Petites-Varennes, Cm. Pouzay)",
  "bbox": [
    0.520055,
    47.088426,
    0.520055,
    47.088426
  ],
  "reprPoint": [
    0.520055,
    47.088426
  ],
  "features": [
    {
      "geometry": {
        "type": "Point",
        "coordinates": [
          0.520055,
          47.088426
        ]
      },
      "id": "center-of-batlas-location",
      "type": "Feature",
      "properties": {
        "description": "A positive identification of the sub-commune location noted in the Barrington Atlas directory",
        "location_precision": "precise",
        "title": "Center point of location",
        "link": "http://pleiades.stoa.org/places/140447/center-of-batlas-location"
      }
    }
  ]
}