{
  "type": "FeatureCollection",
  "title": "25",
  "id": "140456",
  "description": "An ancient place, cited: BAtlas 14 G1 no. 25 (Naveil)",
  "bbox": [
    1.029313,
    47.7937246,
    1.029313,
    47.7937246
  ],
  "reprPoint": [
    1.029313,
    47.7937246
  ],
  "features": [
    {
      "geometry": {
        "type": "Point",
        "coordinates": [
          1.029313,
          47.7937246
        ]
      },
      "id": "center-point-of-commune-naveil",
      "type": "Feature",
      "properties": {
        "description": null,
        "location_precision": "precise",
        "title": "Center point of commune Naveil",
        "link": "http://pleiades.stoa.org/places/140456/center-point-of-commune-naveil"
      }
    }
  ]
}