{
  "type": "FeatureCollection",
  "title": "Barrington Atlas feature labeled 63",
  "id": "140494",
  "description": "An ancient place, cited: BAtlas 14 F3 no. 63 (Villar, Cm. Fouqueure)",
  "bbox": [
    0.0741219,
    45.883169,
    0.0741219,
    45.883169
  ],
  "reprPoint": [
    0.0741219,
    45.883169
  ],
  "features": [
    {
      "geometry": {
        "type": "Point",
        "coordinates": [
          0.0741219,
          45.883169
        ]
      },
      "id": "center-of-batlas-location",
      "type": "Feature",
      "properties": {
        "description": "The center of the commune noted in the Barrington Atlas directory",
        "location_precision": "precise",
        "title": "Center point of location",
        "link": "http://pleiades.stoa.org/places/140494/center-of-batlas-location"
      }
    }
  ]
}