{
  "type": "FeatureCollection",
  "title": "Barrington Atlas feature labeled 49",
  "id": "140480",
  "description": "An ancient place, cited: BAtlas 14 D2 no. 49 (Les Minimes, Cm. La Rochelle)",
  "bbox": [
    -1.162168,
    46.143788,
    -1.162168,
    46.143788
  ],
  "reprPoint": [
    -1.162168,
    46.143788
  ],
  "features": [
    {
      "geometry": {
        "type": "Point",
        "coordinates": [
          -1.162168,
          46.143788
        ]
      },
      "id": "center-of-batlas-location",
      "type": "Feature",
      "properties": {
        "description": "A positive identification of the sub-commune location noted in the Barrington Atlas directory",
        "location_precision": "precise",
        "title": "Center point of location",
        "link": "http://pleiades.stoa.org/places/140480/center-of-batlas-location"
      }
    }
  ]
}