{
  "type": "FeatureCollection",
  "title": "Barrington Atlas feature labeled 36",
  "id": "140467",
  "description": "An ancient place, cited: BAtlas 14 H2 no. 36 (Sannat)",
  "bbox": [
    2.406225,
    46.11954,
    2.406225,
    46.11954
  ],
  "reprPoint": [
    2.406225,
    46.11954
  ],
  "features": [
    {
      "geometry": {
        "type": "Point",
        "coordinates": [
          2.406225,
          46.11954
        ]
      },
      "id": "center-of-batlas-location",
      "type": "Feature",
      "properties": {
        "description": "A positive identification of the sub-commune location noted in the Barrington Atlas directory",
        "location_precision": "precise",
        "title": "Center point of location",
        "link": "http://pleiades.stoa.org/places/140467/center-of-batlas-location"
      }
    }
  ]
}