{
  "type": "FeatureCollection",
  "title": "Unnamed villa in Martizay",
  "id": "140474",
  "bbox": [
    1.043282,
    46.807165,
    1.043282,
    46.807165
  ],
  "description": "An ancient villa located in the modern French village of Martizay.",
  "names": [
    "Martizay"
  ],
  "features": [
    {
      "type": "Feature",
      "geometry": {
        "type": "Point",
        "coordinates": [
          1.043282,
          46.807165
        ]
      },
      "properties": {
        "description": "representative point"
      }
    },
    {
      "geometry": {
        "type": "Point",
        "coordinates": [
          1.043282,
          46.807165
        ]
      },
      "id": "center-point-of-the-village-martizay",
      "type": "Feature",
      "properties": {
        "description": null,
        "location_precision": "precise",
        "title": "Center point of the village Martizay",
        "link": "http://pleiades.stoa.org/places/140474/center-point-of-the-village-martizay"
      }
    }
  ]
}