{
  "type": "FeatureCollection",
  "title": "Barrington Atlas feature labeled 15",
  "id": "140446",
  "description": "An ancient place, cited: BAtlas 14 F1 no. 15 (Châtigny, Cm. Fondettes)",
  "bbox": [
    0.58787,
    47.39029,
    0.58787,
    47.39029
  ],
  "reprPoint": [
    0.58787,
    47.39029
  ],
  "features": [
    {
      "geometry": {
        "type": "Point",
        "coordinates": [
          0.58787,
          47.39029
        ]
      },
      "id": "center-of-batlas-location",
      "type": "Feature",
      "properties": {
        "description": "A positive identification of the sub-commune location noted in the Barrington Atlas directory",
        "location_precision": "precise",
        "title": "Center point of location",
        "link": "http://pleiades.stoa.org/places/140446/center-of-batlas-location"
      }
    }
  ]
}