{
  "type": "FeatureCollection",
  "title": "Barrington Atlas feature labeled 19",
  "id": "140450",
  "bbox": [
    0.817751,
    47.345493,
    0.817751,
    47.345493
  ],
  "description": "An ancient place, cited: BAtlas 14 F1 no. 19 (Chavonnière, Cm. Véretz)",
  "features": [
    {
      "type": "Feature",
      "geometry": {
        "type": "Point",
        "coordinates": [
          0.817751,
          47.345493
        ]
      },
      "properties": {
        "description": "representative point"
      }
    },
    {
      "geometry": {
        "type": "Point",
        "coordinates": [
          0.817751,
          47.345493
        ]
      },
      "id": "center-of-batlas-location",
      "type": "Feature",
      "properties": {
        "description": "A positive identification of the sub-commune location noted in the Barrington Atlas directory",
        "location_precision": "precise",
        "title": "Center point of location",
        "link": "http://pleiades.stoa.org/places/140450/center-of-batlas-location"
      }
    }
  ]
}