{
  "type": "FeatureCollection",
  "title": "Barrington Atlas feature labeled 53",
  "id": "140484",
  "description": "An ancient place, cited: BAtlas 14 E3 no. 53 (Cissac-Médoc, Cm. Le Château de Villambis)",
  "bbox": [
    -0.854929,
    45.216181,
    -0.854929,
    45.216181
  ],
  "reprPoint": [
    -0.854929,
    45.216181
  ],
  "features": [
    {
      "geometry": {
        "type": "Point",
        "coordinates": [
          -0.854929,
          45.216181
        ]
      },
      "id": "center-of-batlas-location",
      "type": "Feature",
      "properties": {
        "description": "A positive identification of the sub-commune location noted in the Barrington Atlas directory",
        "location_precision": "precise",
        "title": "Center point of location",
        "link": "http://pleiades.stoa.org/places/140484/center-of-batlas-location"
      }
    }
  ]
}