{
  "type": "FeatureCollection",
  "title": "33",
  "id": "140464",
  "bbox": [
    3.304413,
    46.554957,
    3.304413,
    46.554957
  ],
  "description": "An ancient place, cited: BAtlas 14 I2 no. 33 (Vallières, Cm. Neuvy)",
  "features": [
    {
      "type": "Feature",
      "geometry": {
        "type": "Point",
        "coordinates": [
          3.304413,
          46.554957
        ]
      },
      "properties": {
        "description": "representative point"
      }
    },
    {
      "geometry": {
        "type": "Point",
        "coordinates": [
          3.304413,
          46.554957
        ]
      },
      "id": "center-point-if-vallieres-commune-neuvy",
      "type": "Feature",
      "properties": {
        "description": null,
        "location_precision": "precise",
        "title": "Center point of Vallières, commune Neuvy",
        "link": "http://pleiades.stoa.org/places/140464/center-point-if-vallieres-commune-neuvy"
      }
    }
  ]
}