{
  "type": "FeatureCollection",
  "title": "Unnamed villa in Martizay",
  "id": "140474",
  "bbox": [
    1.0430442,
    46.8070415,
    1.0430442,
    46.8070415
  ],
  "description": "An ancient villa located in the modern French village of Martizay.",
  "names": [
    "Martizay"
  ],
  "features": [
    {
      "type": "Feature",
      "geometry": {
        "type": "Point",
        "coordinates": [
          1.0430442,
          46.8070415
        ]
      },
      "properties": {
        "description": "representative point"
      }
    },
    {
      "geometry": {
        "type": "Point",
        "coordinates": [
          1.0430442,
          46.8070415
        ]
      },
      "id": "osm-location-of-modern-village-of-martizy",
      "type": "Feature",
      "properties": {
        "description": "Location based on OpenStreetMap",
        "location_precision": "precise",
        "title": "OSM location of modern village of Martizy",
        "link": "http://pleiades.stoa.org/places/140474/osm-location-of-modern-village-of-martizy"
      }
    }
  ]
}