{
  "type": "FeatureCollection",
  "title": "Barrington Atlas feature labeled 85",
  "id": "140516",
  "bbox": [
    1.422638,
    45.093221,
    1.422638,
    45.093221
  ],
  "description": "An ancient place, cited: BAtlas 14 G3 no. 85 (Lavialle, Laroche, Cm. St-Cernin-de-Larche)",
  "features": [
    {
      "type": "Feature",
      "geometry": {
        "type": "Point",
        "coordinates": [
          1.422638,
          45.093221
        ]
      },
      "properties": {
        "description": "representative point"
      }
    },
    {
      "geometry": {
        "type": "Point",
        "coordinates": [
          1.422638,
          45.093221
        ]
      },
      "id": "center-of-batlas-location",
      "type": "Feature",
      "properties": {
        "description": "The center of the commune noted in the Barrington Atlas directory",
        "location_precision": "precise",
        "title": "Center point of location",
        "link": "http://pleiades.stoa.org/places/140516/center-of-batlas-location"
      }
    }
  ]
}