{
  "type": "FeatureCollection",
  "title": "Loupiac",
  "id": "140572",
  "bbox": [
    -0.3033324,
    44.6253171,
    -0.3033324,
    44.6253171
  ],
  "description": "An ancient place, cited: BAtlas 14 E4 no. 141 (Loupiac)",
  "names": [
    "Loupiac"
  ],
  "features": [
    {
      "type": "Feature",
      "geometry": {
        "type": "Point",
        "coordinates": [
          -0.3033324,
          44.6253171
        ]
      },
      "properties": {
        "description": "representative point"
      }
    },
    {
      "geometry": {
        "type": "Point",
        "coordinates": [
          -0.3033324,
          44.6253171
        ]
      },
      "id": "osm-location",
      "type": "Feature",
      "properties": {
        "description": "Location based on OpenStreetMap",
        "location_precision": "precise",
        "title": "OSM location",
        "link": "http://pleiades.stoa.org/places/140572/osm-location"
      }
    }
  ]
}