{
  "type": "FeatureCollection",
  "title": "Unnamed villa",
  "id": "140507",
  "bbox": [
    1.273321,
    45.870793,
    1.273321,
    45.870793
  ],
  "description": "An unnamed Gallo-Roman villa at modern Brachaud in France (BAtlas 14 G3 no. 76).",
  "features": [
    {
      "type": "Feature",
      "geometry": {
        "type": "Point",
        "coordinates": [
          1.273321,
          45.870793
        ]
      },
      "properties": {
        "description": "representative point"
      }
    },
    {
      "geometry": {
        "type": "Point",
        "coordinates": [
          1.273321,
          45.870793
        ]
      },
      "id": "center-point-of-the-archaeological-site-brachaud-commune-limoges",
      "type": "Feature",
      "properties": {
        "description": "The archaeological site of the Gallo-Roman villa is visible on satellite images",
        "location_precision": "precise",
        "title": "Center point of the archaeological site Brachaud, commune Limoges",
        "link": "http://pleiades.stoa.org/places/140507/center-point-of-the-archaeological-site-brachaud-commune-limoges"
      }
    }
  ]
}