{
  "type": "FeatureCollection",
  "title": "Barrington Atlas feature labeled 124",
  "id": "140555",
  "bbox": [
    -0.381703,
    44.753407,
    -0.381703,
    44.753407
  ],
  "description": "An ancient place, cited: BAtlas 14 E4 no. 124 (St-Genès-de-Lombaud)",
  "features": [
    {
      "type": "Feature",
      "geometry": {
        "type": "Point",
        "coordinates": [
          -0.381703,
          44.753407
        ]
      },
      "properties": {
        "description": "representative point"
      }
    },
    {
      "geometry": {
        "type": "Point",
        "coordinates": [
          -0.381703,
          44.753407
        ]
      },
      "id": "center-of-batlas-location",
      "type": "Feature",
      "properties": {
        "description": "A positive identification of the sub-commune location noted in the Barrington Atlas directory",
        "location_precision": "precise",
        "title": "Center point of location",
        "link": "http://pleiades.stoa.org/places/140555/center-of-batlas-location"
      }
    }
  ]
}