{
  "type": "FeatureCollection",
  "title": "Barrington Atlas feature labeled 101",
  "id": "140532",
  "description": "An ancient place, cited: BAtlas 14 G4 no. 101 (Majonelle, Cm. Montlauzun)",
  "bbox": [
    1.198191,
    44.303449,
    1.198191,
    44.303449
  ],
  "reprPoint": [
    1.198191,
    44.303449
  ],
  "names": [
    "Mayjounelle"
  ],
  "features": [
    {
      "geometry": {
        "type": "Point",
        "coordinates": [
          1.198191,
          44.303449
        ]
      },
      "id": "center-of-batlas-location",
      "type": "Feature",
      "properties": {
        "description": "A positive identification of the sub-commune location noted in the Barrington Atlas directory",
        "location_precision": "precise",
        "title": "Center point of location",
        "link": "http://pleiades.stoa.org/places/140532/center-of-batlas-location"
      }
    }
  ]
}