{
  "type": "FeatureCollection",
  "title": "Barrington Atlas feature labeled 73",
  "id": "140504",
  "description": "An ancient place, cited: BAtlas 14 F3 no. 73 (Le Petit Peyrou, Cm. Orgedeuil)",
  "bbox": [
    0.475018,
    45.69491,
    0.475018,
    45.69491
  ],
  "reprPoint": [
    0.475018,
    45.69491
  ],
  "features": [
    {
      "geometry": {
        "type": "Point",
        "coordinates": [
          0.475018,
          45.69491
        ]
      },
      "id": "center-of-batlas-location",
      "type": "Feature",
      "properties": {
        "description": "A positive identification of the sub-commune location noted in the Barrington Atlas directory",
        "location_precision": "precise",
        "title": "Center point of location",
        "link": "http://pleiades.stoa.org/places/140504/center-of-batlas-location"
      }
    }
  ]
}