{
  "type": "FeatureCollection",
  "title": "Loupiac",
  "id": "140572",
  "description": "An ancient place, cited: BAtlas 14 E4 no. 141 (Loupiac)",
  "bbox": [
    -0.298356,
    44.628042,
    -0.298356,
    44.628042
  ],
  "reprPoint": [
    -0.298356,
    44.628042
  ],
  "names": [
    "Loupiac"
  ],
  "features": [
    {
      "geometry": {
        "type": "Point",
        "coordinates": [
          -0.298356,
          44.628042
        ]
      },
      "id": "center-of-batlas-location",
      "type": "Feature",
      "properties": {
        "description": "A positive identification of the sub-commune location noted in the Barrington Atlas directory",
        "location_precision": "precise",
        "title": "Center point of location",
        "link": "http://pleiades.stoa.org/places/140572/center-of-batlas-location"
      }
    }
  ]
}