{
  "type": "FeatureCollection",
  "title": "Barrington Atlas feature labeled 110",
  "id": "140541",
  "description": "An ancient place, cited: BAtlas 14 F4 no. 110 (Ste-Bazeille, Cm. Lestang)",
  "bbox": [
    0.0965469,
    44.526462,
    0.0965469,
    44.526462
  ],
  "reprPoint": [
    0.0965469,
    44.526462
  ],
  "features": [
    {
      "geometry": {
        "type": "Point",
        "coordinates": [
          0.0965469,
          44.526462
        ]
      },
      "id": "center-of-batlas-location",
      "type": "Feature",
      "properties": {
        "description": "A positive identification of the sub-commune location noted in the Barrington Atlas directory",
        "location_precision": "precise",
        "title": "Center point of location",
        "link": "http://pleiades.stoa.org/places/140541/center-of-batlas-location"
      }
    }
  ]
}