{
  "type": "FeatureCollection",
  "title": "Barrington Atlas feature labeled 145",
  "id": "140576",
  "description": "An ancient place, cited: BAtlas 14 E4 no. 145 (Cameillac, Cm. Léogeats)",
  "bbox": [
    -0.36934,
    44.503332,
    -0.36934,
    44.503332
  ],
  "reprPoint": [
    -0.36934,
    44.503332
  ],
  "features": [
    {
      "geometry": {
        "type": "Point",
        "coordinates": [
          -0.36934,
          44.503332
        ]
      },
      "id": "center-of-batlas-location",
      "type": "Feature",
      "properties": {
        "description": "A positive identification of the sub-commune location noted in the Barrington Atlas directory",
        "location_precision": "precise",
        "title": "Center point of location",
        "link": "http://pleiades.stoa.org/places/140576/center-of-batlas-location"
      }
    }
  ]
}