{
  "type": "FeatureCollection",
  "title": "Barrington Atlas feature labeled 95",
  "id": "140526",
  "description": "An ancient place, cited: BAtlas 14 H4 no. 95 (Girmou, Cm. Firmi)",
  "bbox": [
    2.336133,
    44.538362,
    2.336133,
    44.538362
  ],
  "reprPoint": [
    2.336133,
    44.538362
  ],
  "features": [
    {
      "geometry": {
        "type": "Point",
        "coordinates": [
          2.336133,
          44.538362
        ]
      },
      "id": "center-of-batlas-location",
      "type": "Feature",
      "properties": {
        "description": "A positive identification of the sub-commune location noted in the Barrington Atlas directory",
        "location_precision": "precise",
        "title": "Center point of location",
        "link": "http://pleiades.stoa.org/places/140526/center-of-batlas-location"
      }
    }
  ]
}