{
  "type": "FeatureCollection",
  "title": "Barrington Atlas feature labeled 142",
  "id": "140573",
  "description": "An ancient place, cited: BAtlas 14 E4 no. 142 (Cadillac)",
  "bbox": [
    -0.320481,
    44.637022,
    -0.320481,
    44.637022
  ],
  "reprPoint": [
    -0.320481,
    44.637022
  ],
  "features": [
    {
      "geometry": {
        "type": "Point",
        "coordinates": [
          -0.320481,
          44.637022
        ]
      },
      "id": "center-of-batlas-location",
      "type": "Feature",
      "properties": {
        "description": "A positive identification of the sub-commune location noted in the Barrington Atlas directory",
        "location_precision": "precise",
        "title": "Center point of location",
        "link": "http://pleiades.stoa.org/places/140573/center-of-batlas-location"
      }
    }
  ]
}