{
  "type": "FeatureCollection",
  "title": "Unnamed Gallo-Roman villa (Montlauzun)",
  "id": "140532",
  "bbox": [
    1.198191,
    44.303449,
    1.198191,
    44.303449
  ],
  "description": "Majonelle, Cm. Montlauzun, France, was the site of a long-lived villa of substantial size. According to M. Labrousse writing in PECS, the presence of a \"Byzantine coin of Phokis\" denotes a very late occupation.",
  "names": [
    "Mayjounelle"
  ],
  "features": [
    {
      "type": "Feature",
      "geometry": {
        "type": "Point",
        "coordinates": [
          1.198191,
          44.303449
        ]
      },
      "properties": {
        "description": "representative point"
      }
    },
    {
      "geometry": {
        "type": "Point",
        "coordinates": [
          1.198191,
          44.303449
        ]
      },
      "id": "center-of-batlas-location",
      "type": "Feature",
      "properties": {
        "description": "A positive identification of the sub-commune location noted in the Barrington Atlas directory",
        "location_precision": "precise",
        "title": "Center point of location",
        "link": "http://pleiades.stoa.org/places/140532/center-of-batlas-location"
      }
    }
  ]
}