{
  "type": "FeatureCollection",
  "title": "Unnamed villa",
  "id": "140503",
  "description": "An ancient place, cited: BAtlas 14 F3 no. 72 (Les Boissières, Cm. Montbron)",
  "bbox": [
    0.497235,
    45.653017,
    0.497235,
    45.653017
  ],
  "reprPoint": [
    0.497235,
    45.653017
  ],
  "features": [
    {
      "geometry": {
        "type": "Point",
        "coordinates": [
          0.497235,
          45.653017
        ]
      },
      "id": "center-of-batlas-location",
      "type": "Feature",
      "properties": {
        "description": "A positive identification of the sub-commune location noted in the Barrington Atlas directory",
        "location_precision": "precise",
        "title": "Center point of location",
        "link": "http://pleiades.stoa.org/places/140503/center-of-batlas-location"
      }
    }
  ]
}