{
  "type": "FeatureCollection",
  "title": "Tomba di Fadilla",
  "id": "1410177",
  "bbox": [
    12.488494,
    41.964297,
    12.488494,
    41.964297
  ],
  "description": "A Roman tomb on the Via Flaminia at Grottarossa that is associated with Annia Aurelia Fadilla, the daughter of the emperor Marcus Aurelius.",
  "connectsWith": [
    "856514595"
  ],
  "names": [
    "Tomb of Fadilla"
  ],
  "features": [
    {
      "type": "Feature",
      "geometry": {
        "type": "Point",
        "coordinates": [
          12.488494,
          41.964297
        ]
      },
      "properties": {
        "description": "representative point"
      }
    },
    {
      "geometry": {
        "type": "Point",
        "coordinates": [
          12.488494,
          41.964297
        ]
      },
      "id": "imagery-location-of-tomba-di-fadilla",
      "type": "Feature",
      "properties": {
        "description": "Coordinates following GeoHack.",
        "location_precision": "precise",
        "title": "Imagery location of Tomba di Fadilla",
        "link": "http://pleiades.stoa.org/places/1410177/imagery-location-of-tomba-di-fadilla"
      }
    }
  ]
}