{
  "type": "FeatureCollection",
  "title": "Fexitoialum",
  "id": "141953",
  "bbox": [
    1.436995,
    44.445321,
    1.442975,
    44.4509746
  ],
  "description": "An ancient place, cited: BAtlas 14 unlocated Fexitoialum",
  "connectsWith": [
    "138329"
  ],
  "names": [
    "Fexitoialum"
  ],
  "features": [
    {
      "type": "Feature",
      "geometry": {
        "type": "Point",
        "coordinates": [
          1.44014133333,
          44.4478665333
        ]
      },
      "properties": {
        "description": "representative point"
      }
    },
    {
      "geometry": null,
      "id": "batlas-location",
      "type": "Feature",
      "properties": {
        "description": null,
        "location_precision": "unlocated",
        "title": "Barrington Atlas location",
        "link": "http://pleiades.stoa.org/places/141953/batlas-location"
      }
    }
  ]
}