{
  "type": "FeatureCollection",
  "title": "Ianus Augustus",
  "id": "143866644",
  "bbox": [
    -3.8094553,
    37.9978772,
    -3.8094553,
    37.9978772
  ],
  "description": "The remains of a Roman arch may mark the boundary between the Roman provinces of Hispania Baetica and Hispania Tarraconensis.",
  "connectsWith": [
    "803793619"
  ],
  "features": [
    {
      "type": "Feature",
      "geometry": {
        "type": "Point",
        "coordinates": [
          -3.8094553,
          37.9978772
        ]
      },
      "properties": {
        "description": "representative point"
      }
    },
    {
      "geometry": {
        "type": "Point",
        "coordinates": [
          -3.8094553,
          37.9978772
        ]
      },
      "id": "osm-location-of-arco-jano",
      "type": "Feature",
      "properties": {
        "description": "Representative location based on OpenStreetMap",
        "location_precision": "precise",
        "title": "OSM location of Arco Jano",
        "link": "http://pleiades.stoa.org/places/143866644/osm-location-of-arco-jano"
      }
    }
  ]
}