{
  "type": "FeatureCollection",
  "title": "Nuraghe Nuraddeo",
  "id": "144604065",
  "bbox": [
    8.579722,
    40.324166,
    8.579722,
    40.324166
  ],
  "description": "A Middle Bronze Age nuragic site with a central tower standing ca. 14 m. tall near Suni, Sardinia.",
  "connectsWith": [
    "472014"
  ],
  "features": [
    {
      "type": "Feature",
      "geometry": {
        "type": "Point",
        "coordinates": [
          8.579722,
          40.324166
        ]
      },
      "properties": {
        "description": "representative point"
      }
    },
    {
      "geometry": {
        "type": "Point",
        "coordinates": [
          8.579722,
          40.324166
        ]
      },
      "id": "location-of-nuraghe-nuraddeo",
      "type": "Feature",
      "properties": {
        "description": "Coordinates after Wikimapia; verified in Google Earth 2013.",
        "location_precision": "precise",
        "title": "Imagery location of Nuraghe Nuraddeo",
        "link": "http://pleiades.stoa.org/places/144604065/location-of-nuraghe-nuraddeo"
      }
    }
  ]
}