{
  "type": "FeatureCollection",
  "title": "Assur Archive 41",
  "id": "146128416",
  "bbox": [
    43.256647,
    35.454939,
    43.256647,
    35.454939
  ],
  "description": "In the ruins of a private house outside the inner town wall in cC9I, excavators discovered a small archive consisting of 3 clay tablets and fragments as well as one clay envelope, dating to the mid-7th century BC. These texts are loan documents, as well as one list, which is a harvest report.",
  "connectsWith": [
    "893945"
  ],
  "names": [
    "Assur Archive 41",
    "N 26 Archive"
  ],
  "features": [
    {
      "type": "Feature",
      "geometry": {
        "type": "Point",
        "coordinates": [
          43.256647,
          35.454939
        ]
      },
      "properties": {
        "description": "representative point"
      }
    },
    {
      "geometry": {
        "type": "Point",
        "coordinates": [
          43.256647,
          35.454939
        ]
      },
      "id": "plan-location-of-assur-archive-41",
      "type": "Feature",
      "properties": {
        "description": "Representative locations of the Neo-Assyrian archive at Assur on the basis of Pedersén 1987 Plan(s) 62.",
        "location_precision": "precise",
        "title": "Plan location of Assur Archive 41",
        "link": "http://pleiades.stoa.org/places/146128416/plan-location-of-assur-archive-41"
      }
    }
  ]
}