{
  "type": "FeatureCollection",
  "title": "Araura/Cessero",
  "id": "147997",
  "description": "Araura/Cessero was originally a Celtic oppidum and, later, a road station on the Via Domitia.",
  "bbox": [
    3.42009,
    43.394529,
    3.420272,
    43.394594
  ],
  "connectsWith": [
    "910480188"
  ],
  "reprPoint": [
    3.420181,
    43.3945615
  ],
  "names": [
    "Saint-Thibéry",
    "Araura",
    "Cessero"
  ],
  "features": [
    {
      "geometry": {
        "type": "Point",
        "coordinates": [
          3.42009,
          43.394594
        ]
      },
      "id": "darmc-location-1613",
      "type": "Feature",
      "properties": {
        "description": "500K scale point location",
        "location_precision": "precise",
        "title": "DARMC location 1613",
        "link": "http://pleiades.stoa.org/places/147997/darmc-location-1613"
      }
    },
    {
      "geometry": {
        "type": "Point",
        "coordinates": [
          3.420272,
          43.394529
        ]
      },
      "id": "darmc-location-3299",
      "type": "Feature",
      "properties": {
        "description": "1M scale point location",
        "location_precision": "precise",
        "title": "DARMC location 3299",
        "link": "http://pleiades.stoa.org/places/147997/darmc-location-3299"
      }
    }
  ]
}