{
  "type": "FeatureCollection",
  "title": "Araura/Cessero",
  "id": "147997",
  "bbox": [
    3.42009,
    43.394529,
    3.420272,
    43.394594
  ],
  "description": "Araura/Cessero was originally a Celtic oppidum and, later, a road station on the Via Domitia.",
  "names": [
    "Araura",
    "Cessero",
    "Saint-Thibéry",
    "Cesse Rone"
  ],
  "features": [
    {
      "type": "Feature",
      "geometry": {
        "type": "Point",
        "coordinates": [
          3.420181,
          43.3945615
        ]
      },
      "properties": {
        "description": "representative point"
      }
    },
    {
      "geometry": {
        "type": "Point",
        "coordinates": [
          3.42009,
          43.394594
        ]
      },
      "id": "darmc-location-1613",
      "type": "Feature",
      "properties": {
        "description": "1:500,000 scale representative point location digitized from the Barrington Atlas of the Greek and Roman World by the Digital Atlas of Roman and Medieval Civilizations project at Harvard University.",
        "location_precision": "precise",
        "title": "DARMC location 1613",
        "link": "http://pleiades.stoa.org/places/147997/darmc-location-1613"
      }
    },
    {
      "geometry": {
        "type": "Point",
        "coordinates": [
          3.420272,
          43.394529
        ]
      },
      "id": "darmc-location-3299",
      "type": "Feature",
      "properties": {
        "description": "1:1 million scale representative point location digitized from the Barrington Atlas of the Greek and Roman World by the Digital Atlas of Roman and Medieval Civilizations project at Harvard University.",
        "location_precision": "precise",
        "title": "DARMC location 3299",
        "link": "http://pleiades.stoa.org/places/147997/darmc-location-3299"
      }
    }
  ]
}