{
  "type": "FeatureCollection",
  "title": "Alès",
  "id": "147988",
  "description": "An ancient place, cited: BAtlas 15 C1 Alès",
  "bbox": [
    4.078972,
    44.127214,
    4.078972,
    44.127214
  ],
  "reprPoint": [
    4.078972,
    44.127214
  ],
  "features": [
    {
      "geometry": {
        "type": "Point",
        "coordinates": [
          4.078972,
          44.127214
        ]
      },
      "id": "darmc-location-16093",
      "type": "Feature",
      "properties": {
        "description": "500K scale point location",
        "location_precision": "precise",
        "title": "DARMC location 16093",
        "link": "http://pleiades.stoa.org/places/147988/darmc-location-16093"
      }
    }
  ]
}