{
  "type": "FeatureCollection",
  "title": "Aspiran",
  "id": "148002",
  "bbox": [
    3.44945,
    43.56714,
    3.44945,
    43.56714
  ],
  "description": "An ancient place, cited: BAtlas 15 A2 Aspiran",
  "features": [
    {
      "type": "Feature",
      "geometry": {
        "type": "Point",
        "coordinates": [
          3.44945,
          43.56714
        ]
      },
      "properties": {
        "description": "representative point"
      }
    },
    {
      "geometry": {
        "type": "Point",
        "coordinates": [
          3.44945,
          43.56714
        ]
      },
      "id": "darmc-location-17368",
      "type": "Feature",
      "properties": {
        "description": "500K scale point location",
        "location_precision": "precise",
        "title": "DARMC location 17368",
        "link": "http://pleiades.stoa.org/places/148002/darmc-location-17368"
      }
    }
  ]
}