{
  "type": "FeatureCollection",
  "title": "Beauregard",
  "id": "148018",
  "bbox": [
    5.042732,
    43.786975,
    5.042732,
    43.786975
  ],
  "description": "An ancient place, cited: BAtlas 15 E2 Beauregard",
  "names": [
    "Notre-Dame de Beauregard"
  ],
  "features": [
    {
      "type": "Feature",
      "geometry": {
        "type": "Point",
        "coordinates": [
          5.042732,
          43.786975
        ]
      },
      "properties": {
        "description": "representative point"
      }
    },
    {
      "geometry": {
        "type": "Point",
        "coordinates": [
          5.042732,
          43.786975
        ]
      },
      "id": "darmc-location-6342",
      "type": "Feature",
      "properties": {
        "description": "500K scale point location",
        "location_precision": "precise",
        "title": "DARMC location 6342",
        "link": "http://pleiades.stoa.org/places/148018/darmc-location-6342"
      }
    }
  ]
}