{
  "type": "FeatureCollection",
  "title": "Estel Roman Quarry",
  "id": "148076",
  "bbox": [
    4.54959,
    43.955306,
    4.54959,
    43.955306
  ],
  "description": "A limestone quarry from which was sourced the stone used in the construction of the Pont du Gard. The quarry was excavated in the late 1990s and early 2000s on a site 600-700 meters northeast of the aqueduct bridge. ",
  "names": [
    "Carrière de l’Estel"
  ],
  "features": [
    {
      "type": "Feature",
      "geometry": {
        "type": "Point",
        "coordinates": [
          4.54959,
          43.955306
        ]
      },
      "properties": {
        "description": "representative point"
      }
    },
    {
      "geometry": {
        "type": "Point",
        "coordinates": [
          4.54959,
          43.955306
        ]
      },
      "id": "darmc-location-7251",
      "type": "Feature",
      "properties": {
        "description": "1:500,000 scale representative point location digitized from the Barrington Atlas of the Greek and Roman World by the Digital Atlas of Roman and Medieval Civilizations project at Harvard University.",
        "location_precision": "precise",
        "title": "DARMC location 7251",
        "link": "http://pleiades.stoa.org/places/148076/darmc-location-7251"
      }
    }
  ]
}