{
  "type": "FeatureCollection",
  "title": "Dilis",
  "id": "148068",
  "description": "An ancient place, cited: BAtlas 15 E3 Dilis",
  "bbox": [
    5.026714,
    43.356777,
    5.026714,
    43.356777
  ],
  "reprPoint": [
    5.026714,
    43.356777
  ],
  "names": [
    "Dilis"
  ],
  "features": [
    {
      "geometry": {
        "type": "Point",
        "coordinates": [
          5.026714,
          43.356777
        ]
      },
      "id": "darmc-location-8680",
      "type": "Feature",
      "properties": {
        "description": "500K scale point location",
        "location_precision": "precise",
        "title": "DARMC location 8680",
        "link": "http://pleiades.stoa.org/places/148068/darmc-location-8680"
      }
    }
  ]
}