{
  "type": "FeatureCollection",
  "title": "Barutel Roman Quarry",
  "id": "148014",
  "bbox": [
    4.3002532,
    43.8864126,
    4.3002532,
    43.8864126
  ],
  "description": "A cluster of Roman-era limestone quarries near modern Carrières de Barutel, northwest of Nîmes in France (BAtlas 15 C2 Barutel).",
  "features": [
    {
      "type": "Feature",
      "geometry": {
        "type": "Point",
        "coordinates": [
          4.3002532,
          43.8864126
        ]
      },
      "properties": {
        "description": "representative point"
      }
    },
    {
      "geometry": {
        "type": "Point",
        "coordinates": [
          4.3002532,
          43.8864126
        ]
      },
      "id": "osm-location-of-carriare-romaine-de-barutel",
      "type": "Feature",
      "properties": {
        "description": "Representative location based on OpenStreetMap",
        "location_precision": "precise",
        "title": "OSM location of Carrière romaine de Barutel",
        "link": "http://pleiades.stoa.org/places/148014/osm-location-of-carriare-romaine-de-barutel"
      }
    }
  ]
}