{
  "type": "FeatureCollection",
  "title": "Fossae Marianae?",
  "id": "148084",
  "bbox": [
    4.944532,
    43.437712,
    4.944532,
    43.437712
  ],
  "description": "An ancient place, cited: BAtlas 15 D3 Fossae Marianae?",
  "names": [
    "Fossae Marianae"
  ],
  "features": [
    {
      "type": "Feature",
      "geometry": {
        "type": "Point",
        "coordinates": [
          4.944532,
          43.437712
        ]
      },
      "properties": {
        "description": "representative point"
      }
    },
    {
      "geometry": {
        "type": "Point",
        "coordinates": [
          4.944532,
          43.437712
        ]
      },
      "id": "darmc-location-6430",
      "type": "Feature",
      "properties": {
        "description": "500K scale point location",
        "location_precision": "precise",
        "title": "DARMC location 6430",
        "link": "http://pleiades.stoa.org/places/148084/darmc-location-6430"
      }
    }
  ]
}