{
  "type": "FeatureCollection",
  "title": "Barutel Roman Quarry",
  "id": "148014",
  "bbox": [
    4.300123,
    43.886486,
    4.300123,
    43.886486
  ],
  "description": "A cluster of Roman-era limestone quarries near modern Carrières de Barutel, northwest of Nîmes in France (BAtlas 15 C2 Barutel).",
  "features": [
    {
      "type": "Feature",
      "geometry": {
        "type": "Point",
        "coordinates": [
          4.300123,
          43.886486
        ]
      },
      "properties": {
        "description": "representative point"
      }
    },
    {
      "geometry": {
        "type": "Point",
        "coordinates": [
          4.300123,
          43.886486
        ]
      },
      "id": "center-point-of-the-carrieres-romaines-near-carrieres-de-barutel",
      "type": "Feature",
      "properties": {
        "description": "Center point of the Carrières romaines (Roman quarries) near Carrières de Barutel",
        "location_precision": "precise",
        "title": "Center point of the Carrières romaines near Carrières de Barutel",
        "link": "http://pleiades.stoa.org/places/148014/center-point-of-the-carrieres-romaines-near-carrieres-de-barutel"
      }
    }
  ]
}