{
  "type": "FeatureCollection",
  "title": "Clos de Serre",
  "id": "148052",
  "description": "An ancient place, cited: BAtlas 15 D2 Clos de Serre",
  "bbox": [
    4.9418,
    43.89376,
    4.9418,
    43.89376
  ],
  "reprPoint": [
    4.9418,
    43.89376
  ],
  "features": [
    {
      "geometry": {
        "type": "Point",
        "coordinates": [
          4.9449,
          43.894161
        ]
      },
      "id": "darmc-location-17397",
      "type": "Feature",
      "properties": {
        "description": "500K scale point location",
        "location_precision": "precise",
        "title": "DARMC location 17397",
        "link": "http://pleiades.stoa.org/places/148052/darmc-location-17397"
      }
    },
    {
      "geometry": {
        "type": "Point",
        "coordinates": [
          4.9418,
          43.89376
        ]
      },
      "id": "dare-location",
      "type": "Feature",
      "properties": {
        "description": "Representative point location, site precision",
        "location_precision": "precise",
        "title": "DARE Location",
        "link": "http://pleiades.stoa.org/places/148052/dare-location"
      }
    }
  ]
}