{
  "type": "FeatureCollection",
  "title": "Clermont-l’Hérault",
  "id": "148049",
  "bbox": [
    3.434802,
    43.626007,
    3.434802,
    43.626007
  ],
  "description": "An ancient place, cited: BAtlas 15 A2 Clermont-l’Hérault",
  "features": [
    {
      "type": "Feature",
      "geometry": {
        "type": "Point",
        "coordinates": [
          3.434802,
          43.626007
        ]
      },
      "properties": {
        "description": "representative point"
      }
    },
    {
      "geometry": {
        "type": "Point",
        "coordinates": [
          3.434802,
          43.626007
        ]
      },
      "id": "darmc-location-27396",
      "type": "Feature",
      "properties": {
        "description": "500K scale point location",
        "location_precision": "precise",
        "title": "DARMC location 27396",
        "link": "http://pleiades.stoa.org/places/148049/darmc-location-27396"
      }
    }
  ]
}