{
  "type": "FeatureCollection",
  "title": "Estel",
  "id": "148076",
  "description": "An ancient place, cited: BAtlas 15 D2 Estel",
  "bbox": [
    4.54959,
    43.955306,
    4.54959,
    43.955306
  ],
  "reprPoint": [
    4.54959,
    43.955306
  ],
  "features": [
    {
      "geometry": {
        "type": "Point",
        "coordinates": [
          4.54959,
          43.955306
        ]
      },
      "id": "darmc-location-7251",
      "type": "Feature",
      "properties": {
        "description": "500K scale point location",
        "location_precision": "precise",
        "title": "DARMC location 7251",
        "link": "http://pleiades.stoa.org/places/148076/darmc-location-7251"
      }
    }
  ]
}