{
  "type": "FeatureCollection",
  "title": "Castellas de Rognac",
  "id": "148038",
  "description": "An ancient place, cited: BAtlas 15 E3 Castellas de Rognac",
  "bbox": [
    5.24804044446,
    43.4842140661,
    5.24804044446,
    43.4842140661
  ],
  "reprPoint": [
    5.24804044446,
    43.4842140661
  ],
  "names": [
    "Castellas de Rognac"
  ],
  "features": [
    {
      "geometry": {
        "type": "Point",
        "coordinates": [
          5.246238,
          43.491064
        ]
      },
      "id": "darmc-location-5641",
      "type": "Feature",
      "properties": {
        "description": "500K scale point location",
        "location_precision": "precise",
        "title": "DARMC location 5641",
        "link": "http://pleiades.stoa.org/places/148038/darmc-location-5641"
      }
    },
    {
      "geometry": {
        "type": "Point",
        "coordinates": [
          5.24804044446,
          43.4842140661
        ]
      },
      "id": "dare-location",
      "type": "Feature",
      "properties": {
        "description": "Representative point location, site precision",
        "location_precision": "precise",
        "title": "DARE Location",
        "link": "http://pleiades.stoa.org/places/148038/dare-location"
      }
    }
  ]
}