{
  "type": "FeatureCollection",
  "title": "Gradus Massilitanorum",
  "id": "148094",
  "description": "An ancient place, cited: BAtlas 15 D3 Gradus Massilitanorum",
  "bbox": [
    4.745185,
    43.474313,
    4.745185,
    43.474313
  ],
  "reprPoint": [
    4.745185,
    43.474313
  ],
  "names": [
    "Gradus Massilitanorum"
  ],
  "features": [
    {
      "geometry": {
        "type": "Point",
        "coordinates": [
          4.745185,
          43.474313
        ]
      },
      "id": "darmc-location-8038",
      "type": "Feature",
      "properties": {
        "description": "500K scale point location",
        "location_precision": "precise",
        "title": "DARMC location 8038",
        "link": "http://pleiades.stoa.org/places/148094/darmc-location-8038"
      }
    }
  ]
}