{
  "type": "FeatureCollection",
  "title": "Beaumont-du-Ventoux",
  "id": "148017",
  "description": "An ancient place, cited: BAtlas 15 E1 Beaumont-du-Ventoux",
  "bbox": [
    5.165554,
    44.183767,
    5.165554,
    44.183767
  ],
  "reprPoint": [
    5.165554,
    44.183767
  ],
  "features": [
    {
      "geometry": {
        "type": "Point",
        "coordinates": [
          5.165554,
          44.183767
        ]
      },
      "id": "darmc-location-17240",
      "type": "Feature",
      "properties": {
        "description": "500K scale point location",
        "location_precision": "precise",
        "title": "DARMC location 17240",
        "link": "http://pleiades.stoa.org/places/148017/darmc-location-17240"
      }
    }
  ]
}