{
  "type": "FeatureCollection",
  "title": "Lunel-Viel",
  "id": "148120",
  "bbox": [
    4.092021,
    43.679345,
    4.092021,
    43.679345
  ],
  "description": "An ancient place, cited: BAtlas 15 C2 Lunel-Viel",
  "connectsWith": [
    "834876934"
  ],
  "features": [
    {
      "type": "Feature",
      "geometry": {
        "type": "Point",
        "coordinates": [
          4.092021,
          43.679345
        ]
      },
      "properties": {
        "description": "representative point"
      }
    },
    {
      "geometry": {
        "type": "Point",
        "coordinates": [
          4.092021,
          43.679345
        ]
      },
      "id": "darmc-location-16702",
      "type": "Feature",
      "properties": {
        "description": "500K scale point location",
        "location_precision": "precise",
        "title": "DARMC location 16702",
        "link": "http://pleiades.stoa.org/places/148120/darmc-location-16702"
      }
    }
  ]
}