{
  "type": "FeatureCollection",
  "title": "St-Blaise",
  "id": "148178",
  "bbox": [
    4.981817,
    43.463003,
    4.981817,
    43.463003
  ],
  "description": "An ancient place, cited: BAtlas 15 D3 St-Blaise",
  "names": [
    "Saint-Blaise"
  ],
  "features": [
    {
      "type": "Feature",
      "geometry": {
        "type": "Point",
        "coordinates": [
          4.981817,
          43.463003
        ]
      },
      "properties": {
        "description": "representative point"
      }
    },
    {
      "geometry": {
        "type": "Point",
        "coordinates": [
          4.981817,
          43.463003
        ]
      },
      "id": "darmc-location-15364",
      "type": "Feature",
      "properties": {
        "description": "500K scale point location",
        "location_precision": "precise",
        "title": "DARMC location 15364",
        "link": "http://pleiades.stoa.org/places/148178/darmc-location-15364"
      }
    }
  ]
}