{
  "type": "FeatureCollection",
  "title": "Luteva/*Forum Neronis",
  "id": "148121",
  "bbox": [
    3.323529,
    43.730344,
    3.323931,
    43.730407
  ],
  "description": "An ancient place, cited: BAtlas 15 A2 Luteva/*Forum Neronis",
  "names": [
    "Luteva",
    "Forum Neronis",
    "Civ. Lutevensium",
    "Lodève"
  ],
  "features": [
    {
      "type": "Feature",
      "geometry": {
        "type": "Point",
        "coordinates": [
          3.32373,
          43.7303755
        ]
      },
      "properties": {
        "description": "representative point"
      }
    },
    {
      "geometry": {
        "type": "Point",
        "coordinates": [
          3.323529,
          43.730407
        ]
      },
      "id": "darmc-location-1700",
      "type": "Feature",
      "properties": {
        "description": "500K scale point location",
        "location_precision": "precise",
        "title": "DARMC location 1700",
        "link": "http://pleiades.stoa.org/places/148121/darmc-location-1700"
      }
    },
    {
      "geometry": {
        "type": "Point",
        "coordinates": [
          3.323931,
          43.730344
        ]
      },
      "id": "darmc-location-4650",
      "type": "Feature",
      "properties": {
        "description": "1M scale point location",
        "location_precision": "precise",
        "title": "DARMC location 4650",
        "link": "http://pleiades.stoa.org/places/148121/darmc-location-4650"
      }
    }
  ]
}