{
  "type": "FeatureCollection",
  "title": "Notre-Dame-de-Pitié",
  "id": "148144",
  "description": "An ancient place, cited: BAtlas 15 E3 Notre-Dame-de-Pitié",
  "bbox": [
    5.232867,
    43.405741,
    5.232867,
    43.405741
  ],
  "reprPoint": [
    5.232867,
    43.405741
  ],
  "features": [
    {
      "geometry": {
        "type": "Point",
        "coordinates": [
          5.232867,
          43.405741
        ]
      },
      "id": "darmc-location-16810",
      "type": "Feature",
      "properties": {
        "description": "500K scale point location",
        "location_precision": "precise",
        "title": "DARMC location 16810",
        "link": "http://pleiades.stoa.org/places/148144/darmc-location-16810"
      }
    }
  ]
}