{
  "type": "FeatureCollection",
  "title": "Mus Roman Quarry",
  "id": "148139",
  "bbox": [
    4.200436,
    43.739746,
    4.200436,
    43.739746
  ],
  "description": "A Roman-era sandstone quarry at Mus in France.",
  "features": [
    {
      "type": "Feature",
      "geometry": {
        "type": "Point",
        "coordinates": [
          4.200436,
          43.739746
        ]
      },
      "properties": {
        "description": "representative point"
      }
    },
    {
      "geometry": {
        "type": "Point",
        "coordinates": [
          4.200436,
          43.739746
        ]
      },
      "id": "darmc-location-7387",
      "type": "Feature",
      "properties": {
        "description": "1:500,000 scale representative point location digitized from the Barrington Atlas of the Greek and Roman World by the Digital Atlas of Roman and Medieval Civilizations project at Harvard University.",
        "location_precision": "precise",
        "title": "DARMC location 7387",
        "link": "http://pleiades.stoa.org/places/148139/darmc-location-7387"
      }
    }
  ]
}