{
  "type": "FeatureCollection",
  "title": "Mus",
  "id": "148139",
  "description": "An ancient place, cited: BAtlas 15 C2 Mus",
  "bbox": [
    4.200436,
    43.739746,
    4.200436,
    43.739746
  ],
  "reprPoint": [
    4.200436,
    43.739746
  ],
  "features": [
    {
      "geometry": {
        "type": "Point",
        "coordinates": [
          4.200436,
          43.739746
        ]
      },
      "id": "darmc-location-7387",
      "type": "Feature",
      "properties": {
        "description": "500K scale point location",
        "location_precision": "precise",
        "title": "DARMC location 7387",
        "link": "http://pleiades.stoa.org/places/148139/darmc-location-7387"
      }
    }
  ]
}