{
  "type": "FeatureCollection",
  "title": "Vindalium?",
  "id": "148236",
  "description": "Vindalium? is a site in Gallia Narbonensis where Domitius Ahenobarbus defeated the Allobroges (121 BC).",
  "bbox": [
    4.903091,
    43.998253,
    4.903091,
    43.998253
  ],
  "connectsWith": [
    "802c31143f90ef98caa72f3c0926c67a"
  ],
  "reprPoint": [
    4.903091,
    43.998253
  ],
  "names": [
    "Vindalium"
  ],
  "features": [
    {
      "geometry": {
        "type": "Point",
        "coordinates": [
          4.903091,
          43.998253
        ]
      },
      "id": "darmc-location-6554",
      "type": "Feature",
      "properties": {
        "description": "500K scale point location",
        "location_precision": "precise",
        "title": "DARMC location 6554",
        "link": "http://pleiades.stoa.org/places/148236/darmc-location-6554"
      }
    }
  ]
}