{
  "type": "FeatureCollection",
  "title": "Teste-Nègre",
  "id": "148216",
  "bbox": [
    5.307387,
    43.401657,
    5.307387,
    43.401657
  ],
  "description": "An ancient place, cited: BAtlas 15 E3 Teste-Nègre",
  "features": [
    {
      "type": "Feature",
      "geometry": {
        "type": "Point",
        "coordinates": [
          5.307387,
          43.401657
        ]
      },
      "properties": {
        "description": "representative point"
      }
    },
    {
      "geometry": {
        "type": "Point",
        "coordinates": [
          5.307387,
          43.401657
        ]
      },
      "id": "darmc-location-16960",
      "type": "Feature",
      "properties": {
        "description": "500K scale point location",
        "location_precision": "precise",
        "title": "DARMC location 16960",
        "link": "http://pleiades.stoa.org/places/148216/darmc-location-16960"
      }
    }
  ]
}