{
  "type": "FeatureCollection",
  "title": "Ucetia",
  "id": "148222",
  "description": "An ancient place, cited: BAtlas 15 C1 Ucetia",
  "bbox": [
    4.422229,
    44.012135,
    4.422229,
    44.012135
  ],
  "reprPoint": [
    4.422229,
    44.012135
  ],
  "names": [
    "Uzès",
    "Ucetia"
  ],
  "features": [
    {
      "geometry": {
        "type": "Point",
        "coordinates": [
          4.418997,
          44.01068
        ]
      },
      "id": "darmc-location-6501",
      "type": "Feature",
      "properties": {
        "description": "500K scale point location",
        "location_precision": "precise",
        "title": "DARMC location 6501",
        "link": "http://pleiades.stoa.org/places/148222/darmc-location-6501"
      }
    },
    {
      "geometry": {
        "type": "Point",
        "coordinates": [
          4.422229,
          44.012135
        ]
      },
      "id": "dare-location",
      "type": "Feature",
      "properties": {
        "description": "Representative point location, site precision",
        "location_precision": "precise",
        "title": "DARE Location",
        "link": "http://pleiades.stoa.org/places/148222/dare-location"
      }
    }
  ]
}