{
  "type": "FeatureCollection",
  "title": "Vendres",
  "id": "148231",
  "description": "An ancient place, cited: BAtlas 15 A3 Vendres",
  "bbox": [
    3.225971,
    43.269254,
    3.225971,
    43.269254
  ],
  "reprPoint": [
    3.225971,
    43.269254
  ],
  "features": [
    {
      "geometry": {
        "type": "Point",
        "coordinates": [
          3.225971,
          43.269254
        ]
      },
      "id": "darmc-location-17637",
      "type": "Feature",
      "properties": {
        "description": "500K scale point location",
        "location_precision": "precise",
        "title": "DARMC location 17637",
        "link": "http://pleiades.stoa.org/places/148231/darmc-location-17637"
      }
    }
  ]
}