{
  "type": "FeatureCollection",
  "title": "Tavel",
  "id": "148212",
  "description": "An ancient place, cited: BAtlas 15 D1 Tavel",
  "bbox": [
    4.701146,
    44.011067,
    4.701146,
    44.011067
  ],
  "reprPoint": [
    4.701146,
    44.011067
  ],
  "features": [
    {
      "geometry": {
        "type": "Point",
        "coordinates": [
          4.701146,
          44.011067
        ]
      },
      "id": "darmc-location-17623",
      "type": "Feature",
      "properties": {
        "description": "500K scale point location",
        "location_precision": "precise",
        "title": "DARMC location 17623",
        "link": "http://pleiades.stoa.org/places/148212/darmc-location-17623"
      }
    }
  ]
}