{
  "type": "FeatureCollection",
  "title": "Maen Castle",
  "id": "149003409",
  "bbox": [
    -5.7080356,
    50.0727155,
    -5.7080356,
    50.0727155
  ],
  "description": "Maen Castle is an Iron Age promontory fort near Land's End in Cornwall.",
  "features": [
    {
      "type": "Feature",
      "geometry": {
        "type": "Point",
        "coordinates": [
          -5.7080356,
          50.0727155
        ]
      },
      "properties": {
        "description": "representative point"
      }
    },
    {
      "geometry": {
        "type": "Point",
        "coordinates": [
          -5.7080356,
          50.0727155
        ]
      },
      "id": "location-of-maen-castle-hill-fort",
      "type": "Feature",
      "properties": {
        "description": "Representative location based on OpenStreetMap.",
        "location_precision": "precise",
        "title": "OSM location of Maen Castle",
        "link": "http://pleiades.stoa.org/places/149003409/location-of-maen-castle-hill-fort"
      }
    }
  ]
}