{
  "type": "FeatureCollection",
  "title": "Untitled",
  "id": "149498",
  "description": "An ancient place, cited: BAtlas 15 E1 unnamed bridge (Vasio)",
  "bbox": [
    5.0745852,
    44.2388162,
    5.0745852,
    44.2388162
  ],
  "reprPoint": [
    5.0745852,
    44.2388162
  ],
  "features": [
    {
      "geometry": {
        "type": "Point",
        "coordinates": [
          5.0745852,
          44.2388162
        ]
      },
      "id": "location-of-roman-bridge",
      "type": "Feature",
      "properties": {
        "description": "Location based on OpenStreetMap",
        "location_precision": "precise",
        "title": "location of Roman bridge",
        "link": "http://pleiades.stoa.org/places/149498/location-of-roman-bridge"
      }
    }
  ]
}