{
  "type": "FeatureCollection",
  "title": "Raviscanina",
  "id": "149580279",
  "bbox": [
    14.242723,
    41.37022,
    14.242723,
    41.37022
  ],
  "description": "A pre-Roman center located in the territory of Allifae.",
  "names": [
    "Raviscanina"
  ],
  "features": [
    {
      "type": "Feature",
      "geometry": {
        "type": "Point",
        "coordinates": [
          14.242723,
          41.37022
        ]
      },
      "properties": {
        "description": "representative point"
      }
    },
    {
      "geometry": {
        "type": "Point",
        "coordinates": [
          14.242723,
          41.37022
        ]
      },
      "id": "osm-location-of-raviscanina",
      "type": "Feature",
      "properties": {
        "description": "Location based on OpenStreetMap",
        "location_precision": "precise",
        "title": "OSM location of Raviscanina",
        "link": "http://pleiades.stoa.org/places/149580279/osm-location-of-raviscanina"
      }
    }
  ]
}