{
  "type": "FeatureCollection",
  "title": "Roman amphitheater at *Moridunum",
  "id": "153271174",
  "bbox": [
    -4.2965029,
    51.8619809,
    -4.2965029,
    51.8619809
  ],
  "description": "The Roman amphitheater at Moridunum is located in Carmarthenshire. It is one of only seven surviving Roman amphitheaters in Britain.",
  "connectsWith": [
    "79602"
  ],
  "features": [
    {
      "type": "Feature",
      "geometry": {
        "type": "Point",
        "coordinates": [
          -4.2965029,
          51.8619809
        ]
      },
      "properties": {
        "description": "representative point"
      }
    },
    {
      "geometry": {
        "type": "Point",
        "coordinates": [
          -4.2965029,
          51.8619809
        ]
      },
      "id": "location-of-roman-amphitheater",
      "type": "Feature",
      "properties": {
        "description": "Representative location based on OpenStreetMap.",
        "location_precision": "precise",
        "title": "OSM location of Roman amphitheater",
        "link": "http://pleiades.stoa.org/places/153271174/location-of-roman-amphitheater"
      }
    }
  ]
}