{
  "type": "FeatureCollection",
  "title": "Roman villa at West Mersea",
  "id": "155499663",
  "bbox": [
    0.917361,
    51.7769754,
    0.917361,
    51.7769754
  ],
  "description": "Remains of a tessellated floor pavement likely indicate the presence of a villa.",
  "connectsWith": [
    "490598212"
  ],
  "features": [
    {
      "type": "Feature",
      "geometry": {
        "type": "Point",
        "coordinates": [
          0.917361,
          51.7769754
        ]
      },
      "properties": {
        "description": "representative point"
      }
    },
    {
      "geometry": {
        "type": "Point",
        "coordinates": [
          0.917361,
          51.7769754
        ]
      },
      "id": "osm-location-of-west-mersea",
      "type": "Feature",
      "properties": {
        "description": "Location of the modern community based on a node derived from OpenStreetMap.",
        "location_precision": "precise",
        "title": "OSM location of West Mersea",
        "link": "http://pleiades.stoa.org/places/155499663/osm-location-of-west-mersea"
      }
    }
  ]
}