{
  "type": "FeatureCollection",
  "title": "Roman amphitheater at Tusculum",
  "id": "157403317",
  "bbox": [
    12.7022019,
    41.7983281,
    12.7022019,
    41.7983281
  ],
  "description": "Today the Roman amphitheater at Tusculum is poorly preserved. These ruins have never been systematically investigated.",
  "connectsWith": [
    "423108"
  ],
  "features": [
    {
      "type": "Feature",
      "geometry": {
        "type": "Point",
        "coordinates": [
          12.7022019,
          41.7983281
        ]
      },
      "properties": {
        "description": "representative point"
      }
    },
    {
      "geometry": {
        "type": "Point",
        "coordinates": [
          12.7022019,
          41.7983281
        ]
      },
      "id": "location-of-roman-amphitheater",
      "type": "Feature",
      "properties": {
        "description": "Representative location based on OpenStreetMap.",
        "location_precision": "precise",
        "title": "OSM location of Roman amphitheater",
        "link": "http://pleiades.stoa.org/places/157403317/location-of-roman-amphitheater"
      }
    }
  ]
}