{
  "type": "FeatureCollection",
  "title": "Monument near Ghirza",
  "id": "157793747",
  "bbox": [
    14.582482,
    30.998355,
    14.582482,
    30.998355
  ],
  "description": "A monument near the modern site of Ghirza",
  "connectsWith": [
    "344376"
  ],
  "features": [
    {
      "type": "Feature",
      "geometry": {
        "type": "Point",
        "coordinates": [
          14.582482,
          30.998355
        ]
      },
      "properties": {
        "description": "representative point"
      }
    },
    {
      "geometry": {
        "type": "Point",
        "coordinates": [
          14.582482,
          30.998355
        ]
      },
      "id": "darmc-location-33625",
      "type": "Feature",
      "properties": {
        "description": "representative point location digitized from the Barrington Atlas of the Greek and Roman World by the Digital Atlas of Roman and Medieval Civilizations project at Harvard University.",
        "location_precision": "precise",
        "title": "DARMC location 33625",
        "link": "http://pleiades.stoa.org/places/157793747/darmc-location-33625"
      }
    }
  ]
}