{
  "type": "FeatureCollection",
  "title": "Monument near Ghirza",
  "id": "157793747",
  "description": "A monument near the modern site of Ghirza",
  "bbox": [
    14.582482,
    30.998355,
    14.582482,
    30.998355
  ],
  "reprPoint": [
    14.582482,
    30.998355
  ],
  "features": [
    {
      "geometry": {
        "type": "Point",
        "coordinates": [
          14.582482,
          30.998355
        ]
      },
      "id": "darmc-location-33625",
      "type": "Feature",
      "properties": {
        "description": "scale point location",
        "location_precision": "precise",
        "title": "DARMC location 33625",
        "link": "http://pleiades.stoa.org/places/157793747/darmc-location-33625"
      }
    }
  ]
}