{
  "type": "FeatureCollection",
  "title": "Unnamed villa at Costebelle",
  "id": "157838",
  "description": "A Roman-era villa at modern Costebelle (commune Hyères) in France: BAtlas 16 B3 Costebelle",
  "bbox": [
    6.121322,
    43.103084,
    6.121322,
    43.103084
  ],
  "reprPoint": [
    6.121322,
    43.103084
  ],
  "features": [
    {
      "geometry": {
        "type": "Point",
        "coordinates": [
          6.121322,
          43.103084
        ]
      },
      "id": "location-of-costebelle-commune-hyeres",
      "type": "Feature",
      "properties": {
        "description": null,
        "location_precision": "precise",
        "title": "Location of Costebelle, commune Hyères",
        "link": "http://pleiades.stoa.org/places/157838/location-of-costebelle-commune-hyeres"
      }
    }
  ]
}