{
  "type": "FeatureCollection",
  "title": "Bordighera",
  "id": "157823",
  "description": "An ancient place, cited: BAtlas 16 E2 Bordighera",
  "bbox": [
    7.66083,
    43.779807,
    7.66083,
    43.779807
  ],
  "reprPoint": [
    7.66083,
    43.779807
  ],
  "features": [
    {
      "geometry": {
        "type": "Point",
        "coordinates": [
          7.66083,
          43.779807
        ]
      },
      "id": "darmc-location-23715",
      "type": "Feature",
      "properties": {
        "description": "Point location",
        "location_precision": "precise",
        "title": "DARMC location 23715",
        "link": "http://pleiades.stoa.org/places/157823/darmc-location-23715"
      }
    }
  ]
}