{
  "type": "FeatureCollection",
  "title": "Le Candéou",
  "id": "157833",
  "bbox": [
    6.87945,
    43.62179,
    6.87945,
    43.62179
  ],
  "description": "An ancient place, cited: BAtlas 16 C2 Le Candéou",
  "features": [
    {
      "type": "Feature",
      "geometry": {
        "type": "Point",
        "coordinates": [
          6.87945,
          43.62179
        ]
      },
      "properties": {
        "description": "representative point"
      }
    },
    {
      "geometry": {
        "type": "Point",
        "coordinates": [
          6.87945,
          43.62179
        ]
      },
      "id": "dare-location-of-modern-le-candeou",
      "type": "Feature",
      "properties": {
        "description": "Coordinates of the modern locality from DARE. Verified in Google Earth.",
        "location_precision": "precise",
        "title": "DARE Location of Modern Le Candéou",
        "link": "http://pleiades.stoa.org/places/157833/dare-location-of-modern-le-candeou"
      }
    }
  ]
}