{
  "type": "FeatureCollection",
  "title": "Costa Bellene/Ballene (Capo Don?)",
  "id": "157837",
  "description": "A Roman mansio on the via Iulia Augusta and Early Christian church.",
  "bbox": [
    7.862982,
    43.833884,
    7.862982,
    43.833884
  ],
  "connectsWith": [
    "507729266",
    "157879",
    "157802"
  ],
  "reprPoint": [
    7.862982,
    43.833884
  ],
  "names": [
    "Costa Bellene",
    "Costa Ballene",
    "Costa Balenae"
  ],
  "features": [
    {
      "geometry": {
        "type": "Point",
        "coordinates": [
          7.862982,
          43.833884
        ]
      },
      "id": "capo-don",
      "type": "Feature",
      "properties": {
        "description": "The place where archaeologists have tentatively identified the ancient Costa Balenae/Bellene.",
        "location_precision": "precise",
        "title": "Capo Don",
        "link": "http://pleiades.stoa.org/places/157837/capo-don"
      }
    }
  ]
}