{
  "type": "FeatureCollection",
  "title": "Costa Bellene/Ballene (Capo Don?)",
  "id": "157837",
  "description": "A Roman mansio on the via Iulia Augusta. An Early Christian complex (basilica, baptistery, cemetery) developed nearby and lasted until the Middle Ages.",
  "bbox": [
    7.862982,
    43.833884,
    7.8676571,
    43.8356046
  ],
  "connectsWith": [
    "819ed1224143949d322000da40c8bc88",
    "a0e6ff2bf6990d52ed57bf8a641f8ebe",
    "041464df5ceda504a78a496f91e75dbd"
  ],
  "reprPoint": [
    7.86531955,
    43.8347443
  ],
  "names": [
    "Costa Bellene",
    "Costa Ballene",
    "Costa Balenae"
  ],
  "features": [
    {
      "geometry": {
        "type": "Point",
        "coordinates": [
          7.862982,
          43.833884
        ]
      },
      "id": "capo-don",
      "type": "Feature",
      "properties": {
        "description": "The place where archaeologists have tentatively identified the ancient Costa Balenae/Bellene.",
        "location_precision": "precise",
        "title": "Capo Don",
        "link": "http://pleiades.stoa.org/places/157837/capo-don"
      }
    },
    {
      "geometry": {
        "type": "Point",
        "coordinates": [
          7.8676571,
          43.8356046
        ]
      },
      "id": "costa-balenae-archaeological-area",
      "type": "Feature",
      "properties": {
        "description": "Remains of Early Christian baptistery and church. Location based on OpenStreetMap",
        "location_precision": "precise",
        "title": "Costa Balenae archaeological area",
        "link": "http://pleiades.stoa.org/places/157837/costa-balenae-archaeological-area"
      }
    }
  ]
}