{
  "type": "FeatureCollection",
  "title": "Navelis",
  "id": "157891",
  "bbox": [
    7.28351,
    43.725031,
    7.28351,
    43.725031
  ],
  "description": "An ancient place, cited: BAtlas 16 D2 Navelis",
  "names": [
    "Navelis"
  ],
  "features": [
    {
      "type": "Feature",
      "geometry": {
        "type": "Point",
        "coordinates": [
          7.28351,
          43.725031
        ]
      },
      "properties": {
        "description": "representative point"
      }
    },
    {
      "geometry": {
        "type": "Point",
        "coordinates": [
          7.28351,
          43.725031
        ]
      },
      "id": "darmc-location-5531",
      "type": "Feature",
      "properties": {
        "description": "500K scale point location",
        "location_precision": "precise",
        "title": "DARMC location 5531",
        "link": "http://pleiades.stoa.org/places/157891/darmc-location-5531"
      }
    }
  ]
}