{
  "type": "FeatureCollection",
  "title": "Lero (island)",
  "id": "157874",
  "bbox": [
    7.049411,
    43.5194059,
    7.049411,
    43.5194059
  ],
  "description": "An ancient place, cited: BAtlas 16 D2 Lero Ins.",
  "names": [
    "Lero"
  ],
  "features": [
    {
      "type": "Feature",
      "geometry": {
        "type": "Point",
        "coordinates": [
          7.049411,
          43.5194059
        ]
      },
      "properties": {
        "description": "representative point"
      }
    },
    {
      "geometry": {
        "type": "Point",
        "coordinates": [
          7.049411,
          43.5194059
        ]
      },
      "id": "centerpoint-of-ile-sainte-marguerite",
      "type": "Feature",
      "properties": {
        "description": null,
        "location_precision": "precise",
        "title": "Centerpoint of Île Sainte-Marguerite",
        "link": "http://pleiades.stoa.org/places/157874/centerpoint-of-ile-sainte-marguerite"
      }
    }
  ]
}