{
  "type": "FeatureCollection",
  "title": "Le Candéou",
  "id": "157833",
  "description": "An ancient place, cited: BAtlas 16 C2 Le Candéou",
  "bbox": [
    6.878874,
    43.630027,
    6.878874,
    43.630027
  ],
  "reprPoint": [
    6.878874,
    43.630027
  ],
  "features": [
    {
      "geometry": {
        "type": "Point",
        "coordinates": [
          6.878874,
          43.630027
        ]
      },
      "id": "darmc-location-17496",
      "type": "Feature",
      "properties": {
        "description": "500K scale point location",
        "location_precision": "precise",
        "title": "DARMC location 17496",
        "link": "http://pleiades.stoa.org/places/157833/darmc-location-17496"
      }
    }
  ]
}