{
  "type": "FeatureCollection",
  "title": "Sanremo",
  "id": "157924",
  "bbox": [
    7.759577,
    43.808196,
    7.778383,
    43.818292
  ],
  "description": "An ancient place, cited: BAtlas 16 E2 Sanremo",
  "names": [
    "Villa Matuciana"
  ],
  "features": [
    {
      "type": "Feature",
      "geometry": {
        "type": "Point",
        "coordinates": [
          7.76898,
          43.813244
        ]
      },
      "properties": {
        "description": "representative point"
      }
    },
    {
      "geometry": {
        "type": "Point",
        "coordinates": [
          7.778383,
          43.818292
        ]
      },
      "id": "darmc-location-17585",
      "type": "Feature",
      "properties": {
        "description": "500K scale point location",
        "location_precision": "precise",
        "title": "DARMC location 17585",
        "link": "http://pleiades.stoa.org/places/157924/darmc-location-17585"
      }
    },
    {
      "geometry": {
        "type": "Point",
        "coordinates": [
          7.759577,
          43.808196
        ]
      },
      "id": "villa-romana-della-foce",
      "type": "Feature",
      "properties": {
        "description": "Coordinates after GeoHack, verified in Google Earth.",
        "location_precision": "precise",
        "title": "Imagery location of Villa romana della Foce",
        "link": "http://pleiades.stoa.org/places/157924/villa-romana-della-foce"
      }
    }
  ]
}