{
  "type": "FeatureCollection",
  "title": "La Trinité",
  "id": "157938",
  "description": "An ancient place, cited: BAtlas 16 C2 La Trinité",
  "bbox": [
    6.552252,
    43.57211,
    6.552252,
    43.57211
  ],
  "reprPoint": [
    6.552252,
    43.57211
  ],
  "features": [
    {
      "geometry": {
        "type": "Point",
        "coordinates": [
          6.552252,
          43.57211
        ]
      },
      "id": "darmc-location-17490",
      "type": "Feature",
      "properties": {
        "description": "500K scale point location",
        "location_precision": "precise",
        "title": "DARMC location 17490",
        "link": "http://pleiades.stoa.org/places/157938/darmc-location-17490"
      }
    }
  ]
}