{
  "type": "FeatureCollection",
  "title": "Roussivau",
  "id": "157915",
  "bbox": [
    6.845027,
    43.47388,
    6.845027,
    43.47388
  ],
  "description": "An ancient place, cited: BAtlas 16 C3 Roussivau",
  "features": [
    {
      "type": "Feature",
      "geometry": {
        "type": "Point",
        "coordinates": [
          6.845027,
          43.47388
        ]
      },
      "properties": {
        "description": "representative point"
      }
    },
    {
      "geometry": {
        "type": "Point",
        "coordinates": [
          6.845027,
          43.47388
        ]
      },
      "id": "darmc-location-17575",
      "type": "Feature",
      "properties": {
        "description": "500K scale point location",
        "location_precision": "precise",
        "title": "DARMC location 17575",
        "link": "http://pleiades.stoa.org/places/157915/darmc-location-17575"
      }
    }
  ]
}