{
  "type": "FeatureCollection",
  "title": "St-Michel",
  "id": "157919",
  "description": "An ancient place, cited: BAtlas 16 B3 St-Michel",
  "bbox": [
    6.038716,
    43.182771,
    6.038716,
    43.182771
  ],
  "reprPoint": [
    6.038716,
    43.182771
  ],
  "features": [
    {
      "geometry": {
        "type": "Point",
        "coordinates": [
          6.038716,
          43.182771
        ]
      },
      "id": "darmc-location-16844",
      "type": "Feature",
      "properties": {
        "description": "500K scale point location",
        "location_precision": "precise",
        "title": "DARMC location 16844",
        "link": "http://pleiades.stoa.org/places/157919/darmc-location-16844"
      }
    }
  ]
}