{
  "type": "FeatureCollection",
  "title": "Circus Flaminius",
  "id": "158081395",
  "bbox": [
    12.486137,
    41.891775,
    12.486137,
    41.891775
  ],
  "description": "Located in the southern Campus Martius, the Circus Flaminius is a large area built by C. Flaminius Nepos in 221 B.C. Various games, including the ludi plebeii, ludi Taurii, ludi saeculares, were celebrated here. The circus was also a place of popular assembly.",
  "connectsWith": [
    "423025",
    "72845305"
  ],
  "names": [
    "circus Flaminius"
  ],
  "features": [
    {
      "type": "Feature",
      "geometry": {
        "type": "Point",
        "coordinates": [
          12.486137,
          41.891775
        ]
      },
      "properties": {
        "description": "representative point"
      }
    }
  ]
}