{
  "type": "FeatureCollection",
  "title": "Circus Flaminius",
  "id": "158081395",
  "bbox": [
    12.4783033,
    41.8911116,
    12.4803659,
    41.8927174
  ],
  "description": "Located in the southern Campus Martius, the Circus Flaminius is a large area built by C. Flaminius Nepos in 221 B.C. Various games, including the ludi plebeii, ludi Taurii, ludi saeculares, were celebrated here. The circus was also a place of popular assembly.",
  "connectsWith": [
    "423025",
    "72845305",
    "936873471"
  ],
  "names": [
    "circus Flaminius",
    "Circo Flaminio"
  ],
  "features": [
    {
      "type": "Feature",
      "geometry": {
        "type": "Point",
        "coordinates": [
          12.4785726352,
          41.8925223042
        ]
      },
      "properties": {
        "description": "representative point"
      }
    }
  ]
}