{
  "type": "FeatureCollection",
  "title": "Surt",
  "id": "159615010",
  "bbox": [
    17.1023529,
    31.1303878,
    17.1023529,
    31.1303878
  ],
  "description": "Medieval Arab city, earlier the site of a Jewish colony established by Augustus, located 55km east of modern Sirte, Libya. The site may have been occupied between the Roman period and the Late Medieval period, but this is not certain.",
  "connectsWith": [
    "1043",
    "363959"
  ],
  "features": [
    {
      "type": "Feature",
      "geometry": {
        "type": "Point",
        "coordinates": [
          17.1023529,
          31.1303878
        ]
      },
      "properties": {
        "description": "representative point"
      }
    },
    {
      "geometry": {
        "type": "Point",
        "coordinates": [
          17.1023529,
          31.1303878
        ]
      },
      "id": "surt",
      "type": "Feature",
      "properties": {
        "description": "Point based on an OpenStreetMap node representing Surt after Mouton 2012.",
        "location_precision": "precise",
        "title": "OSM location of Surt",
        "link": "http://pleiades.stoa.org/places/159615010/surt"
      }
    }
  ]
}