{
  "type": "FeatureCollection",
  "title": "Odeion at Sagalassos",
  "id": "160453231",
  "bbox": [
    30.5184978,
    37.676264,
    30.5184978,
    37.676264
  ],
  "description": "The Odeion at Sagalassos occupies a terrace that is north of the Lower Agora and downslope from the Upper Agora.",
  "connectsWith": [
    "639087"
  ],
  "features": [
    {
      "type": "Feature",
      "geometry": {
        "type": "Point",
        "coordinates": [
          30.5184978,
          37.676264
        ]
      },
      "properties": {
        "description": "representative point"
      }
    },
    {
      "geometry": {
        "type": "Point",
        "coordinates": [
          30.5184978,
          37.676264
        ]
      },
      "id": "osm-location-of-odeion",
      "type": "Feature",
      "properties": {
        "description": "Location based on OpenStreetMap",
        "location_precision": "precise",
        "title": "OSM location of odeion",
        "link": "http://pleiades.stoa.org/places/160453231/osm-location-of-odeion"
      }
    }
  ]
}