{
  "type": "FeatureCollection",
  "title": "Studforth Hill",
  "id": "160823659",
  "bbox": [
    -1.3796296,
    54.0881157,
    -1.3796296,
    54.0881157
  ],
  "description": "The remains of a Romano-British amphitheater were discovered on Studforth Hill, just outside the village of Aldborough between Harrogate and York in northern England.",
  "connectsWith": [
    "89209"
  ],
  "features": [
    {
      "type": "Feature",
      "geometry": {
        "type": "Point",
        "coordinates": [
          -1.3796296,
          54.0881157
        ]
      },
      "properties": {
        "description": "representative point"
      }
    },
    {
      "geometry": {
        "type": "Point",
        "coordinates": [
          -1.3796296,
          54.0881157
        ]
      },
      "id": "osm-location-of-studforth-hill",
      "type": "Feature",
      "properties": {
        "description": "Representative location based on OpenStreetMap",
        "location_precision": "precise",
        "title": "OSM location of Studforth Hill",
        "link": "http://pleiades.stoa.org/places/160823659/osm-location-of-studforth-hill"
      }
    }
  ]
}