{
  "type": "FeatureCollection",
  "title": "Unnamed monastery",
  "id": "160817",
  "bbox": [
    7.047285,
    43.506577,
    7.047285,
    43.506577
  ],
  "description": "A monastery founded in late antiquity on the island then known as Lerina/Planasia (modern Île Saint-Honorat, France; BAtlas 16 D2 unnamed monastery)",
  "connectsWith": [
    "157906"
  ],
  "features": [
    {
      "type": "Feature",
      "geometry": {
        "type": "Point",
        "coordinates": [
          7.047285,
          43.506577
        ]
      },
      "properties": {
        "description": "representative point"
      }
    },
    {
      "geometry": {
        "type": "Point",
        "coordinates": [
          7.047285,
          43.506577
        ]
      },
      "id": "abbaye-de-lerins-ile-saint-honorat",
      "type": "Feature",
      "properties": {
        "description": null,
        "location_precision": "precise",
        "title": "Abbaye de Lérins, Île Saint-Honorat",
        "link": "http://pleiades.stoa.org/places/160817/abbaye-de-lerins-ile-saint-honorat"
      }
    }
  ]
}