{
  "type": "FeatureCollection",
  "title": "Haurina",
  "id": "161546548",
  "bbox": [
    37.078065,
    34.2691848,
    37.078065,
    34.2691848
  ],
  "description": "A town mentioned in Neo-Assyrian sources; the modern site is Ḥawārīn.",
  "names": [
    "Ḥawārīn",
    "Hāurīna"
  ],
  "features": [
    {
      "type": "Feature",
      "geometry": {
        "type": "Point",
        "coordinates": [
          37.078065,
          34.2691848
        ]
      },
      "properties": {
        "description": "representative point"
      }
    },
    {
      "geometry": {
        "type": "Point",
        "coordinates": [
          37.078065,
          34.2691848
        ]
      },
      "id": "osm-location-of-hawarin",
      "type": "Feature",
      "properties": {
        "description": "Location based on OpenStreetMap",
        "location_precision": "precise",
        "title": "OSM location of Hawarin",
        "link": "http://pleiades.stoa.org/places/161546548/osm-location-of-hawarin"
      }
    }
  ]
}