{
  "type": "FeatureCollection",
  "title": "Marble Quarries at Karystos",
  "id": "163292061",
  "bbox": [
    24.4469025,
    38.0377,
    24.4469025,
    38.0377
  ],
  "description": "A complex quarry landscape near Karystos, heavily exploited especially in Roman times, for highly prized Cipollino Verde (marmor Carystium).",
  "connectsWith": [
    "570336"
  ],
  "features": [
    {
      "type": "Feature",
      "geometry": {
        "type": "Point",
        "coordinates": [
          24.4469025,
          38.0377
        ]
      },
      "properties": {
        "description": "representative point"
      }
    },
    {
      "geometry": {
        "type": "Point",
        "coordinates": [
          24.4469025,
          38.0377
        ]
      },
      "id": "osm-location-roman-quarry",
      "type": "Feature",
      "properties": {
        "description": "Location based on OpenStreetMap",
        "location_precision": "precise",
        "title": "OSM Location: Roman Quarry",
        "link": "http://pleiades.stoa.org/places/163292061/osm-location-roman-quarry"
      }
    }
  ]
}