{
  "type": "FeatureCollection",
  "title": "Untitled",
  "id": "164618019",
  "bbox": [
    21.239923,
    42.591446,
    21.239923,
    42.591446
  ],
  "description": "Unlabeled feature captured from the Barrington Atlas",
  "connectsWith": [
    "209142"
  ],
  "features": [
    {
      "type": "Feature",
      "geometry": {
        "type": "Point",
        "coordinates": [
          21.239923,
          42.591446
        ]
      },
      "properties": {
        "description": "representative point"
      }
    },
    {
      "geometry": {
        "type": "Point",
        "coordinates": [
          21.239923,
          42.591446
        ]
      },
      "id": "darmc-location-18812",
      "type": "Feature",
      "properties": {
        "description": "1M scale point location",
        "location_precision": "precise",
        "title": "DARMC location 18812",
        "link": "http://pleiades.stoa.org/places/164618019/darmc-location-18812"
      }
    }
  ]
}