{
  "type": "FeatureCollection",
  "title": "Untitled",
  "id": "164618009",
  "description": "Unlabeled feature captured from the Barrington Atlas",
  "bbox": [
    21.417919,
    42.578415,
    21.417919,
    42.578415
  ],
  "reprPoint": [
    21.417919,
    42.578415
  ],
  "features": [
    {
      "geometry": {
        "type": "Point",
        "coordinates": [
          21.417919,
          42.578415
        ]
      },
      "id": "darmc-location-18811",
      "type": "Feature",
      "properties": {
        "description": "1M scale point location",
        "location_precision": "precise",
        "title": "DARMC location 18811",
        "link": "http://pleiades.stoa.org/places/164618009/darmc-location-18811"
      }
    }
  ]
}