{
  "type": "FeatureCollection",
  "title": "Untitled",
  "id": "164618018",
  "description": "Unlabeled feature captured from the Barrington Atlas",
  "bbox": [
    22.728468,
    46.174621,
    22.728468,
    46.174621
  ],
  "reprPoint": [
    22.728468,
    46.174621
  ],
  "features": [
    {
      "geometry": {
        "type": "Point",
        "coordinates": [
          22.728468,
          46.174621
        ]
      },
      "id": "darmc-location-18773",
      "type": "Feature",
      "properties": {
        "description": "1M scale point location",
        "location_precision": "precise",
        "title": "DARMC location 18773",
        "link": "http://pleiades.stoa.org/places/164618018/darmc-location-18773"
      }
    }
  ]
}