{
  "type": "FeatureCollection",
  "title": "Untitled",
  "id": "164618008",
  "bbox": [
    19.245141,
    44.448828,
    19.245141,
    44.448828
  ],
  "description": "Unlabeled feature captured from the Barrington Atlas",
  "connectsWith": [
    "207245"
  ],
  "features": [
    {
      "type": "Feature",
      "geometry": {
        "type": "Point",
        "coordinates": [
          19.245141,
          44.448828
        ]
      },
      "properties": {
        "description": "representative point"
      }
    },
    {
      "geometry": {
        "type": "Point",
        "coordinates": [
          19.245141,
          44.448828
        ]
      },
      "id": "darmc-location-18759",
      "type": "Feature",
      "properties": {
        "description": "1M scale point location",
        "location_precision": "precise",
        "title": "DARMC location 18759",
        "link": "http://pleiades.stoa.org/places/164618008/darmc-location-18759"
      }
    }
  ]
}