{
  "type": "FeatureCollection",
  "title": "Saint-Sernin-sur-Rance",
  "id": "165170193",
  "bbox": [
    2.6034391,
    43.8723055,
    2.6363035,
    43.8847922
  ],
  "description": "Remains of a rustic temple and a menhir were discovered in the early 1960s near Boutaran.",
  "features": [
    {
      "type": "Feature",
      "geometry": {
        "type": "Point",
        "coordinates": [
          2.6198713,
          43.87854885
        ]
      },
      "properties": {
        "description": "representative point"
      }
    },
    {
      "geometry": {
        "type": "Point",
        "coordinates": [
          2.6034391,
          43.8847922
        ]
      },
      "id": "saint-sernin-sur-rance",
      "type": "Feature",
      "properties": {
        "description": "Representative location based on OpenStreetMap.",
        "location_precision": "precise",
        "title": "OSM location of Saint-Sernin-sur-Rance",
        "link": "http://pleiades.stoa.org/places/165170193/saint-sernin-sur-rance"
      }
    },
    {
      "geometry": {
        "type": "Point",
        "coordinates": [
          2.6363035,
          43.8723055
        ]
      },
      "id": "boutaran",
      "type": "Feature",
      "properties": {
        "description": "Representative location based on OpenStreetMap.",
        "location_precision": "precise",
        "title": "OSM location of Boutaran",
        "link": "http://pleiades.stoa.org/places/165170193/boutaran"
      }
    }
  ]
}