{
  "type": "FeatureCollection",
  "title": "Chauvet Cave",
  "id": "165753155",
  "bbox": [
    4.4161408,
    44.3881219,
    4.4161408,
    44.3881219
  ],
  "description": "The Chauvet-Pont-d'Arc Cave in southern France contains the earliest known and best preserved figurative cave paintings in the world, dating from the Upper Paleolithic. The cave was discovered on December 18, 1994, and was added to the UNESCO World Heritage List on June 22, 2014.",
  "features": [
    {
      "type": "Feature",
      "geometry": {
        "type": "Point",
        "coordinates": [
          4.4161408,
          44.3881219
        ]
      },
      "properties": {
        "description": "representative point"
      }
    },
    {
      "geometry": {
        "type": "Point",
        "coordinates": [
          4.4161408,
          44.3881219
        ]
      },
      "id": "osm-location",
      "type": "Feature",
      "properties": {
        "description": "Representative location based on OpenStreetMap.",
        "location_precision": "precise",
        "title": "OSM location of Chauvet Cave",
        "link": "http://pleiades.stoa.org/places/165753155/osm-location"
      }
    }
  ]
}