{
  "type": "FeatureCollection",
  "title": "Choga Mami",
  "id": "166031522",
  "bbox": [
    45.4499786,
    33.8833361,
    45.4499786,
    33.8833361
  ],
  "description": "Choga Mami was a Samarran settlement located in what is now the Diyala province of Southern Iraq. The site originates in the sixth millennium B.C.",
  "features": [
    {
      "type": "Feature",
      "geometry": {
        "type": "Point",
        "coordinates": [
          45.4499786,
          33.8833361
        ]
      },
      "properties": {
        "description": "representative point"
      }
    },
    {
      "geometry": {
        "type": "Point",
        "coordinates": [
          45.4499786,
          33.8833361
        ]
      },
      "id": "osm-location-of-choga-mami",
      "type": "Feature",
      "properties": {
        "description": "Representative location based on OpenStreetMap.",
        "location_precision": "precise",
        "title": "OSM location of Choga Mami",
        "link": "http://pleiades.stoa.org/places/166031522/osm-location-of-choga-mami"
      }
    }
  ]
}