{
  "type": "FeatureCollection",
  "title": "Roman villa at Híjar en Las Gabias",
  "id": "167120129",
  "bbox": [
    -3.6768336,
    37.1500887,
    -3.6768336,
    37.1500887
  ],
  "description": "A Roman villa, of which the pars fructuaria has been excavated.",
  "features": [
    {
      "type": "Feature",
      "geometry": {
        "type": "Point",
        "coordinates": [
          -3.6768336,
          37.1500887
        ]
      },
      "properties": {
        "description": "representative point"
      }
    },
    {
      "geometry": {
        "type": "Point",
        "coordinates": [
          -3.6768336,
          37.1500887
        ]
      },
      "id": "osm-location-of-modern-hajar",
      "type": "Feature",
      "properties": {
        "description": "Location based on OpenStreetMap",
        "location_precision": "precise",
        "title": "OSM location of modern Híjar",
        "link": "http://pleiades.stoa.org/places/167120129/osm-location-of-modern-hajar"
      }
    }
  ]
}