{
  "type": "FeatureCollection",
  "title": "Aquae Segetae",
  "id": "167649",
  "bbox": [
    4.070241,
    45.591571,
    4.072211,
    45.592393
  ],
  "description": "An ancient place, cited: BAtlas 17 C2 Aquae Segetae",
  "names": [
    "Aquae Segetae"
  ],
  "features": [
    {
      "type": "Feature",
      "geometry": {
        "type": "Point",
        "coordinates": [
          4.071226,
          45.591982
        ]
      },
      "properties": {
        "description": "representative point"
      }
    },
    {
      "geometry": {
        "type": "Point",
        "coordinates": [
          4.072211,
          45.592393
        ]
      },
      "id": "darmc-location-1611",
      "type": "Feature",
      "properties": {
        "description": "500K scale point location",
        "location_precision": "precise",
        "title": "DARMC location 1611",
        "link": "http://pleiades.stoa.org/places/167649/darmc-location-1611"
      }
    },
    {
      "geometry": {
        "type": "Point",
        "coordinates": [
          4.070241,
          45.591571
        ]
      },
      "id": "dare-location",
      "type": "Feature",
      "properties": {
        "description": "Representative point location, site precision",
        "location_precision": "precise",
        "title": "DARE Location",
        "link": "http://pleiades.stoa.org/places/167649/dare-location"
      }
    }
  ]
}