{
  "type": "FeatureCollection",
  "title": "Beaune-sur-Arzon",
  "id": "167672",
  "description": "An ancient place, cited: BAtlas 17 B3 Beaune-sur-Arzon",
  "bbox": [
    3.815973,
    45.279466,
    3.815973,
    45.279466
  ],
  "reprPoint": [
    3.815973,
    45.279466
  ],
  "features": [
    {
      "geometry": {
        "type": "Point",
        "coordinates": [
          3.815973,
          45.279466
        ]
      },
      "id": "darmc-location-17241",
      "type": "Feature",
      "properties": {
        "description": "500K scale point location",
        "location_precision": "precise",
        "title": "DARMC location 17241",
        "link": "http://pleiades.stoa.org/places/167672/darmc-location-17241"
      }
    }
  ]
}