{
  "type": "FeatureCollection",
  "title": "Auris",
  "id": "167661",
  "bbox": [
    6.086561,
    45.046309,
    6.086561,
    45.046309
  ],
  "description": "An ancient place, cited: BAtlas 17 G3 Auris",
  "features": [
    {
      "type": "Feature",
      "geometry": {
        "type": "Point",
        "coordinates": [
          6.086561,
          45.046309
        ]
      },
      "properties": {
        "description": "representative point"
      }
    },
    {
      "geometry": {
        "type": "Point",
        "coordinates": [
          6.086561,
          45.046309
        ]
      },
      "id": "darmc-location-7237",
      "type": "Feature",
      "properties": {
        "description": "500K scale point location",
        "location_precision": "precise",
        "title": "DARMC location 7237",
        "link": "http://pleiades.stoa.org/places/167661/darmc-location-7237"
      }
    }
  ]
}