{
  "type": "FeatureCollection",
  "title": "Andance",
  "id": "167644",
  "bbox": [
    4.799028,
    45.241016,
    4.799028,
    45.241016
  ],
  "description": "An ancient place, cited: BAtlas 17 D3 Andance",
  "names": [
    "Andance"
  ],
  "features": [
    {
      "type": "Feature",
      "geometry": {
        "type": "Point",
        "coordinates": [
          4.799028,
          45.241016
        ]
      },
      "properties": {
        "description": "representative point"
      }
    },
    {
      "geometry": {
        "type": "Point",
        "coordinates": [
          4.799028,
          45.241016
        ]
      },
      "id": "darmc-location-15856",
      "type": "Feature",
      "properties": {
        "description": "500K scale point location",
        "location_precision": "precise",
        "title": "DARMC location 15856",
        "link": "http://pleiades.stoa.org/places/167644/darmc-location-15856"
      }
    }
  ]
}