{
  "type": "FeatureCollection",
  "title": "Batiana",
  "id": "167668",
  "description": "An ancient place, cited: BAtlas 17 D4 Batiana",
  "bbox": [
    4.886189,
    44.833654,
    4.886189,
    44.833654
  ],
  "reprPoint": [
    4.886189,
    44.833654
  ],
  "names": [
    "Batiana"
  ],
  "features": [
    {
      "geometry": {
        "type": "Point",
        "coordinates": [
          4.886189,
          44.833654
        ]
      },
      "id": "darmc-location-7982",
      "type": "Feature",
      "properties": {
        "description": "500K scale point location",
        "location_precision": "precise",
        "title": "DARMC location 7982",
        "link": "http://pleiades.stoa.org/places/167668/darmc-location-7982"
      }
    }
  ]
}