{
  "type": "FeatureCollection",
  "title": "Chessy-les-Mines",
  "id": "167712",
  "bbox": [
    4.606207,
    45.888836,
    4.606207,
    45.888836
  ],
  "description": "An ancient place, cited: BAtlas 17 D2 Chessy-les-Mines",
  "features": [
    {
      "type": "Feature",
      "geometry": {
        "type": "Point",
        "coordinates": [
          4.606207,
          45.888836
        ]
      },
      "properties": {
        "description": "representative point"
      }
    },
    {
      "geometry": {
        "type": "Point",
        "coordinates": [
          4.606207,
          45.888836
        ]
      },
      "id": "darmc-location-15649",
      "type": "Feature",
      "properties": {
        "description": "500K scale point location",
        "location_precision": "precise",
        "title": "DARMC location 15649",
        "link": "http://pleiades.stoa.org/places/167712/darmc-location-15649"
      }
    }
  ]
}