{
  "type": "FeatureCollection",
  "title": "Corlier",
  "id": "167726",
  "description": "An ancient place, cited: BAtlas 17 E1 Corlier",
  "bbox": [
    5.49861,
    46.03029,
    5.49861,
    46.03029
  ],
  "reprPoint": [
    5.49861,
    46.03029
  ],
  "features": [
    {
      "geometry": {
        "type": "Point",
        "coordinates": [
          5.49861,
          46.03029
        ]
      },
      "id": "darmc-location-15937",
      "type": "Feature",
      "properties": {
        "description": "500K scale point location",
        "location_precision": "precise",
        "title": "DARMC location 15937",
        "link": "http://pleiades.stoa.org/places/167726/darmc-location-15937"
      }
    }
  ]
}