{
  "type": "FeatureCollection",
  "title": "Fay",
  "id": "167763",
  "bbox": [
    5.671117,
    45.661997,
    5.671117,
    45.661997
  ],
  "description": "An ancient place, cited: BAtlas 17 F2 Fay",
  "features": [
    {
      "type": "Feature",
      "geometry": {
        "type": "Point",
        "coordinates": [
          5.671117,
          45.661997
        ]
      },
      "properties": {
        "description": "representative point"
      }
    },
    {
      "geometry": {
        "type": "Point",
        "coordinates": [
          5.671117,
          45.661997
        ]
      },
      "id": "darmc-location-7252",
      "type": "Feature",
      "properties": {
        "description": "500K scale point location",
        "location_precision": "precise",
        "title": "DARMC location 7252",
        "link": "http://pleiades.stoa.org/places/167763/darmc-location-7252"
      }
    }
  ]
}