{
  "type": "FeatureCollection",
  "title": "Labisco",
  "id": "167798",
  "bbox": [
    5.754422,
    45.436151,
    5.754422,
    45.436151
  ],
  "description": "An ancient place, cited: BAtlas 17 F3 Labisco",
  "names": [
    "Labisco"
  ],
  "features": [
    {
      "type": "Feature",
      "geometry": {
        "type": "Point",
        "coordinates": [
          5.754422,
          45.436151
        ]
      },
      "properties": {
        "description": "representative point"
      }
    },
    {
      "geometry": {
        "type": "Point",
        "coordinates": [
          5.754422,
          45.436151
        ]
      },
      "id": "darmc-location-6420",
      "type": "Feature",
      "properties": {
        "description": "500K scale point location",
        "location_precision": "precise",
        "title": "DARMC location 6420",
        "link": "http://pleiades.stoa.org/places/167798/darmc-location-6420"
      }
    }
  ]
}