{
  "type": "FeatureCollection",
  "title": "Darentiaca",
  "id": "167737",
  "bbox": [
    5.198998,
    44.696872,
    5.198998,
    44.696872
  ],
  "description": "An ancient place, cited: BAtlas 17 E4 Darentiaca",
  "names": [
    "Darentiaca"
  ],
  "features": [
    {
      "type": "Feature",
      "geometry": {
        "type": "Point",
        "coordinates": [
          5.198998,
          44.696872
        ]
      },
      "properties": {
        "description": "representative point"
      }
    },
    {
      "geometry": {
        "type": "Point",
        "coordinates": [
          5.198998,
          44.696872
        ]
      },
      "id": "darmc-location-8579",
      "type": "Feature",
      "properties": {
        "description": "500K scale point location",
        "location_precision": "precise",
        "title": "DARMC location 8579",
        "link": "http://pleiades.stoa.org/places/167737/darmc-location-8579"
      }
    }
  ]
}