{
  "type": "FeatureCollection",
  "title": "Flaviac",
  "id": "167767",
  "bbox": [
    4.673747,
    44.747032,
    4.673747,
    44.747032
  ],
  "description": "An ancient place, cited: BAtlas 17 D4 Flaviac",
  "features": [
    {
      "type": "Feature",
      "geometry": {
        "type": "Point",
        "coordinates": [
          4.673747,
          44.747032
        ]
      },
      "properties": {
        "description": "representative point"
      }
    },
    {
      "geometry": {
        "type": "Point",
        "coordinates": [
          4.673747,
          44.747032
        ]
      },
      "id": "darmc-location-7367",
      "type": "Feature",
      "properties": {
        "description": "500K scale point location",
        "location_precision": "precise",
        "title": "DARMC location 7367",
        "link": "http://pleiades.stoa.org/places/167767/darmc-location-7367"
      }
    }
  ]
}