{
  "type": "FeatureCollection",
  "title": "Crêt-Châtelard",
  "id": "167730",
  "description": "An ancient place, cited: BAtlas 17 C2 Crêt-Châtelard",
  "bbox": [
    4.135256,
    45.855278,
    4.140917,
    45.867224
  ],
  "reprPoint": [
    4.1380865,
    45.861251
  ],
  "features": [
    {
      "geometry": {
        "type": "Point",
        "coordinates": [
          4.140917,
          45.855278
        ]
      },
      "id": "center-point-of-oppidum-cret-du-chatelard-commune-saint-marcel-de-felines",
      "type": "Feature",
      "properties": {
        "description": null,
        "location_precision": "precise",
        "title": "Center point of oppidum Crêt du Châtelard, commune Saint-Marcel-de-Félines",
        "link": "http://pleiades.stoa.org/places/167730/center-point-of-oppidum-cret-du-chatelard-commune-saint-marcel-de-felines"
      }
    }
  ]
}