{
  "type": "FeatureCollection",
  "title": "Cordon",
  "id": "167725",
  "description": "An ancient place, cited: BAtlas 17 F2 Cordon",
  "bbox": [
    5.62964,
    45.625125,
    5.62964,
    45.625125
  ],
  "reprPoint": [
    5.62964,
    45.625125
  ],
  "features": [
    {
      "geometry": {
        "type": "Point",
        "coordinates": [
          5.62964,
          45.625125
        ]
      },
      "id": "darmc-location-7249",
      "type": "Feature",
      "properties": {
        "description": "500K scale point location",
        "location_precision": "precise",
        "title": "DARMC location 7249",
        "link": "http://pleiades.stoa.org/places/167725/darmc-location-7249"
      }
    }
  ]
}