{
  "type": "FeatureCollection",
  "title": "Portes",
  "id": "167874",
  "description": "An ancient place, cited: BAtlas 17 C5 Portes",
  "bbox": [
    4.021968,
    44.270084,
    4.021968,
    44.270084
  ],
  "reprPoint": [
    4.021968,
    44.270084
  ],
  "features": [
    {
      "geometry": {
        "type": "Point",
        "coordinates": [
          4.021968,
          44.270084
        ]
      },
      "id": "darmc-location-7390",
      "type": "Feature",
      "properties": {
        "description": "500K scale point location",
        "location_precision": "precise",
        "title": "DARMC location 7390",
        "link": "http://pleiades.stoa.org/places/167874/darmc-location-7390"
      }
    }
  ]
}