{
  "type": "FeatureCollection",
  "title": "Lemincum",
  "id": "167806",
  "description": "An ancient place, cited: BAtlas 17 F2 Lemincum",
  "bbox": [
    5.920743,
    45.566626,
    5.920858,
    45.566635
  ],
  "reprPoint": [
    5.9208005,
    45.5666305
  ],
  "names": [
    "Lemincum"
  ],
  "features": [
    {
      "geometry": {
        "type": "Point",
        "coordinates": [
          5.920858,
          45.566626
        ]
      },
      "id": "darmc-location-13454",
      "type": "Feature",
      "properties": {
        "description": "1M scale point location",
        "location_precision": "precise",
        "title": "DARMC location 13454",
        "link": "http://pleiades.stoa.org/places/167806/darmc-location-13454"
      }
    },
    {
      "geometry": {
        "type": "Point",
        "coordinates": [
          5.920743,
          45.566635
        ]
      },
      "id": "darmc-location-16688",
      "type": "Feature",
      "properties": {
        "description": "500K scale point location",
        "location_precision": "precise",
        "title": "DARMC location 16688",
        "link": "http://pleiades.stoa.org/places/167806/darmc-location-16688"
      }
    }
  ]
}