{
  "type": "FeatureCollection",
  "title": "Novem Craris",
  "id": "167856",
  "description": "An ancient place, cited: BAtlas 17 D5 Novem Craris",
  "bbox": [
    4.742201,
    44.41467,
    4.742201,
    44.41467
  ],
  "reprPoint": [
    4.742201,
    44.41467
  ],
  "names": [
    "Le Logis de Berre",
    "Novem Craris"
  ],
  "features": [
    {
      "geometry": {
        "type": "Point",
        "coordinates": [
          4.742201,
          44.41467
        ]
      },
      "id": "darmc-location-8921",
      "type": "Feature",
      "properties": {
        "description": "500K scale point location",
        "location_precision": "precise",
        "title": "DARMC location 8921",
        "link": "http://pleiades.stoa.org/places/167856/darmc-location-8921"
      }
    }
  ]
}