{
  "type": "FeatureCollection",
  "title": "Passy",
  "id": "167866",
  "bbox": [
    6.686031,
    45.92345,
    6.686031,
    45.92345
  ],
  "description": "An ancient place, cited: BAtlas 17 H2 Passy",
  "features": [
    {
      "type": "Feature",
      "geometry": {
        "type": "Point",
        "coordinates": [
          6.686031,
          45.92345
        ]
      },
      "properties": {
        "description": "representative point"
      }
    },
    {
      "geometry": {
        "type": "Point",
        "coordinates": [
          6.686031,
          45.92345
        ]
      },
      "id": "darmc-location-16127",
      "type": "Feature",
      "properties": {
        "description": "1M scale point location",
        "location_precision": "precise",
        "title": "DARMC location 16127",
        "link": "http://pleiades.stoa.org/places/167866/darmc-location-16127"
      }
    }
  ]
}