{
  "type": "FeatureCollection",
  "title": "Mediolanum",
  "id": "167828",
  "description": "An ancient place, cited: BAtlas 17 C2 Mediolanum",
  "bbox": [
    4.493707,
    45.875632,
    4.493707,
    45.875632
  ],
  "reprPoint": [
    4.493707,
    45.875632
  ],
  "names": [
    "Mediolanum"
  ],
  "features": [
    {
      "geometry": {
        "type": "Point",
        "coordinates": [
          4.493707,
          45.875632
        ]
      },
      "id": "center-point-of-commune-pontcharra-sur-turdine",
      "type": "Feature",
      "properties": {
        "description": null,
        "location_precision": "precise",
        "title": "Center point of commune Pontcharra-sur-Turdine",
        "link": "http://pleiades.stoa.org/places/167828/center-point-of-commune-pontcharra-sur-turdine"
      }
    }
  ]
}