{
  "type": "FeatureCollection",
  "title": "Lucenay",
  "id": "167814",
  "description": "An ancient place, cited: BAtlas 17 D2 Lucenay",
  "bbox": [
    4.702564,
    45.912928,
    4.702564,
    45.912928
  ],
  "reprPoint": [
    4.702564,
    45.912928
  ],
  "features": [
    {
      "geometry": {
        "type": "Point",
        "coordinates": [
          4.702564,
          45.912928
        ]
      },
      "id": "darmc-location-7416",
      "type": "Feature",
      "properties": {
        "description": "500K scale point location",
        "location_precision": "precise",
        "title": "DARMC location 7416",
        "link": "http://pleiades.stoa.org/places/167814/darmc-location-7416"
      }
    }
  ]
}