{
  "type": "FeatureCollection",
  "title": "Rodumna",
  "id": "167885",
  "description": "An ancient place, cited: BAtlas 17 C1 Rodumna",
  "bbox": [
    4.071772,
    46.039132,
    4.071772,
    46.039132
  ],
  "reprPoint": [
    4.071772,
    46.039132
  ],
  "names": [
    "Roanne",
    "Rodumna"
  ],
  "features": [
    {
      "geometry": {
        "type": "Point",
        "coordinates": [
          4.071772,
          46.039132
        ]
      },
      "id": "darmc-location-14515",
      "type": "Feature",
      "properties": {
        "description": "1M scale point location",
        "location_precision": "precise",
        "title": "DARMC location 14515",
        "link": "http://pleiades.stoa.org/places/167885/darmc-location-14515"
      }
    }
  ]
}