{
  "type": "FeatureCollection",
  "title": "St-Martin-d’Uriage",
  "id": "167899",
  "description": "An ancient place, cited: BAtlas 17 F3 St-Martin-d’Uriage",
  "bbox": [
    5.837117,
    45.151325,
    5.837117,
    45.151325
  ],
  "reprPoint": [
    5.837117,
    45.151325
  ],
  "features": [
    {
      "geometry": {
        "type": "Point",
        "coordinates": [
          5.837117,
          45.151325
        ]
      },
      "id": "darmc-location-15368",
      "type": "Feature",
      "properties": {
        "description": "500K scale point location",
        "location_precision": "precise",
        "title": "DARMC location 15368",
        "link": "http://pleiades.stoa.org/places/167899/darmc-location-15368"
      }
    }
  ]
}