{
  "type": "FeatureCollection",
  "title": "La Motte-St-Martin",
  "id": "167846",
  "description": "An ancient place, cited: BAtlas 17 F4 La Motte-St-Martin",
  "bbox": [
    5.71089,
    44.961028,
    5.71089,
    44.961028
  ],
  "reprPoint": [
    5.71089,
    44.961028
  ],
  "features": [
    {
      "geometry": {
        "type": "Point",
        "coordinates": [
          5.71089,
          44.961028
        ]
      },
      "id": "darmc-location-26048",
      "type": "Feature",
      "properties": {
        "description": "500K scale point location",
        "location_precision": "precise",
        "title": "DARMC location 26048",
        "link": "http://pleiades.stoa.org/places/167846/darmc-location-26048"
      }
    }
  ]
}