{
  "type": "FeatureCollection",
  "title": "Limony",
  "id": "167812",
  "description": "An ancient place, cited: BAtlas 17 D3 Limony",
  "bbox": [
    4.757599,
    45.352156,
    4.757599,
    45.352156
  ],
  "reprPoint": [
    4.757599,
    45.352156
  ],
  "features": [
    {
      "geometry": {
        "type": "Point",
        "coordinates": [
          4.757599,
          45.352156
        ]
      },
      "id": "darmc-location-17509",
      "type": "Feature",
      "properties": {
        "description": "500K scale point location",
        "location_precision": "precise",
        "title": "DARMC location 17509",
        "link": "http://pleiades.stoa.org/places/167812/darmc-location-17509"
      }
    }
  ]
}