{
  "type": "FeatureCollection",
  "title": "*Mimas",
  "id": "167834",
  "description": "An ancient place, cited: BAtlas 17 A4 *Mimas",
  "bbox": [
    3.497516,
    44.517324,
    3.49867,
    44.518715
  ],
  "reprPoint": [
    3.498093,
    44.5180195
  ],
  "names": [
    "Mimas"
  ],
  "features": [
    {
      "geometry": {
        "type": "Point",
        "coordinates": [
          3.497516,
          44.518715
        ]
      },
      "id": "darmc-location-6754",
      "type": "Feature",
      "properties": {
        "description": "500K scale point location",
        "location_precision": "precise",
        "title": "DARMC location 6754",
        "link": "http://pleiades.stoa.org/places/167834/darmc-location-6754"
      }
    },
    {
      "geometry": {
        "type": "Point",
        "coordinates": [
          3.49867,
          44.517324
        ]
      },
      "id": "dare-location",
      "type": "Feature",
      "properties": {
        "description": "Representative point location, site precision",
        "location_precision": "precise",
        "title": "DARE Location",
        "link": "http://pleiades.stoa.org/places/167834/dare-location"
      }
    }
  ]
}