{
  "type": "FeatureCollection",
  "title": "Peyrus",
  "id": "167868",
  "description": "An ancient place, cited: BAtlas 17 E4 Peyrus",
  "bbox": [
    5.1055,
    44.913098,
    5.1055,
    44.913098
  ],
  "reprPoint": [
    5.1055,
    44.913098
  ],
  "features": [
    {
      "geometry": {
        "type": "Point",
        "coordinates": [
          5.1055,
          44.913098
        ]
      },
      "id": "darmc-location-7388",
      "type": "Feature",
      "properties": {
        "description": "500K scale point location",
        "location_precision": "precise",
        "title": "DARMC location 7388",
        "link": "http://pleiades.stoa.org/places/167868/darmc-location-7388"
      }
    }
  ]
}