{
  "type": "FeatureCollection",
  "title": "Salins-les-Thermes",
  "id": "167909",
  "bbox": [
    6.528298,
    45.471473,
    6.528298,
    45.471473
  ],
  "description": "An ancient place, cited: BAtlas 17 H3 Salins-les-Thermes",
  "features": [
    {
      "type": "Feature",
      "geometry": {
        "type": "Point",
        "coordinates": [
          6.528298,
          45.471473
        ]
      },
      "properties": {
        "description": "representative point"
      }
    },
    {
      "geometry": {
        "type": "Point",
        "coordinates": [
          6.528298,
          45.471473
        ]
      },
      "id": "darmc-location-26180",
      "type": "Feature",
      "properties": {
        "description": "500K scale point location",
        "location_precision": "precise",
        "title": "DARMC location 26180",
        "link": "http://pleiades.stoa.org/places/167909/darmc-location-26180"
      }
    }
  ]
}