{
  "type": "FeatureCollection",
  "title": "Vologatae",
  "id": "167978",
  "description": "An ancient place, cited: BAtlas 17 F4 Vologatae",
  "bbox": [
    5.564001,
    44.568983,
    5.564001,
    44.568983
  ],
  "reprPoint": [
    5.564001,
    44.568983
  ],
  "names": [
    "Vologatae"
  ],
  "features": [
    {
      "geometry": {
        "type": "Point",
        "coordinates": [
          5.564001,
          44.568983
        ]
      },
      "id": "darmc-location-6558",
      "type": "Feature",
      "properties": {
        "description": "500K scale point location",
        "location_precision": "precise",
        "title": "DARMC location 6558",
        "link": "http://pleiades.stoa.org/places/167978/darmc-location-6558"
      }
    }
  ]
}