{
  "type": "FeatureCollection",
  "title": "Varces-Allières-et-Risset",
  "id": "167955",
  "description": "An ancient place, cited: BAtlas 17 F3 Varces-Allières-et-Risset",
  "bbox": [
    5.679483,
    45.088055,
    5.679483,
    45.088055
  ],
  "reprPoint": [
    5.679483,
    45.088055
  ],
  "features": [
    {
      "geometry": {
        "type": "Point",
        "coordinates": [
          5.679483,
          45.088055
        ]
      },
      "id": "darmc-location-26244",
      "type": "Feature",
      "properties": {
        "description": "500K scale point location",
        "location_precision": "precise",
        "title": "DARMC location 26244",
        "link": "http://pleiades.stoa.org/places/167955/darmc-location-26244"
      }
    }
  ]
}