{
  "type": "FeatureCollection",
  "title": "Termas romanas de Santa María",
  "id": "168208659",
  "bbox": [
    -4.555913,
    37.0149137,
    -4.555913,
    37.0149137
  ],
  "description": "Remains of Roman baths at Antequera in Spain.",
  "connectsWith": [
    "265799"
  ],
  "names": [
    "Termas romanas de Santa Maria la Mayor"
  ],
  "features": [
    {
      "type": "Feature",
      "geometry": {
        "type": "Point",
        "coordinates": [
          -4.555913,
          37.0149137
        ]
      },
      "properties": {
        "description": "representative point"
      }
    },
    {
      "geometry": {
        "type": "Point",
        "coordinates": [
          -4.555913,
          37.0149137
        ]
      },
      "id": "termas-romanas-de-santa-maria",
      "type": "Feature",
      "properties": {
        "description": "Location via OpenStreetMap, based on geotagged photos in Flickr and Panoramio. Dates after BAtlas.",
        "location_precision": "precise",
        "title": "OSM location of Termas romanas de Santa María",
        "link": "http://pleiades.stoa.org/places/168208659/termas-romanas-de-santa-maria"
      }
    }
  ]
}