{
  "type": "FeatureCollection",
  "title": "Church of Saint Catherine, Thessaloniki",
  "id": "170580013",
  "bbox": [
    22.944237,
    40.643213,
    22.944237,
    40.643213
  ],
  "description": "A late Byzantine church in Thessalonica.",
  "connectsWith": [
    "491741"
  ],
  "features": [
    {
      "type": "Feature",
      "geometry": {
        "type": "Point",
        "coordinates": [
          22.944237,
          40.643213
        ]
      },
      "properties": {
        "description": "representative point"
      }
    },
    {
      "geometry": {
        "type": "Point",
        "coordinates": [
          22.944237,
          40.643213
        ]
      },
      "id": "imagery-location",
      "type": "Feature",
      "properties": {
        "description": "A late Byzantine church in Thessalonica",
        "location_precision": "precise",
        "title": "Imagery Location of Church of Saint Catherine",
        "link": "http://pleiades.stoa.org/places/170580013/imagery-location"
      }
    }
  ]
}