{
  "type": "FeatureCollection",
  "title": "Tell Agrab",
  "id": "171585551",
  "bbox": [
    44.8742850623,
    33.3391861956,
    44.8742850623,
    33.3391861956
  ],
  "description": "Tell Agrab, or Ajrab, is a medium-sized archaeological mound in the Diyala Province of central Iraq, some forty kilometers east of Baghdad. The site was excavated by archaeologists from the Oriental Institute of the University of Chicago in 1936 and 1937. Tell Agrab seems to have been inhabited from the early 3rd millennium BCE until the beginning of the Old Babylonian Period (ca. 1800 BCE). In its early history, the site held a temple possibly dedicated to the god Šara.",
  "names": [
    "Tall Ajrab",
    "Tell Agrab",
    "Tall Aghrab"
  ],
  "features": [
    {
      "type": "Feature",
      "geometry": {
        "type": "Point",
        "coordinates": [
          44.8742850623,
          33.3391861956
        ]
      },
      "properties": {
        "description": "representative point"
      }
    },
    {
      "geometry": {
        "type": "Point",
        "coordinates": [
          44.8742850623,
          33.3391861956
        ]
      },
      "id": "imagery-location-of-tell-agrab",
      "type": "Feature",
      "properties": {
        "description": null,
        "location_precision": "precise",
        "title": "Imagery location of Tell Agrab",
        "link": "http://pleiades.stoa.org/places/171585551/imagery-location-of-tell-agrab"
      }
    }
  ]
}