{
  "type": "FeatureCollection",
  "title": "Apliki",
  "id": "172140914",
  "bbox": [
    33.1172213,
    34.9309782,
    33.1172213,
    34.9309782
  ],
  "description": "Apliki in central Cyprus was the site of Bronze Age copper smelting.",
  "connectsWith": [
    "707498"
  ],
  "names": [
    "Apliki"
  ],
  "features": [
    {
      "type": "Feature",
      "geometry": {
        "type": "Point",
        "coordinates": [
          33.1172213,
          34.9309782
        ]
      },
      "properties": {
        "description": "representative point"
      }
    },
    {
      "geometry": {
        "type": "Point",
        "coordinates": [
          33.1172213,
          34.9309782
        ]
      },
      "id": "apliki",
      "type": "Feature",
      "properties": {
        "description": "Representative location based on OpenStreetMap",
        "location_precision": "precise",
        "title": "OSM location of modern Apliki",
        "link": "http://pleiades.stoa.org/places/172140914/apliki"
      }
    }
  ]
}