{
  "type": "FeatureCollection",
  "title": "Castro de São Lourenço",
  "id": "175451017",
  "bbox": [
    -8.7617788,
    41.5559156,
    -8.7617788,
    41.5559156
  ],
  "description": "A Bronze Age settlement.",
  "features": [
    {
      "type": "Feature",
      "geometry": {
        "type": "Point",
        "coordinates": [
          -8.7617788,
          41.5559156
        ]
      },
      "properties": {
        "description": "representative point"
      }
    },
    {
      "geometry": {
        "type": "Point",
        "coordinates": [
          -8.7617788,
          41.5559156
        ]
      },
      "id": "osm-location",
      "type": "Feature",
      "properties": {
        "description": "Representative location of archaeological site of Castro de São Lourenço based on OpenStreetMap.",
        "location_precision": "precise",
        "title": "OSM location of Castro de São Lourenço",
        "link": "http://pleiades.stoa.org/places/175451017/osm-location"
      }
    }
  ]
}