{
  "type": "FeatureCollection",
  "title": "Praetorium at Gortyna",
  "id": "177278517",
  "bbox": [
    24.9514088,
    35.0588379,
    24.9514088,
    35.0588379
  ],
  "description": "The Praetorium at Gortyna dates to the first century A.D.",
  "connectsWith": [
    "589796"
  ],
  "features": [
    {
      "type": "Feature",
      "geometry": {
        "type": "Point",
        "coordinates": [
          24.9514088,
          35.0588379
        ]
      },
      "properties": {
        "description": "representative point"
      }
    },
    {
      "geometry": {
        "type": "Point",
        "coordinates": [
          24.9514088,
          35.0588379
        ]
      },
      "id": "osm-location-of-praetorium",
      "type": "Feature",
      "properties": {
        "description": "Location based on OpenStreetMap",
        "location_precision": "precise",
        "title": "OSM location of Praetorium",
        "link": "http://pleiades.stoa.org/places/177278517/osm-location-of-praetorium"
      }
    }
  ]
}