{
  "type": "FeatureCollection",
  "title": "Cambete",
  "id": "177486",
  "description": "An ancient place, cited: BAtlas 18 E2 Cambete",
  "bbox": [
    7.503772,
    47.690543,
    7.503772,
    47.690543
  ],
  "reprPoint": [
    7.503772,
    47.690543
  ],
  "names": [
    "Cambete"
  ],
  "features": [
    {
      "geometry": {
        "type": "Point",
        "coordinates": [
          7.503772,
          47.690543
        ]
      },
      "id": "darmc-location-9647",
      "type": "Feature",
      "properties": {
        "description": "1M scale point location",
        "location_precision": "precise",
        "title": "DARMC location 9647",
        "link": "http://pleiades.stoa.org/places/177486/darmc-location-9647"
      }
    }
  ]
}