{
  "type": "FeatureCollection",
  "title": "Basilia",
  "id": "177468",
  "bbox": [
    7.580599,
    47.556434,
    7.592273,
    47.559623
  ],
  "description": "An ancient place, cited: BAtlas 18 E2 Basilia",
  "names": [
    "Basilia",
    "Basel"
  ],
  "features": [
    {
      "type": "Feature",
      "geometry": {
        "type": "Point",
        "coordinates": [
          7.586436,
          47.5580285
        ]
      },
      "properties": {
        "description": "representative point"
      }
    },
    {
      "geometry": {
        "type": "Point",
        "coordinates": [
          7.580599,
          47.559623
        ]
      },
      "id": "darmc-location-2944",
      "type": "Feature",
      "properties": {
        "description": "1:1 million scale representative point location digitized from the Barrington Atlas of the Greek and Roman World by the Digital Atlas of Roman and Medieval Civilizations project at Harvard University.",
        "location_precision": "precise",
        "title": "DARMC location 2944",
        "link": "http://pleiades.stoa.org/places/177468/darmc-location-2944"
      }
    },
    {
      "geometry": {
        "type": "Point",
        "coordinates": [
          7.592273,
          47.556434
        ]
      },
      "id": "dare-location",
      "type": "Feature",
      "properties": {
        "description": "Representative point location, site precision",
        "location_precision": "precise",
        "title": "DARE Location",
        "link": "http://pleiades.stoa.org/places/177468/dare-location"
      }
    }
  ]
}