{
  "type": "FeatureCollection",
  "title": "Col. Iulia Equestris/Noviodunum",
  "id": "177496",
  "description": "An ancient place, cited: BAtlas 18 D3 Col. Iulia Equestris/Noviodunum",
  "bbox": [
    6.238405,
    46.380843,
    6.238405,
    46.380843
  ],
  "reprPoint": [
    6.238405,
    46.380843
  ],
  "names": [
    "Nyon",
    "Col. Iulia Equestris",
    "Noviodunum"
  ],
  "features": [
    {
      "geometry": {
        "type": "Point",
        "coordinates": [
          6.238405,
          46.380843
        ]
      },
      "id": "darmc-location-12060",
      "type": "Feature",
      "properties": {
        "description": "1M scale point location",
        "location_precision": "precise",
        "title": "DARMC location 12060",
        "link": "http://pleiades.stoa.org/places/177496/darmc-location-12060"
      }
    },
    {
      "geometry": {
        "type": "Point",
        "coordinates": [
          6.2412447,
          46.3831955
        ]
      },
      "id": "location-of-roman-amphitheater",
      "type": "Feature",
      "properties": {
        "description": "Location based on OpenStreetMap",
        "location_precision": "precise",
        "title": "location of Roman amphitheater",
        "link": "http://pleiades.stoa.org/places/177496/location-of-roman-amphitheater"
      }
    }
  ]
}