{
  "type": "FeatureCollection",
  "title": "Col. Augusta Raurica",
  "id": "177494",
  "bbox": [
    7.721984,
    47.533194,
    7.722311,
    47.533303
  ],
  "description": "Col. Augusta Raurica (modern Augst) was a Roman colony on the south bank of the Rhine established by Iulius Caesar and L. Munatius Plancus in 44 B.C.",
  "connectsWith": [
    "180449"
  ],
  "names": [
    "Col. Augusta Raurica",
    "Col. Paterna Pia Apollinaris Augusta Emerita Raurica",
    "Rauraci",
    "Augst"
  ],
  "features": [
    {
      "type": "Feature",
      "geometry": {
        "type": "Point",
        "coordinates": [
          7.722118,
          47.533241
        ]
      },
      "properties": {
        "description": "representative point"
      }
    },
    {
      "geometry": {
        "type": "Point",
        "coordinates": [
          7.721984,
          47.533303
        ]
      },
      "id": "darmc-location-12054",
      "type": "Feature",
      "properties": {
        "description": "1M scale point location",
        "location_precision": "precise",
        "title": "DARMC location 12054",
        "link": "http://pleiades.stoa.org/places/177494/darmc-location-12054"
      }
    },
    {
      "geometry": {
        "type": "Point",
        "coordinates": [
          7.722059,
          47.533194
        ]
      },
      "id": "darmc-location-21574",
      "type": "Feature",
      "properties": {
        "description": "5M scale point location",
        "location_precision": "precise",
        "title": "DARMC location 21574",
        "link": "http://pleiades.stoa.org/places/177494/darmc-location-21574"
      }
    },
    {
      "geometry": {
        "type": "Point",
        "coordinates": [
          7.722311,
          47.533226
        ]
      },
      "id": "dare-location",
      "type": "Feature",
      "properties": {
        "description": "Representative point location, site precision",
        "location_precision": "precise",
        "title": "DARE Location",
        "link": "http://pleiades.stoa.org/places/177494/dare-location"
      }
    }
  ]
}