{
  "type": "FeatureCollection",
  "title": "Grozon",
  "id": "177531",
  "bbox": [
    5.700704,
    46.890112,
    5.700704,
    46.890112
  ],
  "description": "An ancient place, cited: BAtlas 18 C3 Grozon",
  "features": [
    {
      "type": "Feature",
      "geometry": {
        "type": "Point",
        "coordinates": [
          5.700704,
          46.890112
        ]
      },
      "properties": {
        "description": "representative point"
      }
    },
    {
      "geometry": {
        "type": "Point",
        "coordinates": [
          5.700704,
          46.890112
        ]
      },
      "id": "darmc-location-12616",
      "type": "Feature",
      "properties": {
        "description": "1M scale point location",
        "location_precision": "precise",
        "title": "DARMC location 12616",
        "link": "http://pleiades.stoa.org/places/177531/darmc-location-12616"
      }
    }
  ]
}