{
  "type": "FeatureCollection",
  "title": "Mont-Rivel",
  "id": "177583",
  "description": "An ancient place, cited: BAtlas 18 C3 Mont-Rivel",
  "bbox": [
    5.921531,
    46.759137,
    5.939666,
    46.761367
  ],
  "reprPoint": [
    5.9305985,
    46.760252
  ],
  "features": [
    {
      "geometry": {
        "type": "Point",
        "coordinates": [
          5.921531,
          46.761367
        ]
      },
      "id": "dare-location",
      "type": "Feature",
      "properties": {
        "description": "Representative point location, site precision",
        "location_precision": "precise",
        "title": "DARE Location",
        "link": "http://pleiades.stoa.org/places/177583/dare-location"
      }
    },
    {
      "geometry": {
        "type": "Point",
        "coordinates": [
          5.939666,
          46.759137
        ]
      },
      "id": "darmc-location-26100",
      "type": "Feature",
      "properties": {
        "description": "1M scale point location",
        "location_precision": "precise",
        "title": "DARMC location 26100",
        "link": "http://pleiades.stoa.org/places/177583/darmc-location-26100"
      }
    }
  ]
}