{
  "type": "FeatureCollection",
  "title": "tribus Menenia",
  "id": "177623366",
  "bbox": [
    12.486137,
    41.891775,
    12.486137,
    41.891775
  ],
  "description": "The gens Menenia was an ancient patrician line that lent its name to the tribus Menenia.",
  "connectsWith": [
    "423025",
    "432900"
  ],
  "names": [
    "Menenia"
  ],
  "features": [
    {
      "type": "Feature",
      "geometry": {
        "type": "Point",
        "coordinates": [
          12.486137,
          41.891775
        ]
      },
      "properties": {
        "description": "representative point"
      }
    }
  ]
}