{
  "type": "FeatureCollection",
  "title": "Vivisco",
  "id": "177663",
  "bbox": [
    6.847173,
    46.458838,
    6.847173,
    46.458838
  ],
  "description": "An ancient place, cited: BAtlas 18 D3 Vivisco",
  "names": [
    "Vivisco",
    "Vibisco"
  ],
  "features": [
    {
      "type": "Feature",
      "geometry": {
        "type": "Point",
        "coordinates": [
          6.847173,
          46.458838
        ]
      },
      "properties": {
        "description": "representative point"
      }
    },
    {
      "geometry": {
        "type": "Point",
        "coordinates": [
          6.847173,
          46.458838
        ]
      },
      "id": "darmc-location-19718",
      "type": "Feature",
      "properties": {
        "description": "1M scale point location",
        "location_precision": "precise",
        "title": "DARMC location 19718",
        "link": "http://pleiades.stoa.org/places/177663/darmc-location-19718"
      }
    }
  ]
}