{
  "type": "FeatureCollection",
  "title": "Pierre-de-Bresse",
  "id": "177604",
  "description": "An ancient place, cited: BAtlas 18 C3 Pierre-de-Bresse",
  "bbox": [
    5.257582,
    46.886977,
    5.257582,
    46.886977
  ],
  "reprPoint": [
    5.257582,
    46.886977
  ],
  "features": [
    {
      "geometry": {
        "type": "Point",
        "coordinates": [
          5.257582,
          46.886977
        ]
      },
      "id": "darmc-location-24284",
      "type": "Feature",
      "properties": {
        "description": "1M scale point location",
        "location_precision": "precise",
        "title": "DARMC location 24284",
        "link": "http://pleiades.stoa.org/places/177604/darmc-location-24284"
      }
    }
  ]
}