{
  "type": "FeatureCollection",
  "title": "Theater at Sybaris/Thurii/Copia",
  "id": "178686122",
  "bbox": [
    16.491777,
    39.7158244,
    16.491777,
    39.7158244
  ],
  "description": "The Roman Theater at Sybaris/Thurii/Copia dates originally to the Augustan period.",
  "connectsWith": [
    "452457"
  ],
  "features": [
    {
      "type": "Feature",
      "geometry": {
        "type": "Point",
        "coordinates": [
          16.491777,
          39.7158244
        ]
      },
      "properties": {
        "description": "representative point"
      }
    },
    {
      "geometry": {
        "type": "Point",
        "coordinates": [
          16.491777,
          39.7158244
        ]
      },
      "id": "location-of-theater",
      "type": "Feature",
      "properties": {
        "description": "Representative location based on OpenStreetMap.",
        "location_precision": "precise",
        "title": "OSM location of teatro antico",
        "link": "http://pleiades.stoa.org/places/178686122/location-of-theater"
      }
    }
  ]
}