{
  "type": "FeatureCollection",
  "title": "Roman theater at Aosta",
  "id": "179717291",
  "bbox": [
    7.3217401,
    45.738629,
    7.3217401,
    45.738629
  ],
  "description": "The Roman theater at Aosta dates ca. 25 B.C.",
  "connectsWith": [
    "383579"
  ],
  "features": [
    {
      "type": "Feature",
      "geometry": {
        "type": "Point",
        "coordinates": [
          7.3217401,
          45.738629
        ]
      },
      "properties": {
        "description": "representative point"
      }
    },
    {
      "geometry": {
        "type": "Point",
        "coordinates": [
          7.3217401,
          45.738629
        ]
      },
      "id": "osm-location-of-roman-theater",
      "type": "Feature",
      "properties": {
        "description": "Location based on OpenStreetMap",
        "location_precision": "precise",
        "title": "OSM Location of Roman theater",
        "link": "http://pleiades.stoa.org/places/179717291/osm-location-of-roman-theater"
      }
    }
  ]
}