{
  "type": "FeatureCollection",
  "title": "Mound at Banāt al-Hassan (Adams 100)",
  "id": "180784164",
  "bbox": [
    45.5218,
    31.5757,
    45.5218,
    31.5757
  ],
  "description": "Part of a group of mounds in central Mesopotamia, this settlement (number 100 in Adams 1972) containing remains dated from the Akkadian through Larsa periods.",
  "connectsWith": [
    "690025800"
  ],
  "names": [
    "Banāt al-Hassan"
  ],
  "features": [
    {
      "type": "Feature",
      "geometry": {
        "type": "Point",
        "coordinates": [
          45.5218,
          31.5757
        ]
      },
      "properties": {
        "description": "representative point"
      }
    },
    {
      "geometry": {
        "type": "Point",
        "coordinates": [
          45.5218,
          31.5757
        ]
      },
      "id": "cigs-location-of-banat-al-hassan",
      "type": "Feature",
      "properties": {
        "description": null,
        "location_precision": "precise",
        "title": " CIGS location of Adams 100 (Banāt al-Hassan)",
        "link": "http://pleiades.stoa.org/places/180784164/cigs-location-of-banat-al-hassan"
      }
    }
  ]
}