{
  "type": "FeatureCollection",
  "title": "Filo Musiaco",
  "id": "181211",
  "description": "An ancient place, cited: BAtlas 18 unlocated Filo Musiaco",
  "bbox": [
    6.339442,
    47.094804,
    6.339442,
    47.094804
  ],
  "reprPoint": [
    6.339442,
    47.094804
  ],
  "names": [
    "Filo Musiaco"
  ],
  "features": [
    {
      "id": "batlas-location",
      "type": "Feature",
      "properties": {
        "description": null,
        "location_precision": "unlocated",
        "title": "Barrington Atlas location",
        "link": "http://pleiades.stoa.org/places/181211/batlas-location"
      }
    },
    {
      "geometry": {
        "type": "Point",
        "coordinates": [
          6.339442,
          47.094804
        ]
      },
      "id": "dare-location",
      "type": "Feature",
      "properties": {
        "description": "Representative point location, village precision",
        "location_precision": "precise",
        "title": "DARE Location",
        "link": "http://pleiades.stoa.org/places/181211/dare-location"
      }
    }
  ]
}