{
  "type": "FeatureCollection",
  "title": "Grotta dell'Uzzo",
  "id": "182402266",
  "bbox": [
    12.7876363,
    38.1107097,
    12.7876363,
    38.1107097
  ],
  "description": "The Grotta dell'Uzzo is an important archaeological site in Sicily with traces of human settlement beginning 10,000 years BP.",
  "connectsWith": [
    "462492"
  ],
  "features": [
    {
      "type": "Feature",
      "geometry": {
        "type": "Point",
        "coordinates": [
          12.7876363,
          38.1107097
        ]
      },
      "properties": {
        "description": "representative point"
      }
    },
    {
      "geometry": {
        "type": "Point",
        "coordinates": [
          12.7876363,
          38.1107097
        ]
      },
      "id": "location-of-grotta-delluzzo",
      "type": "Feature",
      "properties": {
        "description": "Representative location based on OpenStreetMap.",
        "location_precision": "precise",
        "title": "OSM location of Grotta dell'Uzzo",
        "link": "http://pleiades.stoa.org/places/182402266/location-of-grotta-delluzzo"
      }
    }
  ]
}