{
  "type": "FeatureCollection",
  "title": "tribus Cornelia",
  "id": "182931391",
  "bbox": [
    12.486137,
    41.042508,
    15.0126591,
    42.956143
  ],
  "description": "A rural tribe of ancient Rome.",
  "connectsWith": [
    "423025"
  ],
  "names": [
    "Cornelia"
  ],
  "features": [
    {
      "type": "Feature",
      "geometry": {
        "type": "Point",
        "coordinates": [
          13.4512515408,
          41.8867987919
        ]
      },
      "properties": {
        "description": "representative point"
      }
    }
  ]
}