{
  "type": "FeatureCollection",
  "title": "Unnamed spring supplying Lambaesis via aqueduct",
  "id": "183817910",
  "bbox": [
    6.323578,
    35.385119,
    6.323578,
    35.385119
  ],
  "description": "Unlabeled feature captured from the Barrington Atlas",
  "connectsWith": [
    "335226"
  ],
  "features": [
    {
      "type": "Feature",
      "geometry": {
        "type": "Point",
        "coordinates": [
          6.323578,
          35.385119
        ]
      },
      "properties": {
        "description": "representative point"
      }
    },
    {
      "geometry": {
        "type": "Point",
        "coordinates": [
          6.323578,
          35.385119
        ]
      },
      "id": "darmc-location-33381",
      "type": "Feature",
      "properties": {
        "description": "representative point location digitized from the Barrington Atlas of the Greek and Roman World by the Digital Atlas of Roman and Medieval Civilizations project at Harvard University.",
        "location_precision": "precise",
        "title": "DARMC location 33381",
        "link": "http://pleiades.stoa.org/places/183817910/darmc-location-33381"
      }
    }
  ]
}