{
  "type": "FeatureCollection",
  "title": "Temple East of Lavinium",
  "id": "183817905",
  "bbox": [
    12.48422,
    41.661501,
    12.48422,
    41.661501
  ],
  "description": "From the 5th century BC.",
  "connectsWith": [
    "422960"
  ],
  "features": [
    {
      "type": "Feature",
      "geometry": {
        "type": "Point",
        "coordinates": [
          12.48422,
          41.661501
        ]
      },
      "properties": {
        "description": "representative point"
      }
    },
    {
      "geometry": {
        "type": "Point",
        "coordinates": [
          12.48422,
          41.661501
        ]
      },
      "id": "darmc-location-13989",
      "type": "Feature",
      "properties": {
        "description": "150K scale point location",
        "location_precision": "precise",
        "title": "DARMC location 13989",
        "link": "http://pleiades.stoa.org/places/183817905/darmc-location-13989"
      }
    }
  ]
}