{
  "type": "FeatureCollection",
  "title": "Unnamed spring supplying Lambaesis via aqueduct",
  "id": "183817910",
  "description": "Unlabeled feature captured from the Barrington Atlas",
  "bbox": [
    6.323578,
    35.385119,
    6.323578,
    35.385119
  ],
  "reprPoint": [
    6.323578,
    35.385119
  ],
  "features": [
    {
      "geometry": {
        "type": "Point",
        "coordinates": [
          6.323578,
          35.385119
        ]
      },
      "id": "darmc-location-33381",
      "type": "Feature",
      "properties": {
        "description": "scale point location",
        "location_precision": "precise",
        "title": "DARMC location 33381",
        "link": "http://pleiades.stoa.org/places/183817910/darmc-location-33381"
      }
    }
  ]
}