{
  "type": "FeatureCollection",
  "title": "Roman theater at Herakleia",
  "id": "185859210",
  "bbox": [
    21.342733,
    41.0113997,
    21.342733,
    41.0113997
  ],
  "description": "The Roman theater at Herakleia dates to the time of Hadrian and remained in use until the fourth century. Its remains came to light in 1968.",
  "connectsWith": [
    "481861"
  ],
  "features": [
    {
      "type": "Feature",
      "geometry": {
        "type": "Point",
        "coordinates": [
          21.342733,
          41.0113997
        ]
      },
      "properties": {
        "description": "representative point"
      }
    },
    {
      "geometry": {
        "type": "Point",
        "coordinates": [
          21.342733,
          41.0113997
        ]
      },
      "id": "osm-location-of-roman-theater",
      "type": "Feature",
      "properties": {
        "description": "Location based on OpenStreetMap",
        "location_precision": "precise",
        "title": "OSM Location of Roman theater",
        "link": "http://pleiades.stoa.org/places/185859210/osm-location-of-roman-theater"
      }
    }
  ]
}