{
  "type": "FeatureCollection",
  "title": "Ad Fines",
  "id": "187249",
  "bbox": [
    8.954175,
    47.594335,
    8.960718,
    47.59578
  ],
  "description": "An ancient place, cited: BAtlas 19 A2 Ad Fines",
  "names": [
    "Ad Fines"
  ],
  "features": [
    {
      "type": "Feature",
      "geometry": {
        "type": "Point",
        "coordinates": [
          8.9574465,
          47.5950575
        ]
      },
      "properties": {
        "description": "representative point"
      }
    },
    {
      "geometry": {
        "type": "Point",
        "coordinates": [
          8.954175,
          47.59578
        ]
      },
      "id": "darmc-location-2318",
      "type": "Feature",
      "properties": {
        "description": "1M scale point location",
        "location_precision": "precise",
        "title": "DARMC location 2318",
        "link": "http://pleiades.stoa.org/places/187249/darmc-location-2318"
      }
    },
    {
      "geometry": {
        "type": "Point",
        "coordinates": [
          8.960718,
          47.594335
        ]
      },
      "id": "dare-location",
      "type": "Feature",
      "properties": {
        "description": "Representative point location, site precision",
        "location_precision": "precise",
        "title": "DARE Location",
        "link": "http://pleiades.stoa.org/places/187249/dare-location"
      }
    }
  ]
}