{
  "type": "FeatureCollection",
  "title": "Artobriga",
  "id": "187295",
  "bbox": [
    12.645465,
    47.86997,
    12.645465,
    47.86997
  ],
  "description": "An ancient place, cited: BAtlas 19 E2 Artobriga",
  "names": [
    "Artobriga"
  ],
  "features": [
    {
      "type": "Feature",
      "geometry": {
        "type": "Point",
        "coordinates": [
          12.645465,
          47.86997
        ]
      },
      "properties": {
        "description": "representative point"
      }
    },
    {
      "geometry": {
        "type": "Point",
        "coordinates": [
          12.645465,
          47.86997
        ]
      },
      "id": "darmc-location-8670",
      "type": "Feature",
      "properties": {
        "description": "1M scale point location",
        "location_precision": "precise",
        "title": "DARMC location 8670",
        "link": "http://pleiades.stoa.org/places/187295/darmc-location-8670"
      }
    }
  ]
}