{
  "type": "FeatureCollection",
  "title": "Altenstadt",
  "id": "187276",
  "description": "An ancient place, cited: BAtlas 19 C2 Altenstadt",
  "bbox": [
    10.872233,
    47.823158,
    10.872233,
    47.823158
  ],
  "reprPoint": [
    10.872233,
    47.823158
  ],
  "features": [
    {
      "geometry": {
        "type": "Point",
        "coordinates": [
          10.872233,
          47.823158
        ]
      },
      "id": "darmc-location-1094",
      "type": "Feature",
      "properties": {
        "description": "1M scale point location",
        "location_precision": "precise",
        "title": "DARMC location 1094",
        "link": "http://pleiades.stoa.org/places/187276/darmc-location-1094"
      }
    }
  ]
}