{
  "type": "FeatureCollection",
  "title": "‘Apicilia’",
  "id": "187287",
  "bbox": [
    12.991773,
    45.789263,
    12.991773,
    45.789263
  ],
  "description": "An ancient place, cited: BAtlas 19 E4 ‘Apicilia’",
  "names": [
    "Apicilia"
  ],
  "features": [
    {
      "type": "Feature",
      "geometry": {
        "type": "Point",
        "coordinates": [
          12.991773,
          45.789263
        ]
      },
      "properties": {
        "description": "representative point"
      }
    },
    {
      "geometry": {
        "type": "Point",
        "coordinates": [
          12.991773,
          45.789263
        ]
      },
      "id": "darmc-location-8669",
      "type": "Feature",
      "properties": {
        "description": "1M scale point location",
        "location_precision": "precise",
        "title": "DARMC location 8669",
        "link": "http://pleiades.stoa.org/places/187287/darmc-location-8669"
      }
    }
  ]
}