{
  "type": "FeatureCollection",
  "title": "Altenburg-Rheinau",
  "id": "187275",
  "description": "An ancient place, cited: BAtlas 19 A2 Altenburg-Rheinau",
  "bbox": [
    8.604032,
    47.64231,
    8.607958,
    47.644237
  ],
  "reprPoint": [
    8.605995,
    47.6432735
  ],
  "features": [
    {
      "geometry": {
        "type": "Point",
        "coordinates": [
          8.607958,
          47.64231
        ]
      },
      "id": "dare-location",
      "type": "Feature",
      "properties": {
        "description": "Representative point location, site precision",
        "location_precision": "precise",
        "title": "DARE Location",
        "link": "http://pleiades.stoa.org/places/187275/dare-location"
      }
    },
    {
      "geometry": {
        "type": "Point",
        "coordinates": [
          8.604032,
          47.644237
        ]
      },
      "id": "darmc-location-21329",
      "type": "Feature",
      "properties": {
        "description": "1M scale point location",
        "location_precision": "precise",
        "title": "DARMC location 21329",
        "link": "http://pleiades.stoa.org/places/187275/darmc-location-21329"
      }
    }
  ]
}