{
  "type": "FeatureCollection",
  "title": "Coveliacae?",
  "id": "187354",
  "bbox": [
    11.202012,
    47.637352,
    11.202012,
    47.637352
  ],
  "description": "An ancient place, cited: BAtlas 19 D2 Coveliacae?",
  "names": [
    "Coveliacae"
  ],
  "features": [
    {
      "type": "Feature",
      "geometry": {
        "type": "Point",
        "coordinates": [
          11.202012,
          47.637352
        ]
      },
      "properties": {
        "description": "representative point"
      }
    },
    {
      "geometry": {
        "type": "Point",
        "coordinates": [
          11.202012,
          47.637352
        ]
      },
      "id": "darmc-location-7602",
      "type": "Feature",
      "properties": {
        "description": "1M scale point location",
        "location_precision": "precise",
        "title": "DARMC location 7602",
        "link": "http://pleiades.stoa.org/places/187354/darmc-location-7602"
      }
    }
  ]
}