{
  "type": "FeatureCollection",
  "title": "Ernolatia",
  "id": "187371",
  "description": "An ancient place, cited: BAtlas 19 G2 Ernolatia",
  "bbox": [
    14.205657,
    47.764783,
    14.205657,
    47.764783
  ],
  "reprPoint": [
    14.205657,
    47.764783
  ],
  "names": [
    "Ernolatia"
  ],
  "features": [
    {
      "geometry": {
        "type": "Point",
        "coordinates": [
          14.205657,
          47.764783
        ]
      },
      "id": "darmc-location-8591",
      "type": "Feature",
      "properties": {
        "description": "1M scale point location",
        "location_precision": "precise",
        "title": "DARMC location 8591",
        "link": "http://pleiades.stoa.org/places/187371/darmc-location-8591"
      }
    }
  ]
}