{
  "type": "FeatureCollection",
  "title": "Calalzo",
  "id": "187333",
  "bbox": [
    12.383583,
    46.447238,
    12.383583,
    46.447238
  ],
  "description": "An ancient place, cited: BAtlas 19 E3 Calalzo",
  "features": [
    {
      "type": "Feature",
      "geometry": {
        "type": "Point",
        "coordinates": [
          12.383583,
          46.447238
        ]
      },
      "properties": {
        "description": "representative point"
      }
    },
    {
      "geometry": {
        "type": "Point",
        "coordinates": [
          12.383583,
          46.447238
        ]
      },
      "id": "darmc-location-15924",
      "type": "Feature",
      "properties": {
        "description": "1M scale point location",
        "location_precision": "precise",
        "title": "DARMC location 15924",
        "link": "http://pleiades.stoa.org/places/187333/darmc-location-15924"
      }
    }
  ]
}