{
  "type": "FeatureCollection",
  "title": "Balzers",
  "id": "187307",
  "bbox": [
    9.500504,
    47.065134,
    9.500504,
    47.065134
  ],
  "description": "An ancient place, cited: BAtlas 19 B2 Balzers",
  "features": [
    {
      "type": "Feature",
      "geometry": {
        "type": "Point",
        "coordinates": [
          9.500504,
          47.065134
        ]
      },
      "properties": {
        "description": "representative point"
      }
    },
    {
      "geometry": {
        "type": "Point",
        "coordinates": [
          9.500504,
          47.065134
        ]
      },
      "id": "darmc-location-11646",
      "type": "Feature",
      "properties": {
        "description": "1M scale point location",
        "location_precision": "precise",
        "title": "DARMC location 11646",
        "link": "http://pleiades.stoa.org/places/187307/darmc-location-11646"
      }
    }
  ]
}