{
  "type": "FeatureCollection",
  "title": "Filzbach",
  "id": "187379",
  "description": "An ancient place, cited: BAtlas 19 B2 Filzbach",
  "bbox": [
    9.129565,
    47.119155,
    9.129565,
    47.119155
  ],
  "reprPoint": [
    9.129565,
    47.119155
  ],
  "features": [
    {
      "geometry": {
        "type": "Point",
        "coordinates": [
          9.129565,
          47.119155
        ]
      },
      "id": "darmc-location-7756",
      "type": "Feature",
      "properties": {
        "description": "1M scale point location",
        "location_precision": "precise",
        "title": "DARMC location 7756",
        "link": "http://pleiades.stoa.org/places/187379/darmc-location-7756"
      }
    }
  ]
}