{
  "type": "FeatureCollection",
  "title": "*Bedaium",
  "id": "187309",
  "bbox": [
    12.477721,
    47.934824,
    12.477721,
    47.934824
  ],
  "description": "An ancient place, cited: BAtlas 19 E2 *Bedaium",
  "names": [
    "Bedaium"
  ],
  "features": [
    {
      "type": "Feature",
      "geometry": {
        "type": "Point",
        "coordinates": [
          12.477721,
          47.934824
        ]
      },
      "properties": {
        "description": "representative point"
      }
    },
    {
      "geometry": {
        "type": "Point",
        "coordinates": [
          12.477721,
          47.934824
        ]
      },
      "id": "darmc-location-11678",
      "type": "Feature",
      "properties": {
        "description": "1M scale point location",
        "location_precision": "precise",
        "title": "DARMC location 11678",
        "link": "http://pleiades.stoa.org/places/187309/darmc-location-11678"
      }
    }
  ]
}