{
  "type": "FeatureCollection",
  "title": "Duel",
  "id": "187365",
  "bbox": [
    13.648147,
    46.6988267,
    13.648147,
    46.6988267
  ],
  "description": "An ancient place, cited: BAtlas 19 F3 Duel",
  "features": [
    {
      "type": "Feature",
      "geometry": {
        "type": "Point",
        "coordinates": [
          13.648147,
          46.6988267
        ]
      },
      "properties": {
        "description": "representative point"
      }
    },
    {
      "geometry": {
        "type": "Point",
        "coordinates": [
          13.648147,
          46.6988267
        ]
      },
      "id": "osm-location-of-kastell-duel",
      "type": "Feature",
      "properties": {
        "description": "Representative location based on OpenStreetMap",
        "location_precision": "precise",
        "title": "OSM location of Kastell Duel",
        "link": "http://pleiades.stoa.org/places/187365/osm-location-of-kastell-duel"
      }
    }
  ]
}