{
  "type": "FeatureCollection",
  "title": "[Glemona]",
  "id": "187394",
  "description": "An ancient place, cited: BAtlas 19 F3 [Glemona]",
  "bbox": [
    13.139752,
    46.27711,
    13.139752,
    46.27711
  ],
  "connectsWith": [
    "788760849"
  ],
  "reprPoint": [
    13.139752,
    46.27711
  ],
  "names": [
    "Glemona"
  ],
  "features": [
    {
      "geometry": {
        "type": "Point",
        "coordinates": [
          13.139752,
          46.27711
        ]
      },
      "id": "darmc-location-6601",
      "type": "Feature",
      "properties": {
        "description": "1M scale point location",
        "location_precision": "precise",
        "title": "DARMC location 6601",
        "link": "http://pleiades.stoa.org/places/187394/darmc-location-6601"
      }
    }
  ]
}