{
  "type": "FeatureCollection",
  "title": "Bellunum",
  "id": "187311",
  "bbox": [
    12.217395,
    46.140031,
    12.217395,
    46.140031
  ],
  "description": "An ancient place, cited: BAtlas 19 E3 Bellunum",
  "names": [
    "Bellunum"
  ],
  "features": [
    {
      "type": "Feature",
      "geometry": {
        "type": "Point",
        "coordinates": [
          12.217395,
          46.140031
        ]
      },
      "properties": {
        "description": "representative point"
      }
    },
    {
      "geometry": {
        "type": "Point",
        "coordinates": [
          12.217395,
          46.140031
        ]
      },
      "id": "darmc-location-11690",
      "type": "Feature",
      "properties": {
        "description": "1M scale point location",
        "location_precision": "precise",
        "title": "DARMC location 11690",
        "link": "http://pleiades.stoa.org/places/187311/darmc-location-11690"
      }
    }
  ]
}