{
  "type": "FeatureCollection",
  "title": "Duel",
  "id": "187365",
  "bbox": [
    13.656949,
    46.698892,
    13.656949,
    46.698892
  ],
  "description": "An ancient place, cited: BAtlas 19 F3 Duel",
  "features": [
    {
      "type": "Feature",
      "geometry": {
        "type": "Point",
        "coordinates": [
          13.656949,
          46.698892
        ]
      },
      "properties": {
        "description": "representative point"
      }
    },
    {
      "geometry": {
        "type": "Point",
        "coordinates": [
          13.656949,
          46.698892
        ]
      },
      "id": "darmc-location-12274",
      "type": "Feature",
      "properties": {
        "description": "1M scale point location",
        "location_precision": "precise",
        "title": "DARMC location 12274",
        "link": "http://pleiades.stoa.org/places/187365/darmc-location-12274"
      }
    }
  ]
}