{
  "type": "FeatureCollection",
  "title": "[Enemase]",
  "id": "187369",
  "description": "An ancient place, cited: BAtlas 19 D3 [Enemase]",
  "bbox": [
    11.289643,
    46.337585,
    11.289643,
    46.337585
  ],
  "reprPoint": [
    11.289643,
    46.337585
  ],
  "names": [
    "Enemase"
  ],
  "features": [
    {
      "geometry": {
        "type": "Point",
        "coordinates": [
          11.289643,
          46.337585
        ]
      },
      "id": "darmc-location-6648",
      "type": "Feature",
      "properties": {
        "description": "1M scale point location",
        "location_precision": "precise",
        "title": "DARMC location 6648",
        "link": "http://pleiades.stoa.org/places/187369/darmc-location-6648"
      }
    }
  ]
}