{
  "type": "FeatureCollection",
  "title": "Forum Iulii",
  "id": "187386",
  "bbox": [
    13.431685,
    46.090625,
    13.434992,
    46.093107
  ],
  "description": "A settlement  founded as a Roman municipium along the line of the Via Iulia Augusta by Julius Caesar ca. 50 BCE (cited: BAtlas 19 F3 Forum Iulii)",
  "names": [
    "Forum Iulii",
    "Cividale del Friuli"
  ],
  "features": [
    {
      "type": "Feature",
      "geometry": {
        "type": "Point",
        "coordinates": [
          13.4333385,
          46.091866
        ]
      },
      "properties": {
        "description": "representative point"
      }
    },
    {
      "geometry": {
        "type": "Point",
        "coordinates": [
          13.434992,
          46.090625
        ]
      },
      "id": "darmc-location-12447",
      "type": "Feature",
      "properties": {
        "description": "1:1 million scale representative point location digitized from the Barrington Atlas of the Greek and Roman World by the Digital Atlas of Roman and Medieval Civilizations project at Harvard University.",
        "location_precision": "precise",
        "title": "DARMC location 12447",
        "link": "http://pleiades.stoa.org/places/187386/darmc-location-12447"
      }
    },
    {
      "geometry": {
        "type": "Point",
        "coordinates": [
          13.431685,
          46.093107
        ]
      },
      "id": "dare-location",
      "type": "Feature",
      "properties": {
        "description": "Representative point location, site precision",
        "location_precision": "precise",
        "title": "DARE Location",
        "link": "http://pleiades.stoa.org/places/187386/dare-location"
      }
    }
  ]
}