{
  "type": "FeatureCollection",
  "title": "Maiensis Statio",
  "id": "187465",
  "bbox": [
    11.163976,
    46.669126,
    11.1690766,
    46.6716426
  ],
  "description": "An ancient place, cited: BAtlas 19 D3 Maiensis Statio",
  "names": [
    "Maiensis Statio"
  ],
  "features": [
    {
      "type": "Feature",
      "geometry": {
        "type": "Point",
        "coordinates": [
          11.1665263,
          46.6703843
        ]
      },
      "properties": {
        "description": "representative point"
      }
    },
    {
      "geometry": {
        "type": "Point",
        "coordinates": [
          11.163976,
          46.669126
        ]
      },
      "id": "darmc-location-8060",
      "type": "Feature",
      "properties": {
        "description": "1M scale point location",
        "location_precision": "precise",
        "title": "DARMC location 8060",
        "link": "http://pleiades.stoa.org/places/187465/darmc-location-8060"
      }
    },
    {
      "geometry": {
        "type": "Point",
        "coordinates": [
          11.1690766,
          46.6716426
        ]
      },
      "id": "location-of-river-bridge",
      "type": "Feature",
      "properties": {
        "description": "Location based on OpenStreetMap",
        "location_precision": "precise",
        "title": "location of Roman bridge",
        "link": "http://pleiades.stoa.org/places/187465/location-of-river-bridge"
      }
    }
  ]
}