{
  "type": "FeatureCollection",
  "title": "Isinisca",
  "id": "187426",
  "bbox": [
    11.76939,
    47.920814,
    11.76939,
    47.920814
  ],
  "description": "An ancient place, cited: BAtlas 19 D2 Isinisca",
  "names": [
    "Isinisca"
  ],
  "features": [
    {
      "type": "Feature",
      "geometry": {
        "type": "Point",
        "coordinates": [
          11.76939,
          47.920814
        ]
      },
      "properties": {
        "description": "representative point"
      }
    },
    {
      "geometry": {
        "type": "Point",
        "coordinates": [
          11.76939,
          47.920814
        ]
      },
      "id": "darmc-location-8683",
      "type": "Feature",
      "properties": {
        "description": "1M scale point location",
        "location_precision": "precise",
        "title": "DARMC location 8683",
        "link": "http://pleiades.stoa.org/places/187426/darmc-location-8683"
      }
    }
  ]
}