{
  "type": "FeatureCollection",
  "title": "Gurina",
  "id": "187403",
  "description": "An ancient place, cited: BAtlas 19 F3 Gurina",
  "bbox": [
    13.079529,
    46.661699,
    13.079529,
    46.661699
  ],
  "reprPoint": [
    13.079529,
    46.661699
  ],
  "features": [
    {
      "geometry": {
        "type": "Point",
        "coordinates": [
          13.079529,
          46.661699
        ]
      },
      "id": "darmc-location-12629",
      "type": "Feature",
      "properties": {
        "description": "1M scale point location",
        "location_precision": "precise",
        "title": "DARMC location 12629",
        "link": "http://pleiades.stoa.org/places/187403/darmc-location-12629"
      }
    }
  ]
}