{
  "type": "FeatureCollection",
  "title": "Gummern",
  "id": "187402",
  "description": "An ancient place, cited: BAtlas 19 F3 Gummern",
  "bbox": [
    13.768338,
    46.655517,
    13.768338,
    46.655517
  ],
  "reprPoint": [
    13.768338,
    46.655517
  ],
  "features": [
    {
      "geometry": {
        "type": "Point",
        "coordinates": [
          13.768338,
          46.655517
        ]
      },
      "id": "darmc-location-9226",
      "type": "Feature",
      "properties": {
        "description": "1M scale point location",
        "location_precision": "precise",
        "title": "DARMC location 9226",
        "link": "http://pleiades.stoa.org/places/187402/darmc-location-9226"
      }
    }
  ]
}