{
  "type": "FeatureCollection",
  "title": "Matrei",
  "id": "187469",
  "description": "An ancient place, cited: BAtlas 19 E2 Matrei",
  "bbox": [
    12.541439,
    46.996813,
    12.541439,
    46.996813
  ],
  "reprPoint": [
    12.541439,
    46.996813
  ],
  "features": [
    {
      "geometry": {
        "type": "Point",
        "coordinates": [
          12.541439,
          46.996813
        ]
      },
      "id": "darmc-location-9266",
      "type": "Feature",
      "properties": {
        "description": "1M scale point location",
        "location_precision": "precise",
        "title": "DARMC location 9266",
        "link": "http://pleiades.stoa.org/places/187469/darmc-location-9266"
      }
    }
  ]
}