{
  "type": "FeatureCollection",
  "title": "Statio Timaviensis",
  "id": "187558",
  "description": "An ancient place, cited: BAtlas 19 F3 Statio Timaviensis",
  "bbox": [
    13.001737,
    46.584765,
    13.001737,
    46.584765
  ],
  "reprPoint": [
    13.001737,
    46.584765
  ],
  "names": [
    "Statio Timaviensis"
  ],
  "features": [
    {
      "geometry": {
        "type": "Point",
        "coordinates": [
          13.001737,
          46.584765
        ]
      },
      "id": "darmc-location-8631",
      "type": "Feature",
      "properties": {
        "description": "1M scale point location",
        "location_precision": "precise",
        "title": "DARMC location 8631",
        "link": "http://pleiades.stoa.org/places/187558/darmc-location-8631"
      }
    }
  ]
}