{
  "type": "FeatureCollection",
  "title": "Pillerhöhe",
  "id": "187510",
  "description": "An ancient place, cited: BAtlas 19 C2 Pillerhöhe",
  "bbox": [
    10.667092,
    47.118282,
    10.667092,
    47.118282
  ],
  "reprPoint": [
    10.667092,
    47.118282
  ],
  "features": [
    {
      "geometry": {
        "type": "Point",
        "coordinates": [
          10.667092,
          47.118282
        ]
      },
      "id": "darmc-location-16141",
      "type": "Feature",
      "properties": {
        "description": "1M scale point location",
        "location_precision": "precise",
        "title": "DARMC location 16141",
        "link": "http://pleiades.stoa.org/places/187510/darmc-location-16141"
      }
    }
  ]
}