{
  "type": "FeatureCollection",
  "title": "Treffen",
  "id": "187592",
  "description": "An ancient place, cited: BAtlas 19 F3 Treffen",
  "bbox": [
    13.854454,
    46.668245,
    13.854454,
    46.668245
  ],
  "reprPoint": [
    13.854454,
    46.668245
  ],
  "features": [
    {
      "geometry": {
        "type": "Point",
        "coordinates": [
          13.854454,
          46.668245
        ]
      },
      "id": "darmc-location-9572",
      "type": "Feature",
      "properties": {
        "description": "1M scale point location",
        "location_precision": "precise",
        "title": "DARMC location 9572",
        "link": "http://pleiades.stoa.org/places/187592/darmc-location-9572"
      }
    }
  ]
}