{
  "type": "FeatureCollection",
  "title": "Schaan",
  "id": "187541",
  "description": "An ancient place, cited: BAtlas 19 B2 Schaan",
  "bbox": [
    9.508578,
    47.163854,
    9.508578,
    47.163854
  ],
  "reprPoint": [
    9.508578,
    47.163854
  ],
  "features": [
    {
      "geometry": {
        "type": "Point",
        "coordinates": [
          9.508578,
          47.163854
        ]
      },
      "id": "darmc-location-8279",
      "type": "Feature",
      "properties": {
        "description": "1M scale point location",
        "location_precision": "precise",
        "title": "DARMC location 8279",
        "link": "http://pleiades.stoa.org/places/187541/darmc-location-8279"
      }
    }
  ]
}