{
  "type": "FeatureCollection",
  "title": "Santicum",
  "id": "187537",
  "bbox": [
    13.848725,
    46.615977,
    13.848725,
    46.615977
  ],
  "description": "A settlement located at a favorable crossing over the Drau river that was an important road junction.",
  "names": [
    "Santicum",
    "Villach"
  ],
  "features": [
    {
      "type": "Feature",
      "geometry": {
        "type": "Point",
        "coordinates": [
          13.848725,
          46.615977
        ]
      },
      "properties": {
        "description": "representative point"
      }
    },
    {
      "geometry": {
        "type": "Point",
        "coordinates": [
          13.848725,
          46.615977
        ]
      },
      "id": "darmc-location-8944",
      "type": "Feature",
      "properties": {
        "description": "1M scale point location",
        "location_precision": "precise",
        "title": "DARMC location 8944",
        "link": "http://pleiades.stoa.org/places/187537/darmc-location-8944"
      }
    }
  ]
}