{
  "type": "FeatureCollection",
  "title": "Riom",
  "id": "187530",
  "bbox": [
    9.581967,
    46.609377,
    9.581967,
    46.609377
  ],
  "description": "An ancient place, cited: BAtlas 19 B3 Riom",
  "features": [
    {
      "type": "Feature",
      "geometry": {
        "type": "Point",
        "coordinates": [
          9.581967,
          46.609377
        ]
      },
      "properties": {
        "description": "representative point"
      }
    },
    {
      "geometry": {
        "type": "Point",
        "coordinates": [
          9.581967,
          46.609377
        ]
      },
      "id": "darmc-location-8939",
      "type": "Feature",
      "properties": {
        "description": "1M scale point location",
        "location_precision": "precise",
        "title": "DARMC location 8939",
        "link": "http://pleiades.stoa.org/places/187530/darmc-location-8939"
      }
    }
  ]
}