{
  "type": "FeatureCollection",
  "title": "Tiliaventum fl.",
  "id": "187585",
  "description": "An ancient place, cited: BAtlas 19 E3 Tiliaventum fl.",
  "bbox": [
    13.0614613,
    45.6598441,
    13.0614613,
    45.6598441
  ],
  "reprPoint": [
    13.0614613,
    45.6598441
  ],
  "names": [
    "Tiliaventum",
    "Tiliaventum Maius",
    "Tiliaventum Minus"
  ],
  "features": [
    {
      "geometry": {
        "type": "Point",
        "coordinates": [
          13.0614613,
          45.6598441
        ]
      },
      "id": "location-of-fiume-tagliamento",
      "type": "Feature",
      "properties": {
        "description": "Location based on OpenStreetMap",
        "location_precision": "precise",
        "title": "location of Fiume Tagliamento",
        "link": "http://pleiades.stoa.org/places/187585/location-of-fiume-tagliamento"
      }
    }
  ]
}