{
  "type": "FeatureCollection",
  "title": "Tarrenz",
  "id": "187569",
  "bbox": [
    10.762062,
    47.262394,
    10.762062,
    47.262394
  ],
  "description": "An ancient place, cited: BAtlas 19 C2 Tarrenz",
  "features": [
    {
      "type": "Feature",
      "geometry": {
        "type": "Point",
        "coordinates": [
          10.762062,
          47.262394
        ]
      },
      "properties": {
        "description": "representative point"
      }
    },
    {
      "geometry": {
        "type": "Point",
        "coordinates": [
          10.762062,
          47.262394
        ]
      },
      "id": "darmc-location-15014",
      "type": "Feature",
      "properties": {
        "description": "1M scale point location",
        "location_precision": "precise",
        "title": "DARMC location 15014",
        "link": "http://pleiades.stoa.org/places/187569/darmc-location-15014"
      }
    }
  ]
}