{
  "type": "FeatureCollection",
  "title": "Tenna",
  "id": "187577",
  "description": "An ancient place, cited: BAtlas 19 D3 Tenna",
  "bbox": [
    11.265332,
    46.016835,
    11.265332,
    46.016835
  ],
  "reprPoint": [
    11.265332,
    46.016835
  ],
  "features": [
    {
      "geometry": {
        "type": "Point",
        "coordinates": [
          11.265332,
          46.016835
        ]
      },
      "id": "darmc-location-15075",
      "type": "Feature",
      "properties": {
        "description": "1M scale point location",
        "location_precision": "precise",
        "title": "DARMC location 15075",
        "link": "http://pleiades.stoa.org/places/187577/darmc-location-15075"
      }
    }
  ]
}