{
  "type": "FeatureCollection",
  "title": "Siniyah Island Monastery",
  "id": "191480805",
  "bbox": [
    55.647662,
    25.619172,
    55.647662,
    25.619172
  ],
  "description": "A church and possible monastic complex identified in 2021/2022 on modern Siniyah Island in the emirate of Umm al-Quwain, UAE.",
  "features": [
    {
      "type": "Feature",
      "geometry": {
        "type": "Point",
        "coordinates": [
          55.647662,
          25.619172
        ]
      },
      "properties": {
        "description": "representative point"
      }
    },
    {
      "geometry": {
        "type": "Point",
        "coordinates": [
          55.647662,
          25.619172
        ]
      },
      "id": "imagery-location-of-excavated-area",
      "type": "Feature",
      "properties": {
        "description": "Location determined and located in Google Earth with reference to information and imagery in New Arab article (2022). Dates after article as well.",
        "location_precision": "precise",
        "title": "Imagery Location of excavated area",
        "link": "http://pleiades.stoa.org/places/191480805/imagery-location-of-excavated-area"
      }
    }
  ]
}