{
  "type": "FeatureCollection",
  "title": "Holme Roman temporary camp",
  "id": "191547538",
  "bbox": [
    -0.7896067,
    53.1240053,
    -0.7896067,
    53.1240053
  ],
  "description": "A Roman marching camp covering 9.3 ha.",
  "features": [
    {
      "type": "Feature",
      "geometry": {
        "type": "Point",
        "coordinates": [
          -0.7896067,
          53.1240053
        ]
      },
      "properties": {
        "description": "representative point"
      }
    },
    {
      "geometry": {
        "type": "Point",
        "coordinates": [
          -0.7896067,
          53.1240053
        ]
      },
      "id": "osm-location",
      "type": "Feature",
      "properties": {
        "description": "Representative location based on OpenStreetMap.",
        "location_precision": "precise",
        "title": "OSM location of Holme marching camp",
        "link": "http://pleiades.stoa.org/places/191547538/osm-location"
      }
    }
  ]
}