{
  "type": "FeatureCollection",
  "title": "Julier Pass",
  "id": "191774",
  "description": "An ancient place, cited: BAtlas 19 B3 no. 3 (Julier Pass)",
  "bbox": [
    9.7276274,
    46.4721226,
    9.7276274,
    46.4721226
  ],
  "reprPoint": [
    9.7276274,
    46.4721226
  ],
  "features": [
    {
      "geometry": {
        "type": "Point",
        "coordinates": [
          9.7276274,
          46.4721226
        ]
      },
      "id": "osm-location",
      "type": "Feature",
      "properties": {
        "description": "Representative point derived from an OpenStreetMap node.",
        "location_precision": "precise",
        "title": "OSM location",
        "link": "http://pleiades.stoa.org/places/191774/osm-location"
      }
    }
  ]
}