{
  "type": "FeatureCollection",
  "title": "Julier Pass",
  "id": "191774",
  "bbox": [
    9.7276274,
    46.4721226,
    9.7281114,
    46.4722189
  ],
  "description": "An ancient place, cited: BAtlas 19 B3 no. 3 (Julier Pass)",
  "features": [
    {
      "type": "Feature",
      "geometry": {
        "type": "Point",
        "coordinates": [
          9.7278694,
          46.47217075
        ]
      },
      "properties": {
        "description": "representative point"
      }
    },
    {
      "geometry": {
        "type": "Point",
        "coordinates": [
          9.7276274,
          46.4721226
        ]
      },
      "id": "osm-location",
      "type": "Feature",
      "properties": {
        "description": "Representative point derived from an OpenStreetMap node.",
        "location_precision": "precise",
        "title": "OSM location",
        "link": "http://pleiades.stoa.org/places/191774/osm-location"
      }
    },
    {
      "geometry": {
        "type": "Point",
        "coordinates": [
          9.7281114,
          46.4722189
        ]
      },
      "id": "osm-location-of-pass-dal-ga1-4glia",
      "type": "Feature",
      "properties": {
        "description": "Location based on OpenStreetMap",
        "location_precision": "precise",
        "title": "OSM location of Pass dal Güglia",
        "link": "http://pleiades.stoa.org/places/191774/osm-location-of-pass-dal-ga1-4glia"
      }
    }
  ]
}