{
  "type": "FeatureCollection",
  "title": "Zas Cave",
  "id": "194606909",
  "bbox": [
    25.4989159,
    37.0349061,
    25.4989159,
    37.0349061
  ],
  "description": "A sacred cave located on Mt. Zas on the island of Naxos, Zas Cave preserves evidence of human occupation ranging from the Late Neolithic period to the Early Cycladic III period. Local tradition holds that the sky god Zeus hid from Cronus in the cave. Rock cuttings in the area refer to \"Zeus Melosios\".",
  "connectsWith": [
    "599822"
  ],
  "names": [
    "Cave of Zas (Naxos)"
  ],
  "features": [
    {
      "type": "Feature",
      "geometry": {
        "type": "Point",
        "coordinates": [
          25.4989159,
          37.0349061
        ]
      },
      "properties": {
        "description": "representative point"
      }
    },
    {
      "geometry": {
        "type": "Point",
        "coordinates": [
          25.4989159,
          37.0349061
        ]
      },
      "id": "osm-location-of-zas-cave",
      "type": "Feature",
      "properties": {
        "description": "Representative location based on OpenStreetMap",
        "location_precision": "precise",
        "title": "OSM location of Zas Cave",
        "link": "http://pleiades.stoa.org/places/194606909/osm-location-of-zas-cave"
      }
    }
  ]
}