{
  "type": "FeatureCollection",
  "title": "Spera",
  "id": "195955354",
  "bbox": [
    -5.8060565,
    36.8716918,
    -5.8060565,
    36.8716918
  ],
  "description": "A Spanish village located in the north of Cádiz, between Sevilla and Cádiz, and that belonged to the kingdom of Alfonso X. It is now known as Espera.",
  "names": [
    "Spera",
    "Espera"
  ],
  "features": [
    {
      "type": "Feature",
      "geometry": {
        "type": "Point",
        "coordinates": [
          -5.8060565,
          36.8716918
        ]
      },
      "properties": {
        "description": "representative point"
      }
    },
    {
      "geometry": {
        "type": "Point",
        "coordinates": [
          -5.8060565,
          36.8716918
        ]
      },
      "id": "osm-location-of-espera",
      "type": "Feature",
      "properties": {
        "description": "Location based on OpenStreetMap",
        "location_precision": "precise",
        "title": "OSM location of modern Espera",
        "link": "http://pleiades.stoa.org/places/195955354/osm-location-of-espera"
      }
    }
  ]
}