{
  "type": "FeatureCollection",
  "title": "Litana Silva",
  "id": "196750886",
  "bbox": [
    9.696586,
    44.49452,
    11.349271,
    45.052752
  ],
  "description": "The Litana Silva was a forest located in Gallia Cispadana in the territory of the Boii. It was the site of the defeat of the Roman consul L. Postumius Albinus in 216 BC. Its precise location is uncertain, but it probably lay somewhere in the flat land south of the Po river in Italy.",
  "connectsWith": [
    "383741",
    "393421",
    "383737",
    "383755"
  ],
  "names": [
    "Litana silua"
  ],
  "features": [
    {
      "type": "Feature",
      "geometry": {
        "type": "Point",
        "coordinates": [
          10.5216056,
          44.7735796
        ]
      },
      "properties": {
        "description": "representative point"
      }
    }
  ]
}