{
  "type": "FeatureCollection",
  "title": "Ad Fines (Laktaši)",
  "id": "197061",
  "bbox": [
    17.301666,
    44.906786,
    17.3022887,
    44.9074664
  ],
  "description": "An attested Roman road station that modern scholars have associated with Laktaši near Banja Luka in Bosnia.",
  "names": [
    "Ad Fines"
  ],
  "features": [
    {
      "type": "Feature",
      "geometry": {
        "type": "Point",
        "coordinates": [
          17.30197735,
          44.9071262
        ]
      },
      "properties": {
        "description": "representative point"
      }
    },
    {
      "geometry": {
        "type": "Point",
        "coordinates": [
          17.301666,
          44.906786
        ]
      },
      "id": "dare-location",
      "type": "Feature",
      "properties": {
        "description": "Representative point location, village precision",
        "location_precision": "precise",
        "title": "DARE Location",
        "link": "http://pleiades.stoa.org/places/197061/dare-location"
      }
    },
    {
      "geometry": {
        "type": "Point",
        "coordinates": [
          17.3022887,
          44.9074664
        ]
      },
      "id": "osm-location-of-modern-laktaa-i",
      "type": "Feature",
      "properties": {
        "description": "Location based on OpenStreetMap",
        "location_precision": "precise",
        "title": "OSM location of modern Laktaši",
        "link": "http://pleiades.stoa.org/places/197061/osm-location-of-modern-laktaa-i"
      }
    }
  ]
}