{
  "type": "FeatureCollection",
  "title": "Ad Labores?",
  "id": "197064",
  "description": "An ancient place, cited: BAtlas 20 F4 Ad Labores?",
  "bbox": [
    18.769761,
    45.540045,
    18.769761,
    45.540045
  ],
  "reprPoint": [
    18.769761,
    45.540045
  ],
  "names": [
    "Ad Labores"
  ],
  "features": [
    {
      "geometry": {
        "type": "Point",
        "coordinates": [
          18.769761,
          45.540045
        ]
      },
      "id": "darmc-location-8711",
      "type": "Feature",
      "properties": {
        "description": "1M scale point location",
        "location_precision": "precise",
        "title": "DARMC location 8711",
        "link": "http://pleiades.stoa.org/places/197064/darmc-location-8711"
      }
    }
  ]
}