{
  "type": "FeatureCollection",
  "title": "Aegida",
  "id": "197092",
  "description": "Aegida was an ancient town of Histria that is mentioned only by Pliny the Elder.",
  "bbox": [
    13.764656,
    45.55341,
    13.764656,
    45.55341
  ],
  "reprPoint": [
    13.764656,
    45.55341
  ],
  "names": [
    "Aegida"
  ],
  "features": [
    {
      "geometry": {
        "type": "Point",
        "coordinates": [
          13.764656,
          45.55341
        ]
      },
      "id": "darmc-location-11180",
      "type": "Feature",
      "properties": {
        "description": "1M scale point location",
        "location_precision": "precise",
        "title": "DARMC location 11180",
        "link": "http://pleiades.stoa.org/places/197092/darmc-location-11180"
      }
    }
  ]
}