{
  "type": "FeatureCollection",
  "title": "Ad Turres",
  "id": "197088",
  "bbox": [
    14.689261,
    45.174936,
    14.689261,
    45.174936
  ],
  "description": "An ancient place, cited: BAtlas 20 B4 Ad Turres",
  "names": [
    "Ad Turres"
  ],
  "features": [
    {
      "type": "Feature",
      "geometry": {
        "type": "Point",
        "coordinates": [
          14.689261,
          45.174936
        ]
      },
      "properties": {
        "description": "representative point"
      }
    },
    {
      "geometry": {
        "type": "Point",
        "coordinates": [
          14.689261,
          45.174936
        ]
      },
      "id": "darmc-location-2693",
      "type": "Feature",
      "properties": {
        "description": "1M scale point location",
        "location_precision": "precise",
        "title": "DARMC location 2693",
        "link": "http://pleiades.stoa.org/places/197088/darmc-location-2693"
      }
    }
  ]
}