{
  "type": "FeatureCollection",
  "title": "*Ad Fornulos",
  "id": "197063",
  "bbox": [
    13.713064,
    45.890011,
    13.713064,
    45.890011
  ],
  "description": "An ancient place, cited: BAtlas 20 A4 *Ad Fornulos",
  "names": [
    "Ad Fornulos"
  ],
  "features": [
    {
      "type": "Feature",
      "geometry": {
        "type": "Point",
        "coordinates": [
          13.713064,
          45.890011
        ]
      },
      "properties": {
        "description": "representative point"
      }
    },
    {
      "geometry": {
        "type": "Point",
        "coordinates": [
          13.713064,
          45.890011
        ]
      },
      "id": "darmc-location-8498",
      "type": "Feature",
      "properties": {
        "description": "1M scale point location",
        "location_precision": "precise",
        "title": "DARMC location 8498",
        "link": "http://pleiades.stoa.org/places/197063/darmc-location-8498"
      }
    }
  ]
}