{
  "type": "FeatureCollection",
  "title": "Ad Fines",
  "id": "197061",
  "bbox": [
    17.301666,
    44.906786,
    17.301666,
    44.906786
  ],
  "description": "An ancient place, cited: BAtlas 20 E5 Ad Fines",
  "names": [
    "Ad Fines"
  ],
  "features": [
    {
      "type": "Feature",
      "geometry": {
        "type": "Point",
        "coordinates": [
          17.301666,
          44.906786
        ]
      },
      "properties": {
        "description": "representative point"
      }
    },
    {
      "geometry": {
        "type": "Point",
        "coordinates": [
          17.301666,
          44.906786
        ]
      },
      "id": "dare-location",
      "type": "Feature",
      "properties": {
        "description": "Representative point location, village precision",
        "location_precision": "precise",
        "title": "DARE Location",
        "link": "http://pleiades.stoa.org/places/197061/dare-location"
      }
    }
  ]
}