{
  "type": "FeatureCollection",
  "title": "Bassiana",
  "id": "197160",
  "description": "An ancient place, cited: BAtlas 20 D2 Bassiana",
  "bbox": [
    16.935227,
    47.254062,
    16.935227,
    47.254062
  ],
  "reprPoint": [
    16.935227,
    47.254062
  ],
  "names": [
    "Bassiana"
  ],
  "features": [
    {
      "geometry": {
        "type": "Point",
        "coordinates": [
          16.935227,
          47.254062
        ]
      },
      "id": "darmc-location-2946",
      "type": "Feature",
      "properties": {
        "description": "1M scale point location",
        "location_precision": "precise",
        "title": "DARMC location 2946",
        "link": "http://pleiades.stoa.org/places/197160/darmc-location-2946"
      }
    }
  ]
}