{
  "type": "FeatureCollection",
  "title": "Arba Ins.",
  "id": "197135",
  "description": "Arba Ins. (Rab island) in the Adriatic Sea.",
  "bbox": [
    14.7426317,
    44.7786584,
    14.7426317,
    44.7786584
  ],
  "connectsWith": [
    "1004",
    "197353"
  ],
  "reprPoint": [
    14.7426317,
    44.7786584
  ],
  "names": [
    "Arba"
  ],
  "features": [
    {
      "geometry": {
        "type": "Point",
        "coordinates": [
          14.7426317,
          44.7786584
        ]
      },
      "id": "location-of-Arba-Ins",
      "type": "Feature",
      "properties": {
        "description": "Location based on OpenStreetMap",
        "location_precision": "precise",
        "title": "location of Arba Ins.",
        "link": "http://pleiades.stoa.org/places/197135/location-of-Arba-Ins"
      }
    }
  ]
}