{
  "type": "FeatureCollection",
  "title": "Carnium",
  "id": "197193",
  "description": "An ancient place, cited: BAtlas 20 B3 Carnium",
  "bbox": [
    14.355657,
    46.239202,
    14.355657,
    46.239202
  ],
  "reprPoint": [
    14.355657,
    46.239202
  ],
  "names": [
    "Carnium"
  ],
  "features": [
    {
      "geometry": {
        "type": "Point",
        "coordinates": [
          14.355657,
          46.239202
        ]
      },
      "id": "darmc-location-11910",
      "type": "Feature",
      "properties": {
        "description": "1M scale point location",
        "location_precision": "precise",
        "title": "DARMC location 11910",
        "link": "http://pleiades.stoa.org/places/197193/darmc-location-11910"
      }
    }
  ]
}