{
  "type": "FeatureCollection",
  "title": "Apeva",
  "id": "197121",
  "bbox": [
    17.269098,
    44.340784,
    17.269098,
    44.340784
  ],
  "description": "An ancient place, cited: BAtlas 20 E5 Apeva",
  "names": [
    "Apeva"
  ],
  "features": [
    {
      "type": "Feature",
      "geometry": {
        "type": "Point",
        "coordinates": [
          17.269098,
          44.340784
        ]
      },
      "properties": {
        "description": "representative point"
      }
    },
    {
      "geometry": {
        "type": "Point",
        "coordinates": [
          17.269098,
          44.340784
        ]
      },
      "id": "darmc-location-7975",
      "type": "Feature",
      "properties": {
        "description": "1M scale point location",
        "location_precision": "precise",
        "title": "DARMC location 7975",
        "link": "http://pleiades.stoa.org/places/197121/darmc-location-7975"
      }
    }
  ]
}