{
  "type": "FeatureCollection",
  "title": "Albona",
  "id": "197102",
  "description": "An ancient place, cited: BAtlas 20 B4 Albona",
  "bbox": [
    14.115747,
    45.098398,
    14.115747,
    45.098398
  ],
  "connectsWith": [
    "855236251"
  ],
  "reprPoint": [
    14.115747,
    45.098398
  ],
  "names": [
    "Albona"
  ],
  "features": [
    {
      "geometry": {
        "type": "Point",
        "coordinates": [
          14.115747,
          45.098398
        ]
      },
      "id": "darmc-location-11297",
      "type": "Feature",
      "properties": {
        "description": "1M scale point location",
        "location_precision": "precise",
        "title": "DARMC location 11297",
        "link": "http://pleiades.stoa.org/places/197102/darmc-location-11297"
      }
    }
  ]
}