{
  "type": "FeatureCollection",
  "title": "Arba (island)",
  "id": "197135",
  "bbox": [
    14.7426317,
    44.7786584,
    14.7426317,
    44.7786584
  ],
  "description": "Rab island in the Adriatic Sea.",
  "connectsWith": [
    "1004",
    "197353",
    "197377"
  ],
  "names": [
    "Arba"
  ],
  "features": [
    {
      "type": "Feature",
      "geometry": {
        "type": "Point",
        "coordinates": [
          14.7426317,
          44.7786584
        ]
      },
      "properties": {
        "description": "representative point"
      }
    },
    {
      "geometry": {
        "type": "Point",
        "coordinates": [
          14.7426317,
          44.7786584
        ]
      },
      "id": "location-of-rab-island",
      "type": "Feature",
      "properties": {
        "description": "Representative ocation based on OpenStreetMap.",
        "location_precision": "precise",
        "title": "OSM location of Rab island",
        "link": "http://pleiades.stoa.org/places/197135/location-of-rab-island"
      }
    }
  ]
}