{
  "type": "FeatureCollection",
  "title": "Gorsium/Herculia",
  "id": "197287",
  "description": "An ancient place, cited: BAtlas 20 F2 Gorsium/Herculia",
  "bbox": [
    18.420278,
    47.089722,
    18.420278,
    47.089722
  ],
  "reprPoint": [
    18.420278,
    47.089722
  ],
  "names": [
    "Tác",
    "Gorsium",
    "Herculia"
  ],
  "features": [
    {
      "geometry": {
        "type": "Point",
        "coordinates": [
          18.420278,
          47.089722
        ]
      },
      "id": "dare-location",
      "type": "Feature",
      "properties": {
        "description": "Representative point location, site precision",
        "location_precision": "precise",
        "title": "DARE Location",
        "link": "http://pleiades.stoa.org/places/197287/dare-location"
      }
    },
    {
      "geometry": {
        "type": "Point",
        "coordinates": [
          18.420373,
          47.089886
        ]
      },
      "id": "darmc-location-12589",
      "type": "Feature",
      "properties": {
        "description": "1M scale point location",
        "location_precision": "precise",
        "title": "DARMC location 12589",
        "link": "http://pleiades.stoa.org/places/197287/darmc-location-12589"
      }
    }
  ]
}