{
  "type": "FeatureCollection",
  "title": "Cibalae",
  "id": "197207",
  "description": "An ancient place, cited: BAtlas 20 F4 Cibalae",
  "bbox": [
    18.801056,
    45.291016,
    18.801056,
    45.291016
  ],
  "reprPoint": [
    18.801056,
    45.291016
  ],
  "names": [
    "Cibalae"
  ],
  "features": [
    {
      "geometry": {
        "type": "Point",
        "coordinates": [
          18.801056,
          45.291016
        ]
      },
      "id": "darmc-location-12029",
      "type": "Feature",
      "properties": {
        "description": "1M scale point location",
        "location_precision": "precise",
        "title": "DARMC location 12029",
        "link": "http://pleiades.stoa.org/places/197207/darmc-location-12029"
      }
    }
  ]
}