{
  "type": "FeatureCollection",
  "title": "Iovia",
  "id": "197326",
  "bbox": [
    16.61509,
    46.253769,
    16.61509,
    46.253769
  ],
  "description": "An ancient place, cited: BAtlas 20 D3 Iovia",
  "names": [
    "Iovia"
  ],
  "features": [
    {
      "type": "Feature",
      "geometry": {
        "type": "Point",
        "coordinates": [
          16.61509,
          46.253769
        ]
      },
      "properties": {
        "description": "representative point"
      }
    },
    {
      "geometry": {
        "type": "Point",
        "coordinates": [
          16.61509,
          46.253769
        ]
      },
      "id": "darmc-location-1867",
      "type": "Feature",
      "properties": {
        "description": "1M scale point location",
        "location_precision": "precise",
        "title": "DARMC location 1867",
        "link": "http://pleiades.stoa.org/places/197326/darmc-location-1867"
      }
    }
  ]
}