{
  "type": "FeatureCollection",
  "title": "Lugio/Florentia",
  "id": "197360",
  "bbox": [
    18.761297,
    46.0881113,
    18.7617279,
    46.091147
  ],
  "description": "An ancient place, cited: BAtlas 20 F3 Lugio/Florentia",
  "names": [
    "Lugio",
    "Florentia"
  ],
  "features": [
    {
      "type": "Feature",
      "geometry": {
        "type": "Point",
        "coordinates": [
          18.76151245,
          46.08962915
        ]
      },
      "properties": {
        "description": "representative point"
      }
    },
    {
      "geometry": {
        "type": "Point",
        "coordinates": [
          18.761297,
          46.091147
        ]
      },
      "id": "dare-location",
      "type": "Feature",
      "properties": {
        "description": "Representative point location, site precision",
        "location_precision": "precise",
        "title": "DARE Location",
        "link": "http://pleiades.stoa.org/places/197360/dare-location"
      }
    },
    {
      "geometry": {
        "type": "Point",
        "coordinates": [
          18.7617279,
          46.0881113
        ]
      },
      "id": "osm-location-of-florentia",
      "type": "Feature",
      "properties": {
        "description": "Representative location based on OpenStreetMap",
        "location_precision": "precise",
        "title": "OSM location of Florentia",
        "link": "http://pleiades.stoa.org/places/197360/osm-location-of-florentia"
      }
    }
  ]
}