{
  "type": "FeatureCollection",
  "title": "Nagykovácsi",
  "id": "197396",
  "description": "An ancient place, cited: BAtlas 20 F2 Nagykovácsi",
  "bbox": [
    18.878428,
    47.575858,
    18.878428,
    47.575858
  ],
  "reprPoint": [
    18.878428,
    47.575858
  ],
  "features": [
    {
      "geometry": {
        "type": "Point",
        "coordinates": [
          18.878428,
          47.575858
        ]
      },
      "id": "darmc-location-13859",
      "type": "Feature",
      "properties": {
        "description": "1M scale point location",
        "location_precision": "precise",
        "title": "DARMC location 13859",
        "link": "http://pleiades.stoa.org/places/197396/darmc-location-13859"
      }
    }
  ]
}