{
  "type": "FeatureCollection",
  "title": "Leusaba",
  "id": "197350",
  "description": "An ancient place, cited: BAtlas 20 E5 Leusaba",
  "bbox": [
    17.083952,
    44.416993,
    17.083952,
    44.416993
  ],
  "reprPoint": [
    17.083952,
    44.416993
  ],
  "names": [
    "Leusaba"
  ],
  "features": [
    {
      "geometry": {
        "type": "Point",
        "coordinates": [
          17.083952,
          44.416993
        ]
      },
      "id": "darmc-location-8902",
      "type": "Feature",
      "properties": {
        "description": "1M scale point location",
        "location_precision": "precise",
        "title": "DARMC location 8902",
        "link": "http://pleiades.stoa.org/places/197350/darmc-location-8902"
      }
    }
  ]
}