{
  "type": "FeatureCollection",
  "title": "Metulum",
  "id": "197380",
  "description": "An ancient place, cited: BAtlas 20 C4 Metulum",
  "bbox": [
    15.299752,
    45.209371,
    15.299752,
    45.209371
  ],
  "reprPoint": [
    15.299752,
    45.209371
  ],
  "names": [
    "Metulum"
  ],
  "features": [
    {
      "geometry": {
        "type": "Point",
        "coordinates": [
          15.299752,
          45.209371
        ]
      },
      "id": "darmc-location-13728",
      "type": "Feature",
      "properties": {
        "description": "1M scale point location",
        "location_precision": "precise",
        "title": "DARMC location 13728",
        "link": "http://pleiades.stoa.org/places/197380/darmc-location-13728"
      }
    }
  ]
}