{
  "type": "FeatureCollection",
  "title": "‘Mestrianis’",
  "id": "197378",
  "description": "An ancient place, cited: BAtlas 20 E3 ‘Mestrianis’",
  "bbox": [
    17.071344,
    46.942773,
    17.071344,
    46.942773
  ],
  "reprPoint": [
    17.071344,
    46.942773
  ],
  "names": [
    "Mestrianis"
  ],
  "features": [
    {
      "geometry": {
        "type": "Point",
        "coordinates": [
          17.071344,
          46.942773
        ]
      },
      "id": "darmc-location-13718",
      "type": "Feature",
      "properties": {
        "description": "1M scale point location",
        "location_precision": "precise",
        "title": "DARMC location 13718",
        "link": "http://pleiades.stoa.org/places/197378/darmc-location-13718"
      }
    }
  ]
}