{
  "type": "FeatureCollection",
  "title": "Lugio/Florentia",
  "id": "197360",
  "description": "An ancient place, cited: BAtlas 20 F3 Lugio/Florentia",
  "bbox": [
    18.761297,
    46.091147,
    18.761297,
    46.091147
  ],
  "reprPoint": [
    18.761297,
    46.091147
  ],
  "names": [
    "Lugio",
    "Florentia"
  ],
  "features": [
    {
      "geometry": {
        "type": "Point",
        "coordinates": [
          18.761297,
          46.091147
        ]
      },
      "id": "dare-location",
      "type": "Feature",
      "properties": {
        "description": "Representative point location, site precision",
        "location_precision": "precise",
        "title": "DARE Location",
        "link": "http://pleiades.stoa.org/places/197360/dare-location"
      }
    },
    {
      "geometry": {
        "type": "Point",
        "coordinates": [
          18.758743,
          46.081535
        ]
      },
      "id": "darmc-location-7933",
      "type": "Feature",
      "properties": {
        "description": "1M scale point location",
        "location_precision": "precise",
        "title": "DARMC location 7933",
        "link": "http://pleiades.stoa.org/places/197360/darmc-location-7933"
      }
    }
  ]
}