{
  "type": "FeatureCollection",
  "title": "Hyllis Pr.",
  "id": "197309",
  "description": "An ancient place, cited: BAtlas 20 C6 Hyllis Pr.",
  "bbox": [
    15.9689188,
    43.4932638,
    15.9689188,
    43.4932638
  ],
  "reprPoint": [
    15.9689188,
    43.4932638
  ],
  "names": [
    "Hyllis Pr."
  ],
  "features": [
    {
      "geometry": {
        "type": "Point",
        "coordinates": [
          15.9689188,
          43.4932638
        ]
      },
      "id": "location-of-punta-planka",
      "type": "Feature",
      "properties": {
        "description": "Location based on OpenStreetMap",
        "location_precision": "precise",
        "title": "location of Punta Planka",
        "link": "http://pleiades.stoa.org/places/197309/location-of-punta-planka"
      }
    }
  ]
}