{
  "type": "FeatureCollection",
  "title": "*Ponte Navata",
  "id": "197452",
  "description": "*Ponte Navata, a late Roman fort on Sibrik hill, Visegrád.",
  "bbox": [
    18.980086,
    47.798208,
    18.980086,
    47.798208
  ],
  "reprPoint": [
    18.980086,
    47.798208
  ],
  "names": [
    "Ponte Navata"
  ],
  "features": [
    {
      "geometry": {
        "type": "Point",
        "coordinates": [
          18.980086,
          47.798208
        ]
      },
      "id": "dare-location",
      "type": "Feature",
      "properties": {
        "description": "Representative point location, site precision",
        "location_precision": "precise",
        "title": "DARE Location",
        "link": "http://pleiades.stoa.org/places/197452/dare-location"
      }
    },
    {
      "geometry": {
        "type": "Point",
        "coordinates": [
          18.9811222,
          47.7979363
        ]
      },
      "id": "location-of-ponte-navata",
      "type": "Feature",
      "properties": {
        "description": "Location based on OpenStreetMap",
        "location_precision": "precise",
        "title": "location of Ponte Navata",
        "link": "http://pleiades.stoa.org/places/197452/location-of-ponte-navata"
      }
    }
  ]
}