{
  "type": "FeatureCollection",
  "title": "Neapolis",
  "id": "197403",
  "description": "An ancient place, cited: BAtlas 20 A4 Neapolis",
  "bbox": [
    13.562104,
    45.315245,
    13.562104,
    45.315245
  ],
  "reprPoint": [
    13.562104,
    45.315245
  ],
  "names": [
    "Neapolis",
    "Emoniia",
    "Emonia"
  ],
  "features": [
    {
      "geometry": {
        "type": "Point",
        "coordinates": [
          13.562104,
          45.315245
        ]
      },
      "id": "dare-location",
      "type": "Feature",
      "properties": {
        "description": "Representative point location, village precision",
        "location_precision": "precise",
        "title": "DARE Location",
        "link": "http://pleiades.stoa.org/places/197403/dare-location"
      }
    }
  ]
}