{
  "type": "FeatureCollection",
  "title": "[Salinae]",
  "id": "197485",
  "description": "An ancient place, cited: BAtlas 20 F5 [Salinae]",
  "bbox": [
    18.694616,
    44.560024,
    18.694616,
    44.560024
  ],
  "reprPoint": [
    18.694616,
    44.560024
  ],
  "names": [
    "Salinae"
  ],
  "features": [
    {
      "geometry": {
        "type": "Point",
        "coordinates": [
          18.694616,
          44.560024
        ]
      },
      "id": "darmc-location-4837",
      "type": "Feature",
      "properties": {
        "description": "1M scale point location",
        "location_precision": "precise",
        "title": "DARMC location 4837",
        "link": "http://pleiades.stoa.org/places/197485/darmc-location-4837"
      }
    }
  ]
}