{
  "type": "FeatureCollection",
  "title": "Pelva",
  "id": "197431",
  "description": "An ancient place, cited: BAtlas 20 D6 Pelva",
  "bbox": [
    16.7775,
    43.875555,
    16.7775,
    43.875555
  ],
  "reprPoint": [
    16.7775,
    43.875555
  ],
  "names": [
    "Pelva"
  ],
  "features": [
    {
      "geometry": {
        "type": "Point",
        "coordinates": [
          16.7775,
          43.875555
        ]
      },
      "id": "darmc-location-14177",
      "type": "Feature",
      "properties": {
        "description": "1M scale point location",
        "location_precision": "precise",
        "title": "DARMC location 14177",
        "link": "http://pleiades.stoa.org/places/197431/darmc-location-14177"
      }
    }
  ]
}