{
  "type": "FeatureCollection",
  "title": "Sapua",
  "id": "197493",
  "description": "An ancient place, cited: BAtlas 20 E5 Sapua",
  "bbox": [
    17.406947,
    44.300812,
    17.406947,
    44.300812
  ],
  "reprPoint": [
    17.406947,
    44.300812
  ],
  "names": [
    "Sapua"
  ],
  "features": [
    {
      "geometry": {
        "type": "Point",
        "coordinates": [
          17.406947,
          44.300812
        ]
      },
      "id": "darmc-location-8945",
      "type": "Feature",
      "properties": {
        "description": "1M scale point location",
        "location_precision": "precise",
        "title": "DARMC location 8945",
        "link": "http://pleiades.stoa.org/places/197493/darmc-location-8945"
      }
    }
  ]
}