{
  "type": "FeatureCollection",
  "title": "Nedinum",
  "id": "197404",
  "description": "An ancient place, cited: BAtlas 20 C5 Nedinum",
  "bbox": [
    15.497238,
    44.071458,
    15.497238,
    44.071458
  ],
  "reprPoint": [
    15.497238,
    44.071458
  ],
  "names": [
    "Nedinum"
  ],
  "features": [
    {
      "geometry": {
        "type": "Point",
        "coordinates": [
          15.497238,
          44.071458
        ]
      },
      "id": "darmc-location-13896",
      "type": "Feature",
      "properties": {
        "description": "1M scale point location",
        "location_precision": "precise",
        "title": "DARMC location 13896",
        "link": "http://pleiades.stoa.org/places/197404/darmc-location-13896"
      }
    }
  ]
}