{
  "type": "FeatureCollection",
  "title": "‘Saldis’",
  "id": "197484",
  "bbox": [
    18.830811,
    44.946813,
    18.830811,
    44.946813
  ],
  "description": "An ancient place, cited: BAtlas 20 F5 ‘Saldis’",
  "names": [
    "Saldis"
  ],
  "features": [
    {
      "type": "Feature",
      "geometry": {
        "type": "Point",
        "coordinates": [
          18.830811,
          44.946813
        ]
      },
      "properties": {
        "description": "representative point"
      }
    },
    {
      "geometry": {
        "type": "Point",
        "coordinates": [
          18.830811,
          44.946813
        ]
      },
      "id": "darmc-location-8532",
      "type": "Feature",
      "properties": {
        "description": "1M scale point location",
        "location_precision": "precise",
        "title": "DARMC location 8532",
        "link": "http://pleiades.stoa.org/places/197484/darmc-location-8532"
      }
    }
  ]
}