{
  "type": "FeatureCollection",
  "title": "Sarute",
  "id": "197497",
  "description": "An ancient place, cited: BAtlas 20 E5 Sarute",
  "bbox": [
    17.151002,
    44.179755,
    17.151002,
    44.179755
  ],
  "reprPoint": [
    17.151002,
    44.179755
  ],
  "names": [
    "Sarute"
  ],
  "features": [
    {
      "geometry": {
        "type": "Point",
        "coordinates": [
          17.151002,
          44.179755
        ]
      },
      "id": "darmc-location-8948",
      "type": "Feature",
      "properties": {
        "description": "1M scale point location",
        "location_precision": "precise",
        "title": "DARMC location 8948",
        "link": "http://pleiades.stoa.org/places/197497/darmc-location-8948"
      }
    }
  ]
}