{
  "type": "FeatureCollection",
  "title": "Nesactium",
  "id": "197405",
  "description": "Nesactium was an ancient town of Histria.",
  "bbox": [
    13.970379,
    44.916934,
    13.970379,
    44.916934
  ],
  "connectsWith": [
    "855236251"
  ],
  "reprPoint": [
    13.970379,
    44.916934
  ],
  "names": [
    "Nesactium"
  ],
  "features": [
    {
      "geometry": {
        "type": "Point",
        "coordinates": [
          13.970379,
          44.916934
        ]
      },
      "id": "dare-location",
      "type": "Feature",
      "properties": {
        "description": "Representative point location, site precision",
        "location_precision": "precise",
        "title": "DARE Location",
        "link": "http://pleiades.stoa.org/places/197405/dare-location"
      }
    },
    {
      "geometry": {
        "type": "Point",
        "coordinates": [
          13.969585,
          44.916779
        ]
      },
      "id": "darmc-location-13910",
      "type": "Feature",
      "properties": {
        "description": "1M scale point location",
        "location_precision": "precise",
        "title": "DARMC location 13910",
        "link": "http://pleiades.stoa.org/places/197405/darmc-location-13910"
      }
    }
  ]
}