{
  "type": "FeatureCollection",
  "title": "Perbál",
  "id": "197432",
  "description": "An ancient place, cited: BAtlas 20 F2 Perbál",
  "bbox": [
    18.759954,
    47.59137,
    18.759954,
    47.59137
  ],
  "reprPoint": [
    18.759954,
    47.59137
  ],
  "features": [
    {
      "geometry": {
        "type": "Point",
        "coordinates": [
          18.759954,
          47.59137
        ]
      },
      "id": "darmc-location-14183",
      "type": "Feature",
      "properties": {
        "description": "1M scale point location",
        "location_precision": "precise",
        "title": "DARMC location 14183",
        "link": "http://pleiades.stoa.org/places/197432/darmc-location-14183"
      }
    }
  ]
}