{
  "type": "FeatureCollection",
  "title": "Tricciana",
  "id": "197558",
  "description": "An ancient place, cited: BAtlas 20 F3 Tricciana",
  "bbox": [
    18.101446,
    46.837681,
    18.101446,
    46.837681
  ],
  "reprPoint": [
    18.101446,
    46.837681
  ],
  "names": [
    "Tricciana"
  ],
  "features": [
    {
      "geometry": {
        "type": "Point",
        "coordinates": [
          18.101446,
          46.837681
        ]
      },
      "id": "darmc-location-15255",
      "type": "Feature",
      "properties": {
        "description": "1M scale point location",
        "location_precision": "precise",
        "title": "DARMC location 15255",
        "link": "http://pleiades.stoa.org/places/197558/darmc-location-15255"
      }
    }
  ]
}