{
  "type": "FeatureCollection",
  "title": "‘Stravianis’",
  "id": "197532",
  "description": "An ancient place, cited: BAtlas 20 F4 ‘Stravianis’",
  "bbox": [
    18.035862,
    45.437653,
    18.035862,
    45.437653
  ],
  "reprPoint": [
    18.035862,
    45.437653
  ],
  "names": [
    "Stravianis"
  ],
  "features": [
    {
      "geometry": {
        "type": "Point",
        "coordinates": [
          18.035862,
          45.437653
        ]
      },
      "id": "darmc-location-7184",
      "type": "Feature",
      "properties": {
        "description": "1M scale point location",
        "location_precision": "precise",
        "title": "DARMC location 7184",
        "link": "http://pleiades.stoa.org/places/197532/darmc-location-7184"
      }
    }
  ]
}