{
  "type": "FeatureCollection",
  "title": "Tragurium",
  "id": "197555",
  "bbox": [
    16.25063,
    43.517639,
    16.25063,
    43.517639
  ],
  "description": "An ancient place, cited: BAtlas 20 D6 Tragurium",
  "names": [
    "Tragurium"
  ],
  "features": [
    {
      "type": "Feature",
      "geometry": {
        "type": "Point",
        "coordinates": [
          16.25063,
          43.517639
        ]
      },
      "properties": {
        "description": "representative point"
      }
    },
    {
      "geometry": {
        "type": "Point",
        "coordinates": [
          16.25063,
          43.517639
        ]
      },
      "id": "darmc-location-15237",
      "type": "Feature",
      "properties": {
        "description": "1M scale point location",
        "location_precision": "precise",
        "title": "DARMC location 15237",
        "link": "http://pleiades.stoa.org/places/197555/darmc-location-15237"
      }
    }
  ]
}