{
  "type": "FeatureCollection",
  "title": "Volgum",
  "id": "197585",
  "description": "An ancient place, cited: BAtlas 20 E3 Volgum",
  "bbox": [
    17.244062,
    46.71162,
    17.244062,
    46.71162
  ],
  "reprPoint": [
    17.244062,
    46.71162
  ],
  "names": [
    "Volgum"
  ],
  "features": [
    {
      "geometry": {
        "type": "Point",
        "coordinates": [
          17.244062,
          46.71162
        ]
      },
      "id": "darmc-location-15433",
      "type": "Feature",
      "properties": {
        "description": "1M scale point location",
        "location_precision": "precise",
        "title": "DARMC location 15433",
        "link": "http://pleiades.stoa.org/places/197585/darmc-location-15433"
      }
    }
  ]
}