{
  "type": "FeatureCollection",
  "title": "Velence",
  "id": "197577",
  "bbox": [
    18.647975,
    47.241828,
    18.647975,
    47.241828
  ],
  "description": "An ancient place, cited: BAtlas 20 F2 Velence",
  "features": [
    {
      "type": "Feature",
      "geometry": {
        "type": "Point",
        "coordinates": [
          18.647975,
          47.241828
        ]
      },
      "properties": {
        "description": "representative point"
      }
    },
    {
      "geometry": {
        "type": "Point",
        "coordinates": [
          18.647975,
          47.241828
        ]
      },
      "id": "darmc-location-15362",
      "type": "Feature",
      "properties": {
        "description": "1M scale point location",
        "location_precision": "precise",
        "title": "DARMC location 15362",
        "link": "http://pleiades.stoa.org/places/197577/darmc-location-15362"
      }
    }
  ]
}