{
  "type": "FeatureCollection",
  "title": "‘Silvo’",
  "id": "197514",
  "description": "An ancient place, cited: BAtlas 20 A4 ‘Silvo’",
  "bbox": [
    13.505237,
    45.500513,
    13.505237,
    45.500513
  ],
  "reprPoint": [
    13.505237,
    45.500513
  ],
  "names": [
    "Silvo"
  ],
  "features": [
    {
      "geometry": {
        "type": "Point",
        "coordinates": [
          13.505237,
          45.500513
        ]
      },
      "id": "darmc-location-14751",
      "type": "Feature",
      "properties": {
        "description": "1M scale point location",
        "location_precision": "precise",
        "title": "DARMC location 14751",
        "link": "http://pleiades.stoa.org/places/197514/darmc-location-14751"
      }
    }
  ]
}