{
  "type": "FeatureCollection",
  "title": "Teutoburgium",
  "id": "197551",
  "description": "An ancient place, cited: BAtlas 20 F4 Teutoburgium",
  "bbox": [
    18.988055,
    45.483793,
    18.988055,
    45.483793
  ],
  "reprPoint": [
    18.988055,
    45.483793
  ],
  "names": [
    "Teutoburgium"
  ],
  "features": [
    {
      "geometry": {
        "type": "Point",
        "coordinates": [
          18.987393,
          45.484348
        ]
      },
      "id": "darmc-location-8359",
      "type": "Feature",
      "properties": {
        "description": "1M scale point location",
        "location_precision": "precise",
        "title": "DARMC location 8359",
        "link": "http://pleiades.stoa.org/places/197551/darmc-location-8359"
      }
    },
    {
      "geometry": {
        "type": "Point",
        "coordinates": [
          18.988055,
          45.483793
        ]
      },
      "id": "dare-location",
      "type": "Feature",
      "properties": {
        "description": "Representative point location, site precision",
        "location_precision": "precise",
        "title": "DARE Location",
        "link": "http://pleiades.stoa.org/places/197551/dare-location"
      }
    }
  ]
}