{
  "type": "FeatureCollection",
  "title": "Volgum",
  "id": "197585",
  "bbox": [
    17.244062,
    46.7096385,
    17.2465316,
    46.71162
  ],
  "description": "A fortified Roman settlement located 7 km south of the city of Keszthely, Hungary.",
  "names": [
    "Volgum"
  ],
  "features": [
    {
      "type": "Feature",
      "geometry": {
        "type": "Point",
        "coordinates": [
          17.2452968,
          46.71062925
        ]
      },
      "properties": {
        "description": "representative point"
      }
    },
    {
      "geometry": {
        "type": "Point",
        "coordinates": [
          17.244062,
          46.71162
        ]
      },
      "id": "darmc-location-15433",
      "type": "Feature",
      "properties": {
        "description": "1:1 million scale representative point location digitized from the Barrington Atlas of the Greek and Roman World by the Digital Atlas of Roman and Medieval Civilizations project at Harvard University.",
        "location_precision": "precise",
        "title": "DARMC location 15433",
        "link": "http://pleiades.stoa.org/places/197585/darmc-location-15433"
      }
    },
    {
      "geometry": {
        "type": "Point",
        "coordinates": [
          17.2465316,
          46.7096385
        ]
      },
      "id": "osm-location",
      "type": "Feature",
      "properties": {
        "description": "Representative location based on OpenStreetMap.",
        "location_precision": "precise",
        "title": "OSM location of Római castrum Fenekpuszta",
        "link": "http://pleiades.stoa.org/places/197585/osm-location"
      }
    }
  ]
}