{
  "type": "FeatureCollection",
  "title": "‘Vereis’",
  "id": "197576",
  "bbox": [
    18.267202,
    45.730953,
    18.267202,
    45.730953
  ],
  "description": "An ancient place, cited: BAtlas 20 F4 ‘Vereis’",
  "names": [
    "Vereis"
  ],
  "features": [
    {
      "type": "Feature",
      "geometry": {
        "type": "Point",
        "coordinates": [
          18.267202,
          45.730953
        ]
      },
      "properties": {
        "description": "representative point"
      }
    },
    {
      "geometry": {
        "type": "Point",
        "coordinates": [
          18.267202,
          45.730953
        ]
      },
      "id": "darmc-location-7209",
      "type": "Feature",
      "properties": {
        "description": "1M scale point location",
        "location_precision": "precise",
        "title": "DARMC location 7209",
        "link": "http://pleiades.stoa.org/places/197576/darmc-location-7209"
      }
    }
  ]
}