{
  "type": "FeatureCollection",
  "title": "Chughā Sabz",
  "id": "198812460",
  "bbox": [
    47.3953,
    33.3179,
    47.3953,
    33.3179
  ],
  "description": "A mound where a cuneiform inscription has been found.",
  "names": [
    "Chughā Sabz"
  ],
  "features": [
    {
      "type": "Feature",
      "geometry": {
        "type": "Point",
        "coordinates": [
          47.3953,
          33.3179
        ]
      },
      "properties": {
        "description": "representative point"
      }
    },
    {
      "geometry": {
        "type": "Point",
        "coordinates": [
          47.3953,
          33.3179
        ]
      },
      "id": "cigs-location-of-chugha-sabz",
      "type": "Feature",
      "properties": {
        "description": null,
        "location_precision": "precise",
        "title": "CIGS location of Chughā Sabz",
        "link": "http://pleiades.stoa.org/places/198812460/cigs-location-of-chugha-sabz"
      }
    }
  ]
}