{
  "type": "FeatureCollection",
  "title": "Ermine Street",
  "id": "203193875",
  "bbox": [
    -1.356271,
    51.386848,
    0.506787,
    53.957672
  ],
  "description": "The Ermine Street was a major Roman road of Britain, running from Londinium to Colonia Lindum and Eburacum.",
  "names": [
    "Ermine Street"
  ],
  "features": [
    {
      "type": "Feature",
      "geometry": {
        "type": "Point",
        "coordinates": [
          -0.5678065,
          53.6815235
        ]
      },
      "properties": {
        "description": "representative point"
      }
    }
  ]
}