{
  "type": "FeatureCollection",
  "title": "Ermine Street",
  "id": "203193875",
  "bbox": [
    -1.972586,
    51.386848,
    0.506787,
    53.957672
  ],
  "description": "The Ermine Street was a major Roman road of Britain, running from Londinium to Colonia Lindum and Eburacum.",
  "features": [
    {
      "type": "Feature",
      "geometry": {
        "type": "Point",
        "coordinates": [
          -0.820511112669,
          52.6411365287
        ]
      },
      "properties": {
        "description": "representative point"
      }
    }
  ]
}