{
  "type": "FeatureCollection",
  "title": "Barnhouse Settlement",
  "id": "203544460",
  "description": "The Barnhouse Settlement is a Neolithic village of approximately 15 houses located adjacent to the Loch of Harray, Orkney Mainland, Scotland.",
  "bbox": [
    -3.206714,
    58.9957834,
    -3.206714,
    58.9957834
  ],
  "connectsWith": [
    "89261"
  ],
  "reprPoint": [
    -3.206714,
    58.9957834
  ],
  "features": [
    {
      "geometry": {
        "type": "Point",
        "coordinates": [
          -3.206714,
          58.9957834
        ]
      },
      "id": "location-of-barnhouse-settlement",
      "type": "Feature",
      "properties": {
        "description": "Location based on OpenStreetMap",
        "location_precision": "precise",
        "title": "location of Barnhouse Settlement",
        "link": "http://pleiades.stoa.org/places/203544460/location-of-barnhouse-settlement"
      }
    }
  ]
}