{
  "type": "FeatureCollection",
  "title": "Enekrogen, Kannikeg책rd, Slamrebjerg, Sluseg책rd",
  "id": "20455",
  "description": "An ancient place, cited: BAtlas 2 G2 Enekrogen, Kannikeg책rd, Slamrebjerg, Sluseg책rd",
  "bbox": [
    15.056726,
    55.078983,
    15.056726,
    55.078983
  ],
  "reprPoint": [
    15.056726,
    55.078983
  ],
  "features": [
    {
      "geometry": {
        "type": "Point",
        "coordinates": [
          15.056726,
          55.078983
        ]
      },
      "id": "darmc-location-33587",
      "type": "Feature",
      "properties": {
        "description": "scale point location",
        "location_precision": "precise",
        "title": "DARMC location 33587",
        "link": "http://pleiades.stoa.org/places/20455/darmc-location-33587"
      }
    }
  ]
}