{
  "type": "FeatureCollection",
  "title": "Grudziądz-Rządz",
  "id": "20475",
  "description": "An ancient place, cited: BAtlas 2 G3 Grudziądz-Rządz",
  "bbox": [
    18.753566,
    53.483736,
    18.753566,
    53.483736
  ],
  "reprPoint": [
    18.753566,
    53.483736
  ],
  "features": [
    {
      "geometry": {
        "type": "Point",
        "coordinates": [
          18.753566,
          53.483736
        ]
      },
      "id": "darmc-location-33878",
      "type": "Feature",
      "properties": {
        "description": "scale point location",
        "location_precision": "precise",
        "title": "DARMC location 33878",
        "link": "http://pleiades.stoa.org/places/20475/darmc-location-33878"
      }
    }
  ]
}