{
  "type": "FeatureCollection",
  "title": "Roman amphitheater at Uchi Maius",
  "id": "20481513",
  "bbox": [
    9.0847777,
    36.4123893,
    9.0847777,
    36.4123893
  ],
  "description": "A Roman amphitheater located at Uchi Maius (modern Henchir ed-Douâmis).",
  "connectsWith": [
    "315242"
  ],
  "features": [
    {
      "type": "Feature",
      "geometry": {
        "type": "Point",
        "coordinates": [
          9.0847777,
          36.4123893
        ]
      },
      "properties": {
        "description": "representative point"
      }
    },
    {
      "geometry": {
        "type": "Point",
        "coordinates": [
          9.0847777,
          36.4123893
        ]
      },
      "id": "osm-location-of-roman-amphitheater",
      "type": "Feature",
      "properties": {
        "description": "Representative location based on OpenStreetMap.",
        "location_precision": "precise",
        "title": "OSM location of Roman amphitheater",
        "link": "http://pleiades.stoa.org/places/20481513/osm-location-of-roman-amphitheater"
      }
    }
  ]
}