{
  "type": "FeatureCollection",
  "title": "Karlino",
  "id": "20506",
  "bbox": [
    15.877106,
    54.033665,
    15.877106,
    54.033665
  ],
  "description": "An ancient place, cited: BAtlas 2 G3 Karlino",
  "features": [
    {
      "type": "Feature",
      "geometry": {
        "type": "Point",
        "coordinates": [
          15.877106,
          54.033665
        ]
      },
      "properties": {
        "description": "representative point"
      }
    },
    {
      "geometry": {
        "type": "Point",
        "coordinates": [
          15.877106,
          54.033665
        ]
      },
      "id": "darmc-location-13022",
      "type": "Feature",
      "properties": {
        "description": "5M scale point location",
        "location_precision": "precise",
        "title": "DARMC location 13022",
        "link": "http://pleiades.stoa.org/places/20506/darmc-location-13022"
      }
    }
  ]
}