{
  "type": "FeatureCollection",
  "title": "Łęg Piekarski",
  "id": "20521",
  "description": "An ancient place, cited: BAtlas 2 G3 Łęg Piekarski",
  "bbox": [
    18.519463,
    51.893773,
    18.519463,
    51.893773
  ],
  "reprPoint": [
    18.519463,
    51.893773
  ],
  "features": [
    {
      "geometry": {
        "type": "Point",
        "coordinates": [
          18.519463,
          51.893773
        ]
      },
      "id": "darmc-location-33595",
      "type": "Feature",
      "properties": {
        "description": "scale point location",
        "location_precision": "precise",
        "title": "DARMC location 33595",
        "link": "http://pleiades.stoa.org/places/20521/darmc-location-33595"
      }
    }
  ]
}