{
  "type": "FeatureCollection",
  "title": "Leśno",
  "id": "20522",
  "description": "An ancient place, cited: BAtlas 2 G3 Leśno",
  "bbox": [
    17.699655,
    53.949803,
    17.699655,
    53.949803
  ],
  "reprPoint": [
    17.699655,
    53.949803
  ],
  "features": [
    {
      "geometry": {
        "type": "Point",
        "coordinates": [
          17.699655,
          53.949803
        ]
      },
      "id": "darmc-location-23588",
      "type": "Feature",
      "properties": {
        "description": "Point location",
        "location_precision": "precise",
        "title": "DARMC location 23588",
        "link": "http://pleiades.stoa.org/places/20522/darmc-location-23588"
      }
    }
  ]
}