{
  "type": "FeatureCollection",
  "title": "Lugii",
  "id": "20533",
  "description": "An ancient place, cited: BAtlas 2 G3 Lugii",
  "bbox": [
    16.7764,
    51.527063,
    16.7764,
    51.527063
  ],
  "reprPoint": [
    16.7764,
    51.527063
  ],
  "names": [
    "Lugii"
  ],
  "features": [
    {
      "geometry": {
        "type": "Point",
        "coordinates": [
          16.7764,
          51.527063
        ]
      },
      "id": "darmc-location-23778",
      "type": "Feature",
      "properties": {
        "description": "Point location",
        "location_precision": "precise",
        "title": "DARMC location 23778",
        "link": "http://pleiades.stoa.org/places/20533/darmc-location-23778"
      }
    }
  ]
}