{
  "type": "FeatureCollection",
  "title": "Odry",
  "id": "20563",
  "bbox": [
    18.017484,
    53.890952,
    18.017484,
    53.890952
  ],
  "description": "An ancient place, cited: BAtlas 2 G3 Odry",
  "features": [
    {
      "type": "Feature",
      "geometry": {
        "type": "Point",
        "coordinates": [
          18.017484,
          53.890952
        ]
      },
      "properties": {
        "description": "representative point"
      }
    },
    {
      "geometry": {
        "type": "Point",
        "coordinates": [
          18.017484,
          53.890952
        ]
      },
      "id": "darmc-location-23868",
      "type": "Feature",
      "properties": {
        "description": "Point location",
        "location_precision": "precise",
        "title": "DARMC location 23868",
        "link": "http://pleiades.stoa.org/places/20563/darmc-location-23868"
      }
    }
  ]
}