{
  "type": "FeatureCollection",
  "title": "Öremölla",
  "id": "20565",
  "bbox": [
    13.572631,
    55.418396,
    13.572631,
    55.418396
  ],
  "description": "An ancient place, cited: BAtlas 2 F2 Öremölla",
  "features": [
    {
      "type": "Feature",
      "geometry": {
        "type": "Point",
        "coordinates": [
          13.572631,
          55.418396
        ]
      },
      "properties": {
        "description": "representative point"
      }
    },
    {
      "geometry": {
        "type": "Point",
        "coordinates": [
          13.572631,
          55.418396
        ]
      },
      "id": "darmc-location-33865",
      "type": "Feature",
      "properties": {
        "description": "representative point location digitized from the Barrington Atlas of the Greek and Roman World by the Digital Atlas of Roman and Medieval Civilizations project at Harvard University.",
        "location_precision": "precise",
        "title": "DARMC location 33865",
        "link": "http://pleiades.stoa.org/places/20565/darmc-location-33865"
      }
    }
  ]
}