{
  "type": "FeatureCollection",
  "title": "Snartemo",
  "id": "20609",
  "description": "An ancient place, cited: BAtlas 2 E2 Snartemo",
  "bbox": [
    7.214408,
    58.333635,
    7.214408,
    58.333635
  ],
  "reprPoint": [
    7.214408,
    58.333635
  ],
  "features": [
    {
      "geometry": {
        "type": "Point",
        "coordinates": [
          7.214408,
          58.333635
        ]
      },
      "id": "darmc-location-23857",
      "type": "Feature",
      "properties": {
        "description": "Point location",
        "location_precision": "precise",
        "title": "DARMC location 23857",
        "link": "http://pleiades.stoa.org/places/20609/darmc-location-23857"
      }
    }
  ]
}