{
  "type": "FeatureCollection",
  "title": "Vistula (river)",
  "id": "20639",
  "bbox": [
    21.0903548,
    52.2163331,
    21.0903548,
    52.2163331
  ],
  "description": "Vistula fl. (Vistula River) flows 1,047 km (651 miles)  from the south of Poland to the Baltic Sea. Its name is first attested in the Natural History of Pliny the Elder.",
  "connectsWith": [
    "20618"
  ],
  "names": [
    "Vistula"
  ],
  "features": [
    {
      "type": "Feature",
      "geometry": {
        "type": "Point",
        "coordinates": [
          21.0903548,
          52.2163331
        ]
      },
      "properties": {
        "description": "representative point"
      }
    },
    {
      "geometry": {
        "type": "Point",
        "coordinates": [
          21.0903548,
          52.2163331
        ]
      },
      "id": "location-of-Vistula-fl",
      "type": "Feature",
      "properties": {
        "description": "Location based on OpenStreetMap",
        "location_precision": "precise",
        "title": "location of Vistula (river)",
        "link": "http://pleiades.stoa.org/places/20639/location-of-Vistula-fl"
      }
    }
  ]
}