{
  "type": "FeatureCollection",
  "title": "Wilhelmsaue",
  "id": "20646",
  "bbox": [
    14.346612,
    52.66284,
    14.346612,
    52.66284
  ],
  "description": "An ancient place, cited: BAtlas 2 F3 Wilhelmsaue",
  "features": [
    {
      "type": "Feature",
      "geometry": {
        "type": "Point",
        "coordinates": [
          14.346612,
          52.66284
        ]
      },
      "properties": {
        "description": "representative point"
      }
    },
    {
      "geometry": {
        "type": "Point",
        "coordinates": [
          14.346612,
          52.66284
        ]
      },
      "id": "darmc-location-23884",
      "type": "Feature",
      "properties": {
        "description": "Point location",
        "location_precision": "precise",
        "title": "DARMC location 23884",
        "link": "http://pleiades.stoa.org/places/20646/darmc-location-23884"
      }
    }
  ]
}