{
  "type": "FeatureCollection",
  "title": "Zgliczyn-Pobodzy",
  "id": "20650",
  "description": "An ancient place, cited: BAtlas 2 H3 Zgliczyn-Pobodzy",
  "bbox": [
    20.026425,
    52.950316,
    20.026425,
    52.950316
  ],
  "reprPoint": [
    20.026425,
    52.950316
  ],
  "features": [
    {
      "geometry": {
        "type": "Point",
        "coordinates": [
          20.026425,
          52.950316
        ]
      },
      "id": "darmc-location-33887",
      "type": "Feature",
      "properties": {
        "description": "scale point location",
        "location_precision": "precise",
        "title": "DARMC location 33887",
        "link": "http://pleiades.stoa.org/places/20650/darmc-location-33887"
      }
    }
  ]
}