{
  "type": "FeatureCollection",
  "title": "Ad Drinum",
  "id": "206877",
  "bbox": [
    19.104152,
    44.387977,
    19.104152,
    44.387977
  ],
  "description": "An ancient place, cited: BAtlas 21 B5 Ad Drinum",
  "names": [
    "Ad Drinum"
  ],
  "features": [
    {
      "type": "Feature",
      "geometry": {
        "type": "Point",
        "coordinates": [
          19.104152,
          44.387977
        ]
      },
      "properties": {
        "description": "representative point"
      }
    },
    {
      "geometry": {
        "type": "Point",
        "coordinates": [
          19.104152,
          44.387977
        ]
      },
      "id": "darmc-location-8495",
      "type": "Feature",
      "properties": {
        "description": "1M scale point location",
        "location_precision": "precise",
        "title": "DARMC location 8495",
        "link": "http://pleiades.stoa.org/places/206877/darmc-location-8495"
      }
    }
  ]
}