{
  "type": "FeatureCollection",
  "title": "Ad Herculem",
  "id": "206880",
  "description": "An ancient place, cited: BAtlas 21 D6 Ad Herculem",
  "bbox": [
    21.717528,
    43.188585,
    21.717528,
    43.188585
  ],
  "reprPoint": [
    21.717528,
    43.188585
  ],
  "names": [
    "Ad Herculem"
  ],
  "features": [
    {
      "geometry": {
        "type": "Point",
        "coordinates": [
          21.717528,
          43.188585
        ]
      },
      "id": "dare-location",
      "type": "Feature",
      "properties": {
        "description": "Representative point location, village precision",
        "location_precision": "precise",
        "title": "DARE Location",
        "link": "http://pleiades.stoa.org/places/206880/dare-location"
      }
    }
  ]
}