{
  "type": "FeatureCollection",
  "title": "*Ad Mutrium",
  "id": "206886",
  "description": "An ancient place, cited: BAtlas 21 F5 *Ad Mutrium",
  "bbox": [
    23.263581,
    44.403519,
    23.263581,
    44.403519
  ],
  "reprPoint": [
    23.263581,
    44.403519
  ],
  "names": [
    "Ad Mutrium",
    "Amutrium"
  ],
  "features": [
    {
      "geometry": {
        "type": "Point",
        "coordinates": [
          23.366658,
          44.583319
        ]
      },
      "id": "darmc-location-24454",
      "type": "Feature",
      "properties": {
        "description": "1M scale point location",
        "location_precision": "precise",
        "title": "DARMC location 24454",
        "link": "http://pleiades.stoa.org/places/206886/darmc-location-24454"
      }
    },
    {
      "geometry": {
        "type": "Point",
        "coordinates": [
          23.263581,
          44.403519
        ]
      },
      "id": "dare-location",
      "type": "Feature",
      "properties": {
        "description": "Representative point location, village precision",
        "location_precision": "precise",
        "title": "DARE Location",
        "link": "http://pleiades.stoa.org/places/206886/dare-location"
      }
    }
  ]
}