{
  "type": "FeatureCollection",
  "title": "Bumbeşti",
  "id": "206999",
  "bbox": [
    23.38156,
    45.178701,
    23.38156,
    45.178701
  ],
  "description": "An ancient place, cited: BAtlas 21 F4 Bumbeşti",
  "features": [
    {
      "type": "Feature",
      "geometry": {
        "type": "Point",
        "coordinates": [
          23.38156,
          45.178701
        ]
      },
      "properties": {
        "description": "representative point"
      }
    },
    {
      "geometry": {
        "type": "Point",
        "coordinates": [
          23.38156,
          45.178701
        ]
      },
      "id": "darmc-location-24311",
      "type": "Feature",
      "properties": {
        "description": "1M scale point location",
        "location_precision": "precise",
        "title": "DARMC location 24311",
        "link": "http://pleiades.stoa.org/places/206999/darmc-location-24311"
      }
    }
  ]
}