{
  "type": "FeatureCollection",
  "title": "Ballanstra",
  "id": "206955",
  "description": "An ancient place, cited: BAtlas 21 E6 Ballanstra",
  "bbox": [
    22.868223,
    42.994188,
    22.868223,
    42.994188
  ],
  "reprPoint": [
    22.868223,
    42.994188
  ],
  "names": [
    "Ballanstra"
  ],
  "features": [
    {
      "geometry": {
        "type": "Point",
        "coordinates": [
          22.868223,
          42.994188
        ]
      },
      "id": "darmc-location-24482",
      "type": "Feature",
      "properties": {
        "description": "1M scale point location",
        "location_precision": "precise",
        "title": "DARMC location 24482",
        "link": "http://pleiades.stoa.org/places/206955/darmc-location-24482"
      }
    }
  ]
}