{
  "type": "FeatureCollection",
  "title": "*Aquae",
  "id": "206928",
  "bbox": [
    23.003213,
    45.741049,
    23.00804,
    45.763249
  ],
  "description": "*Aquae or pagus Aquensis was a bath site located along the Strei river in the territory of Ulpia Traiana Sarmizegetusa.",
  "names": [
    "Aquae",
    "Călan"
  ],
  "features": [
    {
      "type": "Feature",
      "geometry": {
        "type": "Point",
        "coordinates": [
          23.004822,
          45.7558486667
        ]
      },
      "properties": {
        "description": "representative point"
      }
    },
    {
      "geometry": {
        "type": "Point",
        "coordinates": [
          23.003213,
          45.763248
        ]
      },
      "id": "darmc-location-23100",
      "type": "Feature",
      "properties": {
        "description": "Point location",
        "location_precision": "precise",
        "title": "DARMC location 23100",
        "link": "http://pleiades.stoa.org/places/206928/darmc-location-23100"
      }
    },
    {
      "geometry": {
        "type": "Point",
        "coordinates": [
          23.003213,
          45.763249
        ]
      },
      "id": "darmc-location-33746",
      "type": "Feature",
      "properties": {
        "description": "representative point location digitized from the Barrington Atlas of the Greek and Roman World by the Digital Atlas of Roman and Medieval Civilizations project at Harvard University.",
        "location_precision": "precise",
        "title": "DARMC location 33746",
        "link": "http://pleiades.stoa.org/places/206928/darmc-location-33746"
      }
    },
    {
      "geometry": {
        "type": "Point",
        "coordinates": [
          23.00804,
          45.741049
        ]
      },
      "id": "dare-location",
      "type": "Feature",
      "properties": {
        "description": "Representative point location, site precision",
        "location_precision": "precise",
        "title": "DARE Location",
        "link": "http://pleiades.stoa.org/places/206928/dare-location"
      }
    }
  ]
}