{
  "type": "FeatureCollection",
  "title": "Almaşu Mare",
  "id": "206908",
  "description": "An ancient place, cited: BAtlas 21 F3 Almaşu Mare",
  "bbox": [
    23.116375,
    46.11056,
    23.116375,
    46.11056
  ],
  "reprPoint": [
    23.116375,
    46.11056
  ],
  "features": [
    {
      "geometry": {
        "type": "Point",
        "coordinates": [
          23.116375,
          46.11056
        ]
      },
      "id": "darmc-location-24562",
      "type": "Feature",
      "properties": {
        "description": "1M scale point location",
        "location_precision": "precise",
        "title": "DARMC location 24562",
        "link": "http://pleiades.stoa.org/places/206908/darmc-location-24562"
      }
    }
  ]
}