{
  "type": "FeatureCollection",
  "title": "Bahna",
  "id": "206948",
  "description": "An ancient place, cited: BAtlas 21 E5 Bahna",
  "bbox": [
    22.497913,
    44.774639,
    22.497913,
    44.774639
  ],
  "reprPoint": [
    22.497913,
    44.774639
  ],
  "features": [
    {
      "geometry": {
        "type": "Point",
        "coordinates": [
          22.497913,
          44.774639
        ]
      },
      "id": "darmc-location-24504",
      "type": "Feature",
      "properties": {
        "description": "1M scale point location",
        "location_precision": "precise",
        "title": "DARMC location 24504",
        "link": "http://pleiades.stoa.org/places/206948/darmc-location-24504"
      }
    }
  ]
}