{
  "type": "FeatureCollection",
  "title": "Balainac",
  "id": "206953",
  "description": "An ancient place, cited: BAtlas 21 D6 Balainac",
  "bbox": [
    21.788336,
    43.243931,
    21.788336,
    43.243931
  ],
  "reprPoint": [
    21.788336,
    43.243931
  ],
  "features": [
    {
      "geometry": {
        "type": "Point",
        "coordinates": [
          21.788336,
          43.243931
        ]
      },
      "id": "darmc-location-7323",
      "type": "Feature",
      "properties": {
        "description": "1M scale point location",
        "location_precision": "precise",
        "title": "DARMC location 7323",
        "link": "http://pleiades.stoa.org/places/206953/darmc-location-7323"
      }
    }
  ]
}