{
  "type": "FeatureCollection",
  "title": "Ampelum",
  "id": "206917",
  "bbox": [
    23.231394,
    46.107572,
    23.231394,
    46.107572
  ],
  "description": "An ancient place, cited: BAtlas 21 F3 Ampelum",
  "names": [
    "Ampelum"
  ],
  "features": [
    {
      "type": "Feature",
      "geometry": {
        "type": "Point",
        "coordinates": [
          23.231394,
          46.107572
        ]
      },
      "properties": {
        "description": "representative point"
      }
    },
    {
      "geometry": {
        "type": "Point",
        "coordinates": [
          23.231394,
          46.107572
        ]
      },
      "id": "darmc-location-24564",
      "type": "Feature",
      "properties": {
        "description": "1M scale point location",
        "location_precision": "precise",
        "title": "DARMC location 24564",
        "link": "http://pleiades.stoa.org/places/206917/darmc-location-24564"
      }
    }
  ]
}