{
  "type": "FeatureCollection",
  "title": "Budalia",
  "id": "206995",
  "description": "An ancient place, cited: BAtlas 21 B5 Budalia",
  "bbox": [
    19.463467,
    45.010018,
    19.463467,
    45.010018
  ],
  "reprPoint": [
    19.463467,
    45.010018
  ],
  "names": [
    "Budalia"
  ],
  "features": [
    {
      "geometry": {
        "type": "Point",
        "coordinates": [
          19.463467,
          45.010018
        ]
      },
      "id": "darmc-location-8004",
      "type": "Feature",
      "properties": {
        "description": "1M scale point location",
        "location_precision": "precise",
        "title": "DARMC location 8004",
        "link": "http://pleiades.stoa.org/places/206995/darmc-location-8004"
      }
    }
  ]
}