{
  "type": "FeatureCollection",
  "title": "Burgenae",
  "id": "207001",
  "description": "An ancient place, cited: BAtlas 21 C5 Burgenae",
  "bbox": [
    20.283336,
    44.949991,
    20.283336,
    44.949991
  ],
  "connectsWith": [
    "226577"
  ],
  "reprPoint": [
    20.283336,
    44.949991
  ],
  "names": [
    "Burgenae"
  ],
  "features": [
    {
      "geometry": {
        "type": "Point",
        "coordinates": [
          20.283336,
          44.949991
        ]
      },
      "id": "darmc-location-7478",
      "type": "Feature",
      "properties": {
        "description": "1M scale point location",
        "location_precision": "precise",
        "title": "DARMC location 7478",
        "link": "http://pleiades.stoa.org/places/207001/darmc-location-7478"
      }
    }
  ]
}