{
  "type": "FeatureCollection",
  "title": "Cheia",
  "id": "207028",
  "description": "An ancient place, cited: BAtlas 21 F3 Cheia",
  "bbox": [
    23.708423,
    46.542066,
    23.708423,
    46.542066
  ],
  "reprPoint": [
    23.708423,
    46.542066
  ],
  "features": [
    {
      "geometry": {
        "type": "Point",
        "coordinates": [
          23.708423,
          46.542066
        ]
      },
      "id": "darmc-location-24608",
      "type": "Feature",
      "properties": {
        "description": "1M scale point location",
        "location_precision": "precise",
        "title": "DARMC location 24608",
        "link": "http://pleiades.stoa.org/places/207028/darmc-location-24608"
      }
    }
  ]
}