{
  "type": "FeatureCollection",
  "title": "‘Cametas’",
  "id": "207006",
  "description": "An ancient place, cited: BAtlas 21 D6 ‘Cametas’",
  "bbox": [
    21.57156,
    43.65977,
    21.57156,
    43.65977
  ],
  "reprPoint": [
    21.57156,
    43.65977
  ],
  "names": [
    "Cametas"
  ],
  "features": [
    {
      "geometry": {
        "type": "Point",
        "coordinates": [
          21.57156,
          43.65977
        ]
      },
      "id": "darmc-location-24369",
      "type": "Feature",
      "properties": {
        "description": "1M scale point location",
        "location_precision": "precise",
        "title": "DARMC location 24369",
        "link": "http://pleiades.stoa.org/places/207006/darmc-location-24369"
      }
    }
  ]
}