{
  "type": "FeatureCollection",
  "title": "Crna Trava",
  "id": "207054",
  "description": "An ancient place, cited: BAtlas 21 E7 Crna Trava",
  "bbox": [
    22.31455,
    42.875343,
    22.31455,
    42.875343
  ],
  "reprPoint": [
    22.31455,
    42.875343
  ],
  "features": [
    {
      "geometry": {
        "type": "Point",
        "coordinates": [
          22.31455,
          42.875343
        ]
      },
      "id": "darmc-location-24326",
      "type": "Feature",
      "properties": {
        "description": "1M scale point location",
        "location_precision": "precise",
        "title": "DARMC location 24326",
        "link": "http://pleiades.stoa.org/places/207054/darmc-location-24326"
      }
    }
  ]
}