{
  "type": "FeatureCollection",
  "title": "Dierna",
  "id": "207078",
  "description": "An ancient place, cited: BAtlas 21 E5 Dierna",
  "bbox": [
    22.407644,
    44.738264,
    22.407644,
    44.738264
  ],
  "connectsWith": [
    "226577"
  ],
  "reprPoint": [
    22.407644,
    44.738264
  ],
  "names": [
    "Dierna",
    "Tierua",
    "Zerna"
  ],
  "features": [
    {
      "geometry": {
        "type": "Point",
        "coordinates": [
          22.396173,
          44.725157
        ]
      },
      "id": "darmc-location-24621",
      "type": "Feature",
      "properties": {
        "description": "1M scale point location",
        "location_precision": "precise",
        "title": "DARMC location 24621",
        "link": "http://pleiades.stoa.org/places/207078/darmc-location-24621"
      }
    },
    {
      "geometry": {
        "type": "Point",
        "coordinates": [
          22.407644,
          44.738264
        ]
      },
      "id": "dare-location",
      "type": "Feature",
      "properties": {
        "description": "Representative point location, site precision",
        "location_precision": "precise",
        "title": "DARE Location",
        "link": "http://pleiades.stoa.org/places/207078/dare-location"
      }
    }
  ]
}