{
  "type": "FeatureCollection",
  "title": "Dorticum",
  "id": "207093",
  "description": "An ancient place, cited: BAtlas 21 E5 Dorticum",
  "bbox": [
    22.736228,
    44.19265,
    22.736228,
    44.19265
  ],
  "reprPoint": [
    22.736228,
    44.19265
  ],
  "names": [
    "Dorticum"
  ],
  "features": [
    {
      "geometry": {
        "type": "Point",
        "coordinates": [
          22.736228,
          44.19265
        ]
      },
      "id": "darmc-location-24336",
      "type": "Feature",
      "properties": {
        "description": "1M scale point location",
        "location_precision": "precise",
        "title": "DARMC location 24336",
        "link": "http://pleiades.stoa.org/places/207093/darmc-location-24336"
      }
    }
  ]
}