{
  "type": "FeatureCollection",
  "title": "Cărpiniş",
  "id": "207013",
  "bbox": [
    23.032332,
    45.878111,
    23.032332,
    45.878111
  ],
  "description": "An ancient place, cited: BAtlas 21 F4 Cărpiniş",
  "features": [
    {
      "type": "Feature",
      "geometry": {
        "type": "Point",
        "coordinates": [
          23.032332,
          45.878111
        ]
      },
      "properties": {
        "description": "representative point"
      }
    },
    {
      "geometry": {
        "type": "Point",
        "coordinates": [
          23.032332,
          45.878111
        ]
      },
      "id": "darmc-location-24511",
      "type": "Feature",
      "properties": {
        "description": "1M scale point location",
        "location_precision": "precise",
        "title": "DARMC location 24511",
        "link": "http://pleiades.stoa.org/places/207013/darmc-location-24511"
      }
    }
  ]
}