{
  "type": "FeatureCollection",
  "title": "*Diana",
  "id": "207077",
  "description": "An ancient place, cited: BAtlas 21 E5 *Diana",
  "bbox": [
    22.556944,
    44.640833,
    22.556944,
    44.640833
  ],
  "reprPoint": [
    22.556944,
    44.640833
  ],
  "names": [
    "Diana",
    "Zanes"
  ],
  "features": [
    {
      "geometry": {
        "type": "Point",
        "coordinates": [
          22.590217,
          44.597914
        ]
      },
      "id": "darmc-location-689",
      "type": "Feature",
      "properties": {
        "description": "1M scale point location",
        "location_precision": "precise",
        "title": "DARMC location 689",
        "link": "http://pleiades.stoa.org/places/207077/darmc-location-689"
      }
    },
    {
      "geometry": {
        "type": "Point",
        "coordinates": [
          22.5439,
          44.6533
        ]
      },
      "id": "location-of-diana-roman-castrum",
      "type": "Feature",
      "properties": {
        "description": "verified in Google Earth 2013",
        "location_precision": "precise",
        "title": "location of Diana Roman Castrum",
        "link": "http://pleiades.stoa.org/places/207077/location-of-diana-roman-castrum"
      }
    },
    {
      "geometry": {
        "type": "Point",
        "coordinates": [
          22.556944,
          44.640833
        ]
      },
      "id": "dare-location",
      "type": "Feature",
      "properties": {
        "description": "Representative point location, village precision",
        "location_precision": "precise",
        "title": "DARE Location",
        "link": "http://pleiades.stoa.org/places/207077/dare-location"
      }
    }
  ]
}