{
  "type": "FeatureCollection",
  "title": "Buziaş",
  "id": "207002",
  "bbox": [
    21.600005,
    45.650001,
    21.600005,
    45.650001
  ],
  "description": "An ancient place, cited: BAtlas 21 D4 Buziaş",
  "features": [
    {
      "type": "Feature",
      "geometry": {
        "type": "Point",
        "coordinates": [
          21.600005,
          45.650001
        ]
      },
      "properties": {
        "description": "representative point"
      }
    },
    {
      "geometry": {
        "type": "Point",
        "coordinates": [
          21.600005,
          45.650001
        ]
      },
      "id": "darmc-location-23893",
      "type": "Feature",
      "properties": {
        "description": "Point location",
        "location_precision": "precise",
        "title": "DARMC location 23893",
        "link": "http://pleiades.stoa.org/places/207002/darmc-location-23893"
      }
    }
  ]
}