{
  "type": "FeatureCollection",
  "title": "Castra Margensia",
  "id": "207016",
  "description": "An ancient place, cited: BAtlas 21 D5 Castra Margensia",
  "bbox": [
    21.028338,
    44.698276,
    21.028338,
    44.698276
  ],
  "reprPoint": [
    21.028338,
    44.698276
  ],
  "names": [
    "Castra Margensia"
  ],
  "features": [
    {
      "geometry": {
        "type": "Point",
        "coordinates": [
          21.028338,
          44.698276
        ]
      },
      "id": "darmc-location-7531",
      "type": "Feature",
      "properties": {
        "description": "1M scale point location",
        "location_precision": "precise",
        "title": "DARMC location 7531",
        "link": "http://pleiades.stoa.org/places/207016/darmc-location-7531"
      }
    }
  ]
}