{
  "type": "FeatureCollection",
  "title": "Centum Putea",
  "id": "207024",
  "bbox": [
    21.585516,
    45.266996,
    21.585516,
    45.266996
  ],
  "description": "An ancient place, cited: BAtlas 21 D4 Centum Putea",
  "names": [
    "Centum Putea"
  ],
  "features": [
    {
      "type": "Feature",
      "geometry": {
        "type": "Point",
        "coordinates": [
          21.585516,
          45.266996
        ]
      },
      "properties": {
        "description": "representative point"
      }
    },
    {
      "geometry": {
        "type": "Point",
        "coordinates": [
          21.585516,
          45.266996
        ]
      },
      "id": "darmc-location-24319",
      "type": "Feature",
      "properties": {
        "description": "1M scale point location",
        "location_precision": "precise",
        "title": "DARMC location 24319",
        "link": "http://pleiades.stoa.org/places/207024/darmc-location-24319"
      }
    }
  ]
}