{
  "type": "FeatureCollection",
  "title": "Desa",
  "id": "207075",
  "description": "An ancient place, cited: BAtlas 21 F6 Desa",
  "bbox": [
    23.033899,
    43.866568,
    23.033899,
    43.866568
  ],
  "reprPoint": [
    23.033899,
    43.866568
  ],
  "features": [
    {
      "geometry": {
        "type": "Point",
        "coordinates": [
          23.033899,
          43.866568
        ]
      },
      "id": "darmc-location-24033",
      "type": "Feature",
      "properties": {
        "description": "1M scale point location",
        "location_precision": "precise",
        "title": "DARMC location 24033",
        "link": "http://pleiades.stoa.org/places/207075/darmc-location-24033"
      }
    }
  ]
}