{
  "type": "FeatureCollection",
  "title": "Combustica",
  "id": "207043",
  "description": "An ancient place, cited: BAtlas 21 E6 Combustica",
  "bbox": [
    22.651414,
    43.716603,
    22.651414,
    43.716603
  ],
  "reprPoint": [
    22.651414,
    43.716603
  ],
  "names": [
    "Combustica"
  ],
  "features": [
    {
      "geometry": {
        "type": "Point",
        "coordinates": [
          22.651414,
          43.716603
        ]
      },
      "id": "darmc-location-24373",
      "type": "Feature",
      "properties": {
        "description": "1M scale point location",
        "location_precision": "precise",
        "title": "DARMC location 24373",
        "link": "http://pleiades.stoa.org/places/207043/darmc-location-24373"
      }
    }
  ]
}