{
  "type": "FeatureCollection",
  "title": "Cenad",
  "id": "207023",
  "description": "An ancient place, cited: BAtlas 21 C3 Cenad",
  "bbox": [
    20.585818,
    46.138105,
    20.585818,
    46.138105
  ],
  "reprPoint": [
    20.585818,
    46.138105
  ],
  "features": [
    {
      "geometry": {
        "type": "Point",
        "coordinates": [
          20.585818,
          46.138105
        ]
      },
      "id": "darmc-location-7554",
      "type": "Feature",
      "properties": {
        "description": "1M scale point location",
        "location_precision": "precise",
        "title": "DARMC location 7554",
        "link": "http://pleiades.stoa.org/places/207023/darmc-location-7554"
      }
    }
  ]
}