{
  "type": "FeatureCollection",
  "title": "Hajdučka Vodenica",
  "id": "207162",
  "description": "An ancient place, cited: BAtlas 21 E5 Hajdučka Vodenica",
  "bbox": [
    22.280242,
    44.600081,
    22.280242,
    44.600081
  ],
  "reprPoint": [
    22.280242,
    44.600081
  ],
  "features": [
    {
      "geometry": {
        "type": "Point",
        "coordinates": [
          22.280242,
          44.600081
        ]
      },
      "id": "darmc-location-6885",
      "type": "Feature",
      "properties": {
        "description": "1M scale point location",
        "location_precision": "precise",
        "title": "DARMC location 6885",
        "link": "http://pleiades.stoa.org/places/207162/darmc-location-6885"
      }
    }
  ]
}