{
  "type": "FeatureCollection",
  "title": "Hum",
  "id": "207174",
  "bbox": [
    21.912467,
    43.357351,
    21.912467,
    43.357351
  ],
  "description": "An ancient place, cited: BAtlas 21 D6 Hum",
  "features": [
    {
      "type": "Feature",
      "geometry": {
        "type": "Point",
        "coordinates": [
          21.912467,
          43.357351
        ]
      },
      "properties": {
        "description": "representative point"
      }
    },
    {
      "geometry": {
        "type": "Point",
        "coordinates": [
          21.912467,
          43.357351
        ]
      },
      "id": "darmc-location-7799",
      "type": "Feature",
      "properties": {
        "description": "1M scale point location",
        "location_precision": "precise",
        "title": "DARMC location 7799",
        "link": "http://pleiades.stoa.org/places/207174/darmc-location-7799"
      }
    }
  ]
}