{
  "type": "FeatureCollection",
  "title": "Iscroni",
  "id": "207190",
  "description": "An ancient place, cited: BAtlas 21 F4 Iscroni",
  "bbox": [
    23.334992,
    45.378772,
    23.334992,
    45.378772
  ],
  "reprPoint": [
    23.334992,
    45.378772
  ],
  "features": [
    {
      "geometry": {
        "type": "Point",
        "coordinates": [
          23.334992,
          45.378772
        ]
      },
      "id": "darmc-location-24524",
      "type": "Feature",
      "properties": {
        "description": "1M scale point location",
        "location_precision": "precise",
        "title": "DARMC location 24524",
        "link": "http://pleiades.stoa.org/places/207190/darmc-location-24524"
      }
    }
  ]
}