{
  "type": "FeatureCollection",
  "title": "Dumbrava",
  "id": "207102",
  "bbox": [
    23.217254,
    46.822791,
    23.217254,
    46.822791
  ],
  "description": "An ancient place, cited: BAtlas 21 F3 Dumbrava",
  "features": [
    {
      "type": "Feature",
      "geometry": {
        "type": "Point",
        "coordinates": [
          23.217254,
          46.822791
        ]
      },
      "properties": {
        "description": "representative point"
      }
    },
    {
      "geometry": {
        "type": "Point",
        "coordinates": [
          23.217254,
          46.822791
        ]
      },
      "id": "darmc-location-24629",
      "type": "Feature",
      "properties": {
        "description": "1M scale point location",
        "location_precision": "precise",
        "title": "DARMC location 24629",
        "link": "http://pleiades.stoa.org/places/207102/darmc-location-24629"
      }
    }
  ]
}