{
  "type": "FeatureCollection",
  "title": "Egeta",
  "id": "207107",
  "bbox": [
    22.445309,
    44.469116,
    22.445309,
    44.469116
  ],
  "description": "An ancient place, cited: BAtlas 21 E5 Egeta",
  "names": [
    "Egeta"
  ],
  "features": [
    {
      "type": "Feature",
      "geometry": {
        "type": "Point",
        "coordinates": [
          22.445309,
          44.469116
        ]
      },
      "properties": {
        "description": "representative point"
      }
    },
    {
      "geometry": {
        "type": "Point",
        "coordinates": [
          22.445309,
          44.469116
        ]
      },
      "id": "darmc-location-24340",
      "type": "Feature",
      "properties": {
        "description": "1M scale point location",
        "location_precision": "precise",
        "title": "DARMC location 24340",
        "link": "http://pleiades.stoa.org/places/207107/darmc-location-24340"
      }
    }
  ]
}