{
  "type": "FeatureCollection",
  "title": "Hammeum",
  "id": "207164",
  "description": "An ancient place, cited: BAtlas 21 D6 Hammeum",
  "bbox": [
    21.600011,
    43.233333,
    21.600011,
    43.233333
  ],
  "reprPoint": [
    21.600011,
    43.233333
  ],
  "names": [
    "Hammeum"
  ],
  "features": [
    {
      "geometry": {
        "type": "Point",
        "coordinates": [
          21.600011,
          43.233333
        ]
      },
      "id": "darmc-location-24377",
      "type": "Feature",
      "properties": {
        "description": "1M scale point location",
        "location_precision": "precise",
        "title": "DARMC location 24377",
        "link": "http://pleiades.stoa.org/places/207164/darmc-location-24377"
      }
    }
  ]
}