{
  "type": "FeatureCollection",
  "title": "Hunedoara",
  "id": "207175",
  "description": "An ancient place, cited: BAtlas 21 E4 Hunedoara",
  "bbox": [
    22.920569,
    45.766197,
    22.920569,
    45.766197
  ],
  "reprPoint": [
    22.920569,
    45.766197
  ],
  "features": [
    {
      "geometry": {
        "type": "Point",
        "coordinates": [
          22.920569,
          45.766197
        ]
      },
      "id": "darmc-location-24650",
      "type": "Feature",
      "properties": {
        "description": "1M scale point location",
        "location_precision": "precise",
        "title": "DARMC location 24650",
        "link": "http://pleiades.stoa.org/places/207175/darmc-location-24650"
      }
    }
  ]
}