{
  "type": "FeatureCollection",
  "title": "Gheorgheni",
  "id": "207132",
  "bbox": [
    23.688492,
    46.712293,
    23.688492,
    46.712293
  ],
  "description": "An ancient place, cited: BAtlas 21 F3 Gheorgheni",
  "features": [
    {
      "type": "Feature",
      "geometry": {
        "type": "Point",
        "coordinates": [
          23.688492,
          46.712293
        ]
      },
      "properties": {
        "description": "representative point"
      }
    },
    {
      "geometry": {
        "type": "Point",
        "coordinates": [
          23.688492,
          46.712293
        ]
      },
      "id": "darmc-location-24640",
      "type": "Feature",
      "properties": {
        "description": "1M scale point location",
        "location_precision": "precise",
        "title": "DARMC location 24640",
        "link": "http://pleiades.stoa.org/places/207132/darmc-location-24640"
      }
    }
  ]
}