{
  "type": "FeatureCollection",
  "title": "Iovis Pagus",
  "id": "207189",
  "description": "An ancient place, cited: BAtlas 21 D5 Iovis Pagus",
  "bbox": [
    21.33776,
    44.391826,
    21.33776,
    44.391826
  ],
  "reprPoint": [
    21.33776,
    44.391826
  ],
  "names": [
    "Iovis Pagus"
  ],
  "features": [
    {
      "geometry": {
        "type": "Point",
        "coordinates": [
          21.33776,
          44.391826
        ]
      },
      "id": "darmc-location-8050",
      "type": "Feature",
      "properties": {
        "description": "1M scale point location",
        "location_precision": "precise",
        "title": "DARMC location 8050",
        "link": "http://pleiades.stoa.org/places/207189/darmc-location-8050"
      }
    }
  ]
}