{
  "type": "FeatureCollection",
  "title": "Iustiniana Prima",
  "id": "207193",
  "bbox": [
    21.660388,
    42.960472,
    21.660388,
    42.960472
  ],
  "description": "An ancient place, cited: BAtlas 21 D7 Iustiniana Prima",
  "names": [
    "Iustiniana Prima"
  ],
  "features": [
    {
      "type": "Feature",
      "geometry": {
        "type": "Point",
        "coordinates": [
          21.660388,
          42.960472
        ]
      },
      "properties": {
        "description": "representative point"
      }
    },
    {
      "geometry": {
        "type": "Point",
        "coordinates": [
          21.660388,
          42.960472
        ]
      },
      "id": "darmc-location-12907",
      "type": "Feature",
      "properties": {
        "description": "1M scale point location",
        "location_precision": "precise",
        "title": "DARMC location 12907",
        "link": "http://pleiades.stoa.org/places/207193/darmc-location-12907"
      }
    }
  ]
}