{
  "type": "FeatureCollection",
  "title": "Iskrets",
  "id": "207191",
  "bbox": [
    23.252179,
    42.986836,
    23.252179,
    42.986836
  ],
  "description": "An ancient place, cited: BAtlas 21 F7 Iskrets",
  "features": [
    {
      "type": "Feature",
      "geometry": {
        "type": "Point",
        "coordinates": [
          23.252179,
          42.986836
        ]
      },
      "properties": {
        "description": "representative point"
      }
    },
    {
      "geometry": {
        "type": "Point",
        "coordinates": [
          23.252179,
          42.986836
        ]
      },
      "id": "darmc-location-24654",
      "type": "Feature",
      "properties": {
        "description": "1M scale point location",
        "location_precision": "precise",
        "title": "DARMC location 24654",
        "link": "http://pleiades.stoa.org/places/207191/darmc-location-24654"
      }
    }
  ]
}