{
  "type": "FeatureCollection",
  "title": "Iezureni",
  "id": "207184",
  "bbox": [
    23.275174,
    45.034007,
    23.275174,
    45.034007
  ],
  "description": "An ancient place, cited: BAtlas 21 F4 Iezureni",
  "features": [
    {
      "type": "Feature",
      "geometry": {
        "type": "Point",
        "coordinates": [
          23.275174,
          45.034007
        ]
      },
      "properties": {
        "description": "representative point"
      }
    },
    {
      "geometry": {
        "type": "Point",
        "coordinates": [
          23.275174,
          45.034007
        ]
      },
      "id": "darmc-location-24652",
      "type": "Feature",
      "properties": {
        "description": "1M scale point location",
        "location_precision": "precise",
        "title": "DARMC location 24652",
        "link": "http://pleiades.stoa.org/places/207184/darmc-location-24652"
      }
    }
  ]
}