{
  "type": "FeatureCollection",
  "title": "‘Masclianis’",
  "id": "207270",
  "description": "An ancient place, cited: BAtlas 21 E4 ‘Masclianis’",
  "bbox": [
    22.283849,
    45.255182,
    22.283849,
    45.255182
  ],
  "reprPoint": [
    22.283849,
    45.255182
  ],
  "names": [
    "Masclianis"
  ],
  "features": [
    {
      "geometry": {
        "type": "Point",
        "coordinates": [
          22.283849,
          45.255182
        ]
      },
      "id": "darmc-location-24380",
      "type": "Feature",
      "properties": {
        "description": "1M scale point location",
        "location_precision": "precise",
        "title": "DARMC location 24380",
        "link": "http://pleiades.stoa.org/places/207270/darmc-location-24380"
      }
    }
  ]
}