{
  "type": "FeatureCollection",
  "title": "Marchevo",
  "id": "207266",
  "bbox": [
    23.345141,
    43.512153,
    23.345141,
    43.512153
  ],
  "description": "An ancient place, cited: BAtlas 21 F6 Marchevo",
  "features": [
    {
      "type": "Feature",
      "geometry": {
        "type": "Point",
        "coordinates": [
          23.345141,
          43.512153
        ]
      },
      "properties": {
        "description": "representative point"
      }
    },
    {
      "geometry": {
        "type": "Point",
        "coordinates": [
          23.345141,
          43.512153
        ]
      },
      "id": "darmc-location-24389",
      "type": "Feature",
      "properties": {
        "description": "1M scale point location",
        "location_precision": "precise",
        "title": "DARMC location 24389",
        "link": "http://pleiades.stoa.org/places/207266/darmc-location-24389"
      }
    }
  ]
}