{
  "type": "FeatureCollection",
  "title": "Koprivnica",
  "id": "207214",
  "description": "An ancient place, cited: BAtlas 21 E5 Koprivnica",
  "bbox": [
    22.356548,
    44.016204,
    22.356548,
    44.016204
  ],
  "reprPoint": [
    22.356548,
    44.016204
  ],
  "features": [
    {
      "geometry": {
        "type": "Point",
        "coordinates": [
          22.356548,
          44.016204
        ]
      },
      "id": "darmc-location-13261",
      "type": "Feature",
      "properties": {
        "description": "1M scale point location",
        "location_precision": "precise",
        "title": "DARMC location 13261",
        "link": "http://pleiades.stoa.org/places/207214/darmc-location-13261"
      }
    }
  ]
}