{
  "type": "FeatureCollection",
  "title": "Mesteacăn",
  "id": "207277",
  "bbox": [
    22.794522,
    46.154081,
    22.794522,
    46.154081
  ],
  "description": "An ancient place, cited: BAtlas 21 E3 Mesteacăn",
  "features": [
    {
      "type": "Feature",
      "geometry": {
        "type": "Point",
        "coordinates": [
          22.794522,
          46.154081
        ]
      },
      "properties": {
        "description": "representative point"
      }
    },
    {
      "geometry": {
        "type": "Point",
        "coordinates": [
          22.794522,
          46.154081
        ]
      },
      "id": "darmc-location-9269",
      "type": "Feature",
      "properties": {
        "description": "1M scale point location",
        "location_precision": "precise",
        "title": "DARMC location 9269",
        "link": "http://pleiades.stoa.org/places/207277/darmc-location-9269"
      }
    }
  ]
}