{
  "type": "FeatureCollection",
  "title": "Margus (river)",
  "id": "207268",
  "bbox": [
    21.0386919,
    44.7183621,
    21.0386919,
    44.7183621
  ],
  "description": "An ancient place, cited: BAtlas 21 D5 Margus fl.",
  "connectsWith": [
    "226577"
  ],
  "names": [
    "Margus",
    "Brongos"
  ],
  "features": [
    {
      "type": "Feature",
      "geometry": {
        "type": "Point",
        "coordinates": [
          21.0386919,
          44.7183621
        ]
      },
      "properties": {
        "description": "representative point"
      }
    },
    {
      "geometry": {
        "type": "Point",
        "coordinates": [
          21.0386919,
          44.7183621
        ]
      },
      "id": "osm-location",
      "type": "Feature",
      "properties": {
        "description": "Location based on OpenStreetMap",
        "location_precision": "precise",
        "title": "OSM location of the Great Morava River",
        "link": "http://pleiades.stoa.org/places/207268/osm-location"
      }
    }
  ]
}