{
  "type": "FeatureCollection",
  "title": "Meldia",
  "id": "207275",
  "bbox": [
    22.930004,
    42.922129,
    22.930004,
    42.922129
  ],
  "description": "An ancient place, cited: BAtlas 21 E7 Meldia",
  "names": [
    "Meldia"
  ],
  "features": [
    {
      "type": "Feature",
      "geometry": {
        "type": "Point",
        "coordinates": [
          22.930004,
          42.922129
        ]
      },
      "properties": {
        "description": "representative point"
      }
    },
    {
      "geometry": {
        "type": "Point",
        "coordinates": [
          22.930004,
          42.922129
        ]
      },
      "id": "darmc-location-24483",
      "type": "Feature",
      "properties": {
        "description": "1M scale point location",
        "location_precision": "precise",
        "title": "DARMC location 24483",
        "link": "http://pleiades.stoa.org/places/207275/darmc-location-24483"
      }
    }
  ]
}