{
  "type": "FeatureCollection",
  "title": "Lukovo",
  "id": "207248",
  "description": "An ancient place, cited: BAtlas 21 D6 Lukovo",
  "bbox": [
    21.827849,
    43.800091,
    21.827849,
    43.800091
  ],
  "reprPoint": [
    21.827849,
    43.800091
  ],
  "features": [
    {
      "geometry": {
        "type": "Point",
        "coordinates": [
          21.827849,
          43.800091
        ]
      },
      "id": "darmc-location-7934",
      "type": "Feature",
      "properties": {
        "description": "1M scale point location",
        "location_precision": "precise",
        "title": "DARMC location 7934",
        "link": "http://pleiades.stoa.org/places/207248/darmc-location-7934"
      }
    }
  ]
}