{
  "type": "FeatureCollection",
  "title": "Ovsinjac",
  "id": "207326",
  "bbox": [
    22.13736,
    43.137378,
    22.13736,
    43.137378
  ],
  "description": "An ancient place, cited: BAtlas 21 E6 Ovsinjac",
  "features": [
    {
      "type": "Feature",
      "geometry": {
        "type": "Point",
        "coordinates": [
          22.13736,
          43.137378
        ]
      },
      "properties": {
        "description": "representative point"
      }
    },
    {
      "geometry": {
        "type": "Point",
        "coordinates": [
          22.13736,
          43.137378
        ]
      },
      "id": "darmc-location-8170",
      "type": "Feature",
      "properties": {
        "description": "1M scale point location",
        "location_precision": "precise",
        "title": "DARMC location 8170",
        "link": "http://pleiades.stoa.org/places/207326/darmc-location-8170"
      }
    }
  ]
}