{
  "type": "FeatureCollection",
  "title": "Reciu",
  "id": "207380",
  "description": "An ancient place, cited: BAtlas 21 F4 Reciu",
  "bbox": [
    23.673964,
    45.864978,
    23.673964,
    45.864978
  ],
  "reprPoint": [
    23.673964,
    45.864978
  ],
  "features": [
    {
      "geometry": {
        "type": "Point",
        "coordinates": [
          23.673964,
          45.864978
        ]
      },
      "id": "darmc-location-24733",
      "type": "Feature",
      "properties": {
        "description": "1M scale point location",
        "location_precision": "precise",
        "title": "DARMC location 24733",
        "link": "http://pleiades.stoa.org/places/207380/darmc-location-24733"
      }
    }
  ]
}