{
  "type": "FeatureCollection",
  "title": "Ocna Dejului",
  "id": "207317",
  "description": "An ancient place, cited: BAtlas 21 F2 Ocna Dejului",
  "bbox": [
    23.851649,
    47.11468,
    23.851649,
    47.11468
  ],
  "reprPoint": [
    23.851649,
    47.11468
  ],
  "features": [
    {
      "geometry": {
        "type": "Point",
        "coordinates": [
          23.851649,
          47.11468
        ]
      },
      "id": "darmc-location-24489",
      "type": "Feature",
      "properties": {
        "description": "1M scale point location",
        "location_precision": "precise",
        "title": "DARMC location 24489",
        "link": "http://pleiades.stoa.org/places/207317/darmc-location-24489"
      }
    }
  ]
}