{
  "type": "FeatureCollection",
  "title": "Romuliana",
  "id": "207395",
  "description": "Galerius commissioned the Late Roman fortified palace compound and memorial complex of Gamzigrad-Romuliana in the late third and early fourth centuries.",
  "bbox": [
    22.1857501,
    43.899206,
    22.1857501,
    43.899206
  ],
  "reprPoint": [
    22.1857501,
    43.899206
  ],
  "names": [
    "Romuliana"
  ],
  "features": [
    {
      "geometry": {
        "type": "Point",
        "coordinates": [
          22.184915,
          43.899105
        ]
      },
      "id": "darmc-location-24735",
      "type": "Feature",
      "properties": {
        "description": "1M scale point location",
        "location_precision": "precise",
        "title": "DARMC location 24735",
        "link": "http://pleiades.stoa.org/places/207395/darmc-location-24735"
      }
    },
    {
      "geometry": {
        "type": "Point",
        "coordinates": [
          22.1857501,
          43.899206
        ]
      },
      "id": "dare-location",
      "type": "Feature",
      "properties": {
        "description": "Representative point location, site precision",
        "location_precision": "precise",
        "title": "DARE Location",
        "link": "http://pleiades.stoa.org/places/207395/dare-location"
      }
    }
  ]
}