{
  "type": "FeatureCollection",
  "title": "Plješivica",
  "id": "207349",
  "description": "An ancient place, cited: BAtlas 21 B6 Plješivica",
  "bbox": [
    19.014258,
    43.837149,
    19.014258,
    43.837149
  ],
  "reprPoint": [
    19.014258,
    43.837149
  ],
  "features": [
    {
      "geometry": {
        "type": "Point",
        "coordinates": [
          19.014258,
          43.837149
        ]
      },
      "id": "darmc-location-14321",
      "type": "Feature",
      "properties": {
        "description": "1M scale point location",
        "location_precision": "precise",
        "title": "DARMC location 14321",
        "link": "http://pleiades.stoa.org/places/207349/darmc-location-14321"
      }
    }
  ]
}