{
  "type": "FeatureCollection",
  "title": "Orljane",
  "id": "207324",
  "description": "An ancient place, cited: BAtlas 21 D6 Orljane",
  "bbox": [
    21.8197,
    43.194677,
    21.8197,
    43.194677
  ],
  "reprPoint": [
    21.8197,
    43.194677
  ],
  "features": [
    {
      "geometry": {
        "type": "Point",
        "coordinates": [
          21.8197,
          43.194677
        ]
      },
      "id": "darmc-location-8165",
      "type": "Feature",
      "properties": {
        "description": "1M scale point location",
        "location_precision": "precise",
        "title": "DARMC location 8165",
        "link": "http://pleiades.stoa.org/places/207324/darmc-location-8165"
      }
    }
  ]
}