{
  "type": "FeatureCollection",
  "title": "Recaş",
  "id": "207379",
  "description": "An ancient place, cited: BAtlas 21 D4 Recaş",
  "bbox": [
    21.513079,
    45.800616,
    21.513079,
    45.800616
  ],
  "reprPoint": [
    21.513079,
    45.800616
  ],
  "features": [
    {
      "geometry": {
        "type": "Point",
        "coordinates": [
          21.513079,
          45.800616
        ]
      },
      "id": "darmc-location-24546",
      "type": "Feature",
      "properties": {
        "description": "1M scale point location",
        "location_precision": "precise",
        "title": "DARMC location 24546",
        "link": "http://pleiades.stoa.org/places/207379/darmc-location-24546"
      }
    }
  ]
}