{
  "type": "FeatureCollection",
  "title": "Pons Augusti",
  "id": "207357",
  "description": "An ancient place, cited: BAtlas 21 E4 Pons Augusti",
  "bbox": [
    22.518892,
    45.504578,
    22.518892,
    45.504578
  ],
  "reprPoint": [
    22.518892,
    45.504578
  ],
  "names": [
    "Pons Augusti"
  ],
  "features": [
    {
      "geometry": {
        "type": "Point",
        "coordinates": [
          22.518892,
          45.504578
        ]
      },
      "id": "darmc-location-24456",
      "type": "Feature",
      "properties": {
        "description": "1M scale point location",
        "location_precision": "precise",
        "title": "DARMC location 24456",
        "link": "http://pleiades.stoa.org/places/207357/darmc-location-24456"
      }
    }
  ]
}