{
  "type": "FeatureCollection",
  "title": "Spaneta",
  "id": "207460",
  "bbox": [
    19.308365,
    45.082078,
    19.308365,
    45.082078
  ],
  "description": "An ancient place, cited: BAtlas 21 B4 Spaneta",
  "names": [
    "Spaneta"
  ],
  "features": [
    {
      "type": "Feature",
      "geometry": {
        "type": "Point",
        "coordinates": [
          19.308365,
          45.082078
        ]
      },
      "properties": {
        "description": "representative point"
      }
    },
    {
      "geometry": {
        "type": "Point",
        "coordinates": [
          19.308365,
          45.082078
        ]
      },
      "id": "darmc-location-8627",
      "type": "Feature",
      "properties": {
        "description": "1M scale point location",
        "location_precision": "precise",
        "title": "DARMC location 8627",
        "link": "http://pleiades.stoa.org/places/207460/darmc-location-8627"
      }
    }
  ]
}