{
  "type": "FeatureCollection",
  "title": "Taliata",
  "id": "207485",
  "description": "An ancient place, cited: BAtlas 21 E5 Taliata",
  "bbox": [
    22.144349,
    44.443587,
    22.144349,
    44.443587
  ],
  "reprPoint": [
    22.144349,
    44.443587
  ],
  "names": [
    "Taliata"
  ],
  "features": [
    {
      "geometry": {
        "type": "Point",
        "coordinates": [
          22.144349,
          44.443587
        ]
      },
      "id": "darmc-location-8350",
      "type": "Feature",
      "properties": {
        "description": "1M scale point location",
        "location_precision": "precise",
        "title": "DARMC location 8350",
        "link": "http://pleiades.stoa.org/places/207485/darmc-location-8350"
      }
    }
  ]
}