{
  "type": "FeatureCollection",
  "title": "Tibiscum",
  "id": "207495",
  "description": "Tibiscum was an ancient settlement of Dacia mentioned by Ptolemy that later became a Roman castrum and municipium.",
  "bbox": [
    22.186456,
    45.459075,
    22.186456,
    45.459075
  ],
  "reprPoint": [
    22.186456,
    45.459075
  ],
  "names": [
    "Tibiscum"
  ],
  "features": [
    {
      "geometry": {
        "type": "Point",
        "coordinates": [
          22.186456,
          45.459075
        ]
      },
      "id": "darmc-location-24775",
      "type": "Feature",
      "properties": {
        "description": "1M scale point location",
        "location_precision": "precise",
        "title": "DARMC location 24775",
        "link": "http://pleiades.stoa.org/places/207495/darmc-location-24775"
      }
    }
  ]
}