{
  "type": "FeatureCollection",
  "title": "Tihău",
  "id": "207498",
  "description": "An ancient place, cited: BAtlas 21 F2 Tihău",
  "bbox": [
    23.327689,
    47.227733,
    23.327689,
    47.227733
  ],
  "reprPoint": [
    23.327689,
    47.227733
  ],
  "features": [
    {
      "geometry": {
        "type": "Point",
        "coordinates": [
          23.327689,
          47.227733
        ]
      },
      "id": "darmc-location-24442",
      "type": "Feature",
      "properties": {
        "description": "1M scale point location",
        "location_precision": "precise",
        "title": "DARMC location 24442",
        "link": "http://pleiades.stoa.org/places/207498/darmc-location-24442"
      }
    }
  ]
}