{
  "type": "FeatureCollection",
  "title": "Ţigănaşi",
  "id": "207497",
  "bbox": [
    22.499581,
    44.433627,
    22.499581,
    44.433627
  ],
  "description": "An ancient place, cited: BAtlas 21 E5 Ţigănaşi",
  "features": [
    {
      "type": "Feature",
      "geometry": {
        "type": "Point",
        "coordinates": [
          22.499581,
          44.433627
        ]
      },
      "properties": {
        "description": "representative point"
      }
    },
    {
      "geometry": {
        "type": "Point",
        "coordinates": [
          22.499581,
          44.433627
        ]
      },
      "id": "darmc-location-24776",
      "type": "Feature",
      "properties": {
        "description": "1M scale point location",
        "location_precision": "precise",
        "title": "DARMC location 24776",
        "link": "http://pleiades.stoa.org/places/207497/darmc-location-24776"
      }
    }
  ]
}