{
  "type": "FeatureCollection",
  "title": "Săcelu",
  "id": "207407",
  "description": "An ancient place, cited: BAtlas 21 F4 Săcelu",
  "bbox": [
    23.545095,
    45.110687,
    23.545095,
    45.110687
  ],
  "reprPoint": [
    23.545095,
    45.110687
  ],
  "features": [
    {
      "geometry": {
        "type": "Point",
        "coordinates": [
          23.545095,
          45.110687
        ]
      },
      "id": "darmc-location-24424",
      "type": "Feature",
      "properties": {
        "description": "1M scale point location",
        "location_precision": "precise",
        "title": "DARMC location 24424",
        "link": "http://pleiades.stoa.org/places/207407/darmc-location-24424"
      }
    }
  ]
}