{
  "type": "FeatureCollection",
  "title": "Savus (river)",
  "id": "207429",
  "description": "An ancient place, cited: BAtlas 21 B5 Savus fl.",
  "bbox": [
    14.4163643,
    46.1388513,
    14.4163643,
    46.1388513
  ],
  "reprPoint": [
    14.4163643,
    46.1388513
  ],
  "names": [
    "Savus"
  ],
  "features": [
    {
      "geometry": {
        "type": "Point",
        "coordinates": [
          14.4163643,
          46.1388513
        ]
      },
      "id": "location-of-sava-river",
      "type": "Feature",
      "properties": {
        "description": "Location based on OpenStreetMap",
        "location_precision": "precise",
        "title": "location of Sava river",
        "link": "http://pleiades.stoa.org/places/207429/location-of-sava-river"
      }
    }
  ]
}