{
  "type": "FeatureCollection",
  "title": "Ţebea",
  "id": "207490",
  "description": "An ancient place, cited: BAtlas 21 E3 Ţebea",
  "bbox": [
    22.737849,
    46.200236,
    22.737849,
    46.200236
  ],
  "reprPoint": [
    22.737849,
    46.200236
  ],
  "features": [
    {
      "geometry": {
        "type": "Point",
        "coordinates": [
          22.737849,
          46.200236
        ]
      },
      "id": "darmc-location-9297",
      "type": "Feature",
      "properties": {
        "description": "1M scale point location",
        "location_precision": "precise",
        "title": "DARMC location 9297",
        "link": "http://pleiades.stoa.org/places/207490/darmc-location-9297"
      }
    }
  ]
}