{
  "type": "FeatureCollection",
  "title": "Slovac",
  "id": "207454",
  "description": "An ancient place, cited: BAtlas 21 C5 Slovac",
  "bbox": [
    20.085144,
    44.346284,
    20.085144,
    44.346284
  ],
  "reprPoint": [
    20.085144,
    44.346284
  ],
  "features": [
    {
      "geometry": {
        "type": "Point",
        "coordinates": [
          20.085144,
          44.346284
        ]
      },
      "id": "darmc-location-8322",
      "type": "Feature",
      "properties": {
        "description": "1M scale point location",
        "location_precision": "precise",
        "title": "DARMC location 8322",
        "link": "http://pleiades.stoa.org/places/207454/darmc-location-8322"
      }
    }
  ]
}