{
  "type": "FeatureCollection",
  "title": "Stalać",
  "id": "207463",
  "bbox": [
    21.425181,
    43.67783,
    21.425181,
    43.67783
  ],
  "description": "An ancient place, cited: BAtlas 21 D6 Stalać",
  "features": [
    {
      "type": "Feature",
      "geometry": {
        "type": "Point",
        "coordinates": [
          21.425181,
          43.67783
        ]
      },
      "properties": {
        "description": "representative point"
      }
    },
    {
      "geometry": {
        "type": "Point",
        "coordinates": [
          21.425181,
          43.67783
        ]
      },
      "id": "darmc-location-24434",
      "type": "Feature",
      "properties": {
        "description": "1M scale point location",
        "location_precision": "precise",
        "title": "DARMC location 24434",
        "link": "http://pleiades.stoa.org/places/207463/darmc-location-24434"
      }
    }
  ]
}