{
  "type": "FeatureCollection",
  "title": "Techeru",
  "id": "207491",
  "bbox": [
    23.049627,
    46.136338,
    23.049627,
    46.136338
  ],
  "description": "An ancient place, cited: BAtlas 21 F3 Techeru",
  "features": [
    {
      "type": "Feature",
      "geometry": {
        "type": "Point",
        "coordinates": [
          23.049627,
          46.136338
        ]
      },
      "properties": {
        "description": "representative point"
      }
    },
    {
      "geometry": {
        "type": "Point",
        "coordinates": [
          23.049627,
          46.136338
        ]
      },
      "id": "darmc-location-15035",
      "type": "Feature",
      "properties": {
        "description": "1M scale point location",
        "location_precision": "precise",
        "title": "DARMC location 15035",
        "link": "http://pleiades.stoa.org/places/207491/darmc-location-15035"
      }
    }
  ]
}