{
  "type": "FeatureCollection",
  "title": "Salaš Noćajski",
  "id": "207410",
  "description": "An ancient place, cited: BAtlas 21 B5 Salaš Noćajski",
  "bbox": [
    19.585725,
    44.946902,
    19.585725,
    44.946902
  ],
  "reprPoint": [
    19.585725,
    44.946902
  ],
  "features": [
    {
      "geometry": {
        "type": "Point",
        "coordinates": [
          19.585725,
          44.946902
        ]
      },
      "id": "darmc-location-8263",
      "type": "Feature",
      "properties": {
        "description": "1M scale point location",
        "location_precision": "precise",
        "title": "DARMC location 8263",
        "link": "http://pleiades.stoa.org/places/207410/darmc-location-8263"
      }
    }
  ]
}