{
  "type": "FeatureCollection",
  "title": "Săcărîmbu",
  "id": "207406",
  "bbox": [
    23.041878,
    45.973313,
    23.041878,
    45.973313
  ],
  "description": "An ancient place, cited: BAtlas 21 F4 Săcărîmbu",
  "features": [
    {
      "type": "Feature",
      "geometry": {
        "type": "Point",
        "coordinates": [
          23.041878,
          45.973313
        ]
      },
      "properties": {
        "description": "representative point"
      }
    },
    {
      "geometry": {
        "type": "Point",
        "coordinates": [
          23.041878,
          45.973313
        ]
      },
      "id": "darmc-location-24498",
      "type": "Feature",
      "properties": {
        "description": "1M scale point location",
        "location_precision": "precise",
        "title": "DARMC location 24498",
        "link": "http://pleiades.stoa.org/places/207406/darmc-location-24498"
      }
    }
  ]
}