{
  "type": "FeatureCollection",
  "title": "Sjarina",
  "id": "207448",
  "description": "An ancient place, cited: BAtlas 21 D7 Sjarina",
  "bbox": [
    21.600171,
    42.783394,
    21.600171,
    42.783394
  ],
  "reprPoint": [
    21.600171,
    42.783394
  ],
  "features": [
    {
      "geometry": {
        "type": "Point",
        "coordinates": [
          21.600171,
          42.783394
        ]
      },
      "id": "darmc-location-24757",
      "type": "Feature",
      "properties": {
        "description": "1M scale point location",
        "location_precision": "precise",
        "title": "DARMC location 24757",
        "link": "http://pleiades.stoa.org/places/207448/darmc-location-24757"
      }
    }
  ]
}