{
  "type": "FeatureCollection",
  "title": "(S)Acidava",
  "id": "207408",
  "bbox": [
    23.794334,
    46.020781,
    23.794334,
    46.020781
  ],
  "description": "An ancient place, cited: BAtlas 21 F4 (S)Acidava",
  "names": [
    "Sacidava",
    "Acidava"
  ],
  "features": [
    {
      "type": "Feature",
      "geometry": {
        "type": "Point",
        "coordinates": [
          23.794334,
          46.020781
        ]
      },
      "properties": {
        "description": "representative point"
      }
    },
    {
      "geometry": {
        "type": "Point",
        "coordinates": [
          23.794334,
          46.020781
        ]
      },
      "id": "darmc-location-2705",
      "type": "Feature",
      "properties": {
        "description": "1M scale point location",
        "location_precision": "precise",
        "title": "DARMC location 2705",
        "link": "http://pleiades.stoa.org/places/207408/darmc-location-2705"
      }
    }
  ]
}