{
  "type": "FeatureCollection",
  "title": "Salcia",
  "id": "207411",
  "description": "An ancient place, cited: BAtlas 21 E5 Salcia",
  "bbox": [
    22.9286,
    44.142253,
    22.9286,
    44.142253
  ],
  "reprPoint": [
    22.9286,
    44.142253
  ],
  "features": [
    {
      "geometry": {
        "type": "Point",
        "coordinates": [
          22.9286,
          44.142253
        ]
      },
      "id": "darmc-location-24741",
      "type": "Feature",
      "properties": {
        "description": "1M scale point location",
        "location_precision": "precise",
        "title": "DARMC location 24741",
        "link": "http://pleiades.stoa.org/places/207411/darmc-location-24741"
      }
    }
  ]
}