{
  "type": "FeatureCollection",
  "title": "Svilajnac",
  "id": "207475",
  "description": "An ancient place, cited: BAtlas 21 D5 Svilajnac",
  "bbox": [
    21.199979,
    44.216623,
    21.199979,
    44.216623
  ],
  "reprPoint": [
    21.199979,
    44.216623
  ],
  "features": [
    {
      "geometry": {
        "type": "Point",
        "coordinates": [
          21.199979,
          44.216623
        ]
      },
      "id": "darmc-location-24436",
      "type": "Feature",
      "properties": {
        "description": "1M scale point location",
        "location_precision": "precise",
        "title": "DARMC location 24436",
        "link": "http://pleiades.stoa.org/places/207475/darmc-location-24436"
      }
    }
  ]
}