{
  "type": "FeatureCollection",
  "title": "Sasca Montană",
  "id": "207426",
  "bbox": [
    21.715944,
    44.88329,
    21.715944,
    44.88329
  ],
  "description": "An ancient place, cited: BAtlas 21 D5 Sasca Montană",
  "features": [
    {
      "type": "Feature",
      "geometry": {
        "type": "Point",
        "coordinates": [
          21.715944,
          44.88329
        ]
      },
      "properties": {
        "description": "representative point"
      }
    },
    {
      "geometry": {
        "type": "Point",
        "coordinates": [
          21.715944,
          44.88329
        ]
      },
      "id": "darmc-location-24745",
      "type": "Feature",
      "properties": {
        "description": "1M scale point location",
        "location_precision": "precise",
        "title": "DARMC location 24745",
        "link": "http://pleiades.stoa.org/places/207426/darmc-location-24745"
      }
    }
  ]
}