{
  "type": "FeatureCollection",
  "title": "Stojnik",
  "id": "207466",
  "bbox": [
    20.499254,
    44.507562,
    20.499254,
    44.507562
  ],
  "description": "An ancient place, cited: BAtlas 21 C5 Stojnik",
  "features": [
    {
      "type": "Feature",
      "geometry": {
        "type": "Point",
        "coordinates": [
          20.499254,
          44.507562
        ]
      },
      "properties": {
        "description": "representative point"
      }
    },
    {
      "geometry": {
        "type": "Point",
        "coordinates": [
          20.499254,
          44.507562
        ]
      },
      "id": "darmc-location-24765",
      "type": "Feature",
      "properties": {
        "description": "1M scale point location",
        "location_precision": "precise",
        "title": "DARMC location 24765",
        "link": "http://pleiades.stoa.org/places/207466/darmc-location-24765"
      }
    }
  ]
}