{
  "type": "FeatureCollection",
  "title": "Stragari",
  "id": "207467",
  "bbox": [
    20.666636,
    44.149925,
    20.666636,
    44.149925
  ],
  "description": "An ancient place, cited: BAtlas 21 C5 Stragari",
  "features": [
    {
      "type": "Feature",
      "geometry": {
        "type": "Point",
        "coordinates": [
          20.666636,
          44.149925
        ]
      },
      "properties": {
        "description": "representative point"
      }
    },
    {
      "geometry": {
        "type": "Point",
        "coordinates": [
          20.666636,
          44.149925
        ]
      },
      "id": "darmc-location-24435",
      "type": "Feature",
      "properties": {
        "description": "1M scale point location",
        "location_precision": "precise",
        "title": "DARMC location 24435",
        "link": "http://pleiades.stoa.org/places/207467/darmc-location-24435"
      }
    }
  ]
}