{
  "type": "FeatureCollection",
  "title": "Šarkamen",
  "id": "207423",
  "description": "An ancient place, cited: BAtlas 21 E5 Šarkamen",
  "bbox": [
    22.330334,
    44.243686,
    22.330334,
    44.243686
  ],
  "reprPoint": [
    22.330334,
    44.243686
  ],
  "features": [
    {
      "geometry": {
        "type": "Point",
        "coordinates": [
          22.330334,
          44.243686
        ]
      },
      "id": "darmc-location-8275",
      "type": "Feature",
      "properties": {
        "description": "1M scale point location",
        "location_precision": "precise",
        "title": "DARMC location 8275",
        "link": "http://pleiades.stoa.org/places/207423/darmc-location-8275"
      }
    }
  ]
}