{
  "type": "FeatureCollection",
  "title": "Zanoge",
  "id": "207574",
  "bbox": [
    23.319902,
    43.06816,
    23.319902,
    43.06816
  ],
  "description": "An ancient place, cited: BAtlas 21 F6 Zanoge",
  "features": [
    {
      "type": "Feature",
      "geometry": {
        "type": "Point",
        "coordinates": [
          23.319902,
          43.06816
        ]
      },
      "properties": {
        "description": "representative point"
      }
    },
    {
      "geometry": {
        "type": "Point",
        "coordinates": [
          23.319902,
          43.06816
        ]
      },
      "id": "darmc-location-24794",
      "type": "Feature",
      "properties": {
        "description": "1M scale point location",
        "location_precision": "precise",
        "title": "DARMC location 24794",
        "link": "http://pleiades.stoa.org/places/207574/darmc-location-24794"
      }
    }
  ]
}