{
  "type": "FeatureCollection",
  "title": "Zrenjanin",
  "id": "207582",
  "description": "An ancient place, cited: BAtlas 21 C4 Zrenjanin",
  "bbox": [
    20.403579,
    45.365829,
    20.403579,
    45.365829
  ],
  "reprPoint": [
    20.403579,
    45.365829
  ],
  "features": [
    {
      "geometry": {
        "type": "Point",
        "coordinates": [
          20.403579,
          45.365829
        ]
      },
      "id": "darmc-location-10270",
      "type": "Feature",
      "properties": {
        "description": "1M scale point location",
        "location_precision": "precise",
        "title": "DARMC location 10270",
        "link": "http://pleiades.stoa.org/places/207582/darmc-location-10270"
      }
    }
  ]
}