{
  "type": "FeatureCollection",
  "title": "Ulpia Traiana Sarmizegetusa",
  "id": "207527",
  "bbox": [
    22.783233,
    45.513,
    22.7873,
    45.516489
  ],
  "description": "The Roman capital of Dacia established by Trajan and located some 40 km from the indigenous center of Sarmizegetusa Regia (cited: BAtlas 21 E4 Ulpia Traiana Sarmizegetusa)",
  "names": [
    "Ulpia Traiana Sarmizegetusa"
  ],
  "features": [
    {
      "type": "Feature",
      "geometry": {
        "type": "Point",
        "coordinates": [
          22.7852665,
          45.5147445
        ]
      },
      "properties": {
        "description": "representative point"
      }
    },
    {
      "geometry": {
        "type": "Point",
        "coordinates": [
          22.783233,
          45.516489
        ]
      },
      "id": "darmc-location-34783",
      "type": "Feature",
      "properties": {
        "description": "5M scale point location",
        "location_precision": "precise",
        "title": "DARMC location 34783",
        "link": "http://pleiades.stoa.org/places/207527/darmc-location-34783"
      }
    },
    {
      "geometry": {
        "type": "Point",
        "coordinates": [
          22.7873,
          45.513
        ]
      },
      "id": "dare-location",
      "type": "Feature",
      "properties": {
        "description": "Representative point location, site precision",
        "location_precision": "precise",
        "title": "DARE Location",
        "link": "http://pleiades.stoa.org/places/207527/dare-location"
      }
    }
  ]
}