{
  "type": "FeatureCollection",
  "title": "Žuč",
  "id": "207586",
  "description": "An ancient place, cited: BAtlas 21 D6 Žuč",
  "bbox": [
    21.16886,
    43.20098,
    21.16886,
    43.20098
  ],
  "reprPoint": [
    21.16886,
    43.20098
  ],
  "features": [
    {
      "geometry": {
        "type": "Point",
        "coordinates": [
          21.16886,
          43.20098
        ]
      },
      "id": "darmc-location-24804",
      "type": "Feature",
      "properties": {
        "description": "1M scale point location",
        "location_precision": "precise",
        "title": "DARMC location 24804",
        "link": "http://pleiades.stoa.org/places/207586/darmc-location-24804"
      }
    }
  ]
}