{
  "type": "FeatureCollection",
  "title": "Turnu Rueni",
  "id": "207520",
  "description": "An ancient place, cited: BAtlas 21 E4 Turnu Rueni",
  "bbox": [
    22.333698,
    45.389929,
    22.333698,
    45.389929
  ],
  "reprPoint": [
    22.333698,
    45.389929
  ],
  "features": [
    {
      "geometry": {
        "type": "Point",
        "coordinates": [
          22.333698,
          45.389929
        ]
      },
      "id": "darmc-location-24531",
      "type": "Feature",
      "properties": {
        "description": "1M scale point location",
        "location_precision": "precise",
        "title": "DARMC location 24531",
        "link": "http://pleiades.stoa.org/places/207520/darmc-location-24531"
      }
    }
  ]
}