{
  "type": "FeatureCollection",
  "title": "Trepča",
  "id": "207511",
  "bbox": [
    20.899511,
    42.921979,
    20.899511,
    42.921979
  ],
  "description": "An ancient place, cited: BAtlas 21 C7 Trepča",
  "features": [
    {
      "type": "Feature",
      "geometry": {
        "type": "Point",
        "coordinates": [
          20.899511,
          42.921979
        ]
      },
      "properties": {
        "description": "representative point"
      }
    },
    {
      "geometry": {
        "type": "Point",
        "coordinates": [
          20.899511,
          42.921979
        ]
      },
      "id": "darmc-location-24779",
      "type": "Feature",
      "properties": {
        "description": "1M scale point location",
        "location_precision": "precise",
        "title": "DARMC location 24779",
        "link": "http://pleiades.stoa.org/places/207511/darmc-location-24779"
      }
    }
  ]
}