{
  "type": "FeatureCollection",
  "title": "Unnamed bridge",
  "id": "208942842",
  "bbox": [
    12.777484,
    43.678181,
    12.777484,
    43.678181
  ],
  "description": "An ancient place, cited: BAtlas 42 D1-C4 unnamed bridge (on Via Flaminia (20))",
  "connectsWith": [
    "856514595"
  ],
  "features": [
    {
      "type": "Feature",
      "geometry": {
        "type": "Point",
        "coordinates": [
          12.777484,
          43.678181
        ]
      },
      "properties": {
        "description": "representative point"
      }
    },
    {
      "geometry": {
        "type": "Point",
        "coordinates": [
          12.777484,
          43.678181
        ]
      },
      "id": "darmc-location-27721",
      "type": "Feature",
      "properties": {
        "description": "500K scale point location",
        "location_precision": "precise",
        "title": "DARMC location 27721",
        "link": "http://pleiades.stoa.org/places/208942842/darmc-location-27721"
      }
    }
  ]
}