{
  "type": "FeatureCollection",
  "title": "Untitled",
  "id": "208942235",
  "bbox": [
    9.753109,
    36.183052,
    9.753109,
    36.183052
  ],
  "description": "An ancient place, cited: BAtlas 32 E4 unnamed unlabeled ((15 monuments, 2 walls))",
  "features": [
    {
      "type": "Feature",
      "geometry": {
        "type": "Point",
        "coordinates": [
          9.753109,
          36.183052
        ]
      },
      "properties": {
        "description": "representative point"
      }
    },
    {
      "geometry": {
        "type": "Point",
        "coordinates": [
          9.753109,
          36.183052
        ]
      },
      "id": "darmc-location-25761",
      "type": "Feature",
      "properties": {
        "description": "500K scale point location",
        "location_precision": "precise",
        "title": "DARMC location 25761",
        "link": "http://pleiades.stoa.org/places/208942235/darmc-location-25761"
      }
    }
  ]
}