{
  "type": "FeatureCollection",
  "title": "Untitled",
  "id": "208943441",
  "description": "An ancient place, cited: BAtlas 33 C3 unnamed unlabeled ((7 monuments))",
  "bbox": [
    8.501896,
    34.80418,
    8.501896,
    34.80418
  ],
  "reprPoint": [
    8.501896,
    34.80418
  ],
  "features": [
    {
      "geometry": {
        "type": "Point",
        "coordinates": [
          8.501896,
          34.80418
        ]
      },
      "id": "darmc-location-16190",
      "type": "Feature",
      "properties": {
        "description": "500K scale point location",
        "location_precision": "precise",
        "title": "DARMC location 16190",
        "link": "http://pleiades.stoa.org/places/208943441/darmc-location-16190"
      }
    }
  ]
}