{
  "type": "FeatureCollection",
  "title": "Untitled",
  "id": "208942919",
  "bbox": [
    7.728443,
    36.512462,
    7.728443,
    36.512462
  ],
  "description": "An ancient place, cited: BAtlas 31 H3 unnamed unlabeled (settlements)",
  "features": [
    {
      "type": "Feature",
      "geometry": {
        "type": "Point",
        "coordinates": [
          7.728443,
          36.512462
        ]
      },
      "properties": {
        "description": "representative point"
      }
    },
    {
      "geometry": {
        "type": "Point",
        "coordinates": [
          7.728443,
          36.512462
        ]
      },
      "id": "darmc-location-16990",
      "type": "Feature",
      "properties": {
        "description": "500K scale point location",
        "location_precision": "precise",
        "title": "DARMC location 16990",
        "link": "http://pleiades.stoa.org/places/208942919/darmc-location-16990"
      }
    }
  ]
}