{
  "type": "FeatureCollection",
  "title": "Untitled",
  "id": "208943470",
  "description": "An ancient place, cited: BAtlas 33 B3 unnamed unlabeled ((1 monument))",
  "bbox": [
    8.480558,
    34.730902,
    8.480558,
    34.730902
  ],
  "reprPoint": [
    8.480558,
    34.730902
  ],
  "features": [
    {
      "geometry": {
        "type": "Point",
        "coordinates": [
          8.480558,
          34.730902
        ]
      },
      "id": "darmc-location-27163",
      "type": "Feature",
      "properties": {
        "description": "500K scale point location",
        "location_precision": "precise",
        "title": "DARMC location 27163",
        "link": "http://pleiades.stoa.org/places/208943470/darmc-location-27163"
      }
    }
  ]
}