{
  "type": "FeatureCollection",
  "title": "Untitled",
  "id": "208943092",
  "description": "An ancient place, cited: BAtlas 33 E1 unnamed unlabeled ((1 wall, 4 monuments, 3 aqueducts))",
  "bbox": [
    9.806229,
    35.923453,
    9.806229,
    35.923453
  ],
  "reprPoint": [
    9.806229,
    35.923453
  ],
  "features": [
    {
      "geometry": {
        "type": "Point",
        "coordinates": [
          9.806229,
          35.923453
        ]
      },
      "id": "darmc-location-27699",
      "type": "Feature",
      "properties": {
        "description": "500K scale point location",
        "location_precision": "precise",
        "title": "DARMC location 27699",
        "link": "http://pleiades.stoa.org/places/208943092/darmc-location-27699"
      }
    }
  ]
}