{
  "type": "FeatureCollection",
  "title": "Untitled",
  "id": "208943269",
  "description": "An ancient place, cited: BAtlas 32 F3 unnamed unlabeled ((1 monument))",
  "bbox": [
    10.07493,
    36.939325,
    10.07493,
    36.939325
  ],
  "reprPoint": [
    10.07493,
    36.939325
  ],
  "features": [
    {
      "geometry": {
        "type": "Point",
        "coordinates": [
          10.07493,
          36.939325
        ]
      },
      "id": "darmc-location-15992",
      "type": "Feature",
      "properties": {
        "description": "500K scale point location",
        "location_precision": "precise",
        "title": "DARMC location 15992",
        "link": "http://pleiades.stoa.org/places/208943269/darmc-location-15992"
      }
    }
  ]
}