{
  "type": "FeatureCollection",
  "title": "Untitled",
  "id": "208942184",
  "description": "An ancient place, cited: BAtlas 32 E3 unnamed unlabeled ((15 monuments))",
  "bbox": [
    9.775258,
    36.639859,
    9.775258,
    36.639859
  ],
  "reprPoint": [
    9.775258,
    36.639859
  ],
  "features": [
    {
      "geometry": {
        "type": "Point",
        "coordinates": [
          9.775258,
          36.639859
        ]
      },
      "id": "darmc-location-15880",
      "type": "Feature",
      "properties": {
        "description": "500K scale point location",
        "location_precision": "precise",
        "title": "DARMC location 15880",
        "link": "http://pleiades.stoa.org/places/208942184/darmc-location-15880"
      }
    }
  ]
}