{
  "type": "FeatureCollection",
  "title": "Untitled",
  "id": "208942422",
  "description": "An ancient place, cited: BAtlas 32 D4 unnamed unlabeled ((7 monuments, 1 cemetery, 2 walls))",
  "bbox": [
    9.330692,
    36.380923,
    9.330692,
    36.380923
  ],
  "reprPoint": [
    9.330692,
    36.380923
  ],
  "features": [
    {
      "geometry": {
        "type": "Point",
        "coordinates": [
          9.330692,
          36.380923
        ]
      },
      "id": "darmc-location-33114",
      "type": "Feature",
      "properties": {
        "description": "scale point location",
        "location_precision": "precise",
        "title": "DARMC location 33114",
        "link": "http://pleiades.stoa.org/places/208942422/darmc-location-33114"
      }
    }
  ]
}