{
  "type": "FeatureCollection",
  "title": "Untitled",
  "id": "208942412",
  "description": "An ancient place, cited: BAtlas 32 D4 unnamed unlabeled ((7 monuments, 1 cemetery, 2 walls))",
  "bbox": [
    9.297094,
    36.080324,
    9.297094,
    36.080324
  ],
  "reprPoint": [
    9.297094,
    36.080324
  ],
  "features": [
    {
      "geometry": {
        "type": "Point",
        "coordinates": [
          9.297094,
          36.080324
        ]
      },
      "id": "darmc-location-15575",
      "type": "Feature",
      "properties": {
        "description": "500K scale point location",
        "location_precision": "precise",
        "title": "DARMC location 15575",
        "link": "http://pleiades.stoa.org/places/208942412/darmc-location-15575"
      }
    }
  ]
}