{
  "type": "FeatureCollection",
  "title": "Untitled",
  "id": "208942285",
  "description": "An ancient place, cited: BAtlas 32 B3 unnamed unlabeled ((1 monument, 1 cemetery))",
  "bbox": [
    8.281239,
    36.703959,
    8.281239,
    36.703959
  ],
  "reprPoint": [
    8.281239,
    36.703959
  ],
  "features": [
    {
      "geometry": {
        "type": "Point",
        "coordinates": [
          8.281239,
          36.703959
        ]
      },
      "id": "darmc-location-15834",
      "type": "Feature",
      "properties": {
        "description": "500K scale point location",
        "location_precision": "precise",
        "title": "DARMC location 15834",
        "link": "http://pleiades.stoa.org/places/208942285/darmc-location-15834"
      }
    }
  ]
}