{
  "type": "FeatureCollection",
  "title": "Untitled",
  "id": "208942916",
  "description": "An ancient place, cited: BAtlas 31 H3 unnamed unlabeled (settlements)",
  "bbox": [
    7.594769,
    36.611551,
    7.594769,
    36.611551
  ],
  "reprPoint": [
    7.594769,
    36.611551
  ],
  "features": [
    {
      "geometry": {
        "type": "Point",
        "coordinates": [
          7.594769,
          36.611551
        ]
      },
      "id": "darmc-location-27342",
      "type": "Feature",
      "properties": {
        "description": "500K scale point location",
        "location_precision": "precise",
        "title": "DARMC location 27342",
        "link": "http://pleiades.stoa.org/places/208942916/darmc-location-27342"
      }
    }
  ]
}