{
  "type": "FeatureCollection",
  "title": "Untitled",
  "id": "208943363",
  "description": "An ancient place, cited: BAtlas 32 G3 unnamed unlabeled ((1 bath, 1 cemetery))",
  "bbox": [
    10.665763,
    36.651806,
    10.665763,
    36.651806
  ],
  "reprPoint": [
    10.665763,
    36.651806
  ],
  "features": [
    {
      "geometry": {
        "type": "Point",
        "coordinates": [
          10.665763,
          36.651806
        ]
      },
      "id": "darmc-location-15962",
      "type": "Feature",
      "properties": {
        "description": "500K scale point location",
        "location_precision": "precise",
        "title": "DARMC location 15962",
        "link": "http://pleiades.stoa.org/places/208943363/darmc-location-15962"
      }
    }
  ]
}