{
  "type": "FeatureCollection",
  "title": "Untitled",
  "id": "208943466",
  "description": "An ancient place, cited: BAtlas 33 B3 unnamed unlabeled ((1 monument))",
  "bbox": [
    8.191774,
    34.62157,
    8.191774,
    34.62157
  ],
  "reprPoint": [
    8.191774,
    34.62157
  ],
  "features": [
    {
      "geometry": {
        "type": "Point",
        "coordinates": [
          8.191774,
          34.62157
        ]
      },
      "id": "darmc-location-25785",
      "type": "Feature",
      "properties": {
        "description": "500K scale point location",
        "location_precision": "precise",
        "title": "DARMC location 25785",
        "link": "http://pleiades.stoa.org/places/208943466/darmc-location-25785"
      }
    }
  ]
}