{
  "type": "FeatureCollection",
  "title": "Untitled",
  "id": "208943088",
  "description": "An ancient place, cited: BAtlas 33 E1 unnamed unlabeled ((1 wall, 4 monuments, 3 aqueducts))",
  "bbox": [
    9.641688,
    35.851375,
    9.641688,
    35.851375
  ],
  "reprPoint": [
    9.641688,
    35.851375
  ],
  "features": [
    {
      "geometry": {
        "type": "Point",
        "coordinates": [
          9.641688,
          35.851375
        ]
      },
      "id": "darmc-location-20846",
      "type": "Feature",
      "properties": {
        "description": "500K scale point location",
        "location_precision": "precise",
        "title": "DARMC location 20846",
        "link": "http://pleiades.stoa.org/places/208943088/darmc-location-20846"
      }
    }
  ]
}