{
  "type": "FeatureCollection",
  "title": "Untitled",
  "id": "208942994",
  "description": "An ancient place, cited: BAtlas 33 G1 unnamed unlabeled ((1 cemetery))",
  "bbox": [
    10.589115,
    35.901132,
    10.589115,
    35.901132
  ],
  "reprPoint": [
    10.589115,
    35.901132
  ],
  "features": [
    {
      "geometry": {
        "type": "Point",
        "coordinates": [
          10.589115,
          35.901132
        ]
      },
      "id": "darmc-location-27320",
      "type": "Feature",
      "properties": {
        "description": "500K scale point location",
        "location_precision": "precise",
        "title": "DARMC location 27320",
        "link": "http://pleiades.stoa.org/places/208942994/darmc-location-27320"
      }
    }
  ]
}