{
  "type": "FeatureCollection",
  "title": "Untitled",
  "id": "208942528",
  "description": "An ancient place, cited: BAtlas 34 F3 unnamed feature ()",
  "bbox": [
    7.260452,
    34.584504,
    7.260452,
    34.584504
  ],
  "reprPoint": [
    7.260452,
    34.584504
  ],
  "features": [
    {
      "geometry": {
        "type": "Point",
        "coordinates": [
          7.260452,
          34.584504
        ]
      },
      "id": "darmc-location-20701",
      "type": "Feature",
      "properties": {
        "description": "500K scale point location",
        "location_precision": "precise",
        "title": "DARMC location 20701",
        "link": "http://pleiades.stoa.org/places/208942528/darmc-location-20701"
      }
    }
  ]
}