{
  "type": "FeatureCollection",
  "title": "Untitled",
  "id": "208942381",
  "description": "An ancient place, cited: BAtlas 32 C3 unnamed unlabeled ((2 monuments))",
  "bbox": [
    8.754645,
    36.943792,
    8.754645,
    36.943792
  ],
  "reprPoint": [
    8.754645,
    36.943792
  ],
  "features": [
    {
      "geometry": {
        "type": "Point",
        "coordinates": [
          8.754645,
          36.943792
        ]
      },
      "id": "darmc-location-26644",
      "type": "Feature",
      "properties": {
        "description": "500K scale point location",
        "location_precision": "precise",
        "title": "DARMC location 26644",
        "link": "http://pleiades.stoa.org/places/208942381/darmc-location-26644"
      }
    }
  ]
}