{
  "type": "FeatureCollection",
  "title": "Untitled",
  "id": "208943576",
  "description": "An ancient place, cited: BAtlas 33 D1 unnamed unlabeled ((1 aqueduct, 2 monuments, 2 cemeteries))",
  "bbox": [
    9.132056,
    35.698479,
    9.132056,
    35.698479
  ],
  "reprPoint": [
    9.132056,
    35.698479
  ],
  "features": [
    {
      "geometry": {
        "type": "Point",
        "coordinates": [
          9.132056,
          35.698479
        ]
      },
      "id": "darmc-location-20785",
      "type": "Feature",
      "properties": {
        "description": "500K scale point location",
        "location_precision": "precise",
        "title": "DARMC location 20785",
        "link": "http://pleiades.stoa.org/places/208943576/darmc-location-20785"
      }
    }
  ]
}