{
  "type": "FeatureCollection",
  "title": "Untitled",
  "id": "208942747",
  "description": "An ancient place, cited: BAtlas 34 E3 unnamed feature ()",
  "bbox": [
    6.022584,
    34.789218,
    6.022584,
    34.789218
  ],
  "reprPoint": [
    6.022584,
    34.789218
  ],
  "features": [
    {
      "geometry": {
        "type": "Point",
        "coordinates": [
          6.022584,
          34.789218
        ]
      },
      "id": "darmc-location-33362",
      "type": "Feature",
      "properties": {
        "description": "scale point location",
        "location_precision": "precise",
        "title": "DARMC location 33362",
        "link": "http://pleiades.stoa.org/places/208942747/darmc-location-33362"
      }
    }
  ]
}