{
  "type": "FeatureCollection",
  "title": "Untitled",
  "id": "208942272",
  "description": "An ancient place, cited: BAtlas 32 B3 unnamed unlabeled ((1 monument, 1 cemetery))",
  "bbox": [
    8.431872,
    36.503979,
    8.431872,
    36.503979
  ],
  "reprPoint": [
    8.431872,
    36.503979
  ],
  "features": [
    {
      "geometry": {
        "type": "Point",
        "coordinates": [
          8.431872,
          36.503979
        ]
      },
      "id": "darmc-location-26707",
      "type": "Feature",
      "properties": {
        "description": "500K scale point location",
        "location_precision": "precise",
        "title": "DARMC location 26707",
        "link": "http://pleiades.stoa.org/places/208942272/darmc-location-26707"
      }
    }
  ]
}