{
  "type": "FeatureCollection",
  "title": "Untitled",
  "id": "208942572",
  "bbox": [
    7.007626,
    35.942147,
    7.007626,
    35.942147
  ],
  "description": "An ancient place, cited: BAtlas 34 F2 unnamed feature ()",
  "features": [
    {
      "type": "Feature",
      "geometry": {
        "type": "Point",
        "coordinates": [
          7.007626,
          35.942147
        ]
      },
      "properties": {
        "description": "representative point"
      }
    },
    {
      "geometry": {
        "type": "Point",
        "coordinates": [
          7.007626,
          35.942147
        ]
      },
      "id": "darmc-location-14947",
      "type": "Feature",
      "properties": {
        "description": "500K scale point location",
        "location_precision": "precise",
        "title": "DARMC location 14947",
        "link": "http://pleiades.stoa.org/places/208942572/darmc-location-14947"
      }
    }
  ]
}