{
  "type": "FeatureCollection",
  "title": "Ponte del Toro",
  "id": "208942845",
  "description": "A Roman arched bridge on the Via Flaminia near modern Terni.",
  "bbox": [
    12.704738,
    42.549514,
    12.704738,
    42.549514
  ],
  "connectsWith": [
    "856514595"
  ],
  "reprPoint": [
    12.704738,
    42.549514
  ],
  "features": [
    {
      "geometry": {
        "type": "Point",
        "coordinates": [
          12.704738,
          42.549514
        ]
      },
      "id": "darmc-location-27730",
      "type": "Feature",
      "properties": {
        "description": "500K scale point location",
        "location_precision": "precise",
        "title": "DARMC location 27730",
        "link": "http://pleiades.stoa.org/places/208942845/darmc-location-27730"
      }
    }
  ]
}