{
  "type": "FeatureCollection",
  "title": "Untitled",
  "id": "208943129",
  "bbox": [
    10.385006,
    35.472855,
    10.385006,
    35.472855
  ],
  "description": "An ancient place, cited: BAtlas 33 F2 unnamed unlabeled ((1 cemetery, 1 monument, 1 aqueduct))",
  "features": [
    {
      "type": "Feature",
      "geometry": {
        "type": "Point",
        "coordinates": [
          10.385006,
          35.472855
        ]
      },
      "properties": {
        "description": "representative point"
      }
    },
    {
      "geometry": {
        "type": "Point",
        "coordinates": [
          10.385006,
          35.472855
        ]
      },
      "id": "darmc-location-20884",
      "type": "Feature",
      "properties": {
        "description": "500K scale point location",
        "location_precision": "precise",
        "title": "DARMC location 20884",
        "link": "http://pleiades.stoa.org/places/208943129/darmc-location-20884"
      }
    }
  ]
}