{
  "type": "FeatureCollection",
  "title": "Untitled",
  "id": "208942520",
  "description": "An ancient place, cited: BAtlas 32 C4 unlabeled (settlements)",
  "bbox": [
    8.711474,
    36.319575,
    8.711474,
    36.319575
  ],
  "reprPoint": [
    8.711474,
    36.319575
  ],
  "features": [
    {
      "geometry": {
        "type": "Point",
        "coordinates": [
          8.711474,
          36.319575
        ]
      },
      "id": "darmc-location-15733",
      "type": "Feature",
      "properties": {
        "description": "500K scale point location",
        "location_precision": "precise",
        "title": "DARMC location 15733",
        "link": "http://pleiades.stoa.org/places/208942520/darmc-location-15733"
      }
    }
  ]
}