{
  "type": "FeatureCollection",
  "title": "Untitled",
  "id": "208942215",
  "description": "An ancient place, cited: BAtlas 32 E4 unnamed unlabeled ((15 monuments, 2 walls))",
  "bbox": [
    9.534709,
    36.040552,
    9.534709,
    36.040552
  ],
  "reprPoint": [
    9.534709,
    36.040552
  ],
  "features": [
    {
      "geometry": {
        "type": "Point",
        "coordinates": [
          9.534709,
          36.040552
        ]
      },
      "id": "darmc-location-15868",
      "type": "Feature",
      "properties": {
        "description": "500K scale point location",
        "location_precision": "precise",
        "title": "DARMC location 15868",
        "link": "http://pleiades.stoa.org/places/208942215/darmc-location-15868"
      }
    }
  ]
}