{
  "type": "FeatureCollection",
  "title": "Untitled",
  "id": "208943542",
  "description": "An ancient place, cited: BAtlas 33 D2 unnamed unlabeled ((5 monuments))",
  "bbox": [
    9.17462,
    35.302912,
    9.17462,
    35.302912
  ],
  "reprPoint": [
    9.17462,
    35.302912
  ],
  "features": [
    {
      "geometry": {
        "type": "Point",
        "coordinates": [
          9.17462,
          35.302912
        ]
      },
      "id": "darmc-location-27245",
      "type": "Feature",
      "properties": {
        "description": "500K scale point location",
        "location_precision": "precise",
        "title": "DARMC location 27245",
        "link": "http://pleiades.stoa.org/places/208943542/darmc-location-27245"
      }
    }
  ]
}