{
  "type": "FeatureCollection",
  "title": "Untitled",
  "id": "208942543",
  "description": "An ancient place, cited: BAtlas 34 F3 unnamed feature ()",
  "bbox": [
    7.410762,
    34.434495,
    7.410762,
    34.434495
  ],
  "reprPoint": [
    7.410762,
    34.434495
  ],
  "features": [
    {
      "geometry": {
        "type": "Point",
        "coordinates": [
          7.410762,
          34.434495
        ]
      },
      "id": "darmc-location-20697",
      "type": "Feature",
      "properties": {
        "description": "500K scale point location",
        "location_precision": "precise",
        "title": "DARMC location 20697",
        "link": "http://pleiades.stoa.org/places/208942543/darmc-location-20697"
      }
    }
  ]
}