{
  "type": "FeatureCollection",
  "title": "Untitled",
  "id": "208943007",
  "description": "An ancient place, cited: BAtlas 33 G2 unnamed unlabeled ((3 monuments, 1 bath))",
  "bbox": [
    10.858846,
    35.196872,
    10.858846,
    35.196872
  ],
  "reprPoint": [
    10.858846,
    35.196872
  ],
  "features": [
    {
      "geometry": {
        "type": "Point",
        "coordinates": [
          10.858846,
          35.196872
        ]
      },
      "id": "darmc-location-20395",
      "type": "Feature",
      "properties": {
        "description": "500K scale point location",
        "location_precision": "precise",
        "title": "DARMC location 20395",
        "link": "http://pleiades.stoa.org/places/208943007/darmc-location-20395"
      }
    }
  ]
}