{
  "type": "FeatureCollection",
  "title": "Untitled",
  "id": "208942552",
  "bbox": [
    7.863721,
    35.148723,
    7.863721,
    35.148723
  ],
  "description": "An ancient place, cited: BAtlas 34 F2 unnamed feature ()",
  "features": [
    {
      "type": "Feature",
      "geometry": {
        "type": "Point",
        "coordinates": [
          7.863721,
          35.148723
        ]
      },
      "properties": {
        "description": "representative point"
      }
    },
    {
      "geometry": {
        "type": "Point",
        "coordinates": [
          7.863721,
          35.148723
        ]
      },
      "id": "darmc-location-20601",
      "type": "Feature",
      "properties": {
        "description": "500K scale point location",
        "location_precision": "precise",
        "title": "DARMC location 20601",
        "link": "http://pleiades.stoa.org/places/208942552/darmc-location-20601"
      }
    }
  ]
}