{
  "type": "FeatureCollection",
  "title": "Untitled",
  "id": "208943600",
  "bbox": [
    5.850889,
    36.360549,
    5.850889,
    36.360549
  ],
  "description": "An ancient place, cited: BAtlas 31 D4 unnamed unlabeled (settlements)",
  "features": [
    {
      "type": "Feature",
      "geometry": {
        "type": "Point",
        "coordinates": [
          5.850889,
          36.360549
        ]
      },
      "properties": {
        "description": "representative point"
      }
    },
    {
      "geometry": {
        "type": "Point",
        "coordinates": [
          5.850889,
          36.360549
        ]
      },
      "id": "darmc-location-20919",
      "type": "Feature",
      "properties": {
        "description": "500K scale point location",
        "location_precision": "precise",
        "title": "DARMC location 20919",
        "link": "http://pleiades.stoa.org/places/208943600/darmc-location-20919"
      }
    }
  ]
}