{
  "type": "FeatureCollection",
  "title": "Untitled",
  "id": "208942946",
  "description": "An ancient place, cited: BAtlas 31 F4 unnamed unlabeled (settlements)",
  "bbox": [
    6.873727,
    36.033369,
    6.873727,
    36.033369
  ],
  "reprPoint": [
    6.873727,
    36.033369
  ],
  "features": [
    {
      "geometry": {
        "type": "Point",
        "coordinates": [
          6.873727,
          36.033369
        ]
      },
      "id": "darmc-location-20968",
      "type": "Feature",
      "properties": {
        "description": "500K scale point location",
        "location_precision": "precise",
        "title": "DARMC location 20968",
        "link": "http://pleiades.stoa.org/places/208942946/darmc-location-20968"
      }
    }
  ]
}