{
  "type": "FeatureCollection",
  "title": "Untitled",
  "id": "208943083",
  "description": "An ancient place, cited: BAtlas 33 E1 unnamed unlabeled ((1 wall, 4 monuments, 3 aqueducts))",
  "bbox": [
    9.659933,
    35.838214,
    9.659933,
    35.838214
  ],
  "reprPoint": [
    9.659933,
    35.838214
  ],
  "features": [
    {
      "geometry": {
        "type": "Point",
        "coordinates": [
          9.659933,
          35.838214
        ]
      },
      "id": "darmc-location-20848",
      "type": "Feature",
      "properties": {
        "description": "500K scale point location",
        "location_precision": "precise",
        "title": "DARMC location 20848",
        "link": "http://pleiades.stoa.org/places/208943083/darmc-location-20848"
      }
    }
  ]
}