{
  "type": "FeatureCollection",
  "title": "Untitled",
  "id": "208943121",
  "description": "An ancient place, cited: BAtlas 33 F1 unnamed unlabeled ((3 cemeteries, 1 monument, 1 wall))",
  "bbox": [
    10.200033,
    35.555606,
    10.200033,
    35.555606
  ],
  "reprPoint": [
    10.200033,
    35.555606
  ],
  "features": [
    {
      "geometry": {
        "type": "Point",
        "coordinates": [
          10.200033,
          35.555606
        ]
      },
      "id": "darmc-location-25828",
      "type": "Feature",
      "properties": {
        "description": "500K scale point location",
        "location_precision": "precise",
        "title": "DARMC location 25828",
        "link": "http://pleiades.stoa.org/places/208943121/darmc-location-25828"
      }
    }
  ]
}