{
  "type": "FeatureCollection",
  "title": "Untitled",
  "id": "208943255",
  "description": "An ancient place, cited: BAtlas 32 F3 unnamed unlabeled ((1 monument))",
  "bbox": [
    10.026482,
    36.605863,
    10.026482,
    36.605863
  ],
  "reprPoint": [
    10.026482,
    36.605863
  ],
  "features": [
    {
      "geometry": {
        "type": "Point",
        "coordinates": [
          10.026482,
          36.605863
        ]
      },
      "id": "darmc-location-16136",
      "type": "Feature",
      "properties": {
        "description": "500K scale point location",
        "location_precision": "precise",
        "title": "DARMC location 16136",
        "link": "http://pleiades.stoa.org/places/208943255/darmc-location-16136"
      }
    }
  ]
}