{
  "type": "FeatureCollection",
  "title": "Untitled",
  "id": "208943429",
  "description": "An ancient place, cited: BAtlas 33 C3 unnamed unlabeled ((7 monuments))",
  "bbox": [
    8.814916,
    34.942446,
    8.814916,
    34.942446
  ],
  "reprPoint": [
    8.814916,
    34.942446
  ],
  "features": [
    {
      "geometry": {
        "type": "Point",
        "coordinates": [
          8.814916,
          34.942446
        ]
      },
      "id": "darmc-location-27206",
      "type": "Feature",
      "properties": {
        "description": "500K scale point location",
        "location_precision": "precise",
        "title": "DARMC location 27206",
        "link": "http://pleiades.stoa.org/places/208943429/darmc-location-27206"
      }
    }
  ]
}