{
  "type": "FeatureCollection",
  "title": "Untitled",
  "id": "208942212",
  "description": "An ancient place, cited: BAtlas 32 E3 unnamed unlabeled ((15 monuments))",
  "bbox": [
    9.582687,
    36.735094,
    9.582687,
    36.735094
  ],
  "reprPoint": [
    9.582687,
    36.735094
  ],
  "features": [
    {
      "geometry": {
        "type": "Point",
        "coordinates": [
          9.582687,
          36.735094
        ]
      },
      "id": "darmc-location-26761",
      "type": "Feature",
      "properties": {
        "description": "500K scale point location",
        "location_precision": "precise",
        "title": "DARMC location 26761",
        "link": "http://pleiades.stoa.org/places/208942212/darmc-location-26761"
      }
    }
  ]
}