{
  "type": "FeatureCollection",
  "title": "Untitled",
  "id": "208942920",
  "description": "An ancient place, cited: BAtlas 31 H3 unnamed unlabeled (settlements)",
  "bbox": [
    7.853337,
    36.754924,
    7.853337,
    36.754924
  ],
  "reprPoint": [
    7.853337,
    36.754924
  ],
  "features": [
    {
      "geometry": {
        "type": "Point",
        "coordinates": [
          7.853337,
          36.754924
        ]
      },
      "id": "darmc-location-27350",
      "type": "Feature",
      "properties": {
        "description": "500K scale point location",
        "location_precision": "precise",
        "title": "DARMC location 27350",
        "link": "http://pleiades.stoa.org/places/208942920/darmc-location-27350"
      }
    }
  ]
}