{
  "type": "FeatureCollection",
  "title": "Untitled",
  "id": "208942532",
  "bbox": [
    7.494251,
    34.708564,
    7.494251,
    34.708564
  ],
  "description": "An ancient place, cited: BAtlas 34 F3 unnamed feature ()",
  "features": [
    {
      "type": "Feature",
      "geometry": {
        "type": "Point",
        "coordinates": [
          7.494251,
          34.708564
        ]
      },
      "properties": {
        "description": "representative point"
      }
    },
    {
      "geometry": {
        "type": "Point",
        "coordinates": [
          7.494251,
          34.708564
        ]
      },
      "id": "darmc-location-20679",
      "type": "Feature",
      "properties": {
        "description": "500K scale point location",
        "location_precision": "precise",
        "title": "DARMC location 20679",
        "link": "http://pleiades.stoa.org/places/208942532/darmc-location-20679"
      }
    }
  ]
}