{
  "type": "FeatureCollection",
  "title": "Untitled",
  "id": "208942473",
  "description": "An ancient place, cited: BAtlas 32 D2 unnamed unlabeled ((5 monuments))",
  "bbox": [
    9.273018,
    37.128475,
    9.273018,
    37.128475
  ],
  "reprPoint": [
    9.273018,
    37.128475
  ],
  "features": [
    {
      "geometry": {
        "type": "Point",
        "coordinates": [
          9.273018,
          37.128475
        ]
      },
      "id": "darmc-location-26615",
      "type": "Feature",
      "properties": {
        "description": "500K scale point location",
        "location_precision": "precise",
        "title": "DARMC location 26615",
        "link": "http://pleiades.stoa.org/places/208942473/darmc-location-26615"
      }
    }
  ]
}