{
  "type": "FeatureCollection",
  "title": "Untitled",
  "id": "208943648",
  "description": "An ancient place, cited: BAtlas 31 C4 unnamed unlabeled (settlements)",
  "bbox": [
    5.249937,
    36.182487,
    5.249937,
    36.182487
  ],
  "reprPoint": [
    5.249937,
    36.182487
  ],
  "features": [
    {
      "geometry": {
        "type": "Point",
        "coordinates": [
          5.249937,
          36.182487
        ]
      },
      "id": "darmc-location-20444",
      "type": "Feature",
      "properties": {
        "description": "500K scale point location",
        "location_precision": "precise",
        "title": "DARMC location 20444",
        "link": "http://pleiades.stoa.org/places/208943648/darmc-location-20444"
      }
    }
  ]
}