{
  "type": "FeatureCollection",
  "title": "Untitled",
  "id": "208943572",
  "description": "An ancient place, cited: BAtlas 33 D1 unnamed unlabeled ((1 aqueduct, 2 monuments, 2 cemeteries))",
  "bbox": [
    9.049232,
    35.791603,
    9.049232,
    35.791603
  ],
  "reprPoint": [
    9.049232,
    35.791603
  ],
  "features": [
    {
      "geometry": {
        "type": "Point",
        "coordinates": [
          9.049232,
          35.791603
        ]
      },
      "id": "darmc-location-20781",
      "type": "Feature",
      "properties": {
        "description": "500K scale point location",
        "location_precision": "precise",
        "title": "DARMC location 20781",
        "link": "http://pleiades.stoa.org/places/208943572/darmc-location-20781"
      }
    }
  ]
}