{
  "type": "FeatureCollection",
  "title": "Untitled",
  "id": "208942811",
  "bbox": [
    6.813462,
    35.23615,
    6.813462,
    35.23615
  ],
  "description": "An ancient place, cited: BAtlas 34 E2 unnamed feature ()",
  "features": [
    {
      "type": "Feature",
      "geometry": {
        "type": "Point",
        "coordinates": [
          6.813462,
          35.23615
        ]
      },
      "properties": {
        "description": "representative point"
      }
    },
    {
      "geometry": {
        "type": "Point",
        "coordinates": [
          6.813462,
          35.23615
        ]
      },
      "id": "darmc-location-16175",
      "type": "Feature",
      "properties": {
        "description": "500K scale point location",
        "location_precision": "precise",
        "title": "DARMC location 16175",
        "link": "http://pleiades.stoa.org/places/208942811/darmc-location-16175"
      }
    }
  ]
}