{
  "type": "FeatureCollection",
  "title": "Untitled",
  "id": "208943098",
  "description": "An ancient place, cited: BAtlas 33 E1 unnamed unlabeled ((1 wall, 4 monuments, 3 aqueducts))",
  "bbox": [
    9.591814,
    35.701681,
    9.591814,
    35.701681
  ],
  "reprPoint": [
    9.591814,
    35.701681
  ],
  "features": [
    {
      "geometry": {
        "type": "Point",
        "coordinates": [
          9.591814,
          35.701681
        ]
      },
      "id": "darmc-location-20826",
      "type": "Feature",
      "properties": {
        "description": "500K scale point location",
        "location_precision": "precise",
        "title": "DARMC location 20826",
        "link": "http://pleiades.stoa.org/places/208943098/darmc-location-20826"
      }
    }
  ]
}