{
  "type": "FeatureCollection",
  "title": "Untitled",
  "id": "208942259",
  "bbox": [
    9.58595,
    36.361564,
    9.58595,
    36.361564
  ],
  "description": "An ancient place, cited: BAtlas 32 E4 unnamed unlabeled ((15 monuments, 2 walls))",
  "features": [
    {
      "type": "Feature",
      "geometry": {
        "type": "Point",
        "coordinates": [
          9.58595,
          36.361564
        ]
      },
      "properties": {
        "description": "representative point"
      }
    },
    {
      "geometry": {
        "type": "Point",
        "coordinates": [
          9.58595,
          36.361564
        ]
      },
      "id": "darmc-location-26775",
      "type": "Feature",
      "properties": {
        "description": "500K scale point location",
        "location_precision": "precise",
        "title": "DARMC location 26775",
        "link": "http://pleiades.stoa.org/places/208942259/darmc-location-26775"
      }
    }
  ]
}