{
  "type": "FeatureCollection",
  "title": "Untitled",
  "id": "208942606",
  "description": "An ancient place, cited: BAtlas 34 F2 unnamed feature ()",
  "bbox": [
    7.55758,
    35.247824,
    7.55758,
    35.247824
  ],
  "reprPoint": [
    7.55758,
    35.247824
  ],
  "features": [
    {
      "geometry": {
        "type": "Point",
        "coordinates": [
          7.55758,
          35.247824
        ]
      },
      "id": "darmc-location-20620",
      "type": "Feature",
      "properties": {
        "description": "500K scale point location",
        "location_precision": "precise",
        "title": "DARMC location 20620",
        "link": "http://pleiades.stoa.org/places/208942606/darmc-location-20620"
      }
    }
  ]
}