{
  "type": "FeatureCollection",
  "title": "Untitled",
  "id": "208943125",
  "bbox": [
    10.346026,
    35.999746,
    10.346026,
    35.999746
  ],
  "description": "An ancient place, cited: BAtlas 33 F1 unnamed unlabeled ((3 cemeteries, 1 monument, 1 wall))",
  "features": [
    {
      "type": "Feature",
      "geometry": {
        "type": "Point",
        "coordinates": [
          10.346026,
          35.999746
        ]
      },
      "properties": {
        "description": "representative point"
      }
    },
    {
      "geometry": {
        "type": "Point",
        "coordinates": [
          10.346026,
          35.999746
        ]
      },
      "id": "darmc-location-33134",
      "type": "Feature",
      "properties": {
        "description": "representative point location digitized from the Barrington Atlas of the Greek and Roman World by the Digital Atlas of Roman and Medieval Civilizations project at Harvard University.",
        "location_precision": "precise",
        "title": "DARMC location 33134",
        "link": "http://pleiades.stoa.org/places/208943125/darmc-location-33134"
      }
    }
  ]
}