{
  "type": "FeatureCollection",
  "title": "Untitled",
  "id": "208943370",
  "description": "An ancient place, cited: BAtlas 32 G3 unnamed unlabeled ((1 bath, 1 cemetery))",
  "bbox": [
    10.687441,
    36.781904,
    10.687441,
    36.781904
  ],
  "reprPoint": [
    10.687441,
    36.781904
  ],
  "features": [
    {
      "geometry": {
        "type": "Point",
        "coordinates": [
          10.687441,
          36.781904
        ]
      },
      "id": "darmc-location-26793",
      "type": "Feature",
      "properties": {
        "description": "500K scale point location",
        "location_precision": "precise",
        "title": "DARMC location 26793",
        "link": "http://pleiades.stoa.org/places/208943370/darmc-location-26793"
      }
    }
  ]
}