{
  "type": "FeatureCollection",
  "title": "Untitled",
  "id": "208943608",
  "bbox": [
    5.69823,
    36.087002,
    5.69823,
    36.087002
  ],
  "description": "An ancient place, cited: BAtlas 31 D4 unnamed unlabeled (settlements)",
  "features": [
    {
      "type": "Feature",
      "geometry": {
        "type": "Point",
        "coordinates": [
          5.69823,
          36.087002
        ]
      },
      "properties": {
        "description": "representative point"
      }
    },
    {
      "geometry": {
        "type": "Point",
        "coordinates": [
          5.69823,
          36.087002
        ]
      },
      "id": "darmc-location-20903",
      "type": "Feature",
      "properties": {
        "description": "500K scale point location",
        "location_precision": "precise",
        "title": "DARMC location 20903",
        "link": "http://pleiades.stoa.org/places/208943608/darmc-location-20903"
      }
    }
  ]
}