{
  "type": "FeatureCollection",
  "title": "Untitled",
  "id": "208943739",
  "description": "An ancient place, cited: BAtlas 33 H2 unnamed unlabeled ((4 cemeteries))",
  "bbox": [
    11.025055,
    35.3592,
    11.025055,
    35.3592
  ],
  "reprPoint": [
    11.025055,
    35.3592
  ],
  "features": [
    {
      "geometry": {
        "type": "Point",
        "coordinates": [
          11.025055,
          35.3592
        ]
      },
      "id": "darmc-location-33296",
      "type": "Feature",
      "properties": {
        "description": "scale point location",
        "location_precision": "precise",
        "title": "DARMC location 33296",
        "link": "http://pleiades.stoa.org/places/208943739/darmc-location-33296"
      }
    }
  ]
}