{
  "type": "FeatureCollection",
  "title": "Untitled",
  "id": "208942262",
  "description": "An ancient place, cited: BAtlas 32 E4 unnamed unlabeled ((15 monuments, 2 walls))",
  "bbox": [
    9.559808,
    36.144873,
    9.559808,
    36.144873
  ],
  "reprPoint": [
    9.559808,
    36.144873
  ],
  "features": [
    {
      "geometry": {
        "type": "Point",
        "coordinates": [
          9.559808,
          36.144873
        ]
      },
      "id": "darmc-location-26778",
      "type": "Feature",
      "properties": {
        "description": "500K scale point location",
        "location_precision": "precise",
        "title": "DARMC location 26778",
        "link": "http://pleiades.stoa.org/places/208942262/darmc-location-26778"
      }
    }
  ]
}