{
  "type": "FeatureCollection",
  "title": "Untitled",
  "id": "208942187",
  "bbox": [
    9.792366,
    36.703404,
    9.792366,
    36.703404
  ],
  "description": "An ancient place, cited: BAtlas 32 E3 unnamed unlabeled ((15 monuments))",
  "features": [
    {
      "type": "Feature",
      "geometry": {
        "type": "Point",
        "coordinates": [
          9.792366,
          36.703404
        ]
      },
      "properties": {
        "description": "representative point"
      }
    },
    {
      "geometry": {
        "type": "Point",
        "coordinates": [
          9.792366,
          36.703404
        ]
      },
      "id": "darmc-location-26797",
      "type": "Feature",
      "properties": {
        "description": "500K scale point location",
        "location_precision": "precise",
        "title": "DARMC location 26797",
        "link": "http://pleiades.stoa.org/places/208942187/darmc-location-26797"
      }
    }
  ]
}