{
  "type": "FeatureCollection",
  "title": "Untitled",
  "id": "208943379",
  "description": "An ancient place, cited: BAtlas 32 G3 unnamed unlabeled ((1 bath, 1 cemetery))",
  "bbox": [
    10.683844,
    36.85134,
    10.683844,
    36.85134
  ],
  "reprPoint": [
    10.683844,
    36.85134
  ],
  "features": [
    {
      "geometry": {
        "type": "Point",
        "coordinates": [
          10.683844,
          36.85134
        ]
      },
      "id": "darmc-location-16031",
      "type": "Feature",
      "properties": {
        "description": "500K scale point location",
        "location_precision": "precise",
        "title": "DARMC location 16031",
        "link": "http://pleiades.stoa.org/places/208943379/darmc-location-16031"
      }
    }
  ]
}