{
  "type": "FeatureCollection",
  "title": "Untitled",
  "id": "208943132",
  "description": "An ancient place, cited: BAtlas 33 F2 unnamed unlabeled ((1 cemetery, 1 monument, 1 aqueduct))",
  "bbox": [
    10.266341,
    35.422268,
    10.266341,
    35.422268
  ],
  "reprPoint": [
    10.266341,
    35.422268
  ],
  "features": [
    {
      "geometry": {
        "type": "Point",
        "coordinates": [
          10.266341,
          35.422268
        ]
      },
      "id": "darmc-location-20888",
      "type": "Feature",
      "properties": {
        "description": "500K scale point location",
        "location_precision": "precise",
        "title": "DARMC location 20888",
        "link": "http://pleiades.stoa.org/places/208943132/darmc-location-20888"
      }
    }
  ]
}