{
  "type": "FeatureCollection",
  "title": "Untitled",
  "id": "208943587",
  "description": "An ancient place, cited: BAtlas 31 D4 unnamed unlabeled (settlements)",
  "bbox": [
    5.91221,
    36.015659,
    5.91221,
    36.015659
  ],
  "reprPoint": [
    5.91221,
    36.015659
  ],
  "features": [
    {
      "geometry": {
        "type": "Point",
        "coordinates": [
          5.91221,
          36.015659
        ]
      },
      "id": "darmc-location-19412",
      "type": "Feature",
      "properties": {
        "description": "500K scale point location",
        "location_precision": "precise",
        "title": "DARMC location 19412",
        "link": "http://pleiades.stoa.org/places/208943587/darmc-location-19412"
      }
    }
  ]
}