{
  "type": "FeatureCollection",
  "title": "Untitled",
  "id": "208943265",
  "description": "An ancient place, cited: BAtlas 32 F3 unnamed unlabeled ((1 monument))",
  "bbox": [
    10.295732,
    36.883274,
    10.295732,
    36.883274
  ],
  "reprPoint": [
    10.295732,
    36.883274
  ],
  "features": [
    {
      "geometry": {
        "type": "Point",
        "coordinates": [
          10.295732,
          36.883274
        ]
      },
      "id": "darmc-location-15996",
      "type": "Feature",
      "properties": {
        "description": "500K scale point location",
        "location_precision": "precise",
        "title": "DARMC location 15996",
        "link": "http://pleiades.stoa.org/places/208943265/darmc-location-15996"
      }
    }
  ]
}