{
  "type": "FeatureCollection",
  "title": "Untitled",
  "id": "208942799",
  "bbox": [
    6.792439,
    35.448749,
    6.792439,
    35.448749
  ],
  "description": "An ancient place, cited: BAtlas 34 E2 unnamed feature ()",
  "features": [
    {
      "type": "Feature",
      "geometry": {
        "type": "Point",
        "coordinates": [
          6.792439,
          35.448749
        ]
      },
      "properties": {
        "description": "representative point"
      }
    },
    {
      "geometry": {
        "type": "Point",
        "coordinates": [
          6.792439,
          35.448749
        ]
      },
      "id": "darmc-location-14959",
      "type": "Feature",
      "properties": {
        "description": "500K scale point location",
        "location_precision": "precise",
        "title": "DARMC location 14959",
        "link": "http://pleiades.stoa.org/places/208942799/darmc-location-14959"
      }
    }
  ]
}