{
  "type": "FeatureCollection",
  "title": "Untitled",
  "id": "208943452",
  "bbox": [
    27.56228,
    38.39285,
    27.56228,
    38.39285
  ],
  "description": "An ancient place, cited: BAtlas 56 F5 unnamed tumulus (E Boukolion)",
  "features": [
    {
      "type": "Feature",
      "geometry": {
        "type": "Point",
        "coordinates": [
          27.56228,
          38.39285
        ]
      },
      "properties": {
        "description": "representative point"
      }
    },
    {
      "geometry": {
        "type": "Point",
        "coordinates": [
          27.56228,
          38.39285
        ]
      },
      "id": "darmc-location-33054",
      "type": "Feature",
      "properties": {
        "description": "  scale point location",
        "location_precision": "precise",
        "title": "DARMC location 33054",
        "link": "http://pleiades.stoa.org/places/208943452/darmc-location-33054"
      }
    }
  ]
}