{
  "type": "FeatureCollection",
  "title": "Untitled",
  "id": "208943331",
  "description": "An ancient place, cited: BAtlas 32 G3 unnamed unlabeled ((1 bath, 1 cemetery))",
  "bbox": [
    10.889707,
    36.611725,
    10.889707,
    36.611725
  ],
  "reprPoint": [
    10.889707,
    36.611725
  ],
  "features": [
    {
      "geometry": {
        "type": "Point",
        "coordinates": [
          10.889707,
          36.611725
        ]
      },
      "id": "darmc-location-15958",
      "type": "Feature",
      "properties": {
        "description": "500K scale point location",
        "location_precision": "precise",
        "title": "DARMC location 15958",
        "link": "http://pleiades.stoa.org/places/208943331/darmc-location-15958"
      }
    }
  ]
}