{
  "type": "FeatureCollection",
  "title": "Untitled",
  "id": "208943375",
  "description": "An ancient place, cited: BAtlas 32 G3 unnamed unlabeled ((1 bath, 1 cemetery))",
  "bbox": [
    10.837783,
    36.951619,
    10.837783,
    36.951619
  ],
  "reprPoint": [
    10.837783,
    36.951619
  ],
  "features": [
    {
      "geometry": {
        "type": "Point",
        "coordinates": [
          10.837783,
          36.951619
        ]
      },
      "id": "darmc-location-15980",
      "type": "Feature",
      "properties": {
        "description": "500K scale point location",
        "location_precision": "precise",
        "title": "DARMC location 15980",
        "link": "http://pleiades.stoa.org/places/208943375/darmc-location-15980"
      }
    }
  ]
}