{
  "type": "FeatureCollection",
  "title": "Untitled",
  "id": "208943748",
  "bbox": [
    11.14369,
    35.239678,
    11.14369,
    35.239678
  ],
  "description": "An ancient place, cited: BAtlas 33 H2 unnamed unlabeled ((4 cemeteries))",
  "features": [
    {
      "type": "Feature",
      "geometry": {
        "type": "Point",
        "coordinates": [
          11.14369,
          35.239678
        ]
      },
      "properties": {
        "description": "representative point"
      }
    },
    {
      "geometry": {
        "type": "Point",
        "coordinates": [
          11.14369,
          35.239678
        ]
      },
      "id": "darmc-location-27334",
      "type": "Feature",
      "properties": {
        "description": "500K scale point location",
        "location_precision": "precise",
        "title": "DARMC location 27334",
        "link": "http://pleiades.stoa.org/places/208943748/darmc-location-27334"
      }
    }
  ]
}