{
  "type": "FeatureCollection",
  "title": "Untitled",
  "id": "208942768",
  "description": "An ancient place, cited: BAtlas 34 E2 unnamed feature ()",
  "bbox": [
    6.254147,
    35.097488,
    6.254147,
    35.097488
  ],
  "reprPoint": [
    6.254147,
    35.097488
  ],
  "features": [
    {
      "geometry": {
        "type": "Point",
        "coordinates": [
          6.254147,
          35.097488
        ]
      },
      "id": "darmc-location-20655",
      "type": "Feature",
      "properties": {
        "description": "500K scale point location",
        "location_precision": "precise",
        "title": "DARMC location 20655",
        "link": "http://pleiades.stoa.org/places/208942768/darmc-location-20655"
      }
    }
  ]
}