{
  "type": "FeatureCollection",
  "title": "Untitled",
  "id": "208943467",
  "bbox": [
    8.249234,
    34.653542,
    8.249234,
    34.653542
  ],
  "description": "An ancient place, cited: BAtlas 33 B3 unnamed unlabeled ((1 monument))",
  "features": [
    {
      "type": "Feature",
      "geometry": {
        "type": "Point",
        "coordinates": [
          8.249234,
          34.653542
        ]
      },
      "properties": {
        "description": "representative point"
      }
    },
    {
      "geometry": {
        "type": "Point",
        "coordinates": [
          8.249234,
          34.653542
        ]
      },
      "id": "darmc-location-16189",
      "type": "Feature",
      "properties": {
        "description": "500K scale point location",
        "location_precision": "precise",
        "title": "DARMC location 16189",
        "link": "http://pleiades.stoa.org/places/208943467/darmc-location-16189"
      }
    }
  ]
}