{
  "type": "FeatureCollection",
  "title": "Untitled",
  "id": "208943272",
  "bbox": [
    10.083812,
    36.953602,
    10.083812,
    36.953602
  ],
  "description": "An ancient place, cited: BAtlas 32 F3 unnamed unlabeled ((1 monument))",
  "features": [
    {
      "type": "Feature",
      "geometry": {
        "type": "Point",
        "coordinates": [
          10.083812,
          36.953602
        ]
      },
      "properties": {
        "description": "representative point"
      }
    },
    {
      "geometry": {
        "type": "Point",
        "coordinates": [
          10.083812,
          36.953602
        ]
      },
      "id": "darmc-location-15986",
      "type": "Feature",
      "properties": {
        "description": "500K scale point location",
        "location_precision": "precise",
        "title": "DARMC location 15986",
        "link": "http://pleiades.stoa.org/places/208943272/darmc-location-15986"
      }
    }
  ]
}