{
  "type": "FeatureCollection",
  "title": "Untitled",
  "id": "208943324",
  "bbox": [
    10.972123,
    36.925959,
    10.972123,
    36.925959
  ],
  "description": "An ancient place, cited: BAtlas 32 G3 unnamed unlabeled ((1 bath, 1 cemetery))",
  "features": [
    {
      "type": "Feature",
      "geometry": {
        "type": "Point",
        "coordinates": [
          10.972123,
          36.925959
        ]
      },
      "properties": {
        "description": "representative point"
      }
    },
    {
      "geometry": {
        "type": "Point",
        "coordinates": [
          10.972123,
          36.925959
        ]
      },
      "id": "darmc-location-26825",
      "type": "Feature",
      "properties": {
        "description": "500K scale point location",
        "location_precision": "precise",
        "title": "DARMC location 26825",
        "link": "http://pleiades.stoa.org/places/208943324/darmc-location-26825"
      }
    }
  ]
}