{
  "type": "FeatureCollection",
  "title": "Untitled",
  "id": "208943738",
  "description": "An ancient place, cited: BAtlas 33 H2 unnamed unlabeled ((4 cemeteries))",
  "bbox": [
    11.023182,
    35.075852,
    11.023182,
    35.075852
  ],
  "reprPoint": [
    11.023182,
    35.075852
  ],
  "features": [
    {
      "geometry": {
        "type": "Point",
        "coordinates": [
          11.023182,
          35.075852
        ]
      },
      "id": "darmc-location-25614",
      "type": "Feature",
      "properties": {
        "description": "500K scale point location",
        "location_precision": "precise",
        "title": "DARMC location 25614",
        "link": "http://pleiades.stoa.org/places/208943738/darmc-location-25614"
      }
    }
  ]
}