{
  "type": "FeatureCollection",
  "title": "Untitled",
  "id": "208943448",
  "description": "An ancient place, cited: BAtlas 33 C3 unnamed unlabeled ((7 monuments))",
  "bbox": [
    8.598627,
    34.822656,
    8.598627,
    34.822656
  ],
  "reprPoint": [
    8.598627,
    34.822656
  ],
  "features": [
    {
      "geometry": {
        "type": "Point",
        "coordinates": [
          8.598627,
          34.822656
        ]
      },
      "id": "darmc-location-27166",
      "type": "Feature",
      "properties": {
        "description": "500K scale point location",
        "location_precision": "precise",
        "title": "DARMC location 27166",
        "link": "http://pleiades.stoa.org/places/208943448/darmc-location-27166"
      }
    }
  ]
}