{
  "type": "FeatureCollection",
  "title": "Untitled",
  "id": "208942356",
  "bbox": [
    8.846331,
    36.686584,
    8.846331,
    36.686584
  ],
  "description": "An ancient place, cited: BAtlas 32 C3 unnamed unlabeled ((2 monuments))",
  "features": [
    {
      "type": "Feature",
      "geometry": {
        "type": "Point",
        "coordinates": [
          8.846331,
          36.686584
        ]
      },
      "properties": {
        "description": "representative point"
      }
    },
    {
      "geometry": {
        "type": "Point",
        "coordinates": [
          8.846331,
          36.686584
        ]
      },
      "id": "darmc-location-15819",
      "type": "Feature",
      "properties": {
        "description": "500K scale point location",
        "location_precision": "precise",
        "title": "DARMC location 15819",
        "link": "http://pleiades.stoa.org/places/208942356/darmc-location-15819"
      }
    }
  ]
}