{
  "type": "FeatureCollection",
  "title": "Untitled",
  "id": "208943282",
  "bbox": [
    10.054676,
    36.607655,
    10.054676,
    36.607655
  ],
  "description": "An ancient place, cited: BAtlas 32 F3 unnamed unlabeled ((1 monument))",
  "features": [
    {
      "type": "Feature",
      "geometry": {
        "type": "Point",
        "coordinates": [
          10.054676,
          36.607655
        ]
      },
      "properties": {
        "description": "representative point"
      }
    },
    {
      "geometry": {
        "type": "Point",
        "coordinates": [
          10.054676,
          36.607655
        ]
      },
      "id": "darmc-location-25745",
      "type": "Feature",
      "properties": {
        "description": "500K scale point location",
        "location_precision": "precise",
        "title": "DARMC location 25745",
        "link": "http://pleiades.stoa.org/places/208943282/darmc-location-25745"
      }
    }
  ]
}