{
  "type": "FeatureCollection",
  "title": "Untitled",
  "id": "208942516",
  "description": "An ancient place, cited: BAtlas 32 C4 unlabeled (settlements)",
  "bbox": [
    8.575979,
    36.193706,
    8.575979,
    36.193706
  ],
  "reprPoint": [
    8.575979,
    36.193706
  ],
  "features": [
    {
      "geometry": {
        "type": "Point",
        "coordinates": [
          8.575979,
          36.193706
        ]
      },
      "id": "darmc-location-15695",
      "type": "Feature",
      "properties": {
        "description": "500K scale point location",
        "location_precision": "precise",
        "title": "DARMC location 15695",
        "link": "http://pleiades.stoa.org/places/208942516/darmc-location-15695"
      }
    }
  ]
}