{
  "type": "FeatureCollection",
  "title": "Untitled",
  "id": "208943193",
  "description": "An ancient place, cited: BAtlas 34 D2 unnamed feature ()",
  "bbox": [
    5.408093,
    35.861007,
    5.408093,
    35.861007
  ],
  "reprPoint": [
    5.408093,
    35.861007
  ],
  "features": [
    {
      "geometry": {
        "type": "Point",
        "coordinates": [
          5.408093,
          35.861007
        ]
      },
      "id": "darmc-location-20705",
      "type": "Feature",
      "properties": {
        "description": "500K scale point location",
        "location_precision": "precise",
        "title": "DARMC location 20705",
        "link": "http://pleiades.stoa.org/places/208943193/darmc-location-20705"
      }
    }
  ]
}