{
  "type": "FeatureCollection",
  "title": "Untitled",
  "id": "208942217",
  "description": "An ancient place, cited: BAtlas 32 E4 unnamed unlabeled ((15 monuments, 2 walls))",
  "bbox": [
    9.909922,
    36.397935,
    9.909922,
    36.397935
  ],
  "reprPoint": [
    9.909922,
    36.397935
  ],
  "features": [
    {
      "geometry": {
        "type": "Point",
        "coordinates": [
          9.909922,
          36.397935
        ]
      },
      "id": "darmc-location-25748",
      "type": "Feature",
      "properties": {
        "description": "500K scale point location",
        "location_precision": "precise",
        "title": "DARMC location 25748",
        "link": "http://pleiades.stoa.org/places/208942217/darmc-location-25748"
      }
    }
  ]
}