{
  "type": "FeatureCollection",
  "title": "Untitled",
  "id": "208943505",
  "description": "An ancient place, cited: BAtlas 33 D2 unnamed unlabeled ((5 monuments))",
  "bbox": [
    9.396313,
    35.392806,
    9.396313,
    35.392806
  ],
  "reprPoint": [
    9.396313,
    35.392806
  ],
  "features": [
    {
      "geometry": {
        "type": "Point",
        "coordinates": [
          9.396313,
          35.392806
        ]
      },
      "id": "darmc-location-20820",
      "type": "Feature",
      "properties": {
        "description": "500K scale point location",
        "location_precision": "precise",
        "title": "DARMC location 20820",
        "link": "http://pleiades.stoa.org/places/208943505/darmc-location-20820"
      }
    }
  ]
}