{
  "type": "FeatureCollection",
  "title": "Untitled",
  "id": "208942996",
  "description": "An ancient place, cited: BAtlas 33 G1 unnamed unlabeled ((1 cemetery))",
  "bbox": [
    10.536653,
    35.607329,
    10.536653,
    35.607329
  ],
  "reprPoint": [
    10.536653,
    35.607329
  ],
  "features": [
    {
      "geometry": {
        "type": "Point",
        "coordinates": [
          10.536653,
          35.607329
        ]
      },
      "id": "darmc-location-20371",
      "type": "Feature",
      "properties": {
        "description": "500K scale point location",
        "location_precision": "precise",
        "title": "DARMC location 20371",
        "link": "http://pleiades.stoa.org/places/208942996/darmc-location-20371"
      }
    }
  ]
}