{
  "type": "FeatureCollection",
  "title": "Untitled",
  "id": "208942907",
  "bbox": [
    7.955623,
    36.668077,
    7.955623,
    36.668077
  ],
  "description": "An ancient place, cited: BAtlas 31 H3 unnamed unlabeled (settlements)",
  "features": [
    {
      "type": "Feature",
      "geometry": {
        "type": "Point",
        "coordinates": [
          7.955623,
          36.668077
        ]
      },
      "properties": {
        "description": "representative point"
      }
    },
    {
      "geometry": {
        "type": "Point",
        "coordinates": [
          7.955623,
          36.668077
        ]
      },
      "id": "darmc-location-15799",
      "type": "Feature",
      "properties": {
        "description": "500K scale point location",
        "location_precision": "precise",
        "title": "DARMC location 15799",
        "link": "http://pleiades.stoa.org/places/208942907/darmc-location-15799"
      }
    }
  ]
}