{
  "type": "FeatureCollection",
  "title": "Untitled",
  "id": "208943124",
  "description": "An ancient place, cited: BAtlas 33 F1 unnamed unlabeled ((3 cemeteries, 1 monument, 1 wall))",
  "bbox": [
    10.257615,
    35.943811,
    10.257615,
    35.943811
  ],
  "reprPoint": [
    10.257615,
    35.943811
  ],
  "features": [
    {
      "geometry": {
        "type": "Point",
        "coordinates": [
          10.257615,
          35.943811
        ]
      },
      "id": "darmc-location-33299",
      "type": "Feature",
      "properties": {
        "description": "scale point location",
        "location_precision": "precise",
        "title": "DARMC location 33299",
        "link": "http://pleiades.stoa.org/places/208943124/darmc-location-33299"
      }
    }
  ]
}