{
  "type": "FeatureCollection",
  "title": "Untitled",
  "id": "208942275",
  "bbox": [
    8.025967,
    36.711577,
    8.025967,
    36.711577
  ],
  "description": "An ancient place, cited: BAtlas 32 B3 unnamed unlabeled ((1 monument, 1 cemetery))",
  "features": [
    {
      "type": "Feature",
      "geometry": {
        "type": "Point",
        "coordinates": [
          8.025967,
          36.711577
        ]
      },
      "properties": {
        "description": "representative point"
      }
    },
    {
      "geometry": {
        "type": "Point",
        "coordinates": [
          8.025967,
          36.711577
        ]
      },
      "id": "darmc-location-15842",
      "type": "Feature",
      "properties": {
        "description": "500K scale point location",
        "location_precision": "precise",
        "title": "DARMC location 15842",
        "link": "http://pleiades.stoa.org/places/208942275/darmc-location-15842"
      }
    }
  ]
}