{
  "type": "FeatureCollection",
  "title": "Untitled",
  "id": "208942193",
  "description": "An ancient place, cited: BAtlas 32 E3 unnamed unlabeled ((15 monuments))",
  "bbox": [
    9.63395,
    36.960246,
    9.63395,
    36.960246
  ],
  "reprPoint": [
    9.63395,
    36.960246
  ],
  "features": [
    {
      "geometry": {
        "type": "Point",
        "coordinates": [
          9.63395,
          36.960246
        ]
      },
      "id": "darmc-location-26753",
      "type": "Feature",
      "properties": {
        "description": "500K scale point location",
        "location_precision": "precise",
        "title": "DARMC location 26753",
        "link": "http://pleiades.stoa.org/places/208942193/darmc-location-26753"
      }
    }
  ]
}