{
  "type": "FeatureCollection",
  "title": "Untitled",
  "id": "208942281",
  "description": "An ancient place, cited: BAtlas 32 B3 unnamed unlabeled ((1 monument, 1 cemetery))",
  "bbox": [
    8.372324,
    36.739777,
    8.372324,
    36.739777
  ],
  "reprPoint": [
    8.372324,
    36.739777
  ],
  "features": [
    {
      "geometry": {
        "type": "Point",
        "coordinates": [
          8.372324,
          36.739777
        ]
      },
      "id": "darmc-location-15832",
      "type": "Feature",
      "properties": {
        "description": "500K scale point location",
        "location_precision": "precise",
        "title": "DARMC location 15832",
        "link": "http://pleiades.stoa.org/places/208942281/darmc-location-15832"
      }
    }
  ]
}