{
  "type": "FeatureCollection",
  "title": "Untitled",
  "id": "208943189",
  "bbox": [
    5.456136,
    35.661889,
    5.456136,
    35.661889
  ],
  "description": "An ancient place, cited: BAtlas 34 D2 unnamed feature ()",
  "features": [
    {
      "type": "Feature",
      "geometry": {
        "type": "Point",
        "coordinates": [
          5.456136,
          35.661889
        ]
      },
      "properties": {
        "description": "representative point"
      }
    },
    {
      "geometry": {
        "type": "Point",
        "coordinates": [
          5.456136,
          35.661889
        ]
      },
      "id": "darmc-location-33321",
      "type": "Feature",
      "properties": {
        "description": "  scale point location",
        "location_precision": "precise",
        "title": "DARMC location 33321",
        "link": "http://pleiades.stoa.org/places/208943189/darmc-location-33321"
      }
    }
  ]
}