{
  "type": "FeatureCollection",
  "title": "Untitled",
  "id": "208943479",
  "description": "An ancient place, cited: BAtlas 30 E4/F4 no. 7 (Tumuli)",
  "bbox": [
    2.789122,
    36.07535,
    2.789122,
    36.07535
  ],
  "reprPoint": [
    2.789122,
    36.07535
  ],
  "features": [
    {
      "geometry": {
        "type": "Point",
        "coordinates": [
          2.789122,
          36.07535
        ]
      },
      "id": "darmc-location-33242",
      "type": "Feature",
      "properties": {
        "description": "scale point location",
        "location_precision": "precise",
        "title": "DARMC location 33242",
        "link": "http://pleiades.stoa.org/places/208943479/darmc-location-33242"
      }
    }
  ]
}