{
  "type": "FeatureCollection",
  "title": "Untitled",
  "id": "208942324",
  "description": "An ancient place, cited: BAtlas 32 C3 unnamed unlabeled ((2 monuments))",
  "bbox": [
    8.79858,
    36.937258,
    8.79858,
    36.937258
  ],
  "reprPoint": [
    8.79858,
    36.937258
  ],
  "features": [
    {
      "geometry": {
        "type": "Point",
        "coordinates": [
          8.79858,
          36.937258
        ]
      },
      "id": "darmc-location-26621",
      "type": "Feature",
      "properties": {
        "description": "500K scale point location",
        "location_precision": "precise",
        "title": "DARMC location 26621",
        "link": "http://pleiades.stoa.org/places/208942324/darmc-location-26621"
      }
    }
  ]
}