{
  "type": "FeatureCollection",
  "title": "Untitled",
  "id": "208943292",
  "description": "An ancient place, cited: BAtlas 34 C2 unnamed feature ()",
  "bbox": [
    4.942106,
    35.703925,
    4.942106,
    35.703925
  ],
  "reprPoint": [
    4.942106,
    35.703925
  ],
  "features": [
    {
      "geometry": {
        "type": "Point",
        "coordinates": [
          4.942106,
          35.703925
        ]
      },
      "id": "darmc-location-19386",
      "type": "Feature",
      "properties": {
        "description": "500K scale point location",
        "location_precision": "precise",
        "title": "DARMC location 19386",
        "link": "http://pleiades.stoa.org/places/208943292/darmc-location-19386"
      }
    }
  ]
}