{
  "type": "FeatureCollection",
  "title": "Untitled",
  "id": "208943632",
  "description": "An ancient place, cited: BAtlas 33 C4-D4 unnamed unlabeled ((8 stretches of wall))",
  "bbox": [
    9.139149,
    34.157845,
    9.139149,
    34.157845
  ],
  "reprPoint": [
    9.139149,
    34.157845
  ],
  "features": [
    {
      "geometry": {
        "type": "Point",
        "coordinates": [
          9.139149,
          34.157845
        ]
      },
      "id": "darmc-location-16198",
      "type": "Feature",
      "properties": {
        "description": "500K scale point location",
        "location_precision": "precise",
        "title": "DARMC location 16198",
        "link": "http://pleiades.stoa.org/places/208943632/darmc-location-16198"
      }
    }
  ]
}