{
  "type": "FeatureCollection",
  "title": "Untitled",
  "id": "208943151",
  "bbox": [
    5.092193,
    35.557722,
    5.092193,
    35.557722
  ],
  "description": "An ancient place, cited: BAtlas 34 D2 unnamed feature ()",
  "features": [
    {
      "type": "Feature",
      "geometry": {
        "type": "Point",
        "coordinates": [
          5.092193,
          35.557722
        ]
      },
      "properties": {
        "description": "representative point"
      }
    },
    {
      "geometry": {
        "type": "Point",
        "coordinates": [
          5.092193,
          35.557722
        ]
      },
      "id": "darmc-location-19396",
      "type": "Feature",
      "properties": {
        "description": "500K scale point location",
        "location_precision": "precise",
        "title": "DARMC location 19396",
        "link": "http://pleiades.stoa.org/places/208943151/darmc-location-19396"
      }
    }
  ]
}