{
  "type": "FeatureCollection",
  "title": "Untitled",
  "id": "208942810",
  "description": "An ancient place, cited: BAtlas 34 E2 unnamed feature ()",
  "bbox": [
    6.700542,
    35.204811,
    6.700542,
    35.204811
  ],
  "reprPoint": [
    6.700542,
    35.204811
  ],
  "features": [
    {
      "geometry": {
        "type": "Point",
        "coordinates": [
          6.700542,
          35.204811
        ]
      },
      "id": "darmc-location-16177",
      "type": "Feature",
      "properties": {
        "description": "500K scale point location",
        "location_precision": "precise",
        "title": "DARMC location 16177",
        "link": "http://pleiades.stoa.org/places/208942810/darmc-location-16177"
      }
    }
  ]
}