{
  "type": "FeatureCollection",
  "title": "Untitled",
  "id": "208942966",
  "description": "An ancient place, cited: BAtlas 34 B2 unnamed feature ()",
  "bbox": [
    3.245096,
    35.928594,
    3.245096,
    35.928594
  ],
  "reprPoint": [
    3.245096,
    35.928594
  ],
  "features": [
    {
      "geometry": {
        "type": "Point",
        "coordinates": [
          3.245096,
          35.928594
        ]
      },
      "id": "darmc-location-16139",
      "type": "Feature",
      "properties": {
        "description": "500K scale point location",
        "location_precision": "precise",
        "title": "DARMC location 16139",
        "link": "http://pleiades.stoa.org/places/208942966/darmc-location-16139"
      }
    }
  ]
}