{
  "type": "FeatureCollection",
  "title": "Untitled",
  "id": "208942477",
  "bbox": [
    9.273721,
    37.145748,
    9.273721,
    37.145748
  ],
  "description": "An ancient place, cited: BAtlas 32 D2 unnamed unlabeled ((5 monuments))",
  "features": [
    {
      "type": "Feature",
      "geometry": {
        "type": "Point",
        "coordinates": [
          9.273721,
          37.145748
        ]
      },
      "properties": {
        "description": "representative point"
      }
    },
    {
      "geometry": {
        "type": "Point",
        "coordinates": [
          9.273721,
          37.145748
        ]
      },
      "id": "darmc-location-25716",
      "type": "Feature",
      "properties": {
        "description": "500K scale point location",
        "location_precision": "precise",
        "title": "DARMC location 25716",
        "link": "http://pleiades.stoa.org/places/208942477/darmc-location-25716"
      }
    }
  ]
}