{
  "type": "FeatureCollection",
  "title": "Untitled",
  "id": "208943257",
  "description": "An ancient place, cited: BAtlas 32 F3 unnamed unlabeled ((1 monument))",
  "bbox": [
    10.277687,
    36.537164,
    10.277687,
    36.537164
  ],
  "reprPoint": [
    10.277687,
    36.537164
  ],
  "features": [
    {
      "geometry": {
        "type": "Point",
        "coordinates": [
          10.277687,
          36.537164
        ]
      },
      "id": "darmc-location-16007",
      "type": "Feature",
      "properties": {
        "description": "500K scale point location",
        "location_precision": "precise",
        "title": "DARMC location 16007",
        "link": "http://pleiades.stoa.org/places/208943257/darmc-location-16007"
      }
    }
  ]
}