{
  "type": "FeatureCollection",
  "title": "Untitled",
  "id": "208942747",
  "bbox": [
    6.022584,
    34.789218,
    6.022584,
    34.789218
  ],
  "description": "An ancient place, cited: BAtlas 34 E3 unnamed feature ()",
  "features": [
    {
      "type": "Feature",
      "geometry": {
        "type": "Point",
        "coordinates": [
          6.022584,
          34.789218
        ]
      },
      "properties": {
        "description": "representative point"
      }
    },
    {
      "geometry": {
        "type": "Point",
        "coordinates": [
          6.022584,
          34.789218
        ]
      },
      "id": "darmc-location-33362",
      "type": "Feature",
      "properties": {
        "description": "representative point location digitized from the Barrington Atlas of the Greek and Roman World by the Digital Atlas of Roman and Medieval Civilizations project at Harvard University.",
        "location_precision": "precise",
        "title": "DARMC location 33362",
        "link": "http://pleiades.stoa.org/places/208942747/darmc-location-33362"
      }
    }
  ]
}