{
  "type": "FeatureCollection",
  "title": "Untitled",
  "id": "208943216",
  "description": "An ancient place, cited: BAtlas 32 F4 unnamed unlabeled ((6 monuments))",
  "bbox": [
    10.09945,
    36.429627,
    10.09945,
    36.429627
  ],
  "reprPoint": [
    10.09945,
    36.429627
  ],
  "features": [
    {
      "geometry": {
        "type": "Point",
        "coordinates": [
          10.09945,
          36.429627
        ]
      },
      "id": "darmc-location-26810",
      "type": "Feature",
      "properties": {
        "description": "500K scale point location",
        "location_precision": "precise",
        "title": "DARMC location 26810",
        "link": "http://pleiades.stoa.org/places/208943216/darmc-location-26810"
      }
    }
  ]
}