{
  "type": "FeatureCollection",
  "title": "Untitled",
  "id": "208943495",
  "bbox": [
    9.269781,
    35.179754,
    9.269781,
    35.179754
  ],
  "description": "An ancient place, cited: BAtlas 33 D2 unnamed unlabeled ((5 monuments))",
  "features": [
    {
      "type": "Feature",
      "geometry": {
        "type": "Point",
        "coordinates": [
          9.269781,
          35.179754
        ]
      },
      "properties": {
        "description": "representative point"
      }
    },
    {
      "geometry": {
        "type": "Point",
        "coordinates": [
          9.269781,
          35.179754
        ]
      },
      "id": "darmc-location-27261",
      "type": "Feature",
      "properties": {
        "description": "500K scale point location",
        "location_precision": "precise",
        "title": "DARMC location 27261",
        "link": "http://pleiades.stoa.org/places/208943495/darmc-location-27261"
      }
    }
  ]
}