{
  "type": "FeatureCollection",
  "title": "Untitled",
  "id": "208943616",
  "description": "An ancient place, cited: BAtlas 31 D4 unnamed unlabeled (settlements)",
  "bbox": [
    5.861835,
    36.490489,
    5.861835,
    36.490489
  ],
  "reprPoint": [
    5.861835,
    36.490489
  ],
  "features": [
    {
      "geometry": {
        "type": "Point",
        "coordinates": [
          5.861835,
          36.490489
        ]
      },
      "id": "darmc-location-20921",
      "type": "Feature",
      "properties": {
        "description": "500K scale point location",
        "location_precision": "precise",
        "title": "DARMC location 20921",
        "link": "http://pleiades.stoa.org/places/208943616/darmc-location-20921"
      }
    }
  ]
}