{
  "type": "FeatureCollection",
  "title": "Untitled",
  "id": "208943623",
  "description": "An ancient place, cited: BAtlas 31 D4 unnamed unlabeled (settlements)",
  "bbox": [
    5.783938,
    36.265138,
    5.783938,
    36.265138
  ],
  "reprPoint": [
    5.783938,
    36.265138
  ],
  "features": [
    {
      "geometry": {
        "type": "Point",
        "coordinates": [
          5.783938,
          36.265138
        ]
      },
      "id": "darmc-location-20464",
      "type": "Feature",
      "properties": {
        "description": "500K scale point location",
        "location_precision": "precise",
        "title": "DARMC location 20464",
        "link": "http://pleiades.stoa.org/places/208943623/darmc-location-20464"
      }
    }
  ]
}