{
  "type": "FeatureCollection",
  "title": "Untitled",
  "id": "208942469",
  "bbox": [
    9.332441,
    37.055954,
    9.332441,
    37.055954
  ],
  "description": "An ancient place, cited: BAtlas 32 D2 unnamed unlabeled ((5 monuments))",
  "features": [
    {
      "type": "Feature",
      "geometry": {
        "type": "Point",
        "coordinates": [
          9.332441,
          37.055954
        ]
      },
      "properties": {
        "description": "representative point"
      }
    },
    {
      "geometry": {
        "type": "Point",
        "coordinates": [
          9.332441,
          37.055954
        ]
      },
      "id": "darmc-location-15850",
      "type": "Feature",
      "properties": {
        "description": "500K scale point location",
        "location_precision": "precise",
        "title": "DARMC location 15850",
        "link": "http://pleiades.stoa.org/places/208942469/darmc-location-15850"
      }
    }
  ]
}