{
  "type": "FeatureCollection",
  "title": "Untitled",
  "id": "208943705",
  "description": "An ancient place, cited: BAtlas 33 F3 unnamed unlabeled ((6 monuments, 1 wall, 1 aqueduct))",
  "bbox": [
    10.127074,
    34.667613,
    10.127074,
    34.667613
  ],
  "reprPoint": [
    10.127074,
    34.667613
  ],
  "features": [
    {
      "geometry": {
        "type": "Point",
        "coordinates": [
          10.127074,
          34.667613
        ]
      },
      "id": "darmc-location-25826",
      "type": "Feature",
      "properties": {
        "description": "500K scale point location",
        "location_precision": "precise",
        "title": "DARMC location 25826",
        "link": "http://pleiades.stoa.org/places/208943705/darmc-location-25826"
      }
    }
  ]
}