{
  "type": "FeatureCollection",
  "title": "Untitled",
  "id": "208942409",
  "description": "An ancient place, cited: BAtlas 32 D4 unnamed unlabeled ((7 monuments, 1 cemetery, 2 walls))",
  "bbox": [
    9.209387,
    36.076708,
    9.209387,
    36.076708
  ],
  "reprPoint": [
    9.209387,
    36.076708
  ],
  "features": [
    {
      "geometry": {
        "type": "Point",
        "coordinates": [
          9.209387,
          36.076708
        ]
      },
      "id": "darmc-location-15570",
      "type": "Feature",
      "properties": {
        "description": "500K scale point location",
        "location_precision": "precise",
        "title": "DARMC location 15570",
        "link": "http://pleiades.stoa.org/places/208942409/darmc-location-15570"
      }
    }
  ]
}