{
  "type": "FeatureCollection",
  "title": "Untitled",
  "id": "208943184",
  "description": "An ancient place, cited: BAtlas 34 D2 unnamed feature ()",
  "bbox": [
    5.908951,
    35.353734,
    5.908951,
    35.353734
  ],
  "reprPoint": [
    5.908951,
    35.353734
  ],
  "features": [
    {
      "geometry": {
        "type": "Point",
        "coordinates": [
          5.908951,
          35.353734
        ]
      },
      "id": "darmc-location-19508",
      "type": "Feature",
      "properties": {
        "description": "500K scale point location",
        "location_precision": "precise",
        "title": "DARMC location 19508",
        "link": "http://pleiades.stoa.org/places/208943184/darmc-location-19508"
      }
    }
  ]
}