{
  "type": "FeatureCollection",
  "title": "Untitled",
  "id": "208943613",
  "bbox": [
    5.731689,
    36.049332,
    5.731689,
    36.049332
  ],
  "description": "An ancient place, cited: BAtlas 31 D4 unnamed unlabeled (settlements)",
  "features": [
    {
      "type": "Feature",
      "geometry": {
        "type": "Point",
        "coordinates": [
          5.731689,
          36.049332
        ]
      },
      "properties": {
        "description": "representative point"
      }
    },
    {
      "geometry": {
        "type": "Point",
        "coordinates": [
          5.731689,
          36.049332
        ]
      },
      "id": "darmc-location-20908",
      "type": "Feature",
      "properties": {
        "description": "500K scale point location",
        "location_precision": "precise",
        "title": "DARMC location 20908",
        "link": "http://pleiades.stoa.org/places/208943613/darmc-location-20908"
      }
    }
  ]
}