{
  "type": "FeatureCollection",
  "title": "Untitled",
  "id": "208942897",
  "bbox": [
    7.600649,
    36.116675,
    7.600649,
    36.116675
  ],
  "description": "An ancient place, cited: BAtlas 31 H4 unnamed unlabeled (settlements)",
  "features": [
    {
      "type": "Feature",
      "geometry": {
        "type": "Point",
        "coordinates": [
          7.600649,
          36.116675
        ]
      },
      "properties": {
        "description": "representative point"
      }
    },
    {
      "geometry": {
        "type": "Point",
        "coordinates": [
          7.600649,
          36.116675
        ]
      },
      "id": "darmc-location-21047",
      "type": "Feature",
      "properties": {
        "description": "500K scale point location",
        "location_precision": "precise",
        "title": "DARMC location 21047",
        "link": "http://pleiades.stoa.org/places/208942897/darmc-location-21047"
      }
    }
  ]
}