{
  "type": "FeatureCollection",
  "title": "Untitled",
  "id": "208943365",
  "description": "An ancient place, cited: BAtlas 32 G3 unnamed unlabeled ((1 bath, 1 cemetery))",
  "bbox": [
    10.947559,
    36.997363,
    10.947559,
    36.997363
  ],
  "reprPoint": [
    10.947559,
    36.997363
  ],
  "features": [
    {
      "geometry": {
        "type": "Point",
        "coordinates": [
          10.947559,
          36.997363
        ]
      },
      "id": "darmc-location-15964",
      "type": "Feature",
      "properties": {
        "description": "500K scale point location",
        "location_precision": "precise",
        "title": "DARMC location 15964",
        "link": "http://pleiades.stoa.org/places/208943365/darmc-location-15964"
      }
    }
  ]
}