{
  "type": "FeatureCollection",
  "title": "Untitled",
  "id": "208942170",
  "description": "An ancient place, cited: BAtlas 32 E3 unnamed unlabeled ((15 monuments))",
  "bbox": [
    9.967465,
    36.585175,
    9.967465,
    36.585175
  ],
  "reprPoint": [
    9.967465,
    36.585175
  ],
  "features": [
    {
      "geometry": {
        "type": "Point",
        "coordinates": [
          9.967465,
          36.585175
        ]
      },
      "id": "darmc-location-25739",
      "type": "Feature",
      "properties": {
        "description": "500K scale point location",
        "location_precision": "precise",
        "title": "DARMC location 25739",
        "link": "http://pleiades.stoa.org/places/208942170/darmc-location-25739"
      }
    }
  ]
}