{
  "type": "FeatureCollection",
  "title": "Untitled",
  "id": "208943416",
  "description": "An ancient place, cited: BAtlas 33 C3 unnamed unlabeled ((7 monuments))",
  "bbox": [
    8.883709,
    34.971524,
    8.883709,
    34.971524
  ],
  "reprPoint": [
    8.883709,
    34.971524
  ],
  "features": [
    {
      "geometry": {
        "type": "Point",
        "coordinates": [
          8.883709,
          34.971524
        ]
      },
      "id": "darmc-location-27212",
      "type": "Feature",
      "properties": {
        "description": "500K scale point location",
        "location_precision": "precise",
        "title": "DARMC location 27212",
        "link": "http://pleiades.stoa.org/places/208943416/darmc-location-27212"
      }
    }
  ]
}