{
  "type": "FeatureCollection",
  "title": "Untitled",
  "id": "208942549",
  "bbox": [
    7.969428,
    35.202827,
    7.969428,
    35.202827
  ],
  "description": "An ancient place, cited: BAtlas 34 F2 unnamed feature ()",
  "features": [
    {
      "type": "Feature",
      "geometry": {
        "type": "Point",
        "coordinates": [
          7.969428,
          35.202827
        ]
      },
      "properties": {
        "description": "representative point"
      }
    },
    {
      "geometry": {
        "type": "Point",
        "coordinates": [
          7.969428,
          35.202827
        ]
      },
      "id": "darmc-location-27136",
      "type": "Feature",
      "properties": {
        "description": "500K scale point location",
        "location_precision": "precise",
        "title": "DARMC location 27136",
        "link": "http://pleiades.stoa.org/places/208942549/darmc-location-27136"
      }
    }
  ]
}