{
  "type": "FeatureCollection",
  "title": "Untitled",
  "id": "208942623",
  "bbox": [
    7.063229,
    35.108405,
    7.063229,
    35.108405
  ],
  "description": "An ancient place, cited: BAtlas 34 F2 unnamed feature ()",
  "features": [
    {
      "type": "Feature",
      "geometry": {
        "type": "Point",
        "coordinates": [
          7.063229,
          35.108405
        ]
      },
      "properties": {
        "description": "representative point"
      }
    },
    {
      "geometry": {
        "type": "Point",
        "coordinates": [
          7.063229,
          35.108405
        ]
      },
      "id": "darmc-location-20638",
      "type": "Feature",
      "properties": {
        "description": "500K scale point location",
        "location_precision": "precise",
        "title": "DARMC location 20638",
        "link": "http://pleiades.stoa.org/places/208942623/darmc-location-20638"
      }
    }
  ]
}