{
  "type": "FeatureCollection",
  "title": "Untitled",
  "id": "208943020",
  "description": "An ancient place, cited: BAtlas 33 G2 unnamed unlabeled ((3 monuments, 1 bath))",
  "bbox": [
    10.806016,
    35.283707,
    10.806016,
    35.283707
  ],
  "reprPoint": [
    10.806016,
    35.283707
  ],
  "features": [
    {
      "geometry": {
        "type": "Point",
        "coordinates": [
          10.806016,
          35.283707
        ]
      },
      "id": "darmc-location-33293",
      "type": "Feature",
      "properties": {
        "description": "scale point location",
        "location_precision": "precise",
        "title": "DARMC location 33293",
        "link": "http://pleiades.stoa.org/places/208943020/darmc-location-33293"
      }
    }
  ]
}