{
  "type": "FeatureCollection",
  "title": "Untitled",
  "id": "208942728",
  "bbox": [
    5.152824,
    34.567147,
    5.152824,
    34.567147
  ],
  "description": "An ancient place, cited: BAtlas 34 D3 unnamed feature ()",
  "features": [
    {
      "type": "Feature",
      "geometry": {
        "type": "Point",
        "coordinates": [
          5.152824,
          34.567147
        ]
      },
      "properties": {
        "description": "representative point"
      }
    },
    {
      "geometry": {
        "type": "Point",
        "coordinates": [
          5.152824,
          34.567147
        ]
      },
      "id": "darmc-location-16159",
      "type": "Feature",
      "properties": {
        "description": "500K scale point location",
        "location_precision": "precise",
        "title": "DARMC location 16159",
        "link": "http://pleiades.stoa.org/places/208942728/darmc-location-16159"
      }
    }
  ]
}