{
  "type": "FeatureCollection",
  "title": "Untitled",
  "id": "208943366",
  "bbox": [
    10.961015,
    36.997457,
    10.961015,
    36.997457
  ],
  "description": "An ancient place, cited: BAtlas 32 G3 unnamed unlabeled ((1 bath, 1 cemetery))",
  "features": [
    {
      "type": "Feature",
      "geometry": {
        "type": "Point",
        "coordinates": [
          10.961015,
          36.997457
        ]
      },
      "properties": {
        "description": "representative point"
      }
    },
    {
      "geometry": {
        "type": "Point",
        "coordinates": [
          10.961015,
          36.997457
        ]
      },
      "id": "darmc-location-15965",
      "type": "Feature",
      "properties": {
        "description": "500K scale point location",
        "location_precision": "precise",
        "title": "DARMC location 15965",
        "link": "http://pleiades.stoa.org/places/208943366/darmc-location-15965"
      }
    }
  ]
}