{
  "type": "FeatureCollection",
  "title": "Untitled",
  "id": "208942635",
  "description": "An ancient place, cited: BAtlas 34 F2 unnamed feature ()",
  "bbox": [
    7.142649,
    35.72455,
    7.142649,
    35.72455
  ],
  "reprPoint": [
    7.142649,
    35.72455
  ],
  "features": [
    {
      "geometry": {
        "type": "Point",
        "coordinates": [
          7.142649,
          35.72455
        ]
      },
      "id": "darmc-location-19474",
      "type": "Feature",
      "properties": {
        "description": "500K scale point location",
        "location_precision": "precise",
        "title": "DARMC location 19474",
        "link": "http://pleiades.stoa.org/places/208942635/darmc-location-19474"
      }
    }
  ]
}