{
  "type": "FeatureCollection",
  "title": "Untitled",
  "id": "208943072",
  "description": "An ancient place, cited: BAtlas 33 D3 unnamed unlabeled ((1 aqueduct))",
  "bbox": [
    9.096914,
    34.618579,
    9.096914,
    34.618579
  ],
  "reprPoint": [
    9.096914,
    34.618579
  ],
  "features": [
    {
      "geometry": {
        "type": "Point",
        "coordinates": [
          9.096914,
          34.618579
        ]
      },
      "id": "darmc-location-20800",
      "type": "Feature",
      "properties": {
        "description": "500K scale point location",
        "location_precision": "precise",
        "title": "DARMC location 20800",
        "link": "http://pleiades.stoa.org/places/208943072/darmc-location-20800"
      }
    }
  ]
}