{
  "type": "FeatureCollection",
  "title": "Untitled",
  "id": "208942263",
  "description": "An ancient place, cited: BAtlas 32 E4 unnamed unlabeled ((15 monuments, 2 walls))",
  "bbox": [
    9.705196,
    36.058409,
    9.705196,
    36.058409
  ],
  "reprPoint": [
    9.705196,
    36.058409
  ],
  "features": [
    {
      "geometry": {
        "type": "Point",
        "coordinates": [
          9.705196,
          36.058409
        ]
      },
      "id": "darmc-location-16041",
      "type": "Feature",
      "properties": {
        "description": "500K scale point location",
        "location_precision": "precise",
        "title": "DARMC location 16041",
        "link": "http://pleiades.stoa.org/places/208942263/darmc-location-16041"
      }
    }
  ]
}