{
  "type": "FeatureCollection",
  "title": "Untitled",
  "id": "208943153",
  "description": "An ancient place, cited: BAtlas 34 D2 unnamed feature ()",
  "bbox": [
    5.307486,
    35.462539,
    5.307486,
    35.462539
  ],
  "reprPoint": [
    5.307486,
    35.462539
  ],
  "features": [
    {
      "geometry": {
        "type": "Point",
        "coordinates": [
          5.307486,
          35.462539
        ]
      },
      "id": "darmc-location-19406",
      "type": "Feature",
      "properties": {
        "description": "500K scale point location",
        "location_precision": "precise",
        "title": "DARMC location 19406",
        "link": "http://pleiades.stoa.org/places/208943153/darmc-location-19406"
      }
    }
  ]
}