{
  "type": "FeatureCollection",
  "title": "Untitled",
  "id": "208942953",
  "description": "An ancient place, cited: BAtlas 31 F4 unnamed unlabeled (settlements)",
  "bbox": [
    6.887063,
    36.003769,
    6.887063,
    36.003769
  ],
  "reprPoint": [
    6.887063,
    36.003769
  ],
  "features": [
    {
      "geometry": {
        "type": "Point",
        "coordinates": [
          6.887063,
          36.003769
        ]
      },
      "id": "darmc-location-19435",
      "type": "Feature",
      "properties": {
        "description": "500K scale point location",
        "location_precision": "precise",
        "title": "DARMC location 19435",
        "link": "http://pleiades.stoa.org/places/208942953/darmc-location-19435"
      }
    }
  ]
}