{
  "type": "FeatureCollection",
  "title": "Untitled",
  "id": "208942675",
  "bbox": [
    7.071673,
    35.94051,
    7.071673,
    35.94051
  ],
  "description": "An ancient place, cited: BAtlas 34 F2 unnamed feature ()",
  "features": [
    {
      "type": "Feature",
      "geometry": {
        "type": "Point",
        "coordinates": [
          7.071673,
          35.94051
        ]
      },
      "properties": {
        "description": "representative point"
      }
    },
    {
      "geometry": {
        "type": "Point",
        "coordinates": [
          7.071673,
          35.94051
        ]
      },
      "id": "darmc-location-19436",
      "type": "Feature",
      "properties": {
        "description": "500K scale point location",
        "location_precision": "precise",
        "title": "DARMC location 19436",
        "link": "http://pleiades.stoa.org/places/208942675/darmc-location-19436"
      }
    }
  ]
}