{
  "type": "FeatureCollection",
  "title": "Untitled",
  "id": "208943588",
  "description": "An ancient place, cited: BAtlas 31 D4 unnamed unlabeled (settlements)",
  "bbox": [
    5.563467,
    36.166345,
    5.563467,
    36.166345
  ],
  "reprPoint": [
    5.563467,
    36.166345
  ],
  "features": [
    {
      "geometry": {
        "type": "Point",
        "coordinates": [
          5.563467,
          36.166345
        ]
      },
      "id": "darmc-location-20469",
      "type": "Feature",
      "properties": {
        "description": "500K scale point location",
        "location_precision": "precise",
        "title": "DARMC location 20469",
        "link": "http://pleiades.stoa.org/places/208943588/darmc-location-20469"
      }
    }
  ]
}