{
  "type": "FeatureCollection",
  "title": "Untitled",
  "id": "208942392",
  "description": "An ancient place, cited: BAtlas 32 D4 unnamed unlabeled ((7 monuments, 1 cemetery, 2 walls))",
  "bbox": [
    9.306925,
    36.059929,
    9.306925,
    36.059929
  ],
  "reprPoint": [
    9.306925,
    36.059929
  ],
  "features": [
    {
      "geometry": {
        "type": "Point",
        "coordinates": [
          9.306925,
          36.059929
        ]
      },
      "id": "darmc-location-15582",
      "type": "Feature",
      "properties": {
        "description": "500K scale point location",
        "location_precision": "precise",
        "title": "DARMC location 15582",
        "link": "http://pleiades.stoa.org/places/208942392/darmc-location-15582"
      }
    }
  ]
}