{
  "type": "FeatureCollection",
  "title": "Untitled",
  "id": "208943289",
  "bbox": [
    4.900663,
    35.679631,
    4.900663,
    35.679631
  ],
  "description": "An ancient place, cited: BAtlas 34 C2 unnamed feature ()",
  "features": [
    {
      "type": "Feature",
      "geometry": {
        "type": "Point",
        "coordinates": [
          4.900663,
          35.679631
        ]
      },
      "properties": {
        "description": "representative point"
      }
    },
    {
      "geometry": {
        "type": "Point",
        "coordinates": [
          4.900663,
          35.679631
        ]
      },
      "id": "darmc-location-19388",
      "type": "Feature",
      "properties": {
        "description": "500K scale point location",
        "location_precision": "precise",
        "title": "DARMC location 19388",
        "link": "http://pleiades.stoa.org/places/208943289/darmc-location-19388"
      }
    }
  ]
}