{
  "type": "FeatureCollection",
  "title": "Untitled",
  "id": "208943249",
  "bbox": [
    10.027987,
    36.684307,
    10.027987,
    36.684307
  ],
  "description": "An ancient place, cited: BAtlas 32 F3 unnamed unlabeled ((1 monument))",
  "features": [
    {
      "type": "Feature",
      "geometry": {
        "type": "Point",
        "coordinates": [
          10.027987,
          36.684307
        ]
      },
      "properties": {
        "description": "representative point"
      }
    },
    {
      "geometry": {
        "type": "Point",
        "coordinates": [
          10.027987,
          36.684307
        ]
      },
      "id": "darmc-location-15905",
      "type": "Feature",
      "properties": {
        "description": "500K scale point location",
        "location_precision": "precise",
        "title": "DARMC location 15905",
        "link": "http://pleiades.stoa.org/places/208943249/darmc-location-15905"
      }
    }
  ]
}