{
  "type": "FeatureCollection",
  "title": "Untitled",
  "id": "208942598",
  "bbox": [
    7.410879,
    35.103057,
    7.410879,
    35.103057
  ],
  "description": "An ancient place, cited: BAtlas 34 F2 unnamed feature ()",
  "features": [
    {
      "type": "Feature",
      "geometry": {
        "type": "Point",
        "coordinates": [
          7.410879,
          35.103057
        ]
      },
      "properties": {
        "description": "representative point"
      }
    },
    {
      "geometry": {
        "type": "Point",
        "coordinates": [
          7.410879,
          35.103057
        ]
      },
      "id": "darmc-location-20629",
      "type": "Feature",
      "properties": {
        "description": "500K scale point location",
        "location_precision": "precise",
        "title": "DARMC location 20629",
        "link": "http://pleiades.stoa.org/places/208942598/darmc-location-20629"
      }
    }
  ]
}