{
  "type": "FeatureCollection",
  "title": "Untitled",
  "id": "208942175",
  "description": "An ancient place, cited: BAtlas 32 E3 unnamed unlabeled ((15 monuments))",
  "bbox": [
    9.985955,
    36.605007,
    9.985955,
    36.605007
  ],
  "reprPoint": [
    9.985955,
    36.605007
  ],
  "features": [
    {
      "geometry": {
        "type": "Point",
        "coordinates": [
          9.985955,
          36.605007
        ]
      },
      "id": "darmc-location-16135",
      "type": "Feature",
      "properties": {
        "description": "500K scale point location",
        "location_precision": "precise",
        "title": "DARMC location 16135",
        "link": "http://pleiades.stoa.org/places/208942175/darmc-location-16135"
      }
    }
  ]
}