{
  "type": "FeatureCollection",
  "title": "Untitled",
  "id": "208942304",
  "description": "An ancient place, cited: BAtlas 32 B3 unnamed unlabeled ((1 monument, 1 cemetery))",
  "bbox": [
    8.4969,
    36.660345,
    8.4969,
    36.660345
  ],
  "reprPoint": [
    8.4969,
    36.660345
  ],
  "features": [
    {
      "geometry": {
        "type": "Point",
        "coordinates": [
          8.4969,
          36.660345
        ]
      },
      "id": "darmc-location-15811",
      "type": "Feature",
      "properties": {
        "description": "500K scale point location",
        "location_precision": "precise",
        "title": "DARMC location 15811",
        "link": "http://pleiades.stoa.org/places/208942304/darmc-location-15811"
      }
    }
  ]
}