{
  "type": "FeatureCollection",
  "title": "Untitled",
  "id": "208943209",
  "description": "An ancient place, cited: BAtlas 32 F4 unnamed unlabeled ((6 monuments))",
  "bbox": [
    10.140263,
    36.053001,
    10.140263,
    36.053001
  ],
  "reprPoint": [
    10.140263,
    36.053001
  ],
  "features": [
    {
      "geometry": {
        "type": "Point",
        "coordinates": [
          10.140263,
          36.053001
        ]
      },
      "id": "darmc-location-15913",
      "type": "Feature",
      "properties": {
        "description": "500K scale point location",
        "location_precision": "precise",
        "title": "DARMC location 15913",
        "link": "http://pleiades.stoa.org/places/208943209/darmc-location-15913"
      }
    }
  ]
}