{
  "type": "FeatureCollection",
  "title": "Untitled",
  "id": "208942967",
  "description": "An ancient place, cited: BAtlas 34 B2 unnamed feature ()",
  "bbox": [
    3.7162,
    35.491975,
    3.7162,
    35.491975
  ],
  "reprPoint": [
    3.7162,
    35.491975
  ],
  "features": [
    {
      "geometry": {
        "type": "Point",
        "coordinates": [
          3.7162,
          35.491975
        ]
      },
      "id": "darmc-location-33352",
      "type": "Feature",
      "properties": {
        "description": "scale point location",
        "location_precision": "precise",
        "title": "DARMC location 33352",
        "link": "http://pleiades.stoa.org/places/208942967/darmc-location-33352"
      }
    }
  ]
}