{
  "type": "FeatureCollection",
  "title": "Untitled",
  "id": "208942490",
  "description": "An ancient place, cited: BAtlas 32 D3 unnamed unlabeled ((2 monuments))",
  "bbox": [
    9.022133,
    36.557364,
    9.022133,
    36.557364
  ],
  "reprPoint": [
    9.022133,
    36.557364
  ],
  "features": [
    {
      "geometry": {
        "type": "Point",
        "coordinates": [
          9.022133,
          36.557364
        ]
      },
      "id": "darmc-location-26709",
      "type": "Feature",
      "properties": {
        "description": "500K scale point location",
        "location_precision": "precise",
        "title": "DARMC location 26709",
        "link": "http://pleiades.stoa.org/places/208942490/darmc-location-26709"
      }
    }
  ]
}