{
  "type": "FeatureCollection",
  "title": "Untitled",
  "id": "208942642",
  "description": "An ancient place, cited: BAtlas 34 F2 unnamed feature ()",
  "bbox": [
    7.173991,
    35.285262,
    7.173991,
    35.285262
  ],
  "reprPoint": [
    7.173991,
    35.285262
  ],
  "features": [
    {
      "geometry": {
        "type": "Point",
        "coordinates": [
          7.173991,
          35.285262
        ]
      },
      "id": "darmc-location-20572",
      "type": "Feature",
      "properties": {
        "description": "500K scale point location",
        "location_precision": "precise",
        "title": "DARMC location 20572",
        "link": "http://pleiades.stoa.org/places/208942642/darmc-location-20572"
      }
    }
  ]
}