{
  "type": "FeatureCollection",
  "title": "Untitled",
  "id": "208942158",
  "description": "An ancient place, cited: BAtlas 32 E3 unnamed unlabeled ((15 monuments))",
  "bbox": [
    9.863056,
    36.597639,
    9.874375,
    36.599168
  ],
  "reprPoint": [
    9.8687155,
    36.5984035
  ],
  "features": [
    {
      "geometry": {
        "type": "Point",
        "coordinates": [
          9.874375,
          36.597639
        ]
      },
      "id": "darmc-location-25740",
      "type": "Feature",
      "properties": {
        "description": "500K scale point location",
        "location_precision": "precise",
        "title": "DARMC location 25740",
        "link": "http://pleiades.stoa.org/places/208942158/darmc-location-25740"
      }
    },
    {
      "geometry": {
        "type": "Point",
        "coordinates": [
          9.863056,
          36.599168
        ]
      },
      "id": "dare-location",
      "type": "Feature",
      "properties": {
        "description": "Representative point location, site precision",
        "location_precision": "precise",
        "title": "DARE Location",
        "link": "http://pleiades.stoa.org/places/208942158/dare-location"
      }
    }
  ]
}