{
  "type": "FeatureCollection",
  "title": "Untitled",
  "id": "208942296",
  "bbox": [
    8.190802,
    36.617169,
    8.190802,
    36.617169
  ],
  "description": "An ancient place, cited: BAtlas 32 B3 unnamed unlabeled ((1 monument, 1 cemetery))",
  "features": [
    {
      "type": "Feature",
      "geometry": {
        "type": "Point",
        "coordinates": [
          8.190802,
          36.617169
        ]
      },
      "properties": {
        "description": "representative point"
      }
    },
    {
      "geometry": {
        "type": "Point",
        "coordinates": [
          8.190802,
          36.617169
        ]
      },
      "id": "darmc-location-15803",
      "type": "Feature",
      "properties": {
        "description": "500K scale point location",
        "location_precision": "precise",
        "title": "DARMC location 15803",
        "link": "http://pleiades.stoa.org/places/208942296/darmc-location-15803"
      }
    }
  ]
}