{
  "type": "FeatureCollection",
  "title": "Untitled",
  "id": "208942428",
  "description": "An ancient place, cited: BAtlas 32 D4 unnamed unlabeled ((7 monuments, 1 cemetery, 2 walls))",
  "bbox": [
    9.028959,
    36.209813,
    9.028959,
    36.209813
  ],
  "reprPoint": [
    9.028959,
    36.209813
  ],
  "features": [
    {
      "geometry": {
        "type": "Point",
        "coordinates": [
          9.028959,
          36.209813
        ]
      },
      "id": "darmc-location-15720",
      "type": "Feature",
      "properties": {
        "description": "500K scale point location",
        "location_precision": "precise",
        "title": "DARMC location 15720",
        "link": "http://pleiades.stoa.org/places/208942428/darmc-location-15720"
      }
    }
  ]
}