{
  "type": "FeatureCollection",
  "title": "Untitled",
  "id": "208943177",
  "description": "An ancient place, cited: BAtlas 34 D2 unnamed feature ()",
  "bbox": [
    5.373027,
    35.369572,
    5.373027,
    35.369572
  ],
  "reprPoint": [
    5.373027,
    35.369572
  ],
  "features": [
    {
      "geometry": {
        "type": "Point",
        "coordinates": [
          5.373027,
          35.369572
        ]
      },
      "id": "darmc-location-19129",
      "type": "Feature",
      "properties": {
        "description": "500K scale point location",
        "location_precision": "precise",
        "title": "DARMC location 19129",
        "link": "http://pleiades.stoa.org/places/208943177/darmc-location-19129"
      }
    }
  ]
}