{
  "type": "FeatureCollection",
  "title": "Untitled",
  "id": "208943001",
  "description": "An ancient place, cited: BAtlas 33 G1 unnamed unlabeled ((1 cemetery))",
  "bbox": [
    10.563953,
    35.574499,
    10.563953,
    35.574499
  ],
  "reprPoint": [
    10.563953,
    35.574499
  ],
  "features": [
    {
      "geometry": {
        "type": "Point",
        "coordinates": [
          10.563953,
          35.574499
        ]
      },
      "id": "darmc-location-20374",
      "type": "Feature",
      "properties": {
        "description": "500K scale point location",
        "location_precision": "precise",
        "title": "DARMC location 20374",
        "link": "http://pleiades.stoa.org/places/208943001/darmc-location-20374"
      }
    }
  ]
}