{
  "type": "FeatureCollection",
  "title": "Untitled",
  "id": "208942419",
  "description": "An ancient place, cited: BAtlas 32 D4 unnamed unlabeled ((7 monuments, 1 cemetery, 2 walls))",
  "bbox": [
    9.001934,
    36.080027,
    9.001934,
    36.080027
  ],
  "reprPoint": [
    9.001934,
    36.080027
  ],
  "features": [
    {
      "geometry": {
        "type": "Point",
        "coordinates": [
          9.001934,
          36.080027
        ]
      },
      "id": "darmc-location-15565",
      "type": "Feature",
      "properties": {
        "description": "500K scale point location",
        "location_precision": "precise",
        "title": "DARMC location 15565",
        "link": "http://pleiades.stoa.org/places/208942419/darmc-location-15565"
      }
    }
  ]
}