{
  "type": "FeatureCollection",
  "title": "Untitled",
  "id": "208942904",
  "bbox": [
    7.811376,
    36.577787,
    7.811376,
    36.577787
  ],
  "description": "An ancient place, cited: BAtlas 31 H3 unnamed unlabeled (settlements)",
  "features": [
    {
      "type": "Feature",
      "geometry": {
        "type": "Point",
        "coordinates": [
          7.811376,
          36.577787
        ]
      },
      "properties": {
        "description": "representative point"
      }
    },
    {
      "geometry": {
        "type": "Point",
        "coordinates": [
          7.811376,
          36.577787
        ]
      },
      "id": "darmc-location-15795",
      "type": "Feature",
      "properties": {
        "description": "500K scale point location",
        "location_precision": "precise",
        "title": "DARMC location 15795",
        "link": "http://pleiades.stoa.org/places/208942904/darmc-location-15795"
      }
    }
  ]
}