{
  "type": "FeatureCollection",
  "title": "Untitled",
  "id": "208942195",
  "description": "An ancient place, cited: BAtlas 32 E3 unnamed unlabeled ((15 monuments))",
  "bbox": [
    9.598081,
    36.849617,
    9.598081,
    36.849617
  ],
  "reprPoint": [
    9.598081,
    36.849617
  ],
  "features": [
    {
      "geometry": {
        "type": "Point",
        "coordinates": [
          9.598081,
          36.849617
        ]
      },
      "id": "darmc-location-26759",
      "type": "Feature",
      "properties": {
        "description": "500K scale point location",
        "location_precision": "precise",
        "title": "DARMC location 26759",
        "link": "http://pleiades.stoa.org/places/208942195/darmc-location-26759"
      }
    }
  ]
}