{
  "type": "FeatureCollection",
  "title": "Untitled",
  "id": "208942438",
  "description": "An ancient place, cited: BAtlas 32 E2 unnamed unlabeled ((4 cemeteries))",
  "bbox": [
    9.968659,
    37.093871,
    9.968659,
    37.093871
  ],
  "reprPoint": [
    9.968659,
    37.093871
  ],
  "features": [
    {
      "geometry": {
        "type": "Point",
        "coordinates": [
          9.968659,
          37.093871
        ]
      },
      "id": "darmc-location-26784",
      "type": "Feature",
      "properties": {
        "description": "500K scale point location",
        "location_precision": "precise",
        "title": "DARMC location 26784",
        "link": "http://pleiades.stoa.org/places/208942438/darmc-location-26784"
      }
    }
  ]
}