{
  "type": "FeatureCollection",
  "title": "Untitled",
  "id": "208943015",
  "description": "An ancient place, cited: BAtlas 33 G2 unnamed unlabeled ((3 monuments, 1 bath))",
  "bbox": [
    10.717397,
    35.255335,
    10.717397,
    35.255335
  ],
  "reprPoint": [
    10.717397,
    35.255335
  ],
  "features": [
    {
      "geometry": {
        "type": "Point",
        "coordinates": [
          10.717397,
          35.255335
        ]
      },
      "id": "darmc-location-27307",
      "type": "Feature",
      "properties": {
        "description": "500K scale point location",
        "location_precision": "precise",
        "title": "DARMC location 27307",
        "link": "http://pleiades.stoa.org/places/208943015/darmc-location-27307"
      }
    }
  ]
}