{
  "type": "FeatureCollection",
  "title": "Untitled",
  "id": "208942797",
  "description": "An ancient place, cited: BAtlas 34 E2 unnamed feature ()",
  "bbox": [
    6.73171,
    35.620382,
    6.73171,
    35.620382
  ],
  "reprPoint": [
    6.73171,
    35.620382
  ],
  "features": [
    {
      "geometry": {
        "type": "Point",
        "coordinates": [
          6.73171,
          35.620382
        ]
      },
      "id": "darmc-location-14955",
      "type": "Feature",
      "properties": {
        "description": "500K scale point location",
        "location_precision": "precise",
        "title": "DARMC location 14955",
        "link": "http://pleiades.stoa.org/places/208942797/darmc-location-14955"
      }
    }
  ]
}