{
  "type": "FeatureCollection",
  "title": "Untitled",
  "id": "208942718",
  "bbox": [
    5.851399,
    34.570326,
    5.851399,
    34.570326
  ],
  "description": "An ancient place, cited: BAtlas 34 D3 unnamed feature ()",
  "features": [
    {
      "type": "Feature",
      "geometry": {
        "type": "Point",
        "coordinates": [
          5.851399,
          34.570326
        ]
      },
      "properties": {
        "description": "representative point"
      }
    },
    {
      "geometry": {
        "type": "Point",
        "coordinates": [
          5.851399,
          34.570326
        ]
      },
      "id": "darmc-location-16163",
      "type": "Feature",
      "properties": {
        "description": "500K scale point location",
        "location_precision": "precise",
        "title": "DARMC location 16163",
        "link": "http://pleiades.stoa.org/places/208942718/darmc-location-16163"
      }
    }
  ]
}