{
  "type": "FeatureCollection",
  "title": "Untitled",
  "id": "208943071",
  "description": "An ancient place, cited: BAtlas 33 D3 unnamed unlabeled ((1 aqueduct))",
  "bbox": [
    9.161719,
    34.641527,
    9.161719,
    34.641527
  ],
  "reprPoint": [
    9.161719,
    34.641527
  ],
  "features": [
    {
      "geometry": {
        "type": "Point",
        "coordinates": [
          9.161719,
          34.641527
        ]
      },
      "id": "darmc-location-20801",
      "type": "Feature",
      "properties": {
        "description": "500K scale point location",
        "location_precision": "precise",
        "title": "DARMC location 20801",
        "link": "http://pleiades.stoa.org/places/208943071/darmc-location-20801"
      }
    }
  ]
}