{
  "type": "FeatureCollection",
  "title": "Untitled",
  "id": "208942270",
  "bbox": [
    8.307817,
    36.61239,
    8.307817,
    36.61239
  ],
  "description": "An ancient place, cited: BAtlas 32 B3 unnamed unlabeled ((1 monument, 1 cemetery))",
  "features": [
    {
      "type": "Feature",
      "geometry": {
        "type": "Point",
        "coordinates": [
          8.307817,
          36.61239
        ]
      },
      "properties": {
        "description": "representative point"
      }
    },
    {
      "geometry": {
        "type": "Point",
        "coordinates": [
          8.307817,
          36.61239
        ]
      },
      "id": "darmc-location-26701",
      "type": "Feature",
      "properties": {
        "description": "500K scale point location",
        "location_precision": "precise",
        "title": "DARMC location 26701",
        "link": "http://pleiades.stoa.org/places/208942270/darmc-location-26701"
      }
    }
  ]
}