{
  "type": "FeatureCollection",
  "title": "Untitled",
  "id": "208942274",
  "bbox": [
    8.431139,
    36.511458,
    8.431139,
    36.511458
  ],
  "description": "An ancient place, cited: BAtlas 32 B3 unnamed unlabeled ((1 monument, 1 cemetery))",
  "features": [
    {
      "type": "Feature",
      "geometry": {
        "type": "Point",
        "coordinates": [
          8.431139,
          36.511458
        ]
      },
      "properties": {
        "description": "representative point"
      }
    },
    {
      "geometry": {
        "type": "Point",
        "coordinates": [
          8.431139,
          36.511458
        ]
      },
      "id": "darmc-location-26705",
      "type": "Feature",
      "properties": {
        "description": "500K scale point location",
        "location_precision": "precise",
        "title": "DARMC location 26705",
        "link": "http://pleiades.stoa.org/places/208942274/darmc-location-26705"
      }
    }
  ]
}