{
  "type": "FeatureCollection",
  "title": "Untitled",
  "id": "208943721",
  "description": "An ancient place, cited: BAtlas 31 E3 unnamed unlabeled (settlements)",
  "bbox": [
    6.489765,
    36.507337,
    6.489765,
    36.507337
  ],
  "reprPoint": [
    6.489765,
    36.507337
  ],
  "features": [
    {
      "geometry": {
        "type": "Point",
        "coordinates": [
          6.489765,
          36.507337
        ]
      },
      "id": "darmc-location-25837",
      "type": "Feature",
      "properties": {
        "description": "500K scale point location",
        "location_precision": "precise",
        "title": "DARMC location 25837",
        "link": "http://pleiades.stoa.org/places/208943721/darmc-location-25837"
      }
    }
  ]
}