{
  "type": "FeatureCollection",
  "title": "Untitled",
  "id": "208942527",
  "description": "An ancient place, cited: BAtlas 34 F3 unnamed feature ()",
  "bbox": [
    7.23695,
    34.386144,
    7.23695,
    34.386144
  ],
  "reprPoint": [
    7.23695,
    34.386144
  ],
  "features": [
    {
      "geometry": {
        "type": "Point",
        "coordinates": [
          7.23695,
          34.386144
        ]
      },
      "id": "darmc-location-20700",
      "type": "Feature",
      "properties": {
        "description": "500K scale point location",
        "location_precision": "precise",
        "title": "DARMC location 20700",
        "link": "http://pleiades.stoa.org/places/208942527/darmc-location-20700"
      }
    }
  ]
}