{
  "type": "FeatureCollection",
  "title": "Untitled",
  "id": "208943620",
  "description": "An ancient place, cited: BAtlas 31 D4 unnamed unlabeled (settlements)",
  "bbox": [
    5.904168,
    36.092465,
    5.904168,
    36.092465
  ],
  "reprPoint": [
    5.904168,
    36.092465
  ],
  "features": [
    {
      "geometry": {
        "type": "Point",
        "coordinates": [
          5.904168,
          36.092465
        ]
      },
      "id": "darmc-location-20913",
      "type": "Feature",
      "properties": {
        "description": "500K scale point location",
        "location_precision": "precise",
        "title": "DARMC location 20913",
        "link": "http://pleiades.stoa.org/places/208943620/darmc-location-20913"
      }
    }
  ]
}