{
  "type": "FeatureCollection",
  "title": "Untitled",
  "id": "208943533",
  "description": "An ancient place, cited: BAtlas 33 D2 unnamed unlabeled ((5 monuments))",
  "bbox": [
    9.1471,
    35.179915,
    9.1471,
    35.179915
  ],
  "reprPoint": [
    9.1471,
    35.179915
  ],
  "features": [
    {
      "geometry": {
        "type": "Point",
        "coordinates": [
          9.1471,
          35.179915
        ]
      },
      "id": "darmc-location-20795",
      "type": "Feature",
      "properties": {
        "description": "500K scale point location",
        "location_precision": "precise",
        "title": "DARMC location 20795",
        "link": "http://pleiades.stoa.org/places/208943533/darmc-location-20795"
      }
    }
  ]
}