{
  "type": "FeatureCollection",
  "title": "Untitled",
  "id": "208942786",
  "description": "An ancient place, cited: BAtlas 34 E2 unnamed feature ()",
  "bbox": [
    6.776617,
    35.639998,
    6.776617,
    35.639998
  ],
  "reprPoint": [
    6.776617,
    35.639998
  ],
  "features": [
    {
      "geometry": {
        "type": "Point",
        "coordinates": [
          6.776617,
          35.639998
        ]
      },
      "id": "darmc-location-19484",
      "type": "Feature",
      "properties": {
        "description": "500K scale point location",
        "location_precision": "precise",
        "title": "DARMC location 19484",
        "link": "http://pleiades.stoa.org/places/208942786/darmc-location-19484"
      }
    }
  ]
}