{
  "type": "FeatureCollection",
  "title": "Untitled",
  "id": "208942689",
  "description": "An ancient place, cited: BAtlas 34 G2 unnamed feature ()",
  "bbox": [
    8.086098,
    35.846037,
    8.086098,
    35.846037
  ],
  "reprPoint": [
    8.086098,
    35.846037
  ],
  "features": [
    {
      "geometry": {
        "type": "Point",
        "coordinates": [
          8.086098,
          35.846037
        ]
      },
      "id": "darmc-location-27155",
      "type": "Feature",
      "properties": {
        "description": "500K scale point location",
        "location_precision": "precise",
        "title": "DARMC location 27155",
        "link": "http://pleiades.stoa.org/places/208942689/darmc-location-27155"
      }
    }
  ]
}