{
  "type": "FeatureCollection",
  "title": "Untitled",
  "id": "208942302",
  "description": "An ancient place, cited: BAtlas 32 B3 unnamed unlabeled ((1 monument, 1 cemetery))",
  "bbox": [
    8.152249,
    36.592122,
    8.152249,
    36.592122
  ],
  "reprPoint": [
    8.152249,
    36.592122
  ],
  "features": [
    {
      "geometry": {
        "type": "Point",
        "coordinates": [
          8.152249,
          36.592122
        ]
      },
      "id": "darmc-location-15790",
      "type": "Feature",
      "properties": {
        "description": "500K scale point location",
        "location_precision": "precise",
        "title": "DARMC location 15790",
        "link": "http://pleiades.stoa.org/places/208942302/darmc-location-15790"
      }
    }
  ]
}