{
  "type": "FeatureCollection",
  "title": "Untitled",
  "id": "208943285",
  "bbox": [
    4.396186,
    35.814028,
    4.396186,
    35.814028
  ],
  "description": "An ancient place, cited: BAtlas 34 C2 unnamed feature ()",
  "features": [
    {
      "type": "Feature",
      "geometry": {
        "type": "Point",
        "coordinates": [
          4.396186,
          35.814028
        ]
      },
      "properties": {
        "description": "representative point"
      }
    },
    {
      "geometry": {
        "type": "Point",
        "coordinates": [
          4.396186,
          35.814028
        ]
      },
      "id": "darmc-location-19391",
      "type": "Feature",
      "properties": {
        "description": "500K scale point location",
        "location_precision": "precise",
        "title": "DARMC location 19391",
        "link": "http://pleiades.stoa.org/places/208943285/darmc-location-19391"
      }
    }
  ]
}