{
  "type": "FeatureCollection",
  "title": "Untitled",
  "id": "208942397",
  "bbox": [
    9.348807,
    36.153319,
    9.348807,
    36.153319
  ],
  "description": "An ancient place, cited: BAtlas 32 D4 unnamed unlabeled ((7 monuments, 1 cemetery, 2 walls))",
  "features": [
    {
      "type": "Feature",
      "geometry": {
        "type": "Point",
        "coordinates": [
          9.348807,
          36.153319
        ]
      },
      "properties": {
        "description": "representative point"
      }
    },
    {
      "geometry": {
        "type": "Point",
        "coordinates": [
          9.348807,
          36.153319
        ]
      },
      "id": "darmc-location-15587",
      "type": "Feature",
      "properties": {
        "description": "500K scale point location",
        "location_precision": "precise",
        "title": "DARMC location 15587",
        "link": "http://pleiades.stoa.org/places/208942397/darmc-location-15587"
      }
    }
  ]
}