{
  "type": "FeatureCollection",
  "title": "Untitled",
  "id": "208943398",
  "bbox": [
    2.726559,
    35.019567,
    2.726559,
    35.019567
  ],
  "description": "An ancient place, cited: BAtlas 34 A2 unnamed feature ()",
  "features": [
    {
      "type": "Feature",
      "geometry": {
        "type": "Point",
        "coordinates": [
          2.726559,
          35.019567
        ]
      },
      "properties": {
        "description": "representative point"
      }
    },
    {
      "geometry": {
        "type": "Point",
        "coordinates": [
          2.726559,
          35.019567
        ]
      },
      "id": "darmc-location-33325",
      "type": "Feature",
      "properties": {
        "description": "representative point location digitized from the Barrington Atlas of the Greek and Roman World by the Digital Atlas of Roman and Medieval Civilizations project at Harvard University.",
        "location_precision": "precise",
        "title": "DARMC location 33325",
        "link": "http://pleiades.stoa.org/places/208943398/darmc-location-33325"
      }
    }
  ]
}