{
  "type": "FeatureCollection",
  "title": "Untitled",
  "id": "208942203",
  "bbox": [
    9.583255,
    36.513101,
    9.583255,
    36.513101
  ],
  "description": "An ancient place, cited: BAtlas 32 E3 unnamed unlabeled ((15 monuments))",
  "features": [
    {
      "type": "Feature",
      "geometry": {
        "type": "Point",
        "coordinates": [
          9.583255,
          36.513101
        ]
      },
      "properties": {
        "description": "representative point"
      }
    },
    {
      "geometry": {
        "type": "Point",
        "coordinates": [
          9.583255,
          36.513101
        ]
      },
      "id": "darmc-location-16040",
      "type": "Feature",
      "properties": {
        "description": "500K scale point location",
        "location_precision": "precise",
        "title": "DARMC location 16040",
        "link": "http://pleiades.stoa.org/places/208942203/darmc-location-16040"
      }
    }
  ]
}