{
  "type": "FeatureCollection",
  "title": "Untitled",
  "id": "208943695",
  "description": "An ancient place, cited: BAtlas 33 F3 unnamed unlabeled ((6 monuments, 1 wall, 1 aqueduct))",
  "bbox": [
    10.287122,
    34.560403,
    10.287122,
    34.560403
  ],
  "reprPoint": [
    10.287122,
    34.560403
  ],
  "features": [
    {
      "geometry": {
        "type": "Point",
        "coordinates": [
          10.287122,
          34.560403
        ]
      },
      "id": "darmc-location-20327",
      "type": "Feature",
      "properties": {
        "description": "500K scale point location",
        "location_precision": "precise",
        "title": "DARMC location 20327",
        "link": "http://pleiades.stoa.org/places/208943695/darmc-location-20327"
      }
    }
  ]
}