{
  "type": "FeatureCollection",
  "title": "Untitled",
  "id": "208943231",
  "description": "An ancient place, cited: BAtlas 32 F4 unnamed unlabeled ((6 monuments))",
  "bbox": [
    10.46388,
    36.289893,
    10.46388,
    36.289893
  ],
  "reprPoint": [
    10.46388,
    36.289893
  ],
  "features": [
    {
      "geometry": {
        "type": "Point",
        "coordinates": [
          10.46388,
          36.289893
        ]
      },
      "id": "darmc-location-15929",
      "type": "Feature",
      "properties": {
        "description": "500K scale point location",
        "location_precision": "precise",
        "title": "DARMC location 15929",
        "link": "http://pleiades.stoa.org/places/208943231/darmc-location-15929"
      }
    }
  ]
}