{
  "type": "FeatureCollection",
  "title": "Untitled",
  "id": "208943227",
  "description": "An ancient place, cited: BAtlas 32 F4 unnamed unlabeled ((6 monuments))",
  "bbox": [
    10.088209,
    36.257222,
    10.088209,
    36.257222
  ],
  "reprPoint": [
    10.088209,
    36.257222
  ],
  "features": [
    {
      "geometry": {
        "type": "Point",
        "coordinates": [
          10.088209,
          36.257222
        ]
      },
      "id": "darmc-location-16009",
      "type": "Feature",
      "properties": {
        "description": "500K scale point location",
        "location_precision": "precise",
        "title": "DARMC location 16009",
        "link": "http://pleiades.stoa.org/places/208943227/darmc-location-16009"
      }
    }
  ]
}