{
  "type": "FeatureCollection",
  "title": "Untitled",
  "id": "208943096",
  "description": "An ancient place, cited: BAtlas 33 E1 unnamed unlabeled ((1 wall, 4 monuments, 3 aqueducts))",
  "bbox": [
    9.610771,
    35.949643,
    9.610771,
    35.949643
  ],
  "reprPoint": [
    9.610771,
    35.949643
  ],
  "features": [
    {
      "geometry": {
        "type": "Point",
        "coordinates": [
          9.610771,
          35.949643
        ]
      },
      "id": "darmc-location-20824",
      "type": "Feature",
      "properties": {
        "description": "500K scale point location",
        "location_precision": "precise",
        "title": "DARMC location 20824",
        "link": "http://pleiades.stoa.org/places/208943096/darmc-location-20824"
      }
    }
  ]
}