{
  "type": "FeatureCollection",
  "title": "Untitled",
  "id": "208943250",
  "description": "An ancient place, cited: BAtlas 32 F3 unnamed unlabeled ((1 monument))",
  "bbox": [
    10.00241,
    36.841158,
    10.00241,
    36.841158
  ],
  "reprPoint": [
    10.00241,
    36.841158
  ],
  "features": [
    {
      "geometry": {
        "type": "Point",
        "coordinates": [
          10.00241,
          36.841158
        ]
      },
      "id": "darmc-location-15900",
      "type": "Feature",
      "properties": {
        "description": "500K scale point location",
        "location_precision": "precise",
        "title": "DARMC location 15900",
        "link": "http://pleiades.stoa.org/places/208943250/darmc-location-15900"
      }
    }
  ]
}