{
  "type": "FeatureCollection",
  "title": "Untitled",
  "id": "208942314",
  "description": "An ancient place, cited: BAtlas 32 B3 unnamed unlabeled ((1 monument, 1 cemetery))",
  "bbox": [
    8.194286,
    36.566185,
    8.194286,
    36.566185
  ],
  "reprPoint": [
    8.194286,
    36.566185
  ],
  "features": [
    {
      "geometry": {
        "type": "Point",
        "coordinates": [
          8.194286,
          36.566185
        ]
      },
      "id": "darmc-location-15789",
      "type": "Feature",
      "properties": {
        "description": "500K scale point location",
        "location_precision": "precise",
        "title": "DARMC location 15789",
        "link": "http://pleiades.stoa.org/places/208942314/darmc-location-15789"
      }
    }
  ]
}