{
  "type": "FeatureCollection",
  "title": "Untitled",
  "id": "208943502",
  "description": "An ancient place, cited: BAtlas 33 D2 unnamed unlabeled ((5 monuments))",
  "bbox": [
    9.359337,
    35.352245,
    9.359337,
    35.352245
  ],
  "reprPoint": [
    9.359337,
    35.352245
  ],
  "features": [
    {
      "geometry": {
        "type": "Point",
        "coordinates": [
          9.359337,
          35.352245
        ]
      },
      "id": "darmc-location-27274",
      "type": "Feature",
      "properties": {
        "description": "500K scale point location",
        "location_precision": "precise",
        "title": "DARMC location 27274",
        "link": "http://pleiades.stoa.org/places/208943502/darmc-location-27274"
      }
    }
  ]
}