{
  "type": "FeatureCollection",
  "title": "Untitled",
  "id": "208943062",
  "bbox": [
    9.641875,
    34.917277,
    9.641875,
    34.917277
  ],
  "description": "An ancient place, cited: BAtlas 33 E3 unnamed unlabeled ((2 monuments))",
  "features": [
    {
      "type": "Feature",
      "geometry": {
        "type": "Point",
        "coordinates": [
          9.641875,
          34.917277
        ]
      },
      "properties": {
        "description": "representative point"
      }
    },
    {
      "geometry": {
        "type": "Point",
        "coordinates": [
          9.641875,
          34.917277
        ]
      },
      "id": "darmc-location-20838",
      "type": "Feature",
      "properties": {
        "description": "500K scale point location",
        "location_precision": "precise",
        "title": "DARMC location 20838",
        "link": "http://pleiades.stoa.org/places/208943062/darmc-location-20838"
      }
    }
  ]
}