{
  "type": "FeatureCollection",
  "title": "Untitled",
  "id": "208942839",
  "bbox": [
    12.676511,
    43.586198,
    12.676511,
    43.586198
  ],
  "description": "An ancient place, cited: BAtlas 42 D1-C4 unnamed bridge (on Via Flaminia (20))",
  "connectsWith": [
    "856514595"
  ],
  "features": [
    {
      "type": "Feature",
      "geometry": {
        "type": "Point",
        "coordinates": [
          12.676511,
          43.586198
        ]
      },
      "properties": {
        "description": "representative point"
      }
    },
    {
      "geometry": {
        "type": "Point",
        "coordinates": [
          12.676511,
          43.586198
        ]
      },
      "id": "darmc-location-27724",
      "type": "Feature",
      "properties": {
        "description": "500K scale point location",
        "location_precision": "precise",
        "title": "DARMC location 27724",
        "link": "http://pleiades.stoa.org/places/208942839/darmc-location-27724"
      }
    }
  ]
}