{
  "type": "FeatureCollection",
  "title": "Untitled",
  "id": "208942323",
  "description": "An ancient place, cited: BAtlas 32 C3 unnamed unlabeled ((2 monuments))",
  "bbox": [
    8.777705,
    36.904031,
    8.777705,
    36.904031
  ],
  "reprPoint": [
    8.777705,
    36.904031
  ],
  "features": [
    {
      "geometry": {
        "type": "Point",
        "coordinates": [
          8.777705,
          36.904031
        ]
      },
      "id": "darmc-location-26626",
      "type": "Feature",
      "properties": {
        "description": "500K scale point location",
        "location_precision": "precise",
        "title": "DARMC location 26626",
        "link": "http://pleiades.stoa.org/places/208942323/darmc-location-26626"
      }
    }
  ]
}