{
  "type": "FeatureCollection",
  "title": "Untitled",
  "id": "208943609",
  "bbox": [
    5.528656,
    36.107829,
    5.528656,
    36.107829
  ],
  "description": "An ancient place, cited: BAtlas 31 D4 unnamed unlabeled (settlements)",
  "features": [
    {
      "type": "Feature",
      "geometry": {
        "type": "Point",
        "coordinates": [
          5.528656,
          36.107829
        ]
      },
      "properties": {
        "description": "representative point"
      }
    },
    {
      "geometry": {
        "type": "Point",
        "coordinates": [
          5.528656,
          36.107829
        ]
      },
      "id": "darmc-location-20900",
      "type": "Feature",
      "properties": {
        "description": "500K scale point location",
        "location_precision": "precise",
        "title": "DARMC location 20900",
        "link": "http://pleiades.stoa.org/places/208943609/darmc-location-20900"
      }
    }
  ]
}