{
  "type": "FeatureCollection",
  "title": "Untitled",
  "id": "208942629",
  "bbox": [
    7.2377,
    35.200503,
    7.2377,
    35.200503
  ],
  "description": "An ancient place, cited: BAtlas 34 F2 unnamed feature ()",
  "features": [
    {
      "type": "Feature",
      "geometry": {
        "type": "Point",
        "coordinates": [
          7.2377,
          35.200503
        ]
      },
      "properties": {
        "description": "representative point"
      }
    },
    {
      "geometry": {
        "type": "Point",
        "coordinates": [
          7.2377,
          35.200503
        ]
      },
      "id": "darmc-location-20634",
      "type": "Feature",
      "properties": {
        "description": "500K scale point location",
        "location_precision": "precise",
        "title": "DARMC location 20634",
        "link": "http://pleiades.stoa.org/places/208942629/darmc-location-20634"
      }
    }
  ]
}