{
  "type": "FeatureCollection",
  "title": "Untitled",
  "id": "208943597",
  "bbox": [
    5.683321,
    36.212583,
    5.683321,
    36.212583
  ],
  "description": "An ancient place, cited: BAtlas 31 D4 unnamed unlabeled (settlements)",
  "features": [
    {
      "type": "Feature",
      "geometry": {
        "type": "Point",
        "coordinates": [
          5.683321,
          36.212583
        ]
      },
      "properties": {
        "description": "representative point"
      }
    },
    {
      "geometry": {
        "type": "Point",
        "coordinates": [
          5.683321,
          36.212583
        ]
      },
      "id": "darmc-location-20471",
      "type": "Feature",
      "properties": {
        "description": "500K scale point location",
        "location_precision": "precise",
        "title": "DARMC location 20471",
        "link": "http://pleiades.stoa.org/places/208943597/darmc-location-20471"
      }
    }
  ]
}