{
  "type": "FeatureCollection",
  "title": "Untitled",
  "id": "208942766",
  "description": "An ancient place, cited: BAtlas 34 E2 unnamed feature ()",
  "bbox": [
    6.398084,
    35.145721,
    6.398084,
    35.145721
  ],
  "reprPoint": [
    6.398084,
    35.145721
  ],
  "features": [
    {
      "geometry": {
        "type": "Point",
        "coordinates": [
          6.398084,
          35.145721
        ]
      },
      "id": "darmc-location-20657",
      "type": "Feature",
      "properties": {
        "description": "500K scale point location",
        "location_precision": "precise",
        "title": "DARMC location 20657",
        "link": "http://pleiades.stoa.org/places/208942766/darmc-location-20657"
      }
    }
  ]
}