{
  "type": "FeatureCollection",
  "title": "Untitled",
  "id": "208942809",
  "bbox": [
    6.969627,
    35.406146,
    6.969627,
    35.406146
  ],
  "description": "An ancient place, cited: BAtlas 34 E2 unnamed feature ()",
  "features": [
    {
      "type": "Feature",
      "geometry": {
        "type": "Point",
        "coordinates": [
          6.969627,
          35.406146
        ]
      },
      "properties": {
        "description": "representative point"
      }
    },
    {
      "geometry": {
        "type": "Point",
        "coordinates": [
          6.969627,
          35.406146
        ]
      },
      "id": "darmc-location-16173",
      "type": "Feature",
      "properties": {
        "description": "500K scale point location",
        "location_precision": "precise",
        "title": "DARMC location 16173",
        "link": "http://pleiades.stoa.org/places/208942809/darmc-location-16173"
      }
    }
  ]
}