{
  "type": "FeatureCollection",
  "title": "Untitled",
  "id": "208943465",
  "description": "An ancient place, cited: BAtlas 33 B3 unnamed unlabeled ((1 monument))",
  "bbox": [
    8.192699,
    34.611325,
    8.192699,
    34.611325
  ],
  "reprPoint": [
    8.192699,
    34.611325
  ],
  "features": [
    {
      "geometry": {
        "type": "Point",
        "coordinates": [
          8.192699,
          34.611325
        ]
      },
      "id": "darmc-location-25786",
      "type": "Feature",
      "properties": {
        "description": "500K scale point location",
        "location_precision": "precise",
        "title": "DARMC location 25786",
        "link": "http://pleiades.stoa.org/places/208943465/darmc-location-25786"
      }
    }
  ]
}