{
  "type": "FeatureCollection",
  "title": "Untitled",
  "id": "208943464",
  "description": "An ancient place, cited: BAtlas 33 B3 unnamed unlabeled ((1 monument))",
  "bbox": [
    8.164806,
    34.670813,
    8.164806,
    34.670813
  ],
  "reprPoint": [
    8.164806,
    34.670813
  ],
  "features": [
    {
      "geometry": {
        "type": "Point",
        "coordinates": [
          8.164806,
          34.670813
        ]
      },
      "id": "darmc-location-27141",
      "type": "Feature",
      "properties": {
        "description": "500K scale point location",
        "location_precision": "precise",
        "title": "DARMC location 27141",
        "link": "http://pleiades.stoa.org/places/208943464/darmc-location-27141"
      }
    }
  ]
}