{
  "type": "FeatureCollection",
  "title": "Untitled",
  "id": "208942556",
  "bbox": [
    7.963369,
    35.115734,
    7.963369,
    35.115734
  ],
  "description": "An ancient place, cited: BAtlas 34 F2 unnamed feature ()",
  "features": [
    {
      "type": "Feature",
      "geometry": {
        "type": "Point",
        "coordinates": [
          7.963369,
          35.115734
        ]
      },
      "properties": {
        "description": "representative point"
      }
    },
    {
      "geometry": {
        "type": "Point",
        "coordinates": [
          7.963369,
          35.115734
        ]
      },
      "id": "darmc-location-20605",
      "type": "Feature",
      "properties": {
        "description": "500K scale point location",
        "location_precision": "precise",
        "title": "DARMC location 20605",
        "link": "http://pleiades.stoa.org/places/208942556/darmc-location-20605"
      }
    }
  ]
}