{
  "type": "FeatureCollection",
  "title": "Untitled",
  "id": "208942498",
  "bbox": [
    9.125257,
    36.862144,
    9.125257,
    36.862144
  ],
  "description": "An ancient place, cited: BAtlas 32 D3 unnamed unlabeled ((2 monuments))",
  "features": [
    {
      "type": "Feature",
      "geometry": {
        "type": "Point",
        "coordinates": [
          9.125257,
          36.862144
        ]
      },
      "properties": {
        "description": "representative point"
      }
    },
    {
      "geometry": {
        "type": "Point",
        "coordinates": [
          9.125257,
          36.862144
        ]
      },
      "id": "darmc-location-26727",
      "type": "Feature",
      "properties": {
        "description": "500K scale point location",
        "location_precision": "precise",
        "title": "DARMC location 26727",
        "link": "http://pleiades.stoa.org/places/208942498/darmc-location-26727"
      }
    }
  ]
}