{
  "type": "FeatureCollection",
  "title": "Untitled",
  "id": "208942967",
  "bbox": [
    3.7162,
    35.491975,
    3.7162,
    35.491975
  ],
  "description": "An ancient place, cited: BAtlas 34 B2 unnamed feature ()",
  "features": [
    {
      "type": "Feature",
      "geometry": {
        "type": "Point",
        "coordinates": [
          3.7162,
          35.491975
        ]
      },
      "properties": {
        "description": "representative point"
      }
    },
    {
      "geometry": {
        "type": "Point",
        "coordinates": [
          3.7162,
          35.491975
        ]
      },
      "id": "darmc-location-33352",
      "type": "Feature",
      "properties": {
        "description": "representative point location digitized from the Barrington Atlas of the Greek and Roman World by the Digital Atlas of Roman and Medieval Civilizations project at Harvard University.",
        "location_precision": "precise",
        "title": "DARMC location 33352",
        "link": "http://pleiades.stoa.org/places/208942967/darmc-location-33352"
      }
    }
  ]
}