{
  "type": "FeatureCollection",
  "title": "Untitled",
  "id": "208942858",
  "description": "An ancient place, cited: BAtlas 31 H4 unnamed unlabeled (settlements)",
  "bbox": [
    7.796768,
    36.241053,
    7.796768,
    36.241053
  ],
  "reprPoint": [
    7.796768,
    36.241053
  ],
  "features": [
    {
      "geometry": {
        "type": "Point",
        "coordinates": [
          7.796768,
          36.241053
        ]
      },
      "id": "darmc-location-26679",
      "type": "Feature",
      "properties": {
        "description": "500K scale point location",
        "location_precision": "precise",
        "title": "DARMC location 26679",
        "link": "http://pleiades.stoa.org/places/208942858/darmc-location-26679"
      }
    }
  ]
}