{
  "type": "FeatureCollection",
  "title": "Untitled",
  "id": "208942171",
  "description": "An ancient place, cited: BAtlas 32 E3 unnamed unlabeled ((15 monuments))",
  "bbox": [
    9.580764,
    36.919468,
    9.580764,
    36.919468
  ],
  "reprPoint": [
    9.580764,
    36.919468
  ],
  "features": [
    {
      "geometry": {
        "type": "Point",
        "coordinates": [
          9.580764,
          36.919468
        ]
      },
      "id": "darmc-location-25736",
      "type": "Feature",
      "properties": {
        "description": "500K scale point location",
        "location_precision": "precise",
        "title": "DARMC location 25736",
        "link": "http://pleiades.stoa.org/places/208942171/darmc-location-25736"
      }
    }
  ]
}