{
  "type": "FeatureCollection",
  "title": "Untitled",
  "id": "208942463",
  "description": "An ancient place, cited: BAtlas 32 E2 unnamed unlabeled ((4 cemeteries))",
  "bbox": [
    9.539339,
    37.115175,
    9.539339,
    37.115175
  ],
  "reprPoint": [
    9.539339,
    37.115175
  ],
  "features": [
    {
      "geometry": {
        "type": "Point",
        "coordinates": [
          9.539339,
          37.115175
        ]
      },
      "id": "darmc-location-26743",
      "type": "Feature",
      "properties": {
        "description": "500K scale point location",
        "location_precision": "precise",
        "title": "DARMC location 26743",
        "link": "http://pleiades.stoa.org/places/208942463/darmc-location-26743"
      }
    }
  ]
}