{
  "type": "FeatureCollection",
  "title": "Untitled",
  "id": "208943617",
  "description": "An ancient place, cited: BAtlas 31 D4 unnamed unlabeled (settlements)",
  "bbox": [
    5.881615,
    36.436899,
    5.881615,
    36.436899
  ],
  "reprPoint": [
    5.881615,
    36.436899
  ],
  "features": [
    {
      "geometry": {
        "type": "Point",
        "coordinates": [
          5.881615,
          36.436899
        ]
      },
      "id": "darmc-location-20922",
      "type": "Feature",
      "properties": {
        "description": "500K scale point location",
        "location_precision": "precise",
        "title": "DARMC location 20922",
        "link": "http://pleiades.stoa.org/places/208943617/darmc-location-20922"
      }
    }
  ]
}