{
  "type": "FeatureCollection",
  "title": "Untitled",
  "id": "208942389",
  "description": "An ancient place, cited: BAtlas 32 D4 unnamed unlabeled ((7 monuments, 1 cemetery, 2 walls))",
  "bbox": [
    9.226096,
    36.184155,
    9.226096,
    36.184155
  ],
  "reprPoint": [
    9.226096,
    36.184155
  ],
  "features": [
    {
      "geometry": {
        "type": "Point",
        "coordinates": [
          9.226096,
          36.184155
        ]
      },
      "id": "darmc-location-15590",
      "type": "Feature",
      "properties": {
        "description": "500K scale point location",
        "location_precision": "precise",
        "title": "DARMC location 15590",
        "link": "http://pleiades.stoa.org/places/208942389/darmc-location-15590"
      }
    }
  ]
}