{
  "type": "FeatureCollection",
  "title": "Untitled",
  "id": "208942503",
  "description": "An ancient place, cited: BAtlas 32 D3 unnamed unlabeled ((2 monuments))",
  "bbox": [
    9.307148,
    36.955713,
    9.307148,
    36.955713
  ],
  "reprPoint": [
    9.307148,
    36.955713
  ],
  "features": [
    {
      "geometry": {
        "type": "Point",
        "coordinates": [
          9.307148,
          36.955713
        ]
      },
      "id": "darmc-location-26617",
      "type": "Feature",
      "properties": {
        "description": "500K scale point location",
        "location_precision": "precise",
        "title": "DARMC location 26617",
        "link": "http://pleiades.stoa.org/places/208942503/darmc-location-26617"
      }
    }
  ]
}