{
  "type": "FeatureCollection",
  "title": "Untitled",
  "id": "208943603",
  "bbox": [
    5.571372,
    36.036189,
    5.571372,
    36.036189
  ],
  "description": "An ancient place, cited: BAtlas 31 D4 unnamed unlabeled (settlements)",
  "features": [
    {
      "type": "Feature",
      "geometry": {
        "type": "Point",
        "coordinates": [
          5.571372,
          36.036189
        ]
      },
      "properties": {
        "description": "representative point"
      }
    },
    {
      "geometry": {
        "type": "Point",
        "coordinates": [
          5.571372,
          36.036189
        ]
      },
      "id": "darmc-location-20906",
      "type": "Feature",
      "properties": {
        "description": "500K scale point location",
        "location_precision": "precise",
        "title": "DARMC location 20906",
        "link": "http://pleiades.stoa.org/places/208943603/darmc-location-20906"
      }
    }
  ]
}