{
  "type": "FeatureCollection",
  "title": "Untitled",
  "id": "208943252",
  "description": "An ancient place, cited: BAtlas 32 F3 unnamed unlabeled ((1 monument))",
  "bbox": [
    10.150738,
    36.561496,
    10.150738,
    36.561496
  ],
  "reprPoint": [
    10.150738,
    36.561496
  ],
  "features": [
    {
      "geometry": {
        "type": "Point",
        "coordinates": [
          10.150738,
          36.561496
        ]
      },
      "id": "darmc-location-16015",
      "type": "Feature",
      "properties": {
        "description": "500K scale point location",
        "location_precision": "precise",
        "title": "DARMC location 16015",
        "link": "http://pleiades.stoa.org/places/208943252/darmc-location-16015"
      }
    }
  ]
}