{
  "type": "FeatureCollection",
  "title": "Untitled",
  "id": "208943590",
  "description": "An ancient place, cited: BAtlas 31 D4 unnamed unlabeled (settlements)",
  "bbox": [
    5.660522,
    36.27781,
    5.660522,
    36.27781
  ],
  "reprPoint": [
    5.660522,
    36.27781
  ],
  "features": [
    {
      "geometry": {
        "type": "Point",
        "coordinates": [
          5.660522,
          36.27781
        ]
      },
      "id": "darmc-location-20460",
      "type": "Feature",
      "properties": {
        "description": "500K scale point location",
        "location_precision": "precise",
        "title": "DARMC location 20460",
        "link": "http://pleiades.stoa.org/places/208943590/darmc-location-20460"
      }
    }
  ]
}