{
  "type": "FeatureCollection",
  "title": "Untitled",
  "id": "208943494",
  "description": "An ancient place, cited: BAtlas 33 D2 unnamed unlabeled ((5 monuments))",
  "bbox": [
    9.298794,
    35.094653,
    9.298794,
    35.094653
  ],
  "reprPoint": [
    9.298794,
    35.094653
  ],
  "features": [
    {
      "geometry": {
        "type": "Point",
        "coordinates": [
          9.298794,
          35.094653
        ]
      },
      "id": "darmc-location-27260",
      "type": "Feature",
      "properties": {
        "description": "500K scale point location",
        "location_precision": "precise",
        "title": "DARMC location 27260",
        "link": "http://pleiades.stoa.org/places/208943494/darmc-location-27260"
      }
    }
  ]
}