{
  "type": "FeatureCollection",
  "title": "Untitled",
  "id": "208942732",
  "bbox": [
    5.393978,
    34.721037,
    5.393978,
    34.721037
  ],
  "description": "An ancient place, cited: BAtlas 34 D3 unnamed feature ()",
  "features": [
    {
      "type": "Feature",
      "geometry": {
        "type": "Point",
        "coordinates": [
          5.393978,
          34.721037
        ]
      },
      "properties": {
        "description": "representative point"
      }
    },
    {
      "geometry": {
        "type": "Point",
        "coordinates": [
          5.393978,
          34.721037
        ]
      },
      "id": "darmc-location-33339",
      "type": "Feature",
      "properties": {
        "description": "representative point location digitized from the Barrington Atlas of the Greek and Roman World by the Digital Atlas of Roman and Medieval Civilizations project at Harvard University.",
        "location_precision": "precise",
        "title": "DARMC location 33339",
        "link": "http://pleiades.stoa.org/places/208942732/darmc-location-33339"
      }
    }
  ]
}