{
  "type": "FeatureCollection",
  "title": "Untitled",
  "id": "208943509",
  "description": "An ancient place, cited: BAtlas 33 D2 unnamed unlabeled ((5 monuments))",
  "bbox": [
    9.278083,
    35.196716,
    9.278083,
    35.196716
  ],
  "reprPoint": [
    9.278083,
    35.196716
  ],
  "features": [
    {
      "geometry": {
        "type": "Point",
        "coordinates": [
          9.278083,
          35.196716
        ]
      },
      "id": "darmc-location-27262",
      "type": "Feature",
      "properties": {
        "description": "500K scale point location",
        "location_precision": "precise",
        "title": "DARMC location 27262",
        "link": "http://pleiades.stoa.org/places/208943509/darmc-location-27262"
      }
    }
  ]
}