{
  "type": "FeatureCollection",
  "title": "Untitled",
  "id": "208943460",
  "description": "An ancient place, cited: BAtlas 33 B3 unnamed unlabeled ((1 monument))",
  "bbox": [
    8.279334,
    34.731594,
    8.279334,
    34.731594
  ],
  "reprPoint": [
    8.279334,
    34.731594
  ],
  "features": [
    {
      "geometry": {
        "type": "Point",
        "coordinates": [
          8.279334,
          34.731594
        ]
      },
      "id": "darmc-location-27145",
      "type": "Feature",
      "properties": {
        "description": "500K scale point location",
        "location_precision": "precise",
        "title": "DARMC location 27145",
        "link": "http://pleiades.stoa.org/places/208943460/darmc-location-27145"
      }
    }
  ]
}