{
  "type": "FeatureCollection",
  "title": "Untitled",
  "id": "208943707",
  "description": "An ancient place, cited: BAtlas 33 F3 unnamed unlabeled ((6 monuments, 1 wall, 1 aqueduct))",
  "bbox": [
    10.082704,
    34.659149,
    10.082704,
    34.659149
  ],
  "reprPoint": [
    10.082704,
    34.659149
  ],
  "features": [
    {
      "geometry": {
        "type": "Point",
        "coordinates": [
          10.082704,
          34.659149
        ]
      },
      "id": "darmc-location-25825",
      "type": "Feature",
      "properties": {
        "description": "500K scale point location",
        "location_precision": "precise",
        "title": "DARMC location 25825",
        "link": "http://pleiades.stoa.org/places/208943707/darmc-location-25825"
      }
    }
  ]
}