{
  "type": "FeatureCollection",
  "title": "Untitled",
  "id": "208943158",
  "description": "An ancient place, cited: BAtlas 34 D2 unnamed feature ()",
  "bbox": [
    5.385276,
    35.500688,
    5.385276,
    35.500688
  ],
  "reprPoint": [
    5.385276,
    35.500688
  ],
  "features": [
    {
      "geometry": {
        "type": "Point",
        "coordinates": [
          5.385276,
          35.500688
        ]
      },
      "id": "darmc-location-19401",
      "type": "Feature",
      "properties": {
        "description": "500K scale point location",
        "location_precision": "precise",
        "title": "DARMC location 19401",
        "link": "http://pleiades.stoa.org/places/208943158/darmc-location-19401"
      }
    }
  ]
}