{
  "type": "FeatureCollection",
  "title": "Untitled",
  "id": "208942853",
  "bbox": [
    7.958285,
    36.270384,
    7.958285,
    36.270384
  ],
  "description": "An ancient place, cited: BAtlas 31 H4 unnamed unlabeled (settlements)",
  "features": [
    {
      "type": "Feature",
      "geometry": {
        "type": "Point",
        "coordinates": [
          7.958285,
          36.270384
        ]
      },
      "properties": {
        "description": "representative point"
      }
    },
    {
      "geometry": {
        "type": "Point",
        "coordinates": [
          7.958285,
          36.270384
        ]
      },
      "id": "darmc-location-15704",
      "type": "Feature",
      "properties": {
        "description": "500K scale point location",
        "location_precision": "precise",
        "title": "DARMC location 15704",
        "link": "http://pleiades.stoa.org/places/208942853/darmc-location-15704"
      }
    }
  ]
}