{
  "type": "FeatureCollection",
  "title": "Untitled",
  "id": "208942218",
  "bbox": [
    9.948515,
    36.436293,
    9.948515,
    36.436293
  ],
  "description": "An ancient place, cited: BAtlas 32 E4 unnamed unlabeled ((15 monuments, 2 walls))",
  "features": [
    {
      "type": "Feature",
      "geometry": {
        "type": "Point",
        "coordinates": [
          9.948515,
          36.436293
        ]
      },
      "properties": {
        "description": "representative point"
      }
    },
    {
      "geometry": {
        "type": "Point",
        "coordinates": [
          9.948515,
          36.436293
        ]
      },
      "id": "darmc-location-25747",
      "type": "Feature",
      "properties": {
        "description": "500K scale point location",
        "location_precision": "precise",
        "title": "DARMC location 25747",
        "link": "http://pleiades.stoa.org/places/208942218/darmc-location-25747"
      }
    }
  ]
}