{
  "type": "FeatureCollection",
  "title": "Untitled",
  "id": "208942960",
  "bbox": [
    3.620068,
    35.863108,
    3.620068,
    35.863108
  ],
  "description": "An ancient place, cited: BAtlas 34 B2 unnamed feature ()",
  "features": [
    {
      "type": "Feature",
      "geometry": {
        "type": "Point",
        "coordinates": [
          3.620068,
          35.863108
        ]
      },
      "properties": {
        "description": "representative point"
      }
    },
    {
      "geometry": {
        "type": "Point",
        "coordinates": [
          3.620068,
          35.863108
        ]
      },
      "id": "darmc-location-19365",
      "type": "Feature",
      "properties": {
        "description": "500K scale point location",
        "location_precision": "precise",
        "title": "DARMC location 19365",
        "link": "http://pleiades.stoa.org/places/208942960/darmc-location-19365"
      }
    }
  ]
}