{
  "type": "FeatureCollection",
  "title": "Untitled",
  "id": "208942446",
  "description": "An ancient place, cited: BAtlas 32 E2 unnamed unlabeled ((4 cemeteries))",
  "bbox": [
    9.758448,
    37.325099,
    9.758448,
    37.325099
  ],
  "reprPoint": [
    9.758448,
    37.325099
  ],
  "features": [
    {
      "geometry": {
        "type": "Point",
        "coordinates": [
          9.758448,
          37.325099
        ]
      },
      "id": "darmc-location-26738",
      "type": "Feature",
      "properties": {
        "description": "500K scale point location",
        "location_precision": "precise",
        "title": "DARMC location 26738",
        "link": "http://pleiades.stoa.org/places/208942446/darmc-location-26738"
      }
    }
  ]
}