{
  "type": "FeatureCollection",
  "title": "Untitled",
  "id": "208943749",
  "description": "An ancient place, cited: BAtlas 33 H2 unnamed unlabeled ((4 cemeteries))",
  "bbox": [
    11.026676,
    35.222754,
    11.026676,
    35.222754
  ],
  "reprPoint": [
    11.026676,
    35.222754
  ],
  "features": [
    {
      "geometry": {
        "type": "Point",
        "coordinates": [
          11.026676,
          35.222754
        ]
      },
      "id": "darmc-location-27330",
      "type": "Feature",
      "properties": {
        "description": "500K scale point location",
        "location_precision": "precise",
        "title": "DARMC location 27330",
        "link": "http://pleiades.stoa.org/places/208943749/darmc-location-27330"
      }
    }
  ]
}