{
  "type": "FeatureCollection",
  "title": "Untitled",
  "id": "208942386",
  "description": "An ancient place, cited: BAtlas 32 D4 unnamed unlabeled ((7 monuments, 1 cemetery, 2 walls))",
  "bbox": [
    9.219678,
    36.014267,
    9.219678,
    36.014267
  ],
  "reprPoint": [
    9.219678,
    36.014267
  ],
  "features": [
    {
      "geometry": {
        "type": "Point",
        "coordinates": [
          9.219678,
          36.014267
        ]
      },
      "id": "darmc-location-25726",
      "type": "Feature",
      "properties": {
        "description": "500K scale point location",
        "location_precision": "precise",
        "title": "DARMC location 25726",
        "link": "http://pleiades.stoa.org/places/208942386/darmc-location-25726"
      }
    }
  ]
}