{
  "type": "FeatureCollection",
  "title": "Untitled",
  "id": "208942452",
  "description": "An ancient place, cited: BAtlas 32 E2 unnamed unlabeled ((4 cemeteries))",
  "bbox": [
    9.706948,
    37.277694,
    9.706948,
    37.277694
  ],
  "reprPoint": [
    9.706948,
    37.277694
  ],
  "features": [
    {
      "geometry": {
        "type": "Point",
        "coordinates": [
          9.706948,
          37.277694
        ]
      },
      "id": "darmc-location-15859",
      "type": "Feature",
      "properties": {
        "description": "500K scale point location",
        "location_precision": "precise",
        "title": "DARMC location 15859",
        "link": "http://pleiades.stoa.org/places/208942452/darmc-location-15859"
      }
    }
  ]
}