{
  "type": "FeatureCollection",
  "title": "Untitled",
  "id": "208942930",
  "description": "An ancient place, cited: BAtlas 31 G3 unnamed unlabeled (settlements)",
  "bbox": [
    7.445116,
    36.57198,
    7.445116,
    36.57198
  ],
  "reprPoint": [
    7.445116,
    36.57198
  ],
  "features": [
    {
      "geometry": {
        "type": "Point",
        "coordinates": [
          7.445116,
          36.57198
        ]
      },
      "id": "darmc-location-16988",
      "type": "Feature",
      "properties": {
        "description": "500K scale point location",
        "location_precision": "precise",
        "title": "DARMC location 16988",
        "link": "http://pleiades.stoa.org/places/208942930/darmc-location-16988"
      }
    }
  ]
}