{
  "type": "FeatureCollection",
  "title": "Untitled",
  "id": "208942863",
  "description": "An ancient place, cited: BAtlas 31 H4 unnamed unlabeled (settlements)",
  "bbox": [
    7.636826,
    36.049578,
    7.636826,
    36.049578
  ],
  "reprPoint": [
    7.636826,
    36.049578
  ],
  "features": [
    {
      "geometry": {
        "type": "Point",
        "coordinates": [
          7.636826,
          36.049578
        ]
      },
      "id": "darmc-location-21052",
      "type": "Feature",
      "properties": {
        "description": "500K scale point location",
        "location_precision": "precise",
        "title": "DARMC location 21052",
        "link": "http://pleiades.stoa.org/places/208942863/darmc-location-21052"
      }
    }
  ]
}