{
  "type": "FeatureCollection",
  "title": "Untitled",
  "id": "208942256",
  "description": "An ancient place, cited: BAtlas 32 E4 unnamed unlabeled ((15 monuments, 2 walls))",
  "bbox": [
    9.776207,
    36.469894,
    9.776207,
    36.469894
  ],
  "reprPoint": [
    9.776207,
    36.469894
  ],
  "features": [
    {
      "geometry": {
        "type": "Point",
        "coordinates": [
          9.776207,
          36.469894
        ]
      },
      "id": "darmc-location-26770",
      "type": "Feature",
      "properties": {
        "description": "500K scale point location",
        "location_precision": "precise",
        "title": "DARMC location 26770",
        "link": "http://pleiades.stoa.org/places/208942256/darmc-location-26770"
      }
    }
  ]
}