{
  "type": "FeatureCollection",
  "title": "Untitled",
  "id": "208943023",
  "description": "An ancient place, cited: BAtlas 33 G2 unnamed unlabeled ((3 monuments, 1 bath))",
  "bbox": [
    10.872455,
    35.26454,
    10.872455,
    35.26454
  ],
  "reprPoint": [
    10.872455,
    35.26454
  ],
  "features": [
    {
      "geometry": {
        "type": "Point",
        "coordinates": [
          10.872455,
          35.26454
        ]
      },
      "id": "darmc-location-27325",
      "type": "Feature",
      "properties": {
        "description": "500K scale point location",
        "location_precision": "precise",
        "title": "DARMC location 27325",
        "link": "http://pleiades.stoa.org/places/208943023/darmc-location-27325"
      }
    }
  ]
}