{
  "type": "FeatureCollection",
  "title": "Untitled",
  "id": "208942600",
  "bbox": [
    7.424687,
    35.151436,
    7.424687,
    35.151436
  ],
  "description": "An ancient place, cited: BAtlas 34 F2 unnamed feature ()",
  "features": [
    {
      "type": "Feature",
      "geometry": {
        "type": "Point",
        "coordinates": [
          7.424687,
          35.151436
        ]
      },
      "properties": {
        "description": "representative point"
      }
    },
    {
      "geometry": {
        "type": "Point",
        "coordinates": [
          7.424687,
          35.151436
        ]
      },
      "id": "darmc-location-20627",
      "type": "Feature",
      "properties": {
        "description": "500K scale point location",
        "location_precision": "precise",
        "title": "DARMC location 20627",
        "link": "http://pleiades.stoa.org/places/208942600/darmc-location-20627"
      }
    }
  ]
}