{
  "type": "FeatureCollection",
  "title": "Untitled",
  "id": "208942564",
  "description": "An ancient place, cited: BAtlas 34 F2 unnamed feature ()",
  "bbox": [
    7.602155,
    35.488668,
    7.602155,
    35.488668
  ],
  "reprPoint": [
    7.602155,
    35.488668
  ],
  "features": [
    {
      "geometry": {
        "type": "Point",
        "coordinates": [
          7.602155,
          35.488668
        ]
      },
      "id": "darmc-location-20593",
      "type": "Feature",
      "properties": {
        "description": "500K scale point location",
        "location_precision": "precise",
        "title": "DARMC location 20593",
        "link": "http://pleiades.stoa.org/places/208942564/darmc-location-20593"
      }
    }
  ]
}