{
  "type": "FeatureCollection",
  "title": "Untitled",
  "id": "208943453",
  "description": "An ancient place, cited: BAtlas 56 F5 unnamed tumulus (E Boukolion)",
  "bbox": [
    27.718104,
    38.474088,
    27.718104,
    38.474088
  ],
  "reprPoint": [
    27.718104,
    38.474088
  ],
  "features": [
    {
      "geometry": {
        "type": "Point",
        "coordinates": [
          27.718104,
          38.474088
        ]
      },
      "id": "darmc-location-33055",
      "type": "Feature",
      "properties": {
        "description": "scale point location",
        "location_precision": "precise",
        "title": "DARMC location 33055",
        "link": "http://pleiades.stoa.org/places/208943453/darmc-location-33055"
      }
    }
  ]
}