{
  "type": "FeatureCollection",
  "title": "Untitled",
  "id": "208942618",
  "description": "An ancient place, cited: BAtlas 34 F2 unnamed feature ()",
  "bbox": [
    7.49911,
    35.693123,
    7.49911,
    35.693123
  ],
  "reprPoint": [
    7.49911,
    35.693123
  ],
  "features": [
    {
      "geometry": {
        "type": "Point",
        "coordinates": [
          7.49911,
          35.693123
        ]
      },
      "id": "darmc-location-19461",
      "type": "Feature",
      "properties": {
        "description": "500K scale point location",
        "location_precision": "precise",
        "title": "DARMC location 19461",
        "link": "http://pleiades.stoa.org/places/208942618/darmc-location-19461"
      }
    }
  ]
}