{
  "type": "FeatureCollection",
  "title": "Untitled",
  "id": "208943038",
  "bbox": [
    9.643962,
    35.313572,
    9.643962,
    35.313572
  ],
  "description": "An ancient place, cited: BAtlas 33 E2 unnamed unlabeled ((5 aqueducts, 1 monument))",
  "features": [
    {
      "type": "Feature",
      "geometry": {
        "type": "Point",
        "coordinates": [
          9.643962,
          35.313572
        ]
      },
      "properties": {
        "description": "representative point"
      }
    },
    {
      "geometry": {
        "type": "Point",
        "coordinates": [
          9.643962,
          35.313572
        ]
      },
      "id": "darmc-location-27285",
      "type": "Feature",
      "properties": {
        "description": "500K scale point location",
        "location_precision": "precise",
        "title": "DARMC location 27285",
        "link": "http://pleiades.stoa.org/places/208943038/darmc-location-27285"
      }
    }
  ]
}