{
  "type": "FeatureCollection",
  "title": "Untitled",
  "id": "208942909",
  "bbox": [
    7.772595,
    36.810833,
    7.772595,
    36.810833
  ],
  "description": "An ancient place, cited: BAtlas 31 H3 unnamed unlabeled (settlements)",
  "features": [
    {
      "type": "Feature",
      "geometry": {
        "type": "Point",
        "coordinates": [
          7.772595,
          36.810833
        ]
      },
      "properties": {
        "description": "representative point"
      }
    },
    {
      "geometry": {
        "type": "Point",
        "coordinates": [
          7.772595,
          36.810833
        ]
      },
      "id": "darmc-location-21060",
      "type": "Feature",
      "properties": {
        "description": "500K scale point location",
        "location_precision": "precise",
        "title": "DARMC location 21060",
        "link": "http://pleiades.stoa.org/places/208942909/darmc-location-21060"
      }
    }
  ]
}