{
  "type": "FeatureCollection",
  "title": "Roecliffe Fort",
  "id": "209534779",
  "bbox": [
    -1.409909,
    54.092747,
    -1.409909,
    54.092747
  ],
  "description": "The site of a Roman fort and an adjacent settlement is located on a terrace south of the River Ure to the west of Boroughbridge. The Roman fort was identified via geophysical survey and test excavations.",
  "connectsWith": [
    "89209"
  ],
  "features": [
    {
      "type": "Feature",
      "geometry": {
        "type": "Point",
        "coordinates": [
          -1.409909,
          54.092747
        ]
      },
      "properties": {
        "description": "representative point"
      }
    },
    {
      "geometry": {
        "type": "Point",
        "coordinates": [
          -1.409909,
          54.092747
        ]
      },
      "id": "vici-org-location-of-roecliffe-fort",
      "type": "Feature",
      "properties": {
        "description": null,
        "location_precision": "precise",
        "title": "vici.org location of Roecliffe Fort",
        "link": "http://pleiades.stoa.org/places/209534779/vici-org-location-of-roecliffe-fort"
      }
    }
  ]
}