{
  "type": "FeatureCollection",
  "title": "Mangadu Megalithic Site",
  "id": "210176087",
  "bbox": [
    76.622222,
    8.911111,
    76.622222,
    8.911111
  ],
  "description": "An archaeological site with Iron Age funerary megaliths located in the vicinity of the modern Moonamkutty-Mangad Road in the northeastern portion of India's Kollam municipality. The site was damaged by cashewnut tree farming and is now not visible due to habitation on the site.",
  "features": [
    {
      "type": "Feature",
      "geometry": {
        "type": "Point",
        "coordinates": [
          76.622222,
          8.911111
        ]
      },
      "properties": {
        "description": "representative point"
      }
    },
    {
      "geometry": {
        "type": "Point",
        "coordinates": [
          76.622222,
          8.911111
        ]
      },
      "id": "approximate-imagery-location-of-mangadu",
      "type": "Feature",
      "properties": {
        "description": "Approximate imagery location based on Google Earth representing Mangadu after Satyamurthy 1992.",
        "location_precision": "precise",
        "title": "Approximate imagery location of Mangadu",
        "link": "http://pleiades.stoa.org/places/210176087/approximate-imagery-location-of-mangadu"
      }
    }
  ]
}