{
  "type": "FeatureCollection",
  "title": "Withdrawn: Tellaro Roman villa",
  "id": "215496319",
  "description": "This place resource is a duplicate for http://pleiades.stoa.org/places/462122 and was erroneously created and published. It has been withdrawn and moved to errata.",
  "bbox": [
    15.0784713,
    36.8359248,
    15.0784713,
    36.8359248
  ],
  "reprPoint": [
    15.0784713,
    36.8359248
  ],
  "features": [
    {
      "geometry": {
        "type": "Point",
        "coordinates": [
          15.0784713,
          36.8359248
        ]
      },
      "id": "location-of-tellaro-roman-villa",
      "type": "Feature",
      "properties": {
        "description": "Location based on OpenStreetMap",
        "location_precision": "precise",
        "title": "location of Tellaro Roman villa",
        "link": "http://pleiades.stoa.org/errata/215496319/location-of-tellaro-roman-villa"
      }
    }
  ]
}