{
  "type": "FeatureCollection",
  "title": "Altar at the temple of Amphiaraos",
  "id": "215521453",
  "bbox": [
    23.84525,
    38.290694,
    23.84525,
    38.290694
  ],
  "description": "An altar located to the east of the temple of Amphiaraos.",
  "connectsWith": [
    "540628"
  ],
  "features": [
    {
      "type": "Feature",
      "geometry": {
        "type": "Point",
        "coordinates": [
          23.84525,
          38.290694
        ]
      },
      "properties": {
        "description": "representative point"
      }
    },
    {
      "geometry": {
        "type": "Point",
        "coordinates": [
          23.84525,
          38.290694
        ]
      },
      "id": "altar-at-the-temple-of-amphiaraos",
      "type": "Feature",
      "properties": {
        "description": "Altar to the east of the temple of Amphiaraos",
        "location_precision": "precise",
        "title": "Altar at the temple of Amphiaraos",
        "link": "http://pleiades.stoa.org/places/215521453/altar-at-the-temple-of-amphiaraos"
      }
    }
  ]
}