{
  "type": "FeatureCollection",
  "title": "Anchialus",
  "id": "216702",
  "bbox": [
    27.641374,
    42.555937,
    27.641374,
    42.555937
  ],
  "description": "An ancient place, cited: BAtlas 22 E6 Anchialus",
  "connectsWith": [
    "220489"
  ],
  "names": [
    "Anchialus"
  ],
  "features": [
    {
      "type": "Feature",
      "geometry": {
        "type": "Point",
        "coordinates": [
          27.641374,
          42.555937
        ]
      },
      "properties": {
        "description": "representative point"
      }
    },
    {
      "geometry": {
        "type": "Point",
        "coordinates": [
          27.641374,
          42.555937
        ]
      },
      "id": "darmc-location-24566",
      "type": "Feature",
      "properties": {
        "description": "1M scale point location",
        "location_precision": "precise",
        "title": "DARMC location 24566",
        "link": "http://pleiades.stoa.org/places/216702/darmc-location-24566"
      }
    }
  ]
}