{
  "type": "FeatureCollection",
  "title": "Dionysopolis/Krounoi",
  "id": "216793",
  "bbox": [
    28.162771,
    43.409932,
    28.163044,
    43.42563
  ],
  "description": "An ancient place, cited: BAtlas 22 F5 Dionysopolis/Krounoi",
  "connectsWith": [
    "220489"
  ],
  "names": [
    "Dionysopolis",
    "Krounoi"
  ],
  "features": [
    {
      "type": "Feature",
      "geometry": {
        "type": "Point",
        "coordinates": [
          28.1629075,
          43.417781
        ]
      },
      "properties": {
        "description": "representative point"
      }
    },
    {
      "geometry": {
        "type": "Point",
        "coordinates": [
          28.162771,
          43.42563
        ]
      },
      "id": "darmc-location-24623",
      "type": "Feature",
      "properties": {
        "description": "1M scale point location",
        "location_precision": "precise",
        "title": "DARMC location 24623",
        "link": "http://pleiades.stoa.org/places/216793/darmc-location-24623"
      }
    },
    {
      "geometry": {
        "type": "Point",
        "coordinates": [
          28.163044,
          43.409932
        ]
      },
      "id": "dare-location",
      "type": "Feature",
      "properties": {
        "description": "Representative point location, site precision",
        "location_precision": "precise",
        "title": "DARE Location",
        "link": "http://pleiades.stoa.org/places/216793/dare-location"
      }
    }
  ]
}