{
  "type": "FeatureCollection",
  "title": "Appiaria",
  "id": "216707",
  "description": "An ancient place, cited: BAtlas 22 D5 Appiaria",
  "bbox": [
    26.245621,
    43.987675,
    26.245621,
    43.987675
  ],
  "reprPoint": [
    26.245621,
    43.987675
  ],
  "names": [
    "Appiaria",
    "Appiarienses"
  ],
  "features": [
    {
      "geometry": {
        "type": "Point",
        "coordinates": [
          26.245621,
          43.987675
        ]
      },
      "id": "darmc-location-24208",
      "type": "Feature",
      "properties": {
        "description": "1M scale point location",
        "location_precision": "precise",
        "title": "DARMC location 24208",
        "link": "http://pleiades.stoa.org/places/216707/darmc-location-24208"
      }
    }
  ]
}