{
  "type": "FeatureCollection",
  "title": "Dinogetia",
  "id": "216791",
  "description": "Dinogetia, a Roman castrum located in the province of Moesia.",
  "bbox": [
    28.181768,
    45.378218,
    28.181768,
    45.378218
  ],
  "reprPoint": [
    28.181768,
    45.378218
  ],
  "names": [
    "Dinogetia"
  ],
  "features": [
    {
      "geometry": {
        "type": "Point",
        "coordinates": [
          28.181768,
          45.378218
        ]
      },
      "id": "dare-location",
      "type": "Feature",
      "properties": {
        "description": "Representative point location, site precision",
        "location_precision": "precise",
        "title": "DARE Location",
        "link": "http://pleiades.stoa.org/places/216791/dare-location"
      }
    }
  ]
}