{
  "type": "FeatureCollection",
  "title": "Buridava Roman Fort and Vicus",
  "id": "216741",
  "bbox": [
    24.298549,
    45.034038,
    24.304173,
    45.038197
  ],
  "description": "A Roman fort and associated structures at modern Stolniceni, Romania. An indigenous settlement was likely located a few kilometers to the north.",
  "connectsWith": [
    "725888431"
  ],
  "names": [
    "Stolniceni",
    "Buridava",
    "Buridavenses"
  ],
  "features": [
    {
      "type": "Feature",
      "geometry": {
        "type": "Point",
        "coordinates": [
          24.301361,
          45.0361175
        ]
      },
      "properties": {
        "description": "representative point"
      }
    },
    {
      "geometry": {
        "type": "Point",
        "coordinates": [
          24.304173,
          45.034038
        ]
      },
      "id": "imagery-location-of-excavated-bathhouse",
      "type": "Feature",
      "properties": {
        "description": "Location determined in Google Earth using imagery labeled \"2023 Maxar Technologies\" with reference to figures 17.3-17.7 on pages 62-65 of Țentea 2021.",
        "location_precision": "precise",
        "title": "Imagery Location of excavated bathhouse",
        "link": "http://pleiades.stoa.org/places/216741/imagery-location-of-excavated-bathhouse"
      }
    },
    {
      "geometry": {
        "type": "Point",
        "coordinates": [
          24.298549,
          45.038197
        ]
      },
      "id": "approximate-imagery-location-of-fortification",
      "type": "Feature",
      "properties": {
        "description": "Location determined in Google Earth against imagery against historical (2012) imagery with reference to crop marks visible in 1966 Corona satellite photograph published as figure 17.2 on page 62 of Țentea 2021.",
        "location_precision": "precise",
        "title": "Approximate imagery location of fortification",
        "link": "http://pleiades.stoa.org/places/216741/approximate-imagery-location-of-fortification"
      }
    }
  ]
}