{
  "type": "FeatureCollection",
  "title": "Capidava",
  "id": "216748",
  "description": "An ancient place, cited: BAtlas 22 F4 Capidava",
  "bbox": [
    28.090266,
    44.493688,
    28.090376,
    44.49379
  ],
  "reprPoint": [
    28.090321,
    44.493739
  ],
  "names": [
    "Capidava"
  ],
  "features": [
    {
      "geometry": {
        "type": "Point",
        "coordinates": [
          28.090266,
          44.493688
        ]
      },
      "id": "darmc-location-23950",
      "type": "Feature",
      "properties": {
        "description": "1M scale point location",
        "location_precision": "precise",
        "title": "DARMC location 23950",
        "link": "http://pleiades.stoa.org/places/216748/darmc-location-23950"
      }
    },
    {
      "geometry": {
        "type": "Point",
        "coordinates": [
          28.090376,
          44.49379
        ]
      },
      "id": "dare-location",
      "type": "Feature",
      "properties": {
        "description": "Representative point location, site precision",
        "location_precision": "precise",
        "title": "DARE Location",
        "link": "http://pleiades.stoa.org/places/216748/dare-location"
      }
    }
  ]
}