{
  "type": "FeatureCollection",
  "title": "Buridava",
  "id": "216741",
  "bbox": [
    24.301708,
    45.019209,
    24.360676,
    45.105944
  ],
  "description": "An ancient place, cited: BAtlas 22 B3 Buridava",
  "names": [
    "Buridava",
    "Buridavenses"
  ],
  "features": [
    {
      "type": "Feature",
      "geometry": {
        "type": "Point",
        "coordinates": [
          24.331192,
          45.0625765
        ]
      },
      "properties": {
        "description": "representative point"
      }
    },
    {
      "geometry": {
        "type": "Point",
        "coordinates": [
          24.301708,
          45.019209
        ]
      },
      "id": "darmc-location-7482",
      "type": "Feature",
      "properties": {
        "description": "1M scale point location",
        "location_precision": "precise",
        "title": "DARMC location 7482",
        "link": "http://pleiades.stoa.org/places/216741/darmc-location-7482"
      }
    },
    {
      "geometry": {
        "type": "Point",
        "coordinates": [
          24.360676,
          45.105944
        ]
      },
      "id": "dare-location",
      "type": "Feature",
      "properties": {
        "description": "Representative point location, site precision",
        "location_precision": "precise",
        "title": "DARE Location",
        "link": "http://pleiades.stoa.org/places/216741/dare-location"
      }
    }
  ]
}