{
  "type": "FeatureCollection",
  "title": "Diocletianopolis",
  "id": "216792",
  "description": "An ancient place, cited: BAtlas 22 B6 Diocletianopolis",
  "bbox": [
    24.705119,
    42.499957,
    24.710314,
    42.506479
  ],
  "reprPoint": [
    24.7077165,
    42.503218
  ],
  "names": [
    "Diocletianopolis"
  ],
  "features": [
    {
      "geometry": {
        "type": "Point",
        "coordinates": [
          24.710314,
          42.506479
        ]
      },
      "id": "darmc-location-24622",
      "type": "Feature",
      "properties": {
        "description": "1M scale point location",
        "location_precision": "precise",
        "title": "DARMC location 24622",
        "link": "http://pleiades.stoa.org/places/216792/darmc-location-24622"
      }
    },
    {
      "geometry": {
        "type": "Point",
        "coordinates": [
          24.705119,
          42.499957
        ]
      },
      "id": "dare-location",
      "type": "Feature",
      "properties": {
        "description": "Representative point location, site precision",
        "location_precision": "precise",
        "title": "DARE Location",
        "link": "http://pleiades.stoa.org/places/216792/dare-location"
      }
    }
  ]
}