{
  "type": "FeatureCollection",
  "title": "Dervent",
  "id": "216787",
  "bbox": [
    27.449758,
    44.133248,
    27.449758,
    44.133248
  ],
  "description": "An ancient place, cited: BAtlas 22 E4 Dervent",
  "features": [
    {
      "type": "Feature",
      "geometry": {
        "type": "Point",
        "coordinates": [
          27.449758,
          44.133248
        ]
      },
      "properties": {
        "description": "representative point"
      }
    },
    {
      "geometry": {
        "type": "Point",
        "coordinates": [
          27.449758,
          44.133248
        ]
      },
      "id": "darmc-location-24330",
      "type": "Feature",
      "properties": {
        "description": "1M scale point location",
        "location_precision": "precise",
        "title": "DARMC location 24330",
        "link": "http://pleiades.stoa.org/places/216787/darmc-location-24330"
      }
    }
  ]
}