{
  "type": "FeatureCollection",
  "title": "Callatis",
  "id": "216744",
  "bbox": [
    28.58275,
    43.817152,
    28.58275,
    43.817152
  ],
  "description": "An ancient place, cited: BAtlas 22 F5 Callatis",
  "connectsWith": [
    "220489"
  ],
  "names": [
    "Callatis"
  ],
  "features": [
    {
      "type": "Feature",
      "geometry": {
        "type": "Point",
        "coordinates": [
          28.58275,
          43.817152
        ]
      },
      "properties": {
        "description": "representative point"
      }
    },
    {
      "geometry": {
        "type": "Point",
        "coordinates": [
          28.58275,
          43.817152
        ]
      },
      "id": "darmc-location-24605",
      "type": "Feature",
      "properties": {
        "description": "1M scale point location",
        "location_precision": "precise",
        "title": "DARMC location 24605",
        "link": "http://pleiades.stoa.org/places/216744/darmc-location-24605"
      }
    }
  ]
}