{
  "type": "FeatureCollection",
  "title": "Angustia?",
  "id": "216703",
  "description": "An ancient place, cited: BAtlas 22 D2 Angustia?",
  "bbox": [
    26.303834,
    46.041741,
    26.303834,
    46.041741
  ],
  "reprPoint": [
    26.303834,
    46.041741
  ],
  "names": [
    "Angustia"
  ],
  "features": [
    {
      "geometry": {
        "type": "Point",
        "coordinates": [
          26.303834,
          46.041741
        ]
      },
      "id": "darmc-location-24207",
      "type": "Feature",
      "properties": {
        "description": "1M scale point location",
        "location_precision": "precise",
        "title": "DARMC location 24207",
        "link": "http://pleiades.stoa.org/places/216703/darmc-location-24207"
      }
    }
  ]
}