{
  "type": "FeatureCollection",
  "title": "Arubium",
  "id": "216712",
  "bbox": [
    28.1270759,
    45.2393598,
    28.137099,
    45.253041
  ],
  "description": "An ancient place, cited: BAtlas 22 F3 Arubium",
  "names": [
    "Arubium"
  ],
  "features": [
    {
      "type": "Feature",
      "geometry": {
        "type": "Point",
        "coordinates": [
          28.13208745,
          45.2462004
        ]
      },
      "properties": {
        "description": "representative point"
      }
    },
    {
      "geometry": {
        "type": "Point",
        "coordinates": [
          28.137099,
          45.253041
        ]
      },
      "id": "darmc-location-23928",
      "type": "Feature",
      "properties": {
        "description": "1M scale point location",
        "location_precision": "precise",
        "title": "DARMC location 23928",
        "link": "http://pleiades.stoa.org/places/216712/darmc-location-23928"
      }
    },
    {
      "geometry": {
        "type": "Point",
        "coordinates": [
          28.1270759,
          45.2393598
        ]
      },
      "id": "location-of-arrubium",
      "type": "Feature",
      "properties": {
        "description": "Representative location based on OpenStreetMap.",
        "location_precision": "precise",
        "title": "OSM location of Arrubium",
        "link": "http://pleiades.stoa.org/places/216712/location-of-arrubium"
      }
    }
  ]
}