{
  "type": "FeatureCollection",
  "title": "Dăeni",
  "id": "216783",
  "description": "An ancient place, cited: BAtlas 22 F4 Dăeni",
  "bbox": [
    28.134271,
    44.85318,
    28.134271,
    44.85318
  ],
  "reprPoint": [
    28.134271,
    44.85318
  ],
  "features": [
    {
      "geometry": {
        "type": "Point",
        "coordinates": [
          28.134271,
          44.85318
        ]
      },
      "id": "darmc-location-23930",
      "type": "Feature",
      "properties": {
        "description": "1M scale point location",
        "location_precision": "precise",
        "title": "DARMC location 23930",
        "link": "http://pleiades.stoa.org/places/216783/darmc-location-23930"
      }
    }
  ]
}