{
  "type": "FeatureCollection",
  "title": "Cochirleni",
  "id": "216773",
  "description": "An ancient place, cited: BAtlas 22 F4 Cochirleni",
  "bbox": [
    27.999023,
    44.278893,
    27.999023,
    44.278893
  ],
  "reprPoint": [
    27.999023,
    44.278893
  ],
  "features": [
    {
      "geometry": {
        "type": "Point",
        "coordinates": [
          27.999023,
          44.278893
        ]
      },
      "id": "darmc-location-23911",
      "type": "Feature",
      "properties": {
        "description": "1M scale point location",
        "location_precision": "precise",
        "title": "DARMC location 23911",
        "link": "http://pleiades.stoa.org/places/216773/darmc-location-23911"
      }
    }
  ]
}