{
  "type": "FeatureCollection",
  "title": "Mesembria",
  "id": "216882",
  "bbox": [
    27.7181,
    42.658743,
    27.730787,
    42.660417
  ],
  "description": "Originally a Thracian site known as Menebria, Mesembria was subsequently settled by Dorian Greeks in the early sixth century BC, eventually becoming an important trading colony on the Black Sea coast (modern Nesebar, Bulgaria). Listed as a UNESCO World Heritage Site in 1983.",
  "connectsWith": [
    "220489"
  ],
  "names": [
    "Mesembria",
    "Nessebar",
    "Mesambria Pontica",
    "Nesebar",
    "Mesambria"
  ],
  "features": [
    {
      "type": "Feature",
      "geometry": {
        "type": "Point",
        "coordinates": [
          27.7244435,
          42.65958
        ]
      },
      "properties": {
        "description": "representative point"
      }
    },
    {
      "geometry": {
        "type": "Point",
        "coordinates": [
          27.7181,
          42.660417
        ]
      },
      "id": "darmc-location-24692",
      "type": "Feature",
      "properties": {
        "description": "1:1 million scale representative point location digitized from the Barrington Atlas of the Greek and Roman World by the Digital Atlas of Roman and Medieval Civilizations project at Harvard University.",
        "location_precision": "precise",
        "title": "DARMC location 24692",
        "link": "http://pleiades.stoa.org/places/216882/darmc-location-24692"
      }
    },
    {
      "geometry": {
        "type": "Point",
        "coordinates": [
          27.730787,
          42.658743
        ]
      },
      "id": "dare-location",
      "type": "Feature",
      "properties": {
        "description": "Representative point location, site precision",
        "location_precision": "precise",
        "title": "DARE Location",
        "link": "http://pleiades.stoa.org/places/216882/dare-location"
      }
    }
  ]
}