{
  "type": "FeatureCollection",
  "title": "Naulochos/Templum Iovis?",
  "id": "216893",
  "bbox": [
    27.883333,
    42.816667,
    27.883333,
    42.816667
  ],
  "description": "A seaside settlement of ancient Thrace that was a colony of Mesembria. Romans referred to the site as Templum Iovis, although Pliny the Elder refers to it as \"Tetranaulochus.\"",
  "connectsWith": [
    "220489",
    "1224"
  ],
  "names": [
    "Naulochos",
    "Templum Iovis",
    "Tetranaulochus"
  ],
  "features": [
    {
      "type": "Feature",
      "geometry": {
        "type": "Point",
        "coordinates": [
          27.883333,
          42.816667
        ]
      },
      "properties": {
        "description": "representative point"
      }
    },
    {
      "geometry": {
        "type": "Point",
        "coordinates": [
          27.883333,
          42.816667
        ]
      },
      "id": "location-of-naulochos-templum-iovis",
      "type": "Feature",
      "properties": {
        "description": "coordinates after Wikipedia; verified in Google Earth 2013.",
        "location_precision": "precise",
        "title": "location of Naulochos/Templum Iovis?",
        "link": "http://pleiades.stoa.org/places/216893/location-of-naulochos-templum-iovis"
      }
    }
  ]
}