{
  "type": "FeatureCollection",
  "title": "Fîlfani",
  "id": "216810",
  "description": "An ancient place, cited: BAtlas 22 B4 Fîlfani",
  "bbox": [
    24.760404,
    44.612155,
    24.760404,
    44.612155
  ],
  "reprPoint": [
    24.760404,
    44.612155
  ],
  "features": [
    {
      "geometry": {
        "type": "Point",
        "coordinates": [
          24.760404,
          44.612155
        ]
      },
      "id": "darmc-location-24343",
      "type": "Feature",
      "properties": {
        "description": "1M scale point location",
        "location_precision": "precise",
        "title": "DARMC location 24343",
        "link": "http://pleiades.stoa.org/places/216810/darmc-location-24343"
      }
    }
  ]
}