{
  "type": "FeatureCollection",
  "title": "Hierasos/Gerasus/Tiarantos? (river)",
  "id": "216837",
  "bbox": [
    20.2732883,
    46.847661,
    20.2732883,
    46.847661
  ],
  "description": "Hierasos/Gerasus/Tiarantos? fl., a river of Dacia.",
  "names": [
    "Hierasos",
    "Gerasus",
    "Tiarantos"
  ],
  "features": [
    {
      "type": "Feature",
      "geometry": {
        "type": "Point",
        "coordinates": [
          20.2732883,
          46.847661
        ]
      },
      "properties": {
        "description": "representative point"
      }
    },
    {
      "geometry": {
        "type": "Point",
        "coordinates": [
          20.2732883,
          46.847661
        ]
      },
      "id": "location-of-cris-river",
      "type": "Feature",
      "properties": {
        "description": "Location based on OpenStreetMap",
        "location_precision": "precise",
        "title": "location of Criș River",
        "link": "http://pleiades.stoa.org/places/216837/location-of-cris-river"
      }
    }
  ]
}