{
  "type": "FeatureCollection",
  "title": "Inlăceni",
  "id": "216851",
  "description": "An ancient place, cited: BAtlas 22 C2 Inlăceni",
  "bbox": [
    25.111639,
    46.431143,
    25.111639,
    46.431143
  ],
  "reprPoint": [
    25.111639,
    46.431143
  ],
  "features": [
    {
      "geometry": {
        "type": "Point",
        "coordinates": [
          25.111639,
          46.431143
        ]
      },
      "id": "darmc-location-24350",
      "type": "Feature",
      "properties": {
        "description": "1M scale point location",
        "location_precision": "precise",
        "title": "DARMC location 24350",
        "link": "http://pleiades.stoa.org/places/216851/darmc-location-24350"
      }
    }
  ]
}