{
  "type": "FeatureCollection",
  "title": "Durostorum",
  "id": "216800",
  "description": "An ancient place, cited: BAtlas 22 E4 Durostorum",
  "bbox": [
    27.259474,
    44.117033,
    27.260732,
    44.121183
  ],
  "reprPoint": [
    27.260103,
    44.119108
  ],
  "names": [
    "Durostorum"
  ],
  "features": [
    {
      "geometry": {
        "type": "Point",
        "coordinates": [
          27.260732,
          44.117033
        ]
      },
      "id": "darmc-location-24630",
      "type": "Feature",
      "properties": {
        "description": "1M scale point location",
        "location_precision": "precise",
        "title": "DARMC location 24630",
        "link": "http://pleiades.stoa.org/places/216800/darmc-location-24630"
      }
    },
    {
      "geometry": {
        "type": "Point",
        "coordinates": [
          27.259474,
          44.121183
        ]
      },
      "id": "dare-location",
      "type": "Feature",
      "properties": {
        "description": "Representative point location, site precision",
        "location_precision": "precise",
        "title": "DARE Location",
        "link": "http://pleiades.stoa.org/places/216800/dare-location"
      }
    }
  ]
}