{
  "type": "FeatureCollection",
  "title": "Kazanluk",
  "id": "216863",
  "description": "An ancient place, cited: BAtlas 22 C6 Kazanluk",
  "bbox": [
    25.394463,
    42.618717,
    25.394463,
    42.618717
  ],
  "reprPoint": [
    25.394463,
    42.618717
  ],
  "features": [
    {
      "geometry": {
        "type": "Point",
        "coordinates": [
          25.394463,
          42.618717
        ]
      },
      "id": "darmc-location-23749",
      "type": "Feature",
      "properties": {
        "description": "Point location",
        "location_precision": "precise",
        "title": "DARMC location 23749",
        "link": "http://pleiades.stoa.org/places/216863/darmc-location-23749"
      }
    }
  ]
}