{
  "type": "FeatureCollection",
  "title": "Gerania",
  "id": "216815",
  "description": "An ancient place, cited: BAtlas 22 F5 Gerania",
  "bbox": [
    28.054253,
    43.343479,
    28.054253,
    43.343479
  ],
  "connectsWith": [
    "220489"
  ],
  "reprPoint": [
    28.054253,
    43.343479
  ],
  "names": [
    "Gerania"
  ],
  "features": [
    {
      "geometry": {
        "type": "Point",
        "coordinates": [
          28.054253,
          43.343479
        ]
      },
      "id": "darmc-location-24637",
      "type": "Feature",
      "properties": {
        "description": "1M scale point location",
        "location_precision": "precise",
        "title": "DARMC location 24637",
        "link": "http://pleiades.stoa.org/places/216815/darmc-location-24637"
      }
    }
  ]
}