{
  "type": "FeatureCollection",
  "title": "Mesembria",
  "id": "216882",
  "description": "Originally a Thracian site known as Menebria, Mesembria (or Nessebar) was subsequently settled by Dorian Greeks in the early sixth century BC, eventually becoming an important trading colony on the Black Sea coast. Listed as a UNESCO World Heritage Site in 1983.",
  "bbox": [
    27.730787,
    42.658743,
    27.730787,
    42.658743
  ],
  "connectsWith": [
    "220489"
  ],
  "reprPoint": [
    27.730787,
    42.658743
  ],
  "names": [
    "Mesembria",
    "Nessebar"
  ],
  "features": [
    {
      "geometry": {
        "type": "Point",
        "coordinates": [
          27.7181,
          42.660417
        ]
      },
      "id": "darmc-location-24692",
      "type": "Feature",
      "properties": {
        "description": "1M scale point location",
        "location_precision": "precise",
        "title": "DARMC location 24692",
        "link": "http://pleiades.stoa.org/places/216882/darmc-location-24692"
      }
    },
    {
      "geometry": {
        "type": "Point",
        "coordinates": [
          27.730787,
          42.658743
        ]
      },
      "id": "dare-location",
      "type": "Feature",
      "properties": {
        "description": "Representative point location, site precision",
        "location_precision": "precise",
        "title": "DARE Location",
        "link": "http://pleiades.stoa.org/places/216882/dare-location"
      }
    }
  ]
}