{
  "type": "FeatureCollection",
  "title": "Madara",
  "id": "216874",
  "description": "An ancient place, cited: BAtlas 22 E5 Madara",
  "bbox": [
    27.099907,
    43.283045,
    27.099907,
    43.283045
  ],
  "reprPoint": [
    27.099907,
    43.283045
  ],
  "features": [
    {
      "geometry": {
        "type": "Point",
        "coordinates": [
          27.099907,
          43.283045
        ]
      },
      "id": "darmc-location-24825",
      "type": "Feature",
      "properties": {
        "description": "1M scale point location",
        "location_precision": "precise",
        "title": "DARMC location 24825",
        "link": "http://pleiades.stoa.org/places/216874/darmc-location-24825"
      }
    }
  ]
}