{
  "type": "FeatureCollection",
  "title": "Odorheiu Secuiesc",
  "id": "216905",
  "description": "An ancient place, cited: BAtlas 22 C2 Odorheiu Secuiesc",
  "bbox": [
    25.301186,
    46.313132,
    25.301186,
    46.313132
  ],
  "reprPoint": [
    25.301186,
    46.313132
  ],
  "features": [
    {
      "geometry": {
        "type": "Point",
        "coordinates": [
          25.301186,
          46.313132
        ]
      },
      "id": "darmc-location-24397",
      "type": "Feature",
      "properties": {
        "description": "1M scale point location",
        "location_precision": "precise",
        "title": "DARMC location 24397",
        "link": "http://pleiades.stoa.org/places/216905/darmc-location-24397"
      }
    }
  ]
}