{
  "type": "FeatureCollection",
  "title": "Olteni",
  "id": "216910",
  "description": "An ancient place, cited: BAtlas 22 C2 Olteni",
  "bbox": [
    25.848815,
    45.974122,
    25.848815,
    45.974122
  ],
  "reprPoint": [
    25.848815,
    45.974122
  ],
  "features": [
    {
      "geometry": {
        "type": "Point",
        "coordinates": [
          25.848815,
          45.974122
        ]
      },
      "id": "darmc-location-24399",
      "type": "Feature",
      "properties": {
        "description": "1M scale point location",
        "location_precision": "precise",
        "title": "DARMC location 24399",
        "link": "http://pleiades.stoa.org/places/216910/darmc-location-24399"
      }
    }
  ]
}