{
  "type": "FeatureCollection",
  "title": "Purcăreni",
  "id": "216945",
  "description": "An ancient place, cited: BAtlas 22 B4 Purcăreni",
  "bbox": [
    24.88314,
    44.961137,
    24.92708,
    44.990649
  ],
  "reprPoint": [
    24.90511,
    44.975893
  ],
  "features": [
    {
      "geometry": {
        "type": "Point",
        "coordinates": [
          24.92708,
          44.990649
        ]
      },
      "id": "darmc-location-8212",
      "type": "Feature",
      "properties": {
        "description": "1M scale point location",
        "location_precision": "precise",
        "title": "DARMC location 8212",
        "link": "http://pleiades.stoa.org/places/216945/darmc-location-8212"
      }
    },
    {
      "geometry": {
        "type": "Point",
        "coordinates": [
          24.88314,
          44.961137
        ]
      },
      "id": "dare-location",
      "type": "Feature",
      "properties": {
        "description": "Representative point location, village precision",
        "location_precision": "precise",
        "title": "DARE Location",
        "link": "http://pleiades.stoa.org/places/216945/dare-location"
      }
    }
  ]
}