{
  "type": "FeatureCollection",
  "title": "Romula/Malva",
  "id": "216958",
  "description": "An ancient place, cited: BAtlas 22 B4 Romula/Malva",
  "bbox": [
    24.39414,
    44.172611,
    24.400273,
    44.175814
  ],
  "reprPoint": [
    24.3972065,
    44.1742125
  ],
  "names": [
    "Romula",
    "Malva"
  ],
  "features": [
    {
      "geometry": {
        "type": "Point",
        "coordinates": [
          24.400273,
          44.175814
        ]
      },
      "id": "darmc-location-24196",
      "type": "Feature",
      "properties": {
        "description": "1M scale point location",
        "location_precision": "precise",
        "title": "DARMC location 24196",
        "link": "http://pleiades.stoa.org/places/216958/darmc-location-24196"
      }
    },
    {
      "geometry": {
        "type": "Point",
        "coordinates": [
          24.39414,
          44.172611
        ]
      },
      "id": "dare-location",
      "type": "Feature",
      "properties": {
        "description": "Representative point location, site precision",
        "location_precision": "precise",
        "title": "DARE Location",
        "link": "http://pleiades.stoa.org/places/216958/dare-location"
      }
    }
  ]
}