{
  "type": "FeatureCollection",
  "title": "Storgosia",
  "id": "216992",
  "description": "An ancient place, cited: BAtlas 22 B5 Storgosia",
  "bbox": [
    24.620705,
    43.383008,
    24.628933,
    43.408334
  ],
  "reprPoint": [
    24.624819,
    43.395671
  ],
  "names": [
    "Storgosia"
  ],
  "features": [
    {
      "geometry": {
        "type": "Point",
        "coordinates": [
          24.620705,
          43.408334
        ]
      },
      "id": "darmc-location-24291",
      "type": "Feature",
      "properties": {
        "description": "1M scale point location",
        "location_precision": "precise",
        "title": "DARMC location 24291",
        "link": "http://pleiades.stoa.org/places/216992/darmc-location-24291"
      }
    },
    {
      "geometry": {
        "type": "Point",
        "coordinates": [
          24.628933,
          43.383008
        ]
      },
      "id": "dare-location",
      "type": "Feature",
      "properties": {
        "description": "Representative point location, site precision",
        "location_precision": "precise",
        "title": "DARE Location",
        "link": "http://pleiades.stoa.org/places/216992/dare-location"
      }
    }
  ]
}