{
  "type": "FeatureCollection",
  "title": "Sub Radices",
  "id": "216995",
  "bbox": [
    24.599701,
    42.727346,
    24.599701,
    42.727346
  ],
  "description": "An ancient place, cited: BAtlas 22 B6 Sub Radices",
  "names": [
    "Sub Radices"
  ],
  "features": [
    {
      "type": "Feature",
      "geometry": {
        "type": "Point",
        "coordinates": [
          24.599701,
          42.727346
        ]
      },
      "properties": {
        "description": "representative point"
      }
    },
    {
      "geometry": {
        "type": "Point",
        "coordinates": [
          24.599701,
          42.727346
        ]
      },
      "id": "darmc-location-24292",
      "type": "Feature",
      "properties": {
        "description": "1M scale point location",
        "location_precision": "precise",
        "title": "DARMC location 24292",
        "link": "http://pleiades.stoa.org/places/216995/darmc-location-24292"
      }
    }
  ]
}