{
  "type": "FeatureCollection",
  "title": "Piatra Roşie",
  "id": "216928",
  "bbox": [
    28.199722,
    45.11789,
    28.199722,
    45.11789
  ],
  "description": "An ancient place, cited: BAtlas 22 F3 Piatra Roşie",
  "features": [
    {
      "type": "Feature",
      "geometry": {
        "type": "Point",
        "coordinates": [
          28.199722,
          45.11789
        ]
      },
      "properties": {
        "description": "representative point"
      }
    },
    {
      "geometry": {
        "type": "Point",
        "coordinates": [
          28.199722,
          45.11789
        ]
      },
      "id": "darmc-location-2564",
      "type": "Feature",
      "properties": {
        "description": "1M scale point location",
        "location_precision": "precise",
        "title": "DARMC location 2564",
        "link": "http://pleiades.stoa.org/places/216928/darmc-location-2564"
      }
    }
  ]
}