{
  "type": "FeatureCollection",
  "title": "Tomis",
  "id": "217016",
  "description": "Founded as a Greek colony on the Black Sea coast ca. 600 BC.",
  "bbox": [
    28.661176,
    44.172489,
    28.661176,
    44.172489
  ],
  "connectsWith": [
    "220489"
  ],
  "reprPoint": [
    28.661176,
    44.172489
  ],
  "names": [
    "Tomis"
  ],
  "features": [
    {
      "geometry": {
        "type": "Point",
        "coordinates": [
          28.638299,
          44.173224
        ]
      },
      "id": "darmc-location-24141",
      "type": "Feature",
      "properties": {
        "description": "1M scale point location",
        "location_precision": "precise",
        "title": "DARMC location 24141",
        "link": "http://pleiades.stoa.org/places/217016/darmc-location-24141"
      }
    },
    {
      "geometry": {
        "type": "Point",
        "coordinates": [
          28.661176,
          44.172489
        ]
      },
      "id": "dare-location",
      "type": "Feature",
      "properties": {
        "description": "Representative point location, village precision",
        "location_precision": "precise",
        "title": "DARE Location",
        "link": "http://pleiades.stoa.org/places/217016/dare-location"
      }
    }
  ]
}