{
  "type": "FeatureCollection",
  "title": "Vicus Urb(...)",
  "id": "217057",
  "description": "An ancient place, cited: BAtlas 22 F4 Vicus Urb(...)",
  "bbox": [
    28.457081,
    44.629956,
    28.457288,
    44.6301
  ],
  "reprPoint": [
    28.4571845,
    44.630028
  ],
  "names": [
    "Vicus Urb(...)"
  ],
  "features": [
    {
      "geometry": {
        "type": "Point",
        "coordinates": [
          28.457288,
          44.6301
        ]
      },
      "id": "darmc-location-24551",
      "type": "Feature",
      "properties": {
        "description": "1M scale point location",
        "location_precision": "precise",
        "title": "DARMC location 24551",
        "link": "http://pleiades.stoa.org/places/217057/darmc-location-24551"
      }
    },
    {
      "geometry": {
        "type": "Point",
        "coordinates": [
          28.457081,
          44.629956
        ]
      },
      "id": "darmc-location-24819",
      "type": "Feature",
      "properties": {
        "description": "1M scale point location",
        "location_precision": "precise",
        "title": "DARMC location 24819",
        "link": "http://pleiades.stoa.org/places/217057/darmc-location-24819"
      }
    }
  ]
}