{
  "type": "FeatureCollection",
  "title": "Vicus Petrus",
  "id": "217048",
  "description": "An ancient place, cited: BAtlas 22 F4 Vicus Petrus",
  "bbox": [
    28.605266,
    44.809832,
    28.605266,
    44.809832
  ],
  "reprPoint": [
    28.605266,
    44.809832
  ],
  "names": [
    "Vicus Petrus"
  ],
  "features": [
    {
      "geometry": {
        "type": "Point",
        "coordinates": [
          28.605266,
          44.809832
        ]
      },
      "id": "darmc-location-23953",
      "type": "Feature",
      "properties": {
        "description": "1M scale point location",
        "location_precision": "precise",
        "title": "DARMC location 23953",
        "link": "http://pleiades.stoa.org/places/217048/darmc-location-23953"
      }
    }
  ]
}