{
  "type": "FeatureCollection",
  "title": "Vicus Scenopesis",
  "id": "217052",
  "description": "An ancient place, cited: BAtlas 22 F4 Vicus Scenopesis",
  "bbox": [
    28.112919,
    44.519308,
    28.112919,
    44.519308
  ],
  "reprPoint": [
    28.112919,
    44.519308
  ],
  "names": [
    "Vicus Scenopesis"
  ],
  "features": [
    {
      "geometry": {
        "type": "Point",
        "coordinates": [
          28.112919,
          44.519308
        ]
      },
      "id": "darmc-location-23956",
      "type": "Feature",
      "properties": {
        "description": "1M scale point location",
        "location_precision": "precise",
        "title": "DARMC location 23956",
        "link": "http://pleiades.stoa.org/places/217052/darmc-location-23956"
      }
    }
  ]
}