{
  "type": "FeatureCollection",
  "title": "Thalamonium",
  "id": "217007",
  "description": "An ancient place, cited: BAtlas 22 F3 Thalamonium",
  "bbox": [
    28.916885,
    45.149867,
    28.916885,
    45.149867
  ],
  "reprPoint": [
    28.916885,
    45.149867
  ],
  "names": [
    "Thalamonium"
  ],
  "features": [
    {
      "geometry": {
        "type": "Point",
        "coordinates": [
          28.916885,
          45.149867
        ]
      },
      "id": "darmc-location-23943",
      "type": "Feature",
      "properties": {
        "description": "1M scale point location",
        "location_precision": "precise",
        "title": "DARMC location 23943",
        "link": "http://pleiades.stoa.org/places/217007/darmc-location-23943"
      }
    }
  ]
}