{
  "type": "FeatureCollection",
  "title": "Roman bridge at Valeriana",
  "id": "218198",
  "bbox": [
    24.271632,
    43.69115,
    24.271632,
    43.69115
  ],
  "description": "A bridge constructed across the Danube at the Roman fort of Valeriana.",
  "connectsWith": [
    "226577",
    "217038"
  ],
  "features": [
    {
      "type": "Feature",
      "geometry": {
        "type": "Point",
        "coordinates": [
          24.271632,
          43.69115
        ]
      },
      "properties": {
        "description": "representative point"
      }
    },
    {
      "geometry": {
        "type": "Point",
        "coordinates": [
          24.271632,
          43.69115
        ]
      },
      "id": "imagery-location-of-pier-no-1-of-the-roman-bridge-at-valeriana",
      "type": "Feature",
      "properties": {
        "description": "Point representing the location of a surviving pier of the Roman bridge at Valeriana, after Bondoc 2018.",
        "location_precision": "precise",
        "title": "Imagery location of pier no. 1 of the Roman bridge at Valeriana",
        "link": "http://pleiades.stoa.org/places/218198/imagery-location-of-pier-no-1-of-the-roman-bridge-at-valeriana"
      }
    }
  ]
}