{
  "type": "FeatureCollection",
  "title": "Untitled",
  "id": "218198",
  "bbox": [
    24.316735,
    43.673897,
    24.316735,
    43.673897
  ],
  "description": "An ancient place, cited: BAtlas 22 B5 unnamed bridge (Valeriana)",
  "features": [
    {
      "type": "Feature",
      "geometry": {
        "type": "Point",
        "coordinates": [
          24.316735,
          43.673897
        ]
      },
      "properties": {
        "description": "representative point"
      }
    },
    {
      "geometry": {
        "type": "Point",
        "coordinates": [
          24.316735,
          43.673897
        ]
      },
      "id": "darmc-location-14598",
      "type": "Feature",
      "properties": {
        "description": "1M scale point location",
        "location_precision": "precise",
        "title": "DARMC location 14598",
        "link": "http://pleiades.stoa.org/places/218198/darmc-location-14598"
      }
    }
  ]
}