{
  "type": "FeatureCollection",
  "title": "Tobillas",
  "id": "218813276",
  "bbox": [
    -3.1870721,
    42.880094,
    -3.1870721,
    42.880094
  ],
  "description": "A village located in the valley of the Omecillo River, a tributary of the Ebro. Tobillas has been the focus of a case study interested in the processes of village formation from both archaeological and historical perspectives.",
  "features": [
    {
      "type": "Feature",
      "geometry": {
        "type": "Point",
        "coordinates": [
          -3.1870721,
          42.880094
        ]
      },
      "properties": {
        "description": "representative point"
      }
    },
    {
      "geometry": {
        "type": "Point",
        "coordinates": [
          -3.1870721,
          42.880094
        ]
      },
      "id": "osm-location-of-tobillas",
      "type": "Feature",
      "properties": {
        "description": "Representative location based on OpenStreetMap",
        "location_precision": "precise",
        "title": "OSM location of Tobillas",
        "link": "http://pleiades.stoa.org/places/218813276/osm-location-of-tobillas"
      }
    }
  ]
}