{
  "type": "FeatureCollection",
  "title": "City walls of Sabucina",
  "id": "221984496",
  "bbox": [
    14.121265,
    37.502691,
    14.121265,
    37.502691
  ],
  "description": "The fortification walls of the Classical city.",
  "connectsWith": [
    "462483"
  ],
  "features": [
    {
      "type": "Feature",
      "geometry": {
        "type": "Point",
        "coordinates": [
          14.121265,
          37.502691
        ]
      },
      "properties": {
        "description": "representative point"
      }
    },
    {
      "geometry": {
        "type": "Point",
        "coordinates": [
          14.121265,
          37.502691
        ]
      },
      "id": "city-walls",
      "type": "Feature",
      "properties": {
        "description": "Fortification walls of the Classical city.",
        "location_precision": "precise",
        "title": "City walls",
        "link": "http://pleiades.stoa.org/places/221984496/city-walls"
      }
    }
  ]
}