{
  "type": "FeatureCollection",
  "title": "Dort Oba",
  "id": "226585",
  "bbox": [
    34.092742,
    45.138663,
    34.092742,
    45.138663
  ],
  "description": "An ancient place, cited: BAtlas 23 H3 Dort Oba",
  "connectsWith": [
    "226778"
  ],
  "features": [
    {
      "type": "Feature",
      "geometry": {
        "type": "Point",
        "coordinates": [
          34.092742,
          45.138663
        ]
      },
      "properties": {
        "description": "representative point"
      }
    },
    {
      "geometry": {
        "type": "Point",
        "coordinates": [
          34.092742,
          45.138663
        ]
      },
      "id": "darmc-location-23212",
      "type": "Feature",
      "properties": {
        "description": "Point location",
        "location_precision": "precise",
        "title": "DARMC location 23212",
        "link": "http://pleiades.stoa.org/places/226585/darmc-location-23212"
      }
    }
  ]
}