{
  "type": "FeatureCollection",
  "title": "Danuvius/Istros/Hister (river)",
  "id": "226577",
  "bbox": [
    8.155,
    45.2293931,
    28.7366937,
    48.095556
  ],
  "description": "The Danube river.",
  "connectsWith": [
    "226720",
    "226595"
  ],
  "names": [
    "Danuvius",
    "Istros",
    "Hister",
    "Danube"
  ],
  "features": [
    {
      "type": "Feature",
      "geometry": {
        "type": "Point",
        "coordinates": [
          18.44584685,
          46.66247455
        ]
      },
      "properties": {
        "description": "representative point"
      }
    },
    {
      "geometry": {
        "type": "Point",
        "coordinates": [
          8.155,
          48.095556
        ]
      },
      "id": "location-of-primary-source-of-danuvius-istros-hister-fl",
      "type": "Feature",
      "properties": {
        "description": "verified in Google Earth 2013.",
        "location_precision": "precise",
        "title": "location of primary source of Danuvius/Istros/Hister fl.",
        "link": "http://pleiades.stoa.org/places/226577/location-of-primary-source-of-danuvius-istros-hister-fl"
      }
    },
    {
      "geometry": {
        "type": "Point",
        "coordinates": [
          28.7366937,
          45.2293931
        ]
      },
      "id": "location-of-modern-head-of-danuvius-istros-hister",
      "type": "Feature",
      "properties": {
        "description": "Location based on OpenStreetMap. Derived from the node at the separation of the main stream of the Danube and its first major sub-stream (Bratul Chilia) running into the delta.",
        "location_precision": "precise",
        "title": "OSM location of modern head of Danuvius/Istros/Hister river delta",
        "link": "http://pleiades.stoa.org/places/226577/location-of-modern-head-of-danuvius-istros-hister"
      }
    }
  ]
}