{
  "type": "FeatureCollection",
  "title": "Belen'koye",
  "id": "226534",
  "description": "An ancient place, cited: BAtlas 23 D2 Belen'koye",
  "bbox": [
    30.372461,
    46.05397,
    30.372461,
    46.05397
  ],
  "reprPoint": [
    30.372461,
    46.05397
  ],
  "features": [
    {
      "geometry": {
        "type": "Point",
        "coordinates": [
          30.372461,
          46.05397
        ]
      },
      "id": "darmc-location-24587",
      "type": "Feature",
      "properties": {
        "description": "1M scale point location",
        "location_precision": "precise",
        "title": "DARMC location 24587",
        "link": "http://pleiades.stoa.org/places/226534/darmc-location-24587"
      }
    }
  ]
}