{
  "type": "FeatureCollection",
  "title": "Danuvius/Istros/Hister fl.",
  "id": "226577",
  "description": "The Danube river.",
  "bbox": [
    8.155,
    45.2293931,
    28.7366937,
    48.095556
  ],
  "connectsWith": [
    "226720"
  ],
  "reprPoint": [
    13.437992925,
    47.323945525
  ],
  "names": [
    "Danuvius",
    "Istros",
    "Hister",
    "Danube"
  ],
  "features": [
    {
      "geometry": {
        "type": "Point",
        "coordinates": [
          8.34,
          48.02
        ]
      },
      "id": "batlas-location",
      "type": "Feature",
      "properties": {
        "description": "Representative location for the Danuvius/Istros river, based on coordinates in the Barrington Atlas.",
        "location_precision": "precise",
        "title": "Barrington Atlas location",
        "link": "http://pleiades.stoa.org/places/226577/batlas-location"
      }
    },
    {
      "geometry": {
        "type": "Point",
        "coordinates": [
          28.7366937,
          45.2293931
        ]
      },
      "id": "location-of-modern-head-of-danuvius-istros-hister",
      "type": "Feature",
      "properties": {
        "description": "Location based on OpenStreetMap. Derived from the node at the separation of the main stream of the Danube and its first major sub-stream (Bratul Chilia) running into the delta.",
        "location_precision": "precise",
        "title": "OSM location of modern head of Danuvius/Istros/Hister river delta",
        "link": "http://pleiades.stoa.org/places/226577/location-of-modern-head-of-danuvius-istros-hister"
      }
    },
    {
      "geometry": {
        "type": "Point",
        "coordinates": [
          8.155,
          48.095556
        ]
      },
      "id": "location-of-primary-source-of-danuvius-istros-hister-fl",
      "type": "Feature",
      "properties": {
        "description": "verified in Google Earth 2013.",
        "location_precision": "precise",
        "title": "location of primary source of Danuvius/Istros/Hister fl.",
        "link": "http://pleiades.stoa.org/places/226577/location-of-primary-source-of-danuvius-istros-hister-fl"
      }
    }
  ]
}