{
  "type": "FeatureCollection",
  "title": "Abuzlar",
  "id": "226504",
  "description": "An ancient place, cited: BAtlas 23 F3 Abuzlar",
  "bbox": [
    32.627506,
    45.481553,
    32.627506,
    45.481553
  ],
  "reprPoint": [
    32.627506,
    45.481553
  ],
  "features": [
    {
      "geometry": {
        "type": "Point",
        "coordinates": [
          32.627506,
          45.481553
        ]
      },
      "id": "darmc-location-24555",
      "type": "Feature",
      "properties": {
        "description": "1M scale point location",
        "location_precision": "precise",
        "title": "DARMC location 24555",
        "link": "http://pleiades.stoa.org/places/226504/darmc-location-24555"
      }
    }
  ]
}