{
  "type": "FeatureCollection",
  "title": "Danuvius/Istros/Hister fl.",
  "id": "226577",
  "description": "The Danube river.",
  "bbox": [
    8.155,
    47.950833,
    8.520278,
    48.095556
  ],
  "connectsWith": [
    "226720"
  ],
  "reprPoint": [
    8.338426,
    48.0221296667
  ],
  "names": [
    "Danuvius",
    "Istros",
    "Hister",
    "Danube"
  ],
  "features": [
    {
      "geometry": {
        "type": "Point",
        "coordinates": [
          8.34,
          48.02
        ]
      },
      "id": "batlas-location",
      "type": "Feature",
      "properties": {
        "description": "Representative location for the Danuvius/Istros river, based on coordinates in the Barrington Atlas.",
        "location_precision": "precise",
        "title": "Barrington Atlas location",
        "link": "http://pleiades.stoa.org/places/226577/batlas-location"
      }
    }
  ]
}