{
  "type": "FeatureCollection",
  "title": "Alekseyevka",
  "id": "226515",
  "bbox": [
    34.183459,
    47.549825,
    34.183459,
    47.549825
  ],
  "description": "An ancient place, cited: BAtlas 23 H1 Alekseyevka",
  "features": [
    {
      "type": "Feature",
      "geometry": {
        "type": "Point",
        "coordinates": [
          34.183459,
          47.549825
        ]
      },
      "properties": {
        "description": "representative point"
      }
    },
    {
      "geometry": {
        "type": "Point",
        "coordinates": [
          34.183459,
          47.549825
        ]
      },
      "id": "darmc-location-11302",
      "type": "Feature",
      "properties": {
        "description": "1M scale point location",
        "location_precision": "precise",
        "title": "DARMC location 11302",
        "link": "http://pleiades.stoa.org/places/226515/darmc-location-11302"
      }
    }
  ]
}