{
  "type": "FeatureCollection",
  "title": "Belyayevka",
  "id": "226536",
  "description": "An ancient place, cited: BAtlas 23 D2 Belyayevka",
  "bbox": [
    30.214637,
    46.472891,
    30.214637,
    46.472891
  ],
  "reprPoint": [
    30.214637,
    46.472891
  ],
  "features": [
    {
      "geometry": {
        "type": "Point",
        "coordinates": [
          30.214637,
          46.472891
        ]
      },
      "id": "darmc-location-24806",
      "type": "Feature",
      "properties": {
        "description": "1M scale point location",
        "location_precision": "precise",
        "title": "DARMC location 24806",
        "link": "http://pleiades.stoa.org/places/226536/darmc-location-24806"
      }
    }
  ]
}