{
  "type": "FeatureCollection",
  "title": "Bel'bekskoye",
  "id": "226533",
  "bbox": [
    33.560769,
    44.682449,
    33.560769,
    44.682449
  ],
  "description": "An ancient place, cited: BAtlas 23 G4 Bel'bekskoye",
  "features": [
    {
      "type": "Feature",
      "geometry": {
        "type": "Point",
        "coordinates": [
          33.560769,
          44.682449
        ]
      },
      "properties": {
        "description": "representative point"
      }
    },
    {
      "geometry": {
        "type": "Point",
        "coordinates": [
          33.560769,
          44.682449
        ]
      },
      "id": "darmc-location-11683",
      "type": "Feature",
      "properties": {
        "description": "1M scale point location",
        "location_precision": "precise",
        "title": "DARMC location 11683",
        "link": "http://pleiades.stoa.org/places/226533/darmc-location-11683"
      }
    }
  ]
}