{
  "type": "FeatureCollection",
  "title": "Gurzuf",
  "id": "226614",
  "bbox": [
    34.287505,
    44.552758,
    34.287505,
    44.552758
  ],
  "description": "According to Hind, a sanctuary dating ca. third century BC to second century AD was identified at the Gurzuf Pass. Silver and bronze statuettes of Graeco-Roman divinities were recovered.",
  "connectsWith": [
    "226609"
  ],
  "features": [
    {
      "type": "Feature",
      "geometry": {
        "type": "Point",
        "coordinates": [
          34.287505,
          44.552758
        ]
      },
      "properties": {
        "description": "representative point"
      }
    },
    {
      "geometry": {
        "type": "Point",
        "coordinates": [
          34.287505,
          44.552758
        ]
      },
      "id": "darmc-location-24821",
      "type": "Feature",
      "properties": {
        "description": "1M scale point location",
        "location_precision": "precise",
        "title": "DARMC location 24821",
        "link": "http://pleiades.stoa.org/places/226614/darmc-location-24821"
      }
    }
  ]
}