{
  "type": "FeatureCollection",
  "title": "Konsulovskoye",
  "id": "226663",
  "description": "An ancient place, cited: BAtlas 23 G1 Konsulovskoye",
  "bbox": [
    33.632072,
    47.034532,
    33.632072,
    47.034532
  ],
  "reprPoint": [
    33.632072,
    47.034532
  ],
  "features": [
    {
      "geometry": {
        "type": "Point",
        "coordinates": [
          33.632072,
          47.034532
        ]
      },
      "id": "darmc-location-13256",
      "type": "Feature",
      "properties": {
        "description": "1M scale point location",
        "location_precision": "precise",
        "title": "DARMC location 13256",
        "link": "http://pleiades.stoa.org/places/226663/darmc-location-13256"
      }
    }
  ]
}