{
  "type": "FeatureCollection",
  "title": "Neapolis",
  "id": "226695",
  "description": "An ancient place, cited: BAtlas 23 H4 Neapolis",
  "bbox": [
    34.119907,
    44.942408,
    34.119907,
    44.942408
  ],
  "reprPoint": [
    34.119907,
    44.942408
  ],
  "names": [
    "Neapolis"
  ],
  "features": [
    {
      "geometry": {
        "type": "Point",
        "coordinates": [
          34.122139,
          44.945916
        ]
      },
      "id": "darmc-location-24113",
      "type": "Feature",
      "properties": {
        "description": "1M scale point location",
        "location_precision": "precise",
        "title": "DARMC location 24113",
        "link": "http://pleiades.stoa.org/places/226695/darmc-location-24113"
      }
    },
    {
      "geometry": {
        "type": "Point",
        "coordinates": [
          34.119907,
          44.942408
        ]
      },
      "id": "dare-location",
      "type": "Feature",
      "properties": {
        "description": "Representative point location, site precision",
        "location_precision": "precise",
        "title": "DARE Location",
        "link": "http://pleiades.stoa.org/places/226695/dare-location"
      }
    },
    {
      "geometry": {
        "type": "Point",
        "coordinates": [
          34.1179335,
          44.9444422
        ]
      },
      "id": "location-of-archaeological-area",
      "type": "Feature",
      "properties": {
        "description": "Location based on OpenStreetMap",
        "location_precision": "precise",
        "title": "location of archaeological area",
        "link": "http://pleiades.stoa.org/places/226695/location-of-archaeological-area"
      }
    }
  ]
}