{
  "type": "FeatureCollection",
  "title": "Neapolis",
  "id": "226695",
  "bbox": [
    34.1179335,
    44.942408,
    34.119907,
    44.9444422
  ],
  "description": "An important Scythian settlement, capital of the late Scythian state on the Crimean peninsula.",
  "connectsWith": [
    "226778"
  ],
  "names": [
    "Neapolis"
  ],
  "features": [
    {
      "type": "Feature",
      "geometry": {
        "type": "Point",
        "coordinates": [
          34.11892025,
          44.9434251
        ]
      },
      "properties": {
        "description": "representative point"
      }
    },
    {
      "geometry": {
        "type": "Point",
        "coordinates": [
          34.119907,
          44.942408
        ]
      },
      "id": "dare-location",
      "type": "Feature",
      "properties": {
        "description": "Representative point location, site precision",
        "location_precision": "precise",
        "title": "DARE Location",
        "link": "http://pleiades.stoa.org/places/226695/dare-location"
      }
    },
    {
      "geometry": {
        "type": "Point",
        "coordinates": [
          34.1179335,
          44.9444422
        ]
      },
      "id": "location-of-archaeological-area",
      "type": "Feature",
      "properties": {
        "description": "Location based on OpenStreetMap",
        "location_precision": "precise",
        "title": "location of archaeological area",
        "link": "http://pleiades.stoa.org/places/226695/location-of-archaeological-area"
      }
    }
  ]
}