{
  "type": "FeatureCollection",
  "title": "Germes",
  "id": "226602",
  "description": "An ancient place, cited: BAtlas 23 H1 Germes",
  "bbox": [
    35.166721,
    47.8339,
    35.166721,
    47.8339
  ],
  "reprPoint": [
    35.166721,
    47.8339
  ],
  "features": [
    {
      "geometry": {
        "type": "Point",
        "coordinates": [
          35.166721,
          47.8339
        ]
      },
      "id": "darmc-location-23828",
      "type": "Feature",
      "properties": {
        "description": "Point location",
        "location_precision": "precise",
        "title": "DARMC location 23828",
        "link": "http://pleiades.stoa.org/places/226602/darmc-location-23828"
      }
    }
  ]
}