{
  "type": "FeatureCollection",
  "title": "Gogolevka",
  "id": "226607",
  "bbox": [
    35.034899,
    45.111659,
    35.034899,
    45.111659
  ],
  "description": "An ancient place, cited: BAtlas 23 I3 Gogolevka",
  "features": [
    {
      "type": "Feature",
      "geometry": {
        "type": "Point",
        "coordinates": [
          35.034899,
          45.111659
        ]
      },
      "properties": {
        "description": "representative point"
      }
    },
    {
      "geometry": {
        "type": "Point",
        "coordinates": [
          35.034899,
          45.111659
        ]
      },
      "id": "darmc-location-12571",
      "type": "Feature",
      "properties": {
        "description": "1M scale point location",
        "location_precision": "precise",
        "title": "DARMC location 12571",
        "link": "http://pleiades.stoa.org/places/226607/darmc-location-12571"
      }
    }
  ]
}