{
  "type": "FeatureCollection",
  "title": "Gaymanova",
  "id": "226601",
  "description": "An ancient place, cited: BAtlas 23 I1 Gaymanova",
  "bbox": [
    35.251912,
    47.451863,
    35.251912,
    47.451863
  ],
  "reprPoint": [
    35.251912,
    47.451863
  ],
  "features": [
    {
      "geometry": {
        "type": "Point",
        "coordinates": [
          35.251912,
          47.451863
        ]
      },
      "id": "darmc-location-23203",
      "type": "Feature",
      "properties": {
        "description": "Point location",
        "location_precision": "precise",
        "title": "DARMC location 23203",
        "link": "http://pleiades.stoa.org/places/226601/darmc-location-23203"
      }
    }
  ]
}