{
  "type": "FeatureCollection",
  "title": "Mezhvodnoye",
  "id": "226687",
  "bbox": [
    32.844091,
    45.583757,
    32.844091,
    45.583757
  ],
  "description": "An ancient place, cited: BAtlas 23 F3 Mezhvodnoye",
  "features": [
    {
      "type": "Feature",
      "geometry": {
        "type": "Point",
        "coordinates": [
          32.844091,
          45.583757
        ]
      },
      "properties": {
        "description": "representative point"
      }
    },
    {
      "geometry": {
        "type": "Point",
        "coordinates": [
          32.844091,
          45.583757
        ]
      },
      "id": "darmc-location-24693",
      "type": "Feature",
      "properties": {
        "description": "1M scale point location",
        "location_precision": "precise",
        "title": "DARMC location 24693",
        "link": "http://pleiades.stoa.org/places/226687/darmc-location-24693"
      }
    }
  ]
}