{
  "type": "FeatureCollection",
  "title": "Shabo",
  "id": "226760",
  "bbox": [
    30.386864,
    46.12993,
    30.386864,
    46.12993
  ],
  "description": "An ancient place, cited: BAtlas 23 D2 Shabo",
  "features": [
    {
      "type": "Feature",
      "geometry": {
        "type": "Point",
        "coordinates": [
          30.386864,
          46.12993
        ]
      },
      "properties": {
        "description": "representative point"
      }
    },
    {
      "geometry": {
        "type": "Point",
        "coordinates": [
          30.386864,
          46.12993
        ]
      },
      "id": "darmc-location-24750",
      "type": "Feature",
      "properties": {
        "description": "1M scale point location",
        "location_precision": "precise",
        "title": "DARMC location 24750",
        "link": "http://pleiades.stoa.org/places/226760/darmc-location-24750"
      }
    }
  ]
}