{
  "type": "FeatureCollection",
  "title": "Rogachik",
  "id": "226739",
  "description": "An ancient place, cited: BAtlas 23 H1 Rogachik",
  "bbox": [
    34.099488,
    47.328499,
    34.099488,
    47.328499
  ],
  "reprPoint": [
    34.099488,
    47.328499
  ],
  "features": [
    {
      "geometry": {
        "type": "Point",
        "coordinates": [
          34.099488,
          47.328499
        ]
      },
      "id": "darmc-location-23827",
      "type": "Feature",
      "properties": {
        "description": "Point location",
        "location_precision": "precise",
        "title": "DARMC location 23827",
        "link": "http://pleiades.stoa.org/places/226739/darmc-location-23827"
      }
    }
  ]
}