{
  "type": "FeatureCollection",
  "title": "Rybal'chye 2",
  "id": "226744",
  "description": "An ancient place, cited: BAtlas 23 F2 Rybal'chye 2",
  "bbox": [
    32.234799,
    46.473887,
    32.234799,
    46.473887
  ],
  "reprPoint": [
    32.234799,
    46.473887
  ],
  "features": [
    {
      "geometry": {
        "type": "Point",
        "coordinates": [
          32.234799,
          46.473887
        ]
      },
      "id": "darmc-location-34739",
      "type": "Feature",
      "properties": {
        "description": "1M scale point location",
        "location_precision": "precise",
        "title": "DARMC location 34739",
        "link": "http://pleiades.stoa.org/places/226744/darmc-location-34739"
      }
    }
  ]
}