{
  "type": "FeatureCollection",
  "title": "Staryy Krym",
  "id": "226769",
  "description": "An ancient place, cited: BAtlas 23 I3 Staryy Krym",
  "bbox": [
    35.088723,
    45.029113,
    35.088723,
    45.029113
  ],
  "reprPoint": [
    35.088723,
    45.029113
  ],
  "features": [
    {
      "geometry": {
        "type": "Point",
        "coordinates": [
          35.088723,
          45.029113
        ]
      },
      "id": "darmc-location-24763",
      "type": "Feature",
      "properties": {
        "description": "1M scale point location",
        "location_precision": "precise",
        "title": "DARMC location 24763",
        "link": "http://pleiades.stoa.org/places/226769/darmc-location-24763"
      }
    }
  ]
}