{
  "type": "FeatureCollection",
  "title": "Ta Antiphilou",
  "id": "226772",
  "bbox": [
    29.72392,
    45.821653,
    29.72392,
    45.821653
  ],
  "description": "An ancient place, cited: BAtlas 23 C3 Ta Antiphilou",
  "names": [
    "Ta Antiphilou"
  ],
  "features": [
    {
      "type": "Feature",
      "geometry": {
        "type": "Point",
        "coordinates": [
          29.72392,
          45.821653
        ]
      },
      "properties": {
        "description": "representative point"
      }
    },
    {
      "geometry": {
        "type": "Point",
        "coordinates": [
          29.72392,
          45.821653
        ]
      },
      "id": "darmc-location-9546",
      "type": "Feature",
      "properties": {
        "description": "1M scale point location",
        "location_precision": "precise",
        "title": "DARMC location 9546",
        "link": "http://pleiades.stoa.org/places/226772/darmc-location-9546"
      }
    }
  ]
}