{
  "type": "FeatureCollection",
  "title": "Skel'ki",
  "id": "226763",
  "description": "An ancient place, cited: BAtlas 23 H1 Skel'ki",
  "bbox": [
    35.121783,
    47.44046,
    35.121783,
    47.44046
  ],
  "reprPoint": [
    35.121783,
    47.44046
  ],
  "features": [
    {
      "geometry": {
        "type": "Point",
        "coordinates": [
          35.121783,
          47.44046
        ]
      },
      "id": "darmc-location-34758",
      "type": "Feature",
      "properties": {
        "description": "1M scale point location",
        "location_precision": "precise",
        "title": "DARMC location 34758",
        "link": "http://pleiades.stoa.org/places/226763/darmc-location-34758"
      }
    }
  ]
}