{
  "type": "FeatureCollection",
  "title": "Romanovka",
  "id": "226740",
  "description": "An ancient place, cited: BAtlas 23 I3 Romanovka",
  "bbox": [
    35.052247,
    45.122499,
    35.052247,
    45.122499
  ],
  "reprPoint": [
    35.052247,
    45.122499
  ],
  "features": [
    {
      "geometry": {
        "type": "Point",
        "coordinates": [
          35.052247,
          45.122499
        ]
      },
      "id": "darmc-location-14518",
      "type": "Feature",
      "properties": {
        "description": "1M scale point location",
        "location_precision": "precise",
        "title": "DARMC location 14518",
        "link": "http://pleiades.stoa.org/places/226740/darmc-location-14518"
      }
    }
  ]
}