{
  "type": "FeatureCollection",
  "title": "Semenovka",
  "id": "226759",
  "description": "An ancient place, cited: BAtlas 23 D2 Semenovka",
  "bbox": [
    30.120825,
    46.278906,
    30.120825,
    46.278906
  ],
  "reprPoint": [
    30.120825,
    46.278906
  ],
  "features": [
    {
      "geometry": {
        "type": "Point",
        "coordinates": [
          30.120825,
          46.278906
        ]
      },
      "id": "darmc-location-24240",
      "type": "Feature",
      "properties": {
        "description": "1M scale point location",
        "location_precision": "precise",
        "title": "DARMC location 24240",
        "link": "http://pleiades.stoa.org/places/226759/darmc-location-24240"
      }
    }
  ]
}