{
  "type": "FeatureCollection",
  "title": "Varvarovka",
  "id": "226805",
  "description": "An ancient place, cited: BAtlas 23 E2 Varvarovka",
  "bbox": [
    31.926824,
    46.978797,
    31.926824,
    46.978797
  ],
  "reprPoint": [
    31.926824,
    46.978797
  ],
  "features": [
    {
      "geometry": {
        "type": "Point",
        "coordinates": [
          31.926824,
          46.978797
        ]
      },
      "id": "darmc-location-15690",
      "type": "Feature",
      "properties": {
        "description": "1M scale point location",
        "location_precision": "precise",
        "title": "DARMC location 15690",
        "link": "http://pleiades.stoa.org/places/226805/darmc-location-15690"
      }
    }
  ]
}