{
  "type": "FeatureCollection",
  "title": "Zolotoy Kurgan",
  "id": "226832",
  "description": "An ancient place, cited: BAtlas 23 G3 Zolotoy Kurgan",
  "bbox": [
    33.912952,
    45.063386,
    33.912952,
    45.063386
  ],
  "reprPoint": [
    33.912952,
    45.063386
  ],
  "features": [
    {
      "geometry": {
        "type": "Point",
        "coordinates": [
          33.912952,
          45.063386
        ]
      },
      "id": "darmc-location-23214",
      "type": "Feature",
      "properties": {
        "description": "Point location",
        "location_precision": "precise",
        "title": "DARMC location 23214",
        "link": "http://pleiades.stoa.org/places/226832/darmc-location-23214"
      }
    }
  ]
}