{
  "type": "FeatureCollection",
  "title": "Zhevakova",
  "id": "226828",
  "bbox": [
    30.814623,
    46.592463,
    30.814623,
    46.592463
  ],
  "description": "An ancient place, cited: BAtlas 23 D2 Zhevakova",
  "features": [
    {
      "type": "Feature",
      "geometry": {
        "type": "Point",
        "coordinates": [
          30.814623,
          46.592463
        ]
      },
      "properties": {
        "description": "representative point"
      }
    },
    {
      "geometry": {
        "type": "Point",
        "coordinates": [
          30.814623,
          46.592463
        ]
      },
      "id": "darmc-location-15527",
      "type": "Feature",
      "properties": {
        "description": "1M scale point location",
        "location_precision": "precise",
        "title": "DARMC location 15527",
        "link": "http://pleiades.stoa.org/places/226828/darmc-location-15527"
      }
    }
  ]
}