{
  "type": "FeatureCollection",
  "title": "Sam'alla (province)",
  "id": "227756061",
  "bbox": [
    35.4111353467,
    36.9303120368,
    36.927509,
    37.5812744
  ],
  "description": "The eighth-century-BC Assyrian king Shalmaneser V (r. 726-722 BC) conquered Sam'al and its territory and established the city as the administrative capital of an Assyrian province named after it.",
  "connectsWith": [
    "303882989",
    "652445664",
    "1043",
    "29492",
    "357078915",
    "361968004",
    "333117475"
  ],
  "names": [
    "Sam'alla"
  ],
  "features": [
    {
      "type": "Feature",
      "geometry": {
        "type": "Point",
        "coordinates": [
          36.1693221733,
          37.2557932184
        ]
      },
      "properties": {
        "description": "representative point"
      }
    }
  ]
}