{
  "type": "FeatureCollection",
  "title": "Qutb Minar",
  "id": "229277206",
  "bbox": [
    77.1855011,
    28.524401,
    77.1855011,
    28.524401
  ],
  "description": "The second tallest minar (73 m) in India after Minar-E-Fateh was built by Qutb-ud-din Aibak beginning in AD 1192. The monument is listed as a UNESCO World Heritage Site.",
  "names": [
    "Qutb Minar"
  ],
  "features": [
    {
      "type": "Feature",
      "geometry": {
        "type": "Point",
        "coordinates": [
          77.1855011,
          28.524401
        ]
      },
      "properties": {
        "description": "representative point"
      }
    },
    {
      "geometry": {
        "type": "Point",
        "coordinates": [
          77.1855011,
          28.524401
        ]
      },
      "id": "osm-location",
      "type": "Feature",
      "properties": {
        "description": "Representative point derived from an OpenStreetMap node.",
        "location_precision": "precise",
        "title": "OSM Location of Qutb Minar",
        "link": "http://pleiades.stoa.org/places/229277206/osm-location"
      }
    }
  ]
}