{
  "type": "FeatureCollection",
  "title": "Roman amphitheater at Thermae Himeraeae",
  "id": "233803923",
  "bbox": [
    13.6937879,
    37.9878085,
    13.6937879,
    37.9878085
  ],
  "description": "Roman amphitheater at Termini Imerese was of modest size and is today poorly preserved.",
  "connectsWith": [
    "462513"
  ],
  "features": [
    {
      "type": "Feature",
      "geometry": {
        "type": "Point",
        "coordinates": [
          13.6937879,
          37.9878085
        ]
      },
      "properties": {
        "description": "representative point"
      }
    },
    {
      "geometry": {
        "type": "Point",
        "coordinates": [
          13.6937879,
          37.9878085
        ]
      },
      "id": "location-of-roman-amphitheater",
      "type": "Feature",
      "properties": {
        "description": "Location based on OpenStreetMap",
        "location_precision": "precise",
        "title": "OSM location of Roman amphitheater",
        "link": "http://pleiades.stoa.org/places/233803923/location-of-roman-amphitheater"
      }
    }
  ]
}