{
  "type": "FeatureCollection",
  "title": "Avia",
  "id": "236360",
  "description": "An ancient place, cited: BAtlas 24 F4 Avia",
  "bbox": [
    -5.292256,
    40.903398,
    -5.292256,
    40.903398
  ],
  "reprPoint": [
    -5.292256,
    40.903398
  ],
  "names": [
    "Avia"
  ],
  "features": [
    {
      "geometry": {
        "type": "Point",
        "coordinates": [
          -5.292256,
          40.903398
        ]
      },
      "id": "darmc-location-19738",
      "type": "Feature",
      "properties": {
        "description": "1M scale point location",
        "location_precision": "precise",
        "title": "DARMC location 19738",
        "link": "http://pleiades.stoa.org/places/236360/darmc-location-19738"
      }
    }
  ]
}