{
  "type": "FeatureCollection",
  "title": "Arboukale/Albocela",
  "id": "236340",
  "description": "An ancient place, cited: BAtlas 24 F3 Arboukale/Albocela",
  "bbox": [
    -5.394988,
    41.525944,
    -5.394988,
    41.525944
  ],
  "reprPoint": [
    -5.394988,
    41.525944
  ],
  "names": [
    "Arboukale",
    "Albocela"
  ],
  "features": [
    {
      "geometry": {
        "type": "Point",
        "coordinates": [
          -5.394988,
          41.525944
        ]
      },
      "id": "darmc-location-19728",
      "type": "Feature",
      "properties": {
        "description": "1M scale point location",
        "location_precision": "precise",
        "title": "DARMC location 19728",
        "link": "http://pleiades.stoa.org/places/236340/darmc-location-19728"
      }
    }
  ]
}