{
  "type": "FeatureCollection",
  "title": "Amaia",
  "id": "236328",
  "description": "An ancient place, cited: BAtlas 24 G2 Amaia",
  "bbox": [
    -4.162806,
    42.642298,
    -4.162806,
    42.642298
  ],
  "reprPoint": [
    -4.162806,
    42.642298
  ],
  "names": [
    "Amaia"
  ],
  "features": [
    {
      "geometry": {
        "type": "Point",
        "coordinates": [
          -4.162806,
          42.642298
        ]
      },
      "id": "darmc-location-7574",
      "type": "Feature",
      "properties": {
        "description": "1M scale point location",
        "location_precision": "precise",
        "title": "DARMC location 7574",
        "link": "http://pleiades.stoa.org/places/236328/darmc-location-7574"
      }
    }
  ]
}