{
  "type": "FeatureCollection",
  "title": "Cale",
  "id": "236396",
  "bbox": [
    -8.610232,
    41.149974,
    -8.610232,
    41.149974
  ],
  "description": "Cale was the site of an ancient city located at the mouth of the Durius fl. The Roman colony Portus Cale was established there in 136 BC.",
  "connectsWith": [
    "236400",
    "236455"
  ],
  "names": [
    "Cale"
  ],
  "features": [
    {
      "type": "Feature",
      "geometry": {
        "type": "Point",
        "coordinates": [
          -8.610232,
          41.149974
        ]
      },
      "properties": {
        "description": "representative point"
      }
    },
    {
      "geometry": {
        "type": "Point",
        "coordinates": [
          -8.610232,
          41.149974
        ]
      },
      "id": "darmc-location-20094",
      "type": "Feature",
      "properties": {
        "description": "1:1 million scale representative point location digitized from the Barrington Atlas of the Greek and Roman World by the Digital Atlas of Roman and Medieval Civilizations project at Harvard University.",
        "location_precision": "precise",
        "title": "DARMC location 20094",
        "link": "http://pleiades.stoa.org/places/236396/darmc-location-20094"
      }
    }
  ]
}