{
  "type": "FeatureCollection",
  "title": "Amaia",
  "id": "236328",
  "bbox": [
    -4.1720898,
    42.6492328,
    -4.1720898,
    42.6492328
  ],
  "description": "An ancient place, cited: BAtlas 24 G2 Amaia",
  "names": [
    "Amaia"
  ],
  "features": [
    {
      "type": "Feature",
      "geometry": {
        "type": "Point",
        "coordinates": [
          -4.1720898,
          42.6492328
        ]
      },
      "properties": {
        "description": "representative point"
      }
    },
    {
      "geometry": {
        "type": "Point",
        "coordinates": [
          -4.1720898,
          42.6492328
        ]
      },
      "id": "osm-location",
      "type": "Feature",
      "properties": {
        "description": "Location based on OpenStreetMap",
        "location_precision": "precise",
        "title": "OSM location",
        "link": "http://pleiades.stoa.org/places/236328/osm-location"
      }
    }
  ]
}