{
  "type": "FeatureCollection",
  "title": "Cabeço de Mua",
  "id": "236391",
  "bbox": [
    -6.756811,
    41.247568,
    -6.756811,
    41.247568
  ],
  "description": "An ancient place, cited: BAtlas 24 E3 Cabeço de Mua",
  "features": [
    {
      "type": "Feature",
      "geometry": {
        "type": "Point",
        "coordinates": [
          -6.756811,
          41.247568
        ]
      },
      "properties": {
        "description": "representative point"
      }
    },
    {
      "geometry": {
        "type": "Point",
        "coordinates": [
          -6.756811,
          41.247568
        ]
      },
      "id": "darmc-location-19553",
      "type": "Feature",
      "properties": {
        "description": "1M scale point location",
        "location_precision": "precise",
        "title": "DARMC location 19553",
        "link": "http://pleiades.stoa.org/places/236391/darmc-location-19553"
      }
    }
  ]
}