{
  "type": "FeatureCollection",
  "title": "Cohors I Celtiberorum",
  "id": "236437",
  "description": "An ancient place, cited: BAtlas 24 C1 Cohors I Celtiberorum",
  "bbox": [
    -8.043758,
    43.084238,
    -8.043758,
    43.084238
  ],
  "reprPoint": [
    -8.043758,
    43.084238
  ],
  "names": [
    "Cohors I Celtiberorum"
  ],
  "features": [
    {
      "geometry": {
        "type": "Point",
        "coordinates": [
          -8.043758,
          43.084238
        ]
      },
      "id": "darmc-location-19093",
      "type": "Feature",
      "properties": {
        "description": "1M scale point location",
        "location_precision": "precise",
        "title": "DARMC location 19093",
        "link": "http://pleiades.stoa.org/places/236437/darmc-location-19093"
      }
    }
  ]
}