{
  "type": "FeatureCollection",
  "title": "Iuliobriga",
  "id": "236493",
  "description": "An ancient place, cited: BAtlas 24 G2 Iuliobriga",
  "bbox": [
    -4.113918,
    42.985111,
    -4.113918,
    42.985111
  ],
  "reprPoint": [
    -4.113918,
    42.985111
  ],
  "names": [
    "Iuliobriga"
  ],
  "features": [
    {
      "geometry": {
        "type": "Point",
        "coordinates": [
          -4.113918,
          42.985111
        ]
      },
      "id": "darmc-location-5353",
      "type": "Feature",
      "properties": {
        "description": "1M scale point location",
        "location_precision": "precise",
        "title": "DARMC location 5353",
        "link": "http://pleiades.stoa.org/places/236493/darmc-location-5353"
      }
    }
  ]
}