{
  "type": "FeatureCollection",
  "title": "Gemestarium",
  "id": "236473",
  "description": "An ancient place, cited: BAtlas 24 E2 Gemestarium",
  "bbox": [
    -6.904559,
    42.485118,
    -6.904559,
    42.485118
  ],
  "reprPoint": [
    -6.904559,
    42.485118
  ],
  "names": [
    "Gemestarium"
  ],
  "features": [
    {
      "geometry": {
        "type": "Point",
        "coordinates": [
          -6.904559,
          42.485118
        ]
      },
      "id": "darmc-location-19671",
      "type": "Feature",
      "properties": {
        "description": "1M scale point location",
        "location_precision": "precise",
        "title": "DARMC location 19671",
        "link": "http://pleiades.stoa.org/places/236473/darmc-location-19671"
      }
    }
  ]
}