{
  "type": "FeatureCollection",
  "title": "Castro Ventosa",
  "id": "236418",
  "bbox": [
    -6.754668,
    42.5993708,
    -6.754668,
    42.5993708
  ],
  "description": "An ancient place, cited: BAtlas 24 E2 Castro Ventosa",
  "features": [
    {
      "type": "Feature",
      "geometry": {
        "type": "Point",
        "coordinates": [
          -6.754668,
          42.5993708
        ]
      },
      "properties": {
        "description": "representative point"
      }
    },
    {
      "geometry": {
        "type": "Point",
        "coordinates": [
          -6.754668,
          42.5993708
        ]
      },
      "id": "osm-location-of-castro-ventosa",
      "type": "Feature",
      "properties": {
        "description": "Representative location based on OpenStreetMap",
        "location_precision": "precise",
        "title": "OSM location of Castro Ventosa",
        "link": "http://pleiades.stoa.org/places/236418/osm-location-of-castro-ventosa"
      }
    }
  ]
}