{
  "type": "FeatureCollection",
  "title": "Castro Ventosa",
  "id": "236418",
  "description": "An ancient place, cited: BAtlas 24 E2 Castro Ventosa",
  "bbox": [
    -6.725684,
    42.59986,
    -6.725684,
    42.59986
  ],
  "reprPoint": [
    -6.725684,
    42.59986
  ],
  "features": [
    {
      "geometry": {
        "type": "Point",
        "coordinates": [
          -6.725684,
          42.59986
        ]
      },
      "id": "darmc-location-20136",
      "type": "Feature",
      "properties": {
        "description": "1M scale point location",
        "location_precision": "precise",
        "title": "DARMC location 20136",
        "link": "http://pleiades.stoa.org/places/236418/darmc-location-20136"
      }
    }
  ]
}