{
  "type": "FeatureCollection",
  "title": "Lapatia Korou Akron/Trileukon (promontory)",
  "id": "236511",
  "bbox": [
    -7.8685184,
    43.7732744,
    -7.8685184,
    43.7732744
  ],
  "description": "The modern Punta dos Aguillóns, which is the eastern component of Cabo Ortegal, a cape on the Atlantic coast of modern Spain.",
  "names": [
    "Punta dos Aguillóns",
    "Lapatia Korou Akron",
    "Trileukon Pr."
  ],
  "features": [
    {
      "type": "Feature",
      "geometry": {
        "type": "Point",
        "coordinates": [
          -7.8685184,
          43.7732744
        ]
      },
      "properties": {
        "description": "representative point"
      }
    },
    {
      "geometry": {
        "type": "Point",
        "coordinates": [
          -7.8685184,
          43.7732744
        ]
      },
      "id": "osm-location-of-punta-dos-aguilla3s",
      "type": "Feature",
      "properties": {
        "description": "Location based on OpenStreetMap",
        "location_precision": "precise",
        "title": "OSM Location of Punta dos Aguillós",
        "link": "http://pleiades.stoa.org/places/236511/osm-location-of-punta-dos-aguilla3s"
      }
    }
  ]
}