{
  "type": "FeatureCollection",
  "title": "Monte Mozinho",
  "id": "236549",
  "description": "An ancient place, cited: BAtlas 24 C3 Monte Mozinho",
  "bbox": [
    -8.29381,
    41.1477,
    -8.29381,
    41.1477
  ],
  "reprPoint": [
    -8.29381,
    41.1477
  ],
  "features": [
    {
      "geometry": {
        "type": "Point",
        "coordinates": [
          -8.29381,
          41.1477
        ]
      },
      "id": "darmc-location-20495",
      "type": "Feature",
      "properties": {
        "description": "1M scale point location",
        "location_precision": "precise",
        "title": "DARMC location 20495",
        "link": "http://pleiades.stoa.org/places/236549/darmc-location-20495"
      }
    }
  ]
}