{
  "type": "FeatureCollection",
  "title": "Macedinho",
  "id": "236530",
  "bbox": [
    -7.104955,
    41.405245,
    -7.104955,
    41.405245
  ],
  "description": "An ancient place, cited: BAtlas 24 D3 Macedinho",
  "features": [
    {
      "type": "Feature",
      "geometry": {
        "type": "Point",
        "coordinates": [
          -7.104955,
          41.405245
        ]
      },
      "properties": {
        "description": "representative point"
      }
    },
    {
      "geometry": {
        "type": "Point",
        "coordinates": [
          -7.104955,
          41.405245
        ]
      },
      "id": "darmc-location-19527",
      "type": "Feature",
      "properties": {
        "description": "1M scale point location",
        "location_precision": "precise",
        "title": "DARMC location 19527",
        "link": "http://pleiades.stoa.org/places/236530/darmc-location-19527"
      }
    }
  ]
}