{
  "type": "FeatureCollection",
  "title": "Navatejera",
  "id": "236560",
  "description": "An ancient place, cited: BAtlas 24 F2 Navatejera",
  "bbox": [
    -5.57178,
    42.599832,
    -5.57178,
    42.599832
  ],
  "reprPoint": [
    -5.57178,
    42.599832
  ],
  "features": [
    {
      "geometry": {
        "type": "Point",
        "coordinates": [
          -5.57178,
          42.599832
        ]
      },
      "id": "darmc-location-21007",
      "type": "Feature",
      "properties": {
        "description": "1M scale point location",
        "location_precision": "precise",
        "title": "DARMC location 21007",
        "link": "http://pleiades.stoa.org/places/236560/darmc-location-21007"
      }
    }
  ]
}