{
  "type": "FeatureCollection",
  "title": "Petavonium",
  "id": "236598",
  "bbox": [
    -5.9981701,
    42.0898132,
    -5.9981701,
    42.0898132
  ],
  "description": "An ancient place, cited: BAtlas 24 F2 Petavonium",
  "names": [
    "Petavonium"
  ],
  "features": [
    {
      "type": "Feature",
      "geometry": {
        "type": "Point",
        "coordinates": [
          -5.9981701,
          42.0898132
        ]
      },
      "properties": {
        "description": "representative point"
      }
    },
    {
      "geometry": {
        "type": "Point",
        "coordinates": [
          -5.9981701,
          42.0898132
        ]
      },
      "id": "location-of-castrum",
      "type": "Feature",
      "properties": {
        "description": "Location based on OpenStreetMap",
        "location_precision": "precise",
        "title": "location of castrum",
        "link": "http://pleiades.stoa.org/places/236598/location-of-castrum"
      }
    }
  ]
}