{
  "type": "FeatureCollection",
  "title": "Monte Mozinho",
  "id": "236549",
  "bbox": [
    -8.3117268,
    41.146493,
    -8.3117268,
    41.146493
  ],
  "description": "An ancient place, cited: BAtlas 24 C3 Monte Mozinho",
  "connectsWith": [
    "927078047"
  ],
  "features": [
    {
      "type": "Feature",
      "geometry": {
        "type": "Point",
        "coordinates": [
          -8.3117268,
          41.146493
        ]
      },
      "properties": {
        "description": "representative point"
      }
    },
    {
      "geometry": {
        "type": "Point",
        "coordinates": [
          -8.3117268,
          41.146493
        ]
      },
      "id": "osm-location",
      "type": "Feature",
      "properties": {
        "description": "Representative location based on OpenStreetMap, chronology following Wikipedia.",
        "location_precision": "precise",
        "title": "OSM location of Castro de Monte Mozinho",
        "link": "http://pleiades.stoa.org/places/236549/osm-location"
      }
    }
  ]
}