{
  "type": "FeatureCollection",
  "title": "Petavonium",
  "id": "236598",
  "description": "An ancient place, cited: BAtlas 24 F2 Petavonium",
  "bbox": [
    -5.983374,
    42.08996,
    -5.983374,
    42.08996
  ],
  "reprPoint": [
    -5.983374,
    42.08996
  ],
  "names": [
    "Petavonium"
  ],
  "features": [
    {
      "geometry": {
        "type": "Point",
        "coordinates": [
          -5.983374,
          42.08996
        ]
      },
      "id": "darmc-location-19174",
      "type": "Feature",
      "properties": {
        "description": "1M scale point location",
        "location_precision": "precise",
        "title": "DARMC location 19174",
        "link": "http://pleiades.stoa.org/places/236598/darmc-location-19174"
      }
    }
  ]
}