{
  "type": "FeatureCollection",
  "title": "Mancellus",
  "id": "236533",
  "description": "An ancient place, cited: BAtlas 24 H2 Mancellus",
  "bbox": [
    -3.755971,
    42.025829,
    -3.755962,
    42.025843
  ],
  "reprPoint": [
    -3.7559665,
    42.025836
  ],
  "names": [
    "Mancellus"
  ],
  "features": [
    {
      "geometry": {
        "type": "Point",
        "coordinates": [
          -3.755971,
          42.025843
        ]
      },
      "id": "darmc-location-7274",
      "type": "Feature",
      "properties": {
        "description": "1M scale point location",
        "location_precision": "precise",
        "title": "DARMC location 7274",
        "link": "http://pleiades.stoa.org/places/236533/darmc-location-7274"
      }
    },
    {
      "geometry": {
        "type": "Point",
        "coordinates": [
          -3.755962,
          42.025829
        ]
      },
      "id": "darmc-location-7343",
      "type": "Feature",
      "properties": {
        "description": "1M scale point location",
        "location_precision": "precise",
        "title": "DARMC location 7343",
        "link": "http://pleiades.stoa.org/places/236533/darmc-location-7343"
      }
    }
  ]
}