{
  "type": "FeatureCollection",
  "title": "Memoriana",
  "id": "236541",
  "description": "An ancient place, cited: BAtlas 24 F1 Memoriana",
  "bbox": [
    -5.828947,
    43.1585,
    -5.828947,
    43.1585
  ],
  "reprPoint": [
    -5.828947,
    43.1585
  ],
  "names": [
    "Memoriana"
  ],
  "features": [
    {
      "geometry": {
        "type": "Point",
        "coordinates": [
          -5.828947,
          43.1585
        ]
      },
      "id": "darmc-location-19680",
      "type": "Feature",
      "properties": {
        "description": "1M scale point location",
        "location_precision": "precise",
        "title": "DARMC location 19680",
        "link": "http://pleiades.stoa.org/places/236541/darmc-location-19680"
      }
    }
  ]
}