{
  "type": "FeatureCollection",
  "title": "*Tongobriga",
  "id": "236685",
  "bbox": [
    -8.144603,
    41.159889,
    -8.144603,
    41.159889
  ],
  "description": "An ancient place, cited: BAtlas 24 C3 *Tongobriga",
  "names": [
    "Tongobriga",
    "Tountobriga"
  ],
  "features": [
    {
      "type": "Feature",
      "geometry": {
        "type": "Point",
        "coordinates": [
          -8.144603,
          41.159889
        ]
      },
      "properties": {
        "description": "representative point"
      }
    },
    {
      "geometry": {
        "type": "Point",
        "coordinates": [
          -8.144603,
          41.159889
        ]
      },
      "id": "darmc-location-2104",
      "type": "Feature",
      "properties": {
        "description": "1:1 million scale representative point location digitized from the Barrington Atlas of the Greek and Roman World by the Digital Atlas of Roman and Medieval Civilizations project at Harvard University.",
        "location_precision": "precise",
        "title": "DARMC location 2104",
        "link": "http://pleiades.stoa.org/places/236685/darmc-location-2104"
      }
    }
  ]
}