{
  "type": "FeatureCollection",
  "title": "Trileukoi (islands)",
  "id": "236689",
  "bbox": [
    -7.8684078,
    43.7778792,
    -7.8684078,
    43.7778792
  ],
  "description": "Small, rocky islets in Galicia located adjacent to Cabo Ortegal.",
  "names": [
    "Trileukoi",
    "Os Aguillons"
  ],
  "features": [
    {
      "type": "Feature",
      "geometry": {
        "type": "Point",
        "coordinates": [
          -7.8684078,
          43.7778792
        ]
      },
      "properties": {
        "description": "representative point"
      }
    },
    {
      "geometry": {
        "type": "Point",
        "coordinates": [
          -7.8684078,
          43.7778792
        ]
      },
      "id": "osm-location",
      "type": "Feature",
      "properties": {
        "description": "Location based on OpenStreetMap",
        "location_precision": "precise",
        "title": "OSM location of southernmost islet",
        "link": "http://pleiades.stoa.org/places/236689/osm-location"
      }
    }
  ]
}