{
  "type": "FeatureCollection",
  "title": "Tritium",
  "id": "236691",
  "bbox": [
    -3.484908,
    42.459336,
    -3.484908,
    42.459336
  ],
  "description": "An ancient place, cited: BAtlas 24 H2 Tritium",
  "names": [
    "Tritium"
  ],
  "features": [
    {
      "type": "Feature",
      "geometry": {
        "type": "Point",
        "coordinates": [
          -3.484908,
          42.459336
        ]
      },
      "properties": {
        "description": "representative point"
      }
    },
    {
      "geometry": {
        "type": "Point",
        "coordinates": [
          -3.484908,
          42.459336
        ]
      },
      "id": "darmc-location-2121",
      "type": "Feature",
      "properties": {
        "description": "1M scale point location",
        "location_precision": "precise",
        "title": "DARMC location 2121",
        "link": "http://pleiades.stoa.org/places/236691/darmc-location-2121"
      }
    }
  ]
}