{
  "type": "FeatureCollection",
  "title": "Pisoraca",
  "id": "236603",
  "bbox": [
    -4.33076,
    42.594547,
    -4.33076,
    42.594547
  ],
  "description": "An ancient place, cited: BAtlas 24 G2 Pisoraca",
  "names": [
    "Pisoraca",
    "Legio IV"
  ],
  "features": [
    {
      "type": "Feature",
      "geometry": {
        "type": "Point",
        "coordinates": [
          -4.33076,
          42.594547
        ]
      },
      "properties": {
        "description": "representative point"
      }
    },
    {
      "geometry": {
        "type": "Point",
        "coordinates": [
          -4.33076,
          42.594547
        ]
      },
      "id": "darmc-location-3451",
      "type": "Feature",
      "properties": {
        "description": "1M scale point location",
        "location_precision": "precise",
        "title": "DARMC location 3451",
        "link": "http://pleiades.stoa.org/places/236603/darmc-location-3451"
      }
    }
  ]
}