{
  "type": "FeatureCollection",
  "title": "El Raso",
  "id": "236626",
  "bbox": [
    -5.357813,
    40.1832267,
    -5.357813,
    40.1832267
  ],
  "description": "A fortified settlement of the Vettones located in the municipality of Candeleda (Ávila, Spain) near the hamlet of El Raso. Archaeological remains at the site consist of several walled enclosures distributed in at least three areas covering some 20 ha.",
  "connectsWith": [
    "236712"
  ],
  "features": [
    {
      "type": "Feature",
      "geometry": {
        "type": "Point",
        "coordinates": [
          -5.357813,
          40.1832267
        ]
      },
      "properties": {
        "description": "representative point"
      }
    },
    {
      "geometry": {
        "type": "Point",
        "coordinates": [
          -5.357813,
          40.1832267
        ]
      },
      "id": "el-raso",
      "type": "Feature",
      "properties": {
        "description": "Representative location based on a node derived from OpenStreetMap.",
        "location_precision": "precise",
        "title": "OSM location of Castro Celta de El Raso",
        "link": "http://pleiades.stoa.org/places/236626/el-raso"
      }
    }
  ]
}