{
  "type": "FeatureCollection",
  "title": "Três Minas",
  "id": "236688",
  "description": "An ancient place, cited: BAtlas 24 D3 Três Minas",
  "bbox": [
    -7.506858,
    41.492858,
    -7.506858,
    41.492858
  ],
  "reprPoint": [
    -7.506858,
    41.492858
  ],
  "features": [
    {
      "geometry": {
        "type": "Point",
        "coordinates": [
          -7.506858,
          41.492858
        ]
      },
      "id": "darmc-location-19542",
      "type": "Feature",
      "properties": {
        "description": "1M scale point location",
        "location_precision": "precise",
        "title": "DARMC location 19542",
        "link": "http://pleiades.stoa.org/places/236688/darmc-location-19542"
      }
    }
  ]
}