{
  "type": "FeatureCollection",
  "title": "Ruiseñada",
  "id": "236632",
  "description": "An ancient place, cited: BAtlas 24 G1 Ruiseñada",
  "bbox": [
    -4.290536,
    43.3639,
    -4.290536,
    43.3639
  ],
  "reprPoint": [
    -4.290536,
    43.3639
  ],
  "features": [
    {
      "geometry": {
        "type": "Point",
        "coordinates": [
          -4.290536,
          43.3639
        ]
      },
      "id": "darmc-location-19428",
      "type": "Feature",
      "properties": {
        "description": "1M scale point location",
        "location_precision": "precise",
        "title": "DARMC location 19428",
        "link": "http://pleiades.stoa.org/places/236632/darmc-location-19428"
      }
    }
  ]
}