{
  "type": "FeatureCollection",
  "title": "Torre de Hércules",
  "id": "236686",
  "description": "A lighthouse that has served as a marker for the  La Coruña harbor since the late first century AD.",
  "bbox": [
    -8.406686,
    43.385907,
    -8.406686,
    43.385907
  ],
  "reprPoint": [
    -8.406686,
    43.385907
  ],
  "features": [
    {
      "geometry": {
        "type": "Point",
        "coordinates": [
          -8.406686,
          43.385907
        ]
      },
      "id": "darmc-location-33831",
      "type": "Feature",
      "properties": {
        "description": "scale point location",
        "location_precision": "precise",
        "title": "DARMC location 33831",
        "link": "http://pleiades.stoa.org/places/236686/darmc-location-33831"
      }
    }
  ]
}