{
  "type": "FeatureCollection",
  "title": "El Raso",
  "id": "236626",
  "bbox": [
    -5.339144,
    40.170422,
    -5.339144,
    40.170422
  ],
  "description": "An ancient place, cited: BAtlas 24 F4 El Raso",
  "features": [
    {
      "type": "Feature",
      "geometry": {
        "type": "Point",
        "coordinates": [
          -5.339144,
          40.170422
        ]
      },
      "properties": {
        "description": "representative point"
      }
    },
    {
      "geometry": {
        "type": "Point",
        "coordinates": [
          -5.339144,
          40.170422
        ]
      },
      "id": "darmc-location-969",
      "type": "Feature",
      "properties": {
        "description": "1M scale point location",
        "location_precision": "precise",
        "title": "DARMC location 969",
        "link": "http://pleiades.stoa.org/places/236626/darmc-location-969"
      }
    }
  ]
}