{
  "type": "FeatureCollection",
  "title": "S. Olaia",
  "id": "236649",
  "description": "An ancient place, cited: BAtlas 24 C4 S. Olaia",
  "bbox": [
    -8.866464,
    40.147942,
    -8.866464,
    40.147942
  ],
  "reprPoint": [
    -8.866464,
    40.147942
  ],
  "features": [
    {
      "geometry": {
        "type": "Point",
        "coordinates": [
          -8.866464,
          40.147942
        ]
      },
      "id": "darmc-location-3061",
      "type": "Feature",
      "properties": {
        "description": "1M scale point location",
        "location_precision": "precise",
        "title": "DARMC location 3061",
        "link": "http://pleiades.stoa.org/places/236649/darmc-location-3061"
      }
    }
  ]
}