{
  "type": "FeatureCollection",
  "title": "Los Pradillos",
  "id": "236615",
  "bbox": [
    -4.359225,
    42.617023,
    -4.359225,
    42.617023
  ],
  "description": "An ancient place, cited: BAtlas 24 G2 Los Pradillos",
  "features": [
    {
      "type": "Feature",
      "geometry": {
        "type": "Point",
        "coordinates": [
          -4.359225,
          42.617023
        ]
      },
      "properties": {
        "description": "representative point"
      }
    },
    {
      "geometry": {
        "type": "Point",
        "coordinates": [
          -4.359225,
          42.617023
        ]
      },
      "id": "darmc-location-20976",
      "type": "Feature",
      "properties": {
        "description": "1M scale point location",
        "location_precision": "precise",
        "title": "DARMC location 20976",
        "link": "http://pleiades.stoa.org/places/236615/darmc-location-20976"
      }
    }
  ]
}