{
  "type": "FeatureCollection",
  "title": "Portus Victoriae Iuliobrigensium",
  "id": "236613",
  "bbox": [
    -3.807998,
    43.460818,
    -3.807998,
    43.460818
  ],
  "description": "An ancient place, cited: BAtlas 24 H1 Portus Victoriae Iuliobrigensium",
  "names": [
    "Portus Victoriae Iuliobrigensium"
  ],
  "features": [
    {
      "type": "Feature",
      "geometry": {
        "type": "Point",
        "coordinates": [
          -3.807998,
          43.460818
        ]
      },
      "properties": {
        "description": "representative point"
      }
    },
    {
      "geometry": {
        "type": "Point",
        "coordinates": [
          -3.807998,
          43.460818
        ]
      },
      "id": "darmc-location-2060",
      "type": "Feature",
      "properties": {
        "description": "1M scale point location",
        "location_precision": "precise",
        "title": "DARMC location 2060",
        "link": "http://pleiades.stoa.org/places/236613/darmc-location-2060"
      }
    }
  ]
}