{
  "type": "FeatureCollection",
  "title": "Sanfins",
  "id": "236651",
  "description": "An ancient place, cited: BAtlas 24 C3 Sanfins",
  "bbox": [
    -8.385957,
    41.323876,
    -8.382506,
    41.327553
  ],
  "reprPoint": [
    -8.3842315,
    41.3257145
  ],
  "features": [
    {
      "geometry": {
        "type": "Point",
        "coordinates": [
          -8.382506,
          41.327553
        ]
      },
      "id": "darmc-location-3095",
      "type": "Feature",
      "properties": {
        "description": "1M scale point location",
        "location_precision": "precise",
        "title": "DARMC location 3095",
        "link": "http://pleiades.stoa.org/places/236651/darmc-location-3095"
      }
    },
    {
      "geometry": {
        "type": "Point",
        "coordinates": [
          -8.385957,
          41.323876
        ]
      },
      "id": "dare-location",
      "type": "Feature",
      "properties": {
        "description": "Representative point location, site precision",
        "location_precision": "precise",
        "title": "DARE Location",
        "link": "http://pleiades.stoa.org/places/236651/dare-location"
      }
    }
  ]
}