{
  "type": "FeatureCollection",
  "title": "Tude/Castellum Tyde",
  "id": "236692",
  "description": "An ancient place, cited: BAtlas 24 C2 Tude/Castellum Tyde",
  "bbox": [
    -8.644839,
    42.046164,
    -8.644839,
    42.046164
  ],
  "reprPoint": [
    -8.644839,
    42.046164
  ],
  "names": [
    "Tude",
    "Castellum Tyde"
  ],
  "features": [
    {
      "geometry": {
        "type": "Point",
        "coordinates": [
          -8.643756,
          42.046197
        ]
      },
      "id": "darmc-location-19698",
      "type": "Feature",
      "properties": {
        "description": "1M scale point location",
        "location_precision": "precise",
        "title": "DARMC location 19698",
        "link": "http://pleiades.stoa.org/places/236692/darmc-location-19698"
      }
    },
    {
      "geometry": {
        "type": "Point",
        "coordinates": [
          -8.644839,
          42.046164
        ]
      },
      "id": "dare-location",
      "type": "Feature",
      "properties": {
        "description": "Representative point location, village precision",
        "location_precision": "precise",
        "title": "DARE Location",
        "link": "http://pleiades.stoa.org/places/236692/dare-location"
      }
    }
  ]
}