{
  "type": "FeatureCollection",
  "title": "Torre de Hércules",
  "id": "236686",
  "bbox": [
    -8.406686,
    43.385907,
    -8.406686,
    43.385907
  ],
  "description": "A lighthouse that has served as a marker for the La Coruña harbor since the late first century AD.",
  "names": [
    "Tower of Hercules"
  ],
  "features": [
    {
      "type": "Feature",
      "geometry": {
        "type": "Point",
        "coordinates": [
          -8.406686,
          43.385907
        ]
      },
      "properties": {
        "description": "representative point"
      }
    },
    {
      "geometry": {
        "type": "Point",
        "coordinates": [
          -8.406686,
          43.385907
        ]
      },
      "id": "darmc-location-33831",
      "type": "Feature",
      "properties": {
        "description": "representative point location digitized from the Barrington Atlas of the Greek and Roman World by the Digital Atlas of Roman and Medieval Civilizations project at Harvard University.",
        "location_precision": "precise",
        "title": "DARMC location 33831",
        "link": "http://pleiades.stoa.org/places/236686/darmc-location-33831"
      }
    }
  ]
}