{
  "type": "FeatureCollection",
  "title": "Vicus Veniensis",
  "id": "236718",
  "bbox": [
    -7.186387,
    40.228178,
    -7.186387,
    40.228178
  ],
  "description": "An ancient place, cited: BAtlas 24 D4 Vicus Veniensis",
  "names": [
    "Vicus Veniensis"
  ],
  "features": [
    {
      "type": "Feature",
      "geometry": {
        "type": "Point",
        "coordinates": [
          -7.186387,
          40.228178
        ]
      },
      "properties": {
        "description": "representative point"
      }
    },
    {
      "geometry": {
        "type": "Point",
        "coordinates": [
          -7.186387,
          40.228178
        ]
      },
      "id": "darmc-location-3708",
      "type": "Feature",
      "properties": {
        "description": "1M scale point location",
        "location_precision": "precise",
        "title": "DARMC location 3708",
        "link": "http://pleiades.stoa.org/places/236718/darmc-location-3708"
      }
    }
  ]
}