{
  "type": "FeatureCollection",
  "title": "Nadlesk",
  "id": "237312030",
  "bbox": [
    14.4659596,
    45.7046923,
    14.4659596,
    45.7046923
  ],
  "description": "Nadlesk, Slovenia, was the site of a Roman fortification and associated settlement.",
  "features": [
    {
      "type": "Feature",
      "geometry": {
        "type": "Point",
        "coordinates": [
          14.4659596,
          45.7046923
        ]
      },
      "properties": {
        "description": "representative point"
      }
    },
    {
      "geometry": {
        "type": "Point",
        "coordinates": [
          14.4659596,
          45.7046923
        ]
      },
      "id": "osm-location-of-nadlesk",
      "type": "Feature",
      "properties": {
        "description": "Location based on OpenStreetMap",
        "location_precision": "precise",
        "title": "OSM location of Nadlesk",
        "link": "http://pleiades.stoa.org/places/237312030/osm-location-of-nadlesk"
      }
    }
  ]
}