{
  "type": "FeatureCollection",
  "title": "Roman villa at Tourmont",
  "id": "237325182",
  "bbox": [
    5.68273,
    46.8604,
    5.68273,
    46.8604
  ],
  "description": "Remains of a large Roman villa and site of a significant coin hoard of the third century A.D.",
  "features": [
    {
      "type": "Feature",
      "geometry": {
        "type": "Point",
        "coordinates": [
          5.68273,
          46.8604
        ]
      },
      "properties": {
        "description": "representative point"
      }
    },
    {
      "geometry": {
        "type": "Point",
        "coordinates": [
          5.68273,
          46.8604
        ]
      },
      "id": "osm-location-of-modern-tourmont",
      "type": "Feature",
      "properties": {
        "description": "Location based on OpenStreetMap",
        "location_precision": "precise",
        "title": "OSM location of modern Tourmont",
        "link": "http://pleiades.stoa.org/places/237325182/osm-location-of-modern-tourmont"
      }
    }
  ]
}