{
  "type": "FeatureCollection",
  "title": "Nuraghe Sa Ucchiusura",
  "id": "237657886",
  "bbox": [
    8.7482268,
    40.2937405,
    8.7482268,
    40.2937405
  ],
  "description": "A monopteral nuraghe built of trachite. The ruined walls stand to at least four meters in height.",
  "connectsWith": [
    "472014"
  ],
  "features": [
    {
      "type": "Feature",
      "geometry": {
        "type": "Point",
        "coordinates": [
          8.7482268,
          40.2937405
        ]
      },
      "properties": {
        "description": "representative point"
      }
    },
    {
      "geometry": {
        "type": "Point",
        "coordinates": [
          8.7482268,
          40.2937405
        ]
      },
      "id": "osm-location",
      "type": "Feature",
      "properties": {
        "description": "Representative location based on OpenStreetMap",
        "location_precision": "precise",
        "title": "OSM location of Nuraghe Sa Ucchiusura",
        "link": "http://pleiades.stoa.org/places/237657886/osm-location"
      }
    }
  ]
}