{
  "type": "FeatureCollection",
  "title": "Cáparra Roman bridge",
  "id": "237854",
  "bbox": [
    -6.1037,
    40.1703,
    -6.1037,
    40.1703
  ],
  "description": "An unnamed bridge over the river Caparra, just north of ancient Capera, which is west-southwest of modern Casablanca (Guijo de Granadilla, Caceres, Extremadura, Spain)",
  "features": [
    {
      "type": "Feature",
      "geometry": {
        "type": "Point",
        "coordinates": [
          -6.1037,
          40.1703
        ]
      },
      "properties": {
        "description": "representative point"
      }
    },
    {
      "geometry": {
        "type": "Point",
        "coordinates": [
          -6.1037,
          40.1703
        ]
      },
      "id": "bridge-near-capera",
      "type": "Feature",
      "properties": {
        "description": null,
        "location_precision": "precise",
        "title": "location of bridge near Capera",
        "link": "http://pleiades.stoa.org/places/237854/bridge-near-capera"
      }
    }
  ]
}