{
  "type": "FeatureCollection",
  "title": "Puente Mayor del Tormes",
  "id": "237851",
  "description": "A Roman bridge over Rio Tormes in Salamanca, Spain.",
  "bbox": [
    -5.67,
    40.958,
    -5.67,
    40.958
  ],
  "reprPoint": [
    -5.67,
    40.958
  ],
  "features": [
    {
      "geometry": {
        "type": "Point",
        "coordinates": [
          -5.67,
          40.958
        ]
      },
      "id": "location-if-bridge-at-salamantica-over-r.-tormes",
      "type": "Feature",
      "properties": {
        "description": null,
        "location_precision": "precise",
        "title": "Location of bridge over R. Tormes at Salmantica",
        "link": "http://pleiades.stoa.org/places/237851/location-if-bridge-at-salamantica-over-r.-tormes"
      }
    }
  ]
}