{
  "type": "FeatureCollection",
  "title": "Cáparra Roman bridge",
  "id": "237854",
  "bbox": [
    -6.1025093,
    40.1706877,
    -6.1025093,
    40.1706877
  ],
  "description": "An unnamed bridge over the river Caparra, just north of ancient Capera, which is west-southwest of modern Casablanca (Guijo de Granadilla, Caceres, Extremadura, Spain)",
  "features": [
    {
      "type": "Feature",
      "geometry": {
        "type": "Point",
        "coordinates": [
          -6.1025093,
          40.1706877
        ]
      },
      "properties": {
        "description": "representative point"
      }
    },
    {
      "geometry": {
        "type": "Point",
        "coordinates": [
          -6.1025093,
          40.1706877
        ]
      },
      "id": "osm-location-of-puente-romano-de-ca-parra",
      "type": "Feature",
      "properties": {
        "description": "Representative location based on OpenStreetMap",
        "location_precision": "precise",
        "title": "OSM location of Puente Romano de Cáparra",
        "link": "http://pleiades.stoa.org/places/237854/osm-location-of-puente-romano-de-ca-parra"
      }
    }
  ]
}