{
  "type": "FeatureCollection",
  "title": "Sanctuary at Leben",
  "id": "238864239",
  "bbox": [
    24.9240693,
    34.9324766,
    24.9240693,
    34.9324766
  ],
  "description": "Leben is known for a sanctuary of Asklepios at Leben dating to the first and second centuries CE.",
  "connectsWith": [
    "589901"
  ],
  "features": [
    {
      "type": "Feature",
      "geometry": {
        "type": "Point",
        "coordinates": [
          24.9240693,
          34.9324766
        ]
      },
      "properties": {
        "description": "representative point"
      }
    },
    {
      "geometry": {
        "type": "Point",
        "coordinates": [
          24.9240693,
          34.9324766
        ]
      },
      "id": "osm-location-of-sanctuary",
      "type": "Feature",
      "properties": {
        "description": "Representative location based on OpenStreetMap.",
        "location_precision": "precise",
        "title": "OSM location of sanctuary",
        "link": "http://pleiades.stoa.org/places/238864239/osm-location-of-sanctuary"
      }
    }
  ]
}