{
  "type": "FeatureCollection",
  "title": "Untitled",
  "id": "239338",
  "description": "An ancient place, cited: BAtlas 24 F1 unnamed pass (SE Memoriana)",
  "bbox": [
    -5.661563,
    43.062432,
    -5.661563,
    43.062432
  ],
  "reprPoint": [
    -5.661563,
    43.062432
  ],
  "features": [
    {
      "geometry": {
        "type": "Point",
        "coordinates": [
          -5.661563,
          43.062432
        ]
      },
      "id": "darmc-location-29583",
      "type": "Feature",
      "properties": {
        "description": "500K scale point location",
        "location_precision": "precise",
        "title": "DARMC location 29583",
        "link": "http://pleiades.stoa.org/places/239338/darmc-location-29583"
      }
    }
  ]
}