{
  "type": "FeatureCollection",
  "title": "Villa of Lucius Nonius Calpurnius Torquatus Asprenas",
  "id": "239384580",
  "bbox": [
    12.417829,
    41.793932,
    12.417829,
    41.793932
  ],
  "description": "The remains of a Roman villa on the Via Ostiense have been linked to Lucius Nonius Calpurnius Torquatus Asprenas.",
  "features": [
    {
      "type": "Feature",
      "geometry": {
        "type": "Point",
        "coordinates": [
          12.417829,
          41.793932
        ]
      },
      "properties": {
        "description": "representative point"
      }
    },
    {
      "geometry": {
        "type": "Point",
        "coordinates": [
          12.417829,
          41.793932
        ]
      },
      "id": "imagery-location-of-cistern",
      "type": "Feature",
      "properties": {
        "description": null,
        "location_precision": "precise",
        "title": "Imagery location of cistern",
        "link": "http://pleiades.stoa.org/places/239384580/imagery-location-of-cistern"
      }
    }
  ]
}