{
  "type": "FeatureCollection",
  "title": "Münster-Sarmsheim Roman Villa",
  "id": "24337731",
  "bbox": [
    7.8971815,
    49.946831,
    7.8971815,
    49.946831
  ],
  "description": "Remains of a Roman villa, including mosaic pavements, were discovered.",
  "features": [
    {
      "type": "Feature",
      "geometry": {
        "type": "Point",
        "coordinates": [
          7.8971815,
          49.946831
        ]
      },
      "properties": {
        "description": "representative point"
      }
    },
    {
      "geometry": {
        "type": "Point",
        "coordinates": [
          7.8971815,
          49.946831
        ]
      },
      "id": "osm-location-of-rapmerstraae-2-ma1-4nster",
      "type": "Feature",
      "properties": {
        "description": "Location based on OpenStreetMap. Mosaic findspot per PECS.",
        "location_precision": "precise",
        "title": "OSM Location of Römerstraße 2, Münster-Sarmsheim",
        "link": "http://pleiades.stoa.org/places/24337731/osm-location-of-rapmerstraae-2-ma1-4nster"
      }
    }
  ]
}