{
  "type": "FeatureCollection",
  "title": "Pont de Bornègre",
  "id": "244926839",
  "bbox": [
    4.4760982,
    43.9837547,
    4.4760982,
    43.9837547
  ],
  "description": "A Roman aqueduct bridge connected to the Roman aqueduct of Nîmes.",
  "connectsWith": [
    "148738"
  ],
  "features": [
    {
      "type": "Feature",
      "geometry": {
        "type": "Point",
        "coordinates": [
          4.4760982,
          43.9837547
        ]
      },
      "properties": {
        "description": "representative point"
      }
    },
    {
      "geometry": {
        "type": "Point",
        "coordinates": [
          4.4760982,
          43.9837547
        ]
      },
      "id": "location-of-ponte-de-bornegre",
      "type": "Feature",
      "properties": {
        "description": "Representative location based on OpenStreetMap.",
        "location_precision": "precise",
        "title": "OSM location of Ponte de Bornegre",
        "link": "http://pleiades.stoa.org/places/244926839/location-of-ponte-de-bornegre"
      }
    }
  ]
}