{
  "type": "FeatureCollection",
  "title": "Gallo-Roman settlement, locality of Courac",
  "id": "244926838",
  "bbox": [
    4.5867846,
    44.106589,
    4.5867846,
    44.106589
  ],
  "description": "Near the locality of Courac, just north of modern Tresques, are the remains of a diffuse Gallo-Roman settlement occupied from the first to fourth centuries A.D.",
  "features": [
    {
      "type": "Feature",
      "geometry": {
        "type": "Point",
        "coordinates": [
          4.5867846,
          44.106589
        ]
      },
      "properties": {
        "description": "representative point"
      }
    },
    {
      "geometry": {
        "type": "Point",
        "coordinates": [
          4.5867846,
          44.106589
        ]
      },
      "id": "tresques",
      "type": "Feature",
      "properties": {
        "description": "Representative location based on OpenStreetMap.",
        "location_precision": "precise",
        "title": "OSM location of modern Tresques",
        "link": "http://pleiades.stoa.org/places/244926838/tresques"
      }
    }
  ]
}