{
  "type": "FeatureCollection",
  "title": "Civitavecchia di Arpino",
  "id": "245569735",
  "bbox": [
    13.617578,
    41.648294,
    13.617578,
    41.648294
  ],
  "description": "The fortified acropolis of the ancient city of Arpinum.",
  "connectsWith": [
    "432700"
  ],
  "features": [
    {
      "type": "Feature",
      "geometry": {
        "type": "Point",
        "coordinates": [
          13.617578,
          41.648294
        ]
      },
      "properties": {
        "description": "representative point"
      }
    },
    {
      "geometry": {
        "type": "Point",
        "coordinates": [
          13.617578,
          41.648294
        ]
      },
      "id": "civitavecchia-di-arpino",
      "type": "Feature",
      "properties": {
        "description": "Acropolis of the ancient city of Arpinum. Coordinates following GeoHack.",
        "location_precision": "precise",
        "title": "Imagery location of Civitavecchia di Arpino",
        "link": "http://pleiades.stoa.org/places/245569735/civitavecchia-di-arpino"
      }
    }
  ]
}