{
  "type": "FeatureCollection",
  "title": "Andelos",
  "id": "246163",
  "description": "A Roman settlement in Spain",
  "bbox": [
    -1.8593,
    42.5992,
    -1.8593,
    42.5992
  ],
  "reprPoint": [
    -1.8593,
    42.5992
  ],
  "names": [
    "Andelos"
  ],
  "features": [
    {
      "geometry": {
        "type": "Point",
        "coordinates": [
          -1.8593,
          42.5992
        ]
      },
      "id": "center-point-of-visible-ancient-remains-andelos",
      "type": "Feature",
      "properties": {
        "description": null,
        "location_precision": "precise",
        "title": "Center point of visible ancient remains - Andelos",
        "link": "http://pleiades.stoa.org/places/246163/center-point-of-visible-ancient-remains-andelos"
      }
    }
  ]
}