{
  "type": "FeatureCollection",
  "title": "Alto de los Casares",
  "id": "246160",
  "bbox": [
    -2.230739,
    42.030204,
    -2.230739,
    42.030204
  ],
  "description": "An ancient place, cited: BAtlas 25 C3 Alto de los Casares",
  "features": [
    {
      "type": "Feature",
      "geometry": {
        "type": "Point",
        "coordinates": [
          -2.230739,
          42.030204
        ]
      },
      "properties": {
        "description": "representative point"
      }
    },
    {
      "geometry": {
        "type": "Point",
        "coordinates": [
          -2.230739,
          42.030204
        ]
      },
      "id": "darmc-location-19961",
      "type": "Feature",
      "properties": {
        "description": "1M scale point location",
        "location_precision": "precise",
        "title": "DARMC location 19961",
        "link": "http://pleiades.stoa.org/places/246160/darmc-location-19961"
      }
    }
  ]
}