{
  "type": "FeatureCollection",
  "title": "Albiga",
  "id": "246155",
  "description": "An ancient place, cited: BAtlas 25 H2 Albiga",
  "bbox": [
    2.14259,
    43.928513,
    2.14259,
    43.928513
  ],
  "reprPoint": [
    2.14259,
    43.928513
  ],
  "names": [
    "Albi",
    "Albiga"
  ],
  "features": [
    {
      "geometry": {
        "type": "Point",
        "coordinates": [
          2.146408,
          43.928255
        ]
      },
      "id": "darmc-location-11296",
      "type": "Feature",
      "properties": {
        "description": "1M scale point location",
        "location_precision": "precise",
        "title": "DARMC location 11296",
        "link": "http://pleiades.stoa.org/places/246155/darmc-location-11296"
      }
    },
    {
      "geometry": {
        "type": "Point",
        "coordinates": [
          2.14259,
          43.928513
        ]
      },
      "id": "dare-location",
      "type": "Feature",
      "properties": {
        "description": "Representative point location, site precision",
        "location_precision": "precise",
        "title": "DARE Location",
        "link": "http://pleiades.stoa.org/places/246155/dare-location"
      }
    }
  ]
}