{
  "type": "FeatureCollection",
  "title": "Ardiège",
  "id": "246184",
  "description": "An ancient place, cited: BAtlas 25 F2 Ardiège",
  "bbox": [
    0.642715,
    43.069472,
    0.642715,
    43.069472
  ],
  "reprPoint": [
    0.642715,
    43.069472
  ],
  "features": [
    {
      "geometry": {
        "type": "Point",
        "coordinates": [
          0.642715,
          43.069472
        ]
      },
      "id": "darmc-location-9171",
      "type": "Feature",
      "properties": {
        "description": "1M scale point location",
        "location_precision": "precise",
        "title": "DARMC location 9171",
        "link": "http://pleiades.stoa.org/places/246184/darmc-location-9171"
      }
    }
  ]
}