{
  "type": "FeatureCollection",
  "title": "Atax fl.",
  "id": "246199",
  "description": "The Aude river.",
  "bbox": [
    2.8706087,
    43.2125,
    3.240278,
    43.2350237
  ],
  "reprPoint": [
    3.05544335,
    43.22376185
  ],
  "names": [
    "Atax",
    "Narbon"
  ],
  "features": [
    {
      "geometry": {
        "type": "Point",
        "coordinates": [
          3.240278,
          43.2125
        ]
      },
      "id": "location-of-atax-fl.mouth",
      "type": "Feature",
      "properties": {
        "description": "verified in Google Earth.",
        "location_precision": "precise",
        "title": "location of Atax fl.mouth",
        "link": "http://pleiades.stoa.org/places/246199/location-of-atax-fl.mouth"
      }
    },
    {
      "geometry": {
        "type": "Point",
        "coordinates": [
          2.8706087,
          43.2350237
        ]
      },
      "id": "location-of-course-of-Atax-fl",
      "type": "Feature",
      "properties": {
        "description": "Location based on OpenStreetMap",
        "location_precision": "precise",
        "title": "location of course of Atax fl.",
        "link": "http://pleiades.stoa.org/places/246199/location-of-course-of-Atax-fl"
      }
    }
  ]
}