{
  "type": "FeatureCollection",
  "title": "Adeba",
  "id": "246145",
  "description": "An ancient place, cited: BAtlas 25 F5 Adeba",
  "bbox": [
    0.474684,
    40.471026,
    0.474684,
    40.471026
  ],
  "reprPoint": [
    0.474684,
    40.471026
  ],
  "names": [
    "Adeba"
  ],
  "features": [
    {
      "geometry": {
        "type": "Point",
        "coordinates": [
          0.474684,
          40.471026
        ]
      },
      "id": "darmc-location-19928",
      "type": "Feature",
      "properties": {
        "description": "1M scale point location",
        "location_precision": "precise",
        "title": "DARMC location 19928",
        "link": "http://pleiades.stoa.org/places/246145/darmc-location-19928"
      }
    }
  ]
}