{
  "type": "FeatureCollection",
  "title": "Ad Septimum Decimum",
  "id": "246140",
  "bbox": [
    1.176063,
    41.336206,
    1.176063,
    41.336206
  ],
  "description": "An ancient place, cited: BAtlas 25 G4 Ad Septimum Decimum",
  "names": [
    "Ad Septimum Decimum"
  ],
  "features": [
    {
      "type": "Feature",
      "geometry": {
        "type": "Point",
        "coordinates": [
          1.176063,
          41.336206
        ]
      },
      "properties": {
        "description": "representative point"
      }
    },
    {
      "geometry": {
        "type": "Point",
        "coordinates": [
          1.176063,
          41.336206
        ]
      },
      "id": "darmc-location-19242",
      "type": "Feature",
      "properties": {
        "description": "1M scale point location",
        "location_precision": "precise",
        "title": "DARMC location 19242",
        "link": "http://pleiades.stoa.org/places/246140/darmc-location-19242"
      }
    }
  ]
}