{
  "type": "FeatureCollection",
  "title": "El Atalayón",
  "id": "246198",
  "description": "An ancient place, cited: BAtlas 25 C4 El Atalayón",
  "bbox": [
    -2.383451,
    41.819995,
    -2.383451,
    41.819995
  ],
  "reprPoint": [
    -2.383451,
    41.819995
  ],
  "features": [
    {
      "geometry": {
        "type": "Point",
        "coordinates": [
          -2.383451,
          41.819995
        ]
      },
      "id": "darmc-location-19112",
      "type": "Feature",
      "properties": {
        "description": "1M scale point location",
        "location_precision": "precise",
        "title": "DARMC location 19112",
        "link": "http://pleiades.stoa.org/places/246198/darmc-location-19112"
      }
    }
  ]
}