{
  "type": "FeatureCollection",
  "title": "Carae/Caraca",
  "id": "246289",
  "description": "An ancient place, cited: BAtlas 25 D4 Carae/Caraca",
  "bbox": [
    -1.314129,
    41.087041,
    -1.314129,
    41.087041
  ],
  "reprPoint": [
    -1.314129,
    41.087041
  ],
  "names": [
    "Carae",
    "Caraca"
  ],
  "features": [
    {
      "geometry": {
        "type": "Point",
        "coordinates": [
          -1.314129,
          41.087041
        ]
      },
      "id": "darmc-location-7295",
      "type": "Feature",
      "properties": {
        "description": "1M scale point location",
        "location_precision": "precise",
        "title": "DARMC location 7295",
        "link": "http://pleiades.stoa.org/places/246289/darmc-location-7295"
      }
    }
  ]
}