{
  "type": "FeatureCollection",
  "title": "Calagurris (Nassica) Iulia",
  "id": "246279",
  "description": "Calagurris (Nassica) Iulia (modern Calahorra, Spain) was conquered by Rome in 187 BC and later supported Quintus Sertorius in his war against Cn. Pompeius Magnus.",
  "bbox": [
    -1.961128,
    42.301498,
    -1.961128,
    42.301498
  ],
  "reprPoint": [
    -1.961128,
    42.301498
  ],
  "names": [
    "Calagurris Nassica Iulia",
    "Calagurris Iulia"
  ],
  "features": [
    {
      "geometry": {
        "type": "Point",
        "coordinates": [
          -1.965033,
          42.303705
        ]
      },
      "id": "darmc-location-20091",
      "type": "Feature",
      "properties": {
        "description": "1M scale point location",
        "location_precision": "precise",
        "title": "DARMC location 20091",
        "link": "http://pleiades.stoa.org/places/246279/darmc-location-20091"
      }
    },
    {
      "geometry": {
        "type": "Point",
        "coordinates": [
          -1.961128,
          42.301498
        ]
      },
      "id": "dare-location",
      "type": "Feature",
      "properties": {
        "description": "Representative point location, site precision",
        "location_precision": "precise",
        "title": "DARE Location",
        "link": "http://pleiades.stoa.org/places/246279/dare-location"
      }
    }
  ]
}