{
  "type": "FeatureCollection",
  "title": "Bene(h)arnum",
  "id": "246237",
  "description": "An ancient place, cited: BAtlas 25 E2 Bene(h)arnum",
  "bbox": [
    -0.434655,
    43.332678,
    -0.434655,
    43.332678
  ],
  "reprPoint": [
    -0.434655,
    43.332678
  ],
  "names": [
    "Beneharnum",
    "Benearnum"
  ],
  "features": [
    {
      "geometry": {
        "type": "Point",
        "coordinates": [
          -0.434655,
          43.332678
        ]
      },
      "id": "darmc-location-11698",
      "type": "Feature",
      "properties": {
        "description": "1M scale point location",
        "location_precision": "precise",
        "title": "DARMC location 11698",
        "link": "http://pleiades.stoa.org/places/246237/darmc-location-11698"
      }
    }
  ]
}