{
  "type": "FeatureCollection",
  "title": "Ayerdi",
  "id": "246216",
  "description": "An ancient place, cited: BAtlas 25 D2 Ayerdi",
  "bbox": [
    -1.620214,
    42.998188,
    -1.620214,
    42.998188
  ],
  "reprPoint": [
    -1.620214,
    42.998188
  ],
  "features": [
    {
      "geometry": {
        "type": "Point",
        "coordinates": [
          -1.620214,
          42.998188
        ]
      },
      "id": "darmc-location-19477",
      "type": "Feature",
      "properties": {
        "description": "1M scale point location",
        "location_precision": "precise",
        "title": "DARMC location 19477",
        "link": "http://pleiades.stoa.org/places/246216/darmc-location-19477"
      }
    }
  ]
}