{
  "type": "FeatureCollection",
  "title": "Carae/Caraca",
  "id": "246289",
  "bbox": [
    -1.314129,
    41.087041,
    -1.314129,
    41.087041
  ],
  "description": "An unlocated Roman road station that, according to the Antonine Itinerary, was located between Agiria (modern Calamocha or Salvacañete?) and Sermonae (Cariñena?) on the Roman road from Laminium (Alhambra?) to Caesaraugusta (Zaragosa). It may be the same place as one \"Caraca\" mentioned by the Geographer of Ravenna as lying between Complutum (Alcalá de Henares) and \"Puteis\".",
  "connectsWith": [
    "246649"
  ],
  "names": [
    "Carae",
    "Caraca"
  ],
  "features": [
    {
      "type": "Feature",
      "geometry": {
        "type": "Point",
        "coordinates": [
          -1.314129,
          41.087041
        ]
      },
      "properties": {
        "description": "representative point"
      }
    },
    {
      "geometry": {
        "type": "Point",
        "coordinates": [
          -1.314129,
          41.087041
        ]
      },
      "id": "darmc-location-7295",
      "type": "Feature",
      "properties": {
        "description": "1:1 million scale representative point location digitized from the Barrington Atlas of the Greek and Roman World by the Digital Atlas of Roman and Medieval Civilizations project at Harvard University.",
        "location_precision": "precise",
        "title": "DARMC location 7295",
        "link": "http://pleiades.stoa.org/places/246289/darmc-location-7295"
      }
    }
  ]
}