{
  "type": "FeatureCollection",
  "title": "*Badera",
  "id": "246218",
  "description": "An ancient place, cited: BAtlas 25 G2 *Badera",
  "bbox": [
    1.612796,
    43.455038,
    1.612796,
    43.455038
  ],
  "reprPoint": [
    1.612796,
    43.455038
  ],
  "names": [
    "Badera"
  ],
  "features": [
    {
      "geometry": {
        "type": "Point",
        "coordinates": [
          1.612796,
          43.455038
        ]
      },
      "id": "darmc-location-7980",
      "type": "Feature",
      "properties": {
        "description": "1M scale point location",
        "location_precision": "precise",
        "title": "DARMC location 7980",
        "link": "http://pleiades.stoa.org/places/246218/darmc-location-7980"
      }
    }
  ]
}