{
  "type": "FeatureCollection",
  "title": "Col. Caesaraugusta",
  "id": "246344",
  "bbox": [
    -0.901469,
    41.652123,
    -0.876643,
    41.694308
  ],
  "description": "An ancient place, cited: BAtlas 25 E4 Col. Caesaraugusta",
  "names": [
    "Col. Caesaraugusta",
    "Zaragoza"
  ],
  "features": [
    {
      "type": "Feature",
      "geometry": {
        "type": "Point",
        "coordinates": [
          -0.885335333333,
          41.6675596667
        ]
      },
      "properties": {
        "description": "representative point"
      }
    },
    {
      "geometry": {
        "type": "Point",
        "coordinates": [
          -0.876643,
          41.656248
        ]
      },
      "id": "darmc-location-20179",
      "type": "Feature",
      "properties": {
        "description": "1M scale point location",
        "location_precision": "precise",
        "title": "DARMC location 20179",
        "link": "http://pleiades.stoa.org/places/246344/darmc-location-20179"
      }
    },
    {
      "geometry": {
        "type": "Point",
        "coordinates": [
          -0.901469,
          41.694308
        ]
      },
      "id": "darmc-location-30087",
      "type": "Feature",
      "properties": {
        "description": "5M scale point location",
        "location_precision": "precise",
        "title": "DARMC location 30087",
        "link": "http://pleiades.stoa.org/places/246344/darmc-location-30087"
      }
    },
    {
      "geometry": {
        "type": "Point",
        "coordinates": [
          -0.877894,
          41.652123
        ]
      },
      "id": "dare-location",
      "type": "Feature",
      "properties": {
        "description": "Representative point location, site precision",
        "location_precision": "precise",
        "title": "DARE Location",
        "link": "http://pleiades.stoa.org/places/246344/dare-location"
      }
    }
  ]
}