{
  "type": "FeatureCollection",
  "title": "Espejón",
  "id": "246387",
  "bbox": [
    -3.259624,
    41.830958,
    -3.259624,
    41.830958
  ],
  "description": "An ancient place, cited: BAtlas 25 B4 Espejón",
  "features": [
    {
      "type": "Feature",
      "geometry": {
        "type": "Point",
        "coordinates": [
          -3.259624,
          41.830958
        ]
      },
      "properties": {
        "description": "representative point"
      }
    },
    {
      "geometry": {
        "type": "Point",
        "coordinates": [
          -3.259624,
          41.830958
        ]
      },
      "id": "darmc-location-19501",
      "type": "Feature",
      "properties": {
        "description": "1M scale point location",
        "location_precision": "precise",
        "title": "DARMC location 19501",
        "link": "http://pleiades.stoa.org/places/246387/darmc-location-19501"
      }
    }
  ]
}