{
  "type": "FeatureCollection",
  "title": "Contrebia (Belaisca)",
  "id": "246355",
  "bbox": [
    -1.030536,
    41.509148,
    -1.030536,
    41.509148
  ],
  "description": "An ancient place, cited: BAtlas 25 D4 Contrebia (Belaisca)",
  "names": [
    "Contrebia Belaisca",
    "Contrebia"
  ],
  "features": [
    {
      "type": "Feature",
      "geometry": {
        "type": "Point",
        "coordinates": [
          -1.030536,
          41.509148
        ]
      },
      "properties": {
        "description": "representative point"
      }
    },
    {
      "geometry": {
        "type": "Point",
        "coordinates": [
          -1.030536,
          41.509148
        ]
      },
      "id": "darmc-location-20193",
      "type": "Feature",
      "properties": {
        "description": "1M scale point location",
        "location_precision": "precise",
        "title": "DARMC location 20193",
        "link": "http://pleiades.stoa.org/places/246355/darmc-location-20193"
      }
    }
  ]
}