{
  "type": "FeatureCollection",
  "title": "Cinniana",
  "id": "246335",
  "bbox": [
    2.910473,
    42.066067,
    2.910473,
    42.066067
  ],
  "description": "An ancient place, cited: BAtlas 25 H3 Cinniana",
  "names": [
    "Cinniana",
    "Cilniana"
  ],
  "features": [
    {
      "type": "Feature",
      "geometry": {
        "type": "Point",
        "coordinates": [
          2.910473,
          42.066067
        ]
      },
      "properties": {
        "description": "representative point"
      }
    },
    {
      "geometry": {
        "type": "Point",
        "coordinates": [
          2.910473,
          42.066067
        ]
      },
      "id": "darmc-location-8565",
      "type": "Feature",
      "properties": {
        "description": "1M scale point location",
        "location_precision": "precise",
        "title": "DARMC location 8565",
        "link": "http://pleiades.stoa.org/places/246335/darmc-location-8565"
      }
    }
  ]
}