{
  "type": "FeatureCollection",
  "title": "Fesciago",
  "id": "246390",
  "description": "An ancient place, cited: BAtlas 25 G2 Fesciago",
  "bbox": [
    1.971599,
    43.954733,
    1.971599,
    43.954733
  ],
  "reprPoint": [
    1.971599,
    43.954733
  ],
  "names": [
    "Fesciago"
  ],
  "features": [
    {
      "geometry": {
        "type": "Point",
        "coordinates": [
          1.971599,
          43.954733
        ]
      },
      "id": "darmc-location-16329",
      "type": "Feature",
      "properties": {
        "description": "1M scale point location",
        "location_precision": "precise",
        "title": "DARMC location 16329",
        "link": "http://pleiades.stoa.org/places/246390/darmc-location-16329"
      }
    }
  ]
}