{
  "type": "FeatureCollection",
  "title": "Deobriga",
  "id": "246365",
  "bbox": [
    -2.912018,
    42.707897,
    -2.912018,
    42.707897
  ],
  "description": "An ancient place, cited: BAtlas 25 C3 Deobriga",
  "names": [
    "Deobriga",
    "Sobobrica"
  ],
  "features": [
    {
      "type": "Feature",
      "geometry": {
        "type": "Point",
        "coordinates": [
          -2.912018,
          42.707897
        ]
      },
      "properties": {
        "description": "representative point"
      }
    },
    {
      "geometry": {
        "type": "Point",
        "coordinates": [
          -2.912018,
          42.707897
        ]
      },
      "id": "darmc-location-19906",
      "type": "Feature",
      "properties": {
        "description": "1M scale point location",
        "location_precision": "precise",
        "title": "DARMC location 19906",
        "link": "http://pleiades.stoa.org/places/246365/darmc-location-19906"
      }
    }
  ]
}