{
  "type": "FeatureCollection",
  "title": "Fines",
  "id": "246391",
  "bbox": [
    1.359924,
    44.00308,
    1.359924,
    44.00308
  ],
  "description": "An ancient place, cited: BAtlas 25 G1 Fines",
  "names": [
    "Fines"
  ],
  "features": [
    {
      "type": "Feature",
      "geometry": {
        "type": "Point",
        "coordinates": [
          1.359924,
          44.00308
        ]
      },
      "properties": {
        "description": "representative point"
      }
    },
    {
      "geometry": {
        "type": "Point",
        "coordinates": [
          1.359924,
          44.00308
        ]
      },
      "id": "darmc-location-2638",
      "type": "Feature",
      "properties": {
        "description": "1M scale point location",
        "location_precision": "precise",
        "title": "DARMC location 2638",
        "link": "http://pleiades.stoa.org/places/246391/darmc-location-2638"
      }
    }
  ]
}