{
  "type": "FeatureCollection",
  "title": "Egara",
  "id": "246377",
  "description": "An ancient place, cited: BAtlas 25 H4 Egara",
  "bbox": [
    2.010425,
    41.560997,
    2.010425,
    41.560997
  ],
  "reprPoint": [
    2.010425,
    41.560997
  ],
  "names": [
    "Egara"
  ],
  "features": [
    {
      "geometry": {
        "type": "Point",
        "coordinates": [
          2.010425,
          41.560997
        ]
      },
      "id": "darmc-location-20239",
      "type": "Feature",
      "properties": {
        "description": "1M scale point location",
        "location_precision": "precise",
        "title": "DARMC location 20239",
        "link": "http://pleiades.stoa.org/places/246377/darmc-location-20239"
      }
    }
  ]
}