{
  "type": "FeatureCollection",
  "title": "Los Castillos",
  "id": "246312",
  "bbox": [
    -2.746945,
    42.73491,
    -2.746945,
    42.73491
  ],
  "description": "An ancient place, cited: BAtlas 25 C3 Los Castillos",
  "features": [
    {
      "type": "Feature",
      "geometry": {
        "type": "Point",
        "coordinates": [
          -2.746945,
          42.73491
        ]
      },
      "properties": {
        "description": "representative point"
      }
    },
    {
      "geometry": {
        "type": "Point",
        "coordinates": [
          -2.746945,
          42.73491
        ]
      },
      "id": "darmc-location-20449",
      "type": "Feature",
      "properties": {
        "description": "1M scale point location",
        "location_precision": "precise",
        "title": "DARMC location 20449",
        "link": "http://pleiades.stoa.org/places/246312/darmc-location-20449"
      }
    }
  ]
}