{
  "type": "FeatureCollection",
  "title": "Forum Gallorum",
  "id": "246395",
  "description": "An ancient place, cited: BAtlas 25 E3 Forum Gallorum",
  "bbox": [
    -0.688751,
    42.27498,
    -0.688751,
    42.27498
  ],
  "reprPoint": [
    -0.688751,
    42.27498
  ],
  "names": [
    "Forum Gallorum"
  ],
  "features": [
    {
      "geometry": {
        "type": "Point",
        "coordinates": [
          -0.688751,
          42.27498
        ]
      },
      "id": "darmc-location-7291",
      "type": "Feature",
      "properties": {
        "description": "1M scale point location",
        "location_precision": "precise",
        "title": "DARMC location 7291",
        "link": "http://pleiades.stoa.org/places/246395/darmc-location-7291"
      }
    }
  ]
}