{
  "type": "FeatureCollection",
  "title": "Contrebia Leucada",
  "id": "246356",
  "bbox": [
    -1.94689,
    41.999629,
    -1.94689,
    41.999629
  ],
  "description": "An ancient place, cited: BAtlas 25 D3 Contrebia Leucada",
  "names": [
    "Contrebia Leucada"
  ],
  "features": [
    {
      "type": "Feature",
      "geometry": {
        "type": "Point",
        "coordinates": [
          -1.94689,
          41.999629
        ]
      },
      "properties": {
        "description": "representative point"
      }
    },
    {
      "geometry": {
        "type": "Point",
        "coordinates": [
          -1.94689,
          41.999629
        ]
      },
      "id": "darmc-location-20194",
      "type": "Feature",
      "properties": {
        "description": "1M scale point location",
        "location_precision": "precise",
        "title": "DARMC location 20194",
        "link": "http://pleiades.stoa.org/places/246356/darmc-location-20194"
      }
    }
  ]
}