{
  "type": "FeatureCollection",
  "title": "Cauterets",
  "id": "246319",
  "description": "An ancient place, cited: BAtlas 25 E3 Cauterets",
  "bbox": [
    -0.114151,
    42.887377,
    -0.114151,
    42.887377
  ],
  "reprPoint": [
    -0.114151,
    42.887377
  ],
  "names": [
    "Cauterets"
  ],
  "features": [
    {
      "geometry": {
        "type": "Point",
        "coordinates": [
          -0.114151,
          42.887377
        ]
      },
      "id": "darmc-location-20146",
      "type": "Feature",
      "properties": {
        "description": "1M scale point location",
        "location_precision": "precise",
        "title": "DARMC location 20146",
        "link": "http://pleiades.stoa.org/places/246319/darmc-location-20146"
      }
    }
  ]
}