{
  "type": "FeatureCollection",
  "title": "Cerviano",
  "id": "246329",
  "bbox": [
    2.028364,
    43.659694,
    2.028364,
    43.659694
  ],
  "description": "An ancient place, cited: BAtlas 25 H2 Cerviano",
  "names": [
    "Cerviano"
  ],
  "features": [
    {
      "type": "Feature",
      "geometry": {
        "type": "Point",
        "coordinates": [
          2.028364,
          43.659694
        ]
      },
      "properties": {
        "description": "representative point"
      }
    },
    {
      "geometry": {
        "type": "Point",
        "coordinates": [
          2.028364,
          43.659694
        ]
      },
      "id": "darmc-location-16323",
      "type": "Feature",
      "properties": {
        "description": "1M scale point location",
        "location_precision": "precise",
        "title": "DARMC location 16323",
        "link": "http://pleiades.stoa.org/places/246329/darmc-location-16323"
      }
    }
  ]
}