{
  "type": "FeatureCollection",
  "title": "Hebromagus/Eburomagus",
  "id": "246413",
  "description": "Hebromagus/Eburomagus (modern Bram, Aude) was a crossroads village along the road from Narbo to Tolosa.",
  "bbox": [
    2.112346,
    43.242555,
    2.112346,
    43.242555
  ],
  "reprPoint": [
    2.112346,
    43.242555
  ],
  "names": [
    "Bram",
    "Hebromagus",
    "Eburomagus"
  ],
  "features": [
    {
      "geometry": {
        "type": "Point",
        "coordinates": [
          2.112346,
          43.242555
        ]
      },
      "id": "darmc-location-12684",
      "type": "Feature",
      "properties": {
        "description": "1M scale point location",
        "location_precision": "precise",
        "title": "DARMC location 12684",
        "link": "http://pleiades.stoa.org/places/246413/darmc-location-12684"
      }
    }
  ]
}