{
  "type": "FeatureCollection",
  "title": "Iuncaria",
  "id": "246449",
  "description": "An ancient place, cited: BAtlas 25 H3 Iuncaria",
  "bbox": [
    2.873118,
    42.275356,
    2.966727,
    42.419977
  ],
  "reprPoint": [
    2.9199225,
    42.3476665
  ],
  "names": [
    "Iuncaria"
  ],
  "features": [
    {
      "geometry": {
        "type": "Point",
        "coordinates": [
          2.966727,
          42.275356
        ]
      },
      "id": "iuncaria-1",
      "type": "Feature",
      "properties": {
        "description": null,
        "location_precision": "precise",
        "title": "Representative point",
        "link": "http://pleiades.stoa.org/places/246449/iuncaria-1"
      }
    }
  ]
}