{
  "type": "FeatureCollection",
  "title": "Lounarion Akron",
  "id": "246474",
  "bbox": [
    3.2334713,
    41.9503531,
    3.2334713,
    41.9503531
  ],
  "description": "An ancient promontory listed in Ptolemy's Geography. Thought to be the modern Cap Begur on the so-called Costa Brava: a section of the Mediterranean coast of modern Spain (Catalunya).",
  "names": [
    "Lounarion Akron",
    "Cap Begur"
  ],
  "features": [
    {
      "type": "Feature",
      "geometry": {
        "type": "Point",
        "coordinates": [
          3.2334713,
          41.9503531
        ]
      },
      "properties": {
        "description": "representative point"
      }
    },
    {
      "geometry": {
        "type": "Point",
        "coordinates": [
          3.2334713,
          41.9503531
        ]
      },
      "id": "osm-location-of-cap-de-begur",
      "type": "Feature",
      "properties": {
        "description": "Location based on OpenStreetMap",
        "location_precision": "precise",
        "title": "OSM location of Cap de Begur",
        "link": "http://pleiades.stoa.org/places/246474/osm-location-of-cap-de-begur"
      }
    }
  ]
}