{
  "type": "FeatureCollection",
  "title": "Gallicum",
  "id": "246402",
  "description": "An ancient place, cited: BAtlas 25 E4 Gallicum",
  "bbox": [
    -0.788248,
    41.869036,
    -0.788248,
    41.869036
  ],
  "reprPoint": [
    -0.788248,
    41.869036
  ],
  "names": [
    "Gallicum"
  ],
  "features": [
    {
      "geometry": {
        "type": "Point",
        "coordinates": [
          -0.788248,
          41.869036
        ]
      },
      "id": "darmc-location-7257",
      "type": "Feature",
      "properties": {
        "description": "1M scale point location",
        "location_precision": "precise",
        "title": "DARMC location 7257",
        "link": "http://pleiades.stoa.org/places/246402/darmc-location-7257"
      }
    }
  ]
}