{
  "type": "FeatureCollection",
  "title": "Las Gimenas",
  "id": "246407",
  "description": "An ancient place, cited: BAtlas 25 C3 Las Gimenas",
  "bbox": [
    -2.351508,
    42.075381,
    -2.351508,
    42.075381
  ],
  "reprPoint": [
    -2.351508,
    42.075381
  ],
  "features": [
    {
      "geometry": {
        "type": "Point",
        "coordinates": [
          -2.351508,
          42.075381
        ]
      },
      "id": "darmc-location-20422",
      "type": "Feature",
      "properties": {
        "description": "1M scale point location",
        "location_precision": "precise",
        "title": "DARMC location 20422",
        "link": "http://pleiades.stoa.org/places/246407/darmc-location-20422"
      }
    }
  ]
}