{
  "type": "FeatureCollection",
  "title": "Galliaco",
  "id": "246401",
  "bbox": [
    1.896859,
    43.900118,
    1.896859,
    43.900118
  ],
  "description": "An ancient place, cited: BAtlas 25 G2 Galliaco",
  "names": [
    "Galliaco"
  ],
  "features": [
    {
      "type": "Feature",
      "geometry": {
        "type": "Point",
        "coordinates": [
          1.896859,
          43.900118
        ]
      },
      "properties": {
        "description": "representative point"
      }
    },
    {
      "geometry": {
        "type": "Point",
        "coordinates": [
          1.896859,
          43.900118
        ]
      },
      "id": "darmc-location-17431",
      "type": "Feature",
      "properties": {
        "description": "1M scale point location",
        "location_precision": "precise",
        "title": "DARMC location 17431",
        "link": "http://pleiades.stoa.org/places/246401/darmc-location-17431"
      }
    }
  ]
}