{
  "type": "FeatureCollection",
  "title": "Granoialo",
  "id": "246409",
  "description": "An ancient place, cited: BAtlas 25 G2 Granoialo",
  "bbox": [
    1.426873,
    43.977413,
    1.930928,
    44.355155
  ],
  "reprPoint": [
    1.76287233333,
    44.1033736667
  ],
  "names": [
    "Granoialo"
  ],
  "features": [
    {
      "geometry": {
        "type": "Point",
        "coordinates": [
          1.930816,
          43.977553
        ]
      },
      "id": "darmc-location-17448",
      "type": "Feature",
      "properties": {
        "description": "1M scale point location",
        "location_precision": "precise",
        "title": "DARMC location 17448",
        "link": "http://pleiades.stoa.org/places/246409/darmc-location-17448"
      }
    },
    {
      "geometry": {
        "type": "Point",
        "coordinates": [
          1.930928,
          43.977413
        ]
      },
      "id": "dare-location",
      "type": "Feature",
      "properties": {
        "description": "Representative point location, village precision",
        "location_precision": "precise",
        "title": "DARE Location",
        "link": "http://pleiades.stoa.org/places/246409/dare-location"
      }
    }
  ]
}