{
  "type": "FeatureCollection",
  "title": "Marchamalo",
  "id": "246485",
  "description": "An ancient place, cited: BAtlas 25 B5 Marchamalo",
  "bbox": [
    -3.200958,
    40.668205,
    -3.200958,
    40.668205
  ],
  "reprPoint": [
    -3.200958,
    40.668205
  ],
  "features": [
    {
      "geometry": {
        "type": "Point",
        "coordinates": [
          -3.200958,
          40.668205
        ]
      },
      "id": "darmc-location-23754",
      "type": "Feature",
      "properties": {
        "description": "Point location",
        "location_precision": "precise",
        "title": "DARMC location 23754",
        "link": "http://pleiades.stoa.org/places/246485/darmc-location-23754"
      }
    }
  ]
}