{
  "type": "FeatureCollection",
  "title": "Lounarion Akron",
  "id": "246474",
  "bbox": [
    3.2318419,
    41.9501869,
    3.2318419,
    41.9501869
  ],
  "description": "An ancient promontory listed in Ptolemy's Geography. Thought to be the modern Cap Begur on the so-called Costa Brava: a section of the  Mediterranean coast of modern Spain (Catalunya).",
  "names": [
    "Lounarion Akron",
    "Cap Begur"
  ],
  "features": [
    {
      "type": "Feature",
      "geometry": {
        "type": "Point",
        "coordinates": [
          3.2318419,
          41.9501869
        ]
      },
      "properties": {
        "description": "representative point"
      }
    },
    {
      "geometry": {
        "type": "Point",
        "coordinates": [
          3.2318419,
          41.9501869
        ]
      },
      "id": "osm-location",
      "type": "Feature",
      "properties": {
        "description": "Representative polygonal geometry for the modern Cap Begur in eastern Spain, derived from an OpenStreetMap way.",
        "location_precision": "precise",
        "title": "OSM Location",
        "link": "http://pleiades.stoa.org/places/246474/osm-location"
      }
    }
  ]
}