{
  "type": "FeatureCollection",
  "title": "Labitulosa",
  "id": "246457",
  "description": "An ancient place, cited: BAtlas 25 F3 Labitulosa",
  "bbox": [
    0.287408,
    42.144689,
    0.287408,
    42.144689
  ],
  "reprPoint": [
    0.287408,
    42.144689
  ],
  "names": [
    "Labitulosa"
  ],
  "features": [
    {
      "geometry": {
        "type": "Point",
        "coordinates": [
          0.287408,
          42.144689
        ]
      },
      "id": "darmc-location-20410",
      "type": "Feature",
      "properties": {
        "description": "1M scale point location",
        "location_precision": "precise",
        "title": "DARMC location 20410",
        "link": "http://pleiades.stoa.org/places/246457/darmc-location-20410"
      }
    }
  ]
}