{
  "type": "FeatureCollection",
  "title": "La Mesa",
  "id": "246499",
  "bbox": [
    -3.203588,
    42.400744,
    -3.203588,
    42.400744
  ],
  "description": "An ancient place, cited: BAtlas 25 B3 La Mesa",
  "features": [
    {
      "type": "Feature",
      "geometry": {
        "type": "Point",
        "coordinates": [
          -3.203588,
          42.400744
        ]
      },
      "properties": {
        "description": "representative point"
      }
    },
    {
      "geometry": {
        "type": "Point",
        "coordinates": [
          -3.203588,
          42.400744
        ]
      },
      "id": "darmc-location-30427",
      "type": "Feature",
      "properties": {
        "description": "1M scale point location",
        "location_precision": "precise",
        "title": "DARMC location 30427",
        "link": "http://pleiades.stoa.org/places/246499/darmc-location-30427"
      }
    }
  ]
}