{
  "type": "FeatureCollection",
  "title": "Iuncaria",
  "id": "246449",
  "bbox": [
    2.96815,
    42.2748,
    2.96815,
    42.2748
  ],
  "description": "An Roman road station, mentioned in the Antonine Itinerary. It was located at modern L’Aigüeta in Figures, Spain.",
  "names": [
    "L’Aigüeta",
    "Iuncaria"
  ],
  "features": [
    {
      "type": "Feature",
      "geometry": {
        "type": "Point",
        "coordinates": [
          2.96815,
          42.2748
        ]
      },
      "properties": {
        "description": "representative point"
      }
    },
    {
      "geometry": {
        "type": "Point",
        "coordinates": [
          2.96815,
          42.2748
        ]
      },
      "id": "iuncaria-1",
      "type": "Feature",
      "properties": {
        "description": null,
        "location_precision": "precise",
        "title": "Geonames Location of l'Aigüeta",
        "link": "http://pleiades.stoa.org/places/246449/iuncaria-1"
      }
    }
  ]
}