{
  "type": "FeatureCollection",
  "title": "Nertobriga",
  "id": "246518",
  "bbox": [
    -1.428502,
    41.498964,
    -1.364596,
    41.502134
  ],
  "description": "An ancient place, cited: BAtlas 25 D4 Nertobriga",
  "names": [
    "Nertobriga"
  ],
  "features": [
    {
      "type": "Feature",
      "geometry": {
        "type": "Point",
        "coordinates": [
          -1.396549,
          41.500549
        ]
      },
      "properties": {
        "description": "representative point"
      }
    },
    {
      "geometry": {
        "type": "Point",
        "coordinates": [
          -1.428502,
          41.498964
        ]
      },
      "id": "darmc-location-20523",
      "type": "Feature",
      "properties": {
        "description": "1:1 million scale representative point location digitized from the Barrington Atlas of the Greek and Roman World by the Digital Atlas of Roman and Medieval Civilizations project at Harvard University.",
        "location_precision": "precise",
        "title": "DARMC location 20523",
        "link": "http://pleiades.stoa.org/places/246518/darmc-location-20523"
      }
    },
    {
      "geometry": {
        "type": "Point",
        "coordinates": [
          -1.364596,
          41.502134
        ]
      },
      "id": "dare-location",
      "type": "Feature",
      "properties": {
        "description": "Representative point location, site precision",
        "location_precision": "precise",
        "title": "DARE Location",
        "link": "http://pleiades.stoa.org/places/246518/dare-location"
      }
    }
  ]
}