{
  "type": "FeatureCollection",
  "title": "El Palomar",
  "id": "246553",
  "bbox": [
    -0.67444,
    40.998055,
    -0.67444,
    40.998055
  ],
  "description": "An ancient place, cited: BAtlas 25 E5 El Palomar",
  "features": [
    {
      "type": "Feature",
      "geometry": {
        "type": "Point",
        "coordinates": [
          -0.67444,
          40.998055
        ]
      },
      "properties": {
        "description": "representative point"
      }
    },
    {
      "geometry": {
        "type": "Point",
        "coordinates": [
          -0.67444,
          40.998055
        ]
      },
      "id": "darmc-location-20245",
      "type": "Feature",
      "properties": {
        "description": "1M scale point location",
        "location_precision": "precise",
        "title": "DARMC location 20245",
        "link": "http://pleiades.stoa.org/places/246553/darmc-location-20245"
      }
    }
  ]
}