{
  "type": "FeatureCollection",
  "title": "Molì de l’Espigol",
  "id": "246503",
  "description": "An ancient place, cited: BAtlas 25 G4 Molì de l’Espigol",
  "bbox": [
    1.052617,
    41.701528,
    1.0721619,
    41.7094444
  ],
  "reprPoint": [
    1.06238945,
    41.7054862
  ],
  "features": [
    {
      "geometry": {
        "type": "Point",
        "coordinates": [
          1.052617,
          41.701528
        ]
      },
      "id": "darmc-location-30494",
      "type": "Feature",
      "properties": {
        "description": "1M scale point location",
        "location_precision": "precise",
        "title": "DARMC location 30494",
        "link": "http://pleiades.stoa.org/places/246503/darmc-location-30494"
      }
    },
    {
      "geometry": {
        "type": "Point",
        "coordinates": [
          1.0721619,
          41.7094444
        ]
      },
      "id": "location-of-oppidum",
      "type": "Feature",
      "properties": {
        "description": "Representative location based on OpenStreetMap.",
        "location_precision": "precise",
        "title": "OSM location of Poblado íbero del Molino de Espigol",
        "link": "http://pleiades.stoa.org/places/246503/location-of-oppidum"
      }
    }
  ]
}