{
  "type": "FeatureCollection",
  "title": "Rubricatum?",
  "id": "246592",
  "description": "An ancient place, cited: BAtlas 25 H4 Rubricatum?",
  "bbox": [
    2.031269,
    41.492345,
    2.031269,
    41.492345
  ],
  "reprPoint": [
    2.031269,
    41.492345
  ],
  "names": [
    "Rubricatum"
  ],
  "features": [
    {
      "geometry": {
        "type": "Point",
        "coordinates": [
          2.031269,
          41.492345
        ]
      },
      "id": "darmc-location-3500",
      "type": "Feature",
      "properties": {
        "description": "1M scale point location",
        "location_precision": "precise",
        "title": "DARMC location 3500",
        "link": "http://pleiades.stoa.org/places/246592/darmc-location-3500"
      }
    }
  ]
}