{
  "type": "FeatureCollection",
  "title": "La Muela",
  "id": "246511",
  "description": "An ancient place, cited: BAtlas 25 E5 La Muela",
  "bbox": [
    -0.785907,
    40.691264,
    -0.785907,
    40.691264
  ],
  "reprPoint": [
    -0.785907,
    40.691264
  ],
  "features": [
    {
      "geometry": {
        "type": "Point",
        "coordinates": [
          -0.785907,
          40.691264
        ]
      },
      "id": "darmc-location-7576",
      "type": "Feature",
      "properties": {
        "description": "1M scale point location",
        "location_precision": "precise",
        "title": "DARMC location 7576",
        "link": "http://pleiades.stoa.org/places/246511/darmc-location-7576"
      }
    }
  ]
}