{
  "type": "FeatureCollection",
  "title": "Platea",
  "id": "246564",
  "bbox": [
    -1.647023,
    41.354379,
    -1.647023,
    41.354379
  ],
  "description": "An ancient place, cited: BAtlas 25 D4 Platea",
  "names": [
    "Platea"
  ],
  "features": [
    {
      "type": "Feature",
      "geometry": {
        "type": "Point",
        "coordinates": [
          -1.647023,
          41.354379
        ]
      },
      "properties": {
        "description": "representative point"
      }
    },
    {
      "geometry": {
        "type": "Point",
        "coordinates": [
          -1.647023,
          41.354379
        ]
      },
      "id": "darmc-location-3453",
      "type": "Feature",
      "properties": {
        "description": "1M scale point location",
        "location_precision": "precise",
        "title": "DARMC location 3453",
        "link": "http://pleiades.stoa.org/places/246564/darmc-location-3453"
      }
    }
  ]
}