{
  "type": "FeatureCollection",
  "title": "Oruña",
  "id": "246538",
  "description": "An ancient place, cited: BAtlas 25 D4 Oruña",
  "bbox": [
    -1.701422,
    41.819042,
    -1.701422,
    41.819042
  ],
  "reprPoint": [
    -1.701422,
    41.819042
  ],
  "features": [
    {
      "geometry": {
        "type": "Point",
        "coordinates": [
          -1.701422,
          41.819042
        ]
      },
      "id": "darmc-location-891",
      "type": "Feature",
      "properties": {
        "description": "1M scale point location",
        "location_precision": "precise",
        "title": "DARMC location 891",
        "link": "http://pleiades.stoa.org/places/246538/darmc-location-891"
      }
    }
  ]
}