{
  "type": "FeatureCollection",
  "title": "Novum Oppidum",
  "id": "246522",
  "description": "An ancient place, cited: BAtlas 25 E2 Novum Oppidum",
  "bbox": [
    -0.045659,
    43.09786,
    -0.045659,
    43.09786
  ],
  "reprPoint": [
    -0.045659,
    43.09786
  ],
  "names": [
    "Novum Oppidum"
  ],
  "features": [
    {
      "geometry": {
        "type": "Point",
        "coordinates": [
          -0.045659,
          43.09786
        ]
      },
      "id": "darmc-location-19344",
      "type": "Feature",
      "properties": {
        "description": "1M scale point location",
        "location_precision": "precise",
        "title": "DARMC location 19344",
        "link": "http://pleiades.stoa.org/places/246522/darmc-location-19344"
      }
    }
  ]
}