{
  "type": "FeatureCollection",
  "title": "Petregontio",
  "id": "246562",
  "description": "An ancient place, cited: BAtlas 25 H2 Petregontio",
  "bbox": [
    2.202612,
    43.700995,
    2.202612,
    43.700995
  ],
  "reprPoint": [
    2.202612,
    43.700995
  ],
  "names": [
    "Petregontio"
  ],
  "features": [
    {
      "geometry": {
        "type": "Point",
        "coordinates": [
          2.202612,
          43.700995
        ]
      },
      "id": "darmc-location-16345",
      "type": "Feature",
      "properties": {
        "description": "1M scale point location",
        "location_precision": "precise",
        "title": "DARMC location 16345",
        "link": "http://pleiades.stoa.org/places/246562/darmc-location-16345"
      }
    }
  ]
}