{
  "type": "FeatureCollection",
  "title": "El Palao",
  "id": "246550",
  "bbox": [
    -0.183192,
    41.025075,
    -0.183192,
    41.025075
  ],
  "description": "An ancient place, cited: BAtlas 25 E4 El Palao",
  "features": [
    {
      "type": "Feature",
      "geometry": {
        "type": "Point",
        "coordinates": [
          -0.183192,
          41.025075
        ]
      },
      "properties": {
        "description": "representative point"
      }
    },
    {
      "geometry": {
        "type": "Point",
        "coordinates": [
          -0.183192,
          41.025075
        ]
      },
      "id": "darmc-location-20244",
      "type": "Feature",
      "properties": {
        "description": "1M scale point location",
        "location_precision": "precise",
        "title": "DARMC location 20244",
        "link": "http://pleiades.stoa.org/places/246550/darmc-location-20244"
      }
    }
  ]
}