{
  "type": "FeatureCollection",
  "title": "El Molinillo",
  "id": "246504",
  "description": "An ancient place, cited: BAtlas 25 C4 El Molinillo",
  "bbox": [
    -2.399916,
    41.526454,
    -2.399916,
    41.526454
  ],
  "reprPoint": [
    -2.399916,
    41.526454
  ],
  "features": [
    {
      "geometry": {
        "type": "Point",
        "coordinates": [
          -2.399916,
          41.526454
        ]
      },
      "id": "darmc-location-20243",
      "type": "Feature",
      "properties": {
        "description": "1M scale point location",
        "location_precision": "precise",
        "title": "DARMC location 20243",
        "link": "http://pleiades.stoa.org/places/246504/darmc-location-20243"
      }
    }
  ]
}