{
  "type": "FeatureCollection",
  "title": "Neroua (river)",
  "id": "246517",
  "bbox": [
    -2.9808908,
    42.9389421,
    -2.9808908,
    42.9389421
  ],
  "description": "An ancient place, cited: BAtlas 25 C2 Neroua fl.",
  "connectsWith": [
    "236376"
  ],
  "names": [
    "Neroua"
  ],
  "features": [
    {
      "type": "Feature",
      "geometry": {
        "type": "Point",
        "coordinates": [
          -2.9808908,
          42.9389421
        ]
      },
      "properties": {
        "description": "representative point"
      }
    },
    {
      "geometry": {
        "type": "Point",
        "coordinates": [
          -2.9808908,
          42.9389421
        ]
      },
      "id": "location-of-Neroua-fl",
      "type": "Feature",
      "properties": {
        "description": "Location based on OpenStreetMap",
        "location_precision": "precise",
        "title": "location of Neroua fl.",
        "link": "http://pleiades.stoa.org/places/246517/location-of-Neroua-fl"
      }
    }
  ]
}