{
  "type": "FeatureCollection",
  "title": "Pompelo",
  "id": "246567",
  "description": "Cn. Pompeius Magnus is considered to have been the founder of Pompelo (modern Pamplona) while on campaign against Sertorius in 75 BC.",
  "bbox": [
    -1.644224,
    42.817991,
    -1.644224,
    42.817991
  ],
  "connectsWith": [
    "6ae198fdb7a105b379e1e1e52a5e223b",
    "b690029e1fe8af990c15036de622166f"
  ],
  "reprPoint": [
    -1.644224,
    42.817991
  ],
  "names": [
    "Pompelo"
  ],
  "features": [
    {
      "geometry": {
        "type": "Point",
        "coordinates": [
          -1.644224,
          42.817991
        ]
      },
      "id": "darmc-location-3455",
      "type": "Feature",
      "properties": {
        "description": "1M scale point location",
        "location_precision": "precise",
        "title": "DARMC location 3455",
        "link": "http://pleiades.stoa.org/places/246567/darmc-location-3455"
      }
    }
  ]
}