{
  "type": "FeatureCollection",
  "title": "Parets Delgades",
  "id": "246556",
  "description": "An ancient place, cited: BAtlas 25 G4 Parets Delgades",
  "bbox": [
    1.207231,
    41.209,
    1.207231,
    41.209
  ],
  "reprPoint": [
    1.207231,
    41.209
  ],
  "features": [
    {
      "geometry": {
        "type": "Point",
        "coordinates": [
          1.207231,
          41.209
        ]
      },
      "id": "darmc-location-21182",
      "type": "Feature",
      "properties": {
        "description": "1M scale point location",
        "location_precision": "precise",
        "title": "DARMC location 21182",
        "link": "http://pleiades.stoa.org/places/246556/darmc-location-21182"
      }
    }
  ]
}