{
  "type": "FeatureCollection",
  "title": "Nertobriga",
  "id": "246518",
  "description": "An ancient place, cited: BAtlas 25 D4 Nertobriga",
  "bbox": [
    -1.364596,
    41.502134,
    -1.364596,
    41.502134
  ],
  "reprPoint": [
    -1.364596,
    41.502134
  ],
  "names": [
    "Nertobriga"
  ],
  "features": [
    {
      "geometry": {
        "type": "Point",
        "coordinates": [
          -1.428502,
          41.498964
        ]
      },
      "id": "darmc-location-20523",
      "type": "Feature",
      "properties": {
        "description": "1M scale point location",
        "location_precision": "precise",
        "title": "DARMC location 20523",
        "link": "http://pleiades.stoa.org/places/246518/darmc-location-20523"
      }
    },
    {
      "geometry": {
        "type": "Point",
        "coordinates": [
          -1.364596,
          41.502134
        ]
      },
      "id": "dare-location",
      "type": "Feature",
      "properties": {
        "description": "Representative point location, site precision",
        "location_precision": "precise",
        "title": "DARE Location",
        "link": "http://pleiades.stoa.org/places/246518/dare-location"
      }
    }
  ]
}