{
  "type": "FeatureCollection",
  "title": "Pompelo",
  "id": "246567",
  "bbox": [
    -1.644224,
    42.817991,
    -1.644224,
    42.817991
  ],
  "description": "Cn. Pompeius Magnus is considered to have been the founder of Pompelo (modern Pamplona) while on campaign against Sertorius in 75 BC.",
  "connectsWith": [
    "246730",
    "771100775"
  ],
  "names": [
    "Pompelo"
  ],
  "features": [
    {
      "type": "Feature",
      "geometry": {
        "type": "Point",
        "coordinates": [
          -1.644224,
          42.817991
        ]
      },
      "properties": {
        "description": "representative point"
      }
    },
    {
      "geometry": {
        "type": "Point",
        "coordinates": [
          -1.644224,
          42.817991
        ]
      },
      "id": "darmc-location-3455",
      "type": "Feature",
      "properties": {
        "description": "1M scale point location",
        "location_precision": "precise",
        "title": "DARMC location 3455",
        "link": "http://pleiades.stoa.org/places/246567/darmc-location-3455"
      }
    }
  ]
}