{
  "type": "FeatureCollection",
  "title": "Oleastrum",
  "id": "246529",
  "description": "An ancient place, cited: BAtlas 25 F4 Oleastrum",
  "bbox": [
    0.912577,
    41.006039,
    0.912577,
    41.006039
  ],
  "reprPoint": [
    0.912577,
    41.006039
  ],
  "names": [
    "Oleastrum"
  ],
  "features": [
    {
      "geometry": {
        "type": "Point",
        "coordinates": [
          0.912577,
          41.006039
        ]
      },
      "id": "darmc-location-7337",
      "type": "Feature",
      "properties": {
        "description": "1M scale point location",
        "location_precision": "precise",
        "title": "DARMC location 7337",
        "link": "http://pleiades.stoa.org/places/246529/darmc-location-7337"
      }
    }
  ]
}