{
  "type": "FeatureCollection",
  "title": "Summus Pyreneus",
  "id": "246672",
  "description": "An ancient place, cited: BAtlas 25 E3 Summus Pyreneus",
  "bbox": [
    -0.82811,
    42.757527,
    -0.82811,
    42.757527
  ],
  "reprPoint": [
    -0.82811,
    42.757527
  ],
  "names": [
    "Summus Pyreneus"
  ],
  "features": [
    {
      "geometry": {
        "type": "Point",
        "coordinates": [
          -0.82811,
          42.757527
        ]
      },
      "id": "darmc-location-7294",
      "type": "Feature",
      "properties": {
        "description": "1M scale point location",
        "location_precision": "precise",
        "title": "DARMC location 7294",
        "link": "http://pleiades.stoa.org/places/246672/darmc-location-7294"
      }
    }
  ]
}