{
  "type": "FeatureCollection",
  "title": "St-Pons",
  "id": "246605",
  "bbox": [
    2.76123,
    43.487702,
    2.76123,
    43.487702
  ],
  "description": "An ancient place, cited: BAtlas 25 H2 St-Pons",
  "features": [
    {
      "type": "Feature",
      "geometry": {
        "type": "Point",
        "coordinates": [
          2.76123,
          43.487702
        ]
      },
      "properties": {
        "description": "representative point"
      }
    },
    {
      "geometry": {
        "type": "Point",
        "coordinates": [
          2.76123,
          43.487702
        ]
      },
      "id": "darmc-location-19287",
      "type": "Feature",
      "properties": {
        "description": "1M scale point location",
        "location_precision": "precise",
        "title": "DARMC location 19287",
        "link": "http://pleiades.stoa.org/places/246605/darmc-location-19287"
      }
    }
  ]
}