{
  "type": "FeatureCollection",
  "title": "Saviniago",
  "id": "246629",
  "description": "An ancient place, cited: BAtlas 25 F2 Saviniago",
  "bbox": [
    0.181754,
    43.943892,
    0.181754,
    43.943892
  ],
  "reprPoint": [
    0.181754,
    43.943892
  ],
  "names": [
    "Séviac",
    "Saviniago"
  ],
  "features": [
    {
      "geometry": {
        "type": "Point",
        "coordinates": [
          0.180448,
          43.941754
        ]
      },
      "id": "darmc-location-17588",
      "type": "Feature",
      "properties": {
        "description": "1M scale point location",
        "location_precision": "precise",
        "title": "DARMC location 17588",
        "link": "http://pleiades.stoa.org/places/246629/darmc-location-17588"
      }
    },
    {
      "geometry": {
        "type": "Point",
        "coordinates": [
          0.181754,
          43.943892
        ]
      },
      "id": "dare-location",
      "type": "Feature",
      "properties": {
        "description": "Representative point location, site precision",
        "location_precision": "precise",
        "title": "DARE Location",
        "link": "http://pleiades.stoa.org/places/246629/dare-location"
      }
    }
  ]
}