{
  "type": "FeatureCollection",
  "title": "St-Hilaire",
  "id": "246604",
  "bbox": [
    3.057716,
    43.533849,
    3.057716,
    43.533849
  ],
  "description": "An ancient place, cited: BAtlas 25 I2 St-Hilaire",
  "features": [
    {
      "type": "Feature",
      "geometry": {
        "type": "Point",
        "coordinates": [
          3.057716,
          43.533849
        ]
      },
      "properties": {
        "description": "representative point"
      }
    },
    {
      "geometry": {
        "type": "Point",
        "coordinates": [
          3.057716,
          43.533849
        ]
      },
      "id": "darmc-location-19285",
      "type": "Feature",
      "properties": {
        "description": "1M scale point location",
        "location_precision": "precise",
        "title": "DARMC location 19285",
        "link": "http://pleiades.stoa.org/places/246604/darmc-location-19285"
      }
    }
  ]
}