{
  "type": "FeatureCollection",
  "title": "Torre de los Escipiones",
  "id": "246696",
  "bbox": [
    1.318856,
    41.1319778,
    1.318919,
    41.132017
  ],
  "description": "A first century AD tower tomb built 6 km from Tarraco, the Torre dels Escipions has been listed as a UNESCO World Heritage Site.",
  "connectsWith": [
    "803793619",
    "246349"
  ],
  "names": [
    "Torre dels Escipions",
    "Torre de los Escipiones"
  ],
  "features": [
    {
      "type": "Feature",
      "geometry": {
        "type": "Point",
        "coordinates": [
          1.3188875,
          41.1319974
        ]
      },
      "properties": {
        "description": "representative point"
      }
    },
    {
      "geometry": {
        "type": "Point",
        "coordinates": [
          1.318856,
          41.132017
        ]
      },
      "id": "dare-location",
      "type": "Feature",
      "properties": {
        "description": "Representative point location, site precision",
        "location_precision": "precise",
        "title": "DARE Location",
        "link": "http://pleiades.stoa.org/places/246696/dare-location"
      }
    },
    {
      "geometry": {
        "type": "Point",
        "coordinates": [
          1.318919,
          41.1319778
        ]
      },
      "id": "location-of-torre-dels-escipions",
      "type": "Feature",
      "properties": {
        "description": "Representative location based on OpenStreetMap",
        "location_precision": "precise",
        "title": "OSM location of Torre dels Escipions",
        "link": "http://pleiades.stoa.org/places/246696/location-of-torre-dels-escipions"
      }
    }
  ]
}