{
  "type": "FeatureCollection",
  "title": "San Esteban Ancient Settlement",
  "id": "246617",
  "bbox": [
    -1.3394126,
    40.881543,
    -1.3394126,
    40.881543
  ],
  "description": "An ancient settlement that flourished during the Roman Republic and Early Empire. It is located on the modern Cerro San Esteban at El Poyo del Cid in the Calamocha municipality, Teruel province, Aragon, Spain. Its ancient name is not known.",
  "connectsWith": [
    "246296"
  ],
  "names": [
    "S. Esteban",
    "Yacimiento Arqueológico Cerro de San Esteban"
  ],
  "features": [
    {
      "type": "Feature",
      "geometry": {
        "type": "Point",
        "coordinates": [
          -1.3394126,
          40.881543
        ]
      },
      "properties": {
        "description": "representative point"
      }
    },
    {
      "geometry": {
        "type": "Point",
        "coordinates": [
          -1.3394126,
          40.881543
        ]
      },
      "id": "osm-location-of-yacimiento-cerro-de-s-esteban",
      "type": "Feature",
      "properties": {
        "description": "Location based on OpenStreetMap. Dates after BAtlas.",
        "location_precision": "precise",
        "title": "OSM Location of Yacimiento Cerro de S. Esteban",
        "link": "http://pleiades.stoa.org/places/246617/osm-location-of-yacimiento-cerro-de-s-esteban"
      }
    }
  ]
}