{
  "type": "FeatureCollection",
  "title": "Sost",
  "id": "246659",
  "description": "An ancient place, cited: BAtlas 25 F3 Sost",
  "bbox": [
    0.533604,
    42.927557,
    0.557387,
    42.929857
  ],
  "reprPoint": [
    0.5454955,
    42.928707
  ],
  "names": [
    "Pic de Montlas"
  ],
  "features": [
    {
      "geometry": {
        "type": "Point",
        "coordinates": [
          0.557387,
          42.927557
        ]
      },
      "id": "darmc-location-19535",
      "type": "Feature",
      "properties": {
        "description": "1M scale point location",
        "location_precision": "precise",
        "title": "DARMC location 19535",
        "link": "http://pleiades.stoa.org/places/246659/darmc-location-19535"
      }
    },
    {
      "geometry": {
        "type": "Point",
        "coordinates": [
          0.533604,
          42.929857
        ]
      },
      "id": "dare-location",
      "type": "Feature",
      "properties": {
        "description": "Representative point location, site precision",
        "location_precision": "precise",
        "title": "DARE Location",
        "link": "http://pleiades.stoa.org/places/246659/dare-location"
      }
    }
  ]
}