{
  "type": "FeatureCollection",
  "title": "Torre de los Escipiones",
  "id": "246696",
  "description": "An ancient place, cited: BAtlas 25 G4 Torre de los Escipiones",
  "bbox": [
    1.245439,
    41.119033,
    1.318856,
    41.132017
  ],
  "reprPoint": [
    1.2821475,
    41.125525
  ],
  "features": [
    {
      "geometry": {
        "type": "Point",
        "coordinates": [
          1.245439,
          41.119033
        ]
      },
      "id": "darmc-location-20665",
      "type": "Feature",
      "properties": {
        "description": "1M scale point location",
        "location_precision": "precise",
        "title": "DARMC location 20665",
        "link": "http://pleiades.stoa.org/places/246696/darmc-location-20665"
      }
    },
    {
      "geometry": {
        "type": "Point",
        "coordinates": [
          1.318856,
          41.132017
        ]
      },
      "id": "dare-location",
      "type": "Feature",
      "properties": {
        "description": "Representative point location, site precision",
        "location_precision": "precise",
        "title": "DARE Location",
        "link": "http://pleiades.stoa.org/places/246696/dare-location"
      }
    }
  ]
}