{
  "type": "FeatureCollection",
  "title": "Summus Pyreneus",
  "id": "246671",
  "description": "An ancient place, cited: BAtlas 25 D2 Summus Pyreneus",
  "bbox": [
    -1.324058,
    43.019858,
    -1.324058,
    43.019858
  ],
  "reprPoint": [
    -1.324058,
    43.019858
  ],
  "names": [
    "Summus Pyreneus"
  ],
  "features": [
    {
      "geometry": {
        "type": "Point",
        "coordinates": [
          -1.324058,
          43.019858
        ]
      },
      "id": "darmc-location-7293",
      "type": "Feature",
      "properties": {
        "description": "1M scale point location",
        "location_precision": "precise",
        "title": "DARMC location 7293",
        "link": "http://pleiades.stoa.org/places/246671/darmc-location-7293"
      }
    }
  ]
}