{
  "type": "FeatureCollection",
  "title": "Torre de los Escipiones",
  "id": "246696",
  "description": "A first century AD tower tomb built 6 km from Tarraco, the Torre dels Escipions has been listed as a UNESCO World Heritage Site.",
  "bbox": [
    1.318856,
    41.132017,
    1.318856,
    41.132017
  ],
  "reprPoint": [
    1.318856,
    41.132017
  ],
  "features": [
    {
      "geometry": {
        "type": "Point",
        "coordinates": [
          1.318856,
          41.132017
        ]
      },
      "id": "dare-location",
      "type": "Feature",
      "properties": {
        "description": "Representative point location, site precision",
        "location_precision": "precise",
        "title": "DARE Location",
        "link": "http://pleiades.stoa.org/places/246696/dare-location"
      }
    }
  ]
}