{
  "type": "FeatureCollection",
  "title": "S. Esteban",
  "id": "246617",
  "description": "An ancient place, cited: BAtlas 25 D5 S. Esteban",
  "bbox": [
    -1.36211,
    40.84253,
    -1.36211,
    40.84253
  ],
  "reprPoint": [
    -1.36211,
    40.84253
  ],
  "features": [
    {
      "geometry": {
        "type": "Point",
        "coordinates": [
          -1.36211,
          40.84253
        ]
      },
      "id": "darmc-location-3504",
      "type": "Feature",
      "properties": {
        "description": "1M scale point location",
        "location_precision": "precise",
        "title": "DARMC location 3504",
        "link": "http://pleiades.stoa.org/places/246617/darmc-location-3504"
      }
    }
  ]
}