{
  "type": "FeatureCollection",
  "title": "Tria Capita",
  "id": "246705",
  "description": "An ancient place, cited: BAtlas 25 F5 Tria Capita",
  "bbox": [
    0.700237,
    40.804813,
    0.700237,
    40.804813
  ],
  "reprPoint": [
    0.700237,
    40.804813
  ],
  "names": [
    "Tria Capita"
  ],
  "features": [
    {
      "geometry": {
        "type": "Point",
        "coordinates": [
          0.700237,
          40.804813
        ]
      },
      "id": "darmc-location-19362",
      "type": "Feature",
      "properties": {
        "description": "1M scale point location",
        "location_precision": "precise",
        "title": "DARMC location 19362",
        "link": "http://pleiades.stoa.org/places/246705/darmc-location-19362"
      }
    }
  ]
}