{
  "type": "FeatureCollection",
  "title": "Victoriacum",
  "id": "246740",
  "bbox": [
    -2.671675,
    42.846718,
    -2.671675,
    42.846718
  ],
  "description": "An ancient place, cited: BAtlas 25 C3 Victoriacum",
  "names": [
    "Victoriacum"
  ],
  "features": [
    {
      "type": "Feature",
      "geometry": {
        "type": "Point",
        "coordinates": [
          -2.671675,
          42.846718
        ]
      },
      "properties": {
        "description": "representative point"
      }
    },
    {
      "geometry": {
        "type": "Point",
        "coordinates": [
          -2.671675,
          42.846718
        ]
      },
      "id": "darmc-location-4569",
      "type": "Feature",
      "properties": {
        "description": "1M scale point location",
        "location_precision": "precise",
        "title": "DARMC location 4569",
        "link": "http://pleiades.stoa.org/places/246740/darmc-location-4569"
      }
    }
  ]
}