{
  "type": "FeatureCollection",
  "title": "La Vayssière",
  "id": "246731",
  "bbox": [
    3.194218,
    43.983042,
    3.194218,
    43.983042
  ],
  "description": "An ancient place, cited: BAtlas 25 I1 La Vayssière",
  "features": [
    {
      "type": "Feature",
      "geometry": {
        "type": "Point",
        "coordinates": [
          3.194218,
          43.983042
        ]
      },
      "properties": {
        "description": "representative point"
      }
    },
    {
      "geometry": {
        "type": "Point",
        "coordinates": [
          3.194218,
          43.983042
        ]
      },
      "id": "center-point-of-les-vayssieres-commune-lhospitalet-du-larzac",
      "type": "Feature",
      "properties": {
        "description": null,
        "location_precision": "precise",
        "title": "Center point of Les Vayssières, commune L'Hospitalet-du-Larzac",
        "link": "http://pleiades.stoa.org/places/246731/center-point-of-les-vayssieres-commune-lhospitalet-du-larzac"
      }
    }
  ]
}