{
  "type": "FeatureCollection",
  "title": "Vetrusa",
  "id": "246738",
  "bbox": [
    -2.860418,
    42.682448,
    -2.860418,
    42.682448
  ],
  "description": "An ancient place, cited: BAtlas 25 C3 Vetrusa",
  "features": [
    {
      "type": "Feature",
      "geometry": {
        "type": "Point",
        "coordinates": [
          -2.860418,
          42.682448
        ]
      },
      "properties": {
        "description": "representative point"
      }
    },
    {
      "geometry": {
        "type": "Point",
        "coordinates": [
          -2.860418,
          42.682448
        ]
      },
      "id": "darmc-location-4567",
      "type": "Feature",
      "properties": {
        "description": "1M scale point location",
        "location_precision": "precise",
        "title": "DARMC location 4567",
        "link": "http://pleiades.stoa.org/places/246738/darmc-location-4567"
      }
    }
  ]
}