{
  "type": "FeatureCollection",
  "title": "Vareia?",
  "id": "246729",
  "bbox": [
    -2.406884,
    42.461895,
    -2.406884,
    42.461895
  ],
  "description": "An ancient place, cited: BAtlas 25 C3 Vareia?",
  "names": [
    "Vareia"
  ],
  "features": [
    {
      "type": "Feature",
      "geometry": {
        "type": "Point",
        "coordinates": [
          -2.406884,
          42.461895
        ]
      },
      "properties": {
        "description": "representative point"
      }
    },
    {
      "geometry": {
        "type": "Point",
        "coordinates": [
          -2.406884,
          42.461895
        ]
      },
      "id": "darmc-location-4556",
      "type": "Feature",
      "properties": {
        "description": "1M scale point location",
        "location_precision": "precise",
        "title": "DARMC location 4556",
        "link": "http://pleiades.stoa.org/places/246729/darmc-location-4556"
      }
    }
  ]
}