{
  "type": "FeatureCollection",
  "title": "Valdestrada",
  "id": "246724",
  "bbox": [
    -0.436628,
    40.826776,
    -0.436628,
    40.826776
  ],
  "description": "An ancient place, cited: BAtlas 25 E5 Valdestrada",
  "features": [
    {
      "type": "Feature",
      "geometry": {
        "type": "Point",
        "coordinates": [
          -0.436628,
          40.826776
        ]
      },
      "properties": {
        "description": "representative point"
      }
    },
    {
      "geometry": {
        "type": "Point",
        "coordinates": [
          -0.436628,
          40.826776
        ]
      },
      "id": "darmc-location-19545",
      "type": "Feature",
      "properties": {
        "description": "1M scale point location",
        "location_precision": "precise",
        "title": "DARMC location 19545",
        "link": "http://pleiades.stoa.org/places/246724/darmc-location-19545"
      }
    }
  ]
}