{
  "type": "FeatureCollection",
  "title": "Poggio del Molino",
  "id": "24736652",
  "bbox": [
    10.4896134,
    42.9858967,
    10.4896134,
    42.9858967
  ],
  "description": "A Roman villa overlooking the Tyrrhenian sea located within the former territory of Populonia.",
  "connectsWith": [
    "403212"
  ],
  "features": [
    {
      "type": "Feature",
      "geometry": {
        "type": "Point",
        "coordinates": [
          10.4896134,
          42.9858967
        ]
      },
      "properties": {
        "description": "representative point"
      }
    },
    {
      "geometry": {
        "type": "Point",
        "coordinates": [
          10.4896134,
          42.9858967
        ]
      },
      "id": "osm-location",
      "type": "Feature",
      "properties": {
        "description": "Representative location based on OpenStreetMap.",
        "location_precision": "precise",
        "title": "OSM location of Parco archeologico di Baratti e Populonia - Scavo a Poggio del Molino o del Telegrafo",
        "link": "http://pleiades.stoa.org/places/24736652/osm-location"
      }
    }
  ]
}