{
  "type": "FeatureCollection",
  "title": "Untitled",
  "id": "247647",
  "description": "An ancient place, cited: BAtlas 25 C4 unnamed bridge (Golmayo, SW Numantia)",
  "bbox": [
    -2.542903,
    41.747134,
    -2.542903,
    41.747134
  ],
  "reprPoint": [
    -2.542903,
    41.747134
  ],
  "features": [
    {
      "geometry": {
        "type": "Point",
        "coordinates": [
          -2.542903,
          41.747134
        ]
      },
      "id": "darmc-location-27815",
      "type": "Feature",
      "properties": {
        "description": "1M scale point location",
        "location_precision": "precise",
        "title": "DARMC location 27815",
        "link": "http://pleiades.stoa.org/places/247647/darmc-location-27815"
      }
    }
  ]
}