{
  "type": "FeatureCollection",
  "title": "Untitled",
  "id": "247648",
  "description": "An ancient place, cited: BAtlas 25 D2 unnamed bridge (Puente de Reparacea over R. Baidasoa, SE Oiasso)",
  "bbox": [
    -1.62778,
    43.134832,
    -1.62778,
    43.134832
  ],
  "reprPoint": [
    -1.62778,
    43.134832
  ],
  "features": [
    {
      "geometry": {
        "type": "Point",
        "coordinates": [
          -1.62778,
          43.134832
        ]
      },
      "id": "darmc-location-27819",
      "type": "Feature",
      "properties": {
        "description": "1M scale point location",
        "location_precision": "precise",
        "title": "DARMC location 27819",
        "link": "http://pleiades.stoa.org/places/247648/darmc-location-27819"
      }
    }
  ]
}