{
  "type": "FeatureCollection",
  "title": "Puente Romano (Talamanca del Jarama)",
  "id": "247643",
  "description": "A five span stone bridge (Talamanca over R. Jarama, W Arriaca).",
  "bbox": [
    -3.53107,
    40.723108,
    -3.52016,
    40.75137
  ],
  "reprPoint": [
    -3.525615,
    40.737239
  ],
  "features": [
    {
      "geometry": {
        "type": "Point",
        "coordinates": [
          -3.52016,
          40.75137
        ]
      },
      "id": "location-of-bridge-over-r.-jarama-at-talamanca-del-jarama",
      "type": "Feature",
      "properties": {
        "description": "A five span stone bridge",
        "location_precision": "precise",
        "title": "Location of bridge over R. jarama at Talamanca del Jarama",
        "link": "http://pleiades.stoa.org/places/247643/location-of-bridge-over-r.-jarama-at-talamanca-del-jarama"
      }
    }
  ]
}