{
  "type": "FeatureCollection",
  "title": "Anfiteatro di Bleso",
  "id": "248553771",
  "bbox": [
    12.7981959,
    41.960833,
    12.7981959,
    41.960833
  ],
  "description": "The \"Anfiteatro di Bleso\" is a second century A.D. Roman amphitheater at Tibur (modern Tivoli in Italy).",
  "connectsWith": [
    "423081"
  ],
  "features": [
    {
      "type": "Feature",
      "geometry": {
        "type": "Point",
        "coordinates": [
          12.7981959,
          41.960833
        ]
      },
      "properties": {
        "description": "representative point"
      }
    },
    {
      "geometry": {
        "type": "Point",
        "coordinates": [
          12.7981959,
          41.960833
        ]
      },
      "id": "osm-location-of-anfiteatro-di-bleso",
      "type": "Feature",
      "properties": {
        "description": "Location based on OpenStreetMap",
        "location_precision": "precise",
        "title": "OSM location of Anfiteatro di Bleso",
        "link": "http://pleiades.stoa.org/places/248553771/osm-location-of-anfiteatro-di-bleso"
      }
    }
  ]
}