{
  "type": "FeatureCollection",
  "title": "Untitled",
  "id": "249951",
  "description": "An ancient place, cited: BAtlas 25 F2 no. 45 (La Tasque, Cm. Cadeilhan-St-Clar)",
  "bbox": [
    0.788422,
    43.830641,
    0.788422,
    43.830641
  ],
  "reprPoint": [
    0.788422,
    43.830641
  ],
  "names": [
    "La Tasque"
  ],
  "features": [
    {
      "geometry": {
        "type": "Point",
        "coordinates": [
          0.788422,
          43.830641
        ]
      },
      "id": "center-of-batlas-location",
      "type": "Feature",
      "properties": {
        "description": "A positive identification of the sub-commune location noted in the Barrington Atlas directory",
        "location_precision": "precise",
        "title": "Center point of location",
        "link": "http://pleiades.stoa.org/places/249951/center-of-batlas-location"
      }
    }
  ]
}