{
  "type": "FeatureCollection",
  "title": "Untitled",
  "id": "249980",
  "description": "An ancient place, cited: BAtlas 25 F2 no. 74 (L’Isle-de-Noé)",
  "bbox": [
    0.413096,
    43.586765,
    0.413096,
    43.586765
  ],
  "reprPoint": [
    0.413096,
    43.586765
  ],
  "features": [
    {
      "geometry": {
        "type": "Point",
        "coordinates": [
          0.413096,
          43.586765
        ]
      },
      "id": "center-of-batlas-location",
      "type": "Feature",
      "properties": {
        "description": "A positive identification of the sub-commune location noted in the Barrington Atlas directory",
        "location_precision": "precise",
        "title": "Center point of location",
        "link": "http://pleiades.stoa.org/places/249980/center-of-batlas-location"
      }
    }
  ]
}