{
  "type": "FeatureCollection",
  "title": "Untitled",
  "id": "249926",
  "description": "An ancient place, cited: BAtlas 25 E2 no. 20 (Maspie)",
  "bbox": [
    -0.147899,
    43.421,
    -0.147899,
    43.421
  ],
  "reprPoint": [
    -0.147899,
    43.421
  ],
  "features": [
    {
      "geometry": {
        "type": "Point",
        "coordinates": [
          -0.147899,
          43.421
        ]
      },
      "id": "center-of-batlas-location",
      "type": "Feature",
      "properties": {
        "description": "A positive identification of the sub-commune location noted in the Barrington Atlas directory",
        "location_precision": "precise",
        "title": "Center point of location",
        "link": "http://pleiades.stoa.org/places/249926/center-of-batlas-location"
      }
    }
  ]
}