{
  "type": "FeatureCollection",
  "title": "Untitled",
  "id": "249970",
  "description": "An ancient place, cited: BAtlas 25 G2 no. 64 (Madron, Cm. Saverdun)",
  "bbox": [
    1.573541,
    43.246669,
    1.573541,
    43.246669
  ],
  "reprPoint": [
    1.573541,
    43.246669
  ],
  "features": [
    {
      "geometry": {
        "type": "Point",
        "coordinates": [
          1.573541,
          43.246669
        ]
      },
      "id": "center-of-batlas-location",
      "type": "Feature",
      "properties": {
        "description": "A positive identification of the sub-commune location noted in the Barrington Atlas directory",
        "location_precision": "precise",
        "title": "Center point of location",
        "link": "http://pleiades.stoa.org/places/249970/center-of-batlas-location"
      }
    }
  ]
}