{
  "type": "FeatureCollection",
  "title": "Untitled",
  "id": "249952",
  "description": "An ancient place, cited: BAtlas 25 F2 no. 46 (Le Moulin, Cm. Homps)",
  "bbox": [
    0.844504,
    43.812924,
    0.844504,
    43.812924
  ],
  "reprPoint": [
    0.844504,
    43.812924
  ],
  "features": [
    {
      "geometry": {
        "type": "Point",
        "coordinates": [
          0.844504,
          43.812924
        ]
      },
      "id": "center-of-batlas-location",
      "type": "Feature",
      "properties": {
        "description": "A positive identification of the sub-commune location noted in the Barrington Atlas directory",
        "location_precision": "precise",
        "title": "Center point of location",
        "link": "http://pleiades.stoa.org/places/249952/center-of-batlas-location"
      }
    }
  ]
}