{
  "type": "FeatureCollection",
  "title": "Untitled",
  "id": "249991",
  "description": "An ancient place, cited: BAtlas 25 F2 no. 85 (Pujo)",
  "bbox": [
    0.066436,
    43.347612,
    0.066436,
    43.347612
  ],
  "reprPoint": [
    0.066436,
    43.347612
  ],
  "names": [
    "Pujo"
  ],
  "features": [
    {
      "geometry": {
        "type": "Point",
        "coordinates": [
          0.066436,
          43.347612
        ]
      },
      "id": "center-of-batlas-location",
      "type": "Feature",
      "properties": {
        "description": "A positive identification of the sub-commune location noted in the Barrington Atlas directory",
        "location_precision": "precise",
        "title": "Center point of location",
        "link": "http://pleiades.stoa.org/places/249991/center-of-batlas-location"
      }
    }
  ]
}