{
  "type": "FeatureCollection",
  "title": "Untitled",
  "id": "249974",
  "bbox": [
    0.469799,
    43.428389,
    0.469799,
    43.428389
  ],
  "description": "An ancient place, cited: BAtlas 25 F2 no. 68 (St-Elix-Theux)",
  "features": [
    {
      "type": "Feature",
      "geometry": {
        "type": "Point",
        "coordinates": [
          0.469799,
          43.428389
        ]
      },
      "properties": {
        "description": "representative point"
      }
    },
    {
      "geometry": {
        "type": "Point",
        "coordinates": [
          0.469799,
          43.428389
        ]
      },
      "id": "center-of-batlas-location",
      "type": "Feature",
      "properties": {
        "description": "A positive identification of the sub-commune location noted in the Barrington Atlas directory",
        "location_precision": "precise",
        "title": "Center point of location",
        "link": "http://pleiades.stoa.org/places/249974/center-of-batlas-location"
      }
    }
  ]
}