{
  "type": "FeatureCollection",
  "title": "Barat de Vin Gallo-Roman villa",
  "id": "249908",
  "bbox": [
    -1.034417,
    43.5184724,
    -1.034417,
    43.5184724
  ],
  "description": "A Gallo-Roman villa dating to the third through fifth centuries. There are well-preserved elements of a bath complex.",
  "names": [
    "Sorde-l'Abbaye"
  ],
  "features": [
    {
      "type": "Feature",
      "geometry": {
        "type": "Point",
        "coordinates": [
          -1.034417,
          43.5184724
        ]
      },
      "properties": {
        "description": "representative point"
      }
    },
    {
      "geometry": {
        "type": "Point",
        "coordinates": [
          -1.034417,
          43.5184724
        ]
      },
      "id": "osm-location-of-villa-gallo-romaine-de-barat-de",
      "type": "Feature",
      "properties": {
        "description": "Representative location based on OpenStreetMap",
        "location_precision": "precise",
        "title": "OSM location of Villa gallo-romaine de Barat de Vin",
        "link": "http://pleiades.stoa.org/places/249908/osm-location-of-villa-gallo-romaine-de-barat-de"
      }
    }
  ]
}