{
  "type": "FeatureCollection",
  "title": "Untitled",
  "id": "249910",
  "description": "An ancient place, cited: BAtlas 25 E2 no. 4 (Gaujacq)",
  "bbox": [
    -0.74003,
    43.64104,
    -0.74003,
    43.64104
  ],
  "reprPoint": [
    -0.74003,
    43.64104
  ],
  "features": [
    {
      "geometry": {
        "type": "Point",
        "coordinates": [
          -0.74003,
          43.64104
        ]
      },
      "id": "center-of-batlas-location",
      "type": "Feature",
      "properties": {
        "description": "A positive identification of the sub-commune location noted in the Barrington Atlas directory",
        "location_precision": "precise",
        "title": "Center point of location",
        "link": "http://pleiades.stoa.org/places/249910/center-of-batlas-location"
      }
    }
  ]
}