{
  "type": "FeatureCollection",
  "title": "Untitled",
  "id": "249928",
  "description": "An ancient place, cited: BAtlas 25 E2 no. 22 (Bielle)",
  "bbox": [
    -0.432195,
    43.055106,
    -0.432195,
    43.055106
  ],
  "reprPoint": [
    -0.432195,
    43.055106
  ],
  "features": [
    {
      "geometry": {
        "type": "Point",
        "coordinates": [
          -0.432195,
          43.055106
        ]
      },
      "id": "center-of-batlas-location",
      "type": "Feature",
      "properties": {
        "description": "A positive identification of the sub-commune location noted in the Barrington Atlas directory",
        "location_precision": "precise",
        "title": "Center point of location",
        "link": "http://pleiades.stoa.org/places/249928/center-of-batlas-location"
      }
    }
  ]
}