{
  "type": "FeatureCollection",
  "title": "Untitled",
  "id": "249913",
  "description": "An ancient place, cited: BAtlas 25 E2 no. 7 (Labastide d’Armagnac)",
  "bbox": [
    -0.18562,
    43.969386,
    -0.18562,
    43.969386
  ],
  "reprPoint": [
    -0.18562,
    43.969386
  ],
  "names": [
    "Labastide-d'Armagnac"
  ],
  "features": [
    {
      "geometry": {
        "type": "Point",
        "coordinates": [
          -0.18562,
          43.969386
        ]
      },
      "id": "center-of-batlas-location",
      "type": "Feature",
      "properties": {
        "description": "A positive identification of the sub-commune location noted in the Barrington Atlas directory",
        "location_precision": "precise",
        "title": "Center point of location",
        "link": "http://pleiades.stoa.org/places/249913/center-of-batlas-location"
      }
    }
  ]
}