{
  "type": "FeatureCollection",
  "title": "Untitled",
  "id": "249971",
  "bbox": [
    1.346575,
    43.276267,
    1.346575,
    43.276267
  ],
  "description": "An ancient place, cited: BAtlas 25 G2 no. 65 (Lézat-sur-Lèze)",
  "names": [
    "Lézat-sur-Lèze"
  ],
  "features": [
    {
      "type": "Feature",
      "geometry": {
        "type": "Point",
        "coordinates": [
          1.346575,
          43.276267
        ]
      },
      "properties": {
        "description": "representative point"
      }
    },
    {
      "geometry": {
        "type": "Point",
        "coordinates": [
          1.346575,
          43.276267
        ]
      },
      "id": "center-of-batlas-location",
      "type": "Feature",
      "properties": {
        "description": "A positive identification of the sub-commune location noted in the Barrington Atlas directory",
        "location_precision": "precise",
        "title": "Center point of location",
        "link": "http://pleiades.stoa.org/places/249971/center-of-batlas-location"
      }
    }
  ]
}