{
  "type": "FeatureCollection",
  "title": "Lalonquette",
  "id": "249924",
  "description": "A Gallo-Roman villa.",
  "bbox": [
    -0.310707,
    43.502662,
    -0.310707,
    43.502662
  ],
  "reprPoint": [
    -0.310707,
    43.502662
  ],
  "names": [
    "Lalonquette"
  ],
  "features": [
    {
      "geometry": {
        "type": "Point",
        "coordinates": [
          -0.310707,
          43.502662
        ]
      },
      "id": "center-of-batlas-location",
      "type": "Feature",
      "properties": {
        "description": "A positive identification of the sub-commune location noted in the Barrington Atlas directory",
        "location_precision": "precise",
        "title": "Center point of location",
        "link": "http://pleiades.stoa.org/places/249924/center-of-batlas-location"
      }
    }
  ]
}