{
  "type": "FeatureCollection",
  "title": "Untitled",
  "id": "249943",
  "description": "An ancient place, cited: BAtlas 25 F2 no. 37 (Condom)",
  "bbox": [
    0.372492,
    43.958223,
    0.372492,
    43.958223
  ],
  "reprPoint": [
    0.372492,
    43.958223
  ],
  "features": [
    {
      "geometry": {
        "type": "Point",
        "coordinates": [
          0.372492,
          43.958223
        ]
      },
      "id": "center-of-batlas-location",
      "type": "Feature",
      "properties": {
        "description": "A positive identification of the sub-commune location noted in the Barrington Atlas directory",
        "location_precision": "precise",
        "title": "Center point of location",
        "link": "http://pleiades.stoa.org/places/249943/center-of-batlas-location"
      }
    }
  ]
}