{
  "type": "FeatureCollection",
  "title": "Untitled",
  "id": "249978",
  "description": "An ancient place, cited: BAtlas 25 F2 no. 72 (Auterive)",
  "bbox": [
    0.614222,
    43.582351,
    0.614222,
    43.582351
  ],
  "reprPoint": [
    0.614222,
    43.582351
  ],
  "features": [
    {
      "geometry": {
        "type": "Point",
        "coordinates": [
          0.614222,
          43.582351
        ]
      },
      "id": "center-of-batlas-location",
      "type": "Feature",
      "properties": {
        "description": "A positive identification of the sub-commune location noted in the Barrington Atlas directory",
        "location_precision": "precise",
        "title": "Center point of location",
        "link": "http://pleiades.stoa.org/places/249978/center-of-batlas-location"
      }
    }
  ]
}