{
  "type": "FeatureCollection",
  "title": "Untitled",
  "id": "249934",
  "bbox": [
    0.558733,
    44.031642,
    0.558733,
    44.031642
  ],
  "description": "An ancient place, cited: BAtlas 25 F1 no. 28 (La Gleyzette, Cm. St-Mézard)",
  "features": [
    {
      "type": "Feature",
      "geometry": {
        "type": "Point",
        "coordinates": [
          0.558733,
          44.031642
        ]
      },
      "properties": {
        "description": "representative point"
      }
    },
    {
      "geometry": {
        "type": "Point",
        "coordinates": [
          0.558733,
          44.031642
        ]
      },
      "id": "center-of-batlas-location",
      "type": "Feature",
      "properties": {
        "description": "The center of the commune noted in the Barrington Atlas directory",
        "location_precision": "precise",
        "title": "Center point of location",
        "link": "http://pleiades.stoa.org/places/249934/center-of-batlas-location"
      }
    }
  ]
}