{
  "type": "FeatureCollection",
  "title": "Untitled",
  "id": "249953",
  "description": "An ancient place, cited: BAtlas 25 F2 no. 47 (Puységur)",
  "bbox": [
    0.603899,
    43.776629,
    0.603899,
    43.776629
  ],
  "reprPoint": [
    0.603899,
    43.776629
  ],
  "names": [
    "Puységur"
  ],
  "features": [
    {
      "geometry": {
        "type": "Point",
        "coordinates": [
          0.603899,
          43.776629
        ]
      },
      "id": "center-of-batlas-location",
      "type": "Feature",
      "properties": {
        "description": "A positive identification of the sub-commune location noted in the Barrington Atlas directory",
        "location_precision": "precise",
        "title": "Center point of location",
        "link": "http://pleiades.stoa.org/places/249953/center-of-batlas-location"
      }
    }
  ]
}