{
  "type": "FeatureCollection",
  "title": "Untitled",
  "id": "249908",
  "description": "An ancient place, cited: BAtlas 25 D2 no. 2 (Sorde-l’Abbaye)",
  "bbox": [
    -1.054922,
    43.529556,
    -1.054922,
    43.529556
  ],
  "reprPoint": [
    -1.054922,
    43.529556
  ],
  "names": [
    "Sorde-l'Abbaye"
  ],
  "features": [
    {
      "geometry": {
        "type": "Point",
        "coordinates": [
          -1.054922,
          43.529556
        ]
      },
      "id": "center-of-batlas-location",
      "type": "Feature",
      "properties": {
        "description": "A positive identification of the sub-commune location noted in the Barrington Atlas directory",
        "location_precision": "precise",
        "title": "Center point of location",
        "link": "http://pleiades.stoa.org/places/249908/center-of-batlas-location"
      }
    }
  ]
}