{
  "type": "FeatureCollection",
  "title": "Untitled",
  "id": "249947",
  "description": "An ancient place, cited: BAtlas 25 F2 no. 41 (Cieutat, Cm. d’Eauze)",
  "bbox": [
    0.11314,
    43.861766,
    0.11314,
    43.861766
  ],
  "reprPoint": [
    0.11314,
    43.861766
  ],
  "features": [
    {
      "geometry": {
        "type": "Point",
        "coordinates": [
          0.11314,
          43.861766
        ]
      },
      "id": "center-of-batlas-location",
      "type": "Feature",
      "properties": {
        "description": "A positive identification of the sub-commune location noted in the Barrington Atlas directory",
        "location_precision": "precise",
        "title": "Center point of location",
        "link": "http://pleiades.stoa.org/places/249947/center-of-batlas-location"
      }
    }
  ]
}