{
  "type": "FeatureCollection",
  "title": "Untitled",
  "id": "249925",
  "description": "An ancient place, cited: BAtlas 25 E2 no. 19 (Simacourbe)",
  "bbox": [
    -0.16544,
    43.44611,
    -0.16544,
    43.44611
  ],
  "reprPoint": [
    -0.16544,
    43.44611
  ],
  "features": [
    {
      "geometry": {
        "type": "Point",
        "coordinates": [
          -0.16544,
          43.44611
        ]
      },
      "id": "center-of-batlas-location",
      "type": "Feature",
      "properties": {
        "description": "A positive identification of the sub-commune location noted in the Barrington Atlas directory",
        "location_precision": "precise",
        "title": "Center point of location",
        "link": "http://pleiades.stoa.org/places/249925/center-of-batlas-location"
      }
    }
  ]
}