{
  "type": "FeatureCollection",
  "title": "Untitled",
  "id": "249957",
  "bbox": [
    2.018373,
    43.979944,
    2.018373,
    43.979944
  ],
  "description": "An ancient place, cited: BAtlas 25 G2 no. 51 (Larroque, Cm. Cestayrols)",
  "features": [
    {
      "type": "Feature",
      "geometry": {
        "type": "Point",
        "coordinates": [
          2.018373,
          43.979944
        ]
      },
      "properties": {
        "description": "representative point"
      }
    },
    {
      "geometry": {
        "type": "Point",
        "coordinates": [
          2.018373,
          43.979944
        ]
      },
      "id": "center-of-batlas-location",
      "type": "Feature",
      "properties": {
        "description": "A positive identification of the sub-commune location noted in the Barrington Atlas directory",
        "location_precision": "precise",
        "title": "Center point of location",
        "link": "http://pleiades.stoa.org/places/249957/center-of-batlas-location"
      }
    }
  ]
}