{
  "type": "FeatureCollection",
  "title": "Untitled",
  "id": "249977",
  "bbox": [
    0.711425,
    43.58742,
    0.711425,
    43.58742
  ],
  "description": "An ancient place, cited: BAtlas 25 F2 no. 71 (Le Taros, Cm. Castelnau-Barbarens)",
  "features": [
    {
      "type": "Feature",
      "geometry": {
        "type": "Point",
        "coordinates": [
          0.711425,
          43.58742
        ]
      },
      "properties": {
        "description": "representative point"
      }
    },
    {
      "geometry": {
        "type": "Point",
        "coordinates": [
          0.711425,
          43.58742
        ]
      },
      "id": "center-of-batlas-location",
      "type": "Feature",
      "properties": {
        "description": "A positive identification of the sub-commune location noted in the Barrington Atlas directory",
        "location_precision": "precise",
        "title": "Center point of location",
        "link": "http://pleiades.stoa.org/places/249977/center-of-batlas-location"
      }
    }
  ]
}