{
  "type": "FeatureCollection",
  "title": "Untitled",
  "id": "250001",
  "bbox": [
    1.06974,
    43.203636,
    1.06974,
    43.203636
  ],
  "description": "An ancient place, cited: BAtlas 25 G2 no. 95 (Palaminy)",
  "features": [
    {
      "type": "Feature",
      "geometry": {
        "type": "Point",
        "coordinates": [
          1.06974,
          43.203636
        ]
      },
      "properties": {
        "description": "representative point"
      }
    },
    {
      "geometry": {
        "type": "Point",
        "coordinates": [
          1.06974,
          43.203636
        ]
      },
      "id": "center-of-batlas-location",
      "type": "Feature",
      "properties": {
        "description": "A positive identification of the sub-commune location noted in the Barrington Atlas directory",
        "location_precision": "precise",
        "title": "Center point of location",
        "link": "http://pleiades.stoa.org/places/250001/center-of-batlas-location"
      }
    }
  ]
}