{
  "type": "FeatureCollection",
  "title": "Untitled",
  "id": "250031",
  "description": "An ancient place, cited: BAtlas 25 B3 no. 125 (Montes de la Peña (Salinas de Rosio))",
  "bbox": [
    -3.418966,
    42.981398,
    -3.418966,
    42.981398
  ],
  "reprPoint": [
    -3.418966,
    42.981398
  ],
  "features": [
    {
      "geometry": {
        "type": "Point",
        "coordinates": [
          -3.418966,
          42.981398
        ]
      },
      "id": "darmc-location-31004",
      "type": "Feature",
      "properties": {
        "description": "1M scale point location",
        "location_precision": "precise",
        "title": "DARMC location 31004",
        "link": "http://pleiades.stoa.org/places/250031/darmc-location-31004"
      }
    }
  ]
}