{
  "type": "FeatureCollection",
  "title": "Olivet d’en Pujol",
  "id": "250007",
  "bbox": [
    3.058078,
    42.122417,
    3.058078,
    42.122417
  ],
  "description": "An agricultural storage and processing facility including a large number of dolia, likely associated with a Roman villa or suburban fundus, Olivet d'en Pujol is located in the modern municipality of Vilademat, which is in the Catalonian comarca of Alt Empordà.",
  "names": [
    "Olivet d’en Pujol",
    "Olivet de la Pujada del Delme"
  ],
  "features": [
    {
      "type": "Feature",
      "geometry": {
        "type": "Point",
        "coordinates": [
          3.058078,
          42.122417
        ]
      },
      "properties": {
        "description": "representative point"
      }
    },
    {
      "geometry": {
        "type": "Point",
        "coordinates": [
          3.058078,
          42.122417
        ]
      },
      "id": "imagery-location-of-visible-remains",
      "type": "Feature",
      "properties": {
        "description": "Centerpoint of remains visible in Google Earth historical imagery dated 12/31/2009.",
        "location_precision": "precise",
        "title": "Imagery Location of visible remains",
        "link": "http://pleiades.stoa.org/places/250007/imagery-location-of-visible-remains"
      }
    }
  ]
}