{
  "type": "FeatureCollection",
  "title": "Untitled",
  "id": "250007",
  "bbox": [
    3.0753648,
    42.1327669,
    3.0753648,
    42.1327669
  ],
  "description": "An ancient place, cited: BAtlas 25 I3 no. 101 (Olivet d’en Pujol (Vilademat))",
  "features": [
    {
      "type": "Feature",
      "geometry": {
        "type": "Point",
        "coordinates": [
          3.0753648,
          42.1327669
        ]
      },
      "properties": {
        "description": "representative point"
      }
    },
    {
      "geometry": {
        "type": "Point",
        "coordinates": [
          3.0753648,
          42.1327669
        ]
      },
      "id": "osm-location",
      "type": "Feature",
      "properties": {
        "description": "Location based on OpenStreetMap",
        "location_precision": "precise",
        "title": "OSM location of modern village of Viladamat",
        "link": "http://pleiades.stoa.org/places/250007/osm-location"
      }
    }
  ]
}