{
  "type": "FeatureCollection",
  "title": "Untitled",
  "id": "250005",
  "bbox": [
    1.388013,
    43.001537,
    1.388013,
    43.001537
  ],
  "description": "An ancient place, cited: BAtlas 25 G2 no. 99 (Le Goutil, Cm. La Bastide-de-Sérou)",
  "features": [
    {
      "type": "Feature",
      "geometry": {
        "type": "Point",
        "coordinates": [
          1.388013,
          43.001537
        ]
      },
      "properties": {
        "description": "representative point"
      }
    },
    {
      "geometry": {
        "type": "Point",
        "coordinates": [
          1.388013,
          43.001537
        ]
      },
      "id": "center-of-batlas-location",
      "type": "Feature",
      "properties": {
        "description": "A positive identification of the sub-commune location noted in the Barrington Atlas directory",
        "location_precision": "precise",
        "title": "Center point of location",
        "link": "http://pleiades.stoa.org/places/250005/center-of-batlas-location"
      }
    }
  ]
}