{
  "type": "FeatureCollection",
  "title": "Monastery of Saint John the Theologian",
  "id": "251542598",
  "bbox": [
    26.5472911,
    37.3091209,
    26.5472911,
    37.3091209
  ],
  "description": "The Monastery of Saint John the Theologian (also known as the Monastery of Saint John the Divine) is a Greek Orthodox monastery dating to AD 1088 on the island of Patmos.",
  "connectsWith": [
    "599872"
  ],
  "features": [
    {
      "type": "Feature",
      "geometry": {
        "type": "Point",
        "coordinates": [
          26.5472911,
          37.3091209
        ]
      },
      "properties": {
        "description": "representative point"
      }
    },
    {
      "geometry": {
        "type": "Point",
        "coordinates": [
          26.5472911,
          37.3091209
        ]
      },
      "id": "location-of-monastery-of-saint-john-the-theologian",
      "type": "Feature",
      "properties": {
        "description": "Representative location based on OpenStreetMap.",
        "location_precision": "precise",
        "title": "OSM location of Monastery of Saint John the Theologian",
        "link": "http://pleiades.stoa.org/places/251542598/location-of-monastery-of-saint-john-the-theologian"
      }
    }
  ]
}