{
  "type": "FeatureCollection",
  "title": "Pyramid K.1 at El-Kurru",
  "id": "252614721",
  "bbox": [
    31.7709239,
    18.4094923,
    31.7709239,
    18.4094923
  ],
  "description": "The oldest tomb at El-Kurru.",
  "connectsWith": [
    "805623"
  ],
  "features": [
    {
      "type": "Feature",
      "geometry": {
        "type": "Point",
        "coordinates": [
          31.7709239,
          18.4094923
        ]
      },
      "properties": {
        "description": "representative point"
      }
    },
    {
      "geometry": {
        "type": "Point",
        "coordinates": [
          31.7709239,
          18.4094923
        ]
      },
      "id": "location-of-pyramid-ku-1",
      "type": "Feature",
      "properties": {
        "description": "Location based on OpenStreetMap",
        "location_precision": "precise",
        "title": "OSM location of pyramid Ku 1",
        "link": "http://pleiades.stoa.org/places/252614721/location-of-pyramid-ku-1"
      }
    }
  ]
}