{
  "type": "FeatureCollection",
  "title": "Beta Samati",
  "id": "253102124",
  "bbox": [
    38.91667,
    14.25,
    38.91667,
    14.25
  ],
  "description": "Archaeological investigation at the site of Beta Samati, located between Aksum and the Red Sea, has revealed remains of a significant Aksumite administrative center. The archaeological site is located in the vicinity of Yeha, Ethiopia.",
  "features": [
    {
      "type": "Feature",
      "geometry": {
        "type": "Point",
        "coordinates": [
          38.91667,
          14.25
        ]
      },
      "properties": {
        "description": "representative point"
      }
    },
    {
      "geometry": {
        "type": "Point",
        "coordinates": [
          38.91667,
          14.25
        ]
      },
      "id": "osm-location-of-modern-yeha-ethiopia",
      "type": "Feature",
      "properties": {
        "description": "Location based on OpenStreetMap",
        "location_precision": "precise",
        "title": "OSM location of modern Yeha, Ethiopia",
        "link": "http://pleiades.stoa.org/places/253102124/osm-location-of-modern-yeha-ethiopia"
      }
    }
  ]
}