{
  "type": "FeatureCollection",
  "title": "Beta Samati",
  "id": "253102124",
  "bbox": [
    39.0355175,
    14.3434935,
    39.0355175,
    14.3434935
  ],
  "description": "Archaeological investigation at the site of Beta Samati, located between Aksum and the Red Sea, has revealed remains of a significant Aksumite administrative center. The archaeological site is located in the vicinity of Yeha, Ethiopia.",
  "features": [
    {
      "type": "Feature",
      "geometry": {
        "type": "Point",
        "coordinates": [
          39.0355175,
          14.3434935
        ]
      },
      "properties": {
        "description": "representative point"
      }
    },
    {
      "geometry": {
        "type": "Point",
        "coordinates": [
          39.0355175,
          14.3434935
        ]
      },
      "id": "osm-location-of-beta-samati-a-adeg-adegaaa2-aps",
      "type": "Feature",
      "properties": {
        "description": "Representative location based on OpenStreetMap",
        "location_precision": "precise",
        "title": "OSM location of beta samati ቤተ ሰማዕቲ ፣ መዝብር",
        "link": "http://pleiades.stoa.org/places/253102124/osm-location-of-beta-samati-a-adeg-adegaaa2-aps"
      }
    }
  ]
}