{
  "type": "FeatureCollection",
  "title": "Ad Herculem",
  "id": "255953",
  "description": "An ancient place, cited: BAtlas 26 D5 Ad Herculem",
  "bbox": [
    -6.163431,
    36.351621,
    -6.163431,
    36.351621
  ],
  "reprPoint": [
    -6.163431,
    36.351621
  ],
  "names": [
    "Ad Herculem"
  ],
  "features": [
    {
      "geometry": {
        "type": "Point",
        "coordinates": [
          -6.163431,
          36.351621
        ]
      },
      "id": "darmc-location-7448",
      "type": "Feature",
      "properties": {
        "description": "1M scale point location",
        "location_precision": "precise",
        "title": "DARMC location 7448",
        "link": "http://pleiades.stoa.org/places/255953/darmc-location-7448"
      }
    }
  ]
}