{
  "type": "FeatureCollection",
  "title": "Artigi",
  "id": "255990",
  "description": "An ancient place, cited: BAtlas 26 E3 Artigi",
  "bbox": [
    -5.545601,
    38.722599,
    -5.545601,
    38.722599
  ],
  "reprPoint": [
    -5.545601,
    38.722599
  ],
  "names": [
    "Artigi"
  ],
  "features": [
    {
      "geometry": {
        "type": "Point",
        "coordinates": [
          -5.545601,
          38.722599
        ]
      },
      "id": "darmc-location-19732",
      "type": "Feature",
      "properties": {
        "description": "1M scale point location",
        "location_precision": "precise",
        "title": "DARMC location 19732",
        "link": "http://pleiades.stoa.org/places/255990/darmc-location-19732"
      }
    }
  ]
}