{
  "type": "FeatureCollection",
  "title": "Alcántara",
  "id": "255966",
  "bbox": [
    -6.886579,
    39.719023,
    -6.886579,
    39.719023
  ],
  "description": "The Roman temple of Alcántara is a well-preserved structure located at one side of the Alcántara Bridge in Extremadura (Spain). The building, dating to A.D. 103, is the work of Caius Iulius Lacer. The lintel inscription indicates the structure was dedicated to Trajan.",
  "connectsWith": [
    "257459"
  ],
  "features": [
    {
      "type": "Feature",
      "geometry": {
        "type": "Point",
        "coordinates": [
          -6.886579,
          39.719023
        ]
      },
      "properties": {
        "description": "representative point"
      }
    },
    {
      "geometry": {
        "type": "Point",
        "coordinates": [
          -6.886579,
          39.719023
        ]
      },
      "id": "darmc-location-4015",
      "type": "Feature",
      "properties": {
        "description": "1M scale point location",
        "location_precision": "precise",
        "title": "DARMC location 4015",
        "link": "http://pleiades.stoa.org/places/255966/darmc-location-4015"
      }
    }
  ]
}