{
  "type": "FeatureCollection",
  "title": "Arunda",
  "id": "255992",
  "description": "An ancient place, cited: BAtlas 26 E5 Arunda",
  "bbox": [
    -5.166408,
    36.74194,
    -5.166408,
    36.74194
  ],
  "reprPoint": [
    -5.166408,
    36.74194
  ],
  "names": [
    "Arunda"
  ],
  "features": [
    {
      "geometry": {
        "type": "Point",
        "coordinates": [
          -5.166408,
          36.74194
        ]
      },
      "id": "darmc-location-19987",
      "type": "Feature",
      "properties": {
        "description": "1M scale point location",
        "location_precision": "precise",
        "title": "DARMC location 19987",
        "link": "http://pleiades.stoa.org/places/255992/darmc-location-19987"
      }
    }
  ]
}