{
  "type": "FeatureCollection",
  "title": "Alcántara",
  "id": "255966",
  "description": "An ancient place, cited: BAtlas 26 D2 Alcántara",
  "bbox": [
    -6.8915053,
    39.719023,
    -6.886579,
    39.7216254
  ],
  "reprPoint": [
    -6.88904215,
    39.7203242
  ],
  "features": [
    {
      "geometry": {
        "type": "Point",
        "coordinates": [
          -6.886579,
          39.719023
        ]
      },
      "id": "darmc-location-4015",
      "type": "Feature",
      "properties": {
        "description": "1M scale point location",
        "location_precision": "precise",
        "title": "DARMC location 4015",
        "link": "http://pleiades.stoa.org/places/255966/darmc-location-4015"
      }
    }
  ]
}