{
  "type": "FeatureCollection",
  "title": "Castelo do Corregedor",
  "id": "256078",
  "description": "An ancient place, cited: BAtlas 26 C2 Castelo do Corregedor",
  "bbox": [
    -7.38019,
    39.396411,
    -7.38019,
    39.396411
  ],
  "reprPoint": [
    -7.38019,
    39.396411
  ],
  "features": [
    {
      "geometry": {
        "type": "Point",
        "coordinates": [
          -7.38019,
          39.396411
        ]
      },
      "id": "darmc-location-20128",
      "type": "Feature",
      "properties": {
        "description": "1M scale point location",
        "location_precision": "precise",
        "title": "DARMC location 20128",
        "link": "http://pleiades.stoa.org/places/256078/darmc-location-20128"
      }
    }
  ]
}