{
  "type": "FeatureCollection",
  "title": "Burdoga",
  "id": "256034",
  "description": "An ancient place, cited: BAtlas 26 E5 Burdoga",
  "bbox": [
    -5.812472,
    36.750825,
    -5.812472,
    36.750825
  ],
  "reprPoint": [
    -5.812472,
    36.750825
  ],
  "names": [
    "Burdoga"
  ],
  "features": [
    {
      "geometry": {
        "type": "Point",
        "coordinates": [
          -5.812472,
          36.750825
        ]
      },
      "id": "darmc-location-19751",
      "type": "Feature",
      "properties": {
        "description": "1M scale point location",
        "location_precision": "precise",
        "title": "DARMC location 19751",
        "link": "http://pleiades.stoa.org/places/256034/darmc-location-19751"
      }
    }
  ]
}