{
  "type": "FeatureCollection",
  "title": "Carrascona",
  "id": "256061",
  "description": "An ancient place, cited: BAtlas 26 E5 Carrascona",
  "bbox": [
    -5.980893,
    36.974787,
    -5.980893,
    36.974787
  ],
  "reprPoint": [
    -5.980893,
    36.974787
  ],
  "features": [
    {
      "geometry": {
        "type": "Point",
        "coordinates": [
          -5.980893,
          36.974787
        ]
      },
      "id": "darmc-location-20805",
      "type": "Feature",
      "properties": {
        "description": "1M scale point location",
        "location_precision": "precise",
        "title": "DARMC location 20805",
        "link": "http://pleiades.stoa.org/places/256061/darmc-location-20805"
      }
    }
  ]
}