{
  "type": "FeatureCollection",
  "title": "El Carambolo",
  "id": "256055",
  "bbox": [
    -6.03749,
    37.3931284,
    -6.03749,
    37.3931284
  ],
  "description": "An ancient place, cited: BAtlas 26 D4 El Carambolo",
  "features": [
    {
      "type": "Feature",
      "geometry": {
        "type": "Point",
        "coordinates": [
          -6.03749,
          37.3931284
        ]
      },
      "properties": {
        "description": "representative point"
      }
    },
    {
      "geometry": {
        "type": "Point",
        "coordinates": [
          -6.03749,
          37.3931284
        ]
      },
      "id": "osm-location-of-el-carambolo",
      "type": "Feature",
      "properties": {
        "description": "Representative location based on OpenStreetMap",
        "location_precision": "precise",
        "title": "OSM location of El Carambolo",
        "link": "http://pleiades.stoa.org/places/256055/osm-location-of-el-carambolo"
      }
    }
  ]
}