{
  "type": "FeatureCollection",
  "title": "Casa Branca",
  "id": "256066",
  "bbox": [
    -8.1083642,
    38.1544849,
    -8.1083642,
    38.1544849
  ],
  "description": "An ancient place, cited: BAtlas 26 B3 Casa Branca",
  "features": [
    {
      "type": "Feature",
      "geometry": {
        "type": "Point",
        "coordinates": [
          -8.1083642,
          38.1544849
        ]
      },
      "properties": {
        "description": "representative point"
      }
    },
    {
      "geometry": {
        "type": "Point",
        "coordinates": [
          -8.1083642,
          38.1544849
        ]
      },
      "id": "osm-location",
      "type": "Feature",
      "properties": {
        "description": "Representative location based on OpenStreetMap.",
        "location_precision": "precise",
        "title": "OSM location of Fortificação Romana de Casa Branca",
        "link": "http://pleiades.stoa.org/places/256066/osm-location"
      }
    }
  ]
}