{
  "type": "FeatureCollection",
  "title": "Castillo del Puerto",
  "id": "256082",
  "description": "An ancient place, cited: BAtlas 26 D2 Castillo del Puerto",
  "bbox": [
    -6.323822,
    39.374883,
    -6.323822,
    39.374883
  ],
  "reprPoint": [
    -6.323822,
    39.374883
  ],
  "features": [
    {
      "geometry": {
        "type": "Point",
        "coordinates": [
          -6.323822,
          39.374883
        ]
      },
      "id": "darmc-location-19084",
      "type": "Feature",
      "properties": {
        "description": "1M scale point location",
        "location_precision": "precise",
        "title": "DARMC location 19084",
        "link": "http://pleiades.stoa.org/places/256082/darmc-location-19084"
      }
    }
  ]
}