{
  "type": "FeatureCollection",
  "title": "Las Canteras",
  "id": "256050",
  "description": "An ancient place, cited: BAtlas 26 E4 Las Canteras",
  "bbox": [
    -5.777157,
    37.385449,
    -5.777157,
    37.385449
  ],
  "reprPoint": [
    -5.777157,
    37.385449
  ],
  "features": [
    {
      "geometry": {
        "type": "Point",
        "coordinates": [
          -5.777157,
          37.385449
        ]
      },
      "id": "darmc-location-20952",
      "type": "Feature",
      "properties": {
        "description": "1M scale point location",
        "location_precision": "precise",
        "title": "DARMC location 20952",
        "link": "http://pleiades.stoa.org/places/256050/darmc-location-20952"
      }
    }
  ]
}