{
  "type": "FeatureCollection",
  "title": "El Carambolo",
  "id": "256055",
  "bbox": [
    -6.038989,
    37.391091,
    -6.038989,
    37.391091
  ],
  "description": "An ancient place, cited: BAtlas 26 D4 El Carambolo",
  "features": [
    {
      "type": "Feature",
      "geometry": {
        "type": "Point",
        "coordinates": [
          -6.038989,
          37.391091
        ]
      },
      "properties": {
        "description": "representative point"
      }
    },
    {
      "geometry": {
        "type": "Point",
        "coordinates": [
          -6.038989,
          37.391091
        ]
      },
      "id": "darmc-location-20241",
      "type": "Feature",
      "properties": {
        "description": "1M scale point location",
        "location_precision": "precise",
        "title": "DARMC location 20241",
        "link": "http://pleiades.stoa.org/places/256055/darmc-location-20241"
      }
    }
  ]
}