{
  "type": "FeatureCollection",
  "title": "Caspiana",
  "id": "256070",
  "bbox": [
    -6.409619,
    38.753844,
    -6.409619,
    38.753844
  ],
  "description": "An ancient place, cited: BAtlas 26 D3 Caspiana",
  "names": [
    "Caspiana"
  ],
  "features": [
    {
      "type": "Feature",
      "geometry": {
        "type": "Point",
        "coordinates": [
          -6.409619,
          38.753844
        ]
      },
      "properties": {
        "description": "representative point"
      }
    },
    {
      "geometry": {
        "type": "Point",
        "coordinates": [
          -6.409619,
          38.753844
        ]
      },
      "id": "darmc-location-19603",
      "type": "Feature",
      "properties": {
        "description": "1M scale point location",
        "location_precision": "precise",
        "title": "DARMC location 19603",
        "link": "http://pleiades.stoa.org/places/256070/darmc-location-19603"
      }
    }
  ]
}