{
  "type": "FeatureCollection",
  "title": "Casal da Várzea",
  "id": "256067",
  "description": "An ancient place, cited: BAtlas 26 B2 Casal da Várzea",
  "bbox": [
    -8.049349,
    39.467159,
    -8.049349,
    39.467159
  ],
  "reprPoint": [
    -8.049349,
    39.467159
  ],
  "features": [
    {
      "geometry": {
        "type": "Point",
        "coordinates": [
          -8.049349,
          39.467159
        ]
      },
      "id": "darmc-location-17975",
      "type": "Feature",
      "properties": {
        "description": "1M scale point location",
        "location_precision": "precise",
        "title": "DARMC location 17975",
        "link": "http://pleiades.stoa.org/places/256067/darmc-location-17975"
      }
    }
  ]
}