{
  "type": "FeatureCollection",
  "title": "Casa Branca",
  "id": "256066",
  "description": "An ancient place, cited: BAtlas 26 B3 Casa Branca",
  "bbox": [
    -8.165553,
    38.539979,
    -8.165553,
    38.539979
  ],
  "reprPoint": [
    -8.165553,
    38.539979
  ],
  "features": [
    {
      "geometry": {
        "type": "Point",
        "coordinates": [
          -8.165553,
          38.539979
        ]
      },
      "id": "darmc-location-20120",
      "type": "Feature",
      "properties": {
        "description": "1M scale point location",
        "location_precision": "precise",
        "title": "DARMC location 20120",
        "link": "http://pleiades.stoa.org/places/256066/darmc-location-20120"
      }
    }
  ]
}