{
  "type": "FeatureCollection",
  "title": "Castra Caecilia",
  "id": "256083",
  "description": "An ancient place, cited: BAtlas 26 D2 Castra Caecilia",
  "bbox": [
    -6.370782,
    39.476214,
    -6.352065,
    39.5024526
  ],
  "reprPoint": [
    -6.3614235,
    39.4893333
  ],
  "names": [
    "Castra Caecilia"
  ],
  "features": [
    {
      "geometry": {
        "type": "Point",
        "coordinates": [
          -6.370782,
          39.476214
        ]
      },
      "id": "darmc-location-19604",
      "type": "Feature",
      "properties": {
        "description": "1M scale point location",
        "location_precision": "precise",
        "title": "DARMC location 19604",
        "link": "http://pleiades.stoa.org/places/256083/darmc-location-19604"
      }
    },
    {
      "geometry": {
        "type": "Point",
        "coordinates": [
          -6.352065,
          39.5024526
        ]
      },
      "id": "location-of-castrum",
      "type": "Feature",
      "properties": {
        "description": "Representative location based on OpenStreetMap.",
        "location_precision": "precise",
        "title": "OSM location of castrum",
        "link": "http://pleiades.stoa.org/places/256083/location-of-castrum"
      }
    }
  ]
}