{
  "type": "FeatureCollection",
  "title": "Campanario",
  "id": "256046",
  "bbox": [
    -6.811738,
    37.556029,
    -6.811738,
    37.556029
  ],
  "description": "An ancient place, cited: BAtlas 26 D4 Campanario",
  "features": [
    {
      "type": "Feature",
      "geometry": {
        "type": "Point",
        "coordinates": [
          -6.811738,
          37.556029
        ]
      },
      "properties": {
        "description": "representative point"
      }
    },
    {
      "geometry": {
        "type": "Point",
        "coordinates": [
          -6.811738,
          37.556029
        ]
      },
      "id": "darmc-location-19485",
      "type": "Feature",
      "properties": {
        "description": "1M scale point location",
        "location_precision": "precise",
        "title": "DARMC location 19485",
        "link": "http://pleiades.stoa.org/places/256046/darmc-location-19485"
      }
    }
  ]
}