{
  "type": "FeatureCollection",
  "title": "Cerro de los Mártires",
  "id": "256095",
  "description": "An ancient place, cited: BAtlas 26 D5 Cerro de los Mártires",
  "bbox": [
    -6.212305,
    36.437707,
    -6.212305,
    36.437707
  ],
  "reprPoint": [
    -6.212305,
    36.437707
  ],
  "features": [
    {
      "geometry": {
        "type": "Point",
        "coordinates": [
          -6.212305,
          36.437707
        ]
      },
      "id": "darmc-location-3818",
      "type": "Feature",
      "properties": {
        "description": "1M scale point location",
        "location_precision": "precise",
        "title": "DARMC location 3818",
        "link": "http://pleiades.stoa.org/places/256095/darmc-location-3818"
      }
    }
  ]
}