{
  "type": "FeatureCollection",
  "title": "Los Barros",
  "id": "256018",
  "description": "An ancient place, cited: BAtlas 26 D3 Los Barros",
  "bbox": [
    -6.685157,
    38.490749,
    -6.685157,
    38.490749
  ],
  "reprPoint": [
    -6.685157,
    38.490749
  ],
  "features": [
    {
      "geometry": {
        "type": "Point",
        "coordinates": [
          -6.685157,
          38.490749
        ]
      },
      "id": "darmc-location-20974",
      "type": "Feature",
      "properties": {
        "description": "1M scale point location",
        "location_precision": "precise",
        "title": "DARMC location 20974",
        "link": "http://pleiades.stoa.org/places/256018/darmc-location-20974"
      }
    }
  ]
}