{
  "type": "FeatureCollection",
  "title": "Caserío de Riguelo",
  "id": "256069",
  "description": "An ancient place, cited: BAtlas 26 F4 Caserío de Riguelo",
  "bbox": [
    -4.716555,
    37.279098,
    -4.716555,
    37.279098
  ],
  "reprPoint": [
    -4.716555,
    37.279098
  ],
  "features": [
    {
      "geometry": {
        "type": "Point",
        "coordinates": [
          -4.716555,
          37.279098
        ]
      },
      "id": "darmc-location-19663",
      "type": "Feature",
      "properties": {
        "description": "1M scale point location",
        "location_precision": "precise",
        "title": "DARMC location 19663",
        "link": "http://pleiades.stoa.org/places/256069/darmc-location-19663"
      }
    }
  ]
}