{
  "type": "FeatureCollection",
  "title": "Chorrillo",
  "id": "256104",
  "bbox": [
    -5.741071,
    37.378667,
    -5.741071,
    37.378667
  ],
  "description": "An ancient place, cited: BAtlas 26 E4 Chorrillo",
  "features": [
    {
      "type": "Feature",
      "geometry": {
        "type": "Point",
        "coordinates": [
          -5.741071,
          37.378667
        ]
      },
      "properties": {
        "description": "representative point"
      }
    },
    {
      "geometry": {
        "type": "Point",
        "coordinates": [
          -5.741071,
          37.378667
        ]
      },
      "id": "darmc-location-4463",
      "type": "Feature",
      "properties": {
        "description": "1M scale point location",
        "location_precision": "precise",
        "title": "DARMC location 4463",
        "link": "http://pleiades.stoa.org/places/256104/darmc-location-4463"
      }
    }
  ]
}