{
  "type": "FeatureCollection",
  "title": "Cetaria",
  "id": "256103",
  "bbox": [
    -5.433107,
    36.07249,
    -5.433107,
    36.07249
  ],
  "description": "An ancient place, cited: BAtlas 26 E5 Cetaria",
  "names": [
    "Cetaria"
  ],
  "features": [
    {
      "type": "Feature",
      "geometry": {
        "type": "Point",
        "coordinates": [
          -5.433107,
          36.07249
        ]
      },
      "properties": {
        "description": "representative point"
      }
    },
    {
      "geometry": {
        "type": "Point",
        "coordinates": [
          -5.433107,
          36.07249
        ]
      },
      "id": "darmc-location-19762",
      "type": "Feature",
      "properties": {
        "description": "1M scale point location",
        "location_precision": "precise",
        "title": "DARMC location 19762",
        "link": "http://pleiades.stoa.org/places/256103/darmc-location-19762"
      }
    }
  ]
}