{
  "type": "FeatureCollection",
  "title": "Cerro Macareño",
  "id": "256100",
  "description": "An ancient place, cited: BAtlas 26 E4 Cerro Macareño",
  "bbox": [
    -5.979346,
    37.487775,
    -5.979346,
    37.487775
  ],
  "reprPoint": [
    -5.979346,
    37.487775
  ],
  "features": [
    {
      "geometry": {
        "type": "Point",
        "coordinates": [
          -5.979346,
          37.487775
        ]
      },
      "id": "darmc-location-20153",
      "type": "Feature",
      "properties": {
        "description": "1M scale point location",
        "location_precision": "precise",
        "title": "DARMC location 20153",
        "link": "http://pleiades.stoa.org/places/256100/darmc-location-20153"
      }
    }
  ]
}