{
  "type": "FeatureCollection",
  "title": "Herakleios Porthmos/Gaditanum Fretum",
  "id": "256198",
  "description": "The Strait of Gibraltar, a narrow strait that connects the Atlantic Ocean and the Mediterranean Sea and separates Europe from Africa.",
  "bbox": [
    -5.485833,
    35.971667,
    -5.485833,
    35.971667
  ],
  "reprPoint": [
    -5.485833,
    35.971667
  ],
  "names": [
    "Herakleios Porthmos",
    "Gaditanum Fretum",
    "Tartessium Fretum",
    "Europae Fretum",
    "Hiberum Fretum",
    "Hispanum Fretum"
  ],
  "features": [
    {
      "geometry": {
        "type": "Point",
        "coordinates": [
          -5.485833,
          35.971667
        ]
      },
      "id": "location-of-herakleios-porthmos-gaditanum-fretum",
      "type": "Feature",
      "properties": {
        "description": "coordinates after GeoHack, verified in Google Earth.",
        "location_precision": "precise",
        "title": "Location of the Straits of Gibraltar",
        "link": "http://pleiades.stoa.org/places/256198/location-of-herakleios-porthmos-gaditanum-fretum"
      }
    }
  ]
}