{
  "type": "FeatureCollection",
  "title": "Gadeira/Gades/Col. Augusta Gaditana",
  "id": "256177",
  "description": "Gadeira/Gades/Col. Augusta Gaditana (modern Cadiz, Spain) is an ancient city of Spain and one of the oldest continuously occupied cities of Europe. Its origins may be Phoenician (Gadir (Phoenician: גדר)).",
  "bbox": [
    -6.294444,
    36.528381,
    -6.294444,
    36.528381
  ],
  "reprPoint": [
    -6.294444,
    36.528381
  ],
  "names": [
    "Cadiz",
    "Gadeira",
    "Gades",
    "Col. Augusta Gaditana",
    "Urbs Iulia Gaditana"
  ],
  "features": [
    {
      "geometry": {
        "type": "Point",
        "coordinates": [
          -6.29246,
          36.529723
        ]
      },
      "id": "darmc-location-20271",
      "type": "Feature",
      "properties": {
        "description": "1M scale point location",
        "location_precision": "precise",
        "title": "DARMC location 20271",
        "link": "http://pleiades.stoa.org/places/256177/darmc-location-20271"
      }
    },
    {
      "geometry": {
        "type": "Point",
        "coordinates": [
          -6.292458,
          36.529729
        ]
      },
      "id": "darmc-location-20272",
      "type": "Feature",
      "properties": {
        "description": "5M scale point location",
        "location_precision": "precise",
        "title": "DARMC location 20272",
        "link": "http://pleiades.stoa.org/places/256177/darmc-location-20272"
      }
    },
    {
      "geometry": {
        "type": "Point",
        "coordinates": [
          -6.294444,
          36.528381
        ]
      },
      "id": "dare-location",
      "type": "Feature",
      "properties": {
        "description": "Representative point location, site precision",
        "location_precision": "precise",
        "title": "DARE Location",
        "link": "http://pleiades.stoa.org/places/256177/dare-location"
      }
    }
  ]
}