{
  "type": "FeatureCollection",
  "title": "Evandria(na)",
  "id": "256165",
  "bbox": [
    -6.4556,
    38.852762,
    -6.4556,
    38.852762
  ],
  "description": "An ancient place, cited: BAtlas 26 D3 Evandria(na)",
  "names": [
    "Evandriana",
    "Evandria"
  ],
  "features": [
    {
      "type": "Feature",
      "geometry": {
        "type": "Point",
        "coordinates": [
          -6.4556,
          38.852762
        ]
      },
      "properties": {
        "description": "representative point"
      }
    },
    {
      "geometry": {
        "type": "Point",
        "coordinates": [
          -6.4556,
          38.852762
        ]
      },
      "id": "darmc-location-19610",
      "type": "Feature",
      "properties": {
        "description": "1M scale point location",
        "location_precision": "precise",
        "title": "DARMC location 19610",
        "link": "http://pleiades.stoa.org/places/256165/darmc-location-19610"
      }
    }
  ]
}