{
  "type": "FeatureCollection",
  "title": "Gadeira/Gades/Col. Augusta Gaditana",
  "id": "256177",
  "bbox": [
    -6.294444,
    36.528381,
    -6.292458,
    36.529729
  ],
  "description": "Gadeira/Gades/Col. Augusta Gaditana (modern Cadiz, Spain) is an ancient city of Spain and one of the oldest continuously occupied cities of Europe. Its origins may be Phoenician (Gadir (Phoenician: גדר)).",
  "connectsWith": [
    "803793619",
    "256138",
    "255954"
  ],
  "names": [
    "Gadeira",
    "Gades",
    "Col. Augusta Gaditana",
    "Urbs Iulia Gaditana",
    "Cadiz"
  ],
  "features": [
    {
      "type": "Feature",
      "geometry": {
        "type": "Point",
        "coordinates": [
          -6.29312066667,
          36.5292776667
        ]
      },
      "properties": {
        "description": "representative point"
      }
    },
    {
      "geometry": {
        "type": "Point",
        "coordinates": [
          -6.29246,
          36.529723
        ]
      },
      "id": "darmc-location-20271",
      "type": "Feature",
      "properties": {
        "description": "1:1 million scale representative point location digitized from the Barrington Atlas of the Greek and Roman World by the Digital Atlas of Roman and Medieval Civilizations project at Harvard University.",
        "location_precision": "precise",
        "title": "DARMC location 20271",
        "link": "http://pleiades.stoa.org/places/256177/darmc-location-20271"
      }
    },
    {
      "geometry": {
        "type": "Point",
        "coordinates": [
          -6.292458,
          36.529729
        ]
      },
      "id": "darmc-location-20272",
      "type": "Feature",
      "properties": {
        "description": "5M scale representative point location digitized from the Barrington Atlas of the Greek and Roman World by the Digital Atlas of Roman and Medieval Civilizations project at Harvard University.",
        "location_precision": "precise",
        "title": "DARMC location 20272",
        "link": "http://pleiades.stoa.org/places/256177/darmc-location-20272"
      }
    },
    {
      "geometry": {
        "type": "Point",
        "coordinates": [
          -6.294444,
          36.528381
        ]
      },
      "id": "dare-location",
      "type": "Feature",
      "properties": {
        "description": "Representative point location, site precision",
        "location_precision": "precise",
        "title": "DARE Location",
        "link": "http://pleiades.stoa.org/places/256177/dare-location"
      }
    }
  ]
}