{
  "type": "FeatureCollection",
  "title": "Detumo",
  "id": "256149",
  "description": "An ancient place, cited: BAtlas 26 E4 Detumo",
  "bbox": [
    -5.174338,
    37.773018,
    -5.174338,
    37.773018
  ],
  "reprPoint": [
    -5.174338,
    37.773018
  ],
  "names": [
    "Detumo"
  ],
  "features": [
    {
      "geometry": {
        "type": "Point",
        "coordinates": [
          -5.174338,
          37.773018
        ]
      },
      "id": "darmc-location-19769",
      "type": "Feature",
      "properties": {
        "description": "1M scale point location",
        "location_precision": "precise",
        "title": "DARMC location 19769",
        "link": "http://pleiades.stoa.org/places/256149/darmc-location-19769"
      }
    }
  ]
}