{
  "type": "FeatureCollection",
  "title": "Escádia Grande",
  "id": "256161",
  "description": "An ancient place, cited: BAtlas 26 B2 Escádia Grande",
  "bbox": [
    -8.256331,
    39.969583,
    -8.256331,
    39.969583
  ],
  "reprPoint": [
    -8.256331,
    39.969583
  ],
  "features": [
    {
      "geometry": {
        "type": "Point",
        "coordinates": [
          -8.256331,
          39.969583
        ]
      },
      "id": "darmc-location-19500",
      "type": "Feature",
      "properties": {
        "description": "1M scale point location",
        "location_precision": "precise",
        "title": "DARMC location 19500",
        "link": "http://pleiades.stoa.org/places/256161/darmc-location-19500"
      }
    }
  ]
}