{
  "type": "FeatureCollection",
  "title": "Cuneus (promontory)",
  "id": "256145",
  "bbox": [
    -7.8896295,
    36.9603556,
    -7.8896295,
    36.9603556
  ],
  "description": "Cabo de Santa Maria is the southernmost point of mainland Portugal.",
  "names": [
    "Cuneus Pr.",
    "Cabo de Santa Maria"
  ],
  "features": [
    {
      "type": "Feature",
      "geometry": {
        "type": "Point",
        "coordinates": [
          -7.8896295,
          36.9603556
        ]
      },
      "properties": {
        "description": "representative point"
      }
    },
    {
      "geometry": {
        "type": "Point",
        "coordinates": [
          -7.8896295,
          36.9603556
        ]
      },
      "id": "osm-location-of-cabo-de-santa-maria",
      "type": "Feature",
      "properties": {
        "description": "Representative location based on OpenStreetMap",
        "location_precision": "precise",
        "title": "OSM location of Cabo de Santa Maria",
        "link": "http://pleiades.stoa.org/places/256145/osm-location-of-cabo-de-santa-maria"
      }
    }
  ]
}