{
  "type": "FeatureCollection",
  "title": "Cuneus Pr.",
  "id": "256145",
  "description": "An ancient place, cited: BAtlas 26 C5 Cuneus Pr.",
  "bbox": [
    -7.888056,
    36.95,
    -7.888056,
    36.95
  ],
  "reprPoint": [
    -7.888056,
    36.95
  ],
  "names": [
    "Cuneus Pr."
  ],
  "features": [
    {
      "geometry": {
        "type": "Point",
        "coordinates": [
          -7.888056,
          36.95
        ]
      },
      "id": "location-of-cuneus-pr",
      "type": "Feature",
      "properties": {
        "description": "coordinates for the Cabo de Santa Maria (Faro) after GeoHack, verified in Google Earth.",
        "location_precision": "precise",
        "title": "location of Cuneus Pr.",
        "link": "http://pleiades.stoa.org/places/256145/location-of-cuneus-pr"
      }
    }
  ]
}