{
  "type": "FeatureCollection",
  "title": "Las Cucharas",
  "id": "256140",
  "bbox": [
    -5.724482,
    38.750722,
    -5.724482,
    38.750722
  ],
  "description": "An ancient place, cited: BAtlas 26 E3 Las Cucharas",
  "features": [
    {
      "type": "Feature",
      "geometry": {
        "type": "Point",
        "coordinates": [
          -5.724482,
          38.750722
        ]
      },
      "properties": {
        "description": "representative point"
      }
    },
    {
      "geometry": {
        "type": "Point",
        "coordinates": [
          -5.724482,
          38.750722
        ]
      },
      "id": "darmc-location-21175",
      "type": "Feature",
      "properties": {
        "description": "1M scale point location",
        "location_precision": "precise",
        "title": "DARMC location 21175",
        "link": "http://pleiades.stoa.org/places/256140/darmc-location-21175"
      }
    }
  ]
}