{
  "type": "FeatureCollection",
  "title": "Ilipa Magna",
  "id": "256222",
  "description": "Ilipa Magna was located on the right bank of the Baetis river. It is now the modern Alcalá del Río. In antiquity it was notable for silver mines located nearby.",
  "bbox": [
    -5.978254,
    37.518215,
    -5.978254,
    37.518215
  ],
  "connectsWith": [
    "256010"
  ],
  "reprPoint": [
    -5.978254,
    37.518215
  ],
  "names": [
    "Ilipa Magna",
    "Ibylla",
    "Ilipa Ilia",
    "Alcala del Rio"
  ],
  "features": [
    {
      "geometry": {
        "type": "Point",
        "coordinates": [
          -5.978254,
          37.518215
        ]
      },
      "id": "darmc-location-20323",
      "type": "Feature",
      "properties": {
        "description": "1M scale point location",
        "location_precision": "precise",
        "title": "DARMC location 20323",
        "link": "http://pleiades.stoa.org/places/256222/darmc-location-20323"
      }
    }
  ]
}