{
  "type": "FeatureCollection",
  "title": "Italica",
  "id": "256231",
  "description": "A city in Spain founded in 206 BC by Publius Cornelius Scipio Africanus as a site at which to settle Roman soldiers wounded in the Battle of Ilipa.",
  "bbox": [
    -6.04344,
    37.441411,
    -6.04344,
    37.441411
  ],
  "reprPoint": [
    -6.04344,
    37.441411
  ],
  "names": [
    "Italica"
  ],
  "features": [
    {
      "geometry": {
        "type": "Point",
        "coordinates": [
          -6.046795,
          37.443901
        ]
      },
      "id": "darmc-location-20348",
      "type": "Feature",
      "properties": {
        "description": "1M scale point location",
        "location_precision": "precise",
        "title": "DARMC location 20348",
        "link": "http://pleiades.stoa.org/places/256231/darmc-location-20348"
      }
    },
    {
      "geometry": {
        "type": "Point",
        "coordinates": [
          -6.04344,
          37.441411
        ]
      },
      "id": "dare-location",
      "type": "Feature",
      "properties": {
        "description": "Representative point location, site precision",
        "location_precision": "precise",
        "title": "DARE Location",
        "link": "http://pleiades.stoa.org/places/256231/dare-location"
      }
    },
    {
      "geometry": {
        "type": "Point",
        "coordinates": [
          -6.046833,
          37.4438807
        ]
      },
      "id": "roman-amphitheater-of-italica",
      "type": "Feature",
      "properties": {
        "description": "The amphitheater of Italica, built in the second century AD, was one of the largest in the Roman world and could accommodate an estimated 25,000 spectators.",
        "location_precision": "precise",
        "title": "location of Roman amphitheater of Italica",
        "link": "http://pleiades.stoa.org/places/256231/roman-amphitheater-of-italica"
      }
    }
  ]
}