{
  "type": "FeatureCollection",
  "title": "Italica",
  "id": "256231",
  "description": "A city in Spain founded in 206 B.C. by Publius Cornelius Scipio Africanus as a site at which to settle Roman soldiers wounded in the Battle of Ilipa.",
  "bbox": [
    -6.046833,
    37.441411,
    -6.04344,
    37.443901
  ],
  "reprPoint": [
    -6.04568933333,
    37.4430642333
  ],
  "names": [
    "Italica"
  ],
  "features": [
    {
      "geometry": {
        "type": "Point",
        "coordinates": [
          -6.046795,
          37.443901
        ]
      },
      "id": "darmc-location-20348",
      "type": "Feature",
      "properties": {
        "description": "1M scale point location",
        "location_precision": "precise",
        "title": "DARMC location 20348",
        "link": "http://pleiades.stoa.org/places/256231/darmc-location-20348"
      }
    },
    {
      "geometry": {
        "type": "Point",
        "coordinates": [
          -6.04344,
          37.441411
        ]
      },
      "id": "dare-location",
      "type": "Feature",
      "properties": {
        "description": "Representative point location, site precision",
        "location_precision": "precise",
        "title": "DARE Location",
        "link": "http://pleiades.stoa.org/places/256231/dare-location"
      }
    },
    {
      "geometry": {
        "type": "Point",
        "coordinates": [
          -6.046833,
          37.4438807
        ]
      },
      "id": "roman-amphitheater-of-italica",
      "type": "Feature",
      "properties": {
        "description": "The amphitheater of Italica, built in the second century A.D., was one of the largest in the Roman world and could accommodate an estimated 25,000 spectators. Coordinates following GeoHack, verified in Google Earth.",
        "location_precision": "precise",
        "title": "Imagery location of Roman amphitheater of Italica",
        "link": "http://pleiades.stoa.org/places/256231/roman-amphitheater-of-italica"
      }
    }
  ]
}