{
  "type": "FeatureCollection",
  "title": "Ipagrum/Epagrum",
  "id": "256226",
  "bbox": [
    -4.660417,
    37.515021,
    -4.656039,
    37.520598
  ],
  "description": "An ancient place, cited: BAtlas 26 F4 Ipagrum/Epagrum",
  "names": [
    "Ipagrum",
    "Epagrum",
    "Aguilar de la Frontera"
  ],
  "features": [
    {
      "type": "Feature",
      "geometry": {
        "type": "Point",
        "coordinates": [
          -4.658228,
          37.5178095
        ]
      },
      "properties": {
        "description": "representative point"
      }
    },
    {
      "geometry": {
        "type": "Point",
        "coordinates": [
          -4.656039,
          37.515021
        ]
      },
      "id": "darmc-location-19786",
      "type": "Feature",
      "properties": {
        "description": "1M scale point location",
        "location_precision": "precise",
        "title": "DARMC location 19786",
        "link": "http://pleiades.stoa.org/places/256226/darmc-location-19786"
      }
    },
    {
      "geometry": {
        "type": "Point",
        "coordinates": [
          -4.660417,
          37.520598
        ]
      },
      "id": "dare-location",
      "type": "Feature",
      "properties": {
        "description": "Representative point location, site precision",
        "location_precision": "precise",
        "title": "DARE Location",
        "link": "http://pleiades.stoa.org/places/256226/dare-location"
      }
    }
  ]
}