{
  "type": "FeatureCollection",
  "title": "Irni",
  "id": "256230",
  "bbox": [
    -5.121603,
    37.029983,
    -5.096211,
    37.070065
  ],
  "description": "Irni was the site of a Roman municipium located in the Conventus Hispalensis (Baetica) - the Municipium Flavium Irnitanum. Findspot of the Lex Irnitana, a copy of a Flavian municipal law.",
  "names": [
    "Municipium Flavium Irnitanum",
    "Irni"
  ],
  "features": [
    {
      "type": "Feature",
      "geometry": {
        "type": "Point",
        "coordinates": [
          -5.108907,
          37.050024
        ]
      },
      "properties": {
        "description": "representative point"
      }
    },
    {
      "geometry": {
        "type": "Point",
        "coordinates": [
          -5.096211,
          37.070065
        ]
      },
      "id": "darmc-location-20344",
      "type": "Feature",
      "properties": {
        "description": "1:1 million scale representative point location digitized from the Barrington Atlas of the Greek and Roman World by the Digital Atlas of Roman and Medieval Civilizations project at Harvard University.",
        "location_precision": "precise",
        "title": "DARMC location 20344",
        "link": "http://pleiades.stoa.org/places/256230/darmc-location-20344"
      }
    },
    {
      "geometry": {
        "type": "Point",
        "coordinates": [
          -5.121603,
          37.029983
        ]
      },
      "id": "dare-location",
      "type": "Feature",
      "properties": {
        "description": "Representative point location, site precision",
        "location_precision": "precise",
        "title": "DARE Location",
        "link": "http://pleiades.stoa.org/places/256230/dare-location"
      }
    }
  ]
}