{
  "type": "FeatureCollection",
  "title": "(I)Tucci",
  "id": "256232",
  "description": "An ancient place, cited: BAtlas 26 D4 (I)Tucci",
  "bbox": [
    -6.363638,
    37.44811,
    -6.363638,
    37.44811
  ],
  "reprPoint": [
    -6.363638,
    37.44811
  ],
  "names": [
    "Itucci",
    "Tucci"
  ],
  "features": [
    {
      "geometry": {
        "type": "Point",
        "coordinates": [
          -6.363638,
          37.44811
        ]
      },
      "id": "darmc-location-2123",
      "type": "Feature",
      "properties": {
        "description": "1M scale point location",
        "location_precision": "precise",
        "title": "DARMC location 2123",
        "link": "http://pleiades.stoa.org/places/256232/darmc-location-2123"
      }
    }
  ]
}