{
  "type": "FeatureCollection",
  "title": "Irni",
  "id": "256230",
  "description": "An ancient place, cited: BAtlas 26 E4 Irni",
  "bbox": [
    -5.121603,
    37.029983,
    -5.096211,
    37.070065
  ],
  "reprPoint": [
    -5.108907,
    37.050024
  ],
  "names": [
    "Irni"
  ],
  "features": [
    {
      "geometry": {
        "type": "Point",
        "coordinates": [
          -5.096211,
          37.070065
        ]
      },
      "id": "darmc-location-20344",
      "type": "Feature",
      "properties": {
        "description": "1M scale point location",
        "location_precision": "precise",
        "title": "DARMC location 20344",
        "link": "http://pleiades.stoa.org/places/256230/darmc-location-20344"
      }
    },
    {
      "geometry": {
        "type": "Point",
        "coordinates": [
          -5.121603,
          37.029983
        ]
      },
      "id": "dare-location",
      "type": "Feature",
      "properties": {
        "description": "Representative point location, site precision",
        "location_precision": "precise",
        "title": "DARE Location",
        "link": "http://pleiades.stoa.org/places/256230/dare-location"
      }
    }
  ]
}