{
  "type": "FeatureCollection",
  "title": "Ilipa Magna",
  "id": "256222",
  "description": "An ancient place, cited: BAtlas 26 E4 Ilipa Magna",
  "bbox": [
    -5.978254,
    37.518215,
    -5.978254,
    37.518215
  ],
  "reprPoint": [
    -5.978254,
    37.518215
  ],
  "names": [
    "Ilipa Magna",
    "Ibylla",
    "Ilipa Ilia"
  ],
  "features": [
    {
      "geometry": {
        "type": "Point",
        "coordinates": [
          -5.978254,
          37.518215
        ]
      },
      "id": "darmc-location-20323",
      "type": "Feature",
      "properties": {
        "description": "1M scale point location",
        "location_precision": "precise",
        "title": "DARMC location 20323",
        "link": "http://pleiades.stoa.org/places/256222/darmc-location-20323"
      }
    }
  ]
}