{
  "type": "FeatureCollection",
  "title": "Lora la Vieja",
  "id": "256273",
  "description": "An ancient place, cited: BAtlas 26 E4 Lora la Vieja",
  "bbox": [
    -5.526348,
    37.659227,
    -5.526348,
    37.659227
  ],
  "reprPoint": [
    -5.526348,
    37.659227
  ],
  "features": [
    {
      "geometry": {
        "type": "Point",
        "coordinates": [
          -5.526348,
          37.659227
        ]
      },
      "id": "darmc-location-20444",
      "type": "Feature",
      "properties": {
        "description": "1M scale point location",
        "location_precision": "precise",
        "title": "DARMC location 20444",
        "link": "http://pleiades.stoa.org/places/256273/darmc-location-20444"
      }
    }
  ]
}