{
  "type": "FeatureCollection",
  "title": "Mercablum/Merifabion",
  "id": "256295",
  "description": "An ancient place, cited: BAtlas 26 D5 Mercablum/Merifabion",
  "bbox": [
    -6.088556,
    36.276482,
    -6.088556,
    36.276482
  ],
  "reprPoint": [
    -6.088556,
    36.276482
  ],
  "names": [
    "Mercablum",
    "Merifabion"
  ],
  "features": [
    {
      "geometry": {
        "type": "Point",
        "coordinates": [
          -6.088556,
          36.276482
        ]
      },
      "id": "darmc-location-20484",
      "type": "Feature",
      "properties": {
        "description": "1M scale point location",
        "location_precision": "precise",
        "title": "DARMC location 20484",
        "link": "http://pleiades.stoa.org/places/256295/darmc-location-20484"
      }
    }
  ]
}