{
  "type": "FeatureCollection",
  "title": "Metellinum",
  "id": "256298",
  "description": "An ancient place, cited: BAtlas 26 E3 Metellinum",
  "bbox": [
    -5.956007,
    38.966178,
    -5.956007,
    38.966178
  ],
  "reprPoint": [
    -5.956007,
    38.966178
  ],
  "names": [
    "Metellinum"
  ],
  "features": [
    {
      "geometry": {
        "type": "Point",
        "coordinates": [
          -5.957706,
          38.96297
        ]
      },
      "id": "darmc-location-20486",
      "type": "Feature",
      "properties": {
        "description": "1M scale point location",
        "location_precision": "precise",
        "title": "DARMC location 20486",
        "link": "http://pleiades.stoa.org/places/256298/darmc-location-20486"
      }
    },
    {
      "geometry": {
        "type": "Point",
        "coordinates": [
          -5.956007,
          38.966178
        ]
      },
      "id": "dare-location",
      "type": "Feature",
      "properties": {
        "description": "Representative point location, site precision",
        "location_precision": "precise",
        "title": "DARE Location",
        "link": "http://pleiades.stoa.org/places/256298/dare-location"
      }
    }
  ]
}