{
  "type": "FeatureCollection",
  "title": "Italica",
  "id": "256231",
  "bbox": [
    -6.046795,
    37.441411,
    -6.04344,
    37.443901
  ],
  "description": "A city in Spain founded in 206 B.C. by Publius Cornelius Scipio Africanus as a site at which to settle Roman soldiers wounded in the Battle of Ilipa.",
  "names": [
    "Italica"
  ],
  "features": [
    {
      "type": "Feature",
      "geometry": {
        "type": "Point",
        "coordinates": [
          -6.0451175,
          37.442656
        ]
      },
      "properties": {
        "description": "representative point"
      }
    },
    {
      "geometry": {
        "type": "Point",
        "coordinates": [
          -6.046795,
          37.443901
        ]
      },
      "id": "darmc-location-20348",
      "type": "Feature",
      "properties": {
        "description": "1M scale point location",
        "location_precision": "precise",
        "title": "DARMC location 20348",
        "link": "http://pleiades.stoa.org/places/256231/darmc-location-20348"
      }
    },
    {
      "geometry": {
        "type": "Point",
        "coordinates": [
          -6.04344,
          37.441411
        ]
      },
      "id": "dare-location",
      "type": "Feature",
      "properties": {
        "description": "Representative point location, site precision",
        "location_precision": "precise",
        "title": "DARE Location",
        "link": "http://pleiades.stoa.org/places/256231/dare-location"
      }
    }
  ]
}