{
  "type": "FeatureCollection",
  "title": "Lacunis",
  "id": "256253",
  "description": "An ancient place, cited: BAtlas 26 D3 Lacunis",
  "bbox": [
    -6.274346,
    38.08679,
    -6.274346,
    38.08679
  ],
  "reprPoint": [
    -6.274346,
    38.08679
  ],
  "names": [
    "Lacunis"
  ],
  "features": [
    {
      "geometry": {
        "type": "Point",
        "coordinates": [
          -6.274346,
          38.08679
        ]
      },
      "id": "darmc-location-20413",
      "type": "Feature",
      "properties": {
        "description": "1M scale point location",
        "location_precision": "precise",
        "title": "DARMC location 20413",
        "link": "http://pleiades.stoa.org/places/256253/darmc-location-20413"
      }
    }
  ]
}