{
  "type": "FeatureCollection",
  "title": "Italica",
  "id": "256231",
  "bbox": [
    -6.0476304,
    37.4397867,
    -6.0385625,
    37.4444206
  ],
  "description": "A city in Spain founded in 206 B.C. by Publius Cornelius Scipio Africanus as a site at which to settle Roman soldiers wounded in the Battle of Ilipa.",
  "connectsWith": [
    "256010"
  ],
  "names": [
    "Italica",
    "Italika"
  ],
  "features": [
    {
      "type": "Feature",
      "geometry": {
        "type": "Point",
        "coordinates": [
          -6.04328576095,
          37.4413094241
        ]
      },
      "properties": {
        "description": "representative point"
      }
    }
  ]
}