{
  "type": "FeatureCollection",
  "title": "Londobris (island)",
  "id": "256272",
  "description": "Londobris Ins., the modern Berlenga Grande Island, is the largest of the islands of the Berlengas Archipelago.",
  "bbox": [
    -9.5100012,
    39.4157975,
    -9.5100012,
    39.4157975
  ],
  "connectsWith": [
    "845"
  ],
  "reprPoint": [
    -9.5100012,
    39.4157975
  ],
  "names": [
    "Londobris"
  ],
  "features": [
    {
      "geometry": {
        "type": "Point",
        "coordinates": [
          -9.5100012,
          39.4157975
        ]
      },
      "id": "berlenga-grande",
      "type": "Feature",
      "properties": {
        "description": "Location based on OpenStreetMap",
        "location_precision": "precise",
        "title": "OSM location",
        "link": "http://pleiades.stoa.org/places/256272/berlenga-grande"
      }
    }
  ]
}