{
  "type": "FeatureCollection",
  "title": "Municipium Flavium V(...)",
  "id": "256317",
  "bbox": [
    -5.677934,
    38.259603,
    -5.677934,
    38.259603
  ],
  "description": "An ancient place, cited: BAtlas 26 E3 Municipium Flavium V(...)",
  "names": [
    "Municipium Flavium V(...)"
  ],
  "features": [
    {
      "type": "Feature",
      "geometry": {
        "type": "Point",
        "coordinates": [
          -5.677934,
          38.259603
        ]
      },
      "properties": {
        "description": "representative point"
      }
    },
    {
      "geometry": {
        "type": "Point",
        "coordinates": [
          -5.677934,
          38.259603
        ]
      },
      "id": "darmc-location-20505",
      "type": "Feature",
      "properties": {
        "description": "1M scale point location",
        "location_precision": "precise",
        "title": "DARMC location 20505",
        "link": "http://pleiades.stoa.org/places/256317/darmc-location-20505"
      }
    }
  ]
}