{
  "type": "FeatureCollection",
  "title": "Ossonoba",
  "id": "256345",
  "description": "An ancient place, cited: BAtlas 26 C4 Ossonoba",
  "bbox": [
    -7.935108,
    37.01535,
    -7.935108,
    37.01535
  ],
  "reprPoint": [
    -7.935108,
    37.01535
  ],
  "names": [
    "Faro",
    "Ossonoba"
  ],
  "features": [
    {
      "geometry": {
        "type": "Point",
        "coordinates": [
          -7.935108,
          37.01535
        ]
      },
      "id": "darmc-location-894",
      "type": "Feature",
      "properties": {
        "description": "1M scale point location",
        "location_precision": "precise",
        "title": "DARMC location 894",
        "link": "http://pleiades.stoa.org/places/256345/darmc-location-894"
      }
    }
  ]
}