{
  "type": "FeatureCollection",
  "title": "Monte de S. Martinho",
  "id": "256305",
  "description": "An ancient place, cited: BAtlas 26 C2 Monte de S. Martinho",
  "bbox": [
    -7.46468,
    39.804068,
    -7.46468,
    39.804068
  ],
  "reprPoint": [
    -7.46468,
    39.804068
  ],
  "features": [
    {
      "geometry": {
        "type": "Point",
        "coordinates": [
          -7.46468,
          39.804068
        ]
      },
      "id": "darmc-location-20999",
      "type": "Feature",
      "properties": {
        "description": "1M scale point location",
        "location_precision": "precise",
        "title": "DARMC location 20999",
        "link": "http://pleiades.stoa.org/places/256305/darmc-location-20999"
      }
    }
  ]
}