{
  "type": "FeatureCollection",
  "title": "Monte do Outeiro",
  "id": "256308",
  "description": "An ancient place, cited: BAtlas 26 C3 Monte do Outeiro",
  "bbox": [
    -7.876543,
    38.173427,
    -7.876543,
    38.173427
  ],
  "reprPoint": [
    -7.876543,
    38.173427
  ],
  "features": [
    {
      "geometry": {
        "type": "Point",
        "coordinates": [
          -7.876543,
          38.173427
        ]
      },
      "id": "darmc-location-21002",
      "type": "Feature",
      "properties": {
        "description": "1M scale point location",
        "location_precision": "precise",
        "title": "DARMC location 21002",
        "link": "http://pleiades.stoa.org/places/256308/darmc-location-21002"
      }
    }
  ]
}