{
  "type": "FeatureCollection",
  "title": "Ponte de Tôr",
  "id": "256378",
  "bbox": [
    -7.987647,
    37.199007,
    -7.987647,
    37.199007
  ],
  "description": "An ancient place, cited: BAtlas 26 B4 Ponte de Tôr",
  "features": [
    {
      "type": "Feature",
      "geometry": {
        "type": "Point",
        "coordinates": [
          -7.987647,
          37.199007
        ]
      },
      "properties": {
        "description": "representative point"
      }
    },
    {
      "geometry": {
        "type": "Point",
        "coordinates": [
          -7.987647,
          37.199007
        ]
      },
      "id": "darmc-location-17992",
      "type": "Feature",
      "properties": {
        "description": "1M scale point location",
        "location_precision": "precise",
        "title": "DARMC location 17992",
        "link": "http://pleiades.stoa.org/places/256378/darmc-location-17992"
      }
    }
  ]
}