{
  "type": "FeatureCollection",
  "title": "Las Minillas",
  "id": "256301",
  "description": "An ancient place, cited: BAtlas 26 F3 Las Minillas",
  "bbox": [
    -4.957496,
    38.881402,
    -4.957496,
    38.881402
  ],
  "reprPoint": [
    -4.957496,
    38.881402
  ],
  "features": [
    {
      "geometry": {
        "type": "Point",
        "coordinates": [
          -4.957496,
          38.881402
        ]
      },
      "id": "darmc-location-19518",
      "type": "Feature",
      "properties": {
        "description": "1M scale point location",
        "location_precision": "precise",
        "title": "DARMC location 19518",
        "link": "http://pleiades.stoa.org/places/256301/darmc-location-19518"
      }
    }
  ]
}