{
  "type": "FeatureCollection",
  "title": "Phornakis",
  "id": "256362",
  "description": "An ancient place, cited: BAtlas 26 D3 Phornakis",
  "bbox": [
    -6.180009,
    38.507411,
    -6.180009,
    38.507411
  ],
  "reprPoint": [
    -6.180009,
    38.507411
  ],
  "names": [
    "Phornakis"
  ],
  "features": [
    {
      "geometry": {
        "type": "Point",
        "coordinates": [
          -6.180009,
          38.507411
        ]
      },
      "id": "darmc-location-19854",
      "type": "Feature",
      "properties": {
        "description": "1M scale point location",
        "location_precision": "precise",
        "title": "DARMC location 19854",
        "link": "http://pleiades.stoa.org/places/256362/darmc-location-19854"
      }
    }
  ]
}