{
  "type": "FeatureCollection",
  "title": "Ponte de Sor",
  "id": "256377",
  "bbox": [
    -8.009612,
    39.247834,
    -8.009612,
    39.247834
  ],
  "description": "An ancient place, cited: BAtlas 26 C2 Ponte de Sor",
  "features": [
    {
      "type": "Feature",
      "geometry": {
        "type": "Point",
        "coordinates": [
          -8.009612,
          39.247834
        ]
      },
      "properties": {
        "description": "representative point"
      }
    },
    {
      "geometry": {
        "type": "Point",
        "coordinates": [
          -8.009612,
          39.247834
        ]
      },
      "id": "darmc-location-17991",
      "type": "Feature",
      "properties": {
        "description": "1M scale point location",
        "location_precision": "precise",
        "title": "DARMC location 17991",
        "link": "http://pleiades.stoa.org/places/256377/darmc-location-17991"
      }
    }
  ]
}