{
  "type": "FeatureCollection",
  "title": "Ponte da Senhora da Azenha",
  "id": "256375",
  "description": "An ancient place, cited: BAtlas 26 C1 Ponte da Senhora da Azenha",
  "bbox": [
    -7.22846,
    39.916891,
    -7.22846,
    39.916891
  ],
  "reprPoint": [
    -7.22846,
    39.916891
  ],
  "features": [
    {
      "geometry": {
        "type": "Point",
        "coordinates": [
          -7.22846,
          39.916891
        ]
      },
      "id": "darmc-location-17990",
      "type": "Feature",
      "properties": {
        "description": "1M scale point location",
        "location_precision": "precise",
        "title": "DARMC location 17990",
        "link": "http://pleiades.stoa.org/places/256375/darmc-location-17990"
      }
    }
  ]
}