{
  "type": "FeatureCollection",
  "title": "Ponte da Sancha",
  "id": "256374",
  "description": "An ancient place, cited: BAtlas 26 B1 Ponte da Sancha",
  "bbox": [
    -8.493909,
    40.099889,
    -8.493909,
    40.099889
  ],
  "reprPoint": [
    -8.493909,
    40.099889
  ],
  "features": [
    {
      "geometry": {
        "type": "Point",
        "coordinates": [
          -8.493909,
          40.099889
        ]
      },
      "id": "darmc-location-17989",
      "type": "Feature",
      "properties": {
        "description": "1M scale point location",
        "location_precision": "precise",
        "title": "DARMC location 17989",
        "link": "http://pleiades.stoa.org/places/256374/darmc-location-17989"
      }
    }
  ]
}