{
  "type": "FeatureCollection",
  "title": "Olontigi",
  "id": "256339",
  "description": "An ancient place, cited: BAtlas 26 D4 Olontigi",
  "bbox": [
    -6.248394,
    37.305179,
    -6.248394,
    37.305179
  ],
  "reprPoint": [
    -6.248394,
    37.305179
  ],
  "names": [
    "Olontigi"
  ],
  "features": [
    {
      "geometry": {
        "type": "Point",
        "coordinates": [
          -6.248394,
          37.305179
        ]
      },
      "id": "darmc-location-4541",
      "type": "Feature",
      "properties": {
        "description": "1M scale point location",
        "location_precision": "precise",
        "title": "DARMC location 4541",
        "link": "http://pleiades.stoa.org/places/256339/darmc-location-4541"
      }
    }
  ]
}