{
  "type": "FeatureCollection",
  "title": "Ossonoba",
  "id": "256345",
  "bbox": [
    -7.935108,
    37.01535,
    -7.935108,
    37.01535
  ],
  "description": "An ancient place, cited: BAtlas 26 C4 Ossonoba",
  "names": [
    "Ossonoba",
    "Faro"
  ],
  "features": [
    {
      "type": "Feature",
      "geometry": {
        "type": "Point",
        "coordinates": [
          -7.935108,
          37.01535
        ]
      },
      "properties": {
        "description": "representative point"
      }
    },
    {
      "geometry": {
        "type": "Point",
        "coordinates": [
          -7.935108,
          37.01535
        ]
      },
      "id": "darmc-location-894",
      "type": "Feature",
      "properties": {
        "description": "1:1 million scale representative point location digitized from the Barrington Atlas of the Greek and Roman World by the Digital Atlas of Roman and Medieval Civilizations project at Harvard University.",
        "location_precision": "precise",
        "title": "DARMC location 894",
        "link": "http://pleiades.stoa.org/places/256345/darmc-location-894"
      }
    }
  ]
}