{
  "type": "FeatureCollection",
  "title": "Saguntia",
  "id": "256412",
  "description": "An ancient place, cited: BAtlas 26 E5 Saguntia",
  "bbox": [
    -5.834164,
    36.552106,
    -5.834164,
    36.552106
  ],
  "reprPoint": [
    -5.834164,
    36.552106
  ],
  "names": [
    "Saguntia"
  ],
  "features": [
    {
      "geometry": {
        "type": "Point",
        "coordinates": [
          -5.834164,
          36.552106
        ]
      },
      "id": "darmc-location-19864",
      "type": "Feature",
      "properties": {
        "description": "1M scale point location",
        "location_precision": "precise",
        "title": "DARMC location 19864",
        "link": "http://pleiades.stoa.org/places/256412/darmc-location-19864"
      }
    }
  ]
}