{
  "type": "FeatureCollection",
  "title": "Tapada da Ordem",
  "id": "256466",
  "description": "An ancient place, cited: BAtlas 26 C2 Tapada da Ordem",
  "bbox": [
    -7.028397,
    39.768893,
    -7.028397,
    39.768893
  ],
  "reprPoint": [
    -7.028397,
    39.768893
  ],
  "features": [
    {
      "geometry": {
        "type": "Point",
        "coordinates": [
          -7.028397,
          39.768893
        ]
      },
      "id": "darmc-location-19538",
      "type": "Feature",
      "properties": {
        "description": "1M scale point location",
        "location_precision": "precise",
        "title": "DARMC location 19538",
        "link": "http://pleiades.stoa.org/places/256466/darmc-location-19538"
      }
    }
  ]
}