{
  "type": "FeatureCollection",
  "title": "Sierra de la Martela",
  "id": "256450",
  "description": "An ancient place, cited: BAtlas 26 D3 Sierra de la Martela",
  "bbox": [
    -6.46713,
    38.085719,
    -6.46713,
    38.085719
  ],
  "reprPoint": [
    -6.46713,
    38.085719
  ],
  "features": [
    {
      "geometry": {
        "type": "Point",
        "coordinates": [
          -6.46713,
          38.085719
        ]
      },
      "id": "darmc-location-3547",
      "type": "Feature",
      "properties": {
        "description": "1M scale point location",
        "location_precision": "precise",
        "title": "DARMC location 3547",
        "link": "http://pleiades.stoa.org/places/256450/darmc-location-3547"
      }
    }
  ]
}