{
  "type": "FeatureCollection",
  "title": "Saepo",
  "id": "256411",
  "bbox": [
    -5.464318,
    36.579768,
    -5.464318,
    36.579768
  ],
  "description": "An ancient place, cited: BAtlas 26 E5 Saepo",
  "names": [
    "Saepo"
  ],
  "features": [
    {
      "type": "Feature",
      "geometry": {
        "type": "Point",
        "coordinates": [
          -5.464318,
          36.579768
        ]
      },
      "properties": {
        "description": "representative point"
      }
    },
    {
      "geometry": {
        "type": "Point",
        "coordinates": [
          -5.464318,
          36.579768
        ]
      },
      "id": "darmc-location-3068",
      "type": "Feature",
      "properties": {
        "description": "1M scale point location",
        "location_precision": "precise",
        "title": "DARMC location 3068",
        "link": "http://pleiades.stoa.org/places/256411/darmc-location-3068"
      }
    }
  ]
}