{
  "type": "FeatureCollection",
  "title": "Torre de Palma",
  "id": "256478",
  "description": "An ancient place, cited: BAtlas 26 C2 Torre de Palma",
  "bbox": [
    -7.488473,
    39.062264,
    -7.488473,
    39.062264
  ],
  "reprPoint": [
    -7.488473,
    39.062264
  ],
  "features": [
    {
      "geometry": {
        "type": "Point",
        "coordinates": [
          -7.488499,
          39.068673
        ]
      },
      "id": "darmc-location-21129",
      "type": "Feature",
      "properties": {
        "description": "1M scale point location",
        "location_precision": "precise",
        "title": "DARMC location 21129",
        "link": "http://pleiades.stoa.org/places/256478/darmc-location-21129"
      }
    },
    {
      "geometry": {
        "type": "Point",
        "coordinates": [
          -7.488473,
          39.062264
        ]
      },
      "id": "dare-location",
      "type": "Feature",
      "properties": {
        "description": "Representative point location, site precision",
        "location_precision": "precise",
        "title": "DARE Location",
        "link": "http://pleiades.stoa.org/places/256478/dare-location"
      }
    }
  ]
}