{
  "type": "FeatureCollection",
  "title": "Turirecina/Regina",
  "id": "256492",
  "description": "An ancient place, cited: BAtlas 26 E5 Turirecina/Regina",
  "bbox": [
    -5.806689,
    36.67173,
    -5.806689,
    36.67173
  ],
  "reprPoint": [
    -5.806689,
    36.67173
  ],
  "names": [
    "Turirecina",
    "Regina",
    "Col. Civium Romanorum Regina"
  ],
  "features": [
    {
      "geometry": {
        "type": "Point",
        "coordinates": [
          -5.806689,
          36.67173
        ]
      },
      "id": "darmc-location-19892",
      "type": "Feature",
      "properties": {
        "description": "1M scale point location",
        "location_precision": "precise",
        "title": "DARMC location 19892",
        "link": "http://pleiades.stoa.org/places/256492/darmc-location-19892"
      }
    }
  ]
}