{
  "type": "FeatureCollection",
  "title": "Solana de Belalcázar",
  "id": "256455",
  "description": "An ancient place, cited: BAtlas 26 E3 Solana de Belalcázar",
  "bbox": [
    -5.165482,
    38.582704,
    -5.165482,
    38.582704
  ],
  "reprPoint": [
    -5.165482,
    38.582704
  ],
  "features": [
    {
      "geometry": {
        "type": "Point",
        "coordinates": [
          -5.165482,
          38.582704
        ]
      },
      "id": "darmc-location-19532",
      "type": "Feature",
      "properties": {
        "description": "1M scale point location",
        "location_precision": "precise",
        "title": "DARMC location 19532",
        "link": "http://pleiades.stoa.org/places/256455/darmc-location-19532"
      }
    }
  ]
}