{
  "type": "FeatureCollection",
  "title": "S. Eulalia",
  "id": "256425",
  "bbox": [
    -6.667522,
    37.809447,
    -6.667522,
    37.809447
  ],
  "description": "An ancient place, cited: BAtlas 26 D4 S. Eulalia",
  "features": [
    {
      "type": "Feature",
      "geometry": {
        "type": "Point",
        "coordinates": [
          -6.667522,
          37.809447
        ]
      },
      "properties": {
        "description": "representative point"
      }
    },
    {
      "geometry": {
        "type": "Point",
        "coordinates": [
          -6.667522,
          37.809447
        ]
      },
      "id": "darmc-location-3058",
      "type": "Feature",
      "properties": {
        "description": "1M scale point location",
        "location_precision": "precise",
        "title": "DARMC location 3058",
        "link": "http://pleiades.stoa.org/places/256425/darmc-location-3058"
      }
    }
  ]
}