{
  "type": "FeatureCollection",
  "title": "Terrugem",
  "id": "256469",
  "bbox": [
    -8.636878,
    39.213818,
    -8.636878,
    39.213818
  ],
  "description": "An ancient place, cited: BAtlas 26 B2 Terrugem",
  "features": [
    {
      "type": "Feature",
      "geometry": {
        "type": "Point",
        "coordinates": [
          -8.636878,
          39.213818
        ]
      },
      "properties": {
        "description": "representative point"
      }
    },
    {
      "geometry": {
        "type": "Point",
        "coordinates": [
          -8.636878,
          39.213818
        ]
      },
      "id": "darmc-location-17999",
      "type": "Feature",
      "properties": {
        "description": "1M scale point location",
        "location_precision": "precise",
        "title": "DARMC location 17999",
        "link": "http://pleiades.stoa.org/places/256469/darmc-location-17999"
      }
    }
  ]
}