{
  "type": "FeatureCollection",
  "title": "Las Torres Roman Villa",
  "id": "256480",
  "bbox": [
    -5.0653084,
    36.4512858,
    -5.0653084,
    36.4512858
  ],
  "description": "An ancient place, cited: BAtlas 26 F5 Las Torres",
  "features": [
    {
      "type": "Feature",
      "geometry": {
        "type": "Point",
        "coordinates": [
          -5.0653084,
          36.4512858
        ]
      },
      "properties": {
        "description": "representative point"
      }
    },
    {
      "geometry": {
        "type": "Point",
        "coordinates": [
          -5.0653084,
          36.4512858
        ]
      },
      "id": "osm-location",
      "type": "Feature",
      "properties": {
        "description": "Representative location based on OpenStreetMap.",
        "location_precision": "precise",
        "title": "OSM location of Villa romana Las Torres",
        "link": "http://pleiades.stoa.org/places/256480/osm-location"
      }
    }
  ]
}