{
  "type": "FeatureCollection",
  "title": "Ulia (Fidentia)",
  "id": "256499",
  "description": "An ancient place, cited: BAtlas 26 F4 Ulia (Fidentia)",
  "bbox": [
    -4.698889,
    37.648657,
    -4.698889,
    37.648657
  ],
  "reprPoint": [
    -4.698889,
    37.648657
  ],
  "names": [
    "Ulia Fidentia",
    "Ulia"
  ],
  "features": [
    {
      "geometry": {
        "type": "Point",
        "coordinates": [
          -4.698889,
          37.648657
        ]
      },
      "id": "darmc-location-310",
      "type": "Feature",
      "properties": {
        "description": "1M scale point location",
        "location_precision": "precise",
        "title": "DARMC location 310",
        "link": "http://pleiades.stoa.org/places/256499/darmc-location-310"
      }
    }
  ]
}