{
  "type": "FeatureCollection",
  "title": "Torre de Palma",
  "id": "256478",
  "bbox": [
    -7.488473,
    39.062264,
    -7.488473,
    39.062264
  ],
  "description": "A large Roman villa inhabited from ca. the second century A.D. to the Visigothic period.",
  "features": [
    {
      "type": "Feature",
      "geometry": {
        "type": "Point",
        "coordinates": [
          -7.488473,
          39.062264
        ]
      },
      "properties": {
        "description": "representative point"
      }
    },
    {
      "geometry": {
        "type": "Point",
        "coordinates": [
          -7.488473,
          39.062264
        ]
      },
      "id": "dare-location",
      "type": "Feature",
      "properties": {
        "description": "Representative point location, site precision",
        "location_precision": "precise",
        "title": "DARE Location",
        "link": "http://pleiades.stoa.org/places/256478/dare-location"
      }
    }
  ]
}