{
  "type": "FeatureCollection",
  "title": "Torre da Cardeira",
  "id": "256475",
  "description": "An ancient place, cited: BAtlas 26 C4 Torre da Cardeira",
  "bbox": [
    -7.689594,
    37.963084,
    -7.689594,
    37.963084
  ],
  "reprPoint": [
    -7.689594,
    37.963084
  ],
  "features": [
    {
      "geometry": {
        "type": "Point",
        "coordinates": [
          -7.689594,
          37.963084
        ]
      },
      "id": "darmc-location-21127",
      "type": "Feature",
      "properties": {
        "description": "1M scale point location",
        "location_precision": "precise",
        "title": "DARMC location 21127",
        "link": "http://pleiades.stoa.org/places/256475/darmc-location-21127"
      }
    }
  ]
}