{
  "type": "FeatureCollection",
  "title": "Las Torres",
  "id": "256480",
  "description": "An ancient place, cited: BAtlas 26 F5 Las Torres",
  "bbox": [
    -5.0653084,
    36.4512858,
    -4.993735,
    36.468528
  ],
  "reprPoint": [
    -5.0295217,
    36.4599069
  ],
  "features": [
    {
      "geometry": {
        "type": "Point",
        "coordinates": [
          -4.993735,
          36.468528
        ]
      },
      "id": "darmc-location-20957",
      "type": "Feature",
      "properties": {
        "description": "1M scale point location",
        "location_precision": "precise",
        "title": "DARMC location 20957",
        "link": "http://pleiades.stoa.org/places/256480/darmc-location-20957"
      }
    }
  ]
}