{
  "type": "FeatureCollection",
  "title": "Urgapa?",
  "id": "256500",
  "description": "An ancient place, cited: BAtlas 26 F4 Urgapa?",
  "bbox": [
    -4.658062,
    37.20784,
    -4.658062,
    37.20784
  ],
  "reprPoint": [
    -4.658062,
    37.20784
  ],
  "names": [
    "Urgapa"
  ],
  "features": [
    {
      "geometry": {
        "type": "Point",
        "coordinates": [
          -4.658062,
          37.20784
        ]
      },
      "id": "darmc-location-315",
      "type": "Feature",
      "properties": {
        "description": "1M scale point location",
        "location_precision": "precise",
        "title": "DARMC location 315",
        "link": "http://pleiades.stoa.org/places/256500/darmc-location-315"
      }
    }
  ]
}