{
  "type": "FeatureCollection",
  "title": "U(r)gia",
  "id": "256501",
  "bbox": [
    -5.82933,
    36.990065,
    -5.82933,
    36.990065
  ],
  "description": "U(r)gia was located 27 Roman miles northwest of Hasta Regia.",
  "names": [
    "Urgia",
    "Ugia",
    "Caesaris Salutariensis",
    "Castrum Iulium"
  ],
  "features": [
    {
      "type": "Feature",
      "geometry": {
        "type": "Point",
        "coordinates": [
          -5.82933,
          36.990065
        ]
      },
      "properties": {
        "description": "representative point"
      }
    },
    {
      "geometry": {
        "type": "Point",
        "coordinates": [
          -5.82933,
          36.990065
        ]
      },
      "id": "darmc-location-309",
      "type": "Feature",
      "properties": {
        "description": "1M scale point location",
        "location_precision": "precise",
        "title": "DARMC location 309",
        "link": "http://pleiades.stoa.org/places/256501/darmc-location-309"
      }
    }
  ]
}