{
  "type": "FeatureCollection",
  "title": "Villo",
  "id": "256521",
  "bbox": [
    -5.300639,
    37.218871,
    -5.300639,
    37.218871
  ],
  "description": "An ancient place, cited: BAtlas 26 E4 Villo",
  "names": [
    "Villo"
  ],
  "features": [
    {
      "type": "Feature",
      "geometry": {
        "type": "Point",
        "coordinates": [
          -5.300639,
          37.218871
        ]
      },
      "properties": {
        "description": "representative point"
      }
    },
    {
      "geometry": {
        "type": "Point",
        "coordinates": [
          -5.300639,
          37.218871
        ]
      },
      "id": "darmc-location-3712",
      "type": "Feature",
      "properties": {
        "description": "1M scale point location",
        "location_precision": "precise",
        "title": "DARMC location 3712",
        "link": "http://pleiades.stoa.org/places/256521/darmc-location-3712"
      }
    }
  ]
}