{
  "type": "FeatureCollection",
  "title": "Arthur's O'On",
  "id": "260256455",
  "bbox": [
    -3.7991598,
    56.024464,
    -3.7991598,
    56.024464
  ],
  "description": "A circular Roman temple that stood on the river Carron until it was destroyed in 1743.",
  "names": [
    "Arthur's O'on"
  ],
  "features": [
    {
      "type": "Feature",
      "geometry": {
        "type": "Point",
        "coordinates": [
          -3.7991598,
          56.024464
        ]
      },
      "properties": {
        "description": "representative point"
      }
    },
    {
      "geometry": {
        "type": "Point",
        "coordinates": [
          -3.7991598,
          56.024464
        ]
      },
      "id": "site-of-arthurs-oon",
      "type": "Feature",
      "properties": {
        "description": "Representative location based on OpenStreetMap.",
        "location_precision": "precise",
        "title": "OSM location of Arthur's O'On",
        "link": "http://pleiades.stoa.org/places/260256455/site-of-arthurs-oon"
      }
    }
  ]
}