{
  "type": "FeatureCollection",
  "title": "Hospitium of Hermes",
  "id": "260329423",
  "description": "A Roman hospitium located near the Porta Stabia in Pompeii (I, 1, 8).",
  "bbox": [
    14.4897455,
    40.7486364,
    14.4897455,
    40.7486364
  ],
  "connectsWith": [
    "433032"
  ],
  "reprPoint": [
    14.4897455,
    40.7486364
  ],
  "features": [
    {
      "geometry": {
        "type": "Point",
        "coordinates": [
          14.4897455,
          40.7486364
        ]
      },
      "id": "hospitium-di-hermes",
      "type": "Feature",
      "properties": {
        "description": "Representative location based on OpenStreetMap",
        "location_precision": "precise",
        "title": "OSM location of so-called Hospitium di Hermes",
        "link": "http://pleiades.stoa.org/places/260329423/hospitium-di-hermes"
      }
    }
  ]
}