{
  "type": "FeatureCollection",
  "title": "Temple of Demeter and Kore",
  "id": "260724426",
  "bbox": [
    8.6354995,
    39.2015099,
    8.6354995,
    39.2015099
  ],
  "description": "A Punic and Roman temple sacred to Demeter and Kore located at Bagoi, Perdaxius, Sardinia.",
  "connectsWith": [
    "472014"
  ],
  "features": [
    {
      "type": "Feature",
      "geometry": {
        "type": "Point",
        "coordinates": [
          8.6354995,
          39.2015099
        ]
      },
      "properties": {
        "description": "representative point"
      }
    },
    {
      "geometry": {
        "type": "Point",
        "coordinates": [
          8.6354995,
          39.2015099
        ]
      },
      "id": "osm-location",
      "type": "Feature",
      "properties": {
        "description": "Location based on OpenStreetMap",
        "location_precision": "precise",
        "title": "OSM location of Bagoi, Perdaxius",
        "link": "http://pleiades.stoa.org/places/260724426/osm-location"
      }
    }
  ]
}