{
  "type": "FeatureCollection",
  "title": "Beitin",
  "id": "260940008",
  "description": "A settlement which originally dates to the Chalcolithic period.",
  "bbox": [
    35.238333,
    31.928333,
    35.238333,
    31.928333
  ],
  "connectsWith": [
    "687934"
  ],
  "reprPoint": [
    35.238333,
    31.928333
  ],
  "names": [
    "Bethega",
    "Bethela"
  ],
  "features": [
    {
      "geometry": {
        "type": "Point",
        "coordinates": [
          35.238333,
          31.928333
        ]
      },
      "id": "location-of-beitin",
      "type": "Feature",
      "properties": {
        "description": "Modern settlement; coordinates following GeoHack.",
        "location_precision": "precise",
        "title": "location of Beitin",
        "link": "http://pleiades.stoa.org/places/260940008/location-of-beitin"
      }
    }
  ]
}