{
  "type": "FeatureCollection",
  "title": "Piana di Monte Verna",
  "id": "262148219",
  "description": "An ancient Oscan center delimited by a megalithic fortification wall.",
  "bbox": [
    14.333333,
    41.166667,
    14.333333,
    41.166667
  ],
  "reprPoint": [
    14.333333,
    41.166667
  ],
  "features": [
    {
      "geometry": {
        "type": "Point",
        "coordinates": [
          14.333333,
          41.166667
        ]
      },
      "id": "location-of-piana-di-monte-verna",
      "type": "Feature",
      "properties": {
        "description": null,
        "location_precision": "precise",
        "title": "location of Piana di Monte Verna",
        "link": "http://pleiades.stoa.org/places/262148219/location-of-piana-di-monte-verna"
      }
    }
  ]
}