{
  "type": "FeatureCollection",
  "title": "Roman amphitheater at Cyzicus",
  "id": "263157373",
  "bbox": [
    27.8846826,
    40.3982552,
    27.8846826,
    40.3982552
  ],
  "description": "The Roman amphitheater at Cyzicus.",
  "connectsWith": [
    "511218"
  ],
  "features": [
    {
      "type": "Feature",
      "geometry": {
        "type": "Point",
        "coordinates": [
          27.8846826,
          40.3982552
        ]
      },
      "properties": {
        "description": "representative point"
      }
    },
    {
      "geometry": {
        "type": "Point",
        "coordinates": [
          27.8846826,
          40.3982552
        ]
      },
      "id": "osm-location-of-roman-amphitheater",
      "type": "Feature",
      "properties": {
        "description": "Representative location based on OpenStreetMap.",
        "location_precision": "precise",
        "title": "OSM location of Kyzikos Amphitheatre",
        "link": "http://pleiades.stoa.org/places/263157373/osm-location-of-roman-amphitheater"
      }
    }
  ]
}