{
  "type": "FeatureCollection",
  "title": "Anticaria",
  "id": "265799",
  "bbox": [
    -4.562887,
    37.019374,
    -4.562887,
    37.019374
  ],
  "description": "An ancient Roman town mentioned in the Antonine Itinerary and by the Ravenna Cosmographer. Modern Antequera in Spain.",
  "names": [
    "Anticaria"
  ],
  "features": [
    {
      "type": "Feature",
      "geometry": {
        "type": "Point",
        "coordinates": [
          -4.562887,
          37.019374
        ]
      },
      "properties": {
        "description": "representative point"
      }
    },
    {
      "geometry": {
        "type": "Point",
        "coordinates": [
          -4.562887,
          37.019374
        ]
      },
      "id": "darmc-location-19969",
      "type": "Feature",
      "properties": {
        "description": "1M scale point location",
        "location_precision": "precise",
        "title": "DARMC location 19969",
        "link": "http://pleiades.stoa.org/places/265799/darmc-location-19969"
      }
    }
  ]
}