{
  "type": "FeatureCollection",
  "title": "Alonis",
  "id": "265796",
  "description": "An ancient place, cited: BAtlas 27 E3 Alonis",
  "bbox": [
    -0.555223,
    38.192287,
    -0.555223,
    38.192287
  ],
  "reprPoint": [
    -0.555223,
    38.192287
  ],
  "names": [
    "Alonis"
  ],
  "features": [
    {
      "geometry": {
        "type": "Point",
        "coordinates": [
          -0.555223,
          38.192287
        ]
      },
      "id": "darmc-location-19722",
      "type": "Feature",
      "properties": {
        "description": "1M scale point location",
        "location_precision": "precise",
        "title": "DARMC location 19722",
        "link": "http://pleiades.stoa.org/places/265796/darmc-location-19722"
      }
    }
  ]
}