{
  "type": "FeatureCollection",
  "title": "Ad Duo Solaria",
  "id": "265769",
  "description": "An ancient place, cited: BAtlas 27 B3 Ad Duo Solaria",
  "bbox": [
    -3.103507,
    38.342214,
    -3.103507,
    38.342214
  ],
  "reprPoint": [
    -3.103507,
    38.342214
  ],
  "names": [
    "Ad Duo Solaria"
  ],
  "features": [
    {
      "geometry": {
        "type": "Point",
        "coordinates": [
          -3.103507,
          38.342214
        ]
      },
      "id": "darmc-location-19587",
      "type": "Feature",
      "properties": {
        "description": "1M scale point location",
        "location_precision": "precise",
        "title": "DARMC location 19587",
        "link": "http://pleiades.stoa.org/places/265769/darmc-location-19587"
      }
    }
  ]
}