{
  "type": "FeatureCollection",
  "title": "(Ad) Murum",
  "id": "265776",
  "bbox": [
    -3.360099,
    39.181617,
    -3.360099,
    39.181617
  ],
  "description": "An ancient place, cited: BAtlas 27 B2 (Ad) Murum",
  "names": [
    "Ad Murum",
    "Murum"
  ],
  "features": [
    {
      "type": "Feature",
      "geometry": {
        "type": "Point",
        "coordinates": [
          -3.360099,
          39.181617
        ]
      },
      "properties": {
        "description": "representative point"
      }
    },
    {
      "geometry": {
        "type": "Point",
        "coordinates": [
          -3.360099,
          39.181617
        ]
      },
      "id": "darmc-location-19616",
      "type": "Feature",
      "properties": {
        "description": "1M scale point location",
        "location_precision": "precise",
        "title": "DARMC location 19616",
        "link": "http://pleiades.stoa.org/places/265776/darmc-location-19616"
      }
    }
  ]
}