{
  "type": "FeatureCollection",
  "title": "Dianium/Hemeroskopeion",
  "id": "265880",
  "bbox": [
    0.107511,
    38.842795,
    0.107511,
    38.842795
  ],
  "description": "An ancient place, cited: BAtlas 27 F3 Dianium/Hemeroskopeion",
  "connectsWith": [
    "269561"
  ],
  "names": [
    "Dianium",
    "Hemeroskopeion",
    "Dénia"
  ],
  "features": [
    {
      "type": "Feature",
      "geometry": {
        "type": "Point",
        "coordinates": [
          0.107511,
          38.842795
        ]
      },
      "properties": {
        "description": "representative point"
      }
    },
    {
      "geometry": {
        "type": "Point",
        "coordinates": [
          0.107511,
          38.842795
        ]
      },
      "id": "darmc-location-963",
      "type": "Feature",
      "properties": {
        "description": "1:1 million scale representative point location digitized from the Barrington Atlas of the Greek and Roman World by the Digital Atlas of Roman and Medieval Civilizations project at Harvard University.",
        "location_precision": "precise",
        "title": "DARMC location 963",
        "link": "http://pleiades.stoa.org/places/265880/darmc-location-963"
      }
    }
  ]
}