{
  "type": "FeatureCollection",
  "title": "Buñola",
  "id": "265830",
  "bbox": [
    2.699401,
    39.69665,
    2.699401,
    39.69665
  ],
  "description": "An ancient place, cited: BAtlas 27 inset Buñola",
  "connectsWith": [
    "632227173"
  ],
  "features": [
    {
      "type": "Feature",
      "geometry": {
        "type": "Point",
        "coordinates": [
          2.699401,
          39.69665
        ]
      },
      "properties": {
        "description": "representative point"
      }
    },
    {
      "geometry": {
        "type": "Point",
        "coordinates": [
          2.699401,
          39.69665
        ]
      },
      "id": "darmc-location-29482",
      "type": "Feature",
      "properties": {
        "description": "1M scale point location",
        "location_precision": "precise",
        "title": "DARMC location 29482",
        "link": "http://pleiades.stoa.org/places/265830/darmc-location-29482"
      }
    }
  ]
}