{
  "type": "FeatureCollection",
  "title": "Roman Villa at El Faro (Torrox)",
  "id": "265896",
  "description": "A Roman villa located at the modern lighthouse on Avenida del Faro, Torrox, 29770, Málaga in Spain.",
  "bbox": [
    -3.9576942,
    36.7266472,
    -3.9576942,
    36.7266472
  ],
  "reprPoint": [
    -3.9576942,
    36.7266472
  ],
  "names": [
    "Villa del Faro"
  ],
  "features": [
    {
      "geometry": {
        "type": "Point",
        "coordinates": [
          -3.9576942,
          36.7266472
        ]
      },
      "id": "osm-location-of-roman-villa",
      "type": "Feature",
      "properties": {
        "description": "Location based on OpenStreetMap",
        "location_precision": "precise",
        "title": "OSM location of Roman villa",
        "link": "http://pleiades.stoa.org/places/265896/osm-location-of-roman-villa"
      }
    }
  ]
}