{
  "type": "FeatureCollection",
  "title": "Cerro de las Cabezas",
  "id": "265861",
  "description": "An ancient place, cited: BAtlas 27 B3 Cerro de las Cabezas",
  "bbox": [
    -3.4203201,
    38.7080052,
    -3.416159,
    38.803197
  ],
  "reprPoint": [
    -3.41823955,
    38.7556011
  ],
  "features": [
    {
      "geometry": {
        "type": "Point",
        "coordinates": [
          -3.416159,
          38.803197
        ]
      },
      "id": "darmc-location-20154",
      "type": "Feature",
      "properties": {
        "description": "1M scale point location",
        "location_precision": "precise",
        "title": "DARMC location 20154",
        "link": "http://pleiades.stoa.org/places/265861/darmc-location-20154"
      }
    }
  ]
}