{
  "type": "FeatureCollection",
  "title": "Dianium/Hemeroskopeion",
  "id": "265880",
  "description": "An ancient place, cited: BAtlas 27 F3 Dianium/Hemeroskopeion",
  "bbox": [
    0.107511,
    38.842795,
    0.107511,
    38.842795
  ],
  "reprPoint": [
    0.107511,
    38.842795
  ],
  "names": [
    "Dianium",
    "Hemeroskopeion",
    "Dénia"
  ],
  "features": [
    {
      "geometry": {
        "type": "Point",
        "coordinates": [
          0.107511,
          38.842795
        ]
      },
      "id": "darmc-location-963",
      "type": "Feature",
      "properties": {
        "description": "1M scale point location",
        "location_precision": "precise",
        "title": "DARMC location 963",
        "link": "http://pleiades.stoa.org/places/265880/darmc-location-963"
      }
    }
  ]
}