{
  "type": "FeatureCollection",
  "title": "El Faro",
  "id": "265896",
  "description": "An ancient place, cited: BAtlas 27 B5 El Faro",
  "bbox": [
    -3.9576942,
    36.726561,
    -3.957352,
    36.7266472
  ],
  "reprPoint": [
    -3.9575231,
    36.7266041
  ],
  "features": [
    {
      "geometry": {
        "type": "Point",
        "coordinates": [
          -3.9576942,
          36.7266472
        ]
      },
      "id": "location-of-roman-villa",
      "type": "Feature",
      "properties": {
        "description": "Location based on OpenStreetMap",
        "location_precision": "precise",
        "title": "location of Roman villa",
        "link": "http://pleiades.stoa.org/places/265896/location-of-roman-villa"
      }
    },
    {
      "geometry": {
        "type": "Point",
        "coordinates": [
          -3.957352,
          36.726561
        ]
      },
      "id": "darmc-location-20842",
      "type": "Feature",
      "properties": {
        "description": "1M scale point location",
        "location_precision": "precise",
        "title": "DARMC location 20842",
        "link": "http://pleiades.stoa.org/places/265896/darmc-location-20842"
      }
    }
  ]
}