{
  "type": "FeatureCollection",
  "title": "El Faro",
  "id": "265896",
  "description": "An ancient place, cited: BAtlas 27 B5 El Faro",
  "bbox": [
    -3.957352,
    36.726561,
    -3.957352,
    36.726561
  ],
  "reprPoint": [
    -3.957352,
    36.726561
  ],
  "features": [
    {
      "geometry": {
        "type": "Point",
        "coordinates": [
          -3.957352,
          36.726561
        ]
      },
      "id": "darmc-location-20842",
      "type": "Feature",
      "properties": {
        "description": "1M scale point location",
        "location_precision": "precise",
        "title": "DARMC location 20842",
        "link": "http://pleiades.stoa.org/places/265896/darmc-location-20842"
      }
    }
  ]
}