{
  "type": "FeatureCollection",
  "title": "Colubraria? (island)",
  "id": "265874",
  "bbox": [
    0.685142,
    39.897619,
    0.685142,
    39.897619
  ],
  "description": "An ancient place, cited: BAtlas 27 F2 Colubraria? Ins.",
  "connectsWith": [
    "1043"
  ],
  "names": [
    "Colubraria"
  ],
  "features": [
    {
      "type": "Feature",
      "geometry": {
        "type": "Point",
        "coordinates": [
          0.685142,
          39.897619
        ]
      },
      "properties": {
        "description": "representative point"
      }
    },
    {
      "geometry": {
        "type": "Point",
        "coordinates": [
          0.685142,
          39.897619
        ]
      },
      "id": "location-of-columbrete-grande",
      "type": "Feature",
      "properties": {
        "description": "Representative location based on GeoHack.",
        "location_precision": "precise",
        "title": "GeoHack location of Columbrete Grande",
        "link": "http://pleiades.stoa.org/places/265874/location-of-columbrete-grande"
      }
    }
  ]
}