{
  "type": "FeatureCollection",
  "title": "Cartagena-Mazarrón",
  "id": "265848",
  "bbox": [
    -1.229486,
    37.613798,
    -1.229486,
    37.613798
  ],
  "description": "An ancient place, cited: BAtlas 27 D4 Cartagena-Mazarrón",
  "features": [
    {
      "type": "Feature",
      "geometry": {
        "type": "Point",
        "coordinates": [
          -1.229486,
          37.613798
        ]
      },
      "properties": {
        "description": "representative point"
      }
    },
    {
      "geometry": {
        "type": "Point",
        "coordinates": [
          -1.229486,
          37.613798
        ]
      },
      "id": "darmc-location-29555",
      "type": "Feature",
      "properties": {
        "description": "1M scale point location",
        "location_precision": "precise",
        "title": "DARMC location 29555",
        "link": "http://pleiades.stoa.org/places/265848/darmc-location-29555"
      }
    }
  ]
}