{
  "type": "FeatureCollection",
  "title": "Consabura/Consabrum",
  "id": "265876",
  "description": "An ancient place, cited: BAtlas 27 B2 Consabura/Consabrum",
  "bbox": [
    -3.606772,
    39.460299,
    -3.606772,
    39.460299
  ],
  "reprPoint": [
    -3.606772,
    39.460299
  ],
  "names": [
    "Consabura",
    "Consabrum",
    "Kondabora"
  ],
  "features": [
    {
      "geometry": {
        "type": "Point",
        "coordinates": [
          -3.606772,
          39.460299
        ]
      },
      "id": "darmc-location-20192",
      "type": "Feature",
      "properties": {
        "description": "1M scale point location",
        "location_precision": "precise",
        "title": "DARMC location 20192",
        "link": "http://pleiades.stoa.org/places/265876/darmc-location-20192"
      }
    }
  ]
}