{
  "type": "FeatureCollection",
  "title": "Cerro de las Cabezas",
  "id": "265861",
  "bbox": [
    -3.4203201,
    38.7080052,
    -3.4203201,
    38.7080052
  ],
  "description": "An ancient place, cited: BAtlas 27 B3 Cerro de las Cabezas",
  "features": [
    {
      "type": "Feature",
      "geometry": {
        "type": "Point",
        "coordinates": [
          -3.4203201,
          38.7080052
        ]
      },
      "properties": {
        "description": "representative point"
      }
    },
    {
      "geometry": {
        "type": "Point",
        "coordinates": [
          -3.4203201,
          38.7080052
        ]
      },
      "id": "osm-location",
      "type": "Feature",
      "properties": {
        "description": "Location based on OpenStreetMap",
        "location_precision": "precise",
        "title": "OSM location",
        "link": "http://pleiades.stoa.org/places/265861/osm-location"
      }
    }
  ]
}