{
  "type": "FeatureCollection",
  "title": "Jumilla",
  "id": "265943",
  "description": "An ancient place, cited: BAtlas 27 D3 Jumilla",
  "bbox": [
    -1.322204,
    38.475704,
    -1.322204,
    38.475704
  ],
  "reprPoint": [
    -1.322204,
    38.475704
  ],
  "features": [
    {
      "geometry": {
        "type": "Point",
        "coordinates": [
          -1.322204,
          38.475704
        ]
      },
      "id": "darmc-location-20355",
      "type": "Feature",
      "properties": {
        "description": "1M scale point location",
        "location_precision": "precise",
        "title": "DARMC location 20355",
        "link": "http://pleiades.stoa.org/places/265943/darmc-location-20355"
      }
    }
  ]
}