{
  "type": "FeatureCollection",
  "title": "Mago",
  "id": "265960",
  "bbox": [
    4.264116,
    39.889482,
    4.264116,
    39.889482
  ],
  "description": "Mago (now Mahón or Maó) on the island of Menorca was established as an ancient commercial center because of its high-quality harborage. Its ancient name is thought to derive from Mago, brother of Hannibal, who occupied the Insula Minor after he fled from Gades in 206 BCE.",
  "connectsWith": [
    "572631626"
  ],
  "names": [
    "Mago"
  ],
  "features": [
    {
      "type": "Feature",
      "geometry": {
        "type": "Point",
        "coordinates": [
          4.264116,
          39.889482
        ]
      },
      "properties": {
        "description": "representative point"
      }
    },
    {
      "geometry": {
        "type": "Point",
        "coordinates": [
          4.264116,
          39.889482
        ]
      },
      "id": "darmc-location-30460",
      "type": "Feature",
      "properties": {
        "description": "1:1 million scale representative point location digitized from the Barrington Atlas of the Greek and Roman World by the Digital Atlas of Roman and Medieval Civilizations project at Harvard University.",
        "location_precision": "precise",
        "title": "DARMC location 30460",
        "link": "http://pleiades.stoa.org/places/265960/darmc-location-30460"
      }
    }
  ]
}