{
  "type": "FeatureCollection",
  "title": "Onuba",
  "id": "265985",
  "bbox": [
    -4.496471,
    37.953182,
    -4.496471,
    37.953182
  ],
  "description": "An ancient place, cited: BAtlas 27 A4 Onuba",
  "names": [
    "Onuba"
  ],
  "features": [
    {
      "type": "Feature",
      "geometry": {
        "type": "Point",
        "coordinates": [
          -4.496471,
          37.953182
        ]
      },
      "properties": {
        "description": "representative point"
      }
    },
    {
      "geometry": {
        "type": "Point",
        "coordinates": [
          -4.496471,
          37.953182
        ]
      },
      "id": "darmc-location-888",
      "type": "Feature",
      "properties": {
        "description": "1M scale point location",
        "location_precision": "precise",
        "title": "DARMC location 888",
        "link": "http://pleiades.stoa.org/places/265985/darmc-location-888"
      }
    }
  ]
}