{
  "type": "FeatureCollection",
  "title": "Iliberri",
  "id": "265921",
  "bbox": [
    -3.597934,
    37.176484,
    -3.597934,
    37.176484
  ],
  "description": "An ancient settlement located to the west of modern Granada. Its precise location is unknown.",
  "names": [
    "Iliberri",
    "Elvira",
    "Municipium Florentinum",
    "Granada"
  ],
  "features": [
    {
      "type": "Feature",
      "geometry": {
        "type": "Point",
        "coordinates": [
          -3.597934,
          37.176484
        ]
      },
      "properties": {
        "description": "representative point"
      }
    },
    {
      "geometry": {
        "type": "Point",
        "coordinates": [
          -3.597934,
          37.176484
        ]
      },
      "id": "darmc-location-20321",
      "type": "Feature",
      "properties": {
        "description": "1:1 million scale representative point location digitized from the Barrington Atlas of the Greek and Roman World by the Digital Atlas of Roman and Medieval Civilizations project at Harvard University.",
        "location_precision": "precise",
        "title": "DARMC location 20321",
        "link": "http://pleiades.stoa.org/places/265921/darmc-location-20321"
      }
    }
  ]
}