{
  "type": "FeatureCollection",
  "title": "El Laderón",
  "id": "265945",
  "description": "An ancient place, cited: BAtlas 27 A4 El Laderón",
  "bbox": [
    -4.373006,
    37.540948,
    -4.373006,
    37.540948
  ],
  "reprPoint": [
    -4.373006,
    37.540948
  ],
  "features": [
    {
      "geometry": {
        "type": "Point",
        "coordinates": [
          -4.373006,
          37.540948
        ]
      },
      "id": "darmc-location-20242",
      "type": "Feature",
      "properties": {
        "description": "1M scale point location",
        "location_precision": "precise",
        "title": "DARMC location 20242",
        "link": "http://pleiades.stoa.org/places/265945/darmc-location-20242"
      }
    }
  ]
}