{
  "type": "FeatureCollection",
  "title": "Mago",
  "id": "265960",
  "bbox": [
    4.2647291,
    39.8894325,
    4.2647291,
    39.8894325
  ],
  "description": "Mago (now Mahón or Maó) on the island of Menorca was established as an ancient commercial center because of its high-quality harborage. Its ancient name is thought to derive from Mago, brother of Hannibal, who occupied the Insula Minor after he fled from Gades in 206 BCE.",
  "connectsWith": [
    "572631626"
  ],
  "names": [
    "Mago",
    "Mao",
    "Mahon"
  ],
  "features": [
    {
      "type": "Feature",
      "geometry": {
        "type": "Point",
        "coordinates": [
          4.2647291,
          39.8894325
        ]
      },
      "properties": {
        "description": "representative point"
      }
    },
    {
      "geometry": {
        "type": "Point",
        "coordinates": [
          4.2647291,
          39.8894325
        ]
      },
      "id": "osm-location",
      "type": "Feature",
      "properties": {
        "description": "Location based on OpenStreetMap",
        "location_precision": "precise",
        "title": "OSM location of Maó",
        "link": "http://pleiades.stoa.org/places/265960/osm-location"
      }
    }
  ]
}