{
  "type": "FeatureCollection",
  "title": "Fuente de las Piedras",
  "id": "265903",
  "bbox": [
    -4.425933,
    37.474391,
    -4.425933,
    37.474391
  ],
  "description": "An ancient place, cited: BAtlas 27 A4 Fuente de las Piedras",
  "connectsWith": [
    "265919"
  ],
  "features": [
    {
      "type": "Feature",
      "geometry": {
        "type": "Point",
        "coordinates": [
          -4.425933,
          37.474391
        ]
      },
      "properties": {
        "description": "representative point"
      }
    },
    {
      "geometry": {
        "type": "Point",
        "coordinates": [
          -4.425933,
          37.474391
        ]
      },
      "id": "darmc-location-20878",
      "type": "Feature",
      "properties": {
        "description": "1M scale point location",
        "location_precision": "precise",
        "title": "DARMC location 20878",
        "link": "http://pleiades.stoa.org/places/265903/darmc-location-20878"
      }
    }
  ]
}