{
  "type": "FeatureCollection",
  "title": "Mago",
  "id": "265960",
  "description": "An ancient place, cited: BAtlas 27 inset Mago",
  "bbox": [
    4.264116,
    39.8894325,
    4.2647291,
    39.889482
  ],
  "connectsWith": [
    "572631626"
  ],
  "reprPoint": [
    4.26442255,
    39.88945725
  ],
  "names": [
    "Mago"
  ],
  "features": [
    {
      "geometry": {
        "type": "Point",
        "coordinates": [
          4.264116,
          39.889482
        ]
      },
      "id": "darmc-location-30460",
      "type": "Feature",
      "properties": {
        "description": "1M scale point location",
        "location_precision": "precise",
        "title": "DARMC location 30460",
        "link": "http://pleiades.stoa.org/places/265960/darmc-location-30460"
      }
    }
  ]
}