{
  "type": "FeatureCollection",
  "title": "Jumilla",
  "id": "265943",
  "bbox": [
    -1.3275218,
    38.4353536,
    -1.322204,
    38.475704
  ],
  "description": "An ancient settlement of southeastern Spain, whose ancient name is not known today. Occupation of the area seems to stretch from the bronze age up to modern times.",
  "features": [
    {
      "type": "Feature",
      "geometry": {
        "type": "Point",
        "coordinates": [
          -1.3248629,
          38.4555288
        ]
      },
      "properties": {
        "description": "representative point"
      }
    },
    {
      "geometry": {
        "type": "Point",
        "coordinates": [
          -1.322204,
          38.475704
        ]
      },
      "id": "darmc-location-20355",
      "type": "Feature",
      "properties": {
        "description": "1M scale point location",
        "location_precision": "precise",
        "title": "DARMC location 20355",
        "link": "http://pleiades.stoa.org/places/265943/darmc-location-20355"
      }
    },
    {
      "geometry": {
        "type": "Point",
        "coordinates": [
          -1.3275218,
          38.4353536
        ]
      },
      "id": "osm-location-of-coimbra",
      "type": "Feature",
      "properties": {
        "description": "Representative location based on OpenStreetMap.",
        "location_precision": "precise",
        "title": "OSM location of Coimbra",
        "link": "http://pleiades.stoa.org/places/265943/osm-location-of-coimbra"
      }
    }
  ]
}