{
  "type": "FeatureCollection",
  "title": "*Ipsca",
  "id": "265937",
  "bbox": [
    -4.39041,
    37.67242,
    -4.39041,
    37.67242
  ],
  "description": "An ancient place, cited: BAtlas 27 A4 *Ipsca",
  "names": [
    "Ipsca",
    "Municipium Contributum Ipscense"
  ],
  "features": [
    {
      "type": "Feature",
      "geometry": {
        "type": "Point",
        "coordinates": [
          -4.39041,
          37.67242
        ]
      },
      "properties": {
        "description": "representative point"
      }
    },
    {
      "geometry": {
        "type": "Point",
        "coordinates": [
          -4.39041,
          37.67242
        ]
      },
      "id": "darmc-location-20339",
      "type": "Feature",
      "properties": {
        "description": "1M scale point location",
        "location_precision": "precise",
        "title": "DARMC location 20339",
        "link": "http://pleiades.stoa.org/places/265937/darmc-location-20339"
      }
    }
  ]
}