{
  "type": "FeatureCollection",
  "title": "Maenuba/Menova",
  "id": "265959",
  "bbox": [
    -4.100678,
    36.77864,
    -4.100678,
    36.77864
  ],
  "description": "An ancient place, cited: BAtlas 27 A5 Maenuba/Menova",
  "names": [
    "Maenuba",
    "Menova",
    "Maenoba"
  ],
  "features": [
    {
      "type": "Feature",
      "geometry": {
        "type": "Point",
        "coordinates": [
          -4.100678,
          36.77864
        ]
      },
      "properties": {
        "description": "representative point"
      }
    },
    {
      "geometry": {
        "type": "Point",
        "coordinates": [
          -4.100678,
          36.77864
        ]
      },
      "id": "darmc-location-20458",
      "type": "Feature",
      "properties": {
        "description": "1M scale point location",
        "location_precision": "precise",
        "title": "DARMC location 20458",
        "link": "http://pleiades.stoa.org/places/265959/darmc-location-20458"
      }
    }
  ]
}