{
  "type": "FeatureCollection",
  "title": "Hoyo de la Campana",
  "id": "265914",
  "description": "An ancient place, cited: BAtlas 27 B4 Hoyo de la Campana",
  "bbox": [
    -3.605316,
    37.128828,
    -3.605316,
    37.128828
  ],
  "reprPoint": [
    -3.605316,
    37.128828
  ],
  "features": [
    {
      "geometry": {
        "type": "Point",
        "coordinates": [
          -3.605316,
          37.128828
        ]
      },
      "id": "darmc-location-19508",
      "type": "Feature",
      "properties": {
        "description": "1M scale point location",
        "location_precision": "precise",
        "title": "DARMC location 19508",
        "link": "http://pleiades.stoa.org/places/265914/darmc-location-19508"
      }
    }
  ]
}