{
  "type": "FeatureCollection",
  "title": "Murgi",
  "id": "265977",
  "bbox": [
    -2.812733,
    36.775074,
    -2.812733,
    36.775074
  ],
  "description": "An ancient place, cited: BAtlas 27 C5 Murgi",
  "names": [
    "Murgi"
  ],
  "features": [
    {
      "type": "Feature",
      "geometry": {
        "type": "Point",
        "coordinates": [
          -2.812733,
          36.775074
        ]
      },
      "properties": {
        "description": "representative point"
      }
    },
    {
      "geometry": {
        "type": "Point",
        "coordinates": [
          -2.812733,
          36.775074
        ]
      },
      "id": "darmc-location-19821",
      "type": "Feature",
      "properties": {
        "description": "1M scale point location",
        "location_precision": "precise",
        "title": "DARMC location 19821",
        "link": "http://pleiades.stoa.org/places/265977/darmc-location-19821"
      }
    }
  ]
}