{
  "type": "FeatureCollection",
  "title": "Mariana",
  "id": "265965",
  "bbox": [
    -2.92748,
    38.547361,
    -2.92748,
    38.547361
  ],
  "description": "An ancient place, cited: BAtlas 27 C3 Mariana",
  "names": [
    "Mariana"
  ],
  "features": [
    {
      "type": "Feature",
      "geometry": {
        "type": "Point",
        "coordinates": [
          -2.92748,
          38.547361
        ]
      },
      "properties": {
        "description": "representative point"
      }
    },
    {
      "geometry": {
        "type": "Point",
        "coordinates": [
          -2.92748,
          38.547361
        ]
      },
      "id": "darmc-location-7590",
      "type": "Feature",
      "properties": {
        "description": "1M scale point location",
        "location_precision": "precise",
        "title": "DARMC location 7590",
        "link": "http://pleiades.stoa.org/places/265965/darmc-location-7590"
      }
    }
  ]
}