{
  "type": "FeatureCollection",
  "title": "Malaca",
  "id": "265963",
  "bbox": [
    -4.420163,
    36.719658,
    -4.420163,
    36.719658
  ],
  "description": "A Roman city of Baetica that was perhaps founded by the Carthaginians in the fifth century BC.",
  "names": [
    "Malaca",
    "Malaga",
    "municipium Flavium Malacitanum"
  ],
  "features": [
    {
      "type": "Feature",
      "geometry": {
        "type": "Point",
        "coordinates": [
          -4.420163,
          36.719658
        ]
      },
      "properties": {
        "description": "representative point"
      }
    },
    {
      "geometry": {
        "type": "Point",
        "coordinates": [
          -4.420163,
          36.719658
        ]
      },
      "id": "darmc-location-20463",
      "type": "Feature",
      "properties": {
        "description": "1:1 million scale representative point location digitized from the Barrington Atlas of the Greek and Roman World by the Digital Atlas of Roman and Medieval Civilizations project at Harvard University.",
        "location_precision": "precise",
        "title": "DARMC location 20463",
        "link": "http://pleiades.stoa.org/places/265963/darmc-location-20463"
      }
    }
  ]
}