{
  "type": "FeatureCollection",
  "title": "Iliberri",
  "id": "265921",
  "description": "An ancient place, cited: BAtlas 27 B4 Iliberri",
  "bbox": [
    -3.597934,
    37.176484,
    -3.597934,
    37.176484
  ],
  "reprPoint": [
    -3.597934,
    37.176484
  ],
  "names": [
    "Iliberri",
    "Elvira",
    "Municipium Florentinum"
  ],
  "features": [
    {
      "geometry": {
        "type": "Point",
        "coordinates": [
          -3.597934,
          37.176484
        ]
      },
      "id": "darmc-location-20321",
      "type": "Feature",
      "properties": {
        "description": "1M scale point location",
        "location_precision": "precise",
        "title": "DARMC location 20321",
        "link": "http://pleiades.stoa.org/places/265921/darmc-location-20321"
      }
    }
  ]
}