{
  "type": "FeatureCollection",
  "title": "Malaca",
  "id": "265963",
  "description": "An ancient place, cited: BAtlas 27 A5 Malaca",
  "bbox": [
    -4.420163,
    36.719658,
    -4.420163,
    36.719658
  ],
  "reprPoint": [
    -4.420163,
    36.719658
  ],
  "names": [
    "Malaca"
  ],
  "features": [
    {
      "geometry": {
        "type": "Point",
        "coordinates": [
          -4.420163,
          36.719658
        ]
      },
      "id": "darmc-location-20463",
      "type": "Feature",
      "properties": {
        "description": "1M scale point location",
        "location_precision": "precise",
        "title": "DARMC location 20463",
        "link": "http://pleiades.stoa.org/places/265963/darmc-location-20463"
      }
    }
  ]
}