{
  "type": "FeatureCollection",
  "title": "Iliturgicola",
  "id": "265925",
  "description": "An ancient place, cited: BAtlas 27 A4 Iliturgicola",
  "bbox": [
    -4.148005,
    37.511643,
    -4.148005,
    37.511643
  ],
  "reprPoint": [
    -4.148005,
    37.511643
  ],
  "names": [
    "Iliturgicola"
  ],
  "features": [
    {
      "geometry": {
        "type": "Point",
        "coordinates": [
          -4.148005,
          37.511643
        ]
      },
      "id": "darmc-location-19781",
      "type": "Feature",
      "properties": {
        "description": "1M scale point location",
        "location_precision": "precise",
        "title": "DARMC location 19781",
        "link": "http://pleiades.stoa.org/places/265925/darmc-location-19781"
      }
    }
  ]
}