{
  "type": "FeatureCollection",
  "title": "Segisa?",
  "id": "266035",
  "description": "An ancient place, cited: BAtlas 27 D3 Segisa?",
  "bbox": [
    -1.418729,
    38.239102,
    -1.418729,
    38.239102
  ],
  "reprPoint": [
    -1.418729,
    38.239102
  ],
  "names": [
    "Segisa"
  ],
  "features": [
    {
      "geometry": {
        "type": "Point",
        "coordinates": [
          -1.418729,
          38.239102
        ]
      },
      "id": "darmc-location-3516",
      "type": "Feature",
      "properties": {
        "description": "1M scale point location",
        "location_precision": "precise",
        "title": "DARMC location 3516",
        "link": "http://pleiades.stoa.org/places/266035/darmc-location-3516"
      }
    }
  ]
}