{
  "type": "FeatureCollection",
  "title": "Vicus Cuminarius",
  "id": "266094",
  "description": "An ancient place, cited: BAtlas 27 B2 Vicus Cuminarius",
  "bbox": [
    -3.499679,
    39.960387,
    -3.499679,
    39.960387
  ],
  "reprPoint": [
    -3.499679,
    39.960387
  ],
  "names": [
    "Vicus Cuminarius"
  ],
  "features": [
    {
      "geometry": {
        "type": "Point",
        "coordinates": [
          -3.499679,
          39.960387
        ]
      },
      "id": "darmc-location-19895",
      "type": "Feature",
      "properties": {
        "description": "1M scale point location",
        "location_precision": "precise",
        "title": "DARMC location 19895",
        "link": "http://pleiades.stoa.org/places/266094/darmc-location-19895"
      }
    }
  ]
}