{
  "type": "FeatureCollection",
  "title": "Puente de la Olmilla",
  "id": "266009",
  "bbox": [
    -2.806268,
    38.618079,
    -2.806268,
    38.618079
  ],
  "description": "An ancient place, cited: BAtlas 27 C3 Puente de la Olmilla",
  "features": [
    {
      "type": "Feature",
      "geometry": {
        "type": "Point",
        "coordinates": [
          -2.806268,
          38.618079
        ]
      },
      "properties": {
        "description": "representative point"
      }
    },
    {
      "geometry": {
        "type": "Point",
        "coordinates": [
          -2.806268,
          38.618079
        ]
      },
      "id": "darmc-location-21047",
      "type": "Feature",
      "properties": {
        "description": "1M scale point location",
        "location_precision": "precise",
        "title": "DARMC location 21047",
        "link": "http://pleiades.stoa.org/places/266009/darmc-location-21047"
      }
    }
  ]
}