{
  "type": "FeatureCollection",
  "title": "Sebelaci",
  "id": "266034",
  "bbox": [
    -0.138097,
    39.959582,
    -0.138097,
    39.959582
  ],
  "description": "An ancient place, cited: BAtlas 27 E2 Sebelaci",
  "names": [
    "Sebelaci"
  ],
  "features": [
    {
      "type": "Feature",
      "geometry": {
        "type": "Point",
        "coordinates": [
          -0.138097,
          39.959582
        ]
      },
      "properties": {
        "description": "representative point"
      }
    },
    {
      "geometry": {
        "type": "Point",
        "coordinates": [
          -0.138097,
          39.959582
        ]
      },
      "id": "darmc-location-19870",
      "type": "Feature",
      "properties": {
        "description": "1M scale point location",
        "location_precision": "precise",
        "title": "DARMC location 19870",
        "link": "http://pleiades.stoa.org/places/266034/darmc-location-19870"
      }
    }
  ]
}