{
  "type": "FeatureCollection",
  "title": "El Ruedo",
  "id": "266015",
  "bbox": [
    -4.0896184,
    37.4430896,
    -4.0896184,
    37.4430896
  ],
  "description": "An ancient place, cited: BAtlas 27 A4 El Ruedo",
  "features": [
    {
      "type": "Feature",
      "geometry": {
        "type": "Point",
        "coordinates": [
          -4.0896184,
          37.4430896
        ]
      },
      "properties": {
        "description": "representative point"
      }
    },
    {
      "geometry": {
        "type": "Point",
        "coordinates": [
          -4.0896184,
          37.4430896
        ]
      },
      "id": "osm-location-of-villa-romana-el-ruedo",
      "type": "Feature",
      "properties": {
        "description": "Representative location based on OpenStreetMap.",
        "location_precision": "precise",
        "title": "OSM location of Villa Romana \"El Ruedo\"",
        "link": "http://pleiades.stoa.org/places/266015/osm-location-of-villa-romana-el-ruedo"
      }
    }
  ]
}