{
  "type": "FeatureCollection",
  "title": "Sierra de Gádor",
  "id": "266039",
  "description": "An ancient place, cited: BAtlas 27 C5 Sierra de Gádor",
  "bbox": [
    -2.762919,
    36.835734,
    -2.762919,
    36.835734
  ],
  "reprPoint": [
    -2.762919,
    36.835734
  ],
  "features": [
    {
      "geometry": {
        "type": "Point",
        "coordinates": [
          -2.762919,
          36.835734
        ]
      },
      "id": "darmc-location-19531",
      "type": "Feature",
      "properties": {
        "description": "1M scale point location",
        "location_precision": "precise",
        "title": "DARMC location 19531",
        "link": "http://pleiades.stoa.org/places/266039/darmc-location-19531"
      }
    }
  ]
}