{
  "type": "FeatureCollection",
  "title": "El Ruedo",
  "id": "266015",
  "description": "An ancient place, cited: BAtlas 27 A4 El Ruedo",
  "bbox": [
    -4.091237,
    37.439007,
    -4.090122,
    37.443024
  ],
  "reprPoint": [
    -4.0906795,
    37.4410155
  ],
  "features": [
    {
      "geometry": {
        "type": "Point",
        "coordinates": [
          -4.090122,
          37.443024
        ]
      },
      "id": "location-of-roman-villa",
      "type": "Feature",
      "properties": {
        "description": "Location based on OpenStreetMap",
        "location_precision": "precise",
        "title": "location of Roman villa",
        "link": "http://pleiades.stoa.org/places/266015/location-of-roman-villa"
      }
    }
  ]
}