{
  "type": "FeatureCollection",
  "title": "Puente del Obispo",
  "id": "266008",
  "description": "An ancient place, cited: BAtlas 27 B4 Puente del Obispo",
  "bbox": [
    -3.540398,
    37.95069,
    -3.540398,
    37.95069
  ],
  "reprPoint": [
    -3.540398,
    37.95069
  ],
  "features": [
    {
      "geometry": {
        "type": "Point",
        "coordinates": [
          -3.540398,
          37.95069
        ]
      },
      "id": "darmc-location-19422",
      "type": "Feature",
      "properties": {
        "description": "1M scale point location",
        "location_precision": "precise",
        "title": "DARMC location 19422",
        "link": "http://pleiades.stoa.org/places/266008/darmc-location-19422"
      }
    }
  ]
}