{
  "type": "FeatureCollection",
  "title": "Sierra Elvira",
  "id": "266040",
  "bbox": [
    -3.726138,
    37.228764,
    -3.726138,
    37.228764
  ],
  "description": "An ancient place, cited: BAtlas 27 B4 Sierra Elvira",
  "features": [
    {
      "type": "Feature",
      "geometry": {
        "type": "Point",
        "coordinates": [
          -3.726138,
          37.228764
        ]
      },
      "properties": {
        "description": "representative point"
      }
    },
    {
      "geometry": {
        "type": "Point",
        "coordinates": [
          -3.726138,
          37.228764
        ]
      },
      "id": "darmc-location-19530",
      "type": "Feature",
      "properties": {
        "description": "1M scale point location",
        "location_precision": "precise",
        "title": "DARMC location 19530",
        "link": "http://pleiades.stoa.org/places/266040/darmc-location-19530"
      }
    }
  ]
}