{
  "type": "FeatureCollection",
  "title": "El Ruedo",
  "id": "266015",
  "description": "An ancient place, cited: BAtlas 27 A4 El Ruedo",
  "bbox": [
    -4.091237,
    37.439007,
    -4.091237,
    37.439007
  ],
  "reprPoint": [
    -4.091237,
    37.439007
  ],
  "features": [
    {
      "geometry": {
        "type": "Point",
        "coordinates": [
          -4.091237,
          37.439007
        ]
      },
      "id": "darmc-location-20846",
      "type": "Feature",
      "properties": {
        "description": "1M scale point location",
        "location_precision": "precise",
        "title": "DARMC location 20846",
        "link": "http://pleiades.stoa.org/places/266015/darmc-location-20846"
      }
    }
  ]
}