{
  "type": "FeatureCollection",
  "title": "Urci?",
  "id": "266085",
  "description": "An ancient place, cited: BAtlas 27 C5 Urci?",
  "bbox": [
    -2.450598,
    36.913021,
    -2.450598,
    36.913021
  ],
  "reprPoint": [
    -2.450598,
    36.913021
  ],
  "names": [
    "Urci"
  ],
  "features": [
    {
      "geometry": {
        "type": "Point",
        "coordinates": [
          -2.450598,
          36.913021
        ]
      },
      "id": "darmc-location-313",
      "type": "Feature",
      "properties": {
        "description": "1M scale point location",
        "location_precision": "precise",
        "title": "DARMC location 313",
        "link": "http://pleiades.stoa.org/places/266085/darmc-location-313"
      }
    }
  ]
}