{
  "type": "FeatureCollection",
  "title": "Auchinhove camp",
  "id": "26901681",
  "description": "Temporary Roman camp of Flavian date",
  "bbox": [
    -2.898871,
    57.551961,
    -2.898871,
    57.551961
  ],
  "reprPoint": [
    -2.898871,
    57.551961
  ],
  "features": [
    {
      "geometry": {
        "type": "Point",
        "coordinates": [
          -2.898871,
          57.551961
        ]
      },
      "id": "centerpoint-of-the-camp-approx",
      "type": "Feature",
      "properties": {
        "description": "Centerpoint of camp as recorded by aerial observation and excavation.",
        "location_precision": "precise",
        "title": "Centerpoint of the camp (approx)",
        "link": "http://pleiades.stoa.org/places/26901681/centerpoint-of-the-camp-approx"
      }
    }
  ]
}