{
  "type": "FeatureCollection",
  "title": "Ain el Hammam",
  "id": "275583",
  "description": "An ancient place, cited: BAtlas 28 C2 Ain el Hammam",
  "bbox": [
    -5.924985,
    35.636653,
    -5.924985,
    35.636653
  ],
  "reprPoint": [
    -5.924985,
    35.636653
  ],
  "features": [
    {
      "geometry": {
        "type": "Point",
        "coordinates": [
          -5.924985,
          35.636653
        ]
      },
      "id": "darmc-location-23230",
      "type": "Feature",
      "properties": {
        "description": "Point location",
        "location_precision": "precise",
        "title": "DARMC location 23230",
        "link": "http://pleiades.stoa.org/places/275583/darmc-location-23230"
      }
    }
  ]
}