{
  "type": "FeatureCollection",
  "title": "Banasa",
  "id": "275599",
  "description": "Colonia Iulia Valentia Banasa was one of the three colonies founded by emperor Augustus between 33 and 25 BC in Mauretania Tingitana.",
  "bbox": [
    -6.115434,
    34.60192,
    -6.115434,
    34.60192
  ],
  "reprPoint": [
    -6.115434,
    34.60192
  ],
  "names": [
    "Banasa",
    "Col. Iulia Valentia Banasa",
    "Col. Iulia Valentia Banasa"
  ],
  "features": [
    {
      "geometry": {
        "type": "Point",
        "coordinates": [
          -6.115434,
          34.60192
        ]
      },
      "id": "dare-location",
      "type": "Feature",
      "properties": {
        "description": "Representative point location, site precision",
        "location_precision": "precise",
        "title": "DARE Location",
        "link": "http://pleiades.stoa.org/places/275599/dare-location"
      }
    },
    {
      "geometry": {
        "type": "Point",
        "coordinates": [
          -6.115264,
          34.601987
        ]
      },
      "id": "darmc-location-11648",
      "type": "Feature",
      "properties": {
        "description": "500K scale point location",
        "location_precision": "precise",
        "title": "DARMC location 11648",
        "link": "http://pleiades.stoa.org/places/275599/darmc-location-11648"
      }
    }
  ]
}