{
  "type": "FeatureCollection",
  "title": "Banasa",
  "id": "275599",
  "description": "An ancient place, cited: BAtlas 28 B4 Banasa",
  "bbox": [
    -6.115434,
    34.60192,
    -6.115264,
    34.601987
  ],
  "reprPoint": [
    -6.115349,
    34.6019535
  ],
  "names": [
    "Banasa",
    "Col. Iulia Valentia Banasa"
  ],
  "features": [
    {
      "geometry": {
        "type": "Point",
        "coordinates": [
          -6.115434,
          34.60192
        ]
      },
      "id": "dare-location",
      "type": "Feature",
      "properties": {
        "description": "Representative point location, site precision",
        "location_precision": "precise",
        "title": "DARE Location",
        "link": "http://pleiades.stoa.org/places/275599/dare-location"
      }
    },
    {
      "geometry": {
        "type": "Point",
        "coordinates": [
          -6.115264,
          34.601987
        ]
      },
      "id": "darmc-location-11648",
      "type": "Feature",
      "properties": {
        "description": "500K scale point location",
        "location_precision": "precise",
        "title": "DARMC location 11648",
        "link": "http://pleiades.stoa.org/places/275599/darmc-location-11648"
      }
    }
  ]
}