{
  "type": "FeatureCollection",
  "title": "Beni Said",
  "id": "275604",
  "bbox": [
    -5.829997,
    35.730002,
    -5.829997,
    35.730002
  ],
  "description": "An ancient place, cited: BAtlas 28 C2 Beni Said",
  "features": [
    {
      "type": "Feature",
      "geometry": {
        "type": "Point",
        "coordinates": [
          -5.829997,
          35.730002
        ]
      },
      "properties": {
        "description": "representative point"
      }
    },
    {
      "geometry": {
        "type": "Point",
        "coordinates": [
          -5.829997,
          35.730002
        ]
      },
      "id": "darmc-location-7348",
      "type": "Feature",
      "properties": {
        "description": "500K scale point location",
        "location_precision": "precise",
        "title": "DARMC location 7348",
        "link": "http://pleiades.stoa.org/places/275604/darmc-location-7348"
      }
    }
  ]
}