{
  "type": "FeatureCollection",
  "title": "Cottae?",
  "id": "275615",
  "description": "An ancient place, cited: BAtlas 28 C2 Cottae?",
  "bbox": [
    -5.93005,
    35.79,
    -5.93005,
    35.79
  ],
  "reprPoint": [
    -5.93005,
    35.79
  ],
  "names": [
    "Cottae",
    "Kotes",
    "Gytte"
  ],
  "features": [
    {
      "geometry": {
        "type": "Point",
        "coordinates": [
          -5.93005,
          35.79
        ]
      },
      "id": "darmc-location-12103",
      "type": "Feature",
      "properties": {
        "description": "500K scale point location",
        "location_precision": "precise",
        "title": "DARMC location 12103",
        "link": "http://pleiades.stoa.org/places/275615/darmc-location-12103"
      }
    }
  ]
}