{
  "type": "FeatureCollection",
  "title": "el Rhorba",
  "id": "275692",
  "bbox": [
    -5.758288,
    35.728292,
    -5.758288,
    35.728292
  ],
  "description": "An ancient place, cited: BAtlas 28 C2 el Rhorba",
  "features": [
    {
      "type": "Feature",
      "geometry": {
        "type": "Point",
        "coordinates": [
          -5.758288,
          35.728292
        ]
      },
      "properties": {
        "description": "representative point"
      }
    },
    {
      "geometry": {
        "type": "Point",
        "coordinates": [
          -5.758288,
          35.728292
        ]
      },
      "id": "darmc-location-8477",
      "type": "Feature",
      "properties": {
        "description": "500K scale point location",
        "location_precision": "precise",
        "title": "DARMC location 8477",
        "link": "http://pleiades.stoa.org/places/275692/darmc-location-8477"
      }
    }
  ]
}