{
  "type": "FeatureCollection",
  "title": "Mezgalef",
  "id": "275680",
  "bbox": [
    -6.09,
    35.289999,
    -6.09,
    35.289999
  ],
  "description": "An ancient place, cited: BAtlas 28 B3 Mezgalef",
  "features": [
    {
      "type": "Feature",
      "geometry": {
        "type": "Point",
        "coordinates": [
          -6.09,
          35.289999
        ]
      },
      "properties": {
        "description": "representative point"
      }
    },
    {
      "geometry": {
        "type": "Point",
        "coordinates": [
          -6.09,
          35.289999
        ]
      },
      "id": "darmc-location-17528",
      "type": "Feature",
      "properties": {
        "description": "500K scale point location",
        "location_precision": "precise",
        "title": "DARMC location 17528",
        "link": "http://pleiades.stoa.org/places/275680/darmc-location-17528"
      }
    }
  ]
}