{
  "type": "FeatureCollection",
  "title": "MM18",
  "id": "275681",
  "description": "An ancient place, cited: BAtlas 28 B4 MM18",
  "bbox": [
    -6.127611,
    34.799334,
    -6.127611,
    34.799334
  ],
  "reprPoint": [
    -6.127611,
    34.799334
  ],
  "features": [
    {
      "geometry": {
        "type": "Point",
        "coordinates": [
          -6.127611,
          34.799334
        ]
      },
      "id": "darmc-location-23566",
      "type": "Feature",
      "properties": {
        "description": "500K scale point location",
        "location_precision": "precise",
        "title": "DARMC location 23566",
        "link": "http://pleiades.stoa.org/places/275681/darmc-location-23566"
      }
    }
  ]
}