{
  "type": "FeatureCollection",
  "title": "Krimda",
  "id": "275658",
  "description": "An ancient place, cited: BAtlas 28 B3 Krimda",
  "bbox": [
    -6.07,
    35.27,
    -6.07,
    35.27
  ],
  "reprPoint": [
    -6.07,
    35.27
  ],
  "features": [
    {
      "geometry": {
        "type": "Point",
        "coordinates": [
          -6.07,
          35.27
        ]
      },
      "id": "darmc-location-17703",
      "type": "Feature",
      "properties": {
        "description": "500K scale point location",
        "location_precision": "precise",
        "title": "DARMC location 17703",
        "link": "http://pleiades.stoa.org/places/275658/darmc-location-17703"
      }
    }
  ]
}