{
  "type": "FeatureCollection",
  "title": "Khedis",
  "id": "275651",
  "description": "An ancient place, cited: BAtlas 28 A6 Khedis",
  "bbox": [
    -6.763371,
    33.9894,
    -6.763371,
    33.9894
  ],
  "reprPoint": [
    -6.763371,
    33.9894
  ],
  "features": [
    {
      "geometry": {
        "type": "Point",
        "coordinates": [
          -6.763371,
          33.9894
        ]
      },
      "id": "darmc-location-13152",
      "type": "Feature",
      "properties": {
        "description": "500K scale point location",
        "location_precision": "precise",
        "title": "DARMC location 13152",
        "link": "http://pleiades.stoa.org/places/275651/darmc-location-13152"
      }
    }
  ]
}