{
  "type": "FeatureCollection",
  "title": "Gandori",
  "id": "275634",
  "description": "An ancient place, cited: BAtlas 28 C2 Gandori",
  "bbox": [
    -5.768108,
    35.774585,
    -5.768108,
    35.774585
  ],
  "reprPoint": [
    -5.768108,
    35.774585
  ],
  "features": [
    {
      "geometry": {
        "type": "Point",
        "coordinates": [
          -5.768108,
          35.774585
        ]
      },
      "id": "darmc-location-7768",
      "type": "Feature",
      "properties": {
        "description": "500K scale point location",
        "location_precision": "precise",
        "title": "DARMC location 7768",
        "link": "http://pleiades.stoa.org/places/275634/darmc-location-7768"
      }
    }
  ]
}