{
  "type": "FeatureCollection",
  "title": "Gadadra",
  "id": "275632",
  "description": "An ancient place, cited: BAtlas 28 B4 Gadadra",
  "bbox": [
    -6.133148,
    34.499464,
    -6.133148,
    34.499464
  ],
  "reprPoint": [
    -6.133148,
    34.499464
  ],
  "features": [
    {
      "geometry": {
        "type": "Point",
        "coordinates": [
          -6.133148,
          34.499464
        ]
      },
      "id": "darmc-location-17430",
      "type": "Feature",
      "properties": {
        "description": "500K scale point location",
        "location_precision": "precise",
        "title": "DARMC location 17430",
        "link": "http://pleiades.stoa.org/places/275632/darmc-location-17430"
      }
    }
  ]
}