{
  "type": "FeatureCollection",
  "title": "Bou Rebaa",
  "id": "275607",
  "description": "An ancient place, cited: BAtlas 28 C5 Bou Rebaa",
  "bbox": [
    -5.754021,
    34.059561,
    -5.754021,
    34.059561
  ],
  "reprPoint": [
    -5.754021,
    34.059561
  ],
  "features": [
    {
      "geometry": {
        "type": "Point",
        "coordinates": [
          -5.754021,
          34.059561
        ]
      },
      "id": "darmc-location-7462",
      "type": "Feature",
      "properties": {
        "description": "500K scale point location",
        "location_precision": "precise",
        "title": "DARMC location 7462",
        "link": "http://pleiades.stoa.org/places/275607/darmc-location-7462"
      }
    }
  ]
}