{
  "type": "FeatureCollection",
  "title": "Koudia Fergana",
  "id": "275657",
  "description": "An ancient place, cited: BAtlas 28 C4 Koudia Fergana",
  "bbox": [
    -5.937707,
    34.843173,
    -5.937707,
    34.843173
  ],
  "reprPoint": [
    -5.937707,
    34.843173
  ],
  "features": [
    {
      "geometry": {
        "type": "Point",
        "coordinates": [
          -5.937707,
          34.843173
        ]
      },
      "id": "darmc-location-7133",
      "type": "Feature",
      "properties": {
        "description": "500K scale point location",
        "location_precision": "precise",
        "title": "DARMC location 7133",
        "link": "http://pleiades.stoa.org/places/275657/darmc-location-7133"
      }
    }
  ]
}