{
  "type": "FeatureCollection",
  "title": "Sidi el Mekki",
  "id": "275712",
  "bbox": [
    -5.955336,
    34.14842,
    -5.955336,
    34.14842
  ],
  "description": "South of the marabout of Sidi el Mekki on the upper Beht river in modern Morocco, archaeological survey in the late 20th century identified pottery remains consistent with a small rural establishment of the Roman imperial era.",
  "features": [
    {
      "type": "Feature",
      "geometry": {
        "type": "Point",
        "coordinates": [
          -5.955336,
          34.14842
        ]
      },
      "properties": {
        "description": "representative point"
      }
    },
    {
      "geometry": {
        "type": "Point",
        "coordinates": [
          -5.955336,
          34.14842
        ]
      },
      "id": "akerraz-1995-location-of-qn26-sidi-el-mekki-sud",
      "type": "Feature",
      "properties": {
        "description": null,
        "location_precision": "precise",
        "title": "Akerraz 1995 location of QN26 Sidi el Mekki sud",
        "link": "http://pleiades.stoa.org/places/275712/akerraz-1995-location-of-qn26-sidi-el-mekki-sud"
      }
    }
  ]
}