{
  "type": "FeatureCollection",
  "title": "Volubilis",
  "id": "275740",
  "bbox": [
    -5.5548,
    34.0725,
    -5.5548,
    34.0725
  ],
  "description": "A town of Mauretania Tingitana and a Roman colony.",
  "connectsWith": [
    "275673"
  ],
  "names": [
    "Volubilis",
    "Volubilitani",
    "Ouoloubilianoi"
  ],
  "features": [
    {
      "type": "Feature",
      "geometry": {
        "type": "Point",
        "coordinates": [
          -5.5548,
          34.0725
        ]
      },
      "properties": {
        "description": "representative point"
      }
    },
    {
      "geometry": {
        "type": "Point",
        "coordinates": [
          -5.5548,
          34.0725
        ]
      },
      "id": "center-point-of-visible-remains-volubilis",
      "type": "Feature",
      "properties": {
        "description": "coordinates after GeoHack.",
        "location_precision": "precise",
        "title": "Center point of visible remains",
        "link": "http://pleiades.stoa.org/places/275740/center-point-of-visible-remains-volubilis"
      }
    }
  ]
}