{
  "type": "FeatureCollection",
  "title": "Sidi Mbark",
  "id": "275718",
  "description": "An ancient place, cited: BAtlas 28 B5 Sidi Mbark",
  "bbox": [
    -6.375247,
    34.474925,
    -6.375247,
    34.474925
  ],
  "reprPoint": [
    -6.375247,
    34.474925
  ],
  "features": [
    {
      "geometry": {
        "type": "Point",
        "coordinates": [
          -6.375247,
          34.474925
        ]
      },
      "id": "darmc-location-14724",
      "type": "Feature",
      "properties": {
        "description": "500K scale point location",
        "location_precision": "precise",
        "title": "DARMC location 14724",
        "link": "http://pleiades.stoa.org/places/275718/darmc-location-14724"
      }
    }
  ]
}