{
  "type": "FeatureCollection",
  "title": "Volubilis",
  "id": "275740",
  "description": "A town of Mauretania Tingitana and a Roman colony",
  "bbox": [
    -5.5548,
    34.0725,
    -5.5548,
    34.0725
  ],
  "reprPoint": [
    -5.5548,
    34.0725
  ],
  "names": [
    "Volubilis",
    "Volubilitani",
    "Ouoloubilianoi"
  ],
  "features": [
    {
      "geometry": {
        "type": "Point",
        "coordinates": [
          -5.5548,
          34.0725
        ]
      },
      "id": "center-point-of-visible-remains-volubilis",
      "type": "Feature",
      "properties": {
        "description": null,
        "location_precision": "precise",
        "title": "center point of visible remains - Volubilis",
        "link": "http://pleiades.stoa.org/places/275740/center-point-of-visible-remains-volubilis"
      }
    }
  ]
}