{
  "type": "FeatureCollection",
  "title": "Tamuda (river)",
  "id": "275733",
  "description": "An ancient place, cited: BAtlas 28 D2 Tamuda fl.",
  "bbox": [
    -5.4101103,
    35.5623508,
    -5.4101103,
    35.5623508
  ],
  "reprPoint": [
    -5.4101103,
    35.5623508
  ],
  "names": [
    "Tamuda",
    "Tumuada"
  ],
  "features": [
    {
      "geometry": {
        "type": "Point",
        "coordinates": [
          -5.4101103,
          35.5623508
        ]
      },
      "id": "location-of-Tamuda-fl",
      "type": "Feature",
      "properties": {
        "description": "Location based on OpenStreetMap",
        "location_precision": "precise",
        "title": "location of Oud Martil (river)",
        "link": "http://pleiades.stoa.org/places/275733/location-of-Tamuda-fl"
      }
    }
  ]
}