{
  "type": "FeatureCollection",
  "title": "Sidi Mohammed ben Naseur",
  "id": "275719",
  "bbox": [
    -5.997415,
    34.308691,
    -5.997415,
    34.308691
  ],
  "description": "An ancient place, cited: BAtlas 28 B5 Sidi Mohammed ben Naseur",
  "features": [
    {
      "type": "Feature",
      "geometry": {
        "type": "Point",
        "coordinates": [
          -5.997415,
          34.308691
        ]
      },
      "properties": {
        "description": "representative point"
      }
    },
    {
      "geometry": {
        "type": "Point",
        "coordinates": [
          -5.997415,
          34.308691
        ]
      },
      "id": "darmc-location-17596",
      "type": "Feature",
      "properties": {
        "description": "500K scale point location",
        "location_precision": "precise",
        "title": "DARMC location 17596",
        "link": "http://pleiades.stoa.org/places/275719/darmc-location-17596"
      }
    }
  ]
}