{
  "type": "FeatureCollection",
  "title": "Sidi Moussa",
  "id": "275720",
  "description": "An ancient place, cited: BAtlas 28 C5 Sidi Moussa",
  "bbox": [
    -5.723152,
    34.052133,
    -5.723152,
    34.052133
  ],
  "reprPoint": [
    -5.723152,
    34.052133
  ],
  "features": [
    {
      "geometry": {
        "type": "Point",
        "coordinates": [
          -5.723152,
          34.052133
        ]
      },
      "id": "darmc-location-14727",
      "type": "Feature",
      "properties": {
        "description": "500K scale point location",
        "location_precision": "precise",
        "title": "DARMC location 14727",
        "link": "http://pleiades.stoa.org/places/275720/darmc-location-14727"
      }
    }
  ]
}