{
  "type": "FeatureCollection",
  "title": "Untitled",
  "id": "277846",
  "description": "An ancient place, cited: BAtlas 28 D2 unnamed feature (rural settlement E Tamuda)",
  "bbox": [
    -5.390233,
    35.555497,
    -5.390233,
    35.555497
  ],
  "reprPoint": [
    -5.390233,
    35.555497
  ],
  "features": [
    {
      "geometry": {
        "type": "Point",
        "coordinates": [
          -5.390233,
          35.555497
        ]
      },
      "id": "darmc-location-27119",
      "type": "Feature",
      "properties": {
        "description": "500K scale point location",
        "location_precision": "precise",
        "title": "DARMC location 27119",
        "link": "http://pleiades.stoa.org/places/277846/darmc-location-27119"
      }
    }
  ]
}