{
  "type": "FeatureCollection",
  "title": "Akropolis of Klazomenai",
  "id": "278163592",
  "bbox": [
    26.7678498,
    38.358374,
    26.7678498,
    38.358374
  ],
  "description": "The Akropolis of Klazomenai",
  "connectsWith": [
    "550650"
  ],
  "features": [
    {
      "type": "Feature",
      "geometry": {
        "type": "Point",
        "coordinates": [
          26.7678498,
          38.358374
        ]
      },
      "properties": {
        "description": "representative point"
      }
    },
    {
      "geometry": {
        "type": "Point",
        "coordinates": [
          26.7678498,
          38.358374
        ]
      },
      "id": "osm-location-of-klazomenai-akropolis",
      "type": "Feature",
      "properties": {
        "description": "Representative location based on OpenStreetMap",
        "location_precision": "precise",
        "title": "OSM location of Klazomenai Akropolis",
        "link": "http://pleiades.stoa.org/places/278163592/osm-location-of-klazomenai-akropolis"
      }
    }
  ]
}