{
  "type": "FeatureCollection",
  "title": "Ain Bénia",
  "id": "285397",
  "description": "An ancient place, cited: BAtlas 29 G1 Ain Bénia",
  "bbox": [
    1.693235,
    35.103058,
    1.693235,
    35.103058
  ],
  "reprPoint": [
    1.693235,
    35.103058
  ],
  "features": [
    {
      "geometry": {
        "type": "Point",
        "coordinates": [
          1.693235,
          35.103058
        ]
      },
      "id": "darmc-location-17353",
      "type": "Feature",
      "properties": {
        "description": "1M scale point location",
        "location_precision": "precise",
        "title": "DARMC location 17353",
        "link": "http://pleiades.stoa.org/places/285397/darmc-location-17353"
      }
    }
  ]
}