{
  "type": "FeatureCollection",
  "title": "Agueneb",
  "id": "285395",
  "description": "An ancient place, cited: BAtlas 29 G3 Agueneb",
  "bbox": [
    1.369109,
    33.907941,
    1.369109,
    33.907941
  ],
  "reprPoint": [
    1.369109,
    33.907941
  ],
  "features": [
    {
      "geometry": {
        "type": "Point",
        "coordinates": [
          1.369109,
          33.907941
        ]
      },
      "id": "darmc-location-15696",
      "type": "Feature",
      "properties": {
        "description": "1M scale point location",
        "location_precision": "precise",
        "title": "DARMC location 15696",
        "link": "http://pleiades.stoa.org/places/285395/darmc-location-15696"
      }
    }
  ]
}