{
  "type": "FeatureCollection",
  "title": "Koudiat Sidi ben Beha",
  "id": "285471",
  "description": "An ancient place, cited: BAtlas 29 G1 Koudiat Sidi ben Beha",
  "bbox": [
    1.298818,
    35.07079,
    1.298818,
    35.07079
  ],
  "reprPoint": [
    1.298818,
    35.07079
  ],
  "features": [
    {
      "geometry": {
        "type": "Point",
        "coordinates": [
          1.298818,
          35.07079
        ]
      },
      "id": "darmc-location-7135",
      "type": "Feature",
      "properties": {
        "description": "1M scale point location",
        "location_precision": "precise",
        "title": "DARMC location 7135",
        "link": "http://pleiades.stoa.org/places/285471/darmc-location-7135"
      }
    }
  ]
}