{
  "type": "FeatureCollection",
  "title": "Cen(..)?",
  "id": "285426",
  "description": "An ancient place, cited: BAtlas 29 G2 Cen(..)?",
  "bbox": [
    1.099985,
    35.01676,
    1.099985,
    35.01676
  ],
  "reprPoint": [
    1.099985,
    35.01676
  ],
  "names": [
    "Cen..",
    "Cen"
  ],
  "features": [
    {
      "geometry": {
        "type": "Point",
        "coordinates": [
          1.099985,
          35.01676
        ]
      },
      "id": "darmc-location-7553",
      "type": "Feature",
      "properties": {
        "description": "1M scale point location",
        "location_precision": "precise",
        "title": "DARMC location 7553",
        "link": "http://pleiades.stoa.org/places/285426/darmc-location-7553"
      }
    }
  ]
}