{
  "type": "FeatureCollection",
  "title": "Gadaum Castra",
  "id": "285444",
  "description": "An ancient place, cited: BAtlas 29 F1 Gadaum Castra",
  "bbox": [
    0.824593,
    35.929412,
    0.824593,
    35.929412
  ],
  "reprPoint": [
    0.824593,
    35.929412
  ],
  "names": [
    "Gadaum Castra"
  ],
  "features": [
    {
      "geometry": {
        "type": "Point",
        "coordinates": [
          0.824593,
          35.929412
        ]
      },
      "id": "darmc-location-12468",
      "type": "Feature",
      "properties": {
        "description": "1M scale point location",
        "location_precision": "precise",
        "title": "DARMC location 12468",
        "link": "http://pleiades.stoa.org/places/285444/darmc-location-12468"
      }
    }
  ]
}