{
  "type": "FeatureCollection",
  "title": "Kerkab",
  "id": "285458",
  "description": "An ancient place, cited: BAtlas 29 F2 Kerkab",
  "bbox": [
    0.214719,
    34.988179,
    0.214719,
    34.988179
  ],
  "reprPoint": [
    0.214719,
    34.988179
  ],
  "features": [
    {
      "geometry": {
        "type": "Point",
        "coordinates": [
          0.214719,
          34.988179
        ]
      },
      "id": "darmc-location-13116",
      "type": "Feature",
      "properties": {
        "description": "1M scale point location",
        "location_precision": "precise",
        "title": "DARMC location 13116",
        "link": "http://pleiades.stoa.org/places/285458/darmc-location-13116"
      }
    }
  ]
}