{
  "type": "FeatureCollection",
  "title": "Altava",
  "id": "285413",
  "description": "An ancient place, cited: BAtlas 29 D2 Altava",
  "bbox": [
    -1.031484,
    34.903623,
    -1.031484,
    34.903623
  ],
  "reprPoint": [
    -1.031484,
    34.903623
  ],
  "names": [
    "Altava"
  ],
  "features": [
    {
      "geometry": {
        "type": "Point",
        "coordinates": [
          -1.031484,
          34.903623
        ]
      },
      "id": "darmc-location-11328",
      "type": "Feature",
      "properties": {
        "description": "1M scale point location",
        "location_precision": "precise",
        "title": "DARMC location 11328",
        "link": "http://pleiades.stoa.org/places/285413/darmc-location-11328"
      }
    }
  ]
}