{
  "type": "FeatureCollection",
  "title": "Ste-Barbe-du-Tlélat",
  "id": "285514",
  "description": "An ancient place, cited: BAtlas 29 E1 Ste-Barbe-du-Tlélat",
  "bbox": [
    -0.447241,
    35.548873,
    -0.447241,
    35.548873
  ],
  "reprPoint": [
    -0.447241,
    35.548873
  ],
  "features": [
    {
      "geometry": {
        "type": "Point",
        "coordinates": [
          -0.447241,
          35.548873
        ]
      },
      "id": "darmc-location-26220",
      "type": "Feature",
      "properties": {
        "description": "1M scale point location",
        "location_precision": "precise",
        "title": "DARMC location 26220",
        "link": "http://pleiades.stoa.org/places/285514/darmc-location-26220"
      }
    }
  ]
}