{
  "type": "FeatureCollection",
  "title": "Tres Inss.",
  "id": "285540",
  "description": "An ancient place, cited: BAtlas 29 C1 Tres Inss.",
  "bbox": [
    -2.4385015,
    35.1760726,
    -2.4225804,
    35.184363
  ],
  "reprPoint": [
    -2.42942003333,
    35.1806575667
  ],
  "names": [
    "Tres"
  ],
  "features": [
    {
      "geometry": {
        "type": "Point",
        "coordinates": [
          -2.4271782,
          35.1815371
        ]
      },
      "id": "isla-isabel-ii",
      "type": "Feature",
      "properties": {
        "description": "Location based on OpenStreetMap",
        "location_precision": "precise",
        "title": "Isla Isabel II",
        "link": "http://pleiades.stoa.org/places/285540/isla-isabel-ii"
      }
    },
    {
      "geometry": {
        "type": "Point",
        "coordinates": [
          -2.4225804,
          35.184363
        ]
      },
      "id": "isla-del-rey",
      "type": "Feature",
      "properties": {
        "description": "Location based on OpenStreetMap",
        "location_precision": "precise",
        "title": "Isla del Rey",
        "link": "http://pleiades.stoa.org/places/285540/isla-del-rey"
      }
    },
    {
      "geometry": {
        "type": "Point",
        "coordinates": [
          -2.4385015,
          35.1760726
        ]
      },
      "id": "isla-del-congreso",
      "type": "Feature",
      "properties": {
        "description": "Location based on OpenStreetMap",
        "location_precision": "precise",
        "title": "Isla del Congreso",
        "link": "http://pleiades.stoa.org/places/285540/isla-del-congreso"
      }
    }
  ]
}