{
  "type": "FeatureCollection",
  "title": "Nazzano Romano",
  "id": "288445158",
  "description": "Nazzano Romano was the site of an Etruscan settlement covering some 7 hectares and dating between the eighth and fifth centuries B.C.",
  "bbox": [
    12.5976389,
    42.229257,
    12.5976389,
    42.229257
  ],
  "reprPoint": [
    12.5976389,
    42.229257
  ],
  "features": [
    {
      "geometry": {
        "type": "Point",
        "coordinates": [
          12.5976389,
          42.229257
        ]
      },
      "id": "location-of-nazzano-romano",
      "type": "Feature",
      "properties": {
        "description": "Representative point derived from an OpenStreetMap node.",
        "location_precision": "precise",
        "title": "OSM location of Nazzano",
        "link": "http://pleiades.stoa.org/places/288445158/location-of-nazzano-romano"
      }
    }
  ]
}