{
  "type": "FeatureCollection",
  "title": "Upper Agora",
  "id": "290042871",
  "bbox": [
    30.5176234,
    37.6773148,
    30.5176234,
    37.6773148
  ],
  "description": "The Upper Agora at Sagalassos is in use from the Hellenistic period onward.",
  "connectsWith": [
    "639087"
  ],
  "features": [
    {
      "type": "Feature",
      "geometry": {
        "type": "Point",
        "coordinates": [
          30.5176234,
          37.6773148
        ]
      },
      "properties": {
        "description": "representative point"
      }
    },
    {
      "geometry": {
        "type": "Point",
        "coordinates": [
          30.5176234,
          37.6773148
        ]
      },
      "id": "osm-location-of-upper-agora",
      "type": "Feature",
      "properties": {
        "description": "Location based on OpenStreetMap",
        "location_precision": "precise",
        "title": "OSM location of Upper Agora",
        "link": "http://pleiades.stoa.org/places/290042871/osm-location-of-upper-agora"
      }
    }
  ]
}