{
  "type": "FeatureCollection",
  "title": "Pian di Civita, Tarquinii",
  "id": "292680658",
  "bbox": [
    11.795556,
    42.262778,
    11.795556,
    42.262778
  ],
  "description": "The Pian di Civita was the ancient urban area of Tarquinia.",
  "connectsWith": [
    "413332"
  ],
  "names": [
    "Pian di Civita"
  ],
  "features": [
    {
      "type": "Feature",
      "geometry": {
        "type": "Point",
        "coordinates": [
          11.795556,
          42.262778
        ]
      },
      "properties": {
        "description": "representative point"
      }
    },
    {
      "geometry": {
        "type": "Point",
        "coordinates": [
          11.795556,
          42.262778
        ]
      },
      "id": "centerpoint-of-the-pian-di-civita",
      "type": "Feature",
      "properties": {
        "description": "the ancient urban area of Tarquinia; verified in Google Earth 2013.",
        "location_precision": "precise",
        "title": "centerpoint of the Pian di Civita",
        "link": "http://pleiades.stoa.org/places/292680658/centerpoint-of-the-pian-di-civita"
      }
    }
  ]
}