{
  "type": "FeatureCollection",
  "title": "Broglio di Trebisacce",
  "id": "294527345",
  "bbox": [
    16.5032732,
    39.8644864,
    16.5032732,
    39.8644864
  ],
  "description": "Broglio di Trebisacce is the site of a protohistoric settlement located on the plain of Sibari not far from the Calabrian coast. Discovered in 1978, the site was excavsed by Renato Peroni from 1979 to 1985.",
  "features": [
    {
      "type": "Feature",
      "geometry": {
        "type": "Point",
        "coordinates": [
          16.5032732,
          39.8644864
        ]
      },
      "properties": {
        "description": "representative point"
      }
    },
    {
      "geometry": {
        "type": "Point",
        "coordinates": [
          16.5032732,
          39.8644864
        ]
      },
      "id": "osm-location-of-broglio-di-trebisacce",
      "type": "Feature",
      "properties": {
        "description": "Representative location based on OpenStreetMap",
        "location_precision": "precise",
        "title": "OSM location of Broglio di Trebisacce",
        "link": "http://pleiades.stoa.org/places/294527345/osm-location-of-broglio-di-trebisacce"
      }
    }
  ]
}