{
  "type": "FeatureCollection",
  "title": "Alexandria",
  "id": "29457",
  "description": "An ancient place, cited: BAtlas 3 H3 Alexandria",
  "bbox": [
    61.837118,
    34.309952,
    62.191888,
    37.616639
  ],
  "reprPoint": [
    62.0461946,
    35.6398832
  ],
  "names": [
    "Alexandria"
  ],
  "features": [
    {
      "geometry": {
        "type": "Point",
        "coordinates": [
          62.18842,
          34.345849
        ]
      },
      "id": "darmc-location-21198",
      "type": "Feature",
      "properties": {
        "description": "Point location",
        "location_precision": "precise",
        "title": "DARMC location 21198",
        "link": "http://pleiades.stoa.org/places/29457/darmc-location-21198"
      }
    },
    {
      "geometry": {
        "type": "Point",
        "coordinates": [
          62.191888,
          34.33733
        ]
      },
      "id": "darmc-location-7513",
      "type": "Feature",
      "properties": {
        "description": "5M scale point location",
        "location_precision": "precise",
        "title": "DARMC location 7513",
        "link": "http://pleiades.stoa.org/places/29457/darmc-location-7513"
      }
    },
    {
      "geometry": {
        "type": "Point",
        "coordinates": [
          62.112006,
          34.309952
        ]
      },
      "id": "darmc-location-7514",
      "type": "Feature",
      "properties": {
        "description": "5M scale point location",
        "location_precision": "precise",
        "title": "DARMC location 7514",
        "link": "http://pleiades.stoa.org/places/29457/darmc-location-7514"
      }
    },
    {
      "geometry": {
        "type": "Point",
        "coordinates": [
          61.901541,
          37.616639
        ]
      },
      "id": "darmc-location-7572",
      "type": "Feature",
      "properties": {
        "description": "5M scale point location",
        "location_precision": "precise",
        "title": "DARMC location 7572",
        "link": "http://pleiades.stoa.org/places/29457/darmc-location-7572"
      }
    },
    {
      "geometry": {
        "type": "Point",
        "coordinates": [
          61.837118,
          37.589646
        ]
      },
      "id": "darmc-location-7573",
      "type": "Feature",
      "properties": {
        "description": "5M scale point location",
        "location_precision": "precise",
        "title": "DARMC location 7573",
        "link": "http://pleiades.stoa.org/places/29457/darmc-location-7573"
      }
    }
  ]
}