{
  "type": "FeatureCollection",
  "title": "Douar Mazouna",
  "id": "295257",
  "description": "An ancient place, cited: BAtlas 30 inset Douar Mazouna",
  "bbox": [
    0.894896,
    36.125289,
    0.894896,
    36.125289
  ],
  "reprPoint": [
    0.894896,
    36.125289
  ],
  "features": [
    {
      "geometry": {
        "type": "Point",
        "coordinates": [
          0.894896,
          36.125289
        ]
      },
      "id": "darmc-location-22248",
      "type": "Feature",
      "properties": {
        "description": "500K scale point location",
        "location_precision": "precise",
        "title": "DARMC location 22248",
        "link": "http://pleiades.stoa.org/places/295257/darmc-location-22248"
      }
    }
  ]
}