{
  "type": "FeatureCollection",
  "title": "Irbir",
  "id": "295281",
  "description": "An ancient place, cited: BAtlas 30 H3 Irbir",
  "bbox": [
    4.188315,
    36.541001,
    4.188315,
    36.541001
  ],
  "reprPoint": [
    4.188315,
    36.541001
  ],
  "features": [
    {
      "geometry": {
        "type": "Point",
        "coordinates": [
          4.188315,
          36.541001
        ]
      },
      "id": "darmc-location-12886",
      "type": "Feature",
      "properties": {
        "description": "500K scale point location",
        "location_precision": "precise",
        "title": "DARMC location 12886",
        "link": "http://pleiades.stoa.org/places/295281/darmc-location-12886"
      }
    }
  ]
}