{
  "type": "FeatureCollection",
  "title": "Castellum Elephantaria?",
  "id": "295244",
  "description": "An ancient place, cited: BAtlas 30 E4 Castellum Elephantaria?",
  "bbox": [
    2.689575,
    36.466553,
    2.689575,
    36.466553
  ],
  "reprPoint": [
    2.689575,
    36.466553
  ],
  "names": [
    "Castellum Elephantaria"
  ],
  "features": [
    {
      "geometry": {
        "type": "Point",
        "coordinates": [
          2.689575,
          36.466553
        ]
      },
      "id": "darmc-location-21921",
      "type": "Feature",
      "properties": {
        "description": "500K scale point location",
        "location_precision": "precise",
        "title": "DARMC location 21921",
        "link": "http://pleiades.stoa.org/places/295244/darmc-location-21921"
      }
    }
  ]
}