{
  "type": "FeatureCollection",
  "title": "Cartenna",
  "id": "295240",
  "bbox": [
    1.308828,
    36.50978,
    1.3131,
    36.510308
  ],
  "description": "An ancient place, cited: BAtlas 30 B3 Cartenna",
  "names": [
    "Cartenna"
  ],
  "features": [
    {
      "type": "Feature",
      "geometry": {
        "type": "Point",
        "coordinates": [
          1.310964,
          36.510044
        ]
      },
      "properties": {
        "description": "representative point"
      }
    },
    {
      "geometry": {
        "type": "Point",
        "coordinates": [
          1.3131,
          36.510308
        ]
      },
      "id": "darmc-location-11913",
      "type": "Feature",
      "properties": {
        "description": "500K scale point location",
        "location_precision": "precise",
        "title": "DARMC location 11913",
        "link": "http://pleiades.stoa.org/places/295240/darmc-location-11913"
      }
    },
    {
      "geometry": {
        "type": "Point",
        "coordinates": [
          1.308828,
          36.50978
        ]
      },
      "id": "dare-location",
      "type": "Feature",
      "properties": {
        "description": "Representative point location, village precision",
        "location_precision": "precise",
        "title": "DARE Location",
        "link": "http://pleiades.stoa.org/places/295240/dare-location"
      }
    }
  ]
}