{
  "type": "FeatureCollection",
  "title": "Akbou des Ait bou Mahdi",
  "id": "295213",
  "description": "An ancient place, cited: BAtlas 30 H3 Akbou des Ait bou Mahdi",
  "bbox": [
    4.181324,
    36.531134,
    4.181324,
    36.531134
  ],
  "reprPoint": [
    4.181324,
    36.531134
  ],
  "features": [
    {
      "geometry": {
        "type": "Point",
        "coordinates": [
          4.181324,
          36.531134
        ]
      },
      "id": "darmc-location-15849",
      "type": "Feature",
      "properties": {
        "description": "500K scale point location",
        "location_precision": "precise",
        "title": "DARMC location 15849",
        "link": "http://pleiades.stoa.org/places/295213/darmc-location-15849"
      }
    }
  ]
}