{
  "type": "FeatureCollection",
  "title": "Castellum Elephantaria?",
  "id": "295244",
  "bbox": [
    2.6879953,
    36.4674416,
    2.6879953,
    36.4674416
  ],
  "description": "An ancient place, cited: BAtlas 30 E4 Castellum Elephantaria?",
  "names": [
    "Castellum Elephantaria"
  ],
  "features": [
    {
      "type": "Feature",
      "geometry": {
        "type": "Point",
        "coordinates": [
          2.6879953,
          36.4674416
        ]
      },
      "properties": {
        "description": "representative point"
      }
    },
    {
      "geometry": {
        "type": "Point",
        "coordinates": [
          2.6879953,
          36.4674416
        ]
      },
      "id": "osm-location-of-mouzaia",
      "type": "Feature",
      "properties": {
        "description": "Location based on OpenStreetMap",
        "location_precision": "precise",
        "title": "OSM location of Mouzaia",
        "link": "http://pleiades.stoa.org/places/295244/osm-location-of-mouzaia"
      }
    }
  ]
}