{
  "type": "FeatureCollection",
  "title": "Dar Mendil",
  "id": "295255",
  "bbox": [
    3.688616,
    36.835369,
    3.688616,
    36.835369
  ],
  "description": "An ancient place, cited: BAtlas 30 G3 Dar Mendil",
  "features": [
    {
      "type": "Feature",
      "geometry": {
        "type": "Point",
        "coordinates": [
          3.688616,
          36.835369
        ]
      },
      "properties": {
        "description": "representative point"
      }
    },
    {
      "geometry": {
        "type": "Point",
        "coordinates": [
          3.688616,
          36.835369
        ]
      },
      "id": "darmc-location-12152",
      "type": "Feature",
      "properties": {
        "description": "500K scale point location",
        "location_precision": "precise",
        "title": "DARMC location 12152",
        "link": "http://pleiades.stoa.org/places/295255/darmc-location-12152"
      }
    }
  ]
}