{
  "type": "FeatureCollection",
  "title": "Castellum Tulei",
  "id": "295246",
  "bbox": [
    3.792489,
    36.76875,
    3.792489,
    36.76875
  ],
  "description": "An ancient place, cited: BAtlas 30 G3 Castellum Tulei",
  "names": [
    "Castellum Tulei"
  ],
  "features": [
    {
      "type": "Feature",
      "geometry": {
        "type": "Point",
        "coordinates": [
          3.792489,
          36.76875
        ]
      },
      "properties": {
        "description": "representative point"
      }
    },
    {
      "geometry": {
        "type": "Point",
        "coordinates": [
          3.792489,
          36.76875
        ]
      },
      "id": "darmc-location-21928",
      "type": "Feature",
      "properties": {
        "description": "500K scale point location",
        "location_precision": "precise",
        "title": "DARMC location 21928",
        "link": "http://pleiades.stoa.org/places/295246/darmc-location-21928"
      }
    }
  ]
}