{
  "type": "FeatureCollection",
  "title": "Ain el Hammam",
  "id": "295211",
  "description": "An ancient place, cited: BAtlas 30 inset Ain el Hammam",
  "bbox": [
    1.126896,
    35.781097,
    1.126896,
    35.781097
  ],
  "reprPoint": [
    1.126896,
    35.781097
  ],
  "features": [
    {
      "geometry": {
        "type": "Point",
        "coordinates": [
          1.126896,
          35.781097
        ]
      },
      "id": "darmc-location-11068",
      "type": "Feature",
      "properties": {
        "description": "500K scale point location",
        "location_precision": "precise",
        "title": "DARMC location 11068",
        "link": "http://pleiades.stoa.org/places/295211/darmc-location-11068"
      }
    }
  ]
}