{
  "type": "FeatureCollection",
  "title": "Agouni Tabet",
  "id": "295209",
  "description": "An ancient place, cited: BAtlas 30 H3 Agouni Tabet",
  "bbox": [
    4.324969,
    36.783887,
    4.324969,
    36.783887
  ],
  "reprPoint": [
    4.324969,
    36.783887
  ],
  "features": [
    {
      "geometry": {
        "type": "Point",
        "coordinates": [
          4.324969,
          36.783887
        ]
      },
      "id": "darmc-location-11214",
      "type": "Feature",
      "properties": {
        "description": "500K scale point location",
        "location_precision": "precise",
        "title": "DARMC location 11214",
        "link": "http://pleiades.stoa.org/places/295209/darmc-location-11214"
      }
    }
  ]
}