{
  "type": "FeatureCollection",
  "title": "Cap Ivi",
  "id": "295237",
  "bbox": [
    0.231134,
    36.119266,
    0.231134,
    36.119266
  ],
  "description": "An ancient place, cited: BAtlas 30 inset Cap Ivi",
  "features": [
    {
      "type": "Feature",
      "geometry": {
        "type": "Point",
        "coordinates": [
          0.231134,
          36.119266
        ]
      },
      "properties": {
        "description": "representative point"
      }
    },
    {
      "geometry": {
        "type": "Point",
        "coordinates": [
          0.231134,
          36.119266
        ]
      },
      "id": "darmc-location-21894",
      "type": "Feature",
      "properties": {
        "description": "500K scale point location",
        "location_precision": "precise",
        "title": "DARMC location 21894",
        "link": "http://pleiades.stoa.org/places/295237/darmc-location-21894"
      }
    }
  ]
}