{
  "type": "FeatureCollection",
  "title": "el Senadek",
  "id": "295337",
  "description": "An ancient place, cited: BAtlas 30 G3 el Senadek",
  "bbox": [
    3.785022,
    36.818747,
    3.785022,
    36.818747
  ],
  "reprPoint": [
    3.785022,
    36.818747
  ],
  "features": [
    {
      "geometry": {
        "type": "Point",
        "coordinates": [
          3.785022,
          36.818747
        ]
      },
      "id": "darmc-location-15572",
      "type": "Feature",
      "properties": {
        "description": "500K scale point location",
        "location_precision": "precise",
        "title": "DARMC location 15572",
        "link": "http://pleiades.stoa.org/places/295337/darmc-location-15572"
      }
    }
  ]
}