{
  "type": "FeatureCollection",
  "title": "Tachachit Roman Site",
  "id": "295349",
  "bbox": [
    4.116589,
    36.367032,
    4.116589,
    36.367032
  ],
  "description": "A small fortified hilltop settlement located on private land in the modern Algerian village of \"Crète Rouge\" at Tachachit, which is approximately 8km north of El Adjiba. Noted already by Gsell for AAA, a 2012 cultural inventory notes visible remnants of walls, roof tiles, drainage conduit, a cistern, and a polychrome opus-tesselatum mosaic.",
  "features": [
    {
      "type": "Feature",
      "geometry": {
        "type": "Point",
        "coordinates": [
          4.116589,
          36.367032
        ]
      },
      "properties": {
        "description": "representative point"
      }
    },
    {
      "geometry": {
        "type": "Point",
        "coordinates": [
          4.116589,
          36.367032
        ]
      },
      "id": "imagery-location",
      "type": "Feature",
      "properties": {
        "description": "Imagery location after description in Boutarene 2017.",
        "location_precision": "precise",
        "title": "Imagery Location",
        "link": "http://pleiades.stoa.org/places/295349/imagery-location"
      }
    }
  ]
}