{
  "type": "FeatureCollection",
  "title": "Rapidum",
  "id": "295329",
  "description": "Rapidum was a Roman camp of the Mauretanian limes.",
  "bbox": [
    3.421825,
    36.136435,
    3.421825,
    36.136435
  ],
  "reprPoint": [
    3.421825,
    36.136435
  ],
  "names": [
    "Rapidum"
  ],
  "features": [
    {
      "geometry": {
        "type": "Point",
        "coordinates": [
          3.424132,
          36.137254
        ]
      },
      "id": "darmc-location-14472",
      "type": "Feature",
      "properties": {
        "description": "500K scale point location",
        "location_precision": "precise",
        "title": "DARMC location 14472",
        "link": "http://pleiades.stoa.org/places/295329/darmc-location-14472"
      }
    },
    {
      "geometry": {
        "type": "Point",
        "coordinates": [
          3.421825,
          36.136435
        ]
      },
      "id": "dare-location",
      "type": "Feature",
      "properties": {
        "description": "Representative point location, site precision",
        "location_precision": "precise",
        "title": "DARE Location",
        "link": "http://pleiades.stoa.org/places/295329/dare-location"
      }
    }
  ]
}