{
  "type": "FeatureCollection",
  "title": "Rusuccuru",
  "id": "295334",
  "description": "An ancient place, cited: BAtlas 30 G3 Rusuccuru",
  "bbox": [
    3.906969,
    36.909102,
    3.906969,
    36.909102
  ],
  "reprPoint": [
    3.906969,
    36.909102
  ],
  "names": [
    "Rusuccuru",
    "Rusuccenses"
  ],
  "features": [
    {
      "geometry": {
        "type": "Point",
        "coordinates": [
          3.91232,
          36.916607
        ]
      },
      "id": "darmc-location-14545",
      "type": "Feature",
      "properties": {
        "description": "500K scale point location",
        "location_precision": "precise",
        "title": "DARMC location 14545",
        "link": "http://pleiades.stoa.org/places/295334/darmc-location-14545"
      }
    },
    {
      "geometry": {
        "type": "Point",
        "coordinates": [
          3.906969,
          36.909102
        ]
      },
      "id": "dare-location",
      "type": "Feature",
      "properties": {
        "description": "Representative point location, village precision",
        "location_precision": "precise",
        "title": "DARE Location",
        "link": "http://pleiades.stoa.org/places/295334/dare-location"
      }
    }
  ]
}