{
  "type": "FeatureCollection",
  "title": "Thanaramusa Castra",
  "id": "295354",
  "description": "An ancient place, cited: BAtlas 30 E4 Thanaramusa Castra",
  "bbox": [
    2.914292,
    36.135629,
    2.914292,
    36.135629
  ],
  "reprPoint": [
    2.914292,
    36.135629
  ],
  "names": [
    "Thanaramusa Castra"
  ],
  "features": [
    {
      "geometry": {
        "type": "Point",
        "coordinates": [
          2.914292,
          36.135629
        ]
      },
      "id": "darmc-location-15112",
      "type": "Feature",
      "properties": {
        "description": "500K scale point location",
        "location_precision": "precise",
        "title": "DARMC location 15112",
        "link": "http://pleiades.stoa.org/places/295354/darmc-location-15112"
      }
    }
  ]
}