{
  "type": "FeatureCollection",
  "title": "Rusuccuru",
  "id": "295334",
  "bbox": [
    3.906969,
    36.909102,
    3.91232,
    36.916607
  ],
  "description": "The ancient city of Rusuccuru was founded as a Punic settlement on the Oued Sebaou river. In the Roman period, an inscription indicates that Rusuccuru achieved the status of municipium under Septimius Severus, yet some sources continue to refer to it as a colonia.",
  "connectsWith": [
    "295280",
    "295359",
    "298982"
  ],
  "names": [
    "Rusuccuru",
    "Rusuccenses"
  ],
  "features": [
    {
      "type": "Feature",
      "geometry": {
        "type": "Point",
        "coordinates": [
          3.9096445,
          36.9128545
        ]
      },
      "properties": {
        "description": "representative point"
      }
    },
    {
      "geometry": {
        "type": "Point",
        "coordinates": [
          3.91232,
          36.916607
        ]
      },
      "id": "darmc-location-14545",
      "type": "Feature",
      "properties": {
        "description": "500K scale point location",
        "location_precision": "precise",
        "title": "DARMC location 14545",
        "link": "http://pleiades.stoa.org/places/295334/darmc-location-14545"
      }
    },
    {
      "geometry": {
        "type": "Point",
        "coordinates": [
          3.906969,
          36.909102
        ]
      },
      "id": "dare-location",
      "type": "Feature",
      "properties": {
        "description": "Representative point location, village precision",
        "location_precision": "precise",
        "title": "DARE Location",
        "link": "http://pleiades.stoa.org/places/295334/dare-location"
      }
    }
  ]
}