{
  "type": "FeatureCollection",
  "title": "Timici",
  "id": "295362",
  "bbox": [
    0.9222293,
    36.2472325,
    0.9222293,
    36.2472325
  ],
  "description": "A Roman settlement in Mauretania, mentioned in Ptolemy and Pliny, that has been associated with a site that was known as Sidi bou Chaïb in the mid 20th century. That site is now in the territory of the modern Algerian town of Taougrite (colonial Paul-Robert), Chlef province.",
  "names": [
    "Sidi bou Chaib",
    "Timici"
  ],
  "features": [
    {
      "type": "Feature",
      "geometry": {
        "type": "Point",
        "coordinates": [
          0.9222293,
          36.2472325
        ]
      },
      "properties": {
        "description": "representative point"
      }
    },
    {
      "geometry": {
        "type": "Point",
        "coordinates": [
          0.9222293,
          36.2472325
        ]
      },
      "id": "osm-location-of-modern-taougrite",
      "type": "Feature",
      "properties": {
        "description": "Location based on OpenStreetMap",
        "location_precision": "precise",
        "title": "OSM Location of modern Taougrite",
        "link": "http://pleiades.stoa.org/places/295362/osm-location-of-modern-taougrite"
      }
    }
  ]
}