{
  "type": "FeatureCollection",
  "title": "Sufasar",
  "id": "295346",
  "description": "An ancient place, cited: BAtlas 30 E4 Sufasar",
  "bbox": [
    2.511476,
    36.192569,
    2.511476,
    36.192569
  ],
  "reprPoint": [
    2.511476,
    36.192569
  ],
  "names": [
    "Sufasar"
  ],
  "features": [
    {
      "geometry": {
        "type": "Point",
        "coordinates": [
          2.515064,
          36.192331
        ]
      },
      "id": "darmc-location-14926",
      "type": "Feature",
      "properties": {
        "description": "500K scale point location",
        "location_precision": "precise",
        "title": "DARMC location 14926",
        "link": "http://pleiades.stoa.org/places/295346/darmc-location-14926"
      }
    },
    {
      "geometry": {
        "type": "Point",
        "coordinates": [
          2.511476,
          36.192569
        ]
      },
      "id": "dare-location",
      "type": "Feature",
      "properties": {
        "description": "Representative point location, village precision",
        "location_precision": "precise",
        "title": "DARE Location",
        "link": "http://pleiades.stoa.org/places/295346/dare-location"
      }
    }
  ]
}