{
  "type": "FeatureCollection",
  "title": "Trois Îlots",
  "id": "295367",
  "description": "An ancient place, cited: BAtlas 30 D3 Trois Îlots",
  "bbox": [
    2.27916,
    36.624145,
    2.27916,
    36.624145
  ],
  "reprPoint": [
    2.27916,
    36.624145
  ],
  "features": [
    {
      "geometry": {
        "type": "Point",
        "coordinates": [
          2.27916,
          36.624145
        ]
      },
      "id": "darmc-location-25270",
      "type": "Feature",
      "properties": {
        "description": "500K scale point location",
        "location_precision": "precise",
        "title": "DARMC location 25270",
        "link": "http://pleiades.stoa.org/places/295367/darmc-location-25270"
      }
    }
  ]
}