{
  "type": "FeatureCollection",
  "title": "Jumeirah",
  "id": "29617",
  "description": "An ancient place, cited: BAtlas 3 G4 Jumeirah",
  "bbox": [
    55.250773,
    25.208098,
    55.250773,
    25.208098
  ],
  "reprPoint": [
    55.250773,
    25.208098
  ],
  "features": [
    {
      "geometry": {
        "type": "Point",
        "coordinates": [
          55.250773,
          25.208098
        ]
      },
      "id": "darmc-location-20354",
      "type": "Feature",
      "properties": {
        "description": "5M scale point location",
        "location_precision": "precise",
        "title": "DARMC location 20354",
        "link": "http://pleiades.stoa.org/places/29617/darmc-location-20354"
      }
    }
  ]
}