{
  "type": "FeatureCollection",
  "title": "Kalon Oros",
  "id": "29621",
  "bbox": [
    57.263889,
    23.1,
    57.4,
    23.236944
  ],
  "description": "The Kalon Oros is mentioned in the Periplus Maris Erythraei and has been identified by modern scholars with the modern Jebel Akhdar in Oman.",
  "connectsWith": [
    "932433"
  ],
  "names": [
    "Kalon Oros",
    "Jebel Akhdar"
  ],
  "features": [
    {
      "type": "Feature",
      "geometry": {
        "type": "Point",
        "coordinates": [
          57.3319445,
          23.168472
        ]
      },
      "properties": {
        "description": "representative point"
      }
    }
  ]
}