{
  "type": "FeatureCollection",
  "title": "House of the Columns",
  "id": "297059708",
  "bbox": [
    -5.5552713,
    34.0746166,
    -5.5552713,
    34.0746166
  ],
  "description": "Roman Peristyle House with interior garden and fountain.",
  "connectsWith": [
    "275740"
  ],
  "features": [
    {
      "type": "Feature",
      "geometry": {
        "type": "Point",
        "coordinates": [
          -5.5552713,
          34.0746166
        ]
      },
      "properties": {
        "description": "representative point"
      }
    },
    {
      "geometry": {
        "type": "Point",
        "coordinates": [
          -5.5552713,
          34.0746166
        ]
      },
      "id": "osm-location-of-house-of-the-columns",
      "type": "Feature",
      "properties": {
        "description": "Representative location based on OpenStreetMap",
        "location_precision": "precise",
        "title": "OSM location of House of the Columns",
        "link": "http://pleiades.stoa.org/places/297059708/osm-location-of-house-of-the-columns"
      }
    }
  ]
}