{
  "type": "FeatureCollection",
  "title": "Post-Archaic necropolis at Poggio dei Cavallari",
  "id": "297163721",
  "bbox": [
    12.746919,
    41.512733,
    12.746919,
    41.512733
  ],
  "description": "A necropolis located along a road that once led to the Mater Matuta sanctuary composed of approximately 50 tombs.",
  "connectsWith": [
    "423060"
  ],
  "features": [
    {
      "type": "Feature",
      "geometry": {
        "type": "Point",
        "coordinates": [
          12.746919,
          41.512733
        ]
      },
      "properties": {
        "description": "representative point"
      }
    },
    {
      "geometry": {
        "type": "Point",
        "coordinates": [
          12.746919,
          41.512733
        ]
      },
      "id": "imagery-location",
      "type": "Feature",
      "properties": {
        "description": "A necropolis located along a road that once led to the Mater Matuta sanctuary composed of approximately 50 tombs.",
        "location_precision": "precise",
        "title": "Imagery Location of Post-Archaic necropolis",
        "link": "http://pleiades.stoa.org/places/297163721/imagery-location"
      }
    }
  ]
}