{
  "type": "FeatureCollection",
  "title": "Phra(da)/Prophthasia/Frakh-kar-Peroz",
  "id": "29718",
  "bbox": [
    62.1159443,
    32.379488,
    62.1159443,
    32.379488
  ],
  "description": "An ancient place, cited: BAtlas 3 H3 Phra(da)/Prophthasia/Frakh-kar-Peroz",
  "names": [
    "Phrada",
    "Phra",
    "Prophthasía",
    "Frakh-kar-Peroz",
    "Propasta",
    "Phrada",
    "Phra",
    "Farah",
    "Frāh",
    "Farāh",
    "Farah",
    "Prophthasia"
  ],
  "features": [
    {
      "type": "Feature",
      "geometry": {
        "type": "Point",
        "coordinates": [
          62.1159443,
          32.379488
        ]
      },
      "properties": {
        "description": "representative point"
      }
    },
    {
      "geometry": {
        "type": "Point",
        "coordinates": [
          62.1159443,
          32.379488
        ]
      },
      "id": "osm-location-of-farah-bala-hisar",
      "type": "Feature",
      "properties": {
        "description": "Location based on OpenStreetMap",
        "location_precision": "precise",
        "title": "OSM location of Farah Bala Hisar",
        "link": "http://pleiades.stoa.org/places/29718/osm-location-of-farah-bala-hisar"
      }
    }
  ]
}