{
  "type": "FeatureCollection",
  "title": "Phra(da)/Prophthasia/Frakh-kar-Peroz",
  "id": "29718",
  "description": "An ancient place, cited: BAtlas 3 H3 Phra(da)/Prophthasia/Frakh-kar-Peroz",
  "bbox": [
    61.490615,
    32.452692,
    61.490615,
    32.452692
  ],
  "reprPoint": [
    61.490615,
    32.452692
  ],
  "names": [
    "Phrada",
    "Phra",
    "Prophthasia",
    "Frakh-kar-Peroz",
    "Propasta",
    "Phrada",
    "Phra",
    "Farah",
    "Frāh",
    "Farāh",
    "Farah",
    "Prophthasia"
  ],
  "features": [
    {
      "geometry": {
        "type": "Point",
        "coordinates": [
          61.490615,
          32.452692
        ]
      },
      "id": "darmc-location-10203",
      "type": "Feature",
      "properties": {
        "description": "5M scale point location",
        "location_precision": "precise",
        "title": "DARMC location 10203",
        "link": "http://pleiades.stoa.org/places/29718/darmc-location-10203"
      }
    }
  ]
}