{
  "type": "FeatureCollection",
  "title": "[Siraf]",
  "id": "29762",
  "bbox": [
    52.33683,
    27.670345,
    52.33683,
    27.670345
  ],
  "description": "An ancient place, cited: BAtlas 3 F4 [Siraf]",
  "names": [
    "Siraf"
  ],
  "features": [
    {
      "type": "Feature",
      "geometry": {
        "type": "Point",
        "coordinates": [
          52.33683,
          27.670345
        ]
      },
      "properties": {
        "description": "representative point"
      }
    },
    {
      "geometry": {
        "type": "Point",
        "coordinates": [
          52.33683,
          27.670345
        ]
      },
      "id": "darmc-location-3553",
      "type": "Feature",
      "properties": {
        "description": "5M scale point location",
        "location_precision": "precise",
        "title": "DARMC location 3553",
        "link": "http://pleiades.stoa.org/places/29762/darmc-location-3553"
      }
    }
  ]
}