{
  "type": "FeatureCollection",
  "title": "Tepe Yahya",
  "id": "29783",
  "description": "An ancient place, cited: BAtlas 3 G4 Tepe Yahya",
  "bbox": [
    56.350333,
    28.58276,
    56.350333,
    28.58276
  ],
  "reprPoint": [
    56.350333,
    28.58276
  ],
  "features": [
    {
      "geometry": {
        "type": "Point",
        "coordinates": [
          56.350333,
          28.58276
        ]
      },
      "id": "darmc-location-1846",
      "type": "Feature",
      "properties": {
        "description": "5M scale point location",
        "location_precision": "precise",
        "title": "DARMC location 1846",
        "link": "http://pleiades.stoa.org/places/29783/darmc-location-1846"
      }
    }
  ]
}