{
  "type": "FeatureCollection",
  "title": "Tepe Yahya",
  "id": "29783",
  "bbox": [
    56.8675,
    28.3309,
    56.8675,
    28.3309
  ],
  "description": "An ancient place, cited: BAtlas 3 G4 Tepe Yahya",
  "names": [
    "Tapah Yahiya",
    "Tapah Yahiya"
  ],
  "features": [
    {
      "type": "Feature",
      "geometry": {
        "type": "Point",
        "coordinates": [
          56.8675,
          28.3309
        ]
      },
      "properties": {
        "description": "representative point"
      }
    },
    {
      "geometry": {
        "type": "Point",
        "coordinates": [
          56.8675,
          28.3309
        ]
      },
      "id": "cigs-location-of-tapah-yahiya",
      "type": "Feature",
      "properties": {
        "description": "Representative location of Tapah Yahiya from Cuneiform Inscriptions Geographical Site Index (CIGS).",
        "location_precision": "precise",
        "title": "CIGS location of Tapah Yahiya",
        "link": "http://pleiades.stoa.org/places/29783/cigs-location-of-tapah-yahiya"
      }
    }
  ]
}