{
  "type": "FeatureCollection",
  "title": "Rabana-Merquly",
  "id": "300035018",
  "bbox": [
    45.21906,
    35.747436,
    45.236427,
    35.75376
  ],
  "description": "A major, but relatively short-lived, fortified site in the Zagros mountains of modern Iraqi Kurdistan comprising two settlement loci within a large fortified area. Remains include stone foundations for mudbrick fortification walls and buildings, a stone-cut stairway, and two rock-reliefs depicting an unnamed ruler in elaborate costume. The complex has some evidence for reoccupation in Sasanian, Islamic and modern times.",
  "names": [
    "Natounia pros to Kapro"
  ],
  "features": [
    {
      "type": "Feature",
      "geometry": {
        "type": "Point",
        "coordinates": [
          45.2277435,
          35.750598
        ]
      },
      "properties": {
        "description": "representative point"
      }
    },
    {
      "geometry": {
        "type": "Point",
        "coordinates": [
          45.236427,
          35.747436
        ]
      },
      "id": "imagery-location-of-merquly",
      "type": "Feature",
      "properties": {
        "description": "After Brown 2022, Figure 1.",
        "location_precision": "precise",
        "title": "Imagery location of Merquly",
        "link": "http://pleiades.stoa.org/places/300035018/imagery-location-of-merquly"
      }
    },
    {
      "geometry": {
        "type": "Point",
        "coordinates": [
          45.21906,
          35.75376
        ]
      },
      "id": "imagery-location-of-rabana",
      "type": "Feature",
      "properties": {
        "description": null,
        "location_precision": "precise",
        "title": "Imagery Location of Rabana",
        "link": "http://pleiades.stoa.org/places/300035018/imagery-location-of-rabana"
      }
    }
  ]
}