{
  "type": "FeatureCollection",
  "title": "Caumatis/Kanate/Kanthatis",
  "id": "30221",
  "bbox": [
    62.6083271827,
    26.4798739356,
    65.1840937215,
    26.7297173412
  ],
  "description": "An ancient place, cited: BAtlas 3 unlocated Caumatis/Kanate/Kanthatis",
  "connectsWith": [
    "29573"
  ],
  "names": [
    "Caumatis",
    "Kanate",
    "Kanthatis"
  ],
  "features": [
    {
      "type": "Feature",
      "geometry": {
        "type": "Point",
        "coordinates": [
          63.7573921727,
          26.5946046789
        ]
      },
      "properties": {
        "description": "representative point"
      }
    },
    {
      "geometry": null,
      "id": "batlas-location",
      "type": "Feature",
      "properties": {
        "description": null,
        "location_precision": "unlocated",
        "title": "Barrington Atlas location",
        "link": "http://pleiades.stoa.org/places/30221/batlas-location"
      }
    }
  ]
}