{
  "type": "FeatureCollection",
  "title": "Vagnari",
  "id": "303135575",
  "description": "A villa, vicus and necropolis site in modern Puglia, Italy located near the modern city of Gravina.  The site was active from the 1st to 4th centuries CE.  ",
  "bbox": [
    16.283,
    40.834,
    16.283,
    40.834
  ],
  "reprPoint": [
    16.283,
    40.834
  ],
  "names": [
    "Vagnari"
  ],
  "features": [
    {
      "geometry": {
        "type": "Point",
        "coordinates": [
          16.283,
          40.834
        ]
      },
      "id": "imagery-location-of-vagnari",
      "type": "Feature",
      "properties": {
        "description": "Imagery location of Vagnari, based on Google Earth aerial photography.",
        "location_precision": "precise",
        "title": "Imagery location of Vagnari",
        "link": "http://pleiades.stoa.org/places/303135575/imagery-location-of-vagnari"
      }
    }
  ]
}