{
  "type": "FeatureCollection",
  "title": "Sam'alla (kingdom)",
  "id": "303882989",
  "bbox": [
    35.4111353467,
    36.9303120368,
    37.09,
    37.5812744
  ],
  "description": "Sam'alla (šmʾl; also known as Bīt-Gabbāri and yʾdy) was a small Aramean kingdom/city-state during the first half of the first millennium BC. It is named after its capital city Sam'al (modern Zincirli Höyük).",
  "connectsWith": [
    "648980581",
    "802922079",
    "424616150",
    "56567731"
  ],
  "names": [
    "Sam'alla",
    "šmʾl",
    "yʾdy",
    "Mār-Gabbāri"
  ],
  "features": [
    {
      "type": "Feature",
      "geometry": {
        "type": "Point",
        "coordinates": [
          36.5799554115,
          37.1820433515
        ]
      },
      "properties": {
        "description": "representative point"
      }
    }
  ]
}