{
  "type": "FeatureCollection",
  "title": "Via Portuensis?",
  "id": "303999556",
  "bbox": [
    12.2514705,
    41.7747038,
    12.4794,
    41.8893
  ],
  "description": "The Via Portuensis is an ancient Roman road that connected Rome and Portus. It proceeded along the right bank of the Tiber river, starting from the Pons Aemilius. In the first part of its course it is identical to the Via Campana.",
  "names": [
    "Via Portuensis"
  ],
  "features": [
    {
      "type": "Feature",
      "geometry": {
        "type": "Point",
        "coordinates": [
          12.2560371414,
          41.7773596512
        ]
      },
      "properties": {
        "description": "representative point"
      }
    }
  ]
}