{
  "type": "FeatureCollection",
  "title": "Ravenglass Roman Bath House",
  "id": "304814760",
  "bbox": [
    -3.4041335,
    54.3506763,
    -3.4041335,
    54.3506763
  ],
  "description": "The Ravenglass Roman Bath House, also known as \"Walls Castle\", is linked to the second-century CE fort at Glannoventa. English Heritage dates the site ca. 130 and deems it one of the tallest surviving Roman ruins in Britain.",
  "connectsWith": [
    "89193"
  ],
  "features": [
    {
      "type": "Feature",
      "geometry": {
        "type": "Point",
        "coordinates": [
          -3.4041335,
          54.3506763
        ]
      },
      "properties": {
        "description": "representative point"
      }
    },
    {
      "geometry": {
        "type": "Point",
        "coordinates": [
          -3.4041335,
          54.3506763
        ]
      },
      "id": "osm-location-of-roman-bath",
      "type": "Feature",
      "properties": {
        "description": "Known either as 'Ravenglass Roman Bath House' or 'Walls Castle'. Location based on OpenStreetMap.",
        "location_precision": "precise",
        "title": "OSM location of Roman bath",
        "link": "http://pleiades.stoa.org/places/304814760/osm-location-of-roman-bath"
      }
    }
  ]
}