{
  "type": "FeatureCollection",
  "title": "Aquae Thibilitanae",
  "id": "305030",
  "description": "An ancient place, cited: BAtlas 31 G4 Aquae Thibilitanae",
  "bbox": [
    7.270135,
    36.459865,
    7.270135,
    36.459865
  ],
  "reprPoint": [
    7.270135,
    36.459865
  ],
  "names": [
    "Aquae Thibilitanae"
  ],
  "features": [
    {
      "geometry": {
        "type": "Point",
        "coordinates": [
          7.270135,
          36.459865
        ]
      },
      "id": "darmc-location-11452",
      "type": "Feature",
      "properties": {
        "description": "500K scale point location",
        "location_precision": "precise",
        "title": "DARMC location 11452",
        "link": "http://pleiades.stoa.org/places/305030/darmc-location-11452"
      }
    }
  ]
}