{
  "type": "FeatureCollection",
  "title": "Chullu",
  "id": "305063",
  "description": "An ancient place, cited: BAtlas 31 F2 Chullu",
  "bbox": [
    6.55865,
    37.007228,
    6.55865,
    37.007228
  ],
  "reprPoint": [
    6.55865,
    37.007228
  ],
  "names": [
    "Chullu"
  ],
  "features": [
    {
      "geometry": {
        "type": "Point",
        "coordinates": [
          6.565512,
          37.008477
        ]
      },
      "id": "darmc-location-12021",
      "type": "Feature",
      "properties": {
        "description": "500K scale point location",
        "location_precision": "precise",
        "title": "DARMC location 12021",
        "link": "http://pleiades.stoa.org/places/305063/darmc-location-12021"
      }
    },
    {
      "geometry": {
        "type": "Point",
        "coordinates": [
          6.55865,
          37.007228
        ]
      },
      "id": "dare-location",
      "type": "Feature",
      "properties": {
        "description": "Representative point location, village precision",
        "location_precision": "precise",
        "title": "DARE Location",
        "link": "http://pleiades.stoa.org/places/305063/dare-location"
      }
    }
  ]
}