{
  "type": "FeatureCollection",
  "title": "Rusicade/Thapsus",
  "id": "305137",
  "bbox": [
    6.904959,
    36.879641,
    6.906202,
    36.883244
  ],
  "description": "Rusicade/Thapsus was the port of Cirta and a Roman colonia, located at the mouth of the small river Thapsus.",
  "connectsWith": [
    "305163"
  ],
  "names": [
    "Rusicade",
    "Thapsus",
    "Rusicade Colonia"
  ],
  "features": [
    {
      "type": "Feature",
      "geometry": {
        "type": "Point",
        "coordinates": [
          6.9055805,
          36.8814425
        ]
      },
      "properties": {
        "description": "representative point"
      }
    },
    {
      "geometry": {
        "type": "Point",
        "coordinates": [
          6.906202,
          36.883244
        ]
      },
      "id": "darmc-location-14540",
      "type": "Feature",
      "properties": {
        "description": "1:500,000 scale representative point location digitized from the Barrington Atlas of the Greek and Roman World by the Digital Atlas of Roman and Medieval Civilizations project at Harvard University.",
        "location_precision": "precise",
        "title": "DARMC location 14540",
        "link": "http://pleiades.stoa.org/places/305137/darmc-location-14540"
      }
    },
    {
      "geometry": {
        "type": "Point",
        "coordinates": [
          6.904959,
          36.879641
        ]
      },
      "id": "dare-location",
      "type": "Feature",
      "properties": {
        "description": "Representative point location, site precision",
        "location_precision": "precise",
        "title": "DARE Location",
        "link": "http://pleiades.stoa.org/places/305137/dare-location"
      }
    }
  ]
}