{
  "type": "FeatureCollection",
  "title": "Rusicade/Thapsus",
  "id": "305137",
  "description": "Rusicade/Thapsus was the port of Cirta and a Roman colonia, located at the mouth of the small river Thapsus.",
  "bbox": [
    6.904959,
    36.879641,
    6.904959,
    36.879641
  ],
  "connectsWith": [
    "305163"
  ],
  "reprPoint": [
    6.904959,
    36.879641
  ],
  "names": [
    "Rusicade",
    "Thapsus"
  ],
  "features": [
    {
      "geometry": {
        "type": "Point",
        "coordinates": [
          6.906202,
          36.883244
        ]
      },
      "id": "darmc-location-14540",
      "type": "Feature",
      "properties": {
        "description": "500K scale point location",
        "location_precision": "precise",
        "title": "DARMC location 14540",
        "link": "http://pleiades.stoa.org/places/305137/darmc-location-14540"
      }
    },
    {
      "geometry": {
        "type": "Point",
        "coordinates": [
          6.904959,
          36.879641
        ]
      },
      "id": "dare-location",
      "type": "Feature",
      "properties": {
        "description": "Representative point location, site precision",
        "location_precision": "precise",
        "title": "DARE Location",
        "link": "http://pleiades.stoa.org/places/305137/dare-location"
      }
    }
  ]
}