{
  "type": "FeatureCollection",
  "title": "Tubusuctu",
  "id": "305171",
  "description": "An ancient place, cited: BAtlas 31 B3 Tubusuctu",
  "bbox": [
    4.855629,
    36.673393,
    4.855629,
    36.673393
  ],
  "reprPoint": [
    4.855629,
    36.673393
  ],
  "names": [
    "Tubusuctu",
    "Tubusuptu",
    "Tupusuctu"
  ],
  "features": [
    {
      "geometry": {
        "type": "Point",
        "coordinates": [
          4.836816,
          36.661737
        ]
      },
      "id": "darmc-location-15281",
      "type": "Feature",
      "properties": {
        "description": "500K scale point location",
        "location_precision": "precise",
        "title": "DARMC location 15281",
        "link": "http://pleiades.stoa.org/places/305171/darmc-location-15281"
      }
    },
    {
      "geometry": {
        "type": "Point",
        "coordinates": [
          4.855629,
          36.673393
        ]
      },
      "id": "dare-location",
      "type": "Feature",
      "properties": {
        "description": "Representative point location, village precision",
        "location_precision": "precise",
        "title": "DARE Location",
        "link": "http://pleiades.stoa.org/places/305171/dare-location"
      }
    }
  ]
}