{
  "type": "FeatureCollection",
  "title": "Pagus Thigillava",
  "id": "305127",
  "bbox": [
    5.699995,
    36.266866,
    5.699995,
    36.266866
  ],
  "description": "An ancient place, cited: BAtlas 31 D4 Pagus Thigillava",
  "names": [
    "Pagus Thigillava"
  ],
  "features": [
    {
      "type": "Feature",
      "geometry": {
        "type": "Point",
        "coordinates": [
          5.699995,
          36.266866
        ]
      },
      "properties": {
        "description": "representative point"
      }
    },
    {
      "geometry": {
        "type": "Point",
        "coordinates": [
          5.699995,
          36.266866
        ]
      },
      "id": "darmc-location-14078",
      "type": "Feature",
      "properties": {
        "description": "500K scale point location",
        "location_precision": "precise",
        "title": "DARMC location 14078",
        "link": "http://pleiades.stoa.org/places/305127/darmc-location-14078"
      }
    }
  ]
}