{
  "type": "FeatureCollection",
  "title": "Subtabarti",
  "id": "305155",
  "description": "An ancient place, cited: BAtlas 31 D4 Subtabarti",
  "bbox": [
    5.684923,
    36.187011,
    5.684923,
    36.187011
  ],
  "reprPoint": [
    5.684923,
    36.187011
  ],
  "names": [
    "Subtabarti"
  ],
  "features": [
    {
      "geometry": {
        "type": "Point",
        "coordinates": [
          5.684923,
          36.187011
        ]
      },
      "id": "darmc-location-14923",
      "type": "Feature",
      "properties": {
        "description": "500K scale point location",
        "location_precision": "precise",
        "title": "DARMC location 14923",
        "link": "http://pleiades.stoa.org/places/305155/darmc-location-14923"
      }
    }
  ]
}