{
  "type": "FeatureCollection",
  "title": "Thenebreste?",
  "id": "305164",
  "bbox": [
    6.27434,
    36.014677,
    6.274453,
    36.014843
  ],
  "description": "An ancient place, cited: BAtlas 31 G4 Thenebreste?",
  "names": [
    "Thenebreste"
  ],
  "features": [
    {
      "type": "Feature",
      "geometry": {
        "type": "Point",
        "coordinates": [
          6.2743965,
          36.01476
        ]
      },
      "properties": {
        "description": "representative point"
      }
    },
    {
      "geometry": {
        "type": "Point",
        "coordinates": [
          6.274453,
          36.014677
        ]
      },
      "id": "darmc-location-6316",
      "type": "Feature",
      "properties": {
        "description": "500K scale point location",
        "location_precision": "precise",
        "title": "DARMC location 6316",
        "link": "http://pleiades.stoa.org/places/305164/darmc-location-6316"
      }
    },
    {
      "geometry": {
        "type": "Point",
        "coordinates": [
          6.27434,
          36.014843
        ]
      },
      "id": "darmc-location-6317",
      "type": "Feature",
      "properties": {
        "description": "500K scale point location",
        "location_precision": "precise",
        "title": "DARMC location 6317",
        "link": "http://pleiades.stoa.org/places/305164/darmc-location-6317"
      }
    }
  ]
}