{
  "type": "FeatureCollection",
  "title": "Thibilis",
  "id": "305165",
  "description": "An ancient place, cited: BAtlas 31 G4 Thibilis",
  "bbox": [
    7.250462,
    36.383081,
    7.250462,
    36.383081
  ],
  "reprPoint": [
    7.250462,
    36.383081
  ],
  "names": [
    "Thibilis"
  ],
  "features": [
    {
      "geometry": {
        "type": "Point",
        "coordinates": [
          7.249604,
          36.382053
        ]
      },
      "id": "darmc-location-15139",
      "type": "Feature",
      "properties": {
        "description": "500K scale point location",
        "location_precision": "precise",
        "title": "DARMC location 15139",
        "link": "http://pleiades.stoa.org/places/305165/darmc-location-15139"
      }
    },
    {
      "geometry": {
        "type": "Point",
        "coordinates": [
          7.250462,
          36.383081
        ]
      },
      "id": "dare-location",
      "type": "Feature",
      "properties": {
        "description": "Representative point location, village precision",
        "location_precision": "precise",
        "title": "DARE Location",
        "link": "http://pleiades.stoa.org/places/305165/dare-location"
      }
    }
  ]
}