{
  "type": "FeatureCollection",
  "title": "Novar(icia?)",
  "id": "305118",
  "bbox": [
    5.606992,
    36.282402,
    5.606992,
    36.282402
  ],
  "description": "An ancient place, cited: BAtlas 31 D4 Novar(icia?)",
  "names": [
    "Novaricia",
    "Novar"
  ],
  "features": [
    {
      "type": "Feature",
      "geometry": {
        "type": "Point",
        "coordinates": [
          5.606992,
          36.282402
        ]
      },
      "properties": {
        "description": "representative point"
      }
    },
    {
      "geometry": {
        "type": "Point",
        "coordinates": [
          5.606992,
          36.282402
        ]
      },
      "id": "darmc-location-13957",
      "type": "Feature",
      "properties": {
        "description": "500K scale point location",
        "location_precision": "precise",
        "title": "DARMC location 13957",
        "link": "http://pleiades.stoa.org/places/305118/darmc-location-13957"
      }
    }
  ]
}