{
  "type": "FeatureCollection",
  "title": "Forum Boarium",
  "id": "305567842",
  "description": "The so-called \"Forum Boarium\" in Pompeii was erroneously named by its 1755 excavators who discovered the bones of large bovids and assigned the name that still is used to describe this insula in Pompeii's Regio II (II, 5).",
  "bbox": [
    14.4940387,
    40.7522106,
    14.4940387,
    40.7522106
  ],
  "connectsWith": [
    "7e6d2513bd65076fa2221089e9584825"
  ],
  "reprPoint": [
    14.4940387,
    40.7522106
  ],
  "features": [
    {
      "geometry": {
        "type": "Point",
        "coordinates": [
          14.4940387,
          40.7522106
        ]
      },
      "id": "foro-boario",
      "type": "Feature",
      "properties": {
        "description": "Location based on OpenStreetMap",
        "location_precision": "precise",
        "title": "OSM location of so-called \"Foro Boario\"",
        "link": "http://pleiades.stoa.org/places/305567842/foro-boario"
      }
    }
  ]
}