{
  "type": "FeatureCollection",
  "title": "Montagna di Gildone",
  "id": "305770200",
  "bbox": [
    14.7592688,
    41.4943754,
    14.7592688,
    41.4943754
  ],
  "description": "A series of noncontinuous fortifications are extant on Mount Gildone (elevation 902 meters) that enclose part of an upland plateau. A nucleus of 23 Samnite tombs was also discovered in the vicinity.",
  "names": [
    "Montagna di Gildone"
  ],
  "features": [
    {
      "type": "Feature",
      "geometry": {
        "type": "Point",
        "coordinates": [
          14.7592688,
          41.4943754
        ]
      },
      "properties": {
        "description": "representative point"
      }
    },
    {
      "geometry": {
        "type": "Point",
        "coordinates": [
          14.7592688,
          41.4943754
        ]
      },
      "id": "osm-location-of-montagna-di-gildone",
      "type": "Feature",
      "properties": {
        "description": "Representative location of the mountain peak based on OpenStreetMap.",
        "location_precision": "precise",
        "title": "OSM location of Montagna di Gildone",
        "link": "http://pleiades.stoa.org/places/305770200/osm-location-of-montagna-di-gildone"
      }
    }
  ]
}