{
  "type": "FeatureCollection",
  "title": "Rabati Malik",
  "id": "305879597",
  "bbox": [
    65.1489221,
    40.1223102,
    65.1489221,
    40.1223102
  ],
  "description": "An eleventh-century caravanserai along the Silk Road, now located in Uzbekistan. Rabati Malik Caravanserai was built under Karakhanid Shams-al-Mulk Nasr, son of Tamgachkhan Ibragim who ruled in Samarkand from 1068 to 1080. The site was added to the UNESCO World Heritage Tentative List in 2008. ",
  "features": [
    {
      "type": "Feature",
      "geometry": {
        "type": "Point",
        "coordinates": [
          65.1489221,
          40.1223102
        ]
      },
      "properties": {
        "description": "representative point"
      }
    },
    {
      "geometry": {
        "type": "Point",
        "coordinates": [
          65.1489221,
          40.1223102
        ]
      },
      "id": "osm-location",
      "type": "Feature",
      "properties": {
        "description": "Representative location based on OpenStreetMap.",
        "location_precision": "precise",
        "title": "OSM location of Rabati Malik ",
        "link": "http://pleiades.stoa.org/places/305879597/osm-location"
      }
    }
  ]
}