{
  "type": "FeatureCollection",
  "title": "Tomba della Medusa (Roma)",
  "id": "305841487",
  "bbox": [
    12.511348,
    41.905259,
    12.511348,
    41.905259
  ],
  "description": "A Roman chamber tomb now located on the grounds of the Policlinico Umberto I hospital in Rome.",
  "connectsWith": [
    "423025"
  ],
  "features": [
    {
      "type": "Feature",
      "geometry": {
        "type": "Point",
        "coordinates": [
          12.511348,
          41.905259
        ]
      },
      "properties": {
        "description": "representative point"
      }
    },
    {
      "geometry": {
        "type": "Point",
        "coordinates": [
          12.511348,
          41.905259
        ]
      },
      "id": "imagery-location-of-tomba-della-medusa",
      "type": "Feature",
      "properties": {
        "description": "Location determined in Google Earth with reference to Info.roma.it and Arachne imagery and location data.",
        "location_precision": "precise",
        "title": "Imagery Location of Tomba della Medusa",
        "link": "http://pleiades.stoa.org/places/305841487/imagery-location-of-tomba-della-medusa"
      }
    }
  ]
}