{
  "type": "FeatureCollection",
  "title": "Komaros Limen",
  "id": "306176341",
  "bbox": [
    20.705611,
    39.003828,
    20.705611,
    39.003828
  ],
  "description": "A harbor near Actium.",
  "features": [
    {
      "type": "Feature",
      "geometry": {
        "type": "Point",
        "coordinates": [
          20.705611,
          39.003828
        ]
      },
      "properties": {
        "description": "representative point"
      }
    },
    {
      "geometry": {
        "type": "Point",
        "coordinates": [
          20.705611,
          39.003828
        ]
      },
      "id": "location-of-komaros-limen",
      "type": "Feature",
      "properties": {
        "description": "verified in Google Earth 2013 based on position in Barrington Atlas",
        "location_precision": "precise",
        "title": "location of Komaros Limen",
        "link": "http://pleiades.stoa.org/places/306176341/location-of-komaros-limen"
      }
    }
  ]
}