{
  "type": "FeatureCollection",
  "title": "Unnamed iron mine",
  "id": "307289",
  "description": "Located to the west of Hippo Regius (modern Annaba in Algeria).",
  "bbox": [
    7.446431,
    36.886538,
    7.446431,
    36.886538
  ],
  "reprPoint": [
    7.446431,
    36.886538
  ],
  "features": [
    {
      "geometry": {
        "type": "Point",
        "coordinates": [
          7.446431,
          36.886538
        ]
      },
      "id": "darmc-location-19148",
      "type": "Feature",
      "properties": {
        "description": "500K scale point location",
        "location_precision": "precise",
        "title": "DARMC location 19148",
        "link": "http://pleiades.stoa.org/places/307289/darmc-location-19148"
      }
    }
  ]
}