{
  "type": "FeatureCollection",
  "title": "Drumlanrig",
  "id": "309231037",
  "bbox": [
    -3.8089191,
    55.2710536,
    -3.8042737,
    55.2736816
  ],
  "description": "A Roman auxiliary fort located at Drumlanrig in Scotland.",
  "features": [
    {
      "type": "Feature",
      "geometry": {
        "type": "Point",
        "coordinates": [
          -3.8065964,
          55.2723676
        ]
      },
      "properties": {
        "description": "representative point"
      }
    },
    {
      "geometry": {
        "type": "Point",
        "coordinates": [
          -3.8089191,
          55.2736816
        ]
      },
      "id": "osm-location-of-drumlanrig-castle",
      "type": "Feature",
      "properties": {
        "description": "Location based on OpenStreetMap",
        "location_precision": "precise",
        "title": "OSM location of Drumlanrig Castle",
        "link": "http://pleiades.stoa.org/places/309231037/osm-location-of-drumlanrig-castle"
      }
    },
    {
      "geometry": {
        "type": "Point",
        "coordinates": [
          -3.8042737,
          55.2710536
        ]
      },
      "id": "osm-location-of-drumlanrig-roman-fort-and-annexe",
      "type": "Feature",
      "properties": {
        "description": "Representative location based on OpenStreetMap",
        "location_precision": "precise",
        "title": "OSM location of Drumlanrig, Roman fort and annexe",
        "link": "http://pleiades.stoa.org/places/309231037/osm-location-of-drumlanrig-roman-fort-and-annexe"
      }
    }
  ]
}