{
  "type": "FeatureCollection",
  "title": "Porta Praetoria at Aosta",
  "id": "310024671",
  "bbox": [
    7.3233941,
    45.7379536,
    7.3233941,
    45.7379536
  ],
  "description": "A gate of the city wall of the Augustan colony, ca. 25 B.C.",
  "connectsWith": [
    "383579"
  ],
  "features": [
    {
      "type": "Feature",
      "geometry": {
        "type": "Point",
        "coordinates": [
          7.3233941,
          45.7379536
        ]
      },
      "properties": {
        "description": "representative point"
      }
    },
    {
      "geometry": {
        "type": "Point",
        "coordinates": [
          7.3233941,
          45.7379536
        ]
      },
      "id": "location-of-porta-praetoria",
      "type": "Feature",
      "properties": {
        "description": "Representative location derived from OpenStreetMap.",
        "location_precision": "precise",
        "title": "OSM location of Porta Praetoria",
        "link": "http://pleiades.stoa.org/places/310024671/location-of-porta-praetoria"
      }
    }
  ]
}