{
  "type": "FeatureCollection",
  "title": "Ain Moungas",
  "id": "314871",
  "bbox": [
    9.265245,
    36.501153,
    9.265245,
    36.501153
  ],
  "description": "An ancient place, cited: BAtlas 32 D4 Ain Moungas",
  "features": [
    {
      "type": "Feature",
      "geometry": {
        "type": "Point",
        "coordinates": [
          9.265245,
          36.501153
        ]
      },
      "properties": {
        "description": "representative point"
      }
    },
    {
      "geometry": {
        "type": "Point",
        "coordinates": [
          9.265245,
          36.501153
        ]
      },
      "id": "darmc-location-23111",
      "type": "Feature",
      "properties": {
        "description": "Point location",
        "location_precision": "precise",
        "title": "DARMC location 23111",
        "link": "http://pleiades.stoa.org/places/314871/darmc-location-23111"
      }
    }
  ]
}