{
  "type": "FeatureCollection",
  "title": "Aquae Carpitanae",
  "id": "314883",
  "description": "An ancient place, cited: BAtlas 32 G3 Aquae Carpitanae",
  "bbox": [
    10.571634,
    36.799999,
    10.583333,
    36.817395
  ],
  "reprPoint": [
    10.5774835,
    36.808697
  ],
  "names": [
    "Aquae Carpitanae"
  ],
  "features": [
    {
      "geometry": {
        "type": "Point",
        "coordinates": [
          10.583333,
          36.799999
        ]
      },
      "id": "darmc-location-23759",
      "type": "Feature",
      "properties": {
        "description": "Point location",
        "location_precision": "precise",
        "title": "DARMC location 23759",
        "link": "http://pleiades.stoa.org/places/314883/darmc-location-23759"
      }
    },
    {
      "geometry": {
        "type": "Point",
        "coordinates": [
          10.571634,
          36.817395
        ]
      },
      "id": "dare-location",
      "type": "Feature",
      "properties": {
        "description": "Representative point location, site precision",
        "location_precision": "precise",
        "title": "DARE Location",
        "link": "http://pleiades.stoa.org/places/314883/dare-location"
      }
    }
  ]
}