{
  "type": "FeatureCollection",
  "title": "Avitta Bibba",
  "id": "314897",
  "bbox": [
    9.703219,
    36.409049,
    9.705953,
    36.410689
  ],
  "description": "Avitta Bibba was a settlement located in the Roman province of Africa Proconsularis.",
  "names": [
    "Avitta Bibba"
  ],
  "features": [
    {
      "type": "Feature",
      "geometry": {
        "type": "Point",
        "coordinates": [
          9.705953,
          36.409049
        ]
      },
      "properties": {
        "description": "representative point"
      }
    },
    {
      "geometry": {
        "type": "Point",
        "coordinates": [
          9.705953,
          36.409049
        ]
      },
      "id": "darmc-location-6327",
      "type": "Feature",
      "properties": {
        "description": "500K scale point location",
        "location_precision": "precise",
        "title": "DARMC location 6327",
        "link": "http://pleiades.stoa.org/places/314897/darmc-location-6327"
      }
    },
    {
      "geometry": {
        "type": "Point",
        "coordinates": [
          9.703219,
          36.410689
        ]
      },
      "id": "dare-location",
      "type": "Feature",
      "properties": {
        "description": "Representative point location, site precision",
        "location_precision": "precise",
        "title": "DARE Location",
        "link": "http://pleiades.stoa.org/places/314897/dare-location"
      }
    }
  ]
}