{
  "type": "FeatureCollection",
  "title": "Aggersel?",
  "id": "314858",
  "description": "An ancient place, cited: BAtlas 32 F4 Aggersel?",
  "bbox": [
    10.249628,
    36.145019,
    10.251882,
    36.14952
  ],
  "reprPoint": [
    10.250755,
    36.1472695
  ],
  "names": [
    "Aggersel"
  ],
  "features": [
    {
      "geometry": {
        "type": "Point",
        "coordinates": [
          10.249628,
          36.14952
        ]
      },
      "id": "darmc-location-6056",
      "type": "Feature",
      "properties": {
        "description": "500K scale point location",
        "location_precision": "precise",
        "title": "DARMC location 6056",
        "link": "http://pleiades.stoa.org/places/314858/darmc-location-6056"
      }
    },
    {
      "geometry": {
        "type": "Point",
        "coordinates": [
          10.251882,
          36.145019
        ]
      },
      "id": "dare-location",
      "type": "Feature",
      "properties": {
        "description": "Representative point location, village precision",
        "location_precision": "precise",
        "title": "DARE Location",
        "link": "http://pleiades.stoa.org/places/314858/dare-location"
      }
    }
  ]
}