{
  "type": "FeatureCollection",
  "title": "Argoub-el-Bania",
  "id": "314888",
  "description": "An ancient place, cited: BAtlas 32 C2 Argoub-el-Bania",
  "bbox": [
    8.922636,
    37.034978,
    8.922636,
    37.034978
  ],
  "reprPoint": [
    8.922636,
    37.034978
  ],
  "features": [
    {
      "geometry": {
        "type": "Point",
        "coordinates": [
          8.922636,
          37.034978
        ]
      },
      "id": "darmc-location-16278",
      "type": "Feature",
      "properties": {
        "description": "500K scale point location",
        "location_precision": "precise",
        "title": "DARMC location 16278",
        "link": "http://pleiades.stoa.org/places/314888/darmc-location-16278"
      }
    }
  ]
}