{
  "type": "FeatureCollection",
  "title": "Furnos Minus",
  "id": "314960",
  "bbox": [
    9.830048,
    36.693084,
    9.830048,
    36.693084
  ],
  "description": "An ancient place, cited: BAtlas 32 E3 Furnos Minus",
  "names": [
    "Furnos Minus"
  ],
  "features": [
    {
      "type": "Feature",
      "geometry": {
        "type": "Point",
        "coordinates": [
          9.830048,
          36.693084
        ]
      },
      "properties": {
        "description": "representative point"
      }
    },
    {
      "geometry": {
        "type": "Point",
        "coordinates": [
          9.830048,
          36.693084
        ]
      },
      "id": "darmc-location-6434",
      "type": "Feature",
      "properties": {
        "description": "500K scale point location",
        "location_precision": "precise",
        "title": "DARMC location 6434",
        "link": "http://pleiades.stoa.org/places/314960/darmc-location-6434"
      }
    }
  ]
}