{
  "type": "FeatureCollection",
  "title": "Henchir-Bou-Houia",
  "id": "314979",
  "description": "An ancient place, cited: BAtlas 32 D4 Henchir-Bou-Houia",
  "bbox": [
    9.130574,
    36.28825,
    9.130574,
    36.28825
  ],
  "reprPoint": [
    9.130574,
    36.28825
  ],
  "features": [
    {
      "geometry": {
        "type": "Point",
        "coordinates": [
          9.130574,
          36.28825
        ]
      },
      "id": "darmc-location-15032",
      "type": "Feature",
      "properties": {
        "description": "500K scale point location",
        "location_precision": "precise",
        "title": "DARMC location 15032",
        "link": "http://pleiades.stoa.org/places/314979/darmc-location-15032"
      }
    }
  ]
}