{
  "type": "FeatureCollection",
  "title": "Henchir-Douamis-es-Slitnia",
  "id": "314986",
  "description": "An ancient place, cited: BAtlas 32 D3 Henchir-Douamis-es-Slitnia",
  "bbox": [
    9.052069,
    36.857526,
    9.052069,
    36.857526
  ],
  "reprPoint": [
    9.052069,
    36.857526
  ],
  "features": [
    {
      "geometry": {
        "type": "Point",
        "coordinates": [
          9.052069,
          36.857526
        ]
      },
      "id": "darmc-location-15049",
      "type": "Feature",
      "properties": {
        "description": "500K scale point location",
        "location_precision": "precise",
        "title": "DARMC location 15049",
        "link": "http://pleiades.stoa.org/places/314986/darmc-location-15049"
      }
    }
  ]
}