{
  "type": "FeatureCollection",
  "title": "Gillium",
  "id": "314965",
  "bbox": [
    9.038332,
    36.477401,
    9.038332,
    36.477401
  ],
  "description": "An ancient place, cited: BAtlas 32 D4 Gillium",
  "names": [
    "Gillium"
  ],
  "features": [
    {
      "type": "Feature",
      "geometry": {
        "type": "Point",
        "coordinates": [
          9.038332,
          36.477401
        ]
      },
      "properties": {
        "description": "representative point"
      }
    },
    {
      "geometry": {
        "type": "Point",
        "coordinates": [
          9.038332,
          36.477401
        ]
      },
      "id": "darmc-location-6459",
      "type": "Feature",
      "properties": {
        "description": "500K scale point location",
        "location_precision": "precise",
        "title": "DARMC location 6459",
        "link": "http://pleiades.stoa.org/places/314965/darmc-location-6459"
      }
    }
  ]
}