{
  "type": "FeatureCollection",
  "title": "Douar Chabia",
  "id": "314948",
  "description": "An ancient place, cited: BAtlas 32 D3 Douar Chabia",
  "bbox": [
    9.398166,
    36.60873,
    9.398166,
    36.60873
  ],
  "reprPoint": [
    9.398166,
    36.60873
  ],
  "features": [
    {
      "geometry": {
        "type": "Point",
        "coordinates": [
          9.398166,
          36.60873
        ]
      },
      "id": "darmc-location-4874",
      "type": "Feature",
      "properties": {
        "description": "500K scale point location",
        "location_precision": "precise",
        "title": "DARMC location 4874",
        "link": "http://pleiades.stoa.org/places/314948/darmc-location-4874"
      }
    }
  ]
}