{
  "type": "FeatureCollection",
  "title": "Coreva",
  "id": "314940",
  "description": "An ancient place, cited: BAtlas 32 D3 Coreva",
  "bbox": [
    9.453447,
    36.504969,
    9.48485,
    36.512465
  ],
  "reprPoint": [
    9.4691485,
    36.508717
  ],
  "names": [
    "Coreva"
  ],
  "features": [
    {
      "geometry": {
        "type": "Point",
        "coordinates": [
          9.453447,
          36.512465
        ]
      },
      "id": "darmc-location-4845",
      "type": "Feature",
      "properties": {
        "description": "500K scale point location",
        "location_precision": "precise",
        "title": "DARMC location 4845",
        "link": "http://pleiades.stoa.org/places/314940/darmc-location-4845"
      }
    },
    {
      "geometry": {
        "type": "Point",
        "coordinates": [
          9.48485,
          36.504969
        ]
      },
      "id": "dare-location",
      "type": "Feature",
      "properties": {
        "description": "Representative point location, site precision",
        "location_precision": "precise",
        "title": "DARE Location",
        "link": "http://pleiades.stoa.org/places/314940/dare-location"
      }
    }
  ]
}