{
  "type": "FeatureCollection",
  "title": "Elephantaria?",
  "id": "314951",
  "description": "An ancient place, cited: BAtlas 32 E3 Elephantaria?",
  "bbox": [
    9.521908,
    36.645788,
    9.521908,
    36.645788
  ],
  "reprPoint": [
    9.521908,
    36.645788
  ],
  "names": [
    "Elephantaria"
  ],
  "features": [
    {
      "geometry": {
        "type": "Point",
        "coordinates": [
          9.521908,
          36.645788
        ]
      },
      "id": "darmc-location-4898",
      "type": "Feature",
      "properties": {
        "description": "500K scale point location",
        "location_precision": "precise",
        "title": "DARMC location 4898",
        "link": "http://pleiades.stoa.org/places/314951/darmc-location-4898"
      }
    }
  ]
}