{
  "type": "FeatureCollection",
  "title": "Carpi(s)",
  "id": "314920",
  "bbox": [
    10.54863,
    36.76136,
    10.557615,
    36.769129
  ],
  "description": "An ancient place, cited: BAtlas 32 G3 Carpi(s)",
  "names": [
    "Carpis",
    "Carpi"
  ],
  "features": [
    {
      "type": "Feature",
      "geometry": {
        "type": "Point",
        "coordinates": [
          10.5531225,
          36.7652445
        ]
      },
      "properties": {
        "description": "representative point"
      }
    },
    {
      "geometry": {
        "type": "Point",
        "coordinates": [
          10.54863,
          36.769129
        ]
      },
      "id": "darmc-location-5633",
      "type": "Feature",
      "properties": {
        "description": "500K scale point location",
        "location_precision": "precise",
        "title": "DARMC location 5633",
        "link": "http://pleiades.stoa.org/places/314920/darmc-location-5633"
      }
    },
    {
      "geometry": {
        "type": "Point",
        "coordinates": [
          10.557615,
          36.76136
        ]
      },
      "id": "dare-location",
      "type": "Feature",
      "properties": {
        "description": "Representative point location, site precision",
        "location_precision": "precise",
        "title": "DARE Location",
        "link": "http://pleiades.stoa.org/places/314920/dare-location"
      }
    }
  ]
}