{
  "type": "FeatureCollection",
  "title": "Henchir-Gabgab",
  "id": "314999",
  "description": "An ancient place, cited: BAtlas 32 E3 Henchir-Gabgab",
  "bbox": [
    9.740601,
    36.701581,
    9.740601,
    36.701581
  ],
  "reprPoint": [
    9.740601,
    36.701581
  ],
  "features": [
    {
      "geometry": {
        "type": "Point",
        "coordinates": [
          9.740601,
          36.701581
        ]
      },
      "id": "darmc-location-15061",
      "type": "Feature",
      "properties": {
        "description": "500K scale point location",
        "location_precision": "precise",
        "title": "DARMC location 15061",
        "link": "http://pleiades.stoa.org/places/314999/darmc-location-15061"
      }
    }
  ]
}