{
  "type": "FeatureCollection",
  "title": "Bir-Bou-Gharbel",
  "id": "314904",
  "description": "An ancient place, cited: BAtlas 32 D3 Bir-Bou-Gharbel",
  "bbox": [
    9.279857,
    36.92128,
    9.279857,
    36.92128
  ],
  "reprPoint": [
    9.279857,
    36.92128
  ],
  "features": [
    {
      "geometry": {
        "type": "Point",
        "coordinates": [
          9.279857,
          36.92128
        ]
      },
      "id": "darmc-location-16371",
      "type": "Feature",
      "properties": {
        "description": "500K scale point location",
        "location_precision": "precise",
        "title": "DARMC location 16371",
        "link": "http://pleiades.stoa.org/places/314904/darmc-location-16371"
      }
    }
  ]
}