{
  "type": "FeatureCollection",
  "title": "*Chidibbia",
  "id": "314927",
  "description": "An ancient place, cited: BAtlas 32 E3 *Chidibbia",
  "bbox": [
    9.510248,
    36.579541,
    9.510248,
    36.579541
  ],
  "reprPoint": [
    9.510248,
    36.579541
  ],
  "names": [
    "Chidibbia",
    "Pagus N(...)"
  ],
  "features": [
    {
      "geometry": {
        "type": "Point",
        "coordinates": [
          9.510248,
          36.579541
        ]
      },
      "id": "darmc-location-5650",
      "type": "Feature",
      "properties": {
        "description": "500K scale point location",
        "location_precision": "precise",
        "title": "DARMC location 5650",
        "link": "http://pleiades.stoa.org/places/314927/darmc-location-5650"
      }
    }
  ]
}