{
  "type": "FeatureCollection",
  "title": "Henchir-Ali-ben-Amara",
  "id": "314974",
  "bbox": [
    9.90359,
    36.157256,
    9.90359,
    36.157256
  ],
  "description": "An ancient place, cited: BAtlas 32 E4 Henchir-Ali-ben-Amara",
  "features": [
    {
      "type": "Feature",
      "geometry": {
        "type": "Point",
        "coordinates": [
          9.90359,
          36.157256
        ]
      },
      "properties": {
        "description": "representative point"
      }
    },
    {
      "geometry": {
        "type": "Point",
        "coordinates": [
          9.90359,
          36.157256
        ]
      },
      "id": "darmc-location-15027",
      "type": "Feature",
      "properties": {
        "description": "500K scale point location",
        "location_precision": "precise",
        "title": "DARMC location 15027",
        "link": "http://pleiades.stoa.org/places/314974/darmc-location-15027"
      }
    }
  ]
}