{
  "type": "FeatureCollection",
  "title": "Lalla Maiza",
  "id": "315059",
  "description": "An ancient place, cited: BAtlas 32 C4 Lalla Maiza",
  "bbox": [
    8.873348,
    36.394738,
    8.873348,
    36.394738
  ],
  "reprPoint": [
    8.873348,
    36.394738
  ],
  "features": [
    {
      "geometry": {
        "type": "Point",
        "coordinates": [
          8.873348,
          36.394738
        ]
      },
      "id": "darmc-location-6422",
      "type": "Feature",
      "properties": {
        "description": "500K scale point location",
        "location_precision": "precise",
        "title": "DARMC location 6422",
        "link": "http://pleiades.stoa.org/places/315059/darmc-location-6422"
      }
    }
  ]
}