{
  "type": "FeatureCollection",
  "title": "Henchir-Negachia",
  "id": "315015",
  "description": "An ancient place, cited: BAtlas 32 D3 Henchir-Negachia",
  "bbox": [
    9.256019,
    36.8345,
    9.256019,
    36.8345
  ],
  "reprPoint": [
    9.256019,
    36.8345
  ],
  "features": [
    {
      "geometry": {
        "type": "Point",
        "coordinates": [
          9.256019,
          36.8345
        ]
      },
      "id": "darmc-location-15073",
      "type": "Feature",
      "properties": {
        "description": "500K scale point location",
        "location_precision": "precise",
        "title": "DARMC location 15073",
        "link": "http://pleiades.stoa.org/places/315015/darmc-location-15073"
      }
    }
  ]
}