{
  "type": "FeatureCollection",
  "title": "Miz(…)",
  "id": "315083",
  "description": "An ancient place, cited: BAtlas 32 E4 Miz(…)",
  "bbox": [
    9.50765,
    36.421726,
    9.50765,
    36.421726
  ],
  "reprPoint": [
    9.50765,
    36.421726
  ],
  "names": [
    "Miz…",
    "Miz"
  ],
  "features": [
    {
      "geometry": {
        "type": "Point",
        "coordinates": [
          9.50765,
          36.421726
        ]
      },
      "id": "darmc-location-6757",
      "type": "Feature",
      "properties": {
        "description": "500K scale point location",
        "location_precision": "precise",
        "title": "DARMC location 6757",
        "link": "http://pleiades.stoa.org/places/315083/darmc-location-6757"
      }
    }
  ]
}