{
  "type": "FeatureCollection",
  "title": "Numluli",
  "id": "315097",
  "description": "A major settlement, cited: BAtlas 32 D3 Numluli",
  "bbox": [
    9.218381,
    36.52315,
    9.218381,
    36.52315
  ],
  "reprPoint": [
    9.218381,
    36.52315
  ],
  "names": [
    "Numluli"
  ],
  "features": [
    {
      "geometry": {
        "type": "Point",
        "coordinates": [
          9.202678,
          36.522418
        ]
      },
      "id": "darmc-location-16814",
      "type": "Feature",
      "properties": {
        "description": "500K scale point location",
        "location_precision": "precise",
        "title": "DARMC location 16814",
        "link": "http://pleiades.stoa.org/places/315097/darmc-location-16814"
      }
    },
    {
      "geometry": {
        "type": "Point",
        "coordinates": [
          9.218381,
          36.52315
        ]
      },
      "id": "dare-location",
      "type": "Feature",
      "properties": {
        "description": "Representative point location, site precision",
        "location_precision": "precise",
        "title": "DARE Location",
        "link": "http://pleiades.stoa.org/places/315097/dare-location"
      }
    }
  ]
}