{
  "type": "FeatureCollection",
  "title": "Kef-er-Rechga",
  "id": "315049",
  "description": "An ancient place, cited: BAtlas 32 D3 Kef-er-Rechga",
  "bbox": [
    9.066589,
    36.649913,
    9.066589,
    36.649913
  ],
  "reprPoint": [
    9.066589,
    36.649913
  ],
  "features": [
    {
      "geometry": {
        "type": "Point",
        "coordinates": [
          9.066589,
          36.649913
        ]
      },
      "id": "darmc-location-16392",
      "type": "Feature",
      "properties": {
        "description": "500K scale point location",
        "location_precision": "precise",
        "title": "DARMC location 16392",
        "link": "http://pleiades.stoa.org/places/315049/darmc-location-16392"
      }
    }
  ]
}