{
  "type": "FeatureCollection",
  "title": "Henchir-Manndra-el-Kedima",
  "id": "315007",
  "bbox": [
    9.284363,
    36.523959,
    9.284363,
    36.523959
  ],
  "description": "An ancient place, cited: BAtlas 32 D3 Henchir-Manndra-el-Kedima",
  "features": [
    {
      "type": "Feature",
      "geometry": {
        "type": "Point",
        "coordinates": [
          9.284363,
          36.523959
        ]
      },
      "properties": {
        "description": "representative point"
      }
    },
    {
      "geometry": {
        "type": "Point",
        "coordinates": [
          9.284363,
          36.523959
        ]
      },
      "id": "darmc-location-15067",
      "type": "Feature",
      "properties": {
        "description": "500K scale point location",
        "location_precision": "precise",
        "title": "DARMC location 15067",
        "link": "http://pleiades.stoa.org/places/315007/darmc-location-15067"
      }
    }
  ]
}