{
  "type": "FeatureCollection",
  "title": "Henchir-Teffaha",
  "id": "315032",
  "description": "An ancient place, cited: BAtlas 32 E3 Henchir-Teffaha",
  "bbox": [
    9.591841,
    36.710026,
    9.591841,
    36.710026
  ],
  "reprPoint": [
    9.591841,
    36.710026
  ],
  "features": [
    {
      "geometry": {
        "type": "Point",
        "coordinates": [
          9.591841,
          36.710026
        ]
      },
      "id": "darmc-location-15092",
      "type": "Feature",
      "properties": {
        "description": "500K scale point location",
        "location_precision": "precise",
        "title": "DARMC location 15092",
        "link": "http://pleiades.stoa.org/places/315032/darmc-location-15092"
      }
    }
  ]
}