{
  "type": "FeatureCollection",
  "title": "Ksar Tyr",
  "id": "315055",
  "description": "An ancient place, cited: BAtlas 32 E3 Ksar Tyr",
  "bbox": [
    9.796508,
    36.599712,
    9.799954,
    36.599941
  ],
  "reprPoint": [
    9.798231,
    36.5998265
  ],
  "features": [
    {
      "geometry": {
        "type": "Point",
        "coordinates": [
          9.799954,
          36.599712
        ]
      },
      "id": "darmc-location-6397",
      "type": "Feature",
      "properties": {
        "description": "500K scale point location",
        "location_precision": "precise",
        "title": "DARMC location 6397",
        "link": "http://pleiades.stoa.org/places/315055/darmc-location-6397"
      }
    },
    {
      "geometry": {
        "type": "Point",
        "coordinates": [
          9.796508,
          36.599941
        ]
      },
      "id": "dare-location",
      "type": "Feature",
      "properties": {
        "description": "Representative point location, site precision",
        "location_precision": "precise",
        "title": "DARE Location",
        "link": "http://pleiades.stoa.org/places/315055/dare-location"
      }
    }
  ]
}