{
  "type": "FeatureCollection",
  "title": "Henchir-Gastlaia",
  "id": "315001",
  "description": "An ancient place, cited: BAtlas 32 F4 Henchir-Gastlaia",
  "bbox": [
    10.388085,
    36.202753,
    10.388085,
    36.202753
  ],
  "reprPoint": [
    10.388085,
    36.202753
  ],
  "features": [
    {
      "geometry": {
        "type": "Point",
        "coordinates": [
          10.388085,
          36.202753
        ]
      },
      "id": "darmc-location-27467",
      "type": "Feature",
      "properties": {
        "description": "500K scale point location",
        "location_precision": "precise",
        "title": "DARMC location 27467",
        "link": "http://pleiades.stoa.org/places/315001/darmc-location-27467"
      }
    }
  ]
}