{
  "type": "FeatureCollection",
  "title": "Marsa Nouira",
  "id": "315069",
  "bbox": [
    9.507797,
    37.26988,
    9.507797,
    37.26988
  ],
  "description": "An ancient place, cited: BAtlas 32 E2 Marsa Nouira",
  "features": [
    {
      "type": "Feature",
      "geometry": {
        "type": "Point",
        "coordinates": [
          9.507797,
          37.26988
        ]
      },
      "properties": {
        "description": "representative point"
      }
    },
    {
      "geometry": {
        "type": "Point",
        "coordinates": [
          9.507797,
          37.26988
        ]
      },
      "id": "darmc-location-6733",
      "type": "Feature",
      "properties": {
        "description": "500K scale point location",
        "location_precision": "precise",
        "title": "DARMC location 6733",
        "link": "http://pleiades.stoa.org/places/315069/darmc-location-6733"
      }
    }
  ]
}