{
  "type": "FeatureCollection",
  "title": "Ksar-Hellal",
  "id": "315054",
  "bbox": [
    9.434393,
    36.396457,
    9.434393,
    36.396457
  ],
  "description": "An ancient place, cited: BAtlas 32 D4 Ksar-Hellal",
  "features": [
    {
      "type": "Feature",
      "geometry": {
        "type": "Point",
        "coordinates": [
          9.434393,
          36.396457
        ]
      },
      "properties": {
        "description": "representative point"
      }
    },
    {
      "geometry": {
        "type": "Point",
        "coordinates": [
          9.434393,
          36.396457
        ]
      },
      "id": "darmc-location-33614",
      "type": "Feature",
      "properties": {
        "description": "  scale point location",
        "location_precision": "precise",
        "title": "DARMC location 33614",
        "link": "http://pleiades.stoa.org/places/315054/darmc-location-33614"
      }
    }
  ]
}