{
  "type": "FeatureCollection",
  "title": "Hermaia Akra/Mercurii Pr./Kalon Akroterion?",
  "id": "315036",
  "bbox": [
    11.0416578,
    37.0836241,
    11.0416578,
    37.0836241
  ],
  "description": "Cap Bon is a peninsula of northeastern Tunisia.",
  "connectsWith": [
    "315249"
  ],
  "names": [
    "Hermaia Akra",
    "Mercurii Pr.",
    "Kalon Akroterion",
    "Cap Bon"
  ],
  "features": [
    {
      "type": "Feature",
      "geometry": {
        "type": "Point",
        "coordinates": [
          11.0416578,
          37.0836241
        ]
      },
      "properties": {
        "description": "representative point"
      }
    },
    {
      "geometry": {
        "type": "Point",
        "coordinates": [
          11.0416578,
          37.0836241
        ]
      },
      "id": "osm-location-of-cap-bon",
      "type": "Feature",
      "properties": {
        "description": "Representative point location of the cape based on OpenStreetMap.",
        "location_precision": "precise",
        "title": "OSM location of Cap Bon",
        "link": "http://pleiades.stoa.org/places/315036/osm-location-of-cap-bon"
      }
    }
  ]
}