{
  "type": "FeatureCollection",
  "title": "Hippo Diarrhytus",
  "id": "315038",
  "bbox": [
    9.873108,
    37.276147,
    9.873108,
    37.276147
  ],
  "description": "Hippo Diarrhytus was an ancient port located on the coast of North Africa. The site is now occupied by the city of Bizerte in Tunisia.",
  "names": [
    "Hippo Diarrhytus"
  ],
  "features": [
    {
      "type": "Feature",
      "geometry": {
        "type": "Point",
        "coordinates": [
          9.873108,
          37.276147
        ]
      },
      "properties": {
        "description": "representative point"
      }
    },
    {
      "geometry": {
        "type": "Point",
        "coordinates": [
          9.873108,
          37.276147
        ]
      },
      "id": "darmc-location-5094",
      "type": "Feature",
      "properties": {
        "description": "500K scale point location",
        "location_precision": "precise",
        "title": "DARMC location 5094",
        "link": "http://pleiades.stoa.org/places/315038/darmc-location-5094"
      }
    }
  ]
}