{
  "type": "FeatureCollection",
  "title": "Henchir-Semmech",
  "id": "315020",
  "description": "An ancient place, cited: BAtlas 32 C4 Henchir-Semmech",
  "bbox": [
    8.961653,
    36.405098,
    8.961653,
    36.405098
  ],
  "reprPoint": [
    8.961653,
    36.405098
  ],
  "features": [
    {
      "geometry": {
        "type": "Point",
        "coordinates": [
          8.961653,
          36.405098
        ]
      },
      "id": "darmc-location-15078",
      "type": "Feature",
      "properties": {
        "description": "500K scale point location",
        "location_precision": "precise",
        "title": "DARMC location 15078",
        "link": "http://pleiades.stoa.org/places/315020/darmc-location-15078"
      }
    }
  ]
}