{
  "type": "FeatureCollection",
  "title": "*Naro/Aquae Persianae",
  "id": "315092",
  "description": "An ancient place, cited: BAtlas 32 F3 *Naro/Aquae Persianae",
  "bbox": [
    10.327692,
    36.731005,
    10.327692,
    36.731005
  ],
  "reprPoint": [
    10.327692,
    36.731005
  ],
  "names": [
    "Naro",
    "Aquae Persianae"
  ],
  "features": [
    {
      "geometry": {
        "type": "Point",
        "coordinates": [
          10.327692,
          36.731005
        ]
      },
      "id": "darmc-location-6786",
      "type": "Feature",
      "properties": {
        "description": "500K scale point location",
        "location_precision": "precise",
        "title": "DARMC location 6786",
        "link": "http://pleiades.stoa.org/places/315092/darmc-location-6786"
      }
    }
  ]
}