{
  "type": "FeatureCollection",
  "title": "Rusucmona?/Castra Delia",
  "id": "315132",
  "description": "An ancient place, cited: BAtlas 32 F2 Rusucmona?/Castra Delia",
  "bbox": [
    10.183586,
    37.166532,
    10.248117,
    37.170466
  ],
  "reprPoint": [
    10.2075612333,
    37.1687016
  ],
  "names": [
    "Rusucmona",
    "Castra Delia"
  ],
  "features": [
    {
      "geometry": {
        "type": "Point",
        "coordinates": [
          10.248117,
          37.170466
        ]
      },
      "id": "darmc-location-955",
      "type": "Feature",
      "properties": {
        "description": "500K scale point location",
        "location_precision": "precise",
        "title": "DARMC location 955",
        "link": "http://pleiades.stoa.org/places/315132/darmc-location-955"
      }
    },
    {
      "geometry": {
        "type": "Point",
        "coordinates": [
          10.183586,
          37.166532
        ]
      },
      "id": "darmc-location-5017",
      "type": "Feature",
      "properties": {
        "description": "500K scale point location",
        "location_precision": "precise",
        "title": "DARMC location 5017",
        "link": "http://pleiades.stoa.org/places/315132/darmc-location-5017"
      }
    }
  ]
}