{
  "type": "FeatureCollection",
  "title": "Ras-el-Kasba",
  "id": "315127",
  "description": "An ancient place, cited: BAtlas 32 D3 Ras-el-Kasba",
  "bbox": [
    9.043874,
    36.969765,
    9.043874,
    36.969765
  ],
  "reprPoint": [
    9.043874,
    36.969765
  ],
  "features": [
    {
      "geometry": {
        "type": "Point",
        "coordinates": [
          9.043874,
          36.969765
        ]
      },
      "id": "darmc-location-27570",
      "type": "Feature",
      "properties": {
        "description": "500K scale point location",
        "location_precision": "precise",
        "title": "DARMC location 27570",
        "link": "http://pleiades.stoa.org/places/315127/darmc-location-27570"
      }
    }
  ]
}