{
  "type": "FeatureCollection",
  "title": "Saltus Domitianus",
  "id": "315138",
  "bbox": [
    9.181016,
    36.597924,
    9.181016,
    36.597924
  ],
  "description": "An ancient place, cited: BAtlas 32 D3 Saltus Domitianus",
  "names": [
    "Saltus Domitianus"
  ],
  "features": [
    {
      "type": "Feature",
      "geometry": {
        "type": "Point",
        "coordinates": [
          9.181016,
          36.597924
        ]
      },
      "properties": {
        "description": "representative point"
      }
    },
    {
      "geometry": {
        "type": "Point",
        "coordinates": [
          9.181016,
          36.597924
        ]
      },
      "id": "darmc-location-17709",
      "type": "Feature",
      "properties": {
        "description": "500K scale point location",
        "location_precision": "precise",
        "title": "DARMC location 17709",
        "link": "http://pleiades.stoa.org/places/315138/darmc-location-17709"
      }
    }
  ]
}