{
  "type": "FeatureCollection",
  "title": "Sisara Limne",
  "id": "315175",
  "bbox": [
    9.666667,
    37.166667,
    9.666667,
    37.166667
  ],
  "description": "Sisara Limne (Ichkeul Lake).",
  "names": [
    "Sisara Limne"
  ],
  "features": [
    {
      "type": "Feature",
      "geometry": {
        "type": "Point",
        "coordinates": [
          9.666667,
          37.166667
        ]
      },
      "properties": {
        "description": "representative point"
      }
    },
    {
      "geometry": {
        "type": "Point",
        "coordinates": [
          9.666667,
          37.166667
        ]
      },
      "id": "location-of-sisara-limne",
      "type": "Feature",
      "properties": {
        "description": "coordinates after GeoHack, verified in Google Earth 2013.",
        "location_precision": "precise",
        "title": "location of Sisara Limne",
        "link": "http://pleiades.stoa.org/places/315175/location-of-sisara-limne"
      }
    }
  ]
}