{
  "type": "FeatureCollection",
  "title": "Sidi-Medine-el-Aala",
  "id": "315167",
  "description": "An ancient place, cited: BAtlas 32 F4 Sidi-Medine-el-Aala",
  "bbox": [
    10.086446,
    36.348383,
    10.086446,
    36.348383
  ],
  "reprPoint": [
    10.086446,
    36.348383
  ],
  "features": [
    {
      "geometry": {
        "type": "Point",
        "coordinates": [
          10.086446,
          36.348383
        ]
      },
      "id": "darmc-location-15346",
      "type": "Feature",
      "properties": {
        "description": "500K scale point location",
        "location_precision": "precise",
        "title": "DARMC location 15346",
        "link": "http://pleiades.stoa.org/places/315167/darmc-location-15346"
      }
    }
  ]
}