{
  "type": "FeatureCollection",
  "title": "Pagus Ma(...)rensium",
  "id": "315105",
  "description": "An ancient place, cited: BAtlas 32 B3 Pagus Ma(...)rensium",
  "bbox": [
    8.489912,
    36.742692,
    8.489912,
    36.742692
  ],
  "reprPoint": [
    8.489912,
    36.742692
  ],
  "names": [
    "Pagus Ma(...)rensium"
  ],
  "features": [
    {
      "geometry": {
        "type": "Point",
        "coordinates": [
          8.489912,
          36.742692
        ]
      },
      "id": "darmc-location-6836",
      "type": "Feature",
      "properties": {
        "description": "500K scale point location",
        "location_precision": "precise",
        "title": "DARMC location 6836",
        "link": "http://pleiades.stoa.org/places/315105/darmc-location-6836"
      }
    }
  ]
}