{
  "type": "FeatureCollection",
  "title": "Praedia Pullaienorum",
  "id": "315118",
  "bbox": [
    9.120605,
    36.43235,
    9.120605,
    36.43235
  ],
  "description": "An ancient place, cited: BAtlas 32 D4 Praedia Pullaienorum",
  "names": [
    "Praedia Pullaienorum"
  ],
  "features": [
    {
      "type": "Feature",
      "geometry": {
        "type": "Point",
        "coordinates": [
          9.120605,
          36.43235
        ]
      },
      "properties": {
        "description": "representative point"
      }
    },
    {
      "geometry": {
        "type": "Point",
        "coordinates": [
          9.120605,
          36.43235
        ]
      },
      "id": "darmc-location-17706",
      "type": "Feature",
      "properties": {
        "description": "500K scale point location",
        "location_precision": "precise",
        "title": "DARMC location 17706",
        "link": "http://pleiades.stoa.org/places/315118/darmc-location-17706"
      }
    }
  ]
}