{
  "type": "FeatureCollection",
  "title": "Pulchri/Apollinis Pr.",
  "id": "315120",
  "bbox": [
    10.2804885,
    37.1776656,
    10.2804885,
    37.1776656
  ],
  "description": "An ancient place, cited: BAtlas 32 F2 Pulchri/Apollinis Pr.",
  "names": [
    "Pulchri",
    "Apollinis Pr."
  ],
  "features": [
    {
      "type": "Feature",
      "geometry": {
        "type": "Point",
        "coordinates": [
          10.2804885,
          37.1776656
        ]
      },
      "properties": {
        "description": "representative point"
      }
    },
    {
      "geometry": {
        "type": "Point",
        "coordinates": [
          10.2804885,
          37.1776656
        ]
      },
      "id": "osm-location-of-cap-farina",
      "type": "Feature",
      "properties": {
        "description": "Location based on OpenStreetMap",
        "location_precision": "precise",
        "title": "OSM location of Cap Farina",
        "link": "http://pleiades.stoa.org/places/315120/osm-location-of-cap-farina"
      }
    }
  ]
}