{
  "type": "FeatureCollection",
  "title": "Pagus Suttuensis",
  "id": "315108",
  "bbox": [
    8.421198,
    36.418637,
    8.421198,
    36.418637
  ],
  "description": "An ancient place, cited: BAtlas 32 D4 Pagus Suttuensis",
  "names": [
    "Pagus Suttuensis"
  ],
  "features": [
    {
      "type": "Feature",
      "geometry": {
        "type": "Point",
        "coordinates": [
          8.421198,
          36.418637
        ]
      },
      "properties": {
        "description": "representative point"
      }
    },
    {
      "geometry": {
        "type": "Point",
        "coordinates": [
          8.421198,
          36.418637
        ]
      },
      "id": "darmc-location-6838",
      "type": "Feature",
      "properties": {
        "description": "500K scale point location",
        "location_precision": "precise",
        "title": "DARMC location 6838",
        "link": "http://pleiades.stoa.org/places/315108/darmc-location-6838"
      }
    }
  ]
}