{
  "type": "FeatureCollection",
  "title": "Praedia Rufii Volusiani",
  "id": "315119",
  "description": "An ancient place, cited: BAtlas 32 D4 Praedia Rufii Volusiani",
  "bbox": [
    9.291762,
    36.464686,
    9.291762,
    36.464686
  ],
  "reprPoint": [
    9.291762,
    36.464686
  ],
  "names": [
    "Praedia Rufii Volusiani"
  ],
  "features": [
    {
      "geometry": {
        "type": "Point",
        "coordinates": [
          9.291762,
          36.464686
        ]
      },
      "id": "darmc-location-27561",
      "type": "Feature",
      "properties": {
        "description": "500K scale point location",
        "location_precision": "precise",
        "title": "DARMC location 27561",
        "link": "http://pleiades.stoa.org/places/315119/darmc-location-27561"
      }
    }
  ]
}