{
  "type": "FeatureCollection",
  "title": "*Seressi",
  "id": "315150",
  "bbox": [
    9.773609,
    36.166741,
    9.773609,
    36.166741
  ],
  "description": "An ancient place, cited: BAtlas 32 E4 *Seressi",
  "names": [
    "Seressi"
  ],
  "features": [
    {
      "type": "Feature",
      "geometry": {
        "type": "Point",
        "coordinates": [
          9.773609,
          36.166741
        ]
      },
      "properties": {
        "description": "representative point"
      }
    },
    {
      "geometry": {
        "type": "Point",
        "coordinates": [
          9.773609,
          36.166741
        ]
      },
      "id": "darmc-location-5328",
      "type": "Feature",
      "properties": {
        "description": "500K scale point location",
        "location_precision": "precise",
        "title": "DARMC location 5328",
        "link": "http://pleiades.stoa.org/places/315150/darmc-location-5328"
      }
    }
  ]
}