{
  "type": "FeatureCollection",
  "title": "Segermes",
  "id": "315147",
  "bbox": [
    10.301692,
    36.345023,
    10.301692,
    36.345023
  ],
  "description": "An ancient place, cited: BAtlas 32 F4 Segermes",
  "names": [
    "Segermes"
  ],
  "features": [
    {
      "type": "Feature",
      "geometry": {
        "type": "Point",
        "coordinates": [
          10.301692,
          36.345023
        ]
      },
      "properties": {
        "description": "representative point"
      }
    },
    {
      "geometry": {
        "type": "Point",
        "coordinates": [
          10.301692,
          36.345023
        ]
      },
      "id": "darmc-location-977",
      "type": "Feature",
      "properties": {
        "description": "500K scale point location",
        "location_precision": "precise",
        "title": "DARMC location 977",
        "link": "http://pleiades.stoa.org/places/315147/darmc-location-977"
      }
    }
  ]
}