{
  "type": "FeatureCollection",
  "title": "Sululos",
  "id": "315178",
  "description": "An ancient place, cited: BAtlas 32 E4 Sululos",
  "bbox": [
    9.605158,
    36.461372,
    9.605158,
    36.461372
  ],
  "reprPoint": [
    9.605158,
    36.461372
  ],
  "names": [
    "Sululos"
  ],
  "features": [
    {
      "geometry": {
        "type": "Point",
        "coordinates": [
          9.605158,
          36.461372
        ]
      },
      "id": "darmc-location-5381",
      "type": "Feature",
      "properties": {
        "description": "500K scale point location",
        "location_precision": "precise",
        "title": "DARMC location 5381",
        "link": "http://pleiades.stoa.org/places/315178/darmc-location-5381"
      }
    }
  ]
}