{
  "type": "FeatureCollection",
  "title": "Tapphugabe(n)sis",
  "id": "315185",
  "description": "An ancient place, cited: BAtlas 32 E4 Tapphugabe(n)sis",
  "bbox": [
    9.525144,
    36.287237,
    9.525144,
    36.287237
  ],
  "reprPoint": [
    9.525144,
    36.287237
  ],
  "names": [
    "Tapphugabensis",
    "Tapphugabesis"
  ],
  "features": [
    {
      "geometry": {
        "type": "Point",
        "coordinates": [
          9.525144,
          36.287237
        ]
      },
      "id": "darmc-location-6896",
      "type": "Feature",
      "properties": {
        "description": "500K scale point location",
        "location_precision": "precise",
        "title": "DARMC location 6896",
        "link": "http://pleiades.stoa.org/places/315185/darmc-location-6896"
      }
    }
  ]
}