{
  "type": "FeatureCollection",
  "title": "Saltus Lamianus",
  "id": "315139",
  "bbox": [
    9.24277,
    36.605963,
    9.24277,
    36.605963
  ],
  "description": "An ancient place, cited: BAtlas 32 D3 Saltus Lamianus",
  "names": [
    "Saltus Lamianus"
  ],
  "features": [
    {
      "type": "Feature",
      "geometry": {
        "type": "Point",
        "coordinates": [
          9.24277,
          36.605963
        ]
      },
      "properties": {
        "description": "representative point"
      }
    },
    {
      "geometry": {
        "type": "Point",
        "coordinates": [
          9.24277,
          36.605963
        ]
      },
      "id": "darmc-location-17710",
      "type": "Feature",
      "properties": {
        "description": "500K scale point location",
        "location_precision": "precise",
        "title": "DARMC location 17710",
        "link": "http://pleiades.stoa.org/places/315139/darmc-location-17710"
      }
    }
  ]
}