{
  "type": "FeatureCollection",
  "title": "Zigira",
  "id": "315270",
  "description": "An ancient place, cited: BAtlas 32 D3 Zigira",
  "bbox": [
    9.400005,
    36.600011,
    9.400005,
    36.600011
  ],
  "reprPoint": [
    9.400005,
    36.600011
  ],
  "names": [
    "Zigira"
  ],
  "features": [
    {
      "geometry": {
        "type": "Point",
        "coordinates": [
          9.400005,
          36.600011
        ]
      },
      "id": "darmc-location-6574",
      "type": "Feature",
      "properties": {
        "description": "500K scale point location",
        "location_precision": "precise",
        "title": "DARMC location 6574",
        "link": "http://pleiades.stoa.org/places/315270/darmc-location-6574"
      }
    }
  ]
}