{
  "type": "FeatureCollection",
  "title": "Vallis",
  "id": "315254",
  "bbox": [
    9.7466495,
    36.6248409,
    9.7466495,
    36.6248409
  ],
  "description": "An ancient place, associated by scholars with archaeological remains observed at Henchir Ballich near Sidi-Mediene in Tunisia.",
  "names": [
    "Sidi-Mediene",
    "Henchir Ballich",
    "Vallis"
  ],
  "features": [
    {
      "type": "Feature",
      "geometry": {
        "type": "Point",
        "coordinates": [
          9.7466495,
          36.6248409
        ]
      },
      "properties": {
        "description": "representative point"
      }
    },
    {
      "geometry": {
        "type": "Point",
        "coordinates": [
          9.7466495,
          36.6248409
        ]
      },
      "id": "osm-location-of-sidi-medien",
      "type": "Feature",
      "properties": {
        "description": "Location based on OpenStreetMap",
        "location_precision": "precise",
        "title": "OSM location of Sidi Medien",
        "link": "http://pleiades.stoa.org/places/315254/osm-location-of-sidi-medien"
      }
    }
  ]
}