{
  "type": "FeatureCollection",
  "title": "Thuraria",
  "id": "315227",
  "bbox": [
    9.940136,
    36.834925,
    9.940136,
    36.834925
  ],
  "description": "An ancient place, cited: BAtlas 32 E3 Thuraria",
  "names": [
    "Thuraria"
  ],
  "features": [
    {
      "type": "Feature",
      "geometry": {
        "type": "Point",
        "coordinates": [
          9.940136,
          36.834925
        ]
      },
      "properties": {
        "description": "representative point"
      }
    },
    {
      "geometry": {
        "type": "Point",
        "coordinates": [
          9.940136,
          36.834925
        ]
      },
      "id": "darmc-location-8642",
      "type": "Feature",
      "properties": {
        "description": "500K scale point location",
        "location_precision": "precise",
        "title": "DARMC location 8642",
        "link": "http://pleiades.stoa.org/places/315227/darmc-location-8642"
      }
    }
  ]
}