{
  "type": "FeatureCollection",
  "title": "Uzalis",
  "id": "315251",
  "bbox": [
    10.033986,
    37.169048,
    10.033986,
    37.169048
  ],
  "description": "An ancient place, cited: BAtlas 32 F2 Uzalis",
  "names": [
    "Uzalis"
  ],
  "features": [
    {
      "type": "Feature",
      "geometry": {
        "type": "Point",
        "coordinates": [
          10.033986,
          37.169048
        ]
      },
      "properties": {
        "description": "representative point"
      }
    },
    {
      "geometry": {
        "type": "Point",
        "coordinates": [
          10.033986,
          37.169048
        ]
      },
      "id": "darmc-location-6515",
      "type": "Feature",
      "properties": {
        "description": "500K scale point location",
        "location_precision": "precise",
        "title": "DARMC location 6515",
        "link": "http://pleiades.stoa.org/places/315251/darmc-location-6515"
      }
    }
  ]
}