{
  "type": "FeatureCollection",
  "title": "Zucchari(...)",
  "id": "315273",
  "description": "An ancient place, cited: BAtlas 32 E4 Zucchari(...)",
  "bbox": [
    9.983274,
    36.233215,
    9.983274,
    36.233215
  ],
  "reprPoint": [
    9.983274,
    36.233215
  ],
  "names": [
    "Zucchari(...)"
  ],
  "features": [
    {
      "geometry": {
        "type": "Point",
        "coordinates": [
          9.983274,
          36.233215
        ]
      },
      "id": "darmc-location-6576",
      "type": "Feature",
      "properties": {
        "description": "500K scale point location",
        "location_precision": "precise",
        "title": "DARMC location 6576",
        "link": "http://pleiades.stoa.org/places/315273/darmc-location-6576"
      }
    }
  ]
}