{
  "type": "FeatureCollection",
  "title": "Zucchari(...)",
  "id": "315273",
  "bbox": [
    9.9622488,
    36.2626668,
    9.9622488,
    36.2626668
  ],
  "description": "An ancient place, cited: BAtlas 32 E4 Zucchari(...)",
  "connectsWith": [
    "183817904"
  ],
  "names": [
    "Zucchari(...)"
  ],
  "features": [
    {
      "type": "Feature",
      "geometry": {
        "type": "Point",
        "coordinates": [
          9.9622488,
          36.2626668
        ]
      },
      "properties": {
        "description": "representative point"
      }
    },
    {
      "geometry": {
        "type": "Point",
        "coordinates": [
          9.9622488,
          36.2626668
        ]
      },
      "id": "osm-location-of-modern-bent-saidane",
      "type": "Feature",
      "properties": {
        "description": "Location based on OpenStreetMap",
        "location_precision": "precise",
        "title": "OSM Location of modern Bent-Saidane",
        "link": "http://pleiades.stoa.org/places/315273/osm-location-of-modern-bent-saidane"
      }
    }
  ]
}