{
  "type": "FeatureCollection",
  "title": "Thibari",
  "id": "315201",
  "description": "An ancient place, cited: BAtlas 32 D4 Thibari",
  "bbox": [
    9.083041,
    36.505393,
    9.083041,
    36.505393
  ],
  "reprPoint": [
    9.083041,
    36.505393
  ],
  "names": [
    "Thibari"
  ],
  "features": [
    {
      "geometry": {
        "type": "Point",
        "coordinates": [
          9.083041,
          36.505393
        ]
      },
      "id": "dare-location",
      "type": "Feature",
      "properties": {
        "description": "Representative point location, site precision",
        "location_precision": "precise",
        "title": "DARE Location",
        "link": "http://pleiades.stoa.org/places/315201/dare-location"
      }
    }
  ]
}