{
  "type": "FeatureCollection",
  "title": "Thibicaae",
  "id": "315202",
  "bbox": [
    9.791064,
    36.322229,
    9.791064,
    36.322229
  ],
  "description": "An ancient place, cited: BAtlas 32 E4 Thibicaae",
  "names": [
    "Thibicaae"
  ],
  "features": [
    {
      "type": "Feature",
      "geometry": {
        "type": "Point",
        "coordinates": [
          9.791064,
          36.322229
        ]
      },
      "properties": {
        "description": "representative point"
      }
    },
    {
      "geometry": {
        "type": "Point",
        "coordinates": [
          9.791064,
          36.322229
        ]
      },
      "id": "darmc-location-6461",
      "type": "Feature",
      "properties": {
        "description": "500K scale point location",
        "location_precision": "precise",
        "title": "DARMC location 6461",
        "link": "http://pleiades.stoa.org/places/315202/darmc-location-6461"
      }
    }
  ]
}