{
  "type": "FeatureCollection",
  "title": "Turris",
  "id": "315236",
  "bbox": [
    9.793709,
    36.656954,
    9.793709,
    36.656954
  ],
  "description": "An ancient place, cited: BAtlas 32 E3 Turris",
  "names": [
    "Turris"
  ],
  "features": [
    {
      "type": "Feature",
      "geometry": {
        "type": "Point",
        "coordinates": [
          9.793709,
          36.656954
        ]
      },
      "properties": {
        "description": "representative point"
      }
    },
    {
      "geometry": {
        "type": "Point",
        "coordinates": [
          9.793709,
          36.656954
        ]
      },
      "id": "darmc-location-6498",
      "type": "Feature",
      "properties": {
        "description": "500K scale point location",
        "location_precision": "precise",
        "title": "DARMC location 6498",
        "link": "http://pleiades.stoa.org/places/315236/darmc-location-6498"
      }
    }
  ]
}