{
  "type": "FeatureCollection",
  "title": "Thisiduo",
  "id": "315214",
  "bbox": [
    9.667333,
    36.680351,
    9.667333,
    36.680351
  ],
  "description": "An ancient place, cited: BAtlas 32 E3 Thisiduo",
  "names": [
    "Thisiduo"
  ],
  "features": [
    {
      "type": "Feature",
      "geometry": {
        "type": "Point",
        "coordinates": [
          9.667333,
          36.680351
        ]
      },
      "properties": {
        "description": "representative point"
      }
    },
    {
      "geometry": {
        "type": "Point",
        "coordinates": [
          9.667333,
          36.680351
        ]
      },
      "id": "darmc-location-6471",
      "type": "Feature",
      "properties": {
        "description": "500K scale point location",
        "location_precision": "precise",
        "title": "DARMC location 6471",
        "link": "http://pleiades.stoa.org/places/315214/darmc-location-6471"
      }
    }
  ]
}