{
  "type": "FeatureCollection",
  "title": "Vasidice?",
  "id": "315255",
  "description": "An ancient place, cited: BAtlas 32 A4 Vasidice?",
  "bbox": [
    7.96098,
    36.151796,
    7.96098,
    36.151796
  ],
  "reprPoint": [
    7.96098,
    36.151796
  ],
  "names": [
    "Vasidice"
  ],
  "features": [
    {
      "geometry": {
        "type": "Point",
        "coordinates": [
          7.96098,
          36.151796
        ]
      },
      "id": "darmc-location-6528",
      "type": "Feature",
      "properties": {
        "description": "500K scale point location",
        "location_precision": "precise",
        "title": "DARMC location 6528",
        "link": "http://pleiades.stoa.org/places/315255/darmc-location-6528"
      }
    }
  ]
}