{
  "type": "FeatureCollection",
  "title": "Temple of Zeus at Olympia",
  "id": "316294900",
  "bbox": [
    21.630049,
    37.637807,
    21.630049,
    37.637807
  ],
  "description": "The Temple of Zeus at Olympia was built in the second quarter of the fifth century B.C. Libon of Elis served as architect.",
  "connectsWith": [
    "570531"
  ],
  "features": [
    {
      "type": "Feature",
      "geometry": {
        "type": "Point",
        "coordinates": [
          21.630049,
          37.637807
        ]
      },
      "properties": {
        "description": "representative point"
      }
    },
    {
      "geometry": {
        "type": "Point",
        "coordinates": [
          21.630049,
          37.637807
        ]
      },
      "id": "center-of-the-temple-of-zeus-at-olympia",
      "type": "Feature",
      "properties": {
        "description": null,
        "location_precision": "precise",
        "title": "Center of the Temple of Zeus at Olympia",
        "link": "http://pleiades.stoa.org/places/316294900/center-of-the-temple-of-zeus-at-olympia"
      }
    }
  ]
}