{
  "type": "FeatureCollection",
  "title": "Tab캐lu (province)",
  "id": "316924422",
  "bbox": [
    34.572513,
    37.82365,
    34.572513,
    37.82365
  ],
  "description": "In 713 BC, Tabal (together with the reigion Bit-Puruta코) was conquered by the Assyrian king Sargon II (r. 721-705 BC) and established as an Assyrian province. However, by 711 BC, Assyria lost control over the region of Tab캐lu.",
  "connectsWith": [
    "29492"
  ],
  "names": [
    "Tab캐lu"
  ],
  "features": [
    {
      "type": "Feature",
      "geometry": {
        "type": "Point",
        "coordinates": [
          34.572513,
          37.82365
        ]
      },
      "properties": {
        "description": "representative point"
      }
    },
    {
      "geometry": {
        "type": "Point",
        "coordinates": [
          34.572513,
          37.82365
        ]
      },
      "id": "representative-location-of-tabal",
      "type": "Feature",
      "properties": {
        "description": "Representative point of Tabal is based on the Helsinki Atlas.",
        "location_precision": "precise",
        "title": "Representative location of Tabal ",
        "link": "http://pleiades.stoa.org/places/316924422/representative-location-of-tabal"
      }
    }
  ]
}