{
  "type": "FeatureCollection",
  "title": "Untitled",
  "id": "317862",
  "description": "An ancient place, cited: BAtlas 32 G4 unnamed bridge (SW Pupput)",
  "bbox": [
    10.493508,
    36.322191,
    10.493508,
    36.322191
  ],
  "reprPoint": [
    10.493508,
    36.322191
  ],
  "features": [
    {
      "geometry": {
        "type": "Point",
        "coordinates": [
          10.493508,
          36.322191
        ]
      },
      "id": "darmc-location-14412",
      "type": "Feature",
      "properties": {
        "description": "500K scale point location",
        "location_precision": "precise",
        "title": "DARMC location 14412",
        "link": "http://pleiades.stoa.org/places/317862/darmc-location-14412"
      }
    }
  ]
}