{
  "type": "FeatureCollection",
  "title": "Untitled",
  "id": "319378",
  "bbox": [
    8.044696,
    36.174195,
    9.1514742,
    36.336066
  ],
  "description": "Musti → Sicca Veneria → Naraggara → Thagura → Map 31",
  "features": [
    {
      "type": "Feature",
      "geometry": {
        "type": "Point",
        "coordinates": [
          8.56506765,
          36.2285303375
        ]
      },
      "properties": {
        "description": "representative point"
      }
    }
  ]
}