{
  "type": "FeatureCollection",
  "title": "Dicle Tüneli",
  "id": "319653209",
  "bbox": [
    40.5491,
    38.5292,
    40.5491,
    38.5292
  ],
  "description": "Tigris tunnel, a cave of about 750m in which are rock reliefs.",
  "features": [
    {
      "type": "Feature",
      "geometry": {
        "type": "Point",
        "coordinates": [
          40.5491,
          38.5292
        ]
      },
      "properties": {
        "description": "representative point"
      }
    },
    {
      "geometry": {
        "type": "Point",
        "coordinates": [
          40.5491,
          38.5292
        ]
      },
      "id": "cigs-location-of-dicle-tuneli",
      "type": "Feature",
      "properties": {
        "description": null,
        "location_precision": "precise",
        "title": "CIGS location of Dicle Tüneli",
        "link": "http://pleiades.stoa.org/places/319653209/cigs-location-of-dicle-tuneli"
      }
    }
  ]
}