{
  "type": "FeatureCollection",
  "title": "Medinet Habu",
  "id": "321318358",
  "description": "The New Kingdom mortuary temple of Ramesses III at Medinet Habu, on the West bank of the Nile near Luxor.",
  "bbox": [
    32.599093,
    25.7198222222,
    32.6006719574,
    25.7202066
  ],
  "connectsWith": [
    "786067",
    "727172"
  ],
  "reprPoint": [
    32.5998824787,
    25.7200144111
  ],
  "names": [
    "Medinet Habu"
  ],
  "features": [
    {
      "geometry": {
        "type": "Point",
        "coordinates": [
          32.599093,
          25.7202066
        ]
      },
      "id": "northwest-corner-of-mortuary-temple-of-ramesses-iii",
      "type": "Feature",
      "properties": {
        "description": "Location based on OpenStreetMap",
        "location_precision": "precise",
        "title": "Northwest Corner of Mortuary Temple of Ramesses III",
        "link": "http://pleiades.stoa.org/places/321318358/northwest-corner-of-mortuary-temple-of-ramesses-iii"
      }
    },
    {
      "geometry": {
        "type": "Point",
        "coordinates": [
          32.60067195737604,
          25.71982222222222,
          80.80506411125747
        ]
      },
      "id": "location_of_medinet-habu",
      "type": "Feature",
      "properties": {
        "description": "The mortuary temple of Ramesses III at Medinet Habu.",
        "location_precision": "precise",
        "title": "Location of Medinet Habu",
        "link": "http://pleiades.stoa.org/places/321318358/location_of_medinet-habu"
      }
    }
  ]
}