{
  "type": "FeatureCollection",
  "title": "Norton Fitzwarren",
  "id": "322248810",
  "bbox": [
    -3.1687191,
    51.0271813,
    -3.1687191,
    51.0271813
  ],
  "description": "The site of a temporary Roman camp.",
  "features": [
    {
      "type": "Feature",
      "geometry": {
        "type": "Point",
        "coordinates": [
          -3.1687191,
          51.0271813
        ]
      },
      "properties": {
        "description": "representative point"
      }
    },
    {
      "geometry": {
        "type": "Point",
        "coordinates": [
          -3.1687191,
          51.0271813
        ]
      },
      "id": "osm-location-of-norton-fitzwarren-roman-temporary",
      "type": "Feature",
      "properties": {
        "description": "Representative location based on OpenStreetMap",
        "location_precision": "precise",
        "title": "OSM location of Norton Fitzwarren Roman Temporary Camp",
        "link": "http://pleiades.stoa.org/places/322248810/osm-location-of-norton-fitzwarren-roman-temporary"
      }
    }
  ]
}