{
  "type": "FeatureCollection",
  "title": "Santi Quattro Coronati",
  "id": "323041298",
  "bbox": [
    12.4979981,
    41.8883327,
    12.4979981,
    41.8883327
  ],
  "description": "Santi Quattro Coronati is an early Christian basilica on Rome's Caelian Hill begun by Pope Miltiades in the fourth century A.D.",
  "connectsWith": [
    "695491849",
    "423025"
  ],
  "names": [
    "Basilica dei Santi Quattro Coronati"
  ],
  "features": [
    {
      "type": "Feature",
      "geometry": {
        "type": "Point",
        "coordinates": [
          12.4979981,
          41.8883327
        ]
      },
      "properties": {
        "description": "representative point"
      }
    },
    {
      "geometry": {
        "type": "Point",
        "coordinates": [
          12.4979981,
          41.8883327
        ]
      },
      "id": "location-of-basilica",
      "type": "Feature",
      "properties": {
        "description": "Representative location based on OpenStreetMap.",
        "location_precision": "precise",
        "title": "OSM location of Basilica dei Ss. Quattro Coronati",
        "link": "http://pleiades.stoa.org/places/323041298/location-of-basilica"
      }
    }
  ]
}