{
  "type": "FeatureCollection",
  "title": "Ekadima",
  "id": "323375925",
  "bbox": [
    44.415448,
    32.532802,
    44.415448,
    32.532802
  ],
  "description": "The temple of the god Belili, Ekadima (“House Which Creates ...”), was located in the Kumar district of Babylon, in the western half of the inner city. According to the Babylonian topographical text Tintir = Babylon Tablet IV, it was one of seven temples in that part of Babylon.",
  "connectsWith": [
    "893951",
    "633091639"
  ],
  "names": [
    "Ekadima",
    "bīt Belili"
  ],
  "features": [
    {
      "type": "Feature",
      "geometry": {
        "type": "Point",
        "coordinates": [
          44.415448,
          32.532802
        ]
      },
      "properties": {
        "description": "representative point"
      }
    }
  ]
}