{
  "type": "FeatureCollection",
  "title": "Nuraghe Ruggiu",
  "id": "32331671",
  "description": "A nuragic site located near Pozzomaggiore, Sardinia.",
  "bbox": [
    8.67333,
    40.3948882,
    8.67333,
    40.3948882
  ],
  "connectsWith": [
    "472014"
  ],
  "reprPoint": [
    8.67333,
    40.3948882
  ],
  "features": [
    {
      "geometry": {
        "type": "Point",
        "coordinates": [
          8.67333,
          40.3948882
        ]
      },
      "id": "location-of-nuraghe-ruggiu",
      "type": "Feature",
      "properties": {
        "description": "Representative location based on OpenStreetMap.",
        "location_precision": "precise",
        "title": "OSM location of Nuraghe Ruggiu",
        "link": "http://pleiades.stoa.org/places/32331671/location-of-nuraghe-ruggiu"
      }
    }
  ]
}