{
  "type": "FeatureCollection",
  "title": "Capsa (Iustiniana)",
  "id": "324684",
  "bbox": [
    8.7843862,
    34.418648,
    8.786674,
    34.4224374
  ],
  "description": "Capsa (Iustiniana) was an ancient city of Byzacium in north Africa.",
  "names": [
    "Capsa Iustiniana",
    "Capsa",
    "Capsitani",
    "Capsa Colonia",
    "Kapsa",
    "Gafsa"
  ],
  "features": [
    {
      "type": "Feature",
      "geometry": {
        "type": "Point",
        "coordinates": [
          8.7855301,
          34.4205427
        ]
      },
      "properties": {
        "description": "representative point"
      }
    },
    {
      "geometry": {
        "type": "Point",
        "coordinates": [
          8.786674,
          34.418648
        ]
      },
      "id": "dare-location",
      "type": "Feature",
      "properties": {
        "description": "Representative point location, village precision",
        "location_precision": "precise",
        "title": "DARE Location",
        "link": "http://pleiades.stoa.org/places/324684/dare-location"
      }
    },
    {
      "geometry": {
        "type": "Point",
        "coordinates": [
          8.7843862,
          34.4224374
        ]
      },
      "id": "osm-location-of-modern-gafsa",
      "type": "Feature",
      "properties": {
        "description": "Location based on OpenStreetMap",
        "location_precision": "precise",
        "title": "OSM Location of modern Gafsa",
        "link": "http://pleiades.stoa.org/places/324684/osm-location-of-modern-gafsa"
      }
    }
  ]
}