{
  "type": "FeatureCollection",
  "title": "Cillium",
  "id": "324694",
  "bbox": [
    8.798446,
    35.167856,
    8.798446,
    35.167856
  ],
  "description": "Cillium (modern Kasserine, Tunisia) occupies a strategic location in the gap between the Semmama and Chambi mountains, along the road from Gafsa.",
  "connectsWith": [
    "328429"
  ],
  "names": [
    "Cillium"
  ],
  "features": [
    {
      "type": "Feature",
      "geometry": {
        "type": "Point",
        "coordinates": [
          8.798446,
          35.167856
        ]
      },
      "properties": {
        "description": "representative point"
      }
    },
    {
      "geometry": {
        "type": "Point",
        "coordinates": [
          8.798446,
          35.167856
        ]
      },
      "id": "dare-location",
      "type": "Feature",
      "properties": {
        "description": "Representative point location, site precision",
        "location_precision": "precise",
        "title": "DARE Location",
        "link": "http://pleiades.stoa.org/places/324694/dare-location"
      }
    }
  ]
}