{
  "type": "FeatureCollection",
  "title": "Ain-es-Sif",
  "id": "324662",
  "description": "An ancient place, cited: BAtlas 33 E1 Ain-es-Sif",
  "bbox": [
    9.877074,
    36.017362,
    9.877074,
    36.017362
  ],
  "reprPoint": [
    9.877074,
    36.017362
  ],
  "features": [
    {
      "geometry": {
        "type": "Point",
        "coordinates": [
          9.877074,
          36.017362
        ]
      },
      "id": "darmc-location-16074",
      "type": "Feature",
      "properties": {
        "description": "500K scale point location",
        "location_precision": "precise",
        "title": "DARMC location 16074",
        "link": "http://pleiades.stoa.org/places/324662/darmc-location-16074"
      }
    }
  ]
}