{
  "type": "FeatureCollection",
  "title": "Assuras",
  "id": "324669",
  "description": "An ancient place, cited: BAtlas 33 D1 Assuras",
  "bbox": [
    9.022305,
    35.993286,
    9.022305,
    35.993286
  ],
  "reprPoint": [
    9.022305,
    35.993286
  ],
  "names": [
    "Assuras"
  ],
  "features": [
    {
      "geometry": {
        "type": "Point",
        "coordinates": [
          9.022406,
          35.991955
        ]
      },
      "id": "darmc-location-3406",
      "type": "Feature",
      "properties": {
        "description": "500K scale point location",
        "location_precision": "precise",
        "title": "DARMC location 3406",
        "link": "http://pleiades.stoa.org/places/324669/darmc-location-3406"
      }
    },
    {
      "geometry": {
        "type": "Point",
        "coordinates": [
          8.996982,
          35.999812
        ]
      },
      "id": "darmc-location-3407",
      "type": "Feature",
      "properties": {
        "description": "500K scale point location",
        "location_precision": "precise",
        "title": "DARMC location 3407",
        "link": "http://pleiades.stoa.org/places/324669/darmc-location-3407"
      }
    },
    {
      "geometry": {
        "type": "Point",
        "coordinates": [
          9.022305,
          35.993286
        ]
      },
      "id": "dare-location",
      "type": "Feature",
      "properties": {
        "description": "Representative point location, site precision",
        "location_precision": "precise",
        "title": "DARE Location",
        "link": "http://pleiades.stoa.org/places/324669/dare-location"
      }
    }
  ]
}