{
  "type": "FeatureCollection",
  "title": "Capsa (Iustiniana)",
  "id": "324684",
  "description": "Capsa (Iustiniana) was an ancient city of Byzacium in north Africa.",
  "bbox": [
    8.786674,
    34.418648,
    8.786674,
    34.418648
  ],
  "reprPoint": [
    8.786674,
    34.418648
  ],
  "names": [
    "Capsa Iustiniana",
    "Capsa",
    "Capsitani"
  ],
  "features": [
    {
      "geometry": {
        "type": "Point",
        "coordinates": [
          8.786566,
          34.421539
        ]
      },
      "id": "darmc-location-11898",
      "type": "Feature",
      "properties": {
        "description": "1M scale point location",
        "location_precision": "precise",
        "title": "DARMC location 11898",
        "link": "http://pleiades.stoa.org/places/324684/darmc-location-11898"
      }
    },
    {
      "geometry": {
        "type": "Point",
        "coordinates": [
          8.79382,
          34.403804
        ]
      },
      "id": "darmc-location-11899",
      "type": "Feature",
      "properties": {
        "description": "500K scale point location",
        "location_precision": "precise",
        "title": "DARMC location 11899",
        "link": "http://pleiades.stoa.org/places/324684/darmc-location-11899"
      }
    },
    {
      "geometry": {
        "type": "Point",
        "coordinates": [
          8.786674,
          34.418648
        ]
      },
      "id": "dare-location",
      "type": "Feature",
      "properties": {
        "description": "Representative point location, village precision",
        "location_precision": "precise",
        "title": "DARE Location",
        "link": "http://pleiades.stoa.org/places/324684/dare-location"
      }
    }
  ]
}