{
  "type": "FeatureCollection",
  "title": "Agger",
  "id": "324659",
  "bbox": [
    9.5104,
    35.856223,
    9.520857,
    35.868982
  ],
  "description": "An ancient place, cited: BAtlas 33 E1 Agger",
  "names": [
    "Agger"
  ],
  "features": [
    {
      "type": "Feature",
      "geometry": {
        "type": "Point",
        "coordinates": [
          9.5156285,
          35.8626025
        ]
      },
      "properties": {
        "description": "representative point"
      }
    },
    {
      "geometry": {
        "type": "Point",
        "coordinates": [
          9.5104,
          35.868982
        ]
      },
      "id": "darmc-location-11210",
      "type": "Feature",
      "properties": {
        "description": "500K scale point location",
        "location_precision": "precise",
        "title": "DARMC location 11210",
        "link": "http://pleiades.stoa.org/places/324659/darmc-location-11210"
      }
    },
    {
      "geometry": {
        "type": "Point",
        "coordinates": [
          9.520857,
          35.856223
        ]
      },
      "id": "dare-location",
      "type": "Feature",
      "properties": {
        "description": "Representative point location, site precision",
        "location_precision": "precise",
        "title": "DARE Location",
        "link": "http://pleiades.stoa.org/places/324659/dare-location"
      }
    }
  ]
}