{
  "type": "FeatureCollection",
  "title": "Capsa (Iustiniana)",
  "id": "324684",
  "bbox": [
    8.786566,
    34.418648,
    8.786674,
    34.421539
  ],
  "description": "Capsa (Iustiniana) was an ancient city of Byzacium in north Africa.",
  "names": [
    "Capsa Iustiniana",
    "Capsa",
    "Capsitani"
  ],
  "features": [
    {
      "type": "Feature",
      "geometry": {
        "type": "Point",
        "coordinates": [
          8.78662,
          34.4200935
        ]
      },
      "properties": {
        "description": "representative point"
      }
    },
    {
      "geometry": {
        "type": "Point",
        "coordinates": [
          8.786566,
          34.421539
        ]
      },
      "id": "darmc-location-11898",
      "type": "Feature",
      "properties": {
        "description": "1M scale point location",
        "location_precision": "precise",
        "title": "DARMC location 11898",
        "link": "http://pleiades.stoa.org/places/324684/darmc-location-11898"
      }
    },
    {
      "geometry": {
        "type": "Point",
        "coordinates": [
          8.786674,
          34.418648
        ]
      },
      "id": "dare-location",
      "type": "Feature",
      "properties": {
        "description": "Representative point location, village precision",
        "location_precision": "precise",
        "title": "DARE Location",
        "link": "http://pleiades.stoa.org/places/324684/dare-location"
      }
    }
  ]
}