{
  "type": "FeatureCollection",
  "title": "Henchir-et-Tfel",
  "id": "324739",
  "description": "An ancient place, cited: BAtlas 33 C4 Henchir-et-Tfel",
  "bbox": [
    8.610719,
    34.444862,
    8.610719,
    34.444862
  ],
  "reprPoint": [
    8.610719,
    34.444862
  ],
  "features": [
    {
      "geometry": {
        "type": "Point",
        "coordinates": [
          8.610719,
          34.444862
        ]
      },
      "id": "darmc-location-22733",
      "type": "Feature",
      "properties": {
        "description": "500K scale point location",
        "location_precision": "precise",
        "title": "DARMC location 22733",
        "link": "http://pleiades.stoa.org/places/324739/darmc-location-22733"
      }
    }
  ]
}