{
  "type": "FeatureCollection",
  "title": "Henchir-Ksar-el-Ahmar",
  "id": "324742",
  "description": "An ancient place, cited: BAtlas 33 D3 Henchir-Ksar-el-Ahmar",
  "bbox": [
    9.44507,
    34.596711,
    9.44507,
    34.596711
  ],
  "reprPoint": [
    9.44507,
    34.596711
  ],
  "features": [
    {
      "geometry": {
        "type": "Point",
        "coordinates": [
          9.44507,
          34.596711
        ]
      },
      "id": "darmc-location-22708",
      "type": "Feature",
      "properties": {
        "description": "500K scale point location",
        "location_precision": "precise",
        "title": "DARMC location 22708",
        "link": "http://pleiades.stoa.org/places/324742/darmc-location-22708"
      }
    }
  ]
}