{
  "type": "FeatureCollection",
  "title": "Obba",
  "id": "324795",
  "bbox": [
    8.829587,
    35.944739,
    8.829587,
    35.944739
  ],
  "description": "An ancient place, cited: BAtlas 33 C1 Obba",
  "names": [
    "Obba"
  ],
  "features": [
    {
      "type": "Feature",
      "geometry": {
        "type": "Point",
        "coordinates": [
          8.829587,
          35.944739
        ]
      },
      "properties": {
        "description": "representative point"
      }
    },
    {
      "geometry": {
        "type": "Point",
        "coordinates": [
          8.829587,
          35.944739
        ]
      },
      "id": "darmc-location-13975",
      "type": "Feature",
      "properties": {
        "description": "500K scale point location",
        "location_precision": "precise",
        "title": "DARMC location 13975",
        "link": "http://pleiades.stoa.org/places/324795/darmc-location-13975"
      }
    }
  ]
}