{
  "type": "FeatureCollection",
  "title": "Henchir-el-Hammam",
  "id": "324728",
  "description": "An ancient place, cited: BAtlas 33 D1 Henchir-el-Hammam",
  "bbox": [
    9.300023,
    35.826429,
    9.300023,
    35.826429
  ],
  "reprPoint": [
    9.300023,
    35.826429
  ],
  "features": [
    {
      "geometry": {
        "type": "Point",
        "coordinates": [
          9.300023,
          35.826429
        ]
      },
      "id": "darmc-location-13580",
      "type": "Feature",
      "properties": {
        "description": "500K scale point location",
        "location_precision": "precise",
        "title": "DARMC location 13580",
        "link": "http://pleiades.stoa.org/places/324728/darmc-location-13580"
      }
    }
  ]
}