{
  "type": "FeatureCollection",
  "title": "Kebeur-er-Roul",
  "id": "324761",
  "description": "An ancient place, cited: BAtlas 33 D1 Kebeur-er-Roul",
  "bbox": [
    9.415467,
    35.966283,
    9.415467,
    35.966283
  ],
  "reprPoint": [
    9.415467,
    35.966283
  ],
  "features": [
    {
      "geometry": {
        "type": "Point",
        "coordinates": [
          9.415467,
          35.966283
        ]
      },
      "id": "darmc-location-23082",
      "type": "Feature",
      "properties": {
        "description": "500K scale point location",
        "location_precision": "precise",
        "title": "DARMC location 23082",
        "link": "http://pleiades.stoa.org/places/324761/darmc-location-23082"
      }
    }
  ]
}