{
  "type": "FeatureCollection",
  "title": "Henchir-et-Touil",
  "id": "324740",
  "bbox": [
    8.706533,
    35.015406,
    8.706533,
    35.015406
  ],
  "description": "An ancient place, cited: BAtlas 33 C2 Henchir-et-Touil",
  "features": [
    {
      "type": "Feature",
      "geometry": {
        "type": "Point",
        "coordinates": [
          8.706533,
          35.015406
        ]
      },
      "properties": {
        "description": "representative point"
      }
    },
    {
      "geometry": {
        "type": "Point",
        "coordinates": [
          8.706533,
          35.015406
        ]
      },
      "id": "darmc-location-27472",
      "type": "Feature",
      "properties": {
        "description": "500K scale point location",
        "location_precision": "precise",
        "title": "DARMC location 27472",
        "link": "http://pleiades.stoa.org/places/324740/darmc-location-27472"
      }
    }
  ]
}