{
  "type": "FeatureCollection",
  "title": "Henchir-Oulad-Slim",
  "id": "324747",
  "description": "An ancient place, cited: BAtlas 33 H2 Henchir-Oulad-Slim",
  "bbox": [
    11.012786,
    35.166766,
    11.012786,
    35.166766
  ],
  "reprPoint": [
    11.012786,
    35.166766
  ],
  "features": [
    {
      "geometry": {
        "type": "Point",
        "coordinates": [
          11.012786,
          35.166766
        ]
      },
      "id": "darmc-location-22713",
      "type": "Feature",
      "properties": {
        "description": "500K scale point location",
        "location_precision": "precise",
        "title": "DARMC location 22713",
        "link": "http://pleiades.stoa.org/places/324747/darmc-location-22713"
      }
    }
  ]
}