{
  "type": "FeatureCollection",
  "title": "Vazi Sarra",
  "id": "324848",
  "bbox": [
    9.530301,
    36.01617,
    9.530301,
    36.01617
  ],
  "description": "An ancient place, cited: BAtlas 33 E1 Vazi Sarra",
  "names": [
    "Vazi Sarra"
  ],
  "features": [
    {
      "type": "Feature",
      "geometry": {
        "type": "Point",
        "coordinates": [
          9.530301,
          36.01617
        ]
      },
      "properties": {
        "description": "representative point"
      }
    },
    {
      "geometry": {
        "type": "Point",
        "coordinates": [
          9.530301,
          36.01617
        ]
      },
      "id": "darmc-location-16407",
      "type": "Feature",
      "properties": {
        "description": "500K scale point location",
        "location_precision": "precise",
        "title": "DARMC location 16407",
        "link": "http://pleiades.stoa.org/places/324848/darmc-location-16407"
      }
    }
  ]
}