{
  "type": "FeatureCollection",
  "title": "Zella",
  "id": "324852",
  "bbox": [
    11.060551,
    35.500579,
    11.060551,
    35.500579
  ],
  "description": "An ancient place, cited: BAtlas 33 H2 Zella",
  "names": [
    "Zella"
  ],
  "features": [
    {
      "type": "Feature",
      "geometry": {
        "type": "Point",
        "coordinates": [
          11.060551,
          35.500579
        ]
      },
      "properties": {
        "description": "representative point"
      }
    },
    {
      "geometry": {
        "type": "Point",
        "coordinates": [
          11.060551,
          35.500579
        ]
      },
      "id": "darmc-location-15521",
      "type": "Feature",
      "properties": {
        "description": "500K scale point location",
        "location_precision": "precise",
        "title": "DARMC location 15521",
        "link": "http://pleiades.stoa.org/places/324852/darmc-location-15521"
      }
    }
  ]
}