{
  "type": "FeatureCollection",
  "title": "Uluzibbira",
  "id": "324839",
  "bbox": [
    10.441026,
    35.958576,
    10.441026,
    35.958576
  ],
  "description": "An ancient place, cited: BAtlas 33 F1 Uluzibbira",
  "names": [
    "Uluzibbira",
    "Ulisippira",
    "Aelia Uluzibbira"
  ],
  "features": [
    {
      "type": "Feature",
      "geometry": {
        "type": "Point",
        "coordinates": [
          10.441026,
          35.958576
        ]
      },
      "properties": {
        "description": "representative point"
      }
    },
    {
      "geometry": {
        "type": "Point",
        "coordinates": [
          10.441026,
          35.958576
        ]
      },
      "id": "dare-location",
      "type": "Feature",
      "properties": {
        "description": "Representative point location, site precision",
        "location_precision": "precise",
        "title": "DARE Location",
        "link": "http://pleiades.stoa.org/places/324839/dare-location"
      }
    }
  ]
}