{
  "type": "FeatureCollection",
  "title": "Sufes",
  "id": "324815",
  "bbox": [
    9.071977,
    35.542707,
    9.074415,
    35.544012
  ],
  "description": "An ancient place, cited: BAtlas 33 D1 Sufes",
  "connectsWith": [
    "328431"
  ],
  "names": [
    "Sufes"
  ],
  "features": [
    {
      "type": "Feature",
      "geometry": {
        "type": "Point",
        "coordinates": [
          9.073196,
          35.5433595
        ]
      },
      "properties": {
        "description": "representative point"
      }
    },
    {
      "geometry": {
        "type": "Point",
        "coordinates": [
          9.071977,
          35.544012
        ]
      },
      "id": "darmc-location-14927",
      "type": "Feature",
      "properties": {
        "description": "500K scale point location",
        "location_precision": "precise",
        "title": "DARMC location 14927",
        "link": "http://pleiades.stoa.org/places/324815/darmc-location-14927"
      }
    },
    {
      "geometry": {
        "type": "Point",
        "coordinates": [
          9.074415,
          35.542707
        ]
      },
      "id": "dare-location",
      "type": "Feature",
      "properties": {
        "description": "Representative point location, village precision",
        "location_precision": "precise",
        "title": "DARE Location",
        "link": "http://pleiades.stoa.org/places/324815/dare-location"
      }
    }
  ]
}