{
  "type": "FeatureCollection",
  "title": "Uzaae",
  "id": "324842",
  "bbox": [
    10.583314,
    35.729372,
    10.583314,
    35.729372
  ],
  "description": "An ancient place, cited: BAtlas 33 G1 Uzaae",
  "names": [
    "Uzaae"
  ],
  "features": [
    {
      "type": "Feature",
      "geometry": {
        "type": "Point",
        "coordinates": [
          10.583314,
          35.729372
        ]
      },
      "properties": {
        "description": "representative point"
      }
    },
    {
      "geometry": {
        "type": "Point",
        "coordinates": [
          10.583314,
          35.729372
        ]
      },
      "id": "darmc-location-15332",
      "type": "Feature",
      "properties": {
        "description": "500K scale point location",
        "location_precision": "precise",
        "title": "DARMC location 15332",
        "link": "http://pleiades.stoa.org/places/324842/darmc-location-15332"
      }
    }
  ]
}