{
  "type": "FeatureCollection",
  "title": "Sufetula",
  "id": "324816",
  "description": "An ancient place, cited: BAtlas 33 D2 Sufetula",
  "bbox": [
    9.118569,
    35.241611,
    9.118569,
    35.241611
  ],
  "connectsWith": [
    "328428",
    "328429"
  ],
  "reprPoint": [
    9.118569,
    35.241611
  ],
  "names": [
    "Sufetula"
  ],
  "features": [
    {
      "geometry": {
        "type": "Point",
        "coordinates": [
          9.121017,
          35.238719
        ]
      },
      "id": "darmc-location-14928",
      "type": "Feature",
      "properties": {
        "description": "500K scale point location",
        "location_precision": "precise",
        "title": "DARMC location 14928",
        "link": "http://pleiades.stoa.org/places/324816/darmc-location-14928"
      }
    },
    {
      "geometry": {
        "type": "Point",
        "coordinates": [
          9.1225658,
          35.2394478
        ]
      },
      "id": "location-of-roman-theater",
      "type": "Feature",
      "properties": {
        "description": "coordinates after OSM, verified in Google Earth.",
        "location_precision": "precise",
        "title": "location of Roman theater",
        "link": "http://pleiades.stoa.org/places/324816/location-of-roman-theater"
      }
    },
    {
      "geometry": {
        "type": "Point",
        "coordinates": [
          9.1234614,
          35.2355943
        ]
      },
      "id": "arch-of-diocletian",
      "type": "Feature",
      "properties": {
        "description": "Location based on OpenStreetMap; verified in Google Earth.",
        "location_precision": "precise",
        "title": "Arch of Diocletian",
        "link": "http://pleiades.stoa.org/places/324816/arch-of-diocletian"
      }
    },
    {
      "geometry": {
        "type": "Point",
        "coordinates": [
          9.118569,
          35.241611
        ]
      },
      "id": "dare-location",
      "type": "Feature",
      "properties": {
        "description": "Representative point location, site precision",
        "location_precision": "precise",
        "title": "DARE Location",
        "link": "http://pleiades.stoa.org/places/324816/dare-location"
      }
    }
  ]
}