{
  "type": "FeatureCollection",
  "title": "Sidi-Ali-Bou-Khraled",
  "id": "324811",
  "description": "An ancient place, cited: BAtlas 33 C1 Sidi-Ali-Bou-Khraled",
  "bbox": [
    8.657847,
    35.693168,
    8.657847,
    35.693168
  ],
  "reprPoint": [
    8.657847,
    35.693168
  ],
  "features": [
    {
      "geometry": {
        "type": "Point",
        "coordinates": [
          8.657847,
          35.693168
        ]
      },
      "id": "darmc-location-24732",
      "type": "Feature",
      "properties": {
        "description": "500K scale point location",
        "location_precision": "precise",
        "title": "DARMC location 24732",
        "link": "http://pleiades.stoa.org/places/324811/darmc-location-24732"
      }
    }
  ]
}