{
  "type": "FeatureCollection",
  "title": "Thysdrus",
  "id": "324835",
  "description": "Thysdrus (modern El Djem, Tunisia) was a Punic and Roman city of North Africa. It flourished in the second century AD and built its massive amphitheater in the third century. After an abortive revolt in AD 238, the city was destroyed by soldiers loyal to Maximinus Thrax.",
  "bbox": [
    10.706877,
    35.296493,
    10.706877,
    35.296493
  ],
  "connectsWith": [
    "328429",
    "328433"
  ],
  "reprPoint": [
    10.706877,
    35.296493
  ],
  "names": [
    "El Djem",
    "Thysdrus"
  ],
  "features": [
    {
      "geometry": {
        "type": "Point",
        "coordinates": [
          10.708291,
          35.295622
        ]
      },
      "id": "darmc-location-15166",
      "type": "Feature",
      "properties": {
        "description": "500K scale point location",
        "location_precision": "precise",
        "title": "DARMC location 15166",
        "link": "http://pleiades.stoa.org/places/324835/darmc-location-15166"
      }
    },
    {
      "geometry": {
        "type": "Point",
        "coordinates": [
          10.706877,
          35.296493
        ]
      },
      "id": "dare-location",
      "type": "Feature",
      "properties": {
        "description": "Representative point location, site precision",
        "location_precision": "precise",
        "title": "DARE Location",
        "link": "http://pleiades.stoa.org/places/324835/dare-location"
      }
    },
    {
      "geometry": {
        "type": "Point",
        "coordinates": [
          10.706939,
          35.29639
        ]
      },
      "id": "amphitheatre-of-el-jem",
      "type": "Feature",
      "properties": {
        "description": "Third century AD Roman amphitheater; declared a UNESCO World Heritage Site in 1979",
        "location_precision": "precise",
        "title": "Amphitheatre of El Jem",
        "link": "http://pleiades.stoa.org/places/324835/amphitheatre-of-el-jem"
      }
    }
  ]
}