{
  "type": "FeatureCollection",
  "title": "Thysdrus",
  "id": "324835",
  "bbox": [
    10.706877,
    35.295622,
    10.708291,
    35.296493
  ],
  "description": "Thysdrus (modern El Djem, Tunisia) was a Punic and Roman city of North Africa. It flourished in the second century A.D. and built its massive amphitheater in the third century. After an abortive revolt in A.D. 238, the city was destroyed by soldiers loyal to Maximinus Thrax.",
  "connectsWith": [
    "328429",
    "328433"
  ],
  "names": [
    "Thysdrus",
    "El Djem"
  ],
  "features": [
    {
      "type": "Feature",
      "geometry": {
        "type": "Point",
        "coordinates": [
          10.707584,
          35.2960575
        ]
      },
      "properties": {
        "description": "representative point"
      }
    },
    {
      "geometry": {
        "type": "Point",
        "coordinates": [
          10.708291,
          35.295622
        ]
      },
      "id": "darmc-location-15166",
      "type": "Feature",
      "properties": {
        "description": "500K scale point location",
        "location_precision": "precise",
        "title": "DARMC location 15166",
        "link": "http://pleiades.stoa.org/places/324835/darmc-location-15166"
      }
    },
    {
      "geometry": {
        "type": "Point",
        "coordinates": [
          10.706877,
          35.296493
        ]
      },
      "id": "dare-location",
      "type": "Feature",
      "properties": {
        "description": "Representative point location, site precision",
        "location_precision": "precise",
        "title": "DARE Location",
        "link": "http://pleiades.stoa.org/places/324835/dare-location"
      }
    }
  ]
}