{
  "type": "FeatureCollection",
  "title": "Sufetula",
  "id": "324816",
  "bbox": [
    9.118569,
    35.238719,
    9.1225658,
    35.241611
  ],
  "description": "Sufetula, the modern Sbeitla, was founded in the later first century A.D. and was located at a major road junction.",
  "connectsWith": [
    "328429",
    "328428"
  ],
  "names": [
    "Sufetula"
  ],
  "features": [
    {
      "type": "Feature",
      "geometry": {
        "type": "Point",
        "coordinates": [
          9.12071726667,
          35.2399259333
        ]
      },
      "properties": {
        "description": "representative point"
      }
    },
    {
      "geometry": {
        "type": "Point",
        "coordinates": [
          9.121017,
          35.238719
        ]
      },
      "id": "darmc-location-14928",
      "type": "Feature",
      "properties": {
        "description": "500K scale point location",
        "location_precision": "precise",
        "title": "DARMC location 14928",
        "link": "http://pleiades.stoa.org/places/324816/darmc-location-14928"
      }
    },
    {
      "geometry": {
        "type": "Point",
        "coordinates": [
          9.118569,
          35.241611
        ]
      },
      "id": "dare-location",
      "type": "Feature",
      "properties": {
        "description": "Representative point location, site precision",
        "location_precision": "precise",
        "title": "DARE Location",
        "link": "http://pleiades.stoa.org/places/324816/dare-location"
      }
    },
    {
      "geometry": {
        "type": "Point",
        "coordinates": [
          9.1225658,
          35.2394478
        ]
      },
      "id": "location-of-roman-theater",
      "type": "Feature",
      "properties": {
        "description": "coordinates after OSM, verified in Google Earth.",
        "location_precision": "precise",
        "title": "location of Roman theater",
        "link": "http://pleiades.stoa.org/places/324816/location-of-roman-theater"
      }
    }
  ]
}