{
  "type": "FeatureCollection",
  "title": "Untitled",
  "id": "326920",
  "bbox": [
    9.142312,
    35.285954,
    9.142312,
    35.285954
  ],
  "description": "An ancient place, cited: BAtlas 33 D2 unnamed quarry (N Sufetula)",
  "features": [
    {
      "type": "Feature",
      "geometry": {
        "type": "Point",
        "coordinates": [
          9.142312,
          35.285954
        ]
      },
      "properties": {
        "description": "representative point"
      }
    },
    {
      "geometry": {
        "type": "Point",
        "coordinates": [
          9.142312,
          35.285954
        ]
      },
      "id": "darmc-location-19139",
      "type": "Feature",
      "properties": {
        "description": "500K scale point location",
        "location_precision": "precise",
        "title": "DARMC location 19139",
        "link": "http://pleiades.stoa.org/places/326920/darmc-location-19139"
      }
    }
  ]
}