{
  "type": "FeatureCollection",
  "title": "Macellum Magnum",
  "id": "327869515",
  "bbox": [
    12.486137,
    41.891775,
    12.486137,
    41.891775
  ],
  "description": "The great market hall built by the emperor Nero on the Caelian Hill and dedicated in the year 59. The market hall is known from numismatic imagery and some of its archaeological remains have been documented on the Caelian hill.",
  "connectsWith": [
    "423025",
    "917389428",
    "695491849"
  ],
  "names": [
    "Macellum Magnum"
  ],
  "features": [
    {
      "type": "Feature",
      "geometry": {
        "type": "Point",
        "coordinates": [
          12.486137,
          41.891775
        ]
      },
      "properties": {
        "description": "representative point"
      }
    }
  ]
}