{
  "type": "FeatureCollection",
  "title": "Cova des Càrritx cave",
  "id": "32834410",
  "bbox": [
    3.9655536,
    39.9663836,
    3.9655536,
    39.9663836
  ],
  "description": "The Cova des Càrritx cave is a natural cave on the island of Minorca with evidence for prehistoric human activity.",
  "connectsWith": [
    "572631626"
  ],
  "names": [
    "Cova des Carritx"
  ],
  "features": [
    {
      "type": "Feature",
      "geometry": {
        "type": "Point",
        "coordinates": [
          3.9655536,
          39.9663836
        ]
      },
      "properties": {
        "description": "representative point"
      }
    },
    {
      "geometry": {
        "type": "Point",
        "coordinates": [
          3.9655536,
          39.9663836
        ]
      },
      "id": "osm-location-of-cova-des-ca-rritx",
      "type": "Feature",
      "properties": {
        "description": "Representative location based on OpenStreetMap",
        "location_precision": "precise",
        "title": "OSM location of Cova des Càrritx",
        "link": "http://pleiades.stoa.org/places/32834410/osm-location-of-cova-des-ca-rritx"
      }
    }
  ]
}