{
  "type": "FeatureCollection",
  "title": "Untitled",
  "id": "328444",
  "bbox": [
    8.120848,
    34.978743,
    8.595226,
    35.407108
  ],
  "description": "Theveste → Thelepte",
  "features": [
    {
      "type": "Feature",
      "geometry": {
        "type": "Point",
        "coordinates": [
          8.35877025,
          35.1914585
        ]
      },
      "properties": {
        "description": "representative point"
      }
    }
  ]
}