{
  "type": "FeatureCollection",
  "title": "Cuccureddus",
  "id": "328783231",
  "bbox": [
    9.4909084,
    39.1359745,
    9.4909084,
    39.1359745
  ],
  "description": "A Phoenician port of southeastern Sardinia.",
  "connectsWith": [
    "472014"
  ],
  "features": [
    {
      "type": "Feature",
      "geometry": {
        "type": "Point",
        "coordinates": [
          9.4909084,
          39.1359745
        ]
      },
      "properties": {
        "description": "representative point"
      }
    },
    {
      "geometry": {
        "type": "Point",
        "coordinates": [
          9.4909084,
          39.1359745
        ]
      },
      "id": "osm-location-of-insediamento-fenicio-punico-romano",
      "type": "Feature",
      "properties": {
        "description": "Representative location based on OpenStreetMap",
        "location_precision": "precise",
        "title": "OSM location of Insediamento fenicio-punico-romano di Cuccureddus",
        "link": "http://pleiades.stoa.org/places/328783231/osm-location-of-insediamento-fenicio-punico-romano"
      }
    }
  ]
}