{
  "type": "FeatureCollection",
  "title": "Forum of Mactaris",
  "id": "329343086",
  "bbox": [
    9.2077327,
    35.8539263,
    9.2077327,
    35.8539263
  ],
  "description": "One of two fora at Mactaris. This earlier square is adjacent to the Arch of Trajan.",
  "connectsWith": [
    "324774"
  ],
  "features": [
    {
      "type": "Feature",
      "geometry": {
        "type": "Point",
        "coordinates": [
          9.2077327,
          35.8539263
        ]
      },
      "properties": {
        "description": "representative point"
      }
    },
    {
      "geometry": {
        "type": "Point",
        "coordinates": [
          9.2077327,
          35.8539263
        ]
      },
      "id": "location-of-forum",
      "type": "Feature",
      "properties": {
        "description": "Representative location based on an OpenStreetMap node located at the northwest corner of the forum square.",
        "location_precision": "precise",
        "title": "OSM location of Forum",
        "link": "http://pleiades.stoa.org/places/329343086/location-of-forum"
      }
    }
  ]
}