{
  "type": "FeatureCollection",
  "title": "The Siphnian Treasury",
  "id": "333036425",
  "description": "Treasury building erected by the citizens of the island city of Siphnos at Delphi in the late Archaic period, famous for its caryatid columns.",
  "bbox": [
    22.501642,
    38.48162,
    22.501642,
    38.48162
  ],
  "connectsWith": [
    "540726"
  ],
  "reprPoint": [
    22.501642,
    38.48162
  ],
  "features": [
    {
      "geometry": {
        "type": "Point",
        "coordinates": [
          22.501642,
          38.48162
        ]
      },
      "id": "the-siphnian-treasury",
      "type": "Feature",
      "properties": {
        "description": "Representative point derived from Google Earth imagery. Dates after Darling.",
        "location_precision": "precise",
        "title": "Imagery Location of the Siphnian Treasury",
        "link": "http://pleiades.stoa.org/places/333036425/the-siphnian-treasury"
      }
    }
  ]
}