{
  "type": "FeatureCollection",
  "title": "Alea(...)",
  "id": "334488",
  "bbox": [
    6.491168,
    35.516373,
    6.491168,
    35.516373
  ],
  "description": "An ancient place, cited: BAtlas 34 E2 Alea(...)",
  "names": [
    "Alea(...)"
  ],
  "features": [
    {
      "type": "Feature",
      "geometry": {
        "type": "Point",
        "coordinates": [
          6.491168,
          35.516373
        ]
      },
      "properties": {
        "description": "representative point"
      }
    },
    {
      "geometry": {
        "type": "Point",
        "coordinates": [
          6.491168,
          35.516373
        ]
      },
      "id": "darmc-location-11301",
      "type": "Feature",
      "properties": {
        "description": "1M scale point location",
        "location_precision": "precise",
        "title": "DARMC location 11301",
        "link": "http://pleiades.stoa.org/places/334488/darmc-location-11301"
      }
    }
  ]
}