{
  "type": "FeatureCollection",
  "title": "Aquae Herculis",
  "id": "334492",
  "description": "An ancient place, cited: BAtlas 34 D2 Aquae Herculis",
  "bbox": [
    5.780974,
    35.031274,
    5.780974,
    35.031274
  ],
  "reprPoint": [
    5.780974,
    35.031274
  ],
  "names": [
    "Aquae Herculis"
  ],
  "features": [
    {
      "geometry": {
        "type": "Point",
        "coordinates": [
          5.780974,
          35.031274
        ]
      },
      "id": "darmc-location-23353",
      "type": "Feature",
      "properties": {
        "description": "Point location",
        "location_precision": "precise",
        "title": "DARMC location 23353",
        "link": "http://pleiades.stoa.org/places/334492/darmc-location-23353"
      }
    }
  ]
}