{
  "type": "FeatureCollection",
  "title": "Ad Piscinam?",
  "id": "334477",
  "description": "An ancient place, cited: BAtlas 34 D3 Ad Piscinam?",
  "bbox": [
    5.828633,
    34.821914,
    5.828633,
    34.821914
  ],
  "reprPoint": [
    5.828633,
    34.821914
  ],
  "names": [
    "Ad Piscinam"
  ],
  "features": [
    {
      "geometry": {
        "type": "Point",
        "coordinates": [
          5.828633,
          34.821914
        ]
      },
      "id": "darmc-location-23354",
      "type": "Feature",
      "properties": {
        "description": "Point location",
        "location_precision": "precise",
        "title": "DARMC location 23354",
        "link": "http://pleiades.stoa.org/places/334477/darmc-location-23354"
      }
    }
  ]
}