{
  "type": "FeatureCollection",
  "title": "Ad Symmachi?",
  "id": "334479",
  "description": "An ancient place, cited: BAtlas 34 D2 Ad Symmachi?",
  "bbox": [
    6.166658,
    35.233353,
    6.166658,
    35.233353
  ],
  "reprPoint": [
    6.166658,
    35.233353
  ],
  "names": [
    "Ad Symmachi"
  ],
  "features": [
    {
      "geometry": {
        "type": "Point",
        "coordinates": [
          6.166658,
          35.233353
        ]
      },
      "id": "darmc-location-9773",
      "type": "Feature",
      "properties": {
        "description": "1M scale point location",
        "location_precision": "precise",
        "title": "DARMC location 9773",
        "link": "http://pleiades.stoa.org/places/334479/darmc-location-9773"
      }
    }
  ]
}