{
  "type": "FeatureCollection",
  "title": "el Gahra",
  "id": "334551",
  "description": "An ancient place, cited: BAtlas 34 C3 el Gahra",
  "bbox": [
    4.421093,
    34.884791,
    4.421093,
    34.884791
  ],
  "reprPoint": [
    4.421093,
    34.884791
  ],
  "features": [
    {
      "geometry": {
        "type": "Point",
        "coordinates": [
          4.421093,
          34.884791
        ]
      },
      "id": "darmc-location-8473",
      "type": "Feature",
      "properties": {
        "description": "1M scale point location",
        "location_precision": "precise",
        "title": "DARMC location 8473",
        "link": "http://pleiades.stoa.org/places/334551/darmc-location-8473"
      }
    }
  ]
}