{
  "type": "FeatureCollection",
  "title": "Dechret Kamra",
  "id": "334534",
  "description": "An ancient place, cited: BAtlas 34 C3 Dechret Kamra",
  "bbox": [
    4.039351,
    34.460293,
    4.039351,
    34.460293
  ],
  "reprPoint": [
    4.039351,
    34.460293
  ],
  "features": [
    {
      "geometry": {
        "type": "Point",
        "coordinates": [
          4.039351,
          34.460293
        ]
      },
      "id": "darmc-location-7635",
      "type": "Feature",
      "properties": {
        "description": "1M scale point location",
        "location_precision": "precise",
        "title": "DARMC location 7635",
        "link": "http://pleiades.stoa.org/places/334534/darmc-location-7635"
      }
    }
  ]
}