{
  "type": "FeatureCollection",
  "title": "Centenarium Aqua Viva",
  "id": "334527",
  "bbox": [
    5.118813,
    35.088227,
    5.118813,
    35.088227
  ],
  "description": "An ancient place, cited: BAtlas 34 D2 Centenarium Aqua Viva",
  "names": [
    "Centenarium Aqua Viva"
  ],
  "features": [
    {
      "type": "Feature",
      "geometry": {
        "type": "Point",
        "coordinates": [
          5.118813,
          35.088227
        ]
      },
      "properties": {
        "description": "representative point"
      }
    },
    {
      "geometry": {
        "type": "Point",
        "coordinates": [
          5.118813,
          35.088227
        ]
      },
      "id": "darmc-location-7555",
      "type": "Feature",
      "properties": {
        "description": "1M scale point location",
        "location_precision": "precise",
        "title": "DARMC location 7555",
        "link": "http://pleiades.stoa.org/places/334527/darmc-location-7555"
      }
    }
  ]
}