{
  "type": "FeatureCollection",
  "title": "Castellum Dimmidi",
  "id": "334518",
  "bbox": [
    3.498374,
    34.155805,
    3.498374,
    34.155805
  ],
  "description": "An ancient place, cited: BAtlas 34 B3 Castellum Dimmidi",
  "names": [
    "Castellum Dimmidi"
  ],
  "features": [
    {
      "type": "Feature",
      "geometry": {
        "type": "Point",
        "coordinates": [
          3.498374,
          34.155805
        ]
      },
      "properties": {
        "description": "representative point"
      }
    },
    {
      "geometry": {
        "type": "Point",
        "coordinates": [
          3.498374,
          34.155805
        ]
      },
      "id": "darmc-location-17525",
      "type": "Feature",
      "properties": {
        "description": "1M scale point location",
        "location_precision": "precise",
        "title": "DARMC location 17525",
        "link": "http://pleiades.stoa.org/places/334518/darmc-location-17525"
      }
    }
  ]
}