{
  "type": "FeatureCollection",
  "title": "Lobrin(...)",
  "id": "334581",
  "description": "An ancient place, cited: BAtlas 34 D2 Lobrin(...)",
  "bbox": [
    5.276415,
    35.878753,
    5.276415,
    35.878753
  ],
  "reprPoint": [
    5.276415,
    35.878753
  ],
  "names": [
    "Lobrin(...)"
  ],
  "features": [
    {
      "geometry": {
        "type": "Point",
        "coordinates": [
          5.276415,
          35.878753
        ]
      },
      "id": "darmc-location-13519",
      "type": "Feature",
      "properties": {
        "description": "1M scale point location",
        "location_precision": "precise",
        "title": "DARMC location 13519",
        "link": "http://pleiades.stoa.org/places/334581/darmc-location-13519"
      }
    }
  ]
}