{
  "type": "FeatureCollection",
  "title": "Ferme Romanette",
  "id": "334545",
  "description": "An ancient place, cited: BAtlas 34 A2 Ferme Romanette",
  "bbox": [
    2.459976,
    35.314471,
    2.459976,
    35.314471
  ],
  "reprPoint": [
    2.459976,
    35.314471
  ],
  "features": [
    {
      "geometry": {
        "type": "Point",
        "coordinates": [
          2.459976,
          35.314471
        ]
      },
      "id": "darmc-location-17418",
      "type": "Feature",
      "properties": {
        "description": "1M scale point location",
        "location_precision": "precise",
        "title": "DARMC location 17418",
        "link": "http://pleiades.stoa.org/places/334545/darmc-location-17418"
      }
    }
  ]
}