{
  "type": "FeatureCollection",
  "title": "Macri?",
  "id": "334584",
  "description": "An ancient place, cited: BAtlas 34 D2 Macri?",
  "bbox": [
    5.094743,
    35.637737,
    5.094743,
    35.637737
  ],
  "reprPoint": [
    5.094743,
    35.637737
  ],
  "names": [
    "Macri"
  ],
  "features": [
    {
      "geometry": {
        "type": "Point",
        "coordinates": [
          5.094743,
          35.637737
        ]
      },
      "id": "darmc-location-13571",
      "type": "Feature",
      "properties": {
        "description": "1M scale point location",
        "location_precision": "precise",
        "title": "DARMC location 13571",
        "link": "http://pleiades.stoa.org/places/334584/darmc-location-13571"
      }
    }
  ]
}