{
  "type": "FeatureCollection",
  "title": "Djenndel",
  "id": "334539",
  "description": "An ancient place, cited: BAtlas 34 F3 Djenndel",
  "bbox": [
    7.300724,
    34.703145,
    7.300724,
    34.703145
  ],
  "reprPoint": [
    7.300724,
    34.703145
  ],
  "features": [
    {
      "geometry": {
        "type": "Point",
        "coordinates": [
          7.300724,
          34.703145
        ]
      },
      "id": "darmc-location-7651",
      "type": "Feature",
      "properties": {
        "description": "1M scale point location",
        "location_precision": "precise",
        "title": "DARMC location 7651",
        "link": "http://pleiades.stoa.org/places/334539/darmc-location-7651"
      }
    }
  ]
}