{
  "type": "FeatureCollection",
  "title": "Leges Maiores",
  "id": "334575",
  "description": "An ancient place, cited: BAtlas 34 F2 Leges Maiores",
  "bbox": [
    7.395885,
    35.068699,
    7.395885,
    35.068699
  ],
  "reprPoint": [
    7.395885,
    35.068699
  ],
  "names": [
    "Leges Maiores"
  ],
  "features": [
    {
      "geometry": {
        "type": "Point",
        "coordinates": [
          7.395885,
          35.068699
        ]
      },
      "id": "darmc-location-13449",
      "type": "Feature",
      "properties": {
        "description": "1M scale point location",
        "location_precision": "precise",
        "title": "DARMC location 13449",
        "link": "http://pleiades.stoa.org/places/334575/darmc-location-13449"
      }
    }
  ]
}