{
  "type": "FeatureCollection",
  "title": "Bourada",
  "id": "334506",
  "bbox": [
    5.912554,
    34.586774,
    5.912554,
    34.586774
  ],
  "description": "An ancient place, cited: BAtlas 34 D3 Bourada",
  "features": [
    {
      "type": "Feature",
      "geometry": {
        "type": "Point",
        "coordinates": [
          5.912554,
          34.586774
        ]
      },
      "properties": {
        "description": "representative point"
      }
    },
    {
      "geometry": {
        "type": "Point",
        "coordinates": [
          5.912554,
          34.586774
        ]
      },
      "id": "darmc-location-7464",
      "type": "Feature",
      "properties": {
        "description": "1M scale point location",
        "location_precision": "precise",
        "title": "DARMC location 7464",
        "link": "http://pleiades.stoa.org/places/334506/darmc-location-7464"
      }
    }
  ]
}