{
  "type": "FeatureCollection",
  "title": "Mascula Tiberia",
  "id": "334587",
  "description": "A major settlement, cited: BAtlas 34 F2 Mascula Tiberia",
  "bbox": [
    7.150025,
    35.433338,
    7.150025,
    35.433338
  ],
  "reprPoint": [
    7.150025,
    35.433338
  ],
  "names": [
    "Mascula Tiberia"
  ],
  "features": [
    {
      "geometry": {
        "type": "Point",
        "coordinates": [
          7.146711,
          35.43795
        ]
      },
      "id": "darmc-location-23657",
      "type": "Feature",
      "properties": {
        "description": "1M scale point location",
        "location_precision": "precise",
        "title": "DARMC location 23657",
        "link": "http://pleiades.stoa.org/places/334587/darmc-location-23657"
      }
    },
    {
      "geometry": {
        "type": "Point",
        "coordinates": [
          7.150025,
          35.433338
        ]
      },
      "id": "dare-location",
      "type": "Feature",
      "properties": {
        "description": "Representative point location, village precision",
        "location_precision": "precise",
        "title": "DARE Location",
        "link": "http://pleiades.stoa.org/places/334587/dare-location"
      }
    }
  ]
}