{
  "type": "FeatureCollection",
  "title": "Lamasba",
  "id": "334569",
  "description": "Lamasba was a city of Roman Numidia.",
  "bbox": [
    5.909852,
    35.627737,
    5.909852,
    35.627737
  ],
  "reprPoint": [
    5.909852,
    35.627737
  ],
  "names": [
    "Lamasba"
  ],
  "features": [
    {
      "geometry": {
        "type": "Point",
        "coordinates": [
          5.911308,
          35.628988
        ]
      },
      "id": "darmc-location-13386",
      "type": "Feature",
      "properties": {
        "description": "1M scale point location",
        "location_precision": "precise",
        "title": "DARMC location 13386",
        "link": "http://pleiades.stoa.org/places/334569/darmc-location-13386"
      }
    },
    {
      "geometry": {
        "type": "Point",
        "coordinates": [
          5.909852,
          35.627737
        ]
      },
      "id": "dare-location",
      "type": "Feature",
      "properties": {
        "description": "Representative point location, village precision",
        "location_precision": "precise",
        "title": "DARE Location",
        "link": "http://pleiades.stoa.org/places/334569/dare-location"
      }
    }
  ]
}