{
  "type": "FeatureCollection",
  "title": "Lambafundi",
  "id": "334571",
  "bbox": [
    6.465983,
    35.481197,
    6.465983,
    35.481197
  ],
  "description": "An ancient place, cited: BAtlas 34 E2 Lambafundi",
  "names": [
    "Lambafundi"
  ],
  "features": [
    {
      "type": "Feature",
      "geometry": {
        "type": "Point",
        "coordinates": [
          6.465983,
          35.481197
        ]
      },
      "properties": {
        "description": "representative point"
      }
    },
    {
      "geometry": {
        "type": "Point",
        "coordinates": [
          6.465983,
          35.481197
        ]
      },
      "id": "darmc-location-13387",
      "type": "Feature",
      "properties": {
        "description": "1M scale point location",
        "location_precision": "precise",
        "title": "DARMC location 13387",
        "link": "http://pleiades.stoa.org/places/334571/darmc-location-13387"
      }
    }
  ]
}