{
  "type": "FeatureCollection",
  "title": "Cellas/Castellum Cellense?",
  "id": "334526",
  "description": "An ancient place, cited: BAtlas 34 D2 Cellas/Castellum Cellense?",
  "bbox": [
    5.319487,
    35.66983,
    5.319487,
    35.66983
  ],
  "reprPoint": [
    5.319487,
    35.66983
  ],
  "names": [
    "Cellas",
    "Castellum Cellense"
  ],
  "features": [
    {
      "geometry": {
        "type": "Point",
        "coordinates": [
          5.319487,
          35.66983
        ]
      },
      "id": "darmc-location-11953",
      "type": "Feature",
      "properties": {
        "description": "1M scale point location",
        "location_precision": "precise",
        "title": "DARMC location 11953",
        "link": "http://pleiades.stoa.org/places/334526/darmc-location-11953"
      }
    }
  ]
}