{
  "type": "FeatureCollection",
  "title": "Verecunda",
  "id": "334662",
  "bbox": [
    6.28937,
    35.488332,
    6.290047,
    35.489103
  ],
  "description": "An ancient place, cited: BAtlas 34 E2 Verecunda",
  "names": [
    "Verecunda"
  ],
  "features": [
    {
      "type": "Feature",
      "geometry": {
        "type": "Point",
        "coordinates": [
          6.2897085,
          35.4887175
        ]
      },
      "properties": {
        "description": "representative point"
      }
    },
    {
      "geometry": {
        "type": "Point",
        "coordinates": [
          6.290047,
          35.488332
        ]
      },
      "id": "darmc-location-15372",
      "type": "Feature",
      "properties": {
        "description": "1M scale point location",
        "location_precision": "precise",
        "title": "DARMC location 15372",
        "link": "http://pleiades.stoa.org/places/334662/darmc-location-15372"
      }
    },
    {
      "geometry": {
        "type": "Point",
        "coordinates": [
          6.28937,
          35.489103
        ]
      },
      "id": "dare-location",
      "type": "Feature",
      "properties": {
        "description": "Representative point location, village precision",
        "location_precision": "precise",
        "title": "DARE Location",
        "link": "http://pleiades.stoa.org/places/334662/dare-location"
      }
    }
  ]
}