{
  "type": "FeatureCollection",
  "title": "Sidi Khaled",
  "id": "334619",
  "bbox": [
    4.999699,
    34.397304,
    4.999699,
    34.397304
  ],
  "description": "An ancient place, cited: BAtlas 34 D3 Sidi Khaled",
  "features": [
    {
      "type": "Feature",
      "geometry": {
        "type": "Point",
        "coordinates": [
          4.999699,
          34.397304
        ]
      },
      "properties": {
        "description": "representative point"
      }
    },
    {
      "geometry": {
        "type": "Point",
        "coordinates": [
          4.999699,
          34.397304
        ]
      },
      "id": "darmc-location-8309",
      "type": "Feature",
      "properties": {
        "description": "1M scale point location",
        "location_precision": "precise",
        "title": "DARMC location 8309",
        "link": "http://pleiades.stoa.org/places/334619/darmc-location-8309"
      }
    }
  ]
}