{
  "type": "FeatureCollection",
  "title": "Tadutti?",
  "id": "334627",
  "description": "An ancient place, cited: BAtlas 34 E2 Tadutti?",
  "bbox": [
    6.374227,
    35.711899,
    6.374227,
    35.711899
  ],
  "reprPoint": [
    6.374227,
    35.711899
  ],
  "names": [
    "Tadutti"
  ],
  "features": [
    {
      "geometry": {
        "type": "Point",
        "coordinates": [
          6.374227,
          35.711899
        ]
      },
      "id": "darmc-location-14975",
      "type": "Feature",
      "properties": {
        "description": "1M scale point location",
        "location_precision": "precise",
        "title": "DARMC location 14975",
        "link": "http://pleiades.stoa.org/places/334627/darmc-location-14975"
      }
    }
  ]
}