{
  "type": "FeatureCollection",
  "title": "Perdices?",
  "id": "334608",
  "description": "An ancient place, cited: BAtlas 34 D2 Perdices?",
  "bbox": [
    5.390069,
    35.931999,
    5.390069,
    35.931999
  ],
  "reprPoint": [
    5.390069,
    35.931999
  ],
  "names": [
    "Perdices"
  ],
  "features": [
    {
      "geometry": {
        "type": "Point",
        "coordinates": [
          5.390069,
          35.931999
        ]
      },
      "id": "darmc-location-14185",
      "type": "Feature",
      "properties": {
        "description": "1M scale point location",
        "location_precision": "precise",
        "title": "DARMC location 14185",
        "link": "http://pleiades.stoa.org/places/334608/darmc-location-14185"
      }
    }
  ]
}