{
  "type": "FeatureCollection",
  "title": "Din Lligwy",
  "id": "335254448",
  "bbox": [
    -4.2595562,
    53.3507262,
    -4.2595562,
    53.3507262
  ],
  "description": "Din Lligwy is the site of a prehistoric village near the east coast of Anglesey in Wales.",
  "features": [
    {
      "type": "Feature",
      "geometry": {
        "type": "Point",
        "coordinates": [
          -4.2595562,
          53.3507262
        ]
      },
      "properties": {
        "description": "representative point"
      }
    },
    {
      "geometry": {
        "type": "Point",
        "coordinates": [
          -4.2595562,
          53.3507262
        ]
      },
      "id": "location-of-din-lligwy-prehistoric-village",
      "type": "Feature",
      "properties": {
        "description": "Representative location based on OpenStreetMap",
        "location_precision": "precise",
        "title": "OSM location of Din Lligwy prehistoric village",
        "link": "http://pleiades.stoa.org/places/335254448/location-of-din-lligwy-prehistoric-village"
      }
    }
  ]
}