{
  "type": "FeatureCollection",
  "title": "Qal’at Sem’an/Church of Saint Simeon Stylites",
  "id": "336554371",
  "description": "An ancient church, located in modern Syria. Inscribed as a UNESCO World Heritage Site in 2011 as part of the \"Ancient Villages of Northern Syria.\"",
  "bbox": [
    36.8441666667,
    36.3341666667,
    36.8441666667,
    36.3341666667
  ],
  "reprPoint": [
    36.8441666667,
    36.3341666667
  ],
  "features": [
    {
      "geometry": {
        "type": "Point",
        "coordinates": [
          36.8441666667,
          36.3341666667
        ]
      },
      "id": "ruins-of-the-ancient-church-of-saint-simeon-stylites",
      "type": "Feature",
      "properties": {
        "description": "Location of the ruins of Qal’at Sem’an/Church of Saint Simeon Stylites. Coordinates determined from UNESCO World Heritage list and verified by eye in Google Earth in October 2012.",
        "location_precision": "precise",
        "title": "Ruins of the ancient Church of Saint Simeon Stylites",
        "link": "http://pleiades.stoa.org/places/336554371/ruins-of-the-ancient-church-of-saint-simeon-stylites"
      }
    }
  ]
}