{
  "type": "FeatureCollection",
  "title": "Velefi",
  "id": "338300",
  "bbox": [
    7.66,
    35.93,
    7.66,
    35.93
  ],
  "description": "An ancient settlement or road station attested in the Peutinger Map, but otherwise unknown and unlocateable. The map places it together with several other unlocated places on a route in modern Algeria between Gadifaula (modern Ksar Sbehi) and Vatari (which might be modern Fedj es Siouda).",
  "connectsWith": [
    "334659"
  ],
  "names": [
    "Velefi"
  ],
  "features": [
    {
      "type": "Feature",
      "geometry": {
        "type": "Point",
        "coordinates": [
          7.66,
          35.93
        ]
      },
      "properties": {
        "description": "representative point"
      }
    },
    {
      "geometry": null,
      "id": "batlas-location",
      "type": "Feature",
      "properties": {
        "description": null,
        "location_precision": "unlocated",
        "title": "Barrington Atlas location",
        "link": "http://pleiades.stoa.org/places/338300/batlas-location"
      }
    }
  ]
}