{
  "type": "FeatureCollection",
  "title": "Collepardo",
  "id": "342847225",
  "bbox": [
    13.369499,
    41.764322,
    13.369499,
    41.764322
  ],
  "description": "A sixth-century CE city founded in the time of Theodoric the Great that shows traces of first millennium BCE habitation in the form of polygonal masonry walls.",
  "connectsWith": [
    "432901"
  ],
  "features": [
    {
      "type": "Feature",
      "geometry": {
        "type": "Point",
        "coordinates": [
          13.369499,
          41.764322
        ]
      },
      "properties": {
        "description": "representative point"
      }
    },
    {
      "geometry": {
        "type": "Point",
        "coordinates": [
          13.369499,
          41.764322
        ]
      },
      "id": "osm-location-of-collepardo",
      "type": "Feature",
      "properties": {
        "description": "Location based on OpenStreetMap",
        "location_precision": "precise",
        "title": "OSM location of Collepardo",
        "link": "http://pleiades.stoa.org/places/342847225/osm-location-of-collepardo"
      }
    }
  ]
}