{
  "type": "FeatureCollection",
  "title": "Šamaš Gate",
  "id": "344172036",
  "bbox": [
    43.2210906,
    36.4925378,
    43.2486423,
    36.5146497
  ],
  "description": "The Šamaš Gate, which was given the Akkadian ceremonial name Šamaš-mušakšid-ernittīya (\"The God Šamaš Is the One Who Makes Me Triumph\"), is the first of the eight city gates of Dūr-Šarrukīn (\"Fort Sargon\") listed by Sargon II (r. 721–705 BC) in inscriptions recording the construction of his new capital. This gate is the first of the east-facing entrances to the city.",
  "connectsWith": [
    "874458",
    "4517388",
    "175106248",
    "918508895"
  ],
  "names": [
    "Šamaš-mušakšid-ernittīya"
  ],
  "features": [
    {
      "type": "Feature",
      "geometry": {
        "type": "Point",
        "coordinates": [
          43.2349275627,
          36.5038233173
        ]
      },
      "properties": {
        "description": "representative point"
      }
    }
  ]
}