{
  "type": "FeatureCollection",
  "title": "Ad Palmam",
  "id": "344285",
  "bbox": [
    14.131477,
    32.649407,
    14.131477,
    32.649407
  ],
  "description": "An ancient place, cited: BAtlas 35 G2 Ad Palmam",
  "names": [
    "Ad Palmam"
  ],
  "features": [
    {
      "type": "Feature",
      "geometry": {
        "type": "Point",
        "coordinates": [
          14.131477,
          32.649407
        ]
      },
      "properties": {
        "description": "representative point"
      }
    },
    {
      "geometry": {
        "type": "Point",
        "coordinates": [
          14.131477,
          32.649407
        ]
      },
      "id": "darmc-location-2849",
      "type": "Feature",
      "properties": {
        "description": "1M scale point location",
        "location_precision": "precise",
        "title": "DARMC location 2849",
        "link": "http://pleiades.stoa.org/places/344285/darmc-location-2849"
      }
    }
  ]
}