{
  "type": "FeatureCollection",
  "title": "Agarlabas?",
  "id": "344289",
  "bbox": [
    9.432882,
    33.766913,
    9.432882,
    33.766913
  ],
  "description": "An ancient place, cited: BAtlas 35 B1 Agarlabas?",
  "names": [
    "Agarlabas"
  ],
  "features": [
    {
      "type": "Feature",
      "geometry": {
        "type": "Point",
        "coordinates": [
          9.432882,
          33.766913
        ]
      },
      "properties": {
        "description": "representative point"
      }
    },
    {
      "geometry": {
        "type": "Point",
        "coordinates": [
          9.432882,
          33.766913
        ]
      },
      "id": "darmc-location-9774",
      "type": "Feature",
      "properties": {
        "description": "1M scale point location",
        "location_precision": "precise",
        "title": "DARMC location 9774",
        "link": "http://pleiades.stoa.org/places/344289/darmc-location-9774"
      }
    }
  ]
}