{
  "type": "FeatureCollection",
  "title": "Henchir Krebita",
  "id": "344399",
  "description": "An ancient place, cited: BAtlas 35 B1 Henchir Krebita",
  "bbox": [
    9.92346,
    33.449969,
    9.92346,
    33.449969
  ],
  "reprPoint": [
    9.92346,
    33.449969
  ],
  "features": [
    {
      "geometry": {
        "type": "Point",
        "coordinates": [
          9.92346,
          33.449969
        ]
      },
      "id": "darmc-location-15992",
      "type": "Feature",
      "properties": {
        "description": "1M scale point location",
        "location_precision": "precise",
        "title": "DARMC location 15992",
        "link": "http://pleiades.stoa.org/places/344399/darmc-location-15992"
      }
    }
  ]
}