{
  "type": "FeatureCollection",
  "title": "Henchir Bu Hamed",
  "id": "344391",
  "description": "An ancient place, cited: BAtlas 35 C1 Henchir Bu Hamed",
  "bbox": [
    10.738368,
    33.29699,
    10.738368,
    33.29699
  ],
  "reprPoint": [
    10.738368,
    33.29699
  ],
  "features": [
    {
      "geometry": {
        "type": "Point",
        "coordinates": [
          10.738368,
          33.29699
        ]
      },
      "id": "darmc-location-17456",
      "type": "Feature",
      "properties": {
        "description": "1M scale point location",
        "location_precision": "precise",
        "title": "DARMC location 17456",
        "link": "http://pleiades.stoa.org/places/344391/darmc-location-17456"
      }
    }
  ]
}