{
  "type": "FeatureCollection",
  "title": "Casa Rimoniana",
  "id": "344332",
  "description": "An ancient place, cited: BAtlas 35 G2 Casa Rimoniana",
  "bbox": [
    14.94639,
    32.137924,
    14.94639,
    32.137924
  ],
  "reprPoint": [
    14.94639,
    32.137924
  ],
  "names": [
    "Casa Rimoniana"
  ],
  "features": [
    {
      "geometry": {
        "type": "Point",
        "coordinates": [
          14.94639,
          32.137924
        ]
      },
      "id": "darmc-location-9737",
      "type": "Feature",
      "properties": {
        "description": "1M scale point location",
        "location_precision": "precise",
        "title": "DARMC location 9737",
        "link": "http://pleiades.stoa.org/places/344332/darmc-location-9737"
      }
    }
  ]
}