{
  "type": "FeatureCollection",
  "title": "Henchir Bourgou",
  "id": "344390",
  "description": "An ancient place, cited: BAtlas 35 C1 Henchir Bourgou",
  "bbox": [
    10.958747,
    33.815256,
    10.958747,
    33.815256
  ],
  "reprPoint": [
    10.958747,
    33.815256
  ],
  "features": [
    {
      "geometry": {
        "type": "Point",
        "coordinates": [
          10.958747,
          33.815256
        ]
      },
      "id": "darmc-location-12703",
      "type": "Feature",
      "properties": {
        "description": "1M scale point location",
        "location_precision": "precise",
        "title": "DARMC location 12703",
        "link": "http://pleiades.stoa.org/places/344390/darmc-location-12703"
      }
    }
  ]
}