{
  "type": "FeatureCollection",
  "title": "Bir Cuca",
  "id": "344318",
  "bbox": [
    12.979461,
    32.426638,
    12.979461,
    32.426638
  ],
  "description": "An ancient place, cited: BAtlas 35 E2 Bir Cuca",
  "features": [
    {
      "type": "Feature",
      "geometry": {
        "type": "Point",
        "coordinates": [
          12.979461,
          32.426638
        ]
      },
      "properties": {
        "description": "representative point"
      }
    },
    {
      "geometry": {
        "type": "Point",
        "coordinates": [
          12.979461,
          32.426638
        ]
      },
      "id": "darmc-location-17379",
      "type": "Feature",
      "properties": {
        "description": "1M scale point location",
        "location_precision": "precise",
        "title": "DARMC location 17379",
        "link": "http://pleiades.stoa.org/places/344318/darmc-location-17379"
      }
    }
  ]
}