{
  "type": "FeatureCollection",
  "title": "Garian",
  "id": "344361",
  "description": "An ancient place, cited: BAtlas 35 F2 Garian",
  "bbox": [
    13.017562,
    32.169374,
    13.017562,
    32.169374
  ],
  "reprPoint": [
    13.017562,
    32.169374
  ],
  "features": [
    {
      "geometry": {
        "type": "Point",
        "coordinates": [
          13.017562,
          32.169374
        ]
      },
      "id": "darmc-location-15967",
      "type": "Feature",
      "properties": {
        "description": "1M scale point location",
        "location_precision": "precise",
        "title": "DARMC location 15967",
        "link": "http://pleiades.stoa.org/places/344361/darmc-location-15967"
      }
    }
  ]
}