{
  "type": "FeatureCollection",
  "title": "Chizen",
  "id": "344340",
  "description": "An ancient place, cited: BAtlas 35 C1 Chizen",
  "bbox": [
    10.912924,
    33.864917,
    10.912924,
    33.864917
  ],
  "reprPoint": [
    10.912924,
    33.864917
  ],
  "features": [
    {
      "geometry": {
        "type": "Point",
        "coordinates": [
          10.912924,
          33.864917
        ]
      },
      "id": "darmc-location-23387",
      "type": "Feature",
      "properties": {
        "description": "Point location",
        "location_precision": "precise",
        "title": "DARMC location 23387",
        "link": "http://pleiades.stoa.org/places/344340/darmc-location-23387"
      }
    }
  ]
}