{
  "type": "FeatureCollection",
  "title": "Getullu",
  "id": "344373",
  "description": "An ancient place, cited: BAtlas 35 F2 Getullu",
  "bbox": [
    13.596282,
    32.783434,
    13.596282,
    32.783434
  ],
  "reprPoint": [
    13.596282,
    32.783434
  ],
  "names": [
    "Getullu"
  ],
  "features": [
    {
      "geometry": {
        "type": "Point",
        "coordinates": [
          13.596282,
          32.783434
        ]
      },
      "id": "darmc-location-19665",
      "type": "Feature",
      "properties": {
        "description": "1M scale point location",
        "location_precision": "precise",
        "title": "DARMC location 19665",
        "link": "http://pleiades.stoa.org/places/344373/darmc-location-19665"
      }
    }
  ]
}