{
  "type": "FeatureCollection",
  "title": "Derg",
  "id": "344346",
  "bbox": [
    10.459072,
    30.1661,
    10.459072,
    30.1661
  ],
  "description": "An ancient place, cited: BAtlas 35 C4 Derg",
  "features": [
    {
      "type": "Feature",
      "geometry": {
        "type": "Point",
        "coordinates": [
          10.459072,
          30.1661
        ]
      },
      "properties": {
        "description": "representative point"
      }
    },
    {
      "geometry": {
        "type": "Point",
        "coordinates": [
          10.459072,
          30.1661
        ]
      },
      "id": "darmc-location-12185",
      "type": "Feature",
      "properties": {
        "description": "1M scale point location",
        "location_precision": "precise",
        "title": "DARMC location 12185",
        "link": "http://pleiades.stoa.org/places/344346/darmc-location-12185"
      }
    }
  ]
}