{
  "type": "FeatureCollection",
  "title": "Gheriat el-Garbia",
  "id": "344374",
  "description": "Gheriat el-Garbia was the site of a Roman fort in Libya that was part of the Limes Tripolitanus.",
  "bbox": [
    13.418427,
    30.420497,
    13.418427,
    30.420497
  ],
  "reprPoint": [
    13.418427,
    30.420497
  ],
  "features": [
    {
      "geometry": {
        "type": "Point",
        "coordinates": [
          13.418427,
          30.420497
        ]
      },
      "id": "dare-location",
      "type": "Feature",
      "properties": {
        "description": "Representative point location, site precision",
        "location_precision": "precise",
        "title": "DARE Location",
        "link": "http://pleiades.stoa.org/places/344374/dare-location"
      }
    },
    {
      "geometry": {
        "type": "Point",
        "coordinates": [
          13.416015,
          30.416465
        ]
      },
      "id": "darmc-location-17283",
      "type": "Feature",
      "properties": {
        "description": "1M scale point location",
        "location_precision": "precise",
        "title": "DARMC location 17283",
        "link": "http://pleiades.stoa.org/places/344374/darmc-location-17283"
      }
    }
  ]
}