{
  "type": "FeatureCollection",
  "title": "Geran",
  "id": "344371",
  "description": "An ancient place, cited: BAtlas 35 F2 Geran",
  "bbox": [
    13.074156,
    32.849922,
    13.074156,
    32.849922
  ],
  "reprPoint": [
    13.074156,
    32.849922
  ],
  "features": [
    {
      "geometry": {
        "type": "Point",
        "coordinates": [
          13.074156,
          32.849922
        ]
      },
      "id": "darmc-location-15974",
      "type": "Feature",
      "properties": {
        "description": "1M scale point location",
        "location_precision": "precise",
        "title": "DARMC location 15974",
        "link": "http://pleiades.stoa.org/places/344371/darmc-location-15974"
      }
    }
  ]
}