{
  "type": "FeatureCollection",
  "title": "Breviglieri",
  "id": "344330",
  "description": "An ancient place, cited: BAtlas 35 F2 Breviglieri",
  "bbox": [
    13.764682,
    32.44452,
    13.764682,
    32.44452
  ],
  "reprPoint": [
    13.764682,
    32.44452
  ],
  "features": [
    {
      "geometry": {
        "type": "Point",
        "coordinates": [
          13.764682,
          32.44452
        ]
      },
      "id": "darmc-location-5007",
      "type": "Feature",
      "properties": {
        "description": "1M scale point location",
        "location_precision": "precise",
        "title": "DARMC location 5007",
        "link": "http://pleiades.stoa.org/places/344330/darmc-location-5007"
      }
    }
  ]
}