{
  "type": "FeatureCollection",
  "title": "Bir esc-Scedeua",
  "id": "344322",
  "description": "An ancient place, cited: BAtlas 35 F3 Bir esc-Scedeua",
  "bbox": [
    13.450007,
    31.283322,
    13.450007,
    31.283322
  ],
  "reprPoint": [
    13.450007,
    31.283322
  ],
  "features": [
    {
      "geometry": {
        "type": "Point",
        "coordinates": [
          13.450007,
          31.283322
        ]
      },
      "id": "darmc-location-27382",
      "type": "Feature",
      "properties": {
        "description": "1M scale point location",
        "location_precision": "precise",
        "title": "DARMC location 27382",
        "link": "http://pleiades.stoa.org/places/344322/darmc-location-27382"
      }
    }
  ]
}