{
  "type": "FeatureCollection",
  "title": "Gasr el-Gezira",
  "id": "344365",
  "bbox": [
    12.436781,
    32.026267,
    12.436781,
    32.026267
  ],
  "description": "An ancient place, cited: BAtlas 35 E2 Gasr el-Gezira",
  "features": [
    {
      "type": "Feature",
      "geometry": {
        "type": "Point",
        "coordinates": [
          12.436781,
          32.026267
        ]
      },
      "properties": {
        "description": "representative point"
      }
    },
    {
      "geometry": {
        "type": "Point",
        "coordinates": [
          12.436781,
          32.026267
        ]
      },
      "id": "darmc-location-25972",
      "type": "Feature",
      "properties": {
        "description": "1M scale point location",
        "location_precision": "precise",
        "title": "DARMC location 25972",
        "link": "http://pleiades.stoa.org/places/344365/darmc-location-25972"
      }
    }
  ]
}