{
  "type": "FeatureCollection",
  "title": "Henchir Sidi Hamdan",
  "id": "344403",
  "bbox": [
    13.994289,
    32.371678,
    13.994289,
    32.371678
  ],
  "description": "An ancient place, cited: BAtlas 35 G2 Henchir Sidi Hamdan",
  "features": [
    {
      "type": "Feature",
      "geometry": {
        "type": "Point",
        "coordinates": [
          13.994289,
          32.371678
        ]
      },
      "properties": {
        "description": "representative point"
      }
    },
    {
      "geometry": {
        "type": "Point",
        "coordinates": [
          13.994289,
          32.371678
        ]
      },
      "id": "darmc-location-17462",
      "type": "Feature",
      "properties": {
        "description": "1M scale point location",
        "location_precision": "precise",
        "title": "DARMC location 17462",
        "link": "http://pleiades.stoa.org/places/344403/darmc-location-17462"
      }
    }
  ]
}