{
  "type": "FeatureCollection",
  "title": "Tacape",
  "id": "344496",
  "bbox": [
    10.109445,
    33.88643,
    10.109445,
    33.88643
  ],
  "description": "Tacape (modern Gabès) was a commercial city located on the Lesser Syrtis.",
  "connectsWith": [
    "344492",
    "348061",
    "348059"
  ],
  "names": [
    "Tacape",
    "Tacapas"
  ],
  "features": [
    {
      "type": "Feature",
      "geometry": {
        "type": "Point",
        "coordinates": [
          10.109445,
          33.88643
        ]
      },
      "properties": {
        "description": "representative point"
      }
    },
    {
      "geometry": {
        "type": "Point",
        "coordinates": [
          10.109445,
          33.88643
        ]
      },
      "id": "darmc-location-6261",
      "type": "Feature",
      "properties": {
        "description": "1M scale point location",
        "location_precision": "precise",
        "title": "DARMC location 6261",
        "link": "http://pleiades.stoa.org/places/344496/darmc-location-6261"
      }
    }
  ]
}