{
  "type": "FeatureCollection",
  "title": "Ksar Tabria",
  "id": "344418",
  "description": "An ancient place, cited: BAtlas 35 B1 Ksar Tabria",
  "bbox": [
    9.227666,
    33.475801,
    9.227666,
    33.475801
  ],
  "reprPoint": [
    9.227666,
    33.475801
  ],
  "features": [
    {
      "geometry": {
        "type": "Point",
        "coordinates": [
          9.227666,
          33.475801
        ]
      },
      "id": "darmc-location-7146",
      "type": "Feature",
      "properties": {
        "description": "1M scale point location",
        "location_precision": "precise",
        "title": "DARMC location 7146",
        "link": "http://pleiades.stoa.org/places/344418/darmc-location-7146"
      }
    }
  ]
}