{
  "type": "FeatureCollection",
  "title": "Tacape",
  "id": "344496",
  "description": "Tacape (modern Gabès) was a commercial city located on the Lesser Syrtis.",
  "bbox": [
    10.082679,
    33.88643,
    10.109445,
    34.017546
  ],
  "connectsWith": [
    "344492"
  ],
  "reprPoint": [
    10.096062,
    33.951988
  ],
  "names": [
    "Tacape",
    "Tacapas"
  ],
  "features": [
    {
      "geometry": {
        "type": "Point",
        "coordinates": [
          10.109445,
          33.88643
        ]
      },
      "id": "darmc-location-6261",
      "type": "Feature",
      "properties": {
        "description": "1M scale point location",
        "location_precision": "precise",
        "title": "DARMC location 6261",
        "link": "http://pleiades.stoa.org/places/344496/darmc-location-6261"
      }
    }
  ]
}