{
  "type": "FeatureCollection",
  "title": "Locri",
  "id": "344424",
  "description": "An ancient place, cited: BAtlas 35 E2 Locri",
  "bbox": [
    12.111326,
    32.91658,
    12.111326,
    32.91658
  ],
  "reprPoint": [
    12.111326,
    32.91658
  ],
  "names": [
    "Locri"
  ],
  "features": [
    {
      "geometry": {
        "type": "Point",
        "coordinates": [
          12.111326,
          32.91658
        ]
      },
      "id": "darmc-location-10119",
      "type": "Feature",
      "properties": {
        "description": "1M scale point location",
        "location_precision": "precise",
        "title": "DARMC location 10119",
        "link": "http://pleiades.stoa.org/places/344424/darmc-location-10119"
      }
    }
  ]
}