{
  "type": "FeatureCollection",
  "title": "Ras el-Oued Gordab",
  "id": "344471",
  "description": "An ancient place, cited: BAtlas 35 C1 Ras el-Oued Gordab",
  "bbox": [
    10.491745,
    33.033284,
    10.491745,
    33.033284
  ],
  "reprPoint": [
    10.491745,
    33.033284
  ],
  "features": [
    {
      "geometry": {
        "type": "Point",
        "coordinates": [
          10.491745,
          33.033284
        ]
      },
      "id": "darmc-location-27569",
      "type": "Feature",
      "properties": {
        "description": "1M scale point location",
        "location_precision": "precise",
        "title": "DARMC location 27569",
        "link": "http://pleiades.stoa.org/places/344471/darmc-location-27569"
      }
    }
  ]
}