{
  "type": "FeatureCollection",
  "title": "Novum Centenarium",
  "id": "344453",
  "bbox": [
    12.458754,
    31.667759,
    12.458754,
    31.667759
  ],
  "description": "An ancient place, cited: BAtlas 35 E3 Novum Centenarium",
  "names": [
    "Novum Centenarium"
  ],
  "features": [
    {
      "type": "Feature",
      "geometry": {
        "type": "Point",
        "coordinates": [
          12.458754,
          31.667759
        ]
      },
      "properties": {
        "description": "representative point"
      }
    },
    {
      "geometry": {
        "type": "Point",
        "coordinates": [
          12.458754,
          31.667759
        ]
      },
      "id": "darmc-location-8143",
      "type": "Feature",
      "properties": {
        "description": "1M scale point location",
        "location_precision": "precise",
        "title": "DARMC location 8143",
        "link": "http://pleiades.stoa.org/places/344453/darmc-location-8143"
      }
    }
  ]
}