{
  "type": "FeatureCollection",
  "title": "Kinyps",
  "id": "344413",
  "description": "An ancient place, cited: BAtlas 35 G2 Kinyps",
  "bbox": [
    14.447329,
    32.527937,
    14.447329,
    32.527937
  ],
  "reprPoint": [
    14.447329,
    32.527937
  ],
  "names": [
    "Kinyps"
  ],
  "features": [
    {
      "geometry": {
        "type": "Point",
        "coordinates": [
          14.447329,
          32.527937
        ]
      },
      "id": "darmc-location-10284",
      "type": "Feature",
      "properties": {
        "description": "1M scale point location",
        "location_precision": "precise",
        "title": "DARMC location 10284",
        "link": "http://pleiades.stoa.org/places/344413/darmc-location-10284"
      }
    }
  ]
}