{
  "type": "FeatureCollection",
  "title": "Wadi Sasu",
  "id": "344559",
  "description": "An ancient place, cited: BAtlas 35 G2 Wadi Sasu",
  "bbox": [
    14.943099,
    32.134528,
    14.943099,
    32.134528
  ],
  "reprPoint": [
    14.943099,
    32.134528
  ],
  "features": [
    {
      "geometry": {
        "type": "Point",
        "coordinates": [
          14.943099,
          32.134528
        ]
      },
      "id": "darmc-location-17661",
      "type": "Feature",
      "properties": {
        "description": "1M scale point location",
        "location_precision": "precise",
        "title": "DARMC location 17661",
        "link": "http://pleiades.stoa.org/places/344559/darmc-location-17661"
      }
    }
  ]
}