{
  "type": "FeatureCollection",
  "title": "Umm el-Gueloub",
  "id": "344529",
  "bbox": [
    14.410261,
    30.248126,
    14.410261,
    30.248126
  ],
  "description": "An ancient place, cited: BAtlas 35 G4 Umm el-Gueloub",
  "features": [
    {
      "type": "Feature",
      "geometry": {
        "type": "Point",
        "coordinates": [
          14.410261,
          30.248126
        ]
      },
      "properties": {
        "description": "representative point"
      }
    },
    {
      "geometry": {
        "type": "Point",
        "coordinates": [
          14.410261,
          30.248126
        ]
      },
      "id": "darmc-location-18403",
      "type": "Feature",
      "properties": {
        "description": "1M scale point location",
        "location_precision": "precise",
        "title": "DARMC location 18403",
        "link": "http://pleiades.stoa.org/places/344529/darmc-location-18403"
      }
    }
  ]
}