{
  "type": "FeatureCollection",
  "title": "Wadi Umm el-Kharab",
  "id": "344566",
  "description": "An ancient place, cited: BAtlas 35 G3 Wadi Umm el-Kharab",
  "bbox": [
    15.29978,
    31.316391,
    15.29978,
    31.316391
  ],
  "reprPoint": [
    15.29978,
    31.316391
  ],
  "features": [
    {
      "geometry": {
        "type": "Point",
        "coordinates": [
          15.29978,
          31.316391
        ]
      },
      "id": "darmc-location-27666",
      "type": "Feature",
      "properties": {
        "description": "1M scale point location",
        "location_precision": "precise",
        "title": "DARMC location 27666",
        "link": "http://pleiades.stoa.org/places/344566/darmc-location-27666"
      }
    }
  ]
}