{
  "type": "FeatureCollection",
  "title": "Tininai",
  "id": "344518",
  "description": "An ancient place, cited: BAtlas 35 F3 Tininai",
  "bbox": [
    13.780278,
    31.383351,
    13.780278,
    31.383351
  ],
  "reprPoint": [
    13.780278,
    31.383351
  ],
  "features": [
    {
      "geometry": {
        "type": "Point",
        "coordinates": [
          13.780278,
          31.383351
        ]
      },
      "id": "darmc-location-16235",
      "type": "Feature",
      "properties": {
        "description": "1M scale point location",
        "location_precision": "precise",
        "title": "DARMC location 16235",
        "link": "http://pleiades.stoa.org/places/344518/darmc-location-16235"
      }
    }
  ]
}