{
  "type": "FeatureCollection",
  "title": "Villa near Wadi Ghirza",
  "id": "344546",
  "description": "An ancient villa near the Wadi Ghirza",
  "bbox": [
    14.493068,
    30.931884,
    14.493068,
    30.931884
  ],
  "reprPoint": [
    14.493068,
    30.931884
  ],
  "features": [
    {
      "geometry": {
        "type": "Point",
        "coordinates": [
          14.493068,
          30.931884
        ]
      },
      "id": "darmc-location-17654",
      "type": "Feature",
      "properties": {
        "description": "1M scale point location",
        "location_precision": "precise",
        "title": "DARMC location 17654",
        "link": "http://pleiades.stoa.org/places/344546/darmc-location-17654"
      }
    }
  ]
}