{
  "type": "FeatureCollection",
  "title": "Wadi Mimoun",
  "id": "344556",
  "description": "An ancient place, cited: BAtlas 35 G3 Wadi Mimoun",
  "bbox": [
    14.020544,
    31.649826,
    14.289022,
    31.665695
  ],
  "reprPoint": [
    14.154783,
    31.6577605
  ],
  "features": [
    {
      "geometry": {
        "type": "Point",
        "coordinates": [
          14.020544,
          31.665695
        ]
      },
      "id": "darmc-location-6846",
      "type": "Feature",
      "properties": {
        "description": "1M scale point location",
        "location_precision": "precise",
        "title": "DARMC location 6846",
        "link": "http://pleiades.stoa.org/places/344556/darmc-location-6846"
      }
    },
    {
      "geometry": {
        "type": "Point",
        "coordinates": [
          14.289022,
          31.649826
        ]
      },
      "id": "darmc-location-6847",
      "type": "Feature",
      "properties": {
        "description": "1M scale point location",
        "location_precision": "precise",
        "title": "DARMC location 6847",
        "link": "http://pleiades.stoa.org/places/344556/darmc-location-6847"
      }
    }
  ]
}