{
  "type": "FeatureCollection",
  "title": "Tillibari",
  "id": "344516",
  "description": "An ancient place, cited: BAtlas 35 C2 Tillibari",
  "bbox": [
    10.397757,
    32.317527,
    10.397757,
    32.317527
  ],
  "reprPoint": [
    10.397757,
    32.317527
  ],
  "names": [
    "Tillibari",
    "Cilliba"
  ],
  "features": [
    {
      "geometry": {
        "type": "Point",
        "coordinates": [
          10.399072,
          32.31633
        ]
      },
      "id": "darmc-location-8373",
      "type": "Feature",
      "properties": {
        "description": "1M scale point location",
        "location_precision": "precise",
        "title": "DARMC location 8373",
        "link": "http://pleiades.stoa.org/places/344516/darmc-location-8373"
      }
    },
    {
      "geometry": {
        "type": "Point",
        "coordinates": [
          10.397757,
          32.317527
        ]
      },
      "id": "dare-location",
      "type": "Feature",
      "properties": {
        "description": "Representative point location, village precision",
        "location_precision": "precise",
        "title": "DARE Location",
        "link": "http://pleiades.stoa.org/places/344516/dare-location"
      }
    }
  ]
}