{
  "type": "FeatureCollection",
  "title": "Trigh-Tarhuna",
  "id": "344521",
  "description": "An ancient place, cited: BAtlas 35 F2 Trigh-Tarhuna",
  "bbox": [
    13.23445,
    32.876858,
    13.23445,
    32.876858
  ],
  "reprPoint": [
    13.23445,
    32.876858
  ],
  "features": [
    {
      "geometry": {
        "type": "Point",
        "coordinates": [
          13.23445,
          32.876858
        ]
      },
      "id": "darmc-location-26240",
      "type": "Feature",
      "properties": {
        "description": "1M scale point location",
        "location_precision": "precise",
        "title": "DARMC location 26240",
        "link": "http://pleiades.stoa.org/places/344521/darmc-location-26240"
      }
    }
  ]
}