{
  "type": "FeatureCollection",
  "title": "Wadi Sofeggin",
  "id": "344561",
  "description": "An ancient place, cited: BAtlas 35 F3 Wadi Sofeggin",
  "bbox": [
    15.116631,
    31.899553,
    15.116631,
    31.899553
  ],
  "reprPoint": [
    15.116631,
    31.899553
  ],
  "features": [
    {
      "geometry": {
        "type": "Point",
        "coordinates": [
          15.116631,
          31.899553
        ]
      },
      "id": "darmc-location-17663",
      "type": "Feature",
      "properties": {
        "description": "1M scale point location",
        "location_precision": "precise",
        "title": "DARMC location 17663",
        "link": "http://pleiades.stoa.org/places/344561/darmc-location-17663"
      }
    }
  ]
}