{
  "type": "FeatureCollection",
  "title": "Wadi Merteba",
  "id": "344552",
  "description": "An ancient place, cited: BAtlas 35 C2 Wadi Merteba",
  "bbox": [
    10.756757,
    32.161528,
    10.756757,
    32.161528
  ],
  "reprPoint": [
    10.756757,
    32.161528
  ],
  "features": [
    {
      "geometry": {
        "type": "Point",
        "coordinates": [
          10.756757,
          32.161528
        ]
      },
      "id": "darmc-location-26264",
      "type": "Feature",
      "properties": {
        "description": "1M scale point location",
        "location_precision": "precise",
        "title": "DARMC location 26264",
        "link": "http://pleiades.stoa.org/places/344552/darmc-location-26264"
      }
    }
  ]
}