{
  "type": "FeatureCollection",
  "title": "Tall Umm al-ʻAjarib",
  "id": "344945222",
  "bbox": [
    45.9330206,
    31.6207,
    45.9339,
    31.62097
  ],
  "description": "Find place for cuneiform inscription.",
  "names": [
    "Tall Umm al-ʻAjarib"
  ],
  "features": [
    {
      "type": "Feature",
      "geometry": {
        "type": "Point",
        "coordinates": [
          45.9334603,
          31.620835
        ]
      },
      "properties": {
        "description": "representative point"
      }
    },
    {
      "geometry": {
        "type": "Point",
        "coordinates": [
          45.9330206,
          31.62097
        ]
      },
      "id": "tell-umm-al-aqarib-dhi-qar-iraq",
      "type": "Feature",
      "properties": {
        "description": "Location based on OpenStreetMap",
        "location_precision": "precise",
        "title": "OSM location of Tell Umm al-Aqarib - Dhi Qar, Iraq",
        "link": "http://pleiades.stoa.org/places/344945222/tell-umm-al-aqarib-dhi-qar-iraq"
      }
    },
    {
      "geometry": {
        "type": "Point",
        "coordinates": [
          45.9339,
          31.6207
        ]
      },
      "id": "tall-umm-al-ajarib-1",
      "type": "Feature",
      "properties": {
        "description": null,
        "location_precision": "precise",
        "title": "CIGS location of Tall Umm al-ʻAjarib",
        "link": "http://pleiades.stoa.org/places/344945222/tall-umm-al-ajarib-1"
      }
    }
  ]
}