{
  "type": "FeatureCollection",
  "title": "Sissû",
  "id": "34546779",
  "bbox": [
    35.8163535,
    37.4488715,
    35.8163535,
    37.4488715
  ],
  "description": "A town mentioned in Neo-Assyrian sources. It is identified with modern Kozan (formerly Sis) and classical Sision.\r\n",
  "names": [
    "Kozan"
  ],
  "features": [
    {
      "type": "Feature",
      "geometry": {
        "type": "Point",
        "coordinates": [
          35.8163535,
          37.4488715
        ]
      },
      "properties": {
        "description": "representative point"
      }
    },
    {
      "geometry": {
        "type": "Point",
        "coordinates": [
          35.8163535,
          37.4488715
        ]
      },
      "id": "osm-location-of-kozan",
      "type": "Feature",
      "properties": {
        "description": "Representative location based on OpenStreetMap.",
        "location_precision": "precise",
        "title": "OSM location of modern Kozan",
        "link": "http://pleiades.stoa.org/places/34546779/osm-location-of-kozan"
      }
    }
  ]
}