{
  "type": "FeatureCollection",
  "title": "Untitled",
  "id": "347305",
  "description": "An ancient place, cited: BAtlas 35 G3 unnamed monument (el-Amud mausolea near Wadi N'f'd)",
  "bbox": [
    14.63255,
    31.40337,
    14.63255,
    31.40337
  ],
  "reprPoint": [
    14.63255,
    31.40337
  ],
  "features": [
    {
      "geometry": {
        "type": "Point",
        "coordinates": [
          14.63255,
          31.40337
        ]
      },
      "id": "darmc-location-25780",
      "type": "Feature",
      "properties": {
        "description": "500K scale point location",
        "location_precision": "precise",
        "title": "DARMC location 25780",
        "link": "http://pleiades.stoa.org/places/347305/darmc-location-25780"
      }
    }
  ]
}