{
  "type": "FeatureCollection",
  "title": "Ekklesiasterion",
  "id": "349338482",
  "bbox": [
    14.4796767,
    37.4308098,
    14.4796767,
    37.4308098
  ],
  "description": "The Ekklesiasterion of Morgantina is located in the center of the ancient city. While its form resembles that of the Greek theater, it is posited that it functioned as a public building akin to the Roman comitium. It likely dates to the later fourth century B.C.",
  "connectsWith": [
    "462372"
  ],
  "features": [
    {
      "type": "Feature",
      "geometry": {
        "type": "Point",
        "coordinates": [
          14.4796767,
          37.4308098
        ]
      },
      "properties": {
        "description": "representative point"
      }
    },
    {
      "geometry": {
        "type": "Point",
        "coordinates": [
          14.4796767,
          37.4308098
        ]
      },
      "id": "location-of-ekklesiasterion",
      "type": "Feature",
      "properties": {
        "description": "Location based on OpenStreetMap",
        "location_precision": "precise",
        "title": "OSM location of Ekklesiasterion",
        "link": "http://pleiades.stoa.org/places/349338482/location-of-ekklesiasterion"
      }
    }
  ]
}