{
  "type": "FeatureCollection",
  "title": "duplicate: Ekklesiasterion",
  "id": "349338482",
  "bbox": [
    14.4796767,
    37.4308098,
    14.4796767,
    37.4308098
  ],
  "description": "This place resource has been moved to Errata because it is a duplicate for https://pleiades.stoa.org/places/966917974",
  "features": [
    {
      "type": "Feature",
      "geometry": {
        "type": "Point",
        "coordinates": [
          14.4796767,
          37.4308098
        ]
      },
      "properties": {
        "description": "representative point"
      }
    },
    {
      "geometry": {
        "type": "Point",
        "coordinates": [
          14.4796767,
          37.4308098
        ]
      },
      "id": "location-of-ekklesiasterion",
      "type": "Feature",
      "properties": {
        "description": "Location based on OpenStreetMap",
        "location_precision": "precise",
        "title": "OSM location of Ekklesiasterion",
        "link": "http://pleiades.stoa.org/errata/349338482/location-of-ekklesiasterion"
      }
    }
  ]
}