{
  "type": "FeatureCollection",
  "title": "Paleochristian basilica",
  "id": "353853857",
  "bbox": [
    12.628552,
    41.939243,
    12.628552,
    41.939243
  ],
  "description": "A Paleochristian basilica was discovered at the eighth mile of the Via Tiburtina in 2003. The subterranean basilica reused an earlier quarry and may be related to San Sinforosa. The site dates from the late fourth to the middle of the fifth century CE.",
  "connectsWith": [
    "272213281"
  ],
  "features": [
    {
      "type": "Feature",
      "geometry": {
        "type": "Point",
        "coordinates": [
          12.628552,
          41.939243
        ]
      },
      "properties": {
        "description": "representative point"
      }
    },
    {
      "geometry": {
        "type": "Point",
        "coordinates": [
          12.628552,
          41.939243
        ]
      },
      "id": "vici-org-location",
      "type": "Feature",
      "properties": {
        "description": "Coordinates following vici.org",
        "location_precision": "precise",
        "title": "vici.org location",
        "link": "http://pleiades.stoa.org/places/353853857/vici-org-location"
      }
    }
  ]
}