{
  "type": "FeatureCollection",
  "title": "el-Abiad",
  "id": "354097",
  "bbox": [
    13.994788,
    26.760357,
    13.994788,
    26.760357
  ],
  "description": "An ancient place, cited: BAtlas 36 D5 el-Abiad",
  "features": [
    {
      "type": "Feature",
      "geometry": {
        "type": "Point",
        "coordinates": [
          13.994788,
          26.760357
        ]
      },
      "properties": {
        "description": "representative point"
      }
    },
    {
      "geometry": {
        "type": "Point",
        "coordinates": [
          13.994788,
          26.760357
        ]
      },
      "id": "darmc-location-33015",
      "type": "Feature",
      "properties": {
        "description": "representative point location digitized from the Barrington Atlas of the Greek and Roman World by the Digital Atlas of Roman and Medieval Civilizations project at Harvard University.",
        "location_precision": "precise",
        "title": "DARMC location 33015",
        "link": "http://pleiades.stoa.org/places/354097/darmc-location-33015"
      }
    }
  ]
}