{
  "type": "FeatureCollection",
  "title": "el-Fgeg",
  "id": "354113",
  "bbox": [
    13.308046,
    26.544488,
    13.308046,
    26.544488
  ],
  "description": "An ancient place, cited: BAtlas 36 C5 el-Fgeg",
  "features": [
    {
      "type": "Feature",
      "geometry": {
        "type": "Point",
        "coordinates": [
          13.308046,
          26.544488
        ]
      },
      "properties": {
        "description": "representative point"
      }
    },
    {
      "geometry": {
        "type": "Point",
        "coordinates": [
          13.308046,
          26.544488
        ]
      },
      "id": "darmc-location-33006",
      "type": "Feature",
      "properties": {
        "description": "representative point location digitized from the Barrington Atlas of the Greek and Roman World by the Digital Atlas of Roman and Medieval Civilizations project at Harvard University.",
        "location_precision": "precise",
        "title": "DARMC location 33006",
        "link": "http://pleiades.stoa.org/places/354113/darmc-location-33006"
      }
    }
  ]
}