{
  "type": "FeatureCollection",
  "title": "Germa Necropoleis",
  "id": "354123",
  "bbox": [
    12.949973,
    26.55852,
    12.949973,
    26.55852
  ],
  "description": "Necropolis south of Garama Metropolis",
  "features": [
    {
      "type": "Feature",
      "geometry": {
        "type": "Point",
        "coordinates": [
          12.949973,
          26.55852
        ]
      },
      "properties": {
        "description": "representative point"
      }
    },
    {
      "geometry": {
        "type": "Point",
        "coordinates": [
          12.949973,
          26.55852
        ]
      },
      "id": "darmc-location-22999",
      "type": "Feature",
      "properties": {
        "description": "Point location",
        "location_precision": "precise",
        "title": "DARMC location 22999",
        "link": "http://pleiades.stoa.org/places/354123/darmc-location-22999"
      }
    }
  ]
}