{
  "type": "FeatureCollection",
  "title": "el-Gheraia",
  "id": "354124",
  "description": "An ancient place, cited: BAtlas 36 C5 el-Gheraia",
  "bbox": [
    13.368512,
    26.53336,
    13.368512,
    26.53336
  ],
  "reprPoint": [
    13.368512,
    26.53336
  ],
  "features": [
    {
      "geometry": {
        "type": "Point",
        "coordinates": [
          13.368512,
          26.53336
        ]
      },
      "id": "darmc-location-33008",
      "type": "Feature",
      "properties": {
        "description": "scale point location",
        "location_precision": "precise",
        "title": "DARMC location 33008",
        "link": "http://pleiades.stoa.org/places/354124/darmc-location-33008"
      }
    }
  ]
}