{
  "type": "FeatureCollection",
  "title": "el-Hassi",
  "id": "354130",
  "description": "An ancient place, cited: BAtlas 36 B3 el-Hassi",
  "bbox": [
    12.599991,
    28.129287,
    12.725221,
    28.266668
  ],
  "reprPoint": [
    12.662606,
    28.1979775
  ],
  "features": [
    {
      "geometry": {
        "type": "Point",
        "coordinates": [
          12.725221,
          28.129287
        ]
      },
      "id": "darmc-location-15562",
      "type": "Feature",
      "properties": {
        "description": "1M scale point location",
        "location_precision": "precise",
        "title": "DARMC location 15562",
        "link": "http://pleiades.stoa.org/places/354130/darmc-location-15562"
      }
    },
    {
      "geometry": {
        "type": "Point",
        "coordinates": [
          12.599991,
          28.266668
        ]
      },
      "id": "darmc-location-32996",
      "type": "Feature",
      "properties": {
        "description": "scale point location",
        "location_precision": "precise",
        "title": "DARMC location 32996",
        "link": "http://pleiades.stoa.org/places/354130/darmc-location-32996"
      }
    }
  ]
}