{
  "type": "FeatureCollection",
  "title": "'Ain Ghazal",
  "id": "357303540",
  "description": "A Neolithic settlement inhabited from ca. 7250 BC to 5000 BC; located in the northwest of Jordan.",
  "bbox": [
    35.9764962,
    31.9883253,
    35.9764962,
    31.9883253
  ],
  "reprPoint": [
    35.9764962,
    31.9883253
  ],
  "features": [
    {
      "geometry": {
        "type": "Point",
        "coordinates": [
          35.9764962,
          31.9883253
        ]
      },
      "id": "osm-location-of-ain-ghazal",
      "type": "Feature",
      "properties": {
        "description": "Representative location based on OpenStreetMap.",
        "location_precision": "precise",
        "title": "OSM location of 'Ain Ghazal",
        "link": "http://pleiades.stoa.org/places/357303540/osm-location-of-ain-ghazal"
      }
    }
  ]
}