{
  "type": "FeatureCollection",
  "title": "So-called Temple of Aphrodite",
  "id": "357884165",
  "bbox": [
    21.8576607,
    32.8174354,
    21.8576607,
    32.8174354
  ],
  "description": "A temple located on the acropolis of Cyrene.",
  "connectsWith": [
    "373778"
  ],
  "names": [
    "Temple of Aphrodite",
    "Tempio di Afrodite"
  ],
  "features": [
    {
      "type": "Feature",
      "geometry": {
        "type": "Point",
        "coordinates": [
          21.8576607,
          32.8174354
        ]
      },
      "properties": {
        "description": "representative point"
      }
    },
    {
      "geometry": {
        "type": "Point",
        "coordinates": [
          21.8576607,
          32.8174354
        ]
      },
      "id": "temple-of-aphrodite",
      "type": "Feature",
      "properties": {
        "description": "Representative OpenStreetMap location of the Temple of Aphrodite, in the acropolis of Cyrene.",
        "location_precision": "precise",
        "title": "OSM location of the so-called Temple of Aphrodite in Cyrene",
        "link": "http://pleiades.stoa.org/places/357884165/temple-of-aphrodite"
      }
    }
  ]
}