{
  "type": "FeatureCollection",
  "title": "Nuraghe S. Cadrina",
  "id": "359131497",
  "description": "A nuragic village of the Middle Bronze Age (ca. 1700-1350 BC), Nuraghe S. Cadrina has a central tower with an original diameter of 11.70 m.",
  "bbox": [
    8.489198,
    40.637067,
    8.489198,
    40.637067
  ],
  "connectsWith": [
    "472014"
  ],
  "reprPoint": [
    8.489198,
    40.637067
  ],
  "features": [
    {
      "geometry": {
        "type": "Point",
        "coordinates": [
          8.489198,
          40.637067
        ]
      },
      "id": "location-of-nuraghe-s.-cadrina",
      "type": "Feature",
      "properties": {
        "description": "Coordinates after Wikimapia; verified in Google Earth 2013.",
        "location_precision": "precise",
        "title": "location of Nuraghe S. Cadrina",
        "link": "http://pleiades.stoa.org/places/359131497/location-of-nuraghe-s.-cadrina"
      }
    }
  ]
}