{
  "type": "FeatureCollection",
  "title": "Prata Mucia",
  "id": "360312698",
  "bbox": [
    12.486137,
    41.891775,
    12.486137,
    41.891775
  ],
  "description": "The so-called Prata Mucia was a meadow granted to the Roman Republican hero Mucius Scaevola in recognition of his heroism in the face of the invasion of Lars Porsena of Clusium.",
  "connectsWith": [
    "423025",
    "217953464"
  ],
  "names": [
    "Mucia prata"
  ],
  "features": [
    {
      "type": "Feature",
      "geometry": {
        "type": "Point",
        "coordinates": [
          12.486137,
          41.891775
        ]
      },
      "properties": {
        "description": "representative point"
      }
    }
  ]
}