{
  "type": "FeatureCollection",
  "title": "San Roque Theatre - Carteia",
  "id": "362008414",
  "bbox": [
    -5.4072927,
    36.1857375,
    -5.4072927,
    36.1857375
  ],
  "description": "The Roman theater of Carteia.",
  "connectsWith": [
    "256063"
  ],
  "features": [
    {
      "type": "Feature",
      "geometry": {
        "type": "Point",
        "coordinates": [
          -5.4072927,
          36.1857375
        ]
      },
      "properties": {
        "description": "representative point"
      }
    },
    {
      "geometry": {
        "type": "Point",
        "coordinates": [
          -5.4072927,
          36.1857375
        ]
      },
      "id": "osm-location-of-theater",
      "type": "Feature",
      "properties": {
        "description": "Location based on OpenStreetMap",
        "location_precision": "precise",
        "title": "OSM location of San Roque Theatre - Carteia",
        "link": "http://pleiades.stoa.org/places/362008414/osm-location-of-theater"
      }
    }
  ]
}