{
  "type": "FeatureCollection",
  "title": "Annesel",
  "id": "363922",
  "bbox": [
    15.584823,
    31.364153,
    15.584823,
    31.364153
  ],
  "description": "An ancient place, cited: BAtlas 37 A1 Annesel",
  "names": [
    "Annesel"
  ],
  "features": [
    {
      "type": "Feature",
      "geometry": {
        "type": "Point",
        "coordinates": [
          15.584823,
          31.364153
        ]
      },
      "properties": {
        "description": "representative point"
      }
    },
    {
      "geometry": {
        "type": "Point",
        "coordinates": [
          15.584823,
          31.364153
        ]
      },
      "id": "darmc-location-9725",
      "type": "Feature",
      "properties": {
        "description": "1M scale point location",
        "location_precision": "precise",
        "title": "DARMC location 9725",
        "link": "http://pleiades.stoa.org/places/363922/darmc-location-9725"
      }
    }
  ]
}