{
  "type": "FeatureCollection",
  "title": "el-Faschia",
  "id": "363961",
  "description": "An ancient place, cited: BAtlas 37 B1 el-Faschia",
  "bbox": [
    16.425148,
    31.204628,
    16.425148,
    31.204628
  ],
  "reprPoint": [
    16.425148,
    31.204628
  ],
  "features": [
    {
      "geometry": {
        "type": "Point",
        "coordinates": [
          16.425148,
          31.204628
        ]
      },
      "id": "darmc-location-16889",
      "type": "Feature",
      "properties": {
        "description": "1M scale point location",
        "location_precision": "precise",
        "title": "DARMC location 16889",
        "link": "http://pleiades.stoa.org/places/363961/darmc-location-16889"
      }
    }
  ]
}