{
  "type": "FeatureCollection",
  "title": "‘Auxiu’",
  "id": "363933",
  "description": "An ancient place, cited: BAtlas 37 A1 ‘Auxiu’",
  "bbox": [
    15.851181,
    31.281729,
    15.851181,
    31.281729
  ],
  "reprPoint": [
    15.851181,
    31.281729
  ],
  "names": [
    "Auxiu"
  ],
  "features": [
    {
      "geometry": {
        "type": "Point",
        "coordinates": [
          15.851181,
          31.281729
        ]
      },
      "id": "darmc-location-9636",
      "type": "Feature",
      "properties": {
        "description": "1M scale point location",
        "location_precision": "precise",
        "title": "DARMC location 9636",
        "link": "http://pleiades.stoa.org/places/363933/darmc-location-9636"
      }
    }
  ]
}