{
  "type": "FeatureCollection",
  "title": "Gasr ed-Dubban",
  "id": "363966",
  "description": "An ancient place, cited: BAtlas 37 B1 Gasr ed-Dubban",
  "bbox": [
    16.519899,
    31.154266,
    16.519899,
    31.154266
  ],
  "reprPoint": [
    16.519899,
    31.154266
  ],
  "features": [
    {
      "geometry": {
        "type": "Point",
        "coordinates": [
          16.519899,
          31.154266
        ]
      },
      "id": "darmc-location-27441",
      "type": "Feature",
      "properties": {
        "description": "1M scale point location",
        "location_precision": "precise",
        "title": "DARMC location 27441",
        "link": "http://pleiades.stoa.org/places/363966/darmc-location-27441"
      }
    }
  ]
}