{
  "type": "FeatureCollection",
  "title": "Astrochonda",
  "id": "363928",
  "description": "An ancient place, cited: BAtlas 37 E2 Astrochonda",
  "bbox": [
    19.944513,
    30.700047,
    19.944565,
    30.70005
  ],
  "reprPoint": [
    19.944539,
    30.7000485
  ],
  "names": [
    "Astrochonda"
  ],
  "features": [
    {
      "geometry": {
        "type": "Point",
        "coordinates": [
          19.944565,
          30.70005
        ]
      },
      "id": "darmc-location-2851",
      "type": "Feature",
      "properties": {
        "description": "1M scale point location",
        "location_precision": "precise",
        "title": "DARMC location 2851",
        "link": "http://pleiades.stoa.org/places/363928/darmc-location-2851"
      }
    },
    {
      "geometry": {
        "type": "Point",
        "coordinates": [
          19.944513,
          30.700047
        ]
      },
      "id": "darmc-location-2852",
      "type": "Feature",
      "properties": {
        "description": "1M scale point location",
        "location_precision": "precise",
        "title": "DARMC location 2852",
        "link": "http://pleiades.stoa.org/places/363928/darmc-location-2852"
      }
    }
  ]
}