{
  "type": "FeatureCollection",
  "title": "Fines Africae et Cyrenensium",
  "id": "363962",
  "description": "An ancient place, cited: BAtlas 37 D2 Fines Africae et Cyrenensium",
  "bbox": [
    18.7924,
    30.279406,
    18.805925,
    30.2995
  ],
  "reprPoint": [
    18.7991625,
    30.289453
  ],
  "names": [
    "Fines Africae et Cyrenensium",
    "Arae Philaenorum"
  ],
  "features": [
    {
      "geometry": {
        "type": "Point",
        "coordinates": [
          18.805925,
          30.279406
        ]
      },
      "id": "darmc-location-15957",
      "type": "Feature",
      "properties": {
        "description": "1M scale point location",
        "location_precision": "precise",
        "title": "DARMC location 15957",
        "link": "http://pleiades.stoa.org/places/363962/darmc-location-15957"
      }
    }
  ]
}