{
  "type": "FeatureCollection",
  "title": "Ad Puteum",
  "id": "363916",
  "description": "An ancient place, cited: BAtlas 37 E2 Ad Puteum",
  "bbox": [
    19.667441,
    30.317862,
    19.667441,
    30.317862
  ],
  "reprPoint": [
    19.667441,
    30.317862
  ],
  "names": [
    "Ad Puteum"
  ],
  "features": [
    {
      "geometry": {
        "type": "Point",
        "coordinates": [
          19.667441,
          30.317862
        ]
      },
      "id": "darmc-location-9722",
      "type": "Feature",
      "properties": {
        "description": "1M scale point location",
        "location_precision": "precise",
        "title": "DARMC location 9722",
        "link": "http://pleiades.stoa.org/places/363916/darmc-location-9722"
      }
    }
  ]
}