{
  "type": "FeatureCollection",
  "title": "Dafni",
  "id": "363953",
  "description": "An ancient place, cited: BAtlas 37 B1 Dafni",
  "bbox": [
    16.77768,
    31.191409,
    16.77768,
    31.191409
  ],
  "reprPoint": [
    16.77768,
    31.191409
  ],
  "features": [
    {
      "geometry": {
        "type": "Point",
        "coordinates": [
          16.77768,
          31.191409
        ]
      },
      "id": "darmc-location-17406",
      "type": "Feature",
      "properties": {
        "description": "1M scale point location",
        "location_precision": "precise",
        "title": "DARMC location 17406",
        "link": "http://pleiades.stoa.org/places/363953/darmc-location-17406"
      }
    }
  ]
}