{
  "type": "FeatureCollection",
  "title": "Ad Turrem",
  "id": "363918",
  "bbox": [
    17.830009,
    30.779987,
    17.830009,
    30.779987
  ],
  "description": "An ancient place, cited: BAtlas 37 C2 Ad Turrem",
  "names": [
    "Ad Turrem",
    "Turris Lapideum"
  ],
  "features": [
    {
      "type": "Feature",
      "geometry": {
        "type": "Point",
        "coordinates": [
          17.830009,
          30.779987
        ]
      },
      "properties": {
        "description": "representative point"
      }
    },
    {
      "geometry": {
        "type": "Point",
        "coordinates": [
          17.830009,
          30.779987
        ]
      },
      "id": "darmc-location-825",
      "type": "Feature",
      "properties": {
        "description": "1M scale point location",
        "location_precision": "precise",
        "title": "DARMC location 825",
        "link": "http://pleiades.stoa.org/places/363918/darmc-location-825"
      }
    }
  ]
}