{
  "type": "FeatureCollection",
  "title": "Tramaricio",
  "id": "364024",
  "description": "An ancient place, cited: BAtlas 37 C1 Tramaricio",
  "bbox": [
    17.550006,
    30.999875,
    17.550006,
    30.999875
  ],
  "reprPoint": [
    17.550006,
    30.999875
  ],
  "names": [
    "Tramaricio"
  ],
  "features": [
    {
      "geometry": {
        "type": "Point",
        "coordinates": [
          17.550006,
          30.999875
        ]
      },
      "id": "darmc-location-9756",
      "type": "Feature",
      "properties": {
        "description": "1M scale point location",
        "location_precision": "precise",
        "title": "DARMC location 9756",
        "link": "http://pleiades.stoa.org/places/364024/darmc-location-9756"
      }
    }
  ]
}