{
  "type": "FeatureCollection",
  "title": "Umm el-Gbur",
  "id": "364030",
  "bbox": [
    16.743,
    30.946,
    16.743,
    30.946
  ],
  "description": "An ancient settlement at modern Umm el-Gbur in Libya.",
  "features": [
    {
      "type": "Feature",
      "geometry": {
        "type": "Point",
        "coordinates": [
          16.743,
          30.946
        ]
      },
      "properties": {
        "description": "representative point"
      }
    },
    {
      "geometry": {
        "type": "Point",
        "coordinates": [
          16.743,
          30.946
        ]
      },
      "id": "batlas-location",
      "type": "Feature",
      "properties": {
        "description": null,
        "location_precision": "precise",
        "title": "BAtlas Location",
        "link": "http://pleiades.stoa.org/places/364030/batlas-location"
      }
    }
  ]
}