{
  "type": "FeatureCollection",
  "title": "Ras il-Wardija",
  "id": "364392646",
  "bbox": [
    14.1871584,
    36.0365346,
    14.1871584,
    36.0365346
  ],
  "description": "A Punic-Roman sanctuary site located on the western coast of Gozo (Gaulos), Malta.",
  "connectsWith": [
    "462213"
  ],
  "features": [
    {
      "type": "Feature",
      "geometry": {
        "type": "Point",
        "coordinates": [
          14.1871584,
          36.0365346
        ]
      },
      "properties": {
        "description": "representative point"
      }
    },
    {
      "geometry": {
        "type": "Point",
        "coordinates": [
          14.1871584,
          36.0365346
        ]
      },
      "id": "osm-location-of-ras-il-wardija",
      "type": "Feature",
      "properties": {
        "description": "Point representing the location of the Ras il-Wardija site, derived from an OpenStreetMap Node.",
        "location_precision": "precise",
        "title": "OSM location of Ras il-Wardija",
        "link": "http://pleiades.stoa.org/places/364392646/osm-location-of-ras-il-wardija"
      }
    }
  ]
}