{
  "type": "FeatureCollection",
  "title": "Örendibi",
  "id": "364777233",
  "bbox": [
    34.073561,
    36.581786,
    34.073561,
    36.581786
  ],
  "description": "Modern name for ruins of a Byzantine church and surrounding rural settlement in eastern Rough Cilicia",
  "features": [
    {
      "type": "Feature",
      "geometry": {
        "type": "Point",
        "coordinates": [
          34.073561,
          36.581786
        ]
      },
      "properties": {
        "description": "representative point"
      }
    },
    {
      "geometry": {
        "type": "Point",
        "coordinates": [
          34.073561,
          36.581786
        ]
      },
      "id": "osm-location-orendibi",
      "type": "Feature",
      "properties": {
        "description": null,
        "location_precision": "precise",
        "title": "OSM Location: Örendibi",
        "link": "http://pleiades.stoa.org/places/364777233/osm-location-orendibi"
      }
    }
  ]
}