{
  "type": "FeatureCollection",
  "title": "Sanctuary of Aphrodite Pandemos",
  "id": "365016220",
  "bbox": [
    23.72482,
    37.97139,
    23.72482,
    37.97139
  ],
  "description": "The sanctuary of Aphrodite Pandemos (\"of all the People\") and Peitho (\"Persuasion\"), established by Theseus or Solon, was located on the south slope of the Acropolis of Athens, directly below the Nike Temple bastion. It was a centre of the Aphrodisia and Arrephoria festivals. The surviving remains belong to a structure built ca. 287/6 BCE.",
  "connectsWith": [
    "638356144",
    "648120846"
  ],
  "names": [
    "Aphrodítēs pandḗmou hierón"
  ],
  "features": [
    {
      "type": "Feature",
      "geometry": {
        "type": "Point",
        "coordinates": [
          23.72482,
          37.97139
        ]
      },
      "properties": {
        "description": "representative point"
      }
    },
    {
      "geometry": {
        "type": "Point",
        "coordinates": [
          23.72482,
          37.97139
        ]
      },
      "id": "topostext-location-aphrodite-pandemos-shrine",
      "type": "Feature",
      "properties": {
        "description": null,
        "location_precision": "precise",
        "title": "ToposText location: Aphrodite Pandemos shrine",
        "link": "http://pleiades.stoa.org/places/365016220/topostext-location-aphrodite-pandemos-shrine"
      }
    }
  ]
}