{
  "type": "FeatureCollection",
  "title": "Anduarsalia",
  "id": "37101101",
  "bbox": [
    37.241604,
    38.440955,
    38.69165,
    38.727385
  ],
  "description": "A fortress in the vicinity of Til-garimmu fortified by the Assyrian king Sargon II (r. 721-705 BC) against Urarṭu.",
  "connectsWith": [
    "628982",
    "762647722",
    "629008",
    "522605291",
    "100544804",
    "629098",
    "319432673",
    "214160492",
    "3456694"
  ],
  "names": [
    "Anduarsalla"
  ],
  "features": [
    {
      "type": "Feature",
      "geometry": {
        "type": "Point",
        "coordinates": [
          38.1120586667,
          38.616165
        ]
      },
      "properties": {
        "description": "representative point"
      }
    }
  ]
}