{
  "type": "FeatureCollection",
  "title": "Regio XIII (Aventinus)",
  "id": "372769291",
  "bbox": [
    12.4733601,
    41.8798032,
    12.4739297,
    41.8802375
  ],
  "description": "The thirteenth administrative region of ancient Rome was created by Augustus in 7 BCE. This district contained 17 shrines (aediculae), 130 townhouses (domūs), 35 warehouses (horrea), 60 bath houses, and 88 fountains in addition to a list of monuments enumerated in the Regionary Catalogues.",
  "connectsWith": [
    "423025"
  ],
  "features": [
    {
      "type": "Feature",
      "geometry": {
        "type": "Point",
        "coordinates": [
          12.4736449,
          41.88002035
        ]
      },
      "properties": {
        "description": "representative point"
      }
    }
  ]
}