{
  "type": "FeatureCollection",
  "title": "Darnis",
  "id": "373780",
  "description": "An ancient place, cited: BAtlas 38 D1 Darnis",
  "bbox": [
    22.639207,
    32.763363,
    22.6437,
    32.77
  ],
  "reprPoint": [
    22.6415516667,
    32.767385
  ],
  "names": [
    "Darnis",
    "Darne",
    "Derna"
  ],
  "features": [
    {
      "geometry": {
        "type": "Point",
        "coordinates": [
          22.641748,
          32.768792
        ]
      },
      "id": "darmc-location-12158",
      "type": "Feature",
      "properties": {
        "description": "1M scale point location",
        "location_precision": "precise",
        "title": "DARMC location 12158",
        "link": "http://pleiades.stoa.org/places/373780/darmc-location-12158"
      }
    },
    {
      "geometry": {
        "type": "Point",
        "coordinates": [
          22.639207,
          32.763363
        ]
      },
      "id": "dare-location",
      "type": "Feature",
      "properties": {
        "description": "Representative point location, village precision",
        "location_precision": "precise",
        "title": "DARE Location",
        "link": "http://pleiades.stoa.org/places/373780/dare-location"
      }
    }
  ]
}