{
  "type": "FeatureCollection",
  "title": "Ampalaontes?",
  "id": "373730",
  "bbox": [
    20.044533,
    31.913255,
    20.044533,
    31.913255
  ],
  "description": "An ancient place, cited: BAtlas 38 B2 Ampalaontes?",
  "names": [
    "Ampalaontes"
  ],
  "features": [
    {
      "type": "Feature",
      "geometry": {
        "type": "Point",
        "coordinates": [
          20.044533,
          31.913255
        ]
      },
      "properties": {
        "description": "representative point"
      }
    },
    {
      "geometry": {
        "type": "Point",
        "coordinates": [
          20.044533,
          31.913255
        ]
      },
      "id": "darmc-location-11356",
      "type": "Feature",
      "properties": {
        "description": "1M scale point location",
        "location_precision": "precise",
        "title": "DARMC location 11356",
        "link": "http://pleiades.stoa.org/places/373730/darmc-location-11356"
      }
    }
  ]
}