{
  "type": "FeatureCollection",
  "title": "Ain Zeina",
  "id": "373728",
  "description": "An ancient place, cited: BAtlas 38 B1 Ain Zeina",
  "bbox": [
    20.162349,
    32.232314,
    20.162349,
    32.232314
  ],
  "reprPoint": [
    20.162349,
    32.232314
  ],
  "features": [
    {
      "geometry": {
        "type": "Point",
        "coordinates": [
          20.162349,
          32.232314
        ]
      },
      "id": "darmc-location-11248",
      "type": "Feature",
      "properties": {
        "description": "1M scale point location",
        "location_precision": "precise",
        "title": "DARMC location 11248",
        "link": "http://pleiades.stoa.org/places/373728/darmc-location-11248"
      }
    }
  ]
}