{
  "type": "FeatureCollection",
  "title": "Chaulan",
  "id": "373769",
  "description": "An ancient place, cited: BAtlas 38 D1 Chaulan",
  "bbox": [
    22.1289,
    32.5647,
    22.13421,
    32.565129
  ],
  "reprPoint": [
    22.131555,
    32.5649145
  ],
  "features": [
    {
      "geometry": {
        "type": "Point",
        "coordinates": [
          22.13421,
          32.565129
        ]
      },
      "id": "darmc-location-11997",
      "type": "Feature",
      "properties": {
        "description": "1M scale point location",
        "location_precision": "precise",
        "title": "DARMC location 11997",
        "link": "http://pleiades.stoa.org/places/373769/darmc-location-11997"
      }
    }
  ]
}