{
  "type": "FeatureCollection",
  "title": "el-Farzuga",
  "id": "373789",
  "description": "An ancient place, cited: BAtlas 38 B1 el-Farzuga",
  "bbox": [
    20.731216,
    32.5205,
    20.7315,
    32.520533
  ],
  "reprPoint": [
    20.731358,
    32.5205165
  ],
  "features": [
    {
      "geometry": {
        "type": "Point",
        "coordinates": [
          20.731216,
          32.520533
        ]
      },
      "id": "darmc-location-27681",
      "type": "Feature",
      "properties": {
        "description": "1M scale point location",
        "location_precision": "precise",
        "title": "DARMC location 27681",
        "link": "http://pleiades.stoa.org/places/373789/darmc-location-27681"
      }
    }
  ]
}