{
  "type": "FeatureCollection",
  "title": "Darnis",
  "id": "373780",
  "bbox": [
    22.639207,
    32.763363,
    22.641748,
    32.768792
  ],
  "description": "An ancient place, cited: BAtlas 38 D1 Darnis",
  "names": [
    "Darnis",
    "Darne",
    "Derna"
  ],
  "features": [
    {
      "type": "Feature",
      "geometry": {
        "type": "Point",
        "coordinates": [
          22.6404775,
          32.7660775
        ]
      },
      "properties": {
        "description": "representative point"
      }
    },
    {
      "geometry": {
        "type": "Point",
        "coordinates": [
          22.641748,
          32.768792
        ]
      },
      "id": "darmc-location-12158",
      "type": "Feature",
      "properties": {
        "description": "1M scale point location",
        "location_precision": "precise",
        "title": "DARMC location 12158",
        "link": "http://pleiades.stoa.org/places/373780/darmc-location-12158"
      }
    },
    {
      "geometry": {
        "type": "Point",
        "coordinates": [
          22.639207,
          32.763363
        ]
      },
      "id": "dare-location",
      "type": "Feature",
      "properties": {
        "description": "Representative point location, village precision",
        "location_precision": "precise",
        "title": "DARE Location",
        "link": "http://pleiades.stoa.org/places/373780/dare-location"
      }
    }
  ]
}