{
  "type": "FeatureCollection",
  "title": "Drepanon",
  "id": "373782",
  "bbox": [
    20.013881,
    31.476849,
    20.013881,
    31.476849
  ],
  "description": "An ancient place, cited: BAtlas 38 B2 Drepanon",
  "names": [
    "Drepanon"
  ],
  "features": [
    {
      "type": "Feature",
      "geometry": {
        "type": "Point",
        "coordinates": [
          20.013881,
          31.476849
        ]
      },
      "properties": {
        "description": "representative point"
      }
    },
    {
      "geometry": {
        "type": "Point",
        "coordinates": [
          20.013881,
          31.476849
        ]
      },
      "id": "darmc-location-731",
      "type": "Feature",
      "properties": {
        "description": "1M scale point location",
        "location_precision": "precise",
        "title": "DARMC location 731",
        "link": "http://pleiades.stoa.org/places/373782/darmc-location-731"
      }
    }
  ]
}