{
  "type": "FeatureCollection",
  "title": "Chairekla",
  "id": "373767",
  "bbox": [
    20.644052,
    32.254203,
    20.644052,
    32.254203
  ],
  "description": "An ancient place, cited: BAtlas 38 B1 Chairekla",
  "names": [
    "Chairekla"
  ],
  "features": [
    {
      "type": "Feature",
      "geometry": {
        "type": "Point",
        "coordinates": [
          20.644052,
          32.254203
        ]
      },
      "properties": {
        "description": "representative point"
      }
    },
    {
      "geometry": {
        "type": "Point",
        "coordinates": [
          20.644052,
          32.254203
        ]
      },
      "id": "darmc-location-11968",
      "type": "Feature",
      "properties": {
        "description": "1M scale point location",
        "location_precision": "precise",
        "title": "DARMC location 11968",
        "link": "http://pleiades.stoa.org/places/373767/darmc-location-11968"
      }
    }
  ]
}