{
  "type": "FeatureCollection",
  "title": "el-Belgas",
  "id": "373754",
  "bbox": [
    21.987939,
    32.698926,
    21.987939,
    32.698926
  ],
  "description": "An ancient place, cited: BAtlas 38 C1 el-Belgas",
  "features": [
    {
      "type": "Feature",
      "geometry": {
        "type": "Point",
        "coordinates": [
          21.987939,
          32.698926
        ]
      },
      "properties": {
        "description": "representative point"
      }
    },
    {
      "geometry": {
        "type": "Point",
        "coordinates": [
          21.987939,
          32.698926
        ]
      },
      "id": "darmc-location-25574",
      "type": "Feature",
      "properties": {
        "description": "1M scale point location",
        "location_precision": "precise",
        "title": "DARMC location 25574",
        "link": "http://pleiades.stoa.org/places/373754/darmc-location-25574"
      }
    }
  ]
}