{
  "type": "FeatureCollection",
  "title": "Arsinoe/Taucheira",
  "id": "373736",
  "bbox": [
    20.565847,
    32.535553,
    20.569683,
    32.537142
  ],
  "description": "Arsinoe/Taucheira (modern Tocra) may have originally been a Greek foundation that was part of Pentapolis of Cyrenaica. It eventually became a Roman colony and, by the time of Justinian, was fortified.",
  "names": [
    "Arsinoe",
    "Taucheira",
    "Teucheira"
  ],
  "features": [
    {
      "type": "Feature",
      "geometry": {
        "type": "Point",
        "coordinates": [
          20.5672976667,
          32.5363993333
        ]
      },
      "properties": {
        "description": "representative point"
      }
    },
    {
      "geometry": {
        "type": "Point",
        "coordinates": [
          20.569683,
          32.535553
        ]
      },
      "id": "darmc-location-3367",
      "type": "Feature",
      "properties": {
        "description": "1:1 million scale representative point location digitized from the Barrington Atlas of the Greek and Roman World by the Digital Atlas of Roman and Medieval Civilizations project at Harvard University.",
        "location_precision": "precise",
        "title": "DARMC location 3367",
        "link": "http://pleiades.stoa.org/places/373736/darmc-location-3367"
      }
    },
    {
      "geometry": {
        "type": "Point",
        "coordinates": [
          20.566363,
          32.536503
        ]
      },
      "id": "darmc-location-34899",
      "type": "Feature",
      "properties": {
        "description": "representative point location digitized from the Barrington Atlas of the Greek and Roman World by the Digital Atlas of Roman and Medieval Civilizations project at Harvard University.",
        "location_precision": "precise",
        "title": "DARMC location 34899",
        "link": "http://pleiades.stoa.org/places/373736/darmc-location-34899"
      }
    },
    {
      "geometry": {
        "type": "Point",
        "coordinates": [
          20.565847,
          32.537142
        ]
      },
      "id": "dare-location",
      "type": "Feature",
      "properties": {
        "description": "Representative point location, site precision",
        "location_precision": "precise",
        "title": "DARE Location",
        "link": "http://pleiades.stoa.org/places/373736/dare-location"
      }
    }
  ]
}