{
  "type": "FeatureCollection",
  "title": "el-Mtaugat",
  "id": "373858",
  "description": "An ancient place, cited: BAtlas 38 D1 el-Mtaugat",
  "bbox": [
    22.044719,
    32.7628,
    22.0458,
    32.763104
  ],
  "reprPoint": [
    22.0452595,
    32.762952
  ],
  "features": [
    {
      "geometry": {
        "type": "Point",
        "coordinates": [
          22.0458,
          32.7628
        ]
      },
      "id": "batlas-location",
      "type": "Feature",
      "properties": {
        "description": null,
        "location_precision": "precise",
        "title": "Barrington Atlas map location",
        "link": "http://pleiades.stoa.org/places/373858/batlas-location"
      }
    },
    {
      "geometry": {
        "type": "Point",
        "coordinates": [
          22.044719,
          32.763104
        ]
      },
      "id": "darmc-location-25587",
      "type": "Feature",
      "properties": {
        "description": "1M scale point location",
        "location_precision": "precise",
        "title": "DARMC location 25587",
        "link": "http://pleiades.stoa.org/places/373858/darmc-location-25587"
      }
    }
  ]
}