{
  "type": "FeatureCollection",
  "title": "Lasamices?",
  "id": "373838",
  "bbox": [
    21.712327,
    32.590008,
    21.712327,
    32.590008
  ],
  "description": "An ancient place, cited: BAtlas 38 C1 Lasamices?",
  "names": [
    "Lasamices",
    "Lasanices"
  ],
  "features": [
    {
      "type": "Feature",
      "geometry": {
        "type": "Point",
        "coordinates": [
          21.712327,
          32.590008
        ]
      },
      "properties": {
        "description": "representative point"
      }
    },
    {
      "geometry": {
        "type": "Point",
        "coordinates": [
          21.712327,
          32.590008
        ]
      },
      "id": "darmc-location-13419",
      "type": "Feature",
      "properties": {
        "description": "1M scale point location",
        "location_precision": "precise",
        "title": "DARMC location 13419",
        "link": "http://pleiades.stoa.org/places/373838/darmc-location-13419"
      }
    }
  ]
}