{
  "type": "FeatureCollection",
  "title": "Gasr Zeitun",
  "id": "373816",
  "description": "An ancient place, cited: BAtlas 38 D1 Gasr Zeitun",
  "bbox": [
    22.8256,
    32.624289,
    22.827284,
    32.6246
  ],
  "reprPoint": [
    22.826442,
    32.6244445
  ],
  "features": [
    {
      "geometry": {
        "type": "Point",
        "coordinates": [
          22.827284,
          32.624289
        ]
      },
      "id": "darmc-location-15970",
      "type": "Feature",
      "properties": {
        "description": "1M scale point location",
        "location_precision": "precise",
        "title": "DARMC location 15970",
        "link": "http://pleiades.stoa.org/places/373816/darmc-location-15970"
      }
    }
  ]
}