{
  "type": "FeatureCollection",
  "title": "Naustathmos",
  "id": "373862",
  "bbox": [
    22.166358,
    32.910373,
    22.166358,
    32.910373
  ],
  "description": "An ancient place, cited: BAtlas 38 D1 Naustathmos",
  "names": [
    "Naustathmos"
  ],
  "features": [
    {
      "type": "Feature",
      "geometry": {
        "type": "Point",
        "coordinates": [
          22.166358,
          32.910373
        ]
      },
      "properties": {
        "description": "representative point"
      }
    },
    {
      "geometry": {
        "type": "Point",
        "coordinates": [
          22.166358,
          32.910373
        ]
      },
      "id": "darmc-location-5105",
      "type": "Feature",
      "properties": {
        "description": "1:1 million scale representative point location digitized from the Barrington Atlas of the Greek and Roman World by the Digital Atlas of Roman and Medieval Civilizations project at Harvard University.",
        "location_precision": "precise",
        "title": "DARMC location 5105",
        "link": "http://pleiades.stoa.org/places/373862/darmc-location-5105"
      }
    }
  ]
}