{
  "type": "FeatureCollection",
  "title": "Siret Ain Relles",
  "id": "373893",
  "description": "An ancient place, cited: BAtlas 38 C1 Siret Ain Relles",
  "bbox": [
    21.70958,
    32.778547,
    21.70958,
    32.778547
  ],
  "reprPoint": [
    21.70958,
    32.778547
  ],
  "features": [
    {
      "geometry": {
        "type": "Point",
        "coordinates": [
          21.7097,
          32.7786
        ]
      },
      "id": "batlas-location",
      "type": "Feature",
      "properties": {
        "description": null,
        "location_precision": "precise",
        "title": "Barrington Atlas map location",
        "link": "http://pleiades.stoa.org/places/373893/batlas-location"
      }
    },
    {
      "geometry": {
        "type": "Point",
        "coordinates": [
          21.70958,
          32.778547
        ]
      },
      "id": "darmc-location-24774",
      "type": "Feature",
      "properties": {
        "description": "1M scale point location",
        "location_precision": "precise",
        "title": "DARMC location 24774",
        "link": "http://pleiades.stoa.org/places/373893/darmc-location-24774"
      }
    }
  ]
}