{
  "type": "FeatureCollection",
  "title": "Phykous",
  "id": "373872",
  "description": "An ancient place, cited: BAtlas 38 C1 Phykous",
  "bbox": [
    21.6251,
    32.9126,
    21.631788,
    32.919182
  ],
  "reprPoint": [
    21.628444,
    32.915891
  ],
  "names": [
    "Phykous"
  ],
  "features": [
    {
      "geometry": {
        "type": "Point",
        "coordinates": [
          21.631788,
          32.919182
        ]
      },
      "id": "darmc-location-14272",
      "type": "Feature",
      "properties": {
        "description": "1M scale point location",
        "location_precision": "precise",
        "title": "DARMC location 14272",
        "link": "http://pleiades.stoa.org/places/373872/darmc-location-14272"
      }
    }
  ]
}