{
  "type": "FeatureCollection",
  "title": "el-Mechili",
  "id": "373854",
  "description": "An ancient place, cited: BAtlas 38 D1 el-Mechili",
  "bbox": [
    22.278901,
    32.1511,
    22.2844,
    32.158409
  ],
  "reprPoint": [
    22.2816505,
    32.1547545
  ],
  "features": [
    {
      "geometry": {
        "type": "Point",
        "coordinates": [
          22.278901,
          32.158409
        ]
      },
      "id": "darmc-location-25585",
      "type": "Feature",
      "properties": {
        "description": "1M scale point location",
        "location_precision": "precise",
        "title": "DARMC location 25585",
        "link": "http://pleiades.stoa.org/places/373854/darmc-location-25585"
      }
    }
  ]
}