{
  "type": "FeatureCollection",
  "title": "Gasr Silina",
  "id": "373811",
  "description": "An ancient place, cited: BAtlas 38 B1 Gasr Silina",
  "bbox": [
    20.7146,
    32.349845,
    20.733321,
    32.3508
  ],
  "reprPoint": [
    20.7239605,
    32.3503225
  ],
  "features": [
    {
      "geometry": {
        "type": "Point",
        "coordinates": [
          20.733321,
          32.349845
        ]
      },
      "id": "darmc-location-17438",
      "type": "Feature",
      "properties": {
        "description": "1M scale point location",
        "location_precision": "precise",
        "title": "DARMC location 17438",
        "link": "http://pleiades.stoa.org/places/373811/darmc-location-17438"
      }
    }
  ]
}