{
  "type": "FeatureCollection",
  "title": "Serapeion",
  "id": "373887",
  "description": "An ancient place, cited: BAtlas 38 B2 Serapeion",
  "bbox": [
    20.10588,
    31.328274,
    20.10588,
    31.328274
  ],
  "reprPoint": [
    20.10588,
    31.328274
  ],
  "names": [
    "Serapeion"
  ],
  "features": [
    {
      "geometry": {
        "type": "Point",
        "coordinates": [
          20.1059,
          31.3283
        ]
      },
      "id": "batlas-location",
      "type": "Feature",
      "properties": {
        "description": null,
        "location_precision": "precise",
        "title": "Barrington Atlas map location",
        "link": "http://pleiades.stoa.org/places/373887/batlas-location"
      }
    },
    {
      "geometry": {
        "type": "Point",
        "coordinates": [
          20.10588,
          31.328274
        ]
      },
      "id": "darmc-location-16187",
      "type": "Feature",
      "properties": {
        "description": "1M scale point location",
        "location_precision": "precise",
        "title": "DARMC location 16187",
        "link": "http://pleiades.stoa.org/places/373887/darmc-location-16187"
      }
    }
  ]
}