{
  "type": "FeatureCollection",
  "title": "Phykous",
  "id": "373872",
  "bbox": [
    21.631788,
    32.919182,
    21.631788,
    32.919182
  ],
  "description": "An ancient place, cited: BAtlas 38 C1 Phykous",
  "names": [
    "Phykous"
  ],
  "features": [
    {
      "type": "Feature",
      "geometry": {
        "type": "Point",
        "coordinates": [
          21.631788,
          32.919182
        ]
      },
      "properties": {
        "description": "representative point"
      }
    },
    {
      "geometry": {
        "type": "Point",
        "coordinates": [
          21.631788,
          32.919182
        ]
      },
      "id": "darmc-location-14272",
      "type": "Feature",
      "properties": {
        "description": "1:1 million scale representative point location digitized from the Barrington Atlas of the Greek and Roman World by the Digital Atlas of Roman and Medieval Civilizations project at Harvard University.",
        "location_precision": "precise",
        "title": "DARMC location 14272",
        "link": "http://pleiades.stoa.org/places/373872/darmc-location-14272"
      }
    }
  ]
}