{
  "type": "FeatureCollection",
  "title": "Naustathmos",
  "id": "373862",
  "description": "An ancient place, cited: BAtlas 38 D1 Naustathmos",
  "bbox": [
    22.166358,
    32.910373,
    22.1733,
    32.9156
  ],
  "reprPoint": [
    22.169829,
    32.9129865
  ],
  "names": [
    "Naustathmos"
  ],
  "features": [
    {
      "geometry": {
        "type": "Point",
        "coordinates": [
          22.166358,
          32.910373
        ]
      },
      "id": "darmc-location-5105",
      "type": "Feature",
      "properties": {
        "description": "1M scale point location",
        "location_precision": "precise",
        "title": "DARMC location 5105",
        "link": "http://pleiades.stoa.org/places/373862/darmc-location-5105"
      }
    }
  ]
}