{
  "type": "FeatureCollection",
  "title": "Gasr et-Tuil",
  "id": "373804",
  "description": "An ancient place, cited: BAtlas 38 B1 Gasr et-Tuil",
  "bbox": [
    20.299964,
    32.2156,
    20.3101,
    32.216661
  ],
  "reprPoint": [
    20.305032,
    32.2161305
  ],
  "features": [
    {
      "geometry": {
        "type": "Point",
        "coordinates": [
          20.299964,
          32.216661
        ]
      },
      "id": "darmc-location-27446",
      "type": "Feature",
      "properties": {
        "description": "1M scale point location",
        "location_precision": "precise",
        "title": "DARMC location 27446",
        "link": "http://pleiades.stoa.org/places/373804/darmc-location-27446"
      }
    }
  ]
}