{
  "type": "FeatureCollection",
  "title": "Zaviet el-Gsur",
  "id": "373913",
  "description": "An ancient place, cited: BAtlas 38 B1 Zaviet el-Gsur",
  "bbox": [
    20.9686,
    32.441548,
    20.968912,
    32.4418
  ],
  "reprPoint": [
    20.968756,
    32.441674
  ],
  "features": [
    {
      "geometry": {
        "type": "Point",
        "coordinates": [
          20.968912,
          32.441548
        ]
      },
      "id": "darmc-location-27677",
      "type": "Feature",
      "properties": {
        "description": "1M scale point location",
        "location_precision": "precise",
        "title": "DARMC location 27677",
        "link": "http://pleiades.stoa.org/places/373913/darmc-location-27677"
      }
    }
  ]
}