{
  "type": "FeatureCollection",
  "title": "et-Tailimun",
  "id": "373900",
  "bbox": [
    20.172572,
    31.591616,
    20.172572,
    31.591616
  ],
  "description": "An ancient place, cited: BAtlas 38 B2 et-Tailimun",
  "features": [
    {
      "type": "Feature",
      "geometry": {
        "type": "Point",
        "coordinates": [
          20.172572,
          31.591616
        ]
      },
      "properties": {
        "description": "representative point"
      }
    },
    {
      "geometry": {
        "type": "Point",
        "coordinates": [
          20.172572,
          31.591616
        ]
      },
      "id": "darmc-location-18485",
      "type": "Feature",
      "properties": {
        "description": "1M scale point location",
        "location_precision": "precise",
        "title": "DARMC location 18485",
        "link": "http://pleiades.stoa.org/places/373900/darmc-location-18485"
      }
    }
  ]
}