{
  "type": "FeatureCollection",
  "title": "Tell el-Hayyat",
  "id": "374626658",
  "bbox": [
    35.577221,
    32.420818,
    35.577221,
    32.420818
  ],
  "description": "Village site located southwest of Pella (Tabaqat Fahl in Jordan). It was inhabited during the Early and Middle Bronze Age.",
  "features": [
    {
      "type": "Feature",
      "geometry": {
        "type": "Point",
        "coordinates": [
          35.577221,
          32.420818
        ]
      },
      "properties": {
        "description": "representative point"
      }
    },
    {
      "geometry": {
        "type": "Point",
        "coordinates": [
          35.577221,
          32.420818
        ]
      },
      "id": "imagery-location-of-tell-el-hayyat",
      "type": "Feature",
      "properties": {
        "description": "Point representing the approximate center of the visibly excavated portion of the Tell el-Hayyat site.",
        "location_precision": "precise",
        "title": "Imagery location of Tell el-Hayyat",
        "link": "http://pleiades.stoa.org/places/374626658/imagery-location-of-tell-el-hayyat"
      }
    }
  ]
}