{
  "type": "FeatureCollection",
  "title": "Untitled",
  "id": "375239",
  "description": "An ancient place, cited: BAtlas 38 C1 no. 3 (Zaviet el-Argub)",
  "bbox": [
    21.4864,
    32.6674,
    21.4864,
    32.6674
  ],
  "reprPoint": [
    21.4864,
    32.6674
  ],
  "features": [
    {
      "geometry": {
        "type": "Point",
        "coordinates": [
          21.4864,
          32.6674
        ]
      },
      "id": "batlas-location",
      "type": "Feature",
      "properties": {
        "description": null,
        "location_precision": "precise",
        "title": "Barrington Atlas map location",
        "link": "http://pleiades.stoa.org/places/375239/batlas-location"
      }
    }
  ]
}