{
  "type": "FeatureCollection",
  "title": "Untitled",
  "id": "375238",
  "description": "An ancient place, cited: BAtlas 38 C1 no. 2 (Sidi Abd el-Uahad)",
  "bbox": [
    21.5609,
    32.7281,
    21.5609,
    32.7281
  ],
  "reprPoint": [
    21.5609,
    32.7281
  ],
  "features": [
    {
      "geometry": {
        "type": "Point",
        "coordinates": [
          21.5609,
          32.7281
        ]
      },
      "id": "batlas-location",
      "type": "Feature",
      "properties": {
        "description": null,
        "location_precision": "precise",
        "title": "Barrington Atlas map location",
        "link": "http://pleiades.stoa.org/places/375238/batlas-location"
      }
    }
  ]
}