{
  "type": "FeatureCollection",
  "title": "Untitled",
  "id": "375260",
  "bbox": [
    22.1614,
    32.5971,
    22.1614,
    32.5971
  ],
  "description": "An ancient place, cited: BAtlas 38 D1 no. 24 (Gasr Uertig)",
  "features": [
    {
      "type": "Feature",
      "geometry": {
        "type": "Point",
        "coordinates": [
          22.1614,
          32.5971
        ]
      },
      "properties": {
        "description": "representative point"
      }
    },
    {
      "geometry": {
        "type": "Point",
        "coordinates": [
          22.1614,
          32.5971
        ]
      },
      "id": "batlas-location",
      "type": "Feature",
      "properties": {
        "description": null,
        "location_precision": "precise",
        "title": "Barrington Atlas map location",
        "link": "http://pleiades.stoa.org/places/375260/batlas-location"
      }
    }
  ]
}