{
  "type": "FeatureCollection",
  "title": "Khorsabad Gate 4",
  "id": "375821777",
  "bbox": [
    43.2415394,
    36.4969081,
    43.2415394,
    36.4969081
  ],
  "description": "This undecorated gate is the southernmost city gate of the southeast wall of Dūr-Šarrukīn (\"Fort Sargon\"), the capital of the Assyrian Empire constructed by Sargon II (r. 721–705 BC).",
  "connectsWith": [
    "874458",
    "4517388",
    "175106248",
    "918508895"
  ],
  "names": [
    "Gate 4"
  ],
  "features": [
    {
      "type": "Feature",
      "geometry": {
        "type": "Point",
        "coordinates": [
          43.2415394,
          36.4969081
        ]
      },
      "properties": {
        "description": "representative point"
      }
    },
    {
      "geometry": {
        "type": "Point",
        "coordinates": [
          43.2415394,
          36.4969081
        ]
      },
      "id": "osm-location-of-khorsabad-gate-4",
      "type": "Feature",
      "properties": {
        "description": "Location based on OpenStreetMap",
        "location_precision": "precise",
        "title": "OSM location of Khorsabad Gate 4",
        "link": "http://pleiades.stoa.org/places/375821777/osm-location-of-khorsabad-gate-4"
      }
    }
  ]
}