{
  "type": "FeatureCollection",
  "title": "Sanctuary of Isis at Dion",
  "id": "376566547",
  "bbox": [
    22.495222,
    40.176194,
    22.495222,
    40.176194
  ],
  "description": "The sanctuary of Isis at Dion dates to the second century A.D.",
  "connectsWith": [
    "491572"
  ],
  "features": [
    {
      "type": "Feature",
      "geometry": {
        "type": "Point",
        "coordinates": [
          22.495222,
          40.176194
        ]
      },
      "properties": {
        "description": "representative point"
      }
    },
    {
      "geometry": {
        "type": "Point",
        "coordinates": [
          22.495222,
          40.176194
        ]
      },
      "id": "gps-location-sanctuary-of-isis",
      "type": "Feature",
      "properties": {
        "description": "The sanctuary of Isis at Dion.",
        "location_precision": "precise",
        "title": "GPS Location of Sanctuary of Isis",
        "link": "http://pleiades.stoa.org/places/376566547/gps-location-sanctuary-of-isis"
      }
    }
  ]
}