{
  "type": "FeatureCollection",
  "title": "Cistern",
  "id": "378979377",
  "bbox": [
    9.5055027,
    40.9368159,
    9.5055027,
    40.9368159
  ],
  "description": "A Roman period cistern of Olbia on Sardinia.",
  "connectsWith": [
    "471987"
  ],
  "features": [
    {
      "type": "Feature",
      "geometry": {
        "type": "Point",
        "coordinates": [
          9.5055027,
          40.9368159
        ]
      },
      "properties": {
        "description": "representative point"
      }
    },
    {
      "geometry": {
        "type": "Point",
        "coordinates": [
          9.5055027,
          40.9368159
        ]
      },
      "id": "osm-location-of-cistern",
      "type": "Feature",
      "properties": {
        "description": "Location based on OpenStreetMap",
        "location_precision": "precise",
        "title": "OSM location of cistern",
        "link": "http://pleiades.stoa.org/places/378979377/osm-location-of-cistern"
      }
    }
  ]
}