{
  "type": "FeatureCollection",
  "title": "Maroni",
  "id": "380086882",
  "description": "At Maroni Vournes in southern Cyprus, the remains of a large ashlar building of the thirteenth century BC have been excavated.",
  "bbox": [
    33.3810449,
    34.746564,
    33.3810449,
    34.746564
  ],
  "connectsWith": [
    "707498"
  ],
  "reprPoint": [
    33.3810449,
    34.746564
  ],
  "names": [
    "Maroni Vournes"
  ],
  "features": [
    {
      "geometry": {
        "type": "Point",
        "coordinates": [
          33.3810449,
          34.746564
        ]
      },
      "id": "location-of-maroni",
      "type": "Feature",
      "properties": {
        "description": "Representative location based on OpenStreetMap.",
        "location_precision": "precise",
        "title": "OSM location of Maroni Vournes",
        "link": "http://pleiades.stoa.org/places/380086882/location-of-maroni"
      }
    }
  ]
}