{
  "type": "FeatureCollection",
  "title": "Kenan Tepe",
  "id": "381896576",
  "description": "Ancient site on the Tigris river in Turkey",
  "bbox": [
    40.813222,
    37.830588,
    40.813222,
    37.830588
  ],
  "reprPoint": [
    40.813222,
    37.830588
  ],
  "names": [
    "Kenan Tepe"
  ],
  "features": [
    {
      "geometry": {
        "type": "Point",
        "coordinates": [
          40.813222,
          37.830588
        ]
      },
      "id": "point-location",
      "type": "Feature",
      "properties": {
        "description": "Verified in Google Earth in August 2012.",
        "location_precision": "precise",
        "title": "Location of Kenan Tepe from primary excavation report",
        "link": "http://pleiades.stoa.org/places/381896576/point-location"
      }
    }
  ]
}