{
  "type": "FeatureCollection",
  "title": "Unnamed Place",
  "id": "3821290161116960",
  "description": "An unnamed ancient villa or settlement",
  "reprPoint": [
    0.0,
    0.0
  ],
  "features": [
    {
      "geometry": {
        "type": "Point",
        "coordinates": [
          21.696,
          32.9016
        ]
      },
      "id": "batlas-location",
      "type": "Feature",
      "properties": {
        "description": null,
        "location_precision": "precise",
        "title": "Barrington Atlas map location",
        "link": "http://pleiades.stoa.org/places/3821290161116960/batlas-location"
      }
    }
  ]
}