{
  "type": "FeatureCollection",
  "title": "Unnamed Place",
  "id": "3821230961103037",
  "description": "An unnamed ancient villa or settlement",
  "reprPoint": [
    0.0,
    0.0
  ],
  "features": [
    {
      "geometry": {
        "type": "Point",
        "coordinates": [
          20.3037,
          32.3096
        ]
      },
      "id": "batlas-location",
      "type": "Feature",
      "properties": {
        "description": null,
        "location_precision": "precise",
        "title": "Barrington Atlas map location",
        "link": "http://pleiades.stoa.org/places/3821230961103037/batlas-location"
      }
    }
  ]
}