{
  "type": "FeatureCollection",
  "title": "Unnamed Place",
  "id": "3821247771104708",
  "description": "An unnamed ancient villa or settlement",
  "bbox": [
    20.4708,
    32.4777,
    20.4708,
    32.4777
  ],
  "reprPoint": [
    20.4708,
    32.4777
  ],
  "features": [
    {
      "geometry": {
        "type": "Point",
        "coordinates": [
          20.4708,
          32.4777
        ]
      },
      "id": "batlas-location",
      "type": "Feature",
      "properties": {
        "description": null,
        "location_precision": "precise",
        "title": "Barrington Atlas map location",
        "link": "http://pleiades.stoa.org/places/3821247771104708/batlas-location"
      }
    }
  ]
}