{
  "type": "FeatureCollection",
  "title": "Unnamed Place",
  "id": "3821284671118400",
  "description": "An unnamed ancient villa or settlement",
  "bbox": [
    21.84,
    32.8467,
    21.84,
    32.8467
  ],
  "reprPoint": [
    21.84,
    32.8467
  ],
  "features": [
    {
      "geometry": {
        "type": "Point",
        "coordinates": [
          21.84,
          32.8467
        ]
      },
      "id": "batlas-location",
      "type": "Feature",
      "properties": {
        "description": null,
        "location_precision": "precise",
        "title": "Barrington Atlas map location",
        "link": "http://pleiades.stoa.org/places/3821284671118400/batlas-location"
      }
    }
  ]
}