{
  "type": "FeatureCollection",
  "title": "Unnamed Place",
  "id": "3821248011105102",
  "description": "An unnamed ancient villa or settlement",
  "bbox": [
    20.5102,
    32.4801,
    20.5102,
    32.4801
  ],
  "reprPoint": [
    20.5102,
    32.4801
  ],
  "features": [
    {
      "geometry": {
        "type": "Point",
        "coordinates": [
          20.5102,
          32.4801
        ]
      },
      "id": "batlas-location",
      "type": "Feature",
      "properties": {
        "description": null,
        "location_precision": "precise",
        "title": "Barrington Atlas map location",
        "link": "http://pleiades.stoa.org/places/3821248011105102/batlas-location"
      }
    }
  ]
}