{
  "type": "FeatureCollection",
  "title": "Alba Pompeia",
  "id": "383564",
  "bbox": [
    8.035244,
    44.700835,
    8.035244,
    44.700835
  ],
  "description": "Alba Pompeia (modern Alba) was a Celtic and Ligurian settlement that entered into the Roman sphere during the late Republican period. In Imperial times Alba was the birthplace of Pertinax.",
  "connectsWith": [
    "383790"
  ],
  "names": [
    "Alba Pompeia"
  ],
  "features": [
    {
      "type": "Feature",
      "geometry": {
        "type": "Point",
        "coordinates": [
          8.035244,
          44.700835
        ]
      },
      "properties": {
        "description": "representative point"
      }
    },
    {
      "geometry": {
        "type": "Point",
        "coordinates": [
          8.035244,
          44.700835
        ]
      },
      "id": "darmc-location-6084",
      "type": "Feature",
      "properties": {
        "description": "500K scale point location",
        "location_precision": "precise",
        "title": "DARMC location 6084",
        "link": "http://pleiades.stoa.org/places/383564/darmc-location-6084"
      }
    }
  ]
}