{
  "type": "FeatureCollection",
  "title": "Bedriacum",
  "id": "383584",
  "description": "Bedriacum was an ancient town of Cisalpine Gaul located between Verona and Cremona that was the site of two battles during the 'Year of the Four Emperors' (A.D. 69).",
  "bbox": [
    10.442348,
    45.129535,
    10.442348,
    45.129535
  ],
  "connectsWith": [
    "15f7fb8057d1b94a02e01b8430ba5f99"
  ],
  "reprPoint": [
    10.442348,
    45.129535
  ],
  "names": [
    "Bedriacum",
    "Betriacum"
  ],
  "features": [
    {
      "geometry": {
        "type": "Point",
        "coordinates": [
          10.442348,
          45.129535
        ]
      },
      "id": "darmc-location-6343",
      "type": "Feature",
      "properties": {
        "description": "500K scale point location",
        "location_precision": "precise",
        "title": "DARMC location 6343",
        "link": "http://pleiades.stoa.org/places/383584/darmc-location-6343"
      }
    }
  ]
}