{
  "type": "FeatureCollection",
  "title": "Ad IX",
  "id": "383548",
  "bbox": [
    9.322956,
    45.356918,
    9.322956,
    45.356918
  ],
  "description": "An ancient place, cited: BAtlas 39 E3 Ad IX",
  "names": [
    "Ad IX"
  ],
  "features": [
    {
      "type": "Feature",
      "geometry": {
        "type": "Point",
        "coordinates": [
          9.322956,
          45.356918
        ]
      },
      "properties": {
        "description": "representative point"
      }
    },
    {
      "geometry": {
        "type": "Point",
        "coordinates": [
          9.322956,
          45.356918
        ]
      },
      "id": "darmc-location-2675",
      "type": "Feature",
      "properties": {
        "description": "500K scale point location",
        "location_precision": "precise",
        "title": "DARMC location 2675",
        "link": "http://pleiades.stoa.org/places/383548/darmc-location-2675"
      }
    }
  ]
}