{
  "type": "FeatureCollection",
  "title": "Ad Tarum",
  "id": "383556",
  "description": "An ancient place, cited: BAtlas 39 G4 Ad Tarum",
  "bbox": [
    10.211566,
    44.830006,
    10.211566,
    44.830006
  ],
  "connectsWith": [
    "66908841"
  ],
  "reprPoint": [
    10.211566,
    44.830006
  ],
  "names": [
    "Ad Tarum"
  ],
  "features": [
    {
      "geometry": {
        "type": "Point",
        "coordinates": [
          10.211566,
          44.830006
        ]
      },
      "id": "darmc-location-8865",
      "type": "Feature",
      "properties": {
        "description": "500K scale point location",
        "location_precision": "precise",
        "title": "DARMC location 8865",
        "link": "http://pleiades.stoa.org/places/383556/darmc-location-8865"
      }
    }
  ]
}