{
  "type": "FeatureCollection",
  "title": "[Bugella]",
  "id": "383605",
  "bbox": [
    8.058255,
    45.562812,
    8.058255,
    45.562812
  ],
  "description": "An ancient place, cited: BAtlas 39 C2 [Bugella]",
  "names": [
    "Bugella"
  ],
  "features": [
    {
      "type": "Feature",
      "geometry": {
        "type": "Point",
        "coordinates": [
          8.058255,
          45.562812
        ]
      },
      "properties": {
        "description": "representative point"
      }
    },
    {
      "geometry": {
        "type": "Point",
        "coordinates": [
          8.058255,
          45.562812
        ]
      },
      "id": "darmc-location-5622",
      "type": "Feature",
      "properties": {
        "description": "500K scale point location",
        "location_precision": "precise",
        "title": "DARMC location 5622",
        "link": "http://pleiades.stoa.org/places/383605/darmc-location-5622"
      }
    }
  ]
}