{
  "type": "FeatureCollection",
  "title": "*Forum Germanici",
  "id": "383653",
  "bbox": [
    7.475266,
    44.518081,
    7.475266,
    44.518081
  ],
  "description": "An ancient place, cited: BAtlas 39 A4 *Forum Germanici",
  "names": [
    "Forum Germanici"
  ],
  "features": [
    {
      "type": "Feature",
      "geometry": {
        "type": "Point",
        "coordinates": [
          7.475266,
          44.518081
        ]
      },
      "properties": {
        "description": "representative point"
      }
    },
    {
      "geometry": {
        "type": "Point",
        "coordinates": [
          7.475266,
          44.518081
        ]
      },
      "id": "darmc-location-5432",
      "type": "Feature",
      "properties": {
        "description": "500K scale point location",
        "location_precision": "precise",
        "title": "DARMC location 5432",
        "link": "http://pleiades.stoa.org/places/383653/darmc-location-5432"
      }
    }
  ]
}