{
  "type": "FeatureCollection",
  "title": "Desenzano",
  "id": "383634",
  "bbox": [
    10.5381924,
    45.4732041,
    10.5381924,
    45.4732041
  ],
  "description": "At Desenzano, in the province of Lombardia, the remains of a Roman villa dating to the mid-fourth century A.D. were here. The structure is axial and palatial in its nature. Its decorative program includes polychrome mosaic pavements. It is noted for mosaic scenes featuring the Good Shepherd.",
  "features": [
    {
      "type": "Feature",
      "geometry": {
        "type": "Point",
        "coordinates": [
          10.5381924,
          45.4732041
        ]
      },
      "properties": {
        "description": "representative point"
      }
    },
    {
      "geometry": {
        "type": "Point",
        "coordinates": [
          10.5381924,
          45.4732041
        ]
      },
      "id": "osm-location-of-villa-romana-di-desenzano-del",
      "type": "Feature",
      "properties": {
        "description": "Representative location based on OpenStreetMap",
        "location_precision": "precise",
        "title": "OSM location of Villa romana di Desenzano del Garda",
        "link": "http://pleiades.stoa.org/places/383634/osm-location-of-villa-romana-di-desenzano-del"
      }
    }
  ]
}