{
  "type": "FeatureCollection",
  "title": "Durriae",
  "id": "383637",
  "description": "An ancient place, cited: BAtlas 39 D3 Durriae",
  "bbox": [
    8.954,
    45.157083,
    8.954,
    45.157083
  ],
  "reprPoint": [
    8.954,
    45.157083
  ],
  "names": [
    "Durriae"
  ],
  "features": [
    {
      "geometry": {
        "type": "Point",
        "coordinates": [
          8.954,
          45.157083
        ]
      },
      "id": "darmc-location-8585",
      "type": "Feature",
      "properties": {
        "description": "500K scale point location",
        "location_precision": "precise",
        "title": "DARMC location 8585",
        "link": "http://pleiades.stoa.org/places/383637/darmc-location-8585"
      }
    }
  ]
}