{
  "type": "FeatureCollection",
  "title": "[Comacina] (island)",
  "id": "383624",
  "description": "A small island in Lake Como.",
  "bbox": [
    9.1765082,
    45.9642025,
    9.177088,
    45.9646755
  ],
  "connectsWith": [
    "383689"
  ],
  "reprPoint": [
    9.1767981,
    45.964439
  ],
  "names": [
    "[Comacina]"
  ],
  "features": [
    {
      "geometry": {
        "type": "Point",
        "coordinates": [
          9.1765082,
          45.9646755
        ]
      },
      "id": "dare-location",
      "type": "Feature",
      "properties": {
        "description": "Representative point location, village precision",
        "location_precision": "precise",
        "title": "DARE Location",
        "link": "http://pleiades.stoa.org/places/383624/dare-location"
      }
    }
  ]
}