{
  "type": "FeatureCollection",
  "title": "Desenzano",
  "id": "383634",
  "description": "An ancient place, cited: BAtlas 39 H3 Desenzano",
  "bbox": [
    10.534958,
    45.468901,
    10.534958,
    45.468901
  ],
  "reprPoint": [
    10.534958,
    45.468901
  ],
  "features": [
    {
      "geometry": {
        "type": "Point",
        "coordinates": [
          10.534958,
          45.468901
        ]
      },
      "id": "darmc-location-17408",
      "type": "Feature",
      "properties": {
        "description": "500K scale point location",
        "location_precision": "precise",
        "title": "DARMC location 17408",
        "link": "http://pleiades.stoa.org/places/383634/darmc-location-17408"
      }
    }
  ]
}