{
  "type": "FeatureCollection",
  "title": "*Civitas Camunnorum",
  "id": "383617",
  "bbox": [
    10.278604,
    45.94345,
    10.278604,
    45.94345
  ],
  "description": "An ancient place, cited: BAtlas 39 G2 *Civitas Camunnorum",
  "names": [
    "Civitas Camunnorum"
  ],
  "features": [
    {
      "type": "Feature",
      "geometry": {
        "type": "Point",
        "coordinates": [
          10.278604,
          45.94345
        ]
      },
      "properties": {
        "description": "representative point"
      }
    },
    {
      "geometry": {
        "type": "Point",
        "coordinates": [
          10.278604,
          45.94345
        ]
      },
      "id": "darmc-location-5666",
      "type": "Feature",
      "properties": {
        "description": "500K scale point location",
        "location_precision": "precise",
        "title": "DARMC location 5666",
        "link": "http://pleiades.stoa.org/places/383617/darmc-location-5666"
      }
    }
  ]
}