{
  "type": "FeatureCollection",
  "title": "*Forum Novum",
  "id": "383655",
  "bbox": [
    9.679688,
    45.498815,
    9.679688,
    45.498815
  ],
  "description": "An ancient place, cited: BAtlas 39 F3 *Forum Novum",
  "names": [
    "Forum Novum"
  ],
  "features": [
    {
      "type": "Feature",
      "geometry": {
        "type": "Point",
        "coordinates": [
          9.679688,
          45.498815
        ]
      },
      "properties": {
        "description": "representative point"
      }
    },
    {
      "geometry": {
        "type": "Point",
        "coordinates": [
          9.679688,
          45.498815
        ]
      },
      "id": "darmc-location-1588",
      "type": "Feature",
      "properties": {
        "description": "500K scale point location",
        "location_precision": "precise",
        "title": "DARMC location 1588",
        "link": "http://pleiades.stoa.org/places/383655/darmc-location-1588"
      }
    }
  ]
}