{
  "type": "FeatureCollection",
  "title": "[Comacina] (island)",
  "id": "383624",
  "bbox": [
    9.1765082,
    45.9642025,
    9.177088,
    45.9646755
  ],
  "description": "A small island in Lake Como.",
  "connectsWith": [
    "383689"
  ],
  "names": [
    "[Comacina]"
  ],
  "features": [
    {
      "type": "Feature",
      "geometry": {
        "type": "Point",
        "coordinates": [
          9.1767981,
          45.964439
        ]
      },
      "properties": {
        "description": "representative point"
      }
    },
    {
      "geometry": {
        "type": "Point",
        "coordinates": [
          9.1765082,
          45.9646755
        ]
      },
      "id": "dare-location",
      "type": "Feature",
      "properties": {
        "description": "Representative point location, village precision",
        "location_precision": "precise",
        "title": "DARE Location",
        "link": "http://pleiades.stoa.org/places/383624/dare-location"
      }
    },
    {
      "geometry": {
        "type": "Point",
        "coordinates": [
          9.177088,
          45.9642025
        ]
      },
      "id": "osm-location",
      "type": "Feature",
      "properties": {
        "description": "Representative location based on OpenStreetMap.",
        "location_precision": "precise",
        "title": "OSM location of Isola Comacina",
        "link": "http://pleiades.stoa.org/places/383624/osm-location"
      }
    }
  ]
}