{
  "type": "FeatureCollection",
  "title": "[Comacina] Ins.",
  "id": "383624",
  "description": "An ancient place, cited: BAtlas 39 E2 [Comacina] Ins.",
  "bbox": [
    9.1765082,
    45.9646755,
    9.1765082,
    45.9646755
  ],
  "reprPoint": [
    9.1765082,
    45.9646755
  ],
  "names": [
    "[Comacina]"
  ],
  "features": [
    {
      "geometry": {
        "type": "Point",
        "coordinates": [
          9.1765082,
          45.9646755
        ]
      },
      "id": "dare-location",
      "type": "Feature",
      "properties": {
        "description": "Representative point location, village precision",
        "location_precision": "precise",
        "title": "DARE Location",
        "link": "http://pleiades.stoa.org/places/383624/dare-location"
      }
    }
  ]
}