{
  "type": "FeatureCollection",
  "title": "Carbantia/Ad Medias",
  "id": "383610",
  "bbox": [
    8.479819,
    45.18293,
    8.479819,
    45.18293
  ],
  "description": "An ancient place, cited: BAtlas 39 C3 Carbantia/Ad Medias",
  "names": [
    "Carbantia",
    "Ad Medias"
  ],
  "features": [
    {
      "type": "Feature",
      "geometry": {
        "type": "Point",
        "coordinates": [
          8.479819,
          45.18293
        ]
      },
      "properties": {
        "description": "representative point"
      }
    },
    {
      "geometry": {
        "type": "Point",
        "coordinates": [
          8.479819,
          45.18293
        ]
      },
      "id": "darmc-location-8010",
      "type": "Feature",
      "properties": {
        "description": "500K scale point location",
        "location_precision": "precise",
        "title": "DARMC location 8010",
        "link": "http://pleiades.stoa.org/places/383610/darmc-location-8010"
      }
    }
  ]
}