{
  "type": "FeatureCollection",
  "title": "*Minervium",
  "id": "383710",
  "bbox": [
    10.141892,
    45.355168,
    10.141892,
    45.355168
  ],
  "description": "An ancient place, cited: BAtlas 39 G3 *Minervium",
  "names": [
    "Minervium"
  ],
  "features": [
    {
      "type": "Feature",
      "geometry": {
        "type": "Point",
        "coordinates": [
          10.141892,
          45.355168
        ]
      },
      "properties": {
        "description": "representative point"
      }
    },
    {
      "geometry": {
        "type": "Point",
        "coordinates": [
          10.141892,
          45.355168
        ]
      },
      "id": "darmc-location-6755",
      "type": "Feature",
      "properties": {
        "description": "500K scale point location",
        "location_precision": "precise",
        "title": "DARMC location 6755",
        "link": "http://pleiades.stoa.org/places/383710/darmc-location-6755"
      }
    }
  ]
}