{
  "type": "FeatureCollection",
  "title": "Sarius (river)",
  "id": "383768",
  "bbox": [
    9.8309463,
    45.7900406,
    9.8309463,
    45.7900406
  ],
  "description": "An ancient place, cited: BAtlas 39 F2 Sarius fl.",
  "names": [
    "Sarius"
  ],
  "features": [
    {
      "type": "Feature",
      "geometry": {
        "type": "Point",
        "coordinates": [
          9.8309463,
          45.7900406
        ]
      },
      "properties": {
        "description": "representative point"
      }
    },
    {
      "geometry": {
        "type": "Point",
        "coordinates": [
          9.8309463,
          45.7900406
        ]
      },
      "id": "osm-location",
      "type": "Feature",
      "properties": {
        "description": "Representative point derived from an OpenStreetMap way.",
        "location_precision": "precise",
        "title": "OSM location",
        "link": "http://pleiades.stoa.org/places/383768/osm-location"
      }
    }
  ]
}