{
  "type": "FeatureCollection",
  "title": "S. Maria di Minerbe",
  "id": "383782",
  "bbox": [
    10.907233,
    45.560038,
    10.907233,
    45.560038
  ],
  "description": "An ancient place, cited: BAtlas 39 H2 S. Maria di Minerbe",
  "features": [
    {
      "type": "Feature",
      "geometry": {
        "type": "Point",
        "coordinates": [
          10.907233,
          45.560038
        ]
      },
      "properties": {
        "description": "representative point"
      }
    },
    {
      "geometry": {
        "type": "Point",
        "coordinates": [
          10.907233,
          45.560038
        ]
      },
      "id": "darmc-location-16177",
      "type": "Feature",
      "properties": {
        "description": "500K scale point location",
        "location_precision": "precise",
        "title": "DARMC location 16177",
        "link": "http://pleiades.stoa.org/places/383782/darmc-location-16177"
      }
    }
  ]
}