{
  "type": "FeatureCollection",
  "title": "Quadrata",
  "id": "383753",
  "description": "An ancient place, cited: BAtlas 39 B3 Quadrata",
  "bbox": [
    7.969391,
    45.191112,
    7.969391,
    45.191112
  ],
  "reprPoint": [
    7.969391,
    45.191112
  ],
  "names": [
    "Quadrata"
  ],
  "features": [
    {
      "geometry": {
        "type": "Point",
        "coordinates": [
          7.969391,
          45.191112
        ]
      },
      "id": "darmc-location-2702",
      "type": "Feature",
      "properties": {
        "description": "500K scale point location",
        "location_precision": "precise",
        "title": "DARMC location 2702",
        "link": "http://pleiades.stoa.org/places/383753/darmc-location-2702"
      }
    }
  ]
}