{
  "type": "FeatureCollection",
  "title": "Portus Delphini",
  "id": "383750",
  "description": "Ancient settlement and port at the site of modern Portofino in Italy.",
  "bbox": [
    9.207761,
    44.303972,
    9.207761,
    44.303972
  ],
  "reprPoint": [
    9.207761,
    44.303972
  ],
  "names": [
    "Portus Delphini"
  ],
  "features": [
    {
      "geometry": {
        "type": "Point",
        "coordinates": [
          9.207761,
          44.303972
        ]
      },
      "id": "darmc-location-8932",
      "type": "Feature",
      "properties": {
        "description": "500K scale point location",
        "location_precision": "precise",
        "title": "DARMC location 8932",
        "link": "http://pleiades.stoa.org/places/383750/darmc-location-8932"
      }
    }
  ]
}