{
  "type": "FeatureCollection",
  "title": "Saltus Berusetis",
  "id": "383765",
  "bbox": [
    9.989987,
    44.510579,
    9.989987,
    44.510579
  ],
  "description": "An ancient place, cited: BAtlas 39 F4 Saltus Berusetis",
  "names": [
    "Saltus Berusetis"
  ],
  "features": [
    {
      "type": "Feature",
      "geometry": {
        "type": "Point",
        "coordinates": [
          9.989987,
          44.510579
        ]
      },
      "properties": {
        "description": "representative point"
      }
    },
    {
      "geometry": {
        "type": "Point",
        "coordinates": [
          9.989987,
          44.510579
        ]
      },
      "id": "darmc-location-17578",
      "type": "Feature",
      "properties": {
        "description": "500K scale point location",
        "location_precision": "precise",
        "title": "DARMC location 17578",
        "link": "http://pleiades.stoa.org/places/383765/darmc-location-17578"
      }
    }
  ]
}