{
  "type": "FeatureCollection",
  "title": "Pons *Seciae",
  "id": "383748",
  "description": "An ancient place, cited: BAtlas 39 H4 Pons *Seciae",
  "bbox": [
    10.781256,
    44.65373,
    10.781256,
    44.65373
  ],
  "reprPoint": [
    10.781256,
    44.65373
  ],
  "names": [
    "Pons Seciae"
  ],
  "features": [
    {
      "geometry": {
        "type": "Point",
        "coordinates": [
          10.781256,
          44.65373
        ]
      },
      "id": "darmc-location-8519",
      "type": "Feature",
      "properties": {
        "description": "500K scale point location",
        "location_precision": "precise",
        "title": "DARMC location 8519",
        "link": "http://pleiades.stoa.org/places/383748/darmc-location-8519"
      }
    }
  ]
}