{
  "type": "FeatureCollection",
  "title": "Tellegate",
  "id": "383796",
  "bbox": [
    9.852833,
    45.629884,
    9.852833,
    45.629884
  ],
  "description": "An ancient place, cited: BAtlas 39 F2 Tellegate",
  "names": [
    "Tellegate"
  ],
  "features": [
    {
      "type": "Feature",
      "geometry": {
        "type": "Point",
        "coordinates": [
          9.852833,
          45.629884
        ]
      },
      "properties": {
        "description": "representative point"
      }
    },
    {
      "geometry": {
        "type": "Point",
        "coordinates": [
          9.852833,
          45.629884
        ]
      },
      "id": "darmc-location-8637",
      "type": "Feature",
      "properties": {
        "description": "500K scale point location",
        "location_precision": "precise",
        "title": "DARMC location 8637",
        "link": "http://pleiades.stoa.org/places/383796/darmc-location-8637"
      }
    }
  ]
}