{
  "type": "FeatureCollection",
  "title": "Tidone (river)",
  "id": "383800",
  "bbox": [
    9.3202764,
    44.860716,
    9.3202764,
    44.860716
  ],
  "description": "An ancient place, cited: BAtlas 39 E4 Tidone fl.",
  "names": [
    "Tidone"
  ],
  "features": [
    {
      "type": "Feature",
      "geometry": {
        "type": "Point",
        "coordinates": [
          9.3202764,
          44.860716
        ]
      },
      "properties": {
        "description": "representative point"
      }
    },
    {
      "geometry": {
        "type": "Point",
        "coordinates": [
          9.3202764,
          44.860716
        ]
      },
      "id": "osm-location",
      "type": "Feature",
      "properties": {
        "description": "Location based on OpenStreetMap",
        "location_precision": "precise",
        "title": "OSM location",
        "link": "http://pleiades.stoa.org/places/383800/osm-location"
      }
    }
  ]
}