{
  "type": "FeatureCollection",
  "title": "Assur Archive 47",
  "id": "387051092",
  "bbox": [
    43.259383,
    35.456464,
    43.259383,
    35.456464
  ],
  "description": "In a private house in fC8I, excavators discovered a small archive of 7 clay tablets. Available datings range from 762 to postcanonical 622* BC. The archive, belonging to a family of tanners, consists of purchase documents, a juridical settlement, and two documents concerning inheritance.",
  "connectsWith": [
    "893945"
  ],
  "names": [
    "Assur Archive 47",
    "N 32 Archive"
  ],
  "features": [
    {
      "type": "Feature",
      "geometry": {
        "type": "Point",
        "coordinates": [
          43.259383,
          35.456464
        ]
      },
      "properties": {
        "description": "representative point"
      }
    },
    {
      "geometry": {
        "type": "Point",
        "coordinates": [
          43.259383,
          35.456464
        ]
      },
      "id": "plan-location-of-assur-archive-47",
      "type": "Feature",
      "properties": {
        "description": "Representative locations of the Neo-Assyrian archive at Assur on the basis of Pedersén 1987 Plan(s) 62.",
        "location_precision": "precise",
        "title": "Plan location of Assur Archive 47",
        "link": "http://pleiades.stoa.org/places/387051092/plan-location-of-assur-archive-47"
      }
    }
  ]
}