{
  "type": "FeatureCollection",
  "title": "Honos et Virtus, Aedes",
  "id": "387810362",
  "bbox": [
    12.486137,
    41.891775,
    12.486137,
    41.891775
  ],
  "description": "The Temple of Honour and Virtue (aedes Honoris et Virtutis) was a double temple founded by Q. Fabius Maximus Verrucosus in 234 BCE.",
  "connectsWith": [
    "307963010",
    "423025"
  ],
  "features": [
    {
      "type": "Feature",
      "geometry": {
        "type": "Point",
        "coordinates": [
          12.486137,
          41.891775
        ]
      },
      "properties": {
        "description": "representative point"
      }
    }
  ]
}