{
  "type": "FeatureCollection",
  "title": "San Basilio",
  "id": "39090360",
  "bbox": [
    9.1955987,
    39.5398121,
    9.1955987,
    39.5398121
  ],
  "description": "A Roman bath complex that was reused first as a monastic complex and then as the Medieval church of San Basilio.",
  "connectsWith": [
    "472014"
  ],
  "features": [
    {
      "type": "Feature",
      "geometry": {
        "type": "Point",
        "coordinates": [
          9.1955987,
          39.5398121
        ]
      },
      "properties": {
        "description": "representative point"
      }
    },
    {
      "geometry": {
        "type": "Point",
        "coordinates": [
          9.1955987,
          39.5398121
        ]
      },
      "id": "osm-location",
      "type": "Feature",
      "properties": {
        "description": "Representative location based on OpenStreetMap.",
        "location_precision": "precise",
        "title": "OSM location of  Terme romane di San Basilio",
        "link": "http://pleiades.stoa.org/places/39090360/osm-location"
      }
    }
  ]
}