{
  "type": "FeatureCollection",
  "title": "Amnestum",
  "id": "39285",
  "bbox": [
    44.793055,
    16.699491,
    44.793055,
    16.699491
  ],
  "description": "An ancient place, cited: BAtlas 4 B2 Amnestum",
  "names": [
    "Amnestum",
    "Nestum"
  ],
  "features": [
    {
      "type": "Feature",
      "geometry": {
        "type": "Point",
        "coordinates": [
          44.793055,
          16.699491
        ]
      },
      "properties": {
        "description": "representative point"
      }
    },
    {
      "geometry": {
        "type": "Point",
        "coordinates": [
          44.793055,
          16.699491
        ]
      },
      "id": "darmc-location-11352",
      "type": "Feature",
      "properties": {
        "description": "5M scale point location",
        "location_precision": "precise",
        "title": "DARMC location 11352",
        "link": "http://pleiades.stoa.org/places/39285/darmc-location-11352"
      }
    }
  ]
}