{
  "type": "FeatureCollection",
  "title": "Akme",
  "id": "39280",
  "bbox": [
    42.841909,
    16.468331,
    42.841909,
    16.468331
  ],
  "description": "An ancient place, cited: BAtlas 4 B2 Akme",
  "names": [
    "Akme",
    "Ambe"
  ],
  "features": [
    {
      "type": "Feature",
      "geometry": {
        "type": "Point",
        "coordinates": [
          42.841909,
          16.468331
        ]
      },
      "properties": {
        "description": "representative point"
      }
    },
    {
      "geometry": {
        "type": "Point",
        "coordinates": [
          42.841909,
          16.468331
        ]
      },
      "id": "darmc-location-9941",
      "type": "Feature",
      "properties": {
        "description": "5M scale point location",
        "location_precision": "precise",
        "title": "DARMC location 9941",
        "link": "http://pleiades.stoa.org/places/39280/darmc-location-9941"
      }
    }
  ]
}