{
  "type": "FeatureCollection",
  "title": "Baitios",
  "id": "39312",
  "bbox": [
    42.819149,
    16.56401,
    42.819149,
    16.56401
  ],
  "description": "An ancient place, cited: BAtlas 4 B2 Baitios",
  "names": [
    "Baitios",
    "Baitheo"
  ],
  "features": [
    {
      "type": "Feature",
      "geometry": {
        "type": "Point",
        "coordinates": [
          42.819149,
          16.56401
        ]
      },
      "properties": {
        "description": "representative point"
      }
    },
    {
      "geometry": {
        "type": "Point",
        "coordinates": [
          42.819149,
          16.56401
        ]
      },
      "id": "darmc-location-19978",
      "type": "Feature",
      "properties": {
        "description": "5M scale point location",
        "location_precision": "precise",
        "title": "DARMC location 19978",
        "link": "http://pleiades.stoa.org/places/39312/darmc-location-19978"
      }
    }
  ]
}