{
  "type": "FeatureCollection",
  "title": "Caminacum",
  "id": "39319",
  "bbox": [
    44.689,
    16.16805,
    44.689,
    16.16805
  ],
  "description": "Caminacum was an ancient settlement of South Arabia. Its ruins, located in Yemen's Al Jawf Governorate, are known today as Kamna.",
  "names": [
    "Caminacum",
    "Camiaeum",
    "Chamimaum"
  ],
  "features": [
    {
      "type": "Feature",
      "geometry": {
        "type": "Point",
        "coordinates": [
          44.689,
          16.16805
        ]
      },
      "properties": {
        "description": "representative point"
      }
    },
    {
      "geometry": {
        "type": "Point",
        "coordinates": [
          44.689,
          16.16805
        ]
      },
      "id": "imagery-location-of-kamna",
      "type": "Feature",
      "properties": {
        "description": "Location confirmed in Google Earth. Dates after BAtlas.",
        "location_precision": "precise",
        "title": "Imagery location of Kamna",
        "link": "http://pleiades.stoa.org/places/39319/imagery-location-of-kamna"
      }
    }
  ]
}