{
  "type": "FeatureCollection",
  "title": "Caminacum",
  "id": "39319",
  "description": "Caminacum is an ancient settlement of South Arabia (now Yemen).",
  "bbox": [
    44.725668,
    16.167242,
    44.725668,
    16.167242
  ],
  "reprPoint": [
    44.725668,
    16.167242
  ],
  "names": [
    "Caminacum",
    "Camiaeum",
    "Chamimaum"
  ],
  "features": [
    {
      "geometry": {
        "type": "Point",
        "coordinates": [
          44.725668,
          16.167242
        ]
      },
      "id": "darmc-location-20101",
      "type": "Feature",
      "properties": {
        "description": "5M scale point location",
        "location_precision": "precise",
        "title": "DARMC location 20101",
        "link": "http://pleiades.stoa.org/places/39319/darmc-location-20101"
      }
    }
  ]
}