{
  "type": "FeatureCollection",
  "title": "Cardava",
  "id": "39322",
  "bbox": [
    44.705389,
    16.743842,
    44.705389,
    16.743842
  ],
  "description": "An ancient place, cited: BAtlas 4 B2 Cardava",
  "names": [
    "Cardava",
    "Cardaba"
  ],
  "features": [
    {
      "type": "Feature",
      "geometry": {
        "type": "Point",
        "coordinates": [
          44.705389,
          16.743842
        ]
      },
      "properties": {
        "description": "representative point"
      }
    },
    {
      "geometry": {
        "type": "Point",
        "coordinates": [
          44.705389,
          16.743842
        ]
      },
      "id": "darmc-location-11906",
      "type": "Feature",
      "properties": {
        "description": "5M scale point location",
        "location_precision": "precise",
        "title": "DARMC location 11906",
        "link": "http://pleiades.stoa.org/places/39322/darmc-location-11906"
      }
    }
  ]
}