{
  "type": "FeatureCollection",
  "title": "Ad IX",
  "id": "393358",
  "bbox": [
    12.266922,
    45.495449,
    12.266922,
    45.495449
  ],
  "description": "An ancient place, cited: BAtlas 40 C2 Ad IX",
  "names": [
    "Ad IX"
  ],
  "features": [
    {
      "type": "Feature",
      "geometry": {
        "type": "Point",
        "coordinates": [
          12.266922,
          45.495449
        ]
      },
      "properties": {
        "description": "representative point"
      }
    },
    {
      "geometry": {
        "type": "Point",
        "coordinates": [
          12.266922,
          45.495449
        ]
      },
      "id": "darmc-location-2603",
      "type": "Feature",
      "properties": {
        "description": "500K scale point location",
        "location_precision": "precise",
        "title": "DARMC location 2603",
        "link": "http://pleiades.stoa.org/places/393358/darmc-location-2603"
      }
    }
  ]
}