{
  "type": "FeatureCollection",
  "title": "Brundulum",
  "id": "393393",
  "description": "An ancient place, cited: BAtlas 40 C2 Brundulum",
  "bbox": [
    12.282209,
    45.19534,
    12.282209,
    45.19534
  ],
  "reprPoint": [
    12.282209,
    45.19534
  ],
  "names": [
    "Brundulum"
  ],
  "features": [
    {
      "geometry": {
        "type": "Point",
        "coordinates": [
          12.282209,
          45.19534
        ]
      },
      "id": "darmc-location-5605",
      "type": "Feature",
      "properties": {
        "description": "500K scale point location",
        "location_precision": "precise",
        "title": "DARMC location 5605",
        "link": "http://pleiades.stoa.org/places/393393/darmc-location-5605"
      }
    }
  ]
}