{
  "type": "FeatureCollection",
  "title": "Butrium",
  "id": "393394",
  "description": "Butrium was located in Gallia Cispadana; Strabo locates it along the road from Ravenna to Altinum.",
  "bbox": [
    12.154815,
    44.543056,
    12.154815,
    44.543056
  ],
  "reprPoint": [
    12.154815,
    44.543056
  ],
  "names": [
    "Butrium"
  ],
  "features": [
    {
      "geometry": {
        "type": "Point",
        "coordinates": [
          12.154815,
          44.543056
        ]
      },
      "id": "darmc-location-19254",
      "type": "Feature",
      "properties": {
        "description": "500K scale point location",
        "location_precision": "precise",
        "title": "DARMC location 19254",
        "link": "http://pleiades.stoa.org/places/393394/darmc-location-19254"
      }
    }
  ]
}