{
  "type": "FeatureCollection",
  "title": "Anemo fl.",
  "id": "393375",
  "description": "An ancient place, cited: BAtlas 40 B4 Anemo fl.",
  "bbox": [
    12.0616267,
    44.4516895,
    12.0616267,
    44.4516895
  ],
  "reprPoint": [
    12.0616267,
    44.4516895
  ],
  "names": [
    "Anemo"
  ],
  "features": [
    {
      "geometry": {
        "type": "Point",
        "coordinates": [
          12.0616267,
          44.4516895
        ]
      },
      "id": "location-of-Anemo-fl",
      "type": "Feature",
      "properties": {
        "description": "Location based on OpenStreetMap",
        "location_precision": "precise",
        "title": "location of Anemo fl.",
        "link": "http://pleiades.stoa.org/places/393375/location-of-Anemo-fl"
      }
    }
  ]
}