{
  "type": "FeatureCollection",
  "title": "Bedesis fl.",
  "id": "393389",
  "description": "Bedesis fl. (Ronco river)",
  "bbox": [
    12.1422922,
    44.3451651,
    12.1422922,
    44.3451651
  ],
  "reprPoint": [
    12.1422922,
    44.3451651
  ],
  "names": [
    "Bedesis"
  ],
  "features": [
    {
      "geometry": {
        "type": "Point",
        "coordinates": [
          12.1422922,
          44.3451651
        ]
      },
      "id": "location-of-Bedesis-fl",
      "type": "Feature",
      "properties": {
        "description": "Location based on OpenStreetMap",
        "location_precision": "precise",
        "title": "location of Bedesis fl.",
        "link": "http://pleiades.stoa.org/places/393389/location-of-Bedesis-fl"
      }
    }
  ]
}