{
  "type": "FeatureCollection",
  "title": "Montagnana",
  "id": "393455",
  "bbox": [
    11.467218,
    45.233609,
    11.467218,
    45.233609
  ],
  "description": "An ancient place, cited: BAtlas 40 A2 Montagnana",
  "features": [
    {
      "type": "Feature",
      "geometry": {
        "type": "Point",
        "coordinates": [
          11.467218,
          45.233609
        ]
      },
      "properties": {
        "description": "representative point"
      }
    },
    {
      "geometry": {
        "type": "Point",
        "coordinates": [
          11.467218,
          45.233609
        ]
      },
      "id": "darmc-location-8915",
      "type": "Feature",
      "properties": {
        "description": "500K scale point location",
        "location_precision": "precise",
        "title": "DARMC location 8915",
        "link": "http://pleiades.stoa.org/places/393455/darmc-location-8915"
      }
    }
  ]
}