{
  "type": "FeatureCollection",
  "title": "Mons Silicis",
  "id": "393454",
  "description": "An ancient place, cited: BAtlas 40 B2 Mons Silicis",
  "bbox": [
    11.750443,
    45.239638,
    11.750443,
    45.239638
  ],
  "reprPoint": [
    11.750443,
    45.239638
  ],
  "names": [
    "Mons Silicis"
  ],
  "features": [
    {
      "geometry": {
        "type": "Point",
        "coordinates": [
          11.750443,
          45.239638
        ]
      },
      "id": "darmc-location-6761",
      "type": "Feature",
      "properties": {
        "description": "500K scale point location",
        "location_precision": "precise",
        "title": "DARMC location 6761",
        "link": "http://pleiades.stoa.org/places/393454/darmc-location-6761"
      }
    }
  ]
}