{
  "type": "FeatureCollection",
  "title": "[Castrum Cumiacli]",
  "id": "393402",
  "bbox": [
    12.17416,
    44.697767,
    12.17416,
    44.697767
  ],
  "description": "An ancient place, cited: BAtlas 40 C3 [Castrum Cumiacli]",
  "names": [
    "Castrum Cumiacli"
  ],
  "features": [
    {
      "type": "Feature",
      "geometry": {
        "type": "Point",
        "coordinates": [
          12.17416,
          44.697767
        ]
      },
      "properties": {
        "description": "representative point"
      }
    },
    {
      "geometry": {
        "type": "Point",
        "coordinates": [
          12.17416,
          44.697767
        ]
      },
      "id": "darmc-location-18318",
      "type": "Feature",
      "properties": {
        "description": "500K scale point location",
        "location_precision": "precise",
        "title": "DARMC location 18318",
        "link": "http://pleiades.stoa.org/places/393402/darmc-location-18318"
      }
    }
  ]
}