{
  "type": "FeatureCollection",
  "title": "Colicaria",
  "id": "393407",
  "bbox": [
    10.997984,
    44.891684,
    10.997984,
    44.891684
  ],
  "description": "An ancient place, cited: BAtlas 40 A3 Colicaria",
  "names": [
    "Colicaria"
  ],
  "features": [
    {
      "type": "Feature",
      "geometry": {
        "type": "Point",
        "coordinates": [
          10.997984,
          44.891684
        ]
      },
      "properties": {
        "description": "representative point"
      }
    },
    {
      "geometry": {
        "type": "Point",
        "coordinates": [
          10.997984,
          44.891684
        ]
      },
      "id": "darmc-location-17217",
      "type": "Feature",
      "properties": {
        "description": "500K scale point location",
        "location_precision": "precise",
        "title": "DARMC location 17217",
        "link": "http://pleiades.stoa.org/places/393407/darmc-location-17217"
      }
    }
  ]
}