{
  "type": "FeatureCollection",
  "title": "Compitum ad Confluentes",
  "id": "393408",
  "bbox": [
    12.39517,
    44.089401,
    12.39517,
    44.089401
  ],
  "description": "An ancient place, cited: BAtlas 40 C4 Compitum ad Confluentes",
  "names": [
    "Compitum ad Confluentes",
    "Ad confluentes"
  ],
  "features": [
    {
      "type": "Feature",
      "geometry": {
        "type": "Point",
        "coordinates": [
          12.39517,
          44.089401
        ]
      },
      "properties": {
        "description": "representative point"
      }
    },
    {
      "geometry": {
        "type": "Point",
        "coordinates": [
          12.39517,
          44.089401
        ]
      },
      "id": "darmc-location-19300",
      "type": "Feature",
      "properties": {
        "description": "500K scale point location",
        "location_precision": "precise",
        "title": "DARMC location 19300",
        "link": "http://pleiades.stoa.org/places/393408/darmc-location-19300"
      }
    }
  ]
}