{
  "type": "FeatureCollection",
  "title": "Sapis fl.",
  "id": "393490",
  "description": "Sapis fl. (Savio river)",
  "bbox": [
    12.2285179,
    44.119168,
    12.2285179,
    44.119168
  ],
  "connectsWith": [
    "1004"
  ],
  "reprPoint": [
    12.2285179,
    44.119168
  ],
  "names": [
    "Sapis"
  ],
  "features": [
    {
      "geometry": {
        "type": "Point",
        "coordinates": [
          12.2285179,
          44.119168
        ]
      },
      "id": "location-of-Sapis-fl",
      "type": "Feature",
      "properties": {
        "description": "Location based on OpenStreetMap",
        "location_precision": "precise",
        "title": "location of Sapis fl.",
        "link": "http://pleiades.stoa.org/places/393490/location-of-Sapis-fl"
      }
    }
  ]
}