{
  "type": "FeatureCollection",
  "title": "Forum Cornelii",
  "id": "393424",
  "bbox": [
    11.707535,
    44.353995,
    11.707535,
    44.353995
  ],
  "description": "An ancient city  founded by Lucius Cornelius Sulla as a colony ca. 82 BC.",
  "connectsWith": [
    "66908841"
  ],
  "names": [
    "Forum Cornelii",
    "Imola"
  ],
  "features": [
    {
      "type": "Feature",
      "geometry": {
        "type": "Point",
        "coordinates": [
          11.707535,
          44.353995
        ]
      },
      "properties": {
        "description": "representative point"
      }
    },
    {
      "geometry": {
        "type": "Point",
        "coordinates": [
          11.707535,
          44.353995
        ]
      },
      "id": "darmc-location-18450",
      "type": "Feature",
      "properties": {
        "description": "500K scale point location",
        "location_precision": "precise",
        "title": "DARMC location 18450",
        "link": "http://pleiades.stoa.org/places/393424/darmc-location-18450"
      }
    }
  ]
}