{
  "type": "FeatureCollection",
  "title": "Ioula",
  "id": "39353",
  "bbox": [
    48.568626,
    16.249392,
    48.568626,
    16.249392
  ],
  "description": "An ancient place, cited: BAtlas 4 C2 Ioula",
  "names": [
    "Ioula"
  ],
  "features": [
    {
      "type": "Feature",
      "geometry": {
        "type": "Point",
        "coordinates": [
          48.568626,
          16.249392
        ]
      },
      "properties": {
        "description": "representative point"
      }
    },
    {
      "geometry": {
        "type": "Point",
        "coordinates": [
          48.568626,
          16.249392
        ]
      },
      "id": "darmc-location-20244",
      "type": "Feature",
      "properties": {
        "description": "5M scale point location",
        "location_precision": "precise",
        "title": "DARMC location 20244",
        "link": "http://pleiades.stoa.org/places/39353/darmc-location-20244"
      }
    }
  ]
}