{
  "type": "FeatureCollection",
  "title": "Laupas",
  "id": "39368",
  "description": "An ancient place, cited: BAtlas 4 B3 Laupas",
  "bbox": [
    43.445883,
    14.175369,
    43.445883,
    14.175369
  ],
  "reprPoint": [
    43.445883,
    14.175369
  ],
  "names": [
    "Laupas",
    "Boulikas"
  ],
  "features": [
    {
      "geometry": {
        "type": "Point",
        "coordinates": [
          43.445883,
          14.175369
        ]
      },
      "id": "darmc-location-19809",
      "type": "Feature",
      "properties": {
        "description": "5M scale point location",
        "location_precision": "precise",
        "title": "DARMC location 19809",
        "link": "http://pleiades.stoa.org/places/39368/darmc-location-19809"
      }
    }
  ]
}