{
  "type": "FeatureCollection",
  "title": "Maipha",
  "id": "39373",
  "description": "An ancient place, cited: BAtlas 4 C3 Maipha",
  "bbox": [
    47.730183,
    14.555811,
    47.730183,
    14.555811
  ],
  "reprPoint": [
    47.730183,
    14.555811
  ],
  "names": [
    "Maipha",
    "Mephra",
    "Maithath"
  ],
  "features": [
    {
      "geometry": {
        "type": "Point",
        "coordinates": [
          47.730183,
          14.555811
        ]
      },
      "id": "darmc-location-13596",
      "type": "Feature",
      "properties": {
        "description": "5M scale point location",
        "location_precision": "precise",
        "title": "DARMC location 13596",
        "link": "http://pleiades.stoa.org/places/39373/darmc-location-13596"
      }
    }
  ]
}