{
  "type": "FeatureCollection",
  "title": "Porta Tiburtina",
  "id": "393959243",
  "bbox": [
    12.5103101,
    41.8974801,
    12.5103101,
    41.8974801
  ],
  "description": "The Porta Tiburtina is a gate in the Aurelianic Walls through which the Via Tiburtina passes. It is also known today as the Porta San Larenzo.",
  "connectsWith": [
    "423025",
    "529700371"
  ],
  "names": [
    "Porta San Lorenzo"
  ],
  "features": [
    {
      "type": "Feature",
      "geometry": {
        "type": "Point",
        "coordinates": [
          12.5103101,
          41.8974801
        ]
      },
      "properties": {
        "description": "representative point"
      }
    },
    {
      "geometry": {
        "type": "Point",
        "coordinates": [
          12.5103101,
          41.8974801
        ]
      },
      "id": "osm-location-of-porta-san-lorenzo",
      "type": "Feature",
      "properties": {
        "description": "Location based on OpenStreetMap",
        "location_precision": "precise",
        "title": "OSM location of Porta San Lorenzo",
        "link": "http://pleiades.stoa.org/places/393959243/osm-location-of-porta-san-lorenzo"
      }
    }
  ]
}