{
  "type": "FeatureCollection",
  "title": "Nestus",
  "id": "39397",
  "description": "An ancient place, cited: BAtlas 4 B2 Nestus",
  "bbox": [
    44.73158,
    16.561019,
    44.73158,
    16.561019
  ],
  "reprPoint": [
    44.73158,
    16.561019
  ],
  "names": [
    "Nestus"
  ],
  "features": [
    {
      "geometry": {
        "type": "Point",
        "coordinates": [
          44.73158,
          16.561019
        ]
      },
      "id": "darmc-location-13913",
      "type": "Feature",
      "properties": {
        "description": "5M scale point location",
        "location_precision": "precise",
        "title": "DARMC location 13913",
        "link": "http://pleiades.stoa.org/places/39397/darmc-location-13913"
      }
    }
  ]
}