{
  "type": "FeatureCollection",
  "title": "Oreine Ins.",
  "id": "39404",
  "bbox": [
    39.7582797,
    15.4307209,
    39.7582797,
    15.4307209
  ],
  "description": "Oreine Ins. (Dissei) is an island in the Red Sea.",
  "connectsWith": [
    "39272"
  ],
  "names": [
    "Oreine"
  ],
  "features": [
    {
      "type": "Feature",
      "geometry": {
        "type": "Point",
        "coordinates": [
          39.7582797,
          15.4307209
        ]
      },
      "properties": {
        "description": "representative point"
      }
    },
    {
      "geometry": {
        "type": "Point",
        "coordinates": [
          39.7582797,
          15.4307209
        ]
      },
      "id": "location-of-Oreine-Ins",
      "type": "Feature",
      "properties": {
        "description": "Location based on OpenStreetMap",
        "location_precision": "precise",
        "title": "location of Oreine Ins.",
        "link": "http://pleiades.stoa.org/places/39404/location-of-Oreine-Ins"
      }
    }
  ]
}