{
  "type": "FeatureCollection",
  "title": "Opone",
  "id": "39403",
  "bbox": [
    51.286582,
    10.4118,
    51.286582,
    10.4118
  ],
  "description": "Opone, mentioned in the first-century A.D. Periplus of the Erythraean Sea, was a trading center located in the Horn of Africa, likely in present day Somalia.",
  "names": [
    "Opone"
  ],
  "features": [
    {
      "type": "Feature",
      "geometry": {
        "type": "Point",
        "coordinates": [
          51.286582,
          10.4118
        ]
      },
      "properties": {
        "description": "representative point"
      }
    },
    {
      "geometry": {
        "type": "Point",
        "coordinates": [
          51.286582,
          10.4118
        ]
      },
      "id": "darmc-location-19618",
      "type": "Feature",
      "properties": {
        "description": "5M scale point location",
        "location_precision": "precise",
        "title": "DARMC location 19618",
        "link": "http://pleiades.stoa.org/places/39403/darmc-location-19618"
      }
    }
  ]
}