{
  "type": "FeatureCollection",
  "title": "Opone",
  "id": "39403",
  "bbox": [
    51.2760513,
    10.4160905,
    51.2760513,
    10.4160905
  ],
  "description": "Opone, mentioned in the first-century A.D. Periplus of the Erythraean Sea, was a trading center located in the Horn of Africa, likely in the area of present day Hafun, Somalia.",
  "names": [
    "Opone",
    "emporion Opone"
  ],
  "features": [
    {
      "type": "Feature",
      "geometry": {
        "type": "Point",
        "coordinates": [
          51.2760513,
          10.4160905
        ]
      },
      "properties": {
        "description": "representative point"
      }
    },
    {
      "geometry": {
        "type": "Point",
        "coordinates": [
          51.2760513,
          10.4160905
        ]
      },
      "id": "osm-location-of-modern-hafun-somalia",
      "type": "Feature",
      "properties": {
        "description": "Location based on OpenStreetMap",
        "location_precision": "precise",
        "title": "OSM location of modern Hafun, Somalia",
        "link": "http://pleiades.stoa.org/places/39403/osm-location-of-modern-hafun-somalia"
      }
    }
  ]
}