{
  "type": "FeatureCollection",
  "title": "Sarouon",
  "id": "39425",
  "description": "An ancient place, cited: BAtlas 4 C3 Sarouon",
  "bbox": [
    46.394374,
    14.785877,
    46.394374,
    14.785877
  ],
  "reprPoint": [
    46.394374,
    14.785877
  ],
  "names": [
    "Sarouon"
  ],
  "features": [
    {
      "geometry": {
        "type": "Point",
        "coordinates": [
          46.394374,
          14.785877
        ]
      },
      "id": "darmc-location-19545",
      "type": "Feature",
      "properties": {
        "description": "5M scale point location",
        "location_precision": "precise",
        "title": "DARMC location 19545",
        "link": "http://pleiades.stoa.org/places/39425/darmc-location-19545"
      }
    }
  ]
}