{
  "type": "FeatureCollection",
  "title": "Hurri/Ba'il-hurri",
  "id": "395214998",
  "bbox": [
    33.4356378,
    34.8860581,
    33.4356378,
    34.8860581
  ],
  "description": "A mountain, probably located on Cyprus, possibly near Larnaka/Kition, perhaps in the vicinity of Stavrovouni Monastery.",
  "connectsWith": [
    "707498",
    "707534",
    "707556",
    "319430829"
  ],
  "names": [
    "Hurri",
    "Ba'il-hurri"
  ],
  "features": [
    {
      "type": "Feature",
      "geometry": {
        "type": "Point",
        "coordinates": [
          33.4356378,
          34.8860581
        ]
      },
      "properties": {
        "description": "representative point"
      }
    },
    {
      "geometry": {
        "type": "Point",
        "coordinates": [
          33.4356378,
          34.8860581
        ]
      },
      "id": "osm-node-5048461277",
      "type": "Feature",
      "properties": {
        "description": "Location based on OpenStreetMap Node 5048461277",
        "location_precision": "precise",
        "title": "Representative location of Hurri/Ba'il-hurri",
        "link": "http://pleiades.stoa.org/places/395214998/osm-node-5048461277"
      }
    }
  ]
}