{
  "type": "FeatureCollection",
  "title": "Centuriation located near Mutina",
  "id": "396382",
  "bbox": [
    10.925223,
    44.647057,
    10.925223,
    44.647057
  ],
  "description": "BAtlas 40 A3 unnamed centuriation (near Forum Gallorum (Mutina))",
  "connectsWith": [
    "383715"
  ],
  "features": [
    {
      "type": "Feature",
      "geometry": {
        "type": "Point",
        "coordinates": [
          10.925223,
          44.647057
        ]
      },
      "properties": {
        "description": "representative point"
      }
    }
  ]
}