{
  "type": "FeatureCollection",
  "title": "Maiden Castle Roman Fortlet",
  "id": "396674383",
  "bbox": [
    -2.19895,
    54.513628,
    -2.19895,
    54.513628
  ],
  "description": "A Roman fortlet located near Brough in eastern Cumbria (England).",
  "names": [
    "Maiden Castle"
  ],
  "features": [
    {
      "type": "Feature",
      "geometry": {
        "type": "Point",
        "coordinates": [
          -2.19895,
          54.513628
        ]
      },
      "properties": {
        "description": "representative point"
      }
    },
    {
      "geometry": {
        "type": "Point",
        "coordinates": [
          -2.19895,
          54.513628
        ]
      },
      "id": "imagery-location",
      "type": "Feature",
      "properties": {
        "description": "Location sited from NHLE map and verified from Google Maps imagery",
        "location_precision": "precise",
        "title": "Imagery Location of center point of fortlet remains",
        "link": "http://pleiades.stoa.org/places/396674383/imagery-location"
      }
    }
  ]
}