{
  "type": "FeatureCollection",
  "title": "Catacomb of SS. Paul and Agatha",
  "id": "399911222",
  "bbox": [
    14.3978715,
    35.8810967,
    14.3978715,
    35.8810967
  ],
  "description": "An important paleochristian complex of Malta, dating from the fourth to the ninth centuries AD.",
  "connectsWith": [
    "462311"
  ],
  "features": [
    {
      "type": "Feature",
      "geometry": {
        "type": "Point",
        "coordinates": [
          14.3978715,
          35.8810967
        ]
      },
      "properties": {
        "description": "representative point"
      }
    },
    {
      "geometry": {
        "type": "Point",
        "coordinates": [
          14.3978715,
          35.8810967
        ]
      },
      "id": "location-of-catacomb-of-s-paul",
      "type": "Feature",
      "properties": {
        "description": "Representative location based on OpenStreetMap.",
        "location_precision": "precise",
        "title": "OSM location of St. Paul's Catecombs",
        "link": "http://pleiades.stoa.org/places/399911222/location-of-catacomb-of-s-paul"
      }
    }
  ]
}