{
  "type": "FeatureCollection",
  "title": "Tomb of the sons of Sextus Pompeius Justus",
  "id": "402816478",
  "bbox": [
    12.5350616,
    41.8393333,
    12.5350616,
    41.8393333
  ],
  "description": "A tomb on the Via Appia dated ca. 50 CE.",
  "connectsWith": [
    "356966898"
  ],
  "features": [
    {
      "type": "Feature",
      "geometry": {
        "type": "Point",
        "coordinates": [
          12.5350616,
          41.8393333
        ]
      },
      "properties": {
        "description": "representative point"
      }
    },
    {
      "geometry": {
        "type": "Point",
        "coordinates": [
          12.5350616,
          41.8393333
        ]
      },
      "id": "osm-location-of-sepolcro-dei-figli-di-sesto-pompeo",
      "type": "Feature",
      "properties": {
        "description": "Representative location based on OpenStreetMap",
        "location_precision": "precise",
        "title": "OSM location of  Sepolcro dei figli di Sesto Pompeo",
        "link": "http://pleiades.stoa.org/places/402816478/osm-location-of-sepolcro-dei-figli-di-sesto-pompeo"
      }
    }
  ]
}