{
  "type": "FeatureCollection",
  "title": "Bottino",
  "id": "403189",
  "description": "An ancient place, cited: BAtlas 41 C2 Bottino",
  "bbox": [
    10.254552,
    43.990365,
    10.254552,
    43.990365
  ],
  "reprPoint": [
    10.254552,
    43.990365
  ],
  "features": [
    {
      "geometry": {
        "type": "Point",
        "coordinates": [
          10.254552,
          43.990365
        ]
      },
      "id": "darmc-location-19367",
      "type": "Feature",
      "properties": {
        "description": "500K scale point location",
        "location_precision": "precise",
        "title": "DARMC location 19367",
        "link": "http://pleiades.stoa.org/places/403189/darmc-location-19367"
      }
    }
  ]
}