{
  "type": "FeatureCollection",
  "title": "Castellina Marittima",
  "id": "403194",
  "description": "An ancient place, cited: BAtlas 41 D3 Castellina Marittima",
  "bbox": [
    10.576512,
    43.412657,
    10.576512,
    43.412657
  ],
  "reprPoint": [
    10.576512,
    43.412657
  ],
  "features": [
    {
      "geometry": {
        "type": "Point",
        "coordinates": [
          10.576512,
          43.412657
        ]
      },
      "id": "darmc-location-19368",
      "type": "Feature",
      "properties": {
        "description": "500K scale point location",
        "location_precision": "precise",
        "title": "DARMC location 19368",
        "link": "http://pleiades.stoa.org/places/403194/darmc-location-19368"
      }
    }
  ]
}