{
  "type": "FeatureCollection",
  "title": "Massaciuccoli",
  "id": "403241",
  "bbox": [
    10.360869,
    43.836039,
    10.360869,
    43.836039
  ],
  "description": "The Roman-period remains at Massaciuccoli, including luxury villas, baths, and productive areas, are connected with the influential Venulei family. Perhaps of Etruscan origins, the Venulei are also to be linked with Pisa.",
  "names": [
    "Massaciuccoli"
  ],
  "features": [
    {
      "type": "Feature",
      "geometry": {
        "type": "Point",
        "coordinates": [
          10.360869,
          43.836039
        ]
      },
      "properties": {
        "description": "representative point"
      }
    },
    {
      "geometry": {
        "type": "Point",
        "coordinates": [
          10.360869,
          43.836039
        ]
      },
      "id": "darmc-location-20993",
      "type": "Feature",
      "properties": {
        "description": "500K scale point location",
        "location_precision": "precise",
        "title": "DARMC location 20993",
        "link": "http://pleiades.stoa.org/places/403241/darmc-location-20993"
      }
    }
  ]
}