{
  "type": "FeatureCollection",
  "title": "Massaciuccoli",
  "id": "403241",
  "description": "An ancient place, cited: BAtlas 41 C2 Massaciuccoli",
  "bbox": [
    10.3602003,
    43.836039,
    10.360869,
    43.8365873
  ],
  "reprPoint": [
    10.36053465,
    43.83631315
  ],
  "features": [
    {
      "geometry": {
        "type": "Point",
        "coordinates": [
          10.360869,
          43.836039
        ]
      },
      "id": "darmc-location-20993",
      "type": "Feature",
      "properties": {
        "description": "500K scale point location",
        "location_precision": "precise",
        "title": "DARMC location 20993",
        "link": "http://pleiades.stoa.org/places/403241/darmc-location-20993"
      }
    }
  ]
}