{
  "type": "FeatureCollection",
  "title": "Prilius L.",
  "id": "403264",
  "description": "An ancient place, cited: BAtlas 41 D4 Prilius L.",
  "bbox": [
    10.9180743,
    42.782295,
    10.9180743,
    42.782295
  ],
  "reprPoint": [
    10.9180743,
    42.782295
  ],
  "names": [
    "Prilius L."
  ],
  "features": [
    {
      "geometry": {
        "type": "Point",
        "coordinates": [
          10.9180743,
          42.782295
        ]
      },
      "id": "location-of-padule-della-diaccia-botrona",
      "type": "Feature",
      "properties": {
        "description": "Location based on OpenStreetMap",
        "location_precision": "precise",
        "title": "location of Padule della Diaccia Botrona",
        "link": "http://pleiades.stoa.org/places/403264/location-of-padule-della-diaccia-botrona"
      }
    }
  ]
}