{
  "type": "FeatureCollection",
  "title": "Virle",
  "id": "403295",
  "description": "An ancient place, cited: BAtlas 41 D2 Virle",
  "bbox": [
    10.9422,
    43.807358,
    10.9422,
    43.807358
  ],
  "reprPoint": [
    10.9422,
    43.807358
  ],
  "features": [
    {
      "geometry": {
        "type": "Point",
        "coordinates": [
          10.9422,
          43.807358
        ]
      },
      "id": "darmc-location-19380",
      "type": "Feature",
      "properties": {
        "description": "500K scale point location",
        "location_precision": "precise",
        "title": "DARMC location 19380",
        "link": "http://pleiades.stoa.org/places/403295/darmc-location-19380"
      }
    }
  ]
}