{
  "type": "FeatureCollection",
  "title": "Poulnabrone dolmen",
  "id": "406501931",
  "bbox": [
    -9.1400214,
    53.0486903,
    -9.1400214,
    53.0486903
  ],
  "description": "The Poulnabrone dolmen is a portal tomb in County Clare, Ireland, dating between 4200 and 2900 BC.",
  "connectsWith": [
    "20487"
  ],
  "features": [
    {
      "type": "Feature",
      "geometry": {
        "type": "Point",
        "coordinates": [
          -9.1400214,
          53.0486903
        ]
      },
      "properties": {
        "description": "representative point"
      }
    },
    {
      "geometry": {
        "type": "Point",
        "coordinates": [
          -9.1400214,
          53.0486903
        ]
      },
      "id": "location-of-oulnabrone-dolmen",
      "type": "Feature",
      "properties": {
        "description": "Location based on OpenStreetMap",
        "location_precision": "precise",
        "title": "OSM location of Poulnabrone dolmen",
        "link": "http://pleiades.stoa.org/places/406501931/location-of-oulnabrone-dolmen"
      }
    }
  ]
}