{
  "type": "FeatureCollection",
  "title": "Grotte dell'Acqua",
  "id": "407809786",
  "bbox": [
    14.0595539,
    40.8250584,
    14.0595539,
    40.8250584
  ],
  "description": "Architectural remains near Lago Fusaro that may have been associated with a so-called \"villa maritima\".",
  "connectsWith": [
    "432622"
  ],
  "features": [
    {
      "type": "Feature",
      "geometry": {
        "type": "Point",
        "coordinates": [
          14.0595539,
          40.8250584
        ]
      },
      "properties": {
        "description": "representative point"
      }
    },
    {
      "geometry": {
        "type": "Point",
        "coordinates": [
          14.0595539,
          40.8250584
        ]
      },
      "id": "grotte-dellacqua",
      "type": "Feature",
      "properties": {
        "description": "Representative location based on OpenStreetMap",
        "location_precision": "precise",
        "title": "OSM location: Grotte dell'Acqua",
        "link": "http://pleiades.stoa.org/places/407809786/grotte-dellacqua"
      }
    }
  ]
}