{
  "type": "FeatureCollection",
  "title": "Ponte Gobbo",
  "id": "411767088",
  "bbox": [
    9.3892026,
    44.7671115,
    9.3892026,
    44.7671115
  ],
  "description": "A Medieval bridge across the river Trebia that is said to have Roman origins.",
  "connectsWith": [
    "383802"
  ],
  "features": [
    {
      "type": "Feature",
      "geometry": {
        "type": "Point",
        "coordinates": [
          9.3892026,
          44.7671115
        ]
      },
      "properties": {
        "description": "representative point"
      }
    },
    {
      "geometry": {
        "type": "Point",
        "coordinates": [
          9.3892026,
          44.7671115
        ]
      },
      "id": "osm-location",
      "type": "Feature",
      "properties": {
        "description": "Representative location based on OpenStreetMap.",
        "location_precision": "precise",
        "title": "OSM location of Ponte Gobbo",
        "link": "http://pleiades.stoa.org/places/411767088/osm-location"
      }
    }
  ]
}