{
  "type": "FeatureCollection",
  "title": "Ad Aesim",
  "id": "412989",
  "bbox": [
    13.396908,
    43.629616,
    13.396908,
    43.629616
  ],
  "description": "A statio located at the mouth of Aesis fl. on the Adriatic coast; the Antonine Itinerary places it between Ancona and Sena Gallica.",
  "connectsWith": [
    "413003"
  ],
  "names": [
    "Ad Aesim"
  ],
  "features": [
    {
      "type": "Feature",
      "geometry": {
        "type": "Point",
        "coordinates": [
          13.396908,
          43.629616
        ]
      },
      "properties": {
        "description": "representative point"
      }
    },
    {
      "geometry": {
        "type": "Point",
        "coordinates": [
          13.396908,
          43.629616
        ]
      },
      "id": "darmc-location-7173",
      "type": "Feature",
      "properties": {
        "description": "500K scale point location",
        "location_precision": "precise",
        "title": "DARMC location 7173",
        "link": "http://pleiades.stoa.org/places/412989/darmc-location-7173"
      }
    }
  ]
}