{
  "type": "FeatureCollection",
  "title": "Ad Statuas",
  "id": "412997",
  "bbox": [
    11.9011445,
    43.1484136,
    11.9011445,
    43.1484136
  ],
  "description": "A Roman road station, mentioned in the Antonine Itinerary. It was probably located somewhere near modern Valiano in the Italian province of Sienna.",
  "names": [
    "Ad Statuas"
  ],
  "features": [
    {
      "type": "Feature",
      "geometry": {
        "type": "Point",
        "coordinates": [
          11.9011445,
          43.1484136
        ]
      },
      "properties": {
        "description": "representative point"
      }
    },
    {
      "geometry": {
        "type": "Point",
        "coordinates": [
          11.9011445,
          43.1484136
        ]
      },
      "id": "osm-location-of-valiano",
      "type": "Feature",
      "properties": {
        "description": "Location based on OpenStreetMap",
        "location_precision": "precise",
        "title": "OSM location of Valiano",
        "link": "http://pleiades.stoa.org/places/412997/osm-location-of-valiano"
      }
    }
  ]
}