{
  "type": "FeatureCollection",
  "title": "Cetamura",
  "id": "413077",
  "description": "Cetamura is an ancient hilltop settlement with occupation phases stretching from the Etruscans to the Romans to the Medieval period. The site is located near Gaiole, Radda and Castellina in Chianti, Italy.",
  "bbox": [
    11.433331,
    43.469283,
    11.433331,
    43.469283
  ],
  "reprPoint": [
    11.433331,
    43.469283
  ],
  "features": [
    {
      "geometry": {
        "type": "Point",
        "coordinates": [
          11.433331,
          43.469283
        ]
      },
      "id": "darmc-location-18332",
      "type": "Feature",
      "properties": {
        "description": "500K scale point location",
        "location_precision": "precise",
        "title": "DARMC location 18332",
        "link": "http://pleiades.stoa.org/places/413077/darmc-location-18332"
      }
    }
  ]
}