{
  "type": "FeatureCollection",
  "title": "Colle Plinio",
  "id": "413099",
  "description": "A hilltop villa near Tifernum Tiberinum commonly associated with one of the villas of Pliny the Younger.",
  "bbox": [
    12.21452,
    43.53058,
    12.21452,
    43.53058
  ],
  "reprPoint": [
    12.21452,
    43.53058
  ],
  "features": [
    {
      "geometry": {
        "type": "Point",
        "coordinates": [
          12.220454,
          43.531253
        ]
      },
      "id": "darmc-location-4471",
      "type": "Feature",
      "properties": {
        "description": "500K scale point location",
        "location_precision": "precise",
        "title": "DARMC location 4471",
        "link": "http://pleiades.stoa.org/places/413099/darmc-location-4471"
      }
    },
    {
      "geometry": {
        "type": "Point",
        "coordinates": [
          12.21452,
          43.53058
        ]
      },
      "id": "dare-location",
      "type": "Feature",
      "properties": {
        "description": "Representative point location, site precision",
        "location_precision": "precise",
        "title": "DARE Location",
        "link": "http://pleiades.stoa.org/places/413099/dare-location"
      }
    }
  ]
}