{
  "type": "FeatureCollection",
  "title": "Aquae Apollinares",
  "id": "413022",
  "bbox": [
    12.040112,
    42.115141,
    12.041451,
    42.115803
  ],
  "description": "The Aquae Apollinares were thermal springs located between Careiae and Tarquinii, perhaps to be associated with the Bagni di Stigliano or Bagni di Vicarello.",
  "names": [
    "Aquae Apollinares"
  ],
  "features": [
    {
      "type": "Feature",
      "geometry": {
        "type": "Point",
        "coordinates": [
          12.0407815,
          42.115472
        ]
      },
      "properties": {
        "description": "representative point"
      }
    },
    {
      "geometry": {
        "type": "Point",
        "coordinates": [
          12.040112,
          42.115141
        ]
      },
      "id": "darmc-location-23137",
      "type": "Feature",
      "properties": {
        "description": "Point location",
        "location_precision": "precise",
        "title": "DARMC location 23137",
        "link": "http://pleiades.stoa.org/places/413022/darmc-location-23137"
      }
    },
    {
      "geometry": {
        "type": "Point",
        "coordinates": [
          12.041451,
          42.115803
        ]
      },
      "id": "dare-location",
      "type": "Feature",
      "properties": {
        "description": "Representative point location, village precision",
        "location_precision": "precise",
        "title": "DARE Location",
        "link": "http://pleiades.stoa.org/places/413022/dare-location"
      }
    }
  ]
}