{
  "type": "FeatureCollection",
  "title": "Aqua Viva",
  "id": "413021",
  "description": "An ancient place, cited: BAtlas 42 C4 Aqua Viva",
  "bbox": [
    12.446371,
    42.272502,
    12.446371,
    42.272502
  ],
  "reprPoint": [
    12.446371,
    42.272502
  ],
  "names": [
    "Aqua Viva"
  ],
  "features": [
    {
      "geometry": {
        "type": "Point",
        "coordinates": [
          12.446371,
          42.272502
        ]
      },
      "id": "darmc-location-7332",
      "type": "Feature",
      "properties": {
        "description": "500K scale point location",
        "location_precision": "precise",
        "title": "DARMC location 7332",
        "link": "http://pleiades.stoa.org/places/413021/darmc-location-7332"
      }
    }
  ]
}