{
  "type": "FeatureCollection",
  "title": "*Aufenginum",
  "id": "413042",
  "description": "An ancient place, cited: BAtlas 42 F4 *Aufenginum",
  "bbox": [
    13.574956,
    42.254057,
    13.574956,
    42.254057
  ],
  "reprPoint": [
    13.574956,
    42.254057
  ],
  "names": [
    "Aufenginum"
  ],
  "features": [
    {
      "geometry": {
        "type": "Point",
        "coordinates": [
          13.574956,
          42.254057
        ]
      },
      "id": "darmc-location-18222",
      "type": "Feature",
      "properties": {
        "description": "500K scale point location",
        "location_precision": "precise",
        "title": "DARMC location 18222",
        "link": "http://pleiades.stoa.org/places/413042/darmc-location-18222"
      }
    }
  ]
}