{
  "type": "FeatureCollection",
  "title": "Castrum Truentinum",
  "id": "413074",
  "bbox": [
    13.904352,
    42.913675,
    13.904358,
    42.913744
  ],
  "description": "An ancient place, cited: BAtlas 42 F3 Castrum Truentinum",
  "connectsWith": [
    "18271457"
  ],
  "names": [
    "Castrum Truentinum"
  ],
  "features": [
    {
      "type": "Feature",
      "geometry": {
        "type": "Point",
        "coordinates": [
          13.904355,
          42.9137095
        ]
      },
      "properties": {
        "description": "representative point"
      }
    },
    {
      "geometry": {
        "type": "Point",
        "coordinates": [
          13.904352,
          42.913675
        ]
      },
      "id": "darmc-location-946",
      "type": "Feature",
      "properties": {
        "description": "1M scale point location",
        "location_precision": "precise",
        "title": "DARMC location 946",
        "link": "http://pleiades.stoa.org/places/413074/darmc-location-946"
      }
    },
    {
      "geometry": {
        "type": "Point",
        "coordinates": [
          13.904358,
          42.913744
        ]
      },
      "id": "darmc-location-7016",
      "type": "Feature",
      "properties": {
        "description": "500K scale point location",
        "location_precision": "precise",
        "title": "DARMC location 7016",
        "link": "http://pleiades.stoa.org/places/413074/darmc-location-7016"
      }
    }
  ]
}