{
  "type": "FeatureCollection",
  "title": "Ancon(a)",
  "id": "413014",
  "bbox": [
    13.510256,
    43.615813,
    13.518992,
    43.625323
  ],
  "description": "A port city founded by colonists from Syracuse in 387 BC.",
  "connectsWith": [
    "1004",
    "413253"
  ],
  "names": [
    "Ancona",
    "Ancon"
  ],
  "features": [
    {
      "type": "Feature",
      "geometry": {
        "type": "Point",
        "coordinates": [
          13.5153199,
          43.62038265
        ]
      },
      "properties": {
        "description": "representative point"
      }
    },
    {
      "geometry": {
        "type": "Point",
        "coordinates": [
          13.518992,
          43.615842
        ]
      },
      "id": "darmc-location-18190",
      "type": "Feature",
      "properties": {
        "description": "1:500,000 scale representative point location digitized from the Barrington Atlas of the Greek and Roman World by the Digital Atlas of Roman and Medieval Civilizations project at Harvard University.",
        "location_precision": "precise",
        "title": "DARMC location 18190",
        "link": "http://pleiades.stoa.org/places/413014/darmc-location-18190"
      }
    },
    {
      "geometry": {
        "type": "Point",
        "coordinates": [
          13.51897,
          43.615813
        ]
      },
      "id": "darmc-location-19965",
      "type": "Feature",
      "properties": {
        "description": "5M scale representative point location digitized from the Barrington Atlas of the Greek and Roman World by the Digital Atlas of Roman and Medieval Civilizations project at Harvard University.",
        "location_precision": "precise",
        "title": "DARMC location 19965",
        "link": "http://pleiades.stoa.org/places/413014/darmc-location-19965"
      }
    },
    {
      "geometry": {
        "type": "Point",
        "coordinates": [
          13.510256,
          43.625323
        ]
      },
      "id": "dare-location",
      "type": "Feature",
      "properties": {
        "description": "Representative point location, site precision",
        "location_precision": "precise",
        "title": "DARE Location",
        "link": "http://pleiades.stoa.org/places/413014/dare-location"
      }
    },
    {
      "geometry": {
        "type": "Point",
        "coordinates": [
          13.5130616,
          43.6245526
        ]
      },
      "id": "location-of-roman-amphitheater",
      "type": "Feature",
      "properties": {
        "description": "Location based on OpenStreetMap",
        "location_precision": "precise",
        "title": "location of Roman amphitheater",
        "link": "http://pleiades.stoa.org/places/413014/location-of-roman-amphitheater"
      }
    }
  ]
}