{
  "type": "FeatureCollection",
  "title": "Cetamura",
  "id": "413077",
  "bbox": [
    11.43248,
    43.469283,
    11.433331,
    43.49215
  ],
  "description": "Cetamura is an ancient hilltop settlement with occupation phases stretching from the Etruscans to the Romans to the Medieval period. The site is located near Gaiole, Radda and Castellina in Chianti, Italy.",
  "features": [
    {
      "type": "Feature",
      "geometry": {
        "type": "Point",
        "coordinates": [
          11.4329055,
          43.4807165
        ]
      },
      "properties": {
        "description": "representative point"
      }
    },
    {
      "geometry": {
        "type": "Point",
        "coordinates": [
          11.433331,
          43.469283
        ]
      },
      "id": "darmc-location-18332",
      "type": "Feature",
      "properties": {
        "description": "500K scale point location",
        "location_precision": "precise",
        "title": "DARMC location 18332",
        "link": "http://pleiades.stoa.org/places/413077/darmc-location-18332"
      }
    },
    {
      "geometry": {
        "type": "Point",
        "coordinates": [
          11.43248,
          43.49215
        ]
      },
      "id": "location-of-cetamura-del-chianti",
      "type": "Feature",
      "properties": {
        "description": "Representative point derived from an OpenStreetMap way.",
        "location_precision": "precise",
        "title": "OSM location of Cetamura del Chianti",
        "link": "http://pleiades.stoa.org/places/413077/location-of-cetamura-del-chianti"
      }
    }
  ]
}