{
  "type": "FeatureCollection",
  "title": "Cetamura",
  "id": "413077",
  "description": "An ancient place, cited: BAtlas 42 A2 Cetamura",
  "bbox": [
    11.433331,
    43.469283,
    11.433331,
    43.469283
  ],
  "reprPoint": [
    11.433331,
    43.469283
  ],
  "features": [
    {
      "geometry": {
        "type": "Point",
        "coordinates": [
          11.433331,
          43.469283
        ]
      },
      "id": "darmc-location-18332",
      "type": "Feature",
      "properties": {
        "description": "500K scale point location",
        "location_precision": "precise",
        "title": "DARMC location 18332",
        "link": "http://pleiades.stoa.org/places/413077/darmc-location-18332"
      }
    }
  ]
}