{
  "type": "FeatureCollection",
  "title": "Castellum Firmanorum",
  "id": "413069",
  "description": "Castellum Firmanorum was the ancient port of Firmum Picenum.",
  "bbox": [
    13.794334,
    43.183742,
    13.794334,
    43.183742
  ],
  "connectsWith": [
    "413135",
    "413341"
  ],
  "reprPoint": [
    13.794334,
    43.183742
  ],
  "names": [
    "Castellum Firmanorum"
  ],
  "features": [
    {
      "geometry": {
        "type": "Point",
        "coordinates": [
          13.794334,
          43.183742
        ]
      },
      "id": "darmc-location-18016",
      "type": "Feature",
      "properties": {
        "description": "500K scale point location",
        "location_precision": "precise",
        "title": "DARMC location 18016",
        "link": "http://pleiades.stoa.org/places/413069/darmc-location-18016"
      }
    }
  ]
}