{
  "type": "FeatureCollection",
  "title": "Batinus? (river)",
  "id": "413053",
  "description": "The Batinus? is mentioned by Pliny and may correspond to the Tordino river.",
  "bbox": [
    13.676972,
    42.6452379,
    13.676972,
    42.6452379
  ],
  "reprPoint": [
    13.676972,
    42.6452379
  ],
  "names": [
    "Batinus"
  ],
  "features": [
    {
      "geometry": {
        "type": "Point",
        "coordinates": [
          13.676972,
          42.6452379
        ]
      },
      "id": "location-of-tordino-river",
      "type": "Feature",
      "properties": {
        "description": "Location based on OpenStreetMap",
        "location_precision": "precise",
        "title": "location of Tordino river",
        "link": "http://pleiades.stoa.org/places/413053/location-of-tordino-river"
      }
    }
  ]
}