{
  "type": "FeatureCollection",
  "title": "Firmum Picenum",
  "id": "413135",
  "description": "Firmum Picenum was founded as a Latin colony in 264 BC with 6,000 colonists. It received municipal status after 48 BC.",
  "bbox": [
    13.7168264,
    43.1610772,
    13.7168264,
    43.1610772
  ],
  "connectsWith": [
    "112fa10ab74bed06e51e16b4d086917e"
  ],
  "reprPoint": [
    13.7168264,
    43.1610772
  ],
  "names": [
    "Firmum Picenum"
  ],
  "features": [
    {
      "geometry": {
        "type": "Point",
        "coordinates": [
          13.7168264,
          43.1610772
        ]
      },
      "id": "location-of-firmum-picenum",
      "type": "Feature",
      "properties": {
        "description": "Location based on OpenStreetMap",
        "location_precision": "precise",
        "title": "location of Firmum Picenum",
        "link": "http://pleiades.stoa.org/places/413135/location-of-firmum-picenum"
      }
    }
  ]
}