{
  "type": "FeatureCollection",
  "title": "Matilica",
  "id": "413196",
  "bbox": [
    13.011553,
    43.255092,
    13.011553,
    43.255092
  ],
  "description": "An ancient place, cited: BAtlas 42 E2 Matilica",
  "names": [
    "Matilica"
  ],
  "features": [
    {
      "type": "Feature",
      "geometry": {
        "type": "Point",
        "coordinates": [
          13.011553,
          43.255092
        ]
      },
      "properties": {
        "description": "representative point"
      }
    },
    {
      "geometry": {
        "type": "Point",
        "coordinates": [
          13.011553,
          43.255092
        ]
      },
      "id": "darmc-location-18607",
      "type": "Feature",
      "properties": {
        "description": "500K scale point location",
        "location_precision": "precise",
        "title": "DARMC location 18607",
        "link": "http://pleiades.stoa.org/places/413196/darmc-location-18607"
      }
    }
  ]
}