{
  "type": "FeatureCollection",
  "title": "Matilica",
  "id": "413196",
  "bbox": [
    13.011553,
    43.255092,
    13.011553,
    43.255092
  ],
  "description": "Matilica was a municipium in Umbria located near the source of the river Aesis and close to the borders of Picenum. The Liber Coloniarum identifies the settlement as one of the “Civitates Piceni.”",
  "names": [
    "Matilica"
  ],
  "features": [
    {
      "type": "Feature",
      "geometry": {
        "type": "Point",
        "coordinates": [
          13.011553,
          43.255092
        ]
      },
      "properties": {
        "description": "representative point"
      }
    },
    {
      "geometry": {
        "type": "Point",
        "coordinates": [
          13.011553,
          43.255092
        ]
      },
      "id": "darmc-location-18607",
      "type": "Feature",
      "properties": {
        "description": "500K scale point location",
        "location_precision": "precise",
        "title": "DARMC location 18607",
        "link": "http://pleiades.stoa.org/places/413196/darmc-location-18607"
      }
    }
  ]
}