{
  "type": "FeatureCollection",
  "title": "Manliana",
  "id": "413189",
  "bbox": [
    11.78807,
    43.175081,
    11.78807,
    43.175081
  ],
  "description": "An ancient place, cited: BAtlas 42 B2 Manliana",
  "names": [
    "Manliana"
  ],
  "features": [
    {
      "type": "Feature",
      "geometry": {
        "type": "Point",
        "coordinates": [
          11.78807,
          43.175081
        ]
      },
      "properties": {
        "description": "representative point"
      }
    },
    {
      "geometry": {
        "type": "Point",
        "coordinates": [
          11.78807,
          43.175081
        ]
      },
      "id": "darmc-location-7063",
      "type": "Feature",
      "properties": {
        "description": "500K scale point location",
        "location_precision": "precise",
        "title": "DARMC location 7063",
        "link": "http://pleiades.stoa.org/places/413189/darmc-location-7063"
      }
    }
  ]
}