{
  "type": "FeatureCollection",
  "title": "Contrada S. Rustico",
  "id": "413102",
  "description": "An ancient place, cited: BAtlas 42 F3 Contrada S. Rustico",
  "bbox": [
    13.713742,
    42.60531,
    13.713742,
    42.60531
  ],
  "reprPoint": [
    13.713742,
    42.60531
  ],
  "features": [
    {
      "geometry": {
        "type": "Point",
        "coordinates": [
          13.713742,
          42.60531
        ]
      },
      "id": "darmc-location-18368",
      "type": "Feature",
      "properties": {
        "description": "500K scale point location",
        "location_precision": "precise",
        "title": "DARMC location 18368",
        "link": "http://pleiades.stoa.org/places/413102/darmc-location-18368"
      }
    }
  ]
}