{
  "type": "FeatureCollection",
  "title": "Galeata",
  "id": "413154",
  "bbox": [
    11.914199,
    43.998918,
    11.914199,
    43.998918
  ],
  "description": "An ancient place, cited: BAtlas 42 B1 Galeata",
  "features": [
    {
      "type": "Feature",
      "geometry": {
        "type": "Point",
        "coordinates": [
          11.914199,
          43.998918
        ]
      },
      "properties": {
        "description": "representative point"
      }
    },
    {
      "geometry": {
        "type": "Point",
        "coordinates": [
          11.914199,
          43.998918
        ]
      },
      "id": "darmc-location-18471",
      "type": "Feature",
      "properties": {
        "description": "500K scale point location",
        "location_precision": "precise",
        "title": "DARMC location 18471",
        "link": "http://pleiades.stoa.org/places/413154/darmc-location-18471"
      }
    }
  ]
}