{
  "type": "FeatureCollection",
  "title": "Firmum Picenum",
  "id": "413135",
  "bbox": [
    13.7168264,
    43.1610772,
    13.7168264,
    43.1610772
  ],
  "description": "Firmum Picenum was founded as a Latin colony in 264 B.C. with 6,000 colonists. It received municipal status after 48 B.C.",
  "connectsWith": [
    "413253"
  ],
  "names": [
    "Firmum Picenum",
    "Fermo",
    "Firmon Pikenon"
  ],
  "features": [
    {
      "type": "Feature",
      "geometry": {
        "type": "Point",
        "coordinates": [
          13.7168264,
          43.1610772
        ]
      },
      "properties": {
        "description": "representative point"
      }
    },
    {
      "geometry": {
        "type": "Point",
        "coordinates": [
          13.7168264,
          43.1610772
        ]
      },
      "id": "location-of-firmum-picenum",
      "type": "Feature",
      "properties": {
        "description": "Location based on OpenStreetMap",
        "location_precision": "precise",
        "title": "OSM location of Firmum Picenum",
        "link": "http://pleiades.stoa.org/places/413135/location-of-firmum-picenum"
      }
    }
  ]
}