{
  "type": "FeatureCollection",
  "title": "Hispellum",
  "id": "413170",
  "bbox": [
    12.671828,
    42.989813,
    12.671901,
    42.990904
  ],
  "description": "Hispellum (modern Spello) is an ancient settlement of Umbria that became a Roman colony in the first century BC.",
  "connectsWith": [
    "856514595"
  ],
  "names": [
    "Hispellum",
    "Hispellates",
    "Eispellon"
  ],
  "features": [
    {
      "type": "Feature",
      "geometry": {
        "type": "Point",
        "coordinates": [
          12.6718645,
          42.9903585
        ]
      },
      "properties": {
        "description": "representative point"
      }
    },
    {
      "geometry": {
        "type": "Point",
        "coordinates": [
          12.671901,
          42.989813
        ]
      },
      "id": "darmc-location-18037",
      "type": "Feature",
      "properties": {
        "description": "1:500,000 scale representative point location digitized from the Barrington Atlas of the Greek and Roman World by the Digital Atlas of Roman and Medieval Civilizations project at Harvard University.",
        "location_precision": "precise",
        "title": "DARMC location 18037",
        "link": "http://pleiades.stoa.org/places/413170/darmc-location-18037"
      }
    },
    {
      "geometry": {
        "type": "Point",
        "coordinates": [
          12.671828,
          42.990904
        ]
      },
      "id": "dare-location",
      "type": "Feature",
      "properties": {
        "description": "Representative point location, site precision",
        "location_precision": "precise",
        "title": "DARE Location",
        "link": "http://pleiades.stoa.org/places/413170/dare-location"
      }
    }
  ]
}