{
  "type": "FeatureCollection",
  "title": "Falerio",
  "id": "413127",
  "description": "An ancient place, cited: BAtlas 42 E2 Falerio",
  "bbox": [
    13.4695001,
    43.1023718,
    13.5004421,
    43.1068367
  ],
  "reprPoint": [
    13.4800690667,
    43.1049001667
  ],
  "names": [
    "Falerio"
  ],
  "features": [
    {
      "geometry": {
        "type": "Point",
        "coordinates": [
          13.470265,
          43.105492
        ]
      },
      "id": "darmc-location-18428",
      "type": "Feature",
      "properties": {
        "description": "500K scale point location",
        "location_precision": "precise",
        "title": "DARMC location 18428",
        "link": "http://pleiades.stoa.org/places/413127/darmc-location-18428"
      }
    }
  ]
}