{
  "type": "FeatureCollection",
  "title": "Ghiaccio Forte",
  "id": "413156",
  "description": "Ghiaccio Forte was an Etruscan settlement, most likely founded in the fourth century BC, that was sacked by the Romans ca. 280 BC.",
  "bbox": [
    11.347935,
    42.6061983,
    11.392759,
    42.68647
  ],
  "reprPoint": [
    11.370347,
    42.64633415
  ],
  "features": [
    {
      "geometry": {
        "type": "Point",
        "coordinates": [
          11.347935,
          42.68647
        ]
      },
      "id": "darmc-location-18476",
      "type": "Feature",
      "properties": {
        "description": "500K scale point location",
        "location_precision": "precise",
        "title": "DARMC location 18476",
        "link": "http://pleiades.stoa.org/places/413156/darmc-location-18476"
      }
    },
    {
      "geometry": {
        "type": "Point",
        "coordinates": [
          11.392759,
          42.6061983
        ]
      },
      "id": "location-of-ghiaccio-forte",
      "type": "Feature",
      "properties": {
        "description": "Location based on OpenStreetMap",
        "location_precision": "precise",
        "title": "location of Ghiaccio Forte",
        "link": "http://pleiades.stoa.org/places/413156/location-of-ghiaccio-forte"
      }
    }
  ]
}