{
  "type": "FeatureCollection",
  "title": "Ghiaccio Forte",
  "id": "413156",
  "description": "Ghiaccio Forte was an Etruscan settlement, most likely founded in the fourth century B.C., that was sacked by the Romans ca. 280 B.C.",
  "bbox": [
    11.392759,
    42.6061983,
    11.392759,
    42.6061983
  ],
  "reprPoint": [
    11.392759,
    42.6061983
  ],
  "features": [
    {
      "geometry": {
        "type": "Point",
        "coordinates": [
          11.392759,
          42.6061983
        ]
      },
      "id": "location-of-ghiaccio-forte",
      "type": "Feature",
      "properties": {
        "description": "Location based on OpenStreetMap",
        "location_precision": "precise",
        "title": "OSM location of Ghiaccio Forte",
        "link": "http://pleiades.stoa.org/places/413156/location-of-ghiaccio-forte"
      }
    }
  ]
}