{
  "type": "FeatureCollection",
  "title": "Manliana",
  "id": "413189",
  "bbox": [
    11.7716466,
    43.1667601,
    11.7716466,
    43.1667601
  ],
  "description": "One of two Roman road stations with this name in Italy attested in ancient sources. The Barrington Atlas Directory localizes this one at modern Torrita di Siena.",
  "connectsWith": [
    "416770"
  ],
  "names": [
    "Manliana"
  ],
  "features": [
    {
      "type": "Feature",
      "geometry": {
        "type": "Point",
        "coordinates": [
          11.7716466,
          43.1667601
        ]
      },
      "properties": {
        "description": "representative point"
      }
    },
    {
      "geometry": {
        "type": "Point",
        "coordinates": [
          11.7716466,
          43.1667601
        ]
      },
      "id": "osm-location-of-modern-torrita-di-siena",
      "type": "Feature",
      "properties": {
        "description": "Location based on OpenStreetMap",
        "location_precision": "precise",
        "title": "OSM Location of Modern Torrita di Siena",
        "link": "http://pleiades.stoa.org/places/413189/osm-location-of-modern-torrita-di-siena"
      }
    }
  ]
}