{
  "type": "FeatureCollection",
  "title": "Histonium",
  "id": "413171",
  "description": "Histonium, on the Adriatic coast, was a chief town of the Frentani.",
  "bbox": [
    14.709616,
    42.112716,
    14.709616,
    42.112716
  ],
  "connectsWith": [
    "432849"
  ],
  "reprPoint": [
    14.709616,
    42.112716
  ],
  "names": [
    "Histonium"
  ],
  "features": [
    {
      "geometry": {
        "type": "Point",
        "coordinates": [
          14.709616,
          42.112716
        ]
      },
      "id": "darmc-location-18038",
      "type": "Feature",
      "properties": {
        "description": "500K scale point location",
        "location_precision": "precise",
        "title": "DARMC location 18038",
        "link": "http://pleiades.stoa.org/places/413171/darmc-location-18038"
      }
    }
  ]
}