{
  "type": "FeatureCollection",
  "title": "Pausulae",
  "id": "413246",
  "description": "Pausulae was a town of Picenum mentioned by Pliny the Elder.",
  "bbox": [
    13.502355,
    43.275392,
    13.502355,
    43.275392
  ],
  "reprPoint": [
    13.502355,
    43.275392
  ],
  "names": [
    "Pausulae"
  ],
  "features": [
    {
      "geometry": {
        "type": "Point",
        "coordinates": [
          13.502355,
          43.275392
        ]
      },
      "id": "darmc-location-18737",
      "type": "Feature",
      "properties": {
        "description": "500K scale point location",
        "location_precision": "precise",
        "title": "DARMC location 18737",
        "link": "http://pleiades.stoa.org/places/413246/darmc-location-18737"
      }
    }
  ]
}