{
  "type": "FeatureCollection",
  "title": "Potentia",
  "id": "413272",
  "bbox": [
    13.663637,
    43.4146346,
    13.6710295,
    43.425037
  ],
  "description": "A city settled in an area subjugated by Rome during the fourth century BC. The local populace rebelled against Rome after the defeat at Cannae (216 BC), however the defeat of the Carthaginians eventually led to Potentia's reincorporation into the Roman sphere.",
  "names": [
    "Potentia"
  ],
  "features": [
    {
      "type": "Feature",
      "geometry": {
        "type": "Point",
        "coordinates": [
          13.66733325,
          43.4198358
        ]
      },
      "properties": {
        "description": "representative point"
      }
    },
    {
      "geometry": {
        "type": "Point",
        "coordinates": [
          13.663637,
          43.425037
        ]
      },
      "id": "darmc-location-7091",
      "type": "Feature",
      "properties": {
        "description": "1:500,000 scale representative point location digitized from the Barrington Atlas of the Greek and Roman World by the Digital Atlas of Roman and Medieval Civilizations project at Harvard University.",
        "location_precision": "precise",
        "title": "DARMC location 7091",
        "link": "http://pleiades.stoa.org/places/413272/darmc-location-7091"
      }
    },
    {
      "geometry": {
        "type": "Point",
        "coordinates": [
          13.6710295,
          43.4146346
        ]
      },
      "id": "dare-location",
      "type": "Feature",
      "properties": {
        "description": "Representative point location, site precision",
        "location_precision": "precise",
        "title": "DARE Location",
        "link": "http://pleiades.stoa.org/places/413272/dare-location"
      }
    }
  ]
}