{
  "type": "FeatureCollection",
  "title": "Paganica",
  "id": "413241",
  "description": "An ancient place, cited: BAtlas 42 E4 Paganica",
  "bbox": [
    13.470296,
    42.359661,
    13.470296,
    42.359661
  ],
  "reprPoint": [
    13.470296,
    42.359661
  ],
  "names": [
    "Paganica"
  ],
  "features": [
    {
      "geometry": {
        "type": "Point",
        "coordinates": [
          13.470296,
          42.359661
        ]
      },
      "id": "darmc-location-18726",
      "type": "Feature",
      "properties": {
        "description": "500K scale point location",
        "location_precision": "precise",
        "title": "DARMC location 18726",
        "link": "http://pleiades.stoa.org/places/413241/darmc-location-18726"
      }
    }
  ]
}