{
  "type": "FeatureCollection",
  "title": "S. Anatolia",
  "id": "413295",
  "description": "An ancient place, cited: BAtlas 42 E4 S. Anatolia",
  "bbox": [
    13.296968,
    42.147065,
    13.296968,
    42.147065
  ],
  "reprPoint": [
    13.296968,
    42.147065
  ],
  "features": [
    {
      "geometry": {
        "type": "Point",
        "coordinates": [
          13.296968,
          42.147065
        ]
      },
      "id": "darmc-location-30638",
      "type": "Feature",
      "properties": {
        "description": "500K scale point location",
        "location_precision": "precise",
        "title": "DARMC location 30638",
        "link": "http://pleiades.stoa.org/places/413295/darmc-location-30638"
      }
    }
  ]
}