{
  "type": "FeatureCollection",
  "title": "Porta Solestà",
  "id": "413249073",
  "description": "The Porta Solestà is one of the gates of Ascoli Piceno.",
  "bbox": [
    13.5720027,
    42.8582867,
    13.5720027,
    42.8582867
  ],
  "connectsWith": [
    "f707379fcba8e340b994dfa6001516b4"
  ],
  "reprPoint": [
    13.5720027,
    42.8582867
  ],
  "features": [
    {
      "geometry": {
        "type": "Point",
        "coordinates": [
          13.5720027,
          42.8582867
        ]
      },
      "id": "osm-location",
      "type": "Feature",
      "properties": {
        "description": "Representative location based on OpenStreetMap.",
        "location_precision": "precise",
        "title": "OSM location of Porta Solestà",
        "link": "http://pleiades.stoa.org/places/413249073/osm-location"
      }
    }
  ]
}