{
  "type": "FeatureCollection",
  "title": "Pitinum Mergens",
  "id": "413261",
  "description": "An ancient place, cited: BAtlas 42 D1 Pitinum Mergens",
  "bbox": [
    12.627421,
    43.614028,
    12.627421,
    43.614028
  ],
  "reprPoint": [
    12.627421,
    43.614028
  ],
  "names": [
    "Pitinum Mergens"
  ],
  "features": [
    {
      "geometry": {
        "type": "Point",
        "coordinates": [
          12.674662,
          43.61351
        ]
      },
      "id": "darmc-location-18773",
      "type": "Feature",
      "properties": {
        "description": "500K scale point location",
        "location_precision": "precise",
        "title": "DARMC location 18773",
        "link": "http://pleiades.stoa.org/places/413261/darmc-location-18773"
      }
    },
    {
      "geometry": {
        "type": "Point",
        "coordinates": [
          12.627421,
          43.614028
        ]
      },
      "id": "dare-location",
      "type": "Feature",
      "properties": {
        "description": "Representative point location, site precision",
        "location_precision": "precise",
        "title": "DARE Location",
        "link": "http://pleiades.stoa.org/places/413261/dare-location"
      }
    }
  ]
}