{
  "type": "FeatureCollection",
  "title": "Potentia",
  "id": "413272",
  "description": "A city settled in an area subjugated by Rome during the fourth century BC. The local populace rebelled against Rome after the defeat at Cannae (216 BC), however the defeat of the Carthaginians eventually led to Potentia's reincorporation into the Roman sphere.",
  "bbox": [
    13.6710295,
    43.4146346,
    13.6710295,
    43.4146346
  ],
  "reprPoint": [
    13.6710295,
    43.4146346
  ],
  "names": [
    "Potentia"
  ],
  "features": [
    {
      "geometry": {
        "type": "Point",
        "coordinates": [
          13.663637,
          43.425037
        ]
      },
      "id": "darmc-location-7091",
      "type": "Feature",
      "properties": {
        "description": "500K scale point location",
        "location_precision": "precise",
        "title": "DARMC location 7091",
        "link": "http://pleiades.stoa.org/places/413272/darmc-location-7091"
      }
    },
    {
      "geometry": {
        "type": "Point",
        "coordinates": [
          13.6710295,
          43.4146346
        ]
      },
      "id": "dare-location",
      "type": "Feature",
      "properties": {
        "description": "Representative point location, site precision",
        "location_precision": "precise",
        "title": "DARE Location",
        "link": "http://pleiades.stoa.org/places/413272/dare-location"
      }
    }
  ]
}