{
  "type": "FeatureCollection",
  "title": "Pallia (river)",
  "id": "413243",
  "bbox": [
    11.730824,
    42.8824276,
    11.730824,
    42.8824276
  ],
  "description": "The Pallia is a tributary of the Tiber river.",
  "connectsWith": [
    "423080"
  ],
  "names": [
    "Pallia"
  ],
  "features": [
    {
      "type": "Feature",
      "geometry": {
        "type": "Point",
        "coordinates": [
          11.730824,
          42.8824276
        ]
      },
      "properties": {
        "description": "representative point"
      }
    },
    {
      "geometry": {
        "type": "Point",
        "coordinates": [
          11.730824,
          42.8824276
        ]
      },
      "id": "location-of-Pallia-fl",
      "type": "Feature",
      "properties": {
        "description": "Location based on OpenStreetMap",
        "location_precision": "precise",
        "title": "location of Paglia (river)",
        "link": "http://pleiades.stoa.org/places/413243/location-of-Pallia-fl"
      }
    }
  ]
}