{
  "type": "FeatureCollection",
  "title": "Pieve Socana",
  "id": "413254",
  "description": "An ancient place, cited: BAtlas 42 B1 Pieve Socana",
  "bbox": [
    11.82588,
    43.647445,
    11.82588,
    43.647445
  ],
  "reprPoint": [
    11.82588,
    43.647445
  ],
  "features": [
    {
      "geometry": {
        "type": "Point",
        "coordinates": [
          11.82588,
          43.647445
        ]
      },
      "id": "darmc-location-20624",
      "type": "Feature",
      "properties": {
        "description": "500K scale point location",
        "location_precision": "precise",
        "title": "DARMC location 20624",
        "link": "http://pleiades.stoa.org/places/413254/darmc-location-20624"
      }
    }
  ]
}