{
  "type": "FeatureCollection",
  "title": "Sacraria",
  "id": "413292",
  "description": "An ancient place, cited: BAtlas 42 D3 Sacraria",
  "bbox": [
    12.767364,
    42.833321,
    12.767364,
    42.833321
  ],
  "reprPoint": [
    12.767364,
    42.833321
  ],
  "names": [
    "Sacraria"
  ],
  "features": [
    {
      "geometry": {
        "type": "Point",
        "coordinates": [
          12.767364,
          42.833321
        ]
      },
      "id": "darmc-location-19293",
      "type": "Feature",
      "properties": {
        "description": "500K scale point location",
        "location_precision": "precise",
        "title": "DARMC location 19293",
        "link": "http://pleiades.stoa.org/places/413292/darmc-location-19293"
      }
    }
  ]
}