{
  "type": "FeatureCollection",
  "title": "Pisaurus (river)",
  "id": "413257",
  "bbox": [
    12.9032148,
    43.919162,
    12.9032148,
    43.919162
  ],
  "description": "An ancient place, cited: BAtlas 42 D1 Pisaurus fl.",
  "names": [
    "Pisaurus"
  ],
  "features": [
    {
      "type": "Feature",
      "geometry": {
        "type": "Point",
        "coordinates": [
          12.9032148,
          43.919162
        ]
      },
      "properties": {
        "description": "representative point"
      }
    },
    {
      "geometry": {
        "type": "Point",
        "coordinates": [
          12.9032148,
          43.919162
        ]
      },
      "id": "location-of-foglia-river",
      "type": "Feature",
      "properties": {
        "description": "Location based on OpenStreetMap",
        "location_precision": "precise",
        "title": "location of Foglia (river)",
        "link": "http://pleiades.stoa.org/places/413257/location-of-foglia-river"
      }
    }
  ]
}