{
  "type": "FeatureCollection",
  "title": "Raiano",
  "id": "413281",
  "description": "An ancient place, cited: BAtlas 42 F4 Raiano",
  "bbox": [
    13.814815,
    42.102584,
    13.814815,
    42.102584
  ],
  "reprPoint": [
    13.814815,
    42.102584
  ],
  "features": [
    {
      "geometry": {
        "type": "Point",
        "coordinates": [
          13.814815,
          42.102584
        ]
      },
      "id": "darmc-location-20629",
      "type": "Feature",
      "properties": {
        "description": "500K scale point location",
        "location_precision": "precise",
        "title": "DARMC location 20629",
        "link": "http://pleiades.stoa.org/places/413281/darmc-location-20629"
      }
    }
  ]
}