{
  "type": "FeatureCollection",
  "title": "Tuscana",
  "id": "413356",
  "description": "An ancient city that traced its legendary origins to Ascanius, son of Aeneas. The site became an important Etruscan mercantile center and eventually achieved Roman municipal status in 88 BC.",
  "bbox": [
    11.87028,
    42.419248,
    11.87028,
    42.419248
  ],
  "connectsWith": [
    "737328394"
  ],
  "reprPoint": [
    11.87028,
    42.419248
  ],
  "names": [
    "Tuscania",
    "Toscanella",
    "Tuscana"
  ],
  "features": [
    {
      "geometry": {
        "type": "Point",
        "coordinates": [
          11.87028,
          42.419248
        ]
      },
      "id": "darmc-location-18974",
      "type": "Feature",
      "properties": {
        "description": "500K scale point location",
        "location_precision": "precise",
        "title": "DARMC location 18974",
        "link": "http://pleiades.stoa.org/places/413356/darmc-location-18974"
      }
    },
    {
      "geometry": {
        "type": "Point",
        "coordinates": [
          11.8776256,
          42.3952498
        ]
      },
      "id": "location-of-ara-del-tufo-necropolis",
      "type": "Feature",
      "properties": {
        "description": "Polygonal geometry representing the visible enclosure of the site, derived from an OpenStreetMap way",
        "location_precision": "precise",
        "title": "location of Ara del Tufo necropolis",
        "link": "http://pleiades.stoa.org/places/413356/location-of-ara-del-tufo-necropolis"
      }
    },
    {
      "geometry": {
        "type": "Point",
        "coordinates": [
          11.8873701,
          42.4247
        ]
      },
      "id": "location-of-pian-di-mola-necropolis",
      "type": "Feature",
      "properties": {
        "description": "Polygonal geometry representing the visible enclosure of the site, derived from an OpenStreetMap way",
        "location_precision": "precise",
        "title": "location of Pian di Mola necropolis",
        "link": "http://pleiades.stoa.org/places/413356/location-of-pian-di-mola-necropolis"
      }
    }
  ]
}