{
  "type": "FeatureCollection",
  "title": "Vettona",
  "id": "413377",
  "description": "Vettona (modern Bettona) is an ancient settlement of Umbria located between Perusia and Mevania. Pliny the Elder lists it among the municipalities of Umbria, and it also numbered as one of the “xv Populi Umbriae\".",
  "bbox": [
    12.485379,
    43.013864,
    12.485379,
    43.013864
  ],
  "connectsWith": [
    "413360"
  ],
  "reprPoint": [
    12.485379,
    43.013864
  ],
  "names": [
    "Vettona"
  ],
  "features": [
    {
      "geometry": {
        "type": "Point",
        "coordinates": [
          12.485368,
          43.013708
        ]
      },
      "id": "darmc-location-19002",
      "type": "Feature",
      "properties": {
        "description": "500K scale point location",
        "location_precision": "precise",
        "title": "DARMC location 19002",
        "link": "http://pleiades.stoa.org/places/413377/darmc-location-19002"
      }
    },
    {
      "geometry": {
        "type": "Point",
        "coordinates": [
          12.485379,
          43.013864
        ]
      },
      "id": "dare-location",
      "type": "Feature",
      "properties": {
        "description": "Representative point location, village precision",
        "location_precision": "precise",
        "title": "DARE Location",
        "link": "http://pleiades.stoa.org/places/413377/dare-location"
      }
    }
  ]
}