{
  "type": "FeatureCollection",
  "title": "Tiora Matiene",
  "id": "413342",
  "bbox": [
    13.2652927,
    42.4255566,
    13.2652927,
    42.4255566
  ],
  "description": "Tiora Matiene was the site of an ancient oracle of the god Mars. The Barrington Atlas tentatively placed it at modern Teora, near Barete.",
  "names": [
    "Tiora Matiene",
    "Tiora Matiene"
  ],
  "features": [
    {
      "type": "Feature",
      "geometry": {
        "type": "Point",
        "coordinates": [
          13.2652927,
          42.4255566
        ]
      },
      "properties": {
        "description": "representative point"
      }
    },
    {
      "geometry": {
        "type": "Point",
        "coordinates": [
          13.2652927,
          42.4255566
        ]
      },
      "id": "osm-location-of-modern-comune-of-teora",
      "type": "Feature",
      "properties": {
        "description": "Representative location based on OpenStreetMap",
        "location_precision": "precise",
        "title": "OSM location of modern comune of Teora",
        "link": "http://pleiades.stoa.org/places/413342/osm-location-of-modern-comune-of-teora"
      }
    }
  ]
}