{
  "type": "FeatureCollection",
  "title": "Trea",
  "id": "413348",
  "bbox": [
    13.312548,
    43.311591,
    13.312548,
    43.311591
  ],
  "description": "An ancient place, cited: BAtlas 42 E2 Trea",
  "names": [
    "Trea"
  ],
  "features": [
    {
      "type": "Feature",
      "geometry": {
        "type": "Point",
        "coordinates": [
          13.312548,
          43.311591
        ]
      },
      "properties": {
        "description": "representative point"
      }
    },
    {
      "geometry": {
        "type": "Point",
        "coordinates": [
          13.312548,
          43.311591
        ]
      },
      "id": "darmc-location-18959",
      "type": "Feature",
      "properties": {
        "description": "500K scale point location",
        "location_precision": "precise",
        "title": "DARMC location 18959",
        "link": "http://pleiades.stoa.org/places/413348/darmc-location-18959"
      }
    }
  ]
}