{
  "type": "FeatureCollection",
  "title": "Settefinestre",
  "id": "413316",
  "description": "A Late Republican Roman slave-run villa owned by the senatorial family of the Volusii.",
  "bbox": [
    11.326756,
    42.430594,
    11.326756,
    42.430594
  ],
  "reprPoint": [
    11.326756,
    42.430594
  ],
  "features": [
    {
      "geometry": {
        "type": "Point",
        "coordinates": [
          11.326756,
          42.430594
        ]
      },
      "id": "dare-location",
      "type": "Feature",
      "properties": {
        "description": "Representative point location, site precision",
        "location_precision": "precise",
        "title": "DARE Location",
        "link": "http://pleiades.stoa.org/places/413316/dare-location"
      }
    }
  ]
}