{
  "type": "FeatureCollection",
  "title": "Trea",
  "id": "413348",
  "bbox": [
    13.2913795,
    43.3190082,
    13.2913795,
    43.3190082
  ],
  "description": "An ancient place, cited: BAtlas 42 E2 Trea",
  "names": [
    "Trea"
  ],
  "features": [
    {
      "type": "Feature",
      "geometry": {
        "type": "Point",
        "coordinates": [
          13.2913795,
          43.3190082
        ]
      },
      "properties": {
        "description": "representative point"
      }
    },
    {
      "geometry": {
        "type": "Point",
        "coordinates": [
          13.2913795,
          43.3190082
        ]
      },
      "id": "osm-location",
      "type": "Feature",
      "properties": {
        "description": "Location based on OpenStreetMap",
        "location_precision": "precise",
        "title": "OSM location",
        "link": "http://pleiades.stoa.org/places/413348/osm-location"
      }
    }
  ]
}