{
  "type": "FeatureCollection",
  "title": "Trebiae",
  "id": "413349",
  "bbox": [
    12.7474547,
    42.8774972,
    12.7474547,
    42.8774972
  ],
  "description": "Trebiae was an ancient city of Umbria (regio IV) located near the line of the Via Flaminia. It is identified with modern Trevi, north of Spoleto in Italy.",
  "connectsWith": [
    "413091",
    "53991065"
  ],
  "names": [
    "Trebiae"
  ],
  "features": [
    {
      "type": "Feature",
      "geometry": {
        "type": "Point",
        "coordinates": [
          12.7474547,
          42.8774972
        ]
      },
      "properties": {
        "description": "representative point"
      }
    },
    {
      "geometry": {
        "type": "Point",
        "coordinates": [
          12.7474547,
          42.8774972
        ]
      },
      "id": "osm-location-of-trevi",
      "type": "Feature",
      "properties": {
        "description": "Location based on OpenStreetMap",
        "location_precision": "precise",
        "title": "OSM location of Trevi",
        "link": "http://pleiades.stoa.org/places/413349/osm-location-of-trevi"
      }
    }
  ]
}