{
  "type": "FeatureCollection",
  "title": "Settefinestre",
  "id": "413316",
  "description": "Late Republican Roman slave-run villa owned by the senatorial family of the Volusii; cited: BAtlas 42 A4 Settefinestre",
  "bbox": [
    11.326756,
    42.430594,
    11.326756,
    42.430594
  ],
  "reprPoint": [
    11.326756,
    42.430594
  ],
  "features": [
    {
      "geometry": {
        "type": "Point",
        "coordinates": [
          11.329223,
          42.42631
        ]
      },
      "id": "darmc-location-21097",
      "type": "Feature",
      "properties": {
        "description": "500K scale point location",
        "location_precision": "precise",
        "title": "DARMC location 21097",
        "link": "http://pleiades.stoa.org/places/413316/darmc-location-21097"
      }
    },
    {
      "geometry": {
        "type": "Point",
        "coordinates": [
          11.326756,
          42.430594
        ]
      },
      "id": "dare-location",
      "type": "Feature",
      "properties": {
        "description": "Representative point location, site precision",
        "location_precision": "precise",
        "title": "DARE Location",
        "link": "http://pleiades.stoa.org/places/413316/dare-location"
      }
    }
  ]
}