{
  "type": "FeatureCollection",
  "title": "Vespasiae",
  "id": "413375",
  "bbox": [
    13.020469,
    42.787963,
    13.020469,
    42.787963
  ],
  "description": "An ancient place, cited: BAtlas 42 D3 Vespasiae",
  "names": [
    "Vespasiae"
  ],
  "features": [
    {
      "type": "Feature",
      "geometry": {
        "type": "Point",
        "coordinates": [
          13.020469,
          42.787963
        ]
      },
      "properties": {
        "description": "representative point"
      }
    },
    {
      "geometry": {
        "type": "Point",
        "coordinates": [
          13.020469,
          42.787963
        ]
      },
      "id": "darmc-location-19001",
      "type": "Feature",
      "properties": {
        "description": "500K scale point location",
        "location_precision": "precise",
        "title": "DARMC location 19001",
        "link": "http://pleiades.stoa.org/places/413375/darmc-location-19001"
      }
    }
  ]
}