{
  "type": "FeatureCollection",
  "title": "Vomanus fl.",
  "id": "413392",
  "description": "An ancient place, cited: BAtlas 42 F3 Vomanus fl.",
  "bbox": [
    14.033333,
    42.65,
    14.033333,
    42.65
  ],
  "connectsWith": [
    "1004"
  ],
  "reprPoint": [
    14.033333,
    42.65
  ],
  "names": [
    "Vomanus"
  ],
  "features": [
    {
      "geometry": {
        "type": "Point",
        "coordinates": [
          14.033333,
          42.65
        ]
      },
      "id": "mouth-of-vomanus-fl",
      "type": "Feature",
      "properties": {
        "description": "verified in Google Earth 2013.",
        "location_precision": "precise",
        "title": "mouth of Vomano (river)",
        "link": "http://pleiades.stoa.org/places/413392/mouth-of-vomanus-fl"
      }
    }
  ]
}