{
  "type": "FeatureCollection",
  "title": "Tifernum Mataurense",
  "id": "413338",
  "description": "An ancient place, cited: BAtlas 42 C1 Tifernum Mataurense",
  "bbox": [
    12.416182,
    43.666421,
    12.416182,
    43.666421
  ],
  "reprPoint": [
    12.416182,
    43.666421
  ],
  "names": [
    "Tifernum Mataurense"
  ],
  "features": [
    {
      "geometry": {
        "type": "Point",
        "coordinates": [
          12.416182,
          43.666421
        ]
      },
      "id": "darmc-location-18943",
      "type": "Feature",
      "properties": {
        "description": "500K scale point location",
        "location_precision": "precise",
        "title": "DARMC location 18943",
        "link": "http://pleiades.stoa.org/places/413338/darmc-location-18943"
      }
    }
  ]
}