{
  "type": "FeatureCollection",
  "title": "Sentinum",
  "id": "413312",
  "bbox": [
    12.852965,
    43.42179,
    12.858961,
    43.432236
  ],
  "description": "An ancient town in the region of Italy now known as Le Marche, Sentinum is perhaps best known for the pivotal Battle of Sentinum of the Third Samnite War that took place nearby in 295 BC.",
  "connectsWith": [
    "458593872"
  ],
  "names": [
    "Sentinum",
    "Sentinon"
  ],
  "features": [
    {
      "type": "Feature",
      "geometry": {
        "type": "Point",
        "coordinates": [
          12.855963,
          43.427013
        ]
      },
      "properties": {
        "description": "representative point"
      }
    },
    {
      "geometry": {
        "type": "Point",
        "coordinates": [
          12.858961,
          43.432236
        ]
      },
      "id": "darmc-location-18876",
      "type": "Feature",
      "properties": {
        "description": "1:500,000 scale representative point location digitized from the Barrington Atlas of the Greek and Roman World by the Digital Atlas of Roman and Medieval Civilizations project at Harvard University.",
        "location_precision": "precise",
        "title": "DARMC location 18876",
        "link": "http://pleiades.stoa.org/places/413312/darmc-location-18876"
      }
    },
    {
      "geometry": {
        "type": "Point",
        "coordinates": [
          12.852965,
          43.42179
        ]
      },
      "id": "dare-location",
      "type": "Feature",
      "properties": {
        "description": "Representative point location, site precision",
        "location_precision": "precise",
        "title": "DARE Location",
        "link": "http://pleiades.stoa.org/places/413312/dare-location"
      }
    }
  ]
}