{
  "type": "FeatureCollection",
  "title": "Trebiae",
  "id": "413349",
  "description": "Trebiae was an ancient city of Umbria (regio IV) located near the line of the Via Flaminia.",
  "bbox": [
    12.745157,
    42.876716,
    12.745157,
    42.876716
  ],
  "connectsWith": [
    "413091",
    "53991065"
  ],
  "reprPoint": [
    12.745157,
    42.876716
  ],
  "names": [
    "Trebiae"
  ],
  "features": [
    {
      "geometry": {
        "type": "Point",
        "coordinates": [
          12.745157,
          42.876716
        ]
      },
      "id": "darmc-location-18961",
      "type": "Feature",
      "properties": {
        "description": "500K scale point location",
        "location_precision": "precise",
        "title": "DARMC location 18961",
        "link": "http://pleiades.stoa.org/places/413349/darmc-location-18961"
      }
    }
  ]
}