{
  "type": "FeatureCollection",
  "title": "Tiora Matiene",
  "id": "413342",
  "description": "An ancient place, cited: BAtlas 42 E4 Tiora Matiene",
  "bbox": [
    13.285278,
    42.416562,
    13.285278,
    42.416562
  ],
  "reprPoint": [
    13.285278,
    42.416562
  ],
  "names": [
    "Tiora Matiene"
  ],
  "features": [
    {
      "geometry": {
        "type": "Point",
        "coordinates": [
          13.285278,
          42.416562
        ]
      },
      "id": "darmc-location-18132",
      "type": "Feature",
      "properties": {
        "description": "500K scale point location",
        "location_precision": "precise",
        "title": "DARMC location 18132",
        "link": "http://pleiades.stoa.org/places/413342/darmc-location-18132"
      }
    }
  ]
}