{
  "type": "FeatureCollection",
  "title": "Tuscana",
  "id": "413356",
  "bbox": [
    11.87028,
    42.419248,
    11.87028,
    42.419248
  ],
  "description": "An ancient city that traced its legendary origins to Ascanius, son of Aeneas. The site became an important Etruscan mercantile center and eventually achieved Roman municipal status in 88 B.C.",
  "connectsWith": [
    "737328394",
    "580975875"
  ],
  "names": [
    "Tuscana",
    "Tuscania",
    "Toscanella"
  ],
  "features": [
    {
      "type": "Feature",
      "geometry": {
        "type": "Point",
        "coordinates": [
          11.87028,
          42.419248
        ]
      },
      "properties": {
        "description": "representative point"
      }
    },
    {
      "geometry": {
        "type": "Point",
        "coordinates": [
          11.87028,
          42.419248
        ]
      },
      "id": "darmc-location-18974",
      "type": "Feature",
      "properties": {
        "description": "500K scale point location",
        "location_precision": "precise",
        "title": "DARMC location 18974",
        "link": "http://pleiades.stoa.org/places/413356/darmc-location-18974"
      }
    }
  ]
}