{
  "type": "FeatureCollection",
  "title": "Bratolyubovskii Kurgan",
  "id": "413644954",
  "description": "A Scythian burial mound dated to the fourth century B.C. located near the village of Bratolyubivka in Kherson Oblast, Ukraine.",
  "bbox": [
    33.89476,
    46.87594,
    33.89476,
    46.87594
  ],
  "reprPoint": [
    33.89476,
    46.87594
  ],
  "names": [
    "Bratolyubovskii Kurgan"
  ],
  "features": [
    {
      "geometry": {
        "type": "Point",
        "coordinates": [
          33.89476,
          46.87594
        ]
      },
      "id": "approximate-imagery-location-of-bratolyubovskii-kurgan",
      "type": "Feature",
      "properties": {
        "description": "Point representing the approximate Google Earth location of Bratolyubovskii Kurgan.",
        "location_precision": "precise",
        "title": "Approximate imagery location of Bratolyubovskii Kurgan",
        "link": "http://pleiades.stoa.org/places/413644954/approximate-imagery-location-of-bratolyubovskii-kurgan"
      }
    }
  ]
}