{
  "type": "FeatureCollection",
  "title": "Temple of Athena Lindia",
  "id": "414067217",
  "bbox": [
    28.0882281,
    36.0911173,
    28.0882281,
    36.0911173
  ],
  "description": "A Doric temple dating ca. 300 BC located on the acropolis of Lindos. The sanctuary stands above a grotto that likely housed the earlier phases of the cult. The amphiprostyle temple has an elongated floor plan and measures 7.75 x 21.65 m.",
  "connectsWith": [
    "589913"
  ],
  "features": [
    {
      "type": "Feature",
      "geometry": {
        "type": "Point",
        "coordinates": [
          28.0882281,
          36.0911173
        ]
      },
      "properties": {
        "description": "representative point"
      }
    },
    {
      "geometry": {
        "type": "Point",
        "coordinates": [
          28.0882281,
          36.0911173
        ]
      },
      "id": "location-of-temple-of-athena-lindia",
      "type": "Feature",
      "properties": {
        "description": "Location based on OpenStreetMap",
        "location_precision": "precise",
        "title": "OSM location of Temple of Athena Lindia",
        "link": "http://pleiades.stoa.org/places/414067217/location-of-temple-of-athena-lindia"
      }
    }
  ]
}