{
  "type": "FeatureCollection",
  "title": "Merimde",
  "id": "414082997",
  "bbox": [
    30.8498954,
    30.3162987,
    30.8498954,
    30.3162987
  ],
  "description": "Neolithic settlement in Egypt. This settlement was inhabited in the 5th millennium and was the typesite for the Merimde culture.",
  "connectsWith": [
    "727172"
  ],
  "features": [
    {
      "type": "Feature",
      "geometry": {
        "type": "Point",
        "coordinates": [
          30.8498954,
          30.3162987
        ]
      },
      "properties": {
        "description": "representative point"
      }
    },
    {
      "geometry": {
        "type": "Point",
        "coordinates": [
          30.8498954,
          30.3162987
        ]
      },
      "id": "merimde",
      "type": "Feature",
      "properties": {
        "description": "Point based on an OpenStreetMap node representing Merimde after Eiwanger 1984.",
        "location_precision": "precise",
        "title": "OSM location of Merimde",
        "link": "http://pleiades.stoa.org/places/414082997/merimde"
      }
    }
  ]
}