{
  "type": "FeatureCollection",
  "title": "Ponte Buriano",
  "id": "414498",
  "bbox": [
    11.7981913,
    43.5060459,
    11.7981913,
    43.5060459
  ],
  "description": "The bridge known as Ponte Buriano is located at the hamlet of Ponte a Buriano, Italy. The bridge spans the Arno River and dates initially from 1277.",
  "connectsWith": [
    "403181"
  ],
  "features": [
    {
      "type": "Feature",
      "geometry": {
        "type": "Point",
        "coordinates": [
          11.7981913,
          43.5060459
        ]
      },
      "properties": {
        "description": "representative point"
      }
    },
    {
      "geometry": {
        "type": "Point",
        "coordinates": [
          11.7981913,
          43.5060459
        ]
      },
      "id": "osm-location-of-ponte-buriano",
      "type": "Feature",
      "properties": {
        "description": "Representative location based on OpenStreetMap",
        "location_precision": "precise",
        "title": "OSM location of Ponte Buriano",
        "link": "http://pleiades.stoa.org/places/414498/osm-location-of-ponte-buriano"
      }
    }
  ]
}