{
  "type": "FeatureCollection",
  "title": "Acerrae Vafriae",
  "id": "416762",
  "bbox": [
    12.5,
    43.5,
    13.0,
    44.0
  ],
  "description": "An ancient settlement in Umbria, attested by literary or documentary sources, whose precise location cannot be determined today.",
  "connectsWith": [
    "413360",
    "416855"
  ],
  "names": [
    "Acerrae Vafriae"
  ],
  "features": [
    {
      "type": "Feature",
      "geometry": {
        "type": "Point",
        "coordinates": [
          12.75,
          43.75
        ]
      },
      "properties": {
        "description": "representative point"
      }
    },
    {
      "geometry": null,
      "id": "batlas-location",
      "type": "Feature",
      "properties": {
        "description": null,
        "location_precision": "unlocated",
        "title": "Barrington Atlas location",
        "link": "http://pleiades.stoa.org/places/416762/batlas-location"
      }
    }
  ]
}