{
  "type": "FeatureCollection",
  "title": "Novem Pagi",
  "id": "416837",
  "bbox": [
    11.5,
    43.5,
    12.0,
    44.0
  ],
  "description": "An ancient place, cited: BAtlas 42 unlocated Novem Pagi",
  "connectsWith": [
    "413122"
  ],
  "names": [
    "Novem Pagi"
  ],
  "features": [
    {
      "type": "Feature",
      "geometry": {
        "type": "Point",
        "coordinates": [
          11.75,
          43.75
        ]
      },
      "properties": {
        "description": "representative point"
      }
    },
    {
      "geometry": null,
      "id": "batlas-location",
      "type": "Feature",
      "properties": {
        "description": null,
        "location_precision": "unlocated",
        "title": "Barrington Atlas location",
        "link": "http://pleiades.stoa.org/places/416837/batlas-location"
      }
    }
  ]
}