{
  "type": "FeatureCollection",
  "title": "Surpicanum",
  "id": "416863",
  "bbox": [
    13.2965826,
    42.7723609,
    13.2965826,
    42.7723609
  ],
  "description": "An ancient settlement along the Via Salaria, the exact position of which remains unknown.",
  "connectsWith": [
    "18271457"
  ],
  "names": [
    "Surpicanum",
    "Surpicano"
  ],
  "features": [
    {
      "type": "Feature",
      "geometry": {
        "type": "Point",
        "coordinates": [
          13.2965826,
          42.7723609
        ]
      },
      "properties": {
        "description": "representative point"
      }
    },
    {
      "geometry": {
        "type": "Point",
        "coordinates": [
          13.2965826,
          42.7723609
        ]
      },
      "id": "osm-location-of-arquata-del-tronto",
      "type": "Feature",
      "properties": {
        "description": "Representative location based on OpenStreetMap",
        "location_precision": "precise",
        "title": "OSM location of Arquata del Tronto",
        "link": "http://pleiades.stoa.org/places/416863/osm-location-of-arquata-del-tronto"
      }
    }
  ]
}