{
  "type": "FeatureCollection",
  "title": "Paesinates",
  "id": "416841",
  "bbox": [
    12.5,
    43.5,
    13.0,
    44.0
  ],
  "description": "An ancient people whose territory is unlocated",
  "connectsWith": [
    "413360"
  ],
  "names": [
    "Paesinates"
  ],
  "features": [
    {
      "type": "Feature",
      "geometry": {
        "type": "Point",
        "coordinates": [
          12.75,
          43.75
        ]
      },
      "properties": {
        "description": "representative point"
      }
    },
    {
      "geometry": null,
      "id": "batlas-location",
      "type": "Feature",
      "properties": {
        "description": null,
        "location_precision": "unlocated",
        "title": "Barrington Atlas location",
        "link": "http://pleiades.stoa.org/places/416841/batlas-location"
      }
    }
  ]
}