{
  "type": "FeatureCollection",
  "title": "Nuraghe Terra Tenera",
  "id": "41722592",
  "bbox": [
    8.7578349,
    40.3308132,
    8.7578349,
    40.3308132
  ],
  "description": "A single-tower nuraghe located near Sassari, Sardinia.",
  "connectsWith": [
    "472014"
  ],
  "features": [
    {
      "type": "Feature",
      "geometry": {
        "type": "Point",
        "coordinates": [
          8.7578349,
          40.3308132
        ]
      },
      "properties": {
        "description": "representative point"
      }
    },
    {
      "geometry": {
        "type": "Point",
        "coordinates": [
          8.7578349,
          40.3308132
        ]
      },
      "id": "osm-location",
      "type": "Feature",
      "properties": {
        "description": "Location based on OpenStreetMap",
        "location_precision": "precise",
        "title": "OSM location of Nuraghe Terra Tenera",
        "link": "http://pleiades.stoa.org/places/41722592/osm-location"
      }
    }
  ]
}