{
  "type": "FeatureCollection",
  "title": "Santa Cristina",
  "id": "417304347",
  "bbox": [
    8.7289581,
    40.0589523,
    8.7328632,
    40.0613084
  ],
  "description": "A nuragic sanctuary centered on a sacred well that was in use from ca. 1200 to 700 BC.",
  "connectsWith": [
    "472014"
  ],
  "features": [
    {
      "type": "Feature",
      "geometry": {
        "type": "Point",
        "coordinates": [
          8.7297896,
          40.0589523
        ]
      },
      "properties": {
        "description": "representative point"
      }
    },
    {
      "geometry": {
        "type": "Point",
        "coordinates": [
          8.7297896,
          40.0589523
        ]
      },
      "id": "location-of-archaeological-area-of-santa-cristina",
      "type": "Feature",
      "properties": {
        "description": "Location based on OpenStreetMap",
        "location_precision": "precise",
        "title": "OSM location of Parco Archeologico Santa Cristina",
        "link": "http://pleiades.stoa.org/places/417304347/location-of-archaeological-area-of-santa-cristina"
      }
    },
    {
      "geometry": {
        "type": "Point",
        "coordinates": [
          8.7328632,
          40.0613084
        ]
      },
      "id": "location-of-sacred-well",
      "type": "Feature",
      "properties": {
        "description": "Location based on OpenStreetMap",
        "location_precision": "precise",
        "title": "OSM location of sacred well",
        "link": "http://pleiades.stoa.org/places/417304347/location-of-sacred-well"
      }
    },
    {
      "geometry": {
        "type": "Point",
        "coordinates": [
          8.7289581,
          40.0599129
        ]
      },
      "id": "location-of-nuraghe-santa-cristina",
      "type": "Feature",
      "properties": {
        "description": "Location based on OpenStreetMap",
        "location_precision": "precise",
        "title": "OSM location of nuraghe Santa Cristina",
        "link": "http://pleiades.stoa.org/places/417304347/location-of-nuraghe-santa-cristina"
      }
    }
  ]
}