{
  "type": "FeatureCollection",
  "title": "Selvicciola Roman villa",
  "id": "418123958",
  "bbox": [
    11.756252,
    42.544026,
    11.756252,
    42.544026
  ],
  "description": "The Selvicciola Roman villa is the site of a vast Roman rural complex as well as a Longobard cemetery.",
  "names": [
    "Villa romana della Selvicciola"
  ],
  "features": [
    {
      "type": "Feature",
      "geometry": {
        "type": "Point",
        "coordinates": [
          11.756252,
          42.544026
        ]
      },
      "properties": {
        "description": "representative point"
      }
    },
    {
      "geometry": {
        "type": "Point",
        "coordinates": [
          11.756252,
          42.544026
        ]
      },
      "id": "osm-location-of-modern-ischia-di-castro",
      "type": "Feature",
      "properties": {
        "description": "Location based on OpenStreetMap",
        "location_precision": "precise",
        "title": "OSM location of modern Ischia di Castro",
        "link": "http://pleiades.stoa.org/places/418123958/osm-location-of-modern-ischia-di-castro"
      }
    }
  ]
}