{
  "type": "FeatureCollection",
  "title": "Kar-Assurnazirpal",
  "id": "418374056",
  "bbox": [
    40.5554,
    34.9738,
    40.5554,
    34.9738
  ],
  "description": "Town founded by Assurnazipal II, mound (Tall Masaikh) in the Lower Middle Euphrates valley, find place for cuneiform inscription.",
  "names": [
    "Tall Masaikh"
  ],
  "features": [
    {
      "type": "Feature",
      "geometry": {
        "type": "Point",
        "coordinates": [
          40.5554,
          34.9738
        ]
      },
      "properties": {
        "description": "representative point"
      }
    },
    {
      "geometry": {
        "type": "Point",
        "coordinates": [
          40.5554,
          34.9738
        ]
      },
      "id": "cigs-location-of-tall-masaikh",
      "type": "Feature",
      "properties": {
        "description": null,
        "location_precision": "precise",
        "title": "CIGS location of Tall Masaikh",
        "link": "http://pleiades.stoa.org/places/418374056/cigs-location-of-tall-masaikh"
      }
    }
  ]
}