{
  "type": "FeatureCollection",
  "title": "Nea Nikomedeia",
  "id": "419515104",
  "bbox": [
    22.2036834,
    40.5215342,
    22.2036834,
    40.5215342
  ],
  "description": "Nea Nikomedeia is a Neolithic settlement in Macedonia, dating to the seventh millennium BC.",
  "features": [
    {
      "type": "Feature",
      "geometry": {
        "type": "Point",
        "coordinates": [
          22.2036834,
          40.5215342
        ]
      },
      "properties": {
        "description": "representative point"
      }
    },
    {
      "geometry": {
        "type": "Point",
        "coordinates": [
          22.2036834,
          40.5215342
        ]
      },
      "id": "osm-location-of-modern-veria",
      "type": "Feature",
      "properties": {
        "description": "Location based on OpenStreetMap",
        "location_precision": "precise",
        "title": "OSM location of modern Veria",
        "link": "http://pleiades.stoa.org/places/419515104/osm-location-of-modern-veria"
      }
    }
  ]
}