{
  "type": "FeatureCollection",
  "title": "Nymphaeum of via degli Annibaldi",
  "id": "420447351",
  "bbox": [
    12.492121,
    41.891664,
    12.492121,
    41.891664
  ],
  "description": "An elaborate nymphaeum on the Oppian Hill discovered in 1895. The complex dates to the Late Republican period. The ancient nymphaeum was partially obliterated by the construction of the Neronian Domus Aurea.",
  "connectsWith": [
    "423025",
    "91325207"
  ],
  "features": [
    {
      "type": "Feature",
      "geometry": {
        "type": "Point",
        "coordinates": [
          12.492121,
          41.891664
        ]
      },
      "properties": {
        "description": "representative point"
      }
    },
    {
      "geometry": {
        "type": "Point",
        "coordinates": [
          12.492121,
          41.891664
        ]
      },
      "id": "imagery-location-of-nymphaeum-of-the-via-degli-annibaldi",
      "type": "Feature",
      "properties": {
        "description": "Coordinates following GeoHack",
        "location_precision": "precise",
        "title": "Imagery location of Nymphaeum of the via degli Annibaldi",
        "link": "http://pleiades.stoa.org/places/420447351/imagery-location-of-nymphaeum-of-the-via-degli-annibaldi"
      }
    }
  ]
}