{
  "type": "FeatureCollection",
  "title": "Baysān",
  "id": "421715028",
  "bbox": [
    43.1037,
    36.4222,
    43.1041769,
    36.422439
  ],
  "description": "Find place for cuneiform inscription.",
  "names": [
    "Baysān"
  ],
  "features": [
    {
      "type": "Feature",
      "geometry": {
        "type": "Point",
        "coordinates": [
          43.10393845,
          36.4223195
        ]
      },
      "properties": {
        "description": "representative point"
      }
    },
    {
      "geometry": {
        "type": "Point",
        "coordinates": [
          43.1041769,
          36.422439
        ]
      },
      "id": "baysan",
      "type": "Feature",
      "properties": {
        "description": "Location based on OpenStreetMap",
        "location_precision": "precise",
        "title": "OSM location for Baysan",
        "link": "http://pleiades.stoa.org/places/421715028/baysan"
      }
    },
    {
      "geometry": {
        "type": "Point",
        "coordinates": [
          43.1037,
          36.4222
        ]
      },
      "id": "cigs-location-of-baysan",
      "type": "Feature",
      "properties": {
        "description": null,
        "location_precision": "precise",
        "title": "CIGS location of Baysān",
        "link": "http://pleiades.stoa.org/places/421715028/cigs-location-of-baysan"
      }
    }
  ]
}