{
  "type": "FeatureCollection",
  "title": "Hod Hill",
  "id": "42178780",
  "bbox": [
    -2.2078952,
    50.8963551,
    -2.2071988,
    50.8975049
  ],
  "description": "Hod Hill is the site of a large, rectangular Iron Age hill-fort. After the Roman conquest, Romans occupied the hill-fort.",
  "features": [
    {
      "type": "Feature",
      "geometry": {
        "type": "Point",
        "coordinates": [
          -2.207547,
          50.89693
        ]
      },
      "properties": {
        "description": "representative point"
      }
    },
    {
      "geometry": {
        "type": "Point",
        "coordinates": [
          -2.2071988,
          50.8975049
        ]
      },
      "id": "location-of-hod-hill-hill-fort",
      "type": "Feature",
      "properties": {
        "description": "Location based on OpenStreetMap",
        "location_precision": "precise",
        "title": "location of Hod Hill hill fort",
        "link": "http://pleiades.stoa.org/places/42178780/location-of-hod-hill-hill-fort"
      }
    },
    {
      "geometry": {
        "type": "Point",
        "coordinates": [
          -2.2078952,
          50.8963551
        ]
      },
      "id": "location-of-roman-camp",
      "type": "Feature",
      "properties": {
        "description": "Location based on OpenStreetMap",
        "location_precision": "precise",
        "title": "location of Roman camp",
        "link": "http://pleiades.stoa.org/places/42178780/location-of-roman-camp"
      }
    }
  ]
}