{
  "type": "FeatureCollection",
  "title": "Nuraghe Santu Antine",
  "id": "422755499",
  "description": "A nuragic structure dating originally ca. 1,600 to 1,450 BC",
  "bbox": [
    8.769874,
    40.486543,
    8.769874,
    40.486543
  ],
  "connectsWith": [
    "472014"
  ],
  "reprPoint": [
    8.769874,
    40.486543
  ],
  "features": [
    {
      "geometry": {
        "type": "Point",
        "coordinates": [
          8.769874,
          40.486543
        ]
      },
      "id": "location-of-nuraghe-santu-antine",
      "type": "Feature",
      "properties": {
        "description": "location of the nuragic site; verified in Google Earth 2012, eye height 2525 ft.",
        "location_precision": "precise",
        "title": "Location of Nuraghe Santu Antine",
        "link": "http://pleiades.stoa.org/places/422755499/location-of-nuraghe-santu-antine"
      }
    }
  ]
}