{
  "type": "FeatureCollection",
  "title": "Il Barco",
  "id": "422849",
  "description": "An ancient place, cited: BAtlas 43 C2 Il Barco",
  "bbox": [
    12.680435,
    41.806244,
    12.740991,
    41.951088
  ],
  "reprPoint": [
    12.710713,
    41.878666
  ],
  "features": [
    {
      "geometry": {
        "type": "Point",
        "coordinates": [
          12.740991,
          41.951088
        ]
      },
      "id": "darmc-location-20579",
      "type": "Feature",
      "properties": {
        "description": "150K scale point location",
        "location_precision": "precise",
        "title": "DARMC location 20579",
        "link": "http://pleiades.stoa.org/places/422849/darmc-location-20579"
      }
    },
    {
      "geometry": {
        "type": "Point",
        "coordinates": [
          12.680435,
          41.806244
        ]
      },
      "id": "darmc-location-20929",
      "type": "Feature",
      "properties": {
        "description": "150K scale point location",
        "location_precision": "precise",
        "title": "DARMC location 20929",
        "link": "http://pleiades.stoa.org/places/422849/darmc-location-20929"
      }
    }
  ]
}