{
  "type": "FeatureCollection",
  "title": "Acquafredda",
  "id": "422803",
  "description": "An ancient place, cited: BAtlas 43 B2 Acquafredda",
  "bbox": [
    12.389849,
    41.884204,
    12.389849,
    41.884204
  ],
  "reprPoint": [
    12.389849,
    41.884204
  ],
  "features": [
    {
      "geometry": {
        "type": "Point",
        "coordinates": [
          12.389849,
          41.884204
        ]
      },
      "id": "darmc-location-18149",
      "type": "Feature",
      "properties": {
        "description": "150K scale point location",
        "location_precision": "precise",
        "title": "DARMC location 18149",
        "link": "http://pleiades.stoa.org/places/422803/darmc-location-18149"
      }
    }
  ]
}