{
  "type": "FeatureCollection",
  "title": "Ad Nonum",
  "id": "422812",
  "bbox": [
    12.58889,
    41.79083,
    12.58889,
    41.79083
  ],
  "description": "An ancient place, cited: BAtlas 43 C2 Ad Nonum (1)",
  "connectsWith": [
    "356966898"
  ],
  "names": [
    "Ad Nonum"
  ],
  "features": [
    {
      "type": "Feature",
      "geometry": {
        "type": "Point",
        "coordinates": [
          12.58889,
          41.79083
        ]
      },
      "properties": {
        "description": "representative point"
      }
    },
    {
      "geometry": {
        "type": "Point",
        "coordinates": [
          12.58889,
          41.79083
        ]
      },
      "id": "dare-location",
      "type": "Feature",
      "properties": {
        "description": "Representative point location, village precision",
        "location_precision": "precise",
        "title": "DARE Location",
        "link": "http://pleiades.stoa.org/places/422812/dare-location"
      }
    }
  ]
}