{
  "type": "FeatureCollection",
  "title": "Casale del Cavaliere",
  "id": "422870",
  "description": "An ancient place, cited: BAtlas 43 C2 Casale del Cavaliere",
  "bbox": [
    12.660322,
    41.930134,
    12.660322,
    41.930134
  ],
  "reprPoint": [
    12.660322,
    41.930134
  ],
  "features": [
    {
      "geometry": {
        "type": "Point",
        "coordinates": [
          12.660322,
          41.930134
        ]
      },
      "id": "darmc-location-20812",
      "type": "Feature",
      "properties": {
        "description": "150K scale point location",
        "location_precision": "precise",
        "title": "DARMC location 20812",
        "link": "http://pleiades.stoa.org/places/422870/darmc-location-20812"
      }
    }
  ]
}