{
  "type": "FeatureCollection",
  "title": "Ad Sponsas",
  "id": "422816",
  "bbox": [
    12.84611,
    41.58389,
    12.84611,
    41.58389
  ],
  "description": "Ad Sponsas was a road station on the Via Appia.",
  "connectsWith": [
    "356966898"
  ],
  "names": [
    "Ad Sponsas"
  ],
  "features": [
    {
      "type": "Feature",
      "geometry": {
        "type": "Point",
        "coordinates": [
          12.84611,
          41.58389
        ]
      },
      "properties": {
        "description": "representative point"
      }
    },
    {
      "geometry": {
        "type": "Point",
        "coordinates": [
          12.84611,
          41.58389
        ]
      },
      "id": "dare-location",
      "type": "Feature",
      "properties": {
        "description": "Representative point location, village precision",
        "location_precision": "precise",
        "title": "DARE Location",
        "link": "http://pleiades.stoa.org/places/422816/dare-location"
      }
    }
  ]
}