{
  "type": "FeatureCollection",
  "title": "Casal Rotondo",
  "id": "422869",
  "description": "A Roman tomb that supports a Medieval farmhouse (casale) at the sixth mile of the Via Appia. The tomb originally dates ca. 30 BC; it was a large, circular tomb with a diameter of approximately 35 m.",
  "bbox": [
    12.5557162,
    41.8209348,
    12.5557162,
    41.8209348
  ],
  "connectsWith": [
    "356966898"
  ],
  "reprPoint": [
    12.5557162,
    41.8209348
  ],
  "features": [
    {
      "geometry": {
        "type": "Point",
        "coordinates": [
          12.5557162,
          41.8209348
        ]
      },
      "id": "location-of-casal-rotondo",
      "type": "Feature",
      "properties": {
        "description": "Representative location based on OpenStreetMap.",
        "location_precision": "precise",
        "title": "OSM location of Casal Rotondo",
        "link": "http://pleiades.stoa.org/places/422869/location-of-casal-rotondo"
      }
    }
  ]
}