{
  "type": "FeatureCollection",
  "title": "Antium",
  "id": "422837",
  "description": "Antium ranked as one of the most important and most powerful centers of Latium and was captured by Rome at the close of the Latin War in the fourth century BC. Imperial Antium was well known for a number of coastal villas.",
  "bbox": [
    12.628995,
    41.44795,
    12.633381,
    41.611539
  ],
  "reprPoint": [
    12.631188,
    41.5297445
  ],
  "names": [
    "Antium",
    "Anzio"
  ],
  "features": [
    {
      "geometry": {
        "type": "Point",
        "coordinates": [
          12.628995,
          41.44795
        ]
      },
      "id": "darmc-location-6943",
      "type": "Feature",
      "properties": {
        "description": "500K scale point location",
        "location_precision": "precise",
        "title": "DARMC location 6943",
        "link": "http://pleiades.stoa.org/places/422837/darmc-location-6943"
      }
    },
    {
      "geometry": {
        "type": "Point",
        "coordinates": [
          12.6219082,
          41.4461039
        ]
      },
      "id": "location-of-villa-di-nerone",
      "type": "Feature",
      "properties": {
        "description": "Location based on OpenStreetMap",
        "location_precision": "precise",
        "title": "location of Villa di Nerone",
        "link": "http://pleiades.stoa.org/places/422837/location-of-villa-di-nerone"
      }
    }
  ]
}