{
  "type": "FeatureCollection",
  "title": "Ad Sextum",
  "id": "422815",
  "bbox": [
    12.438952,
    41.967709,
    12.438952,
    41.967709
  ],
  "description": "An ancient place, cited: BAtlas 43 B2 Ad Sextum",
  "names": [
    "Ad Sextum"
  ],
  "features": [
    {
      "type": "Feature",
      "geometry": {
        "type": "Point",
        "coordinates": [
          12.438952,
          41.967709
        ]
      },
      "properties": {
        "description": "representative point"
      }
    },
    {
      "geometry": {
        "type": "Point",
        "coordinates": [
          12.438952,
          41.967709
        ]
      },
      "id": "dare-location",
      "type": "Feature",
      "properties": {
        "description": "Representative point location, village precision",
        "location_precision": "precise",
        "title": "DARE Location",
        "link": "http://pleiades.stoa.org/places/422815/dare-location"
      }
    }
  ]
}