{
  "type": "FeatureCollection",
  "title": "Casal Rotondo",
  "id": "422869",
  "description": "A Roman tomb that supports a Medieval farmhouse (casale) at the sixth mile of the Via Appia. The tomb originally dates ca. 30 BC; it was a large, circular tomb with a diameter of approximately 35 m.",
  "bbox": [
    12.555775,
    41.821128,
    12.555775,
    41.821128
  ],
  "connectsWith": [
    "356966898"
  ],
  "reprPoint": [
    12.555775,
    41.821128
  ],
  "features": [
    {
      "geometry": {
        "type": "Point",
        "coordinates": [
          12.555775,
          41.821128
        ]
      },
      "id": "darmc-location-20808",
      "type": "Feature",
      "properties": {
        "description": "150K scale point location",
        "location_precision": "precise",
        "title": "DARMC location 20808",
        "link": "http://pleiades.stoa.org/places/422869/darmc-location-20808"
      }
    }
  ]
}