{
  "type": "FeatureCollection",
  "title": "Case Rosse",
  "id": "422878",
  "description": "An ancient place, cited: BAtlas 43 C2 Case Rosse",
  "bbox": [
    12.648846,
    41.934132,
    12.648846,
    41.934132
  ],
  "reprPoint": [
    12.648846,
    41.934132
  ],
  "features": [
    {
      "geometry": {
        "type": "Point",
        "coordinates": [
          12.648846,
          41.934132
        ]
      },
      "id": "darmc-location-20816",
      "type": "Feature",
      "properties": {
        "description": "150K scale point location",
        "location_precision": "precise",
        "title": "DARMC location 20816",
        "link": "http://pleiades.stoa.org/places/422878/darmc-location-20816"
      }
    }
  ]
}