{
  "type": "FeatureCollection",
  "title": "Buglioncino",
  "id": "422854",
  "description": "An ancient place, cited: BAtlas 43 C3 Buglioncino",
  "bbox": [
    12.590177,
    41.542723,
    12.590177,
    41.542723
  ],
  "reprPoint": [
    12.590177,
    41.542723
  ],
  "features": [
    {
      "geometry": {
        "type": "Point",
        "coordinates": [
          12.590177,
          41.542723
        ]
      },
      "id": "darmc-location-18263",
      "type": "Feature",
      "properties": {
        "description": "150K scale point location",
        "location_precision": "precise",
        "title": "DARMC location 18263",
        "link": "http://pleiades.stoa.org/places/422854/darmc-location-18263"
      }
    }
  ]
}