{
  "type": "FeatureCollection",
  "title": "Castel Savello",
  "id": "422884",
  "description": "An ancient place, cited: BAtlas 43 C3 Castel Savello",
  "bbox": [
    12.637511,
    41.723909,
    12.637511,
    41.723909
  ],
  "reprPoint": [
    12.637511,
    41.723909
  ],
  "features": [
    {
      "geometry": {
        "type": "Point",
        "coordinates": [
          12.637511,
          41.723909
        ]
      },
      "id": "darmc-location-18314",
      "type": "Feature",
      "properties": {
        "description": "150K scale point location",
        "location_precision": "precise",
        "title": "DARMC location 18314",
        "link": "http://pleiades.stoa.org/places/422884/darmc-location-18314"
      }
    }
  ]
}