{
  "type": "FeatureCollection",
  "title": "Case Rosse",
  "id": "422878",
  "bbox": [
    12.648846,
    41.934132,
    12.648846,
    41.934132
  ],
  "description": "Ashby describes a rich archaeological landscape that once included the remains of Roman-period tombs and villas, the latter appointed with mosaics. The modern toponym \"Case Rosse\" is said to derive from a well-preserved Roman tomb executed in brick that was purposefully destroyed in 1824.",
  "features": [
    {
      "type": "Feature",
      "geometry": {
        "type": "Point",
        "coordinates": [
          12.648846,
          41.934132
        ]
      },
      "properties": {
        "description": "representative point"
      }
    },
    {
      "geometry": {
        "type": "Point",
        "coordinates": [
          12.648846,
          41.934132
        ]
      },
      "id": "darmc-location-20816",
      "type": "Feature",
      "properties": {
        "description": "1:150,000 scale representative point location digitized from the Barrington Atlas of the Greek and Roman World by the Digital Atlas of Roman and Medieval Civilizations project at Harvard University.",
        "location_precision": "precise",
        "title": "DARMC location 20816",
        "link": "http://pleiades.stoa.org/places/422878/darmc-location-20816"
      }
    }
  ]
}