{
  "type": "FeatureCollection",
  "title": "Bovillae",
  "id": "422852",
  "bbox": [
    12.617018,
    41.76587,
    12.617018,
    41.76587
  ],
  "description": "A town of ancient Latium along the line of the Via Appia, Bovillae is traditionally considered to be a colony of Alba Longa and was one of the thirty cities of the Latin League.",
  "connectsWith": [
    "356966898"
  ],
  "names": [
    "Bovillae",
    "Bobellas"
  ],
  "features": [
    {
      "type": "Feature",
      "geometry": {
        "type": "Point",
        "coordinates": [
          12.617018,
          41.76587
        ]
      },
      "properties": {
        "description": "representative point"
      }
    },
    {
      "geometry": {
        "type": "Point",
        "coordinates": [
          12.617018,
          41.76587
        ]
      },
      "id": "darmc-location-18260",
      "type": "Feature",
      "properties": {
        "description": "1:500,000 scale representative point location digitized from the Barrington Atlas of the Greek and Roman World by the Digital Atlas of Roman and Medieval Civilizations project at Harvard University.",
        "location_precision": "precise",
        "title": "DARMC location 18260",
        "link": "http://pleiades.stoa.org/places/422852/darmc-location-18260"
      }
    }
  ]
}