{
  "type": "FeatureCollection",
  "title": "Bovillae",
  "id": "422852",
  "description": "A town of ancient Latium along the line of the Via Appia, Bovillae is traditionally considered to be a colony of Alba Longa and was one of the thirty cities of the Latin League.",
  "bbox": [
    12.617018,
    41.76587,
    12.617018,
    41.76587
  ],
  "connectsWith": [
    "356966898"
  ],
  "reprPoint": [
    12.617018,
    41.76587
  ],
  "names": [
    "Bovillae"
  ],
  "features": [
    {
      "geometry": {
        "type": "Point",
        "coordinates": [
          12.617018,
          41.76587
        ]
      },
      "id": "darmc-location-18260",
      "type": "Feature",
      "properties": {
        "description": "500K scale point location",
        "location_precision": "precise",
        "title": "DARMC location 18260",
        "link": "http://pleiades.stoa.org/places/422852/darmc-location-18260"
      }
    }
  ]
}