{
  "type": "FeatureCollection",
  "title": "Ceres et Faustina, T.",
  "id": "422889",
  "bbox": [
    12.524306,
    41.8577713,
    12.524434,
    41.857844
  ],
  "description": "The Roman temple dedicated to Ceres and Faustina received patronage from Herodes Atticus. Its remains were eventually repurposed in the construction of the church of Sant'Urbano.",
  "connectsWith": [
    "423025",
    "390922209"
  ],
  "names": [
    "Ceres et Faustina, T."
  ],
  "features": [
    {
      "type": "Feature",
      "geometry": {
        "type": "Point",
        "coordinates": [
          12.52437,
          41.85780765
        ]
      },
      "properties": {
        "description": "representative point"
      }
    },
    {
      "geometry": {
        "type": "Point",
        "coordinates": [
          12.524306,
          41.857844
        ]
      },
      "id": "dare-location",
      "type": "Feature",
      "properties": {
        "description": "Representative point location, site precision",
        "location_precision": "precise",
        "title": "DARE Location",
        "link": "http://pleiades.stoa.org/places/422889/dare-location"
      }
    },
    {
      "geometry": {
        "type": "Point",
        "coordinates": [
          12.524434,
          41.8577713
        ]
      },
      "id": "se-corner-santurbano",
      "type": "Feature",
      "properties": {
        "description": "Location based on OpenStreetMap, time periods following the Barrington.",
        "location_precision": "precise",
        "title": "SE Corner Sant'Urbano",
        "link": "http://pleiades.stoa.org/places/422889/se-corner-santurbano"
      }
    }
  ]
}