{
  "type": "FeatureCollection",
  "title": "Aeflanus (mountain)",
  "id": "422820",
  "bbox": [
    12.8079802,
    41.9315264,
    12.8208118,
    41.942205
  ],
  "description": "Colle Ripoli-Monte S. Angelo.",
  "names": [
    "Aeflanus"
  ],
  "features": [
    {
      "type": "Feature",
      "geometry": {
        "type": "Point",
        "coordinates": [
          12.814396,
          41.9368657
        ]
      },
      "properties": {
        "description": "representative point"
      }
    },
    {
      "geometry": {
        "type": "Point",
        "coordinates": [
          12.8079802,
          41.942205
        ]
      },
      "id": "location-of-colle-ripoli",
      "type": "Feature",
      "properties": {
        "description": "Location based on OpenStreetMap",
        "location_precision": "precise",
        "title": "OSM location of Colle Ripoli",
        "link": "http://pleiades.stoa.org/places/422820/location-of-colle-ripoli"
      }
    },
    {
      "geometry": {
        "type": "Point",
        "coordinates": [
          12.8208118,
          41.9315264
        ]
      },
      "id": "location-of-monte-s-angelo-in-arcese",
      "type": "Feature",
      "properties": {
        "description": "Location based on OpenStreetMap",
        "location_precision": "precise",
        "title": "OSM location of Monte S. Angelo in Arcese",
        "link": "http://pleiades.stoa.org/places/422820/location-of-monte-s-angelo-in-arcese"
      }
    }
  ]
}