{
  "type": "FeatureCollection",
  "title": "Ceres et Faustina, T.",
  "id": "422889",
  "description": "An ancient place, cited: BAtlas 43 C2 Ceres et Faustina, T.",
  "bbox": [
    12.524306,
    41.8577713,
    12.524434,
    41.857844
  ],
  "reprPoint": [
    12.52437,
    41.85780765
  ],
  "names": [
    "Ceres et Faustina, T."
  ],
  "features": [
    {
      "geometry": {
        "type": "Point",
        "coordinates": [
          12.524434,
          41.8577713
        ]
      },
      "id": "se-corner-santurbano",
      "type": "Feature",
      "properties": {
        "description": "Location based on OpenStreetMap, time periods following the Barrington.",
        "location_precision": "precise",
        "title": "SE Corner Sant'Urbano",
        "link": "http://pleiades.stoa.org/places/422889/se-corner-santurbano"
      }
    },
    {
      "geometry": {
        "type": "Point",
        "coordinates": [
          12.524306,
          41.857844
        ]
      },
      "id": "dare-location",
      "type": "Feature",
      "properties": {
        "description": "Representative point location, site precision",
        "location_precision": "precise",
        "title": "DARE Location",
        "link": "http://pleiades.stoa.org/places/422889/dare-location"
      }
    },
    {
      "geometry": {
        "type": "Point",
        "coordinates": [
          12.523693,
          41.859844
        ]
      },
      "id": "darmc-location-3787",
      "type": "Feature",
      "properties": {
        "description": "150K scale point location",
        "location_precision": "precise",
        "title": "DARMC location 3787",
        "link": "http://pleiades.stoa.org/places/422889/darmc-location-3787"
      }
    }
  ]
}