{
  "type": "FeatureCollection",
  "title": "Antium",
  "id": "422837",
  "bbox": [
    12.628995,
    41.44795,
    12.628995,
    41.44795
  ],
  "description": "Antium ranked as one of the most important and most powerful centers of Latium and was captured by Rome at the close of the Latin War in the fourth century B.C. Imperial Antium was well known for a number of coastal villas.",
  "connectsWith": [
    "966985945"
  ],
  "names": [
    "Antium",
    "Anzio"
  ],
  "features": [
    {
      "type": "Feature",
      "geometry": {
        "type": "Point",
        "coordinates": [
          12.628995,
          41.44795
        ]
      },
      "properties": {
        "description": "representative point"
      }
    },
    {
      "geometry": {
        "type": "Point",
        "coordinates": [
          12.628995,
          41.44795
        ]
      },
      "id": "darmc-location-6943",
      "type": "Feature",
      "properties": {
        "description": "500K scale point location",
        "location_precision": "precise",
        "title": "DARMC location 6943",
        "link": "http://pleiades.stoa.org/places/422837/darmc-location-6943"
      }
    }
  ]
}