{
  "type": "FeatureCollection",
  "title": "Castel Savello",
  "id": "422884",
  "bbox": [
    12.63662,
    41.72277,
    12.637511,
    41.723909
  ],
  "description": "Castel Savello takes its name from a fifteenth-century fortress of the Savelli family at Albano Laziale. Funerary evidence associated with the Latial culture has been documented here.",
  "features": [
    {
      "type": "Feature",
      "geometry": {
        "type": "Point",
        "coordinates": [
          12.6370655,
          41.7233395
        ]
      },
      "properties": {
        "description": "representative point"
      }
    },
    {
      "geometry": {
        "type": "Point",
        "coordinates": [
          12.63662,
          41.72277
        ]
      },
      "id": "imagery-location-of-monte-savello",
      "type": "Feature",
      "properties": {
        "description": "Coordinates following GeoNames",
        "location_precision": "precise",
        "title": "Imagery location of Monte Savello",
        "link": "http://pleiades.stoa.org/places/422884/imagery-location-of-monte-savello"
      }
    },
    {
      "geometry": {
        "type": "Point",
        "coordinates": [
          12.637511,
          41.723909
        ]
      },
      "id": "darmc-location-18314",
      "type": "Feature",
      "properties": {
        "description": "1:150,000 scale representative point location digitized from the Barrington Atlas of the Greek and Roman World by the Digital Atlas of Roman and Medieval Civilizations project at Harvard University.",
        "location_precision": "precise",
        "title": "DARMC location 18314",
        "link": "http://pleiades.stoa.org/places/422884/darmc-location-18314"
      }
    }
  ]
}