{
  "type": "FeatureCollection",
  "title": "Ad Sponsas",
  "id": "422816",
  "description": "An ancient place, cited: BAtlas 43 D3 Ad Sponsas",
  "bbox": [
    12.84611,
    41.58389,
    12.84611,
    41.58389
  ],
  "connectsWith": [
    "356966898"
  ],
  "reprPoint": [
    12.84611,
    41.58389
  ],
  "names": [
    "Ad Sponsas"
  ],
  "features": [
    {
      "geometry": {
        "type": "Point",
        "coordinates": [
          12.84611,
          41.58389
        ]
      },
      "id": "dare-location",
      "type": "Feature",
      "properties": {
        "description": "Representative point location, village precision",
        "location_precision": "precise",
        "title": "DARE Location",
        "link": "http://pleiades.stoa.org/places/422816/dare-location"
      }
    },
    {
      "geometry": {
        "type": "Point",
        "coordinates": [
          12.766882,
          41.641985
        ]
      },
      "id": "darmc-location-7317",
      "type": "Feature",
      "properties": {
        "description": "150K scale point location",
        "location_precision": "precise",
        "title": "DARMC location 7317",
        "link": "http://pleiades.stoa.org/places/422816/darmc-location-7317"
      }
    }
  ]
}