{
  "type": "FeatureCollection",
  "title": "Iuppiter Latiaris, T.",
  "id": "422949",
  "description": "An important Latial sanctuary of Iuppiter located on Mons Albanus (modern Monte Cavo).",
  "bbox": [
    12.709346,
    41.750158,
    12.709346,
    41.750158
  ],
  "connectsWith": [
    "f05adb955aebbd21c9cf17cd6d9fd75a"
  ],
  "reprPoint": [
    12.709346,
    41.750158
  ],
  "names": [
    "Iuppiter Latiaris, T."
  ],
  "features": [
    {
      "geometry": {
        "type": "Point",
        "coordinates": [
          12.709346,
          41.750158
        ]
      },
      "id": "darmc-location-20582",
      "type": "Feature",
      "properties": {
        "description": "150K scale point location",
        "location_precision": "precise",
        "title": "DARMC location 20582",
        "link": "http://pleiades.stoa.org/places/422949/darmc-location-20582"
      }
    }
  ]
}