{
  "type": "FeatureCollection",
  "title": "Fortis Fortuna, T.",
  "id": "422925",
  "description": "An ancient place, cited: BAtlas 43 B2 Fortis Fortuna, T.",
  "bbox": [
    12.480443,
    41.8891,
    12.480883,
    41.889232
  ],
  "reprPoint": [
    12.480663,
    41.889166
  ],
  "names": [
    "Fortis Fortuna, T."
  ],
  "features": [
    {
      "geometry": {
        "type": "Point",
        "coordinates": [
          12.480883,
          41.889232
        ]
      },
      "id": "dare-location",
      "type": "Feature",
      "properties": {
        "description": "Representative point location, site precision",
        "location_precision": "precise",
        "title": "DARE Location",
        "link": "http://pleiades.stoa.org/places/422925/dare-location"
      }
    },
    {
      "geometry": {
        "type": "Point",
        "coordinates": [
          12.480443,
          41.8891
        ]
      },
      "id": "darmc-location-20564",
      "type": "Feature",
      "properties": {
        "description": "150K scale point location",
        "location_precision": "precise",
        "title": "DARMC location 20564",
        "link": "http://pleiades.stoa.org/places/422925/darmc-location-20564"
      }
    }
  ]
}