{
  "type": "FeatureCollection",
  "title": "Marina di S. Nicola",
  "id": "422970",
  "description": "An ancient place, cited: BAtlas 43 A2 Marina di S. Nicola",
  "bbox": [
    12.125131,
    41.926479,
    12.125213,
    41.926517
  ],
  "reprPoint": [
    12.1251856667,
    41.9265043333
  ],
  "features": [
    {
      "geometry": {
        "type": "Point",
        "coordinates": [
          12.125131,
          41.926479
        ]
      },
      "id": "darmc-location-7791",
      "type": "Feature",
      "properties": {
        "description": "500K scale point location",
        "location_precision": "precise",
        "title": "DARMC location 7791",
        "link": "http://pleiades.stoa.org/places/422970/darmc-location-7791"
      }
    },
    {
      "geometry": {
        "type": "Point",
        "coordinates": [
          12.125213,
          41.926517
        ]
      },
      "id": "darmc-location-7805",
      "type": "Feature",
      "properties": {
        "description": "150K scale point location",
        "location_precision": "precise",
        "title": "DARMC location 7805",
        "link": "http://pleiades.stoa.org/places/422970/darmc-location-7805"
      }
    },
    {
      "geometry": {
        "type": "Point",
        "coordinates": [
          12.125213,
          41.926517
        ]
      },
      "id": "darmc-location-20990",
      "type": "Feature",
      "properties": {
        "description": "150K scale point location",
        "location_precision": "precise",
        "title": "DARMC location 20990",
        "link": "http://pleiades.stoa.org/places/422970/darmc-location-20990"
      }
    }
  ]
}