{
  "type": "FeatureCollection",
  "title": "La Colombella",
  "id": "422907",
  "description": "An ancient place, cited: BAtlas 43 D2 La Colombella",
  "bbox": [
    12.892944,
    41.830237,
    12.892944,
    41.830237
  ],
  "reprPoint": [
    12.892944,
    41.830237
  ],
  "features": [
    {
      "geometry": {
        "type": "Point",
        "coordinates": [
          12.892944,
          41.830237
        ]
      },
      "id": "darmc-location-23163",
      "type": "Feature",
      "properties": {
        "description": "Point location",
        "location_precision": "precise",
        "title": "DARMC location 23163",
        "link": "http://pleiades.stoa.org/places/422907/darmc-location-23163"
      }
    }
  ]
}