{
  "type": "FeatureCollection",
  "title": "Diana, T.",
  "id": "422917",
  "description": "A site sacred to Diana near Lake Nemi, comprised of a Tuscan-style sanctuary and a sacred grove.",
  "bbox": [
    12.710217,
    41.723936,
    12.710217,
    41.723936
  ],
  "reprPoint": [
    12.710217,
    41.723936
  ],
  "names": [
    "Diana, T."
  ],
  "features": [
    {
      "geometry": {
        "type": "Point",
        "coordinates": [
          12.710217,
          41.723936
        ]
      },
      "id": "dare-location",
      "type": "Feature",
      "properties": {
        "description": "Representative point location, site precision",
        "location_precision": "precise",
        "title": "DARE Location",
        "link": "http://pleiades.stoa.org/places/422917/dare-location"
      }
    },
    {
      "geometry": {
        "type": "Point",
        "coordinates": [
          12.710195,
          41.718555
        ]
      },
      "id": "darmc-location-7655",
      "type": "Feature",
      "properties": {
        "description": "150K scale point location",
        "location_precision": "precise",
        "title": "DARMC location 7655",
        "link": "http://pleiades.stoa.org/places/422917/darmc-location-7655"
      }
    }
  ]
}