{
  "type": "FeatureCollection",
  "title": "Crustumerium",
  "id": "422914",
  "bbox": [
    12.527692,
    42.017205,
    12.527692,
    42.017205
  ],
  "description": "An ancient town of Latium located at the headwaters of the Allia river, very close to the territory of the Sabines, Crustumerium figures in Rome's early history. The Romans conquered the site in 500 B.C. and formed the tribus Crustumina or Clustumina in 471 B.C.",
  "connectsWith": [
    "485712934"
  ],
  "names": [
    "Crustumerium"
  ],
  "features": [
    {
      "type": "Feature",
      "geometry": {
        "type": "Point",
        "coordinates": [
          12.527692,
          42.017205
        ]
      },
      "properties": {
        "description": "representative point"
      }
    },
    {
      "geometry": {
        "type": "Point",
        "coordinates": [
          12.527692,
          42.017205
        ]
      },
      "id": "darmc-location-18391",
      "type": "Feature",
      "properties": {
        "description": "500K scale point location",
        "location_precision": "precise",
        "title": "DARMC location 18391",
        "link": "http://pleiades.stoa.org/places/422914/darmc-location-18391"
      }
    }
  ]
}