{
  "type": "FeatureCollection",
  "title": "Magliana Vecchia",
  "id": "422968",
  "bbox": [
    12.4039,
    41.82597,
    12.4039,
    41.82597
  ],
  "description": "An ancient place, cited: BAtlas 43 B2 Magliana Vecchia",
  "features": [
    {
      "type": "Feature",
      "geometry": {
        "type": "Point",
        "coordinates": [
          12.4039,
          41.82597
        ]
      },
      "properties": {
        "description": "representative point"
      }
    },
    {
      "geometry": {
        "type": "Point",
        "coordinates": [
          12.4039,
          41.82597
        ]
      },
      "id": "geonames-location-of-magliana-vecchia",
      "type": "Feature",
      "properties": {
        "description": "Location of the modern administrative subdivision derived from GeoNames.",
        "location_precision": "precise",
        "title": "GeoNames location of Magliana Vecchia",
        "link": "http://pleiades.stoa.org/places/422968/geonames-location-of-magliana-vecchia"
      }
    }
  ]
}