{
  "type": "FeatureCollection",
  "title": "Fortis Fortuna, T.",
  "id": "422925",
  "bbox": [
    12.486137,
    41.891775,
    12.486137,
    41.891775
  ],
  "description": "A sanctuary of Fors Fortuna in Trastevere. Varro ascribes its foundation to Servius Tullius.",
  "connectsWith": [
    "423025"
  ],
  "names": [
    "Fortis Fortuna, T."
  ],
  "features": [
    {
      "type": "Feature",
      "geometry": {
        "type": "Point",
        "coordinates": [
          12.486137,
          41.891775
        ]
      },
      "properties": {
        "description": "representative point"
      }
    }
  ]
}