{
  "type": "FeatureCollection",
  "title": "Largo Preneste",
  "id": "422957",
  "bbox": [
    12.541577,
    41.892546,
    12.541577,
    41.892546
  ],
  "description": "An ancient place, cited: BAtlas 43 C2 Largo Preneste",
  "features": [
    {
      "type": "Feature",
      "geometry": {
        "type": "Point",
        "coordinates": [
          12.541577,
          41.892546
        ]
      },
      "properties": {
        "description": "representative point"
      }
    },
    {
      "geometry": {
        "type": "Point",
        "coordinates": [
          12.541577,
          41.892546
        ]
      },
      "id": "darmc-location-23766",
      "type": "Feature",
      "properties": {
        "description": "Point location",
        "location_precision": "precise",
        "title": "DARMC location 23766",
        "link": "http://pleiades.stoa.org/places/422957/darmc-location-23766"
      }
    }
  ]
}