{
  "type": "FeatureCollection",
  "title": "Gordiani",
  "id": "422936",
  "description": "A third century AD villa complex along the Via Praenestina connected with Gordian I, Gordian II, and Gordian III.",
  "bbox": [
    12.553769,
    41.894164,
    12.553769,
    41.894164
  ],
  "connectsWith": [
    "423025",
    "622606468"
  ],
  "reprPoint": [
    12.553769,
    41.894164
  ],
  "names": [
    "Gordiani"
  ],
  "features": [
    {
      "geometry": {
        "type": "Point",
        "coordinates": [
          12.553769,
          41.894164
        ]
      },
      "id": "dare-location",
      "type": "Feature",
      "properties": {
        "description": "Representative point location, site precision",
        "location_precision": "precise",
        "title": "DARE Location",
        "link": "http://pleiades.stoa.org/places/422936/dare-location"
      }
    },
    {
      "geometry": {
        "type": "Point",
        "coordinates": [
          12.553035,
          41.894991
        ]
      },
      "id": "darmc-location-20884",
      "type": "Feature",
      "properties": {
        "description": "150K scale point location",
        "location_precision": "precise",
        "title": "DARMC location 20884",
        "link": "http://pleiades.stoa.org/places/422936/darmc-location-20884"
      }
    }
  ]
}