{
  "type": "FeatureCollection",
  "title": "Marina di S. Nicola",
  "id": "422970",
  "bbox": [
    12.1254406,
    41.9266459,
    12.1254406,
    41.9266459
  ],
  "description": "Marina di S. Nicola is located close to Alsium.",
  "features": [
    {
      "type": "Feature",
      "geometry": {
        "type": "Point",
        "coordinates": [
          12.1254406,
          41.9266459
        ]
      },
      "properties": {
        "description": "representative point"
      }
    },
    {
      "geometry": {
        "type": "Point",
        "coordinates": [
          12.1254406,
          41.9266459
        ]
      },
      "id": "osm-location-of-villa-di-pompeo",
      "type": "Feature",
      "properties": {
        "description": "Representative point derived from an OpenStreetMap node",
        "location_precision": "precise",
        "title": "OSM location of Villa di Pompeo",
        "link": "http://pleiades.stoa.org/places/422970/osm-location-of-villa-di-pompeo"
      }
    }
  ]
}