{
  "type": "FeatureCollection",
  "title": "Crustumerium",
  "id": "422914",
  "bbox": [
    12.550061,
    42.0150826,
    12.550061,
    42.0150826
  ],
  "description": "An ancient town of Latium located at the headwaters of the Allia river, very close to the territory of the Sabines, Crustumerium figures in Rome's early history. The Romans conquered the site in 500 B.C. and formed the tribus Crustumina or Clustumina in 471 B.C.",
  "connectsWith": [
    "485712934"
  ],
  "names": [
    "Crustumerium",
    "Crustumini"
  ],
  "features": [
    {
      "type": "Feature",
      "geometry": {
        "type": "Point",
        "coordinates": [
          12.550061,
          42.0150826
        ]
      },
      "properties": {
        "description": "representative point"
      }
    },
    {
      "geometry": {
        "type": "Point",
        "coordinates": [
          12.550061,
          42.0150826
        ]
      },
      "id": "osm-location-of-crustumerium",
      "type": "Feature",
      "properties": {
        "description": "Representative location based on OpenStreetMap.",
        "location_precision": "precise",
        "title": "OSM location of Crustumerium",
        "link": "http://pleiades.stoa.org/places/422914/osm-location-of-crustumerium"
      }
    }
  ]
}