{
  "type": "FeatureCollection",
  "title": "Fidenae",
  "id": "422923",
  "description": "Fidenae was an ancient city of Latium.",
  "bbox": [
    12.515431,
    41.982053,
    12.515431,
    41.982053
  ],
  "connectsWith": [
    "423080",
    "18271457"
  ],
  "reprPoint": [
    12.515431,
    41.982053
  ],
  "names": [
    "Fidenae"
  ],
  "features": [
    {
      "geometry": {
        "type": "Point",
        "coordinates": [
          12.515431,
          41.982053
        ]
      },
      "id": "darmc-location-18438",
      "type": "Feature",
      "properties": {
        "description": "500K scale point location",
        "location_precision": "precise",
        "title": "DARMC location 18438",
        "link": "http://pleiades.stoa.org/places/422923/darmc-location-18438"
      }
    }
  ]
}