{
  "type": "FeatureCollection",
  "title": "Colle Monitola",
  "id": "422901",
  "description": "An ancient place, cited: BAtlas 43 D2 Colle Monitola",
  "bbox": [
    12.828621,
    41.953118,
    12.828621,
    41.953118
  ],
  "reprPoint": [
    12.828621,
    41.953118
  ],
  "features": [
    {
      "geometry": {
        "type": "Point",
        "coordinates": [
          12.828621,
          41.953118
        ]
      },
      "id": "darmc-location-18362",
      "type": "Feature",
      "properties": {
        "description": "150K scale point location",
        "location_precision": "precise",
        "title": "DARMC location 18362",
        "link": "http://pleiades.stoa.org/places/422901/darmc-location-18362"
      }
    }
  ]
}