{
  "type": "FeatureCollection",
  "title": "Marina di S. Nicola",
  "id": "422970",
  "description": "An ancient place, cited: BAtlas 43 A2 Marina di S. Nicola",
  "bbox": [
    12.125131,
    41.926479,
    12.1254406,
    41.9266459
  ],
  "reprPoint": [
    12.1252494,
    41.926539725
  ],
  "features": [
    {
      "geometry": {
        "type": "Point",
        "coordinates": [
          12.125131,
          41.926479
        ]
      },
      "id": "darmc-location-7791",
      "type": "Feature",
      "properties": {
        "description": "500K scale point location",
        "location_precision": "precise",
        "title": "DARMC location 7791",
        "link": "http://pleiades.stoa.org/places/422970/darmc-location-7791"
      }
    },
    {
      "geometry": {
        "type": "Point",
        "coordinates": [
          12.125213,
          41.926517
        ]
      },
      "id": "darmc-location-7805",
      "type": "Feature",
      "properties": {
        "description": "150K scale point location",
        "location_precision": "precise",
        "title": "DARMC location 7805",
        "link": "http://pleiades.stoa.org/places/422970/darmc-location-7805"
      }
    },
    {
      "geometry": {
        "type": "Point",
        "coordinates": [
          12.125213,
          41.926517
        ]
      },
      "id": "darmc-location-20990",
      "type": "Feature",
      "properties": {
        "description": "150K scale point location",
        "location_precision": "precise",
        "title": "DARMC location 20990",
        "link": "http://pleiades.stoa.org/places/422970/darmc-location-20990"
      }
    },
    {
      "geometry": {
        "type": "Point",
        "coordinates": [
          12.1254406,
          41.9266459
        ]
      },
      "id": "osm-location-of-villa-di-pompeo",
      "type": "Feature",
      "properties": {
        "description": "Representative point derived from an OpenStreetMap node",
        "location_precision": "precise",
        "title": "OSM location of Villa di Pompeo",
        "link": "http://pleiades.stoa.org/places/422970/osm-location-of-villa-di-pompeo"
      }
    }
  ]
}