{
  "type": "FeatureCollection",
  "title": "Pedum?",
  "id": "422997",
  "bbox": [
    12.736281,
    41.910022,
    12.736281,
    41.910022
  ],
  "description": "An ancient place, cited: BAtlas 43 D2 Pedum?",
  "names": [
    "Pedum"
  ],
  "features": [
    {
      "type": "Feature",
      "geometry": {
        "type": "Point",
        "coordinates": [
          12.736281,
          41.910022
        ]
      },
      "properties": {
        "description": "representative point"
      }
    },
    {
      "geometry": {
        "type": "Point",
        "coordinates": [
          12.736281,
          41.910022
        ]
      },
      "id": "darmc-location-18738",
      "type": "Feature",
      "properties": {
        "description": "150K scale point location",
        "location_precision": "precise",
        "title": "DARMC location 18738",
        "link": "http://pleiades.stoa.org/places/422997/darmc-location-18738"
      }
    }
  ]
}