{
  "type": "FeatureCollection",
  "title": "Labicum",
  "id": "422952",
  "description": "Originally a member of the Latin League, the city of Labicum was taken by the Romans ca. 418 B.C. By the time of Augustus, the site was almost certainly deserted and its precise location remains debated today.",
  "bbox": [
    12.736409,
    41.80752,
    12.75,
    41.833333
  ],
  "connectsWith": [
    "74935822"
  ],
  "reprPoint": [
    12.7432045,
    41.8204265
  ],
  "names": [
    "Labicum"
  ],
  "features": [
    {
      "geometry": {
        "type": "Point",
        "coordinates": [
          12.736409,
          41.80752
        ]
      },
      "id": "dare-location",
      "type": "Feature",
      "properties": {
        "description": "Representative point location, village precision",
        "location_precision": "precise",
        "title": "DARE Location",
        "link": "http://pleiades.stoa.org/places/422952/dare-location"
      }
    },
    {
      "geometry": {
        "type": "Point",
        "coordinates": [
          12.75,
          41.833333
        ]
      },
      "id": "location-of-colonna-lazio",
      "type": "Feature",
      "properties": {
        "description": "Coordinates after GeoHack represent a point location for the modern site of Colonna, Lazio, considered by some scholars as the possible site of ancient Labicum",
        "location_precision": "precise",
        "title": "Imagery location of modern Colonna, Lazio",
        "link": "http://pleiades.stoa.org/places/422952/location-of-colonna-lazio"
      }
    }
  ]
}