{
  "type": "FeatureCollection",
  "title": "Labicum",
  "id": "422952",
  "description": "Originally a member of the Latin League, the city of Labicum was taken by the Romans ca. 418 BC. By the time of Augustus, the site was almost certainly deserted and its precise location remains debated today.",
  "bbox": [
    12.736409,
    41.80752,
    12.736409,
    41.80752
  ],
  "connectsWith": [
    "74935822"
  ],
  "reprPoint": [
    12.736409,
    41.80752
  ],
  "names": [
    "Labicum"
  ],
  "features": [
    {
      "geometry": {
        "type": "Point",
        "coordinates": [
          12.736409,
          41.80752
        ]
      },
      "id": "dare-location",
      "type": "Feature",
      "properties": {
        "description": "Representative point location, village precision",
        "location_precision": "precise",
        "title": "DARE Location",
        "link": "http://pleiades.stoa.org/places/422952/dare-location"
      }
    },
    {
      "geometry": {
        "type": "Point",
        "coordinates": [
          12.752837,
          41.834147
        ]
      },
      "id": "darmc-location-28504",
      "type": "Feature",
      "properties": {
        "description": "150K scale point location",
        "location_precision": "precise",
        "title": "DARMC location 28504",
        "link": "http://pleiades.stoa.org/places/422952/darmc-location-28504"
      }
    }
  ]
}