{
  "type": "FeatureCollection",
  "title": "Fidenae",
  "id": "422923",
  "bbox": [
    12.515431,
    41.982053,
    12.515431,
    41.982053
  ],
  "description": "Fidenae was an ancient city of Latium.",
  "connectsWith": [
    "423080",
    "18271457"
  ],
  "names": [
    "Fidenae",
    "Phidenai",
    "Fidenates"
  ],
  "features": [
    {
      "type": "Feature",
      "geometry": {
        "type": "Point",
        "coordinates": [
          12.515431,
          41.982053
        ]
      },
      "properties": {
        "description": "representative point"
      }
    },
    {
      "geometry": {
        "type": "Point",
        "coordinates": [
          12.515431,
          41.982053
        ]
      },
      "id": "darmc-location-18438",
      "type": "Feature",
      "properties": {
        "description": "1:500,000 scale representative point location digitized from the Barrington Atlas of the Greek and Roman World by the Digital Atlas of Roman and Medieval Civilizations project at Harvard University.",
        "location_precision": "precise",
        "title": "DARMC location 18438",
        "link": "http://pleiades.stoa.org/places/422923/darmc-location-18438"
      }
    }
  ]
}