{
  "type": "FeatureCollection",
  "title": "Prima Porta",
  "id": "423015",
  "description": "An ancient place, cited: BAtlas 43 B1 Prima Porta",
  "bbox": [
    12.491225,
    42.001046,
    12.4925,
    42.002778
  ],
  "reprPoint": [
    12.4918625,
    42.001912
  ],
  "features": [
    {
      "geometry": {
        "type": "Point",
        "coordinates": [
          12.4925,
          42.002778
        ]
      },
      "id": "dare-location",
      "type": "Feature",
      "properties": {
        "description": "Representative point location, site precision",
        "location_precision": "precise",
        "title": "DARE Location",
        "link": "http://pleiades.stoa.org/places/423015/dare-location"
      }
    },
    {
      "geometry": {
        "type": "Point",
        "coordinates": [
          12.491225,
          42.001046
        ]
      },
      "id": "darmc-location-21046",
      "type": "Feature",
      "properties": {
        "description": "150K scale point location",
        "location_precision": "precise",
        "title": "DARMC location 21046",
        "link": "http://pleiades.stoa.org/places/423015/darmc-location-21046"
      }
    }
  ]
}