{
  "type": "FeatureCollection",
  "title": "Il Tondo",
  "id": "423086",
  "description": "An ancient place, cited: BAtlas 43 D2 Il Tondo",
  "bbox": [
    12.822996,
    41.855772,
    12.822996,
    41.855772
  ],
  "reprPoint": [
    12.822996,
    41.855772
  ],
  "features": [
    {
      "geometry": {
        "type": "Point",
        "coordinates": [
          12.822996,
          41.855772
        ]
      },
      "id": "darmc-location-20930",
      "type": "Feature",
      "properties": {
        "description": "150K scale point location",
        "location_precision": "precise",
        "title": "DARMC location 20930",
        "link": "http://pleiades.stoa.org/places/423086/darmc-location-20930"
      }
    }
  ]
}