{
  "type": "FeatureCollection",
  "title": "Saxa Rubra",
  "id": "423061",
  "description": "Saxa Rubra (modern Grottarossa) is the name of a road station on the Via Flaminia nine Roman miles from the center of ancient Rome. It was at Saxa Rubra that Constantine I defeated Maxentius in AD 312.",
  "bbox": [
    12.478409,
    41.975827,
    12.478409,
    41.975827
  ],
  "connectsWith": [
    "856514595"
  ],
  "reprPoint": [
    12.478409,
    41.975827
  ],
  "names": [
    "Saxa Rubra"
  ],
  "features": [
    {
      "geometry": {
        "type": "Point",
        "coordinates": [
          12.478409,
          41.975827
        ]
      },
      "id": "location-of-grottarossa",
      "type": "Feature",
      "properties": {
        "description": "coordinates after GeoHack.",
        "location_precision": "precise",
        "title": "location of Grottarossa",
        "link": "http://pleiades.stoa.org/places/423061/location-of-grottarossa"
      }
    }
  ]
}