{
  "type": "FeatureCollection",
  "title": "S. Vincenzo",
  "id": "423059",
  "description": "An ancient place, cited: BAtlas 43 D1 S. Vincenzo",
  "bbox": [
    12.760644,
    42.012051,
    12.760644,
    42.012051
  ],
  "reprPoint": [
    12.760644,
    42.012051
  ],
  "features": [
    {
      "geometry": {
        "type": "Point",
        "coordinates": [
          12.760644,
          42.012051
        ]
      },
      "id": "darmc-location-23161",
      "type": "Feature",
      "properties": {
        "description": "Point location",
        "location_precision": "precise",
        "title": "DARMC location 23161",
        "link": "http://pleiades.stoa.org/places/423059/darmc-location-23161"
      }
    }
  ]
}