{
  "type": "FeatureCollection",
  "title": "Prima Porta",
  "id": "423015",
  "bbox": [
    12.491225,
    42.001046,
    12.4925,
    42.002778
  ],
  "description": "Prima Porta, located to the north of Rome, allegedly derives its modern name from the remains of a Roman aqueduct whose presence signaled to travelers on the Via Flaminia that they had reached Rome. The site is best known for an Imperial villa that belonged to the family of Livia Drusilla.",
  "connectsWith": [
    "422809",
    "699782783"
  ],
  "features": [
    {
      "type": "Feature",
      "geometry": {
        "type": "Point",
        "coordinates": [
          12.4918625,
          42.001912
        ]
      },
      "properties": {
        "description": "representative point"
      }
    },
    {
      "geometry": {
        "type": "Point",
        "coordinates": [
          12.491225,
          42.001046
        ]
      },
      "id": "darmc-location-21046",
      "type": "Feature",
      "properties": {
        "description": "1:150,000 scale representative point location digitized from the Barrington Atlas of the Greek and Roman World by the Digital Atlas of Roman and Medieval Civilizations project at Harvard University.",
        "location_precision": "precise",
        "title": "DARMC location 21046",
        "link": "http://pleiades.stoa.org/places/423015/darmc-location-21046"
      }
    },
    {
      "geometry": {
        "type": "Point",
        "coordinates": [
          12.4925,
          42.002778
        ]
      },
      "id": "dare-location",
      "type": "Feature",
      "properties": {
        "description": "Representative point location, site precision",
        "location_precision": "precise",
        "title": "DARE Location",
        "link": "http://pleiades.stoa.org/places/423015/dare-location"
      }
    }
  ]
}