{
  "type": "FeatureCollection",
  "title": "S. Callisto",
  "id": "423038",
  "description": "A large catacomb on the Via Appia south of Rome notable especially for its so-called 'Crypt of the Popes'.  The catacomb covers approximately 15 hectares.",
  "bbox": [
    12.510677,
    41.858916,
    12.510677,
    41.858916
  ],
  "connectsWith": [
    "356966898",
    "423025",
    "356966898",
    "423025"
  ],
  "reprPoint": [
    12.510677,
    41.858916
  ],
  "names": [
    "Catacomb of Callixtus"
  ],
  "features": [
    {
      "geometry": {
        "type": "Point",
        "coordinates": [
          12.510677,
          41.858916
        ]
      },
      "id": "dare-location",
      "type": "Feature",
      "properties": {
        "description": "Representative point location, site precision",
        "location_precision": "precise",
        "title": "DARE Location",
        "link": "http://pleiades.stoa.org/places/423038/dare-location"
      }
    }
  ]
}