{
  "type": "FeatureCollection",
  "title": "Villa Torlonia",
  "id": "423133",
  "bbox": [
    12.512,
    41.914,
    12.512,
    41.914
  ],
  "description": "A Jewish catacomb discovered in 1919 on the grounds of the Villa Torlonia park in Rome.",
  "connectsWith": [
    "423025"
  ],
  "features": [
    {
      "type": "Feature",
      "geometry": {
        "type": "Point",
        "coordinates": [
          12.512,
          41.914
        ]
      },
      "properties": {
        "description": "representative point"
      }
    },
    {
      "geometry": {
        "type": "Point",
        "coordinates": [
          12.512,
          41.914
        ]
      },
      "id": "dare-location",
      "type": "Feature",
      "properties": {
        "description": "Representative point location, village precision",
        "location_precision": "precise",
        "title": "DARE Location",
        "link": "http://pleiades.stoa.org/places/423133/dare-location"
      }
    }
  ]
}