{
  "type": "FeatureCollection",
  "title": "Via delle Piagge",
  "id": "423119",
  "description": "An ancient place, cited: BAtlas 43 D2 Via delle Piagge",
  "bbox": [
    12.786854,
    41.956104,
    12.786854,
    41.956104
  ],
  "reprPoint": [
    12.786854,
    41.956104
  ],
  "features": [
    {
      "geometry": {
        "type": "Point",
        "coordinates": [
          12.786854,
          41.956104
        ]
      },
      "id": "darmc-location-21184",
      "type": "Feature",
      "properties": {
        "description": "150K scale point location",
        "location_precision": "precise",
        "title": "DARMC location 21184",
        "link": "http://pleiades.stoa.org/places/423119/darmc-location-21184"
      }
    }
  ]
}