{
  "type": "FeatureCollection",
  "title": "Villa Hadriani",
  "id": "423127",
  "description": "The Villa of Hadrian (Villa Adriana in Italian) is a sprawling archaeological complex at Tivoli, Italy. The villa complex was designed and used by the emperor Hadrian in the second century A.D.",
  "bbox": [
    12.775887,
    41.942344,
    12.775887,
    41.942344
  ],
  "reprPoint": [
    12.775887,
    41.942344
  ],
  "names": [
    "Villa Hadriani"
  ],
  "features": [
    {
      "geometry": {
        "type": "Point",
        "coordinates": [
          12.775887,
          41.942344
        ]
      },
      "id": "darmc-location-7988",
      "type": "Feature",
      "properties": {
        "description": "500K scale point location",
        "location_precision": "precise",
        "title": "DARMC location 7988",
        "link": "http://pleiades.stoa.org/places/423127/darmc-location-7988"
      }
    }
  ]
}