{
  "type": "FeatureCollection",
  "title": "Veii",
  "id": "423116",
  "bbox": [
    12.390519,
    42.021338,
    12.390519,
    42.021338
  ],
  "description": "An important city of South Etruria located north-northwest of Rome, Veii was eventually sacked by the Romans in 396 B.C. The ancient city covered some 180 ha.",
  "connectsWith": [
    "413122",
    "690508612",
    "774612717",
    "222169303",
    "963165127",
    "699782783"
  ],
  "names": [
    "Veii",
    "Veio",
    "Beientia",
    "Ouioi",
    "Vei(s)"
  ],
  "features": [
    {
      "type": "Feature",
      "geometry": {
        "type": "Point",
        "coordinates": [
          12.390519,
          42.021338
        ]
      },
      "properties": {
        "description": "representative point"
      }
    },
    {
      "geometry": {
        "type": "Point",
        "coordinates": [
          12.390519,
          42.021338
        ]
      },
      "id": "darmc-location-18991",
      "type": "Feature",
      "properties": {
        "description": "1:500,000 scale representative point location digitized from the Barrington Atlas of the Greek and Roman World by the Digital Atlas of Roman and Medieval Civilizations project at Harvard University.",
        "location_precision": "precise",
        "title": "DARMC location 18991",
        "link": "http://pleiades.stoa.org/places/423116/darmc-location-18991"
      }
    }
  ]
}