{
  "type": "FeatureCollection",
  "title": "Villamagna",
  "id": "423135",
  "description": "A large imperial Roman villa known from letters of Marcus Aurelius (cited BAtlas 43 E3 Villamagna)",
  "bbox": [
    13.111941,
    41.683288,
    13.111941,
    41.683288
  ],
  "reprPoint": [
    13.111941,
    41.683288
  ],
  "features": [
    {
      "geometry": {
        "type": "Point",
        "coordinates": [
          13.111941,
          41.683288
        ]
      },
      "id": "darmc-location-21147",
      "type": "Feature",
      "properties": {
        "description": "150K scale point location",
        "location_precision": "precise",
        "title": "DARMC location 21147",
        "link": "http://pleiades.stoa.org/places/423135/darmc-location-21147"
      }
    }
  ]
}