{
  "type": "FeatureCollection",
  "title": "Veii",
  "id": "423116",
  "description": "An important city of South Etruria located north-northwest of Rome, Veii was eventually sacked by the Romans in 396 B.C. The ancient city covered some 180 ha.",
  "bbox": [
    12.390519,
    42.021338,
    12.390519,
    42.021338
  ],
  "connectsWith": [
    "413122",
    "690508612"
  ],
  "reprPoint": [
    12.390519,
    42.021338
  ],
  "names": [
    "Veii",
    "Veio"
  ],
  "features": [
    {
      "geometry": {
        "type": "Point",
        "coordinates": [
          12.390519,
          42.021338
        ]
      },
      "id": "darmc-location-18991",
      "type": "Feature",
      "properties": {
        "description": "500K scale point location",
        "location_precision": "precise",
        "title": "DARMC location 18991",
        "link": "http://pleiades.stoa.org/places/423116/darmc-location-18991"
      }
    }
  ]
}