{
  "type": "FeatureCollection",
  "title": "Villa Pamphili",
  "id": "423132",
  "description": "The church of San Pancrazio was founded in the sixth century A.D. by Pope Symmachus. It stands beyond the Porta San Pancrazio on the Ianiculum. Below the church is a massive catacomb referred to as S. Pancrazio or Ottavilla. ",
  "bbox": [
    12.453964,
    41.884696,
    12.4540933,
    41.884968
  ],
  "connectsWith": [
    "423025"
  ],
  "reprPoint": [
    12.45402865,
    41.884832
  ],
  "features": [
    {
      "geometry": {
        "type": "Point",
        "coordinates": [
          12.453964,
          41.884968
        ]
      },
      "id": "dare-location",
      "type": "Feature",
      "properties": {
        "description": "Representative point location for the Basilica e Catacombe di San Pancrazio, site precision.",
        "location_precision": "precise",
        "title": "DARE Location",
        "link": "http://pleiades.stoa.org/places/423132/dare-location"
      }
    },
    {
      "geometry": {
        "type": "Point",
        "coordinates": [
          12.4540933,
          41.884696
        ]
      },
      "id": "location-of-basilica-di-san-pancrazio",
      "type": "Feature",
      "properties": {
        "description": "Representative location based on OpenStreetMap.",
        "location_precision": "precise",
        "title": "OSM location of Basilica di San Pancrazio",
        "link": "http://pleiades.stoa.org/places/423132/location-of-basilica-di-san-pancrazio"
      }
    }
  ]
}