{
  "type": "FeatureCollection",
  "title": "Torre Sessano",
  "id": "423101",
  "bbox": [
    12.859575,
    41.508429,
    12.859575,
    41.508429
  ],
  "description": "An ancient place, cited: BAtlas 43 D3 Torre Sessano",
  "features": [
    {
      "type": "Feature",
      "geometry": {
        "type": "Point",
        "coordinates": [
          12.859575,
          41.508429
        ]
      },
      "properties": {
        "description": "representative point"
      }
    },
    {
      "geometry": {
        "type": "Point",
        "coordinates": [
          12.859575,
          41.508429
        ]
      },
      "id": "darmc-location-18956",
      "type": "Feature",
      "properties": {
        "description": "150K scale point location",
        "location_precision": "precise",
        "title": "DARMC location 18956",
        "link": "http://pleiades.stoa.org/places/423101/darmc-location-18956"
      }
    }
  ]
}