{
  "type": "FeatureCollection",
  "title": "Villa Pamphili",
  "id": "423132",
  "description": "The church of San Pancrazio was founded in the sixth century AD by Pope Symmachus. It stands beyond the Porta San Pancrazio on the Ianiculum. Below the church is a massive catacomb referred to as S. Pancrazio or Ottavilla.",
  "bbox": [
    12.453964,
    41.884968,
    12.453964,
    41.884968
  ],
  "connectsWith": [
    "423025"
  ],
  "reprPoint": [
    12.453964,
    41.884968
  ],
  "features": [
    {
      "geometry": {
        "type": "Point",
        "coordinates": [
          12.43215,
          41.883258
        ]
      },
      "id": "darmc-location-23765",
      "type": "Feature",
      "properties": {
        "description": "Point location",
        "location_precision": "precise",
        "title": "DARMC location 23765",
        "link": "http://pleiades.stoa.org/places/423132/darmc-location-23765"
      }
    },
    {
      "geometry": {
        "type": "Point",
        "coordinates": [
          12.453964,
          41.884968
        ]
      },
      "id": "dare-location",
      "type": "Feature",
      "properties": {
        "description": "Representative point location, site precision",
        "location_precision": "precise",
        "title": "DARE Location",
        "link": "http://pleiades.stoa.org/places/423132/dare-location"
      }
    }
  ]
}