{
  "type": "FeatureCollection",
  "title": "Villa Muti",
  "id": "423130",
  "description": "An ancient place, cited: BAtlas 43 C2 Villa Muti",
  "bbox": [
    12.678977,
    41.798429,
    12.678977,
    41.798429
  ],
  "reprPoint": [
    12.678977,
    41.798429
  ],
  "features": [
    {
      "geometry": {
        "type": "Point",
        "coordinates": [
          12.678977,
          41.798429
        ]
      },
      "id": "darmc-location-21144",
      "type": "Feature",
      "properties": {
        "description": "150K scale point location",
        "location_precision": "precise",
        "title": "DARMC location 21144",
        "link": "http://pleiades.stoa.org/places/423130/darmc-location-21144"
      }
    }
  ]
}