{
  "type": "FeatureCollection",
  "title": "Valerio Messala Corvino",
  "id": "423113",
  "description": "An ancient place, cited: BAtlas 43 C2 Valerio Messala Corvino",
  "bbox": [
    12.637681,
    41.764361,
    12.637681,
    41.764361
  ],
  "reprPoint": [
    12.637681,
    41.764361
  ],
  "features": [
    {
      "geometry": {
        "type": "Point",
        "coordinates": [
          12.637681,
          41.764361
        ]
      },
      "id": "darmc-location-21137",
      "type": "Feature",
      "properties": {
        "description": "150K scale point location",
        "location_precision": "precise",
        "title": "DARMC location 21137",
        "link": "http://pleiades.stoa.org/places/423113/darmc-location-21137"
      }
    }
  ]
}