{
  "type": "FeatureCollection",
  "title": "Villa Torlonia",
  "id": "423133",
  "description": "A Jewish catacomb discovered in 1919 on the grounds of the Villa Torlonia in Rome.",
  "bbox": [
    12.512,
    41.914,
    12.512,
    41.914
  ],
  "connectsWith": [
    "423025"
  ],
  "reprPoint": [
    12.512,
    41.914
  ],
  "features": [
    {
      "geometry": {
        "type": "Point",
        "coordinates": [
          12.511313,
          41.914821
        ]
      },
      "id": "darmc-location-21145",
      "type": "Feature",
      "properties": {
        "description": "150K scale point location",
        "location_precision": "precise",
        "title": "DARMC location 21145",
        "link": "http://pleiades.stoa.org/places/423133/darmc-location-21145"
      }
    },
    {
      "geometry": {
        "type": "Point",
        "coordinates": [
          12.679513,
          41.803397
        ]
      },
      "id": "darmc-location-23767",
      "type": "Feature",
      "properties": {
        "description": "Point location",
        "location_precision": "precise",
        "title": "DARMC location 23767",
        "link": "http://pleiades.stoa.org/places/423133/darmc-location-23767"
      }
    },
    {
      "geometry": {
        "type": "Point",
        "coordinates": [
          12.512,
          41.914
        ]
      },
      "id": "dare-location",
      "type": "Feature",
      "properties": {
        "description": "Representative point location, village precision",
        "location_precision": "precise",
        "title": "DARE Location",
        "link": "http://pleiades.stoa.org/places/423133/dare-location"
      }
    }
  ]
}