{
  "type": "FeatureCollection",
  "title": "Stoa in the sanctuary of Zeus Lykaios",
  "id": "424010351",
  "bbox": [
    21.995469,
    37.448354,
    21.995469,
    37.448354
  ],
  "description": "A 62 m long stoa, probably of the fourth century BC. ",
  "connectsWith": [
    "570764"
  ],
  "features": [
    {
      "type": "Feature",
      "geometry": {
        "type": "Point",
        "coordinates": [
          21.995469,
          37.448354
        ]
      },
      "properties": {
        "description": "representative point"
      }
    },
    {
      "geometry": {
        "type": "Point",
        "coordinates": [
          21.995469,
          37.448354
        ]
      },
      "id": "stoa-in-the-sanctuary-of-zeus-lykaios",
      "type": "Feature",
      "properties": {
        "description": "A 62 m long stoa, probably of the fourth century BC. ",
        "location_precision": "precise",
        "title": "Stoa in the sanctuary of Zeus Lykaios",
        "link": "http://pleiades.stoa.org/places/424010351/stoa-in-the-sanctuary-of-zeus-lykaios"
      }
    }
  ]
}