{
  "type": "FeatureCollection",
  "title": "Tomb of the Five Chairs, Caere",
  "id": "424267586",
  "bbox": [
    12.0925497,
    42.0023935,
    12.0925497,
    42.0023935
  ],
  "description": "An Etruscan tomb at Caere dated ca. 625-600 B.C.",
  "connectsWith": [
    "422859"
  ],
  "features": [
    {
      "type": "Feature",
      "geometry": {
        "type": "Point",
        "coordinates": [
          12.0925497,
          42.0023935
        ]
      },
      "properties": {
        "description": "representative point"
      }
    },
    {
      "geometry": {
        "type": "Point",
        "coordinates": [
          12.0925497,
          42.0023935
        ]
      },
      "id": "location-of-the-tomb-of-the-five-chairs",
      "type": "Feature",
      "properties": {
        "description": "An Etruscan tomb ca. 625-600 BC. Location based on OpenStreetMap",
        "location_precision": "precise",
        "title": "OSM location of the Tomb of the Five Chairs",
        "link": "http://pleiades.stoa.org/places/424267586/location-of-the-tomb-of-the-five-chairs"
      }
    }
  ]
}