{
  "type": "FeatureCollection",
  "title": "Muhrapert",
  "id": "42490856",
  "bbox": [
    42.9157,
    38.3461,
    42.9157,
    38.3461
  ],
  "description": "Find place for Urartian inscribed stone.",
  "features": [
    {
      "type": "Feature",
      "geometry": {
        "type": "Point",
        "coordinates": [
          42.9157,
          38.3461
        ]
      },
      "properties": {
        "description": "representative point"
      }
    },
    {
      "geometry": {
        "type": "Point",
        "coordinates": [
          42.9157,
          38.3461
        ]
      },
      "id": "cigs-location-of-muhrapert",
      "type": "Feature",
      "properties": {
        "description": null,
        "location_precision": "precise",
        "title": "CIGS location of Muhrapert",
        "link": "http://pleiades.stoa.org/places/42490856/cigs-location-of-muhrapert"
      }
    }
  ]
}