{
  "type": "FeatureCollection",
  "title": "Villa delle Grotte at Grottarossa",
  "id": "426584",
  "bbox": [
    12.4844546,
    41.9572777,
    12.484503,
    41.957867
  ],
  "description": "A villa with beginnings in the early Republican period, continuing in use to the middle Imperial period.",
  "connectsWith": [
    "422941"
  ],
  "features": [
    {
      "type": "Feature",
      "geometry": {
        "type": "Point",
        "coordinates": [
          12.4844788,
          41.95757235
        ]
      },
      "properties": {
        "description": "representative point"
      }
    },
    {
      "geometry": {
        "type": "Point",
        "coordinates": [
          12.4844546,
          41.9572777
        ]
      },
      "id": "location-of-grottarossa-tombs",
      "type": "Feature",
      "properties": {
        "description": "Representative location based on OpenStreetMap.",
        "location_precision": "precise",
        "title": "OSM location of Grottarossa tombs",
        "link": "http://pleiades.stoa.org/places/426584/location-of-grottarossa-tombs"
      }
    },
    {
      "geometry": {
        "type": "Point",
        "coordinates": [
          12.484503,
          41.957867
        ]
      },
      "id": "villa-delle-grotte",
      "type": "Feature",
      "properties": {
        "description": "A Republican villa site along the Via Flaminia north of Rome",
        "location_precision": "precise",
        "title": "Imagery location of so-called \"Villa delle Grotte\"",
        "link": "http://pleiades.stoa.org/places/426584/villa-delle-grotte"
      }
    }
  ]
}