{
  "type": "FeatureCollection",
  "title": "So-Called Tomb of Clodius",
  "id": "426623",
  "description": "The so-called Tomb of Clodius along the Via Appia near Castel Gandolfo.",
  "bbox": [
    12.6464493,
    41.7399648,
    12.6464493,
    41.7399648
  ],
  "reprPoint": [
    12.6464493,
    41.7399648
  ],
  "features": [
    {
      "geometry": {
        "type": "Point",
        "coordinates": [
          12.6464493,
          41.7399648
        ]
      },
      "id": "location-of-alleged-tomb-of-clodius",
      "type": "Feature",
      "properties": {
        "description": "Location based on OpenStreetMap. Dates after BAtlas.",
        "location_precision": "precise",
        "title": "location of alleged Tomb of Clodius",
        "link": "http://pleiades.stoa.org/places/426623/location-of-alleged-tomb-of-clodius"
      }
    }
  ]
}