{
  "type": "FeatureCollection",
  "title": "Angitiae Lucus",
  "id": "432676",
  "bbox": [
    13.4605973,
    41.958092,
    13.47448,
    41.9711257
  ],
  "description": "An ancient place, cited: BAtlas 44 D2 Angitiae Lucus",
  "names": [
    "Angitiae Lucus",
    "nemus Angitiae",
    "Lucus Angitiae"
  ],
  "features": [
    {
      "type": "Feature",
      "geometry": {
        "type": "Point",
        "coordinates": [
          13.46753865,
          41.96460885
        ]
      },
      "properties": {
        "description": "representative point"
      }
    },
    {
      "geometry": {
        "type": "Point",
        "coordinates": [
          13.47448,
          41.958092
        ]
      },
      "id": "darmc-location-18191",
      "type": "Feature",
      "properties": {
        "description": "500K scale point location",
        "location_precision": "precise",
        "title": "DARMC location 18191",
        "link": "http://pleiades.stoa.org/places/432676/darmc-location-18191"
      }
    },
    {
      "geometry": {
        "type": "Point",
        "coordinates": [
          13.4605973,
          41.9711257
        ]
      },
      "id": "osm-location",
      "type": "Feature",
      "properties": {
        "description": "Representative location based on OpenStreetMap way. Dates after BAtlas.",
        "location_precision": "precise",
        "title": "OSM location of Lucus Angitiae",
        "link": "http://pleiades.stoa.org/places/432676/osm-location"
      }
    }
  ]
}