{
  "type": "FeatureCollection",
  "title": "Angitiae Lucus",
  "id": "432676",
  "description": "An ancient place, cited: BAtlas 44 D2 Angitiae Lucus",
  "bbox": [
    13.47448,
    41.958092,
    13.47448,
    41.958092
  ],
  "reprPoint": [
    13.47448,
    41.958092
  ],
  "names": [
    "Angitiae Lucus"
  ],
  "features": [
    {
      "geometry": {
        "type": "Point",
        "coordinates": [
          13.47448,
          41.958092
        ]
      },
      "id": "darmc-location-18191",
      "type": "Feature",
      "properties": {
        "description": "500K scale point location",
        "location_precision": "precise",
        "title": "DARMC location 18191",
        "link": "http://pleiades.stoa.org/places/432676/darmc-location-18191"
      }
    }
  ]
}