{
  "type": "FeatureCollection",
  "title": "Callifae?",
  "id": "432737",
  "bbox": [
    14.178842,
    41.405755,
    14.178842,
    41.405755
  ],
  "description": "A city of the Samnites that, according to Livy, was captured by the Romans in Republican times. Probably at or in the vicinity of modern Roccavecchia di Pratella in Italy.",
  "connectsWith": [
    "433078"
  ],
  "names": [
    "Callifae"
  ],
  "features": [
    {
      "type": "Feature",
      "geometry": {
        "type": "Point",
        "coordinates": [
          14.178842,
          41.405755
        ]
      },
      "properties": {
        "description": "representative point"
      }
    },
    {
      "geometry": {
        "type": "Point",
        "coordinates": [
          14.178842,
          41.405755
        ]
      },
      "id": "darmc-location-18277",
      "type": "Feature",
      "properties": {
        "description": "500K scale point location",
        "location_precision": "precise",
        "title": "DARMC location 18277",
        "link": "http://pleiades.stoa.org/places/432737/darmc-location-18277"
      }
    }
  ]
}