{
  "type": "FeatureCollection",
  "title": "Caieta",
  "id": "432734",
  "bbox": [
    13.570989,
    41.214072,
    13.570989,
    41.214072
  ],
  "description": "Caieta was a town of ancient Latium located on the Tyrrhenian Sea coast between Tarracina and Formiae.",
  "names": [
    "Caieta"
  ],
  "features": [
    {
      "type": "Feature",
      "geometry": {
        "type": "Point",
        "coordinates": [
          13.570989,
          41.214072
        ]
      },
      "properties": {
        "description": "representative point"
      }
    },
    {
      "geometry": {
        "type": "Point",
        "coordinates": [
          13.570989,
          41.214072
        ]
      },
      "id": "darmc-location-18271",
      "type": "Feature",
      "properties": {
        "description": "500K scale point location",
        "location_precision": "precise",
        "title": "DARMC location 18271",
        "link": "http://pleiades.stoa.org/places/432734/darmc-location-18271"
      }
    }
  ]
}