{
  "type": "FeatureCollection",
  "title": "Callifae?",
  "id": "432737",
  "description": "An ancient place, cited: BAtlas 44 F3 Callifae?",
  "bbox": [
    14.178842,
    41.405755,
    14.178842,
    41.405755
  ],
  "reprPoint": [
    14.178842,
    41.405755
  ],
  "names": [
    "Callifae"
  ],
  "features": [
    {
      "geometry": {
        "type": "Point",
        "coordinates": [
          14.178842,
          41.405755
        ]
      },
      "id": "darmc-location-18277",
      "type": "Feature",
      "properties": {
        "description": "500K scale point location",
        "location_precision": "precise",
        "title": "DARMC location 18277",
        "link": "http://pleiades.stoa.org/places/432737/darmc-location-18277"
      }
    }
  ]
}