{
  "type": "FeatureCollection",
  "title": "Kirkaion Akron/Veneris Pr.",
  "id": "432781",
  "description": "Kirkaion Akron/Veneris Pr. (Monte Circeo) is a mountainous promontory on the Tyrrhenian coast of Italy.",
  "bbox": [
    13.05,
    41.2333,
    13.05,
    41.2333
  ],
  "reprPoint": [
    13.05,
    41.2333
  ],
  "names": [
    "Kirkaion Akron",
    "Veneris Pr."
  ],
  "features": [
    {
      "geometry": {
        "type": "Point",
        "coordinates": [
          13.05,
          41.2333
        ]
      },
      "id": "location-of-kirkaion-akron-veneris-pr",
      "type": "Feature",
      "properties": {
        "description": "coordinates after GeoHack, verified in Google Earth.",
        "location_precision": "precise",
        "title": "location of Kirkaion Akron/Veneris Pr.",
        "link": "http://pleiades.stoa.org/places/432781/location-of-kirkaion-akron-veneris-pr"
      }
    }
  ]
}