{
  "type": "FeatureCollection",
  "title": "Clostra (Romana)",
  "id": "432788",
  "bbox": [
    12.872401,
    41.414938,
    12.872401,
    41.414938
  ],
  "description": "An ancient place, cited: BAtlas 44 C3 Clostra (Romana)",
  "names": [
    "Clostra Romana",
    "Clostra"
  ],
  "features": [
    {
      "type": "Feature",
      "geometry": {
        "type": "Point",
        "coordinates": [
          12.872401,
          41.414938
        ]
      },
      "properties": {
        "description": "representative point"
      }
    },
    {
      "geometry": {
        "type": "Point",
        "coordinates": [
          12.872401,
          41.414938
        ]
      },
      "id": "darmc-location-19260",
      "type": "Feature",
      "properties": {
        "description": "500K scale point location",
        "location_precision": "precise",
        "title": "DARMC location 19260",
        "link": "http://pleiades.stoa.org/places/432788/darmc-location-19260"
      }
    }
  ]
}