{
  "type": "FeatureCollection",
  "title": "Kirkaion Akron/Veneris Pr.",
  "id": "432781",
  "bbox": [
    13.0459251,
    41.2333,
    13.05,
    41.2379462
  ],
  "description": "Kirkaion Akron/Veneris Pr. (Monte Circeo) is a mountainous promontory on the Tyrrhenian coast of Italy.",
  "names": [
    "Kirkaion Akron",
    "Veneris Pr.",
    "Kirkaion",
    "Monte Circeo",
    "Promontorio del Circeo"
  ],
  "features": [
    {
      "type": "Feature",
      "geometry": {
        "type": "Point",
        "coordinates": [
          13.04796255,
          41.2356231
        ]
      },
      "properties": {
        "description": "representative point"
      }
    },
    {
      "geometry": {
        "type": "Point",
        "coordinates": [
          13.05,
          41.2333
        ]
      },
      "id": "location-of-kirkaion-akron-veneris-pr",
      "type": "Feature",
      "properties": {
        "description": "coordinates after GeoHack, verified in Google Earth.",
        "location_precision": "precise",
        "title": "Imagery location of Kirkaion Akron/Veneris Pr.",
        "link": "http://pleiades.stoa.org/places/432781/location-of-kirkaion-akron-veneris-pr"
      }
    },
    {
      "geometry": {
        "type": "Point",
        "coordinates": [
          13.0459251,
          41.2379462
        ]
      },
      "id": "osm-location-of-mount-circeo",
      "type": "Feature",
      "properties": {
        "description": "Location based on OpenStreetMap",
        "location_precision": "precise",
        "title": "OSM location of Mount Circeo",
        "link": "http://pleiades.stoa.org/places/432781/osm-location-of-mount-circeo"
      }
    }
  ]
}