{
  "type": "FeatureCollection",
  "title": "Colle Mitra",
  "id": "432794",
  "description": "An ancient place, cited: BAtlas 44 E1 Colle Mitra",
  "bbox": [
    13.925641,
    42.04688,
    13.925641,
    42.04688
  ],
  "reprPoint": [
    13.925641,
    42.04688
  ],
  "features": [
    {
      "geometry": {
        "type": "Point",
        "coordinates": [
          13.925641,
          42.04688
        ]
      },
      "id": "darmc-location-18361",
      "type": "Feature",
      "properties": {
        "description": "500K scale point location",
        "location_precision": "precise",
        "title": "DARMC location 18361",
        "link": "http://pleiades.stoa.org/places/432794/darmc-location-18361"
      }
    }
  ]
}