{
  "type": "FeatureCollection",
  "title": "Casinum",
  "id": "432764",
  "bbox": [
    13.830583,
    41.492907,
    13.830583,
    41.492907
  ],
  "description": "A Volscian hilltop settlement that became a Roman colony in 312 B.C.",
  "connectsWith": [
    "93042695"
  ],
  "names": [
    "Casinum",
    "Cassino"
  ],
  "features": [
    {
      "type": "Feature",
      "geometry": {
        "type": "Point",
        "coordinates": [
          13.830583,
          41.492907
        ]
      },
      "properties": {
        "description": "representative point"
      }
    },
    {
      "geometry": {
        "type": "Point",
        "coordinates": [
          13.830583,
          41.492907
        ]
      },
      "id": "darmc-location-18308",
      "type": "Feature",
      "properties": {
        "description": "500K scale point location",
        "location_precision": "precise",
        "title": "DARMC location 18308",
        "link": "http://pleiades.stoa.org/places/432764/darmc-location-18308"
      }
    }
  ]
}