{
  "type": "FeatureCollection",
  "title": "Aufidena",
  "id": "432709",
  "bbox": [
    14.108223,
    41.784299,
    14.108223,
    41.784299
  ],
  "description": "An ancient place, cited: BAtlas 44 F2 Aufidena",
  "names": [
    "Aufidena"
  ],
  "features": [
    {
      "type": "Feature",
      "geometry": {
        "type": "Point",
        "coordinates": [
          14.108223,
          41.784299
        ]
      },
      "properties": {
        "description": "representative point"
      }
    },
    {
      "geometry": {
        "type": "Point",
        "coordinates": [
          14.108223,
          41.784299
        ]
      },
      "id": "darmc-location-6950",
      "type": "Feature",
      "properties": {
        "description": "500K scale point location",
        "location_precision": "precise",
        "title": "DARMC location 6950",
        "link": "http://pleiades.stoa.org/places/432709/darmc-location-6950"
      }
    }
  ]
}