{
  "type": "FeatureCollection",
  "title": "Aufidena",
  "id": "432709",
  "bbox": [
    14.108223,
    41.784299,
    14.108223,
    41.784299
  ],
  "description": "A probable Samnite center, the Romans captured Aufidena in 298 BC. It only became a municipium after 49 B.C.",
  "names": [
    "Aufidena"
  ],
  "features": [
    {
      "type": "Feature",
      "geometry": {
        "type": "Point",
        "coordinates": [
          14.108223,
          41.784299
        ]
      },
      "properties": {
        "description": "representative point"
      }
    },
    {
      "geometry": {
        "type": "Point",
        "coordinates": [
          14.108223,
          41.784299
        ]
      },
      "id": "darmc-location-6950",
      "type": "Feature",
      "properties": {
        "description": "1:500,000 scale representative point location digitized from the Barrington Atlas of the Greek and Roman World by the Digital Atlas of Roman and Medieval Civilizations project at Harvard University.",
        "location_precision": "precise",
        "title": "DARMC location 6950",
        "link": "http://pleiades.stoa.org/places/432709/darmc-location-6950"
      }
    }
  ]
}