{
  "type": "FeatureCollection",
  "title": "Casinum",
  "id": "432764",
  "description": "A Volscian hilltop settlement that became a Roman colony in 312 B.C.",
  "bbox": [
    13.821628,
    41.4825511,
    13.830583,
    41.492907
  ],
  "connectsWith": [
    "93042695"
  ],
  "reprPoint": [
    13.8252693333,
    41.4863253
  ],
  "names": [
    "Casinum",
    "Cassino"
  ],
  "features": [
    {
      "geometry": {
        "type": "Point",
        "coordinates": [
          13.830583,
          41.492907
        ]
      },
      "id": "darmc-location-18308",
      "type": "Feature",
      "properties": {
        "description": "500K scale point location",
        "location_precision": "precise",
        "title": "DARMC location 18308",
        "link": "http://pleiades.stoa.org/places/432764/darmc-location-18308"
      }
    },
    {
      "geometry": {
        "type": "Point",
        "coordinates": [
          13.823597,
          41.4825511
        ]
      },
      "id": "loation-of-roman-amphitheater",
      "type": "Feature",
      "properties": {
        "description": "Representative location based on OpenStreetMap.",
        "location_precision": "precise",
        "title": "OSM location of Roman amphitheater",
        "link": "http://pleiades.stoa.org/places/432764/loation-of-roman-amphitheater"
      }
    },
    {
      "geometry": {
        "type": "Point",
        "coordinates": [
          13.821628,
          41.4835178
        ]
      },
      "id": "location-of-roman-theater",
      "type": "Feature",
      "properties": {
        "description": "Location based on OpenStreetMap",
        "location_precision": "precise",
        "title": "location of Roman theater",
        "link": "http://pleiades.stoa.org/places/432764/location-of-roman-theater"
      }
    }
  ]
}