{
  "type": "FeatureCollection",
  "title": "Cocullo",
  "id": "432791",
  "description": "An ancient place, cited: BAtlas 44 E1 Cocullo",
  "bbox": [
    13.77481,
    42.033767,
    13.77481,
    42.033767
  ],
  "reprPoint": [
    13.77481,
    42.033767
  ],
  "features": [
    {
      "geometry": {
        "type": "Point",
        "coordinates": [
          13.77481,
          42.033767
        ]
      },
      "id": "darmc-location-3792",
      "type": "Feature",
      "properties": {
        "description": "500K scale point location",
        "location_precision": "precise",
        "title": "DARMC location 3792",
        "link": "http://pleiades.stoa.org/places/432791/darmc-location-3792"
      }
    }
  ]
}