{
  "type": "FeatureCollection",
  "title": "Fabrateria Nova",
  "id": "432825",
  "bbox": [
    13.558107,
    41.51929,
    13.558107,
    41.51929
  ],
  "description": "An ancient place, cited: BAtlas 44 E2 Fabrateria Nova",
  "names": [
    "Fabrateria Nova"
  ],
  "features": [
    {
      "type": "Feature",
      "geometry": {
        "type": "Point",
        "coordinates": [
          13.558107,
          41.51929
        ]
      },
      "properties": {
        "description": "representative point"
      }
    },
    {
      "geometry": {
        "type": "Point",
        "coordinates": [
          13.558107,
          41.51929
        ]
      },
      "id": "darmc-location-18423",
      "type": "Feature",
      "properties": {
        "description": "500K scale point location",
        "location_precision": "precise",
        "title": "DARMC location 18423",
        "link": "http://pleiades.stoa.org/places/432825/darmc-location-18423"
      }
    }
  ]
}