{
  "type": "FeatureCollection",
  "title": "Lago di Paola",
  "id": "432895",
  "description": "An ancient place, cited: BAtlas 44 D3 Lago di Paola",
  "bbox": [
    13.032806,
    41.266688,
    13.032806,
    41.266688
  ],
  "reprPoint": [
    13.032806,
    41.266688
  ],
  "features": [
    {
      "geometry": {
        "type": "Point",
        "coordinates": [
          13.032806,
          41.266688
        ]
      },
      "id": "darmc-location-7772",
      "type": "Feature",
      "properties": {
        "description": "500K scale point location",
        "location_precision": "precise",
        "title": "DARMC location 7772",
        "link": "http://pleiades.stoa.org/places/432895/darmc-location-7772"
      }
    }
  ]
}