{
  "type": "FeatureCollection",
  "title": "‘Iovis Lareni’",
  "id": "432886",
  "description": "An ancient place, cited: BAtlas 44 F1 ‘Iovis Lareni’",
  "bbox": [
    13.990212,
    42.002986,
    13.990212,
    42.002986
  ],
  "reprPoint": [
    13.990212,
    42.002986
  ],
  "names": [
    "Iovis Lareni"
  ],
  "features": [
    {
      "geometry": {
        "type": "Point",
        "coordinates": [
          14.012773,
          42.005418
        ]
      },
      "id": "darmc-location-30581",
      "type": "Feature",
      "properties": {
        "description": "500K scale point location",
        "location_precision": "precise",
        "title": "DARMC location 30581",
        "link": "http://pleiades.stoa.org/places/432886/darmc-location-30581"
      }
    },
    {
      "geometry": {
        "type": "Point",
        "coordinates": [
          13.990212,
          42.002986
        ]
      },
      "id": "dare-location",
      "type": "Feature",
      "properties": {
        "description": "Representative point location, site precision",
        "location_precision": "precise",
        "title": "DARE Location",
        "link": "http://pleiades.stoa.org/places/432886/dare-location"
      }
    }
  ]
}