{
  "type": "FeatureCollection",
  "title": "Lago di Paola",
  "id": "432895",
  "bbox": [
    13.0386036,
    41.2684151,
    13.0386036,
    41.2684151
  ],
  "description": "A villa of the emperor Domitian located in the area of Circeii.",
  "features": [
    {
      "type": "Feature",
      "geometry": {
        "type": "Point",
        "coordinates": [
          13.0386036,
          41.2684151
        ]
      },
      "properties": {
        "description": "representative point"
      }
    },
    {
      "geometry": {
        "type": "Point",
        "coordinates": [
          13.0386036,
          41.2684151
        ]
      },
      "id": "osm-location-of-villa-di-domiziano-sabaudia",
      "type": "Feature",
      "properties": {
        "description": "Representative location derived from an OpenStreetMap way.",
        "location_precision": "precise",
        "title": "OSM location of Villa di Domiziano (Sabaudia)",
        "link": "http://pleiades.stoa.org/places/432895/osm-location-of-villa-di-domiziano-sabaudia"
      }
    }
  ]
}