{
  "type": "FeatureCollection",
  "title": "Fagifulae",
  "id": "432827",
  "bbox": [
    14.675129,
    41.644929,
    14.675129,
    41.644929
  ],
  "description": "Fagifulae was a center of the Pentrian Samnites.",
  "connectsWith": [
    "433017"
  ],
  "names": [
    "Fagifulae"
  ],
  "features": [
    {
      "type": "Feature",
      "geometry": {
        "type": "Point",
        "coordinates": [
          14.675129,
          41.644929
        ]
      },
      "properties": {
        "description": "representative point"
      }
    },
    {
      "geometry": {
        "type": "Point",
        "coordinates": [
          14.675129,
          41.644929
        ]
      },
      "id": "osm-location-of-montagano",
      "type": "Feature",
      "properties": {
        "description": "Representative location of modern settlement based on OpenStreetMap.",
        "location_precision": "precise",
        "title": "OSM location of modern Montagano",
        "link": "http://pleiades.stoa.org/places/432827/osm-location-of-montagano"
      }
    }
  ]
}