{
  "type": "FeatureCollection",
  "title": "Giurlanda",
  "id": "432866",
  "description": "An ancient place, cited: BAtlas 44 E1 Giurlanda",
  "bbox": [
    13.666003,
    42.026717,
    13.666003,
    42.026717
  ],
  "reprPoint": [
    13.666003,
    42.026717
  ],
  "features": [
    {
      "geometry": {
        "type": "Point",
        "coordinates": [
          13.666003,
          42.026717
        ]
      },
      "id": "darmc-location-18481",
      "type": "Feature",
      "properties": {
        "description": "500K scale point location",
        "location_precision": "precise",
        "title": "DARMC location 18481",
        "link": "http://pleiades.stoa.org/places/432866/darmc-location-18481"
      }
    }
  ]
}