{
  "type": "FeatureCollection",
  "title": "La Giostra",
  "id": "432893",
  "description": "An ancient place, cited: BAtlas 44 E2 La Giostra",
  "bbox": [
    13.581665,
    41.938843,
    13.581665,
    41.938843
  ],
  "reprPoint": [
    13.581665,
    41.938843
  ],
  "features": [
    {
      "geometry": {
        "type": "Point",
        "coordinates": [
          13.581665,
          41.938843
        ]
      },
      "id": "darmc-location-7058",
      "type": "Feature",
      "properties": {
        "description": "500K scale point location",
        "location_precision": "precise",
        "title": "DARMC location 7058",
        "link": "http://pleiades.stoa.org/places/432893/darmc-location-7058"
      }
    }
  ]
}