{
  "type": "FeatureCollection",
  "title": "Fagifulae",
  "id": "432827",
  "description": "An ancient place, cited: BAtlas 44 G2 Fagifulae",
  "bbox": [
    14.667625,
    41.657876,
    14.667625,
    41.657876
  ],
  "reprPoint": [
    14.667625,
    41.657876
  ],
  "names": [
    "Fagifulae"
  ],
  "features": [
    {
      "geometry": {
        "type": "Point",
        "coordinates": [
          14.667625,
          41.657876
        ]
      },
      "id": "darmc-location-18426",
      "type": "Feature",
      "properties": {
        "description": "500K scale point location",
        "location_precision": "precise",
        "title": "DARMC location 18426",
        "link": "http://pleiades.stoa.org/places/432827/darmc-location-18426"
      }
    }
  ]
}