{
  "type": "FeatureCollection",
  "title": "Fundanus L.",
  "id": "432854",
  "description": "A brackish lake ca. 90 km southeast of Rome.",
  "bbox": [
    13.3017682,
    41.3111267,
    13.3017682,
    41.3111267
  ],
  "reprPoint": [
    13.3017682,
    41.3111267
  ],
  "names": [
    "Fundanus L.",
    "Lago di Fondi"
  ],
  "features": [
    {
      "geometry": {
        "type": "Point",
        "coordinates": [
          13.3017682,
          41.3111267
        ]
      },
      "id": "location-of-Fundanus-L",
      "type": "Feature",
      "properties": {
        "description": "Location based on OpenStreetMap",
        "location_precision": "precise",
        "title": "location of Fundanus L.",
        "link": "http://pleiades.stoa.org/places/432854/location-of-Fundanus-L"
      }
    }
  ]
}