{
  "type": "FeatureCollection",
  "title": "‘Iovis Lareni’",
  "id": "432886",
  "bbox": [
    13.9900839,
    42.0021875,
    13.990212,
    42.002986
  ],
  "description": "An ancient place, cited: BAtlas 44 F1 ‘Iovis Lareni’",
  "connectsWith": [
    "926033983"
  ],
  "names": [
    "Iovis Lareni"
  ],
  "features": [
    {
      "type": "Feature",
      "geometry": {
        "type": "Point",
        "coordinates": [
          13.99014795,
          42.00258675
        ]
      },
      "properties": {
        "description": "representative point"
      }
    },
    {
      "geometry": {
        "type": "Point",
        "coordinates": [
          13.990212,
          42.002986
        ]
      },
      "id": "dare-location",
      "type": "Feature",
      "properties": {
        "description": "Representative point location, site precision",
        "location_precision": "precise",
        "title": "DARE Location",
        "link": "http://pleiades.stoa.org/places/432886/dare-location"
      }
    },
    {
      "geometry": {
        "type": "Point",
        "coordinates": [
          13.9900839,
          42.0021875
        ]
      },
      "id": "osm-location",
      "type": "Feature",
      "properties": {
        "description": "Location based on OpenStreetMap",
        "location_precision": "precise",
        "title": "OSM location of Ocriticum",
        "link": "http://pleiades.stoa.org/places/432886/osm-location"
      }
    }
  ]
}