{
  "type": "FeatureCollection",
  "title": "Grottacce",
  "id": "432867",
  "description": "At Grottacce are the remains of a Roman seaside villa or villa maritima.",
  "bbox": [
    11.9017218,
    42.0395539,
    11.9017218,
    42.0395539
  ],
  "connectsWith": [
    "174900201"
  ],
  "reprPoint": [
    11.9017218,
    42.0395539
  ],
  "features": [
    {
      "geometry": {
        "type": "Point",
        "coordinates": [
          11.9017218,
          42.0395539
        ]
      },
      "id": "location-of-roman-villa",
      "type": "Feature",
      "properties": {
        "description": "Representative location based on OpenStreetMap.",
        "location_precision": "precise",
        "title": "OSM location of Roman villa",
        "link": "http://pleiades.stoa.org/places/432867/location-of-roman-villa"
      }
    }
  ]
}