{
  "type": "FeatureCollection",
  "title": "Lago di Paola",
  "id": "432895",
  "description": "A villa of the emperor Domitian located in the area of Circeii.",
  "bbox": [
    13.032806,
    41.266688,
    13.0386036,
    41.2684151
  ],
  "reprPoint": [
    13.0357048,
    41.26755155
  ],
  "features": [
    {
      "geometry": {
        "type": "Point",
        "coordinates": [
          13.032806,
          41.266688
        ]
      },
      "id": "darmc-location-7772",
      "type": "Feature",
      "properties": {
        "description": "500K scale point location",
        "location_precision": "precise",
        "title": "DARMC location 7772",
        "link": "http://pleiades.stoa.org/places/432895/darmc-location-7772"
      }
    },
    {
      "geometry": {
        "type": "Point",
        "coordinates": [
          13.0386036,
          41.2684151
        ]
      },
      "id": "osm-location-of-villa-di-domiziano-sabaudia",
      "type": "Feature",
      "properties": {
        "description": "Representative location derived from an OpenStreetMap way.",
        "location_precision": "precise",
        "title": "OSM location of Villa di Domiziano (Sabaudia)",
        "link": "http://pleiades.stoa.org/places/432895/osm-location-of-villa-di-domiziano-sabaudia"
      }
    }
  ]
}