{
  "type": "FeatureCollection",
  "title": "Fabrateria Nova",
  "id": "432825",
  "bbox": [
    13.558107,
    41.51929,
    13.558107,
    41.51929
  ],
  "description": "Fabrateria Nova received a Roman colony in 124 B.C. that was dispatched by Caius Gracchus. The relationship between Fabrateria Nova and the earlier Volscian site of Fabrateria Vetus remains unclear. The favored location for Fabrateria Nova is at S. Giovanni Incarico, where the Liri and Sacco rivers intersect.",
  "connectsWith": [
    "432826"
  ],
  "names": [
    "Fabrateria Nova",
    "Fabraterni Novi"
  ],
  "features": [
    {
      "type": "Feature",
      "geometry": {
        "type": "Point",
        "coordinates": [
          13.558107,
          41.51929
        ]
      },
      "properties": {
        "description": "representative point"
      }
    },
    {
      "geometry": {
        "type": "Point",
        "coordinates": [
          13.558107,
          41.51929
        ]
      },
      "id": "darmc-location-18423",
      "type": "Feature",
      "properties": {
        "description": "1:500,000 scale representative point location digitized from the Barrington Atlas of the Greek and Roman World by the Digital Atlas of Roman and Medieval Civilizations project at Harvard University.",
        "location_precision": "precise",
        "title": "DARMC location 18423",
        "link": "http://pleiades.stoa.org/places/432825/darmc-location-18423"
      }
    }
  ]
}