{
  "type": "FeatureCollection",
  "title": "Grottacce",
  "id": "432867",
  "description": "At Grottacce are the remains of a Roman seaside villa or villa maritima.",
  "bbox": [
    11.9017218,
    42.0395539,
    11.907877,
    42.040662
  ],
  "connectsWith": [
    "174900201"
  ],
  "reprPoint": [
    11.9058252667,
    42.0402926333
  ],
  "features": [
    {
      "geometry": {
        "type": "Point",
        "coordinates": [
          11.907877,
          42.040662
        ]
      },
      "id": "darmc-location-7737",
      "type": "Feature",
      "properties": {
        "description": "500K scale point location",
        "location_precision": "precise",
        "title": "DARMC location 7737",
        "link": "http://pleiades.stoa.org/places/432867/darmc-location-7737"
      }
    },
    {
      "geometry": {
        "type": "Point",
        "coordinates": [
          11.907877,
          42.040662
        ]
      },
      "id": "darmc-location-7738",
      "type": "Feature",
      "properties": {
        "description": "500K scale point location",
        "location_precision": "precise",
        "title": "DARMC location 7738",
        "link": "http://pleiades.stoa.org/places/432867/darmc-location-7738"
      }
    }
  ]
}