{
  "type": "FeatureCollection",
  "title": "Monte Monaco di Gioia",
  "id": "432953",
  "bbox": [
    14.444996,
    41.301295,
    14.444996,
    41.301295
  ],
  "description": "An ancient place, cited: BAtlas 44 F3 Monte Monaco di Gioia",
  "features": [
    {
      "type": "Feature",
      "geometry": {
        "type": "Point",
        "coordinates": [
          14.444996,
          41.301295
        ]
      },
      "properties": {
        "description": "representative point"
      }
    },
    {
      "geometry": {
        "type": "Point",
        "coordinates": [
          14.444996,
          41.301295
        ]
      },
      "id": "darmc-location-28646",
      "type": "Feature",
      "properties": {
        "description": "500K scale point location",
        "location_precision": "precise",
        "title": "DARMC location 28646",
        "link": "http://pleiades.stoa.org/places/432953/darmc-location-28646"
      }
    }
  ]
}