{
  "type": "FeatureCollection",
  "title": "Matrice",
  "id": "432932",
  "bbox": [
    14.710515,
    41.613726,
    14.710515,
    41.613726
  ],
  "description": "An ancient place, cited: BAtlas 44 G2 Matrice",
  "features": [
    {
      "type": "Feature",
      "geometry": {
        "type": "Point",
        "coordinates": [
          14.710515,
          41.613726
        ]
      },
      "properties": {
        "description": "representative point"
      }
    },
    {
      "geometry": {
        "type": "Point",
        "coordinates": [
          14.710515,
          41.613726
        ]
      },
      "id": "darmc-location-7808",
      "type": "Feature",
      "properties": {
        "description": "500K scale point location",
        "location_precision": "precise",
        "title": "DARMC location 7808",
        "link": "http://pleiades.stoa.org/places/432932/darmc-location-7808"
      }
    }
  ]
}