{
  "type": "FeatureCollection",
  "title": "Monte Nero",
  "id": "432954",
  "description": "An ancient place, cited: BAtlas 44 D2 Monte Nero",
  "bbox": [
    14.070344,
    41.717809,
    14.070344,
    41.717809
  ],
  "reprPoint": [
    14.070344,
    41.717809
  ],
  "features": [
    {
      "geometry": {
        "type": "Point",
        "coordinates": [
          14.070344,
          41.717809
        ]
      },
      "id": "darmc-location-18647",
      "type": "Feature",
      "properties": {
        "description": "500K scale point location",
        "location_precision": "precise",
        "title": "DARMC location 18647",
        "link": "http://pleiades.stoa.org/places/432954/darmc-location-18647"
      }
    }
  ]
}