{
  "type": "FeatureCollection",
  "title": "Pescolanciano",
  "id": "433020",
  "description": "An ancient place, cited: BAtlas 44 F2 Pescolanciano",
  "bbox": [
    14.338156,
    41.679558,
    14.338156,
    41.679558
  ],
  "reprPoint": [
    14.338156,
    41.679558
  ],
  "features": [
    {
      "geometry": {
        "type": "Point",
        "coordinates": [
          14.338156,
          41.679558
        ]
      },
      "id": "darmc-location-18743",
      "type": "Feature",
      "properties": {
        "description": "500K scale point location",
        "location_precision": "precise",
        "title": "DARMC location 18743",
        "link": "http://pleiades.stoa.org/places/433020/darmc-location-18743"
      }
    }
  ]
}