{
  "type": "FeatureCollection",
  "title": "Privernum",
  "id": "433052",
  "description": "A Volscian center that Rome reportedly destroyed in the late fourth century BC.",
  "bbox": [
    13.187599,
    41.489943,
    13.187599,
    41.489943
  ],
  "reprPoint": [
    13.187599,
    41.489943
  ],
  "names": [
    "Privernum"
  ],
  "features": [
    {
      "geometry": {
        "type": "Point",
        "coordinates": [
          13.181697,
          41.473421
        ]
      },
      "id": "darmc-location-18808",
      "type": "Feature",
      "properties": {
        "description": "500K scale point location",
        "location_precision": "precise",
        "title": "DARMC location 18808",
        "link": "http://pleiades.stoa.org/places/433052/darmc-location-18808"
      }
    },
    {
      "geometry": {
        "type": "Point",
        "coordinates": [
          13.187599,
          41.489943
        ]
      },
      "id": "dare-location",
      "type": "Feature",
      "properties": {
        "description": "Representative point location, village precision",
        "location_precision": "precise",
        "title": "DARE Location",
        "link": "http://pleiades.stoa.org/places/433052/dare-location"
      }
    }
  ]
}