{
  "type": "FeatureCollection",
  "title": "Pons Apollinis",
  "id": "433035",
  "description": "An ancient place, cited: BAtlas 44 A1 Pons Apollinis",
  "bbox": [
    11.884241,
    42.042895,
    11.884241,
    42.042895
  ],
  "reprPoint": [
    11.884241,
    42.042895
  ],
  "names": [
    "Pons Apollinis"
  ],
  "features": [
    {
      "geometry": {
        "type": "Point",
        "coordinates": [
          11.884241,
          42.042895
        ]
      },
      "id": "darmc-location-17980",
      "type": "Feature",
      "properties": {
        "description": "500K scale point location",
        "location_precision": "precise",
        "title": "DARMC location 17980",
        "link": "http://pleiades.stoa.org/places/433035/darmc-location-17980"
      }
    }
  ]
}