{
  "type": "FeatureCollection",
  "title": "S. Giacomo",
  "id": "433085",
  "bbox": [
    14.94721,
    41.96428,
    14.94721,
    41.96428
  ],
  "description": "An ancient place, cited: BAtlas 44 G2 S. Giacomo",
  "features": [
    {
      "type": "Feature",
      "geometry": {
        "type": "Point",
        "coordinates": [
          14.94721,
          41.96428
        ]
      },
      "properties": {
        "description": "representative point"
      }
    },
    {
      "geometry": {
        "type": "Point",
        "coordinates": [
          14.94721,
          41.96428
        ]
      },
      "id": "darmc-location-7926",
      "type": "Feature",
      "properties": {
        "description": "500K scale point location",
        "location_precision": "precise",
        "title": "DARMC location 7926",
        "link": "http://pleiades.stoa.org/places/433085/darmc-location-7926"
      }
    }
  ]
}