{
  "type": "FeatureCollection",
  "title": "Privernum",
  "id": "433052",
  "bbox": [
    13.1851343,
    41.4907686,
    13.1851343,
    41.4907686
  ],
  "description": "A Volscian center that Rome reportedly destroyed in the late fourth century B.C.",
  "connectsWith": [
    "433208"
  ],
  "names": [
    "Privernum",
    "Pribernon"
  ],
  "features": [
    {
      "type": "Feature",
      "geometry": {
        "type": "Point",
        "coordinates": [
          13.1851343,
          41.4907686
        ]
      },
      "properties": {
        "description": "representative point"
      }
    },
    {
      "geometry": {
        "type": "Point",
        "coordinates": [
          13.1851343,
          41.4907686
        ]
      },
      "id": "osm-location-of-privernum",
      "type": "Feature",
      "properties": {
        "description": "Representative location based on OpenStreetMap",
        "location_precision": "precise",
        "title": "OSM location of Privernum",
        "link": "http://pleiades.stoa.org/places/433052/osm-location-of-privernum"
      }
    }
  ]
}