{
  "type": "FeatureCollection",
  "title": "Pons Apollinis",
  "id": "433035",
  "bbox": [
    11.8812405,
    42.0387821,
    11.8812405,
    42.0387821
  ],
  "description": "An ancient place, cited: BAtlas 44 A1 Pons Apollinis",
  "names": [
    "Pons Apollinis"
  ],
  "features": [
    {
      "type": "Feature",
      "geometry": {
        "type": "Point",
        "coordinates": [
          11.8812405,
          42.0387821
        ]
      },
      "properties": {
        "description": "representative point"
      }
    },
    {
      "geometry": {
        "type": "Point",
        "coordinates": [
          11.8812405,
          42.0387821
        ]
      },
      "id": "osm-location-of-ponte-romano-di-apollo",
      "type": "Feature",
      "properties": {
        "description": "Representative location based on OpenStreetMap",
        "location_precision": "precise",
        "title": "OSM location of Ponte Romano di Apollo",
        "link": "http://pleiades.stoa.org/places/433035/osm-location-of-ponte-romano-di-apollo"
      }
    }
  ]
}