{
  "type": "FeatureCollection",
  "title": "Privernum",
  "id": "433052",
  "bbox": [
    13.181697,
    41.473421,
    13.181697,
    41.473421
  ],
  "description": "A Volscian center that Rome reportedly destroyed in the late fourth century B.C.",
  "connectsWith": [
    "433208"
  ],
  "names": [
    "Privernum"
  ],
  "features": [
    {
      "type": "Feature",
      "geometry": {
        "type": "Point",
        "coordinates": [
          13.181697,
          41.473421
        ]
      },
      "properties": {
        "description": "representative point"
      }
    },
    {
      "geometry": {
        "type": "Point",
        "coordinates": [
          13.181697,
          41.473421
        ]
      },
      "id": "darmc-location-18808",
      "type": "Feature",
      "properties": {
        "description": "500K scale point location",
        "location_precision": "precise",
        "title": "DARMC location 18808",
        "link": "http://pleiades.stoa.org/places/433052/darmc-location-18808"
      }
    }
  ]
}