{
  "type": "FeatureCollection",
  "title": "Palmaria Ins.",
  "id": "433008",
  "description": "The second largest of the Pontine Islands.",
  "bbox": [
    12.858,
    40.937,
    12.858,
    40.937
  ],
  "connectsWith": [
    "433042"
  ],
  "reprPoint": [
    12.858,
    40.937
  ],
  "names": [
    "Palmaria",
    "Palmarola"
  ],
  "features": [
    {
      "geometry": {
        "type": "Point",
        "coordinates": [
          12.858,
          40.937
        ]
      },
      "id": "location-of-palmaria-ins",
      "type": "Feature",
      "properties": {
        "description": "Coordinates after GeoHack, verified in Google Earth 2013.",
        "location_precision": "precise",
        "title": "location of Palmarola",
        "link": "http://pleiades.stoa.org/places/433008/location-of-palmaria-ins"
      }
    }
  ]
}