{
  "type": "FeatureCollection",
  "title": "Suessa Aurunca",
  "id": "433132",
  "description": "The ancient center of the Aurunci, Suessa Aurunca was abandoned in 337 BC for a more favorable site (modern Sessa) where a Latin colony was established in 313 BC.",
  "bbox": [
    13.930692,
    41.234601,
    13.930692,
    41.234601
  ],
  "reprPoint": [
    13.930692,
    41.234601
  ],
  "names": [
    "Suessa Aurunca"
  ],
  "features": [
    {
      "geometry": {
        "type": "Point",
        "coordinates": [
          13.933756,
          41.241907
        ]
      },
      "id": "darmc-location-18908",
      "type": "Feature",
      "properties": {
        "description": "500K scale point location",
        "location_precision": "precise",
        "title": "DARMC location 18908",
        "link": "http://pleiades.stoa.org/places/433132/darmc-location-18908"
      }
    },
    {
      "geometry": {
        "type": "Point",
        "coordinates": [
          13.930692,
          41.234601
        ]
      },
      "id": "dare-location",
      "type": "Feature",
      "properties": {
        "description": "Representative point location, site precision",
        "location_precision": "precise",
        "title": "DARE Location",
        "link": "http://pleiades.stoa.org/places/433132/dare-location"
      }
    }
  ]
}