{
  "type": "FeatureCollection",
  "title": "Terravecchia",
  "id": "433148",
  "bbox": [
    14.600275,
    41.413173,
    14.600275,
    41.413173
  ],
  "description": "An ancient place, cited: BAtlas 44 G3 Terravecchia",
  "features": [
    {
      "type": "Feature",
      "geometry": {
        "type": "Point",
        "coordinates": [
          14.600275,
          41.413173
        ]
      },
      "properties": {
        "description": "representative point"
      }
    },
    {
      "geometry": {
        "type": "Point",
        "coordinates": [
          14.600275,
          41.413173
        ]
      },
      "id": "darmc-location-6123",
      "type": "Feature",
      "properties": {
        "description": "500K scale point location",
        "location_precision": "precise",
        "title": "DARMC location 6123",
        "link": "http://pleiades.stoa.org/places/433148/darmc-location-6123"
      }
    }
  ]
}