{
  "type": "FeatureCollection",
  "title": "Vicus Feniculensis",
  "id": "433197",
  "bbox": [
    14.076529,
    41.013131,
    14.076529,
    41.013131
  ],
  "description": "An ancient place, cited: BAtlas 44 F3 Vicus Feniculensis",
  "names": [
    "Vicus Feniculensis"
  ],
  "features": [
    {
      "type": "Feature",
      "geometry": {
        "type": "Point",
        "coordinates": [
          14.076529,
          41.013131
        ]
      },
      "properties": {
        "description": "representative point"
      }
    },
    {
      "geometry": {
        "type": "Point",
        "coordinates": [
          14.076529,
          41.013131
        ]
      },
      "id": "darmc-location-19010",
      "type": "Feature",
      "properties": {
        "description": "500K scale point location",
        "location_precision": "precise",
        "title": "DARMC location 19010",
        "link": "http://pleiades.stoa.org/places/433197/darmc-location-19010"
      }
    }
  ]
}