{
  "type": "FeatureCollection",
  "title": "Sora",
  "id": "433126",
  "bbox": [
    13.614105,
    41.715723,
    13.614105,
    41.715723
  ],
  "description": "An ancient city of Latium located in the valley of the Liris River that likely had Volscian origins. The Romans captured the city in 345 BCE and later established a colony there in 303 BCE after the Second Samnite War.",
  "connectsWith": [
    "432910",
    "260329424"
  ],
  "names": [
    "Sora",
    "Sora"
  ],
  "features": [
    {
      "type": "Feature",
      "geometry": {
        "type": "Point",
        "coordinates": [
          13.614105,
          41.715723
        ]
      },
      "properties": {
        "description": "representative point"
      }
    },
    {
      "geometry": {
        "type": "Point",
        "coordinates": [
          13.614105,
          41.715723
        ]
      },
      "id": "location-of-sora",
      "type": "Feature",
      "properties": {
        "description": "Location based on OpenStreetMap",
        "location_precision": "precise",
        "title": "location of Sora",
        "link": "http://pleiades.stoa.org/places/433126/location-of-sora"
      }
    }
  ]
}