{
  "type": "FeatureCollection",
  "title": "Torre S. Limato",
  "id": "433159",
  "description": "An ancient place, cited: BAtlas 44 E3 Torre S. Limato",
  "bbox": [
    13.8403487,
    41.139027,
    13.85795,
    41.1587589
  ],
  "reprPoint": [
    13.84914935,
    41.14889295
  ],
  "features": [
    {
      "geometry": {
        "type": "Point",
        "coordinates": [
          13.85795,
          41.139027
        ]
      },
      "id": "darmc-location-7969",
      "type": "Feature",
      "properties": {
        "description": "500K scale point location",
        "location_precision": "precise",
        "title": "DARMC location 7969",
        "link": "http://pleiades.stoa.org/places/433159/darmc-location-7969"
      }
    }
  ]
}