{
  "type": "FeatureCollection",
  "title": "Oakmere hill fort",
  "id": "434003879",
  "bbox": [
    -2.635518,
    53.206022,
    -2.635518,
    53.206022
  ],
  "description": "Oakmere hill fort is an Iron Age hill fort located in the county of Cheshire in northern England.",
  "features": [
    {
      "type": "Feature",
      "geometry": {
        "type": "Point",
        "coordinates": [
          -2.635518,
          53.206022
        ]
      },
      "properties": {
        "description": "representative point"
      }
    },
    {
      "geometry": {
        "type": "Point",
        "coordinates": [
          -2.635518,
          53.206022
        ]
      },
      "id": "location-of-oakmere-hill-fort",
      "type": "Feature",
      "properties": {
        "description": "coordinates after GeoHack.",
        "location_precision": "precise",
        "title": "Imagery location of Oakmere hill fort",
        "link": "http://pleiades.stoa.org/places/434003879/location-of-oakmere-hill-fort"
      }
    }
  ]
}