{
  "type": "FeatureCollection",
  "title": "Apesokari Tholos tomb B",
  "id": "435488939",
  "bbox": [
    24.948853,
    35.0045419,
    24.948853,
    35.0045419
  ],
  "description": "Minoan tomb in the Mesara Plain in south-central Crete constructed during the Early Minoan I period (ca. 3100-2650 BCE) and expanded later in the Prepalatial and Protopalatial periods (through 1700 BCE).",
  "connectsWith": [
    "92986629",
    "633483353"
  ],
  "features": [
    {
      "type": "Feature",
      "geometry": {
        "type": "Point",
        "coordinates": [
          24.948853,
          35.0045419
        ]
      },
      "properties": {
        "description": "representative point"
      }
    },
    {
      "geometry": {
        "type": "Point",
        "coordinates": [
          24.948853,
          35.0045419
        ]
      },
      "id": "apesokari-tholos-tomb-b",
      "type": "Feature",
      "properties": {
        "description": "Point representing the location of Apesokari Tholos Tomb B, derived from an OpenStreetMap Node.",
        "location_precision": "precise",
        "title": "OSM location of Apesokari Tholos Tomb B",
        "link": "http://pleiades.stoa.org/places/435488939/apesokari-tholos-tomb-b"
      }
    }
  ]
}