{
  "type": "FeatureCollection",
  "title": "Capitulum Hernicum",
  "id": "438705",
  "description": "A Hernican town that still existed in Pliny's time, Capitulum Hernicum received colonists under both Sulla and Iulius Caesar.",
  "bbox": [
    13.146399,
    41.8308503,
    13.146399,
    41.8308503
  ],
  "connectsWith": [
    "c858bf31481aa3b94785b5f055bc8eeb"
  ],
  "reprPoint": [
    13.146399,
    41.8308503
  ],
  "names": [
    "Capitulum Hernicum",
    "Kapitoulon"
  ],
  "features": [
    {
      "id": "batlas-location",
      "type": "Feature",
      "properties": {
        "description": null,
        "location_precision": "unlocated",
        "title": "Barrington Atlas location",
        "link": "http://pleiades.stoa.org/places/438705/batlas-location"
      }
    },
    {
      "geometry": {
        "type": "Point",
        "coordinates": [
          13.146399,
          41.8308503
        ]
      },
      "id": "osm-location-of-piglio",
      "type": "Feature",
      "properties": {
        "description": "Representative modern location based on OpenStreetMap.",
        "location_precision": "precise",
        "title": "OSM location of Piglio",
        "link": "http://pleiades.stoa.org/places/438705/osm-location-of-piglio"
      }
    }
  ]
}