{
  "type": "FeatureCollection",
  "title": "Carventum",
  "id": "438707",
  "bbox": [
    12.76944,
    41.72306,
    12.76944,
    41.72306
  ],
  "description": "Carventum was an ancient city of Latium, listed by Dionysius as one of the thirty states of the Latin League.",
  "connectsWith": [
    "422830"
  ],
  "names": [
    "Carventum",
    "Carventon",
    "Arx Carventana"
  ],
  "features": [
    {
      "type": "Feature",
      "geometry": {
        "type": "Point",
        "coordinates": [
          12.76944,
          41.72306
        ]
      },
      "properties": {
        "description": "representative point"
      }
    },
    {
      "geometry": null,
      "id": "batlas-location",
      "type": "Feature",
      "properties": {
        "description": null,
        "location_precision": "unlocated",
        "title": "Barrington Atlas location",
        "link": "http://pleiades.stoa.org/places/438707/batlas-location"
      }
    }
  ]
}