{
  "type": "FeatureCollection",
  "title": "Capitulum Hernicum",
  "id": "438705",
  "bbox": [
    13.146399,
    41.8308503,
    13.146399,
    41.8308503
  ],
  "description": "A Hernican town that still existed in Pliny's time, Capitulum Hernicum received colonists under both Sulla and Iulius Caesar. An inscription found in the area of Piglio mentions the town, but its precise location is uncertain.",
  "connectsWith": [
    "422944"
  ],
  "names": [
    "Capitulum Hernicum",
    "Kapitoulon"
  ],
  "features": [
    {
      "type": "Feature",
      "geometry": {
        "type": "Point",
        "coordinates": [
          13.146399,
          41.8308503
        ]
      },
      "properties": {
        "description": "representative point"
      }
    },
    {
      "geometry": {
        "type": "Point",
        "coordinates": [
          13.146399,
          41.8308503
        ]
      },
      "id": "osm-location-of-piglio",
      "type": "Feature",
      "properties": {
        "description": "Representative modern location based on OpenStreetMap.",
        "location_precision": "precise",
        "title": "OSM location of Piglio",
        "link": "http://pleiades.stoa.org/places/438705/osm-location-of-piglio"
      }
    }
  ]
}