{
  "type": "FeatureCollection",
  "title": "Lion gate of Butrint",
  "id": "439667643",
  "bbox": [
    20.0209896,
    39.7476348,
    20.0209896,
    39.7476348
  ],
  "description": "The so-called \"Lion gate\" of Butrint is a fifth century A.D. gateway that reuses an Archaic Greek sculpted relief.",
  "connectsWith": [
    "530824"
  ],
  "features": [
    {
      "type": "Feature",
      "geometry": {
        "type": "Point",
        "coordinates": [
          20.0209896,
          39.7476348
        ]
      },
      "properties": {
        "description": "representative point"
      }
    },
    {
      "geometry": {
        "type": "Point",
        "coordinates": [
          20.0209896,
          39.7476348
        ]
      },
      "id": "osm-location-of-lion-gate",
      "type": "Feature",
      "properties": {
        "description": "Representative location based on OpenStreetMap.",
        "location_precision": "precise",
        "title": "OSM location of Lion Gate",
        "link": "http://pleiades.stoa.org/places/439667643/osm-location-of-lion-gate"
      }
    }
  ]
}