{
  "type": "FeatureCollection",
  "title": "Castellina del Marangone",
  "id": "440105873",
  "bbox": [
    11.8359528,
    42.0611968,
    11.8359528,
    42.0611968
  ],
  "description": "A small fortified coastal settlement in Etruria occupied from the tenth century B.C. to the first century B.C.",
  "connectsWith": [
    "723746844"
  ],
  "names": [
    "Castellina del Marangone"
  ],
  "features": [
    {
      "type": "Feature",
      "geometry": {
        "type": "Point",
        "coordinates": [
          11.8359528,
          42.0611968
        ]
      },
      "properties": {
        "description": "representative point"
      }
    },
    {
      "geometry": {
        "type": "Point",
        "coordinates": [
          11.8359528,
          42.0611968
        ]
      },
      "id": "osm-location-of-sito-archeologico-la-la-castellina",
      "type": "Feature",
      "properties": {
        "description": "Representative location based on OpenStreetMap",
        "location_precision": "precise",
        "title": "OSM location of Sito Archeologico la \"La Castellina\"",
        "link": "http://pleiades.stoa.org/places/440105873/osm-location-of-sito-archeologico-la-la-castellina"
      }
    }
  ]
}