{
  "type": "FeatureCollection",
  "title": "Ninguaria (island)",
  "id": "440618978",
  "bbox": [
    -16.58,
    28.23,
    -16.58,
    28.23
  ],
  "description": "Known today as Tenerife, this is the largest of the Canary islands.",
  "connectsWith": [
    "149334673"
  ],
  "names": [
    "Ninguaria"
  ],
  "features": [
    {
      "type": "Feature",
      "geometry": {
        "type": "Point",
        "coordinates": [
          -16.58,
          28.23
        ]
      },
      "properties": {
        "description": "representative point"
      }
    },
    {
      "geometry": {
        "type": "Point",
        "coordinates": [
          -16.58,
          28.23
        ]
      },
      "id": "location-of-tenerife",
      "type": "Feature",
      "properties": {
        "description": "Representative point, after BAtlas, confirmed in Google Earth.",
        "location_precision": "precise",
        "title": "Location of Tenerife",
        "link": "http://pleiades.stoa.org/places/440618978/location-of-tenerife"
      }
    }
  ]
}