{
  "type": "FeatureCollection",
  "title": "Scoglietto",
  "id": "441559176",
  "bbox": [
    11.0510954,
    42.6733078,
    11.0510954,
    42.6733078
  ],
  "description": "A Roman sanctuary in use from the first century B.C. through fifth century A.D.",
  "connectsWith": [
    "403285"
  ],
  "features": [
    {
      "type": "Feature",
      "geometry": {
        "type": "Point",
        "coordinates": [
          11.0510954,
          42.6733078
        ]
      },
      "properties": {
        "description": "representative point"
      }
    },
    {
      "geometry": {
        "type": "Point",
        "coordinates": [
          11.0510954,
          42.6733078
        ]
      },
      "id": "location-of-sanctuary",
      "type": "Feature",
      "properties": {
        "description": "Representative location based on OpenStreetMap.",
        "location_precision": "precise",
        "title": "OSM location of Area dei templi dello Scoglietto",
        "link": "http://pleiades.stoa.org/places/441559176/location-of-sanctuary"
      }
    }
  ]
}