{
  "type": "FeatureCollection",
  "title": "Puntone necropolis",
  "id": "441559175",
  "bbox": [
    11.4915911,
    42.6741524,
    11.4915911,
    42.6741524
  ],
  "description": "An Etruscan necropolis dating to the seventh-fifth centuries B.C. The ancient settlement associated with the site may have been Palmule.",
  "connectsWith": [
    "413044"
  ],
  "features": [
    {
      "type": "Feature",
      "geometry": {
        "type": "Point",
        "coordinates": [
          11.4915911,
          42.6741524
        ]
      },
      "properties": {
        "description": "representative point"
      }
    },
    {
      "geometry": {
        "type": "Point",
        "coordinates": [
          11.4915911,
          42.6741524
        ]
      },
      "id": "location-of-necropolis",
      "type": "Feature",
      "properties": {
        "description": "Representative location based on OpenStreetMap.",
        "location_precision": "precise",
        "title": "OSM location of Necropoli Etrusca del Puntone",
        "link": "http://pleiades.stoa.org/places/441559175/location-of-necropolis"
      }
    }
  ]
}