{
  "type": "FeatureCollection",
  "title": "Ad Fluvium Bradanum",
  "id": "442442",
  "bbox": [
    15.810676,
    40.816934,
    15.810676,
    40.816934
  ],
  "description": "An ancient place, cited: BAtlas 45 C3 Ad Fluvium Bradanum",
  "connectsWith": [
    "442508"
  ],
  "names": [
    "Ad Fluvium Bradanum"
  ],
  "features": [
    {
      "type": "Feature",
      "geometry": {
        "type": "Point",
        "coordinates": [
          15.810676,
          40.816934
        ]
      },
      "properties": {
        "description": "representative point"
      }
    },
    {
      "geometry": {
        "type": "Point",
        "coordinates": [
          15.810676,
          40.816934
        ]
      },
      "id": "darmc-location-19232",
      "type": "Feature",
      "properties": {
        "description": "500K scale point location",
        "location_precision": "precise",
        "title": "DARMC location 19232",
        "link": "http://pleiades.stoa.org/places/442442/darmc-location-19232"
      }
    }
  ]
}