{
  "type": "FeatureCollection",
  "title": "Argos Hippium/Arpi/Argyripa",
  "id": "442476",
  "description": "An ancient place, cited: BAtlas 45 C1 Argos Hippium/Arpi/Argyripa",
  "bbox": [
    15.6112812,
    41.5534853,
    15.6112812,
    41.5534853
  ],
  "reprPoint": [
    15.6112812,
    41.5534853
  ],
  "names": [
    "Argos Hippium",
    "Arpi",
    "Argyripa",
    "Argos Hippium"
  ],
  "features": [
    {
      "geometry": {
        "type": "Point",
        "coordinates": [
          15.6112812,
          41.5534853
        ]
      },
      "id": "osm-location-of-passo-di-corvo",
      "type": "Feature",
      "properties": {
        "description": "Representative location based on OpenStreetMap.",
        "location_precision": "precise",
        "title": "OSM location of Passo di Corvo",
        "link": "http://pleiades.stoa.org/places/442476/osm-location-of-passo-di-corvo"
      }
    }
  ]
}