{
  "type": "FeatureCollection",
  "title": "Argos Hippium/Arpi/Argyripa",
  "id": "442476",
  "bbox": [
    15.555444,
    41.475654,
    15.555444,
    41.475654
  ],
  "description": "An ancient place, cited: BAtlas 45 C1 Argos Hippium/Arpi/Argyripa",
  "connectsWith": [
    "92542458"
  ],
  "names": [
    "Argos Hippium",
    "Arpi",
    "Argyripa",
    "Argos Hippium",
    "Area Archeologica di Passo di Corvo",
    "Arpoi",
    "Argyrippa"
  ],
  "features": [
    {
      "type": "Feature",
      "geometry": {
        "type": "Point",
        "coordinates": [
          15.555444,
          41.475654
        ]
      },
      "properties": {
        "description": "representative point"
      }
    },
    {
      "geometry": {
        "type": "Point",
        "coordinates": [
          15.555444,
          41.475654
        ]
      },
      "id": "darmc-location-18205",
      "type": "Feature",
      "properties": {
        "description": "1:500,000 scale representative point location digitized from the Barrington Atlas of the Greek and Roman World by the Digital Atlas of Roman and Medieval Civilizations project at Harvard University.",
        "location_precision": "precise",
        "title": "DARMC location 18205",
        "link": "http://pleiades.stoa.org/places/442476/darmc-location-18205"
      }
    }
  ]
}