{
  "type": "FeatureCollection",
  "title": "Aeclanum",
  "id": "442451",
  "description": "An ancient settlement in Samnium that came to be associated with the Hirpini.",
  "bbox": [
    15.010364,
    41.054064,
    15.010364,
    41.054064
  ],
  "connectsWith": [
    "270868200",
    "356966898"
  ],
  "reprPoint": [
    15.010364,
    41.054064
  ],
  "names": [
    "Aeclanum"
  ],
  "features": [
    {
      "geometry": {
        "type": "Point",
        "coordinates": [
          14.99419,
          41.042508
        ]
      },
      "id": "darmc-location-18157",
      "type": "Feature",
      "properties": {
        "description": "500K scale point location",
        "location_precision": "precise",
        "title": "DARMC location 18157",
        "link": "http://pleiades.stoa.org/places/442451/darmc-location-18157"
      }
    },
    {
      "geometry": {
        "type": "Point",
        "coordinates": [
          15.010364,
          41.054064
        ]
      },
      "id": "dare-location",
      "type": "Feature",
      "properties": {
        "description": "Representative point location, site precision",
        "location_precision": "precise",
        "title": "DARE Location",
        "link": "http://pleiades.stoa.org/places/442451/dare-location"
      }
    }
  ]
}