{
  "type": "FeatureCollection",
  "title": "*Azetium",
  "id": "442491",
  "description": "An ancient place, cited: BAtlas 45 F2 *Azetium",
  "bbox": [
    17.005771,
    41.009167,
    17.005771,
    41.009167
  ],
  "reprPoint": [
    17.005771,
    41.009167
  ],
  "names": [
    "Azetium",
    "Aegetini",
    "Ezetium"
  ],
  "features": [
    {
      "geometry": {
        "type": "Point",
        "coordinates": [
          17.005771,
          41.009167
        ]
      },
      "id": "darmc-location-18231",
      "type": "Feature",
      "properties": {
        "description": "500K scale point location",
        "location_precision": "precise",
        "title": "DARMC location 18231",
        "link": "http://pleiades.stoa.org/places/442491/darmc-location-18231"
      }
    }
  ]
}