{
  "type": "FeatureCollection",
  "title": "Argos Hippium/Arpi/Argyripa",
  "id": "442476",
  "description": "An ancient place, cited: BAtlas 45 C1 Argos Hippium/Arpi/Argyripa",
  "bbox": [
    15.555444,
    41.475654,
    15.555444,
    41.475654
  ],
  "reprPoint": [
    15.555444,
    41.475654
  ],
  "names": [
    "Argos Hippium",
    "Arpi",
    "Argyripa"
  ],
  "features": [
    {
      "geometry": {
        "type": "Point",
        "coordinates": [
          15.555444,
          41.475654
        ]
      },
      "id": "darmc-location-18205",
      "type": "Feature",
      "properties": {
        "description": "500K scale point location",
        "location_precision": "precise",
        "title": "DARMC location 18205",
        "link": "http://pleiades.stoa.org/places/442476/darmc-location-18205"
      }
    }
  ]
}