{
  "type": "FeatureCollection",
  "title": "Atre",
  "id": "442483",
  "bbox": [
    15.743888,
    41.575477,
    15.743888,
    41.575477
  ],
  "description": "An ancient place, cited: BAtlas 45 C1 Atre",
  "names": [
    "Atre"
  ],
  "features": [
    {
      "type": "Feature",
      "geometry": {
        "type": "Point",
        "coordinates": [
          15.743888,
          41.575477
        ]
      },
      "properties": {
        "description": "representative point"
      }
    },
    {
      "geometry": {
        "type": "Point",
        "coordinates": [
          15.743888,
          41.575477
        ]
      },
      "id": "darmc-location-19251",
      "type": "Feature",
      "properties": {
        "description": "500K scale point location",
        "location_precision": "precise",
        "title": "DARMC location 19251",
        "link": "http://pleiades.stoa.org/places/442483/darmc-location-19251"
      }
    }
  ]
}