{
  "type": "FeatureCollection",
  "title": "Forum Novum",
  "id": "442585",
  "bbox": [
    14.9386214,
    41.166408,
    14.9386214,
    41.166408
  ],
  "description": "An ancient place, cited: BAtlas 45 A2 Forum Novum",
  "names": [
    "Forum Novum"
  ],
  "features": [
    {
      "type": "Feature",
      "geometry": {
        "type": "Point",
        "coordinates": [
          14.9386214,
          41.166408
        ]
      },
      "properties": {
        "description": "representative point"
      }
    },
    {
      "geometry": {
        "type": "Point",
        "coordinates": [
          14.9386214,
          41.166408
        ]
      },
      "id": "dare-location",
      "type": "Feature",
      "properties": {
        "description": "Representative point location, village precision",
        "location_precision": "precise",
        "title": "DARE Location",
        "link": "http://pleiades.stoa.org/places/442585/dare-location"
      }
    }
  ]
}