{
  "type": "FeatureCollection",
  "title": "Villa of the Papyri",
  "id": "442522220",
  "description": "A suburban villa located northwest of Herculaneum that was originally owned by Lucius Calpurnius Piso Caesoninus.",
  "bbox": [
    14.3445,
    40.8078,
    14.3445,
    40.8078
  ],
  "connectsWith": [
    "432873"
  ],
  "reprPoint": [
    14.3445,
    40.8078
  ],
  "features": [
    {
      "geometry": {
        "type": "Point",
        "coordinates": [
          14.3445,
          40.8078
        ]
      },
      "id": "location-of-the-villa-of-the-papyri",
      "type": "Feature",
      "properties": {
        "description": "verified in Google Earth 2012",
        "location_precision": "precise",
        "title": "location of the Villa of the Papyri",
        "link": "http://pleiades.stoa.org/places/442522220/location-of-the-villa-of-the-papyri"
      }
    }
  ]
}