{
  "type": "FeatureCollection",
  "title": "Casalbore",
  "id": "442531",
  "bbox": [
    15.0045788,
    41.2334538,
    15.0045788,
    41.2334538
  ],
  "description": "At modern Casalbore, Italy, archaeological evidence includes a significant temple structure and associated material from the Samnite and Roman periods.",
  "features": [
    {
      "type": "Feature",
      "geometry": {
        "type": "Point",
        "coordinates": [
          15.0045788,
          41.2334538
        ]
      },
      "properties": {
        "description": "representative point"
      }
    },
    {
      "geometry": {
        "type": "Point",
        "coordinates": [
          15.0045788,
          41.2334538
        ]
      },
      "id": "osm-location-of-santuario-sannitico-macchia",
      "type": "Feature",
      "properties": {
        "description": "Location based on OpenStreetMap",
        "location_precision": "precise",
        "title": "OSM location of Santuario Sannitico Macchia Porcara",
        "link": "http://pleiades.stoa.org/places/442531/osm-location-of-santuario-sannitico-macchia"
      }
    }
  ]
}