{
  "type": "FeatureCollection",
  "title": "Brundisium/Brentesion",
  "id": "442509",
  "description": "A Greek and Roman port, terminus of the Via Appia.",
  "bbox": [
    17.946867,
    40.641136,
    17.946867,
    40.641136
  ],
  "connectsWith": [
    "1004",
    "356966898"
  ],
  "reprPoint": [
    17.946867,
    40.641136
  ],
  "names": [
    "Brundisium",
    "Brentesion"
  ],
  "features": [
    {
      "geometry": {
        "type": "Point",
        "coordinates": [
          17.938956,
          40.63619
        ]
      },
      "id": "darmc-location-18262",
      "type": "Feature",
      "properties": {
        "description": "500K scale point location",
        "location_precision": "precise",
        "title": "DARMC location 18262",
        "link": "http://pleiades.stoa.org/places/442509/darmc-location-18262"
      }
    },
    {
      "geometry": {
        "type": "Point",
        "coordinates": [
          17.946867,
          40.641136
        ]
      },
      "id": "dare-location",
      "type": "Feature",
      "properties": {
        "description": "Representative point location, site precision",
        "location_precision": "precise",
        "title": "DARE Location",
        "link": "http://pleiades.stoa.org/places/442509/dare-location"
      }
    }
  ]
}