{
  "type": "FeatureCollection",
  "title": "Casalbore",
  "id": "442531",
  "description": "An ancient place, cited: BAtlas 45 B2 Casalbore",
  "bbox": [
    15.007672,
    41.235053,
    15.007672,
    41.235053
  ],
  "reprPoint": [
    15.007672,
    41.235053
  ],
  "features": [
    {
      "geometry": {
        "type": "Point",
        "coordinates": [
          15.007672,
          41.235053
        ]
      },
      "id": "darmc-location-3783",
      "type": "Feature",
      "properties": {
        "description": "500K scale point location",
        "location_precision": "precise",
        "title": "DARMC location 3783",
        "link": "http://pleiades.stoa.org/places/442531/darmc-location-3783"
      }
    }
  ]
}