{
  "type": "FeatureCollection",
  "title": "Compsa",
  "id": "442550",
  "description": "Compsa was a city of the Hirpini, located near the sources of the Aufidus river.",
  "bbox": [
    15.330711,
    40.869305,
    15.330711,
    40.869305
  ],
  "connectsWith": [
    "61b2d51e9b6cacf93d99cd600805e677"
  ],
  "reprPoint": [
    15.330711,
    40.869305
  ],
  "names": [
    "Compsa"
  ],
  "features": [
    {
      "geometry": {
        "type": "Point",
        "coordinates": [
          15.330711,
          40.869305
        ]
      },
      "id": "darmc-location-18365",
      "type": "Feature",
      "properties": {
        "description": "500K scale point location",
        "location_precision": "precise",
        "title": "DARMC location 18365",
        "link": "http://pleiades.stoa.org/places/442550/darmc-location-18365"
      }
    }
  ]
}