{
  "type": "FeatureCollection",
  "title": "Cerbalus (river)",
  "id": "442539",
  "bbox": [
    15.9089346,
    41.5252957,
    15.9089346,
    41.5252957
  ],
  "description": "An ancient place, cited: BAtlas 45 C2 Cerbalus fl.",
  "connectsWith": [
    "1004"
  ],
  "names": [
    "Cerbalus"
  ],
  "features": [
    {
      "type": "Feature",
      "geometry": {
        "type": "Point",
        "coordinates": [
          15.9089346,
          41.5252957
        ]
      },
      "properties": {
        "description": "representative point"
      }
    },
    {
      "geometry": {
        "type": "Point",
        "coordinates": [
          15.9089346,
          41.5252957
        ]
      },
      "id": "location-of-Cerbalus-fl",
      "type": "Feature",
      "properties": {
        "description": "Location based on OpenStreetMap",
        "location_precision": "precise",
        "title": "location of Cerbalus fl.",
        "link": "http://pleiades.stoa.org/places/442539/location-of-Cerbalus-fl"
      }
    }
  ]
}