{
  "type": "FeatureCollection",
  "title": "Compsa",
  "id": "442550",
  "description": "An ancient place, cited: BAtlas 45 B3 Compsa",
  "bbox": [
    15.330711,
    40.869305,
    15.3316242,
    40.871404
  ],
  "reprPoint": [
    15.3311676,
    40.8703545
  ],
  "names": [
    "Compsa"
  ],
  "features": [
    {
      "geometry": {
        "type": "Point",
        "coordinates": [
          15.330711,
          40.869305
        ]
      },
      "id": "darmc-location-18365",
      "type": "Feature",
      "properties": {
        "description": "500K scale point location",
        "location_precision": "precise",
        "title": "DARMC location 18365",
        "link": "http://pleiades.stoa.org/places/442550/darmc-location-18365"
      }
    }
  ]
}