{
  "type": "FeatureCollection",
  "title": "Frigento",
  "id": "442589",
  "bbox": [
    15.100624,
    41.012349,
    15.100624,
    41.012349
  ],
  "description": "An ancient place, cited: BAtlas 45 B2 Frigento",
  "names": [
    "Frigento"
  ],
  "features": [
    {
      "type": "Feature",
      "geometry": {
        "type": "Point",
        "coordinates": [
          15.100624,
          41.012349
        ]
      },
      "properties": {
        "description": "representative point"
      }
    },
    {
      "geometry": {
        "type": "Point",
        "coordinates": [
          15.100624,
          41.012349
        ]
      },
      "id": "darmc-location-18463",
      "type": "Feature",
      "properties": {
        "description": "500K scale point location",
        "location_precision": "precise",
        "title": "DARMC location 18463",
        "link": "http://pleiades.stoa.org/places/442589/darmc-location-18463"
      }
    }
  ]
}