{
  "type": "FeatureCollection",
  "title": "Compsa",
  "id": "442550",
  "bbox": [
    15.330711,
    40.869305,
    15.3316242,
    40.871404
  ],
  "description": "Compsa was a city of the Hirpini, located near the sources of the Aufidus river.",
  "connectsWith": [
    "442614"
  ],
  "names": [
    "Compsa"
  ],
  "features": [
    {
      "type": "Feature",
      "geometry": {
        "type": "Point",
        "coordinates": [
          15.3311676,
          40.8703545
        ]
      },
      "properties": {
        "description": "representative point"
      }
    },
    {
      "geometry": {
        "type": "Point",
        "coordinates": [
          15.330711,
          40.869305
        ]
      },
      "id": "darmc-location-18365",
      "type": "Feature",
      "properties": {
        "description": "1:500,000 scale representative point location digitized from the Barrington Atlas of the Greek and Roman World by the Digital Atlas of Roman and Medieval Civilizations project at Harvard University.",
        "location_precision": "precise",
        "title": "DARMC location 18365",
        "link": "http://pleiades.stoa.org/places/442550/darmc-location-18365"
      }
    },
    {
      "geometry": {
        "type": "Point",
        "coordinates": [
          15.3316242,
          40.871404
        ]
      },
      "id": "location-of-archaeological-area",
      "type": "Feature",
      "properties": {
        "description": "Location based on OpenStreetMap",
        "location_precision": "precise",
        "title": "OSM location of archaeological area",
        "link": "http://pleiades.stoa.org/places/442550/location-of-archaeological-area"
      }
    }
  ]
}