{
  "type": "FeatureCollection",
  "title": "Craco",
  "id": "442558",
  "description": "An ancient place, cited: BAtlas 45 D4 Craco",
  "bbox": [
    16.436332,
    40.380276,
    16.436332,
    40.380276
  ],
  "reprPoint": [
    16.436332,
    40.380276
  ],
  "features": [
    {
      "geometry": {
        "type": "Point",
        "coordinates": [
          16.436332,
          40.380276
        ]
      },
      "id": "darmc-location-18386",
      "type": "Feature",
      "properties": {
        "description": "500K scale point location",
        "location_precision": "precise",
        "title": "DARMC location 18386",
        "link": "http://pleiades.stoa.org/places/442558/darmc-location-18386"
      }
    }
  ]
}