{
  "type": "FeatureCollection",
  "title": "Hera, T.",
  "id": "442611",
  "description": "The so-called 'Tavole Palatine' is the site of the ruins of a sixth century BC Doric temple sacred to Hera and associated with the city of Metapontum.",
  "bbox": [
    16.81695,
    40.416189,
    16.81695,
    40.416189
  ],
  "connectsWith": [
    "442658"
  ],
  "reprPoint": [
    16.81695,
    40.416189
  ],
  "names": [
    "Hera, T."
  ],
  "features": [
    {
      "geometry": {
        "type": "Point",
        "coordinates": [
          16.81695,
          40.416189
        ]
      },
      "id": "darmc-location-7657",
      "type": "Feature",
      "properties": {
        "description": "500K scale point location",
        "location_precision": "precise",
        "title": "DARMC location 7657",
        "link": "http://pleiades.stoa.org/places/442611/darmc-location-7657"
      }
    }
  ]
}