{
  "type": "FeatureCollection",
  "title": "*Grumum",
  "id": "442604",
  "description": "An ancient place, cited: BAtlas 45 E2 *Grumum",
  "bbox": [
    16.708079,
    41.011963,
    16.708079,
    41.011963
  ],
  "reprPoint": [
    16.708079,
    41.011963
  ],
  "names": [
    "Grumum",
    "Grumbestini"
  ],
  "features": [
    {
      "geometry": {
        "type": "Point",
        "coordinates": [
          16.708079,
          41.011963
        ]
      },
      "id": "darmc-location-18117",
      "type": "Feature",
      "properties": {
        "description": "500K scale point location",
        "location_precision": "precise",
        "title": "DARMC location 18117",
        "link": "http://pleiades.stoa.org/places/442604/darmc-location-18117"
      }
    }
  ]
}