{
  "type": "FeatureCollection",
  "title": "Temple of Hera at Foce del Sele",
  "id": "442610",
  "bbox": [
    14.9694937,
    40.489303,
    14.9694937,
    40.489303
  ],
  "description": "A sanctuary at the mouth of the Sele river in Italy with an octastyle temple dedicated to the Argive Hera.",
  "connectsWith": [
    "442733",
    "442795"
  ],
  "features": [
    {
      "type": "Feature",
      "geometry": {
        "type": "Point",
        "coordinates": [
          14.9694937,
          40.489303
        ]
      },
      "properties": {
        "description": "representative point"
      }
    },
    {
      "geometry": {
        "type": "Point",
        "coordinates": [
          14.9694937,
          40.489303
        ]
      },
      "id": "location-of-argive-heraion",
      "type": "Feature",
      "properties": {
        "description": "Location based on OpenStreetMap",
        "location_precision": "precise",
        "title": "OSM location of Argive Heraion at Foce del Sele",
        "link": "http://pleiades.stoa.org/places/442610/location-of-argive-heraion"
      }
    }
  ]
}