{
  "type": "FeatureCollection",
  "title": "Leonessa",
  "id": "442631",
  "bbox": [
    15.604385,
    41.077678,
    15.604385,
    41.077678
  ],
  "description": "An ancient place, cited: BAtlas 45 C2 Leonessa",
  "features": [
    {
      "type": "Feature",
      "geometry": {
        "type": "Point",
        "coordinates": [
          15.604385,
          41.077678
        ]
      },
      "properties": {
        "description": "representative point"
      }
    },
    {
      "geometry": {
        "type": "Point",
        "coordinates": [
          15.604385,
          41.077678
        ]
      },
      "id": "darmc-location-18512",
      "type": "Feature",
      "properties": {
        "description": "500K scale point location",
        "location_precision": "precise",
        "title": "DARMC location 18512",
        "link": "http://pleiades.stoa.org/places/442631/darmc-location-18512"
      }
    }
  ]
}