{
  "type": "FeatureCollection",
  "title": "Temple of Hera at Foce del Sele",
  "id": "442610",
  "description": "A sanctuary at the mouth of the Sele river in Italy with an octastyle temple dedicated to the Argive Hera.",
  "bbox": [
    14.9694937,
    40.481775,
    14.971578,
    40.489303
  ],
  "reprPoint": [
    14.9701884667,
    40.4867936667
  ],
  "features": [
    {
      "geometry": {
        "type": "Point",
        "coordinates": [
          14.971578,
          40.481775
        ]
      },
      "id": "darmc-location-7656",
      "type": "Feature",
      "properties": {
        "description": "500K scale point location",
        "location_precision": "precise",
        "title": "DARMC location 7656",
        "link": "http://pleiades.stoa.org/places/442610/darmc-location-7656"
      }
    },
    {
      "geometry": {
        "type": "Point",
        "coordinates": [
          14.9694937,
          40.489303
        ]
      },
      "id": "location-of-argive-heraion",
      "type": "Feature",
      "properties": {
        "description": "Location based on OpenStreetMap",
        "location_precision": "precise",
        "title": "location of Argive Heraion at Foce del Sele",
        "link": "http://pleiades.stoa.org/places/442610/location-of-argive-heraion"
      }
    }
  ]
}