{
  "type": "FeatureCollection",
  "title": "Monte Salete",
  "id": "442672",
  "description": "An ancient place, cited: BAtlas 45 F3 Monte Salete",
  "bbox": [
    17.357788,
    40.562522,
    17.357788,
    40.562522
  ],
  "reprPoint": [
    17.357788,
    40.562522
  ],
  "features": [
    {
      "geometry": {
        "type": "Point",
        "coordinates": [
          17.357788,
          40.562522
        ]
      },
      "id": "darmc-location-18652",
      "type": "Feature",
      "properties": {
        "description": "500K scale point location",
        "location_precision": "precise",
        "title": "DARMC location 18652",
        "link": "http://pleiades.stoa.org/places/442672/darmc-location-18652"
      }
    }
  ]
}