{
  "type": "FeatureCollection",
  "title": "Hera temple",
  "id": "442611",
  "bbox": [
    16.8165703,
    40.4161654,
    16.81695,
    40.416189
  ],
  "description": "The so-called 'Tavole Palatine' is the site of the ruins of a sixth century B.C. Doric temple sacred to Hera and associated with the city of Metapontum.",
  "connectsWith": [
    "442658"
  ],
  "names": [
    "Hera, T.",
    "Tavole Palatine"
  ],
  "features": [
    {
      "type": "Feature",
      "geometry": {
        "type": "Point",
        "coordinates": [
          16.8165703,
          40.4161654
        ]
      },
      "properties": {
        "description": "representative point"
      }
    },
    {
      "geometry": {
        "type": "Point",
        "coordinates": [
          16.81695,
          40.416189
        ]
      },
      "id": "darmc-location-7657",
      "type": "Feature",
      "properties": {
        "description": "500K scale point location",
        "location_precision": "precise",
        "title": "DARMC location 7657",
        "link": "http://pleiades.stoa.org/places/442611/darmc-location-7657"
      }
    },
    {
      "geometry": {
        "type": "Point",
        "coordinates": [
          16.8165703,
          40.4161654
        ]
      },
      "id": "osm-location",
      "type": "Feature",
      "properties": {
        "description": "Location based on OpenStreetMap",
        "location_precision": "precise",
        "title": "OSM location of Santuario di Hera (Tavole Palatine)",
        "link": "http://pleiades.stoa.org/places/442611/osm-location"
      }
    }
  ]
}