{
  "type": "FeatureCollection",
  "title": "Li Castelli",
  "id": "442635",
  "description": "An ancient place, cited: BAtlas 45 G4 Li Castelli",
  "bbox": [
    17.690031,
    40.339914,
    17.690031,
    40.339914
  ],
  "reprPoint": [
    17.690031,
    40.339914
  ],
  "features": [
    {
      "geometry": {
        "type": "Point",
        "coordinates": [
          17.690031,
          40.339914
        ]
      },
      "id": "darmc-location-18515",
      "type": "Feature",
      "properties": {
        "description": "500K scale point location",
        "location_precision": "precise",
        "title": "DARMC location 18515",
        "link": "http://pleiades.stoa.org/places/442635/darmc-location-18515"
      }
    }
  ]
}