{
  "type": "FeatureCollection",
  "title": "Neretum",
  "id": "442688",
  "bbox": [
    18.030423,
    40.175928,
    18.030423,
    40.175928
  ],
  "description": "An ancient settlement of the Messapii in Apulia captured by the Romans in 269 BC. The Trajanic extension of the Via Appia ran through the site.",
  "connectsWith": [
    "442657",
    "356966898"
  ],
  "names": [
    "Neretum",
    "Nardò"
  ],
  "features": [
    {
      "type": "Feature",
      "geometry": {
        "type": "Point",
        "coordinates": [
          18.030423,
          40.175928
        ]
      },
      "properties": {
        "description": "representative point"
      }
    },
    {
      "geometry": {
        "type": "Point",
        "coordinates": [
          18.030423,
          40.175928
        ]
      },
      "id": "darmc-location-18695",
      "type": "Feature",
      "properties": {
        "description": "500K scale point location",
        "location_precision": "precise",
        "title": "DARMC location 18695",
        "link": "http://pleiades.stoa.org/places/442688/darmc-location-18695"
      }
    }
  ]
}