{
  "type": "FeatureCollection",
  "title": "Muro Maurizio",
  "id": "442683",
  "description": "An ancient place, cited: BAtlas 45 G3 Muro Maurizio",
  "bbox": [
    17.809247,
    40.559863,
    17.809247,
    40.559863
  ],
  "reprPoint": [
    17.809247,
    40.559863
  ],
  "features": [
    {
      "geometry": {
        "type": "Point",
        "coordinates": [
          17.809247,
          40.559863
        ]
      },
      "id": "darmc-location-18682",
      "type": "Feature",
      "properties": {
        "description": "500K scale point location",
        "location_precision": "precise",
        "title": "DARMC location 18682",
        "link": "http://pleiades.stoa.org/places/442683/darmc-location-18682"
      }
    }
  ]
}