{
  "type": "FeatureCollection",
  "title": "Sal(a)pia(i)/Elpia",
  "id": "442758",
  "description": "An ancient place, cited: BAtlas 45 C2 Sal(a)pia(i)/Elpia",
  "bbox": [
    15.932012,
    41.393416,
    15.987731,
    41.403731
  ],
  "reprPoint": [
    15.9598715,
    41.3985735
  ],
  "names": [
    "Salapia",
    "Salpiai",
    "Salapiai",
    "Salpia",
    "Elpia"
  ],
  "features": [
    {
      "geometry": {
        "type": "Point",
        "coordinates": [
          15.932012,
          41.393416
        ]
      },
      "id": "darmc-location-18414",
      "type": "Feature",
      "properties": {
        "description": "500K scale point location",
        "location_precision": "precise",
        "title": "DARMC location 18414",
        "link": "http://pleiades.stoa.org/places/442758/darmc-location-18414"
      }
    },
    {
      "geometry": {
        "type": "Point",
        "coordinates": [
          15.987731,
          41.403731
        ]
      },
      "id": "darmc-location-18859",
      "type": "Feature",
      "properties": {
        "description": "500K scale point location",
        "location_precision": "precise",
        "title": "DARMC location 18859",
        "link": "http://pleiades.stoa.org/places/442758/darmc-location-18859"
      }
    }
  ]
}