{
  "type": "FeatureCollection",
  "title": "Pontecagnano",
  "id": "442728",
  "bbox": [
    14.871604,
    40.6465,
    14.871604,
    40.6465
  ],
  "description": "The ancient settlement of Pontecagnano is located on the plain of the Sele river, about 4 km from the sea. Settlement begins in the Chalcolithic period. The Early Iron Age sees the arrival of people identified as Villanovans who originated in South Etruria, initiating a proto-urban phase of the settlement covering some 80 ha.",
  "connectsWith": [
    "544710173",
    "442795"
  ],
  "features": [
    {
      "type": "Feature",
      "geometry": {
        "type": "Point",
        "coordinates": [
          14.871604,
          40.6465
        ]
      },
      "properties": {
        "description": "representative point"
      }
    },
    {
      "geometry": {
        "type": "Point",
        "coordinates": [
          14.871604,
          40.6465
        ]
      },
      "id": "darmc-location-18798",
      "type": "Feature",
      "properties": {
        "description": "500K scale point location",
        "location_precision": "precise",
        "title": "DARMC location 18798",
        "link": "http://pleiades.stoa.org/places/442728/darmc-location-18798"
      }
    }
  ]
}