{
  "type": "FeatureCollection",
  "title": "Pisciolo",
  "id": "442721",
  "bbox": [
    15.335012,
    40.952407,
    15.335012,
    40.952407
  ],
  "description": "An ancient place, cited: BAtlas 45 C2 Pisciolo",
  "features": [
    {
      "type": "Feature",
      "geometry": {
        "type": "Point",
        "coordinates": [
          15.335012,
          40.952407
        ]
      },
      "properties": {
        "description": "representative point"
      }
    },
    {
      "geometry": {
        "type": "Point",
        "coordinates": [
          15.335012,
          40.952407
        ]
      },
      "id": "darmc-location-28767",
      "type": "Feature",
      "properties": {
        "description": "500K scale point location",
        "location_precision": "precise",
        "title": "DARMC location 28767",
        "link": "http://pleiades.stoa.org/places/442721/darmc-location-28767"
      }
    }
  ]
}