{
  "type": "FeatureCollection",
  "title": "Ruvo",
  "id": "442755",
  "bbox": [
    15.542359,
    40.849764,
    15.542359,
    40.849764
  ],
  "description": "An ancient place, cited: BAtlas 45 C3 Ruvo",
  "features": [
    {
      "type": "Feature",
      "geometry": {
        "type": "Point",
        "coordinates": [
          15.542359,
          40.849764
        ]
      },
      "properties": {
        "description": "representative point"
      }
    },
    {
      "geometry": {
        "type": "Point",
        "coordinates": [
          15.542359,
          40.849764
        ]
      },
      "id": "darmc-location-18836",
      "type": "Feature",
      "properties": {
        "description": "500K scale point location",
        "location_precision": "precise",
        "title": "DARMC location 18836",
        "link": "http://pleiades.stoa.org/places/442755/darmc-location-18836"
      }
    }
  ]
}