{
  "type": "FeatureCollection",
  "title": "Satrianum",
  "id": "442788",
  "description": "An ancient place, cited: BAtlas 45 C3 Satrianum",
  "bbox": [
    15.629515,
    40.559001,
    15.629515,
    40.559001
  ],
  "reprPoint": [
    15.629515,
    40.559001
  ],
  "names": [
    "Satrianum"
  ],
  "features": [
    {
      "geometry": {
        "type": "Point",
        "coordinates": [
          15.629515,
          40.559001
        ]
      },
      "id": "darmc-location-18867",
      "type": "Feature",
      "properties": {
        "description": "500K scale point location",
        "location_precision": "precise",
        "title": "DARMC location 18867",
        "link": "http://pleiades.stoa.org/places/442788/darmc-location-18867"
      }
    }
  ]
}