{
  "type": "FeatureCollection",
  "title": "Pontecagnano",
  "id": "442728",
  "bbox": [
    14.871604,
    40.6465,
    14.871604,
    40.6465
  ],
  "description": "An ancient place, cited: BAtlas 45 A3 Pontecagnano",
  "features": [
    {
      "type": "Feature",
      "geometry": {
        "type": "Point",
        "coordinates": [
          14.871604,
          40.6465
        ]
      },
      "properties": {
        "description": "representative point"
      }
    },
    {
      "geometry": {
        "type": "Point",
        "coordinates": [
          14.871604,
          40.6465
        ]
      },
      "id": "darmc-location-18798",
      "type": "Feature",
      "properties": {
        "description": "500K scale point location",
        "location_precision": "precise",
        "title": "DARMC location 18798",
        "link": "http://pleiades.stoa.org/places/442728/darmc-location-18798"
      }
    }
  ]
}