{
  "type": "FeatureCollection",
  "title": "Punta della Carpinina",
  "id": "442738",
  "description": "An ancient place, cited: BAtlas 45 B4 Punta della Carpinina",
  "bbox": [
    15.019797,
    40.25535,
    15.019797,
    40.25535
  ],
  "reprPoint": [
    15.019797,
    40.25535
  ],
  "features": [
    {
      "geometry": {
        "type": "Point",
        "coordinates": [
          15.019797,
          40.25535
        ]
      },
      "id": "darmc-location-19182",
      "type": "Feature",
      "properties": {
        "description": "500K scale point location",
        "location_precision": "precise",
        "title": "DARMC location 19182",
        "link": "http://pleiades.stoa.org/places/442738/darmc-location-19182"
      }
    }
  ]
}