{
  "type": "FeatureCollection",
  "title": "Toritto",
  "id": "442822",
  "description": "An ancient place, cited: BAtlas 45 E3 Toritto",
  "bbox": [
    16.680612,
    40.999245,
    16.680612,
    40.999245
  ],
  "reprPoint": [
    16.680612,
    40.999245
  ],
  "features": [
    {
      "geometry": {
        "type": "Point",
        "coordinates": [
          16.680612,
          40.999245
        ]
      },
      "id": "darmc-location-18948",
      "type": "Feature",
      "properties": {
        "description": "500K scale point location",
        "location_precision": "precise",
        "title": "DARMC location 18948",
        "link": "http://pleiades.stoa.org/places/442822/darmc-location-18948"
      }
    }
  ]
}