{
  "type": "FeatureCollection",
  "title": "Urias Sinus",
  "id": "442840",
  "bbox": [
    15.6777981,
    41.90489,
    15.6777981,
    41.90489
  ],
  "description": "An ancient place, cited: BAtlas 45 C1 Urias Sinus",
  "names": [
    "Urias Sinus"
  ],
  "features": [
    {
      "type": "Feature",
      "geometry": {
        "type": "Point",
        "coordinates": [
          15.6777981,
          41.90489
        ]
      },
      "properties": {
        "description": "representative point"
      }
    },
    {
      "geometry": {
        "type": "Point",
        "coordinates": [
          15.6777981,
          41.90489
        ]
      },
      "id": "location-of-urias-sinus",
      "type": "Feature",
      "properties": {
        "description": "Location based on OpenStreetMap",
        "location_precision": "precise",
        "title": "location of Urias Sinus",
        "link": "http://pleiades.stoa.org/places/442840/location-of-urias-sinus"
      }
    }
  ]
}