{
  "type": "FeatureCollection",
  "title": "Soletum",
  "id": "442801",
  "description": "Soletum was a settlement in ancient Calabria.",
  "bbox": [
    18.207212,
    40.189577,
    18.207212,
    40.189577
  ],
  "reprPoint": [
    18.207212,
    40.189577
  ],
  "names": [
    "Soletum"
  ],
  "features": [
    {
      "geometry": {
        "type": "Point",
        "coordinates": [
          18.207212,
          40.189577
        ]
      },
      "id": "darmc-location-18892",
      "type": "Feature",
      "properties": {
        "description": "500K scale point location",
        "location_precision": "precise",
        "title": "DARMC location 18892",
        "link": "http://pleiades.stoa.org/places/442801/darmc-location-18892"
      }
    }
  ]
}