{
  "type": "FeatureCollection",
  "title": "Podere Tartuchino",
  "id": "445462065",
  "bbox": [
    11.4899711,
    42.7098413,
    11.4899711,
    42.7098413
  ],
  "description": "An Etruscan farm site located in the Albegna valley.",
  "connectsWith": [
    "413006"
  ],
  "features": [
    {
      "type": "Feature",
      "geometry": {
        "type": "Point",
        "coordinates": [
          11.4899711,
          42.7098413
        ]
      },
      "properties": {
        "description": "representative point"
      }
    },
    {
      "geometry": {
        "type": "Point",
        "coordinates": [
          11.4899711,
          42.7098413
        ]
      },
      "id": "osm-location-of-podere-tartuchino",
      "type": "Feature",
      "properties": {
        "description": "Location based on OpenStreetMap",
        "location_precision": "precise",
        "title": "OSM location of Podere Tartuchino",
        "link": "http://pleiades.stoa.org/places/445462065/osm-location-of-podere-tartuchino"
      }
    }
  ]
}