{
  "type": "FeatureCollection",
  "title": "Podere Tartuchino",
  "id": "445462065",
  "bbox": [
    11.1920328,
    42.5014587,
    11.5212619,
    42.8408721
  ],
  "description": "An Etruscan farm site located in the Albegna valley.",
  "connectsWith": [
    "413006"
  ],
  "features": [
    {
      "type": "Feature",
      "geometry": {
        "type": "Point",
        "coordinates": [
          11.3958173961,
          42.6606852834
        ]
      },
      "properties": {
        "description": "representative point"
      }
    }
  ]
}