{
  "type": "FeatureCollection",
  "title": "Forum Iulium",
  "id": "445545537",
  "bbox": [
    12.4847317,
    41.891775,
    12.486137,
    41.8941045
  ],
  "description": "The Forum Iulium (or Forum of Caesar, Forum Caesaris) is a forum built by Iulius Caesar and dedicated ca. 46 B.C. The main cult of the forum is that of Venus Genetrix.",
  "connectsWith": [
    "423025",
    "502866838"
  ],
  "names": [
    "Forum Iulium",
    "Forum Caesaris"
  ],
  "features": [
    {
      "type": "Feature",
      "geometry": {
        "type": "Point",
        "coordinates": [
          12.4847743943,
          41.8940673767
        ]
      },
      "properties": {
        "description": "representative point"
      }
    }
  ]
}