{
  "type": "FeatureCollection",
  "title": "Comblessac",
  "id": "44707452",
  "description": "A heptagonal Gallo-Roman temple.",
  "bbox": [
    -2.0997685,
    47.8455833,
    -2.0997685,
    47.8455833
  ],
  "reprPoint": [
    -2.0997685,
    47.8455833
  ],
  "features": [
    {
      "geometry": {
        "type": "Point",
        "coordinates": [
          -2.0997685,
          47.8455833
        ]
      },
      "id": "osm-location-of-temple-romano-celtique-heptagonal",
      "type": "Feature",
      "properties": {
        "description": "Representative location based on OpenStreetMap.",
        "location_precision": "precise",
        "title": "OSM location of Temple romano-celtique heptagonal",
        "link": "http://pleiades.stoa.org/places/44707452/osm-location-of-temple-romano-celtique-heptagonal"
      }
    }
  ]
}