{
  "type": "FeatureCollection",
  "title": "Unstan Chambered Cairn",
  "id": "447888851",
  "bbox": [
    -3.2495928,
    58.9866538,
    -3.2495928,
    58.9866538
  ],
  "description": "A Neolithic chambered cairn dating to the fourth and third millennia BC.",
  "connectsWith": [
    "89261"
  ],
  "features": [
    {
      "type": "Feature",
      "geometry": {
        "type": "Point",
        "coordinates": [
          -3.2495928,
          58.9866538
        ]
      },
      "properties": {
        "description": "representative point"
      }
    },
    {
      "geometry": {
        "type": "Point",
        "coordinates": [
          -3.2495928,
          58.9866538
        ]
      },
      "id": "location-of-unstan-chambered-cairn",
      "type": "Feature",
      "properties": {
        "description": "Representative location based on OpenStreetMap.",
        "location_precision": "precise",
        "title": "OSM location of Unstan Chambered Cairn",
        "link": "http://pleiades.stoa.org/places/447888851/location-of-unstan-chambered-cairn"
      }
    }
  ]
}