{
  "type": "FeatureCollection",
  "title": "Ayios Filon",
  "id": "448083500",
  "bbox": [
    34.3737387,
    35.6298295,
    34.3737387,
    35.6298295
  ],
  "description": "A ruined fifth-century CE basilica on the Karpass peninsula of Cyprus.",
  "connectsWith": [
    "707498"
  ],
  "names": [
    "Ágios Fílon"
  ],
  "features": [
    {
      "type": "Feature",
      "geometry": {
        "type": "Point",
        "coordinates": [
          34.3737387,
          35.6298295
        ]
      },
      "properties": {
        "description": "representative point"
      }
    },
    {
      "geometry": {
        "type": "Point",
        "coordinates": [
          34.3737387,
          35.6298295
        ]
      },
      "id": "location-of-ag-philon",
      "type": "Feature",
      "properties": {
        "description": "Representative location based on OpenStreetMap",
        "location_precision": "precise",
        "title": "OSM location of Ayios Filon",
        "link": "http://pleiades.stoa.org/places/448083500/location-of-ag-philon"
      }
    }
  ]
}