{
  "type": "FeatureCollection",
  "title": "Kastro Phaneromenis/Kastro Kochylou",
  "id": "451513645",
  "bbox": [
    24.94858,
    37.79931,
    24.94858,
    37.79931
  ],
  "description": "One of the two known Genovese fortresses on Andros.",
  "connectsWith": [
    "589693"
  ],
  "names": [
    "Kastro Phaneromenis",
    "Kastro Kochylou"
  ],
  "features": [
    {
      "type": "Feature",
      "geometry": {
        "type": "Point",
        "coordinates": [
          24.94858,
          37.79931
        ]
      },
      "properties": {
        "description": "representative point"
      }
    },
    {
      "geometry": {
        "type": "Point",
        "coordinates": [
          24.94858,
          37.79931
        ]
      },
      "id": "cfl-ago-location-kastro-phaneromenis-kastro-kochylou",
      "type": "Feature",
      "properties": {
        "description": "Genovese fortress, located North-North/East of Kochylos, Andros.",
        "location_precision": "precise",
        "title": "CFL/AGO Location: Kastro Phaneromenis, Kastro Kochylou",
        "link": "http://pleiades.stoa.org/places/451513645/cfl-ago-location-kastro-phaneromenis-kastro-kochylou"
      }
    }
  ]
}