{
  "type": "FeatureCollection",
  "title": "House of Marcus Lucretius",
  "id": "452016171",
  "bbox": [
    14.4869243,
    40.7510258,
    14.4869243,
    40.7510258
  ],
  "description": "The House of Marcus Lucretius was excavated in 1846 and 1851.",
  "connectsWith": [
    "680072866",
    "433032"
  ],
  "names": [
    "Casa delle Suonatrici",
    "House of Marcus Lucretius",
    "IX.3.5",
    "Casa di Marco Lucrezio"
  ],
  "features": [
    {
      "type": "Feature",
      "geometry": {
        "type": "Point",
        "coordinates": [
          14.4869243,
          40.7510258
        ]
      },
      "properties": {
        "description": "representative point"
      }
    },
    {
      "geometry": {
        "type": "Point",
        "coordinates": [
          14.4869243,
          40.7510258
        ]
      },
      "id": "osm-location-of-domus-lucreti",
      "type": "Feature",
      "properties": {
        "description": "Representative location based on OpenStreetMap",
        "location_precision": "precise",
        "title": "OSM location of Domus Lucreti",
        "link": "http://pleiades.stoa.org/places/452016171/osm-location-of-domus-lucreti"
      }
    }
  ]
}