{
  "type": "FeatureCollection",
  "title": "Camerelle",
  "id": "452281",
  "description": "An ancient place, cited: BAtlas 46 D2 Camerelle",
  "bbox": [
    16.2424993,
    39.723335,
    16.29072,
    39.7589979
  ],
  "reprPoint": [
    16.2746464333,
    39.7352226333
  ],
  "features": [
    {
      "geometry": {
        "type": "Point",
        "coordinates": [
          16.29072,
          39.723335
        ]
      },
      "id": "darmc-location-7710",
      "type": "Feature",
      "properties": {
        "description": "500K scale point location",
        "location_precision": "precise",
        "title": "DARMC location 7710",
        "link": "http://pleiades.stoa.org/places/452281/darmc-location-7710"
      }
    },
    {
      "geometry": {
        "type": "Point",
        "coordinates": [
          16.29072,
          39.723335
        ]
      },
      "id": "darmc-location-7711",
      "type": "Feature",
      "properties": {
        "description": "500K scale point location",
        "location_precision": "precise",
        "title": "DARMC location 7711",
        "link": "http://pleiades.stoa.org/places/452281/darmc-location-7711"
      }
    }
  ]
}