{
  "type": "FeatureCollection",
  "title": "Amendolara",
  "id": "452260",
  "description": "An ancient place, cited: BAtlas 46 E2 Amendolara",
  "bbox": [
    16.582314,
    39.952995,
    16.582314,
    39.952995
  ],
  "reprPoint": [
    16.582314,
    39.952995
  ],
  "features": [
    {
      "geometry": {
        "type": "Point",
        "coordinates": [
          16.582314,
          39.952995
        ]
      },
      "id": "darmc-location-18184",
      "type": "Feature",
      "properties": {
        "description": "500K scale point location",
        "location_precision": "precise",
        "title": "DARMC location 18184",
        "link": "http://pleiades.stoa.org/places/452260/darmc-location-18184"
      }
    }
  ]
}