{
  "type": "FeatureCollection",
  "title": "Camerelle Roman Villa",
  "id": "452281",
  "bbox": [
    16.2424993,
    39.7589979,
    16.2424993,
    39.7589979
  ],
  "description": "An ancient place, cited: BAtlas 46 D2 Camerelle",
  "features": [
    {
      "type": "Feature",
      "geometry": {
        "type": "Point",
        "coordinates": [
          16.2424993,
          39.7589979
        ]
      },
      "properties": {
        "description": "representative point"
      }
    },
    {
      "geometry": {
        "type": "Point",
        "coordinates": [
          16.2424993,
          39.7589979
        ]
      },
      "id": "location-of-roman-villa",
      "type": "Feature",
      "properties": {
        "description": "Representative location based on OpenStreetMap.",
        "location_precision": "precise",
        "title": "OSM location of resti di una villa romana",
        "link": "http://pleiades.stoa.org/places/452281/location-of-roman-villa"
      }
    }
  ]
}