{
  "type": "FeatureCollection",
  "title": "Castra Hannibalis",
  "id": "452293",
  "bbox": [
    16.610374,
    38.819771,
    16.610374,
    38.819771
  ],
  "description": "Castra Hannibalis was an ancient town of Bruttium, located on the Gulf of Scyllacium according to Pliny.",
  "names": [
    "Castra Hannibalis",
    "Annibali"
  ],
  "features": [
    {
      "type": "Feature",
      "geometry": {
        "type": "Point",
        "coordinates": [
          16.610374,
          38.819771
        ]
      },
      "properties": {
        "description": "representative point"
      }
    },
    {
      "geometry": {
        "type": "Point",
        "coordinates": [
          16.610374,
          38.819771
        ]
      },
      "id": "darmc-location-19761",
      "type": "Feature",
      "properties": {
        "description": "500K scale point location",
        "location_precision": "precise",
        "title": "DARMC location 19761",
        "link": "http://pleiades.stoa.org/places/452293/darmc-location-19761"
      }
    }
  ]
}