{
  "type": "FeatureCollection",
  "title": "Cersosimo",
  "id": "452298",
  "bbox": [
    16.35088,
    40.048063,
    16.35088,
    40.048063
  ],
  "description": "An ancient place, cited: BAtlas 46 D1 Cersosimo",
  "features": [
    {
      "type": "Feature",
      "geometry": {
        "type": "Point",
        "coordinates": [
          16.35088,
          40.048063
        ]
      },
      "properties": {
        "description": "representative point"
      }
    },
    {
      "geometry": {
        "type": "Point",
        "coordinates": [
          16.35088,
          40.048063
        ]
      },
      "id": "darmc-location-18331",
      "type": "Feature",
      "properties": {
        "description": "500K scale point location",
        "location_precision": "precise",
        "title": "DARMC location 18331",
        "link": "http://pleiades.stoa.org/places/452298/darmc-location-18331"
      }
    }
  ]
}