{
  "type": "FeatureCollection",
  "title": "Ad Columnam",
  "id": "452250",
  "description": "An ancient place, cited: BAtlas 46 C5 Ad Columnam",
  "bbox": [
    15.651754,
    38.191434,
    15.651754,
    38.191434
  ],
  "reprPoint": [
    15.651754,
    38.191434
  ],
  "names": [
    "Ad Columnam"
  ],
  "features": [
    {
      "geometry": {
        "type": "Point",
        "coordinates": [
          15.651754,
          38.191434
        ]
      },
      "id": "darmc-location-19231",
      "type": "Feature",
      "properties": {
        "description": "500K scale point location",
        "location_precision": "precise",
        "title": "DARMC location 19231",
        "link": "http://pleiades.stoa.org/places/452250/darmc-location-19231"
      }
    }
  ]
}