{
  "type": "FeatureCollection",
  "title": "Lokroi Epizephyrioi",
  "id": "452369",
  "description": "An ancient place, cited: BAtlas 46 D5 Lokroi Epizephyrioi",
  "bbox": [
    16.228784,
    38.216171,
    16.259895,
    38.23642
  ],
  "reprPoint": [
    16.2443395,
    38.2262955
  ],
  "names": [
    "Lokroi Epizephyrioi",
    "Narycia"
  ],
  "features": [
    {
      "geometry": {
        "type": "Point",
        "coordinates": [
          16.259895,
          38.23642
        ]
      },
      "id": "darmc-location-18520",
      "type": "Feature",
      "properties": {
        "description": "500K scale point location",
        "location_precision": "precise",
        "title": "DARMC location 18520",
        "link": "http://pleiades.stoa.org/places/452369/darmc-location-18520"
      }
    },
    {
      "geometry": {
        "type": "Point",
        "coordinates": [
          16.228784,
          38.216171
        ]
      },
      "id": "dare-location",
      "type": "Feature",
      "properties": {
        "description": "Representative point location, site precision",
        "location_precision": "precise",
        "title": "DARE Location",
        "link": "http://pleiades.stoa.org/places/452369/dare-location"
      }
    }
  ]
}