{
  "type": "FeatureCollection",
  "title": "Neaethus (river)",
  "id": "452389",
  "bbox": [
    16.813578,
    39.1716388,
    16.813578,
    39.1716388
  ],
  "description": "An ancient place, cited: BAtlas 46 F3 Neaethus fl.",
  "names": [
    "Neaethus"
  ],
  "features": [
    {
      "type": "Feature",
      "geometry": {
        "type": "Point",
        "coordinates": [
          16.813578,
          39.1716388
        ]
      },
      "properties": {
        "description": "representative point"
      }
    },
    {
      "geometry": {
        "type": "Point",
        "coordinates": [
          16.813578,
          39.1716388
        ]
      },
      "id": "location-of-Neaethus-fl",
      "type": "Feature",
      "properties": {
        "description": "Representative modern location based on OpenStreetMap.",
        "location_precision": "precise",
        "title": "OSM location of Neto (river)",
        "link": "http://pleiades.stoa.org/places/452389/location-of-Neaethus-fl"
      }
    }
  ]
}