{
  "type": "FeatureCollection",
  "title": "Muranum",
  "id": "452386",
  "bbox": [
    16.13737,
    39.842839,
    16.13737,
    39.842839
  ],
  "description": "An ancient place, cited: BAtlas 46 D2 Muranum",
  "connectsWith": [
    "455270"
  ],
  "names": [
    "Muranum",
    "Summuranum"
  ],
  "features": [
    {
      "type": "Feature",
      "geometry": {
        "type": "Point",
        "coordinates": [
          16.13737,
          39.842839
        ]
      },
      "properties": {
        "description": "representative point"
      }
    },
    {
      "geometry": {
        "type": "Point",
        "coordinates": [
          16.13737,
          39.842839
        ]
      },
      "id": "darmc-location-18679",
      "type": "Feature",
      "properties": {
        "description": "500K scale point location",
        "location_precision": "precise",
        "title": "DARMC location 18679",
        "link": "http://pleiades.stoa.org/places/452386/darmc-location-18679"
      }
    }
  ]
}