{
  "type": "FeatureCollection",
  "title": "Grimaldi",
  "id": "452328",
  "description": "An ancient place, cited: BAtlas 46 D3 Grimaldi",
  "bbox": [
    16.236574,
    39.143142,
    16.236574,
    39.143142
  ],
  "reprPoint": [
    16.236574,
    39.143142
  ],
  "features": [
    {
      "geometry": {
        "type": "Point",
        "coordinates": [
          16.236574,
          39.143142
        ]
      },
      "id": "darmc-location-18484",
      "type": "Feature",
      "properties": {
        "description": "500K scale point location",
        "location_precision": "precise",
        "title": "DARMC location 18484",
        "link": "http://pleiades.stoa.org/places/452328/darmc-location-18484"
      }
    }
  ]
}