{
  "type": "FeatureCollection",
  "title": "Palinurus",
  "id": "452398",
  "bbox": [
    15.28813,
    40.035965,
    15.28813,
    40.035965
  ],
  "description": "An ancient place, cited: BAtlas 46 B1 Palinurus",
  "names": [
    "Palinurus"
  ],
  "features": [
    {
      "type": "Feature",
      "geometry": {
        "type": "Point",
        "coordinates": [
          15.28813,
          40.035965
        ]
      },
      "properties": {
        "description": "representative point"
      }
    },
    {
      "geometry": {
        "type": "Point",
        "coordinates": [
          15.28813,
          40.035965
        ]
      },
      "id": "darmc-location-18729",
      "type": "Feature",
      "properties": {
        "description": "500K scale point location",
        "location_precision": "precise",
        "title": "DARMC location 18729",
        "link": "http://pleiades.stoa.org/places/452398/darmc-location-18729"
      }
    }
  ]
}