{
  "type": "FeatureCollection",
  "title": "Croto(n)",
  "id": "452317",
  "description": "An Achaean colony in Magna Graecia established in 710 BC by the oikist Myscellus from the city of Rhypes in the Peloponnese.",
  "bbox": [
    17.128852,
    39.081572,
    17.128852,
    39.081572
  ],
  "reprPoint": [
    17.128852,
    39.081572
  ],
  "names": [
    "Croton",
    "Croto",
    "Crotona"
  ],
  "features": [
    {
      "geometry": {
        "type": "Point",
        "coordinates": [
          17.12708,
          39.080763
        ]
      },
      "id": "darmc-location-18390",
      "type": "Feature",
      "properties": {
        "description": "500K scale point location",
        "location_precision": "precise",
        "title": "DARMC location 18390",
        "link": "http://pleiades.stoa.org/places/452317/darmc-location-18390"
      }
    },
    {
      "geometry": {
        "type": "Point",
        "coordinates": [
          17.128852,
          39.081572
        ]
      },
      "id": "dare-location",
      "type": "Feature",
      "properties": {
        "description": "Representative point location, site precision",
        "location_precision": "precise",
        "title": "DARE Location",
        "link": "http://pleiades.stoa.org/places/452317/dare-location"
      }
    }
  ]
}