{
  "type": "FeatureCollection",
  "title": "Malvito",
  "id": "452373",
  "bbox": [
    16.054221,
    39.600799,
    16.054221,
    39.600799
  ],
  "description": "An ancient place, cited: BAtlas 46 D2 Malvito",
  "features": [
    {
      "type": "Feature",
      "geometry": {
        "type": "Point",
        "coordinates": [
          16.054221,
          39.600799
        ]
      },
      "properties": {
        "description": "representative point"
      }
    },
    {
      "geometry": {
        "type": "Point",
        "coordinates": [
          16.054221,
          39.600799
        ]
      },
      "id": "darmc-location-18569",
      "type": "Feature",
      "properties": {
        "description": "500K scale point location",
        "location_precision": "precise",
        "title": "DARMC location 18569",
        "link": "http://pleiades.stoa.org/places/452373/darmc-location-18569"
      }
    }
  ]
}