{
  "type": "FeatureCollection",
  "title": "Grotteria",
  "id": "452329",
  "bbox": [
    16.265795,
    38.366573,
    16.265795,
    38.366573
  ],
  "description": "An ancient place, cited: BAtlas 46 D5 Grotteria",
  "features": [
    {
      "type": "Feature",
      "geometry": {
        "type": "Point",
        "coordinates": [
          16.265795,
          38.366573
        ]
      },
      "properties": {
        "description": "representative point"
      }
    },
    {
      "geometry": {
        "type": "Point",
        "coordinates": [
          16.265795,
          38.366573
        ]
      },
      "id": "darmc-location-18486",
      "type": "Feature",
      "properties": {
        "description": "500K scale point location",
        "location_precision": "precise",
        "title": "DARMC location 18486",
        "link": "http://pleiades.stoa.org/places/452329/darmc-location-18486"
      }
    }
  ]
}