{
  "type": "FeatureCollection",
  "title": "Lokroi Epizephyrioi",
  "id": "452369",
  "bbox": [
    16.228784,
    38.216171,
    16.259895,
    38.23642
  ],
  "description": "Locri is a town and comune in the province of Reggio Calabria, Calabria, in southern Italy. Epizephyrian Locris was founded ca. 680 BC near modern Capo Zefirio, by the Locrians, apparently under the Opuntii (East Locrians) from the city of Opus, but also including Ozolae (West Locrians) and Lacedaemonians.",
  "connectsWith": [
    "455282"
  ],
  "names": [
    "Lokroi Epizephyrioi",
    "Narycia",
    "Locri"
  ],
  "features": [
    {
      "type": "Feature",
      "geometry": {
        "type": "Point",
        "coordinates": [
          16.2443395,
          38.2262955
        ]
      },
      "properties": {
        "description": "representative point"
      }
    },
    {
      "geometry": {
        "type": "Point",
        "coordinates": [
          16.259895,
          38.23642
        ]
      },
      "id": "darmc-location-18520",
      "type": "Feature",
      "properties": {
        "description": "1:500,000 scale representative point location digitized from the Barrington Atlas of the Greek and Roman World by the Digital Atlas of Roman and Medieval Civilizations project at Harvard University.",
        "location_precision": "precise",
        "title": "DARMC location 18520",
        "link": "http://pleiades.stoa.org/places/452369/darmc-location-18520"
      }
    },
    {
      "geometry": {
        "type": "Point",
        "coordinates": [
          16.228784,
          38.216171
        ]
      },
      "id": "dare-location",
      "type": "Feature",
      "properties": {
        "description": "Representative point location, site precision",
        "location_precision": "precise",
        "title": "DARE Location",
        "link": "http://pleiades.stoa.org/places/452369/dare-location"
      }
    }
  ]
}