{
  "type": "FeatureCollection",
  "title": "Lacinium Pr.",
  "id": "452356",
  "description": "The Capo Colonna, the ancient Promunturium Lacinium, is a cape of Calabria located near Crotone.",
  "bbox": [
    17.2025534,
    39.0242001,
    17.2025534,
    39.0242001
  ],
  "reprPoint": [
    17.2025534,
    39.0242001
  ],
  "names": [
    "Lacinium Pr."
  ],
  "features": [
    {
      "geometry": {
        "type": "Point",
        "coordinates": [
          17.2025534,
          39.0242001
        ]
      },
      "id": "location-of-Lacinium-Pr",
      "type": "Feature",
      "properties": {
        "description": "Location based on OpenStreetMap",
        "location_precision": "precise",
        "title": "location of Lacinium Pr.",
        "link": "http://pleiades.stoa.org/places/452356/location-of-Lacinium-Pr"
      }
    }
  ]
}