{
  "type": "FeatureCollection",
  "title": "Noepoli",
  "id": "452392",
  "description": "An ancient place, cited: BAtlas 46 D1 Noepoli",
  "bbox": [
    16.330641,
    40.087811,
    16.330641,
    40.087811
  ],
  "reprPoint": [
    16.330641,
    40.087811
  ],
  "features": [
    {
      "geometry": {
        "type": "Point",
        "coordinates": [
          16.330641,
          40.087811
        ]
      },
      "id": "darmc-location-18701",
      "type": "Feature",
      "properties": {
        "description": "500K scale point location",
        "location_precision": "precise",
        "title": "DARMC location 18701",
        "link": "http://pleiades.stoa.org/places/452392/darmc-location-18701"
      }
    }
  ]
}