{
  "type": "FeatureCollection",
  "title": "Chiuse delle Grotte",
  "id": "452301",
  "bbox": [
    15.154847,
    40.160643,
    15.154847,
    40.160643
  ],
  "description": "An ancient place, cited: BAtlas 46 B1 Chiuse delle Grotte",
  "features": [
    {
      "type": "Feature",
      "geometry": {
        "type": "Point",
        "coordinates": [
          15.154847,
          40.160643
        ]
      },
      "properties": {
        "description": "representative point"
      }
    },
    {
      "geometry": {
        "type": "Point",
        "coordinates": [
          15.154847,
          40.160643
        ]
      },
      "id": "darmc-location-18337",
      "type": "Feature",
      "properties": {
        "description": "500K scale point location",
        "location_precision": "precise",
        "title": "DARMC location 18337",
        "link": "http://pleiades.stoa.org/places/452301/darmc-location-18337"
      }
    }
  ]
}