{
  "type": "FeatureCollection",
  "title": "Medma",
  "id": "452375",
  "description": "Medma (Rosarno) was an ancient settlement founded from Lokroi Epizephyrioi.",
  "bbox": [
    15.976368,
    38.487328,
    15.976368,
    38.487328
  ],
  "reprPoint": [
    15.976368,
    38.487328
  ],
  "names": [
    "Medma"
  ],
  "features": [
    {
      "geometry": {
        "type": "Point",
        "coordinates": [
          15.976368,
          38.487328
        ]
      },
      "id": "darmc-location-18609",
      "type": "Feature",
      "properties": {
        "description": "500K scale point location",
        "location_precision": "precise",
        "title": "DARMC location 18609",
        "link": "http://pleiades.stoa.org/places/452375/darmc-location-18609"
      }
    }
  ]
}