{
  "type": "FeatureCollection",
  "title": "Siris",
  "id": "452450",
  "description": "Siris was an ancient Greek colonial city of Magna Graecia situated at the mouth of the Siris (modern Sinni) river. The city was founded by Ionian Greeks between 690 and 660 BC.",
  "bbox": [
    16.54137,
    40.149042,
    16.54137,
    40.149042
  ],
  "connectsWith": [
    "452451"
  ],
  "reprPoint": [
    16.54137,
    40.149042
  ],
  "names": [
    "Siris"
  ],
  "features": [
    {
      "geometry": {
        "type": "Point",
        "coordinates": [
          16.54137,
          40.149042
        ]
      },
      "id": "darmc-location-18889",
      "type": "Feature",
      "properties": {
        "description": "500K scale point location",
        "location_precision": "precise",
        "title": "DARMC location 18889",
        "link": "http://pleiades.stoa.org/places/452450/darmc-location-18889"
      }
    }
  ]
}