{
  "type": "FeatureCollection",
  "title": "Piano S. Pietro",
  "id": "452407",
  "description": "An ancient place, cited: BAtlas 46 E1 Piano S. Pietro",
  "bbox": [
    16.640241,
    40.152777,
    16.640241,
    40.152777
  ],
  "reprPoint": [
    16.640241,
    40.152777
  ],
  "features": [
    {
      "geometry": {
        "type": "Point",
        "coordinates": [
          16.640241,
          40.152777
        ]
      },
      "id": "darmc-location-18760",
      "type": "Feature",
      "properties": {
        "description": "500K scale point location",
        "location_precision": "precise",
        "title": "DARMC location 18760",
        "link": "http://pleiades.stoa.org/places/452407/darmc-location-18760"
      }
    }
  ]
}