{
  "type": "FeatureCollection",
  "title": "Piano Sollazzo",
  "id": "452408",
  "description": "An ancient place, cited: BAtlas 46 E1 Piano Sollazzo",
  "bbox": [
    16.526426,
    40.172364,
    16.526426,
    40.172364
  ],
  "reprPoint": [
    16.526426,
    40.172364
  ],
  "features": [
    {
      "geometry": {
        "type": "Point",
        "coordinates": [
          16.526426,
          40.172364
        ]
      },
      "id": "darmc-location-18761",
      "type": "Feature",
      "properties": {
        "description": "500K scale point location",
        "location_precision": "precise",
        "title": "DARMC location 18761",
        "link": "http://pleiades.stoa.org/places/452408/darmc-location-18761"
      }
    }
  ]
}