{
  "type": "FeatureCollection",
  "title": "Scyllaeum Pr.",
  "id": "452438",
  "bbox": [
    15.716667,
    38.25,
    15.716667,
    38.25
  ],
  "description": "An ancient place, cited: BAtlas 46 C5 Scyllaeum Pr.",
  "names": [
    "Scyllaeum Pr."
  ],
  "features": [
    {
      "type": "Feature",
      "geometry": {
        "type": "Point",
        "coordinates": [
          15.716667,
          38.25
        ]
      },
      "properties": {
        "description": "representative point"
      }
    },
    {
      "geometry": {
        "type": "Point",
        "coordinates": [
          15.716667,
          38.25
        ]
      },
      "id": "location-of-scyllaeum-pr",
      "type": "Feature",
      "properties": {
        "description": "Representative location based on GeoHack, verified in Google Earth.",
        "location_precision": "precise",
        "title": "GeoHack location of Scyllaeum Pr.",
        "link": "http://pleiades.stoa.org/places/452438/location-of-scyllaeum-pr"
      }
    }
  ]
}