{
  "type": "FeatureCollection",
  "title": "Spezzano Albanese",
  "id": "452454",
  "description": "An ancient place, cited: BAtlas 46 D2 Spezzano Albanese",
  "bbox": [
    16.3113474,
    39.6696653,
    16.311421,
    39.669841
  ],
  "reprPoint": [
    16.3113842,
    39.66975315
  ],
  "features": [
    {
      "geometry": {
        "type": "Point",
        "coordinates": [
          16.311421,
          39.669841
        ]
      },
      "id": "darmc-location-18898",
      "type": "Feature",
      "properties": {
        "description": "500K scale point location",
        "location_precision": "precise",
        "title": "DARMC location 18898",
        "link": "http://pleiades.stoa.org/places/452454/darmc-location-18898"
      }
    },
    {
      "geometry": {
        "type": "Point",
        "coordinates": [
          16.31134739999993,
          39.6696653
        ]
      },
      "id": "dare-location",
      "type": "Feature",
      "properties": {
        "description": "Representative point location, village precision",
        "location_precision": "precise",
        "title": "DARE Location",
        "link": "http://pleiades.stoa.org/places/452454/dare-location"
      }
    }
  ]
}