{
  "type": "FeatureCollection",
  "title": "Vivarium",
  "id": "452492",
  "description": "An ancient place, cited: BAtlas 46 E4 Vivarium",
  "bbox": [
    16.55254,
    38.737999,
    16.55254,
    38.737999
  ],
  "reprPoint": [
    16.55254,
    38.737999
  ],
  "names": [
    "Vivarium"
  ],
  "features": [
    {
      "geometry": {
        "type": "Point",
        "coordinates": [
          16.55254,
          38.737999
        ]
      },
      "id": "darmc-location-2126",
      "type": "Feature",
      "properties": {
        "description": "500K scale point location",
        "location_precision": "precise",
        "title": "DARMC location 2126",
        "link": "http://pleiades.stoa.org/places/452492/darmc-location-2126"
      }
    }
  ]
}