{
  "type": "FeatureCollection",
  "title": "Assur Archive 52b",
  "id": "452563773",
  "bbox": [
    43.257781,
    35.455694,
    43.257781,
    35.455694
  ],
  "description": "In a fill from private house in Room 1A2 (in area eA8V), excavators discovered an archive of 15 texts, belonging to a group of Egyptians. Some of these people have Egyptian names, others have Assyrian names. Available datings belong to a period of some 30 years in the mid-7th century BC. The archive consists of legal documents.",
  "connectsWith": [
    "893945",
    "87246780"
  ],
  "names": [
    "Assur Archive 52b"
  ],
  "features": [
    {
      "type": "Feature",
      "geometry": {
        "type": "Point",
        "coordinates": [
          43.257781,
          35.455694
        ]
      },
      "properties": {
        "description": "representative point"
      }
    },
    {
      "geometry": {
        "type": "Point",
        "coordinates": [
          43.257781,
          35.455694
        ]
      },
      "id": "plan-location-of-assur-archive-52b",
      "type": "Feature",
      "properties": {
        "description": "Representative locations of the Neo-Assyrian archive at Assur on the basis of Pedersén 1987 Plan(s) 62.",
        "location_precision": "precise",
        "title": "Plan location of Assur Archive 52b",
        "link": "http://pleiades.stoa.org/places/452563773/plan-location-of-assur-archive-52b"
      }
    }
  ]
}