{
  "type": "FeatureCollection",
  "title": "Ebursasa",
  "id": "452758808",
  "bbox": [
    44.413087,
    32.538148,
    44.413087,
    32.538148
  ],
  "description": "The temple of the god Šara, Ebursasa (“House of Beautiful Jars”), was located in the Bāb-Lugalerra district of Babylon, in the western half of the inner city. According to the Babylonian topographical text Tintir = Babylon Tablet IV, it was one of three temples in that part of Babylon.",
  "connectsWith": [
    "893951",
    "633091640"
  ],
  "names": [
    "Ebursasa",
    "bīt Šara"
  ],
  "features": [
    {
      "type": "Feature",
      "geometry": {
        "type": "Point",
        "coordinates": [
          44.413087,
          32.538148
        ]
      },
      "properties": {
        "description": "representative point"
      }
    }
  ]
}