{
  "type": "FeatureCollection",
  "title": "Untitled",
  "id": "453759",
  "bbox": [
    16.266607,
    39.096351,
    16.266607,
    39.096351
  ],
  "description": "An ancient place, cited: BAtlas 46 D3 unnamed bridge (N Ad Fluvium Sabutum, over R. Savuto)",
  "connectsWith": [
    "452424"
  ],
  "features": [
    {
      "type": "Feature",
      "geometry": {
        "type": "Point",
        "coordinates": [
          16.266607,
          39.096351
        ]
      },
      "properties": {
        "description": "representative point"
      }
    },
    {
      "geometry": {
        "type": "Point",
        "coordinates": [
          16.266607,
          39.096351
        ]
      },
      "id": "darmc-location-27936",
      "type": "Feature",
      "properties": {
        "description": "500K scale point location",
        "location_precision": "precise",
        "title": "DARMC location 27936",
        "link": "http://pleiades.stoa.org/places/453759/darmc-location-27936"
      }
    }
  ]
}