{
  "type": "FeatureCollection",
  "title": "Emekiliburur",
  "id": "454450225",
  "bbox": [
    44.43119,
    32.54371,
    44.43119,
    32.54371
  ],
  "description": "The temple of the goddess Šarrat-Larsa, Emekiliburur (“House which Gathers All the Me’s”), was located in the Kullab district of Babylon, in the eastern half of the inner city. According to the Babylonian topographical text Tintir = Babylon Tablet IV, it was one of four temples in that part of Babylon.",
  "connectsWith": [
    "893951",
    "5066375"
  ],
  "names": [
    "Emekiliburur",
    "bīt Šarrat-Larsa"
  ],
  "features": [
    {
      "type": "Feature",
      "geometry": {
        "type": "Point",
        "coordinates": [
          44.43119,
          32.54371
        ]
      },
      "properties": {
        "description": "representative point"
      }
    }
  ]
}