{
  "type": "FeatureCollection",
  "title": "Barcombe Hill Roman Quarry",
  "id": "455597764",
  "description": "Two quarry faces to the southwest of the summit of Barcombe Hill, near Vindolanda. Findspot of RIB 3373.",
  "bbox": [
    -2.352563,
    54.988944,
    -2.351889,
    54.989763
  ],
  "reprPoint": [
    -2.352226,
    54.9893535
  ],
  "features": [
    {
      "geometry": {
        "type": "Point",
        "coordinates": [
          -2.351889,
          54.989763
        ]
      },
      "id": "quarry-north-face",
      "type": "Feature",
      "properties": {
        "description": "Coordinates derived from geograph.org.uk.",
        "location_precision": "precise",
        "title": "Imagery location of Quarry-North face",
        "link": "http://pleiades.stoa.org/places/455597764/quarry-north-face"
      }
    },
    {
      "geometry": {
        "type": "Point",
        "coordinates": [
          -2.352563,
          54.988944
        ]
      },
      "id": "quarry-south-face",
      "type": "Feature",
      "properties": {
        "description": "Coordinates derived from geograph.org.uk.",
        "location_precision": "precise",
        "title": "Imagery location of Quarry - South face",
        "link": "http://pleiades.stoa.org/places/455597764/quarry-south-face"
      }
    }
  ]
}