{
  "type": "FeatureCollection",
  "title": "Mausoleum of Menenius Agrippa",
  "id": "457581182",
  "bbox": [
    12.5348794,
    41.9344582,
    12.5348794,
    41.9344582
  ],
  "description": "The so-called mausoleum of Menenius Agrippa stands along the Via Nomentana.",
  "connectsWith": [
    "423025",
    "699256589"
  ],
  "features": [
    {
      "type": "Feature",
      "geometry": {
        "type": "Point",
        "coordinates": [
          12.5348794,
          41.9344582
        ]
      },
      "properties": {
        "description": "representative point"
      }
    },
    {
      "geometry": {
        "type": "Point",
        "coordinates": [
          12.5348794,
          41.9344582
        ]
      },
      "id": "location-of-mausoleum",
      "type": "Feature",
      "properties": {
        "description": "Representative location based on OpenStreetMap.",
        "location_precision": "precise",
        "title": "OSM location of Mausoleo di Menenio Agrippa",
        "link": "http://pleiades.stoa.org/places/457581182/location-of-mausoleum"
      }
    }
  ]
}