{
  "type": "FeatureCollection",
  "title": "Forum granary",
  "id": "458593871",
  "description": "Roman granaries of the forum in Pompeii. (VII,7,29)",
  "bbox": [
    14.4841305,
    40.7498078,
    14.4841305,
    40.7498078
  ],
  "connectsWith": [
    "433032"
  ],
  "reprPoint": [
    14.4841305,
    40.7498078
  ],
  "names": [
    "Poecile",
    "Grannaio",
    "Granai pubblici",
    "Granai del Foro",
    "School",
    "Scuola",
    "Forum holitorium",
    "Forum venale",
    "Horrea granariorum",
    "VII.7.29",
    "Holitorium"
  ],
  "features": [
    {
      "geometry": {
        "type": "Point",
        "coordinates": [
          14.4841305,
          40.7498078
        ]
      },
      "id": "granai-del-foro",
      "type": "Feature",
      "properties": {
        "description": "Location based on OpenStreetMap",
        "location_precision": "precise",
        "title": "OSM location of so-called \"Granai del Foro\"",
        "link": "http://pleiades.stoa.org/places/458593871/granai-del-foro"
      }
    }
  ]
}