{
  "type": "FeatureCollection",
  "title": "Villanovaforru, Nuraghe Genna Maria",
  "id": "460094535",
  "bbox": [
    8.8542447,
    39.6347659,
    8.8542447,
    39.6347659
  ],
  "description": "A multi-period nuragic site that began as a single tower ca. the Middle Bronze Age (1500 BC).",
  "connectsWith": [
    "472014"
  ],
  "features": [
    {
      "type": "Feature",
      "geometry": {
        "type": "Point",
        "coordinates": [
          8.8542447,
          39.6347659
        ]
      },
      "properties": {
        "description": "representative point"
      }
    },
    {
      "geometry": {
        "type": "Point",
        "coordinates": [
          8.8542447,
          39.6347659
        ]
      },
      "id": "osm-location",
      "type": "Feature",
      "properties": {
        "description": "Location based on OpenStreetMap",
        "location_precision": "precise",
        "title": "OSM location of Nuraghe Genna Maria",
        "link": "http://pleiades.stoa.org/places/460094535/osm-location"
      }
    }
  ]
}