{
  "type": "FeatureCollection",
  "title": "Old Winchester Hill",
  "id": "460428554",
  "bbox": [
    -1.0888094,
    50.9808743,
    -1.0888094,
    50.9808743
  ],
  "description": "Old Winchester Hill is the site of both Bronze Age barrows and an Iron Age hill fort.",
  "features": [
    {
      "type": "Feature",
      "geometry": {
        "type": "Point",
        "coordinates": [
          -1.0888094,
          50.9808743
        ]
      },
      "properties": {
        "description": "representative point"
      }
    },
    {
      "geometry": {
        "type": "Point",
        "coordinates": [
          -1.0888094,
          50.9808743
        ]
      },
      "id": "location-of-iron-age-hill-fort",
      "type": "Feature",
      "properties": {
        "description": "Representative location based on OpenStreetMap.",
        "location_precision": "precise",
        "title": "OSM location of Iron Age hill-fort",
        "link": "http://pleiades.stoa.org/places/460428554/location-of-iron-age-hill-fort"
      }
    }
  ]
}