{
  "type": "FeatureCollection",
  "title": "Old Winchester Hill",
  "id": "460428554",
  "description": "Old Winchester Hill is the site of both Bronze Age barrows and an Iron Age hill-fort.",
  "bbox": [
    -1.0888094,
    50.9808743,
    -1.0888094,
    50.9808743
  ],
  "reprPoint": [
    -1.0888094,
    50.9808743
  ],
  "features": [
    {
      "geometry": {
        "type": "Point",
        "coordinates": [
          -1.0887924,
          50.9808962
        ]
      },
      "id": "location-of-old-winchester-hill",
      "type": "Feature",
      "properties": {
        "description": "Location based on OpenStreetMap",
        "location_precision": "precise",
        "title": "OSM location of Old Winchester Hill",
        "link": "http://pleiades.stoa.org/places/460428554/location-of-old-winchester-hill"
      }
    },
    {
      "geometry": {
        "type": "Point",
        "coordinates": [
          -1.0888094,
          50.9808743
        ]
      },
      "id": "location-of-iron-age-hill-fort",
      "type": "Feature",
      "properties": {
        "description": "Representative location based on OpenStreetMap.",
        "location_precision": "precise",
        "title": "OSM location of Iron Age hill-fort",
        "link": "http://pleiades.stoa.org/places/460428554/location-of-iron-age-hill-fort"
      }
    },
    {
      "geometry": {
        "type": "Point",
        "coordinates": [
          -1.085707,
          50.9804579
        ]
      },
      "id": "location-of-bronze-age-barrow",
      "type": "Feature",
      "properties": {
        "description": "Location based on OpenStreetMap",
        "location_precision": "precise",
        "title": "OSM location of Bronze Age barrow",
        "link": "http://pleiades.stoa.org/places/460428554/location-of-bronze-age-barrow"
      }
    }
  ]
}