{
  "type": "FeatureCollection",
  "title": "Aeoliae (islands)",
  "id": "462076",
  "bbox": [
    14.35,
    38.4042,
    15.213,
    38.789
  ],
  "description": "A volcanic archipelago in the Tyrrhenian Sea composed of eight islands.",
  "connectsWith": [
    "1356"
  ],
  "names": [
    "Aeoliae",
    "Aiolou Nesoi",
    "Liparaiai Nesoi",
    "Hephaistiades Nesoi",
    "Aeolian Islands",
    "Isole Eolie",
    "Volcaniae",
    "Hephaistiades"
  ],
  "features": [
    {
      "type": "Feature",
      "geometry": {
        "type": "Point",
        "coordinates": [
          14.8824195,
          38.57980975
        ]
      },
      "properties": {
        "description": "representative point"
      }
    }
  ]
}