{
  "type": "FeatureCollection",
  "title": "Aigithallos Pr.",
  "id": "462083",
  "bbox": [
    12.447991,
    37.844148,
    12.447991,
    37.844148
  ],
  "description": "An ancient place, cited: BAtlas 47 A3 Aigithallos Pr.",
  "names": [
    "Aigithallos Pr."
  ],
  "features": [
    {
      "type": "Feature",
      "geometry": {
        "type": "Point",
        "coordinates": [
          12.447991,
          37.844148
        ]
      },
      "properties": {
        "description": "representative point"
      }
    },
    {
      "geometry": {
        "type": "Point",
        "coordinates": [
          12.447991,
          37.844148
        ]
      },
      "id": "location-of-aigithallos-pr",
      "type": "Feature",
      "properties": {
        "description": "verified in Google Earth 2013",
        "location_precision": "precise",
        "title": "Imagery location of Aigithallos Pr.",
        "link": "http://pleiades.stoa.org/places/462083/location-of-aigithallos-pr"
      }
    }
  ]
}