{
  "type": "FeatureCollection",
  "title": "Chrysas (river)",
  "id": "462158",
  "bbox": [
    14.3487585,
    37.6053322,
    14.3487585,
    37.6053322
  ],
  "description": "A river of central Sicily.",
  "names": [
    "Chrysas"
  ],
  "features": [
    {
      "type": "Feature",
      "geometry": {
        "type": "Point",
        "coordinates": [
          14.3487585,
          37.6053322
        ]
      },
      "properties": {
        "description": "representative point"
      }
    },
    {
      "geometry": {
        "type": "Point",
        "coordinates": [
          14.3487585,
          37.6053322
        ]
      },
      "id": "location-of-Chrysas-fl",
      "type": "Feature",
      "properties": {
        "description": "Location based on OpenStreetMap",
        "location_precision": "precise",
        "title": "location of Chrysas fl.",
        "link": "http://pleiades.stoa.org/places/462158/location-of-Chrysas-fl"
      }
    }
  ]
}