{
  "type": "FeatureCollection",
  "title": "Casalotto",
  "id": "462135",
  "bbox": [
    15.150544,
    37.580758,
    15.150544,
    37.580758
  ],
  "description": "An ancient place, cited: BAtlas 47 G3 Casalotto",
  "features": [
    {
      "type": "Feature",
      "geometry": {
        "type": "Point",
        "coordinates": [
          15.150544,
          37.580758
        ]
      },
      "properties": {
        "description": "representative point"
      }
    },
    {
      "geometry": {
        "type": "Point",
        "coordinates": [
          15.150544,
          37.580758
        ]
      },
      "id": "darmc-location-7725",
      "type": "Feature",
      "properties": {
        "description": "500K scale point location",
        "location_precision": "precise",
        "title": "DARMC location 7725",
        "link": "http://pleiades.stoa.org/places/462135/darmc-location-7725"
      }
    },
    {
      "geometry": {
        "type": "Point",
        "coordinates": [
          15.150544,
          37.580758
        ]
      },
      "id": "darmc-location-7726",
      "type": "Feature",
      "properties": {
        "description": "500K scale point location",
        "location_precision": "precise",
        "title": "DARMC location 7726",
        "link": "http://pleiades.stoa.org/places/462135/darmc-location-7726"
      }
    }
  ]
}