{
  "type": "FeatureCollection",
  "title": "Castellito di Ramacca",
  "id": "462139",
  "description": "An ancient place, cited: BAtlas 47 F4 Castellito di Ramacca",
  "bbox": [
    14.693454,
    37.385182,
    14.693454,
    37.385182
  ],
  "connectsWith": [
    "011dbae16282fae1d9b35a19437412bd"
  ],
  "reprPoint": [
    14.693454,
    37.385182
  ],
  "features": [
    {
      "geometry": {
        "type": "Point",
        "coordinates": [
          14.693454,
          37.385182
        ]
      },
      "id": "darmc-location-7727",
      "type": "Feature",
      "properties": {
        "description": "500K scale point location",
        "location_precision": "precise",
        "title": "DARMC location 7727",
        "link": "http://pleiades.stoa.org/places/462139/darmc-location-7727"
      }
    }
  ]
}