{
  "type": "FeatureCollection",
  "title": "Temple of Apollo Daphnephoros",
  "id": "462127127",
  "bbox": [
    23.7949508,
    38.39523,
    23.7949508,
    38.39523
  ],
  "description": "The Temple of Apollo Daphnephoros at Eretria dates originally to the late archaic period.",
  "connectsWith": [
    "579925"
  ],
  "features": [
    {
      "type": "Feature",
      "geometry": {
        "type": "Point",
        "coordinates": [
          23.7949508,
          38.39523
        ]
      },
      "properties": {
        "description": "representative point"
      }
    },
    {
      "geometry": {
        "type": "Point",
        "coordinates": [
          23.7949508,
          38.39523
        ]
      },
      "id": "osm-location-of-temple-of-apollo-daphnephoros",
      "type": "Feature",
      "properties": {
        "description": "Location based on OpenStreetMap",
        "location_precision": "precise",
        "title": "OSM location of Temple of Apollo Daphnephoros",
        "link": "http://pleiades.stoa.org/places/462127127/osm-location-of-temple-of-apollo-daphnephoros"
      }
    }
  ]
}