{
  "type": "FeatureCollection",
  "title": "Capitium",
  "id": "462130",
  "description": "An ancient place, cited: BAtlas 47 E3 Capitium",
  "bbox": [
    14.47909,
    37.848971,
    14.47909,
    37.848971
  ],
  "reprPoint": [
    14.47909,
    37.848971
  ],
  "names": [
    "Capitium"
  ],
  "features": [
    {
      "geometry": {
        "type": "Point",
        "coordinates": [
          14.47909,
          37.848971
        ]
      },
      "id": "darmc-location-18294",
      "type": "Feature",
      "properties": {
        "description": "500K scale point location",
        "location_precision": "precise",
        "title": "DARMC location 18294",
        "link": "http://pleiades.stoa.org/places/462130/darmc-location-18294"
      }
    }
  ]
}