{
  "type": "FeatureCollection",
  "title": "Capitium",
  "id": "462130",
  "bbox": [
    14.478172,
    37.847854,
    14.47909,
    37.848971
  ],
  "description": "Capitium was an ancient settlement in the Monti Nebrodi of Sicily.",
  "connectsWith": [
    "462492"
  ],
  "names": [
    "Capitium",
    "Capútion",
    "Capizzi"
  ],
  "features": [
    {
      "type": "Feature",
      "geometry": {
        "type": "Point",
        "coordinates": [
          14.478631,
          37.8484125
        ]
      },
      "properties": {
        "description": "representative point"
      }
    },
    {
      "geometry": {
        "type": "Point",
        "coordinates": [
          14.47909,
          37.848971
        ]
      },
      "id": "darmc-location-18294",
      "type": "Feature",
      "properties": {
        "description": "500K scale point location",
        "location_precision": "precise",
        "title": "DARMC location 18294",
        "link": "http://pleiades.stoa.org/places/462130/darmc-location-18294"
      }
    },
    {
      "geometry": {
        "type": "Point",
        "coordinates": [
          14.478172,
          37.847854
        ]
      },
      "id": "capizzi",
      "type": "Feature",
      "properties": {
        "description": "Location of the modern village of Capizzi, thought to be in the area of the ancient settlement of Capitium, based on a representative point derived from an OpenStreetMap node.",
        "location_precision": "precise",
        "title": "OSM location of Capizzi",
        "link": "http://pleiades.stoa.org/places/462130/capizzi"
      }
    }
  ]
}