{
  "type": "FeatureCollection",
  "title": "Castello della Pietra",
  "id": "462140",
  "bbox": [
    12.891772,
    37.664602,
    12.891772,
    37.664602
  ],
  "description": "An ancient place, cited: BAtlas 47 B3 Castello della Pietra",
  "connectsWith": [
    "462492"
  ],
  "features": [
    {
      "type": "Feature",
      "geometry": {
        "type": "Point",
        "coordinates": [
          12.891772,
          37.664602
        ]
      },
      "properties": {
        "description": "representative point"
      }
    },
    {
      "geometry": {
        "type": "Point",
        "coordinates": [
          12.891772,
          37.664602
        ]
      },
      "id": "darmc-location-18012",
      "type": "Feature",
      "properties": {
        "description": "500K scale point location",
        "location_precision": "precise",
        "title": "DARMC location 18012",
        "link": "http://pleiades.stoa.org/places/462140/darmc-location-18012"
      }
    }
  ]
}