{
  "type": "FeatureCollection",
  "title": "Feudo Nobile",
  "id": "462206",
  "bbox": [
    14.381527,
    37.038849,
    14.381527,
    37.038849
  ],
  "description": "An ancient place, cited: BAtlas 47 E4 Feudo Nobile",
  "connectsWith": [
    "462492"
  ],
  "features": [
    {
      "type": "Feature",
      "geometry": {
        "type": "Point",
        "coordinates": [
          14.381527,
          37.038849
        ]
      },
      "properties": {
        "description": "representative point"
      }
    },
    {
      "geometry": {
        "type": "Point",
        "coordinates": [
          14.381527,
          37.038849
        ]
      },
      "id": "darmc-location-20558",
      "type": "Feature",
      "properties": {
        "description": "500K scale point location",
        "location_precision": "precise",
        "title": "DARMC location 20558",
        "link": "http://pleiades.stoa.org/places/462206/darmc-location-20558"
      }
    }
  ]
}