{
  "type": "FeatureCollection",
  "title": "Heraclea Minoa",
  "id": "462237",
  "description": "An ancient Greek city of the south coast of Sicily located at the mouth of the Halykos river. Founded by Selinus in the sixth century BC, the site was abandoned in the first century AD.",
  "bbox": [
    13.2798155,
    37.3919156,
    13.280904,
    37.3942126
  ],
  "connectsWith": [
    "462492",
    "462229"
  ],
  "reprPoint": [
    13.28044,
    37.3933900667
  ],
  "names": [
    "Heraclea Minoa",
    "Makara"
  ],
  "features": [
    {
      "geometry": {
        "type": "Point",
        "coordinates": [
          13.280904,
          37.394042
        ]
      },
      "id": "darmc-location-18031",
      "type": "Feature",
      "properties": {
        "description": "500K scale point location",
        "location_precision": "precise",
        "title": "DARMC location 18031",
        "link": "http://pleiades.stoa.org/places/462237/darmc-location-18031"
      }
    },
    {
      "geometry": {
        "type": "Point",
        "coordinates": [
          13.2798155,
          37.3919156
        ]
      },
      "id": "osm-location",
      "type": "Feature",
      "properties": {
        "description": "Representative point derived form an OpenStreetMap way",
        "location_precision": "precise",
        "title": "OSM location of Heraclea Minoa",
        "link": "http://pleiades.stoa.org/places/462237/osm-location"
      }
    },
    {
      "geometry": {
        "type": "Point",
        "coordinates": [
          13.2806005,
          37.3942126
        ]
      },
      "id": "osm-location-of-theater",
      "type": "Feature",
      "properties": {
        "description": "Representative point derived from an OpenStreetMap way",
        "location_precision": "precise",
        "title": "OSM location of theater",
        "link": "http://pleiades.stoa.org/places/462237/osm-location-of-theater"
      }
    }
  ]
}