{
  "type": "FeatureCollection",
  "title": "Roman Villa at Għajn Tuffieħa, Malta",
  "id": "462218",
  "description": "Ruins at this ancient site include a Roman-era bath complex and extensive mosaics. Its ancient name is unknown.",
  "bbox": [
    14.357491,
    35.926949,
    14.357491,
    35.926949
  ],
  "reprPoint": [
    14.357491,
    35.926949
  ],
  "features": [
    {
      "geometry": {
        "type": "Point",
        "coordinates": [
          14.357491,
          35.926949
        ]
      },
      "id": "visible-remains-of-ghajn-tuffieha-roman-villa",
      "type": "Feature",
      "properties": {
        "description": "Location verified in Google Earth. Dates after BAtlas.",
        "location_precision": "precise",
        "title": "Visible Remains of Ghajn Tuffieha Roman Villa",
        "link": "http://pleiades.stoa.org/places/462218/visible-remains-of-ghajn-tuffieha-roman-villa"
      }
    },
    {
      "id": "batlas-location",
      "type": "Feature",
      "properties": {
        "description": null,
        "location_precision": "unlocated",
        "title": "Barrington Atlas location",
        "link": "http://pleiades.stoa.org/places/462218/batlas-location"
      }
    }
  ]
}