{
  "type": "FeatureCollection",
  "title": "Heraclea Minoa",
  "id": "462237",
  "bbox": [
    13.2798155,
    37.3919156,
    13.280904,
    37.394042
  ],
  "description": "An ancient Greek city of the south coast of Sicily located at the mouth of the Halykos river. Founded by Selinus in the sixth century BC, the site was abandoned in the first century AD.",
  "connectsWith": [
    "462492",
    "462229"
  ],
  "names": [
    "Heraclea Minoa",
    "Makara",
    "Eraclea Minoa"
  ],
  "features": [
    {
      "type": "Feature",
      "geometry": {
        "type": "Point",
        "coordinates": [
          13.28035975,
          37.3929788
        ]
      },
      "properties": {
        "description": "representative point"
      }
    },
    {
      "geometry": {
        "type": "Point",
        "coordinates": [
          13.280904,
          37.394042
        ]
      },
      "id": "darmc-location-18031",
      "type": "Feature",
      "properties": {
        "description": "1:500,000 scale representative point location digitized from the Barrington Atlas of the Greek and Roman World by the Digital Atlas of Roman and Medieval Civilizations project at Harvard University.",
        "location_precision": "precise",
        "title": "DARMC location 18031",
        "link": "http://pleiades.stoa.org/places/462237/darmc-location-18031"
      }
    },
    {
      "geometry": {
        "type": "Point",
        "coordinates": [
          13.2798155,
          37.3919156
        ]
      },
      "id": "osm-location",
      "type": "Feature",
      "properties": {
        "description": "Representative point derived form an OpenStreetMap way",
        "location_precision": "precise",
        "title": "OSM location of Heraclea Minoa",
        "link": "http://pleiades.stoa.org/places/462237/osm-location"
      }
    }
  ]
}