{
  "type": "FeatureCollection",
  "title": "*Logariana",
  "id": "462286",
  "description": "An ancient place, cited: BAtlas 47 F4 *Logariana",
  "bbox": [
    14.90438,
    37.063427,
    14.90438,
    37.063427
  ],
  "reprPoint": [
    14.90438,
    37.063427
  ],
  "names": [
    "Logariana"
  ],
  "features": [
    {
      "geometry": {
        "type": "Point",
        "coordinates": [
          14.90438,
          37.063427
        ]
      },
      "id": "darmc-location-7787",
      "type": "Feature",
      "properties": {
        "description": "500K scale point location",
        "location_precision": "precise",
        "title": "DARMC location 7787",
        "link": "http://pleiades.stoa.org/places/462286/darmc-location-7787"
      }
    }
  ]
}