{
  "type": "FeatureCollection",
  "title": "Euboia?",
  "id": "462203",
  "bbox": [
    14.69916,
    37.154331,
    14.7002376,
    37.155144
  ],
  "description": "An ancient place, cited: BAtlas 47 F4 Euboia?",
  "connectsWith": [
    "462492"
  ],
  "names": [
    "Euboia"
  ],
  "features": [
    {
      "type": "Feature",
      "geometry": {
        "type": "Point",
        "coordinates": [
          14.6996988,
          37.1547375
        ]
      },
      "properties": {
        "description": "representative point"
      }
    },
    {
      "geometry": {
        "type": "Point",
        "coordinates": [
          14.69916,
          37.154331
        ]
      },
      "id": "darmc-location-7040",
      "type": "Feature",
      "properties": {
        "description": "1:500,000 scale representative point location digitized from the Barrington Atlas of the Greek and Roman World by the Digital Atlas of Roman and Medieval Civilizations project at Harvard University.",
        "location_precision": "precise",
        "title": "DARMC location 7040",
        "link": "http://pleiades.stoa.org/places/462203/darmc-location-7040"
      }
    },
    {
      "geometry": {
        "type": "Point",
        "coordinates": [
          14.700237600000037,
          37.155144
        ]
      },
      "id": "dare-location",
      "type": "Feature",
      "properties": {
        "description": "Representative point location, village precision",
        "location_precision": "precise",
        "title": "DARE Location",
        "link": "http://pleiades.stoa.org/places/462203/dare-location"
      }
    }
  ]
}