{
  "type": "FeatureCollection",
  "title": "Fiumedinisi",
  "id": "462208",
  "bbox": [
    15.380031,
    38.025839,
    15.380031,
    38.025839
  ],
  "description": "An ancient place, cited: BAtlas 47 G2 Fiumedinisi",
  "connectsWith": [
    "462492"
  ],
  "features": [
    {
      "type": "Feature",
      "geometry": {
        "type": "Point",
        "coordinates": [
          15.380031,
          38.025839
        ]
      },
      "properties": {
        "description": "representative point"
      }
    },
    {
      "geometry": {
        "type": "Point",
        "coordinates": [
          15.380031,
          38.025839
        ]
      },
      "id": "darmc-location-18442",
      "type": "Feature",
      "properties": {
        "description": "500K scale point location",
        "location_precision": "precise",
        "title": "DARMC location 18442",
        "link": "http://pleiades.stoa.org/places/462208/darmc-location-18442"
      }
    }
  ]
}