{
  "type": "FeatureCollection",
  "title": "Mandra di Mezzo",
  "id": "462297",
  "bbox": [
    13.039528,
    37.784112,
    13.039528,
    37.784112
  ],
  "description": "An ancient place, cited: BAtlas 47 C3 Mandra di Mezzo",
  "connectsWith": [
    "462492"
  ],
  "features": [
    {
      "type": "Feature",
      "geometry": {
        "type": "Point",
        "coordinates": [
          13.039528,
          37.784112
        ]
      },
      "properties": {
        "description": "representative point"
      }
    },
    {
      "geometry": {
        "type": "Point",
        "coordinates": [
          13.039528,
          37.784112
        ]
      },
      "id": "darmc-location-20600",
      "type": "Feature",
      "properties": {
        "description": "500K scale point location",
        "location_precision": "precise",
        "title": "DARMC location 20600",
        "link": "http://pleiades.stoa.org/places/462297/darmc-location-20600"
      }
    }
  ]
}