{
  "type": "FeatureCollection",
  "title": "Heraclea Minoa",
  "id": "462237",
  "description": "An ancient Greek city of the south coast of Sicily located at the mouth of the Halykos river. Founded by Selinus in the sixth century BC, the site was abandoned in the first century AD.",
  "bbox": [
    13.280904,
    37.394042,
    13.280904,
    37.394042
  ],
  "connectsWith": [
    "462492",
    "462229"
  ],
  "reprPoint": [
    13.280904,
    37.394042
  ],
  "names": [
    "Heraclea Minoa",
    "Makara"
  ],
  "features": [
    {
      "geometry": {
        "type": "Point",
        "coordinates": [
          13.280904,
          37.394042
        ]
      },
      "id": "darmc-location-18031",
      "type": "Feature",
      "properties": {
        "description": "500K scale point location",
        "location_precision": "precise",
        "title": "DARMC location 18031",
        "link": "http://pleiades.stoa.org/places/462237/darmc-location-18031"
      }
    }
  ]
}