{
  "type": "FeatureCollection",
  "title": "Marchito",
  "id": "462299",
  "bbox": [
    14.250685,
    37.181328,
    14.250685,
    37.181328
  ],
  "description": "An ancient place, cited: BAtlas 47 E4 Marchito",
  "features": [
    {
      "type": "Feature",
      "geometry": {
        "type": "Point",
        "coordinates": [
          14.250685,
          37.181328
        ]
      },
      "properties": {
        "description": "representative point"
      }
    },
    {
      "geometry": {
        "type": "Point",
        "coordinates": [
          14.250685,
          37.181328
        ]
      },
      "id": "darmc-location-20601",
      "type": "Feature",
      "properties": {
        "description": "500K scale point location",
        "location_precision": "precise",
        "title": "DARMC location 20601",
        "link": "http://pleiades.stoa.org/places/462299/darmc-location-20601"
      }
    }
  ]
}