{
  "type": "FeatureCollection",
  "title": "(H)Enna",
  "id": "462236",
  "description": "An ancient place, cited: BAtlas 47 E3 (H)Enna",
  "bbox": [
    14.279558,
    37.567652,
    14.279558,
    37.567652
  ],
  "connectsWith": [
    "462492"
  ],
  "reprPoint": [
    14.279558,
    37.567652
  ],
  "names": [
    "Henna",
    "Enna"
  ],
  "features": [
    {
      "geometry": {
        "type": "Point",
        "coordinates": [
          14.279558,
          37.567652
        ]
      },
      "id": "darmc-location-18030",
      "type": "Feature",
      "properties": {
        "description": "500K scale point location",
        "location_precision": "precise",
        "title": "DARMC location 18030",
        "link": "http://pleiades.stoa.org/places/462236/darmc-location-18030"
      }
    }
  ]
}