{
  "type": "FeatureCollection",
  "title": "Mylae",
  "id": "462379",
  "description": "An ancient Greek settlement on the north-east coast of Sicily, located at the base of a peninsula that juts into the Tyrrhenian Sea. A colony of Zancle, it was probably founded in the eighth or seventh century BC. In 260 BC, during the First Punic War, the Romans won their first major naval battle against the Carthaginians in the waters off Mylae.",
  "bbox": [
    15.240385,
    38.219365,
    15.240385,
    38.219365
  ],
  "connectsWith": [
    "011dbae16282fae1d9b35a19437412bd"
  ],
  "reprPoint": [
    15.240385,
    38.219365
  ],
  "names": [
    "Mylae",
    "Milazzo",
    "Mylai"
  ],
  "features": [
    {
      "geometry": {
        "type": "Point",
        "coordinates": [
          15.240385,
          38.219365
        ]
      },
      "id": "darmc-location-18685",
      "type": "Feature",
      "properties": {
        "description": "500K scale point location",
        "location_precision": "precise",
        "title": "DARMC location 18685",
        "link": "http://pleiades.stoa.org/places/462379/darmc-location-18685"
      }
    }
  ]
}