{
  "type": "FeatureCollection",
  "title": "Monte della Giudecca",
  "id": "462342",
  "description": "An ancient place, cited: BAtlas 47 C4 Monte della Giudecca",
  "bbox": [
    13.417023,
    37.456476,
    13.417023,
    37.456476
  ],
  "reprPoint": [
    13.417023,
    37.456476
  ],
  "features": [
    {
      "geometry": {
        "type": "Point",
        "coordinates": [
          13.417023,
          37.456476
        ]
      },
      "id": "darmc-location-28540",
      "type": "Feature",
      "properties": {
        "description": "500K scale point location",
        "location_precision": "precise",
        "title": "DARMC location 28540",
        "link": "http://pleiades.stoa.org/places/462342/darmc-location-28540"
      }
    }
  ]
}