{
  "type": "FeatureCollection",
  "title": "Monte Lavanca Nera",
  "id": "462351",
  "bbox": [
    14.2634758,
    37.236281,
    14.2634758,
    37.236281
  ],
  "description": "A peak in south-central Sicily on which archaeological remains of a fortified settlement have been identified. The settlement's ancient name is unknown.",
  "connectsWith": [
    "462492"
  ],
  "features": [
    {
      "type": "Feature",
      "geometry": {
        "type": "Point",
        "coordinates": [
          14.2634758,
          37.236281
        ]
      },
      "properties": {
        "description": "representative point"
      }
    },
    {
      "geometry": {
        "type": "Point",
        "coordinates": [
          14.2634758,
          37.236281
        ]
      },
      "id": "osm-location-of-lavanca-nera",
      "type": "Feature",
      "properties": {
        "description": "Location based on OpenStreetMap",
        "location_precision": "precise",
        "title": "OSM location of Lavanca Nera",
        "link": "http://pleiades.stoa.org/places/462351/osm-location-of-lavanca-nera"
      }
    }
  ]
}