{
  "type": "FeatureCollection",
  "title": "Mylae",
  "id": "462379",
  "description": "An ancient place, cited: BAtlas 47 G2 Mylae",
  "bbox": [
    15.240385,
    38.219365,
    15.240385,
    38.219365
  ],
  "connectsWith": [
    "462492"
  ],
  "reprPoint": [
    15.240385,
    38.219365
  ],
  "names": [
    "Mylae"
  ],
  "features": [
    {
      "geometry": {
        "type": "Point",
        "coordinates": [
          15.240385,
          38.219365
        ]
      },
      "id": "darmc-location-18685",
      "type": "Feature",
      "properties": {
        "description": "500K scale point location",
        "location_precision": "precise",
        "title": "DARMC location 18685",
        "link": "http://pleiades.stoa.org/places/462379/darmc-location-18685"
      }
    }
  ]
}