{
  "type": "FeatureCollection",
  "title": "Monte Lavanca Nera",
  "id": "462351",
  "bbox": [
    14.242453,
    37.247103,
    14.242453,
    37.247103
  ],
  "description": "An ancient place, cited: BAtlas 47 E4 Monte Lavanca Nera",
  "connectsWith": [
    "462492"
  ],
  "features": [
    {
      "type": "Feature",
      "geometry": {
        "type": "Point",
        "coordinates": [
          14.242453,
          37.247103
        ]
      },
      "properties": {
        "description": "representative point"
      }
    },
    {
      "geometry": {
        "type": "Point",
        "coordinates": [
          14.242453,
          37.247103
        ]
      },
      "id": "darmc-location-28550",
      "type": "Feature",
      "properties": {
        "description": "500K scale point location",
        "location_precision": "precise",
        "title": "DARMC location 28550",
        "link": "http://pleiades.stoa.org/places/462351/darmc-location-28550"
      }
    }
  ]
}