{
  "type": "FeatureCollection",
  "title": "Morgantina",
  "id": "462372",
  "description": "An indigenous Sicilian site founded by the Morgeti, according to Strabo, Morgantina was eventually defeated by Syracuse and thus, in turn, passed into Roman hegemony in the third century BC.",
  "bbox": [
    14.479296,
    37.431079,
    14.479296,
    37.431079
  ],
  "connectsWith": [
    "462492"
  ],
  "reprPoint": [
    14.479296,
    37.431079
  ],
  "names": [
    "Morgantina",
    "Morgyna",
    "Murgentia"
  ],
  "features": [
    {
      "geometry": {
        "type": "Point",
        "coordinates": [
          14.479296,
          37.431079
        ]
      },
      "id": "darmc-location-18671",
      "type": "Feature",
      "properties": {
        "description": "500K scale point location",
        "location_precision": "precise",
        "title": "DARMC location 18671",
        "link": "http://pleiades.stoa.org/places/462372/darmc-location-18671"
      }
    },
    {
      "geometry": {
        "type": "Point",
        "coordinates": [
          14.4793751,
          37.4301355
        ]
      },
      "id": "location-of-greek-theater",
      "type": "Feature",
      "properties": {
        "description": "Location based on OpenStreetMap",
        "location_precision": "precise",
        "title": "location of Greek theater",
        "link": "http://pleiades.stoa.org/places/462372/location-of-greek-theater"
      }
    },
    {
      "geometry": {
        "type": "Point",
        "coordinates": [
          14.4796767,
          37.4308098
        ]
      },
      "id": "location-of-ekklesiasterion",
      "type": "Feature",
      "properties": {
        "description": "Location based on OpenStreetMap",
        "location_precision": "precise",
        "title": "location of Ekklesiasterion",
        "link": "http://pleiades.stoa.org/places/462372/location-of-ekklesiasterion"
      }
    }
  ]
}