{
  "type": "FeatureCollection",
  "title": "Montelungo",
  "id": "462369",
  "description": "An ancient place, cited: BAtlas 47 E4 Montelungo",
  "bbox": [
    14.201997,
    37.08352,
    14.201997,
    37.08352
  ],
  "reprPoint": [
    14.201997,
    37.08352
  ],
  "features": [
    {
      "geometry": {
        "type": "Point",
        "coordinates": [
          14.201997,
          37.08352
        ]
      },
      "id": "darmc-location-18665",
      "type": "Feature",
      "properties": {
        "description": "500K scale point location",
        "location_precision": "precise",
        "title": "DARMC location 18665",
        "link": "http://pleiades.stoa.org/places/462369/darmc-location-18665"
      }
    }
  ]
}