{
  "type": "FeatureCollection",
  "title": "Mylae",
  "id": "462379",
  "bbox": [
    15.240385,
    38.219365,
    15.240385,
    38.219365
  ],
  "description": "An ancient Greek settlement on the north-east coast of Sicily, located at the base of a peninsula that juts into the Tyrrhenian Sea. A colony of Zancle, it was probably founded in the eighth or seventh century BC. In 260 BC, during the First Punic War, the Romans won their first major naval battle against the Carthaginians in the waters off Mylae.",
  "connectsWith": [
    "462492"
  ],
  "names": [
    "Mylae",
    "Milazzo",
    "Mylai"
  ],
  "features": [
    {
      "type": "Feature",
      "geometry": {
        "type": "Point",
        "coordinates": [
          15.240385,
          38.219365
        ]
      },
      "properties": {
        "description": "representative point"
      }
    },
    {
      "geometry": {
        "type": "Point",
        "coordinates": [
          15.240385,
          38.219365
        ]
      },
      "id": "darmc-location-18685",
      "type": "Feature",
      "properties": {
        "description": "1:500,000 scale representative point location digitized from the Barrington Atlas of the Greek and Roman World by the Digital Atlas of Roman and Medieval Civilizations project at Harvard University.",
        "location_precision": "precise",
        "title": "DARMC location 18685",
        "link": "http://pleiades.stoa.org/places/462379/darmc-location-18685"
      }
    }
  ]
}