{
  "type": "FeatureCollection",
  "title": "Monte Riparato di Caltavuturo",
  "id": "462361",
  "bbox": [
    13.882395,
    37.8497898,
    13.882395,
    37.8497898
  ],
  "description": "An ancient place, cited: BAtlas 47 D3 Monte Riparato di Caltavuturo",
  "connectsWith": [
    "462492"
  ],
  "features": [
    {
      "type": "Feature",
      "geometry": {
        "type": "Point",
        "coordinates": [
          13.882395,
          37.8497898
        ]
      },
      "properties": {
        "description": "representative point"
      }
    },
    {
      "geometry": {
        "type": "Point",
        "coordinates": [
          13.882395,
          37.8497898
        ]
      },
      "id": "monte-riparato",
      "type": "Feature",
      "properties": {
        "description": "Representative point location, based on OpenStreetMap (and compared against publication)",
        "location_precision": "precise",
        "title": "OSM Location of Monte Riparato",
        "link": "http://pleiades.stoa.org/places/462361/monte-riparato"
      }
    }
  ]
}