{
  "type": "FeatureCollection",
  "title": "Monte Pietroso di Camporeale",
  "id": "462356",
  "description": "An ancient place, cited: BAtlas 47 C3 Monte Pietroso di Camporeale",
  "bbox": [
    13.094844,
    37.898286,
    13.094844,
    37.898286
  ],
  "reprPoint": [
    13.094844,
    37.898286
  ],
  "features": [
    {
      "geometry": {
        "type": "Point",
        "coordinates": [
          13.094844,
          37.898286
        ]
      },
      "id": "darmc-location-28555",
      "type": "Feature",
      "properties": {
        "description": "500K scale point location",
        "location_precision": "precise",
        "title": "DARMC location 28555",
        "link": "http://pleiades.stoa.org/places/462356/darmc-location-28555"
      }
    }
  ]
}