{
  "type": "FeatureCollection",
  "title": "Neaition/Netum",
  "id": "462388",
  "description": "Neaition/Netum was an ancient town in Sicily that likely became subject to Syracuse after 263 BC.",
  "bbox": [
    15.031978,
    36.930279,
    15.031978,
    36.930279
  ],
  "connectsWith": [
    "462492"
  ],
  "reprPoint": [
    15.031978,
    36.930279
  ],
  "names": [
    "Neaition",
    "Netum"
  ],
  "features": [
    {
      "geometry": {
        "type": "Point",
        "coordinates": [
          15.070887,
          36.891793
        ]
      },
      "id": "darmc-location-18689",
      "type": "Feature",
      "properties": {
        "description": "500K scale point location",
        "location_precision": "precise",
        "title": "DARMC location 18689",
        "link": "http://pleiades.stoa.org/places/462388/darmc-location-18689"
      }
    },
    {
      "geometry": {
        "type": "Point",
        "coordinates": [
          15.031978,
          36.930279
        ]
      },
      "id": "dare-location",
      "type": "Feature",
      "properties": {
        "description": "Representative point location, site precision",
        "location_precision": "precise",
        "title": "DARE Location",
        "link": "http://pleiades.stoa.org/places/462388/dare-location"
      }
    }
  ]
}