{
  "type": "FeatureCollection",
  "title": "Monte Balchino di Altobrando",
  "id": "462329",
  "bbox": [
    14.55957,
    37.272863,
    14.55957,
    37.272863
  ],
  "description": "An ancient place, cited: BAtlas 47 F4 Monte Balchino di Altobrando",
  "features": [
    {
      "type": "Feature",
      "geometry": {
        "type": "Point",
        "coordinates": [
          14.55957,
          37.272863
        ]
      },
      "properties": {
        "description": "representative point"
      }
    },
    {
      "geometry": {
        "type": "Point",
        "coordinates": [
          14.55957,
          37.272863
        ]
      },
      "id": "darmc-location-28530",
      "type": "Feature",
      "properties": {
        "description": "500K scale point location",
        "location_precision": "precise",
        "title": "DARMC location 28530",
        "link": "http://pleiades.stoa.org/places/462329/darmc-location-28530"
      }
    }
  ]
}