{
  "type": "FeatureCollection",
  "title": "Monte Riparato di Caltavuturo",
  "id": "462361",
  "description": "An ancient place, cited: BAtlas 47 D3 Monte Riparato di Caltavuturo",
  "bbox": [
    13.889033,
    37.824666,
    13.889033,
    37.824666
  ],
  "reprPoint": [
    13.889033,
    37.824666
  ],
  "features": [
    {
      "geometry": {
        "type": "Point",
        "coordinates": [
          13.889033,
          37.824666
        ]
      },
      "id": "darmc-location-28558",
      "type": "Feature",
      "properties": {
        "description": "500K scale point location",
        "location_precision": "precise",
        "title": "DARMC location 28558",
        "link": "http://pleiades.stoa.org/places/462361/darmc-location-28558"
      }
    }
  ]
}