{
  "type": "FeatureCollection",
  "title": "Megara Hyblaia",
  "id": "462307",
  "bbox": [
    15.181777,
    37.203717,
    15.181777,
    37.203717
  ],
  "description": "Megara Hyblaia was an ancient Greek colony in eastern Sicily founded in the eighth century B.C.",
  "connectsWith": [
    "462492"
  ],
  "names": [
    "Megara Hyblaia",
    "Megara Iblea",
    "Megara"
  ],
  "features": [
    {
      "type": "Feature",
      "geometry": {
        "type": "Point",
        "coordinates": [
          15.181777,
          37.203717
        ]
      },
      "properties": {
        "description": "representative point"
      }
    },
    {
      "geometry": {
        "type": "Point",
        "coordinates": [
          15.181777,
          37.203717
        ]
      },
      "id": "darmc-location-18610",
      "type": "Feature",
      "properties": {
        "description": "1:500,000 scale representative point location digitized from the Barrington Atlas of the Greek and Roman World by the Digital Atlas of Roman and Medieval Civilizations project at Harvard University.",
        "location_precision": "precise",
        "title": "DARMC location 18610",
        "link": "http://pleiades.stoa.org/places/462307/darmc-location-18610"
      }
    }
  ]
}