{
  "type": "FeatureCollection",
  "title": "Montevago",
  "id": "462370",
  "description": "An ancient place, cited: BAtlas 47 C3 Montevago",
  "bbox": [
    12.989483,
    37.702234,
    12.989483,
    37.702234
  ],
  "reprPoint": [
    12.989483,
    37.702234
  ],
  "features": [
    {
      "geometry": {
        "type": "Point",
        "coordinates": [
          12.989483,
          37.702234
        ]
      },
      "id": "darmc-location-7825",
      "type": "Feature",
      "properties": {
        "description": "500K scale point location",
        "location_precision": "precise",
        "title": "DARMC location 7825",
        "link": "http://pleiades.stoa.org/places/462370/darmc-location-7825"
      }
    }
  ]
}