{
  "type": "FeatureCollection",
  "title": "Monte delle Rocche",
  "id": "462343",
  "description": "An ancient place, cited: BAtlas 47 E3 Monte delle Rocche",
  "bbox": [
    14.019575,
    37.575389,
    14.019575,
    37.575389
  ],
  "reprPoint": [
    14.019575,
    37.575389
  ],
  "features": [
    {
      "geometry": {
        "type": "Point",
        "coordinates": [
          14.019575,
          37.575389
        ]
      },
      "id": "darmc-location-28541",
      "type": "Feature",
      "properties": {
        "description": "500K scale point location",
        "location_precision": "precise",
        "title": "DARMC location 28541",
        "link": "http://pleiades.stoa.org/places/462343/darmc-location-28541"
      }
    }
  ]
}