{
  "type": "FeatureCollection",
  "title": "Megara Hyblaia",
  "id": "462307",
  "description": "Megara Hyblaia was an ancient Greek colony in eastern Sicily founded in the eighth century BC.",
  "bbox": [
    15.181777,
    37.203717,
    15.181777,
    37.203717
  ],
  "connectsWith": [
    "462492"
  ],
  "reprPoint": [
    15.181777,
    37.203717
  ],
  "names": [
    "Megara Hyblaia"
  ],
  "features": [
    {
      "geometry": {
        "type": "Point",
        "coordinates": [
          15.181777,
          37.203717
        ]
      },
      "id": "darmc-location-18610",
      "type": "Feature",
      "properties": {
        "description": "500K scale point location",
        "location_precision": "precise",
        "title": "DARMC location 18610",
        "link": "http://pleiades.stoa.org/places/462307/darmc-location-18610"
      }
    }
  ]
}