{
  "type": "FeatureCollection",
  "title": "Motykanos (river)",
  "id": "462374",
  "bbox": [
    14.7553379,
    36.8533316,
    14.7553379,
    36.8533316
  ],
  "description": "An ancient place, cited: BAtlas 47 F5 Motykanos fl.",
  "names": [
    "Motykanos"
  ],
  "features": [
    {
      "type": "Feature",
      "geometry": {
        "type": "Point",
        "coordinates": [
          14.7553379,
          36.8533316
        ]
      },
      "properties": {
        "description": "representative point"
      }
    },
    {
      "geometry": {
        "type": "Point",
        "coordinates": [
          14.7553379,
          36.8533316
        ]
      },
      "id": "location-of-Motykanos-fl",
      "type": "Feature",
      "properties": {
        "description": "Location based on OpenStreetMap",
        "location_precision": "precise",
        "title": "location of Motykanos fl.",
        "link": "http://pleiades.stoa.org/places/462374/location-of-Motykanos-fl"
      }
    }
  ]
}