{
  "type": "FeatureCollection",
  "title": "Monte Navone",
  "id": "462354",
  "description": "An ancient place, cited: BAtlas 47 E4 Monte Navone",
  "bbox": [
    14.287942,
    37.356048,
    14.2882086,
    37.3569023
  ],
  "connectsWith": [
    "462492"
  ],
  "reprPoint": [
    14.2880753,
    37.35647515
  ],
  "features": [
    {
      "geometry": {
        "type": "Point",
        "coordinates": [
          14.287942,
          37.356048
        ]
      },
      "id": "darmc-location-28553",
      "type": "Feature",
      "properties": {
        "description": "500K scale point location",
        "location_precision": "precise",
        "title": "DARMC location 28553",
        "link": "http://pleiades.stoa.org/places/462354/darmc-location-28553"
      }
    }
  ]
}