{
  "type": "FeatureCollection",
  "title": "Monte Balzo di Alimena",
  "id": "462330",
  "description": "An ancient place, cited: BAtlas 47 E3 Monte Balzo di Alimena",
  "bbox": [
    14.114513,
    37.694864,
    14.114513,
    37.694864
  ],
  "reprPoint": [
    14.114513,
    37.694864
  ],
  "features": [
    {
      "geometry": {
        "type": "Point",
        "coordinates": [
          14.114513,
          37.694864
        ]
      },
      "id": "darmc-location-28531",
      "type": "Feature",
      "properties": {
        "description": "500K scale point location",
        "location_precision": "precise",
        "title": "DARMC location 28531",
        "link": "http://pleiades.stoa.org/places/462330/darmc-location-28531"
      }
    }
  ]
}