{
  "type": "FeatureCollection",
  "title": "Monte Navone",
  "id": "462354",
  "bbox": [
    14.287942,
    37.356048,
    14.2882086,
    37.3569023
  ],
  "description": "Monte Navone rises 754 m above sea level in Sicily's Enna province. Archaeological remains of a settlement pre-dating Greek colonisation were discovered on the summit that have been correlated with the Sikel site of Hybla Erea.",
  "connectsWith": [
    "462492"
  ],
  "features": [
    {
      "type": "Feature",
      "geometry": {
        "type": "Point",
        "coordinates": [
          14.2880753,
          37.35647515
        ]
      },
      "properties": {
        "description": "representative point"
      }
    },
    {
      "geometry": {
        "type": "Point",
        "coordinates": [
          14.287942,
          37.356048
        ]
      },
      "id": "darmc-location-28553",
      "type": "Feature",
      "properties": {
        "description": "500K scale point location",
        "location_precision": "precise",
        "title": "DARMC location 28553",
        "link": "http://pleiades.stoa.org/places/462354/darmc-location-28553"
      }
    },
    {
      "geometry": {
        "type": "Point",
        "coordinates": [
          14.2882086,
          37.3569023
        ]
      },
      "id": "osm-location",
      "type": "Feature",
      "properties": {
        "description": "Representative location based on OpenStreetMap.",
        "location_precision": "precise",
        "title": "OSM location of Monte Navone",
        "link": "http://pleiades.stoa.org/places/462354/osm-location"
      }
    }
  ]
}