{
  "type": "FeatureCollection",
  "title": "Scicli",
  "id": "462485",
  "description": "Scicli is the site of settlement beginning in the third millennium BC. The town of Scicli is believed to have been founded by Sicels ca. 300 BC.",
  "bbox": [
    14.702367,
    36.791428,
    14.702367,
    36.791428
  ],
  "connectsWith": [
    "462492"
  ],
  "reprPoint": [
    14.702367,
    36.791428
  ],
  "features": [
    {
      "geometry": {
        "type": "Point",
        "coordinates": [
          14.702367,
          36.791428
        ]
      },
      "id": "darmc-location-18873",
      "type": "Feature",
      "properties": {
        "description": "500K scale point location",
        "location_precision": "precise",
        "title": "DARMC location 18873",
        "link": "http://pleiades.stoa.org/places/462485/darmc-location-18873"
      }
    }
  ]
}