{
  "type": "FeatureCollection",
  "title": "Plemmyrion",
  "id": "462451",
  "bbox": [
    15.306744,
    37.028045,
    15.306744,
    37.028045
  ],
  "description": "An ancient place, cited: BAtlas 47 G4 Plemmyrion",
  "names": [
    "Plemmyrion"
  ],
  "features": [
    {
      "type": "Feature",
      "geometry": {
        "type": "Point",
        "coordinates": [
          15.306744,
          37.028045
        ]
      },
      "properties": {
        "description": "representative point"
      }
    },
    {
      "geometry": {
        "type": "Point",
        "coordinates": [
          15.306744,
          37.028045
        ]
      },
      "id": "darmc-location-20626",
      "type": "Feature",
      "properties": {
        "description": "500K scale point location",
        "location_precision": "precise",
        "title": "DARMC location 20626",
        "link": "http://pleiades.stoa.org/places/462451/darmc-location-20626"
      }
    }
  ]
}