{
  "type": "FeatureCollection",
  "title": "Roman Villa and Medieval Settlement at Piazza Armerina",
  "id": "462435",
  "description": "The so-called \"Villa Romana del Casale\" (of Roman date) and the nearby settlement of Piazza Armerina, which seems to have been occupied by survivors from the villa site after it was destroyed in an earthquake in the early middle ages. The villa is listed as a UNESCO World Heritage Site, in part because of its famous mosaics.",
  "bbox": [
    14.334042,
    37.364591,
    14.334722,
    37.364722
  ],
  "connectsWith": [
    "462492"
  ],
  "reprPoint": [
    14.334382,
    37.3646565
  ],
  "names": [
    "Villa Romana del Casale"
  ],
  "features": [
    {
      "geometry": {
        "type": "Point",
        "coordinates": [
          14.334722,
          37.364722
        ]
      },
      "id": "villa-romana-del-casale",
      "type": "Feature",
      "properties": {
        "description": "Representative point for the center of the excavated archaeological area, derived through analysis of Google Earth imagery. Dates after BAtlas.",
        "location_precision": "precise",
        "title": "Imagery location",
        "link": "http://pleiades.stoa.org/places/462435/villa-romana-del-casale"
      }
    }
  ]
}