{
  "type": "FeatureCollection",
  "title": "Priorato",
  "id": "462457",
  "description": "An ancient place, cited: BAtlas 47 E4 Priorato",
  "bbox": [
    14.144968,
    37.242434,
    14.144968,
    37.242434
  ],
  "reprPoint": [
    14.144968,
    37.242434
  ],
  "features": [
    {
      "geometry": {
        "type": "Point",
        "coordinates": [
          14.144968,
          37.242434
        ]
      },
      "id": "darmc-location-7904",
      "type": "Feature",
      "properties": {
        "description": "500K scale point location",
        "location_precision": "precise",
        "title": "DARMC location 7904",
        "link": "http://pleiades.stoa.org/places/462457/darmc-location-7904"
      }
    },
    {
      "geometry": {
        "type": "Point",
        "coordinates": [
          14.144968,
          37.242434
        ]
      },
      "id": "darmc-location-7905",
      "type": "Feature",
      "properties": {
        "description": "500K scale point location",
        "location_precision": "precise",
        "title": "DARMC location 7905",
        "link": "http://pleiades.stoa.org/places/462457/darmc-location-7905"
      }
    }
  ]
}