{
  "type": "FeatureCollection",
  "title": "Piazza Armerina",
  "id": "462435",
  "description": "An ancient place, cited: BAtlas 47 E4 Piazza Armerina",
  "bbox": [
    14.334722,
    37.364722,
    14.334722,
    37.364722
  ],
  "reprPoint": [
    14.334722,
    37.364722
  ],
  "features": [
    {
      "geometry": {
        "type": "Point",
        "coordinates": [
          14.334722,
          37.364722
        ]
      },
      "id": "villa-romana-del-casale",
      "type": "Feature",
      "properties": {
        "description": "a large, 4th century AD villa complex near Piazza Armerina",
        "location_precision": "precise",
        "title": "Villa Romana del Casale",
        "link": "http://pleiades.stoa.org/places/462435/villa-romana-del-casale"
      }
    }
  ]
}