{
  "type": "FeatureCollection",
  "title": "Pietra Rossa",
  "id": "462437",
  "description": "An ancient place, cited: BAtlas 47 E4 Pietra Rossa",
  "bbox": [
    14.064367,
    37.47819,
    14.064367,
    37.47819
  ],
  "reprPoint": [
    14.064367,
    37.47819
  ],
  "features": [
    {
      "geometry": {
        "type": "Point",
        "coordinates": [
          14.064367,
          37.47819
        ]
      },
      "id": "darmc-location-7665",
      "type": "Feature",
      "properties": {
        "description": "500K scale point location",
        "location_precision": "precise",
        "title": "DARMC location 7665",
        "link": "http://pleiades.stoa.org/places/462437/darmc-location-7665"
      }
    }
  ]
}