{
  "type": "FeatureCollection",
  "title": "Punta Secca",
  "id": "462459",
  "description": "An ancient place, cited: BAtlas 47 F5 Punta Secca",
  "bbox": [
    14.493604,
    36.7879,
    14.50725,
    36.790942
  ],
  "reprPoint": [
    14.500427,
    36.789421
  ],
  "features": [
    {
      "geometry": {
        "type": "Point",
        "coordinates": [
          14.493604,
          36.790942
        ]
      },
      "id": "darmc-location-18814",
      "type": "Feature",
      "properties": {
        "description": "500K scale point location",
        "location_precision": "precise",
        "title": "DARMC location 18814",
        "link": "http://pleiades.stoa.org/places/462459/darmc-location-18814"
      }
    },
    {
      "geometry": {
        "type": "Point",
        "coordinates": [
          14.50725,
          36.7879
        ]
      },
      "id": "dare-location",
      "type": "Feature",
      "properties": {
        "description": "Representative point location, site precision",
        "location_precision": "precise",
        "title": "DARE Location",
        "link": "http://pleiades.stoa.org/places/462459/dare-location"
      }
    }
  ]
}