{
  "type": "FeatureCollection",
  "title": "Punta Secca",
  "id": "462459",
  "bbox": [
    14.50725,
    36.7879,
    14.50725,
    36.7879
  ],
  "description": "An ancient place, cited: BAtlas 47 F5 Punta Secca",
  "connectsWith": [
    "462492"
  ],
  "features": [
    {
      "type": "Feature",
      "geometry": {
        "type": "Point",
        "coordinates": [
          14.50725,
          36.7879
        ]
      },
      "properties": {
        "description": "representative point"
      }
    },
    {
      "geometry": {
        "type": "Point",
        "coordinates": [
          14.50725,
          36.7879
        ]
      },
      "id": "dare-location",
      "type": "Feature",
      "properties": {
        "description": "Representative point location, site precision",
        "location_precision": "precise",
        "title": "DARE Location",
        "link": "http://pleiades.stoa.org/places/462459/dare-location"
      }
    }
  ]
}