{
  "type": "FeatureCollection",
  "title": "Pergus L.",
  "id": "462417",
  "bbox": [
    14.3038017,
    37.5188828,
    14.3038017,
    37.5188828
  ],
  "description": "An ancient place, cited: BAtlas 47 E3 Pergus L.",
  "names": [
    "Pergus L.",
    "Hennaeus L.",
    "Lago di Pergusa"
  ],
  "features": [
    {
      "type": "Feature",
      "geometry": {
        "type": "Point",
        "coordinates": [
          14.3038017,
          37.5188828
        ]
      },
      "properties": {
        "description": "representative point"
      }
    },
    {
      "geometry": {
        "type": "Point",
        "coordinates": [
          14.3038017,
          37.5188828
        ]
      },
      "id": "location-of-Pergus-L",
      "type": "Feature",
      "properties": {
        "description": "Location based on OpenStreetMap",
        "location_precision": "precise",
        "title": "OSM location",
        "link": "http://pleiades.stoa.org/places/462417/location-of-Pergus-L"
      }
    }
  ]
}