{
  "type": "FeatureCollection",
  "title": "Zancle/Messana",
  "id": "462538",
  "bbox": [
    15.556634,
    38.192251,
    15.556634,
    38.192251
  ],
  "description": "Zancle was founded as Greek colony in the eighth century B.C.",
  "connectsWith": [
    "462492"
  ],
  "names": [
    "Zánklē",
    "Messana",
    "Mamertina",
    "Messina"
  ],
  "features": [
    {
      "type": "Feature",
      "geometry": {
        "type": "Point",
        "coordinates": [
          15.556634,
          38.192251
        ]
      },
      "properties": {
        "description": "representative point"
      }
    },
    {
      "geometry": {
        "type": "Point",
        "coordinates": [
          15.556634,
          38.192251
        ]
      },
      "id": "darmc-location-19708",
      "type": "Feature",
      "properties": {
        "description": "500K scale point location",
        "location_precision": "precise",
        "title": "DARMC location 19708",
        "link": "http://pleiades.stoa.org/places/462538/darmc-location-19708"
      }
    }
  ]
}