{
  "type": "FeatureCollection",
  "title": "Zancle/Messana",
  "id": "462538",
  "bbox": [
    15.556634,
    38.192251,
    15.556634,
    38.192251
  ],
  "description": "Zancle was founded as Greek colony in the eighth century B.C. Home of the Mamertines who called for Roman assistance against Carthaginian forces in 264 B.C., sparking the First Punic War.",
  "connectsWith": [
    "462492",
    "499882358"
  ],
  "names": [
    "Zánklē",
    "Messana",
    "Mamertina",
    "Messina"
  ],
  "features": [
    {
      "type": "Feature",
      "geometry": {
        "type": "Point",
        "coordinates": [
          15.556634,
          38.192251
        ]
      },
      "properties": {
        "description": "representative point"
      }
    },
    {
      "geometry": {
        "type": "Point",
        "coordinates": [
          15.556634,
          38.192251
        ]
      },
      "id": "darmc-location-19708",
      "type": "Feature",
      "properties": {
        "description": "1:500,000 scale representative point location digitized from the Barrington Atlas of the Greek and Roman World by the Digital Atlas of Roman and Medieval Civilizations project at Harvard University.",
        "location_precision": "precise",
        "title": "DARMC location 19708",
        "link": "http://pleiades.stoa.org/places/462538/darmc-location-19708"
      }
    }
  ]
}