{
  "type": "FeatureCollection",
  "title": "Thermos fl.",
  "id": "462515",
  "description": "An ancient place, cited: BAtlas 47 D3 Thermos fl.",
  "bbox": [
    13.6515739,
    37.960628,
    13.6515739,
    37.960628
  ],
  "reprPoint": [
    13.6515739,
    37.960628
  ],
  "names": [
    "Thermos"
  ],
  "features": [
    {
      "geometry": {
        "type": "Point",
        "coordinates": [
          13.6515739,
          37.960628
        ]
      },
      "id": "location-of-Thermos-fl",
      "type": "Feature",
      "properties": {
        "description": "Location based on OpenStreetMap",
        "location_precision": "precise",
        "title": "location of Thermos fl.",
        "link": "http://pleiades.stoa.org/places/462515/location-of-Thermos-fl"
      }
    }
  ]
}