{
  "type": "FeatureCollection",
  "title": "Untitled",
  "id": "463572",
  "bbox": [
    12.80502,
    37.607074,
    12.80502,
    37.607074
  ],
  "description": "An ancient place, cited: BAtlas 47 B3 unnamed bridge (Selinus)",
  "connectsWith": [
    "462489"
  ],
  "features": [
    {
      "type": "Feature",
      "geometry": {
        "type": "Point",
        "coordinates": [
          12.80502,
          37.607074
        ]
      },
      "properties": {
        "description": "representative point"
      }
    },
    {
      "geometry": {
        "type": "Point",
        "coordinates": [
          12.80502,
          37.607074
        ]
      },
      "id": "darmc-location-27972",
      "type": "Feature",
      "properties": {
        "description": "500K scale point location",
        "location_precision": "precise",
        "title": "DARMC location 27972",
        "link": "http://pleiades.stoa.org/places/463572/darmc-location-27972"
      }
    }
  ]
}