{
  "type": "FeatureCollection",
  "title": "Untitled",
  "id": "463575",
  "bbox": [
    14.180131,
    38.018848,
    14.180131,
    38.018848
  ],
  "description": "An ancient place, cited: BAtlas 47 E2 unnamed bridge (E Cephaloedium)",
  "features": [
    {
      "type": "Feature",
      "geometry": {
        "type": "Point",
        "coordinates": [
          14.180131,
          38.018848
        ]
      },
      "properties": {
        "description": "representative point"
      }
    },
    {
      "geometry": {
        "type": "Point",
        "coordinates": [
          14.180131,
          38.018848
        ]
      },
      "id": "darmc-location-27940",
      "type": "Feature",
      "properties": {
        "description": "500K scale point location",
        "location_precision": "precise",
        "title": "DARMC location 27940",
        "link": "http://pleiades.stoa.org/places/463575/darmc-location-27940"
      }
    }
  ]
}