{
  "type": "FeatureCollection",
  "title": "Echetla",
  "id": "465884",
  "bbox": [
    14.6240607,
    37.2327642,
    14.6240607,
    37.2327642
  ],
  "description": "An ancient settlement, attested by literary or documentary sources, whose precise location cannot be determined today",
  "connectsWith": [
    "462492"
  ],
  "names": [
    "Echetla"
  ],
  "features": [
    {
      "type": "Feature",
      "geometry": {
        "type": "Point",
        "coordinates": [
          14.6240607,
          37.2327642
        ]
      },
      "properties": {
        "description": "representative point"
      }
    },
    {
      "geometry": {
        "type": "Point",
        "coordinates": [
          14.6240607,
          37.2327642
        ]
      },
      "id": "osm-location",
      "type": "Feature",
      "properties": {
        "description": "Representative location based on OpenStreetMap.",
        "location_precision": "precise",
        "title": "OSM location of Echetla",
        "link": "http://pleiades.stoa.org/places/465884/osm-location"
      }
    }
  ]
}