{
  "type": "FeatureCollection",
  "title": "Echetla",
  "id": "465884",
  "description": "An ancient settlement, attested by literary or documentary sources, whose precise location cannot be determined today",
  "bbox": [
    14.616721,
    37.233346,
    14.616721,
    37.233346
  ],
  "connectsWith": [
    "011dbae16282fae1d9b35a19437412bd"
  ],
  "reprPoint": [
    14.616721,
    37.233346
  ],
  "names": [
    "Echetla"
  ],
  "features": [
    {
      "id": "batlas-location",
      "type": "Feature",
      "properties": {
        "description": null,
        "location_precision": "unlocated",
        "title": "Barrington Atlas location",
        "link": "http://pleiades.stoa.org/places/465884/batlas-location"
      }
    },
    {
      "geometry": {
        "type": "Point",
        "coordinates": [
          14.616721,
          37.233346
        ]
      },
      "id": "osm-location",
      "type": "Feature",
      "properties": {
        "description": "Location based on OpenStreetMap",
        "location_precision": "precise",
        "title": "OSM location",
        "link": "http://pleiades.stoa.org/places/465884/osm-location"
      }
    }
  ]
}