{
  "type": "FeatureCollection",
  "title": "Unnamed Roman fort, Cheeke Street, Exeter",
  "id": "467104240",
  "bbox": [
    -3.5239034,
    50.7260893,
    -3.5239034,
    50.7260893
  ],
  "description": "A previously unknown Roman fort was discovered in Exeter between Bampfylde Street and Cheeke Street during the construction of a bus station in 2019.",
  "connectsWith": [
    "79531"
  ],
  "features": [
    {
      "type": "Feature",
      "geometry": {
        "type": "Point",
        "coordinates": [
          -3.5239034,
          50.7260893
        ]
      },
      "properties": {
        "description": "representative point"
      }
    },
    {
      "geometry": {
        "type": "Point",
        "coordinates": [
          -3.5239034,
          50.7260893
        ]
      },
      "id": "osm-location-of-roman-fort",
      "type": "Feature",
      "properties": {
        "description": "Representative location based on OpenStreetMap",
        "location_precision": "precise",
        "title": "OSM location of Roman Fort",
        "link": "http://pleiades.stoa.org/places/467104240/osm-location-of-roman-fort"
      }
    }
  ]
}