{
  "type": "FeatureCollection",
  "title": "Augustae",
  "id": "471887",
  "bbox": [
    9.088906,
    40.071704,
    9.088906,
    40.071704
  ],
  "description": "An ancient place, cited: BAtlas 48 B2 Augustae",
  "connectsWith": [
    "472014"
  ],
  "names": [
    "Augustae"
  ],
  "features": [
    {
      "type": "Feature",
      "geometry": {
        "type": "Point",
        "coordinates": [
          9.088906,
          40.071704
        ]
      },
      "properties": {
        "description": "representative point"
      }
    },
    {
      "geometry": {
        "type": "Point",
        "coordinates": [
          9.088906,
          40.071704
        ]
      },
      "id": "darmc-location-5313",
      "type": "Feature",
      "properties": {
        "description": "1M scale point location",
        "location_precision": "precise",
        "title": "DARMC location 5313",
        "link": "http://pleiades.stoa.org/places/471887/darmc-location-5313"
      }
    }
  ]
}