{
  "type": "FeatureCollection",
  "title": "Ad Octavum",
  "id": "471879",
  "bbox": [
    8.4993256,
    40.762541,
    8.4993256,
    40.762541
  ],
  "description": "An ancient place, cited: BAtlas 48 A2 Ad Octavum",
  "connectsWith": [
    "472014"
  ],
  "names": [
    "Ad Octavum"
  ],
  "features": [
    {
      "type": "Feature",
      "geometry": {
        "type": "Point",
        "coordinates": [
          8.4993256,
          40.762541
        ]
      },
      "properties": {
        "description": "representative point"
      }
    },
    {
      "geometry": {
        "type": "Point",
        "coordinates": [
          8.4993256,
          40.762541
        ]
      },
      "id": "osm-location-of-san-giovanni",
      "type": "Feature",
      "properties": {
        "description": "Location based on OpenStreetMap",
        "location_precision": "precise",
        "title": "OSM location of San Giovanni",
        "link": "http://pleiades.stoa.org/places/471879/osm-location-of-san-giovanni"
      }
    }
  ]
}