{
  "type": "FeatureCollection",
  "title": "Erucium",
  "id": "471919",
  "description": "An ancient place, cited: BAtlas 48 A2 Erucium",
  "bbox": [
    8.883981,
    40.8346,
    8.883981,
    40.8346
  ],
  "connectsWith": [
    "472014"
  ],
  "reprPoint": [
    8.883981,
    40.8346
  ],
  "names": [
    "Erucium"
  ],
  "features": [
    {
      "geometry": {
        "type": "Point",
        "coordinates": [
          8.883981,
          40.8346
        ]
      },
      "id": "darmc-location-19609",
      "type": "Feature",
      "properties": {
        "description": "1M scale point location",
        "location_precision": "precise",
        "title": "DARMC location 19609",
        "link": "http://pleiades.stoa.org/places/471919/darmc-location-19609"
      }
    }
  ]
}