{
  "type": "FeatureCollection",
  "title": "Iglesias",
  "id": "471950",
  "description": "An ancient place, cited: BAtlas 48 A3 Iglesias",
  "bbox": [
    8.534334,
    39.312681,
    8.534334,
    39.312681
  ],
  "connectsWith": [
    "472014"
  ],
  "reprPoint": [
    8.534334,
    39.312681
  ],
  "features": [
    {
      "geometry": {
        "type": "Point",
        "coordinates": [
          8.534334,
          39.312681
        ]
      },
      "id": "darmc-location-19510",
      "type": "Feature",
      "properties": {
        "description": "1M scale point location",
        "location_precision": "precise",
        "title": "DARMC location 19510",
        "link": "http://pleiades.stoa.org/places/471950/darmc-location-19510"
      }
    }
  ]
}