{
  "type": "FeatureCollection",
  "title": "Nymphaios Limen",
  "id": "471985",
  "description": "An ancient place, cited: BAtlas 48 A2 Nymphaios Limen",
  "bbox": [
    8.205451,
    40.593709,
    8.205451,
    40.593709
  ],
  "reprPoint": [
    8.205451,
    40.593709
  ],
  "names": [
    "Nymphaios Limen"
  ],
  "features": [
    {
      "geometry": {
        "type": "Point",
        "coordinates": [
          8.205451,
          40.593709
        ]
      },
      "id": "darmc-location-19831",
      "type": "Feature",
      "properties": {
        "description": "1M scale point location",
        "location_precision": "precise",
        "title": "DARMC location 19831",
        "link": "http://pleiades.stoa.org/places/471985/darmc-location-19831"
      }
    }
  ]
}