{
  "type": "FeatureCollection",
  "title": "Decimoputzu",
  "id": "471913",
  "bbox": [
    8.916265,
    39.336422,
    8.916265,
    39.336422
  ],
  "description": "An ancient place, cited: BAtlas 48 A3 Decimoputzu",
  "connectsWith": [
    "472014"
  ],
  "features": [
    {
      "type": "Feature",
      "geometry": {
        "type": "Point",
        "coordinates": [
          8.916265,
          39.336422
        ]
      },
      "properties": {
        "description": "representative point"
      }
    },
    {
      "geometry": {
        "type": "Point",
        "coordinates": [
          8.916265,
          39.336422
        ]
      },
      "id": "darmc-location-19667",
      "type": "Feature",
      "properties": {
        "description": "1M scale point location",
        "location_precision": "precise",
        "title": "DARMC location 19667",
        "link": "http://pleiades.stoa.org/places/471913/darmc-location-19667"
      }
    }
  ]
}