{
  "type": "FeatureCollection",
  "title": "Castelsardo",
  "id": "471902",
  "bbox": [
    8.713337,
    40.912809,
    8.713337,
    40.912809
  ],
  "description": "An ancient place, cited: BAtlas 48 A2 Castelsardo",
  "connectsWith": [
    "472014"
  ],
  "features": [
    {
      "type": "Feature",
      "geometry": {
        "type": "Point",
        "coordinates": [
          8.713337,
          40.912809
        ]
      },
      "properties": {
        "description": "representative point"
      }
    },
    {
      "geometry": {
        "type": "Point",
        "coordinates": [
          8.713337,
          40.912809
        ]
      },
      "id": "darmc-location-20129",
      "type": "Feature",
      "properties": {
        "description": "1M scale point location",
        "location_precision": "precise",
        "title": "DARMC location 20129",
        "link": "http://pleiades.stoa.org/places/471902/darmc-location-20129"
      }
    }
  ]
}