{
  "type": "FeatureCollection",
  "title": "Monte Sirai",
  "id": "471974",
  "description": "A Phoenician–Punic and later Roman settlement in southwestern Sardinia, Monte Sirai also has evidence for nuragic settlement during the second millennium BC.",
  "bbox": [
    8.48612,
    39.166403,
    8.528911,
    39.1801
  ],
  "connectsWith": [
    "472014"
  ],
  "reprPoint": [
    8.5075155,
    39.1732515
  ],
  "features": [
    {
      "geometry": {
        "type": "Point",
        "coordinates": [
          8.528911,
          39.166403
        ]
      },
      "id": "darmc-location-20496",
      "type": "Feature",
      "properties": {
        "description": "1M scale point location",
        "location_precision": "precise",
        "title": "DARMC location 20496",
        "link": "http://pleiades.stoa.org/places/471974/darmc-location-20496"
      }
    }
  ]
}