{
  "type": "FeatureCollection",
  "title": "S. Ungroni",
  "id": "472009",
  "bbox": [
    8.580825,
    39.798367,
    8.580825,
    39.798367
  ],
  "description": "An ancient place, cited: BAtlas 48 A3 S. Ungroni",
  "features": [
    {
      "type": "Feature",
      "geometry": {
        "type": "Point",
        "coordinates": [
          8.580825,
          39.798367
        ]
      },
      "properties": {
        "description": "representative point"
      }
    },
    {
      "geometry": {
        "type": "Point",
        "coordinates": [
          8.580825,
          39.798367
        ]
      },
      "id": "darmc-location-21080",
      "type": "Feature",
      "properties": {
        "description": "1M scale point location",
        "location_precision": "precise",
        "title": "DARMC location 21080",
        "link": "http://pleiades.stoa.org/places/472009/darmc-location-21080"
      }
    }
  ]
}