{
  "type": "FeatureCollection",
  "title": "Kersounon",
  "id": "472083",
  "bbox": [
    9.185004,
    42.666293,
    9.185004,
    42.666293
  ],
  "description": "An ancient place, cited: BAtlas 48 D2 Kersounon",
  "names": [
    "Kersounon"
  ],
  "features": [
    {
      "type": "Feature",
      "geometry": {
        "type": "Point",
        "coordinates": [
          9.185004,
          42.666293
        ]
      },
      "properties": {
        "description": "representative point"
      }
    },
    {
      "geometry": {
        "type": "Point",
        "coordinates": [
          9.185004,
          42.666293
        ]
      },
      "id": "darmc-location-19798",
      "type": "Feature",
      "properties": {
        "description": "1M scale point location",
        "location_precision": "precise",
        "title": "DARMC location 19798",
        "link": "http://pleiades.stoa.org/places/472083/darmc-location-19798"
      }
    }
  ]
}