{
  "type": "FeatureCollection",
  "title": "Corsica/Kyrnos (island)",
  "id": "472063",
  "bbox": [
    8.5431581,
    41.3916,
    9.51230911559,
    42.98429
  ],
  "description": "The island of Corsica, in the Mediterranean Sea.",
  "connectsWith": [
    "1043",
    "472127",
    "1356",
    "981548"
  ],
  "names": [
    "Corsica",
    "Kyrnos"
  ],
  "features": [
    {
      "type": "Feature",
      "geometry": {
        "type": "Point",
        "coordinates": [
          9.1903461,
          42.1441461
        ]
      },
      "properties": {
        "description": "representative point"
      }
    }
  ]
}