{
  "type": "FeatureCollection",
  "title": "Usel(l)is",
  "id": "472038",
  "description": "A Roman colonia in western Sardinia",
  "bbox": [
    8.850947,
    39.810711,
    8.850947,
    39.810711
  ],
  "reprPoint": [
    8.850947,
    39.810711
  ],
  "names": [
    "Usellus",
    "Usellis",
    "Uselis"
  ],
  "features": [
    {
      "geometry": {
        "type": "Point",
        "coordinates": [
          8.850947,
          39.810711
        ]
      },
      "id": "darmc-location-4545",
      "type": "Feature",
      "properties": {
        "description": "1M scale point location",
        "location_precision": "precise",
        "title": "DARMC location 4545",
        "link": "http://pleiades.stoa.org/places/472038/darmc-location-4545"
      }
    }
  ]
}