{
  "type": "FeatureCollection",
  "title": "Sulcensis Pr.",
  "id": "472023",
  "bbox": [
    8.3670575,
    39.1130442,
    8.3670575,
    39.1130442
  ],
  "description": "An ancient place, cited: BAtlas 48 A3 Sulcensis Pr.",
  "connectsWith": [
    "471973"
  ],
  "names": [
    "Sulcensis Pr."
  ],
  "features": [
    {
      "type": "Feature",
      "geometry": {
        "type": "Point",
        "coordinates": [
          8.3670575,
          39.1130442
        ]
      },
      "properties": {
        "description": "representative point"
      }
    },
    {
      "geometry": {
        "type": "Point",
        "coordinates": [
          8.3670575,
          39.1130442
        ]
      },
      "id": "osm-location",
      "type": "Feature",
      "properties": {
        "description": "Representative location based on OpenStreetMap.",
        "location_precision": "precise",
        "title": "OSM location of Sulcensis Pr.",
        "link": "http://pleiades.stoa.org/places/472023/osm-location"
      }
    }
  ]
}