{
  "type": "FeatureCollection",
  "title": "Villaspeciosa",
  "id": "472043",
  "description": "An ancient place, cited: BAtlas 48 A3 Villaspeciosa",
  "bbox": [
    8.926278,
    39.313435,
    8.926278,
    39.313435
  ],
  "connectsWith": [
    "db071c997600a6865a2ffa1a64a77945"
  ],
  "reprPoint": [
    8.926278,
    39.313435
  ],
  "features": [
    {
      "geometry": {
        "type": "Point",
        "coordinates": [
          8.926278,
          39.313435
        ]
      },
      "id": "darmc-location-21149",
      "type": "Feature",
      "properties": {
        "description": "1M scale point location",
        "location_precision": "precise",
        "title": "DARMC location 21149",
        "link": "http://pleiades.stoa.org/places/472043/darmc-location-21149"
      }
    }
  ]
}