{
  "type": "FeatureCollection",
  "title": "Keneston",
  "id": "472080",
  "bbox": [
    9.266061,
    42.172503,
    9.266061,
    42.172503
  ],
  "description": "An ancient place, cited: BAtlas 48 D2 Keneston",
  "names": [
    "Keneston"
  ],
  "features": [
    {
      "type": "Feature",
      "geometry": {
        "type": "Point",
        "coordinates": [
          9.266061,
          42.172503
        ]
      },
      "properties": {
        "description": "representative point"
      }
    },
    {
      "geometry": {
        "type": "Point",
        "coordinates": [
          9.266061,
          42.172503
        ]
      },
      "id": "darmc-location-19796",
      "type": "Feature",
      "properties": {
        "description": "1M scale point location",
        "location_precision": "precise",
        "title": "DARMC location 19796",
        "link": "http://pleiades.stoa.org/places/472080/darmc-location-19796"
      }
    }
  ]
}