{
  "type": "FeatureCollection",
  "title": "Pauka",
  "id": "472111",
  "description": "An ancient place, cited: BAtlas 48 C3 Pauka",
  "bbox": [
    8.799868,
    41.711504,
    8.799868,
    41.711504
  ],
  "reprPoint": [
    8.799868,
    41.711504
  ],
  "names": [
    "Pauka"
  ],
  "features": [
    {
      "geometry": {
        "type": "Point",
        "coordinates": [
          8.799868,
          41.711504
        ]
      },
      "id": "darmc-location-19849",
      "type": "Feature",
      "properties": {
        "description": "1M scale point location",
        "location_precision": "precise",
        "title": "DARMC location 19849",
        "link": "http://pleiades.stoa.org/places/472111/darmc-location-19849"
      }
    }
  ]
}