{
  "type": "FeatureCollection",
  "title": "Ourkinion",
  "id": "472107",
  "description": "An ancient place, cited: BAtlas 48 C2 Ourkinion",
  "bbox": [
    8.761599,
    42.040029,
    8.761599,
    42.040029
  ],
  "reprPoint": [
    8.761599,
    42.040029
  ],
  "names": [
    "Ourkinion"
  ],
  "features": [
    {
      "geometry": {
        "type": "Point",
        "coordinates": [
          8.761599,
          42.040029
        ]
      },
      "id": "darmc-location-19843",
      "type": "Feature",
      "properties": {
        "description": "1M scale point location",
        "location_precision": "precise",
        "title": "DARMC location 19843",
        "link": "http://pleiades.stoa.org/places/472107/darmc-location-19843"
      }
    }
  ]
}