{
  "type": "FeatureCollection",
  "title": "Dur-Aššur-ketti-lešir",
  "id": "473755738",
  "bbox": [
    40.8138308,
    36.3875531,
    40.8138308,
    36.3875531
  ],
  "description": "A town mentioned in Neo-Assyrian sources that is identified with modern Tell Bderi.",
  "names": [
    "Tell Bderi"
  ],
  "features": [
    {
      "type": "Feature",
      "geometry": {
        "type": "Point",
        "coordinates": [
          40.8138308,
          36.3875531
        ]
      },
      "properties": {
        "description": "representative point"
      }
    },
    {
      "geometry": {
        "type": "Point",
        "coordinates": [
          40.8138308,
          36.3875531
        ]
      },
      "id": "osm-location-of-tell-bderi",
      "type": "Feature",
      "properties": {
        "description": "Representative location based on OpenStreetMap.",
        "location_precision": "precise",
        "title": "OSM location of Tell Bderi",
        "link": "http://pleiades.stoa.org/places/473755738/osm-location-of-tell-bderi"
      }
    }
  ]
}