{
  "type": "FeatureCollection",
  "title": "Forum of Conimbriga",
  "id": "476697166",
  "bbox": [
    -8.4950275,
    40.0997517,
    -8.4950275,
    40.0997517
  ],
  "description": "The Roman forum of Conímbriga.",
  "connectsWith": [
    "236443"
  ],
  "features": [
    {
      "type": "Feature",
      "geometry": {
        "type": "Point",
        "coordinates": [
          -8.4950275,
          40.0997517
        ]
      },
      "properties": {
        "description": "representative point"
      }
    },
    {
      "geometry": {
        "type": "Point",
        "coordinates": [
          -8.4950275,
          40.0997517
        ]
      },
      "id": "osm-location-of-forum",
      "type": "Feature",
      "properties": {
        "description": "Location based on OpenStreetMap",
        "location_precision": "precise",
        "title": "OSM location of forum",
        "link": "http://pleiades.stoa.org/places/476697166/osm-location-of-forum"
      }
    }
  ]
}