{
  "type": "FeatureCollection",
  "title": "Roman Odeon of Gortyn",
  "id": "481346137",
  "bbox": [
    24.9465988,
    35.0630972,
    24.9465988,
    35.0630972
  ],
  "description": "The Roman Odeon of Gortyn dates to the first century.",
  "connectsWith": [
    "589796"
  ],
  "features": [
    {
      "type": "Feature",
      "geometry": {
        "type": "Point",
        "coordinates": [
          24.9465988,
          35.0630972
        ]
      },
      "properties": {
        "description": "representative point"
      }
    },
    {
      "geometry": {
        "type": "Point",
        "coordinates": [
          24.9465988,
          35.0630972
        ]
      },
      "id": "location-of-odeion",
      "type": "Feature",
      "properties": {
        "description": "Representative location based on OpenStreetMap",
        "location_precision": "precise",
        "title": "OSM location of Odeion",
        "link": "http://pleiades.stoa.org/places/481346137/location-of-odeion"
      }
    }
  ]
}