{
  "type": "FeatureCollection",
  "title": "Cellae",
  "id": "481783",
  "bbox": [
    21.672637,
    40.727666,
    21.686635,
    40.785281
  ],
  "description": "An ancient place, cited: BAtlas 49 D3 Cellae",
  "names": [
    "Cellae"
  ],
  "features": [
    {
      "type": "Feature",
      "geometry": {
        "type": "Point",
        "coordinates": [
          21.679636,
          40.7564735
        ]
      },
      "properties": {
        "description": "representative point"
      }
    },
    {
      "geometry": {
        "type": "Point",
        "coordinates": [
          21.672637,
          40.727666
        ]
      },
      "id": "darmc-location-24371",
      "type": "Feature",
      "properties": {
        "description": "1M scale point location",
        "location_precision": "precise",
        "title": "DARMC location 24371",
        "link": "http://pleiades.stoa.org/places/481783/darmc-location-24371"
      }
    },
    {
      "geometry": {
        "type": "Point",
        "coordinates": [
          21.686635,
          40.785281
        ]
      },
      "id": "dare-location",
      "type": "Feature",
      "properties": {
        "description": "Representative point location, village precision",
        "location_precision": "precise",
        "title": "DARE Location",
        "link": "http://pleiades.stoa.org/places/481783/dare-location"
      }
    }
  ]
}