{
  "type": "FeatureCollection",
  "title": "Ad Quintum",
  "id": "481701",
  "description": "An ancient place, cited: BAtlas 49 B2 Ad Quintum",
  "bbox": [
    20.016667,
    41.099984,
    20.016667,
    41.099984
  ],
  "reprPoint": [
    20.016667,
    41.099984
  ],
  "names": [
    "Ad Quintum"
  ],
  "features": [
    {
      "geometry": {
        "type": "Point",
        "coordinates": [
          20.016667,
          41.099984
        ]
      },
      "id": "darmc-location-24479",
      "type": "Feature",
      "properties": {
        "description": "1M scale point location",
        "location_precision": "precise",
        "title": "DARMC location 24479",
        "link": "http://pleiades.stoa.org/places/481701/darmc-location-24479"
      }
    }
  ]
}