{
  "type": "FeatureCollection",
  "title": "Chepino",
  "id": "481788",
  "description": "An ancient place, cited: BAtlas 49 E1 Chepino",
  "bbox": [
    22.783337,
    42.616658,
    22.783337,
    42.616658
  ],
  "reprPoint": [
    22.783337,
    42.616658
  ],
  "features": [
    {
      "geometry": {
        "type": "Point",
        "coordinates": [
          22.783337,
          42.616658
        ]
      },
      "id": "darmc-location-24321",
      "type": "Feature",
      "properties": {
        "description": "1M scale point location",
        "location_precision": "precise",
        "title": "DARMC location 24321",
        "link": "http://pleiades.stoa.org/places/481788/darmc-location-24321"
      }
    }
  ]
}