{
  "type": "FeatureCollection",
  "title": "Chimaira",
  "id": "481789",
  "description": "An ancient place, cited: BAtlas 49 B3 Chimaira",
  "bbox": [
    19.733345,
    40.116661,
    19.733345,
    40.116661
  ],
  "reprPoint": [
    19.733345,
    40.116661
  ],
  "names": [
    "Chimaira"
  ],
  "features": [
    {
      "geometry": {
        "type": "Point",
        "coordinates": [
          19.733345,
          40.116661
        ]
      },
      "id": "darmc-location-24539",
      "type": "Feature",
      "properties": {
        "description": "1M scale point location",
        "location_precision": "precise",
        "title": "DARMC location 24539",
        "link": "http://pleiades.stoa.org/places/481789/darmc-location-24539"
      }
    }
  ]
}