{
  "type": "FeatureCollection",
  "title": "Burgaraca",
  "id": "481775",
  "description": "An ancient place, cited: BAtlas 49 F1 Burgaraca",
  "bbox": [
    23.6579,
    42.578584,
    23.6579,
    42.578584
  ],
  "reprPoint": [
    23.6579,
    42.578584
  ],
  "names": [
    "Burgaraca"
  ],
  "features": [
    {
      "geometry": {
        "type": "Point",
        "coordinates": [
          23.6579,
          42.578584
        ]
      },
      "id": "darmc-location-8548",
      "type": "Feature",
      "properties": {
        "description": "1M scale point location",
        "location_precision": "precise",
        "title": "DARMC location 8548",
        "link": "http://pleiades.stoa.org/places/481775/darmc-location-8548"
      }
    }
  ]
}