{
  "type": "FeatureCollection",
  "title": "Argyros",
  "id": "481741",
  "description": "An ancient place, cited: BAtlas 49 C3 Argyros",
  "bbox": [
    20.133299,
    40.066574,
    21.262223,
    40.448779
  ],
  "reprPoint": [
    20.697761,
    40.2576765
  ],
  "names": [
    "Argyros"
  ],
  "features": [
    {
      "geometry": {
        "type": "Point",
        "coordinates": [
          20.133299,
          40.066574
        ]
      },
      "id": "darmc-location-24572",
      "type": "Feature",
      "properties": {
        "description": "1M scale point location",
        "location_precision": "precise",
        "title": "DARMC location 24572",
        "link": "http://pleiades.stoa.org/places/481741/darmc-location-24572"
      }
    },
    {
      "geometry": {
        "type": "Point",
        "coordinates": [
          21.262223,
          40.448779
        ]
      },
      "id": "darmc-location-34037",
      "type": "Feature",
      "properties": {
        "description": "1M scale point location",
        "location_precision": "precise",
        "title": "DARMC location 34037",
        "link": "http://pleiades.stoa.org/places/481741/darmc-location-34037"
      }
    }
  ]
}