{
  "type": "FeatureCollection",
  "title": "Bryanion",
  "id": "481773",
  "bbox": [
    21.219321,
    41.237017,
    21.219321,
    41.237017
  ],
  "description": "An ancient place, cited: BAtlas 49 D2 Bryanion",
  "names": [
    "Bryanion"
  ],
  "features": [
    {
      "type": "Feature",
      "geometry": {
        "type": "Point",
        "coordinates": [
          21.219321,
          41.237017
        ]
      },
      "properties": {
        "description": "representative point"
      }
    },
    {
      "geometry": {
        "type": "Point",
        "coordinates": [
          21.219321,
          41.237017
        ]
      },
      "id": "darmc-location-24538",
      "type": "Feature",
      "properties": {
        "description": "1M scale point location",
        "location_precision": "precise",
        "title": "DARMC location 24538",
        "link": "http://pleiades.stoa.org/places/481773/darmc-location-24538"
      }
    }
  ]
}