{
  "type": "FeatureCollection",
  "title": "Germania",
  "id": "481844",
  "bbox": [
    23.264178,
    42.289175,
    23.264178,
    42.289175
  ],
  "description": "An ancient place, cited: BAtlas 49 F1 Germania",
  "names": [
    "Germania"
  ],
  "features": [
    {
      "type": "Feature",
      "geometry": {
        "type": "Point",
        "coordinates": [
          23.264178,
          42.289175
        ]
      },
      "properties": {
        "description": "representative point"
      }
    },
    {
      "geometry": {
        "type": "Point",
        "coordinates": [
          23.264178,
          42.289175
        ]
      },
      "id": "darmc-location-24639",
      "type": "Feature",
      "properties": {
        "description": "1M scale point location",
        "location_precision": "precise",
        "title": "DARMC location 24639",
        "link": "http://pleiades.stoa.org/places/481844/darmc-location-24639"
      }
    }
  ]
}