{
  "type": "FeatureCollection",
  "title": "*Gabuleum",
  "id": "481837",
  "description": "An ancient place, cited: BAtlas 49 C1 *Gabuleum",
  "bbox": [
    20.724177,
    42.212362,
    20.724177,
    42.212362
  ],
  "reprPoint": [
    20.724177,
    42.212362
  ],
  "names": [
    "Gabuleum"
  ],
  "features": [
    {
      "geometry": {
        "type": "Point",
        "coordinates": [
          20.724177,
          42.212362
        ]
      },
      "id": "darmc-location-24374",
      "type": "Feature",
      "properties": {
        "description": "1M scale point location",
        "location_precision": "precise",
        "title": "DARMC location 24374",
        "link": "http://pleiades.stoa.org/places/481837/darmc-location-24374"
      }
    }
  ]
}