{
  "type": "FeatureCollection",
  "title": "*Karistoron",
  "id": "481874",
  "description": "An ancient place, cited: BAtlas 49 E1 *Karistoron",
  "bbox": [
    22.700035,
    42.330809,
    22.700035,
    42.330809
  ],
  "reprPoint": [
    22.700035,
    42.330809
  ],
  "names": [
    "Karistoron"
  ],
  "features": [
    {
      "geometry": {
        "type": "Point",
        "coordinates": [
          22.700035,
          42.330809
        ]
      },
      "id": "darmc-location-16022",
      "type": "Feature",
      "properties": {
        "description": "1M scale point location",
        "location_precision": "precise",
        "title": "DARMC location 16022",
        "link": "http://pleiades.stoa.org/places/481874/darmc-location-16022"
      }
    }
  ]
}