{
  "type": "FeatureCollection",
  "title": "Gorubljane",
  "id": "481848",
  "bbox": [
    23.421808,
    42.610397,
    23.421808,
    42.610397
  ],
  "description": "An ancient place, cited: BAtlas 49 F1 Gorubljane",
  "features": [
    {
      "type": "Feature",
      "geometry": {
        "type": "Point",
        "coordinates": [
          23.421808,
          42.610397
        ]
      },
      "properties": {
        "description": "representative point"
      }
    },
    {
      "geometry": {
        "type": "Point",
        "coordinates": [
          23.421808,
          42.610397
        ]
      },
      "id": "darmc-location-12591",
      "type": "Feature",
      "properties": {
        "description": "1M scale point location",
        "location_precision": "precise",
        "title": "DARMC location 12591",
        "link": "http://pleiades.stoa.org/places/481848/darmc-location-12591"
      }
    }
  ]
}