{
  "type": "FeatureCollection",
  "title": "Kerax",
  "id": "481879",
  "description": "An ancient place, cited: BAtlas 49 C2 Kerax",
  "bbox": [
    20.679107,
    41.177324,
    20.679107,
    41.177324
  ],
  "reprPoint": [
    20.679107,
    41.177324
  ],
  "names": [
    "Kerax"
  ],
  "features": [
    {
      "geometry": {
        "type": "Point",
        "coordinates": [
          20.679107,
          41.177324
        ]
      },
      "id": "darmc-location-24544",
      "type": "Feature",
      "properties": {
        "description": "1M scale point location",
        "location_precision": "precise",
        "title": "DARMC location 24544",
        "link": "http://pleiades.stoa.org/places/481879/darmc-location-24544"
      }
    }
  ]
}