{
  "type": "FeatureCollection",
  "title": "‘Extuomne’",
  "id": "481835",
  "bbox": [
    23.464912,
    42.659229,
    23.464912,
    42.659229
  ],
  "description": "An ancient place, cited: BAtlas 49 F1 ‘Extuomne’",
  "names": [
    "Extuomne"
  ],
  "features": [
    {
      "type": "Feature",
      "geometry": {
        "type": "Point",
        "coordinates": [
          23.464912,
          42.659229
        ]
      },
      "properties": {
        "description": "representative point"
      }
    },
    {
      "geometry": {
        "type": "Point",
        "coordinates": [
          23.464912,
          42.659229
        ]
      },
      "id": "darmc-location-24470",
      "type": "Feature",
      "properties": {
        "description": "1M scale point location",
        "location_precision": "precise",
        "title": "DARMC location 24470",
        "link": "http://pleiades.stoa.org/places/481835/darmc-location-24470"
      }
    }
  ]
}