{
  "type": "FeatureCollection",
  "title": "Pons Servili",
  "id": "481963",
  "bbox": [
    20.511961,
    41.073671,
    20.511961,
    41.073671
  ],
  "description": "An ancient place, cited: BAtlas 49 C2 Pons Servili",
  "names": [
    "Pons Servili"
  ],
  "features": [
    {
      "type": "Feature",
      "geometry": {
        "type": "Point",
        "coordinates": [
          20.511961,
          41.073671
        ]
      },
      "properties": {
        "description": "representative point"
      }
    },
    {
      "geometry": {
        "type": "Point",
        "coordinates": [
          20.511961,
          41.073671
        ]
      },
      "id": "darmc-location-4418",
      "type": "Feature",
      "properties": {
        "description": "1M scale point location",
        "location_precision": "precise",
        "title": "DARMC location 4418",
        "link": "http://pleiades.stoa.org/places/481963/darmc-location-4418"
      }
    }
  ]
}