{
  "type": "FeatureCollection",
  "title": "Skombros (mountain)",
  "id": "481993",
  "bbox": [
    23.283333,
    42.566667,
    23.283333,
    42.566667
  ],
  "description": "Mt. Vitosha.",
  "names": [
    "Skombros"
  ],
  "features": [
    {
      "type": "Feature",
      "geometry": {
        "type": "Point",
        "coordinates": [
          23.283333,
          42.566667
        ]
      },
      "properties": {
        "description": "representative point"
      }
    },
    {
      "geometry": {
        "type": "Point",
        "coordinates": [
          23.283333,
          42.566667
        ]
      },
      "id": "location-of-skombros-m-1",
      "type": "Feature",
      "properties": {
        "description": "verified in Google Earth 2013.",
        "location_precision": "precise",
        "title": "location of Skombros M.",
        "link": "http://pleiades.stoa.org/places/481993/location-of-skombros-m-1"
      }
    }
  ]
}