{
  "type": "FeatureCollection",
  "title": "Treiecto",
  "id": "482021",
  "bbox": [
    20.268158,
    41.160561,
    20.268158,
    41.160561
  ],
  "description": "An ancient place, cited: BAtlas 49 C2 Treiecto",
  "names": [
    "Treiecto"
  ],
  "features": [
    {
      "type": "Feature",
      "geometry": {
        "type": "Point",
        "coordinates": [
          20.268158,
          41.160561
        ]
      },
      "properties": {
        "description": "representative point"
      }
    },
    {
      "geometry": {
        "type": "Point",
        "coordinates": [
          20.268158,
          41.160561
        ]
      },
      "id": "darmc-location-8648",
      "type": "Feature",
      "properties": {
        "description": "1M scale point location",
        "location_precision": "precise",
        "title": "DARMC location 8648",
        "link": "http://pleiades.stoa.org/places/482021/darmc-location-8648"
      }
    }
  ]
}