{
  "type": "FeatureCollection",
  "title": "Sportela",
  "id": "482000",
  "bbox": [
    23.172221,
    42.128406,
    23.172221,
    42.128406
  ],
  "description": "An ancient place, cited: BAtlas 49 F1 Sportela",
  "names": [
    "Sportela"
  ],
  "features": [
    {
      "type": "Feature",
      "geometry": {
        "type": "Point",
        "coordinates": [
          23.172221,
          42.128406
        ]
      },
      "properties": {
        "description": "representative point"
      }
    },
    {
      "geometry": {
        "type": "Point",
        "coordinates": [
          23.172221,
          42.128406
        ]
      },
      "id": "darmc-location-14852",
      "type": "Feature",
      "properties": {
        "description": "1M scale point location",
        "location_precision": "precise",
        "title": "DARMC location 14852",
        "link": "http://pleiades.stoa.org/places/482000/darmc-location-14852"
      }
    }
  ]
}