{
  "type": "FeatureCollection",
  "title": "Puig des Molins necropolis",
  "id": "482947335",
  "bbox": [
    1.4314998,
    38.9055237,
    1.4314998,
    38.9055237
  ],
  "description": "A Carthaginian necropolis on the island of Ibiza.",
  "connectsWith": [
    "265884"
  ],
  "features": [
    {
      "type": "Feature",
      "geometry": {
        "type": "Point",
        "coordinates": [
          1.4314998,
          38.9055237
        ]
      },
      "properties": {
        "description": "representative point"
      }
    },
    {
      "geometry": {
        "type": "Point",
        "coordinates": [
          1.4314998,
          38.9055237
        ]
      },
      "id": "osm-location",
      "type": "Feature",
      "properties": {
        "description": "Location based on OpenStreetMap",
        "location_precision": "precise",
        "title": "OSM location of Necròpoli de Puig des Molins",
        "link": "http://pleiades.stoa.org/places/482947335/osm-location"
      }
    }
  ]
}