{
  "type": "FeatureCollection",
  "title": "Crustuminus Ager",
  "id": "485712934",
  "bbox": [
    12.550061,
    42.0150826,
    12.550061,
    42.0150826
  ],
  "description": "The territory of the city of Crustumerium.",
  "features": [
    {
      "type": "Feature",
      "geometry": {
        "type": "Point",
        "coordinates": [
          12.550061,
          42.0150826
        ]
      },
      "properties": {
        "description": "representative point"
      }
    }
  ]
}