{
  "type": "FeatureCollection",
  "title": "Crustuminus Ager",
  "id": "485712934",
  "bbox": [
    12.527692,
    42.017205,
    12.527692,
    42.017205
  ],
  "description": "The territory of the city of Crustumerium.",
  "features": [
    {
      "type": "Feature",
      "geometry": {
        "type": "Point",
        "coordinates": [
          12.527692,
          42.017205
        ]
      },
      "properties": {
        "description": "representative point"
      }
    }
  ]
}