{
  "type": "FeatureCollection",
  "title": "Roman theater at Soloi/Aipeia?",
  "id": "48637573",
  "bbox": [
    32.8117277,
    35.1395552,
    32.8117277,
    35.1395552
  ],
  "description": "The Roman theater at Soloi, Cyprus.",
  "connectsWith": [
    "707624"
  ],
  "features": [
    {
      "type": "Feature",
      "geometry": {
        "type": "Point",
        "coordinates": [
          32.8117277,
          35.1395552
        ]
      },
      "properties": {
        "description": "representative point"
      }
    },
    {
      "geometry": {
        "type": "Point",
        "coordinates": [
          32.8117277,
          35.1395552
        ]
      },
      "id": "location-of-roman-theater",
      "type": "Feature",
      "properties": {
        "description": "Representative location based on OpenStreetMap",
        "location_precision": "precise",
        "title": "OSM location of Soloi Theatre",
        "link": "http://pleiades.stoa.org/places/48637573/location-of-roman-theater"
      }
    }
  ]
}