{
  "type": "FeatureCollection",
  "title": "Tuscan Archipelago",
  "id": "490307091",
  "bbox": [
    9.817982,
    42.25,
    11.1,
    43.433333
  ],
  "description": "A chain of islands between the Ligurian Sea and Tyrrhenian Sea.",
  "connectsWith": [
    "1356"
  ],
  "features": [
    {
      "type": "Feature",
      "geometry": {
        "type": "Point",
        "coordinates": [
          10.3316725429,
          42.6788369
        ]
      },
      "properties": {
        "description": "representative point"
      }
    }
  ]
}