{
  "type": "FeatureCollection",
  "title": "Villa del fondo Ippolito Zurlo",
  "id": "490597949",
  "bbox": [
    14.471389,
    40.761389,
    14.47517,
    40.775431
  ],
  "description": "A Roman villa located in the contrada Giuliana at Boscoreale on a side street of via Grotta II. The site was excavated by Vincenzo De Prisco in 1897 and subsequently reinterred.",
  "connectsWith": [
    "432723"
  ],
  "features": [
    {
      "type": "Feature",
      "geometry": {
        "type": "Point",
        "coordinates": [
          14.4732795,
          40.76841
        ]
      },
      "properties": {
        "description": "representative point"
      }
    }
  ]
}