{
  "type": "FeatureCollection",
  "title": "Delisinci",
  "id": "491568",
  "description": "An ancient place, cited: BAtlas 50 A1 Delisinci",
  "bbox": [
    21.987365,
    41.795492,
    21.987365,
    41.795492
  ],
  "reprPoint": [
    21.987365,
    41.795492
  ],
  "features": [
    {
      "geometry": {
        "type": "Point",
        "coordinates": [
          21.987365,
          41.795492
        ]
      },
      "id": "darmc-location-12173",
      "type": "Feature",
      "properties": {
        "description": "500K scale point location",
        "location_precision": "precise",
        "title": "DARMC location 12173",
        "link": "http://pleiades.stoa.org/places/491568/darmc-location-12173"
      }
    }
  ]
}