{
  "type": "FeatureCollection",
  "title": "Euboia/Dausara",
  "id": "491593",
  "description": "An ancient place, cited: BAtlas 50 B3 Euboia/Dausara",
  "bbox": [
    22.12943,
    40.76918,
    22.12943,
    40.76918
  ],
  "reprPoint": [
    22.12943,
    40.76918
  ],
  "names": [
    "Euboia",
    "Dausara"
  ],
  "features": [
    {
      "geometry": {
        "type": "Point",
        "coordinates": [
          22.12943,
          40.76918
        ]
      },
      "id": "darmc-location-3001",
      "type": "Feature",
      "properties": {
        "description": "500K scale point location",
        "location_precision": "precise",
        "title": "DARMC location 3001",
        "link": "http://pleiades.stoa.org/places/491593/darmc-location-3001"
      }
    }
  ]
}