{
  "type": "FeatureCollection",
  "title": "Bora/Bermion M.",
  "id": "491551",
  "description": "An ancient place, cited: BAtlas 50 A3 Bora/Bermion M.",
  "bbox": [
    22.010422,
    40.525805,
    22.010422,
    40.525805
  ],
  "reprPoint": [
    22.010422,
    40.525805
  ],
  "names": [
    "Bora",
    "Bermion M."
  ],
  "features": [
    {
      "geometry": {
        "type": "Point",
        "coordinates": [
          22.010422,
          40.525805
        ]
      },
      "id": "location-of-bora-bermion-m",
      "type": "Feature",
      "properties": {
        "description": "verified in Google Earth 2013.",
        "location_precision": "precise",
        "title": "location of Bora/Bermion M.",
        "link": "http://pleiades.stoa.org/places/491551/location-of-bora-bermion-m"
      }
    }
  ]
}