{
  "type": "FeatureCollection",
  "title": "Astibos",
  "id": "491530",
  "bbox": [
    22.186338,
    41.723108,
    22.200552,
    41.738271
  ],
  "description": "An ancient place, cited: BAtlas 50 B1 Astibos",
  "names": [
    "Astibos"
  ],
  "features": [
    {
      "type": "Feature",
      "geometry": {
        "type": "Point",
        "coordinates": [
          22.193445,
          41.7306895
        ]
      },
      "properties": {
        "description": "representative point"
      }
    },
    {
      "geometry": {
        "type": "Point",
        "coordinates": [
          22.200552,
          41.723108
        ]
      },
      "id": "darmc-location-2699",
      "type": "Feature",
      "properties": {
        "description": "1M scale point location",
        "location_precision": "precise",
        "title": "DARMC location 2699",
        "link": "http://pleiades.stoa.org/places/491530/darmc-location-2699"
      }
    },
    {
      "geometry": {
        "type": "Point",
        "coordinates": [
          22.186338,
          41.738271
        ]
      },
      "id": "dare-location",
      "type": "Feature",
      "properties": {
        "description": "Representative point location, site precision",
        "location_precision": "precise",
        "title": "DARE Location",
        "link": "http://pleiades.stoa.org/places/491530/dare-location"
      }
    }
  ]
}