{
  "type": "FeatureCollection",
  "title": "Aphytis",
  "id": "491525",
  "bbox": [
    23.436606,
    40.099366,
    23.436606,
    40.099366
  ],
  "description": "Aphytis was a polis on the Pallene peninsula. It was part of the Delian League in the 5th century BC, part of the Chalkidean League in the first half of the 4th century BC, and part of Macedon in the late 4th century BC and Hellenistic period.",
  "connectsWith": [
    "48050879",
    "491682",
    "991253193"
  ],
  "names": [
    "Aphytis"
  ],
  "features": [
    {
      "type": "Feature",
      "geometry": {
        "type": "Point",
        "coordinates": [
          23.436606,
          40.099366
        ]
      },
      "properties": {
        "description": "representative point"
      }
    },
    {
      "geometry": {
        "type": "Point",
        "coordinates": [
          23.436606,
          40.099366
        ]
      },
      "id": "darmc-location-24035",
      "type": "Feature",
      "properties": {
        "description": "1:1 million scale representative point location digitized from the Barrington Atlas of the Greek and Roman World by the Digital Atlas of Roman and Medieval Civilizations project at Harvard University.",
        "location_precision": "precise",
        "title": "DARMC location 24035",
        "link": "http://pleiades.stoa.org/places/491525/darmc-location-24035"
      }
    }
  ]
}