{
  "type": "FeatureCollection",
  "title": "Aphytis",
  "id": "491525",
  "description": "An ancient place, cited: BAtlas 50 D4 Aphytis",
  "bbox": [
    23.436606,
    40.099366,
    23.436606,
    40.099366
  ],
  "reprPoint": [
    23.436606,
    40.099366
  ],
  "names": [
    "Aphytis"
  ],
  "features": [
    {
      "geometry": {
        "type": "Point",
        "coordinates": [
          23.436606,
          40.099366
        ]
      },
      "id": "darmc-location-24035",
      "type": "Feature",
      "properties": {
        "description": "1M scale point location",
        "location_precision": "precise",
        "title": "DARMC location 24035",
        "link": "http://pleiades.stoa.org/places/491525/darmc-location-24035"
      }
    }
  ]
}