{
  "type": "FeatureCollection",
  "title": "Katerini",
  "id": "491631",
  "bbox": [
    22.5087618,
    40.2713616,
    22.5087618,
    40.2713616
  ],
  "description": "Chance finds and rescue excavations in the vicinity of modern Katerini (Pieria, Greece) indicate the presence of burials and manufacturing facilities in the area during antiquity.",
  "features": [
    {
      "type": "Feature",
      "geometry": {
        "type": "Point",
        "coordinates": [
          22.5087618,
          40.2713616
        ]
      },
      "properties": {
        "description": "representative point"
      }
    },
    {
      "geometry": {
        "type": "Point",
        "coordinates": [
          22.5087618,
          40.2713616
        ]
      },
      "id": "osm-location-modern-katerini",
      "type": "Feature",
      "properties": {
        "description": "Location based on OpenStreetMap",
        "location_precision": "precise",
        "title": "OSM Location: modern Katerini",
        "link": "http://pleiades.stoa.org/places/491631/osm-location-modern-katerini"
      }
    }
  ]
}