{
  "type": "FeatureCollection",
  "title": "Glišič",
  "id": "491604",
  "bbox": [
    22.03656,
    41.466915,
    22.03656,
    41.466915
  ],
  "description": "An ancient place, cited: BAtlas 50 B2 Glišič",
  "features": [
    {
      "type": "Feature",
      "geometry": {
        "type": "Point",
        "coordinates": [
          22.03656,
          41.466915
        ]
      },
      "properties": {
        "description": "representative point"
      }
    },
    {
      "geometry": {
        "type": "Point",
        "coordinates": [
          22.03656,
          41.466915
        ]
      },
      "id": "darmc-location-12566",
      "type": "Feature",
      "properties": {
        "description": "500K scale point location",
        "location_precision": "precise",
        "title": "DARMC location 12566",
        "link": "http://pleiades.stoa.org/places/491604/darmc-location-12566"
      }
    }
  ]
}