{
  "type": "FeatureCollection",
  "title": "Mre탑i훾ko",
  "id": "491666",
  "description": "An ancient place, cited: BAtlas 50 B2 Mre탑i훾ko",
  "bbox": [
    22.051226,
    41.184925,
    22.051226,
    41.184925
  ],
  "reprPoint": [
    22.051226,
    41.184925
  ],
  "features": [
    {
      "geometry": {
        "type": "Point",
        "coordinates": [
          22.051226,
          41.184925
        ]
      },
      "id": "darmc-location-2475",
      "type": "Feature",
      "properties": {
        "description": "1M scale point location",
        "location_precision": "precise",
        "title": "DARMC location 2475",
        "link": "http://pleiades.stoa.org/places/491666/darmc-location-2475"
      }
    }
  ]
}