{
  "type": "FeatureCollection",
  "title": "Krivi Dol",
  "id": "491644",
  "description": "An ancient place, cited: BAtlas 50 B1 Krivi Dol",
  "bbox": [
    22.079389,
    41.798193,
    22.079389,
    41.798193
  ],
  "reprPoint": [
    22.079389,
    41.798193
  ],
  "features": [
    {
      "geometry": {
        "type": "Point",
        "coordinates": [
          22.079389,
          41.798193
        ]
      },
      "id": "darmc-location-13315",
      "type": "Feature",
      "properties": {
        "description": "500K scale point location",
        "location_precision": "precise",
        "title": "DARMC location 13315",
        "link": "http://pleiades.stoa.org/places/491644/darmc-location-13315"
      }
    }
  ]
}