{
  "type": "FeatureCollection",
  "title": "Kozani",
  "id": "491642",
  "description": "An ancient place, cited: BAtlas 50 A4 Kozani",
  "bbox": [
    21.785881,
    40.300864,
    21.785881,
    40.300864
  ],
  "reprPoint": [
    21.785881,
    40.300864
  ],
  "features": [
    {
      "geometry": {
        "type": "Point",
        "coordinates": [
          21.785881,
          40.300864
        ]
      },
      "id": "darmc-location-24065",
      "type": "Feature",
      "properties": {
        "description": "1M scale point location",
        "location_precision": "precise",
        "title": "DARMC location 24065",
        "link": "http://pleiades.stoa.org/places/491642/darmc-location-24065"
      }
    }
  ]
}