{
  "type": "FeatureCollection",
  "title": "Kyrros",
  "id": "491647",
  "description": "An ancient place, cited: BAtlas 50 B3 Kyrros",
  "bbox": [
    22.282275,
    40.782314,
    22.30013,
    40.828282
  ],
  "reprPoint": [
    22.2912025,
    40.805298
  ],
  "names": [
    "Kyrros",
    "Scurio"
  ],
  "features": [
    {
      "geometry": {
        "type": "Point",
        "coordinates": [
          22.282275,
          40.782314
        ]
      },
      "id": "darmc-location-9702",
      "type": "Feature",
      "properties": {
        "description": "500K scale point location",
        "location_precision": "precise",
        "title": "DARMC location 9702",
        "link": "http://pleiades.stoa.org/places/491647/darmc-location-9702"
      }
    },
    {
      "geometry": {
        "type": "Point",
        "coordinates": [
          22.30013,
          40.828282
        ]
      },
      "id": "darmc-location-10112",
      "type": "Feature",
      "properties": {
        "description": "500K scale point location",
        "location_precision": "precise",
        "title": "DARMC location 10112",
        "link": "http://pleiades.stoa.org/places/491647/darmc-location-10112"
      }
    }
  ]
}