{
  "type": "FeatureCollection",
  "title": "Katunci",
  "id": "491632",
  "bbox": [
    23.472909,
    41.466078,
    23.472909,
    41.466078
  ],
  "description": "An ancient place, cited: BAtlas 50 D2 Katunci",
  "features": [
    {
      "type": "Feature",
      "geometry": {
        "type": "Point",
        "coordinates": [
          23.472909,
          41.466078
        ]
      },
      "properties": {
        "description": "representative point"
      }
    },
    {
      "geometry": {
        "type": "Point",
        "coordinates": [
          23.472909,
          41.466078
        ]
      },
      "id": "darmc-location-7889",
      "type": "Feature",
      "properties": {
        "description": "500K scale point location",
        "location_precision": "precise",
        "title": "DARMC location 7889",
        "link": "http://pleiades.stoa.org/places/491632/darmc-location-7889"
      }
    }
  ]
}