{
  "type": "FeatureCollection",
  "title": "Katerini",
  "id": "491631",
  "description": "An ancient place, cited: BAtlas 50 C4 Katerini",
  "bbox": [
    22.508687,
    40.271427,
    22.508687,
    40.271427
  ],
  "reprPoint": [
    22.508687,
    40.271427
  ],
  "features": [
    {
      "geometry": {
        "type": "Point",
        "coordinates": [
          22.508687,
          40.271427
        ]
      },
      "id": "darmc-location-23632",
      "type": "Feature",
      "properties": {
        "description": "Point location",
        "location_precision": "precise",
        "title": "DARMC location 23632",
        "link": "http://pleiades.stoa.org/places/491631/darmc-location-23632"
      }
    }
  ]
}