{
  "type": "FeatureCollection",
  "title": "Kavadarci",
  "id": "491633",
  "bbox": [
    22.03056,
    41.440203,
    22.03056,
    41.440203
  ],
  "description": "An ancient place, cited: BAtlas 50 B2 Kavadarci",
  "features": [
    {
      "type": "Feature",
      "geometry": {
        "type": "Point",
        "coordinates": [
          22.03056,
          41.440203
        ]
      },
      "properties": {
        "description": "representative point"
      }
    },
    {
      "geometry": {
        "type": "Point",
        "coordinates": [
          22.03056,
          41.440203
        ]
      },
      "id": "darmc-location-13075",
      "type": "Feature",
      "properties": {
        "description": "500K scale point location",
        "location_precision": "precise",
        "title": "DARMC location 13075",
        "link": "http://pleiades.stoa.org/places/491633/darmc-location-13075"
      }
    }
  ]
}