{
  "type": "FeatureCollection",
  "title": "Novi Dojran",
  "id": "491674",
  "description": "An ancient place, cited: BAtlas 50 C2 Novi Dojran",
  "bbox": [
    22.707089,
    41.232464,
    22.707089,
    41.232464
  ],
  "reprPoint": [
    22.707089,
    41.232464
  ],
  "features": [
    {
      "geometry": {
        "type": "Point",
        "coordinates": [
          22.707089,
          41.232464
        ]
      },
      "id": "darmc-location-13959",
      "type": "Feature",
      "properties": {
        "description": "500K scale point location",
        "location_precision": "precise",
        "title": "DARMC location 13959",
        "link": "http://pleiades.stoa.org/places/491674/darmc-location-13959"
      }
    }
  ]
}