{
  "type": "FeatureCollection",
  "title": "Grnčište",
  "id": "491609",
  "bbox": [
    21.847604,
    41.641496,
    21.847604,
    41.641496
  ],
  "description": "An ancient place, cited: BAtlas 50 A1 Grnčište",
  "features": [
    {
      "type": "Feature",
      "geometry": {
        "type": "Point",
        "coordinates": [
          21.847604,
          41.641496
        ]
      },
      "properties": {
        "description": "representative point"
      }
    },
    {
      "geometry": {
        "type": "Point",
        "coordinates": [
          21.847604,
          41.641496
        ]
      },
      "id": "darmc-location-12607",
      "type": "Feature",
      "properties": {
        "description": "500K scale point location",
        "location_precision": "precise",
        "title": "DARMC location 12607",
        "link": "http://pleiades.stoa.org/places/491609/darmc-location-12607"
      }
    }
  ]
}