{
  "type": "FeatureCollection",
  "title": "Razlog",
  "id": "491709",
  "bbox": [
    23.388177,
    41.87967,
    23.388177,
    41.87967
  ],
  "description": "An ancient place, cited: BAtlas 50 D1 Razlog",
  "features": [
    {
      "type": "Feature",
      "geometry": {
        "type": "Point",
        "coordinates": [
          23.388177,
          41.87967
        ]
      },
      "properties": {
        "description": "representative point"
      }
    },
    {
      "geometry": {
        "type": "Point",
        "coordinates": [
          23.388177,
          41.87967
        ]
      },
      "id": "darmc-location-8235",
      "type": "Feature",
      "properties": {
        "description": "500K scale point location",
        "location_precision": "precise",
        "title": "DARMC location 8235",
        "link": "http://pleiades.stoa.org/places/491709/darmc-location-8235"
      }
    }
  ]
}