{
  "type": "FeatureCollection",
  "title": "Pythion",
  "id": "491705",
  "bbox": [
    22.229219,
    40.065766,
    22.229219,
    40.065766
  ],
  "description": "An ancient place, cited: BAtlas 50 B4 Pythion",
  "names": [
    "Pythion"
  ],
  "features": [
    {
      "type": "Feature",
      "geometry": {
        "type": "Point",
        "coordinates": [
          22.229219,
          40.065766
        ]
      },
      "properties": {
        "description": "representative point"
      }
    },
    {
      "geometry": {
        "type": "Point",
        "coordinates": [
          22.229219,
          40.065766
        ]
      },
      "id": "darmc-location-61",
      "type": "Feature",
      "properties": {
        "description": "TIB point location",
        "location_precision": "precise",
        "title": "DARMC location 61",
        "link": "http://pleiades.stoa.org/places/491705/darmc-location-61"
      }
    }
  ]
}