{
  "type": "FeatureCollection",
  "title": "Tinde",
  "id": "491743",
  "bbox": [
    23.026394,
    40.395222,
    23.026394,
    40.395222
  ],
  "description": "An ancient place, cited: BAtlas 50 D4 Tinde",
  "names": [
    "Tinde"
  ],
  "features": [
    {
      "type": "Feature",
      "geometry": {
        "type": "Point",
        "coordinates": [
          23.026394,
          40.395222
        ]
      },
      "properties": {
        "description": "representative point"
      }
    },
    {
      "geometry": {
        "type": "Point",
        "coordinates": [
          23.026394,
          40.395222
        ]
      },
      "id": "darmc-location-10240",
      "type": "Feature",
      "properties": {
        "description": "500K scale point location",
        "location_precision": "precise",
        "title": "DARMC location 10240",
        "link": "http://pleiades.stoa.org/places/491743/darmc-location-10240"
      }
    }
  ]
}