{
  "type": "FeatureCollection",
  "title": "Pydna",
  "id": "491703",
  "description": "An ancient place, cited: BAtlas 50 C4 Pydna",
  "bbox": [
    22.560095,
    40.394976,
    22.560095,
    40.394976
  ],
  "connectsWith": [
    "196789404"
  ],
  "reprPoint": [
    22.560095,
    40.394976
  ],
  "names": [
    "Pydna"
  ],
  "features": [
    {
      "geometry": {
        "type": "Point",
        "coordinates": [
          22.560095,
          40.394976
        ]
      },
      "id": "darmc-location-24191",
      "type": "Feature",
      "properties": {
        "description": "1M scale point location",
        "location_precision": "precise",
        "title": "DARMC location 24191",
        "link": "http://pleiades.stoa.org/places/491703/darmc-location-24191"
      }
    }
  ]
}