{
  "type": "FeatureCollection",
  "title": "Vodoča",
  "id": "491751",
  "description": "An ancient place, cited: BAtlas 50 C2 Vodoča",
  "bbox": [
    22.586408,
    41.466816,
    22.586408,
    41.466816
  ],
  "reprPoint": [
    22.586408,
    41.466816
  ],
  "features": [
    {
      "geometry": {
        "type": "Point",
        "coordinates": [
          22.586408,
          41.466816
        ]
      },
      "id": "darmc-location-15428",
      "type": "Feature",
      "properties": {
        "description": "500K scale point location",
        "location_precision": "precise",
        "title": "DARMC location 15428",
        "link": "http://pleiades.stoa.org/places/491751/darmc-location-15428"
      }
    }
  ]
}