{
  "type": "FeatureCollection",
  "title": "Rabrovo",
  "id": "491707",
  "description": "An ancient place, cited: BAtlas 50 C2 Rabrovo",
  "bbox": [
    22.579127,
    41.305454,
    22.579127,
    41.305454
  ],
  "reprPoint": [
    22.579127,
    41.305454
  ],
  "features": [
    {
      "geometry": {
        "type": "Point",
        "coordinates": [
          22.579127,
          41.305454
        ]
      },
      "id": "darmc-location-5618",
      "type": "Feature",
      "properties": {
        "description": "1M scale point location",
        "location_precision": "precise",
        "title": "DARMC location 5618",
        "link": "http://pleiades.stoa.org/places/491707/darmc-location-5618"
      }
    }
  ]
}