{
  "type": "FeatureCollection",
  "title": "Thermaicus Sinus",
  "id": "491739",
  "bbox": [
    22.783333,
    40.383333,
    22.783333,
    40.383333
  ],
  "description": "An ancient place, cited: BAtlas 50 C4 Thermaicus Sinus",
  "names": [
    "Thermaicus Sinus"
  ],
  "features": [
    {
      "type": "Feature",
      "geometry": {
        "type": "Point",
        "coordinates": [
          22.783333,
          40.383333
        ]
      },
      "properties": {
        "description": "representative point"
      }
    },
    {
      "geometry": {
        "type": "Point",
        "coordinates": [
          22.783333,
          40.383333
        ]
      },
      "id": "location-of-thermaic-gulf",
      "type": "Feature",
      "properties": {
        "description": "verified in Google Earth 2013.",
        "location_precision": "precise",
        "title": "location of Thermaic Gulf",
        "link": "http://pleiades.stoa.org/places/491739/location-of-thermaic-gulf"
      }
    }
  ]
}