{
  "type": "FeatureCollection",
  "title": "Stenas",
  "id": "491730",
  "description": "An ancient place, cited: BAtlas 50 B2 Stenas",
  "bbox": [
    22.384158,
    41.351244,
    22.4014,
    41.3792
  ],
  "reprPoint": [
    22.392779,
    41.365222
  ],
  "names": [
    "Stenas"
  ],
  "features": [
    {
      "geometry": {
        "type": "Point",
        "coordinates": [
          22.384158,
          41.351244
        ]
      },
      "id": "darmc-location-2639",
      "type": "Feature",
      "properties": {
        "description": "1M scale point location",
        "location_precision": "precise",
        "title": "DARMC location 2639",
        "link": "http://pleiades.stoa.org/places/491730/darmc-location-2639"
      }
    },
    {
      "geometry": {
        "type": "Point",
        "coordinates": [
          22.401399999999967,
          41.3792
        ]
      },
      "id": "dare-location",
      "type": "Feature",
      "properties": {
        "description": "Representative point location, village precision",
        "location_precision": "precise",
        "title": "DARE Location",
        "link": "http://pleiades.stoa.org/places/491730/dare-location"
      }
    }
  ]
}