{
  "type": "FeatureCollection",
  "title": "Pydna",
  "id": "491703",
  "bbox": [
    22.560095,
    40.394976,
    22.560095,
    40.394976
  ],
  "description": "An ancient place, cited: BAtlas 50 C4 Pydna",
  "connectsWith": [
    "196789404"
  ],
  "names": [
    "Pydna"
  ],
  "features": [
    {
      "type": "Feature",
      "geometry": {
        "type": "Point",
        "coordinates": [
          22.560095,
          40.394976
        ]
      },
      "properties": {
        "description": "representative point"
      }
    },
    {
      "geometry": {
        "type": "Point",
        "coordinates": [
          22.560095,
          40.394976
        ]
      },
      "id": "darmc-location-24191",
      "type": "Feature",
      "properties": {
        "description": "1:1 million scale representative point location digitized from the Barrington Atlas of the Greek and Roman World by the Digital Atlas of Roman and Medieval Civilizations project at Harvard University.",
        "location_precision": "precise",
        "title": "DARMC location 24191",
        "link": "http://pleiades.stoa.org/places/491703/darmc-location-24191"
      }
    }
  ]
}