{
  "type": "FeatureCollection",
  "title": "Vranja",
  "id": "491754",
  "bbox": [
    23.426973,
    41.456594,
    23.426973,
    41.456594
  ],
  "description": "An ancient place, cited: BAtlas 50 D2 Vranja",
  "features": [
    {
      "type": "Feature",
      "geometry": {
        "type": "Point",
        "coordinates": [
          23.426973,
          41.456594
        ]
      },
      "properties": {
        "description": "representative point"
      }
    },
    {
      "geometry": {
        "type": "Point",
        "coordinates": [
          23.426973,
          41.456594
        ]
      },
      "id": "darmc-location-8438",
      "type": "Feature",
      "properties": {
        "description": "500K scale point location",
        "location_precision": "precise",
        "title": "DARMC location 8438",
        "link": "http://pleiades.stoa.org/places/491754/darmc-location-8438"
      }
    }
  ]
}