{
  "type": "FeatureCollection",
  "title": "Untitled",
  "id": "493019",
  "description": "An ancient place, cited: BAtlas 50 C1 unnamed quarry (SW Negrevo)",
  "bbox": [
    22.783879,
    41.783029,
    22.783879,
    41.783029
  ],
  "reprPoint": [
    22.783879,
    41.783029
  ],
  "features": [
    {
      "geometry": {
        "type": "Point",
        "coordinates": [
          22.783879,
          41.783029
        ]
      },
      "id": "darmc-location-19009",
      "type": "Feature",
      "properties": {
        "description": "500K scale point location",
        "location_precision": "precise",
        "title": "DARMC location 19009",
        "link": "http://pleiades.stoa.org/places/493019/darmc-location-19009"
      }
    }
  ]
}