{
  "type": "FeatureCollection",
  "title": "Roman amphitheater at Interamnia Praetuttiorum",
  "id": "493909773",
  "bbox": [
    13.7036316,
    42.6584032,
    13.7036316,
    42.6584032
  ],
  "description": "A Roman amphitheater of the first century A.D.",
  "connectsWith": [
    "413179"
  ],
  "features": [
    {
      "type": "Feature",
      "geometry": {
        "type": "Point",
        "coordinates": [
          13.7036316,
          42.6584032
        ]
      },
      "properties": {
        "description": "representative point"
      }
    },
    {
      "geometry": {
        "type": "Point",
        "coordinates": [
          13.7036316,
          42.6584032
        ]
      },
      "id": "location-of-roman-amphitheater",
      "type": "Feature",
      "properties": {
        "description": "Location based on OpenStreetMap",
        "location_precision": "precise",
        "title": "location of Roman amphitheater",
        "link": "http://pleiades.stoa.org/places/493909773/location-of-roman-amphitheater"
      }
    }
  ]
}