{
  "type": "FeatureCollection",
  "title": "Masseria Petrolio",
  "id": "495078212",
  "bbox": [
    13.3775937,
    41.2231091,
    13.8947953,
    41.9638555
  ],
  "description": "The substruction (basis) of a Roman villa rustica dating to the late republican period located near the course of the Garigliano river.",
  "connectsWith": [
    "432910"
  ],
  "features": [
    {
      "type": "Feature",
      "geometry": {
        "type": "Point",
        "coordinates": [
          13.6485278507,
          41.5495763171
        ]
      },
      "properties": {
        "description": "representative point"
      }
    }
  ]
}