{
  "type": "FeatureCollection",
  "title": "Untitled",
  "id": "495763998",
  "description": "Unlabeled feature captured from the Barrington Atlas",
  "bbox": [
    21.592795,
    42.205045,
    21.592795,
    42.205045
  ],
  "reprPoint": [
    21.592795,
    42.205045
  ],
  "features": [
    {
      "geometry": {
        "type": "Point",
        "coordinates": [
          21.592795,
          42.205045
        ]
      },
      "id": "darmc-location-18838",
      "type": "Feature",
      "properties": {
        "description": "1M scale point location",
        "location_precision": "precise",
        "title": "DARMC location 18838",
        "link": "http://pleiades.stoa.org/places/495763998/darmc-location-18838"
      }
    }
  ]
}