{
  "type": "FeatureCollection",
  "title": "Untitled",
  "id": "495763997",
  "bbox": [
    22.908185,
    41.779175,
    22.908185,
    41.779175
  ],
  "description": "Unlabeled feature captured from the Barrington Atlas",
  "connectsWith": [
    "491686"
  ],
  "features": [
    {
      "type": "Feature",
      "geometry": {
        "type": "Point",
        "coordinates": [
          22.908185,
          41.779175
        ]
      },
      "properties": {
        "description": "representative point"
      }
    },
    {
      "geometry": {
        "type": "Point",
        "coordinates": [
          22.908185,
          41.779175
        ]
      },
      "id": "darmc-location-19011",
      "type": "Feature",
      "properties": {
        "description": "500K scale point location",
        "location_precision": "precise",
        "title": "DARMC location 19011",
        "link": "http://pleiades.stoa.org/places/495763997/darmc-location-19011"
      }
    }
  ]
}