{
  "type": "FeatureCollection",
  "title": "Untitled",
  "id": "495763999",
  "description": "Unlabeled feature captured from the Barrington Atlas",
  "bbox": [
    21.561563,
    42.915195,
    21.561563,
    42.915195
  ],
  "reprPoint": [
    21.561563,
    42.915195
  ],
  "features": [
    {
      "geometry": {
        "type": "Point",
        "coordinates": [
          21.561563,
          42.915195
        ]
      },
      "id": "darmc-location-18813",
      "type": "Feature",
      "properties": {
        "description": "1M scale point location",
        "location_precision": "precise",
        "title": "DARMC location 18813",
        "link": "http://pleiades.stoa.org/places/495763999/darmc-location-18813"
      }
    }
  ]
}