{
  "type": "FeatureCollection",
  "title": "Untitled",
  "id": "495763995",
  "description": "Unlabeled feature captured from the Barrington Atlas",
  "bbox": [
    19.365792,
    44.116581,
    19.365792,
    44.116581
  ],
  "reprPoint": [
    19.365792,
    44.116581
  ],
  "features": [
    {
      "geometry": {
        "type": "Point",
        "coordinates": [
          19.365792,
          44.116581
        ]
      },
      "id": "darmc-location-18762",
      "type": "Feature",
      "properties": {
        "description": "1M scale point location",
        "location_precision": "precise",
        "title": "DARMC location 18762",
        "link": "http://pleiades.stoa.org/places/495763995/darmc-location-18762"
      }
    }
  ]
}