{
  "type": "FeatureCollection",
  "title": "Ipogeo dei Cristallini ",
  "id": "497313871",
  "bbox": [
    14.2538702,
    40.8577579,
    14.2538702,
    40.8577579
  ],
  "description": "A hypogeum tomb of the Hellenistic period in Neapolis (now Naples, Italy).",
  "connectsWith": [
    "433014"
  ],
  "names": [
    "Ipogeo dei Cristallini"
  ],
  "features": [
    {
      "type": "Feature",
      "geometry": {
        "type": "Point",
        "coordinates": [
          14.2538702,
          40.8577579
        ]
      },
      "properties": {
        "description": "representative point"
      }
    },
    {
      "geometry": {
        "type": "Point",
        "coordinates": [
          14.2538702,
          40.8577579
        ]
      },
      "id": "osm-location-of-ipogeo-dei-cristallini",
      "type": "Feature",
      "properties": {
        "description": "Representative location based on OpenStreetMap",
        "location_precision": "precise",
        "title": "OSM location of Ipogeo dei Cristallini",
        "link": "http://pleiades.stoa.org/places/497313871/osm-location-of-ipogeo-dei-cristallini"
      }
    }
  ]
}