{
  "type": "FeatureCollection",
  "title": "Karban-I",
  "id": "497446829",
  "bbox": [
    86.205714,
    51.039376,
    86.205714,
    51.039376
  ],
  "description": "Burial site in the Northern Altai region containing remains associated with the Bulan-Koby culture (2nd-5th centuries CE).",
  "names": [
    "Karban-I"
  ],
  "features": [
    {
      "type": "Feature",
      "geometry": {
        "type": "Point",
        "coordinates": [
          86.205714,
          51.039376
        ]
      },
      "properties": {
        "description": "representative point"
      }
    },
    {
      "geometry": {
        "type": "Point",
        "coordinates": [
          86.205714,
          51.039376
        ]
      },
      "id": "approximate-imagery-location-of-karban-i-site",
      "type": "Feature",
      "properties": {
        "description": "Point representing the approximate centerpoint of the Karban-I site, after Seregin 2022.",
        "location_precision": "precise",
        "title": "Approximate imagery location of Karban-I site",
        "link": "http://pleiades.stoa.org/places/497446829/approximate-imagery-location-of-karban-i-site"
      }
    }
  ]
}