{
  "type": "FeatureCollection",
  "title": "Roman walls of Lugo",
  "id": "49788037",
  "bbox": [
    -7.55333,
    43.011102,
    -7.55333,
    43.011102
  ],
  "description": "Late Roman fortifications.",
  "connectsWith": [
    "236525"
  ],
  "features": [
    {
      "type": "Feature",
      "geometry": {
        "type": "Point",
        "coordinates": [
          -7.55333,
          43.011102
        ]
      },
      "properties": {
        "description": "representative point"
      }
    },
    {
      "geometry": {
        "type": "Point",
        "coordinates": [
          -7.55333,
          43.011102
        ]
      },
      "id": "roman-walls-of-lugo",
      "type": "Feature",
      "properties": {
        "description": "Late Roman fortifications. Coordinates after GeoHack, verified in Google Earth.",
        "location_precision": "precise",
        "title": "Imagery location of Roman walls of Lugo",
        "link": "http://pleiades.stoa.org/places/49788037/roman-walls-of-lugo"
      }
    }
  ]
}