{
  "type": "FeatureCollection",
  "title": "Amaravati",
  "id": "49855",
  "bbox": [
    80.1347,
    16.385871,
    80.1347,
    16.385871
  ],
  "description": "An ancient place, cited: BAtlas 5 E3 Amaravati",
  "features": [
    {
      "type": "Feature",
      "geometry": {
        "type": "Point",
        "coordinates": [
          80.1347,
          16.385871
        ]
      },
      "properties": {
        "description": "representative point"
      }
    },
    {
      "geometry": {
        "type": "Point",
        "coordinates": [
          80.1347,
          16.385871
        ]
      },
      "id": "darmc-location-11341",
      "type": "Feature",
      "properties": {
        "description": "5M scale point location",
        "location_precision": "precise",
        "title": "DARMC location 11341",
        "link": "http://pleiades.stoa.org/places/49855/darmc-location-11341"
      }
    }
  ]
}