{
  "type": "FeatureCollection",
  "title": "Brahmagiri",
  "id": "49926",
  "description": "An ancient place, cited: BAtlas 5 D4 Brahmagiri",
  "bbox": [
    76.772076,
    14.660387,
    76.772076,
    14.660387
  ],
  "reprPoint": [
    76.772076,
    14.660387
  ],
  "features": [
    {
      "geometry": {
        "type": "Point",
        "coordinates": [
          76.772076,
          14.660387
        ]
      },
      "id": "darmc-location-11826",
      "type": "Feature",
      "properties": {
        "description": "5M scale point location",
        "location_precision": "precise",
        "title": "DARMC location 11826",
        "link": "http://pleiades.stoa.org/places/49926/darmc-location-11826"
      }
    }
  ]
}