{
  "type": "FeatureCollection",
  "title": "Cabirus fl.",
  "id": "49931",
  "description": "An ancient place, cited: BAtlas 5 D4 Cabirus fl.",
  "bbox": [
    77.169004,
    12.2946099,
    77.169004,
    12.2946099
  ],
  "reprPoint": [
    77.169004,
    12.2946099
  ],
  "names": [
    "Cabirus",
    "Chaberos"
  ],
  "features": [
    {
      "geometry": {
        "type": "Point",
        "coordinates": [
          77.169004,
          12.2946099
        ]
      },
      "id": "location-of-Cabirus-fl",
      "type": "Feature",
      "properties": {
        "description": "Location based on OpenStreetMap",
        "location_precision": "precise",
        "title": "location of Cabirus fl.",
        "link": "http://pleiades.stoa.org/places/49931/location-of-Cabirus-fl"
      }
    }
  ]
}