{
  "type": "FeatureCollection",
  "title": "Dhatva",
  "id": "49963",
  "description": "An ancient place, cited: BAtlas 5 C2 Dhatva",
  "bbox": [
    73.034315,
    21.28653,
    73.034315,
    21.28653
  ],
  "reprPoint": [
    73.034315,
    21.28653
  ],
  "features": [
    {
      "geometry": {
        "type": "Point",
        "coordinates": [
          73.034315,
          21.28653
        ]
      },
      "id": "darmc-location-20215",
      "type": "Feature",
      "properties": {
        "description": "5M scale point location",
        "location_precision": "precise",
        "title": "DARMC location 20215",
        "link": "http://pleiades.stoa.org/places/49963/darmc-location-20215"
      }
    }
  ]
}