{
  "type": "FeatureCollection",
  "title": "Elankoros",
  "id": "49972",
  "bbox": [
    77.265021,
    8.19228,
    77.265021,
    8.19228
  ],
  "description": "An ancient place, cited: BAtlas 5 D5 Elankoros",
  "names": [
    "Elankoros",
    "Alcon"
  ],
  "features": [
    {
      "type": "Feature",
      "geometry": {
        "type": "Point",
        "coordinates": [
          77.265021,
          8.19228
        ]
      },
      "properties": {
        "description": "representative point"
      }
    },
    {
      "geometry": {
        "type": "Point",
        "coordinates": [
          77.265021,
          8.19228
        ]
      },
      "id": "darmc-location-12317",
      "type": "Feature",
      "properties": {
        "description": "5M scale point location",
        "location_precision": "precise",
        "title": "DARMC location 12317",
        "link": "http://pleiades.stoa.org/places/49972/darmc-location-12317"
      }
    }
  ]
}