{
  "type": "FeatureCollection",
  "title": "Lower Agora",
  "id": "499750546",
  "bbox": [
    13.5858994,
    37.2918294,
    13.5858994,
    37.2918294
  ],
  "description": "The lower agora of the ancient city of Agrigentum contains shops, a sacred area, and the gymnasium complex.",
  "connectsWith": [
    "462086"
  ],
  "features": [
    {
      "type": "Feature",
      "geometry": {
        "type": "Point",
        "coordinates": [
          13.5858994,
          37.2918294
        ]
      },
      "properties": {
        "description": "representative point"
      }
    },
    {
      "geometry": {
        "type": "Point",
        "coordinates": [
          13.5858994,
          37.2918294
        ]
      },
      "id": "location-of-lower-agora",
      "type": "Feature",
      "properties": {
        "description": "coordinates after OSM; location verified in Google Earth.",
        "location_precision": "precise",
        "title": "OSM location of Agora Inferiore",
        "link": "http://pleiades.stoa.org/places/499750546/location-of-lower-agora"
      }
    }
  ]
}