{
  "type": "FeatureCollection",
  "title": "Gintota",
  "id": "49988",
  "description": "An ancient place, cited: BAtlas 5 inset Gintota",
  "bbox": [
    80.180261,
    6.057983,
    80.180261,
    6.057983
  ],
  "reprPoint": [
    80.180261,
    6.057983
  ],
  "features": [
    {
      "geometry": {
        "type": "Point",
        "coordinates": [
          80.180261,
          6.057983
        ]
      },
      "id": "darmc-location-30286",
      "type": "Feature",
      "properties": {
        "description": "5M scale point location",
        "location_precision": "precise",
        "title": "DARMC location 30286",
        "link": "http://pleiades.stoa.org/places/49988/darmc-location-30286"
      }
    }
  ]
}