{
  "type": "FeatureCollection",
  "title": "Agora of Onchestos",
  "id": "499970655",
  "bbox": [
    23.138532,
    38.366312,
    23.138532,
    38.366312
  ],
  "description": "Approximate center point of agora of Onchestos sanctuary visible in satellite imagery.",
  "connectsWith": [
    "540984"
  ],
  "features": [
    {
      "type": "Feature",
      "geometry": {
        "type": "Point",
        "coordinates": [
          23.138532,
          38.366312
        ]
      },
      "properties": {
        "description": "representative point"
      }
    },
    {
      "geometry": {
        "type": "Point",
        "coordinates": [
          23.138532,
          38.366312
        ]
      },
      "id": "bouleuterion",
      "type": "Feature",
      "properties": {
        "description": "Approximate center point of agora of Onchestos sanctuary visible in satellite imagery.",
        "location_precision": "precise",
        "title": "Agora",
        "link": "http://pleiades.stoa.org/places/499970655/bouleuterion"
      }
    }
  ]
}