{
  "type": "FeatureCollection",
  "title": "Kaliyamputhur",
  "id": "50021",
  "description": "An ancient place, cited: BAtlas 5 D4 Kaliyamputhur",
  "bbox": [
    77.45179,
    10.323111,
    77.45179,
    10.323111
  ],
  "reprPoint": [
    77.45179,
    10.323111
  ],
  "features": [
    {
      "geometry": {
        "type": "Point",
        "coordinates": [
          77.45179,
          10.323111
        ]
      },
      "id": "darmc-location-12961",
      "type": "Feature",
      "properties": {
        "description": "5M scale point location",
        "location_precision": "precise",
        "title": "DARMC location 12961",
        "link": "http://pleiades.stoa.org/places/50021/darmc-location-12961"
      }
    }
  ]
}