{
  "type": "FeatureCollection",
  "title": "Kalligeris",
  "id": "50025",
  "bbox": [
    76.152406,
    13.495276,
    76.152406,
    13.495276
  ],
  "description": "An ancient place, cited: BAtlas 5 D4 Kalligeris",
  "names": [
    "Kalligeris"
  ],
  "features": [
    {
      "type": "Feature",
      "geometry": {
        "type": "Point",
        "coordinates": [
          76.152406,
          13.495276
        ]
      },
      "properties": {
        "description": "representative point"
      }
    },
    {
      "geometry": {
        "type": "Point",
        "coordinates": [
          76.152406,
          13.495276
        ]
      },
      "id": "darmc-location-12964",
      "type": "Feature",
      "properties": {
        "description": "5M scale point location",
        "location_precision": "precise",
        "title": "DARMC location 12964",
        "link": "http://pleiades.stoa.org/places/50025/darmc-location-12964"
      }
    }
  ]
}