{
  "type": "FeatureCollection",
  "title": "Kalpitiya",
  "id": "50028",
  "bbox": [
    79.759874,
    8.234006,
    79.759874,
    8.234006
  ],
  "description": "An ancient place, cited: BAtlas 5 inset Kalpitiya",
  "features": [
    {
      "type": "Feature",
      "geometry": {
        "type": "Point",
        "coordinates": [
          79.759874,
          8.234006
        ]
      },
      "properties": {
        "description": "representative point"
      }
    },
    {
      "geometry": {
        "type": "Point",
        "coordinates": [
          79.759874,
          8.234006
        ]
      },
      "id": "darmc-location-30364",
      "type": "Feature",
      "properties": {
        "description": "5M scale point location",
        "location_precision": "precise",
        "title": "DARMC location 30364",
        "link": "http://pleiades.stoa.org/places/50028/darmc-location-30364"
      }
    }
  ]
}