{
  "type": "FeatureCollection",
  "title": "Kammoni",
  "id": "50032",
  "bbox": [
    72.925301,
    21.402921,
    72.925301,
    21.402921
  ],
  "description": "An ancient place, cited: BAtlas 5 C2 Kammoni",
  "names": [
    "Kammoni",
    "Kamani"
  ],
  "features": [
    {
      "type": "Feature",
      "geometry": {
        "type": "Point",
        "coordinates": [
          72.925301,
          21.402921
        ]
      },
      "properties": {
        "description": "representative point"
      }
    },
    {
      "geometry": {
        "type": "Point",
        "coordinates": [
          72.925301,
          21.402921
        ]
      },
      "id": "darmc-location-20367",
      "type": "Feature",
      "properties": {
        "description": "5M scale point location",
        "location_precision": "precise",
        "title": "DARMC location 20367",
        "link": "http://pleiades.stoa.org/places/50032/darmc-location-20367"
      }
    }
  ]
}