{
  "type": "FeatureCollection",
  "title": "Kantakossyla",
  "id": "50038",
  "bbox": [
    80.260333,
    16.150994,
    80.260333,
    16.150994
  ],
  "description": "An ancient place, cited: BAtlas 5 E3 Kantakossyla",
  "names": [
    "Kantakossyla"
  ],
  "features": [
    {
      "type": "Feature",
      "geometry": {
        "type": "Point",
        "coordinates": [
          80.260333,
          16.150994
        ]
      },
      "properties": {
        "description": "representative point"
      }
    },
    {
      "geometry": {
        "type": "Point",
        "coordinates": [
          80.260333,
          16.150994
        ]
      },
      "id": "darmc-location-20369",
      "type": "Feature",
      "properties": {
        "description": "5M scale point location",
        "location_precision": "precise",
        "title": "DARMC location 20369",
        "link": "http://pleiades.stoa.org/places/50038/darmc-location-20369"
      }
    }
  ]
}