{
  "type": "FeatureCollection",
  "title": "Kapuhenvala",
  "id": "50040",
  "bbox": [
    80.273603,
    8.022877,
    80.273603,
    8.022877
  ],
  "description": "An ancient place, cited: BAtlas 5 inset Kapuhenvala",
  "features": [
    {
      "type": "Feature",
      "geometry": {
        "type": "Point",
        "coordinates": [
          80.273603,
          8.022877
        ]
      },
      "properties": {
        "description": "representative point"
      }
    },
    {
      "geometry": {
        "type": "Point",
        "coordinates": [
          80.273603,
          8.022877
        ]
      },
      "id": "darmc-location-23000",
      "type": "Feature",
      "properties": {
        "description": "5M scale point location",
        "location_precision": "precise",
        "title": "DARMC location 23000",
        "link": "http://pleiades.stoa.org/places/50040/darmc-location-23000"
      }
    }
  ]
}