{
  "type": "FeatureCollection",
  "title": "Karur",
  "id": "50048",
  "description": "An ancient place, cited: BAtlas 5 D4 Karur",
  "bbox": [
    78.079902,
    10.951893,
    78.079902,
    10.951893
  ],
  "reprPoint": [
    78.079902,
    10.951893
  ],
  "features": [
    {
      "geometry": {
        "type": "Point",
        "coordinates": [
          78.079902,
          10.951893
        ]
      },
      "id": "darmc-location-20379",
      "type": "Feature",
      "properties": {
        "description": "5M scale point location",
        "location_precision": "precise",
        "title": "DARMC location 20379",
        "link": "http://pleiades.stoa.org/places/50048/darmc-location-20379"
      }
    }
  ]
}