{
  "type": "FeatureCollection",
  "title": "Katriyal",
  "id": "50052",
  "description": "An ancient place, cited: BAtlas 5 D3 Katriyal",
  "bbox": [
    75.78982,
    16.64652,
    75.78982,
    16.64652
  ],
  "reprPoint": [
    75.78982,
    16.64652
  ],
  "features": [
    {
      "geometry": {
        "type": "Point",
        "coordinates": [
          75.78982,
          16.64652
        ]
      },
      "id": "darmc-location-13068",
      "type": "Feature",
      "properties": {
        "description": "5M scale point location",
        "location_precision": "precise",
        "title": "DARMC location 13068",
        "link": "http://pleiades.stoa.org/places/50052/darmc-location-13068"
      }
    }
  ]
}