{
  "type": "FeatureCollection",
  "title": "Kouroula",
  "id": "50084",
  "description": "An ancient place, cited: BAtlas 5 D4 Kouroula",
  "bbox": [
    79.837316,
    10.926422,
    79.837316,
    10.926422
  ],
  "reprPoint": [
    79.837316,
    10.926422
  ],
  "names": [
    "Kouroula"
  ],
  "features": [
    {
      "geometry": {
        "type": "Point",
        "coordinates": [
          79.837316,
          10.926422
        ]
      },
      "id": "darmc-location-19801",
      "type": "Feature",
      "properties": {
        "description": "5M scale point location",
        "location_precision": "precise",
        "title": "DARMC location 19801",
        "link": "http://pleiades.stoa.org/places/50084/darmc-location-19801"
      }
    }
  ]
}