{
  "type": "FeatureCollection",
  "title": "Mandas fl.",
  "id": "50117",
  "description": "An ancient place, cited: BAtlas 5 E3 Mandas fl.",
  "bbox": [
    77.0254367,
    19.1078948,
    77.0254367,
    19.1078948
  ],
  "reprPoint": [
    77.0254367,
    19.1078948
  ],
  "names": [
    "Mandas",
    "Paleris"
  ],
  "features": [
    {
      "geometry": {
        "type": "Point",
        "coordinates": [
          77.0254367,
          19.1078948
        ]
      },
      "id": "location-of-Mandas-fl",
      "type": "Feature",
      "properties": {
        "description": "Location based on OpenStreetMap",
        "location_precision": "precise",
        "title": "location of Mandas fl.",
        "link": "http://pleiades.stoa.org/places/50117/location-of-Mandas-fl"
      }
    }
  ]
}