{
  "type": "FeatureCollection",
  "title": "Colla",
  "id": "501388",
  "description": "An ancient place, cited: BAtlas 51 G3 Colla",
  "bbox": [
    26.42059,
    40.797133,
    26.42059,
    40.797133
  ],
  "reprPoint": [
    26.42059,
    40.797133
  ],
  "names": [
    "Colla"
  ],
  "features": [
    {
      "geometry": {
        "type": "Point",
        "coordinates": [
          26.42059,
          40.797133
        ]
      },
      "id": "darmc-location-9653",
      "type": "Feature",
      "properties": {
        "description": "500K scale point location",
        "location_precision": "precise",
        "title": "DARMC location 9653",
        "link": "http://pleiades.stoa.org/places/501388/darmc-location-9653"
      }
    }
  ]
}