{
  "type": "FeatureCollection",
  "title": "Akanthos",
  "id": "501339",
  "description": "An ancient place, cited: BAtlas 51 B4 Akanthos",
  "bbox": [
    23.880112,
    40.39975,
    23.880112,
    40.39975
  ],
  "reprPoint": [
    23.880112,
    40.39975
  ],
  "names": [
    "Akanthos"
  ],
  "features": [
    {
      "geometry": {
        "type": "Point",
        "coordinates": [
          23.880112,
          40.39975
        ]
      },
      "id": "darmc-location-11267",
      "type": "Feature",
      "properties": {
        "description": "500K scale point location",
        "location_precision": "precise",
        "title": "DARMC location 11267",
        "link": "http://pleiades.stoa.org/places/501339/darmc-location-11267"
      }
    }
  ]
}