{
  "type": "FeatureCollection",
  "title": "Modoura",
  "id": "50138",
  "description": "An ancient place, cited: BAtlas 5 D5 Modoura",
  "bbox": [
    78.122503,
    9.90839,
    78.122503,
    9.90839
  ],
  "reprPoint": [
    78.122503,
    9.90839
  ],
  "names": [
    "Modoura"
  ],
  "features": [
    {
      "geometry": {
        "type": "Point",
        "coordinates": [
          78.122503,
          9.90839
        ]
      },
      "id": "darmc-location-20493",
      "type": "Feature",
      "properties": {
        "description": "5M scale point location",
        "location_precision": "precise",
        "title": "DARMC location 20493",
        "link": "http://pleiades.stoa.org/places/50138/darmc-location-20493"
      }
    }
  ]
}