{
  "type": "FeatureCollection",
  "title": "Akanthos",
  "id": "501339",
  "bbox": [
    23.880112,
    40.39975,
    23.880112,
    40.39975
  ],
  "description": "An ancient place, cited: BAtlas 51 B4 Akanthos",
  "names": [
    "Akanthos"
  ],
  "features": [
    {
      "type": "Feature",
      "geometry": {
        "type": "Point",
        "coordinates": [
          23.880112,
          40.39975
        ]
      },
      "properties": {
        "description": "representative point"
      }
    },
    {
      "geometry": {
        "type": "Point",
        "coordinates": [
          23.880112,
          40.39975
        ]
      },
      "id": "darmc-location-11267",
      "type": "Feature",
      "properties": {
        "description": "1:500,000 scale representative point location digitized from the Barrington Atlas of the Greek and Roman World by the Digital Atlas of Roman and Medieval Civilizations project at Harvard University.",
        "location_precision": "precise",
        "title": "DARMC location 11267",
        "link": "http://pleiades.stoa.org/places/501339/darmc-location-11267"
      }
    }
  ]
}