{
  "type": "FeatureCollection",
  "title": "Akanthos",
  "id": "501339",
  "bbox": [
    23.8853681,
    40.392,
    23.888,
    40.3947152
  ],
  "description": "An ancient settlement in the northeast of the Chalkidiki. The large site is immediately southeast of the modern town of Ierissos.",
  "names": [
    "Ierissos",
    "Akanthos"
  ],
  "features": [
    {
      "type": "Feature",
      "geometry": {
        "type": "Point",
        "coordinates": [
          23.88668405,
          40.3933576
        ]
      },
      "properties": {
        "description": "representative point"
      }
    },
    {
      "geometry": {
        "type": "Point",
        "coordinates": [
          23.8853681,
          40.3947152
        ]
      },
      "id": "osm-location-akanthos",
      "type": "Feature",
      "properties": {
        "description": "Location based on OpenStreetMap. Dates after BAtlas.",
        "location_precision": "precise",
        "title": "OSM Location: Akanthos",
        "link": "http://pleiades.stoa.org/places/501339/osm-location-akanthos"
      }
    },
    {
      "geometry": {
        "type": "Point",
        "coordinates": [
          23.888,
          40.392
        ]
      },
      "id": "topostext-location",
      "type": "Feature",
      "properties": {
        "description": "Dates after BAtlas.",
        "location_precision": "precise",
        "title": "ToposText Location",
        "link": "http://pleiades.stoa.org/places/501339/topostext-location"
      }
    }
  ]
}