{
  "type": "FeatureCollection",
  "title": "Ablanica Rodopi",
  "id": "501324",
  "description": "An ancient place, cited: BAtlas 51 B1 Ablanica Rodopi",
  "bbox": [
    23.778157,
    41.575231,
    23.778157,
    41.575231
  ],
  "reprPoint": [
    23.778157,
    41.575231
  ],
  "features": [
    {
      "geometry": {
        "type": "Point",
        "coordinates": [
          23.778157,
          41.575231
        ]
      },
      "id": "darmc-location-11146",
      "type": "Feature",
      "properties": {
        "description": "500K scale point location",
        "location_precision": "precise",
        "title": "DARMC location 11146",
        "link": "http://pleiades.stoa.org/places/501324/darmc-location-11146"
      }
    }
  ]
}