{
  "type": "FeatureCollection",
  "title": "Bourdepa",
  "id": "501381",
  "bbox": [
    26.212932,
    41.774648,
    26.212932,
    41.774648
  ],
  "description": "An ancient place, cited: BAtlas 51 G1 Bourdepa",
  "names": [
    "Bourdepa"
  ],
  "features": [
    {
      "type": "Feature",
      "geometry": {
        "type": "Point",
        "coordinates": [
          26.212932,
          41.774648
        ]
      },
      "properties": {
        "description": "representative point"
      }
    },
    {
      "geometry": {
        "type": "Point",
        "coordinates": [
          26.212932,
          41.774648
        ]
      },
      "id": "darmc-location-11818",
      "type": "Feature",
      "properties": {
        "description": "500K scale point location",
        "location_precision": "precise",
        "title": "DARMC location 11818",
        "link": "http://pleiades.stoa.org/places/501381/darmc-location-11818"
      }
    }
  ]
}