{
  "type": "FeatureCollection",
  "title": "Kophos",
  "id": "501476",
  "description": "An ancient place, cited: BAtlas 51 B5 Kophos",
  "bbox": [
    23.674509,
    39.955078,
    23.928384,
    39.9714854
  ],
  "reprPoint": [
    23.8401954667,
    39.9658094667
  ],
  "names": [
    "Kophos"
  ],
  "features": [
    {
      "geometry": {
        "type": "Point",
        "coordinates": [
          23.674509,
          39.955078
        ]
      },
      "id": "darmc-location-3021",
      "type": "Feature",
      "properties": {
        "description": "500K scale point location",
        "location_precision": "precise",
        "title": "DARMC location 3021",
        "link": "http://pleiades.stoa.org/places/501476/darmc-location-3021"
      }
    },
    {
      "geometry": {
        "type": "Point",
        "coordinates": [
          23.928384,
          39.970865
        ]
      },
      "id": "darmc-location-3022",
      "type": "Feature",
      "properties": {
        "description": "500K scale point location",
        "location_precision": "precise",
        "title": "DARMC location 3022",
        "link": "http://pleiades.stoa.org/places/501476/darmc-location-3022"
      }
    },
    {
      "geometry": {
        "type": "Point",
        "coordinates": [
          23.917693399999962,
          39.9714854
        ]
      },
      "id": "dare-location",
      "type": "Feature",
      "properties": {
        "description": "Representative point location, village precision",
        "location_precision": "precise",
        "title": "DARE Location",
        "link": "http://pleiades.stoa.org/places/501476/dare-location"
      }
    }
  ]
}