{
  "type": "FeatureCollection",
  "title": "Kolonai",
  "id": "501474",
  "bbox": [
    26.91075,
    40.280834,
    26.91075,
    40.280834
  ],
  "description": "An ancient place, cited: BAtlas 51 H4 Kolonai",
  "names": [
    "Kolonai"
  ],
  "features": [
    {
      "type": "Feature",
      "geometry": {
        "type": "Point",
        "coordinates": [
          26.91075,
          40.280834
        ]
      },
      "properties": {
        "description": "representative point"
      }
    },
    {
      "geometry": {
        "type": "Point",
        "coordinates": [
          26.91075,
          40.280834
        ]
      },
      "id": "darmc-location-3020",
      "type": "Feature",
      "properties": {
        "description": "500K scale point location",
        "location_precision": "precise",
        "title": "DARMC location 3020",
        "link": "http://pleiades.stoa.org/places/501474/darmc-location-3020"
      }
    }
  ]
}