{
  "type": "FeatureCollection",
  "title": "Kophos",
  "id": "501476",
  "description": "An ancient place, cited: BAtlas 51 B5 Kophos",
  "bbox": [
    23.9176934,
    39.9714854,
    23.9176934,
    39.9714854
  ],
  "reprPoint": [
    23.9176934,
    39.9714854
  ],
  "names": [
    "Kophos"
  ],
  "features": [
    {
      "geometry": {
        "type": "Point",
        "coordinates": [
          23.917693399999962,
          39.9714854
        ]
      },
      "id": "dare-location",
      "type": "Feature",
      "properties": {
        "description": "Representative point location, village precision",
        "location_precision": "precise",
        "title": "DARE Location",
        "link": "http://pleiades.stoa.org/places/501476/dare-location"
      }
    }
  ]
}