{
  "type": "FeatureCollection",
  "title": "Gazoros",
  "id": "501423",
  "bbox": [
    23.765874,
    41.016942,
    23.765874,
    41.016942
  ],
  "description": "An ancient place, cited: BAtlas 51 B2 Gazoros",
  "names": [
    "Gazoros"
  ],
  "features": [
    {
      "type": "Feature",
      "geometry": {
        "type": "Point",
        "coordinates": [
          23.765874,
          41.016942
        ]
      },
      "properties": {
        "description": "representative point"
      }
    },
    {
      "geometry": {
        "type": "Point",
        "coordinates": [
          23.765874,
          41.016942
        ]
      },
      "id": "darmc-location-24022",
      "type": "Feature",
      "properties": {
        "description": "1:1 million scale representative point location digitized from the Barrington Atlas of the Greek and Roman World by the Digital Atlas of Roman and Medieval Civilizations project at Harvard University.",
        "location_precision": "precise",
        "title": "DARMC location 24022",
        "link": "http://pleiades.stoa.org/places/501423/darmc-location-24022"
      }
    }
  ]
}