{
  "type": "FeatureCollection",
  "title": "Gazoros",
  "id": "501423",
  "bbox": [
    23.7925,
    41.0392,
    23.7925,
    41.0392
  ],
  "description": "An ancient Macedonian settlement, located near the modern town that bears its name. A likely acropolis has been identified at the church of Hagios Athanasios, northeast of the modern town.",
  "names": [
    "Gazoros"
  ],
  "features": [
    {
      "type": "Feature",
      "geometry": {
        "type": "Point",
        "coordinates": [
          23.7925,
          41.0392
        ]
      },
      "properties": {
        "description": "representative point"
      }
    },
    {
      "geometry": {
        "type": "Point",
        "coordinates": [
          23.7925,
          41.0392
        ]
      },
      "id": "topostext-location",
      "type": "Feature",
      "properties": {
        "description": "Dates after BAtlas",
        "location_precision": "precise",
        "title": "ToposText Location",
        "link": "http://pleiades.stoa.org/places/501423/topostext-location"
      }
    }
  ]
}