{
  "type": "FeatureCollection",
  "title": "Hadrianoupolis",
  "id": "501428",
  "description": "An ancient place, cited: BAtlas 51 H1 Hadrianoupolis",
  "reprPoint": [
    24.257643,
    41.140485
  ],
  "names": [
    "Edirne",
    "Edirne",
    "Hadrianoupolis",
    "Adrianopel",
    "Adrianoupolis",
    "Hadrianoupolis",
    "Uscudama"
  ],
  "features": [
    {
      "geometry": {
        "type": "Point",
        "coordinates": [
          26.57514,
          41.677883
        ]
      },
      "id": "darmc-location-3531",
      "type": "Feature",
      "properties": {
        "description": "500K scale point location",
        "location_precision": "precise",
        "title": "DARMC location 3531",
        "link": "http://pleiades.stoa.org/places/501428/darmc-location-3531"
      }
    },
    {
      "geometry": {
        "type": "Point",
        "coordinates": [
          26.550642,
          41.675035
        ]
      },
      "id": "dare-location",
      "type": "Feature",
      "properties": {
        "description": "Representative point location, village precision",
        "location_precision": "precise",
        "title": "DARE Location",
        "link": "http://pleiades.stoa.org/places/501428/dare-location"
      }
    }
  ]
}