{
  "type": "FeatureCollection",
  "title": "Kalirachi",
  "id": "501449",
  "description": "An ancient place, cited: BAtlas 51 D3 Kalirachi",
  "bbox": [
    24.571001,
    40.701267,
    24.571001,
    40.701267
  ],
  "reprPoint": [
    24.571001,
    40.701267
  ],
  "features": [
    {
      "geometry": {
        "type": "Point",
        "coordinates": [
          24.571001,
          40.701267
        ]
      },
      "id": "darmc-location-9560",
      "type": "Feature",
      "properties": {
        "description": "500K scale point location",
        "location_precision": "precise",
        "title": "DARMC location 9560",
        "link": "http://pleiades.stoa.org/places/501449/darmc-location-9560"
      }
    }
  ]
}