{
  "type": "FeatureCollection",
  "title": "Khoristi",
  "id": "501467",
  "bbox": [
    24.209453,
    41.138829,
    24.209453,
    41.138829
  ],
  "description": "An ancient place, cited: BAtlas 51 C2 Khoristi",
  "features": [
    {
      "type": "Feature",
      "geometry": {
        "type": "Point",
        "coordinates": [
          24.209453,
          41.138829
        ]
      },
      "properties": {
        "description": "representative point"
      }
    },
    {
      "geometry": {
        "type": "Point",
        "coordinates": [
          24.209453,
          41.138829
        ]
      },
      "id": "darmc-location-13175",
      "type": "Feature",
      "properties": {
        "description": "500K scale point location",
        "location_precision": "precise",
        "title": "DARMC location 13175",
        "link": "http://pleiades.stoa.org/places/501467/darmc-location-13175"
      }
    }
  ]
}