{
  "type": "FeatureCollection",
  "title": "Gospodinci",
  "id": "501424",
  "bbox": [
    23.725966,
    41.650776,
    23.725966,
    41.650776
  ],
  "description": "An ancient place, cited: BAtlas 51 B1 Gospodinci",
  "features": [
    {
      "type": "Feature",
      "geometry": {
        "type": "Point",
        "coordinates": [
          23.725966,
          41.650776
        ]
      },
      "properties": {
        "description": "representative point"
      }
    },
    {
      "geometry": {
        "type": "Point",
        "coordinates": [
          23.725966,
          41.650776
        ]
      },
      "id": "darmc-location-12592",
      "type": "Feature",
      "properties": {
        "description": "500K scale point location",
        "location_precision": "precise",
        "title": "DARMC location 12592",
        "link": "http://pleiades.stoa.org/places/501424/darmc-location-12592"
      }
    }
  ]
}