{
  "type": "FeatureCollection",
  "title": "Koutson",
  "id": "501486",
  "description": "An ancient place, cited: BAtlas 51 D2 Koutson",
  "bbox": [
    24.995798,
    41.058328,
    24.995798,
    41.058328
  ],
  "reprPoint": [
    24.995798,
    41.058328
  ],
  "features": [
    {
      "geometry": {
        "type": "Point",
        "coordinates": [
          24.995798,
          41.058328
        ]
      },
      "id": "darmc-location-13295",
      "type": "Feature",
      "properties": {
        "description": "500K scale point location",
        "location_precision": "precise",
        "title": "DARMC location 13295",
        "link": "http://pleiades.stoa.org/places/501486/darmc-location-13295"
      }
    }
  ]
}