{
  "type": "FeatureCollection",
  "title": "Harmanli",
  "id": "501429",
  "bbox": [
    25.902487,
    41.93033,
    25.902487,
    41.93033
  ],
  "description": "An ancient place, cited: BAtlas 51 F1 Harmanli",
  "features": [
    {
      "type": "Feature",
      "geometry": {
        "type": "Point",
        "coordinates": [
          25.902487,
          41.93033
        ]
      },
      "properties": {
        "description": "representative point"
      }
    },
    {
      "geometry": {
        "type": "Point",
        "coordinates": [
          25.902487,
          41.93033
        ]
      },
      "id": "darmc-location-24050",
      "type": "Feature",
      "properties": {
        "description": "1M scale point location",
        "location_precision": "precise",
        "title": "DARMC location 24050",
        "link": "http://pleiades.stoa.org/places/501429/darmc-location-24050"
      }
    }
  ]
}