{
  "type": "FeatureCollection",
  "title": "Komotene",
  "id": "501475",
  "bbox": [
    25.445868,
    41.11702,
    25.445868,
    41.11702
  ],
  "description": "An ancient place, cited: BAtlas 51 E2 Komotene",
  "features": [
    {
      "type": "Feature",
      "geometry": {
        "type": "Point",
        "coordinates": [
          25.445868,
          41.11702
        ]
      },
      "properties": {
        "description": "representative point"
      }
    },
    {
      "geometry": {
        "type": "Point",
        "coordinates": [
          25.445868,
          41.11702
        ]
      },
      "id": "darmc-location-13248",
      "type": "Feature",
      "properties": {
        "description": "500K scale point location",
        "location_precision": "precise",
        "title": "DARMC location 13248",
        "link": "http://pleiades.stoa.org/places/501475/darmc-location-13248"
      }
    }
  ]
}