{
  "type": "FeatureCollection",
  "title": "Karamanci",
  "id": "501457",
  "bbox": [
    25.363169,
    41.746662,
    25.363169,
    41.746662
  ],
  "description": "An ancient place, cited: BAtlas 51 E1 Karamanci",
  "features": [
    {
      "type": "Feature",
      "geometry": {
        "type": "Point",
        "coordinates": [
          25.363169,
          41.746662
        ]
      },
      "properties": {
        "description": "representative point"
      }
    },
    {
      "geometry": {
        "type": "Point",
        "coordinates": [
          25.363169,
          41.746662
        ]
      },
      "id": "darmc-location-13008",
      "type": "Feature",
      "properties": {
        "description": "500K scale point location",
        "location_precision": "precise",
        "title": "DARMC location 13008",
        "link": "http://pleiades.stoa.org/places/501457/darmc-location-13008"
      }
    }
  ]
}