{
  "type": "FeatureCollection",
  "title": "Gazoros",
  "id": "501423",
  "description": "An ancient place, cited: BAtlas 51 B2 Gazoros",
  "bbox": [
    23.765874,
    41.016942,
    23.765874,
    41.016942
  ],
  "reprPoint": [
    23.765874,
    41.016942
  ],
  "names": [
    "Gazoros"
  ],
  "features": [
    {
      "geometry": {
        "type": "Point",
        "coordinates": [
          23.765874,
          41.016942
        ]
      },
      "id": "darmc-location-24022",
      "type": "Feature",
      "properties": {
        "description": "1M scale point location",
        "location_precision": "precise",
        "title": "DARMC location 24022",
        "link": "http://pleiades.stoa.org/places/501423/darmc-location-24022"
      }
    }
  ]
}