{
  "type": "FeatureCollection",
  "title": "Philia",
  "id": "501562",
  "description": "An ancient place, cited: BAtlas 51 E2 Philia",
  "bbox": [
    24.997806,
    41.136977,
    24.997806,
    41.136977
  ],
  "reprPoint": [
    24.997806,
    41.136977
  ],
  "features": [
    {
      "geometry": {
        "type": "Point",
        "coordinates": [
          24.997806,
          41.136977
        ]
      },
      "id": "darmc-location-2562",
      "type": "Feature",
      "properties": {
        "description": "500K scale point location",
        "location_precision": "precise",
        "title": "DARMC location 2562",
        "link": "http://pleiades.stoa.org/places/501562/darmc-location-2562"
      }
    }
  ]
}