{
  "type": "FeatureCollection",
  "title": "Podokhori",
  "id": "501573",
  "bbox": [
    24.011123,
    40.84313,
    24.011123,
    40.84313
  ],
  "description": "An ancient place, cited: BAtlas 51 C3 Podokhori",
  "features": [
    {
      "type": "Feature",
      "geometry": {
        "type": "Point",
        "coordinates": [
          24.011123,
          40.84313
        ]
      },
      "properties": {
        "description": "representative point"
      }
    },
    {
      "geometry": {
        "type": "Point",
        "coordinates": [
          24.011123,
          40.84313
        ]
      },
      "id": "darmc-location-14338",
      "type": "Feature",
      "properties": {
        "description": "500K scale point location",
        "location_precision": "precise",
        "title": "DARMC location 14338",
        "link": "http://pleiades.stoa.org/places/501573/darmc-location-14338"
      }
    }
  ]
}