{
  "type": "FeatureCollection",
  "title": "Rhodolivos",
  "id": "501591",
  "description": "An ancient place, cited: BAtlas 51 B3 Rhodolivos",
  "bbox": [
    23.915297,
    40.968167,
    23.915297,
    40.968167
  ],
  "reprPoint": [
    23.915297,
    40.968167
  ],
  "features": [
    {
      "geometry": {
        "type": "Point",
        "coordinates": [
          23.915297,
          40.968167
        ]
      },
      "id": "darmc-location-14503",
      "type": "Feature",
      "properties": {
        "description": "500K scale point location",
        "location_precision": "precise",
        "title": "DARMC location 14503",
        "link": "http://pleiades.stoa.org/places/501591/darmc-location-14503"
      }
    }
  ]
}