{
  "type": "FeatureCollection",
  "title": "Oraion",
  "id": "501538",
  "description": "An ancient place, cited: BAtlas 51 D2 Oraion",
  "bbox": [
    24.83293,
    41.276691,
    24.83293,
    41.276691
  ],
  "reprPoint": [
    24.83293,
    41.276691
  ],
  "features": [
    {
      "geometry": {
        "type": "Point",
        "coordinates": [
          24.83293,
          41.276691
        ]
      },
      "id": "darmc-location-14028",
      "type": "Feature",
      "properties": {
        "description": "500K scale point location",
        "location_precision": "precise",
        "title": "DARMC location 14028",
        "link": "http://pleiades.stoa.org/places/501538/darmc-location-14028"
      }
    }
  ]
}