{
  "type": "FeatureCollection",
  "title": "Nagadiba",
  "id": "50150",
  "description": "An ancient place, cited: BAtlas 5 inset Nagadiba",
  "bbox": [
    81.205297,
    8.585704,
    81.205297,
    8.585704
  ],
  "reprPoint": [
    81.205297,
    8.585704
  ],
  "names": [
    "Nagadiba",
    "Nagadiba Nesos",
    "Nagadiboi"
  ],
  "features": [
    {
      "geometry": {
        "type": "Point",
        "coordinates": [
          81.205297,
          8.585704
        ]
      },
      "id": "darmc-location-29823",
      "type": "Feature",
      "properties": {
        "description": "5M scale point location",
        "location_precision": "precise",
        "title": "DARMC location 29823",
        "link": "http://pleiades.stoa.org/places/50150/darmc-location-29823"
      }
    }
  ]
}