{
  "type": "FeatureCollection",
  "title": "Olophyxos",
  "id": "501535",
  "bbox": [
    24.190639,
    40.330422,
    24.190639,
    40.330422
  ],
  "description": "An ancient settlement on the Athos/Akte peninsula.",
  "connectsWith": [
    "501365"
  ],
  "names": [
    "Olophyxos"
  ],
  "features": [
    {
      "type": "Feature",
      "geometry": {
        "type": "Point",
        "coordinates": [
          24.190639,
          40.330422
        ]
      },
      "properties": {
        "description": "representative point"
      }
    },
    {
      "geometry": {
        "type": "Point",
        "coordinates": [
          24.190639,
          40.330422
        ]
      },
      "id": "darmc-location-10162",
      "type": "Feature",
      "properties": {
        "description": "500K scale point location",
        "location_precision": "precise",
        "title": "DARMC location 10162",
        "link": "http://pleiades.stoa.org/places/501535/darmc-location-10162"
      }
    }
  ]
}