{
  "type": "FeatureCollection",
  "title": "Philippoi",
  "id": "501564",
  "description": "An ancient place, cited: BAtlas 51 C2 Philippoi",
  "bbox": [
    24.334511,
    41.02518,
    24.334511,
    41.02518
  ],
  "reprPoint": [
    24.334511,
    41.02518
  ],
  "features": [
    {
      "geometry": {
        "type": "Point",
        "coordinates": [
          24.334511,
          41.02518
        ]
      },
      "id": "darmc-location-24244",
      "type": "Feature",
      "properties": {
        "description": "500K scale point location",
        "location_precision": "precise",
        "title": "DARMC location 24244",
        "link": "http://pleiades.stoa.org/places/501564/darmc-location-24244"
      }
    }
  ]
}