{
  "type": "FeatureCollection",
  "title": "Oreini",
  "id": "501540",
  "description": "An ancient place, cited: BAtlas 51 B2 Oreini",
  "bbox": [
    23.591541,
    41.196847,
    23.591541,
    41.196847
  ],
  "reprPoint": [
    23.591541,
    41.196847
  ],
  "features": [
    {
      "geometry": {
        "type": "Point",
        "coordinates": [
          23.591541,
          41.196847
        ]
      },
      "id": "darmc-location-23995",
      "type": "Feature",
      "properties": {
        "description": "1M scale point location",
        "location_precision": "precise",
        "title": "DARMC location 23995",
        "link": "http://pleiades.stoa.org/places/501540/darmc-location-23995"
      }
    }
  ]
}