{
  "type": "FeatureCollection",
  "title": "Mast(o)usia Pr.",
  "id": "501509",
  "description": "An ancient place, cited: BAtlas 51 G4 Mast(o)usia Pr.",
  "bbox": [
    26.16658,
    40.05436,
    26.16658,
    40.05436
  ],
  "reprPoint": [
    26.16658,
    40.05436
  ],
  "names": [
    "Mastousia Pr.",
    "Mastusia Pr."
  ],
  "features": [
    {
      "geometry": {
        "type": "Point",
        "coordinates": [
          26.16658,
          40.05436
        ]
      },
      "id": "location-of-tekke-burnu",
      "type": "Feature",
      "properties": {
        "description": "GeoNames location",
        "location_precision": "precise",
        "title": "Location of Tekke Burnu",
        "link": "http://pleiades.stoa.org/places/501509/location-of-tekke-burnu"
      }
    }
  ]
}