{
  "type": "FeatureCollection",
  "title": "Nike",
  "id": "501526",
  "bbox": [
    26.852251,
    41.594606,
    26.852251,
    41.594606
  ],
  "description": "An ancient place, cited: BAtlas 51 H1 Nike",
  "names": [
    "Nike"
  ],
  "features": [
    {
      "type": "Feature",
      "geometry": {
        "type": "Point",
        "coordinates": [
          26.852251,
          41.594606
        ]
      },
      "properties": {
        "description": "representative point"
      }
    },
    {
      "geometry": {
        "type": "Point",
        "coordinates": [
          26.852251,
          41.594606
        ]
      },
      "id": "darmc-location-13928",
      "type": "Feature",
      "properties": {
        "description": "500K scale point location",
        "location_precision": "precise",
        "title": "DARMC location 13928",
        "link": "http://pleiades.stoa.org/places/501526/darmc-location-13928"
      }
    }
  ]
}