{
  "type": "FeatureCollection",
  "title": "Pangaion (mountain)",
  "id": "501551",
  "bbox": [
    24.082778,
    40.916944,
    24.082778,
    40.916944
  ],
  "description": "Mt. Pangion.",
  "names": [
    "Pangaion"
  ],
  "features": [
    {
      "type": "Feature",
      "geometry": {
        "type": "Point",
        "coordinates": [
          24.082778,
          40.916944
        ]
      },
      "properties": {
        "description": "representative point"
      }
    },
    {
      "geometry": {
        "type": "Point",
        "coordinates": [
          24.082778,
          40.916944
        ]
      },
      "id": "location-of-pangaion-hills",
      "type": "Feature",
      "properties": {
        "description": "verified in Google Earth 2013.",
        "location_precision": "precise",
        "title": "location of Pangaion Hills",
        "link": "http://pleiades.stoa.org/places/501551/location-of-pangaion-hills"
      }
    }
  ]
}