{
  "type": "FeatureCollection",
  "title": "Pyrgos",
  "id": "501586",
  "bbox": [
    24.778583,
    40.741032,
    24.778583,
    40.741032
  ],
  "description": "An ancient place, cited: BAtlas 51 D3 Pyrgos",
  "features": [
    {
      "type": "Feature",
      "geometry": {
        "type": "Point",
        "coordinates": [
          24.778583,
          40.741032
        ]
      },
      "properties": {
        "description": "representative point"
      }
    },
    {
      "geometry": {
        "type": "Point",
        "coordinates": [
          24.778583,
          40.741032
        ]
      },
      "id": "darmc-location-23610",
      "type": "Feature",
      "properties": {
        "description": "Point location",
        "location_precision": "precise",
        "title": "DARMC location 23610",
        "link": "http://pleiades.stoa.org/places/501586/darmc-location-23610"
      }
    }
  ]
}