{
  "type": "FeatureCollection",
  "title": "Phagres",
  "id": "501559",
  "description": "An ancient place, cited: BAtlas 51 B3 Phagres",
  "bbox": [
    23.940471,
    40.760666,
    23.940471,
    40.760666
  ],
  "reprPoint": [
    23.940471,
    40.760666
  ],
  "names": [
    "Phagres"
  ],
  "features": [
    {
      "geometry": {
        "type": "Point",
        "coordinates": [
          23.940471,
          40.760666
        ]
      },
      "id": "darmc-location-10194",
      "type": "Feature",
      "properties": {
        "description": "500K scale point location",
        "location_precision": "precise",
        "title": "DARMC location 10194",
        "link": "http://pleiades.stoa.org/places/501559/darmc-location-10194"
      }
    }
  ]
}