{
  "type": "FeatureCollection",
  "title": "Vălkosel",
  "id": "501656",
  "description": "An ancient place, cited: BAtlas 51 C1 Vălkosel",
  "bbox": [
    23.983772,
    41.515523,
    23.983772,
    41.515523
  ],
  "reprPoint": [
    23.983772,
    41.515523
  ],
  "features": [
    {
      "geometry": {
        "type": "Point",
        "coordinates": [
          23.983772,
          41.515523
        ]
      },
      "id": "darmc-location-15345",
      "type": "Feature",
      "properties": {
        "description": "500K scale point location",
        "location_precision": "precise",
        "title": "DARMC location 15345",
        "link": "http://pleiades.stoa.org/places/501656/darmc-location-15345"
      }
    }
  ]
}