{
  "type": "FeatureCollection",
  "title": "Vodeničarsko",
  "id": "501658",
  "description": "An ancient place, cited: BAtlas 51 E2 Vodeničarsko",
  "bbox": [
    25.27545,
    41.478612,
    25.27545,
    41.478612
  ],
  "reprPoint": [
    25.27545,
    41.478612
  ],
  "features": [
    {
      "geometry": {
        "type": "Point",
        "coordinates": [
          25.27545,
          41.478612
        ]
      },
      "id": "darmc-location-15426",
      "type": "Feature",
      "properties": {
        "description": "500K scale point location",
        "location_precision": "precise",
        "title": "DARMC location 15426",
        "link": "http://pleiades.stoa.org/places/501658/darmc-location-15426"
      }
    }
  ]
}