{
  "type": "FeatureCollection",
  "title": "Naoura/Nitriae",
  "id": "50160",
  "description": "An ancient place, cited: BAtlas 5 C4 Naoura/Nitriae",
  "bbox": [
    74.449703,
    14.281472,
    74.449703,
    14.281472
  ],
  "reprPoint": [
    74.449703,
    14.281472
  ],
  "names": [
    "Naoura",
    "Nitriae"
  ],
  "features": [
    {
      "geometry": {
        "type": "Point",
        "coordinates": [
          74.449703,
          14.281472
        ]
      },
      "id": "darmc-location-19826",
      "type": "Feature",
      "properties": {
        "description": "5M scale point location",
        "location_precision": "precise",
        "title": "DARMC location 19826",
        "link": "http://pleiades.stoa.org/places/50160/darmc-location-19826"
      }
    }
  ]
}