{
  "type": "FeatureCollection",
  "title": "Zervae/Zirinae",
  "id": "501663",
  "bbox": [
    26.311937,
    41.160844,
    26.311937,
    41.160844
  ],
  "description": "An ancient place, cited: BAtlas 51 G2 Zervae/Zirinae",
  "names": [
    "Zervae",
    "Zirinae",
    "Zurbae"
  ],
  "features": [
    {
      "type": "Feature",
      "geometry": {
        "type": "Point",
        "coordinates": [
          26.311937,
          41.160844
        ]
      },
      "properties": {
        "description": "representative point"
      }
    },
    {
      "geometry": {
        "type": "Point",
        "coordinates": [
          26.311937,
          41.160844
        ]
      },
      "id": "darmc-location-9919",
      "type": "Feature",
      "properties": {
        "description": "1:500,000 scale representative point location digitized from the Barrington Atlas of the Greek and Roman World by the Digital Atlas of Roman and Medieval Civilizations project at Harvard University.",
        "location_precision": "precise",
        "title": "DARMC location 9919",
        "link": "http://pleiades.stoa.org/places/501663/darmc-location-9919"
      }
    }
  ]
}