{
  "type": "FeatureCollection",
  "title": "Saos M.",
  "id": "501600",
  "description": "Saos M., a mountain on the island of Samothrace rising to 1,611 m. above sea level.",
  "bbox": [
    25.5874978,
    40.4616628,
    25.5874978,
    40.4616628
  ],
  "connectsWith": [
    "501597"
  ],
  "reprPoint": [
    25.5874978,
    40.4616628
  ],
  "names": [
    "Saos M."
  ],
  "features": [
    {
      "geometry": {
        "type": "Point",
        "coordinates": [
          25.5874978,
          40.4616628
        ]
      },
      "id": "saos",
      "type": "Feature",
      "properties": {
        "description": "Location based on OpenStreetMap",
        "location_precision": "precise",
        "title": "location of Saos",
        "link": "http://pleiades.stoa.org/places/501600/saos"
      }
    }
  ]
}