{
  "type": "FeatureCollection",
  "title": "Thracium/Macedonicum Mare",
  "id": "501639",
  "bbox": [
    25.166667,
    40.366667,
    25.166667,
    40.366667
  ],
  "description": "An ancient place, cited: BAtlas 51 D4 Thracium/Macedonicum Mare",
  "names": [
    "Thracium",
    "Macedonicum Mare"
  ],
  "features": [
    {
      "type": "Feature",
      "geometry": {
        "type": "Point",
        "coordinates": [
          25.166667,
          40.366667
        ]
      },
      "properties": {
        "description": "representative point"
      }
    },
    {
      "geometry": {
        "type": "Point",
        "coordinates": [
          25.166667,
          40.366667
        ]
      },
      "id": "location-of-thracium-macedonicum-mare",
      "type": "Feature",
      "properties": {
        "description": "verified in Google Earth 2013.",
        "location_precision": "precise",
        "title": "location of Thracium/Macedonicum Mare",
        "link": "http://pleiades.stoa.org/places/501639/location-of-thracium-macedonicum-mare"
      }
    }
  ]
}