{
  "type": "FeatureCollection",
  "title": "Zervae/Zirinae",
  "id": "501663",
  "description": "An ancient place, cited: BAtlas 51 G2 Zervae/Zirinae",
  "bbox": [
    26.311937,
    41.160844,
    26.311937,
    41.160844
  ],
  "reprPoint": [
    26.311937,
    41.160844
  ],
  "names": [
    "Zervae",
    "Zirinae",
    "Zurbae"
  ],
  "features": [
    {
      "geometry": {
        "type": "Point",
        "coordinates": [
          26.311937,
          41.160844
        ]
      },
      "id": "darmc-location-9919",
      "type": "Feature",
      "properties": {
        "description": "500K scale point location",
        "location_precision": "precise",
        "title": "DARMC location 9919",
        "link": "http://pleiades.stoa.org/places/501663/darmc-location-9919"
      }
    }
  ]
}