{
  "type": "FeatureCollection",
  "title": "*Skabla",
  "id": "501619",
  "bbox": [
    23.590555,
    40.332591,
    23.590555,
    40.332591
  ],
  "description": "An ancient place, cited: BAtlas 51 B4 *Skabla",
  "names": [
    "Skabla",
    "Skablaioi"
  ],
  "features": [
    {
      "type": "Feature",
      "geometry": {
        "type": "Point",
        "coordinates": [
          23.590555,
          40.332591
        ]
      },
      "properties": {
        "description": "representative point"
      }
    },
    {
      "geometry": {
        "type": "Point",
        "coordinates": [
          23.590555,
          40.332591
        ]
      },
      "id": "darmc-location-9534",
      "type": "Feature",
      "properties": {
        "description": "1:500,000 scale representative point location digitized from the Barrington Atlas of the Greek and Roman World by the Digital Atlas of Roman and Medieval Civilizations project at Harvard University.",
        "location_precision": "precise",
        "title": "DARMC location 9534",
        "link": "http://pleiades.stoa.org/places/501619/darmc-location-9534"
      }
    }
  ]
}