{
  "type": "FeatureCollection",
  "title": "Tell F6 at Failaka",
  "id": "50163780",
  "bbox": [
    48.2793785,
    29.4318442,
    48.2793785,
    29.4318442
  ],
  "description": "Tell on the southwestern corner of Failaka Island containing the remains of two large buildings, tentatively identified as a palace and a temple, dated to 1900-1400 BCE.",
  "connectsWith": [
    "912851"
  ],
  "features": [
    {
      "type": "Feature",
      "geometry": {
        "type": "Point",
        "coordinates": [
          48.2793785,
          29.4318442
        ]
      },
      "properties": {
        "description": "representative point"
      }
    },
    {
      "geometry": {
        "type": "Point",
        "coordinates": [
          48.2793785,
          29.4318442
        ]
      },
      "id": "f6-bronze-age-site",
      "type": "Feature",
      "properties": {
        "description": "Point representing the approximate center point of the Tell F6 site, derived from an OpenStreetMap Node.",
        "location_precision": "precise",
        "title": "OSM location of F6 Bronze Age site",
        "link": "http://pleiades.stoa.org/places/50163780/f6-bronze-age-site"
      }
    }
  ]
}