{
  "type": "FeatureCollection",
  "title": "Lapford",
  "id": "502452939",
  "bbox": [
    -3.8010008,
    50.849223,
    -3.8010008,
    50.849223
  ],
  "description": "Two distinct Roman forts; the smaller covering ca. 1.9 ha and the larger up to 8 ha.",
  "features": [
    {
      "type": "Feature",
      "geometry": {
        "type": "Point",
        "coordinates": [
          -3.8010008,
          50.849223
        ]
      },
      "properties": {
        "description": "representative point"
      }
    },
    {
      "geometry": {
        "type": "Point",
        "coordinates": [
          -3.8010008,
          50.849223
        ]
      },
      "id": "location-of-roman-fort",
      "type": "Feature",
      "properties": {
        "description": "Location based on OpenStreetMap",
        "location_precision": "precise",
        "title": "location of Roman fort",
        "link": "http://pleiades.stoa.org/places/502452939/location-of-roman-fort"
      }
    }
  ]
}