{
  "type": "FeatureCollection",
  "title": "Temple of Demeter at the Sanctuary of Demeter Malophoros, Selinus",
  "id": "502577471",
  "description": "The Temple of Demeter was used for the worship of Demeter (Malophoros), goddess of fertility, grain and agriculture. Built in the seventh century BC, the temple was used continuously until its abandonment ca. 250 BC ",
  "bbox": [
    12.816874,
    37.586763,
    12.816874,
    37.586763
  ],
  "connectsWith": [
    "462489"
  ],
  "reprPoint": [
    12.816874,
    37.586763
  ],
  "features": [
    {
      "geometry": {
        "type": "Point",
        "coordinates": [
          12.816874,
          37.586763
        ]
      },
      "id": "temple-of-demeter-at-the-sanctuary-of-demeter-malophoros",
      "type": "Feature",
      "properties": {
        "description": "Representative imagery location of the archaeological site, verified in Google Earth 2016. Chronology following White 1967.",
        "location_precision": "precise",
        "title": "Imagery location of Temple of Demeter at the Sanctuary of Demeter Malophoros",
        "link": "http://pleiades.stoa.org/places/502577471/temple-of-demeter-at-the-sanctuary-of-demeter-malophoros"
      }
    }
  ]
}