{
  "type": "FeatureCollection",
  "title": "Selour",
  "id": "50260",
  "bbox": [
    77.38007,
    10.432112,
    77.38007,
    10.432112
  ],
  "description": "An ancient place, cited: BAtlas 5 D4 Selour",
  "names": [
    "Selour"
  ],
  "features": [
    {
      "type": "Feature",
      "geometry": {
        "type": "Point",
        "coordinates": [
          77.38007,
          10.432112
        ]
      },
      "properties": {
        "description": "representative point"
      }
    },
    {
      "geometry": {
        "type": "Point",
        "coordinates": [
          77.38007,
          10.432112
        ]
      },
      "id": "darmc-location-14666",
      "type": "Feature",
      "properties": {
        "description": "5M scale point location",
        "location_precision": "precise",
        "title": "DARMC location 14666",
        "link": "http://pleiades.stoa.org/places/50260/darmc-location-14666"
      }
    }
  ]
}