{
  "type": "FeatureCollection",
  "title": "Forum Romanum",
  "id": "502866838",
  "bbox": [
    12.4840267,
    41.890818,
    12.486137,
    41.893128
  ],
  "description": "The ancient Roman forum.",
  "connectsWith": [
    "423025"
  ],
  "names": [
    "Foro Romano",
    "Forum Romanum"
  ],
  "features": [
    {
      "type": "Feature",
      "geometry": {
        "type": "Point",
        "coordinates": [
          12.4853226985,
          41.8921301965
        ]
      },
      "properties": {
        "description": "representative point"
      }
    }
  ]
}