{
  "type": "FeatureCollection",
  "title": "Forum Romanum",
  "id": "502866838",
  "bbox": [
    12.4836986,
    41.8906913,
    12.4885844,
    41.8943962
  ],
  "description": "The ancient Roman forum.",
  "connectsWith": [
    "423025",
    "434423626"
  ],
  "names": [
    "Foro Romano",
    "Forum Romanum",
    "Forum",
    "Forum Magnum",
    "Romaion agora",
    "Roman Forum",
    "archaia agora"
  ],
  "features": [
    {
      "type": "Feature",
      "geometry": {
        "type": "Point",
        "coordinates": [
          12.4847698369,
          41.8925476155
        ]
      },
      "properties": {
        "description": "representative point"
      }
    }
  ]
}