{
  "type": "FeatureCollection",
  "title": "Forum Romanum",
  "id": "502866838",
  "bbox": [
    12.4840267,
    41.890818,
    12.486137,
    41.8941045
  ],
  "description": "The ancient Roman forum.",
  "connectsWith": [
    "423025",
    "434423626"
  ],
  "names": [
    "Foro Romano",
    "Forum Romanum"
  ],
  "features": [
    {
      "type": "Feature",
      "geometry": {
        "type": "Point",
        "coordinates": [
          12.4852686364,
          41.8922967823
        ]
      },
      "properties": {
        "description": "representative point"
      }
    }
  ]
}