{
  "type": "FeatureCollection",
  "title": "Forum Romanum",
  "id": "502866838",
  "description": "The ancient Roman forum.",
  "bbox": [
    12.4840267,
    41.8919597,
    12.4847853,
    41.8929384
  ],
  "connectsWith": [
    "423025"
  ],
  "reprPoint": [
    12.484406,
    41.89244905
  ],
  "names": [
    "Foro Romano"
  ],
  "features": [
    {
      "geometry": {
        "type": "Point",
        "coordinates": [
          12.4847853,
          41.8929384
        ]
      },
      "id": "arch-of-septimius-severus-northwest-corner",
      "type": "Feature",
      "properties": {
        "description": "Location based on OpenStreetMap",
        "location_precision": "precise",
        "title": "Arch of Septimius Severus (northwest corner)",
        "link": "http://pleiades.stoa.org/places/502866838/arch-of-septimius-severus-northwest-corner"
      }
    },
    {
      "geometry": {
        "type": "Point",
        "coordinates": [
          12.4840267,
          41.8919597
        ]
      },
      "id": "basilica-julia-southwest-corner",
      "type": "Feature",
      "properties": {
        "description": "Location based on OpenStreetMap",
        "location_precision": "precise",
        "title": "Basilica Julia (southwest corner)",
        "link": "http://pleiades.stoa.org/places/502866838/basilica-julia-southwest-corner"
      }
    }
  ]
}