{
  "type": "FeatureCollection",
  "title": "Forum Romanum",
  "id": "502866838",
  "bbox": [
    12.4840267,
    41.890818,
    12.4863205,
    41.8941045
  ],
  "description": "The ancient Roman forum.",
  "connectsWith": [
    "423025",
    "434423626"
  ],
  "names": [
    "Foro Romano",
    "Forum Romanum",
    "Forum",
    "Forum Magnum",
    "Romaion agora",
    "Roman Forum",
    "archaia agora"
  ],
  "features": [
    {
      "type": "Feature",
      "geometry": {
        "type": "Point",
        "coordinates": [
          12.485339628,
          41.892297252
        ]
      },
      "properties": {
        "description": "representative point"
      }
    }
  ]
}