{
  "type": "FeatureCollection",
  "title": "Tennagora",
  "id": "50301",
  "bbox": [
    77.897214,
    11.376307,
    77.897214,
    11.376307
  ],
  "description": "An ancient place, cited: BAtlas 5 D4 Tennagora",
  "names": [
    "Tennagora"
  ],
  "features": [
    {
      "type": "Feature",
      "geometry": {
        "type": "Point",
        "coordinates": [
          77.897214,
          11.376307
        ]
      },
      "properties": {
        "description": "representative point"
      }
    },
    {
      "geometry": {
        "type": "Point",
        "coordinates": [
          77.897214,
          11.376307
        ]
      },
      "id": "darmc-location-19886",
      "type": "Feature",
      "properties": {
        "description": "5M scale point location",
        "location_precision": "precise",
        "title": "DARMC location 19886",
        "link": "http://pleiades.stoa.org/places/50301/darmc-location-19886"
      }
    }
  ]
}