{
  "type": "FeatureCollection",
  "title": "Tropina",
  "id": "50311",
  "description": "An ancient place, cited: BAtlas 5 D5 Tropina",
  "bbox": [
    76.482942,
    9.806614,
    76.482942,
    9.806614
  ],
  "reprPoint": [
    76.482942,
    9.806614
  ],
  "names": [
    "Tropina"
  ],
  "features": [
    {
      "geometry": {
        "type": "Point",
        "coordinates": [
          76.482942,
          9.806614
        ]
      },
      "id": "darmc-location-15271",
      "type": "Feature",
      "properties": {
        "description": "5M scale point location",
        "location_precision": "precise",
        "title": "DARMC location 15271",
        "link": "http://pleiades.stoa.org/places/50311/darmc-location-15271"
      }
    }
  ]
}