{
  "type": "FeatureCollection",
  "title": "Aşıklı Höyük",
  "id": "503406424",
  "bbox": [
    34.2296345,
    38.3486007,
    34.2296345,
    38.3486007
  ],
  "description": "Aşıklı Höyük is an ancient settlement mound located in central Cappadocia that was first settled in the Aceramic Neolithic period, ca. 8000 B.C.",
  "features": [
    {
      "type": "Feature",
      "geometry": {
        "type": "Point",
        "coordinates": [
          34.2296345,
          38.3486007
        ]
      },
      "properties": {
        "description": "representative point"
      }
    },
    {
      "geometry": {
        "type": "Point",
        "coordinates": [
          34.2296345,
          38.3486007
        ]
      },
      "id": "osm-location",
      "type": "Feature",
      "properties": {
        "description": "Location based on OpenStreetMap",
        "location_precision": "precise",
        "title": "OSM location",
        "link": "http://pleiades.stoa.org/places/503406424/osm-location"
      }
    }
  ]
}