{
  "type": "FeatureCollection",
  "title": "Monte Catalfaro",
  "id": "50391614",
  "description": "A rocky plateau located north-east of modern Mineo, overlooking Catania, that was inhabited from prehistoric times to the Middle Ages.",
  "bbox": [
    14.7170002,
    37.280398,
    14.7170002,
    37.280398
  ],
  "connectsWith": [
    "011dbae16282fae1d9b35a19437412bd"
  ],
  "reprPoint": [
    14.7170002,
    37.280398
  ],
  "names": [
    "Monte Catalfaro"
  ],
  "features": [
    {
      "geometry": {
        "type": "Point",
        "coordinates": [
          14.7170002,
          37.280398
        ]
      },
      "id": "osm-location-of-monte-catalfaro",
      "type": "Feature",
      "properties": {
        "description": "Location of Monte Catalfaro, near modern Mineo based on an OpenStreetMap node.",
        "location_precision": "precise",
        "title": "OSM location of Monte Catalfaro",
        "link": "http://pleiades.stoa.org/places/50391614/osm-location-of-monte-catalfaro"
      }
    }
  ]
}