{
  "type": "FeatureCollection",
  "title": "Necropolis near Randazzo, Sicily",
  "id": "504285206",
  "bbox": [
    14.949681,
    37.876058,
    14.949681,
    37.876058
  ],
  "description": "A necropolis with remains dating to the fifth century B.C.",
  "connectsWith": [
    "462492"
  ],
  "features": [
    {
      "type": "Feature",
      "geometry": {
        "type": "Point",
        "coordinates": [
          14.949681,
          37.876058
        ]
      },
      "properties": {
        "description": "representative point"
      }
    },
    {
      "geometry": {
        "type": "Point",
        "coordinates": [
          14.949681,
          37.876058
        ]
      },
      "id": "osm-location",
      "type": "Feature",
      "properties": {
        "description": "Representative location of modern community based on a node derived from OpenStreetMap.",
        "location_precision": "precise",
        "title": "OSM location of Randazzo, Sicily",
        "link": "http://pleiades.stoa.org/places/504285206/osm-location"
      }
    }
  ]
}