{
  "type": "FeatureCollection",
  "title": "Skinburness",
  "id": "504812865",
  "bbox": [
    -3.3587034,
    54.8923956,
    -3.3587034,
    54.8923956
  ],
  "description": "Milefortlet 9, Skinburness",
  "connectsWith": [
    "579047271"
  ],
  "features": [
    {
      "type": "Feature",
      "geometry": {
        "type": "Point",
        "coordinates": [
          -3.3587034,
          54.8923956
        ]
      },
      "properties": {
        "description": "representative point"
      }
    },
    {
      "geometry": {
        "type": "Point",
        "coordinates": [
          -3.3587034,
          54.8923956
        ]
      },
      "id": "osm-location",
      "type": "Feature",
      "properties": {
        "description": "Representative location based on OpenStreetMap",
        "location_precision": "precise",
        "title": "OSM location of Milefortlet 9, Skinburness",
        "link": "http://pleiades.stoa.org/places/504812865/osm-location"
      }
    }
  ]
}