{
  "type": "FeatureCollection",
  "title": "TE.E",
  "id": "5066376",
  "bbox": [
    44.434117,
    32.534242,
    44.434117,
    32.534242
  ],
  "description": "According to the Babylonian topographical text Tintir = Babylon, TE.E (read as either Tê or Kisīri) was one of the six city districts of the eastern half of the inner city of Babylon and it contained one temple and two daises.",
  "connectsWith": [
    "893951"
  ],
  "names": [
    "TE.E"
  ],
  "features": [
    {
      "type": "Feature",
      "geometry": {
        "type": "Point",
        "coordinates": [
          44.434117,
          32.534242
        ]
      },
      "properties": {
        "description": "representative point"
      }
    },
    {
      "geometry": {
        "type": "Point",
        "coordinates": [
          44.434117,
          32.534242
        ]
      },
      "id": "imagery-location",
      "type": "Feature",
      "properties": {
        "description": null,
        "location_precision": "precise",
        "title": "Imagery Location of approximate centerpoint of TE.E",
        "link": "http://pleiades.stoa.org/places/5066376/imagery-location"
      }
    }
  ]
}