{
  "type": "FeatureCollection",
  "title": "Abū Dhuba‘",
  "id": "50762146",
  "bbox": [
    45.2922,
    32.0591,
    45.2922,
    32.0591
  ],
  "description": "Minor site from which inscribed bricks have been found.",
  "names": [
    "Abū Dhuba‘"
  ],
  "features": [
    {
      "type": "Feature",
      "geometry": {
        "type": "Point",
        "coordinates": [
          45.2922,
          32.0591
        ]
      },
      "properties": {
        "description": "representative point"
      }
    },
    {
      "geometry": {
        "type": "Point",
        "coordinates": [
          45.2922,
          32.0591
        ]
      },
      "id": "cigs-location-of-abu-dhuba2018",
      "type": "Feature",
      "properties": {
        "description": null,
        "location_precision": "precise",
        "title": "CIGS location of Abū Dhuba‘",
        "link": "http://pleiades.stoa.org/places/50762146/cigs-location-of-abu-dhuba2018"
      }
    }
  ]
}