{
  "type": "FeatureCollection",
  "title": "Artaiouteichos",
  "id": "511159",
  "bbox": [
    28.478392,
    40.366649,
    28.478392,
    40.366649
  ],
  "description": "An ancient place, cited: BAtlas 52 C4 Artaiouteichos",
  "names": [
    "Artaiouteichos"
  ],
  "features": [
    {
      "type": "Feature",
      "geometry": {
        "type": "Point",
        "coordinates": [
          28.478392,
          40.366649
        ]
      },
      "properties": {
        "description": "representative point"
      }
    },
    {
      "geometry": {
        "type": "Point",
        "coordinates": [
          28.478392,
          40.366649
        ]
      },
      "id": "darmc-location-4697",
      "type": "Feature",
      "properties": {
        "description": "500K scale point location",
        "location_precision": "precise",
        "title": "DARMC location 4697",
        "link": "http://pleiades.stoa.org/places/511159/darmc-location-4697"
      }
    }
  ]
}