{
  "type": "FeatureCollection",
  "title": "*Baradendromia",
  "id": "511176",
  "bbox": [
    30.026045,
    40.98169,
    30.026045,
    40.98169
  ],
  "description": "An ancient place, cited: BAtlas 52 G3 *Baradendromia",
  "names": [
    "Baradendromia"
  ],
  "features": [
    {
      "type": "Feature",
      "geometry": {
        "type": "Point",
        "coordinates": [
          30.026045,
          40.98169
        ]
      },
      "properties": {
        "description": "representative point"
      }
    },
    {
      "geometry": {
        "type": "Point",
        "coordinates": [
          30.026045,
          40.98169
        ]
      },
      "id": "darmc-location-6335",
      "type": "Feature",
      "properties": {
        "description": "500K scale point location",
        "location_precision": "precise",
        "title": "DARMC location 6335",
        "link": "http://pleiades.stoa.org/places/511176/darmc-location-6335"
      }
    }
  ]
}