{
  "type": "FeatureCollection",
  "title": "Caenophrurium",
  "id": "511199",
  "description": "An ancient place, cited: BAtlas 52 C2 Caenophrurium",
  "bbox": [
    28.1897914,
    41.2292598,
    28.201399,
    41.23524
  ],
  "reprPoint": [
    28.1955952,
    41.2322499
  ],
  "names": [
    "Caenophrurium"
  ],
  "features": [
    {
      "geometry": {
        "type": "Point",
        "coordinates": [
          28.201399,
          41.23524
        ]
      },
      "id": "darmc-location-24367",
      "type": "Feature",
      "properties": {
        "description": "500K scale point location",
        "location_precision": "precise",
        "title": "DARMC location 24367",
        "link": "http://pleiades.stoa.org/places/511199/darmc-location-24367"
      }
    },
    {
      "geometry": {
        "type": "Point",
        "coordinates": [
          28.18979139999999,
          41.2292598
        ]
      },
      "id": "dare-location",
      "type": "Feature",
      "properties": {
        "description": "Representative point location, village precision",
        "location_precision": "precise",
        "title": "DARE Location",
        "link": "http://pleiades.stoa.org/places/511199/dare-location"
      }
    }
  ]
}