{
  "type": "FeatureCollection",
  "title": "Burtudizon",
  "id": "511195",
  "bbox": [
    27.092423,
    41.427933,
    27.092423,
    41.427933
  ],
  "description": "An ancient place, cited: BAtlas 52 A2 Burtudizon",
  "names": [
    "Burtudizon"
  ],
  "features": [
    {
      "type": "Feature",
      "geometry": {
        "type": "Point",
        "coordinates": [
          27.092423,
          41.427933
        ]
      },
      "properties": {
        "description": "representative point"
      }
    },
    {
      "geometry": {
        "type": "Point",
        "coordinates": [
          27.092423,
          41.427933
        ]
      },
      "id": "darmc-location-24149",
      "type": "Feature",
      "properties": {
        "description": "500K scale point location",
        "location_precision": "precise",
        "title": "DARMC location 24149",
        "link": "http://pleiades.stoa.org/places/511195/darmc-location-24149"
      }
    }
  ]
}