{
  "type": "FeatureCollection",
  "title": "Elaphonnesos? Ins.",
  "id": "511248",
  "bbox": [
    27.508,
    40.501,
    27.508,
    40.501
  ],
  "description": "An ancient place, cited: BAtlas 52 A4 Elaphonnesos? Ins.",
  "names": [
    "Elaphonnesos"
  ],
  "features": [
    {
      "type": "Feature",
      "geometry": {
        "type": "Point",
        "coordinates": [
          27.508,
          40.501
        ]
      },
      "properties": {
        "description": "representative point"
      }
    },
    {
      "geometry": {
        "type": "Point",
        "coordinates": [
          27.508,
          40.501
        ]
      },
      "id": "location-of-elaphonnesos-ins",
      "type": "Feature",
      "properties": {
        "description": "verified in Google Earth 2013 based on Barrington Atlas location.",
        "location_precision": "precise",
        "title": "location of Elaphonnesos? Ins.",
        "link": "http://pleiades.stoa.org/places/511248/location-of-elaphonnesos-ins"
      }
    }
  ]
}