{
  "type": "FeatureCollection",
  "title": "Granicus (river)",
  "id": "511260",
  "bbox": [
    27.2716339,
    40.30671,
    27.2716339,
    40.30671
  ],
  "description": "Granicus fl. (modern Biga Çayı) is a river in Asia Minor that flows from Mount Ida to the Sea of Marmara. ",
  "connectsWith": [
    "511381"
  ],
  "names": [
    "Granicus"
  ],
  "features": [
    {
      "type": "Feature",
      "geometry": {
        "type": "Point",
        "coordinates": [
          27.2716339,
          40.30671
        ]
      },
      "properties": {
        "description": "representative point"
      }
    },
    {
      "geometry": {
        "type": "Point",
        "coordinates": [
          27.2716339,
          40.30671
        ]
      },
      "id": "location-of-Granicus-fl",
      "type": "Feature",
      "properties": {
        "description": "Location based on OpenStreetMap",
        "location_precision": "precise",
        "title": "location of Granicus fl.",
        "link": "http://pleiades.stoa.org/places/511260/location-of-Granicus-fl"
      }
    }
  ]
}