{
  "type": "FeatureCollection",
  "title": "*Kalasyrta",
  "id": "511283",
  "description": "An ancient place, cited: BAtlas 52 G3 *Kalasyrta",
  "bbox": [
    30.026371,
    40.785278,
    30.026371,
    40.785278
  ],
  "reprPoint": [
    30.026371,
    40.785278
  ],
  "names": [
    "Kalasyrta"
  ],
  "features": [
    {
      "geometry": {
        "type": "Point",
        "coordinates": [
          30.026371,
          40.785278
        ]
      },
      "id": "darmc-location-5168",
      "type": "Feature",
      "properties": {
        "description": "500K scale point location",
        "location_precision": "precise",
        "title": "DARMC location 5168",
        "link": "http://pleiades.stoa.org/places/511283/darmc-location-5168"
      }
    }
  ]
}