{
  "type": "FeatureCollection",
  "title": "Delkos/Derkos/Phileatine",
  "id": "511232",
  "description": "A lake located to the north of Byzantium, now called Derkoz Gölü (Turkey).",
  "bbox": [
    28.5925,
    41.3475,
    28.5925,
    41.3475
  ],
  "reprPoint": [
    28.5925,
    41.3475
  ],
  "names": [
    "Phileatine L.",
    "Derkos",
    "Delkos"
  ],
  "features": [
    {
      "geometry": {
        "type": "Point",
        "coordinates": [
          28.5925,
          41.3475
        ]
      },
      "id": "modern-shoreline-derkoz-golu",
      "type": "Feature",
      "properties": {
        "description": "Location based on OpenStreetMap",
        "location_precision": "precise",
        "title": "Modern shoreline of the Derkoz Gölü",
        "link": "http://pleiades.stoa.org/places/511232/modern-shoreline-derkoz-golu"
      }
    }
  ]
}