{
  "type": "FeatureCollection",
  "title": "Halone",
  "id": "511262",
  "description": "An ancient place, cited: BAtlas 52 B4 Halone",
  "bbox": [
    27.608878,
    40.48942,
    27.608878,
    40.48942
  ],
  "connectsWith": [
    "511263"
  ],
  "reprPoint": [
    27.608878,
    40.48942
  ],
  "names": [
    "Halone"
  ],
  "features": [
    {
      "geometry": {
        "type": "Point",
        "coordinates": [
          27.608878,
          40.48942
        ]
      },
      "id": "darmc-location-24230",
      "type": "Feature",
      "properties": {
        "description": "500K scale point location",
        "location_precision": "precise",
        "title": "DARMC location 24230",
        "link": "http://pleiades.stoa.org/places/511262/darmc-location-24230"
      }
    }
  ]
}