{
  "type": "FeatureCollection",
  "title": "Dekaton",
  "id": "511229",
  "description": "An ancient place, cited: BAtlas 52 G3 Dekaton",
  "bbox": [
    30.097628,
    40.72108,
    30.097628,
    40.72108
  ],
  "reprPoint": [
    30.097628,
    40.72108
  ],
  "names": [
    "Dekaton"
  ],
  "features": [
    {
      "geometry": {
        "type": "Point",
        "coordinates": [
          30.097628,
          40.72108
        ]
      },
      "id": "darmc-location-1813",
      "type": "Feature",
      "properties": {
        "description": "500K scale point location",
        "location_precision": "precise",
        "title": "DARMC location 1813",
        "link": "http://pleiades.stoa.org/places/511229/darmc-location-1813"
      }
    }
  ]
}