{
  "type": "FeatureCollection",
  "title": "Charax",
  "id": "511205",
  "description": "An ancient place, cited: BAtlas 52 F3 Charax",
  "bbox": [
    29.613672,
    40.788976,
    29.613672,
    40.788976
  ],
  "reprPoint": [
    29.613672,
    40.788976
  ],
  "names": [
    "Charax"
  ],
  "features": [
    {
      "geometry": {
        "type": "Point",
        "coordinates": [
          29.613672,
          40.788976
        ]
      },
      "id": "darmc-location-23993",
      "type": "Feature",
      "properties": {
        "description": "500K scale point location",
        "location_precision": "precise",
        "title": "DARMC location 23993",
        "link": "http://pleiades.stoa.org/places/511205/darmc-location-23993"
      }
    }
  ]
}