{
  "type": "FeatureCollection",
  "title": "Nicomedia",
  "id": "511337",
  "description": "Nicomedia was founded in 712/11 BC as a Megarian colony named Astacus and was rebuilt by Nicomedes I of Bithynia in 264 BC. The city was an important administrative center of the Roman Empire.",
  "bbox": [
    29.916288,
    40.76445,
    29.923486,
    40.765931
  ],
  "reprPoint": [
    29.919887,
    40.7651905
  ],
  "names": [
    "Nikomēdeia",
    "Nikomedia",
    "Nikomēdia",
    "Nikomedeia",
    "Kocaeli",
    "Nicomedia",
    "İzmid",
    "İzniḳmid",
    "İznikmid",
    "İznikmit",
    "İzmit",
    "Olbia",
    "Niqumūdiya",
    "Ismid"
  ],
  "features": [
    {
      "geometry": {
        "type": "Point",
        "coordinates": [
          29.916288,
          40.765931
        ]
      },
      "id": "darmc-location-23979",
      "type": "Feature",
      "properties": {
        "description": "500K scale point location",
        "location_precision": "precise",
        "title": "DARMC location 23979",
        "link": "http://pleiades.stoa.org/places/511337/darmc-location-23979"
      }
    },
    {
      "geometry": {
        "type": "Point",
        "coordinates": [
          29.923486,
          40.76445
        ]
      },
      "id": "dare-location",
      "type": "Feature",
      "properties": {
        "description": "Representative point location, site precision",
        "location_precision": "precise",
        "title": "DARE Location",
        "link": "http://pleiades.stoa.org/places/511337/dare-location"
      }
    }
  ]
}