{
  "type": "FeatureCollection",
  "title": "Libum",
  "id": "511304",
  "bbox": [
    29.686075,
    40.631587,
    29.686075,
    40.631587
  ],
  "description": "An ancient place, cited: BAtlas 52 F3 Libum",
  "names": [
    "Libum"
  ],
  "features": [
    {
      "type": "Feature",
      "geometry": {
        "type": "Point",
        "coordinates": [
          29.686075,
          40.631587
        ]
      },
      "properties": {
        "description": "representative point"
      }
    },
    {
      "geometry": {
        "type": "Point",
        "coordinates": [
          29.686075,
          40.631587
        ]
      },
      "id": "darmc-location-24379",
      "type": "Feature",
      "properties": {
        "description": "500K scale point location",
        "location_precision": "precise",
        "title": "DARMC location 24379",
        "link": "http://pleiades.stoa.org/places/511304/darmc-location-24379"
      }
    }
  ]
}