{
  "type": "FeatureCollection",
  "title": "*Prepa",
  "id": "511374",
  "description": "An ancient place, cited: BAtlas 52 F3 *Prepa",
  "bbox": [
    29.750652,
    40.856523,
    29.750652,
    40.856523
  ],
  "reprPoint": [
    29.750652,
    40.856523
  ],
  "names": [
    "Prepa"
  ],
  "features": [
    {
      "geometry": {
        "type": "Point",
        "coordinates": [
          29.750652,
          40.856523
        ]
      },
      "id": "darmc-location-5145",
      "type": "Feature",
      "properties": {
        "description": "500K scale point location",
        "location_precision": "precise",
        "title": "DARMC location 5145",
        "link": "http://pleiades.stoa.org/places/511374/darmc-location-5145"
      }
    }
  ]
}