{
  "type": "FeatureCollection",
  "title": "Pylai",
  "id": "511389",
  "description": "An ancient place, cited: BAtlas 52 E3 Pylai",
  "bbox": [
    29.266682,
    40.649833,
    29.273345,
    40.657795
  ],
  "reprPoint": [
    29.2700135,
    40.653814
  ],
  "names": [
    "Pylai"
  ],
  "features": [
    {
      "geometry": {
        "type": "Point",
        "coordinates": [
          29.266682,
          40.649833
        ]
      },
      "id": "darmc-location-24132",
      "type": "Feature",
      "properties": {
        "description": "500K scale point location",
        "location_precision": "precise",
        "title": "DARMC location 24132",
        "link": "http://pleiades.stoa.org/places/511389/darmc-location-24132"
      }
    },
    {
      "geometry": {
        "type": "Point",
        "coordinates": [
          29.273345,
          40.657795
        ]
      },
      "id": "dare-location",
      "type": "Feature",
      "properties": {
        "description": "Representative point location, village precision",
        "location_precision": "precise",
        "title": "DARE Location",
        "link": "http://pleiades.stoa.org/places/511389/dare-location"
      }
    }
  ]
}