{
  "type": "FeatureCollection",
  "title": "Pylai",
  "id": "511389",
  "description": "An ancient place, cited: BAtlas 52 E3 Pylai",
  "bbox": [
    29.273345,
    40.657795,
    29.273345,
    40.657795
  ],
  "reprPoint": [
    29.273345,
    40.657795
  ],
  "names": [
    "Pylai"
  ],
  "features": [
    {
      "geometry": {
        "type": "Point",
        "coordinates": [
          29.273345,
          40.657795
        ]
      },
      "id": "dare-location",
      "type": "Feature",
      "properties": {
        "description": "Representative point location, village precision",
        "location_precision": "precise",
        "title": "DARE Location",
        "link": "http://pleiades.stoa.org/places/511389/dare-location"
      }
    }
  ]
}