{
  "type": "FeatureCollection",
  "title": "Propontis",
  "id": "511381",
  "description": "The Sea of Marmara.",
  "bbox": [
    28.2499999,
    40.6666672,
    28.2499999,
    40.6666672
  ],
  "connectsWith": [
    "08955be08c0573f42e925cfb7166302c"
  ],
  "reprPoint": [
    28.2499999,
    40.6666672
  ],
  "names": [
    "Propontis",
    "Sea of Marmara"
  ],
  "features": [
    {
      "geometry": {
        "type": "Point",
        "coordinates": [
          28.2499999,
          40.6666672
        ]
      },
      "id": "representative-location-for-propontis",
      "type": "Feature",
      "properties": {
        "description": "Location based on OpenStreetMap",
        "location_precision": "precise",
        "title": "representative location for Propontis",
        "link": "http://pleiades.stoa.org/places/511381/representative-location-for-propontis"
      }
    }
  ]
}