{
  "type": "FeatureCollection",
  "title": "Scylla",
  "id": "511413",
  "description": "An ancient place, cited: BAtlas 52 C2 Scylla",
  "bbox": [
    28.299586,
    41.485282,
    28.29966,
    41.485458
  ],
  "reprPoint": [
    28.299623,
    41.48537
  ],
  "names": [
    "Scylla"
  ],
  "features": [
    {
      "geometry": {
        "type": "Point",
        "coordinates": [
          28.299586,
          41.485282
        ]
      },
      "id": "darmc-location-23976",
      "type": "Feature",
      "properties": {
        "description": "500K scale point location",
        "location_precision": "precise",
        "title": "DARMC location 23976",
        "link": "http://pleiades.stoa.org/places/511413/darmc-location-23976"
      }
    },
    {
      "geometry": {
        "type": "Point",
        "coordinates": [
          28.299660000000017,
          41.485458
        ]
      },
      "id": "dare-location",
      "type": "Feature",
      "properties": {
        "description": "Representative point location, village precision",
        "location_precision": "precise",
        "title": "DARE Location",
        "link": "http://pleiades.stoa.org/places/511413/dare-location"
      }
    }
  ]
}