{
  "type": "FeatureCollection",
  "title": "‘Urisio’",
  "id": "511458",
  "description": "An ancient place, cited: BAtlas 52 A2 ‘Urisio’",
  "bbox": [
    27.238012,
    41.41929,
    27.238012,
    41.41929
  ],
  "reprPoint": [
    27.238012,
    41.41929
  ],
  "names": [
    "Urisio"
  ],
  "features": [
    {
      "geometry": {
        "type": "Point",
        "coordinates": [
          27.238012,
          41.41929
        ]
      },
      "id": "darmc-location-24477",
      "type": "Feature",
      "properties": {
        "description": "500K scale point location",
        "location_precision": "precise",
        "title": "DARMC location 24477",
        "link": "http://pleiades.stoa.org/places/511458/darmc-location-24477"
      }
    }
  ]
}