{
  "type": "FeatureCollection",
  "title": "Thrakia Kome",
  "id": "511440",
  "bbox": [
    27.927064,
    40.361304,
    27.927064,
    40.361304
  ],
  "description": "An ancient place, cited: BAtlas 52 B4 Thrakia Kome",
  "names": [
    "Thrakia Kome"
  ],
  "features": [
    {
      "type": "Feature",
      "geometry": {
        "type": "Point",
        "coordinates": [
          27.927064,
          40.361304
        ]
      },
      "properties": {
        "description": "representative point"
      }
    },
    {
      "geometry": {
        "type": "Point",
        "coordinates": [
          27.927064,
          40.361304
        ]
      },
      "id": "darmc-location-6474",
      "type": "Feature",
      "properties": {
        "description": "500K scale point location",
        "location_precision": "precise",
        "title": "DARMC location 6474",
        "link": "http://pleiades.stoa.org/places/511440/darmc-location-6474"
      }
    }
  ]
}