{
  "type": "FeatureCollection",
  "title": "Salmydessos",
  "id": "511404",
  "description": "An ancient place, cited: BAtlas 52 C1 Salmydessos",
  "bbox": [
    28.091144,
    41.637244,
    28.091144,
    41.637244
  ],
  "reprPoint": [
    28.091144,
    41.637244
  ],
  "names": [
    "Salmydessos"
  ],
  "features": [
    {
      "geometry": {
        "type": "Point",
        "coordinates": [
          28.091144,
          41.637244
        ]
      },
      "id": "darmc-location-958",
      "type": "Feature",
      "properties": {
        "description": "500K scale point location",
        "location_precision": "precise",
        "title": "DARMC location 958",
        "link": "http://pleiades.stoa.org/places/511404/darmc-location-958"
      }
    }
  ]
}