{
  "type": "FeatureCollection",
  "title": "‘Utsurgae’",
  "id": "511459",
  "description": "An ancient place, cited: BAtlas 52 B1 ‘Utsurgae’",
  "bbox": [
    27.8703,
    41.5136078,
    27.8761295,
    41.514964
  ],
  "reprPoint": [
    27.87321475,
    41.5142859
  ],
  "names": [
    "Utsurgae"
  ],
  "features": [
    {
      "geometry": {
        "type": "Point",
        "coordinates": [
          27.8703,
          41.514964
        ]
      },
      "id": "darmc-location-24478",
      "type": "Feature",
      "properties": {
        "description": "500K scale point location",
        "location_precision": "precise",
        "title": "DARMC location 24478",
        "link": "http://pleiades.stoa.org/places/511459/darmc-location-24478"
      }
    },
    {
      "geometry": {
        "type": "Point",
        "coordinates": [
          27.876129499999934,
          41.5136078
        ]
      },
      "id": "dare-location",
      "type": "Feature",
      "properties": {
        "description": "Representative point location, village precision",
        "location_precision": "precise",
        "title": "DARE Location",
        "link": "http://pleiades.stoa.org/places/511459/dare-location"
      }
    }
  ]
}