{
  "type": "FeatureCollection",
  "title": "Skylake",
  "id": "511419",
  "description": "An ancient place, cited: BAtlas 52 C4 Skylake",
  "bbox": [
    28.388808,
    40.387037,
    28.388808,
    40.387037
  ],
  "reprPoint": [
    28.388808,
    40.387037
  ],
  "names": [
    "Skylake"
  ],
  "features": [
    {
      "geometry": {
        "type": "Point",
        "coordinates": [
          28.388808,
          40.387037
        ]
      },
      "id": "darmc-location-24184",
      "type": "Feature",
      "properties": {
        "description": "500K scale point location",
        "location_precision": "precise",
        "title": "DARMC location 24184",
        "link": "http://pleiades.stoa.org/places/511419/darmc-location-24184"
      }
    }
  ]
}