{
  "type": "FeatureCollection",
  "title": "S. Autonomos, Mon.",
  "id": "511410",
  "description": "An ancient place, cited: BAtlas 52 F3 S. Autonomos, Mon.",
  "bbox": [
    29.658512,
    40.688842,
    29.658512,
    40.688842
  ],
  "reprPoint": [
    29.658512,
    40.688842
  ],
  "names": [
    "S. Autonomos, Mon.",
    "Soreoi"
  ],
  "features": [
    {
      "geometry": {
        "type": "Point",
        "coordinates": [
          29.658512,
          40.688842
        ]
      },
      "id": "darmc-location-24147",
      "type": "Feature",
      "properties": {
        "description": "500K scale point location",
        "location_precision": "precise",
        "title": "DARMC location 24147",
        "link": "http://pleiades.stoa.org/places/511410/darmc-location-24147"
      }
    }
  ]
}