{
  "type": "FeatureCollection",
  "title": "Thynias Pr.",
  "id": "511445",
  "bbox": [
    28.04554,
    41.87858,
    28.04554,
    41.87858
  ],
  "description": "An ancient place, cited: BAtlas 52 C1 Thynias Pr.",
  "names": [
    "Thynias Pr."
  ],
  "features": [
    {
      "type": "Feature",
      "geometry": {
        "type": "Point",
        "coordinates": [
          28.04554,
          41.87858
        ]
      },
      "properties": {
        "description": "representative point"
      }
    },
    {
      "geometry": {
        "type": "Point",
        "coordinates": [
          28.04554,
          41.87858
        ]
      },
      "id": "location-of-igneada-burnu",
      "type": "Feature",
      "properties": {
        "description": "coordinates after GeoNames.",
        "location_precision": "precise",
        "title": "GeoNames location of  İğneada Burnu (Cape Kuri)",
        "link": "http://pleiades.stoa.org/places/511445/location-of-igneada-burnu"
      }
    }
  ]
}