{
  "type": "FeatureCollection",
  "title": "Eildon Hill hill fort",
  "id": "511968273",
  "description": "Eildon Hill hill fort, a hill fort located on the northern peak of Eildon hill, is the largest Iron Age fort in Scotland, covering 39 acres.",
  "bbox": [
    -2.7079725,
    55.5869022,
    -2.7079725,
    55.5869022
  ],
  "reprPoint": [
    -2.7079725,
    55.5869022
  ],
  "features": [
    {
      "geometry": {
        "type": "Point",
        "coordinates": [
          -2.7079725,
          55.5869022
        ]
      },
      "id": "location-of-eildon-hill-hill-fort",
      "type": "Feature",
      "properties": {
        "description": "Location based on OpenStreetMap",
        "location_precision": "precise",
        "title": "location of Eildon Hill hill fort",
        "link": "http://pleiades.stoa.org/places/511968273/location-of-eildon-hill-hill-fort"
      }
    }
  ]
}