{
  "type": "FeatureCollection",
  "title": "Tell es-Sakan",
  "id": "513433066",
  "bbox": [
    34.404631,
    31.475817,
    34.404631,
    31.475817
  ],
  "description": "Tell es-Sakan is the site of an Egyptian and Canaanite maritime settlement located in what is now the Gaza Strip at the mouth of Wadi Ghazzeh.",
  "features": [
    {
      "type": "Feature",
      "geometry": {
        "type": "Point",
        "coordinates": [
          34.404631,
          31.475817
        ]
      },
      "properties": {
        "description": "representative point"
      }
    },
    {
      "geometry": {
        "type": "Point",
        "coordinates": [
          34.404631,
          31.475817
        ]
      },
      "id": "imagery-location-of-tell-el-sakan",
      "type": "Feature",
      "properties": {
        "description": "Imagery location based on coordinates derived from GeoHack.",
        "location_precision": "precise",
        "title": "Imagery location of Tell El Sakan",
        "link": "http://pleiades.stoa.org/places/513433066/imagery-location-of-tell-el-sakan"
      }
    }
  ]
}