{
  "type": "FeatureCollection",
  "title": "Körzüt (Arapzengi) Kalesi",
  "id": "514805005",
  "bbox": [
    43.7448027,
    38.9131265,
    43.7448027,
    38.9131265
  ],
  "description": "Körzüt is the modern Turkish name of an Urartean fortress situated on a rock spur at the southern end of the Muradiye/Berkri plain, about 3 km north of the modern village of Uluşar (Korsot/Gortsut), in the Muradiye district of Van province in Turkey. According to an inscription of the Urartean King Minua (9th / 8th century BCE), the fortress was built by Minua.",
  "connectsWith": [
    "214160492"
  ],
  "names": [
    "Körzüt Kale",
    "İşli Kalesi",
    "Kordzod Kalesi",
    "Korsot Kalesi",
    "Körzüt Kalesi",
    "Zengibar Kalesi",
    "Körzüt",
    "Korsot",
    "Gortsot",
    "Gortsut",
    "Arapzengi Kale",
    "Gortsot’ aberd"
  ],
  "features": [
    {
      "type": "Feature",
      "geometry": {
        "type": "Point",
        "coordinates": [
          43.7448027,
          38.9131265
        ]
      },
      "properties": {
        "description": "representative point"
      }
    },
    {
      "geometry": {
        "type": "Point",
        "coordinates": [
          43.7448027,
          38.9131265
        ]
      },
      "id": "osm-location-of-gortzot-castle",
      "type": "Feature",
      "properties": {
        "description": "Location based on OpenStreetMap",
        "location_precision": "precise",
        "title": "OSM Location of Gortzot' Castle",
        "link": "http://pleiades.stoa.org/places/514805005/osm-location-of-gortzot-castle"
      }
    }
  ]
}