{
  "type": "FeatureCollection",
  "title": "Horrea Galbana",
  "id": "51787061",
  "bbox": [
    12.4915967,
    41.8880884,
    12.491659,
    41.8881273
  ],
  "description": "Horrea (warehouses) located between the southern part of the Aventine Hill and Monte Testaccio.",
  "connectsWith": [
    "423025",
    "372769291",
    "277030428",
    "937921711"
  ],
  "features": [
    {
      "type": "Feature",
      "geometry": {
        "type": "Point",
        "coordinates": [
          12.4916274225,
          41.8881077401
        ]
      },
      "properties": {
        "description": "representative point"
      }
    }
  ]
}