{
  "type": "FeatureCollection",
  "title": "Ras ben Sakka",
  "id": "518430033",
  "bbox": [
    9.8368897,
    37.3381365,
    9.8368897,
    37.3381365
  ],
  "description": "The northernmost point of the continent of Africa.",
  "features": [
    {
      "type": "Feature",
      "geometry": {
        "type": "Point",
        "coordinates": [
          9.8368897,
          37.3381365
        ]
      },
      "properties": {
        "description": "representative point"
      }
    },
    {
      "geometry": {
        "type": "Point",
        "coordinates": [
          9.8368897,
          37.3381365
        ]
      },
      "id": "osm-location-of-ras-ben-sakka",
      "type": "Feature",
      "properties": {
        "description": "Location based on OpenStreetMap",
        "location_precision": "precise",
        "title": "OSM location of Ras ben Sakka",
        "link": "http://pleiades.stoa.org/places/518430033/osm-location-of-ras-ben-sakka"
      }
    }
  ]
}