{
  "type": "FeatureCollection",
  "title": "Ancyreum Pr.",
  "id": "520959",
  "bbox": [
    29.1654468,
    41.224459,
    29.1654468,
    41.224459
  ],
  "description": "An ancient place, cited: BAtlas 53 B2 Ancyreum Pr.",
  "names": [
    "Ancyreum Pr."
  ],
  "features": [
    {
      "type": "Feature",
      "geometry": {
        "type": "Point",
        "coordinates": [
          29.1654468,
          41.224459
        ]
      },
      "properties": {
        "description": "representative point"
      }
    },
    {
      "geometry": {
        "type": "Point",
        "coordinates": [
          29.1654468,
          41.224459
        ]
      },
      "id": "osm-location-of-yom-burnu",
      "type": "Feature",
      "properties": {
        "description": "Location based on OpenStreetMap",
        "location_precision": "precise",
        "title": "OSM location of Yom Burnu",
        "link": "http://pleiades.stoa.org/places/520959/osm-location-of-yom-burnu"
      }
    }
  ]
}