{
  "type": "FeatureCollection",
  "title": "Boradion",
  "id": "520976",
  "description": "An ancient place, cited: BAtlas 53 B2 Boradion",
  "bbox": [
    29.067899,
    41.102125,
    29.067899,
    41.102125
  ],
  "reprPoint": [
    29.067899,
    41.102125
  ],
  "names": [
    "Boradion"
  ],
  "features": [
    {
      "geometry": {
        "type": "Point",
        "coordinates": [
          29.067899,
          41.102125
        ]
      },
      "id": "darmc-location-24148",
      "type": "Feature",
      "properties": {
        "description": "150K scale point location",
        "location_precision": "precise",
        "title": "DARMC location 24148",
        "link": "http://pleiades.stoa.org/places/520976/darmc-location-24148"
      }
    }
  ]
}