{
  "type": "FeatureCollection",
  "title": "Byzantium",
  "id": "520985",
  "description": "An ancient place, cited: BAtlas 53 A2 Byzantium",
  "bbox": [
    28.970647,
    41.002009,
    28.977116,
    41.009795
  ],
  "reprPoint": [
    28.9738815,
    41.005902
  ],
  "names": [
    "Byzantium"
  ],
  "features": [
    {
      "geometry": {
        "type": "Point",
        "coordinates": [
          28.970647,
          41.009795
        ]
      },
      "id": "darmc-location-23977",
      "type": "Feature",
      "properties": {
        "description": "500K scale point location",
        "location_precision": "precise",
        "title": "DARMC location 23977",
        "link": "http://pleiades.stoa.org/places/520985/darmc-location-23977"
      }
    },
    {
      "geometry": {
        "type": "Point",
        "coordinates": [
          28.977116,
          41.002009
        ]
      },
      "id": "darmc-location-24604",
      "type": "Feature",
      "properties": {
        "description": "5M scale point location",
        "location_precision": "precise",
        "title": "DARMC location 24604",
        "link": "http://pleiades.stoa.org/places/520985/darmc-location-24604"
      }
    }
  ]
}