{
  "type": "FeatureCollection",
  "title": "Moukaporis",
  "id": "521087",
  "description": "An ancient place, cited: BAtlas 53 B2 Moukaporis",
  "bbox": [
    29.082421,
    41.138794,
    29.082421,
    41.138794
  ],
  "reprPoint": [
    29.082421,
    41.138794
  ],
  "names": [
    "Moukaporis"
  ],
  "features": [
    {
      "geometry": {
        "type": "Point",
        "coordinates": [
          29.082421,
          41.138794
        ]
      },
      "id": "darmc-location-24260",
      "type": "Feature",
      "properties": {
        "description": "150K scale point location",
        "location_precision": "precise",
        "title": "DARMC location 24260",
        "link": "http://pleiades.stoa.org/places/521087/darmc-location-24260"
      }
    }
  ]
}