{
  "type": "FeatureCollection",
  "title": "Nausimachion",
  "id": "521094",
  "description": "An ancient place, cited: BAtlas 53 B2 Nausimachion",
  "bbox": [
    29.053607,
    41.059363,
    29.053607,
    41.059363
  ],
  "reprPoint": [
    29.053607,
    41.059363
  ],
  "names": [
    "Nausimachion"
  ],
  "features": [
    {
      "geometry": {
        "type": "Point",
        "coordinates": [
          29.053607,
          41.059363
        ]
      },
      "id": "darmc-location-24173",
      "type": "Feature",
      "properties": {
        "description": "150K scale point location",
        "location_precision": "precise",
        "title": "DARMC location 24173",
        "link": "http://pleiades.stoa.org/places/521094/darmc-location-24173"
      }
    }
  ]
}