{
  "type": "FeatureCollection",
  "title": "Gomon?",
  "id": "521020",
  "bbox": [
    29.153392,
    41.216794,
    29.153392,
    41.216794
  ],
  "description": "An ancient place, cited: BAtlas 53 B2 Gomon?",
  "names": [
    "Gomon"
  ],
  "features": [
    {
      "type": "Feature",
      "geometry": {
        "type": "Point",
        "coordinates": [
          29.153392,
          41.216794
        ]
      },
      "properties": {
        "description": "representative point"
      }
    },
    {
      "geometry": {
        "type": "Point",
        "coordinates": [
          29.153392,
          41.216794
        ]
      },
      "id": "darmc-location-24155",
      "type": "Feature",
      "properties": {
        "description": "150K scale point location",
        "location_precision": "precise",
        "title": "DARMC location 24155",
        "link": "http://pleiades.stoa.org/places/521020/darmc-location-24155"
      }
    }
  ]
}