{
  "type": "FeatureCollection",
  "title": "Kepos",
  "id": "521056",
  "bbox": [
    28.953206,
    41.022065,
    28.953206,
    41.022065
  ],
  "description": "An ancient place, cited: BAtlas 53 A2 Kepos",
  "names": [
    "Kepos"
  ],
  "features": [
    {
      "type": "Feature",
      "geometry": {
        "type": "Point",
        "coordinates": [
          28.953206,
          41.022065
        ]
      },
      "properties": {
        "description": "representative point"
      }
    },
    {
      "geometry": {
        "type": "Point",
        "coordinates": [
          28.953206,
          41.022065
        ]
      },
      "id": "darmc-location-5459",
      "type": "Feature",
      "properties": {
        "description": "1:150,000 scale representative point location digitized from the Barrington Atlas of the Greek and Roman World by the Digital Atlas of Roman and Medieval Civilizations project at Harvard University.",
        "location_precision": "precise",
        "title": "DARMC location 5459",
        "link": "http://pleiades.stoa.org/places/521056/darmc-location-5459"
      }
    }
  ]
}