{
  "type": "FeatureCollection",
  "title": "Pege",
  "id": "521111",
  "description": "An ancient place, cited: BAtlas 53 A3 Pege",
  "bbox": [
    28.915896,
    40.999905,
    28.915896,
    40.999905
  ],
  "reprPoint": [
    28.915896,
    40.999905
  ],
  "names": [
    "Pege"
  ],
  "features": [
    {
      "geometry": {
        "type": "Point",
        "coordinates": [
          28.915896,
          40.999905
        ]
      },
      "id": "darmc-location-5119",
      "type": "Feature",
      "properties": {
        "description": "150K scale point location",
        "location_precision": "precise",
        "title": "DARMC location 5119",
        "link": "http://pleiades.stoa.org/places/521111/darmc-location-5119"
      }
    }
  ]
}