{
  "type": "FeatureCollection",
  "title": "Parabolos",
  "id": "521108",
  "description": "An ancient place, cited: BAtlas 53 B2 Parabolos",
  "bbox": [
    29.030439,
    41.052491,
    29.030439,
    41.052491
  ],
  "reprPoint": [
    29.030439,
    41.052491
  ],
  "names": [
    "Parabolos"
  ],
  "features": [
    {
      "geometry": {
        "type": "Point",
        "coordinates": [
          29.030439,
          41.052491
        ]
      },
      "id": "darmc-location-24176",
      "type": "Feature",
      "properties": {
        "description": "150K scale point location",
        "location_precision": "precise",
        "title": "DARMC location 24176",
        "link": "http://pleiades.stoa.org/places/521108/darmc-location-24176"
      }
    }
  ]
}