{
  "type": "FeatureCollection",
  "title": "Poleatikon",
  "id": "521124",
  "description": "An ancient place, cited: BAtlas 53 B3 Poleatikon",
  "bbox": [
    29.088941,
    40.956377,
    29.088941,
    40.956377
  ],
  "reprPoint": [
    29.088941,
    40.956377
  ],
  "names": [
    "Poleatikon"
  ],
  "features": [
    {
      "geometry": {
        "type": "Point",
        "coordinates": [
          29.088941,
          40.956377
        ]
      },
      "id": "darmc-location-24122",
      "type": "Feature",
      "properties": {
        "description": "150K scale point location",
        "location_precision": "precise",
        "title": "DARMC location 24122",
        "link": "http://pleiades.stoa.org/places/521124/darmc-location-24122"
      }
    }
  ]
}