{
  "type": "FeatureCollection",
  "title": "Neorion",
  "id": "523226",
  "bbox": [
    28.975,
    41.016667,
    28.975,
    41.016667
  ],
  "description": "Neorion Harbor was a harbor of Constantinople in use from the fourth century until the late Ottoman period.",
  "connectsWith": [
    "520998"
  ],
  "names": [
    "Neorion"
  ],
  "features": [
    {
      "type": "Feature",
      "geometry": {
        "type": "Point",
        "coordinates": [
          28.975,
          41.016667
        ]
      },
      "properties": {
        "description": "representative point"
      }
    },
    {
      "geometry": {
        "type": "Point",
        "coordinates": [
          28.975,
          41.016667
        ]
      },
      "id": "imagery-location-of-neorion-harbour",
      "type": "Feature",
      "properties": {
        "description": "Coordinates following GeoHack.",
        "location_precision": "precise",
        "title": "Imagery location of Neorion Harbour",
        "link": "http://pleiades.stoa.org/places/523226/imagery-location-of-neorion-harbour"
      }
    }
  ]
}