{
  "type": "FeatureCollection",
  "title": "Sarmizegetusa Roman amphitheater",
  "id": "524360868",
  "bbox": [
    22.7853206,
    45.5166773,
    22.7853206,
    45.5166773
  ],
  "description": "The Roman amphitheater at Colonia Ulpia Traiana Augusta Dacica Sarmizegetusa was built in A.D. 108/110 and renovated in 158 under the legio IV Flavia Felix",
  "connectsWith": [
    "207527"
  ],
  "features": [
    {
      "type": "Feature",
      "geometry": {
        "type": "Point",
        "coordinates": [
          22.7853206,
          45.5166773
        ]
      },
      "properties": {
        "description": "representative point"
      }
    },
    {
      "geometry": {
        "type": "Point",
        "coordinates": [
          22.7853206,
          45.5166773
        ]
      },
      "id": "location-of-roman-amphitheater",
      "type": "Feature",
      "properties": {
        "description": "Location based on OpenStreetMap",
        "location_precision": "precise",
        "title": "OSM location of Amphiteater of Samizegetusa Ulpia Traiana",
        "link": "http://pleiades.stoa.org/places/524360868/location-of-roman-amphitheater"
      }
    }
  ]
}