{
  "type": "FeatureCollection",
  "title": "Roman Amphitheater at Mérida",
  "id": "525258361",
  "bbox": [
    -6.337954,
    38.916073,
    -6.337954,
    38.916073
  ],
  "description": "The Amphitheatre of Mérida was inaugurated in 8 B.C.",
  "connectsWith": [
    "256155"
  ],
  "features": [
    {
      "type": "Feature",
      "geometry": {
        "type": "Point",
        "coordinates": [
          -6.337954,
          38.916073
        ]
      },
      "properties": {
        "description": "representative point"
      }
    },
    {
      "geometry": {
        "type": "Point",
        "coordinates": [
          -6.337954,
          38.916073
        ]
      },
      "id": "centerpoint-of-the-roman-amphitheater-at-merida",
      "type": "Feature",
      "properties": {
        "description": "Digitized in Google Earth in July 2012 at an eye height of 600m.",
        "location_precision": "precise",
        "title": "Centerpoint of the Roman Amphitheater at Mérida",
        "link": "http://pleiades.stoa.org/places/525258361/centerpoint-of-the-roman-amphitheater-at-merida"
      }
    }
  ]
}