{
  "type": "FeatureCollection",
  "title": "Qermez Dere",
  "id": "52599409",
  "bbox": [
    42.8332907,
    36.5169445,
    42.8332907,
    36.5169445
  ],
  "description": "A tell located in Tal Afar in Nineveh Governorate, Iraq, that was the site of a Neolithic settlement established ca. 8500-7900 BCE. Neolithic roundhouses were documented at the site.",
  "names": [
    "Qermez Dere"
  ],
  "features": [
    {
      "type": "Feature",
      "geometry": {
        "type": "Point",
        "coordinates": [
          42.8332907,
          36.5169445
        ]
      },
      "properties": {
        "description": "representative point"
      }
    },
    {
      "geometry": {
        "type": "Point",
        "coordinates": [
          42.8332907,
          36.5169445
        ]
      },
      "id": "osm-location-of-qermez-dere",
      "type": "Feature",
      "properties": {
        "description": "Representative location based on OpenStreetMap",
        "location_precision": "precise",
        "title": "OSM location of Qermez Dere",
        "link": "http://pleiades.stoa.org/places/52599409/osm-location-of-qermez-dere"
      }
    }
  ]
}