{
  "type": "FeatureCollection",
  "title": "Theater of Melos",
  "id": "528335956",
  "bbox": [
    24.4210603,
    36.7379722,
    24.4210603,
    36.7379722
  ],
  "description": "The Theater of Melos likely has Hellenistic origins but the visible phase belongs to the Roman period.",
  "connectsWith": [
    "570474"
  ],
  "features": [
    {
      "type": "Feature",
      "geometry": {
        "type": "Point",
        "coordinates": [
          24.4210603,
          36.7379722
        ]
      },
      "properties": {
        "description": "representative point"
      }
    },
    {
      "geometry": {
        "type": "Point",
        "coordinates": [
          24.4210603,
          36.7379722
        ]
      },
      "id": "osm-location-of-theater",
      "type": "Feature",
      "properties": {
        "description": "Location based on OpenStreetMap",
        "location_precision": "precise",
        "title": "OSM location of theater",
        "link": "http://pleiades.stoa.org/places/528335956/osm-location-of-theater"
      }
    }
  ]
}