{
  "type": "FeatureCollection",
  "title": "S. Costanza",
  "id": "528606605",
  "description": "A fourth century AD structure along the Via Nomentana that was built by Constantine I as a mausoleum, originally housing the remains of his daughters Constantina and Helena. It was dedicated as a Christian church in the Middle Ages.",
  "bbox": [
    12.517375,
    41.922614,
    12.517375,
    41.922614
  ],
  "connectsWith": [
    "423035",
    "699256589"
  ],
  "reprPoint": [
    12.517375,
    41.922614
  ],
  "features": [
    {
      "geometry": {
        "type": "Point",
        "coordinates": [
          12.517375,
          41.922614
        ]
      },
      "id": "location-of-s.-costanza",
      "type": "Feature",
      "properties": {
        "description": "verified in Google Earth 2012",
        "location_precision": "precise",
        "title": "location of S. Costanza",
        "link": "http://pleiades.stoa.org/places/528606605/location-of-s.-costanza"
      }
    }
  ]
}