{
  "type": "FeatureCollection",
  "title": "Aurelian Walls",
  "id": "529700371",
  "bbox": [
    12.486137,
    41.891775,
    12.486137,
    41.891775
  ],
  "description": "The Aurelian Walls of Rome began as a fortification system built by Aurelian and Probus between 271 and 275. They enclose an area of approximately 1,400 hectares.",
  "connectsWith": [
    "423025",
    "423025"
  ],
  "names": [
    "Aurelianische Mauer",
    "Mura Aureliane",
    "Aurelian Walls"
  ],
  "features": [
    {
      "type": "Feature",
      "geometry": {
        "type": "Point",
        "coordinates": [
          12.486137,
          41.891775
        ]
      },
      "properties": {
        "description": "representative point"
      }
    }
  ]
}