{
  "type": "FeatureCollection",
  "title": "Torre di Donoratico",
  "id": "530611411",
  "bbox": [
    10.586207,
    43.1456301,
    10.586207,
    43.1456301
  ],
  "description": "An Etrusco-Roman fortified hilltop settlement that later served as a fortress of the Della Gherardesca family from the twelfth to the fifteenth centuries.",
  "features": [
    {
      "type": "Feature",
      "geometry": {
        "type": "Point",
        "coordinates": [
          10.586207,
          43.1456301
        ]
      },
      "properties": {
        "description": "representative point"
      }
    },
    {
      "geometry": {
        "type": "Point",
        "coordinates": [
          10.586207,
          43.1456301
        ]
      },
      "id": "location-of-torre-di-donoratico",
      "type": "Feature",
      "properties": {
        "description": "Representative location based on OpenStreetMap.",
        "location_precision": "precise",
        "title": "OSM location of Torre di Donoratico",
        "link": "http://pleiades.stoa.org/places/530611411/location-of-torre-di-donoratico"
      }
    }
  ]
}