{
  "type": "FeatureCollection",
  "title": "Ambracia",
  "id": "530794",
  "description": "Ambracia (modern Arta) was an ancient city of central Greece, founded as a colony of Corinth in the seventh century BC. It was located near the Ambracian Gulf along the course of the river Arachthos.",
  "bbox": [
    20.989927,
    39.154973,
    20.989927,
    39.154973
  ],
  "connectsWith": [
    "530807"
  ],
  "reprPoint": [
    20.989927,
    39.154973
  ],
  "names": [
    "Ambracia"
  ],
  "features": [
    {
      "geometry": {
        "type": "Point",
        "coordinates": [
          20.990258,
          39.154876
        ]
      },
      "id": "darmc-location-2756",
      "type": "Feature",
      "properties": {
        "description": "500K scale point location",
        "location_precision": "precise",
        "title": "DARMC location 2756",
        "link": "http://pleiades.stoa.org/places/530794/darmc-location-2756"
      }
    },
    {
      "geometry": {
        "type": "Point",
        "coordinates": [
          20.989927,
          39.154973
        ]
      },
      "id": "dare-location",
      "type": "Feature",
      "properties": {
        "description": "Representative point location, village precision",
        "location_precision": "precise",
        "title": "DARE Location",
        "link": "http://pleiades.stoa.org/places/530794/dare-location"
      }
    }
  ]
}