{
  "type": "FeatureCollection",
  "title": "Ag. Pandeleimona",
  "id": "530780",
  "bbox": [
    21.1001582,
    38.4895005,
    21.1001582,
    38.4895005
  ],
  "description": "An ancient place, cited: BAtlas 54 D5 Ag. Pandeleimona",
  "features": [
    {
      "type": "Feature",
      "geometry": {
        "type": "Point",
        "coordinates": [
          21.1001582,
          38.4895005
        ]
      },
      "properties": {
        "description": "representative point"
      }
    },
    {
      "geometry": {
        "type": "Point",
        "coordinates": [
          21.1001582,
          38.4895005
        ]
      },
      "id": "osm-location-of-iioiiii-i-i-iiii-i-i-i-ii-ii-i-i-i",
      "type": "Feature",
      "properties": {
        "description": "Representative location based on OpenStreetMap",
        "location_precision": "precise",
        "title": "OSM location of Ακρόπολη Αρχαίας Μάραθου-Κάστρο Αγίου Παντελεήμονος",
        "link": "http://pleiades.stoa.org/places/530780/osm-location-of-iioiiii-i-i-iiii-i-i-i-ii-ii-i-i-i"
      }
    }
  ]
}