{
  "type": "FeatureCollection",
  "title": "Ag. Pandeleimona",
  "id": "530780",
  "description": "An ancient place, cited: BAtlas 54 D5 Ag. Pandeleimona",
  "bbox": [
    21.104241,
    38.488218,
    21.104241,
    38.488218
  ],
  "reprPoint": [
    21.104241,
    38.488218
  ],
  "features": [
    {
      "geometry": {
        "type": "Point",
        "coordinates": [
          21.104241,
          38.488218
        ]
      },
      "id": "darmc-location-21203",
      "type": "Feature",
      "properties": {
        "description": "500K scale point location",
        "location_precision": "precise",
        "title": "DARMC location 21203",
        "link": "http://pleiades.stoa.org/places/530780/darmc-location-21203"
      }
    }
  ]
}