{
  "type": "FeatureCollection",
  "title": "Agriliais",
  "id": "530785",
  "description": "An ancient place, cited: BAtlas 54 D3 Agriliais",
  "bbox": [
    21.113298,
    39.045531,
    21.113298,
    39.045531
  ],
  "reprPoint": [
    21.113298,
    39.045531
  ],
  "features": [
    {
      "geometry": {
        "type": "Point",
        "coordinates": [
          21.113298,
          39.045531
        ]
      },
      "id": "darmc-location-6930",
      "type": "Feature",
      "properties": {
        "description": "500K scale point location",
        "location_precision": "precise",
        "title": "DARMC location 6930",
        "link": "http://pleiades.stoa.org/places/530785/darmc-location-6930"
      }
    }
  ]
}