{
  "type": "FeatureCollection",
  "title": "Ambracia",
  "id": "530794",
  "bbox": [
    20.989927,
    39.154876,
    20.990258,
    39.154973
  ],
  "description": "Ambracia (modern Arta) was an ancient city of central Greece, founded as a colony of Corinth in the seventh century BC. It was located near the Ambracian Gulf along the course of the river Arachthos.",
  "connectsWith": [
    "530807",
    "104777481"
  ],
  "names": [
    "Ambracia",
    "Ambrakía"
  ],
  "features": [
    {
      "type": "Feature",
      "geometry": {
        "type": "Point",
        "coordinates": [
          20.9900925,
          39.1549245
        ]
      },
      "properties": {
        "description": "representative point"
      }
    },
    {
      "geometry": {
        "type": "Point",
        "coordinates": [
          20.990258,
          39.154876
        ]
      },
      "id": "darmc-location-2756",
      "type": "Feature",
      "properties": {
        "description": "1:500,000 scale representative point location digitized from the Barrington Atlas of the Greek and Roman World by the Digital Atlas of Roman and Medieval Civilizations project at Harvard University.",
        "location_precision": "precise",
        "title": "DARMC location 2756",
        "link": "http://pleiades.stoa.org/places/530794/darmc-location-2756"
      }
    },
    {
      "geometry": {
        "type": "Point",
        "coordinates": [
          20.989927,
          39.154973
        ]
      },
      "id": "dare-location",
      "type": "Feature",
      "properties": {
        "description": "Representative point location, village precision",
        "location_precision": "precise",
        "title": "DARE Location",
        "link": "http://pleiades.stoa.org/places/530794/dare-location"
      }
    }
  ]
}