{
  "type": "FeatureCollection",
  "title": "Agia",
  "id": "530773",
  "description": "An ancient place, cited: BAtlas 54 B3 Agia",
  "bbox": [
    20.361723,
    39.319652,
    20.361723,
    39.319652
  ],
  "reprPoint": [
    20.361723,
    39.319652
  ],
  "features": [
    {
      "geometry": {
        "type": "Point",
        "coordinates": [
          20.361723,
          39.319652
        ]
      },
      "id": "darmc-location-11212",
      "type": "Feature",
      "properties": {
        "description": "500K scale point location",
        "location_precision": "precise",
        "title": "DARMC location 11212",
        "link": "http://pleiades.stoa.org/places/530773/darmc-location-11212"
      }
    }
  ]
}