{
  "type": "FeatureCollection",
  "title": "Hellomenon",
  "id": "530888",
  "description": "An ancient place, cited: BAtlas 54 C4 Hellomenon",
  "bbox": [
    20.713062,
    38.713327,
    20.713062,
    38.713327
  ],
  "reprPoint": [
    20.713062,
    38.713327
  ],
  "names": [
    "Hellomenon"
  ],
  "features": [
    {
      "geometry": {
        "type": "Point",
        "coordinates": [
          20.713062,
          38.713327
        ]
      },
      "id": "darmc-location-10066",
      "type": "Feature",
      "properties": {
        "description": "500K scale point location",
        "location_precision": "precise",
        "title": "DARMC location 10066",
        "link": "http://pleiades.stoa.org/places/530888/darmc-location-10066"
      }
    }
  ]
}