{
  "type": "FeatureCollection",
  "title": "Astakos",
  "id": "530815",
  "bbox": [
    21.087253,
    38.547154,
    21.087253,
    38.547154
  ],
  "description": "An ancient place, cited: BAtlas 54 D4 Astakos",
  "names": [
    "Astakos"
  ],
  "features": [
    {
      "type": "Feature",
      "geometry": {
        "type": "Point",
        "coordinates": [
          21.087253,
          38.547154
        ]
      },
      "properties": {
        "description": "representative point"
      }
    },
    {
      "geometry": {
        "type": "Point",
        "coordinates": [
          21.087253,
          38.547154
        ]
      },
      "id": "darmc-location-226",
      "type": "Feature",
      "properties": {
        "description": "500K scale point location",
        "location_precision": "precise",
        "title": "DARMC location 226",
        "link": "http://pleiades.stoa.org/places/530815/darmc-location-226"
      }
    }
  ]
}