{
  "type": "FeatureCollection",
  "title": "Eurymenai?",
  "id": "530875",
  "description": "An ancient place, cited: BAtlas 54 C2 Eurymenai?",
  "bbox": [
    20.919605,
    39.630469,
    20.919605,
    39.630469
  ],
  "reprPoint": [
    20.919605,
    39.630469
  ],
  "names": [
    "Eurymenai"
  ],
  "features": [
    {
      "geometry": {
        "type": "Point",
        "coordinates": [
          20.919605,
          39.630469
        ]
      },
      "id": "darmc-location-3461",
      "type": "Feature",
      "properties": {
        "description": "500K scale point location",
        "location_precision": "precise",
        "title": "DARMC location 3461",
        "link": "http://pleiades.stoa.org/places/530875/darmc-location-3461"
      }
    }
  ]
}