{
  "type": "FeatureCollection",
  "title": "Aphionas",
  "id": "530805",
  "description": "An ancient place, cited: BAtlas 54 A2 Aphionas",
  "bbox": [
    19.659501,
    39.722713,
    19.659501,
    39.722713
  ],
  "reprPoint": [
    19.659501,
    39.722713
  ],
  "features": [
    {
      "geometry": {
        "type": "Point",
        "coordinates": [
          19.659501,
          39.722713
        ]
      },
      "id": "darmc-location-6227",
      "type": "Feature",
      "properties": {
        "description": "500K scale point location",
        "location_precision": "precise",
        "title": "DARMC location 6227",
        "link": "http://pleiades.stoa.org/places/530805/darmc-location-6227"
      }
    }
  ]
}