{
  "type": "FeatureCollection",
  "title": "Astakos (Acarnania)",
  "id": "530815",
  "bbox": [
    21.091351,
    38.554367,
    21.091351,
    38.554367
  ],
  "description": "An ancient city of Acarnania, established in the 5th century BCE, the site of Astakos lies approximately 2 kilometers north of the modern town that now bears its name. Ancient Astakos was succeeded in Byzantine times by a settlement named Dragamestos.",
  "connectsWith": [
    "231467659"
  ],
  "names": [
    "Astakos"
  ],
  "features": [
    {
      "type": "Feature",
      "geometry": {
        "type": "Point",
        "coordinates": [
          21.091351,
          38.554367
        ]
      },
      "properties": {
        "description": "representative point"
      }
    },
    {
      "geometry": {
        "type": "Point",
        "coordinates": [
          21.091351,
          38.554367
        ]
      },
      "id": "vici-org-location",
      "type": "Feature",
      "properties": {
        "description": "Dates after BAtlas",
        "location_precision": "precise",
        "title": "Vici.org location",
        "link": "http://pleiades.stoa.org/places/530815/vici-org-location"
      }
    }
  ]
}