{
  "type": "FeatureCollection",
  "title": "Idomene Minor",
  "id": "530896",
  "description": "An ancient place, cited: BAtlas 54 D3 Idomene Minor",
  "bbox": [
    21.109679,
    39.065432,
    21.109679,
    39.065432
  ],
  "reprPoint": [
    21.109679,
    39.065432
  ],
  "names": [
    "Idomene Minor"
  ],
  "features": [
    {
      "geometry": {
        "type": "Point",
        "coordinates": [
          21.109679,
          39.065432
        ]
      },
      "id": "darmc-location-16011",
      "type": "Feature",
      "properties": {
        "description": "500K scale point location",
        "location_precision": "precise",
        "title": "DARMC location 16011",
        "link": "http://pleiades.stoa.org/places/530896/darmc-location-16011"
      }
    }
  ]
}