{
  "type": "FeatureCollection",
  "title": "Dhrovian",
  "id": "530841",
  "description": "An ancient place, cited: BAtlas 54 B2 Dhrovian",
  "bbox": [
    20.229012,
    39.879185,
    20.229012,
    39.879185
  ],
  "reprPoint": [
    20.229012,
    39.879185
  ],
  "features": [
    {
      "geometry": {
        "type": "Point",
        "coordinates": [
          20.229012,
          39.879185
        ]
      },
      "id": "darmc-location-12193",
      "type": "Feature",
      "properties": {
        "description": "500K scale point location",
        "location_precision": "precise",
        "title": "DARMC location 12193",
        "link": "http://pleiades.stoa.org/places/530841/darmc-location-12193"
      }
    }
  ]
}