{
  "type": "FeatureCollection",
  "title": "Hani Emin Aga",
  "id": "530886",
  "bbox": [
    20.888847,
    39.45253,
    20.888847,
    39.45253
  ],
  "description": "An ancient place, cited: BAtlas 54 C3 Hani Emin Aga",
  "features": [
    {
      "type": "Feature",
      "geometry": {
        "type": "Point",
        "coordinates": [
          20.888847,
          39.45253
        ]
      },
      "properties": {
        "description": "representative point"
      }
    },
    {
      "geometry": {
        "type": "Point",
        "coordinates": [
          20.888847,
          39.45253
        ]
      },
      "id": "darmc-location-12671",
      "type": "Feature",
      "properties": {
        "description": "500K scale point location",
        "location_precision": "precise",
        "title": "DARMC location 12671",
        "link": "http://pleiades.stoa.org/places/530886/darmc-location-12671"
      }
    }
  ]
}