{
  "type": "FeatureCollection",
  "title": "Gourgiana",
  "id": "530880",
  "description": "An ancient place, cited: BAtlas 54 D3 Gourgiana",
  "bbox": [
    21.050759,
    39.417125,
    21.050759,
    39.417125
  ],
  "reprPoint": [
    21.050759,
    39.417125
  ],
  "features": [
    {
      "geometry": {
        "type": "Point",
        "coordinates": [
          21.050759,
          39.417125
        ]
      },
      "id": "darmc-location-12594",
      "type": "Feature",
      "properties": {
        "description": "500K scale point location",
        "location_precision": "precise",
        "title": "DARMC location 12594",
        "link": "http://pleiades.stoa.org/places/530880/darmc-location-12594"
      }
    }
  ]
}