{
  "type": "FeatureCollection",
  "title": "Çuke",
  "id": "530837",
  "description": "An ancient place, cited: BAtlas 54 B2 Çuke",
  "bbox": [
    20.032029,
    39.843709,
    20.032029,
    39.843709
  ],
  "reprPoint": [
    20.032029,
    39.843709
  ],
  "features": [
    {
      "geometry": {
        "type": "Point",
        "coordinates": [
          20.032029,
          39.843709
        ]
      },
      "id": "darmc-location-7609",
      "type": "Feature",
      "properties": {
        "description": "500K scale point location",
        "location_precision": "precise",
        "title": "DARMC location 7609",
        "link": "http://pleiades.stoa.org/places/530837/darmc-location-7609"
      }
    }
  ]
}