{
  "type": "FeatureCollection",
  "title": "Elleniko Stathmo",
  "id": "530867",
  "description": "An ancient place, cited: BAtlas 54 D2 Elleniko Stathmo",
  "bbox": [
    21.36832,
    39.767797,
    21.36832,
    39.767797
  ],
  "reprPoint": [
    21.36832,
    39.767797
  ],
  "features": [
    {
      "geometry": {
        "type": "Point",
        "coordinates": [
          21.36832,
          39.767797
        ]
      },
      "id": "darmc-location-17714",
      "type": "Feature",
      "properties": {
        "description": "500K scale point location",
        "location_precision": "precise",
        "title": "DARMC location 17714",
        "link": "http://pleiades.stoa.org/places/530867/darmc-location-17714"
      }
    }
  ]
}