{
  "type": "FeatureCollection",
  "title": "Klisia",
  "id": "530953",
  "description": "An ancient place, cited: BAtlas 54 B2 Klisia",
  "bbox": [
    20.263142,
    39.581075,
    20.263142,
    39.581075
  ],
  "reprPoint": [
    20.263142,
    39.581075
  ],
  "features": [
    {
      "geometry": {
        "type": "Point",
        "coordinates": [
          20.263142,
          39.581075
        ]
      },
      "id": "darmc-location-13211",
      "type": "Feature",
      "properties": {
        "description": "500K scale point location",
        "location_precision": "precise",
        "title": "DARMC location 13211",
        "link": "http://pleiades.stoa.org/places/530953/darmc-location-13211"
      }
    }
  ]
}