{
  "type": "FeatureCollection",
  "title": "Kalokhori",
  "id": "530913",
  "description": "An ancient place, cited: BAtlas 54 C2 Kalokhori",
  "bbox": [
    20.619736,
    39.687207,
    20.619736,
    39.687207
  ],
  "reprPoint": [
    20.619736,
    39.687207
  ],
  "features": [
    {
      "geometry": {
        "type": "Point",
        "coordinates": [
          20.619736,
          39.687207
        ]
      },
      "id": "darmc-location-7863",
      "type": "Feature",
      "properties": {
        "description": "500K scale point location",
        "location_precision": "precise",
        "title": "DARMC location 7863",
        "link": "http://pleiades.stoa.org/places/530913/darmc-location-7863"
      }
    }
  ]
}