{
  "type": "FeatureCollection",
  "title": "Istone (mountain)",
  "id": "530904",
  "bbox": [
    19.88117,
    39.54997,
    19.88117,
    39.54997
  ],
  "description": "A mountain mentioned in ancient sources, probably Ag. Deka (central Kerkyra).",
  "names": [
    "Agioi Deka",
    "Istone"
  ],
  "features": [
    {
      "type": "Feature",
      "geometry": {
        "type": "Point",
        "coordinates": [
          19.88117,
          39.54997
        ]
      },
      "properties": {
        "description": "representative point"
      }
    },
    {
      "geometry": {
        "type": "Point",
        "coordinates": [
          19.88117,
          39.54997
        ]
      },
      "id": "geonames-location-of-agioi-deka",
      "type": "Feature",
      "properties": {
        "description": null,
        "location_precision": "precise",
        "title": "GeoNames location of Agioi Deka",
        "link": "http://pleiades.stoa.org/places/530904/geonames-location-of-agioi-deka"
      }
    }
  ]
}