{
  "type": "FeatureCollection",
  "title": "Konitsa",
  "id": "530958",
  "description": "An ancient place, cited: BAtlas 54 C1 Konitsa",
  "bbox": [
    20.784467,
    40.038066,
    20.784467,
    40.038066
  ],
  "reprPoint": [
    20.784467,
    40.038066
  ],
  "features": [
    {
      "geometry": {
        "type": "Point",
        "coordinates": [
          20.784467,
          40.038066
        ]
      },
      "id": "darmc-location-2379",
      "type": "Feature",
      "properties": {
        "description": "500K scale point location",
        "location_precision": "precise",
        "title": "DARMC location 2379",
        "link": "http://pleiades.stoa.org/places/530958/darmc-location-2379"
      }
    }
  ]
}