{
  "type": "FeatureCollection",
  "title": "Pirgos (Kakavoula)",
  "id": "530909",
  "bbox": [
    20.8849,
    38.7985,
    20.8849,
    38.7985
  ],
  "description": "A small, rectangular fortress on a raised terrace of land, located near the, possibly earlier, Xylokastro fortification on Mt. Plakoto in the modern municipal unit of Palairos, Aetolia-Acarnania Regional Unit, Greece.",
  "names": [
    "Kakavoula",
    "Pirgos"
  ],
  "features": [
    {
      "type": "Feature",
      "geometry": {
        "type": "Point",
        "coordinates": [
          20.8849,
          38.7985
        ]
      },
      "properties": {
        "description": "representative point"
      }
    },
    {
      "geometry": {
        "type": "Point",
        "coordinates": [
          20.8849,
          38.7985
        ]
      },
      "id": "imagery-location-of-fort",
      "type": "Feature",
      "properties": {
        "description": "Dates after BAtlas.",
        "location_precision": "precise",
        "title": "Imagery location of fort",
        "link": "http://pleiades.stoa.org/places/530909/imagery-location-of-fort"
      }
    }
  ]
}