{
  "type": "FeatureCollection",
  "title": "Kraneia?",
  "id": "530963",
  "description": "An ancient place, cited: BAtlas 54 D3 Kraneia?",
  "bbox": [
    21.065383,
    39.068263,
    21.362948,
    39.434531
  ],
  "reprPoint": [
    21.2141655,
    39.251397
  ],
  "names": [
    "Kraneia"
  ],
  "features": [
    {
      "geometry": {
        "type": "Point",
        "coordinates": [
          21.065383,
          39.068263
        ]
      },
      "id": "darmc-location-13301",
      "type": "Feature",
      "properties": {
        "description": "500K scale point location",
        "location_precision": "precise",
        "title": "DARMC location 13301",
        "link": "http://pleiades.stoa.org/places/530963/darmc-location-13301"
      }
    },
    {
      "geometry": {
        "type": "Point",
        "coordinates": [
          21.362948,
          39.434531
        ]
      },
      "id": "darmc-location-10107",
      "type": "Feature",
      "properties": {
        "description": "TIB point location",
        "location_precision": "precise",
        "title": "DARMC location 10107",
        "link": "http://pleiades.stoa.org/places/530963/darmc-location-10107"
      }
    }
  ]
}