{
  "type": "FeatureCollection",
  "title": "Kato Aetos",
  "id": "530934",
  "description": "An ancient place, cited: BAtlas 54 B2 Kato Aetos",
  "bbox": [
    20.062502,
    39.69003,
    20.062502,
    39.69003
  ],
  "reprPoint": [
    20.062502,
    39.69003
  ],
  "features": [
    {
      "geometry": {
        "type": "Point",
        "coordinates": [
          20.062502,
          39.69003
        ]
      },
      "id": "darmc-location-13061",
      "type": "Feature",
      "properties": {
        "description": "500K scale point location",
        "location_precision": "precise",
        "title": "DARMC location 13061",
        "link": "http://pleiades.stoa.org/places/530934/darmc-location-13061"
      }
    }
  ]
}