{
  "type": "FeatureCollection",
  "title": "Kheimadio",
  "id": "530943",
  "bbox": [
    20.600136,
    39.167565,
    20.600136,
    39.167565
  ],
  "description": "An ancient place, cited: BAtlas 54 C3 Kheimadio",
  "features": [
    {
      "type": "Feature",
      "geometry": {
        "type": "Point",
        "coordinates": [
          20.600136,
          39.167565
        ]
      },
      "properties": {
        "description": "representative point"
      }
    },
    {
      "geometry": {
        "type": "Point",
        "coordinates": [
          20.600136,
          39.167565
        ]
      },
      "id": "darmc-location-23154",
      "type": "Feature",
      "properties": {
        "description": "500K scale point location",
        "location_precision": "precise",
        "title": "DARMC location 23154",
        "link": "http://pleiades.stoa.org/places/530943/darmc-location-23154"
      }
    }
  ]
}