{
  "type": "FeatureCollection",
  "title": "Kakavoula",
  "id": "530909",
  "description": "An ancient place, cited: BAtlas 54 C4 Kakavoula",
  "bbox": [
    20.888008,
    38.796196,
    20.888008,
    38.796196
  ],
  "reprPoint": [
    20.888008,
    38.796196
  ],
  "features": [
    {
      "geometry": {
        "type": "Point",
        "coordinates": [
          20.888008,
          38.796196
        ]
      },
      "id": "darmc-location-7857",
      "type": "Feature",
      "properties": {
        "description": "500K scale point location",
        "location_precision": "precise",
        "title": "DARMC location 7857",
        "link": "http://pleiades.stoa.org/places/530909/darmc-location-7857"
      }
    }
  ]
}