{
  "type": "FeatureCollection",
  "title": "Kerentza",
  "id": "530940",
  "bbox": [
    20.481674,
    39.22853,
    20.481674,
    39.22853
  ],
  "description": "An ancient place, cited: BAtlas 54 B3 Kerentza",
  "features": [
    {
      "type": "Feature",
      "geometry": {
        "type": "Point",
        "coordinates": [
          20.481674,
          39.22853
        ]
      },
      "properties": {
        "description": "representative point"
      }
    },
    {
      "geometry": {
        "type": "Point",
        "coordinates": [
          20.481674,
          39.22853
        ]
      },
      "id": "darmc-location-13113",
      "type": "Feature",
      "properties": {
        "description": "500K scale point location",
        "location_precision": "precise",
        "title": "DARMC location 13113",
        "link": "http://pleiades.stoa.org/places/530940/darmc-location-13113"
      }
    }
  ]
}