{
  "type": "FeatureCollection",
  "title": "Malçan",
  "id": "530991",
  "bbox": [
    20.228664,
    39.800466,
    20.228664,
    39.800466
  ],
  "description": "An ancient place, cited: BAtlas 54 B2 Malçan",
  "features": [
    {
      "type": "Feature",
      "geometry": {
        "type": "Point",
        "coordinates": [
          20.228664,
          39.800466
        ]
      },
      "properties": {
        "description": "representative point"
      }
    },
    {
      "geometry": {
        "type": "Point",
        "coordinates": [
          20.228664,
          39.800466
        ]
      },
      "id": "darmc-location-13603",
      "type": "Feature",
      "properties": {
        "description": "500K scale point location",
        "location_precision": "precise",
        "title": "DARMC location 13603",
        "link": "http://pleiades.stoa.org/places/530991/darmc-location-13603"
      }
    }
  ]
}