{
  "type": "FeatureCollection",
  "title": "Mandrotopos",
  "id": "530992",
  "description": "An ancient place, cited: BAtlas 54 C3 Mandrotopos",
  "bbox": [
    20.57344,
    39.348824,
    20.57344,
    39.348824
  ],
  "reprPoint": [
    20.57344,
    39.348824
  ],
  "features": [
    {
      "geometry": {
        "type": "Point",
        "coordinates": [
          20.57344,
          39.348824
        ]
      },
      "id": "darmc-location-13618",
      "type": "Feature",
      "properties": {
        "description": "500K scale point location",
        "location_precision": "precise",
        "title": "DARMC location 13618",
        "link": "http://pleiades.stoa.org/places/530992/darmc-location-13618"
      }
    }
  ]
}