{
  "type": "FeatureCollection",
  "title": "Palaiokhori",
  "id": "531032",
  "bbox": [
    20.69393,
    39.33883,
    20.69393,
    39.33883
  ],
  "description": "An ancient place, cited: BAtlas 54 C3 Palaiokhori",
  "features": [
    {
      "type": "Feature",
      "geometry": {
        "type": "Point",
        "coordinates": [
          20.69393,
          39.33883
        ]
      },
      "properties": {
        "description": "representative point"
      }
    },
    {
      "geometry": {
        "type": "Point",
        "coordinates": [
          20.69393,
          39.33883
        ]
      },
      "id": "darmc-location-24088",
      "type": "Feature",
      "properties": {
        "description": "500K scale point location",
        "location_precision": "precise",
        "title": "DARMC location 24088",
        "link": "http://pleiades.stoa.org/places/531032/darmc-location-24088"
      }
    }
  ]
}