{
  "type": "FeatureCollection",
  "title": "Rakhi",
  "id": "531084",
  "bbox": [
    20.671114,
    38.204279,
    20.671114,
    38.204279
  ],
  "description": "An ancient place, cited: BAtlas 54 C5 Rakhi",
  "features": [
    {
      "type": "Feature",
      "geometry": {
        "type": "Point",
        "coordinates": [
          20.671114,
          38.204279
        ]
      },
      "properties": {
        "description": "representative point"
      }
    },
    {
      "geometry": {
        "type": "Point",
        "coordinates": [
          20.671114,
          38.204279
        ]
      },
      "id": "darmc-location-8227",
      "type": "Feature",
      "properties": {
        "description": "500K scale point location",
        "location_precision": "precise",
        "title": "DARMC location 8227",
        "link": "http://pleiades.stoa.org/places/531084/darmc-location-8227"
      }
    }
  ]
}