{
  "type": "FeatureCollection",
  "title": "Sistrouni",
  "id": "531098",
  "description": "An ancient place, cited: BAtlas 54 C3 Sistrouni",
  "bbox": [
    20.691569,
    39.42261,
    20.691569,
    39.42261
  ],
  "reprPoint": [
    20.691569,
    39.42261
  ],
  "features": [
    {
      "geometry": {
        "type": "Point",
        "coordinates": [
          20.691569,
          39.42261
        ]
      },
      "id": "darmc-location-14777",
      "type": "Feature",
      "properties": {
        "description": "500K scale point location",
        "location_precision": "precise",
        "title": "DARMC location 14777",
        "link": "http://pleiades.stoa.org/places/531098/darmc-location-14777"
      }
    }
  ]
}