{
  "type": "FeatureCollection",
  "title": "Paramythia",
  "id": "531044",
  "description": "An ancient place, cited: BAtlas 54 C3 Paramythia",
  "bbox": [
    20.519535,
    39.472868,
    20.524652,
    39.478243
  ],
  "reprPoint": [
    20.5220935,
    39.4755555
  ],
  "features": [
    {
      "geometry": {
        "type": "Point",
        "coordinates": [
          20.524652,
          39.478243
        ]
      },
      "id": "darmc-location-14136",
      "type": "Feature",
      "properties": {
        "description": "500K scale point location",
        "location_precision": "precise",
        "title": "DARMC location 14136",
        "link": "http://pleiades.stoa.org/places/531044/darmc-location-14136"
      }
    },
    {
      "geometry": {
        "type": "Point",
        "coordinates": [
          20.519535,
          39.472868
        ]
      },
      "id": "dare-location",
      "type": "Feature",
      "properties": {
        "description": "Representative point location, site precision",
        "location_precision": "precise",
        "title": "DARE Location",
        "link": "http://pleiades.stoa.org/places/531044/dare-location"
      }
    }
  ]
}