{
  "type": "FeatureCollection",
  "title": "Stratos",
  "id": "531104",
  "bbox": [
    21.319477,
    38.671727,
    21.319477,
    38.671727
  ],
  "description": "Stratos was the chief town of Acarnania. Modern Sourovigli in Greece.",
  "connectsWith": [
    "530767",
    "231467659"
  ],
  "names": [
    "Stratos",
    "Stratike"
  ],
  "features": [
    {
      "type": "Feature",
      "geometry": {
        "type": "Point",
        "coordinates": [
          21.319477,
          38.671727
        ]
      },
      "properties": {
        "description": "representative point"
      }
    },
    {
      "geometry": {
        "type": "Point",
        "coordinates": [
          21.319477,
          38.671727
        ]
      },
      "id": "dare-location",
      "type": "Feature",
      "properties": {
        "description": "Representative point location, site precision",
        "location_precision": "precise",
        "title": "DARE Location",
        "link": "http://pleiades.stoa.org/places/531104/dare-location"
      }
    }
  ]
}