{
  "type": "FeatureCollection",
  "title": "Torybeia?",
  "id": "531126",
  "description": "An ancient place, cited: BAtlas 54 D4 Torybeia?",
  "bbox": [
    21.06285,
    38.763022,
    21.06285,
    38.763022
  ],
  "reprPoint": [
    21.06285,
    38.763022
  ],
  "names": [
    "Torybeia",
    "Tyrbeion"
  ],
  "features": [
    {
      "geometry": {
        "type": "Point",
        "coordinates": [
          21.06285,
          38.763022
        ]
      },
      "id": "darmc-location-15223",
      "type": "Feature",
      "properties": {
        "description": "500K scale point location",
        "location_precision": "precise",
        "title": "DARMC location 15223",
        "link": "http://pleiades.stoa.org/places/531126/darmc-location-15223"
      }
    }
  ]
}