{
  "type": "FeatureCollection",
  "title": "Xylokastro (Palairos)",
  "id": "531152",
  "bbox": [
    20.8968,
    38.7942,
    20.8968,
    38.7942
  ],
  "description": "An ancient fort, also known today as Kastri, located on a spur of Mt. Plakoto above a small chapel of Agios Athanasios in the municipal unit of Palairos, Aetolia-Acarnania Regional Unit, Greece.",
  "features": [
    {
      "type": "Feature",
      "geometry": {
        "type": "Point",
        "coordinates": [
          20.8968,
          38.7942
        ]
      },
      "properties": {
        "description": "representative point"
      }
    },
    {
      "geometry": {
        "type": "Point",
        "coordinates": [
          20.8968,
          38.7942
        ]
      },
      "id": "imagery-location-of-kastri",
      "type": "Feature",
      "properties": {
        "description": "Dates after BAtlas.",
        "location_precision": "precise",
        "title": "Imagery location of Kastri",
        "link": "http://pleiades.stoa.org/places/531152/imagery-location-of-kastri"
      }
    }
  ]
}