{
  "type": "FeatureCollection",
  "title": "Xylokastro 2",
  "id": "531152",
  "bbox": [
    20.949391,
    38.641286,
    20.949391,
    38.641286
  ],
  "description": "An ancient place, cited: BAtlas 54 C4 Xylokastro 2",
  "connectsWith": [
    "530917"
  ],
  "features": [
    {
      "type": "Feature",
      "geometry": {
        "type": "Point",
        "coordinates": [
          20.949391,
          38.641286
        ]
      },
      "properties": {
        "description": "representative point"
      }
    },
    {
      "geometry": {
        "type": "Point",
        "coordinates": [
          20.949391,
          38.641286
        ]
      },
      "id": "darmc-location-8454",
      "type": "Feature",
      "properties": {
        "description": "500K scale point location",
        "location_precision": "precise",
        "title": "DARMC location 8454",
        "link": "http://pleiades.stoa.org/places/531152/darmc-location-8454"
      }
    }
  ]
}