{
  "type": "FeatureCollection",
  "title": "Vereniki",
  "id": "531140",
  "bbox": [
    20.542235,
    39.562855,
    20.542235,
    39.562855
  ],
  "description": "An ancient place, cited: BAtlas 54 C2 Vereniki",
  "features": [
    {
      "type": "Feature",
      "geometry": {
        "type": "Point",
        "coordinates": [
          20.542235,
          39.562855
        ]
      },
      "properties": {
        "description": "representative point"
      }
    },
    {
      "geometry": {
        "type": "Point",
        "coordinates": [
          20.542235,
          39.562855
        ]
      },
      "id": "darmc-location-15373",
      "type": "Feature",
      "properties": {
        "description": "500K scale point location",
        "location_precision": "precise",
        "title": "DARMC location 15373",
        "link": "http://pleiades.stoa.org/places/531140/darmc-location-15373"
      }
    }
  ]
}