{
  "type": "FeatureCollection",
  "title": "Tourka",
  "id": "531129",
  "description": "An ancient place, cited: BAtlas 54 D3 Tourka",
  "bbox": [
    21.243904,
    39.024201,
    21.243904,
    39.024201
  ],
  "reprPoint": [
    21.243904,
    39.024201
  ],
  "features": [
    {
      "geometry": {
        "type": "Point",
        "coordinates": [
          21.243904,
          39.024201
        ]
      },
      "id": "darmc-location-15230",
      "type": "Feature",
      "properties": {
        "description": "500K scale point location",
        "location_precision": "precise",
        "title": "DARMC location 15230",
        "link": "http://pleiades.stoa.org/places/531129/darmc-location-15230"
      }
    }
  ]
}