{
  "type": "FeatureCollection",
  "title": "T(o)maros (mountain)",
  "id": "531124",
  "bbox": [
    20.791,
    39.488,
    20.791,
    39.488
  ],
  "description": "An ancient place, cited: BAtlas 54 C2 T(o)maros M.",
  "connectsWith": [
    "531117",
    "531003"
  ],
  "names": [
    "Olytsikas",
    "Oros Tomaros",
    "Tomaros",
    "Tmaros"
  ],
  "features": [
    {
      "type": "Feature",
      "geometry": {
        "type": "Point",
        "coordinates": [
          20.791,
          39.488
        ]
      },
      "properties": {
        "description": "representative point"
      }
    },
    {
      "geometry": {
        "type": "Point",
        "coordinates": [
          20.791,
          39.488
        ]
      },
      "id": "imagery-location-of-tomaros",
      "type": "Feature",
      "properties": {
        "description": "Coordinates following GeoHack.",
        "location_precision": "precise",
        "title": "Imagery location of Tomaros",
        "link": "http://pleiades.stoa.org/places/531124/imagery-location-of-tomaros"
      }
    }
  ]
}