{
  "type": "FeatureCollection",
  "title": "Stratos",
  "id": "531104",
  "description": "Stratos was the chief town of Acarnania. Modern Sourovigli in Greece.",
  "bbox": [
    21.319477,
    38.671727,
    21.319477,
    38.671727
  ],
  "connectsWith": [
    "530767"
  ],
  "reprPoint": [
    21.319477,
    38.671727
  ],
  "names": [
    "Stratos",
    "Stratike"
  ],
  "features": [
    {
      "geometry": {
        "type": "Point",
        "coordinates": [
          21.3195523,
          38.6720964
        ]
      },
      "id": "location-of-ancient-theater",
      "type": "Feature",
      "properties": {
        "description": "Location based on OpenStreetMap",
        "location_precision": "precise",
        "title": "location of ancient theater",
        "link": "http://pleiades.stoa.org/places/531104/location-of-ancient-theater"
      }
    },
    {
      "geometry": {
        "type": "Point",
        "coordinates": [
          21.316272,
          38.672848
        ]
      },
      "id": "darmc-location-6090",
      "type": "Feature",
      "properties": {
        "description": "500K scale point location",
        "location_precision": "precise",
        "title": "DARMC location 6090",
        "link": "http://pleiades.stoa.org/places/531104/darmc-location-6090"
      }
    },
    {
      "geometry": {
        "type": "Point",
        "coordinates": [
          21.319477,
          38.671727
        ]
      },
      "id": "dare-location",
      "type": "Feature",
      "properties": {
        "description": "Representative point location, site precision",
        "location_precision": "precise",
        "title": "DARE Location",
        "link": "http://pleiades.stoa.org/places/531104/dare-location"
      }
    }
  ]
}