{
  "type": "FeatureCollection",
  "title": "tribus Ramnes",
  "id": "531536067",
  "bbox": [
    12.486137,
    41.891775,
    12.486137,
    41.891775
  ],
  "description": "The name of a Roman tribe dating from the earliest period of Roman history.",
  "connectsWith": [
    "423025"
  ],
  "names": [
    "Ramnes"
  ],
  "features": [
    {
      "type": "Feature",
      "geometry": {
        "type": "Point",
        "coordinates": [
          12.486137,
          41.891775
        ]
      },
      "properties": {
        "description": "representative point"
      }
    }
  ]
}