{
  "type": "FeatureCollection",
  "title": "Ponte Corvo",
  "id": "532772123",
  "bbox": [
    11.8837853,
    45.4016924,
    11.8837853,
    45.4016924
  ],
  "description": "A Roman segmental arch bridge across the Bacchiglione river in Padua, Italy.",
  "connectsWith": [
    "393473",
    "393505"
  ],
  "features": [
    {
      "type": "Feature",
      "geometry": {
        "type": "Point",
        "coordinates": [
          11.8837853,
          45.4016924
        ]
      },
      "properties": {
        "description": "representative point"
      }
    },
    {
      "geometry": {
        "type": "Point",
        "coordinates": [
          11.8837853,
          45.4016924
        ]
      },
      "id": "osm-location",
      "type": "Feature",
      "properties": {
        "description": "Representative location based on OpenStreetMap.",
        "location_precision": "precise",
        "title": "OSM location of Ponte Corvo",
        "link": "http://pleiades.stoa.org/places/532772123/osm-location"
      }
    }
  ]
}