{
  "type": "FeatureCollection",
  "title": "Gaziantep",
  "id": "534964140",
  "bbox": [
    37.3793085,
    37.0611756,
    37.3793085,
    37.0611756
  ],
  "description": "Gaziantep, also referred to as Antep, is located in southeastern Turkey. The site has a long history of settlement that begins in the Neolithic period. The site has a significant Hittite presence. Some scholars suggest it is the site of the Hellenistic city of Antiochia ad Taurum.",
  "names": [
    "Gaziantep",
    "Ayntap",
    "Gaziantep",
    "ʿAintāb",
    "Hamtab",
    "ʿAin Ṭāb",
    "ʿAinṭāb",
    "ʿAıntāb",
    "Ayıntap",
    "ʿAnṭāb",
    "ʿAyntab"
  ],
  "features": [
    {
      "type": "Feature",
      "geometry": {
        "type": "Point",
        "coordinates": [
          37.3793085,
          37.0611756
        ]
      },
      "properties": {
        "description": "representative point"
      }
    },
    {
      "geometry": {
        "type": "Point",
        "coordinates": [
          37.3793085,
          37.0611756
        ]
      },
      "id": "osm-location-of-gaziantep",
      "type": "Feature",
      "properties": {
        "description": "Location based on OpenStreetMap",
        "location_precision": "precise",
        "title": "OSM location of Gaziantep",
        "link": "http://pleiades.stoa.org/places/534964140/osm-location-of-gaziantep"
      }
    }
  ]
}