{
  "type": "FeatureCollection",
  "title": "Gallo-Roman temple at Nasium",
  "id": "534922362",
  "bbox": [
    5.386586,
    48.632434,
    5.386586,
    48.632434
  ],
  "description": "Archaeological remains of the Gallo-Roman temple at ancient Nasium, located at Mazeroie, commune Naix-aux-Forges",
  "connectsWith": [
    "109190"
  ],
  "features": [
    {
      "type": "Feature",
      "geometry": {
        "type": "Point",
        "coordinates": [
          5.386586,
          48.632434
        ]
      },
      "properties": {
        "description": "representative point"
      }
    },
    {
      "geometry": {
        "type": "Point",
        "coordinates": [
          5.386586,
          48.632434
        ]
      },
      "id": "imagery-location",
      "type": "Feature",
      "properties": {
        "description": "Archaeological remains of the Gallo-Roman temple at ancient Nasium, located at Mazeroie, commune Naix-aux-Forges",
        "location_precision": "precise",
        "title": "Imagery Location of Gallo-Roman temple",
        "link": "http://pleiades.stoa.org/places/534922362/imagery-location"
      }
    }
  ]
}