{
  "type": "FeatureCollection",
  "title": "Tap o' Noth hill fort",
  "id": "535189143",
  "bbox": [
    -2.8589566,
    57.3512795,
    -2.8589566,
    57.3512795
  ],
  "description": "Tap o' Noth hill fort is located in Aberdeenshire, Scotland; a well preserved vitrified wall survives at the site.",
  "features": [
    {
      "type": "Feature",
      "geometry": {
        "type": "Point",
        "coordinates": [
          -2.8589566,
          57.3512795
        ]
      },
      "properties": {
        "description": "representative point"
      }
    },
    {
      "geometry": {
        "type": "Point",
        "coordinates": [
          -2.8589566,
          57.3512795
        ]
      },
      "id": "location-of-tap-o-noth-hill-fort",
      "type": "Feature",
      "properties": {
        "description": "Location based on OpenStreetMap",
        "location_precision": "precise",
        "title": "location of Tap o' Noth hill fort",
        "link": "http://pleiades.stoa.org/places/535189143/location-of-tap-o-noth-hill-fort"
      }
    }
  ]
}