{
  "type": "FeatureCollection",
  "title": "Flag Fen",
  "id": "535275912",
  "bbox": [
    -0.1894608,
    52.5747722,
    -0.1894608,
    52.5747722
  ],
  "description": "Flag Fen is a Bronze Age ritual site near Peterborough, England, comprised of 60,000 timbers arranged in five rows that connect Whittlesey Island with Peterborough. Dendrochronological evidence has dates the site to ca. 1365–967 BC.",
  "features": [
    {
      "type": "Feature",
      "geometry": {
        "type": "Point",
        "coordinates": [
          -0.1894608,
          52.5747722
        ]
      },
      "properties": {
        "description": "representative point"
      }
    },
    {
      "geometry": {
        "type": "Point",
        "coordinates": [
          -0.1894608,
          52.5747722
        ]
      },
      "id": "location-of-flag-fen",
      "type": "Feature",
      "properties": {
        "description": "Representative location based on OpenStreetMap.",
        "location_precision": "precise",
        "title": "OSM location of Flag Fen",
        "link": "http://pleiades.stoa.org/places/535275912/location-of-flag-fen"
      }
    }
  ]
}