{
  "type": "FeatureCollection",
  "title": "Dam over the Simbruina Stagna",
  "id": "535279839",
  "description": "Between Sublaqueum and Villa Neronis",
  "bbox": [
    13.108406,
    41.921048,
    13.108406,
    41.921048
  ],
  "reprPoint": [
    13.108406,
    41.921048
  ],
  "features": [
    {
      "geometry": {
        "type": "Point",
        "coordinates": [
          13.108406,
          41.921048
        ]
      },
      "id": "darmc-location-33168",
      "type": "Feature",
      "properties": {
        "description": "scale point location",
        "location_precision": "precise",
        "title": "DARMC location 33168",
        "link": "http://pleiades.stoa.org/places/535279839/darmc-location-33168"
      }
    }
  ]
}