{
  "type": "FeatureCollection",
  "title": "Cheddar Gorge",
  "id": "535275913",
  "description": "The Cheddar Gorge is a limestone gorge in the Mendip Hills, near Somerset, England. The gorge and its many caves are the site of human activity dating back to the Upper Paleolithic.",
  "bbox": [
    -2.7543895,
    51.2857067,
    -2.7543895,
    51.2857067
  ],
  "reprPoint": [
    -2.7543895,
    51.2857067
  ],
  "features": [
    {
      "geometry": {
        "type": "Point",
        "coordinates": [
          -2.7543895,
          51.2857067
        ]
      },
      "id": "location-of-cheddar-gorge",
      "type": "Feature",
      "properties": {
        "description": "Representative location based on OpenStreetMap.",
        "location_precision": "precise",
        "title": "OSM location of Cheddar Gorge",
        "link": "http://pleiades.stoa.org/places/535275913/location-of-cheddar-gorge"
      }
    }
  ]
}