{
  "type": "FeatureCollection",
  "title": "Ag. Vasileios",
  "id": "540598",
  "description": "An ancient place, cited: BAtlas 55 E3 Ag. Vasileios",
  "bbox": [
    23.444345,
    38.939931,
    23.444345,
    38.939931
  ],
  "reprPoint": [
    23.444345,
    38.939931
  ],
  "features": [
    {
      "geometry": {
        "type": "Point",
        "coordinates": [
          23.444345,
          38.939931
        ]
      },
      "id": "darmc-location-1979",
      "type": "Feature",
      "properties": {
        "description": "500K scale point location",
        "location_precision": "precise",
        "title": "DARMC location 1979",
        "link": "http://pleiades.stoa.org/places/540598/darmc-location-1979"
      }
    }
  ]
}