{
  "type": "FeatureCollection",
  "title": "Ag. Athanasios",
  "id": "540592",
  "description": "An ancient place, cited: BAtlas 55 E2 Ag. Athanasios",
  "bbox": [
    23.445931,
    39.196184,
    23.445931,
    39.196184
  ],
  "reprPoint": [
    23.445931,
    39.196184
  ],
  "features": [
    {
      "geometry": {
        "type": "Point",
        "coordinates": [
          23.445931,
          39.196184
        ]
      },
      "id": "darmc-location-2293",
      "type": "Feature",
      "properties": {
        "description": "500K scale point location",
        "location_precision": "precise",
        "title": "DARMC location 2293",
        "link": "http://pleiades.stoa.org/places/540592/darmc-location-2293"
      }
    }
  ]
}