{
  "type": "FeatureCollection",
  "title": "Apollo, T.",
  "id": "540651",
  "bbox": [
    23.805061,
    38.585065,
    23.805061,
    38.585065
  ],
  "description": "An ancient place, cited: BAtlas 55 F3 Apollo, T.",
  "names": [
    "Apollo, T."
  ],
  "features": [
    {
      "type": "Feature",
      "geometry": {
        "type": "Point",
        "coordinates": [
          23.805061,
          38.585065
        ]
      },
      "properties": {
        "description": "representative point"
      }
    },
    {
      "geometry": {
        "type": "Point",
        "coordinates": [
          23.805061,
          38.585065
        ]
      },
      "id": "darmc-location-6564",
      "type": "Feature",
      "properties": {
        "description": "500K scale point location",
        "location_precision": "precise",
        "title": "DARMC location 6564",
        "link": "http://pleiades.stoa.org/places/540651/darmc-location-6564"
      }
    }
  ]
}