{
  "type": "FeatureCollection",
  "title": "Anchoe",
  "id": "540635",
  "bbox": [
    23.289105,
    38.541481,
    23.289105,
    38.541481
  ],
  "description": "An ancient place, cited: BAtlas 55 E3 Anchoe",
  "names": [
    "Anchoe"
  ],
  "features": [
    {
      "type": "Feature",
      "geometry": {
        "type": "Point",
        "coordinates": [
          23.289105,
          38.541481
        ]
      },
      "properties": {
        "description": "representative point"
      }
    },
    {
      "geometry": {
        "type": "Point",
        "coordinates": [
          23.289105,
          38.541481
        ]
      },
      "id": "darmc-location-11383",
      "type": "Feature",
      "properties": {
        "description": "1:500,000 scale representative point location digitized from the Barrington Atlas of the Greek and Roman World by the Digital Atlas of Roman and Medieval Civilizations project at Harvard University.",
        "location_precision": "precise",
        "title": "DARMC location 11383",
        "link": "http://pleiades.stoa.org/places/540635/darmc-location-11383"
      }
    }
  ]
}