{
  "type": "FeatureCollection",
  "title": "Artemision",
  "id": "540667",
  "bbox": [
    23.220954,
    39.010259,
    23.221797,
    39.017832
  ],
  "description": "An ancient place, cited: BAtlas 55 E2 Artemision",
  "names": [
    "Artemision",
    "Oritanum"
  ],
  "features": [
    {
      "type": "Feature",
      "geometry": {
        "type": "Point",
        "coordinates": [
          23.2213755,
          39.0140455
        ]
      },
      "properties": {
        "description": "representative point"
      }
    },
    {
      "geometry": {
        "type": "Point",
        "coordinates": [
          23.221797,
          39.010259
        ]
      },
      "id": "darmc-location-6603",
      "type": "Feature",
      "properties": {
        "description": "1:500,000 scale representative point location digitized from the Barrington Atlas of the Greek and Roman World by the Digital Atlas of Roman and Medieval Civilizations project at Harvard University.",
        "location_precision": "precise",
        "title": "DARMC location 6603",
        "link": "http://pleiades.stoa.org/places/540667/darmc-location-6603"
      }
    },
    {
      "geometry": {
        "type": "Point",
        "coordinates": [
          23.220954,
          39.017832
        ]
      },
      "id": "dare-location",
      "type": "Feature",
      "properties": {
        "description": "Representative point location, village precision",
        "location_precision": "precise",
        "title": "DARE Location",
        "link": "http://pleiades.stoa.org/places/540667/dare-location"
      }
    }
  ]
}