{
  "type": "FeatureCollection",
  "title": "Asterion/Peirasia",
  "id": "540674",
  "description": "An ancient place, cited: BAtlas 55 C2 Asterion/Peirasia",
  "bbox": [
    22.075579,
    39.483438,
    22.228649,
    39.513608
  ],
  "reprPoint": [
    22.152114,
    39.498523
  ],
  "names": [
    "Asterion",
    "Peirasia"
  ],
  "features": [
    {
      "geometry": {
        "type": "Point",
        "coordinates": [
          22.075579,
          39.513608
        ]
      },
      "id": "darmc-location-11081",
      "type": "Feature",
      "properties": {
        "description": "TIB point location",
        "location_precision": "precise",
        "title": "DARMC location 11081",
        "link": "http://pleiades.stoa.org/places/540674/darmc-location-11081"
      }
    },
    {
      "geometry": {
        "type": "Point",
        "coordinates": [
          22.228649,
          39.483438
        ]
      },
      "id": "darmc-location-11544",
      "type": "Feature",
      "properties": {
        "description": "500K scale point location",
        "location_precision": "precise",
        "title": "DARMC location 11544",
        "link": "http://pleiades.stoa.org/places/540674/darmc-location-11544"
      }
    }
  ]
}