{
  "type": "FeatureCollection",
  "title": "Antirrhion Pr.",
  "id": "540643",
  "bbox": [
    21.7658,
    38.327,
    21.7658,
    38.327
  ],
  "description": "An ancient place, cited: BAtlas 55 B4 Antirrhion Pr.",
  "names": [
    "Antirrhion Pr."
  ],
  "features": [
    {
      "type": "Feature",
      "geometry": {
        "type": "Point",
        "coordinates": [
          21.7658,
          38.327
        ]
      },
      "properties": {
        "description": "representative point"
      }
    },
    {
      "geometry": {
        "type": "Point",
        "coordinates": [
          21.7658,
          38.327
        ]
      },
      "id": "location-of-antirrhion-pr",
      "type": "Feature",
      "properties": {
        "description": "checked in Google Earth 2013 based on Barrington Atlas position.",
        "location_precision": "precise",
        "title": "location of Antirrhion Pr.",
        "link": "http://pleiades.stoa.org/places/540643/location-of-antirrhion-pr"
      }
    }
  ]
}