{
  "type": "FeatureCollection",
  "title": "Akrai?",
  "id": "540616",
  "bbox": [
    21.582132,
    38.503566,
    21.582132,
    38.503566
  ],
  "description": "An ancient place, cited: BAtlas 55 B3 Akrai?",
  "names": [
    "Akrai"
  ],
  "features": [
    {
      "type": "Feature",
      "geometry": {
        "type": "Point",
        "coordinates": [
          21.582132,
          38.503566
        ]
      },
      "properties": {
        "description": "representative point"
      }
    },
    {
      "geometry": {
        "type": "Point",
        "coordinates": [
          21.582132,
          38.503566
        ]
      },
      "id": "darmc-location-1074",
      "type": "Feature",
      "properties": {
        "description": "1:500,000 scale representative point location digitized from the Barrington Atlas of the Greek and Roman World by the Digital Atlas of Roman and Medieval Civilizations project at Harvard University.",
        "location_precision": "precise",
        "title": "DARMC location 1074",
        "link": "http://pleiades.stoa.org/places/540616/darmc-location-1074"
      }
    }
  ]
}