{
  "type": "FeatureCollection",
  "title": "Sanctuary of Athena Itonia",
  "id": "540677",
  "bbox": [
    22.050757,
    39.261841,
    22.058297,
    39.276634
  ],
  "description": "A pan-thessaliote sanctuary, located at modern Philia Karditsis in Greece.",
  "names": [
    "Itonion"
  ],
  "features": [
    {
      "type": "Feature",
      "geometry": {
        "type": "Point",
        "coordinates": [
          22.054527,
          39.2692375
        ]
      },
      "properties": {
        "description": "representative point"
      }
    },
    {
      "geometry": {
        "type": "Point",
        "coordinates": [
          22.058297,
          39.276634
        ]
      },
      "id": "darmc-location-6608",
      "type": "Feature",
      "properties": {
        "description": "500K scale point location",
        "location_precision": "precise",
        "title": "DARMC location 6608",
        "link": "http://pleiades.stoa.org/places/540677/darmc-location-6608"
      }
    },
    {
      "geometry": {
        "type": "Point",
        "coordinates": [
          22.050757,
          39.261841
        ]
      },
      "id": "visible-remains-of-sanctuary-of-athena-itonia",
      "type": "Feature",
      "properties": {
        "description": "Pan-thessaliote sanctuary, excavated by Theocharis, Pilali-Papasteriou, Papaefthymiou-Papanthimou and Intzesiloglou.",
        "location_precision": "precise",
        "title": "Visible Remains of Sanctuary of Athena Itonia",
        "link": "http://pleiades.stoa.org/places/540677/visible-remains-of-sanctuary-of-athena-itonia"
      }
    }
  ]
}