{
  "type": "FeatureCollection",
  "title": "Dionysos, T.",
  "id": "540735",
  "bbox": [
    22.953174,
    38.523684,
    22.953174,
    38.523684
  ],
  "description": "An ancient place, cited: BAtlas 55 D3 Dionysos, T.",
  "names": [
    "Dionysos, T."
  ],
  "features": [
    {
      "type": "Feature",
      "geometry": {
        "type": "Point",
        "coordinates": [
          22.953174,
          38.523684
        ]
      },
      "properties": {
        "description": "representative point"
      }
    },
    {
      "geometry": {
        "type": "Point",
        "coordinates": [
          22.953174,
          38.523684
        ]
      },
      "id": "darmc-location-6626",
      "type": "Feature",
      "properties": {
        "description": "500K scale point location",
        "location_precision": "precise",
        "title": "DARMC location 6626",
        "link": "http://pleiades.stoa.org/places/540735/darmc-location-6626"
      }
    }
  ]
}