{
  "type": "FeatureCollection",
  "title": "Gonnoi",
  "id": "540793",
  "bbox": [
    22.474276,
    39.856046,
    22.522,
    39.861822
  ],
  "description": "An ancient place, cited: BAtlas 55 C1 Gonnoi",
  "names": [
    "Gonnoi"
  ],
  "features": [
    {
      "type": "Feature",
      "geometry": {
        "type": "Point",
        "coordinates": [
          22.498138,
          39.858934
        ]
      },
      "properties": {
        "description": "representative point"
      }
    },
    {
      "geometry": {
        "type": "Point",
        "coordinates": [
          22.474276,
          39.861822
        ]
      },
      "id": "darmc-location-92",
      "type": "Feature",
      "properties": {
        "description": "TIB representative point location digitized from the Barrington Atlas of the Greek and Roman World by the Digital Atlas of Roman and Medieval Civilizations project at Harvard University.",
        "location_precision": "precise",
        "title": "DARMC location 92",
        "link": "http://pleiades.stoa.org/places/540793/darmc-location-92"
      }
    },
    {
      "geometry": {
        "type": "Point",
        "coordinates": [
          22.522,
          39.856046
        ]
      },
      "id": "darmc-location-12579",
      "type": "Feature",
      "properties": {
        "description": "1:500,000 scale representative point location digitized from the Barrington Atlas of the Greek and Roman World by the Digital Atlas of Roman and Medieval Civilizations project at Harvard University.",
        "location_precision": "precise",
        "title": "DARMC location 12579",
        "link": "http://pleiades.stoa.org/places/540793/darmc-location-12579"
      }
    }
  ]
}