{
  "type": "FeatureCollection",
  "title": "Chalia",
  "id": "540705",
  "bbox": [
    23.570797,
    38.487562,
    23.570797,
    38.487562
  ],
  "description": "Theopompus mentions Chalia as a town of Boeotia. It is also attested epigraphically and may have been a member of the Boeotian league.",
  "names": [
    "Chalia"
  ],
  "features": [
    {
      "type": "Feature",
      "geometry": {
        "type": "Point",
        "coordinates": [
          23.570797,
          38.487562
        ]
      },
      "properties": {
        "description": "representative point"
      }
    },
    {
      "geometry": {
        "type": "Point",
        "coordinates": [
          23.570797,
          38.487562
        ]
      },
      "id": "darmc-location-11976",
      "type": "Feature",
      "properties": {
        "description": "500K scale point location",
        "location_precision": "precise",
        "title": "DARMC location 11976",
        "link": "http://pleiades.stoa.org/places/540705/darmc-location-11976"
      }
    }
  ]
}