{
  "type": "FeatureCollection",
  "title": "Eilesion",
  "id": "540750",
  "description": "A city of southeast Boeotia mentioned by Homer.",
  "bbox": [
    23.507886,
    38.307788,
    23.507886,
    38.307788
  ],
  "reprPoint": [
    23.507886,
    38.307788
  ],
  "names": [
    "Eilesion",
    "Eilésion"
  ],
  "features": [
    {
      "geometry": {
        "type": "Point",
        "coordinates": [
          23.507886,
          38.307788
        ]
      },
      "id": "darmc-location-12303",
      "type": "Feature",
      "properties": {
        "description": "500K scale point location",
        "location_precision": "precise",
        "title": "DARMC location 12303",
        "link": "http://pleiades.stoa.org/places/540750/darmc-location-12303"
      }
    }
  ]
}