{
  "type": "FeatureCollection",
  "title": "Erineos",
  "id": "540769",
  "bbox": [
    22.415737,
    38.694365,
    22.415737,
    38.694365
  ],
  "description": "An ancient place, cited: BAtlas 55 C3 Erineos",
  "connectsWith": [
    "540740"
  ],
  "names": [
    "Erineos"
  ],
  "features": [
    {
      "type": "Feature",
      "geometry": {
        "type": "Point",
        "coordinates": [
          22.415737,
          38.694365
        ]
      },
      "properties": {
        "description": "representative point"
      }
    },
    {
      "geometry": {
        "type": "Point",
        "coordinates": [
          22.415737,
          38.694365
        ]
      },
      "id": "darmc-location-3434",
      "type": "Feature",
      "properties": {
        "description": "1:500,000 scale representative point location digitized from the Barrington Atlas of the Greek and Roman World by the Digital Atlas of Roman and Medieval Civilizations project at Harvard University.",
        "location_precision": "precise",
        "title": "DARMC location 3434",
        "link": "http://pleiades.stoa.org/places/540769/darmc-location-3434"
      }
    }
  ]
}