{
  "type": "FeatureCollection",
  "title": "Dystos",
  "id": "540746",
  "description": "An ancient place, cited: BAtlas 55 G4 Dystos",
  "bbox": [
    24.145303,
    38.355289,
    24.145303,
    38.355289
  ],
  "reprPoint": [
    24.145303,
    38.355289
  ],
  "names": [
    "Dystos"
  ],
  "features": [
    {
      "geometry": {
        "type": "Point",
        "coordinates": [
          24.145303,
          38.355289
        ]
      },
      "id": "darmc-location-12288",
      "type": "Feature",
      "properties": {
        "description": "500K scale point location",
        "location_precision": "precise",
        "title": "DARMC location 12288",
        "link": "http://pleiades.stoa.org/places/540746/darmc-location-12288"
      }
    }
  ]
}