{
  "type": "FeatureCollection",
  "title": "Eilesion",
  "id": "540750",
  "bbox": [
    23.507886,
    38.307788,
    23.507886,
    38.307788
  ],
  "description": "A city of southeast Boeotia mentioned by Homer.",
  "names": [
    "Eilesion",
    "Eilésion"
  ],
  "features": [
    {
      "type": "Feature",
      "geometry": {
        "type": "Point",
        "coordinates": [
          23.507886,
          38.307788
        ]
      },
      "properties": {
        "description": "representative point"
      }
    },
    {
      "geometry": {
        "type": "Point",
        "coordinates": [
          23.507886,
          38.307788
        ]
      },
      "id": "darmc-location-12303",
      "type": "Feature",
      "properties": {
        "description": "1:500,000 scale representative point location digitized from the Barrington Atlas of the Greek and Roman World by the Digital Atlas of Roman and Medieval Civilizations project at Harvard University.",
        "location_precision": "precise",
        "title": "DARMC location 12303",
        "link": "http://pleiades.stoa.org/places/540750/darmc-location-12303"
      }
    }
  ]
}