{
  "type": "FeatureCollection",
  "title": "Glisas",
  "id": "540791",
  "description": "Glisas was an ancient town of Boeotia located northeast of Thebes. Glisas is included in the Homeric catalogue of ships.",
  "bbox": [
    23.390503,
    38.378178,
    23.390503,
    38.378178
  ],
  "connectsWith": [
    "540689"
  ],
  "reprPoint": [
    23.390503,
    38.378178
  ],
  "names": [
    "Glisas"
  ],
  "features": [
    {
      "geometry": {
        "type": "Point",
        "coordinates": [
          23.390503,
          38.378178
        ]
      },
      "id": "darmc-location-12565",
      "type": "Feature",
      "properties": {
        "description": "500K scale point location",
        "location_precision": "precise",
        "title": "DARMC location 12565",
        "link": "http://pleiades.stoa.org/places/540791/darmc-location-12565"
      }
    }
  ]
}