{
  "type": "FeatureCollection",
  "title": "Dystos",
  "id": "540746",
  "bbox": [
    24.1442993,
    38.3550266,
    24.145303,
    38.355289
  ],
  "description": "An ancient settlement of Euboea, its acropolis subsequently became the site of a Venetian tower.",
  "names": [
    "Dystos"
  ],
  "features": [
    {
      "type": "Feature",
      "geometry": {
        "type": "Point",
        "coordinates": [
          24.14480115,
          38.3551578
        ]
      },
      "properties": {
        "description": "representative point"
      }
    },
    {
      "geometry": {
        "type": "Point",
        "coordinates": [
          24.1442993,
          38.3550266
        ]
      },
      "id": "osm-location-i-iii3i-i-iioiiii-i-i-i-iiiii-i",
      "type": "Feature",
      "properties": {
        "description": "Location based on OpenStreetMap",
        "location_precision": "precise",
        "title": "OSM Location: Πύργος Ακρόπολης Δύστου",
        "link": "http://pleiades.stoa.org/places/540746/osm-location-i-iii3i-i-iioiiii-i-i-i-iiiii-i"
      }
    },
    {
      "geometry": {
        "type": "Point",
        "coordinates": [
          24.145303,
          38.355289
        ]
      },
      "id": "darmc-location-12288",
      "type": "Feature",
      "properties": {
        "description": "1:500,000 scale representative point location digitized from the Barrington Atlas of the Greek and Roman World by the Digital Atlas of Roman and Medieval Civilizations project at Harvard University.",
        "location_precision": "precise",
        "title": "DARMC location 12288",
        "link": "http://pleiades.stoa.org/places/540746/darmc-location-12288"
      }
    }
  ]
}