{
  "type": "FeatureCollection",
  "title": "Euripos",
  "id": "540783",
  "description": "An ancient place, cited: BAtlas 55 F4 Euripos",
  "bbox": [
    23.589444,
    38.462778,
    23.60756,
    38.471651
  ],
  "reprPoint": [
    23.598502,
    38.4672145
  ],
  "names": [
    "Euripos"
  ],
  "features": [
    {
      "geometry": {
        "type": "Point",
        "coordinates": [
          23.60756,
          38.471651
        ]
      },
      "id": "darmc-location-11888",
      "type": "Feature",
      "properties": {
        "description": "TIB point location",
        "location_precision": "precise",
        "title": "DARMC location 11888",
        "link": "http://pleiades.stoa.org/places/540783/darmc-location-11888"
      }
    }
  ]
}