{
  "type": "FeatureCollection",
  "title": "Glisas",
  "id": "540791",
  "bbox": [
    23.390503,
    38.378178,
    23.390503,
    38.378178
  ],
  "description": "Glisas was an ancient town of Boeotia located northeast of Thebes. Glisas is included in the Homeric catalogue of ships.",
  "connectsWith": [
    "540689"
  ],
  "names": [
    "Glisas"
  ],
  "features": [
    {
      "type": "Feature",
      "geometry": {
        "type": "Point",
        "coordinates": [
          23.390503,
          38.378178
        ]
      },
      "properties": {
        "description": "representative point"
      }
    },
    {
      "geometry": {
        "type": "Point",
        "coordinates": [
          23.390503,
          38.378178
        ]
      },
      "id": "darmc-location-12565",
      "type": "Feature",
      "properties": {
        "description": "1:500,000 scale representative point location digitized from the Barrington Atlas of the Greek and Roman World by the Digital Atlas of Roman and Medieval Civilizations project at Harvard University.",
        "location_precision": "precise",
        "title": "DARMC location 12565",
        "link": "http://pleiades.stoa.org/places/540791/darmc-location-12565"
      }
    }
  ]
}