{
  "type": "FeatureCollection",
  "title": "Crisaeus Sinus",
  "id": "540718",
  "bbox": [
    22.4390585,
    38.3996559,
    22.4390585,
    38.3996559
  ],
  "description": "An ancient place, cited: BAtlas 55 C4 Crisaeus Sinus",
  "names": [
    "Crisaeus Sinus",
    "Delphikos Kolpos"
  ],
  "features": [
    {
      "type": "Feature",
      "geometry": {
        "type": "Point",
        "coordinates": [
          22.4390585,
          38.3996559
        ]
      },
      "properties": {
        "description": "representative point"
      }
    },
    {
      "geometry": {
        "type": "Point",
        "coordinates": [
          22.4390585,
          38.3996559
        ]
      },
      "id": "osm-location-of-bay-of-itea",
      "type": "Feature",
      "properties": {
        "description": "Location based on OpenStreetMap",
        "location_precision": "precise",
        "title": "OSM location of Bay of Itea",
        "link": "http://pleiades.stoa.org/places/540718/osm-location-of-bay-of-itea"
      }
    }
  ]
}