{
  "type": "FeatureCollection",
  "title": "Graia",
  "id": "540796",
  "bbox": [
    23.630098,
    38.387159,
    23.630098,
    38.387159
  ],
  "description": "An ancient place, cited: BAtlas 55 F4 Graia",
  "names": [
    "Graia"
  ],
  "features": [
    {
      "type": "Feature",
      "geometry": {
        "type": "Point",
        "coordinates": [
          23.630098,
          38.387159
        ]
      },
      "properties": {
        "description": "representative point"
      }
    },
    {
      "geometry": {
        "type": "Point",
        "coordinates": [
          23.630098,
          38.387159
        ]
      },
      "id": "darmc-location-12599",
      "type": "Feature",
      "properties": {
        "description": "500K scale point location",
        "location_precision": "precise",
        "title": "DARMC location 12599",
        "link": "http://pleiades.stoa.org/places/540796/darmc-location-12599"
      }
    }
  ]
}