{
  "type": "FeatureCollection",
  "title": "Euripos",
  "id": "540783",
  "bbox": [
    23.589444,
    38.462778,
    23.60756,
    38.471651
  ],
  "description": "An ancient place, cited: BAtlas 55 F4 Euripos",
  "names": [
    "Euripos"
  ],
  "features": [
    {
      "type": "Feature",
      "geometry": {
        "type": "Point",
        "coordinates": [
          23.598502,
          38.4672145
        ]
      },
      "properties": {
        "description": "representative point"
      }
    },
    {
      "geometry": {
        "type": "Point",
        "coordinates": [
          23.60756,
          38.471651
        ]
      },
      "id": "darmc-location-11888",
      "type": "Feature",
      "properties": {
        "description": "TIB point location",
        "location_precision": "precise",
        "title": "DARMC location 11888",
        "link": "http://pleiades.stoa.org/places/540783/darmc-location-11888"
      }
    },
    {
      "geometry": {
        "type": "Point",
        "coordinates": [
          23.589444,
          38.462778
        ]
      },
      "id": "location-of-euripus-strait",
      "type": "Feature",
      "properties": {
        "description": "Representative location based on GeoHack.",
        "location_precision": "precise",
        "title": "GeoHack location of Euripus Strait",
        "link": "http://pleiades.stoa.org/places/540783/location-of-euripus-strait"
      }
    }
  ]
}