{
  "type": "FeatureCollection",
  "title": "(Eu)Dieron?",
  "id": "540779",
  "bbox": [
    22.415592,
    39.929704,
    22.415592,
    39.929704
  ],
  "description": "An ancient place, cited: BAtlas 55 C1 (Eu)Dieron?",
  "names": [
    "Eudieron",
    "Dieron"
  ],
  "features": [
    {
      "type": "Feature",
      "geometry": {
        "type": "Point",
        "coordinates": [
          22.415592,
          39.929704
        ]
      },
      "properties": {
        "description": "representative point"
      }
    },
    {
      "geometry": {
        "type": "Point",
        "coordinates": [
          22.415592,
          39.929704
        ]
      },
      "id": "darmc-location-12198",
      "type": "Feature",
      "properties": {
        "description": "500K scale point location",
        "location_precision": "precise",
        "title": "DARMC location 12198",
        "link": "http://pleiades.stoa.org/places/540779/darmc-location-12198"
      }
    }
  ]
}