{
  "type": "FeatureCollection",
  "title": "Chalia",
  "id": "540705",
  "bbox": [
    23.570797,
    38.487562,
    23.573961,
    38.489071
  ],
  "description": "Theopompus mentions Chalia as a town of Boeotia. It is also attested epigraphically and may have been a member of the Boeotian league. Fossey locates the city in the vicinity of the church of Agios Minas in modern Drosia. Archaeological finds in the area indicate human activity from as early as the Bronze Age.",
  "names": [
    "Drosia",
    "Ag. Minas",
    "Chalia"
  ],
  "features": [
    {
      "type": "Feature",
      "geometry": {
        "type": "Point",
        "coordinates": [
          23.572379,
          38.4883165
        ]
      },
      "properties": {
        "description": "representative point"
      }
    },
    {
      "geometry": {
        "type": "Point",
        "coordinates": [
          23.573961,
          38.489071
        ]
      },
      "id": "imagery-location-agios-minas",
      "type": "Feature",
      "properties": {
        "description": null,
        "location_precision": "precise",
        "title": "Imagery Location: Agios Minas",
        "link": "http://pleiades.stoa.org/places/540705/imagery-location-agios-minas"
      }
    },
    {
      "geometry": {
        "type": "Point",
        "coordinates": [
          23.570797,
          38.487562
        ]
      },
      "id": "darmc-location-11976",
      "type": "Feature",
      "properties": {
        "description": "1:500,000 scale representative point location digitized from the Barrington Atlas of the Greek and Roman World by the Digital Atlas of Roman and Medieval Civilizations project at Harvard University.",
        "location_precision": "precise",
        "title": "DARMC location 11976",
        "link": "http://pleiades.stoa.org/places/540705/darmc-location-11976"
      }
    }
  ]
}