{
  "type": "FeatureCollection",
  "title": "Karandai",
  "id": "540853",
  "description": "An ancient place, cited: BAtlas 55 D2 Karandai",
  "bbox": [
    22.549487,
    39.11234,
    22.549487,
    39.11234
  ],
  "reprPoint": [
    22.549487,
    39.11234
  ],
  "names": [
    "Karandai"
  ],
  "features": [
    {
      "geometry": {
        "type": "Point",
        "coordinates": [
          22.549487,
          39.11234
        ]
      },
      "id": "darmc-location-7869",
      "type": "Feature",
      "properties": {
        "description": "500K scale point location",
        "location_precision": "precise",
        "title": "DARMC location 7869",
        "link": "http://pleiades.stoa.org/places/540853/darmc-location-7869"
      }
    }
  ]
}