{
  "type": "FeatureCollection",
  "title": "Kabeirion",
  "id": "540844",
  "description": "An ancient place, cited: BAtlas 55 E4 Kabeirion",
  "bbox": [
    23.255096,
    38.318092,
    23.262367,
    38.32584
  ],
  "reprPoint": [
    23.2587315,
    38.321966
  ],
  "names": [
    "Kabeirion"
  ],
  "features": [
    {
      "geometry": {
        "type": "Point",
        "coordinates": [
          23.262367,
          38.32584
        ]
      },
      "id": "darmc-location-16018",
      "type": "Feature",
      "properties": {
        "description": "500K scale point location",
        "location_precision": "precise",
        "title": "DARMC location 16018",
        "link": "http://pleiades.stoa.org/places/540844/darmc-location-16018"
      }
    },
    {
      "geometry": {
        "type": "Point",
        "coordinates": [
          23.255096,
          38.318092
        ]
      },
      "id": "dare-location",
      "type": "Feature",
      "properties": {
        "description": "Representative point location, site precision",
        "location_precision": "precise",
        "title": "DARE Location",
        "link": "http://pleiades.stoa.org/places/540844/dare-location"
      }
    }
  ]
}