{
  "type": "FeatureCollection",
  "title": "Hyettos",
  "id": "540823",
  "bbox": [
    23.103147,
    38.555375,
    23.103147,
    38.555375
  ],
  "description": "An ancient settlement of Boeotia. The site is located about 2 km east of modern Loutsi in Greece.",
  "names": [
    "Hyettos"
  ],
  "features": [
    {
      "type": "Feature",
      "geometry": {
        "type": "Point",
        "coordinates": [
          23.103147,
          38.555375
        ]
      },
      "properties": {
        "description": "representative point"
      }
    },
    {
      "geometry": {
        "type": "Point",
        "coordinates": [
          23.103147,
          38.555375
        ]
      },
      "id": "darmc-location-12816",
      "type": "Feature",
      "properties": {
        "description": "1:500,000 scale representative point location digitized from the Barrington Atlas of the Greek and Roman World by the Digital Atlas of Roman and Medieval Civilizations project at Harvard University.",
        "location_precision": "precise",
        "title": "DARMC location 12816",
        "link": "http://pleiades.stoa.org/places/540823/darmc-location-12816"
      }
    }
  ]
}