{
  "type": "FeatureCollection",
  "title": "Iton?",
  "id": "540842",
  "bbox": [
    22.690378,
    39.135224,
    22.761484,
    39.174314
  ],
  "description": "An ancient place, cited: BAtlas 55 D2 Iton?",
  "names": [
    "Iton",
    "Itonion"
  ],
  "features": [
    {
      "type": "Feature",
      "geometry": {
        "type": "Point",
        "coordinates": [
          22.725931,
          39.154769
        ]
      },
      "properties": {
        "description": "representative point"
      }
    },
    {
      "geometry": {
        "type": "Point",
        "coordinates": [
          22.690378,
          39.174314
        ]
      },
      "id": "darmc-location-24",
      "type": "Feature",
      "properties": {
        "description": "TIB point location",
        "location_precision": "precise",
        "title": "DARMC location 24",
        "link": "http://pleiades.stoa.org/places/540842/darmc-location-24"
      }
    },
    {
      "geometry": {
        "type": "Point",
        "coordinates": [
          22.761484,
          39.135224
        ]
      },
      "id": "darmc-location-6641",
      "type": "Feature",
      "properties": {
        "description": "500K scale point location",
        "location_precision": "precise",
        "title": "DARMC location 6641",
        "link": "http://pleiades.stoa.org/places/540842/darmc-location-6641"
      }
    }
  ]
}