{
  "type": "FeatureCollection",
  "title": "Halai",
  "id": "540800",
  "bbox": [
    23.193751,
    38.653765,
    23.193751,
    38.653765
  ],
  "description": "An ancient place, cited: BAtlas 55 E3 Halai",
  "names": [
    "Halai"
  ],
  "features": [
    {
      "type": "Feature",
      "geometry": {
        "type": "Point",
        "coordinates": [
          23.193751,
          38.653765
        ]
      },
      "properties": {
        "description": "representative point"
      }
    },
    {
      "geometry": {
        "type": "Point",
        "coordinates": [
          23.193751,
          38.653765
        ]
      },
      "id": "darmc-location-12651",
      "type": "Feature",
      "properties": {
        "description": "500K scale point location",
        "location_precision": "precise",
        "title": "DARMC location 12651",
        "link": "http://pleiades.stoa.org/places/540800/darmc-location-12651"
      }
    }
  ]
}