{
  "type": "FeatureCollection",
  "title": "Hyettos",
  "id": "540823",
  "description": "An ancient place, cited: BAtlas 55 E3 Hyettos",
  "bbox": [
    23.103147,
    38.555375,
    23.103147,
    38.555375
  ],
  "reprPoint": [
    23.103147,
    38.555375
  ],
  "names": [
    "Hyettos"
  ],
  "features": [
    {
      "geometry": {
        "type": "Point",
        "coordinates": [
          23.103147,
          38.555375
        ]
      },
      "id": "darmc-location-12816",
      "type": "Feature",
      "properties": {
        "description": "500K scale point location",
        "location_precision": "precise",
        "title": "DARMC location 12816",
        "link": "http://pleiades.stoa.org/places/540823/darmc-location-12816"
      }
    }
  ]
}