{
  "type": "FeatureCollection",
  "title": "Kerinthos",
  "id": "540861",
  "description": "An ancient place, cited: BAtlas 55 E3 Kerinthos",
  "bbox": [
    23.48282,
    38.825075,
    23.48282,
    38.825075
  ],
  "reprPoint": [
    23.48282,
    38.825075
  ],
  "names": [
    "Kerinthos"
  ],
  "features": [
    {
      "geometry": {
        "type": "Point",
        "coordinates": [
          23.48282,
          38.825075
        ]
      },
      "id": "darmc-location-13115",
      "type": "Feature",
      "properties": {
        "description": "500K scale point location",
        "location_precision": "precise",
        "title": "DARMC location 13115",
        "link": "http://pleiades.stoa.org/places/540861/darmc-location-13115"
      }
    }
  ]
}