{
  "type": "FeatureCollection",
  "title": "Larissa",
  "id": "540905",
  "bbox": [
    22.409373,
    39.631893,
    22.43931,
    39.640288
  ],
  "description": "The ancient capital of the Thessalian Pelasgiotis, modern Larisa in Greece.",
  "names": [
    "Larissa"
  ],
  "features": [
    {
      "type": "Feature",
      "geometry": {
        "type": "Point",
        "coordinates": [
          22.42097025,
          39.634851
        ]
      },
      "properties": {
        "description": "representative point"
      }
    },
    {
      "geometry": {
        "type": "Point",
        "coordinates": [
          22.43931,
          39.63478
        ]
      },
      "id": "darmc-location-3805",
      "type": "Feature",
      "properties": {
        "description": "1:500,000 scale representative point location digitized from the Barrington Atlas of the Greek and Roman World by the Digital Atlas of Roman and Medieval Civilizations project at Harvard University.",
        "location_precision": "precise",
        "title": "DARMC location 3805",
        "link": "http://pleiades.stoa.org/places/540905/darmc-location-3805"
      }
    },
    {
      "geometry": {
        "type": "Point",
        "coordinates": [
          22.419875,
          39.631893
        ]
      },
      "id": "darmc-location-24052",
      "type": "Feature",
      "properties": {
        "description": "5M scale representative point location digitized from the Barrington Atlas of the Greek and Roman World by the Digital Atlas of Roman and Medieval Civilizations project at Harvard University.",
        "location_precision": "precise",
        "title": "DARMC location 24052",
        "link": "http://pleiades.stoa.org/places/540905/darmc-location-24052"
      }
    },
    {
      "geometry": {
        "type": "Point",
        "coordinates": [
          22.409373,
          39.632443
        ]
      },
      "id": "darmc-location-12211",
      "type": "Feature",
      "properties": {
        "description": "TIB representative point location digitized from the Barrington Atlas of the Greek and Roman World by the Digital Atlas of Roman and Medieval Civilizations project at Harvard University.",
        "location_precision": "precise",
        "title": "DARMC location 12211",
        "link": "http://pleiades.stoa.org/places/540905/darmc-location-12211"
      }
    },
    {
      "geometry": {
        "type": "Point",
        "coordinates": [
          22.415323,
          39.640288
        ]
      },
      "id": "dare-location",
      "type": "Feature",
      "properties": {
        "description": "Representative point location, site precision",
        "location_precision": "precise",
        "title": "DARE Location",
        "link": "http://pleiades.stoa.org/places/540905/dare-location"
      }
    }
  ]
}