{
  "type": "FeatureCollection",
  "title": "Limnaion",
  "id": "540916",
  "description": "An ancient place, cited: BAtlas 55 C1 Limnaion",
  "bbox": [
    22.106587,
    39.505191,
    22.106587,
    39.505191
  ],
  "reprPoint": [
    22.106587,
    39.505191
  ],
  "names": [
    "Limnaion"
  ],
  "features": [
    {
      "geometry": {
        "type": "Point",
        "coordinates": [
          22.106587,
          39.505191
        ]
      },
      "id": "darmc-location-13499",
      "type": "Feature",
      "properties": {
        "description": "500K scale point location",
        "location_precision": "precise",
        "title": "DARMC location 13499",
        "link": "http://pleiades.stoa.org/places/540916/darmc-location-13499"
      }
    }
  ]
}