{
  "type": "FeatureCollection",
  "title": "Lamia",
  "id": "540902",
  "description": "An ancient place, cited: BAtlas 55 C3 Lamia",
  "bbox": [
    22.442593,
    38.902996,
    22.442593,
    38.902996
  ],
  "reprPoint": [
    22.442593,
    38.902996
  ],
  "names": [
    "Lamia"
  ],
  "features": [
    {
      "geometry": {
        "type": "Point",
        "coordinates": [
          22.442593,
          38.902996
        ]
      },
      "id": "darmc-location-13390",
      "type": "Feature",
      "properties": {
        "description": "500K scale point location",
        "location_precision": "precise",
        "title": "DARMC location 13390",
        "link": "http://pleiades.stoa.org/places/540902/darmc-location-13390"
      }
    }
  ]
}