{
  "type": "FeatureCollection",
  "title": "Molykreion?",
  "id": "540948",
  "bbox": [
    21.757727,
    38.388044,
    21.757727,
    38.388044
  ],
  "description": "An ancient place, cited: BAtlas 55 B4 Molykreion?",
  "names": [
    "Molykreion"
  ],
  "features": [
    {
      "type": "Feature",
      "geometry": {
        "type": "Point",
        "coordinates": [
          21.757727,
          38.388044
        ]
      },
      "properties": {
        "description": "representative point"
      }
    },
    {
      "geometry": {
        "type": "Point",
        "coordinates": [
          21.757727,
          38.388044
        ]
      },
      "id": "darmc-location-13780",
      "type": "Feature",
      "properties": {
        "description": "500K scale point location",
        "location_precision": "precise",
        "title": "DARMC location 13780",
        "link": "http://pleiades.stoa.org/places/540948/darmc-location-13780"
      }
    }
  ]
}