{
  "type": "FeatureCollection",
  "title": "Onchestos",
  "id": "540984",
  "bbox": [
    23.150267,
    38.373269,
    23.150267,
    38.373269
  ],
  "description": "Onchestos was located northwest of Thebes and was the site of an ancient cult of Poseidon. Prior to the Macedonian period the Boeotian confederacy met here.",
  "names": [
    "Onchestos"
  ],
  "features": [
    {
      "type": "Feature",
      "geometry": {
        "type": "Point",
        "coordinates": [
          23.150267,
          38.373269
        ]
      },
      "properties": {
        "description": "representative point"
      }
    },
    {
      "geometry": {
        "type": "Point",
        "coordinates": [
          23.150267,
          38.373269
        ]
      },
      "id": "darmc-location-14015",
      "type": "Feature",
      "properties": {
        "description": "500K scale point location",
        "location_precision": "precise",
        "title": "DARMC location 14015",
        "link": "http://pleiades.stoa.org/places/540984/darmc-location-14015"
      }
    }
  ]
}