{
  "type": "FeatureCollection",
  "title": "Myania",
  "id": "540952",
  "bbox": [
    22.357743,
    38.478043,
    22.357743,
    38.478043
  ],
  "description": "An ancient place, cited: BAtlas 55 C4 Myania",
  "names": [
    "Myania"
  ],
  "features": [
    {
      "type": "Feature",
      "geometry": {
        "type": "Point",
        "coordinates": [
          22.357743,
          38.478043
        ]
      },
      "properties": {
        "description": "representative point"
      }
    },
    {
      "geometry": {
        "type": "Point",
        "coordinates": [
          22.357743,
          38.478043
        ]
      },
      "id": "darmc-location-13839",
      "type": "Feature",
      "properties": {
        "description": "500K scale point location",
        "location_precision": "precise",
        "title": "DARMC location 13839",
        "link": "http://pleiades.stoa.org/places/540952/darmc-location-13839"
      }
    }
  ]
}