{
  "type": "FeatureCollection",
  "title": "Naupactus",
  "id": "540960",
  "bbox": [
    21.831267,
    38.399726,
    21.831267,
    38.399726
  ],
  "description": "Originally a city of the Ozolian Locrians, Naupactus eventually fell to Athens; under Macedonian rule Philip II ceded it to the Aetolians.",
  "connectsWith": [
    "570181"
  ],
  "names": [
    "Naupactus"
  ],
  "features": [
    {
      "type": "Feature",
      "geometry": {
        "type": "Point",
        "coordinates": [
          21.831267,
          38.399726
        ]
      },
      "properties": {
        "description": "representative point"
      }
    },
    {
      "geometry": {
        "type": "Point",
        "coordinates": [
          21.831267,
          38.399726
        ]
      },
      "id": "darmc-location-13885",
      "type": "Feature",
      "properties": {
        "description": "1:500,000 scale representative point location digitized from the Barrington Atlas of the Greek and Roman World by the Digital Atlas of Roman and Medieval Civilizations project at Harvard University.",
        "location_precision": "precise",
        "title": "DARMC location 13885",
        "link": "http://pleiades.stoa.org/places/540960/darmc-location-13885"
      }
    }
  ]
}