{
  "type": "FeatureCollection",
  "title": "Lefkandi",
  "id": "540909",
  "bbox": [
    23.682171,
    38.411782,
    23.682171,
    38.411782
  ],
  "description": "A coastal village on the island of Euboea known especially for rich Bronze Age and Iron Age material.",
  "connectsWith": [
    "540775"
  ],
  "features": [
    {
      "type": "Feature",
      "geometry": {
        "type": "Point",
        "coordinates": [
          23.682171,
          38.411782
        ]
      },
      "properties": {
        "description": "representative point"
      }
    },
    {
      "geometry": {
        "type": "Point",
        "coordinates": [
          23.682171,
          38.411782
        ]
      },
      "id": "darmc-location-13447",
      "type": "Feature",
      "properties": {
        "description": "1:500,000 scale representative point location digitized from the Barrington Atlas of the Greek and Roman World by the Digital Atlas of Roman and Medieval Civilizations project at Harvard University.",
        "location_precision": "precise",
        "title": "DARMC location 13447",
        "link": "http://pleiades.stoa.org/places/540909/darmc-location-13447"
      }
    }
  ]
}