{
  "type": "FeatureCollection",
  "title": "Magoula Kastri",
  "id": "540924",
  "bbox": [
    22.363387,
    39.740123,
    22.363387,
    39.740123
  ],
  "description": "An ancient place, cited: BAtlas 55 C1 Magoula Kastri",
  "features": [
    {
      "type": "Feature",
      "geometry": {
        "type": "Point",
        "coordinates": [
          22.363387,
          39.740123
        ]
      },
      "properties": {
        "description": "representative point"
      }
    },
    {
      "geometry": {
        "type": "Point",
        "coordinates": [
          22.363387,
          39.740123
        ]
      },
      "id": "darmc-location-16068",
      "type": "Feature",
      "properties": {
        "description": "500K scale point location",
        "location_precision": "precise",
        "title": "DARMC location 16068",
        "link": "http://pleiades.stoa.org/places/540924/darmc-location-16068"
      }
    }
  ]
}