{
  "type": "FeatureCollection",
  "title": "Lamia",
  "id": "540902",
  "bbox": [
    22.442593,
    38.902996,
    22.442593,
    38.902996
  ],
  "description": "An ancient settlement of Phthiotis, modern Lamia.",
  "connectsWith": [
    "540930",
    "104777481",
    "668537581"
  ],
  "names": [
    "Lamia"
  ],
  "features": [
    {
      "type": "Feature",
      "geometry": {
        "type": "Point",
        "coordinates": [
          22.442593,
          38.902996
        ]
      },
      "properties": {
        "description": "representative point"
      }
    },
    {
      "geometry": {
        "type": "Point",
        "coordinates": [
          22.442593,
          38.902996
        ]
      },
      "id": "darmc-location-13390",
      "type": "Feature",
      "properties": {
        "description": "1:500,000 scale representative point location digitized from the Barrington Atlas of the Greek and Roman World by the Digital Atlas of Roman and Medieval Civilizations project at Harvard University.",
        "location_precision": "precise",
        "title": "DARMC location 13390",
        "link": "http://pleiades.stoa.org/places/540902/darmc-location-13390"
      }
    }
  ]
}