{
  "type": "FeatureCollection",
  "title": "Schoinos",
  "id": "541091",
  "bbox": [
    23.364042,
    38.421765,
    23.364042,
    38.421765
  ],
  "description": "An ancient place, cited: BAtlas 55 E4 Schoinos",
  "names": [
    "Schoinos"
  ],
  "features": [
    {
      "type": "Feature",
      "geometry": {
        "type": "Point",
        "coordinates": [
          23.364042,
          38.421765
        ]
      },
      "properties": {
        "description": "representative point"
      }
    },
    {
      "geometry": {
        "type": "Point",
        "coordinates": [
          23.364042,
          38.421765
        ]
      },
      "id": "darmc-location-4859",
      "type": "Feature",
      "properties": {
        "description": "500K scale point location",
        "location_precision": "precise",
        "title": "DARMC location 4859",
        "link": "http://pleiades.stoa.org/places/541091/darmc-location-4859"
      }
    }
  ]
}