{
  "type": "FeatureCollection",
  "title": "Phystion",
  "id": "541058",
  "description": "An ancient place, cited: BAtlas 55 B3 Phystion",
  "bbox": [
    21.590774,
    38.599638,
    21.590774,
    38.599638
  ],
  "reprPoint": [
    21.590774,
    38.599638
  ],
  "names": [
    "Phystion"
  ],
  "features": [
    {
      "geometry": {
        "type": "Point",
        "coordinates": [
          21.590774,
          38.599638
        ]
      },
      "id": "darmc-location-14276",
      "type": "Feature",
      "properties": {
        "description": "500K scale point location",
        "location_precision": "precise",
        "title": "DARMC location 14276",
        "link": "http://pleiades.stoa.org/places/541058/darmc-location-14276"
      }
    }
  ]
}