{
  "type": "FeatureCollection",
  "title": "Rhizous",
  "id": "541085",
  "bbox": [
    22.823639,
    39.807258,
    22.823639,
    39.807258
  ],
  "description": "An ancient place, cited: BAtlas 55 D1 Rhizous",
  "connectsWith": [
    "540923"
  ],
  "names": [
    "Rhizous",
    "Rhizus"
  ],
  "features": [
    {
      "type": "Feature",
      "geometry": {
        "type": "Point",
        "coordinates": [
          22.823639,
          39.807258
        ]
      },
      "properties": {
        "description": "representative point"
      }
    },
    {
      "geometry": {
        "type": "Point",
        "coordinates": [
          22.823639,
          39.807258
        ]
      },
      "id": "darmc-location-13938",
      "type": "Feature",
      "properties": {
        "description": "TIB representative point location digitized from the Barrington Atlas of the Greek and Roman World by the Digital Atlas of Roman and Medieval Civilizations project at Harvard University.",
        "location_precision": "precise",
        "title": "DARMC location 13938",
        "link": "http://pleiades.stoa.org/places/541085/darmc-location-13938"
      }
    }
  ]
}