{
  "type": "FeatureCollection",
  "title": "Schedia?",
  "id": "541090",
  "bbox": [
    23.678496,
    38.272852,
    23.678496,
    38.272852
  ],
  "description": "An ancient place, cited: BAtlas 55 F4 Schedia?",
  "names": [
    "Schedia"
  ],
  "features": [
    {
      "type": "Feature",
      "geometry": {
        "type": "Point",
        "coordinates": [
          23.678496,
          38.272852
        ]
      },
      "properties": {
        "description": "representative point"
      }
    },
    {
      "geometry": {
        "type": "Point",
        "coordinates": [
          23.678496,
          38.272852
        ]
      },
      "id": "darmc-location-4857",
      "type": "Feature",
      "properties": {
        "description": "500K scale point location",
        "location_precision": "precise",
        "title": "DARMC location 4857",
        "link": "http://pleiades.stoa.org/places/541090/darmc-location-4857"
      }
    }
  ]
}