{
  "type": "FeatureCollection",
  "title": "Pereia",
  "id": "541025",
  "bbox": [
    22.555166,
    39.141135,
    22.555166,
    39.141135
  ],
  "description": "An ancient place, cited: BAtlas 55 D2 Pereia",
  "names": [
    "Pereia"
  ],
  "features": [
    {
      "type": "Feature",
      "geometry": {
        "type": "Point",
        "coordinates": [
          22.555166,
          39.141135
        ]
      },
      "properties": {
        "description": "representative point"
      }
    },
    {
      "geometry": {
        "type": "Point",
        "coordinates": [
          22.555166,
          39.141135
        ]
      },
      "id": "darmc-location-14186",
      "type": "Feature",
      "properties": {
        "description": "1:500,000 scale representative point location digitized from the Barrington Atlas of the Greek and Roman World by the Digital Atlas of Roman and Medieval Civilizations project at Harvard University.",
        "location_precision": "precise",
        "title": "DARMC location 14186",
        "link": "http://pleiades.stoa.org/places/541025/darmc-location-14186"
      }
    }
  ]
}