{
  "type": "FeatureCollection",
  "title": "Rhizous",
  "id": "541085",
  "description": "An ancient place, cited: BAtlas 55 D1 Rhizous",
  "bbox": [
    22.823639,
    39.796733,
    22.871541,
    39.807258
  ],
  "reprPoint": [
    22.84759,
    39.8019955
  ],
  "names": [
    "Rhizous"
  ],
  "features": [
    {
      "geometry": {
        "type": "Point",
        "coordinates": [
          22.871541,
          39.796733
        ]
      },
      "id": "darmc-location-14501",
      "type": "Feature",
      "properties": {
        "description": "500K scale point location",
        "location_precision": "precise",
        "title": "DARMC location 14501",
        "link": "http://pleiades.stoa.org/places/541085/darmc-location-14501"
      }
    },
    {
      "geometry": {
        "type": "Point",
        "coordinates": [
          22.823639,
          39.807258
        ]
      },
      "id": "darmc-location-13938",
      "type": "Feature",
      "properties": {
        "description": "TIB point location",
        "location_precision": "precise",
        "title": "DARMC location 13938",
        "link": "http://pleiades.stoa.org/places/541085/darmc-location-13938"
      }
    }
  ]
}