{
  "type": "FeatureCollection",
  "title": "Thermon",
  "id": "541139",
  "bbox": [
    21.667571,
    38.558783,
    21.667571,
    38.558783
  ],
  "description": "An ancient place, cited: BAtlas 55 B3 Thermon",
  "connectsWith": [
    "540591",
    "104777481"
  ],
  "names": [
    "Thermon"
  ],
  "features": [
    {
      "type": "Feature",
      "geometry": {
        "type": "Point",
        "coordinates": [
          21.667571,
          38.558783
        ]
      },
      "properties": {
        "description": "representative point"
      }
    },
    {
      "geometry": {
        "type": "Point",
        "coordinates": [
          21.667571,
          38.558783
        ]
      },
      "id": "dare-location",
      "type": "Feature",
      "properties": {
        "description": "Representative point location, site precision",
        "location_precision": "precise",
        "title": "DARE Location",
        "link": "http://pleiades.stoa.org/places/541139/dare-location"
      }
    }
  ]
}