{
  "type": "FeatureCollection",
  "title": "Taphiassos (mountain)",
  "id": "541123",
  "bbox": [
    21.6838695,
    38.362506,
    21.6838695,
    38.362506
  ],
  "description": "A mountain mentioned in ancient sources. Modern Klokova in Grece.",
  "names": [
    "Taphiassos",
    "Klokova"
  ],
  "features": [
    {
      "type": "Feature",
      "geometry": {
        "type": "Point",
        "coordinates": [
          21.6838695,
          38.362506
        ]
      },
      "properties": {
        "description": "representative point"
      }
    },
    {
      "geometry": {
        "type": "Point",
        "coordinates": [
          21.6838695,
          38.362506
        ]
      },
      "id": "osm-location",
      "type": "Feature",
      "properties": {
        "description": "Location based on OpenStreetMap",
        "location_precision": "precise",
        "title": "OSM location of modern Klokova",
        "link": "http://pleiades.stoa.org/places/541123/osm-location"
      }
    }
  ]
}