{
  "type": "FeatureCollection",
  "title": "Thermopylae",
  "id": "541140",
  "bbox": [
    22.538294,
    38.795489,
    22.548994,
    38.796511
  ],
  "description": "Thermopylae is the name of a narrow pass leading from Thessaly into Locris. It was the site of a pivotal battle during the Graeco-Persian wars in 480 BC.",
  "connectsWith": [
    "540929"
  ],
  "names": [
    "Thermopylae",
    "Thermopýlai"
  ],
  "features": [
    {
      "type": "Feature",
      "geometry": {
        "type": "Point",
        "coordinates": [
          22.543644,
          38.796
        ]
      },
      "properties": {
        "description": "representative point"
      }
    },
    {
      "geometry": {
        "type": "Point",
        "coordinates": [
          22.548994,
          38.795489
        ]
      },
      "id": "darmc-location-8365",
      "type": "Feature",
      "properties": {
        "description": "500K scale point location",
        "location_precision": "precise",
        "title": "DARMC location 8365",
        "link": "http://pleiades.stoa.org/places/541140/darmc-location-8365"
      }
    },
    {
      "geometry": {
        "type": "Point",
        "coordinates": [
          22.538294,
          38.796511
        ]
      },
      "id": "dare-location",
      "type": "Feature",
      "properties": {
        "description": "Representative point location, site precision",
        "location_precision": "precise",
        "title": "DARE Location",
        "link": "http://pleiades.stoa.org/places/541140/dare-location"
      }
    }
  ]
}