{
  "type": "FeatureCollection",
  "title": "Teumessos",
  "id": "541133",
  "bbox": [
    23.382283,
    38.357554,
    23.382283,
    38.357554
  ],
  "description": "An ancient place, cited: BAtlas 55 E4 Teumessos",
  "names": [
    "Teumessos"
  ],
  "features": [
    {
      "type": "Feature",
      "geometry": {
        "type": "Point",
        "coordinates": [
          23.382283,
          38.357554
        ]
      },
      "properties": {
        "description": "representative point"
      }
    },
    {
      "geometry": {
        "type": "Point",
        "coordinates": [
          23.382283,
          38.357554
        ]
      },
      "id": "darmc-location-15095",
      "type": "Feature",
      "properties": {
        "description": "500K scale point location",
        "location_precision": "precise",
        "title": "DARMC location 15095",
        "link": "http://pleiades.stoa.org/places/541133/darmc-location-15095"
      }
    }
  ]
}