{
  "type": "FeatureCollection",
  "title": "Thebai/Thebae",
  "id": "541138",
  "description": "The ancient city of Thebes in Boeotia (modern Greece).",
  "bbox": [
    23.317799,
    38.319076,
    23.317799,
    38.319076
  ],
  "connectsWith": [
    "540689"
  ],
  "reprPoint": [
    23.317799,
    38.319076
  ],
  "names": [
    "Thebae",
    "Thiva",
    "Thebes",
    "Thebai"
  ],
  "features": [
    {
      "geometry": {
        "type": "Point",
        "coordinates": [
          23.317355,
          38.319236
        ]
      },
      "id": "darmc-location-24220",
      "type": "Feature",
      "properties": {
        "description": "5M scale point location",
        "location_precision": "precise",
        "title": "DARMC location 24220",
        "link": "http://pleiades.stoa.org/places/541138/darmc-location-24220"
      }
    },
    {
      "geometry": {
        "type": "Point",
        "coordinates": [
          23.317799,
          38.319076
        ]
      },
      "id": "dare-location",
      "type": "Feature",
      "properties": {
        "description": "Representative point location, site precision",
        "location_precision": "precise",
        "title": "DARE Location",
        "link": "http://pleiades.stoa.org/places/541138/dare-location"
      }
    }
  ]
}