{
  "type": "FeatureCollection",
  "title": "Stephon?",
  "id": "541114",
  "description": "An ancient place, cited: BAtlas 55 F4 Stephon?",
  "bbox": [
    23.518744,
    38.328581,
    23.518744,
    38.328581
  ],
  "reprPoint": [
    23.518744,
    38.328581
  ],
  "names": [
    "Stephon"
  ],
  "features": [
    {
      "geometry": {
        "type": "Point",
        "coordinates": [
          23.518744,
          38.328581
        ]
      },
      "id": "darmc-location-14897",
      "type": "Feature",
      "properties": {
        "description": "500K scale point location",
        "location_precision": "precise",
        "title": "DARMC location 14897",
        "link": "http://pleiades.stoa.org/places/541114/darmc-location-14897"
      }
    }
  ]
}