{
  "type": "FeatureCollection",
  "title": "Zeus Akraios, T.",
  "id": "541178",
  "bbox": [
    23.0508239039,
    39.4088346693,
    23.0508239039,
    39.4088346693
  ],
  "description": "A sanctuary of Zeus Akraios on Mount Pelion.",
  "connectsWith": [
    "541021"
  ],
  "names": [
    "Zeus Akraios, T."
  ],
  "features": [
    {
      "type": "Feature",
      "geometry": {
        "type": "Point",
        "coordinates": [
          23.0508239039,
          39.4088346693
        ]
      },
      "properties": {
        "description": "representative point"
      }
    },
    {
      "geometry": {
        "type": "Point",
        "coordinates": [
          23.05082390391578,
          39.40883466932964
        ]
      },
      "id": "batlas-point-location",
      "type": "Feature",
      "properties": {
        "description": "Digitized in QGIS from georegistered map 55.",
        "location_precision": "precise",
        "title": "BAtlas Point Location",
        "link": "http://pleiades.stoa.org/places/541178/batlas-point-location"
      }
    }
  ]
}