{
  "type": "FeatureCollection",
  "title": "Velousia",
  "id": "541171",
  "description": "An ancient place, cited: BAtlas 55 G4 Velousia",
  "bbox": [
    24.089463,
    38.390531,
    24.089463,
    38.390531
  ],
  "reprPoint": [
    24.089463,
    38.390531
  ],
  "features": [
    {
      "geometry": {
        "type": "Point",
        "coordinates": [
          24.089463,
          38.390531
        ]
      },
      "id": "darmc-location-16247",
      "type": "Feature",
      "properties": {
        "description": "500K scale point location",
        "location_precision": "precise",
        "title": "DARMC location 16247",
        "link": "http://pleiades.stoa.org/places/541171/darmc-location-16247"
      }
    }
  ]
}