{
  "type": "FeatureCollection",
  "title": "Trikka",
  "id": "541163",
  "bbox": [
    21.782998,
    39.568904,
    21.782998,
    39.568904
  ],
  "description": "An ancient place, cited: BAtlas 55 B1 Trikka",
  "connectsWith": [
    "540815"
  ],
  "names": [
    "Trikka"
  ],
  "features": [
    {
      "type": "Feature",
      "geometry": {
        "type": "Point",
        "coordinates": [
          21.782998,
          39.568904
        ]
      },
      "properties": {
        "description": "representative point"
      }
    },
    {
      "geometry": {
        "type": "Point",
        "coordinates": [
          21.782998,
          39.568904
        ]
      },
      "id": "darmc-location-15259",
      "type": "Feature",
      "properties": {
        "description": "500K scale point location",
        "location_precision": "precise",
        "title": "DARMC location 15259",
        "link": "http://pleiades.stoa.org/places/541163/darmc-location-15259"
      }
    }
  ]
}