{
  "type": "FeatureCollection",
  "title": "Thebai/Thebae",
  "id": "541138",
  "bbox": [
    23.317799,
    38.319076,
    23.317799,
    38.319076
  ],
  "description": "The ancient city of Thebes in Boeotia (modern Greece).",
  "connectsWith": [
    "540689"
  ],
  "names": [
    "Thebae",
    "Thiva",
    "Thebes",
    "Thebai",
    "te-qa-"
  ],
  "features": [
    {
      "type": "Feature",
      "geometry": {
        "type": "Point",
        "coordinates": [
          23.317799,
          38.319076
        ]
      },
      "properties": {
        "description": "representative point"
      }
    },
    {
      "geometry": {
        "type": "Point",
        "coordinates": [
          23.317799,
          38.319076
        ]
      },
      "id": "dare-location",
      "type": "Feature",
      "properties": {
        "description": "Representative point location, site precision",
        "location_precision": "precise",
        "title": "DARE Location",
        "link": "http://pleiades.stoa.org/places/541138/dare-location"
      }
    }
  ]
}