{
  "type": "FeatureCollection",
  "title": "Tilphosaion?",
  "id": "541148",
  "bbox": [
    22.994538,
    38.371064,
    22.994538,
    38.371064
  ],
  "description": "An ancient place, cited: BAtlas 55 D4 Tilphosaion?",
  "names": [
    "Tilphosaion"
  ],
  "features": [
    {
      "type": "Feature",
      "geometry": {
        "type": "Point",
        "coordinates": [
          22.994538,
          38.371064
        ]
      },
      "properties": {
        "description": "representative point"
      }
    },
    {
      "geometry": {
        "type": "Point",
        "coordinates": [
          22.994538,
          38.371064
        ]
      },
      "id": "darmc-location-8374",
      "type": "Feature",
      "properties": {
        "description": "1:500,000 scale representative point location digitized from the Barrington Atlas of the Greek and Roman World by the Digital Atlas of Roman and Medieval Civilizations project at Harvard University.",
        "location_precision": "precise",
        "title": "DARMC location 8374",
        "link": "http://pleiades.stoa.org/places/541148/darmc-location-8374"
      }
    }
  ]
}