{
  "type": "FeatureCollection",
  "title": "Thaumakia?",
  "id": "541135",
  "bbox": [
    23.339604,
    39.173156,
    23.339604,
    39.173156
  ],
  "description": "An ancient place, cited: BAtlas 55 E2 Thaumakia?",
  "names": [
    "Thaumakia"
  ],
  "features": [
    {
      "type": "Feature",
      "geometry": {
        "type": "Point",
        "coordinates": [
          23.339604,
          39.173156
        ]
      },
      "properties": {
        "description": "representative point"
      }
    },
    {
      "geometry": {
        "type": "Point",
        "coordinates": [
          23.339604,
          39.173156
        ]
      },
      "id": "darmc-location-15115",
      "type": "Feature",
      "properties": {
        "description": "1:500,000 scale representative point location digitized from the Barrington Atlas of the Greek and Roman World by the Digital Atlas of Roman and Medieval Civilizations project at Harvard University.",
        "location_precision": "precise",
        "title": "DARMC location 15115",
        "link": "http://pleiades.stoa.org/places/541135/darmc-location-15115"
      }
    }
  ]
}