{
  "type": "FeatureCollection",
  "title": "New City/Newtown",
  "id": "54136921",
  "bbox": [
    44.426853,
    32.542578,
    44.426853,
    32.542578
  ],
  "description": "According to the Babylonian topographical text Tintir = Babylon, New City (ālu eššu) was one of the six city districts of the eastern half of the inner city of Babylon and it contained two temples and one dais. This city quarter dates back to the late Old Babylonian Period (as demonstrated by a commercial archive excavated in the Merkes).",
  "connectsWith": [
    "893951",
    "5066375"
  ],
  "names": [
    "New City",
    "ālu eššu",
    "ālum eššum ṣīt šamšim"
  ],
  "features": [
    {
      "type": "Feature",
      "geometry": {
        "type": "Point",
        "coordinates": [
          44.426853,
          32.542578
        ]
      },
      "properties": {
        "description": "representative point"
      }
    },
    {
      "geometry": {
        "type": "Point",
        "coordinates": [
          44.426853,
          32.542578
        ]
      },
      "id": "representative-location-of-new-city",
      "type": "Feature",
      "properties": {
        "description": null,
        "location_precision": "precise",
        "title": "Representative location of New City",
        "link": "http://pleiades.stoa.org/places/54136921/representative-location-of-new-city"
      }
    }
  ]
}