{
  "type": "FeatureCollection",
  "title": "San Rocco Military Complex (Trieste)",
  "id": "543783806",
  "bbox": [
    13.844775,
    45.607338,
    13.844775,
    45.607338
  ],
  "description": "A Roman military fortification at modern Trieste, dating from the third to the first centuries BCE.",
  "connectsWith": [
    "187578"
  ],
  "features": [
    {
      "type": "Feature",
      "geometry": {
        "type": "Point",
        "coordinates": [
          13.844775,
          45.607338
        ]
      },
      "properties": {
        "description": "representative point"
      }
    },
    {
      "geometry": {
        "type": "Point",
        "coordinates": [
          13.844775,
          45.607338
        ]
      },
      "id": "vici-org-location-of-san-rocco",
      "type": "Feature",
      "properties": {
        "description": null,
        "location_precision": "precise",
        "title": "Vici.org location of San Rocco",
        "link": "http://pleiades.stoa.org/places/543783806/vici-org-location-of-san-rocco"
      }
    }
  ]
}