{
  "type": "FeatureCollection",
  "title": "Picentino (river)",
  "id": "544710173",
  "bbox": [
    14.8564808,
    40.6332345,
    14.8564808,
    40.6332345
  ],
  "description": "A river of Campania that is connected to the now-lost settlement of Picentia and the Picentinus Ager.",
  "connectsWith": [
    "1356"
  ],
  "features": [
    {
      "type": "Feature",
      "geometry": {
        "type": "Point",
        "coordinates": [
          14.8564808,
          40.6332345
        ]
      },
      "properties": {
        "description": "representative point"
      }
    },
    {
      "geometry": {
        "type": "Point",
        "coordinates": [
          14.8564808,
          40.6332345
        ]
      },
      "id": "osm-location-of-picentino-river",
      "type": "Feature",
      "properties": {
        "description": "Representative modern location of river course based on OpenStreetMap.",
        "location_precision": "precise",
        "title": "OSM location of Picentino (river)",
        "link": "http://pleiades.stoa.org/places/544710173/osm-location-of-picentino-river"
      }
    }
  ]
}