{
  "type": "FeatureCollection",
  "title": "Heptastadion",
  "id": "549287251",
  "bbox": [
    26.1752383,
    39.998364,
    26.7443694,
    40.4200151
  ],
  "description": "The narrowest point in the Hellespont, between Sestos and Abydos.",
  "connectsWith": [
    "501609",
    "501325",
    "501434"
  ],
  "names": [
    "Heptastádion"
  ],
  "features": [
    {
      "type": "Feature",
      "geometry": {
        "type": "Point",
        "coordinates": [
          26.4144303991,
          40.2012426982
        ]
      },
      "properties": {
        "description": "representative point"
      }
    }
  ]
}