{
  "type": "FeatureCollection",
  "title": "Wesseling Roman Villa",
  "id": "549572847",
  "bbox": [
    6.9937858,
    50.804587,
    6.9937858,
    50.804587
  ],
  "description": "A villa rustica at modern Wesseling.",
  "features": [
    {
      "type": "Feature",
      "geometry": {
        "type": "Point",
        "coordinates": [
          6.9937858,
          50.804587
        ]
      },
      "properties": {
        "description": "representative point"
      }
    },
    {
      "geometry": {
        "type": "Point",
        "coordinates": [
          6.9937858,
          50.804587
        ]
      },
      "id": "osm-location",
      "type": "Feature",
      "properties": {
        "description": "Representative location based on OpenStreetMap.",
        "location_precision": "precise",
        "title": "OSM location of Wesseling Villa Rustica",
        "link": "http://pleiades.stoa.org/places/549572847/osm-location"
      }
    }
  ]
}