{
  "type": "FeatureCollection",
  "title": "Chios",
  "id": "550496",
  "bbox": [
    26.129334,
    38.375597,
    26.139133,
    38.377223
  ],
  "description": "An ancient place, cited: BAtlas 56 C5 Chios",
  "connectsWith": [
    "735295266",
    "550497"
  ],
  "names": [
    "Chios"
  ],
  "features": [
    {
      "type": "Feature",
      "geometry": {
        "type": "Point",
        "coordinates": [
          26.1342335,
          38.37641
        ]
      },
      "properties": {
        "description": "representative point"
      }
    },
    {
      "geometry": {
        "type": "Point",
        "coordinates": [
          26.129334,
          38.377223
        ]
      },
      "id": "darmc-location-1466",
      "type": "Feature",
      "properties": {
        "description": "TIB point location",
        "location_precision": "precise",
        "title": "DARMC location 1466",
        "link": "http://pleiades.stoa.org/places/550496/darmc-location-1466"
      }
    },
    {
      "geometry": {
        "type": "Point",
        "coordinates": [
          26.139133,
          38.375597
        ]
      },
      "id": "darmc-location-3183",
      "type": "Feature",
      "properties": {
        "description": "500K scale point location",
        "location_precision": "precise",
        "title": "DARMC location 3183",
        "link": "http://pleiades.stoa.org/places/550496/darmc-location-3183"
      }
    }
  ]
}