{
  "type": "FeatureCollection",
  "title": "Aegae",
  "id": "550404",
  "bbox": [
    27.1897746,
    38.8319945,
    27.19367,
    38.83379
  ],
  "description": "An ancient place, cited: BAtlas 56 E4 Aegae",
  "connectsWith": [
    "550406",
    "177302800"
  ],
  "names": [
    "Aegae"
  ],
  "features": [
    {
      "type": "Feature",
      "geometry": {
        "type": "Point",
        "coordinates": [
          27.1917223,
          38.83289225
        ]
      },
      "properties": {
        "description": "representative point"
      }
    },
    {
      "geometry": {
        "type": "Point",
        "coordinates": [
          27.19367,
          38.83379
        ]
      },
      "id": "geonames-location",
      "type": "Feature",
      "properties": {
        "description": "Representative point location based on a Geonames place record. Dates after BAtlas.",
        "location_precision": "precise",
        "title": "GeoNames location of Aigeai (Aeolis)",
        "link": "http://pleiades.stoa.org/places/550404/geonames-location"
      }
    },
    {
      "geometry": {
        "type": "Point",
        "coordinates": [
          27.1897746,
          38.8319945
        ]
      },
      "id": "osm-location-of-aigai",
      "type": "Feature",
      "properties": {
        "description": "Representative location based on OpenStreetMap",
        "location_precision": "precise",
        "title": "OSM location of Aigai",
        "link": "http://pleiades.stoa.org/places/550404/osm-location-of-aigai"
      }
    }
  ]
}