{
  "type": "FeatureCollection",
  "title": "Antandros",
  "id": "550433",
  "bbox": [
    26.791496,
    39.5785,
    26.791496,
    39.5785
  ],
  "description": "Antandros was a city on the coast of the Troad, near the head of the Gulf of Adramyttium.",
  "connectsWith": [
    "550944"
  ],
  "names": [
    "Antandros"
  ],
  "features": [
    {
      "type": "Feature",
      "geometry": {
        "type": "Point",
        "coordinates": [
          26.791496,
          39.5785
        ]
      },
      "properties": {
        "description": "representative point"
      }
    },
    {
      "geometry": {
        "type": "Point",
        "coordinates": [
          26.791496,
          39.5785
        ]
      },
      "id": "darmc-location-11407",
      "type": "Feature",
      "properties": {
        "description": "1:500,000 scale representative point location digitized from the Barrington Atlas of the Greek and Roman World by the Digital Atlas of Roman and Medieval Civilizations project at Harvard University.",
        "location_precision": "precise",
        "title": "DARMC location 11407",
        "link": "http://pleiades.stoa.org/places/550433/darmc-location-11407"
      }
    }
  ]
}