{
  "type": "FeatureCollection",
  "title": "Chios (settlement)",
  "id": "550496",
  "bbox": [
    26.129334,
    38.3722387,
    26.139133,
    38.377223
  ],
  "description": "The principal ancient city on the Aegean island of Chios.",
  "connectsWith": [
    "735295266",
    "550497"
  ],
  "names": [
    "Chios"
  ],
  "features": [
    {
      "type": "Feature",
      "geometry": {
        "type": "Point",
        "coordinates": [
          26.1338153333,
          38.3750195667
        ]
      },
      "properties": {
        "description": "representative point"
      }
    },
    {
      "geometry": {
        "type": "Point",
        "coordinates": [
          26.129334,
          38.377223
        ]
      },
      "id": "darmc-location-1466",
      "type": "Feature",
      "properties": {
        "description": "TIB representative point location digitized from the Barrington Atlas of the Greek and Roman World by the Digital Atlas of Roman and Medieval Civilizations project at Harvard University.",
        "location_precision": "precise",
        "title": "DARMC location 1466",
        "link": "http://pleiades.stoa.org/places/550496/darmc-location-1466"
      }
    },
    {
      "geometry": {
        "type": "Point",
        "coordinates": [
          26.139133,
          38.375597
        ]
      },
      "id": "darmc-location-3183",
      "type": "Feature",
      "properties": {
        "description": "1:500,000 scale representative point location digitized from the Barrington Atlas of the Greek and Roman World by the Digital Atlas of Roman and Medieval Civilizations project at Harvard University.",
        "location_precision": "precise",
        "title": "DARMC location 3183",
        "link": "http://pleiades.stoa.org/places/550496/darmc-location-3183"
      }
    },
    {
      "geometry": {
        "type": "Point",
        "coordinates": [
          26.132979,
          38.3722387
        ]
      },
      "id": "osm-location-of-modern-chios-town",
      "type": "Feature",
      "properties": {
        "description": "Location based on OpenStreetMap",
        "location_precision": "precise",
        "title": "OSM Location of Modern Chios Town",
        "link": "http://pleiades.stoa.org/places/550496/osm-location-of-modern-chios-town"
      }
    }
  ]
}