{
  "type": "FeatureCollection",
  "title": "Babrantion",
  "id": "550482",
  "bbox": [
    26.13006,
    38.423006,
    26.13006,
    38.423006
  ],
  "description": "An ancient place, cited: BAtlas 56 C5 Babrantion",
  "names": [
    "Babrantion"
  ],
  "features": [
    {
      "type": "Feature",
      "geometry": {
        "type": "Point",
        "coordinates": [
          26.13006,
          38.423006
        ]
      },
      "properties": {
        "description": "representative point"
      }
    },
    {
      "geometry": {
        "type": "Point",
        "coordinates": [
          26.13006,
          38.423006
        ]
      },
      "id": "darmc-location-11612",
      "type": "Feature",
      "properties": {
        "description": "500K scale point location",
        "location_precision": "precise",
        "title": "DARMC location 11612",
        "link": "http://pleiades.stoa.org/places/550482/darmc-location-11612"
      }
    }
  ]
}