{
  "type": "FeatureCollection",
  "title": "*Chondria",
  "id": "550498",
  "description": "An ancient place, cited: BAtlas 56 E5 *Chondria",
  "bbox": [
    27.40204,
    38.140551,
    27.404587,
    38.1463471
  ],
  "reprPoint": [
    27.4033135,
    38.14344905
  ],
  "names": [
    "Chondria"
  ],
  "features": [
    {
      "geometry": {
        "type": "Point",
        "coordinates": [
          27.404587,
          38.140551
        ]
      },
      "id": "darmc-location-12013",
      "type": "Feature",
      "properties": {
        "description": "500K scale point location",
        "location_precision": "precise",
        "title": "DARMC location 12013",
        "link": "http://pleiades.stoa.org/places/550498/darmc-location-12013"
      }
    },
    {
      "geometry": {
        "type": "Point",
        "coordinates": [
          27.402039999999943,
          38.1463471
        ]
      },
      "id": "dare-location",
      "type": "Feature",
      "properties": {
        "description": "Representative point location, village precision",
        "location_precision": "precise",
        "title": "DARE Location",
        "link": "http://pleiades.stoa.org/places/550498/dare-location"
      }
    }
  ]
}