{
  "type": "FeatureCollection",
  "title": "Aegae",
  "id": "550404",
  "description": "An ancient place, cited: BAtlas 56 E4 Aegae",
  "bbox": [
    27.19367,
    38.83379,
    27.19367,
    38.83379
  ],
  "connectsWith": [
    "550406"
  ],
  "reprPoint": [
    27.19367,
    38.83379
  ],
  "names": [
    "Aegae"
  ],
  "features": [
    {
      "geometry": {
        "type": "Point",
        "coordinates": [
          27.19367,
          38.83379
        ]
      },
      "id": "geonames-location",
      "type": "Feature",
      "properties": {
        "description": "Representative point location based on a Geonames place record. Dates after BAtlas.",
        "location_precision": "precise",
        "title": "Geonames Location",
        "link": "http://pleiades.stoa.org/places/550404/geonames-location"
      }
    }
  ]
}