{
  "type": "FeatureCollection",
  "title": "Aegae",
  "id": "550404",
  "description": "An ancient place, cited: BAtlas 56 E4 Aegae",
  "bbox": [
    27.3166667,
    38.9,
    27.3166667,
    38.9
  ],
  "reprPoint": [
    27.3166667,
    38.9
  ],
  "names": [
    "Aegae"
  ],
  "features": [
    {
      "geometry": {
        "type": "Point",
        "coordinates": [
          27.174421,
          38.820323
        ]
      },
      "id": "darmc-location-11179",
      "type": "Feature",
      "properties": {
        "description": "500K scale point location",
        "location_precision": "precise",
        "title": "DARMC location 11179",
        "link": "http://pleiades.stoa.org/places/550404/darmc-location-11179"
      }
    },
    {
      "geometry": {
        "type": "Point",
        "coordinates": [
          27.3166667,
          38.9
        ]
      },
      "id": "dare-location",
      "type": "Feature",
      "properties": {
        "description": "Representative point location, village precision",
        "location_precision": "precise",
        "title": "DARE Location",
        "link": "http://pleiades.stoa.org/places/550404/dare-location"
      }
    }
  ]
}