{
  "type": "FeatureCollection",
  "title": "Dionysos Bresagenes, T.",
  "id": "550514",
  "description": "An ancient place, cited: BAtlas 56 C3 Dionysos Bresagenes, T.",
  "bbox": [
    26.166973,
    39.015443,
    26.166973,
    39.015443
  ],
  "reprPoint": [
    26.166973,
    39.015443
  ],
  "names": [
    "Dionysos Bresagenes, T."
  ],
  "features": [
    {
      "geometry": {
        "type": "Point",
        "coordinates": [
          26.166973,
          39.015443
        ]
      },
      "id": "darmc-location-15944",
      "type": "Feature",
      "properties": {
        "description": "500K scale point location",
        "location_precision": "precise",
        "title": "DARMC location 15944",
        "link": "http://pleiades.stoa.org/places/550514/darmc-location-15944"
      }
    }
  ]
}