{
  "type": "FeatureCollection",
  "title": "Cyme",
  "id": "550506",
  "description": "An ancient place, cited: BAtlas 56 D4 Cyme",
  "bbox": [
    26.936283,
    38.75953,
    26.936283,
    38.75953
  ],
  "reprPoint": [
    26.936283,
    38.75953
  ],
  "names": [
    "Cyme"
  ],
  "features": [
    {
      "geometry": {
        "type": "Point",
        "coordinates": [
          26.942154,
          38.761848
        ]
      },
      "id": "darmc-location-12124",
      "type": "Feature",
      "properties": {
        "description": "500K scale point location",
        "location_precision": "precise",
        "title": "DARMC location 12124",
        "link": "http://pleiades.stoa.org/places/550506/darmc-location-12124"
      }
    },
    {
      "geometry": {
        "type": "Point",
        "coordinates": [
          26.936283,
          38.75953
        ]
      },
      "id": "dare-location",
      "type": "Feature",
      "properties": {
        "description": "Representative point location, site precision",
        "location_precision": "precise",
        "title": "DARE Location",
        "link": "http://pleiades.stoa.org/places/550506/dare-location"
      }
    }
  ]
}