{
  "type": "FeatureCollection",
  "title": "Gergitha?",
  "id": "550548",
  "bbox": [
    27.694738,
    39.184733,
    27.694738,
    39.184733
  ],
  "description": "An ancient place, cited: BAtlas 56 F3 Gergitha?",
  "names": [
    "Gergitha"
  ],
  "features": [
    {
      "type": "Feature",
      "geometry": {
        "type": "Point",
        "coordinates": [
          27.694738,
          39.184733
        ]
      },
      "properties": {
        "description": "representative point"
      }
    },
    {
      "geometry": {
        "type": "Point",
        "coordinates": [
          27.694738,
          39.184733
        ]
      },
      "id": "darmc-location-12527",
      "type": "Feature",
      "properties": {
        "description": "1:500,000 scale representative point location digitized from the Barrington Atlas of the Greek and Roman World by the Digital Atlas of Roman and Medieval Civilizations project at Harvard University.",
        "location_precision": "precise",
        "title": "DARMC location 12527",
        "link": "http://pleiades.stoa.org/places/550548/darmc-location-12527"
      }
    }
  ]
}