{
  "type": "FeatureCollection",
  "title": "Issa?",
  "id": "550599",
  "bbox": [
    26.131466,
    39.207108,
    26.131466,
    39.207108
  ],
  "description": "Ancient Issa on the island of Lesbos is possibly to be identified with a ruined Hellenistic wall-and-tower site (with subsequent additions) on the Xirokastrini hill between modern Kalloni and Parakoila.",
  "connectsWith": [
    "550696"
  ],
  "names": [
    "Issa"
  ],
  "features": [
    {
      "type": "Feature",
      "geometry": {
        "type": "Point",
        "coordinates": [
          26.131466,
          39.207108
        ]
      },
      "properties": {
        "description": "representative point"
      }
    },
    {
      "geometry": {
        "type": "Point",
        "coordinates": [
          26.131466,
          39.207108
        ]
      },
      "id": "darmc-location-12895",
      "type": "Feature",
      "properties": {
        "description": "1:500,000 scale representative point location digitized from the Barrington Atlas of the Greek and Roman World by the Digital Atlas of Roman and Medieval Civilizations project at Harvard University.",
        "location_precision": "precise",
        "title": "DARMC location 12895",
        "link": "http://pleiades.stoa.org/places/550599/darmc-location-12895"
      }
    }
  ]
}