{
  "type": "FeatureCollection",
  "title": "Dotion",
  "id": "550518",
  "description": "An ancient place, cited: BAtlas 56 C5 Dotion",
  "bbox": [
    26.004975,
    38.174089,
    26.004975,
    38.174089
  ],
  "reprPoint": [
    26.004975,
    38.174089
  ],
  "names": [
    "Dotion"
  ],
  "features": [
    {
      "geometry": {
        "type": "Point",
        "coordinates": [
          26.004975,
          38.174089
        ]
      },
      "id": "darmc-location-17410",
      "type": "Feature",
      "properties": {
        "description": "500K scale point location",
        "location_precision": "precise",
        "title": "DARMC location 17410",
        "link": "http://pleiades.stoa.org/places/550518/darmc-location-17410"
      }
    }
  ]
}