{
  "type": "FeatureCollection",
  "title": "Dionysos Bresagenes, T.",
  "id": "550514",
  "bbox": [
    26.1701507,
    39.0066955,
    26.1701507,
    39.0066955
  ],
  "description": "An ancient place, cited: BAtlas 56 C3 Dionysos Bresagenes, T.",
  "connectsWith": [
    "550696"
  ],
  "names": [
    "Dionysos Bresagenes, T."
  ],
  "features": [
    {
      "type": "Feature",
      "geometry": {
        "type": "Point",
        "coordinates": [
          26.1701507,
          39.0066955
        ]
      },
      "properties": {
        "description": "representative point"
      }
    },
    {
      "geometry": {
        "type": "Point",
        "coordinates": [
          26.1701507,
          39.0066955
        ]
      },
      "id": "osm-location-of-ii-ii-ii1i-i1-2iii-i-ii-i-iii-ii",
      "type": "Feature",
      "properties": {
        "description": "Representative location based on OpenStreetMap",
        "location_precision": "precise",
        "title": "OSM location of Ναός Διονύσου του Βρησαγενούς",
        "link": "http://pleiades.stoa.org/places/550514/osm-location-of-ii-ii-ii1i-i1-2iii-i-ii-i-iii-ii"
      }
    }
  ]
}