{
  "type": "FeatureCollection",
  "title": "Gerraidai",
  "id": "550550",
  "bbox": [
    26.788552,
    38.195953,
    26.788552,
    38.195953
  ],
  "description": "An ancient place, cited: BAtlas 56 D5 Gerraidai",
  "names": [
    "Gerraidai",
    "Geraesticus Portus"
  ],
  "features": [
    {
      "type": "Feature",
      "geometry": {
        "type": "Point",
        "coordinates": [
          26.788552,
          38.195953
        ]
      },
      "properties": {
        "description": "representative point"
      }
    },
    {
      "geometry": {
        "type": "Point",
        "coordinates": [
          26.788552,
          38.195953
        ]
      },
      "id": "darmc-location-12534",
      "type": "Feature",
      "properties": {
        "description": "500K scale point location",
        "location_precision": "precise",
        "title": "DARMC location 12534",
        "link": "http://pleiades.stoa.org/places/550550/darmc-location-12534"
      }
    }
  ]
}