{
  "type": "FeatureCollection",
  "title": "Cyme",
  "id": "550506",
  "bbox": [
    26.936283,
    38.75953,
    26.942154,
    38.761848
  ],
  "description": "An ancient place, cited: BAtlas 56 D4 Cyme",
  "connectsWith": [
    "550406"
  ],
  "names": [
    "Cyme"
  ],
  "features": [
    {
      "type": "Feature",
      "geometry": {
        "type": "Point",
        "coordinates": [
          26.9392185,
          38.760689
        ]
      },
      "properties": {
        "description": "representative point"
      }
    },
    {
      "geometry": {
        "type": "Point",
        "coordinates": [
          26.942154,
          38.761848
        ]
      },
      "id": "darmc-location-12124",
      "type": "Feature",
      "properties": {
        "description": "1:500,000 scale representative point location digitized from the Barrington Atlas of the Greek and Roman World by the Digital Atlas of Roman and Medieval Civilizations project at Harvard University.",
        "location_precision": "precise",
        "title": "DARMC location 12124",
        "link": "http://pleiades.stoa.org/places/550506/darmc-location-12124"
      }
    },
    {
      "geometry": {
        "type": "Point",
        "coordinates": [
          26.936283,
          38.75953
        ]
      },
      "id": "dare-location",
      "type": "Feature",
      "properties": {
        "description": "Representative point location, site precision",
        "location_precision": "precise",
        "title": "DARE Location",
        "link": "http://pleiades.stoa.org/places/550506/dare-location"
      }
    }
  ]
}