{
  "type": "FeatureCollection",
  "title": "Issa?",
  "id": "550599",
  "description": "An ancient place, cited: BAtlas 56 C3 Issa?",
  "bbox": [
    26.131466,
    39.207108,
    26.131466,
    39.207108
  ],
  "reprPoint": [
    26.131466,
    39.207108
  ],
  "names": [
    "Issa"
  ],
  "features": [
    {
      "geometry": {
        "type": "Point",
        "coordinates": [
          26.131466,
          39.207108
        ]
      },
      "id": "darmc-location-12895",
      "type": "Feature",
      "properties": {
        "description": "500K scale point location",
        "location_precision": "precise",
        "title": "DARMC location 12895",
        "link": "http://pleiades.stoa.org/places/550599/darmc-location-12895"
      }
    }
  ]
}