{
  "type": "FeatureCollection",
  "title": "Khontro Bigli",
  "id": "550638",
  "description": "An ancient place, cited: BAtlas 56 C3 Khontro Bigli",
  "bbox": [
    26.099211,
    39.145427,
    26.099211,
    39.145427
  ],
  "reprPoint": [
    26.099211,
    39.145427
  ],
  "features": [
    {
      "geometry": {
        "type": "Point",
        "coordinates": [
          26.099211,
          39.145427
        ]
      },
      "id": "darmc-location-16033",
      "type": "Feature",
      "properties": {
        "description": "500K scale point location",
        "location_precision": "precise",
        "title": "DARMC location 16033",
        "link": "http://pleiades.stoa.org/places/550638/darmc-location-16033"
      }
    }
  ]
}