{
  "type": "FeatureCollection",
  "title": "Laneion",
  "id": "550680",
  "description": "An ancient place, cited: BAtlas 56 F2 Laneion",
  "bbox": [
    27.970941,
    39.753857,
    27.970941,
    39.753857
  ],
  "reprPoint": [
    27.970941,
    39.753857
  ],
  "names": [
    "Laneion"
  ],
  "features": [
    {
      "geometry": {
        "type": "Point",
        "coordinates": [
          27.970941,
          39.753857
        ]
      },
      "id": "darmc-location-16333",
      "type": "Feature",
      "properties": {
        "description": "500K scale point location",
        "location_precision": "precise",
        "title": "DARMC location 16333",
        "link": "http://pleiades.stoa.org/places/550680/darmc-location-16333"
      }
    }
  ]
}