{
  "type": "FeatureCollection",
  "title": "Larisa/Ptolemais?",
  "id": "550685",
  "bbox": [
    26.147559,
    39.615744,
    26.147559,
    39.615744
  ],
  "description": "An ancient place, cited: BAtlas 56 C2 Larisa/Ptolemais?",
  "connectsWith": [
    "550944"
  ],
  "names": [
    "Larisa",
    "Ptolemais"
  ],
  "features": [
    {
      "type": "Feature",
      "geometry": {
        "type": "Point",
        "coordinates": [
          26.147559,
          39.615744
        ]
      },
      "properties": {
        "description": "representative point"
      }
    },
    {
      "geometry": {
        "type": "Point",
        "coordinates": [
          26.147559,
          39.615744
        ]
      },
      "id": "darmc-location-3804",
      "type": "Feature",
      "properties": {
        "description": "1:500,000 scale representative point location digitized from the Barrington Atlas of the Greek and Roman World by the Digital Atlas of Roman and Medieval Civilizations project at Harvard University.",
        "location_precision": "precise",
        "title": "DARMC location 3804",
        "link": "http://pleiades.stoa.org/places/550685/darmc-location-3804"
      }
    }
  ]
}