{
  "type": "FeatureCollection",
  "title": "Khydera",
  "id": "550639",
  "description": "An ancient place, cited: BAtlas 56 C3 Khydera",
  "bbox": [
    26.042518,
    39.206879,
    26.042518,
    39.206879
  ],
  "reprPoint": [
    26.042518,
    39.206879
  ],
  "features": [
    {
      "geometry": {
        "type": "Point",
        "coordinates": [
          26.042518,
          39.206879
        ]
      },
      "id": "darmc-location-7103",
      "type": "Feature",
      "properties": {
        "description": "500K scale point location",
        "location_precision": "precise",
        "title": "DARMC location 7103",
        "link": "http://pleiades.stoa.org/places/550639/darmc-location-7103"
      }
    }
  ]
}