{
  "type": "FeatureCollection",
  "title": "Leukai",
  "id": "550697",
  "bbox": [
    26.856796,
    38.546745,
    26.856796,
    38.546745
  ],
  "description": "Leukai was an ancient harbor city on the north shore of the Gulf of Smyrna.",
  "connectsWith": [
    "550573"
  ],
  "names": [
    "Leukai",
    "oppidum Leucae"
  ],
  "features": [
    {
      "type": "Feature",
      "geometry": {
        "type": "Point",
        "coordinates": [
          26.856796,
          38.546745
        ]
      },
      "properties": {
        "description": "representative point"
      }
    },
    {
      "geometry": {
        "type": "Point",
        "coordinates": [
          26.856796,
          38.546745
        ]
      },
      "id": "darmc-location-4458",
      "type": "Feature",
      "properties": {
        "description": "1:500,000 scale representative point location digitized from the Barrington Atlas of the Greek and Roman World by the Digital Atlas of Roman and Medieval Civilizations project at Harvard University.",
        "location_precision": "precise",
        "title": "DARMC location 4458",
        "link": "http://pleiades.stoa.org/places/550697/darmc-location-4458"
      }
    }
  ]
}