{
  "type": "FeatureCollection",
  "title": "Karene?",
  "id": "550621",
  "description": "An ancient place, cited: BAtlas 56 D3 Karene?",
  "bbox": [
    26.842283,
    39.17898,
    26.842283,
    39.17898
  ],
  "reprPoint": [
    26.842283,
    39.17898
  ],
  "names": [
    "Karene"
  ],
  "features": [
    {
      "geometry": {
        "type": "Point",
        "coordinates": [
          26.842283,
          39.17898
        ]
      },
      "id": "darmc-location-13017",
      "type": "Feature",
      "properties": {
        "description": "500K scale point location",
        "location_precision": "precise",
        "title": "DARMC location 13017",
        "link": "http://pleiades.stoa.org/places/550621/darmc-location-13017"
      }
    }
  ]
}