{
  "type": "FeatureCollection",
  "title": "Lekton/Lectum",
  "id": "550691",
  "bbox": [
    26.06278,
    39.4768727,
    26.0638389,
    39.47977
  ],
  "description": "The Lekton promontory (modern Cape Baba or Baba Burnu) is the the westernmost point of Asia Minor.",
  "connectsWith": [
    "560221"
  ],
  "names": [
    "Lekton",
    "promunturium Lectum"
  ],
  "features": [
    {
      "type": "Feature",
      "geometry": {
        "type": "Point",
        "coordinates": [
          26.06330945,
          39.47832135
        ]
      },
      "properties": {
        "description": "representative point"
      }
    },
    {
      "geometry": {
        "type": "Point",
        "coordinates": [
          26.06278,
          39.47977
        ]
      },
      "id": "baba-burnu",
      "type": "Feature",
      "properties": {
        "description": "Representative location based on GeoNames.",
        "location_precision": "precise",
        "title": "GeoNames location of Baba Burnu",
        "link": "http://pleiades.stoa.org/places/550691/baba-burnu"
      }
    },
    {
      "geometry": {
        "type": "Point",
        "coordinates": [
          26.0638389,
          39.4768727
        ]
      },
      "id": "location-of-cape-baba",
      "type": "Feature",
      "properties": {
        "description": "Representative point location based on OpenStreetMap.",
        "location_precision": "precise",
        "title": "OSM location of Cape Baba",
        "link": "http://pleiades.stoa.org/places/550691/location-of-cape-baba"
      }
    }
  ]
}