{
  "type": "FeatureCollection",
  "title": "Karene?",
  "id": "550621",
  "bbox": [
    26.842283,
    39.17898,
    26.842283,
    39.17898
  ],
  "description": "An ancient place, cited: BAtlas 56 D3 Karene?",
  "names": [
    "Karene"
  ],
  "features": [
    {
      "type": "Feature",
      "geometry": {
        "type": "Point",
        "coordinates": [
          26.842283,
          39.17898
        ]
      },
      "properties": {
        "description": "representative point"
      }
    },
    {
      "geometry": {
        "type": "Point",
        "coordinates": [
          26.842283,
          39.17898
        ]
      },
      "id": "darmc-location-13017",
      "type": "Feature",
      "properties": {
        "description": "1:500,000 scale representative point location digitized from the Barrington Atlas of the Greek and Roman World by the Digital Atlas of Roman and Medieval Civilizations project at Harvard University.",
        "location_precision": "precise",
        "title": "DARMC location 13017",
        "link": "http://pleiades.stoa.org/places/550621/darmc-location-13017"
      }
    }
  ]
}