{
  "type": "FeatureCollection",
  "title": "Lekton Pr.",
  "id": "550691",
  "description": "Lekton Pr. (Cape Baba or Baba Burnu) is the the westernmost point of Asia Minor.",
  "bbox": [
    26.06278,
    39.4768727,
    26.0638389,
    39.47977
  ],
  "connectsWith": [
    "560221"
  ],
  "reprPoint": [
    26.06330945,
    39.47832135
  ],
  "names": [
    "Lekton Pr."
  ],
  "features": [
    {
      "geometry": {
        "type": "Point",
        "coordinates": [
          26.06278,
          39.47977
        ]
      },
      "id": "baba-burnu",
      "type": "Feature",
      "properties": {
        "description": "Location based on GeoNames",
        "location_precision": "precise",
        "title": "Baba Burnu",
        "link": "http://pleiades.stoa.org/places/550691/baba-burnu"
      }
    },
    {
      "geometry": {
        "type": "Point",
        "coordinates": [
          26.0638389,
          39.4768727
        ]
      },
      "id": "location-of-cape-baba",
      "type": "Feature",
      "properties": {
        "description": "Location based on OpenStreetMap",
        "location_precision": "precise",
        "title": "location of Cape Baba",
        "link": "http://pleiades.stoa.org/places/550691/location-of-cape-baba"
      }
    }
  ]
}