{
  "type": "FeatureCollection",
  "title": "Kane (mountain)",
  "id": "550616",
  "bbox": [
    26.8597222,
    38.9691667,
    26.8597222,
    38.9691667
  ],
  "description": "Kara Dağ, near Çandarlı.",
  "names": [
    "Kane"
  ],
  "features": [
    {
      "type": "Feature",
      "geometry": {
        "type": "Point",
        "coordinates": [
          26.8597222,
          38.9691667
        ]
      },
      "properties": {
        "description": "representative point"
      }
    },
    {
      "geometry": {
        "type": "Point",
        "coordinates": [
          26.8597222,
          38.9691667
        ]
      },
      "id": "seyret-tepe-tr",
      "type": "Feature",
      "properties": {
        "description": "A peak on Kane Mons",
        "location_precision": "precise",
        "title": "Seyret Tepe",
        "link": "http://pleiades.stoa.org/places/550616/seyret-tepe-tr"
      }
    }
  ]
}