{
  "type": "FeatureCollection",
  "title": "Koloe",
  "id": "550659",
  "description": "An ancient place, cited: BAtlas 56 G5 Koloe",
  "bbox": [
    28.208011,
    38.22593,
    28.208011,
    38.22593
  ],
  "reprPoint": [
    28.208011,
    38.22593
  ],
  "names": [
    "Koloe"
  ],
  "features": [
    {
      "geometry": {
        "type": "Point",
        "coordinates": [
          28.208011,
          38.22593
        ]
      },
      "id": "darmc-location-34952",
      "type": "Feature",
      "properties": {
        "description": "scale point location",
        "location_precision": "precise",
        "title": "DARMC location 34952",
        "link": "http://pleiades.stoa.org/places/550659/darmc-location-34952"
      }
    }
  ]
}