{
  "type": "FeatureCollection",
  "title": "Larisa/Ptolemais?",
  "id": "550685",
  "description": "An ancient place, cited: BAtlas 56 C2 Larisa/Ptolemais?",
  "bbox": [
    26.147559,
    39.615744,
    26.147559,
    39.615744
  ],
  "reprPoint": [
    26.147559,
    39.615744
  ],
  "names": [
    "Larisa",
    "Ptolemais"
  ],
  "features": [
    {
      "geometry": {
        "type": "Point",
        "coordinates": [
          26.147559,
          39.615744
        ]
      },
      "id": "darmc-location-3804",
      "type": "Feature",
      "properties": {
        "description": "500K scale point location",
        "location_precision": "precise",
        "title": "DARMC location 3804",
        "link": "http://pleiades.stoa.org/places/550685/darmc-location-3804"
      }
    }
  ]
}