{
  "type": "FeatureCollection",
  "title": "Leptymnos M.",
  "id": "550694",
  "bbox": [
    26.268611,
    39.3455557,
    26.268611,
    39.3455557
  ],
  "description": "An ancient place, cited: BAtlas 56 C3 Leptymnos M.",
  "names": [
    "Leptymnos M."
  ],
  "features": [
    {
      "type": "Feature",
      "geometry": {
        "type": "Point",
        "coordinates": [
          26.268611,
          39.3455557
        ]
      },
      "properties": {
        "description": "representative point"
      }
    },
    {
      "geometry": {
        "type": "Point",
        "coordinates": [
          26.268611,
          39.3455557
        ]
      },
      "id": "vigla-968m",
      "type": "Feature",
      "properties": {
        "description": "A peak on the Leptymnos mountain range",
        "location_precision": "precise",
        "title": "Vigla",
        "link": "http://pleiades.stoa.org/places/550694/vigla-968m"
      }
    }
  ]
}