{
  "type": "FeatureCollection",
  "title": "Koila",
  "id": "550655",
  "description": "An ancient place, cited: BAtlas 56 C4 Koila",
  "bbox": [
    26.089078,
    38.49903,
    26.089078,
    38.49903
  ],
  "reprPoint": [
    26.089078,
    38.49903
  ],
  "features": [
    {
      "geometry": {
        "type": "Point",
        "coordinates": [
          26.089078,
          38.49903
        ]
      },
      "id": "darmc-location-4147",
      "type": "Feature",
      "properties": {
        "description": "500K scale point location",
        "location_precision": "precise",
        "title": "DARMC location 4147",
        "link": "http://pleiades.stoa.org/places/550655/darmc-location-4147"
      }
    }
  ]
}