{
  "type": "FeatureCollection",
  "title": "Kalapetro",
  "id": "550606",
  "description": "An ancient place, cited: BAtlas 56 C3 Kalapetro",
  "bbox": [
    26.174748,
    39.273917,
    26.174748,
    39.273917
  ],
  "reprPoint": [
    26.174748,
    39.273917
  ],
  "features": [
    {
      "geometry": {
        "type": "Point",
        "coordinates": [
          26.174748,
          39.273917
        ]
      },
      "id": "darmc-location-23613",
      "type": "Feature",
      "properties": {
        "description": "Point location",
        "location_precision": "precise",
        "title": "DARMC location 23613",
        "link": "http://pleiades.stoa.org/places/550606/darmc-location-23613"
      }
    }
  ]
}