{
  "type": "FeatureCollection",
  "title": "Milingos",
  "id": "550743",
  "description": "An ancient place, cited: BAtlas 56 C5 Milingos",
  "bbox": [
    26.139266,
    38.45091,
    26.139266,
    38.45091
  ],
  "connectsWith": [
    "80c7850f33a9bcbe7aab02d76d9b38bb"
  ],
  "reprPoint": [
    26.139266,
    38.45091
  ],
  "features": [
    {
      "geometry": {
        "type": "Point",
        "coordinates": [
          26.139266,
          38.45091
        ]
      },
      "id": "darmc-location-13750",
      "type": "Feature",
      "properties": {
        "description": "500K scale point location",
        "location_precision": "precise",
        "title": "DARMC location 13750",
        "link": "http://pleiades.stoa.org/places/550743/darmc-location-13750"
      }
    }
  ]
}