{
  "type": "FeatureCollection",
  "title": "Marathoussa (island)",
  "id": "550721",
  "bbox": [
    26.7935614,
    38.4068626,
    26.7935614,
    38.4068626
  ],
  "description": "The ancient Marathoussa island is probably to be associated with the modern Yassıca Ada.",
  "names": [
    "Marathoussa"
  ],
  "features": [
    {
      "type": "Feature",
      "geometry": {
        "type": "Point",
        "coordinates": [
          26.7935614,
          38.4068626
        ]
      },
      "properties": {
        "description": "representative point"
      }
    },
    {
      "geometry": {
        "type": "Point",
        "coordinates": [
          26.7935614,
          38.4068626
        ]
      },
      "id": "osm-location",
      "type": "Feature",
      "properties": {
        "description": "Representative modern location based on OpenStreetMap.",
        "location_precision": "precise",
        "title": "OSM location of Yassıca Ada",
        "link": "http://pleiades.stoa.org/places/550721/osm-location"
      }
    }
  ]
}