{
  "type": "FeatureCollection",
  "title": "*Nakrason?",
  "id": "550767",
  "description": "An ancient place, cited: BAtlas 56 F3 *Nakrason?",
  "bbox": [
    27.705557,
    39.044142,
    27.815692,
    39.059088
  ],
  "reprPoint": [
    27.7606245,
    39.051615
  ],
  "names": [
    "Nakrason"
  ],
  "features": [
    {
      "geometry": {
        "type": "Point",
        "coordinates": [
          27.705557,
          39.059088
        ]
      },
      "id": "darmc-location-5101",
      "type": "Feature",
      "properties": {
        "description": "500K scale point location",
        "location_precision": "precise",
        "title": "DARMC location 5101",
        "link": "http://pleiades.stoa.org/places/550767/darmc-location-5101"
      }
    },
    {
      "geometry": {
        "type": "Point",
        "coordinates": [
          27.815692,
          39.044142
        ]
      },
      "id": "darmc-location-5102",
      "type": "Feature",
      "properties": {
        "description": "500K scale point location",
        "location_precision": "precise",
        "title": "DARMC location 5102",
        "link": "http://pleiades.stoa.org/places/550767/darmc-location-5102"
      }
    }
  ]
}