{
  "type": "FeatureCollection",
  "title": "Molibos",
  "id": "550747",
  "description": "An ancient place, cited: BAtlas 56 C3 Molibos",
  "bbox": [
    26.182772,
    39.36627,
    26.182772,
    39.36627
  ],
  "reprPoint": [
    26.182772,
    39.36627
  ],
  "features": [
    {
      "geometry": {
        "type": "Point",
        "coordinates": [
          26.182772,
          39.36627
        ]
      },
      "id": "darmc-location-23612",
      "type": "Feature",
      "properties": {
        "description": "Point location",
        "location_precision": "precise",
        "title": "DARMC location 23612",
        "link": "http://pleiades.stoa.org/places/550747/darmc-location-23612"
      }
    }
  ]
}