{
  "type": "FeatureCollection",
  "title": "*Odon",
  "id": "550780",
  "bbox": [
    28.507199,
    38.723103,
    28.507199,
    38.723103
  ],
  "description": "An ancient place, cited: BAtlas 56 G4 *Odon",
  "names": [
    "Odon"
  ],
  "features": [
    {
      "type": "Feature",
      "geometry": {
        "type": "Point",
        "coordinates": [
          28.507199,
          38.723103
        ]
      },
      "properties": {
        "description": "representative point"
      }
    },
    {
      "geometry": {
        "type": "Point",
        "coordinates": [
          28.507199,
          38.723103
        ]
      },
      "id": "darmc-location-13984",
      "type": "Feature",
      "properties": {
        "description": "500K scale point location",
        "location_precision": "precise",
        "title": "DARMC location 13984",
        "link": "http://pleiades.stoa.org/places/550780/darmc-location-13984"
      }
    }
  ]
}