{
  "type": "FeatureCollection",
  "title": "*Misnya",
  "id": "550745",
  "bbox": [
    27.568638,
    38.86876,
    27.568638,
    38.86876
  ],
  "description": "An ancient place, cited: BAtlas 56 F4 *Misnya",
  "names": [
    "Misnya"
  ],
  "features": [
    {
      "type": "Feature",
      "geometry": {
        "type": "Point",
        "coordinates": [
          27.568638,
          38.86876
        ]
      },
      "properties": {
        "description": "representative point"
      }
    },
    {
      "geometry": {
        "type": "Point",
        "coordinates": [
          27.568638,
          38.86876
        ]
      },
      "id": "darmc-location-13757",
      "type": "Feature",
      "properties": {
        "description": "500K scale point location",
        "location_precision": "precise",
        "title": "DARMC location 13757",
        "link": "http://pleiades.stoa.org/places/550745/darmc-location-13757"
      }
    }
  ]
}