{
  "type": "FeatureCollection",
  "title": "Nakrason (or Nakrasos)",
  "id": "550767",
  "description": "An ancient settlement whose precise location is unknown. Modern scholars place it variously at Bakir, Maltepe, or İlyaslar in modern Turkey.",
  "bbox": [
    27.7034114,
    39.0799664,
    27.793814,
    39.083892
  ],
  "reprPoint": [
    27.7403034667,
    39.0823041333
  ],
  "names": [
    "Maltepe",
    "Nakrason"
  ],
  "features": [
    {
      "geometry": {
        "type": "Point",
        "coordinates": [
          27.723685,
          39.083892
        ]
      },
      "id": "maltepe",
      "type": "Feature",
      "properties": {
        "description": "Prehistoric settlement Höyük, associated by Ramsay with Nakrason. ",
        "location_precision": "precise",
        "title": "Maltepe: Imagery Location",
        "link": "http://pleiades.stoa.org/places/550767/maltepe"
      }
    },
    {
      "geometry": {
        "type": "Point",
        "coordinates": [
          27.7034114,
          39.0799664
        ]
      },
      "id": "bak131r-osm-location",
      "type": "Feature",
      "properties": {
        "description": "Possible location of Nakrason/Nakrasos. Location based on OpenStreetMap.",
        "location_precision": "precise",
        "title": "Bakır: OSM Location",
        "link": "http://pleiades.stoa.org/places/550767/bak131r-osm-location"
      }
    },
    {
      "geometry": {
        "type": "Point",
        "coordinates": [
          27.793814,
          39.083054
        ]
      },
      "id": "ilyaslar-osm-location",
      "type": "Feature",
      "properties": {
        "description": "Possible location of Nakrason/Nakrasos. Location based on OpenStreetMap",
        "location_precision": "precise",
        "title": "İlyaslar: OSM Location",
        "link": "http://pleiades.stoa.org/places/550767/ilyaslar-osm-location"
      }
    }
  ]
}