{
  "type": "FeatureCollection",
  "title": "Myrina",
  "id": "550755",
  "bbox": [
    25.0562181,
    39.8775033,
    25.0562181,
    39.8775033
  ],
  "description": "An ancient place, cited: BAtlas 56 A2 Myrina",
  "connectsWith": [
    "550693"
  ],
  "names": [
    "Myrina"
  ],
  "features": [
    {
      "type": "Feature",
      "geometry": {
        "type": "Point",
        "coordinates": [
          25.0562181,
          39.8775033
        ]
      },
      "properties": {
        "description": "representative point"
      }
    },
    {
      "geometry": {
        "type": "Point",
        "coordinates": [
          25.0562181,
          39.8775033
        ]
      },
      "id": "osm-location-of-myrina-castle",
      "type": "Feature",
      "properties": {
        "description": "Representative location based on OpenStreetMap",
        "location_precision": "precise",
        "title": "OSM location of Myrina Castle",
        "link": "http://pleiades.stoa.org/places/550755/osm-location-of-myrina-castle"
      }
    }
  ]
}