{
  "type": "FeatureCollection",
  "title": "Myrina",
  "id": "550755",
  "description": "An ancient place, cited: BAtlas 56 A2 Myrina",
  "bbox": [
    25.06186,
    39.878652,
    25.06186,
    39.878652
  ],
  "connectsWith": [
    "550693"
  ],
  "reprPoint": [
    25.06186,
    39.878652
  ],
  "names": [
    "Myrina"
  ],
  "features": [
    {
      "geometry": {
        "type": "Point",
        "coordinates": [
          25.06186,
          39.878652
        ]
      },
      "id": "darmc-location-5042",
      "type": "Feature",
      "properties": {
        "description": "500K scale point location",
        "location_precision": "precise",
        "title": "DARMC location 5042",
        "link": "http://pleiades.stoa.org/places/550755/darmc-location-5042"
      }
    }
  ]
}