{
  "type": "FeatureCollection",
  "title": "Skala ton Mistegnon",
  "id": "550887",
  "description": "An ancient place, cited: BAtlas 56 C3 Skala ton Mistegnon",
  "bbox": [
    26.469183,
    39.214228,
    26.469183,
    39.214228
  ],
  "reprPoint": [
    26.469183,
    39.214228
  ],
  "features": [
    {
      "geometry": {
        "type": "Point",
        "coordinates": [
          26.469183,
          39.214228
        ]
      },
      "id": "darmc-location-14628",
      "type": "Feature",
      "properties": {
        "description": "500K scale point location",
        "location_precision": "precise",
        "title": "DARMC location 14628",
        "link": "http://pleiades.stoa.org/places/550887/darmc-location-14628"
      }
    }
  ]
}