{
  "type": "FeatureCollection",
  "title": "Phara",
  "id": "550821",
  "bbox": [
    26.533442,
    39.069898,
    26.533442,
    39.069898
  ],
  "description": "An ancient place, cited: BAtlas 56 D3 Phara",
  "features": [
    {
      "type": "Feature",
      "geometry": {
        "type": "Point",
        "coordinates": [
          26.533442,
          39.069898
        ]
      },
      "properties": {
        "description": "representative point"
      }
    },
    {
      "geometry": {
        "type": "Point",
        "coordinates": [
          26.533442,
          39.069898
        ]
      },
      "id": "darmc-location-5497",
      "type": "Feature",
      "properties": {
        "description": "500K scale point location",
        "location_precision": "precise",
        "title": "DARMC location 5497",
        "link": "http://pleiades.stoa.org/places/550821/darmc-location-5497"
      }
    }
  ]
}