{
  "type": "FeatureCollection",
  "title": "Smyrna/Eurydikeia",
  "id": "550893",
  "description": "An ancient settlement of Asia Minor, modern Izmir in Turkey.",
  "bbox": [
    27.1383,
    38.4153421,
    27.144474,
    38.41905
  ],
  "connectsWith": [
    "dd0549616ada46adce2e94fc8387df77"
  ],
  "reprPoint": [
    27.141387,
    38.41719605
  ],
  "names": [
    "Smyrna",
    "Eurydikeia",
    "Zmyrna"
  ],
  "features": [
    {
      "geometry": {
        "type": "Point",
        "coordinates": [
          27.1383,
          38.41905
        ]
      },
      "id": "dare-location",
      "type": "Feature",
      "properties": {
        "description": "Representative point location, site precision",
        "location_precision": "precise",
        "title": "DARE Location",
        "link": "http://pleiades.stoa.org/places/550893/dare-location"
      }
    },
    {
      "geometry": {
        "type": "Point",
        "coordinates": [
          27.144474,
          38.4153421
        ]
      },
      "id": "izmir",
      "type": "Feature",
      "properties": {
        "description": "Location based on OpenStreetMap; Modern name for Smyrna",
        "location_precision": "precise",
        "title": "İzmir",
        "link": "http://pleiades.stoa.org/places/550893/izmir"
      }
    }
  ]
}