{
  "type": "FeatureCollection",
  "title": "Smyrna/Eurydikeia",
  "id": "550893",
  "bbox": [
    27.1383,
    38.4153421,
    27.144474,
    38.41905
  ],
  "description": "An ancient settlement of Asia Minor, modern Izmir in Turkey.",
  "connectsWith": [
    "837",
    "550771"
  ],
  "names": [
    "Smyrna",
    "Eurydikeia",
    "Zmyrna"
  ],
  "features": [
    {
      "type": "Feature",
      "geometry": {
        "type": "Point",
        "coordinates": [
          27.141387,
          38.41719605
        ]
      },
      "properties": {
        "description": "representative point"
      }
    },
    {
      "geometry": {
        "type": "Point",
        "coordinates": [
          27.1383,
          38.41905
        ]
      },
      "id": "dare-location",
      "type": "Feature",
      "properties": {
        "description": "Representative point location, site precision",
        "location_precision": "precise",
        "title": "DARE Location",
        "link": "http://pleiades.stoa.org/places/550893/dare-location"
      }
    },
    {
      "geometry": {
        "type": "Point",
        "coordinates": [
          27.144474,
          38.4153421
        ]
      },
      "id": "izmir",
      "type": "Feature",
      "properties": {
        "description": "Point geometry representing the center of the modern city of İzmir, Turkey, which is associated with the ancient site of Smyrna. Geometry derived from an OpenStreetMap node.",
        "location_precision": "precise",
        "title": "OSM location of modern İzmir, Turkey",
        "link": "http://pleiades.stoa.org/places/550893/izmir"
      }
    }
  ]
}