{
  "type": "FeatureCollection",
  "title": "*Selinda",
  "id": "550873",
  "bbox": [
    27.587778,
    38.391808,
    27.587778,
    38.391808
  ],
  "description": "An ancient place, cited: BAtlas 56 F5 *Selinda",
  "names": [
    "Selinda"
  ],
  "features": [
    {
      "type": "Feature",
      "geometry": {
        "type": "Point",
        "coordinates": [
          27.587778,
          38.391808
        ]
      },
      "properties": {
        "description": "representative point"
      }
    },
    {
      "geometry": {
        "type": "Point",
        "coordinates": [
          27.587778,
          38.391808
        ]
      },
      "id": "darmc-location-9523",
      "type": "Feature",
      "properties": {
        "description": "500K scale point location",
        "location_precision": "precise",
        "title": "DARMC location 9523",
        "link": "http://pleiades.stoa.org/places/550873/darmc-location-9523"
      }
    }
  ]
}