{
  "type": "FeatureCollection",
  "title": "Polichne",
  "id": "550839",
  "bbox": [
    26.768509,
    38.360198,
    26.768509,
    38.360198
  ],
  "description": "An ancient place, cited: BAtlas 56 D5 Polichne",
  "connectsWith": [
    "550650"
  ],
  "names": [
    "Polichne"
  ],
  "features": [
    {
      "type": "Feature",
      "geometry": {
        "type": "Point",
        "coordinates": [
          26.768509,
          38.360198
        ]
      },
      "properties": {
        "description": "representative point"
      }
    },
    {
      "geometry": {
        "type": "Point",
        "coordinates": [
          26.768509,
          38.360198
        ]
      },
      "id": "darmc-location-3047",
      "type": "Feature",
      "properties": {
        "description": "500K scale point location",
        "location_precision": "precise",
        "title": "DARMC location 3047",
        "link": "http://pleiades.stoa.org/places/550839/darmc-location-3047"
      }
    }
  ]
}