{
  "type": "FeatureCollection",
  "title": "Skala ton Mistegnon",
  "id": "550887",
  "bbox": [
    26.4736729,
    39.2146712,
    26.4736729,
    39.2146712
  ],
  "description": "An ancient place, cited: BAtlas 56 C3 Skala ton Mistegnon",
  "connectsWith": [
    "550696"
  ],
  "features": [
    {
      "type": "Feature",
      "geometry": {
        "type": "Point",
        "coordinates": [
          26.4736729,
          39.2146712
        ]
      },
      "properties": {
        "description": "representative point"
      }
    },
    {
      "geometry": {
        "type": "Point",
        "coordinates": [
          26.4736729,
          39.2146712
        ]
      },
      "id": "osm-location-of-skala-mistegnon",
      "type": "Feature",
      "properties": {
        "description": "Location based on OpenStreetMap",
        "location_precision": "precise",
        "title": "OSM location of Skala Mistegnon",
        "link": "http://pleiades.stoa.org/places/550887/osm-location-of-skala-mistegnon"
      }
    }
  ]
}