{
  "type": "FeatureCollection",
  "title": "*Polichna",
  "id": "550838",
  "description": "An ancient place, cited: BAtlas 56 D5 *Polichna",
  "bbox": [
    26.57715,
    38.429149,
    26.57715,
    38.429149
  ],
  "reprPoint": [
    26.57715,
    38.429149
  ],
  "names": [
    "Polichna"
  ],
  "features": [
    {
      "geometry": {
        "type": "Point",
        "coordinates": [
          26.57715,
          38.429149
        ]
      },
      "id": "darmc-location-3045",
      "type": "Feature",
      "properties": {
        "description": "500K scale point location",
        "location_precision": "precise",
        "title": "DARMC location 3045",
        "link": "http://pleiades.stoa.org/places/550838/darmc-location-3045"
      }
    }
  ]
}