{
  "type": "FeatureCollection",
  "title": "Psyra Ins.",
  "id": "550846",
  "description": "An ancient place, cited: BAtlas 56 B4 Psyra Ins.",
  "bbox": [
    25.586,
    38.567,
    25.586,
    38.567
  ],
  "connectsWith": [
    "550845"
  ],
  "reprPoint": [
    25.586,
    38.567
  ],
  "names": [
    "Psyra"
  ],
  "features": [
    {
      "geometry": {
        "type": "Point",
        "coordinates": [
          25.586,
          38.567
        ]
      },
      "id": "location-psyra-ins",
      "type": "Feature",
      "properties": {
        "description": "Coordinates after BAtlas, verified in Google Earth 2013 with reference to Wikipedia.",
        "location_precision": "precise",
        "title": "location Psyra Ins.",
        "link": "http://pleiades.stoa.org/places/550846/location-psyra-ins"
      }
    }
  ]
}