{
  "type": "FeatureCollection",
  "title": "Tiarai?",
  "id": "550931",
  "bbox": [
    27.100676,
    39.128826,
    27.100676,
    39.128826
  ],
  "description": "An ancient place, cited: BAtlas 56 E3 Tiarai?",
  "names": [
    "Tiarai"
  ],
  "features": [
    {
      "type": "Feature",
      "geometry": {
        "type": "Point",
        "coordinates": [
          27.100676,
          39.128826
        ]
      },
      "properties": {
        "description": "representative point"
      }
    },
    {
      "geometry": {
        "type": "Point",
        "coordinates": [
          27.100676,
          39.128826
        ]
      },
      "id": "darmc-location-15169",
      "type": "Feature",
      "properties": {
        "description": "500K scale point location",
        "location_precision": "precise",
        "title": "DARMC location 15169",
        "link": "http://pleiades.stoa.org/places/550931/darmc-location-15169"
      }
    }
  ]
}