{
  "type": "FeatureCollection",
  "title": "Yusufdere",
  "id": "550954",
  "description": "An ancient place, cited: BAtlas 56 F5 Yusufdere",
  "bbox": [
    27.832764,
    38.20437,
    27.832764,
    38.20437
  ],
  "reprPoint": [
    27.832764,
    38.20437
  ],
  "features": [
    {
      "geometry": {
        "type": "Point",
        "coordinates": [
          27.832764,
          38.20437
        ]
      },
      "id": "darmc-location-15494",
      "type": "Feature",
      "properties": {
        "description": "500K scale point location",
        "location_precision": "precise",
        "title": "DARMC location 15494",
        "link": "http://pleiades.stoa.org/places/550954/darmc-location-15494"
      }
    }
  ]
}