{
  "type": "FeatureCollection",
  "title": "Tyanollos",
  "id": "550949",
  "bbox": [
    27.737205,
    38.724873,
    27.737205,
    38.724873
  ],
  "description": "An ancient place, cited: BAtlas 56 F4 Tyanollos",
  "names": [
    "Tyanollos"
  ],
  "features": [
    {
      "type": "Feature",
      "geometry": {
        "type": "Point",
        "coordinates": [
          27.737205,
          38.724873
        ]
      },
      "properties": {
        "description": "representative point"
      }
    },
    {
      "geometry": {
        "type": "Point",
        "coordinates": [
          27.737205,
          38.724873
        ]
      },
      "id": "darmc-location-15292",
      "type": "Feature",
      "properties": {
        "description": "500K scale point location",
        "location_precision": "precise",
        "title": "DARMC location 15292",
        "link": "http://pleiades.stoa.org/places/550949/darmc-location-15292"
      }
    }
  ]
}