{
  "type": "FeatureCollection",
  "title": "Thymiana",
  "id": "550923",
  "description": "An ancient place, cited: BAtlas 56 C5 Thymiana",
  "bbox": [
    26.144497,
    38.323067,
    26.144497,
    38.323067
  ],
  "reprPoint": [
    26.144497,
    38.323067
  ],
  "features": [
    {
      "geometry": {
        "type": "Point",
        "coordinates": [
          26.144497,
          38.323067
        ]
      },
      "id": "darmc-location-9298",
      "type": "Feature",
      "properties": {
        "description": "500K scale point location",
        "location_precision": "precise",
        "title": "DARMC location 9298",
        "link": "http://pleiades.stoa.org/places/550923/darmc-location-9298"
      }
    }
  ]
}