{
  "type": "FeatureCollection",
  "title": "Pī-Kasî",
  "id": "552857304",
  "bbox": [
    44.6393,
    32.1311,
    44.6393,
    32.1311
  ],
  "description": "Site for the city of Pikasi dating back to the Old Babylonian period. A large number of cuneiform tablets were discovered there during excavations around year 2000.",
  "names": [
    "Tall Abū ‘Antīk"
  ],
  "features": [
    {
      "type": "Feature",
      "geometry": {
        "type": "Point",
        "coordinates": [
          44.6393,
          32.1311
        ]
      },
      "properties": {
        "description": "representative point"
      }
    },
    {
      "geometry": {
        "type": "Point",
        "coordinates": [
          44.6393,
          32.1311
        ]
      },
      "id": "cigs-location-of-tall-abu-2018antik",
      "type": "Feature",
      "properties": {
        "description": null,
        "location_precision": "precise",
        "title": "CIGS location of Tall Abū ‘Antīk",
        "link": "http://pleiades.stoa.org/places/552857304/cigs-location-of-tall-abu-2018antik"
      }
    }
  ]
}