{
  "type": "FeatureCollection",
  "title": "Temple of Vesta at Rome",
  "id": "55302071",
  "description": "The Temple of Vesta, located at the east end of the Forum Romanum.",
  "bbox": [
    12.4862,
    41.8917,
    12.4862,
    41.8917
  ],
  "connectsWith": [
    "423025"
  ],
  "reprPoint": [
    12.4862,
    41.8917
  ],
  "features": [
    {
      "geometry": {
        "type": "Point",
        "coordinates": [
          12.4862,
          41.8917
        ]
      },
      "id": "temple-of-vesta",
      "type": "Feature",
      "properties": {
        "description": "Representative point as determined from Google Earth. Dates after Platner & Ashby.",
        "location_precision": "precise",
        "title": "Imagery Location of the Temple of Vesta",
        "link": "http://pleiades.stoa.org/places/55302071/temple-of-vesta"
      }
    }
  ]
}