{
  "type": "FeatureCollection",
  "title": "Mernouphyta",
  "id": "554280",
  "bbox": [
    27.8357681,
    38.9197091,
    27.8366182,
    38.9206405
  ],
  "description": "An ancient place, cited: BAtlas 56 unlocated Mernouphyta",
  "connectsWith": [
    "177302800",
    "550924"
  ],
  "names": [
    "Mernouphyta"
  ],
  "features": [
    {
      "type": "Feature",
      "geometry": {
        "type": "Point",
        "coordinates": [
          27.8362201557,
          38.9201605136
        ]
      },
      "properties": {
        "description": "representative point"
      }
    },
    {
      "geometry": null,
      "id": "undetermined",
      "type": "Feature",
      "properties": {
        "description": null,
        "location_precision": "unlocated",
        "title": "Undetermined location",
        "link": "http://pleiades.stoa.org/places/554280/undetermined"
      }
    }
  ]
}