{
  "type": "FeatureCollection",
  "title": "Zeus Hyperdexios, T.",
  "id": "554343",
  "bbox": [
    26.1342123,
    39.2074811,
    26.1342123,
    39.2074811
  ],
  "description": "An ancient place, cited: BAtlas 56 unlocated Zeus Hyperdexios, T.",
  "connectsWith": [
    "550696"
  ],
  "names": [
    "Zeus Hyperdexios, T."
  ],
  "features": [
    {
      "type": "Feature",
      "geometry": {
        "type": "Point",
        "coordinates": [
          26.1342123,
          39.2074811
        ]
      },
      "properties": {
        "description": "representative point"
      }
    }
  ]
}