{
  "type": "FeatureCollection",
  "title": "Saar Site",
  "id": "56036938",
  "bbox": [
    50.4899482,
    26.184,
    50.4899482,
    26.184
  ],
  "description": "Early Dilmun settlement founded as early as 2300 BCE, with the main phase of the town being built around 1900 BCE. The site, which is located in modern Bahrain, continued in use around 100-200 years after the establishment of this main phase.",
  "connectsWith": [
    "932485"
  ],
  "names": [
    "Saar Heritage Park"
  ],
  "features": [
    {
      "type": "Feature",
      "geometry": {
        "type": "Point",
        "coordinates": [
          50.4899482,
          26.184
        ]
      },
      "properties": {
        "description": "representative point"
      }
    },
    {
      "geometry": {
        "type": "Point",
        "coordinates": [
          50.4899482,
          26.184
        ]
      },
      "id": "saar-unesco-archaeological-site",
      "type": "Feature",
      "properties": {
        "description": "Point based on an OpenStreetMap node representing the Saar Site.",
        "location_precision": "precise",
        "title": "OSM location of Saar Site",
        "link": "http://pleiades.stoa.org/places/56036938/saar-unesco-archaeological-site"
      }
    }
  ]
}