{
  "type": "FeatureCollection",
  "title": "Solsbury Hill",
  "id": "562474733",
  "description": "Solsbury Hill is a flat-topped hill in Somerset, England, that is the site of an Iron Age hill fort.",
  "bbox": [
    -2.3342785,
    51.4100777,
    -2.3339828,
    51.4112088
  ],
  "reprPoint": [
    -2.33413065,
    51.41064325
  ],
  "features": [
    {
      "geometry": {
        "type": "Point",
        "coordinates": [
          -2.3342785,
          51.4100777
        ]
      },
      "id": "location-of-little-solsbury-hill",
      "type": "Feature",
      "properties": {
        "description": "Location based on OpenStreetMap",
        "location_precision": "precise",
        "title": "location of Little Solsbury Hill",
        "link": "http://pleiades.stoa.org/places/562474733/location-of-little-solsbury-hill"
      }
    },
    {
      "geometry": {
        "type": "Point",
        "coordinates": [
          -2.3339828,
          51.4112088
        ]
      },
      "id": "location-of-solsbury-hill-hill-fort",
      "type": "Feature",
      "properties": {
        "description": "Location based on OpenStreetMap",
        "location_precision": "precise",
        "title": "location of Solsbury Hill hill fort",
        "link": "http://pleiades.stoa.org/places/562474733/location-of-solsbury-hill-hill-fort"
      }
    }
  ]
}