{
  "type": "FeatureCollection",
  "title": "Roman necropolis at al-Bass",
  "id": "562815441",
  "bbox": [
    35.212397,
    33.2702562,
    35.212397,
    33.2702562
  ],
  "description": "The Tyre necropolis, part of the UNESCO World Heritage site of Tyre, contains a triumphal arch and hundreds of stone sarcophagi dated to the Roman and Byzantine periods. It is located adjacent to an older Phoenician burial site.",
  "connectsWith": [
    "678437",
    "562815440"
  ],
  "names": [
    "al-Bass"
  ],
  "features": [
    {
      "type": "Feature",
      "geometry": {
        "type": "Point",
        "coordinates": [
          35.212397,
          33.2702562
        ]
      },
      "properties": {
        "description": "representative point"
      }
    },
    {
      "geometry": {
        "type": "Point",
        "coordinates": [
          35.212397,
          33.2702562
        ]
      },
      "id": "645642628631629-635648631",
      "type": "Feature",
      "properties": {
        "description": "Point representing the location of the Roman/Byzantine necropolis at Tyre el Bass, derived from an OpenStreetMap Node.",
        "location_precision": "precise",
        "title": "OSM location of مقبرة صور",
        "link": "http://pleiades.stoa.org/places/562815441/645642628631629-635648631"
      }
    }
  ]
}