{
  "type": "FeatureCollection",
  "title": "Acropolis?",
  "id": "564394244",
  "bbox": [
    22.11285,
    38.958218,
    22.11285,
    38.958218
  ],
  "description": "The possible location of the acropolis of Makra Kome, according to Stählin (1924, 224) and Béquignon (1937, 316).",
  "connectsWith": [
    "540926"
  ],
  "features": [
    {
      "type": "Feature",
      "geometry": {
        "type": "Point",
        "coordinates": [
          22.11285,
          38.958218
        ]
      },
      "properties": {
        "description": "representative point"
      }
    },
    {
      "geometry": {
        "type": "Point",
        "coordinates": [
          22.11285,
          38.958218
        ]
      },
      "id": "acropolis",
      "type": "Feature",
      "properties": {
        "description": "The possible location of the acropolis of Makra Kome, according to Stählin (1924, 224) and Béquignon (1937, 316).",
        "location_precision": "precise",
        "title": "Acropolis?",
        "link": "http://pleiades.stoa.org/places/564394244/acropolis"
      }
    }
  ]
}