{
  "type": "FeatureCollection",
  "title": "Pen-y-crug",
  "id": "56616071",
  "description": "Pen-y-crug is the location of an Iron Age hill fort in south Wales.",
  "bbox": [
    -3.4151171,
    51.9642927,
    -3.4151171,
    51.9642927
  ],
  "reprPoint": [
    -3.4151171,
    51.9642927
  ],
  "features": [
    {
      "geometry": {
        "type": "Point",
        "coordinates": [
          -3.4151171,
          51.9642927
        ]
      },
      "id": "location-of-pen-y-crug-hill-fort",
      "type": "Feature",
      "properties": {
        "description": "Location based on OpenStreetMap",
        "location_precision": "precise",
        "title": "location of Pen-y-crug hill fort",
        "link": "http://pleiades.stoa.org/places/56616071/location-of-pen-y-crug-hill-fort"
      }
    }
  ]
}