{
  "type": "FeatureCollection",
  "title": "Etruscan sanctuary of San Lorenzo Nuovo",
  "id": "56738064",
  "bbox": [
    11.9299311,
    42.6826138,
    11.9299311,
    42.6826138
  ],
  "description": "An Etruscan sanctuary located on Monte Landro northwest of Lake Bolsena.",
  "names": [
    "San Lorenzo Nuovo"
  ],
  "features": [
    {
      "type": "Feature",
      "geometry": {
        "type": "Point",
        "coordinates": [
          11.9299311,
          42.6826138
        ]
      },
      "properties": {
        "description": "representative point"
      }
    },
    {
      "geometry": {
        "type": "Point",
        "coordinates": [
          11.9299311,
          42.6826138
        ]
      },
      "id": "osm-location-of-monte-landro",
      "type": "Feature",
      "properties": {
        "description": "Representative location of summit of Monte Landro based on OpenStreetMap.",
        "location_precision": "precise",
        "title": "OSM location of Monte Landro",
        "link": "http://pleiades.stoa.org/places/56738064/osm-location-of-monte-landro"
      }
    }
  ]
}