{
  "type": "FeatureCollection",
  "title": "South Slope Spring",
  "id": "567540780",
  "bbox": [
    23.7260453,
    37.9707431,
    23.7260453,
    37.9707431
  ],
  "description": "A spring on the south slope of the Acropolis of Athens, sacred both to the nymphs and Pan.",
  "connectsWith": [
    "638356144"
  ],
  "names": [
    "South Slope Spring"
  ],
  "features": [
    {
      "type": "Feature",
      "geometry": {
        "type": "Point",
        "coordinates": [
          23.7260453,
          37.9707431
        ]
      },
      "properties": {
        "description": "representative point"
      }
    },
    {
      "geometry": {
        "type": "Point",
        "coordinates": [
          23.7260453,
          37.9707431
        ]
      },
      "id": "osm-location-byzantine-cistern",
      "type": "Feature",
      "properties": {
        "description": "Location based on OpenStreetMap",
        "location_precision": "precise",
        "title": "OSM Location: Byzantine Cistern",
        "link": "http://pleiades.stoa.org/places/567540780/osm-location-byzantine-cistern"
      }
    }
  ]
}