{
  "type": "FeatureCollection",
  "title": "Diavolino II tomb",
  "id": "569089650",
  "bbox": [
    10.9942084,
    42.8754314,
    10.9942084,
    42.8754314
  ],
  "description": "An Etruscan tomb of the seventh century B.C.",
  "connectsWith": [
    "403291"
  ],
  "features": [
    {
      "type": "Feature",
      "geometry": {
        "type": "Point",
        "coordinates": [
          10.9942084,
          42.8754314
        ]
      },
      "properties": {
        "description": "representative point"
      }
    },
    {
      "geometry": {
        "type": "Point",
        "coordinates": [
          10.9942084,
          42.8754314
        ]
      },
      "id": "location-of-diavolino-ii-tomb",
      "type": "Feature",
      "properties": {
        "description": "An Etruscan tomb of the seventh century BC. Location based on OpenStreetMap.",
        "location_precision": "precise",
        "title": "OSM location of 'Diavolino II' tomb",
        "link": "http://pleiades.stoa.org/places/569089650/location-of-diavolino-ii-tomb"
      }
    }
  ]
}