{
  "type": "FeatureCollection",
  "title": "Anemosa",
  "id": "570080",
  "description": "An ancient place, cited: BAtlas 58 C2 Anemosa",
  "bbox": [
    22.238568,
    37.571793,
    22.238568,
    37.571793
  ],
  "reprPoint": [
    22.238568,
    37.571793
  ],
  "names": [
    "Anemosa"
  ],
  "features": [
    {
      "geometry": {
        "type": "Point",
        "coordinates": [
          22.238568,
          37.571793
        ]
      },
      "id": "darmc-location-9955",
      "type": "Feature",
      "properties": {
        "description": "500K scale point location",
        "location_precision": "precise",
        "title": "DARMC location 9955",
        "link": "http://pleiades.stoa.org/places/570080/darmc-location-9955"
      }
    }
  ]
}