{
  "type": "FeatureCollection",
  "title": "Apollo Maleatas, T.",
  "id": "570097",
  "description": "An ancient place, cited: BAtlas 58 D3 Apollo Maleatas, T.",
  "bbox": [
    22.710967,
    37.12702,
    22.710967,
    37.12702
  ],
  "reprPoint": [
    22.710967,
    37.12702
  ],
  "names": [
    "Apollo Maleatas, T."
  ],
  "features": [
    {
      "geometry": {
        "type": "Point",
        "coordinates": [
          22.710967,
          37.12702
        ]
      },
      "id": "darmc-location-15878",
      "type": "Feature",
      "properties": {
        "description": "500K scale point location",
        "location_precision": "precise",
        "title": "DARMC location 15878",
        "link": "http://pleiades.stoa.org/places/570097/darmc-location-15878"
      }
    }
  ]
}