{
  "type": "FeatureCollection",
  "title": "Ag. Ioannis Khalara",
  "id": "570037",
  "bbox": [
    24.372386,
    37.680269,
    24.372386,
    37.680269
  ],
  "description": "An ancient place, cited: BAtlas 58 G2 Ag. Ioannis Khalara",
  "features": [
    {
      "type": "Feature",
      "geometry": {
        "type": "Point",
        "coordinates": [
          24.372386,
          37.680269
        ]
      },
      "properties": {
        "description": "representative point"
      }
    },
    {
      "geometry": {
        "type": "Point",
        "coordinates": [
          24.372386,
          37.680269
        ]
      },
      "id": "darmc-location-9158",
      "type": "Feature",
      "properties": {
        "description": "500K scale point location",
        "location_precision": "precise",
        "title": "DARMC location 9158",
        "link": "http://pleiades.stoa.org/places/570037/darmc-location-9158"
      }
    }
  ]
}