{
  "type": "FeatureCollection",
  "title": "Alea",
  "id": "570062",
  "bbox": [
    22.450785,
    37.794666,
    22.450785,
    37.794666
  ],
  "description": "An ancient place, cited: BAtlas 58 C2 Alea",
  "names": [
    "Alea"
  ],
  "features": [
    {
      "type": "Feature",
      "geometry": {
        "type": "Point",
        "coordinates": [
          22.450785,
          37.794666
        ]
      },
      "properties": {
        "description": "representative point"
      }
    },
    {
      "geometry": {
        "type": "Point",
        "coordinates": [
          22.450785,
          37.794666
        ]
      },
      "id": "darmc-location-11300",
      "type": "Feature",
      "properties": {
        "description": "500K scale point location",
        "location_precision": "precise",
        "title": "DARMC location 11300",
        "link": "http://pleiades.stoa.org/places/570062/darmc-location-11300"
      }
    }
  ]
}