{
  "type": "FeatureCollection",
  "title": "Angathia",
  "id": "570081",
  "bbox": [
    24.357182,
    36.725318,
    24.357182,
    36.725318
  ],
  "description": "An ancient place, cited: BAtlas 58 G4 Angathia",
  "connectsWith": [
    "570475"
  ],
  "features": [
    {
      "type": "Feature",
      "geometry": {
        "type": "Point",
        "coordinates": [
          24.357182,
          36.725318
        ]
      },
      "properties": {
        "description": "representative point"
      }
    },
    {
      "geometry": {
        "type": "Point",
        "coordinates": [
          24.357182,
          36.725318
        ]
      },
      "id": "darmc-location-17364",
      "type": "Feature",
      "properties": {
        "description": "500K scale point location",
        "location_precision": "precise",
        "title": "DARMC location 17364",
        "link": "http://pleiades.stoa.org/places/570081/darmc-location-17364"
      }
    }
  ]
}