{
  "type": "FeatureCollection",
  "title": "Aigai",
  "id": "570040",
  "bbox": [
    22.314637,
    38.154879,
    22.314637,
    38.154879
  ],
  "description": "An ancient settlement of Achaia in the Peloponnese. Modern Akrata.",
  "connectsWith": [
    "570028"
  ],
  "names": [
    "Aigai"
  ],
  "features": [
    {
      "type": "Feature",
      "geometry": {
        "type": "Point",
        "coordinates": [
          22.314637,
          38.154879
        ]
      },
      "properties": {
        "description": "representative point"
      }
    },
    {
      "geometry": {
        "type": "Point",
        "coordinates": [
          22.314637,
          38.154879
        ]
      },
      "id": "darmc-location-1052",
      "type": "Feature",
      "properties": {
        "description": "500K scale point location",
        "location_precision": "precise",
        "title": "DARMC location 1052",
        "link": "http://pleiades.stoa.org/places/570040/darmc-location-1052"
      }
    }
  ]
}