{
  "type": "FeatureCollection",
  "title": "Didymoi",
  "id": "570196",
  "bbox": [
    23.154194,
    37.500047,
    23.154194,
    37.500047
  ],
  "description": "A place described by Pausanias who indicates that three sanctuaries are to be found here, namely those of Apollo, Poseidon, and Demeter.",
  "names": [
    "Didymoi"
  ],
  "features": [
    {
      "type": "Feature",
      "geometry": {
        "type": "Point",
        "coordinates": [
          23.154194,
          37.500047
        ]
      },
      "properties": {
        "description": "representative point"
      }
    },
    {
      "geometry": {
        "type": "Point",
        "coordinates": [
          23.154194,
          37.500047
        ]
      },
      "id": "darmc-location-6526",
      "type": "Feature",
      "properties": {
        "description": "1:500,000 scale representative point location digitized from the Barrington Atlas of the Greek and Roman World by the Digital Atlas of Roman and Medieval Civilizations project at Harvard University.",
        "location_precision": "precise",
        "title": "DARMC location 6526",
        "link": "http://pleiades.stoa.org/places/570196/darmc-location-6526"
      }
    }
  ]
}