{
  "type": "FeatureCollection",
  "title": "Araxos Pr.",
  "id": "570101",
  "description": "An ancient place, cited: BAtlas 58 A1 Araxos Pr.",
  "bbox": [
    21.377,
    38.212,
    21.377,
    38.212
  ],
  "connectsWith": [
    "18d443f01c203e0b9c60f75ac332a6ba"
  ],
  "reprPoint": [
    21.377,
    38.212
  ],
  "names": [
    "Araxos Pr."
  ],
  "features": [
    {
      "geometry": {
        "type": "Point",
        "coordinates": [
          21.377,
          38.212
        ]
      },
      "id": "location-of-araxos-pr",
      "type": "Feature",
      "properties": {
        "description": "verified in Google Earth 2013 based on location in Barrington Atlas.",
        "location_precision": "precise",
        "title": "location of Araxos Pr.",
        "link": "http://pleiades.stoa.org/places/570101/location-of-araxos-pr"
      }
    }
  ]
}