{
  "type": "FeatureCollection",
  "title": "Araxos Pr.",
  "id": "570101",
  "description": "Cape Araxos separates the Gulf of Patras from the Ionian Sea.",
  "bbox": [
    21.377,
    38.212,
    21.377,
    38.212
  ],
  "connectsWith": [
    "570577"
  ],
  "reprPoint": [
    21.377,
    38.212
  ],
  "names": [
    "Araxos Pr."
  ],
  "features": [
    {
      "geometry": {
        "type": "Point",
        "coordinates": [
          21.377,
          38.212
        ]
      },
      "id": "location-of-araxos-pr",
      "type": "Feature",
      "properties": {
        "description": "verified in Google Earth 2013 based on location in Barrington Atlas.",
        "location_precision": "precise",
        "title": "Imagery location of Cape Araxos",
        "link": "http://pleiades.stoa.org/places/570101/location-of-araxos-pr"
      }
    }
  ]
}