{
  "type": "FeatureCollection",
  "title": "Boura",
  "id": "570166",
  "description": "An ancient place, cited: BAtlas 58 C1 Boura",
  "bbox": [
    22.231166,
    38.142006,
    22.231166,
    38.142006
  ],
  "reprPoint": [
    22.231166,
    38.142006
  ],
  "names": [
    "Boura"
  ],
  "features": [
    {
      "geometry": {
        "type": "Point",
        "coordinates": [
          22.231166,
          38.142006
        ]
      },
      "id": "darmc-location-9995",
      "type": "Feature",
      "properties": {
        "description": "500K scale point location",
        "location_precision": "precise",
        "title": "DARMC location 9995",
        "link": "http://pleiades.stoa.org/places/570166/darmc-location-9995"
      }
    }
  ]
}