{
  "type": "FeatureCollection",
  "title": "Artemision (mountain)",
  "id": "570121",
  "bbox": [
    22.514885,
    37.6197802,
    22.514885,
    37.6197802
  ],
  "description": "A mountain located between Argolis and Arcadia, with a temple of Artemis at its summit.",
  "names": [
    "Artemision"
  ],
  "features": [
    {
      "type": "Feature",
      "geometry": {
        "type": "Point",
        "coordinates": [
          22.514885,
          37.6197802
        ]
      },
      "properties": {
        "description": "representative point"
      }
    },
    {
      "geometry": {
        "type": "Point",
        "coordinates": [
          22.514885,
          37.6197802
        ]
      },
      "id": "osm-location-of-artemisio",
      "type": "Feature",
      "properties": {
        "description": "Location based on OpenStreetMap",
        "location_precision": "precise",
        "title": "OSM location of Artemisio",
        "link": "http://pleiades.stoa.org/places/570121/osm-location-of-artemisio"
      }
    }
  ]
}