{
  "type": "FeatureCollection",
  "title": "Kastro ano Diakopto",
  "id": "570166",
  "bbox": [
    22.2043433,
    38.14267,
    22.2065,
    38.142804
  ],
  "description": "Abundant spolia, artifacts, and building foundations provide evidence for an ancient settlement in the area of modern Kastro ano Diakopto and the church of Ag. Athanasios on the hill above it to the west. It is probably to be identified with ancient Boura, an attested settlement of Achaia.",
  "names": [
    "Boura"
  ],
  "features": [
    {
      "type": "Feature",
      "geometry": {
        "type": "Point",
        "coordinates": [
          22.20542165,
          38.142737
        ]
      },
      "properties": {
        "description": "representative point"
      }
    },
    {
      "geometry": {
        "type": "Point",
        "coordinates": [
          22.2043433,
          38.142804
        ]
      },
      "id": "osm-location-ii3i1i-i-ii-i-i1-2i-ii1i-i",
      "type": "Feature",
      "properties": {
        "description": "Location based on OpenStreetMap",
        "location_precision": "precise",
        "title": "OSM Location: Άγιος Αθανάσιος",
        "link": "http://pleiades.stoa.org/places/570166/osm-location-ii3i1i-i-ii-i-i1-2i-ii1i-i"
      }
    },
    {
      "geometry": {
        "type": "Point",
        "coordinates": [
          22.2065,
          38.14267
        ]
      },
      "id": "geonames-location-of-modern-kastro-ano-diakopto",
      "type": "Feature",
      "properties": {
        "description": "Point marking the modern location of the village that is probably to be associated with ancient Goura.",
        "location_precision": "precise",
        "title": "Geonames Location of Modern Kastro Ano Diakopto",
        "link": "http://pleiades.stoa.org/places/570166/geonames-location-of-modern-kastro-ano-diakopto"
      }
    }
  ]
}