{
  "type": "FeatureCollection",
  "title": "Aristonautai",
  "id": "570109",
  "bbox": [
    22.635738,
    38.076814,
    22.635738,
    38.076814
  ],
  "description": "An ancient place, cited: BAtlas 58 D1 Aristonautai",
  "names": [
    "Aristonautai"
  ],
  "features": [
    {
      "type": "Feature",
      "geometry": {
        "type": "Point",
        "coordinates": [
          22.635738,
          38.076814
        ]
      },
      "properties": {
        "description": "representative point"
      }
    },
    {
      "geometry": {
        "type": "Point",
        "coordinates": [
          22.635738,
          38.076814
        ]
      },
      "id": "darmc-location-24040",
      "type": "Feature",
      "properties": {
        "description": "1M scale point location",
        "location_precision": "precise",
        "title": "DARMC location 24040",
        "link": "http://pleiades.stoa.org/places/570109/darmc-location-24040"
      }
    }
  ]
}