{
  "type": "FeatureCollection",
  "title": "Didymoi",
  "id": "570196",
  "description": "An ancient place, cited: BAtlas 58 E3 Didymoi",
  "bbox": [
    23.154194,
    37.500047,
    23.154194,
    37.500047
  ],
  "reprPoint": [
    23.154194,
    37.500047
  ],
  "names": [
    "Didymoi"
  ],
  "features": [
    {
      "geometry": {
        "type": "Point",
        "coordinates": [
          23.154194,
          37.500047
        ]
      },
      "id": "darmc-location-6526",
      "type": "Feature",
      "properties": {
        "description": "500K scale point location",
        "location_precision": "precise",
        "title": "DARMC location 6526",
        "link": "http://pleiades.stoa.org/places/570196/darmc-location-6526"
      }
    }
  ]
}