{
  "type": "FeatureCollection",
  "title": "Athenaion",
  "id": "570137",
  "description": "An ancient place, cited: BAtlas 58 C3 Athenaion",
  "bbox": [
    22.258894,
    37.277285,
    22.258894,
    37.277285
  ],
  "reprPoint": [
    22.258894,
    37.277285
  ],
  "names": [
    "Athenaion"
  ],
  "features": [
    {
      "geometry": {
        "type": "Point",
        "coordinates": [
          22.258894,
          37.277285
        ]
      },
      "id": "darmc-location-1113",
      "type": "Feature",
      "properties": {
        "description": "500K scale point location",
        "location_precision": "precise",
        "title": "DARMC location 1113",
        "link": "http://pleiades.stoa.org/places/570137/darmc-location-1113"
      }
    }
  ]
}