{
  "type": "FeatureCollection",
  "title": "Boura",
  "id": "570166",
  "bbox": [
    22.2065,
    38.14267,
    22.2065,
    38.14267
  ],
  "description": "An ancient settlement of Achaia in the Peloponnese. Possibly in the area of modern Diakopto and Ano Diakopto.",
  "names": [
    "Boura"
  ],
  "features": [
    {
      "type": "Feature",
      "geometry": {
        "type": "Point",
        "coordinates": [
          22.2065,
          38.14267
        ]
      },
      "properties": {
        "description": "representative point"
      }
    },
    {
      "geometry": {
        "type": "Point",
        "coordinates": [
          22.2065,
          38.14267
        ]
      },
      "id": "geonames-location-of-modern-kastro-ano-diakopto",
      "type": "Feature",
      "properties": {
        "description": "Point marking the modern location of the village that is probably to be associated with ancient Goura.",
        "location_precision": "precise",
        "title": "Geonames Location of Modern Kastro Ano Diakopto",
        "link": "http://pleiades.stoa.org/places/570166/geonames-location-of-modern-kastro-ano-diakopto"
      }
    }
  ]
}