{
  "type": "FeatureCollection",
  "title": "Sanctuary of Eleusinian Demeter in Laconia",
  "id": "570216",
  "bbox": [
    22.4198,
    37.0138,
    22.4198,
    37.0138
  ],
  "description": "An extensive sanctuary mentioned by Pausanias and located at the modern village of Kalyvia Sochas by virtue of the discovery of a number of inscriptions on the site. Very little of the sanctuary is visible today, as the site was damaged by a number of floods and only ever partly excavated. Modern signage in the village marks the location of some finds.",
  "names": [
    "Kalyvia Sochas",
    "Eleusinion"
  ],
  "features": [
    {
      "type": "Feature",
      "geometry": {
        "type": "Point",
        "coordinates": [
          22.4198,
          37.0138
        ]
      },
      "properties": {
        "description": "representative point"
      }
    },
    {
      "geometry": {
        "type": "Point",
        "coordinates": [
          22.4198,
          37.0138
        ]
      },
      "id": "imagery-location-of-sanctuary",
      "type": "Feature",
      "properties": {
        "description": "Representative point derived from comparison of Cook's sketch map and Google Earth imagery (to include a Streetview image showing modern signage identifying the sanctuary area). Dates after BAtlas.",
        "location_precision": "precise",
        "title": "Imagery Location of Sanctuary",
        "link": "http://pleiades.stoa.org/places/570216/imagery-location-of-sanctuary"
      }
    }
  ]
}