{
  "type": "FeatureCollection",
  "title": "Drepanon (promontory)",
  "id": "570203",
  "bbox": [
    21.8493633,
    38.339024,
    21.8493633,
    38.339024
  ],
  "description": "The modern Cape Drepano, located at the western nnarrowing of the Corinthian Gulf, just east of Rhion/Antirrhion. ",
  "names": [
    "Drepanon Pr.",
    "Drepanon"
  ],
  "features": [
    {
      "type": "Feature",
      "geometry": {
        "type": "Point",
        "coordinates": [
          21.8493633,
          38.339024
        ]
      },
      "properties": {
        "description": "representative point"
      }
    },
    {
      "geometry": {
        "type": "Point",
        "coordinates": [
          21.8493633,
          38.339024
        ]
      },
      "id": "osm-location-of-modern-lighthouse-at-drepano-cape",
      "type": "Feature",
      "properties": {
        "description": "Location based on OpenStreetMap",
        "location_precision": "precise",
        "title": "OSM location of modern lighthouse at Drepano cape",
        "link": "http://pleiades.stoa.org/places/570203/osm-location-of-modern-lighthouse-at-drepano-cape"
      }
    }
  ]
}