{
  "type": "FeatureCollection",
  "title": "Erana",
  "id": "570232",
  "bbox": [
    21.600843,
    37.04374,
    21.600843,
    37.04374
  ],
  "description": "An ancient place, cited: BAtlas 58 B3 Erana",
  "names": [
    "Erana"
  ],
  "features": [
    {
      "type": "Feature",
      "geometry": {
        "type": "Point",
        "coordinates": [
          21.600843,
          37.04374
        ]
      },
      "properties": {
        "description": "representative point"
      }
    },
    {
      "geometry": {
        "type": "Point",
        "coordinates": [
          21.600843,
          37.04374
        ]
      },
      "id": "darmc-location-10044",
      "type": "Feature",
      "properties": {
        "description": "500K scale point location",
        "location_precision": "precise",
        "title": "DARMC location 10044",
        "link": "http://pleiades.stoa.org/places/570232/darmc-location-10044"
      }
    }
  ]
}