{
  "type": "FeatureCollection",
  "title": "Emborio",
  "id": "570224",
  "bbox": [
    24.3918219,
    36.7099574,
    24.3918219,
    36.7099574
  ],
  "description": "An ancient place, cited: BAtlas 58 G4 Emborio",
  "connectsWith": [
    "570475"
  ],
  "features": [
    {
      "type": "Feature",
      "geometry": {
        "type": "Point",
        "coordinates": [
          24.3918219,
          36.7099574
        ]
      },
      "properties": {
        "description": "representative point"
      }
    },
    {
      "geometry": {
        "type": "Point",
        "coordinates": [
          24.3918219,
          36.7099574
        ]
      },
      "id": "osm-location-of-modern-hamlet-of-empourios",
      "type": "Feature",
      "properties": {
        "description": "Location based on OpenStreetMap",
        "location_precision": "precise",
        "title": "OSM location of modern hamlet of Empourios",
        "link": "http://pleiades.stoa.org/places/570224/osm-location-of-modern-hamlet-of-empourios"
      }
    }
  ]
}