{
  "type": "FeatureCollection",
  "title": "Heraion",
  "id": "570288",
  "description": "An ancient place, cited: BAtlas 58 D1 Heraion",
  "bbox": [
    22.8522,
    38.028187,
    22.8522,
    38.028187
  ],
  "reprPoint": [
    22.8522,
    38.028187
  ],
  "names": [
    "Heraion"
  ],
  "features": [
    {
      "geometry": {
        "type": "Point",
        "coordinates": [
          22.856793,
          38.028036
        ]
      },
      "id": "darmc-location-6635",
      "type": "Feature",
      "properties": {
        "description": "500K scale point location",
        "location_precision": "precise",
        "title": "DARMC location 6635",
        "link": "http://pleiades.stoa.org/places/570288/darmc-location-6635"
      }
    },
    {
      "geometry": {
        "type": "Point",
        "coordinates": [
          22.854131,
          38.02054
        ]
      },
      "id": "darmc-location-24250",
      "type": "Feature",
      "properties": {
        "description": "1M scale point location",
        "location_precision": "precise",
        "title": "DARMC location 24250",
        "link": "http://pleiades.stoa.org/places/570288/darmc-location-24250"
      }
    },
    {
      "geometry": {
        "type": "Point",
        "coordinates": [
          22.8522,
          38.028187
        ]
      },
      "id": "dare-location",
      "type": "Feature",
      "properties": {
        "description": "Representative point location, site precision",
        "location_precision": "precise",
        "title": "DARE Location",
        "link": "http://pleiades.stoa.org/places/570288/dare-location"
      }
    }
  ]
}