{
  "type": "FeatureCollection",
  "title": "Eira",
  "id": "570209",
  "description": "An ancient place, cited: BAtlas 58 B3 Eira",
  "bbox": [
    21.927988,
    37.398271,
    21.927988,
    37.398271
  ],
  "reprPoint": [
    21.927988,
    37.398271
  ],
  "names": [
    "Eira",
    "Hira",
    "Ira",
    "Ire"
  ],
  "features": [
    {
      "geometry": {
        "type": "Point",
        "coordinates": [
          21.927988,
          37.398271
        ]
      },
      "id": "darmc-location-12306",
      "type": "Feature",
      "properties": {
        "description": "500K scale point location",
        "location_precision": "precise",
        "title": "DARMC location 12306",
        "link": "http://pleiades.stoa.org/places/570209/darmc-location-12306"
      }
    }
  ]
}