{
  "type": "FeatureCollection",
  "title": "Eleusinion",
  "id": "570216",
  "bbox": [
    22.420186,
    37.011458,
    22.420186,
    37.011458
  ],
  "description": "An ancient place, cited: BAtlas 58 C3 Eleusinion",
  "names": [
    "Eleusinion"
  ],
  "features": [
    {
      "type": "Feature",
      "geometry": {
        "type": "Point",
        "coordinates": [
          22.420186,
          37.011458
        ]
      },
      "properties": {
        "description": "representative point"
      }
    },
    {
      "geometry": {
        "type": "Point",
        "coordinates": [
          22.420186,
          37.011458
        ]
      },
      "id": "darmc-location-15949",
      "type": "Feature",
      "properties": {
        "description": "500K scale point location",
        "location_precision": "precise",
        "title": "DARMC location 15949",
        "link": "http://pleiades.stoa.org/places/570216/darmc-location-15949"
      }
    }
  ]
}