{
  "type": "FeatureCollection",
  "title": "Eileoi",
  "id": "570207",
  "description": "An ancient place, cited: BAtlas 58 E3 Eileoi",
  "bbox": [
    23.26405,
    37.442072,
    23.26405,
    37.442072
  ],
  "reprPoint": [
    23.26405,
    37.442072
  ],
  "names": [
    "Eileoi",
    "Ilei"
  ],
  "features": [
    {
      "geometry": {
        "type": "Point",
        "coordinates": [
          23.26405,
          37.442072
        ]
      },
      "id": "darmc-location-12302",
      "type": "Feature",
      "properties": {
        "description": "500K scale point location",
        "location_precision": "precise",
        "title": "DARMC location 12302",
        "link": "http://pleiades.stoa.org/places/570207/darmc-location-12302"
      }
    }
  ]
}