{
  "type": "FeatureCollection",
  "title": "Emborio",
  "id": "570224",
  "bbox": [
    24.393796,
    36.709481,
    24.393796,
    36.709481
  ],
  "description": "An ancient place, cited: BAtlas 58 G4 Emborio",
  "connectsWith": [
    "570475"
  ],
  "features": [
    {
      "type": "Feature",
      "geometry": {
        "type": "Point",
        "coordinates": [
          24.393796,
          36.709481
        ]
      },
      "properties": {
        "description": "representative point"
      }
    },
    {
      "geometry": {
        "type": "Point",
        "coordinates": [
          24.393796,
          36.709481
        ]
      },
      "id": "darmc-location-12337",
      "type": "Feature",
      "properties": {
        "description": "500K scale point location",
        "location_precision": "precise",
        "title": "DARMC location 12337",
        "link": "http://pleiades.stoa.org/places/570224/darmc-location-12337"
      }
    }
  ]
}