{
  "type": "FeatureCollection",
  "title": "Hormina? M.",
  "id": "570296",
  "bbox": [
    21.141944,
    37.890278,
    21.141944,
    37.890278
  ],
  "description": "An ancient place, cited: BAtlas 58 A2 Hormina? M.",
  "names": [
    "Hormina M.",
    "Hyrmina"
  ],
  "features": [
    {
      "type": "Feature",
      "geometry": {
        "type": "Point",
        "coordinates": [
          21.141944,
          37.890278
        ]
      },
      "properties": {
        "description": "representative point"
      }
    },
    {
      "geometry": {
        "type": "Point",
        "coordinates": [
          21.141944,
          37.890278
        ]
      },
      "id": "osm-node-85850809",
      "type": "Feature",
      "properties": {
        "description": "Medieval castle on Hormina(?) Mons",
        "location_precision": "precise",
        "title": "Chlemoutsi",
        "link": "http://pleiades.stoa.org/places/570296/osm-node-85850809"
      }
    }
  ]
}