{
  "type": "FeatureCollection",
  "title": "Kainepolis",
  "id": "570322",
  "description": "An ancient place, cited: BAtlas 58 C5 Kainepolis",
  "bbox": [
    22.442714,
    36.460433,
    22.442714,
    36.460433
  ],
  "reprPoint": [
    22.442714,
    36.460433
  ],
  "names": [
    "Kainepolis",
    "Kaine"
  ],
  "features": [
    {
      "geometry": {
        "type": "Point",
        "coordinates": [
          22.442714,
          36.460433
        ]
      },
      "id": "darmc-location-12947",
      "type": "Feature",
      "properties": {
        "description": "500K scale point location",
        "location_precision": "precise",
        "title": "DARMC location 12947",
        "link": "http://pleiades.stoa.org/places/570322/darmc-location-12947"
      }
    }
  ]
}