{
  "type": "FeatureCollection",
  "title": "Karyai?/Iasos?",
  "id": "570335",
  "description": "An ancient place, cited: BAtlas 58 C3 Karyai?/Iasos?",
  "bbox": [
    22.416759,
    37.332128,
    22.416759,
    37.332128
  ],
  "reprPoint": [
    22.416759,
    37.332128
  ],
  "names": [
    "Karyai",
    "Iasos"
  ],
  "features": [
    {
      "geometry": {
        "type": "Point",
        "coordinates": [
          22.416759,
          37.332128
        ]
      },
      "id": "darmc-location-4058",
      "type": "Feature",
      "properties": {
        "description": "500K scale point location",
        "location_precision": "precise",
        "title": "DARMC location 4058",
        "link": "http://pleiades.stoa.org/places/570335/darmc-location-4058"
      }
    }
  ]
}