{
  "type": "FeatureCollection",
  "title": "Isthmos",
  "id": "570317",
  "bbox": [
    22.987778,
    37.941389,
    22.987778,
    37.941389
  ],
  "description": "The Isthmus of Corinth is a narrow land bridge connecting the Peloponnese peninsula to the Greek mainland.",
  "names": [
    "Isthmos",
    "Isthmus of Corinth"
  ],
  "features": [
    {
      "type": "Feature",
      "geometry": {
        "type": "Point",
        "coordinates": [
          22.987778,
          37.941389
        ]
      },
      "properties": {
        "description": "representative point"
      }
    },
    {
      "geometry": {
        "type": "Point",
        "coordinates": [
          22.987778,
          37.941389
        ]
      },
      "id": "location-of-isthmos",
      "type": "Feature",
      "properties": {
        "description": "coordinates after GeoHack, verified in Google Earth.",
        "location_precision": "precise",
        "title": "Imagery location of Isthmos",
        "link": "http://pleiades.stoa.org/places/570317/location-of-isthmos"
      }
    }
  ]
}