{
  "type": "FeatureCollection",
  "title": "Kyllene M.",
  "id": "570391",
  "bbox": [
    22.3969314,
    37.9397231,
    22.3969314,
    37.9397231
  ],
  "description": "An ancient place, cited: BAtlas 58 C2 Kyllene M.",
  "names": [
    "Kyllene M."
  ],
  "features": [
    {
      "type": "Feature",
      "geometry": {
        "type": "Point",
        "coordinates": [
          22.3969314,
          37.9397231
        ]
      },
      "properties": {
        "description": "representative point"
      }
    },
    {
      "geometry": {
        "type": "Point",
        "coordinates": [
          22.3969314,
          37.9397231
        ]
      },
      "id": "location-of-Kyllene-M",
      "type": "Feature",
      "properties": {
        "description": "Location based on OpenStreetMap",
        "location_precision": "precise",
        "title": "location of Kyllene M.",
        "link": "http://pleiades.stoa.org/places/570391/location-of-Kyllene-M"
      }
    }
  ]
}