{
  "type": "FeatureCollection",
  "title": "Kastri",
  "id": "570338",
  "bbox": [
    24.392812,
    37.661885,
    24.392812,
    37.661885
  ],
  "description": "An ancient place, cited: BAtlas 58 G2 Kastri",
  "connectsWith": [
    "570348"
  ],
  "features": [
    {
      "type": "Feature",
      "geometry": {
        "type": "Point",
        "coordinates": [
          24.392812,
          37.661885
        ]
      },
      "properties": {
        "description": "representative point"
      }
    },
    {
      "geometry": {
        "type": "Point",
        "coordinates": [
          24.392812,
          37.661885
        ]
      },
      "id": "batlas-location-of-kastri",
      "type": "Feature",
      "properties": {
        "description": "Location determined via digitized version of BAtlas 58. Dates after BAltDir.",
        "location_precision": "precise",
        "title": "BAtlas Location of Kastri",
        "link": "http://pleiades.stoa.org/places/570338/batlas-location-of-kastri"
      }
    }
  ]
}