{
  "type": "FeatureCollection",
  "title": "Kalamai",
  "id": "570323",
  "bbox": [
    22.178607,
    37.045209,
    22.178607,
    37.045209
  ],
  "description": "An ancient place, cited: BAtlas 58 C3 Kalamai",
  "names": [
    "Kalamai"
  ],
  "features": [
    {
      "type": "Feature",
      "geometry": {
        "type": "Point",
        "coordinates": [
          22.178607,
          37.045209
        ]
      },
      "properties": {
        "description": "representative point"
      }
    },
    {
      "geometry": {
        "type": "Point",
        "coordinates": [
          22.178607,
          37.045209
        ]
      },
      "id": "darmc-location-12951",
      "type": "Feature",
      "properties": {
        "description": "1:500,000 scale representative point location digitized from the Barrington Atlas of the Greek and Roman World by the Digital Atlas of Roman and Medieval Civilizations project at Harvard University.",
        "location_precision": "precise",
        "title": "DARMC location 12951",
        "link": "http://pleiades.stoa.org/places/570323/darmc-location-12951"
      }
    }
  ]
}