{
  "type": "FeatureCollection",
  "title": "Karnasion",
  "id": "570331",
  "bbox": [
    21.948808,
    37.266348,
    21.948808,
    37.266348
  ],
  "description": "An ancient place, cited: BAtlas 58 B3 Karnasion",
  "names": [
    "Karnasion"
  ],
  "features": [
    {
      "type": "Feature",
      "geometry": {
        "type": "Point",
        "coordinates": [
          21.948808,
          37.266348
        ]
      },
      "properties": {
        "description": "representative point"
      }
    },
    {
      "geometry": {
        "type": "Point",
        "coordinates": [
          21.948808,
          37.266348
        ]
      },
      "id": "darmc-location-16024",
      "type": "Feature",
      "properties": {
        "description": "1:500,000 scale representative point location digitized from the Barrington Atlas of the Greek and Roman World by the Digital Atlas of Roman and Medieval Civilizations project at Harvard University.",
        "location_precision": "precise",
        "title": "DARMC location 16024",
        "link": "http://pleiades.stoa.org/places/570331/darmc-location-16024"
      }
    }
  ]
}