{
  "type": "FeatureCollection",
  "title": "Karnasion",
  "id": "570331",
  "description": "An ancient place, cited: BAtlas 58 B3 Karnasion",
  "bbox": [
    21.948808,
    37.266348,
    21.948808,
    37.266348
  ],
  "reprPoint": [
    21.948808,
    37.266348
  ],
  "names": [
    "Karnasion"
  ],
  "features": [
    {
      "geometry": {
        "type": "Point",
        "coordinates": [
          21.948808,
          37.266348
        ]
      },
      "id": "darmc-location-16024",
      "type": "Feature",
      "properties": {
        "description": "500K scale point location",
        "location_precision": "precise",
        "title": "DARMC location 16024",
        "link": "http://pleiades.stoa.org/places/570331/darmc-location-16024"
      }
    }
  ]
}