{
  "type": "FeatureCollection",
  "title": "Kainepolis",
  "id": "570322",
  "bbox": [
    22.442714,
    36.460433,
    22.442714,
    36.460433
  ],
  "description": "An ancient place, cited: BAtlas 58 C5 Kainepolis",
  "names": [
    "Kainepolis",
    "Kaine"
  ],
  "features": [
    {
      "type": "Feature",
      "geometry": {
        "type": "Point",
        "coordinates": [
          22.442714,
          36.460433
        ]
      },
      "properties": {
        "description": "representative point"
      }
    },
    {
      "geometry": {
        "type": "Point",
        "coordinates": [
          22.442714,
          36.460433
        ]
      },
      "id": "darmc-location-12947",
      "type": "Feature",
      "properties": {
        "description": "1:500,000 scale representative point location digitized from the Barrington Atlas of the Greek and Roman World by the Digital Atlas of Roman and Medieval Civilizations project at Harvard University.",
        "location_precision": "precise",
        "title": "DARMC location 12947",
        "link": "http://pleiades.stoa.org/places/570322/darmc-location-12947"
      }
    }
  ]
}