{
  "type": "FeatureCollection",
  "title": "Messene",
  "id": "570479",
  "description": "Capital of Messenia",
  "bbox": [
    21.920439,
    37.175372,
    21.920524,
    37.175491
  ],
  "connectsWith": [
    "570480",
    "570318"
  ],
  "reprPoint": [
    21.9204815,
    37.1754315
  ],
  "names": [
    "Messene",
    "Ithome"
  ],
  "features": [
    {
      "geometry": {
        "type": "Point",
        "coordinates": [
          21.922941,
          37.183107
        ]
      },
      "id": "darmc-location-4806",
      "type": "Feature",
      "properties": {
        "description": "500K scale point location",
        "location_precision": "precise",
        "title": "DARMC location 4806",
        "link": "http://pleiades.stoa.org/places/570479/darmc-location-4806"
      }
    },
    {
      "geometry": {
        "type": "Point",
        "coordinates": [
          22.008168,
          37.051474
        ]
      },
      "id": "darmc-location-24083",
      "type": "Feature",
      "properties": {
        "description": "5M scale point location",
        "location_precision": "precise",
        "title": "DARMC location 24083",
        "link": "http://pleiades.stoa.org/places/570479/darmc-location-24083"
      }
    },
    {
      "geometry": {
        "type": "Point",
        "coordinates": [
          21.920524,
          37.175372
        ]
      },
      "id": "the-asklepieion",
      "type": "Feature",
      "properties": {
        "description": "The Asklepieion in Ancient Messene is a sanctuary of Asklepios, Greek god of healing, constructed in 214 BC; the complex includes civic as well as religious buildings",
        "location_precision": "precise",
        "title": "Asklepieion of Messene",
        "link": "http://pleiades.stoa.org/places/570479/the-asklepieion"
      }
    },
    {
      "geometry": {
        "type": "Point",
        "coordinates": [
          21.920439,
          37.175491
        ]
      },
      "id": "dare-location",
      "type": "Feature",
      "properties": {
        "description": "Representative point location, site precision",
        "location_precision": "precise",
        "title": "DARE Location",
        "link": "http://pleiades.stoa.org/places/570479/dare-location"
      }
    }
  ]
}