{
  "type": "FeatureCollection",
  "title": "Kythnos (island)",
  "id": "570403",
  "bbox": [
    24.3890287,
    37.3847165,
    24.3890287,
    37.3847165
  ],
  "description": "Kythnos is an island in the Aegean Sea and one of the Cyclades.",
  "connectsWith": [
    "560353"
  ],
  "names": [
    "Kythnos",
    "Cythnus"
  ],
  "features": [
    {
      "type": "Feature",
      "geometry": {
        "type": "Point",
        "coordinates": [
          24.3890287,
          37.3847165
        ]
      },
      "properties": {
        "description": "representative point"
      }
    },
    {
      "geometry": {
        "type": "Point",
        "coordinates": [
          24.3890287,
          37.3847165
        ]
      },
      "id": "osm-location",
      "type": "Feature",
      "properties": {
        "description": "Location based on OpenStreetMap",
        "location_precision": "precise",
        "title": "OSM location",
        "link": "http://pleiades.stoa.org/places/570403/osm-location"
      }
    }
  ]
}