{
  "type": "FeatureCollection",
  "title": "Malea",
  "id": "570454",
  "description": "An ancient place, cited: BAtlas 58 C3 Malea",
  "bbox": [
    22.168781,
    37.327556,
    22.168781,
    37.327556
  ],
  "reprPoint": [
    22.168781,
    37.327556
  ],
  "names": [
    "Malea",
    "Malaia"
  ],
  "features": [
    {
      "geometry": {
        "type": "Point",
        "coordinates": [
          22.168781,
          37.327556
        ]
      },
      "id": "darmc-location-4661",
      "type": "Feature",
      "properties": {
        "description": "500K scale point location",
        "location_precision": "precise",
        "title": "DARMC location 4661",
        "link": "http://pleiades.stoa.org/places/570454/darmc-location-4661"
      }
    }
  ]
}