{
  "type": "FeatureCollection",
  "title": "Lyrkeia",
  "id": "570446",
  "bbox": [
    22.643094,
    37.686635,
    22.643094,
    37.686635
  ],
  "description": "An ancient place, cited: BAtlas 58 D2 Lyrkeia",
  "names": [
    "Lyrkeia",
    "Lynkea"
  ],
  "features": [
    {
      "type": "Feature",
      "geometry": {
        "type": "Point",
        "coordinates": [
          22.643094,
          37.686635
        ]
      },
      "properties": {
        "description": "representative point"
      }
    },
    {
      "geometry": {
        "type": "Point",
        "coordinates": [
          22.643094,
          37.686635
        ]
      },
      "id": "darmc-location-13556",
      "type": "Feature",
      "properties": {
        "description": "500K scale point location",
        "location_precision": "precise",
        "title": "DARMC location 13556",
        "link": "http://pleiades.stoa.org/places/570446/darmc-location-13556"
      }
    }
  ]
}