{
  "type": "FeatureCollection",
  "title": "Messene",
  "id": "570479",
  "bbox": [
    21.920439,
    37.175491,
    21.922941,
    37.183107
  ],
  "description": "Capital of Messenia",
  "connectsWith": [
    "570480",
    "570318"
  ],
  "names": [
    "Messene",
    "Ithome"
  ],
  "features": [
    {
      "type": "Feature",
      "geometry": {
        "type": "Point",
        "coordinates": [
          21.92169,
          37.179299
        ]
      },
      "properties": {
        "description": "representative point"
      }
    },
    {
      "geometry": {
        "type": "Point",
        "coordinates": [
          21.922941,
          37.183107
        ]
      },
      "id": "darmc-location-4806",
      "type": "Feature",
      "properties": {
        "description": "500K scale point location",
        "location_precision": "precise",
        "title": "DARMC location 4806",
        "link": "http://pleiades.stoa.org/places/570479/darmc-location-4806"
      }
    },
    {
      "geometry": {
        "type": "Point",
        "coordinates": [
          21.920439,
          37.175491
        ]
      },
      "id": "dare-location",
      "type": "Feature",
      "properties": {
        "description": "Representative point location, site precision",
        "location_precision": "precise",
        "title": "DARE Location",
        "link": "http://pleiades.stoa.org/places/570479/dare-location"
      }
    }
  ]
}