{
  "type": "FeatureCollection",
  "title": "Melpeia",
  "id": "570476",
  "description": "An ancient place, cited: BAtlas 58 B3 Melpeia",
  "bbox": [
    21.963136,
    37.43148,
    21.963136,
    37.43148
  ],
  "reprPoint": [
    21.963136,
    37.43148
  ],
  "names": [
    "Melpeia"
  ],
  "features": [
    {
      "geometry": {
        "type": "Point",
        "coordinates": [
          21.963136,
          37.43148
        ]
      },
      "id": "darmc-location-16079",
      "type": "Feature",
      "properties": {
        "description": "500K scale point location",
        "location_precision": "precise",
        "title": "DARMC location 16079",
        "link": "http://pleiades.stoa.org/places/570476/darmc-location-16079"
      }
    }
  ]
}