{
  "type": "FeatureCollection",
  "title": "Letrinoi",
  "id": "570427",
  "description": "An ancient place, cited: BAtlas 58 A2 Letrinoi",
  "bbox": [
    21.431292,
    37.672865,
    21.431292,
    37.672865
  ],
  "reprPoint": [
    21.431292,
    37.672865
  ],
  "names": [
    "Letrinoi"
  ],
  "features": [
    {
      "geometry": {
        "type": "Point",
        "coordinates": [
          21.431292,
          37.672865
        ]
      },
      "id": "darmc-location-10116",
      "type": "Feature",
      "properties": {
        "description": "500K scale point location",
        "location_precision": "precise",
        "title": "DARMC location 10116",
        "link": "http://pleiades.stoa.org/places/570427/darmc-location-10116"
      }
    }
  ]
}