{
  "type": "FeatureCollection",
  "title": "Oion",
  "id": "570525",
  "bbox": [
    22.395174,
    37.365486,
    22.395174,
    37.365486
  ],
  "description": "An ancient place, cited: BAtlas 58 C3 Oion",
  "names": [
    "Oion"
  ],
  "features": [
    {
      "type": "Feature",
      "geometry": {
        "type": "Point",
        "coordinates": [
          22.395174,
          37.365486
        ]
      },
      "properties": {
        "description": "representative point"
      }
    },
    {
      "geometry": {
        "type": "Point",
        "coordinates": [
          22.395174,
          37.365486
        ]
      },
      "id": "darmc-location-3906",
      "type": "Feature",
      "properties": {
        "description": "500K scale point location",
        "location_precision": "precise",
        "title": "DARMC location 3906",
        "link": "http://pleiades.stoa.org/places/570525/darmc-location-3906"
      }
    }
  ]
}