{
  "type": "FeatureCollection",
  "title": "Panormos (settlement, port)",
  "id": "570555",
  "bbox": [
    21.81667,
    38.31667,
    21.81667,
    38.31667
  ],
  "description": "An ancient settlement presumed to have been co-located with a harbor (limen) mentioned by Pausanias as lying 15 stadia east of the Rhion Pr. (modern Rio in Greece), on the north coast of the Peloponnese.",
  "connectsWith": [
    "570577",
    "570556"
  ],
  "names": [
    "Panormos"
  ],
  "features": [
    {
      "type": "Feature",
      "geometry": {
        "type": "Point",
        "coordinates": [
          21.81667,
          38.31667
        ]
      },
      "properties": {
        "description": "representative point"
      }
    },
    {
      "geometry": {
        "type": "Point",
        "coordinates": [
          21.81667,
          38.31667
        ]
      },
      "id": "ayios-vasilios",
      "type": "Feature",
      "properties": {
        "description": "Modern location in the general area identified by John McK. Camp II for Pausanias' Panormos limen. After Geonames, verified in Google Earth.",
        "location_precision": "precise",
        "title": "Ayios Vasilios",
        "link": "http://pleiades.stoa.org/places/570555/ayios-vasilios"
      }
    }
  ]
}