{
  "type": "FeatureCollection",
  "title": "Pelekoudi",
  "id": "570574",
  "bbox": [
    24.524083,
    36.766179,
    24.524083,
    36.766179
  ],
  "description": "An ancient place, cited: BAtlas 58 H4 Pelekoudi",
  "connectsWith": [
    "570475"
  ],
  "features": [
    {
      "type": "Feature",
      "geometry": {
        "type": "Point",
        "coordinates": [
          24.524083,
          36.766179
        ]
      },
      "properties": {
        "description": "representative point"
      }
    },
    {
      "geometry": {
        "type": "Point",
        "coordinates": [
          24.524083,
          36.766179
        ]
      },
      "id": "darmc-location-14169",
      "type": "Feature",
      "properties": {
        "description": "500K scale point location",
        "location_precision": "precise",
        "title": "DARMC location 14169",
        "link": "http://pleiades.stoa.org/places/570574/darmc-location-14169"
      }
    }
  ]
}