{
  "type": "FeatureCollection",
  "title": "Pheraia",
  "id": "570597",
  "description": "An ancient place, cited: BAtlas 58 B2 Pheraia",
  "bbox": [
    21.794283,
    37.696919,
    21.794283,
    37.696919
  ],
  "reprPoint": [
    21.794283,
    37.696919
  ],
  "names": [
    "Pheraia",
    "Pharaia"
  ],
  "features": [
    {
      "geometry": {
        "type": "Point",
        "coordinates": [
          21.794283,
          37.696919
        ]
      },
      "id": "darmc-location-10198",
      "type": "Feature",
      "properties": {
        "description": "500K scale point location",
        "location_precision": "precise",
        "title": "DARMC location 10198",
        "link": "http://pleiades.stoa.org/places/570597/darmc-location-10198"
      }
    }
  ]
}