{
  "type": "FeatureCollection",
  "title": "Olenos",
  "id": "570528",
  "bbox": [
    21.640599,
    38.153707,
    21.640599,
    38.153707
  ],
  "description": "An ancient place, cited: BAtlas 58 B1 Olenos",
  "names": [
    "Olenos"
  ],
  "features": [
    {
      "type": "Feature",
      "geometry": {
        "type": "Point",
        "coordinates": [
          21.640599,
          38.153707
        ]
      },
      "properties": {
        "description": "representative point"
      }
    },
    {
      "geometry": {
        "type": "Point",
        "coordinates": [
          21.640599,
          38.153707
        ]
      },
      "id": "darmc-location-10161",
      "type": "Feature",
      "properties": {
        "description": "500K scale point location",
        "location_precision": "precise",
        "title": "DARMC location 10161",
        "link": "http://pleiades.stoa.org/places/570528/darmc-location-10161"
      }
    }
  ]
}