{
  "type": "FeatureCollection",
  "title": "Pheneos",
  "id": "570595",
  "bbox": [
    22.295238,
    37.919454,
    22.295238,
    37.919454
  ],
  "description": "An ancient place, cited: BAtlas 58 C2 Pheneos",
  "names": [
    "Pheneos"
  ],
  "features": [
    {
      "type": "Feature",
      "geometry": {
        "type": "Point",
        "coordinates": [
          22.295238,
          37.919454
        ]
      },
      "properties": {
        "description": "representative point"
      }
    },
    {
      "geometry": {
        "type": "Point",
        "coordinates": [
          22.295238,
          37.919454
        ]
      },
      "id": "darmc-location-14237",
      "type": "Feature",
      "properties": {
        "description": "1:500,000 scale representative point location digitized from the Barrington Atlas of the Greek and Roman World by the Digital Atlas of Roman and Medieval Civilizations project at Harvard University.",
        "location_precision": "precise",
        "title": "DARMC location 14237",
        "link": "http://pleiades.stoa.org/places/570595/darmc-location-14237"
      }
    }
  ]
}