{
  "type": "FeatureCollection",
  "title": "Mithraeum at Vulci",
  "id": "570500583",
  "bbox": [
    11.6299585,
    42.4194343,
    11.6299585,
    42.4194343
  ],
  "description": "A mithraeum was discovered at Vulci in 1975 during excavations of a Roman aristocratic house.  The shrine was well preserved with two tauroctony scenes dating to the third century. The site was destroyed in the fourth century A.D.",
  "connectsWith": [
    "413393"
  ],
  "features": [
    {
      "type": "Feature",
      "geometry": {
        "type": "Point",
        "coordinates": [
          11.6299585,
          42.4194343
        ]
      },
      "properties": {
        "description": "representative point"
      }
    },
    {
      "geometry": {
        "type": "Point",
        "coordinates": [
          11.6299585,
          42.4194343
        ]
      },
      "id": "location-of-mithraeum",
      "type": "Feature",
      "properties": {
        "description": "Location based on OpenStreetMap",
        "location_precision": "precise",
        "title": "OSM location of Mithraeum",
        "link": "http://pleiades.stoa.org/places/570500583/location-of-mithraeum"
      }
    }
  ]
}