{
  "type": "FeatureCollection",
  "title": "Sicyon/Demetrias",
  "id": "570668",
  "description": "An ancient place, cited: BAtlas 58 D2 Sicyon/Demetrias",
  "bbox": [
    22.711059,
    37.984123,
    22.711059,
    37.984123
  ],
  "reprPoint": [
    22.711059,
    37.984123
  ],
  "names": [
    "Sicyon",
    "Demetrias",
    "Aigialeia",
    "Mekora"
  ],
  "features": [
    {
      "geometry": {
        "type": "Point",
        "coordinates": [
          22.722718,
          37.980475
        ]
      },
      "id": "darmc-location-24101",
      "type": "Feature",
      "properties": {
        "description": "1M scale point location",
        "location_precision": "precise",
        "title": "DARMC location 24101",
        "link": "http://pleiades.stoa.org/places/570668/darmc-location-24101"
      }
    },
    {
      "geometry": {
        "type": "Point",
        "coordinates": [
          22.711059,
          37.984123
        ]
      },
      "id": "dare-location",
      "type": "Feature",
      "properties": {
        "description": "Representative point location, site precision",
        "location_precision": "precise",
        "title": "DARE Location",
        "link": "http://pleiades.stoa.org/places/570668/dare-location"
      }
    }
  ]
}