{
  "type": "FeatureCollection",
  "title": "Pyrrichos",
  "id": "570642",
  "bbox": [
    22.432959,
    36.659054,
    22.432959,
    36.659054
  ],
  "description": "An ancient place, cited: BAtlas 58 C4 Pyrrichos",
  "names": [
    "Pyrrichos"
  ],
  "features": [
    {
      "type": "Feature",
      "geometry": {
        "type": "Point",
        "coordinates": [
          22.432959,
          36.659054
        ]
      },
      "properties": {
        "description": "representative point"
      }
    },
    {
      "geometry": {
        "type": "Point",
        "coordinates": [
          22.432959,
          36.659054
        ]
      },
      "id": "darmc-location-14445",
      "type": "Feature",
      "properties": {
        "description": "500K scale point location",
        "location_precision": "precise",
        "title": "DARMC location 14445",
        "link": "http://pleiades.stoa.org/places/570642/darmc-location-14445"
      }
    }
  ]
}