{
  "type": "FeatureCollection",
  "title": "Probatas",
  "id": "570632",
  "bbox": [
    24.439844,
    36.671508,
    24.439844,
    36.671508
  ],
  "description": "An ancient place, cited: BAtlas 58 G4 Probatas",
  "connectsWith": [
    "570475"
  ],
  "features": [
    {
      "type": "Feature",
      "geometry": {
        "type": "Point",
        "coordinates": [
          24.439844,
          36.671508
        ]
      },
      "properties": {
        "description": "representative point"
      }
    },
    {
      "geometry": {
        "type": "Point",
        "coordinates": [
          24.439844,
          36.671508
        ]
      },
      "id": "darmc-location-17564",
      "type": "Feature",
      "properties": {
        "description": "500K scale point location",
        "location_precision": "precise",
        "title": "DARMC location 17564",
        "link": "http://pleiades.stoa.org/places/570632/darmc-location-17564"
      }
    }
  ]
}