{
  "type": "FeatureCollection",
  "title": "Psophis",
  "id": "570638",
  "bbox": [
    21.892903,
    37.871725,
    21.892903,
    37.871725
  ],
  "description": "An ancient place, cited: BAtlas 58 B2 Psophis",
  "names": [
    "Psophis",
    "Phegeia"
  ],
  "features": [
    {
      "type": "Feature",
      "geometry": {
        "type": "Point",
        "coordinates": [
          21.892903,
          37.871725
        ]
      },
      "properties": {
        "description": "representative point"
      }
    },
    {
      "geometry": {
        "type": "Point",
        "coordinates": [
          21.892903,
          37.871725
        ]
      },
      "id": "darmc-location-14426",
      "type": "Feature",
      "properties": {
        "description": "1:500,000 scale representative point location digitized from the Barrington Atlas of the Greek and Roman World by the Digital Atlas of Roman and Medieval Civilizations project at Harvard University.",
        "location_precision": "precise",
        "title": "DARMC location 14426",
        "link": "http://pleiades.stoa.org/places/570638/darmc-location-14426"
      }
    }
  ]
}