{
  "type": "FeatureCollection",
  "title": "Phleious",
  "id": "570602",
  "description": "An ancient place, cited: BAtlas 58 D2 Phleious",
  "bbox": [
    22.641069,
    37.831664,
    22.641069,
    37.831664
  ],
  "reprPoint": [
    22.641069,
    37.831664
  ],
  "names": [
    "Phleious",
    "Phliasia"
  ],
  "features": [
    {
      "geometry": {
        "type": "Point",
        "coordinates": [
          22.641069,
          37.831664
        ]
      },
      "id": "darmc-location-5535",
      "type": "Feature",
      "properties": {
        "description": "1M scale point location",
        "location_precision": "precise",
        "title": "DARMC location 5535",
        "link": "http://pleiades.stoa.org/places/570602/darmc-location-5535"
      }
    }
  ]
}