{
  "type": "FeatureCollection",
  "title": "Tsitelbegebi",
  "id": "570689970",
  "bbox": [
    43.881694,
    42.139829,
    43.881694,
    42.139829
  ],
  "description": "Settlement site between the villages of Takhtidziri and Dvani in the Kareli Municipality of Georgia. The site has late-Achaemenid-Early Hellenistic and Late Hellenistic-Early Roman period cemeteries. This settlement has largely been washed away by flooding of the River Prone.",
  "features": [
    {
      "type": "Feature",
      "geometry": {
        "type": "Point",
        "coordinates": [
          43.881694,
          42.139829
        ]
      },
      "properties": {
        "description": "representative point"
      }
    },
    {
      "geometry": {
        "type": "Point",
        "coordinates": [
          43.881694,
          42.139829
        ]
      },
      "id": "approximate-imagery-location-of-tsitelbegebi",
      "type": "Feature",
      "properties": {
        "description": "Approximate imagery location based on Google Earth representing Tsitelbegebi after Gagoshidze 2022.",
        "location_precision": "precise",
        "title": "Approximate imagery location of Tsitelbegebi",
        "link": "http://pleiades.stoa.org/places/570689970/approximate-imagery-location-of-tsitelbegebi"
      }
    }
  ]
}