{
  "type": "FeatureCollection",
  "title": "Pyrrichos",
  "id": "570642",
  "bbox": [
    22.430878,
    36.654835,
    22.430878,
    36.654835
  ],
  "description": "An ancient city of the Peloponnesian Mani, located near the modern village of Kavalos/Pyrrhikhos.",
  "names": [
    "Pyrrichos"
  ],
  "features": [
    {
      "type": "Feature",
      "geometry": {
        "type": "Point",
        "coordinates": [
          22.430878,
          36.654835
        ]
      },
      "properties": {
        "description": "representative point"
      }
    },
    {
      "geometry": {
        "type": "Point",
        "coordinates": [
          22.430878,
          36.654835
        ]
      },
      "id": "imagery-location",
      "type": "Feature",
      "properties": {
        "description": "Location determined in Google Earth with reference to Moschou figures 1 & 2. Dates after BAtlas.",
        "location_precision": "precise",
        "title": "Imagery Location",
        "link": "http://pleiades.stoa.org/places/570642/imagery-location"
      }
    }
  ]
}