{
  "type": "FeatureCollection",
  "title": "(Ps)Amathous",
  "id": "570635",
  "description": "An ancient place, cited: BAtlas 58 C5 (Ps)Amathous",
  "bbox": [
    22.48239,
    36.437175,
    22.48239,
    36.437175
  ],
  "reprPoint": [
    22.48239,
    36.437175
  ],
  "names": [
    "Psamathous",
    "Amathous"
  ],
  "features": [
    {
      "geometry": {
        "type": "Point",
        "coordinates": [
          22.48239,
          36.437175
        ]
      },
      "id": "darmc-location-154",
      "type": "Feature",
      "properties": {
        "description": "500K scale point location",
        "location_precision": "precise",
        "title": "DARMC location 154",
        "link": "http://pleiades.stoa.org/places/570635/darmc-location-154"
      }
    }
  ]
}