{
  "type": "FeatureCollection",
  "title": "Soleta",
  "id": "570681",
  "description": "An ancient place, cited: BAtlas 58 H4 Soleta",
  "bbox": [
    24.51833,
    36.689881,
    24.51833,
    36.689881
  ],
  "reprPoint": [
    24.51833,
    36.689881
  ],
  "features": [
    {
      "geometry": {
        "type": "Point",
        "coordinates": [
          24.51833,
          36.689881
        ]
      },
      "id": "darmc-location-17605",
      "type": "Feature",
      "properties": {
        "description": "500K scale point location",
        "location_precision": "precise",
        "title": "DARMC location 17605",
        "link": "http://pleiades.stoa.org/places/570681/darmc-location-17605"
      }
    }
  ]
}