{
  "type": "FeatureCollection",
  "title": "Strouthos? (promontory)",
  "id": "570694",
  "bbox": [
    23.0031378,
    37.4600778,
    23.0031378,
    37.4600778
  ],
  "description": "Pausanias mentions this cape, which is probably to be identified with the modern Touphekares.",
  "names": [
    "Strouthos Pr."
  ],
  "features": [
    {
      "type": "Feature",
      "geometry": {
        "type": "Point",
        "coordinates": [
          23.0031378,
          37.4600778
        ]
      },
      "properties": {
        "description": "representative point"
      }
    },
    {
      "geometry": {
        "type": "Point",
        "coordinates": [
          23.0031378,
          37.4600778
        ]
      },
      "id": "osm-location-of-iioiiii-r-ii1i-iii1i",
      "type": "Feature",
      "properties": {
        "description": "Location based on OpenStreetMap",
        "location_precision": "precise",
        "title": "OSM location of Ακρωτήριο Ίρια",
        "link": "http://pleiades.stoa.org/places/570694/osm-location-of-iioiiii-r-ii1i-iii1i"
      }
    }
  ]
}