{
  "type": "FeatureCollection",
  "title": "Psophis",
  "id": "570638",
  "description": "An ancient place, cited: BAtlas 58 B2 Psophis",
  "bbox": [
    21.892903,
    37.871725,
    21.892903,
    37.871725
  ],
  "reprPoint": [
    21.892903,
    37.871725
  ],
  "names": [
    "Psophis",
    "Phegeia"
  ],
  "features": [
    {
      "geometry": {
        "type": "Point",
        "coordinates": [
          21.892903,
          37.871725
        ]
      },
      "id": "darmc-location-14426",
      "type": "Feature",
      "properties": {
        "description": "500K scale point location",
        "location_precision": "precise",
        "title": "DARMC location 14426",
        "link": "http://pleiades.stoa.org/places/570638/darmc-location-14426"
      }
    }
  ]
}