{
  "type": "FeatureCollection",
  "title": "Psophis",
  "id": "570638",
  "bbox": [
    21.8932614,
    37.8740863,
    21.8932614,
    37.8740863
  ],
  "description": "An ancient place, cited: BAtlas 58 B2 Psophis",
  "names": [
    "Psophis",
    "Phegeia"
  ],
  "features": [
    {
      "type": "Feature",
      "geometry": {
        "type": "Point",
        "coordinates": [
          21.8932614,
          37.8740863
        ]
      },
      "properties": {
        "description": "representative point"
      }
    },
    {
      "geometry": {
        "type": "Point",
        "coordinates": [
          21.8932614,
          37.8740863
        ]
      },
      "id": "osm-location-of-castle-of-psophida-ancient-psophis",
      "type": "Feature",
      "properties": {
        "description": "Representative location based on OpenStreetMap",
        "location_precision": "precise",
        "title": "OSM location of Castle of Psophida;Ancient Psophis",
        "link": "http://pleiades.stoa.org/places/570638/osm-location-of-castle-of-psophida-ancient-psophis"
      }
    }
  ]
}