{
  "type": "FeatureCollection",
  "title": "Treis Ammoundas",
  "id": "570747",
  "bbox": [
    24.334,
    37.677674,
    24.334,
    37.677674
  ],
  "description": "A sanctuary in NW Kea located at Treis Ammoundas dating from the Archaic to Hellenistic periods.",
  "connectsWith": [
    "570348"
  ],
  "features": [
    {
      "type": "Feature",
      "geometry": {
        "type": "Point",
        "coordinates": [
          24.334,
          37.677674
        ]
      },
      "properties": {
        "description": "representative point"
      }
    },
    {
      "geometry": {
        "type": "Point",
        "coordinates": [
          24.334,
          37.677674
        ]
      },
      "id": "darmc-location-16239",
      "type": "Feature",
      "properties": {
        "description": "500K scale point location",
        "location_precision": "precise",
        "title": "DARMC location 16239",
        "link": "http://pleiades.stoa.org/places/570747/darmc-location-16239"
      }
    }
  ]
}