{
  "type": "FeatureCollection",
  "title": "Treis Ammoundas",
  "id": "570747",
  "description": "An ancient place, cited: BAtlas 58 G2 Treis Ammoundas",
  "bbox": [
    24.334,
    37.677674,
    24.334,
    37.677674
  ],
  "reprPoint": [
    24.334,
    37.677674
  ],
  "features": [
    {
      "geometry": {
        "type": "Point",
        "coordinates": [
          24.334,
          37.677674
        ]
      },
      "id": "darmc-location-16239",
      "type": "Feature",
      "properties": {
        "description": "500K scale point location",
        "location_precision": "precise",
        "title": "DARMC location 16239",
        "link": "http://pleiades.stoa.org/places/570747/darmc-location-16239"
      }
    }
  ]
}