{
  "type": "FeatureCollection",
  "title": "Trikolonoi",
  "id": "570750",
  "description": "An ancient place, cited: BAtlas 58 C3 Trikolonoi",
  "bbox": [
    22.165174,
    37.480046,
    22.165174,
    37.480046
  ],
  "reprPoint": [
    22.165174,
    37.480046
  ],
  "names": [
    "Trikolonoi"
  ],
  "features": [
    {
      "geometry": {
        "type": "Point",
        "coordinates": [
          22.165174,
          37.480046
        ]
      },
      "id": "darmc-location-10246",
      "type": "Feature",
      "properties": {
        "description": "500K scale point location",
        "location_precision": "precise",
        "title": "DARMC location 10246",
        "link": "http://pleiades.stoa.org/places/570750/darmc-location-10246"
      }
    }
  ]
}