{
  "type": "FeatureCollection",
  "title": "Tyros",
  "id": "570759",
  "bbox": [
    22.8716721,
    37.2432056,
    22.872471,
    37.243253
  ],
  "description": "An ancient place, cited: BAtlas 58 D3 Tyros",
  "names": [
    "Tyros"
  ],
  "features": [
    {
      "type": "Feature",
      "geometry": {
        "type": "Point",
        "coordinates": [
          22.87207155,
          37.2432293
        ]
      },
      "properties": {
        "description": "representative point"
      }
    },
    {
      "geometry": {
        "type": "Point",
        "coordinates": [
          22.872471,
          37.243253
        ]
      },
      "id": "dare-location",
      "type": "Feature",
      "properties": {
        "description": "Representative point location, village precision",
        "location_precision": "precise",
        "title": "DARE Location",
        "link": "http://pleiades.stoa.org/places/570759/dare-location"
      }
    },
    {
      "geometry": {
        "type": "Point",
        "coordinates": [
          22.8716721,
          37.2432056
        ]
      },
      "id": "osm-location-of-iioiiii-i-i-i-iii-i",
      "type": "Feature",
      "properties": {
        "description": "Representative location based on OpenStreetMap",
        "location_precision": "precise",
        "title": "OSM location of Ακρόπολη Τυρού",
        "link": "http://pleiades.stoa.org/places/570759/osm-location-of-iioiiii-i-i-i-iii-i"
      }
    }
  ]
}