{
  "type": "FeatureCollection",
  "title": "Tyros",
  "id": "570759",
  "description": "An ancient place, cited: BAtlas 58 D3 Tyros",
  "bbox": [
    22.842165,
    37.2399,
    22.872471,
    37.243253
  ],
  "reprPoint": [
    22.857318,
    37.2415765
  ],
  "names": [
    "Tyros"
  ],
  "features": [
    {
      "geometry": {
        "type": "Point",
        "coordinates": [
          22.842165,
          37.2399
        ]
      },
      "id": "darmc-location-24234",
      "type": "Feature",
      "properties": {
        "description": "1M scale point location",
        "location_precision": "precise",
        "title": "DARMC location 24234",
        "link": "http://pleiades.stoa.org/places/570759/darmc-location-24234"
      }
    },
    {
      "geometry": {
        "type": "Point",
        "coordinates": [
          22.872471,
          37.243253
        ]
      },
      "id": "dare-location",
      "type": "Feature",
      "properties": {
        "description": "Representative point location, village precision",
        "location_precision": "precise",
        "title": "DARE Location",
        "link": "http://pleiades.stoa.org/places/570759/dare-location"
      }
    }
  ]
}