{
  "type": "FeatureCollection",
  "title": "Trit(a)ia",
  "id": "570755",
  "description": "An ancient place, cited: BAtlas 58 B2 Trit(a)ia",
  "bbox": [
    21.711021,
    37.9527,
    21.711021,
    37.9527
  ],
  "reprPoint": [
    21.711021,
    37.9527
  ],
  "names": [
    "Tritaia",
    "Tritia"
  ],
  "features": [
    {
      "geometry": {
        "type": "Point",
        "coordinates": [
          21.711021,
          37.9527
        ]
      },
      "id": "darmc-location-15267",
      "type": "Feature",
      "properties": {
        "description": "500K scale point location",
        "location_precision": "precise",
        "title": "DARMC location 15267",
        "link": "http://pleiades.stoa.org/places/570755/darmc-location-15267"
      }
    }
  ]
}