{
  "type": "FeatureCollection",
  "title": "Thalamai",
  "id": "570715",
  "description": "An ancient place, cited: BAtlas 58 C4 Thalamai",
  "bbox": [
    22.325671,
    36.786208,
    22.325671,
    36.786208
  ],
  "reprPoint": [
    22.325671,
    36.786208
  ],
  "names": [
    "Thalamai"
  ],
  "features": [
    {
      "geometry": {
        "type": "Point",
        "coordinates": [
          22.325671,
          36.786208
        ]
      },
      "id": "darmc-location-15106",
      "type": "Feature",
      "properties": {
        "description": "500K scale point location",
        "location_precision": "precise",
        "title": "DARMC location 15106",
        "link": "http://pleiades.stoa.org/places/570715/darmc-location-15106"
      }
    }
  ]
}