{
  "type": "FeatureCollection",
  "title": "Theisoa",
  "id": "570720",
  "bbox": [
    21.934167,
    37.516533,
    21.934167,
    37.516533
  ],
  "description": "An ancient place, cited: BAtlas 58 B2 Theisoa",
  "names": [
    "Theisoa"
  ],
  "features": [
    {
      "type": "Feature",
      "geometry": {
        "type": "Point",
        "coordinates": [
          21.934167,
          37.516533
        ]
      },
      "properties": {
        "description": "representative point"
      }
    },
    {
      "geometry": {
        "type": "Point",
        "coordinates": [
          21.934167,
          37.516533
        ]
      },
      "id": "darmc-location-6314",
      "type": "Feature",
      "properties": {
        "description": "500K scale point location",
        "location_precision": "precise",
        "title": "DARMC location 6314",
        "link": "http://pleiades.stoa.org/places/570720/darmc-location-6314"
      }
    }
  ]
}