{
  "type": "FeatureCollection",
  "title": "Thalamai",
  "id": "570715",
  "bbox": [
    22.325671,
    36.786208,
    22.325671,
    36.786208
  ],
  "description": "An ancient place, cited: BAtlas 58 C4 Thalamai",
  "names": [
    "Thalamai"
  ],
  "features": [
    {
      "type": "Feature",
      "geometry": {
        "type": "Point",
        "coordinates": [
          22.325671,
          36.786208
        ]
      },
      "properties": {
        "description": "representative point"
      }
    },
    {
      "geometry": {
        "type": "Point",
        "coordinates": [
          22.325671,
          36.786208
        ]
      },
      "id": "darmc-location-15106",
      "type": "Feature",
      "properties": {
        "description": "1:500,000 scale representative point location digitized from the Barrington Atlas of the Greek and Roman World by the Digital Atlas of Roman and Medieval Civilizations project at Harvard University.",
        "location_precision": "precise",
        "title": "DARMC location 15106",
        "link": "http://pleiades.stoa.org/places/570715/darmc-location-15106"
      }
    }
  ]
}