{
  "type": "FeatureCollection",
  "title": "Taygetos M.",
  "id": "570706",
  "bbox": [
    22.349956,
    36.953544,
    22.349956,
    36.953544
  ],
  "description": "An ancient place, cited: BAtlas 58 C3 Taygetos M.",
  "connectsWith": [
    "570406"
  ],
  "names": [
    "Taygetos M."
  ],
  "features": [
    {
      "type": "Feature",
      "geometry": {
        "type": "Point",
        "coordinates": [
          22.349956,
          36.953544
        ]
      },
      "properties": {
        "description": "representative point"
      }
    },
    {
      "geometry": {
        "type": "Point",
        "coordinates": [
          22.349956,
          36.953544
        ]
      },
      "id": "location-of-taygetos-m",
      "type": "Feature",
      "properties": {
        "description": "verified in Google Earth 2013.",
        "location_precision": "precise",
        "title": "location of Taygetos M.",
        "link": "http://pleiades.stoa.org/places/570706/location-of-taygetos-m"
      }
    }
  ]
}