{
  "type": "FeatureCollection",
  "title": "Trikrana Ins.",
  "id": "570752",
  "bbox": [
    23.2739852,
    37.25915,
    23.2739852,
    37.25915
  ],
  "description": "An ancient place, cited: BAtlas 58 E3 Trikrana Ins.",
  "connectsWith": [
    "570495"
  ],
  "names": [
    "Trikrana"
  ],
  "features": [
    {
      "type": "Feature",
      "geometry": {
        "type": "Point",
        "coordinates": [
          23.2739852,
          37.25915
        ]
      },
      "properties": {
        "description": "representative point"
      }
    },
    {
      "geometry": {
        "type": "Point",
        "coordinates": [
          23.2739852,
          37.25915
        ]
      },
      "id": "location-of-Trikrana-Ins",
      "type": "Feature",
      "properties": {
        "description": "Location based on OpenStreetMap",
        "location_precision": "precise",
        "title": "location of Trikrana Ins.",
        "link": "http://pleiades.stoa.org/places/570752/location-of-Trikrana-Ins"
      }
    }
  ]
}