{
  "type": "FeatureCollection",
  "title": "Roall auxiliary fort",
  "id": "571616794",
  "bbox": [
    -1.14642,
    53.7203,
    -1.14642,
    53.7203
  ],
  "description": "A Roman auxiliary fort was identified via cropmarks in Kellington, Selby, England, United Kingdom.",
  "features": [
    {
      "type": "Feature",
      "geometry": {
        "type": "Point",
        "coordinates": [
          -1.14642,
          53.7203
        ]
      },
      "properties": {
        "description": "representative point"
      }
    },
    {
      "geometry": {
        "type": "Point",
        "coordinates": [
          -1.14642,
          53.7203
        ]
      },
      "id": "imagery-location",
      "type": "Feature",
      "properties": {
        "description": "Coordinates following GeoHack",
        "location_precision": "precise",
        "title": "Imagery location",
        "link": "http://pleiades.stoa.org/places/571616794/imagery-location"
      }
    }
  ]
}