{
  "type": "FeatureCollection",
  "title": "Claudia",
  "id": "571649387",
  "bbox": [
    12.486137,
    41.891775,
    12.486137,
    41.891775
  ],
  "description": "A Roman rural tribe that was one of the most ancient of Rome's gentes. The gens Claudia traced its history to the earliest days of the Roman Republic. Appius Claudius Sabinus Regillensis, in 495 B.C., was the first of its members to hold the consulship.",
  "connectsWith": [
    "423025",
    "432900"
  ],
  "features": [
    {
      "type": "Feature",
      "geometry": {
        "type": "Point",
        "coordinates": [
          12.486137,
          41.891775
        ]
      },
      "properties": {
        "description": "representative point"
      }
    }
  ]
}