{
  "type": "FeatureCollection",
  "title": "Sikani",
  "id": "572048102",
  "bbox": [
    40.0707,
    36.8423,
    40.0709816,
    36.8425922
  ],
  "description": "A town mentioned in Neo-Assyrian sources that is generally identified with Tell Fekheriye (Tell Faḫārīya).",
  "names": [
    "Tell Fekheriye",
    "Sikāni",
    "Tall al-Fakhīriyah"
  ],
  "features": [
    {
      "type": "Feature",
      "geometry": {
        "type": "Point",
        "coordinates": [
          40.0708408,
          36.8424461
        ]
      },
      "properties": {
        "description": "representative point"
      }
    },
    {
      "geometry": {
        "type": "Point",
        "coordinates": [
          40.0709816,
          36.8425922
        ]
      },
      "id": "osm-location-of-tell-fekheriye",
      "type": "Feature",
      "properties": {
        "description": "Location based on OpenStreetMap",
        "location_precision": "precise",
        "title": "OSM location of Tell Fekheriye",
        "link": "http://pleiades.stoa.org/places/572048102/osm-location-of-tell-fekheriye"
      }
    },
    {
      "geometry": {
        "type": "Point",
        "coordinates": [
          40.0707,
          36.8423
        ]
      },
      "id": "cigs-location-of-tall-al-fakhiriyah",
      "type": "Feature",
      "properties": {
        "description": null,
        "location_precision": "precise",
        "title": "CIGS location of Tall al-Fakhīriyah",
        "link": "http://pleiades.stoa.org/places/572048102/cigs-location-of-tall-al-fakhiriyah"
      }
    }
  ]
}