{
  "type": "FeatureCollection",
  "title": "Minorca (island)",
  "id": "572631626",
  "bbox": [
    4.0044605,
    39.9249126,
    4.0044605,
    39.9249126
  ],
  "description": "Minorca is one of the Balearic Islands of the Mediterranean Sea. Its name likely derives from the Latin 'Insula minor'.",
  "connectsWith": [
    "265817"
  ],
  "features": [
    {
      "type": "Feature",
      "geometry": {
        "type": "Point",
        "coordinates": [
          4.0044605,
          39.9249126
        ]
      },
      "properties": {
        "description": "representative point"
      }
    },
    {
      "geometry": {
        "type": "Point",
        "coordinates": [
          4.0044605,
          39.9249126
        ]
      },
      "id": "location-of-minorca",
      "type": "Feature",
      "properties": {
        "description": "Location based on OpenStreetMap",
        "location_precision": "precise",
        "title": "location of Minorca",
        "link": "http://pleiades.stoa.org/places/572631626/location-of-minorca"
      }
    }
  ]
}