{
  "type": "FeatureCollection",
  "title": "Amiternum (Samnium)",
  "id": "573036190",
  "bbox": [
    13.866147,
    41.539107,
    13.866147,
    41.539107
  ],
  "description": "An ancient city in Samnium located between Interamna Lirenas and Atina.",
  "names": [
    "Amiternum"
  ],
  "features": [
    {
      "type": "Feature",
      "geometry": {
        "type": "Point",
        "coordinates": [
          13.866147,
          41.539107
        ]
      },
      "properties": {
        "description": "representative point"
      }
    },
    {
      "geometry": {
        "type": "Point",
        "coordinates": [
          13.866147,
          41.539107
        ]
      },
      "id": "osm-location-of-santelia-fiumerapido",
      "type": "Feature",
      "properties": {
        "description": "Location based on OpenStreetMap",
        "location_precision": "precise",
        "title": "OSM location of Sant'Elia Fiumerapido",
        "link": "http://pleiades.stoa.org/places/573036190/osm-location-of-santelia-fiumerapido"
      }
    }
  ]
}