{
  "type": "FeatureCollection",
  "title": "Ionaion",
  "id": "573266",
  "bbox": [
    21.596223,
    37.525886,
    21.596223,
    37.525886
  ],
  "description": "An ancient place, cited: BAtlas 58 unlocated Ionaion",
  "connectsWith": [
    "570653"
  ],
  "names": [
    "Ionaion"
  ],
  "features": [
    {
      "type": "Feature",
      "geometry": {
        "type": "Point",
        "coordinates": [
          21.596223,
          37.525886
        ]
      },
      "properties": {
        "description": "representative point"
      }
    },
    {
      "geometry": null,
      "id": "batlas-location",
      "type": "Feature",
      "properties": {
        "description": null,
        "location_precision": "unlocated",
        "title": "Barrington Atlas location",
        "link": "http://pleiades.stoa.org/places/573266/batlas-location"
      }
    }
  ]
}