{
  "type": "FeatureCollection",
  "title": "Kretea",
  "id": "573309",
  "bbox": [
    21.975,
    37.456944,
    21.975,
    37.456944
  ],
  "description": "A place (χώρα) mentioned by Pausanias and placed by him on mount Lykaion.",
  "connectsWith": [
    "570441"
  ],
  "names": [
    "Kretea"
  ],
  "features": [
    {
      "type": "Feature",
      "geometry": {
        "type": "Point",
        "coordinates": [
          21.975,
          37.456944
        ]
      },
      "properties": {
        "description": "representative point"
      }
    },
    {
      "geometry": null,
      "id": "batlas-location",
      "type": "Feature",
      "properties": {
        "description": null,
        "location_precision": "unlocated",
        "title": "Barrington Atlas location",
        "link": "http://pleiades.stoa.org/places/573309/batlas-location"
      }
    }
  ]
}