{
  "type": "FeatureCollection",
  "title": "Skollion",
  "id": "573522",
  "bbox": [
    21.577,
    37.968,
    21.57947,
    37.96864
  ],
  "description": "A physical feature mentioned by Strabo as near Pylos in Elis. It may be identical with the mountain named \"Skollis\" mentioned later in Strabo.",
  "connectsWith": [
    "570676"
  ],
  "names": [
    "Skollion"
  ],
  "features": [
    {
      "type": "Feature",
      "geometry": {
        "type": "Point",
        "coordinates": [
          21.578235,
          37.96832
        ]
      },
      "properties": {
        "description": "representative point"
      }
    }
  ]
}