{
  "type": "FeatureCollection",
  "title": "Kalatepe",
  "id": "574198884",
  "description": "A Chalcolithic mound near the village of Büyükgülücek, 15 km. north of Alaca Höyük.",
  "bbox": [
    34.7455,
    40.3407,
    34.7455,
    40.3407
  ],
  "reprPoint": [
    34.7455,
    40.3407
  ],
  "features": [
    {
      "geometry": {
        "type": "Point",
        "coordinates": [
          34.7455,
          40.3407
        ]
      },
      "id": "imagery-location-of-kalatepe",
      "type": "Feature",
      "properties": {
        "description": "Point representing the approximate location of Kalatepe, from Google Earth after Koşay 1957.",
        "location_precision": "precise",
        "title": "Imagery location of Kalatepe",
        "link": "http://pleiades.stoa.org/places/574198884/imagery-location-of-kalatepe"
      }
    }
  ]
}