{
  "type": "FeatureCollection",
  "title": "Casale dell’Infernaccio",
  "id": "575015998",
  "bbox": [
    12.4143258,
    41.8279581,
    12.4143258,
    41.8279581
  ],
  "description": "A Roman villa located at Magliana Vecchia that dates to the second century A.D.",
  "connectsWith": [
    "422968"
  ],
  "features": [
    {
      "type": "Feature",
      "geometry": {
        "type": "Point",
        "coordinates": [
          12.4143258,
          41.8279581
        ]
      },
      "properties": {
        "description": "representative point"
      }
    },
    {
      "geometry": {
        "type": "Point",
        "coordinates": [
          12.4143258,
          41.8279581
        ]
      },
      "id": "location-of-roman-villa",
      "type": "Feature",
      "properties": {
        "description": "Representative location based on OpenStreetMap.",
        "location_precision": "precise",
        "title": "OSM location of Villa romana dell’Infernaccio",
        "link": "http://pleiades.stoa.org/places/575015998/location-of-roman-villa"
      }
    }
  ]
}