{
  "type": "FeatureCollection",
  "title": "Etruscan necropolis of Dometaia",
  "id": "576868068",
  "bbox": [
    11.0350951,
    43.3933763,
    11.0350951,
    43.3933763
  ],
  "description": "An Etruscan necropolis dating to the sixth century B.C.",
  "features": [
    {
      "type": "Feature",
      "geometry": {
        "type": "Point",
        "coordinates": [
          11.0350951,
          43.3933763
        ]
      },
      "properties": {
        "description": "representative point"
      }
    },
    {
      "geometry": {
        "type": "Point",
        "coordinates": [
          11.0350951,
          43.3933763
        ]
      },
      "id": "osm-location-of-parco-archeologico-di-dometaia",
      "type": "Feature",
      "properties": {
        "description": "Representative location based on OpenStreetMap.",
        "location_precision": "precise",
        "title": "OSM location of Parco archeologico di Dometaia",
        "link": "http://pleiades.stoa.org/places/576868068/osm-location-of-parco-archeologico-di-dometaia"
      }
    }
  ]
}