{
  "type": "FeatureCollection",
  "title": "Mes Aynak",
  "id": "578900328",
  "bbox": [
    69.366728,
    34.4000732,
    69.366728,
    34.4000732
  ],
  "description": "The site of Mes Aynak in modern Afghanistan flourished between the between the fifth and seventh centuries A.D. More than 400 Buddha statues, stupas, and a 40 ha monastery complex have been documented at the site.",
  "features": [
    {
      "type": "Feature",
      "geometry": {
        "type": "Point",
        "coordinates": [
          69.366728,
          34.4000732
        ]
      },
      "properties": {
        "description": "representative point"
      }
    },
    {
      "geometry": {
        "type": "Point",
        "coordinates": [
          69.366728,
          34.4000732
        ]
      },
      "id": "osm-location-of-mes-aynak",
      "type": "Feature",
      "properties": {
        "description": "Location based on OpenStreetMap",
        "location_precision": "precise",
        "title": "OSM location of Mes Aynak",
        "link": "http://pleiades.stoa.org/places/578900328/osm-location-of-mes-aynak"
      }
    }
  ]
}