{
  "type": "FeatureCollection",
  "title": "Atene",
  "id": "579883",
  "description": "An ancient place, cited: BAtlas 59 C4 Atene",
  "bbox": [
    23.964878,
    37.675121,
    23.967958,
    37.675572
  ],
  "reprPoint": [
    23.966418,
    37.6753465
  ],
  "names": [
    "Atene"
  ],
  "features": [
    {
      "geometry": {
        "type": "Point",
        "coordinates": [
          23.967958,
          37.675572
        ]
      },
      "id": "darmc-location-21244",
      "type": "Feature",
      "properties": {
        "description": "Point location",
        "location_precision": "precise",
        "title": "DARMC location 21244",
        "link": "http://pleiades.stoa.org/places/579883/darmc-location-21244"
      }
    },
    {
      "geometry": {
        "type": "Point",
        "coordinates": [
          23.964878,
          37.675121
        ]
      },
      "id": "darmc-location-11552",
      "type": "Feature",
      "properties": {
        "description": "500K scale point location",
        "location_precision": "precise",
        "title": "DARMC location 11552",
        "link": "http://pleiades.stoa.org/places/579883/darmc-location-11552"
      }
    }
  ]
}