{
  "type": "FeatureCollection",
  "title": "Atene",
  "id": "579883",
  "bbox": [
    23.964878,
    37.675121,
    23.967958,
    37.675572
  ],
  "description": "An ancient place, cited: BAtlas 59 C4 Atene",
  "names": [
    "Atḗnē"
  ],
  "features": [
    {
      "type": "Feature",
      "geometry": {
        "type": "Point",
        "coordinates": [
          23.966418,
          37.6753465
        ]
      },
      "properties": {
        "description": "representative point"
      }
    },
    {
      "geometry": {
        "type": "Point",
        "coordinates": [
          23.964878,
          37.675121
        ]
      },
      "id": "darmc-location-11552",
      "type": "Feature",
      "properties": {
        "description": "1:500,000 scale representative point location digitized from the Barrington Atlas of the Greek and Roman World by the Digital Atlas of Roman and Medieval Civilizations project at Harvard University.",
        "location_precision": "precise",
        "title": "DARMC location 11552",
        "link": "http://pleiades.stoa.org/places/579883/darmc-location-11552"
      }
    },
    {
      "geometry": {
        "type": "Point",
        "coordinates": [
          23.967958,
          37.675572
        ]
      },
      "id": "darmc-location-21244",
      "type": "Feature",
      "properties": {
        "description": "Representative point location digitized from the Barrington Atlas of the Greek and Roman World by the Digital Atlas of Roman and Medieval Civilizations project at Harvard University.",
        "location_precision": "precise",
        "title": "DARMC location 21244",
        "link": "http://pleiades.stoa.org/places/579883/darmc-location-21244"
      }
    }
  ]
}