{
  "type": "FeatureCollection",
  "title": "Aphrodite, T.",
  "id": "579874",
  "description": "An ancient place, cited: BAtlas 59 B2 Aphrodite, T.",
  "bbox": [
    23.631163,
    38.016485,
    23.631163,
    38.016485
  ],
  "reprPoint": [
    23.631163,
    38.016485
  ],
  "names": [
    "Aphrodite, T."
  ],
  "features": [
    {
      "geometry": {
        "type": "Point",
        "coordinates": [
          23.631163,
          38.016485
        ]
      },
      "id": "darmc-location-21602",
      "type": "Feature",
      "properties": {
        "description": "Point location",
        "location_precision": "precise",
        "title": "DARMC location 21602",
        "link": "http://pleiades.stoa.org/places/579874/darmc-location-21602"
      }
    }
  ]
}