{
  "type": "FeatureCollection",
  "title": "Aigilia?",
  "id": "579852",
  "description": "An ancient place, cited: BAtlas 59 C3 Aigilia?",
  "bbox": [
    23.906432,
    37.79134,
    23.913072,
    37.793533
  ],
  "reprPoint": [
    23.909752,
    37.7924365
  ],
  "names": [
    "Aigilia"
  ],
  "features": [
    {
      "geometry": {
        "type": "Point",
        "coordinates": [
          23.913072,
          37.793533
        ]
      },
      "id": "darmc-location-21229",
      "type": "Feature",
      "properties": {
        "description": "Point location",
        "location_precision": "precise",
        "title": "DARMC location 21229",
        "link": "http://pleiades.stoa.org/places/579852/darmc-location-21229"
      }
    },
    {
      "geometry": {
        "type": "Point",
        "coordinates": [
          23.906432,
          37.79134
        ]
      },
      "id": "darmc-location-11226",
      "type": "Feature",
      "properties": {
        "description": "500K scale point location",
        "location_precision": "precise",
        "title": "DARMC location 11226",
        "link": "http://pleiades.stoa.org/places/579852/darmc-location-11226"
      }
    }
  ]
}