{
  "type": "FeatureCollection",
  "title": "Agryle Kathyperthen",
  "id": "579849",
  "bbox": [
    23.758,
    37.961,
    23.758,
    37.961
  ],
  "description": "Agryle Kathyperthen (\"Upper Agryle\") was a deme of ancient Attica and one of two demoi of Agryle.",
  "names": [
    "Agryle Kathyperthen"
  ],
  "features": [
    {
      "type": "Feature",
      "geometry": {
        "type": "Point",
        "coordinates": [
          23.758,
          37.961
        ]
      },
      "properties": {
        "description": "representative point"
      }
    },
    {
      "geometry": {
        "type": "Point",
        "coordinates": [
          23.758,
          37.961
        ]
      },
      "id": "geohack-location-of-upper-agryle",
      "type": "Feature",
      "properties": {
        "description": "Coordinates following GeoHack.",
        "location_precision": "precise",
        "title": "GeoHack location of Upper Agryle",
        "link": "http://pleiades.stoa.org/places/579849/geohack-location-of-upper-agryle"
      }
    }
  ]
}