{
  "type": "FeatureCollection",
  "title": "Aigilia?",
  "id": "579852",
  "bbox": [
    23.906432,
    37.79134,
    23.913072,
    37.793533
  ],
  "description": "An ancient place, cited: BAtlas 59 C3 Aigilia?",
  "names": [
    "Aigilia"
  ],
  "features": [
    {
      "type": "Feature",
      "geometry": {
        "type": "Point",
        "coordinates": [
          23.909752,
          37.7924365
        ]
      },
      "properties": {
        "description": "representative point"
      }
    },
    {
      "geometry": {
        "type": "Point",
        "coordinates": [
          23.906432,
          37.79134
        ]
      },
      "id": "darmc-location-11226",
      "type": "Feature",
      "properties": {
        "description": "1:500,000 scale representative point location digitized from the Barrington Atlas of the Greek and Roman World by the Digital Atlas of Roman and Medieval Civilizations project at Harvard University.",
        "location_precision": "precise",
        "title": "DARMC location 11226",
        "link": "http://pleiades.stoa.org/places/579852/darmc-location-11226"
      }
    },
    {
      "geometry": {
        "type": "Point",
        "coordinates": [
          23.913072,
          37.793533
        ]
      },
      "id": "darmc-location-21229",
      "type": "Feature",
      "properties": {
        "description": "Representative point location digitized from the Barrington Atlas of the Greek and Roman World by the Digital Atlas of Roman and Medieval Civilizations project at Harvard University.",
        "location_precision": "precise",
        "title": "DARMC location 21229",
        "link": "http://pleiades.stoa.org/places/579852/darmc-location-21229"
      }
    }
  ]
}