{
  "type": "FeatureCollection",
  "title": "Aphidna",
  "id": "579873",
  "description": "A large Attic deme, located on the Gulf of Kotroni.",
  "bbox": [
    23.836137,
    38.20509,
    23.836166,
    38.205967
  ],
  "reprPoint": [
    23.8361515,
    38.2055285
  ],
  "names": [
    "Aphidna"
  ],
  "features": [
    {
      "geometry": {
        "type": "Point",
        "coordinates": [
          23.836137,
          38.205967
        ]
      },
      "id": "darmc-location-21239",
      "type": "Feature",
      "properties": {
        "description": "Point location",
        "location_precision": "precise",
        "title": "DARMC location 21239",
        "link": "http://pleiades.stoa.org/places/579873/darmc-location-21239"
      }
    },
    {
      "geometry": {
        "type": "Point",
        "coordinates": [
          23.836166,
          38.20509
        ]
      },
      "id": "darmc-location-24029",
      "type": "Feature",
      "properties": {
        "description": "1M scale point location",
        "location_precision": "precise",
        "title": "DARMC location 24029",
        "link": "http://pleiades.stoa.org/places/579873/darmc-location-24029"
      }
    }
  ]
}