{
  "type": "FeatureCollection",
  "title": "Kopros",
  "id": "579989",
  "description": "An ancient place, cited: BAtlas 59 B2 Kopros",
  "bbox": [
    23.557463,
    38.047761,
    23.557463,
    38.047761
  ],
  "reprPoint": [
    23.557463,
    38.047761
  ],
  "names": [
    "Kopros"
  ],
  "features": [
    {
      "geometry": {
        "type": "Point",
        "coordinates": [
          23.557463,
          38.047761
        ]
      },
      "id": "darmc-location-21291",
      "type": "Feature",
      "properties": {
        "description": "Point location",
        "location_precision": "precise",
        "title": "DARMC location 21291",
        "link": "http://pleiades.stoa.org/places/579989/darmc-location-21291"
      }
    }
  ]
}