{
  "type": "FeatureCollection",
  "title": "Diomeia",
  "id": "579912",
  "bbox": [
    23.734335,
    37.967439,
    23.734335,
    37.967439
  ],
  "description": "An ancient place, cited: BAtlas 59 B3 Diomeia",
  "names": [
    "Diómeia"
  ],
  "features": [
    {
      "type": "Feature",
      "geometry": {
        "type": "Point",
        "coordinates": [
          23.734335,
          37.967439
        ]
      },
      "properties": {
        "description": "representative point"
      }
    },
    {
      "geometry": {
        "type": "Point",
        "coordinates": [
          23.734335,
          37.967439
        ]
      },
      "id": "darmc-location-22836",
      "type": "Feature",
      "properties": {
        "description": "Representative point location digitized from the Barrington Atlas of the Greek and Roman World by the Digital Atlas of Roman and Medieval Civilizations project at Harvard University.",
        "location_precision": "precise",
        "title": "DARMC location 22836",
        "link": "http://pleiades.stoa.org/places/579912/darmc-location-22836"
      }
    }
  ]
}