{
  "type": "FeatureCollection",
  "title": "Halai Aixonides",
  "id": "579939",
  "bbox": [
    23.768417,
    37.851683,
    23.771671,
    37.853008
  ],
  "description": "Halai Aixonides was an Attic paralia deme of the Kekropis phyle. It was located near Cape Zoster on the western coast of Attica, south of the deme Aixones, from which the second part of its name derives.",
  "connectsWith": [
    "579888"
  ],
  "names": [
    "Voula",
    "Halai Aixonides"
  ],
  "features": [
    {
      "type": "Feature",
      "geometry": {
        "type": "Point",
        "coordinates": [
          23.770044,
          37.8523455
        ]
      },
      "properties": {
        "description": "representative point"
      }
    },
    {
      "geometry": {
        "type": "Point",
        "coordinates": [
          23.768417,
          37.851683
        ]
      },
      "id": "darmc-location-12652",
      "type": "Feature",
      "properties": {
        "description": "1:500,000 scale representative point location digitized from the Barrington Atlas of the Greek and Roman World by the Digital Atlas of Roman and Medieval Civilizations project at Harvard University.",
        "location_precision": "precise",
        "title": "DARMC location 12652",
        "link": "http://pleiades.stoa.org/places/579939/darmc-location-12652"
      }
    },
    {
      "geometry": {
        "type": "Point",
        "coordinates": [
          23.771671,
          37.853008
        ]
      },
      "id": "darmc-location-21270",
      "type": "Feature",
      "properties": {
        "description": "Representative point location digitized from the Barrington Atlas of the Greek and Roman World by the Digital Atlas of Roman and Medieval Civilizations project at Harvard University.",
        "location_precision": "precise",
        "title": "DARMC location 21270",
        "link": "http://pleiades.stoa.org/places/579939/darmc-location-21270"
      }
    }
  ]
}