{
  "type": "FeatureCollection",
  "title": "Ikarion",
  "id": "579958",
  "description": "An ancient settlement and deme of Attica.",
  "bbox": [
    23.900453,
    38.095615,
    23.900453,
    38.095615
  ],
  "reprPoint": [
    23.900453,
    38.095615
  ],
  "names": [
    "Ikarion"
  ],
  "features": [
    {
      "geometry": {
        "type": "Point",
        "coordinates": [
          23.895761,
          38.106141
        ]
      },
      "id": "darmc-location-12861",
      "type": "Feature",
      "properties": {
        "description": "500K scale point location",
        "location_precision": "precise",
        "title": "DARMC location 12861",
        "link": "http://pleiades.stoa.org/places/579958/darmc-location-12861"
      }
    },
    {
      "geometry": {
        "type": "Point",
        "coordinates": [
          23.88595,
          38.103986
        ]
      },
      "id": "darmc-location-21277",
      "type": "Feature",
      "properties": {
        "description": "Point location",
        "location_precision": "precise",
        "title": "DARMC location 21277",
        "link": "http://pleiades.stoa.org/places/579958/darmc-location-21277"
      }
    },
    {
      "geometry": {
        "type": "Point",
        "coordinates": [
          23.900453,
          38.095615
        ]
      },
      "id": "centerpoint-of-sanctuary-of-dionysos-per-google-earth",
      "type": "Feature",
      "properties": {
        "description": "The Sanctuary of Dionysos, which includes a theater, choregic monument, statue bases, and at least one temple, formed part of the civic center of the Attic deme of Ikarion.",
        "location_precision": "precise",
        "title": "Sanctuary of Dionysos",
        "link": "http://pleiades.stoa.org/places/579958/centerpoint-of-sanctuary-of-dionysos-per-google-earth"
      }
    }
  ]
}