{
  "type": "FeatureCollection",
  "title": "Ionidai?",
  "id": "579960",
  "bbox": [
    23.914475,
    38.028564,
    23.914475,
    38.028564
  ],
  "description": "An ancient place, cited: BAtlas 59 C2 Ionidai?",
  "names": [
    "Ionidai"
  ],
  "features": [
    {
      "type": "Feature",
      "geometry": {
        "type": "Point",
        "coordinates": [
          23.914475,
          38.028564
        ]
      },
      "properties": {
        "description": "representative point"
      }
    },
    {
      "geometry": {
        "type": "Point",
        "coordinates": [
          23.914475,
          38.028564
        ]
      },
      "id": "darmc-location-21562",
      "type": "Feature",
      "properties": {
        "description": "Representative point location digitized from the Barrington Atlas of the Greek and Roman World by the Digital Atlas of Roman and Medieval Civilizations project at Harvard University.",
        "location_precision": "precise",
        "title": "DARMC location 21562",
        "link": "http://pleiades.stoa.org/places/579960/darmc-location-21562"
      }
    }
  ]
}