{
  "type": "FeatureCollection",
  "title": "Kettos?",
  "id": "579978",
  "bbox": [
    23.623805,
    38.013726,
    23.623805,
    38.013726
  ],
  "description": "An ancient place, cited: BAtlas 59 B2 Kettos?",
  "names": [
    "Kettos"
  ],
  "features": [
    {
      "type": "Feature",
      "geometry": {
        "type": "Point",
        "coordinates": [
          23.623805,
          38.013726
        ]
      },
      "properties": {
        "description": "representative point"
      }
    },
    {
      "geometry": {
        "type": "Point",
        "coordinates": [
          23.623805,
          38.013726
        ]
      },
      "id": "darmc-location-21285",
      "type": "Feature",
      "properties": {
        "description": "Point location",
        "location_precision": "precise",
        "title": "DARMC location 21285",
        "link": "http://pleiades.stoa.org/places/579978/darmc-location-21285"
      }
    }
  ]
}