{
  "type": "FeatureCollection",
  "title": "Halai Araphenides",
  "id": "579940",
  "bbox": [
    24.000249,
    37.985193,
    24.008695,
    37.989191
  ],
  "description": "A deme of Attica, located on the eastern shore north of Brauron. The site was known in antiquity for its sanctuary dedicated to Artemis Tauropolos.",
  "names": [
    "Halai Araphenides"
  ],
  "features": [
    {
      "type": "Feature",
      "geometry": {
        "type": "Point",
        "coordinates": [
          24.004472,
          37.987192
        ]
      },
      "properties": {
        "description": "representative point"
      }
    },
    {
      "geometry": {
        "type": "Point",
        "coordinates": [
          24.008695,
          37.989191
        ]
      },
      "id": "darmc-location-12653",
      "type": "Feature",
      "properties": {
        "description": "500K scale point location",
        "location_precision": "precise",
        "title": "DARMC location 12653",
        "link": "http://pleiades.stoa.org/places/579940/darmc-location-12653"
      }
    },
    {
      "geometry": {
        "type": "Point",
        "coordinates": [
          24.000249,
          37.985193
        ]
      },
      "id": "darmc-location-21271",
      "type": "Feature",
      "properties": {
        "description": "Point location",
        "location_precision": "precise",
        "title": "DARMC location 21271",
        "link": "http://pleiades.stoa.org/places/579940/darmc-location-21271"
      }
    }
  ]
}