{
  "type": "FeatureCollection",
  "title": "Helioupolis",
  "id": "579947",
  "bbox": [
    23.757547,
    37.935979,
    23.757547,
    37.935979
  ],
  "description": "An ancient place, cited: BAtlas 59 B3 Helioupolis",
  "features": [
    {
      "type": "Feature",
      "geometry": {
        "type": "Point",
        "coordinates": [
          23.757547,
          37.935979
        ]
      },
      "properties": {
        "description": "representative point"
      }
    },
    {
      "geometry": {
        "type": "Point",
        "coordinates": [
          23.757547,
          37.935979
        ]
      },
      "id": "darmc-location-21273",
      "type": "Feature",
      "properties": {
        "description": "Point location",
        "location_precision": "precise",
        "title": "DARMC location 21273",
        "link": "http://pleiades.stoa.org/places/579947/darmc-location-21273"
      }
    }
  ]
}