{
  "type": "FeatureCollection",
  "title": "Ikarion",
  "id": "579958",
  "bbox": [
    23.88595,
    38.103986,
    23.895761,
    38.106141
  ],
  "description": "An ancient settlement and inland deme of the tribe Aigeis, in Attica, said to be the birthplace of Thespis, the inventor of Greek drama.",
  "connectsWith": [
    "579888"
  ],
  "names": [
    "Ikarion",
    "Ikaria",
    "Ikarion"
  ],
  "features": [
    {
      "type": "Feature",
      "geometry": {
        "type": "Point",
        "coordinates": [
          23.8908555,
          38.1050635
        ]
      },
      "properties": {
        "description": "representative point"
      }
    },
    {
      "geometry": {
        "type": "Point",
        "coordinates": [
          23.895761,
          38.106141
        ]
      },
      "id": "darmc-location-12861",
      "type": "Feature",
      "properties": {
        "description": "1:500,000 scale representative point location digitized from the Barrington Atlas of the Greek and Roman World by the Digital Atlas of Roman and Medieval Civilizations project at Harvard University.",
        "location_precision": "precise",
        "title": "DARMC location 12861",
        "link": "http://pleiades.stoa.org/places/579958/darmc-location-12861"
      }
    },
    {
      "geometry": {
        "type": "Point",
        "coordinates": [
          23.88595,
          38.103986
        ]
      },
      "id": "darmc-location-21277",
      "type": "Feature",
      "properties": {
        "description": "Representative point location digitized from the Barrington Atlas of the Greek and Roman World by the Digital Atlas of Roman and Medieval Civilizations project at Harvard University.",
        "location_precision": "precise",
        "title": "DARMC location 21277",
        "link": "http://pleiades.stoa.org/places/579958/darmc-location-21277"
      }
    }
  ]
}