{
  "type": "FeatureCollection",
  "title": "Kydantidai",
  "id": "579998",
  "description": "An ancient place, cited: BAtlas 59 C2 Kydantidai",
  "bbox": [
    23.891947,
    38.047374,
    23.891947,
    38.047374
  ],
  "reprPoint": [
    23.891947,
    38.047374
  ],
  "names": [
    "Kydantidai"
  ],
  "features": [
    {
      "geometry": {
        "type": "Point",
        "coordinates": [
          23.891947,
          38.047374
        ]
      },
      "id": "darmc-location-21561",
      "type": "Feature",
      "properties": {
        "description": "Point location",
        "location_precision": "precise",
        "title": "DARMC location 21561",
        "link": "http://pleiades.stoa.org/places/579998/darmc-location-21561"
      }
    }
  ]
}