{
  "type": "FeatureCollection",
  "title": "Merenda",
  "id": "580026",
  "description": "An ancient place, cited: BAtlas 59 C3 Merenda",
  "bbox": [
    23.966666,
    37.85,
    23.966666,
    37.85
  ],
  "reprPoint": [
    23.966666,
    37.85
  ],
  "features": [
    {
      "geometry": {
        "type": "Point",
        "coordinates": [
          23.966666,
          37.85
        ]
      },
      "id": "darmc-location-21304",
      "type": "Feature",
      "properties": {
        "description": "Point location",
        "location_precision": "precise",
        "title": "DARMC location 21304",
        "link": "http://pleiades.stoa.org/places/580026/darmc-location-21304"
      }
    }
  ]
}