{
  "type": "FeatureCollection",
  "title": "Kynosoura",
  "id": "580001",
  "description": "An ancient place, cited: BAtlas 59 D2 Kynosoura",
  "bbox": [
    24.05444,
    38.144304,
    24.05444,
    38.144304
  ],
  "reprPoint": [
    24.05444,
    38.144304
  ],
  "features": [
    {
      "geometry": {
        "type": "Point",
        "coordinates": [
          24.05444,
          38.144304
        ]
      },
      "id": "darmc-location-21297",
      "type": "Feature",
      "properties": {
        "description": "Point location",
        "location_precision": "precise",
        "title": "DARMC location 21297",
        "link": "http://pleiades.stoa.org/places/580001/darmc-location-21297"
      }
    }
  ]
}