{
  "type": "FeatureCollection",
  "title": "Lousia",
  "id": "580015",
  "bbox": [
    23.691421,
    38.000521,
    23.691421,
    38.000521
  ],
  "description": "An ancient place, cited: BAtlas 59 B2 Lousia",
  "names": [
    "Lousia"
  ],
  "features": [
    {
      "type": "Feature",
      "geometry": {
        "type": "Point",
        "coordinates": [
          23.691421,
          38.000521
        ]
      },
      "properties": {
        "description": "representative point"
      }
    },
    {
      "geometry": {
        "type": "Point",
        "coordinates": [
          23.691421,
          38.000521
        ]
      },
      "id": "darmc-location-22735",
      "type": "Feature",
      "properties": {
        "description": "Point location",
        "location_precision": "precise",
        "title": "DARMC location 22735",
        "link": "http://pleiades.stoa.org/places/580015/darmc-location-22735"
      }
    }
  ]
}