{
  "type": "FeatureCollection",
  "title": "Lamptrai Kathyperthen",
  "id": "580008",
  "description": "An ancient place, cited: BAtlas 59 C3 Lamptrai Kathyperthen",
  "bbox": [
    23.849996,
    37.876129,
    23.862649,
    37.879719
  ],
  "reprPoint": [
    23.8563225,
    37.877924
  ],
  "names": [
    "Lamptrai Kathyperthen"
  ],
  "features": [
    {
      "geometry": {
        "type": "Point",
        "coordinates": [
          23.862649,
          37.879719
        ]
      },
      "id": "darmc-location-22723",
      "type": "Feature",
      "properties": {
        "description": "Point location",
        "location_precision": "precise",
        "title": "DARMC location 22723",
        "link": "http://pleiades.stoa.org/places/580008/darmc-location-22723"
      }
    },
    {
      "geometry": {
        "type": "Point",
        "coordinates": [
          23.849996,
          37.876129
        ]
      },
      "id": "darmc-location-13396",
      "type": "Feature",
      "properties": {
        "description": "500K scale point location",
        "location_precision": "precise",
        "title": "DARMC location 13396",
        "link": "http://pleiades.stoa.org/places/580008/darmc-location-13396"
      }
    }
  ]
}