{
  "type": "FeatureCollection",
  "title": "Phreatto?",
  "id": "580078",
  "bbox": [
    23.651131,
    37.93452,
    23.651131,
    37.93452
  ],
  "description": "An ancient place, cited: BAtlas 59 B3 Phreatto?",
  "names": [
    "Phreatto",
    "Phreattys"
  ],
  "features": [
    {
      "type": "Feature",
      "geometry": {
        "type": "Point",
        "coordinates": [
          23.651131,
          37.93452
        ]
      },
      "properties": {
        "description": "representative point"
      }
    },
    {
      "geometry": {
        "type": "Point",
        "coordinates": [
          23.651131,
          37.93452
        ]
      },
      "id": "darmc-location-21318",
      "type": "Feature",
      "properties": {
        "description": "Representative point location digitized from the Barrington Atlas of the Greek and Roman World by the Digital Atlas of Roman and Medieval Civilizations project at Harvard University.",
        "location_precision": "precise",
        "title": "DARMC location 21318",
        "link": "http://pleiades.stoa.org/places/580078/darmc-location-21318"
      }
    }
  ]
}