{
  "type": "FeatureCollection",
  "title": "Sounion",
  "id": "580107",
  "bbox": [
    24.034812,
    37.682177,
    24.037027,
    37.684669
  ],
  "description": "The fortified port settlement at Sounion served the Athenian grain ships originating in Euboea and was the site of the sanctuary of Poseidon, among others.",
  "names": [
    "Sounion"
  ],
  "features": [
    {
      "type": "Feature",
      "geometry": {
        "type": "Point",
        "coordinates": [
          24.0359195,
          37.683423
        ]
      },
      "properties": {
        "description": "representative point"
      }
    },
    {
      "geometry": {
        "type": "Point",
        "coordinates": [
          24.037027,
          37.682177
        ]
      },
      "id": "darmc-location-14836",
      "type": "Feature",
      "properties": {
        "description": "500K scale point location",
        "location_precision": "precise",
        "title": "DARMC location 14836",
        "link": "http://pleiades.stoa.org/places/580107/darmc-location-14836"
      }
    },
    {
      "geometry": {
        "type": "Point",
        "coordinates": [
          24.034812,
          37.684669
        ]
      },
      "id": "darmc-location-21639",
      "type": "Feature",
      "properties": {
        "description": "Point location",
        "location_precision": "precise",
        "title": "DARMC location 21639",
        "link": "http://pleiades.stoa.org/places/580107/darmc-location-21639"
      }
    }
  ]
}