{
  "type": "FeatureCollection",
  "title": "Salamis Ins.",
  "id": "580101",
  "description": "Salamis is the largest island of the Saronic Gulf.",
  "bbox": [
    23.51,
    37.93,
    23.51,
    37.93
  ],
  "connectsWith": [
    "570654"
  ],
  "reprPoint": [
    23.51,
    37.93
  ],
  "names": [
    "Salamis"
  ],
  "features": [
    {
      "geometry": {
        "type": "Point",
        "coordinates": [
          23.51,
          37.93
        ]
      },
      "id": "location-of-salamis-ins",
      "type": "Feature",
      "properties": {
        "description": "Coordinates after BAtlas; verified in Google Earth 2013 with reference to Wikipedia.",
        "location_precision": "precise",
        "title": "location of Salamis Ins.",
        "link": "http://pleiades.stoa.org/places/580101/location-of-salamis-ins"
      }
    }
  ]
}