{
  "type": "FeatureCollection",
  "title": "Zeus Ombrios, T.",
  "id": "580137",
  "description": "An ancient place, cited: BAtlas 59 B2 Zeus Ombrios, T.",
  "bbox": [
    23.717493,
    38.174088,
    23.717493,
    38.174088
  ],
  "reprPoint": [
    23.717493,
    38.174088
  ],
  "names": [
    "Zeus Ombrios, T."
  ],
  "features": [
    {
      "geometry": {
        "type": "Point",
        "coordinates": [
          23.717493,
          38.174088
        ]
      },
      "id": "darmc-location-21588",
      "type": "Feature",
      "properties": {
        "description": "Point location",
        "location_precision": "precise",
        "title": "DARMC location 21588",
        "link": "http://pleiades.stoa.org/places/580137/darmc-location-21588"
      }
    }
  ]
}