{
  "type": "FeatureCollection",
  "title": "Sounion",
  "id": "580107",
  "bbox": [
    24.024606,
    37.650263,
    24.02725,
    37.653111
  ],
  "description": "The fortified port settlement at Sounion, a coastal deme of Leontis, served the Athenian grain ships originating in Euboea and was the site of the sanctuary of Poseidon, among others.",
  "connectsWith": [
    "579888"
  ],
  "names": [
    "Sounion"
  ],
  "features": [
    {
      "type": "Feature",
      "geometry": {
        "type": "Point",
        "coordinates": [
          24.027153,
          37.653
        ]
      },
      "properties": {
        "description": "representative point"
      }
    }
  ]
}