{
  "type": "FeatureCollection",
  "title": "Sounion",
  "id": "580107",
  "description": "An ancient place, cited: BAtlas 59 D4 Sounion",
  "bbox": [
    24.034812,
    37.682177,
    24.037027,
    37.684669
  ],
  "reprPoint": [
    24.0359195,
    37.683423
  ],
  "names": [
    "Sounion"
  ],
  "features": [
    {
      "geometry": {
        "type": "Point",
        "coordinates": [
          24.037027,
          37.682177
        ]
      },
      "id": "darmc-location-14836",
      "type": "Feature",
      "properties": {
        "description": "500K scale point location",
        "location_precision": "precise",
        "title": "DARMC location 14836",
        "link": "http://pleiades.stoa.org/places/580107/darmc-location-14836"
      }
    },
    {
      "geometry": {
        "type": "Point",
        "coordinates": [
          24.034812,
          37.684669
        ]
      },
      "id": "darmc-location-21639",
      "type": "Feature",
      "properties": {
        "description": "Point location",
        "location_precision": "precise",
        "title": "DARMC location 21639",
        "link": "http://pleiades.stoa.org/places/580107/darmc-location-21639"
      }
    },
    {
      "geometry": {
        "type": "Point",
        "coordinates": [
          24.027056,
          37.652889
        ]
      },
      "id": "athena-t",
      "type": "Feature",
      "properties": {
        "description": "Temple of Athena at Sounion with L-shaped colonnade. It was built on the site of an earlier temple at the same location.",
        "location_precision": "precise",
        "title": "Temple of Athena",
        "link": "http://pleiades.stoa.org/places/580107/athena-t"
      }
    },
    {
      "geometry": {
        "type": "Point",
        "coordinates": [
          24.02725,
          37.653111
        ]
      },
      "id": "phrontis-t",
      "type": "Feature",
      "properties": {
        "description": "The site of a shrine assumed to honor to the hero Phrontis.",
        "location_precision": "precise",
        "title": "Sanctuary of Phrontis(?)",
        "link": "http://pleiades.stoa.org/places/580107/phrontis-t"
      }
    }
  ]
}