{
  "type": "FeatureCollection",
  "title": "Sypalettos",
  "id": "580112",
  "description": "An ancient place, cited: BAtlas 59 C2 Sypalettos",
  "bbox": [
    23.759008,
    38.071385,
    23.76062,
    38.072254
  ],
  "reprPoint": [
    23.759814,
    38.0718195
  ],
  "names": [
    "Sypalettos"
  ],
  "features": [
    {
      "geometry": {
        "type": "Point",
        "coordinates": [
          23.759008,
          38.071385
        ]
      },
      "id": "darmc-location-14955",
      "type": "Feature",
      "properties": {
        "description": "500K scale point location",
        "location_precision": "precise",
        "title": "DARMC location 14955",
        "link": "http://pleiades.stoa.org/places/580112/darmc-location-14955"
      }
    },
    {
      "geometry": {
        "type": "Point",
        "coordinates": [
          23.76062,
          38.072254
        ]
      },
      "id": "darmc-location-21600",
      "type": "Feature",
      "properties": {
        "description": "Point location",
        "location_precision": "precise",
        "title": "DARMC location 21600",
        "link": "http://pleiades.stoa.org/places/580112/darmc-location-21600"
      }
    }
  ]
}