{
  "type": "FeatureCollection",
  "title": "Sypalettos",
  "id": "580112",
  "bbox": [
    23.759008,
    38.071385,
    23.76062,
    38.072254
  ],
  "description": "An ancient place, cited: BAtlas 59 C2 Sypalettos",
  "names": [
    "Sypalettos"
  ],
  "features": [
    {
      "type": "Feature",
      "geometry": {
        "type": "Point",
        "coordinates": [
          23.759814,
          38.0718195
        ]
      },
      "properties": {
        "description": "representative point"
      }
    },
    {
      "geometry": {
        "type": "Point",
        "coordinates": [
          23.759008,
          38.071385
        ]
      },
      "id": "darmc-location-14955",
      "type": "Feature",
      "properties": {
        "description": "1:500,000 scale representative point location digitized from the Barrington Atlas of the Greek and Roman World by the Digital Atlas of Roman and Medieval Civilizations project at Harvard University.",
        "location_precision": "precise",
        "title": "DARMC location 14955",
        "link": "http://pleiades.stoa.org/places/580112/darmc-location-14955"
      }
    },
    {
      "geometry": {
        "type": "Point",
        "coordinates": [
          23.76062,
          38.072254
        ]
      },
      "id": "darmc-location-21600",
      "type": "Feature",
      "properties": {
        "description": "Representative point location digitized from the Barrington Atlas of the Greek and Roman World by the Digital Atlas of Roman and Medieval Civilizations project at Harvard University.",
        "location_precision": "precise",
        "title": "DARMC location 21600",
        "link": "http://pleiades.stoa.org/places/580112/darmc-location-21600"
      }
    }
  ]
}