{
  "type": "FeatureCollection",
  "title": "Alcázar del rey Don Pedro",
  "id": "580732678",
  "bbox": [
    -5.633932,
    37.4736496,
    -5.633932,
    37.4736496
  ],
  "description": "A fortification at Carmona built by Pedro I of Castile.",
  "connectsWith": [
    "256058"
  ],
  "features": [
    {
      "type": "Feature",
      "geometry": {
        "type": "Point",
        "coordinates": [
          -5.633932,
          37.4736496
        ]
      },
      "properties": {
        "description": "representative point"
      }
    },
    {
      "geometry": {
        "type": "Point",
        "coordinates": [
          -5.633932,
          37.4736496
        ]
      },
      "id": "location-of-alcazar-del-rey-don-pedro",
      "type": "Feature",
      "properties": {
        "description": "Location based on OpenStreetMap",
        "location_precision": "precise",
        "title": "OSM location of Alcázar del rey Don Pedro",
        "link": "http://pleiades.stoa.org/places/580732678/location-of-alcazar-del-rey-don-pedro"
      }
    }
  ]
}