{
  "type": "FeatureCollection",
  "title": "Roman baths, Spoleto",
  "id": "582358500",
  "bbox": [
    12.7358992,
    42.7354504,
    12.7358992,
    42.7354504
  ],
  "description": "Roman baths located at Spoletium.",
  "connectsWith": [
    "413320"
  ],
  "features": [
    {
      "type": "Feature",
      "geometry": {
        "type": "Point",
        "coordinates": [
          12.7358992,
          42.7354504
        ]
      },
      "properties": {
        "description": "representative point"
      }
    },
    {
      "geometry": {
        "type": "Point",
        "coordinates": [
          12.7358992,
          42.7354504
        ]
      },
      "id": "osm-location-of-terme-romane",
      "type": "Feature",
      "properties": {
        "description": "Representative location based on OpenStreetMap",
        "location_precision": "precise",
        "title": "OSM location of Terme romane",
        "link": "http://pleiades.stoa.org/places/582358500/osm-location-of-terme-romane"
      }
    }
  ]
}