{
  "type": "FeatureCollection",
  "title": "Large Temple at Sikait",
  "id": "58370951",
  "bbox": [
    34.7970383,
    24.6308553,
    34.7970383,
    24.6308553
  ],
  "description": "A large rock-cut temple at Sikait in Egypt's Eastern desert.",
  "connectsWith": [
    "786114"
  ],
  "features": [
    {
      "type": "Feature",
      "geometry": {
        "type": "Point",
        "coordinates": [
          34.7970383,
          24.6308553
        ]
      },
      "properties": {
        "description": "representative point"
      }
    },
    {
      "geometry": {
        "type": "Point",
        "coordinates": [
          34.7970383,
          24.6308553
        ]
      },
      "id": "osm-location-of-large-temple",
      "type": "Feature",
      "properties": {
        "description": "Location based on OpenStreetMap, verified with Guzmán 2021 and in Google Earth. Dates after Guzmán.",
        "location_precision": "precise",
        "title": "OSM Location of Large Temple",
        "link": "http://pleiades.stoa.org/places/58370951/osm-location-of-large-temple"
      }
    }
  ]
}