{
  "type": "FeatureCollection",
  "title": "Villa di Teodorico",
  "id": "584523671",
  "bbox": [
    11.9138301,
    44.0045092,
    11.9138301,
    44.0045092
  ],
  "description": "A palatial Roman villa and bath complex that has been connected with Theodoric the Great, with twentieth century interpretations labeling it as Theodoric's \"hunting lodge\". More recent excavations have uncovered evidence for earlier building phases, dating from the first century B.C. through the third century A.D.",
  "connectsWith": [
    "413154"
  ],
  "features": [
    {
      "type": "Feature",
      "geometry": {
        "type": "Point",
        "coordinates": [
          11.9138301,
          44.0045092
        ]
      },
      "properties": {
        "description": "representative point"
      }
    },
    {
      "geometry": {
        "type": "Point",
        "coordinates": [
          11.9138301,
          44.0045092
        ]
      },
      "id": "location-of-roman-villa",
      "type": "Feature",
      "properties": {
        "description": "Location based on OpenStreetMap",
        "location_precision": "precise",
        "title": "OSM location of the so-called \"Villa di Teodorico\"",
        "link": "http://pleiades.stoa.org/places/584523671/location-of-roman-villa"
      }
    }
  ]
}