{
  "type": "FeatureCollection",
  "title": "Roman theater of Milan",
  "id": "585690561",
  "bbox": [
    9.1825625,
    45.465287,
    9.1825625,
    45.465287
  ],
  "description": "The Roman theater of Milan was built during the Augustan period and could accommodate 7,000 to 9,000 spectators.",
  "connectsWith": [
    "383706"
  ],
  "names": [
    "Teatro romano di Milano"
  ],
  "features": [
    {
      "type": "Feature",
      "geometry": {
        "type": "Point",
        "coordinates": [
          9.1825625,
          45.465287
        ]
      },
      "properties": {
        "description": "representative point"
      }
    },
    {
      "geometry": {
        "type": "Point",
        "coordinates": [
          9.1828441,
          45.4653175
        ]
      },
      "id": "location-of-roman-theater",
      "type": "Feature",
      "properties": {
        "description": "Representative location based on OpenStreetMap.",
        "location_precision": "precise",
        "title": "OSM location of Roman theater",
        "link": "http://pleiades.stoa.org/places/585690561/location-of-roman-theater"
      }
    }
  ]
}