{
  "type": "FeatureCollection",
  "title": "Mugharet Abu Halimeh",
  "id": "586635002",
  "bbox": [
    35.181022,
    32.319509,
    35.181022,
    32.319509
  ],
  "description": "Cave tomb near the modern village of Silat aḑ-Ḑahr containing burials from the Roman and Byzantine periods (1st-early 7th century CE). The cave is named after the Abu Halimeh family, which owned the land on which the cave is located at the time of its excavation in 1949.",
  "names": [
    "Mugharet Abu Halimeh"
  ],
  "features": [
    {
      "type": "Feature",
      "geometry": {
        "type": "Point",
        "coordinates": [
          35.181022,
          32.319509
        ]
      },
      "properties": {
        "description": "representative point"
      }
    },
    {
      "geometry": {
        "type": "Point",
        "coordinates": [
          35.181022,
          32.319509
        ]
      },
      "id": "google-earth-approximate-location-of-mugharet-abu-halimeh",
      "type": "Feature",
      "properties": {
        "description": "Point representing the approximate location of the Mugharet Abu Halimeh site, after Sellers and Barmki 1953.",
        "location_precision": "precise",
        "title": "Google Earth approximate location of Mugharet Abu Halimeh",
        "link": "http://pleiades.stoa.org/places/586635002/google-earth-approximate-location-of-mugharet-abu-halimeh"
      }
    }
  ]
}