{
  "type": "FeatureCollection",
  "title": "Crac des Chevaliers",
  "id": "587486981",
  "description": "An ancient castle, located in modern Syria. Inscribed as a UNESCO World Heritage Site in 2006 as part of the \"Crac des Chevaliers and Qal’at Salah El-Din\" listing.",
  "bbox": [
    36.294731,
    34.756897,
    36.294731,
    34.756897
  ],
  "reprPoint": [
    36.294731,
    34.756897
  ],
  "features": [
    {
      "geometry": {
        "type": "Point",
        "coordinates": [
          36.294731,
          34.756897
        ]
      },
      "id": "crac-des-chevaliers",
      "type": "Feature",
      "properties": {
        "description": "Location of Crac des Chevaliers. Coordinates determined by eye in Google Earth in November 2012, following description in UNESCO World Heritage List.",
        "location_precision": "precise",
        "title": "Crac des Chevaliers",
        "link": "http://pleiades.stoa.org/places/587486981/crac-des-chevaliers"
      }
    }
  ]
}