{
  "type": "FeatureCollection",
  "title": "Antiskari",
  "id": "589695",
  "bbox": [
    24.881359,
    34.963671,
    24.881359,
    34.963671
  ],
  "description": "An ancient place, cited: BAtlas 60 C3 Antiskari",
  "features": [
    {
      "type": "Feature",
      "geometry": {
        "type": "Point",
        "coordinates": [
          24.881359,
          34.963671
        ]
      },
      "properties": {
        "description": "representative point"
      }
    },
    {
      "geometry": {
        "type": "Point",
        "coordinates": [
          24.881359,
          34.963671
        ]
      },
      "id": "darmc-location-19169",
      "type": "Feature",
      "properties": {
        "description": "500K scale point location",
        "location_precision": "precise",
        "title": "DARMC location 19169",
        "link": "http://pleiades.stoa.org/places/589695/darmc-location-19169"
      }
    }
  ]
}