{
  "type": "FeatureCollection",
  "title": "Apellonia?",
  "id": "589696",
  "bbox": [
    25.018525,
    35.404896,
    25.018525,
    35.404896
  ],
  "description": "An ancient place, cited: BAtlas 60 D2 Apellonia?",
  "names": [
    "Apellonia",
    "Apollonia"
  ],
  "features": [
    {
      "type": "Feature",
      "geometry": {
        "type": "Point",
        "coordinates": [
          25.018525,
          35.404896
        ]
      },
      "properties": {
        "description": "representative point"
      }
    },
    {
      "geometry": {
        "type": "Point",
        "coordinates": [
          25.018525,
          35.404896
        ]
      },
      "id": "darmc-location-11424",
      "type": "Feature",
      "properties": {
        "description": "1:500,000 scale representative point location digitized from the Barrington Atlas of the Greek and Roman World by the Digital Atlas of Roman and Medieval Civilizations project at Harvard University.",
        "location_precision": "precise",
        "title": "DARMC location 11424",
        "link": "http://pleiades.stoa.org/places/589696/darmc-location-11424"
      }
    }
  ]
}