{
  "type": "FeatureCollection",
  "title": "*Aina?",
  "id": "589677",
  "bbox": [
    24.928581,
    35.058417,
    24.928581,
    35.058417
  ],
  "description": "An ancient place, cited: BAtlas 60 C2 *Aina?",
  "connectsWith": [
    "589748"
  ],
  "names": [
    "Aina"
  ],
  "features": [
    {
      "type": "Feature",
      "geometry": {
        "type": "Point",
        "coordinates": [
          24.928581,
          35.058417
        ]
      },
      "properties": {
        "description": "representative point"
      }
    },
    {
      "geometry": {
        "type": "Point",
        "coordinates": [
          24.928581,
          35.058417
        ]
      },
      "id": "darmc-location-11259",
      "type": "Feature",
      "properties": {
        "description": "500K scale point location",
        "location_precision": "precise",
        "title": "DARMC location 11259",
        "link": "http://pleiades.stoa.org/places/589677/darmc-location-11259"
      }
    }
  ]
}