{
  "type": "FeatureCollection",
  "title": "Acharna",
  "id": "589657",
  "description": "An ancient place, cited: BAtlas 60 D2 Acharna",
  "bbox": [
    25.1595012,
    35.2362295,
    25.163164,
    35.236772
  ],
  "connectsWith": [
    "589748"
  ],
  "reprPoint": [
    25.1613326,
    35.23650075
  ],
  "names": [
    "Acharna"
  ],
  "features": [
    {
      "geometry": {
        "type": "Point",
        "coordinates": [
          25.163164,
          35.236772
        ]
      },
      "id": "darmc-location-11164",
      "type": "Feature",
      "properties": {
        "description": "500K scale point location",
        "location_precision": "precise",
        "title": "DARMC location 11164",
        "link": "http://pleiades.stoa.org/places/589657/darmc-location-11164"
      }
    }
  ]
}