{
  "type": "FeatureCollection",
  "title": "Eltynia",
  "id": "589774",
  "bbox": [
    25.1853171,
    35.2384257,
    25.1853171,
    35.2384257
  ],
  "description": "An ancient place, cited: BAtlas 60 D2 Eltynia",
  "connectsWith": [
    "589748"
  ],
  "names": [
    "Eltynia"
  ],
  "features": [
    {
      "type": "Feature",
      "geometry": {
        "type": "Point",
        "coordinates": [
          25.1853171,
          35.2384257
        ]
      },
      "properties": {
        "description": "representative point"
      }
    },
    {
      "geometry": {
        "type": "Point",
        "coordinates": [
          25.1853171,
          35.2384257
        ]
      },
      "id": "39a3bf3c53bd3b23bf3b9",
      "type": "Feature",
      "properties": {
        "description": "Location based on OpenStreetMap",
        "location_precision": "precise",
        "title": "Κουνάβοι",
        "link": "http://pleiades.stoa.org/places/589774/39a3bf3c53bd3b23bf3b9"
      }
    }
  ]
}