{
  "type": "FeatureCollection",
  "title": "Aptera",
  "id": "589704",
  "bbox": [
    24.1405648,
    35.4629885,
    24.1405648,
    35.4629885
  ],
  "description": "An ancient place, cited: BAtlas 60 B2 Aptera",
  "connectsWith": [
    "589748"
  ],
  "names": [
    "Aptera",
    "Aptara"
  ],
  "features": [
    {
      "type": "Feature",
      "geometry": {
        "type": "Point",
        "coordinates": [
          24.1405648,
          35.4629885
        ]
      },
      "properties": {
        "description": "representative point"
      }
    },
    {
      "geometry": {
        "type": "Point",
        "coordinates": [
          24.1405648,
          35.4629885
        ]
      },
      "id": "location-of-aptera",
      "type": "Feature",
      "properties": {
        "description": "Representative location based on OpenStreetMap",
        "location_precision": "precise",
        "title": "OSM location of Απτέρα",
        "link": "http://pleiades.stoa.org/places/589704/location-of-aptera"
      }
    }
  ]
}