{
  "type": "FeatureCollection",
  "title": "Dreros",
  "id": "589767",
  "bbox": [
    25.6261738,
    35.256232,
    25.629044,
    35.2581262
  ],
  "description": "An ancient Greek settlement near modern Neapoli in the Lasithi region of Crete (about 15km northwest of Agios Nikolaos).",
  "connectsWith": [
    "589748"
  ],
  "names": [
    "Drêros",
    "Dréros"
  ],
  "features": [
    {
      "type": "Feature",
      "geometry": {
        "type": "Point",
        "coordinates": [
          25.6276089,
          35.2571791
        ]
      },
      "properties": {
        "description": "representative point"
      }
    },
    {
      "geometry": {
        "type": "Point",
        "coordinates": [
          25.629044,
          35.256232
        ]
      },
      "id": "imagery-location-centerpoint-of-visible-remains-of-dreros-approx.",
      "type": "Feature",
      "properties": {
        "description": "Surveyed by eye in Google Earth on September 27, 2012 at an eye altitude of 4395 feet. Dates after BAtlas.",
        "location_precision": "precise",
        "title": "Imagery Location: Centerpoint of visible remains of Dreros (approx.)",
        "link": "http://pleiades.stoa.org/places/589767/imagery-location-centerpoint-of-visible-remains-of-dreros-approx."
      }
    },
    {
      "geometry": {
        "type": "Point",
        "coordinates": [
          25.6261738,
          35.2581262
        ]
      },
      "id": "osm-location-dreros",
      "type": "Feature",
      "properties": {
        "description": "Location based on OpenStreetMap",
        "location_precision": "precise",
        "title": "OSM Location: Dreros",
        "link": "http://pleiades.stoa.org/places/589767/osm-location-dreros"
      }
    }
  ]
}