{
  "type": "FeatureCollection",
  "title": "Chersonesos",
  "id": "589745",
  "description": "An ancient place, cited: BAtlas 60 A2 Chersonesos",
  "bbox": [
    23.533687,
    35.378747,
    23.533687,
    35.378747
  ],
  "reprPoint": [
    23.533687,
    35.378747
  ],
  "names": [
    "Chersonesos"
  ],
  "features": [
    {
      "geometry": {
        "type": "Point",
        "coordinates": [
          23.533687,
          35.378747
        ]
      },
      "id": "darmc-location-2988",
      "type": "Feature",
      "properties": {
        "description": "500K scale point location",
        "location_precision": "precise",
        "title": "DARMC location 2988",
        "link": "http://pleiades.stoa.org/places/589745/darmc-location-2988"
      }
    }
  ]
}