{
  "type": "FeatureCollection",
  "title": "*Brasos",
  "id": "589737",
  "bbox": [
    27.7951945381,
    36.1474512544,
    27.7951945381,
    36.1474512544
  ],
  "description": "An ancient settlement of Roman date in western Rhodes attested in ancient textual sources. It may be associated with a locale known today as Prasos/Kastelli.",
  "names": [
    "Brasos"
  ],
  "features": [
    {
      "type": "Feature",
      "geometry": {
        "type": "Point",
        "coordinates": [
          27.7951945381,
          36.1474512544
        ]
      },
      "properties": {
        "description": "representative point"
      }
    },
    {
      "geometry": {
        "type": "Point",
        "coordinates": [
          27.795194538095945,
          36.147451254365855
        ]
      },
      "id": "batlas-location-of-brasos",
      "type": "Feature",
      "properties": {
        "description": "Barrington Atlas hollow point icon digitized using QGIS from a raster image of the BAtlas map georegistered to the original projection (ONC G-3) using grid lines. Dates after BAtlDir.",
        "location_precision": "precise",
        "title": "BAtlas Location of *Brasos",
        "link": "http://pleiades.stoa.org/places/589737/batlas-location-of-brasos"
      }
    }
  ]
}