{
  "type": "FeatureCollection",
  "title": "Aptera",
  "id": "589704",
  "bbox": [
    24.1405648,
    35.4629885,
    24.149388,
    35.466552
  ],
  "description": "An ancient place, cited: BAtlas 60 B2 Aptera",
  "connectsWith": [
    "589748"
  ],
  "names": [
    "Aptera",
    "Aptara"
  ],
  "features": [
    {
      "type": "Feature",
      "geometry": {
        "type": "Point",
        "coordinates": [
          24.1449764,
          35.46477025
        ]
      },
      "properties": {
        "description": "representative point"
      }
    },
    {
      "geometry": {
        "type": "Point",
        "coordinates": [
          24.149388,
          35.466552
        ]
      },
      "id": "darmc-location-11442",
      "type": "Feature",
      "properties": {
        "description": "1:500,000 scale representative point location digitized from the Barrington Atlas of the Greek and Roman World by the Digital Atlas of Roman and Medieval Civilizations project at Harvard University.",
        "location_precision": "precise",
        "title": "DARMC location 11442",
        "link": "http://pleiades.stoa.org/places/589704/darmc-location-11442"
      }
    },
    {
      "geometry": {
        "type": "Point",
        "coordinates": [
          24.1405648,
          35.4629885
        ]
      },
      "id": "location-of-aptera",
      "type": "Feature",
      "properties": {
        "description": "Location based on OpenStreetMap",
        "location_precision": "precise",
        "title": "location of Aptera",
        "link": "http://pleiades.stoa.org/places/589704/location-of-aptera"
      }
    }
  ]
}