{
  "type": "FeatureCollection",
  "title": "Arkaseia",
  "id": "589711",
  "description": "An ancient place, cited: BAtlas 60 E5 Arkaseia",
  "bbox": [
    27.1204377,
    35.4775744,
    27.1204377,
    35.4775744
  ],
  "connectsWith": [
    "589841"
  ],
  "reprPoint": [
    27.1204377,
    35.4775744
  ],
  "names": [
    "Arkaseia"
  ],
  "features": [
    {
      "geometry": {
        "type": "Point",
        "coordinates": [
          27.1204377,
          35.4775744
        ]
      },
      "id": "location-of-arkasa",
      "type": "Feature",
      "properties": {
        "description": "Location based on OpenStreetMap",
        "location_precision": "precise",
        "title": "location of Arkasa",
        "link": "http://pleiades.stoa.org/places/589711/location-of-arkasa"
      }
    }
  ]
}