{
  "type": "FeatureCollection",
  "title": "Dreros",
  "id": "589767",
  "description": "An ancient Greek settlement near modern Neapoli in the Lasithi region of Crete (about 15km northwest of Agios Nikolaos).",
  "bbox": [
    25.62454,
    35.256232,
    25.629044,
    35.257096
  ],
  "connectsWith": [
    "589748"
  ],
  "reprPoint": [
    25.626792,
    35.256664
  ],
  "names": [
    "Dreros"
  ],
  "features": [
    {
      "geometry": {
        "type": "Point",
        "coordinates": [
          25.629044,
          35.256232
        ]
      },
      "id": "centerpoint-of-visible-remains-of-dreros-approx.",
      "type": "Feature",
      "properties": {
        "description": "Surveyed by eye in Google Earth on September 27, 2012 at an eye altitude of 4395 feet. Dates after BAtlas.",
        "location_precision": "precise",
        "title": "Centerpoint of visible remains of Dreros (approx.)",
        "link": "http://pleiades.stoa.org/places/589767/centerpoint-of-visible-remains-of-dreros-approx."
      }
    }
  ]
}