{
  "type": "FeatureCollection",
  "title": "Didymoi? Sinus",
  "id": "589758",
  "bbox": [
    26.1455,
    35.20801,
    26.1455,
    35.20801
  ],
  "description": "The ancient \"Didymoi\" bay on the Cretan coast is possibly to be identified with the modern Bay of Sitia.",
  "names": [
    "Ormos Siteias",
    "Didymoi Sinus"
  ],
  "features": [
    {
      "type": "Feature",
      "geometry": {
        "type": "Point",
        "coordinates": [
          26.1455,
          35.20801
        ]
      },
      "properties": {
        "description": "representative point"
      }
    },
    {
      "geometry": {
        "type": "Point",
        "coordinates": [
          26.1455,
          35.20801
        ]
      },
      "id": "geonames-location-of-ormos-siteias",
      "type": "Feature",
      "properties": {
        "description": "Coordinates following GeoNames",
        "location_precision": "precise",
        "title": "GeoNames location of Órmos Siteías",
        "link": "http://pleiades.stoa.org/places/589758/geonames-location-of-ormos-siteias"
      }
    }
  ]
}