{
  "type": "FeatureCollection",
  "title": "Eronos?",
  "id": "589781",
  "bbox": [
    25.481758,
    35.171325,
    25.481758,
    35.171325
  ],
  "description": "An ancient place, cited: BAtlas 60 D2 Eronos?",
  "names": [
    "Eronos",
    "Erannos"
  ],
  "features": [
    {
      "type": "Feature",
      "geometry": {
        "type": "Point",
        "coordinates": [
          25.481758,
          35.171325
        ]
      },
      "properties": {
        "description": "representative point"
      }
    },
    {
      "geometry": {
        "type": "Point",
        "coordinates": [
          25.481758,
          35.171325
        ]
      },
      "id": "darmc-location-12378",
      "type": "Feature",
      "properties": {
        "description": "1:500,000 scale representative point location digitized from the Barrington Atlas of the Greek and Roman World by the Digital Atlas of Roman and Medieval Civilizations project at Harvard University.",
        "location_precision": "precise",
        "title": "DARMC location 12378",
        "link": "http://pleiades.stoa.org/places/589781/darmc-location-12378"
      }
    }
  ]
}