{
  "type": "FeatureCollection",
  "title": "Apollonia?",
  "id": "589703",
  "description": "An ancient place, cited: BAtlas 60 D2 Apollonia?",
  "bbox": [
    25.069229,
    35.3270599,
    25.069229,
    35.3270599
  ],
  "connectsWith": [
    "589748"
  ],
  "reprPoint": [
    25.069229,
    35.3270599
  ],
  "names": [
    "Apollonia"
  ],
  "features": [
    {
      "geometry": {
        "type": "Point",
        "coordinates": [
          25.069229,
          35.3270599
        ]
      },
      "id": "3933b63b9",
      "type": "Feature",
      "properties": {
        "description": "Location based on OpenStreetMap",
        "location_precision": "precise",
        "title": "Γάζι",
        "link": "http://pleiades.stoa.org/places/589703/3933b63b9"
      }
    }
  ]
}