{
  "type": "FeatureCollection",
  "title": "*Aria?",
  "id": "589709",
  "description": "An ancient place, cited: BAtlas 60 D3 *Aria?",
  "bbox": [
    25.450283,
    34.992568,
    25.450283,
    34.992568
  ],
  "reprPoint": [
    25.450283,
    34.992568
  ],
  "names": [
    "Aria",
    "Albe"
  ],
  "features": [
    {
      "geometry": {
        "type": "Point",
        "coordinates": [
          25.450283,
          34.992568
        ]
      },
      "id": "darmc-location-11487",
      "type": "Feature",
      "properties": {
        "description": "500K scale point location",
        "location_precision": "precise",
        "title": "DARMC location 11487",
        "link": "http://pleiades.stoa.org/places/589709/darmc-location-11487"
      }
    }
  ]
}