{
  "type": "FeatureCollection",
  "title": "Arkades",
  "id": "589710",
  "bbox": [
    25.282439,
    35.080331,
    25.282439,
    35.080331
  ],
  "description": "An ancient place, cited: BAtlas 60 D2 Arkades",
  "connectsWith": [
    "589748"
  ],
  "names": [
    "Arkades",
    "Arkadia"
  ],
  "features": [
    {
      "type": "Feature",
      "geometry": {
        "type": "Point",
        "coordinates": [
          25.282439,
          35.080331
        ]
      },
      "properties": {
        "description": "representative point"
      }
    },
    {
      "geometry": {
        "type": "Point",
        "coordinates": [
          25.282439,
          35.080331
        ]
      },
      "id": "darmc-location-11497",
      "type": "Feature",
      "properties": {
        "description": "500K scale point location",
        "location_precision": "precise",
        "title": "DARMC location 11497",
        "link": "http://pleiades.stoa.org/places/589710/darmc-location-11497"
      }
    }
  ]
}