{
  "type": "FeatureCollection",
  "title": "Bene?",
  "id": "589727",
  "description": "An ancient place, cited: BAtlas 60 D2 Bene?",
  "bbox": [
    25.07758,
    35.003313,
    25.07758,
    35.003313
  ],
  "reprPoint": [
    25.07758,
    35.003313
  ],
  "names": [
    "Bene"
  ],
  "features": [
    {
      "geometry": {
        "type": "Point",
        "coordinates": [
          25.07758,
          35.003313
        ]
      },
      "id": "darmc-location-11697",
      "type": "Feature",
      "properties": {
        "description": "500K scale point location",
        "location_precision": "precise",
        "title": "DARMC location 11697",
        "link": "http://pleiades.stoa.org/places/589727/darmc-location-11697"
      }
    }
  ]
}