{
  "type": "FeatureCollection",
  "title": "Hierapytna",
  "id": "589807",
  "description": "An ancient place, cited: BAtlas 60 E2 Hierapytna",
  "bbox": [
    25.737138,
    35.009031,
    25.740363,
    35.010026
  ],
  "connectsWith": [
    "589748"
  ],
  "reprPoint": [
    25.7387505,
    35.0095285
  ],
  "names": [
    "Hierapytna",
    "Kyrba",
    "Pytna",
    "Kamiros"
  ],
  "features": [
    {
      "geometry": {
        "type": "Point",
        "coordinates": [
          25.740363,
          35.010026
        ]
      },
      "id": "darmc-location-23906",
      "type": "Feature",
      "properties": {
        "description": "5M scale point location",
        "location_precision": "precise",
        "title": "DARMC location 23906",
        "link": "http://pleiades.stoa.org/places/589807/darmc-location-23906"
      }
    },
    {
      "geometry": {
        "type": "Point",
        "coordinates": [
          25.737138,
          35.009031
        ]
      },
      "id": "darmc-location-283",
      "type": "Feature",
      "properties": {
        "description": "500K scale point location",
        "location_precision": "precise",
        "title": "DARMC location 283",
        "link": "http://pleiades.stoa.org/places/589807/darmc-location-283"
      }
    }
  ]
}