{
  "type": "FeatureCollection",
  "title": "Kamilari",
  "id": "589835",
  "bbox": [
    24.793826,
    35.022837,
    24.793826,
    35.022837
  ],
  "description": "An ancient settlement on the island of Crete whose ancient name is not known (BAtlas 60 C2 Kamilari)",
  "features": [
    {
      "type": "Feature",
      "geometry": {
        "type": "Point",
        "coordinates": [
          24.793826,
          35.022837
        ]
      },
      "properties": {
        "description": "representative point"
      }
    },
    {
      "geometry": {
        "type": "Point",
        "coordinates": [
          24.793826,
          35.022837
        ]
      },
      "id": "darmc-location-12974",
      "type": "Feature",
      "properties": {
        "description": "500K scale point location",
        "location_precision": "precise",
        "title": "DARMC location 12974",
        "link": "http://pleiades.stoa.org/places/589835/darmc-location-12974"
      }
    }
  ]
}