{
  "type": "FeatureCollection",
  "title": "Kytaion?",
  "id": "589889",
  "description": "An ancient place, cited: BAtlas 60 C2 Kytaion?",
  "bbox": [
    24.878375,
    35.407779,
    24.878375,
    35.407779
  ],
  "reprPoint": [
    24.878375,
    35.407779
  ],
  "names": [
    "Kytaion"
  ],
  "features": [
    {
      "geometry": {
        "type": "Point",
        "coordinates": [
          24.878375,
          35.407779
        ]
      },
      "id": "darmc-location-13359",
      "type": "Feature",
      "properties": {
        "description": "500K scale point location",
        "location_precision": "precise",
        "title": "DARMC location 13359",
        "link": "http://pleiades.stoa.org/places/589889/darmc-location-13359"
      }
    }
  ]
}