{
  "type": "FeatureCollection",
  "title": "Kamilari",
  "id": "589835",
  "bbox": [
    24.78692,
    35.045356,
    24.78692,
    35.045356
  ],
  "description": "An ancient settlement on the island of Crete whose ancient name is not known.",
  "connectsWith": [
    "589748"
  ],
  "features": [
    {
      "type": "Feature",
      "geometry": {
        "type": "Point",
        "coordinates": [
          24.78692,
          35.045356
        ]
      },
      "properties": {
        "description": "representative point"
      }
    },
    {
      "geometry": {
        "type": "Point",
        "coordinates": [
          24.78692,
          35.045356
        ]
      },
      "id": "tholotos-taphos-kamelareou",
      "type": "Feature",
      "properties": {
        "description": "Point representing the location of the visible remains of Tholos Tomb A at Kamilari, derived from an OpenStreetMap Node.",
        "location_precision": "precise",
        "title": "OSM location of Θόλωτος Τάφος Καμηλάρηου",
        "link": "http://pleiades.stoa.org/places/589835/tholotos-taphos-kamelareou"
      }
    }
  ]
}