{
  "type": "FeatureCollection",
  "title": "Katharo",
  "id": "589854",
  "bbox": [
    25.579513,
    35.14556,
    25.579513,
    35.14556
  ],
  "description": "An ancient place, cited: BAtlas 60 E2 Katharo",
  "features": [
    {
      "type": "Feature",
      "geometry": {
        "type": "Point",
        "coordinates": [
          25.579513,
          35.14556
        ]
      },
      "properties": {
        "description": "representative point"
      }
    },
    {
      "geometry": {
        "type": "Point",
        "coordinates": [
          25.579513,
          35.14556
        ]
      },
      "id": "darmc-location-13060",
      "type": "Feature",
      "properties": {
        "description": "500K scale point location",
        "location_precision": "precise",
        "title": "DARMC location 13060",
        "link": "http://pleiades.stoa.org/places/589854/darmc-location-13060"
      }
    }
  ]
}