{
  "type": "FeatureCollection",
  "title": "Kranaion Antron",
  "id": "589881",
  "description": "An ancient place, cited: BAtlas 60 C2 Kranaion Antron",
  "bbox": [
    24.585537,
    35.256901,
    24.585537,
    35.256901
  ],
  "reprPoint": [
    24.585537,
    35.256901
  ],
  "names": [
    "Kranaion Antron"
  ],
  "features": [
    {
      "geometry": {
        "type": "Point",
        "coordinates": [
          24.585537,
          35.256901
        ]
      },
      "id": "darmc-location-16042",
      "type": "Feature",
      "properties": {
        "description": "500K scale point location",
        "location_precision": "precise",
        "title": "DARMC location 16042",
        "link": "http://pleiades.stoa.org/places/589881/darmc-location-16042"
      }
    }
  ]
}