{
  "type": "FeatureCollection",
  "title": "Kolokythia",
  "id": "589874",
  "description": "An ancient place, cited: BAtlas 60 E2 Kolokythia",
  "bbox": [
    25.750284,
    35.259521,
    25.750284,
    35.259521
  ],
  "reprPoint": [
    25.750284,
    35.259521
  ],
  "features": [
    {
      "geometry": {
        "type": "Point",
        "coordinates": [
          25.750284,
          35.259521
        ]
      },
      "id": "darmc-location-13236",
      "type": "Feature",
      "properties": {
        "description": "500K scale point location",
        "location_precision": "precise",
        "title": "DARMC location 13236",
        "link": "http://pleiades.stoa.org/places/589874/darmc-location-13236"
      }
    }
  ]
}