{
  "type": "FeatureCollection",
  "title": "Katre?",
  "id": "589856",
  "bbox": [
    23.707219,
    35.280752,
    23.707219,
    35.280752
  ],
  "description": "An ancient place, cited: BAtlas 60 A2 Katre?",
  "names": [
    "Katre"
  ],
  "features": [
    {
      "type": "Feature",
      "geometry": {
        "type": "Point",
        "coordinates": [
          23.707219,
          35.280752
        ]
      },
      "properties": {
        "description": "representative point"
      }
    },
    {
      "geometry": {
        "type": "Point",
        "coordinates": [
          23.707219,
          35.280752
        ]
      },
      "id": "darmc-location-13067",
      "type": "Feature",
      "properties": {
        "description": "1:500,000 scale representative point location digitized from the Barrington Atlas of the Greek and Roman World by the Digital Atlas of Roman and Medieval Civilizations project at Harvard University.",
        "location_precision": "precise",
        "title": "DARMC location 13067",
        "link": "http://pleiades.stoa.org/places/589856/darmc-location-13067"
      }
    }
  ]
}