{
  "type": "FeatureCollection",
  "title": "Messapos? fl.",
  "id": "589929",
  "description": "An ancient place, cited: BAtlas 60 B2 Messapos? fl.",
  "bbox": [
    24.3171446,
    35.35351,
    24.3171446,
    35.35351
  ],
  "reprPoint": [
    24.3171446,
    35.35351
  ],
  "names": [
    "Messapos"
  ],
  "features": [
    {
      "geometry": {
        "type": "Point",
        "coordinates": [
          24.3171446,
          35.35351
        ]
      },
      "id": "osm-way-98610618",
      "type": "Feature",
      "properties": {
        "description": "Location based on OpenStreetMap, matched to the BAtlas by AWMC",
        "location_precision": "precise",
        "title": "location of Mafselas (river)",
        "link": "http://pleiades.stoa.org/places/589929/osm-way-98610618"
      }
    }
  ]
}