{
  "type": "FeatureCollection",
  "title": "Paraskeues to Petali",
  "id": "589978",
  "bbox": [
    24.666667,
    36.983333,
    24.666667,
    36.983333
  ],
  "description": "An ancient place, cited: BAtlas 60 C4 Paraskeues to Petali",
  "connectsWith": [
    "590049"
  ],
  "features": [
    {
      "type": "Feature",
      "geometry": {
        "type": "Point",
        "coordinates": [
          24.666667,
          36.983333
        ]
      },
      "properties": {
        "description": "representative point"
      }
    },
    {
      "geometry": null,
      "id": "batlas-location",
      "type": "Feature",
      "properties": {
        "description": null,
        "location_precision": "unlocated",
        "title": "Barrington Atlas location",
        "link": "http://pleiades.stoa.org/places/589978/batlas-location"
      }
    }
  ]
}