{
  "type": "FeatureCollection",
  "title": "Pannona?",
  "id": "589972",
  "bbox": [
    25.03539,
    35.146088,
    25.03539,
    35.146088
  ],
  "description": "An ancient place, cited: BAtlas 60 D2 Pannona?",
  "names": [
    "Pannona"
  ],
  "features": [
    {
      "type": "Feature",
      "geometry": {
        "type": "Point",
        "coordinates": [
          25.03539,
          35.146088
        ]
      },
      "properties": {
        "description": "representative point"
      }
    },
    {
      "geometry": {
        "type": "Point",
        "coordinates": [
          25.03539,
          35.146088
        ]
      },
      "id": "darmc-location-14122",
      "type": "Feature",
      "properties": {
        "description": "500K scale point location",
        "location_precision": "precise",
        "title": "DARMC location 14122",
        "link": "http://pleiades.stoa.org/places/589972/darmc-location-14122"
      }
    }
  ]
}