{
  "type": "FeatureCollection",
  "title": "Phalanna?",
  "id": "589988",
  "bbox": [
    24.508285,
    35.264859,
    24.508285,
    35.264859
  ],
  "description": "An ancient place, cited: BAtlas 60 C2 Phalanna?",
  "connectsWith": [
    "589748"
  ],
  "names": [
    "Phalanna"
  ],
  "features": [
    {
      "type": "Feature",
      "geometry": {
        "type": "Point",
        "coordinates": [
          24.508285,
          35.264859
        ]
      },
      "properties": {
        "description": "representative point"
      }
    },
    {
      "geometry": {
        "type": "Point",
        "coordinates": [
          24.508285,
          35.264859
        ]
      },
      "id": "darmc-location-14221",
      "type": "Feature",
      "properties": {
        "description": "1:500,000 scale representative point location digitized from the Barrington Atlas of the Greek and Roman World by the Digital Atlas of Roman and Medieval Civilizations project at Harvard University.",
        "location_precision": "precise",
        "title": "DARMC location 14221",
        "link": "http://pleiades.stoa.org/places/589988/darmc-location-14221"
      }
    }
  ]
}