{
  "type": "FeatureCollection",
  "title": "Patela",
  "id": "589981",
  "description": "An ancient place, cited: BAtlas 60 D2 Patela",
  "bbox": [
    25.000922,
    35.168633,
    25.000922,
    35.168633
  ],
  "connectsWith": [
    "589748"
  ],
  "reprPoint": [
    25.000922,
    35.168633
  ],
  "features": [
    {
      "geometry": {
        "type": "Point",
        "coordinates": [
          25.000922,
          35.168633
        ]
      },
      "id": "darmc-location-14147",
      "type": "Feature",
      "properties": {
        "description": "500K scale point location",
        "location_precision": "precise",
        "title": "DARMC location 14147",
        "link": "http://pleiades.stoa.org/places/589981/darmc-location-14147"
      }
    }
  ]
}