{
  "type": "FeatureCollection",
  "title": "Lindos",
  "id": "589913",
  "bbox": [
    28.0881777,
    36.0911173,
    28.0882281,
    36.0913239
  ],
  "description": "Lindos is an ancient city located on the island of Rhodes.",
  "connectsWith": [
    "590031"
  ],
  "names": [
    "Lindos",
    "Lindia"
  ],
  "features": [
    {
      "type": "Feature",
      "geometry": {
        "type": "Point",
        "coordinates": [
          28.0882029,
          36.0912206
        ]
      },
      "properties": {
        "description": "representative point"
      }
    },
    {
      "geometry": {
        "type": "Point",
        "coordinates": [
          28.0881777,
          36.0913239
        ]
      },
      "id": "dare-location",
      "type": "Feature",
      "properties": {
        "description": "Representative point location, site precision",
        "location_precision": "precise",
        "title": "DARE Location",
        "link": "http://pleiades.stoa.org/places/589913/dare-location"
      }
    },
    {
      "geometry": {
        "type": "Point",
        "coordinates": [
          28.0882281,
          36.0911173
        ]
      },
      "id": "location-of-temple-of-athena-lindia",
      "type": "Feature",
      "properties": {
        "description": "Location based on OpenStreetMap",
        "location_precision": "precise",
        "title": "OSM location of Temple of Athena Lindia",
        "link": "http://pleiades.stoa.org/places/589913/location-of-temple-of-athena-lindia"
      }
    }
  ]
}