{
  "type": "FeatureCollection",
  "title": "Prinias (Patela)",
  "id": "589981",
  "description": "An Iron Age settlement on the Patela plateau north of the modern village of Prinias; its ancient name is uncertain. The site is notable for its occupation from the end of the Bronze Age through to the Archaic period, as well as for the monumental architecture and Orientalizing sculpture of its Buildings ('Temples') A and B. ",
  "bbox": [
    25.000922,
    35.168633,
    25.000922,
    35.168633
  ],
  "connectsWith": [
    "589748"
  ],
  "reprPoint": [
    25.000922,
    35.168633
  ],
  "names": [
    "Patela",
    "Prinias",
    "Rhizenia"
  ],
  "features": [
    {
      "geometry": {
        "type": "Point",
        "coordinates": [
          25.000922,
          35.168633
        ]
      },
      "id": "darmc-location-14147",
      "type": "Feature",
      "properties": {
        "description": "500K scale point location",
        "location_precision": "precise",
        "title": "DARMC location 14147",
        "link": "http://pleiades.stoa.org/places/589981/darmc-location-14147"
      }
    }
  ]
}