{
  "type": "FeatureCollection",
  "title": "Mithymna?",
  "id": "589935",
  "description": "An ancient place, cited: BAtlas 60 A1 Mithymna?",
  "bbox": [
    23.717462,
    35.502311,
    23.717462,
    35.502311
  ],
  "connectsWith": [
    "589748"
  ],
  "reprPoint": [
    23.717462,
    35.502311
  ],
  "names": [
    "Mithymna"
  ],
  "features": [
    {
      "geometry": {
        "type": "Point",
        "coordinates": [
          23.717462,
          35.502311
        ]
      },
      "id": "darmc-location-13760",
      "type": "Feature",
      "properties": {
        "description": "500K scale point location",
        "location_precision": "precise",
        "title": "DARMC location 13760",
        "link": "http://pleiades.stoa.org/places/589935/darmc-location-13760"
      }
    }
  ]
}