{
  "type": "FeatureCollection",
  "title": "Monopari",
  "id": "589939",
  "description": "An ancient place, cited: BAtlas 60 B2 Monopari",
  "bbox": [
    24.426379,
    35.295371,
    24.426379,
    35.295371
  ],
  "reprPoint": [
    24.426379,
    35.295371
  ],
  "features": [
    {
      "geometry": {
        "type": "Point",
        "coordinates": [
          24.426379,
          35.295371
        ]
      },
      "id": "darmc-location-13790",
      "type": "Feature",
      "properties": {
        "description": "500K scale point location",
        "location_precision": "precise",
        "title": "DARMC location 13790",
        "link": "http://pleiades.stoa.org/places/589939/darmc-location-13790"
      }
    }
  ]
}