{
  "type": "FeatureCollection",
  "title": "Vlithias",
  "id": "590091",
  "description": "An ancient place, cited: BAtlas 60 A2 Vlithias",
  "bbox": [
    23.695221,
    35.279016,
    23.695221,
    35.279016
  ],
  "reprPoint": [
    23.695221,
    35.279016
  ],
  "features": [
    {
      "geometry": {
        "type": "Point",
        "coordinates": [
          23.695221,
          35.279016
        ]
      },
      "id": "darmc-location-25405",
      "type": "Feature",
      "properties": {
        "description": "500K scale point location",
        "location_precision": "precise",
        "title": "DARMC location 25405",
        "link": "http://pleiades.stoa.org/places/590091/darmc-location-25405"
      }
    }
  ]
}