{
  "type": "FeatureCollection",
  "title": "Syros Ins.",
  "id": "590067",
  "description": "An ancient place, cited: BAtlas 60 A5 Syros Ins.",
  "bbox": [
    24.92,
    37.43,
    24.92,
    37.43
  ],
  "connectsWith": [
    "560353",
    "560221"
  ],
  "reprPoint": [
    24.92,
    37.43
  ],
  "names": [
    "Syros"
  ],
  "features": [
    {
      "geometry": {
        "type": "Point",
        "coordinates": [
          24.92,
          37.43
        ]
      },
      "id": "location-of-syros-ins",
      "type": "Feature",
      "properties": {
        "description": "Coordinates after BAtlas; verified in Google Earth 2013 with reference to Wikipedia.",
        "location_precision": "precise",
        "title": "location of Syros Ins.",
        "link": "http://pleiades.stoa.org/places/590067/location-of-syros-ins"
      }
    }
  ]
}