{
  "type": "FeatureCollection",
  "title": "Pyranthos",
  "id": "590022",
  "description": "An ancient place, cited: BAtlas 60 D2 Pyranthos",
  "bbox": [
    25.203857,
    35.079935,
    25.203857,
    35.079935
  ],
  "reprPoint": [
    25.203857,
    35.079935
  ],
  "names": [
    "Pyranthos"
  ],
  "features": [
    {
      "geometry": {
        "type": "Point",
        "coordinates": [
          25.203857,
          35.079935
        ]
      },
      "id": "darmc-location-10216",
      "type": "Feature",
      "properties": {
        "description": "500K scale point location",
        "location_precision": "precise",
        "title": "DARMC location 10216",
        "link": "http://pleiades.stoa.org/places/590022/darmc-location-10216"
      }
    }
  ]
}