{
  "type": "FeatureCollection",
  "title": "Tallaia? M.",
  "id": "590069",
  "description": "An ancient place, cited: BAtlas 60 C2 Tallaia? M.",
  "bbox": [
    24.82232,
    35.37358,
    24.82232,
    35.37358
  ],
  "reprPoint": [
    24.82232,
    35.37358
  ],
  "names": [
    "Tallaia M."
  ],
  "features": [
    {
      "geometry": {
        "type": "Point",
        "coordinates": [
          24.82232,
          35.37358
        ]
      },
      "id": "kouloukonas-oros",
      "type": "Feature",
      "properties": {
        "description": "Location based on GeoNames",
        "location_precision": "precise",
        "title": "location of Kouloúkonas Oŕos",
        "link": "http://pleiades.stoa.org/places/590069/kouloukonas-oros"
      }
    }
  ]
}