{
  "type": "FeatureCollection",
  "title": "Vasiliki",
  "id": "590086",
  "bbox": [
    25.8114283,
    35.0822488,
    25.8114283,
    35.0822488
  ],
  "description": "A settlement in east Crete in use from the Early Minoan period to the Late Minoan period and again in Roman times.",
  "connectsWith": [
    "589748",
    "589748"
  ],
  "features": [
    {
      "type": "Feature",
      "geometry": {
        "type": "Point",
        "coordinates": [
          25.8114283,
          35.0822488
        ]
      },
      "properties": {
        "description": "representative point"
      }
    },
    {
      "geometry": {
        "type": "Point",
        "coordinates": [
          25.8114283,
          35.0822488
        ]
      },
      "id": "osm-location-of-vasiliki",
      "type": "Feature",
      "properties": {
        "description": "Location based on OpenStreetMap",
        "location_precision": "precise",
        "title": "OSM location of Vasiliki",
        "link": "http://pleiades.stoa.org/places/590086/osm-location-of-vasiliki"
      }
    }
  ]
}