{
  "type": "FeatureCollection",
  "title": "Syrinthos?",
  "id": "590065",
  "bbox": [
    26.121005,
    35.011493,
    26.121005,
    35.011493
  ],
  "description": "An ancient place, cited: BAtlas 60 F2 Syrinthos?",
  "connectsWith": [
    "589748"
  ],
  "names": [
    "Syrinthos"
  ],
  "features": [
    {
      "type": "Feature",
      "geometry": {
        "type": "Point",
        "coordinates": [
          26.121005,
          35.011493
        ]
      },
      "properties": {
        "description": "representative point"
      }
    },
    {
      "geometry": {
        "type": "Point",
        "coordinates": [
          26.121005,
          35.011493
        ]
      },
      "id": "darmc-location-14956",
      "type": "Feature",
      "properties": {
        "description": "500K scale point location",
        "location_precision": "precise",
        "title": "DARMC location 14956",
        "link": "http://pleiades.stoa.org/places/590065/darmc-location-14956"
      }
    }
  ]
}