{
  "type": "FeatureCollection",
  "title": "*Stalai?",
  "id": "590059",
  "description": "An ancient place, cited: BAtlas 60 E2 *Stalai?",
  "bbox": [
    25.967625,
    35.0380523,
    25.972065,
    35.042681
  ],
  "connectsWith": [
    "589748"
  ],
  "reprPoint": [
    25.969845,
    35.04036665
  ],
  "names": [
    "Stalai"
  ],
  "features": [
    {
      "geometry": {
        "type": "Point",
        "coordinates": [
          25.972065,
          35.042681
        ]
      },
      "id": "darmc-location-14880",
      "type": "Feature",
      "properties": {
        "description": "500K scale point location",
        "location_precision": "precise",
        "title": "DARMC location 14880",
        "link": "http://pleiades.stoa.org/places/590059/darmc-location-14880"
      }
    },
    {
      "geometry": {
        "type": "Point",
        "coordinates": [
          25.967625,
          35.0380523
        ]
      },
      "id": "location-of-minoan-villa-of-makrygialos",
      "type": "Feature",
      "properties": {
        "description": "Location based on OpenStreetMap",
        "location_precision": "precise",
        "title": "location of Minoan Villa of Makrygialos",
        "link": "http://pleiades.stoa.org/places/590059/location-of-minoan-villa-of-makrygialos"
      }
    }
  ]
}