{
  "type": "FeatureCollection",
  "title": "*Stalai?",
  "id": "590059",
  "bbox": [
    25.967625,
    35.0380523,
    25.967625,
    35.0380523
  ],
  "description": "An ancient place, cited: BAtlas 60 E2 *Stalai?",
  "connectsWith": [
    "589748"
  ],
  "names": [
    "Stalai"
  ],
  "features": [
    {
      "type": "Feature",
      "geometry": {
        "type": "Point",
        "coordinates": [
          25.967625,
          35.0380523
        ]
      },
      "properties": {
        "description": "representative point"
      }
    },
    {
      "geometry": {
        "type": "Point",
        "coordinates": [
          25.967625,
          35.0380523
        ]
      },
      "id": "location-of-minoan-villa-of-makrygialos",
      "type": "Feature",
      "properties": {
        "description": "Representative location based on OpenStreetMap.",
        "location_precision": "precise",
        "title": "OSM location of Minoan Villa of Makrygialos",
        "link": "http://pleiades.stoa.org/places/590059/location-of-minoan-villa-of-makrygialos"
      }
    }
  ]
}