{
  "type": "FeatureCollection",
  "title": "Vasiliki",
  "id": "590086",
  "description": "A settlement in east Crete in use from the Early Minoan period to the Late Minoan period.",
  "bbox": [
    25.808782,
    35.0822488,
    25.8114283,
    35.093087
  ],
  "connectsWith": [
    "589748"
  ],
  "reprPoint": [
    25.81010515,
    35.0876679
  ],
  "features": [
    {
      "geometry": {
        "type": "Point",
        "coordinates": [
          25.808782,
          35.093087
        ]
      },
      "id": "darmc-location-6406",
      "type": "Feature",
      "properties": {
        "description": "500K scale point location",
        "location_precision": "precise",
        "title": "DARMC location 6406",
        "link": "http://pleiades.stoa.org/places/590086/darmc-location-6406"
      }
    },
    {
      "geometry": {
        "type": "Point",
        "coordinates": [
          25.8114283,
          35.0822488
        ]
      },
      "id": "location-of-vasiliki",
      "type": "Feature",
      "properties": {
        "description": "Location based on OpenStreetMap",
        "location_precision": "precise",
        "title": "location of Vasiliki",
        "link": "http://pleiades.stoa.org/places/590086/location-of-vasiliki"
      }
    }
  ]
}