{
  "type": "FeatureCollection",
  "title": "Thoanteion Pr.",
  "id": "590078",
  "bbox": [
    27.13536,
    35.3974,
    27.13536,
    35.3974
  ],
  "description": "Thoanteion Pr., a promontory of Karpathos mentioned by Ptolemy.",
  "connectsWith": [
    "589841"
  ],
  "names": [
    "Thoanteion Pr."
  ],
  "features": [
    {
      "type": "Feature",
      "geometry": {
        "type": "Point",
        "coordinates": [
          27.13536,
          35.3974
        ]
      },
      "properties": {
        "description": "representative point"
      }
    },
    {
      "geometry": {
        "type": "Point",
        "coordinates": [
          27.13536,
          35.3974
        ]
      },
      "id": "geonames-location-of-akra-kastello",
      "type": "Feature",
      "properties": {
        "description": "Coordinates following GeoNames",
        "location_precision": "precise",
        "title": "GeoNames location of Ákra Kástello",
        "link": "http://pleiades.stoa.org/places/590078/geonames-location-of-akra-kastello"
      }
    }
  ]
}