{
  "type": "FeatureCollection",
  "title": "Zeus Thenatas, T.",
  "id": "590101",
  "bbox": [
    25.2053213,
    35.3320287,
    25.2053213,
    35.3320287
  ],
  "description": "Zeus Thenatas, T. is an archaic Greek sanctuary built atop earlier Minoan cult remains. The open-air temple remained in use until the second century AD.",
  "connectsWith": [
    "589748"
  ],
  "names": [
    "Zeus Thenatas, T."
  ],
  "features": [
    {
      "type": "Feature",
      "geometry": {
        "type": "Point",
        "coordinates": [
          25.2053213,
          35.3320287
        ]
      },
      "properties": {
        "description": "representative point"
      }
    },
    {
      "geometry": {
        "type": "Point",
        "coordinates": [
          25.2053213,
          35.3320287
        ]
      },
      "id": "location-of-Zeus-Thenatas-T",
      "type": "Feature",
      "properties": {
        "description": "Location based on OpenStreetMap",
        "location_precision": "precise",
        "title": "OSM location of Zeus Thenatas, T.",
        "link": "http://pleiades.stoa.org/places/590101/location-of-Zeus-Thenatas-T"
      }
    }
  ]
}