{
  "type": "FeatureCollection",
  "title": "Untitled",
  "id": "593433",
  "bbox": [
    24.666667,
    36.983333,
    24.666667,
    36.983333
  ],
  "description": "An ancient place, cited: BAtlas 60 C4 unnamed quarry group (on Siphnos)",
  "features": [
    {
      "type": "Feature",
      "geometry": {
        "type": "Point",
        "coordinates": [
          24.666667,
          36.983333
        ]
      },
      "properties": {
        "description": "representative point"
      }
    },
    {
      "geometry": {
        "type": "Point",
        "coordinates": [
          24.666667,
          36.983333
        ]
      },
      "id": "batlas-location",
      "type": "Feature",
      "properties": {
        "description": null,
        "location_precision": "precise",
        "title": "Barrington Atlas location",
        "link": "http://pleiades.stoa.org/places/593433/batlas-location"
      }
    }
  ]
}