{
  "type": "FeatureCollection",
  "title": "West House at Vasiliki",
  "id": "593460161",
  "bbox": [
    25.81099,
    35.081929,
    25.81099,
    35.081929
  ],
  "description": "The West House is an architectural complex built as an annex to a large building, the Red House, in an Early Minoan settlement at Vasiliki on Crete. ",
  "connectsWith": [
    "590086"
  ],
  "names": [
    "West House"
  ],
  "features": [
    {
      "type": "Feature",
      "geometry": {
        "type": "Point",
        "coordinates": [
          25.81099,
          35.081929
        ]
      },
      "properties": {
        "description": "representative point"
      }
    },
    {
      "geometry": {
        "type": "Point",
        "coordinates": [
          25.81099,
          35.081929
        ]
      },
      "id": "imagery-location-for-west-house",
      "type": "Feature",
      "properties": {
        "description": "Location of the center of the northwest room of the West House at the Vasiliki archaeological site, determined by matching Google satellite imagery with published plans.",
        "location_precision": "precise",
        "title": "Imagery location for West House",
        "link": "http://pleiades.stoa.org/places/593460161/imagery-location-for-west-house"
      }
    }
  ]
}