{
  "type": "FeatureCollection",
  "title": "S'Arcu 'e is Forros",
  "id": "594406649",
  "bbox": [
    9.3999989,
    40.0033844,
    9.3999989,
    40.0033844
  ],
  "description": "A significant nuragic complex with major occupational phases during the middle Bronze Age and during the Bronze- to Iron Age transition. A 17 meter long megaron with its temenos is a main feature of the site.",
  "connectsWith": [
    "472014"
  ],
  "features": [
    {
      "type": "Feature",
      "geometry": {
        "type": "Point",
        "coordinates": [
          9.3999989,
          40.0033844
        ]
      },
      "properties": {
        "description": "representative point"
      }
    },
    {
      "geometry": {
        "type": "Point",
        "coordinates": [
          9.3999989,
          40.0033844
        ]
      },
      "id": "osm-location",
      "type": "Feature",
      "properties": {
        "description": "Location based on OpenStreetMap",
        "location_precision": "precise",
        "title": "OSM location of Area archeologica di S'Arcu 'e is Forros",
        "link": "http://pleiades.stoa.org/places/594406649/osm-location"
      }
    }
  ]
}