{
  "type": "FeatureCollection",
  "title": "Oiai",
  "id": "594989",
  "bbox": [
    27.683572,
    35.876662,
    28.2476283,
    36.4582829
  ],
  "description": "An ancient place, cited: BAtlas 60 unlocated Oiai",
  "connectsWith": [
    "590031"
  ],
  "names": [
    "Oiai"
  ],
  "features": [
    {
      "type": "Feature",
      "geometry": {
        "type": "Point",
        "coordinates": [
          27.9486959898,
          36.1710583343
        ]
      },
      "properties": {
        "description": "representative point"
      }
    }
  ]
}