{
  "type": "FeatureCollection",
  "title": "Lower Warbank Roman Villa",
  "id": "594953359",
  "description": "A Romano-British villa near Keston, built over an earlier Iron Age site. Findspot of RIB 3025.",
  "bbox": [
    0.027901,
    51.350988,
    0.027901,
    51.350988
  ],
  "reprPoint": [
    0.027901,
    51.350988
  ],
  "features": [
    {
      "geometry": {
        "type": "Point",
        "coordinates": [
          0.027901,
          51.350988
        ]
      },
      "id": "representative-point-derived-from-pastscape",
      "type": "Feature",
      "properties": {
        "description": "Coordinates derived from Pastscape record and converted to WGS84 latitude, longitude values from the Ordnance Survey grid reference (TQ 4131 6327), resolved to its center point.",
        "location_precision": "precise",
        "title": "Representative point derived from Pastscape",
        "link": "http://pleiades.stoa.org/places/594953359/representative-point-derived-from-pastscape"
      }
    }
  ]
}