{
  "type": "FeatureCollection",
  "title": "Aornos",
  "id": "59687",
  "description": "Aornos was a mountain fortress and the site of Alexander the Great's last siege during the winter of 327-6 BC. The ancient site likely corresponds to Ūṇa, a peak on the Pīr-Sar west of the Indus river.",
  "bbox": [
    72.803461,
    34.75257,
    72.803461,
    34.75257
  ],
  "reprPoint": [
    72.803461,
    34.75257
  ],
  "names": [
    "Aornos",
    "Aornis"
  ],
  "features": [
    {
      "geometry": {
        "type": "Point",
        "coordinates": [
          72.803461,
          34.75257
        ]
      },
      "id": "darmc-location-19929",
      "type": "Feature",
      "properties": {
        "description": "5M scale point location",
        "location_precision": "precise",
        "title": "DARMC location 19929",
        "link": "http://pleiades.stoa.org/places/59687/darmc-location-19929"
      }
    }
  ]
}