{
  "type": "FeatureCollection",
  "title": "Barygaza",
  "id": "59737",
  "bbox": [
    72.983068,
    21.70078,
    72.983068,
    21.70078
  ],
  "description": "An ancient place, cited: BAtlas 6 C5 Barygaza",
  "names": [
    "Barygaza",
    "Bargose"
  ],
  "features": [
    {
      "type": "Feature",
      "geometry": {
        "type": "Point",
        "coordinates": [
          72.983068,
          21.70078
        ]
      },
      "properties": {
        "description": "representative point"
      }
    },
    {
      "geometry": {
        "type": "Point",
        "coordinates": [
          72.983068,
          21.70078
        ]
      },
      "id": "darmc-location-20032",
      "type": "Feature",
      "properties": {
        "description": "5M scale representative point location digitized from the Barrington Atlas of the Greek and Roman World by the Digital Atlas of Roman and Medieval Civilizations project at Harvard University.",
        "location_precision": "precise",
        "title": "DARMC location 20032",
        "link": "http://pleiades.stoa.org/places/59737/darmc-location-20032"
      }
    }
  ]
}