{
  "type": "FeatureCollection",
  "title": "Capisa",
  "id": "59759",
  "description": "An ancient place, cited: BAtlas 6 B2 Capisa",
  "bbox": [
    69.755491,
    34.951323,
    69.755491,
    34.951323
  ],
  "reprPoint": [
    69.755491,
    34.951323
  ],
  "names": [
    "Capisa",
    "Caphisa"
  ],
  "features": [
    {
      "geometry": {
        "type": "Point",
        "coordinates": [
          69.755491,
          34.951323
        ]
      },
      "id": "darmc-location-20108",
      "type": "Feature",
      "properties": {
        "description": "5M scale point location",
        "location_precision": "precise",
        "title": "DARMC location 20108",
        "link": "http://pleiades.stoa.org/places/59759/darmc-location-20108"
      }
    }
  ]
}