{
  "type": "FeatureCollection",
  "title": "Chrisobora/Kleisobora",
  "id": "59775",
  "description": "An ancient place, cited: BAtlas 6 D4 Chrisobora/Kleisobora",
  "bbox": [
    77.649033,
    28.030792,
    77.649033,
    28.030792
  ],
  "reprPoint": [
    77.649033,
    28.030792
  ],
  "names": [
    "Chrisobora",
    "Kleisobora"
  ],
  "features": [
    {
      "geometry": {
        "type": "Point",
        "coordinates": [
          77.649033,
          28.030792
        ]
      },
      "id": "darmc-location-10012",
      "type": "Feature",
      "properties": {
        "description": "5M scale point location",
        "location_precision": "precise",
        "title": "DARMC location 10012",
        "link": "http://pleiades.stoa.org/places/59775/darmc-location-10012"
      }
    }
  ]
}