{
  "type": "FeatureCollection",
  "title": "Cyropolis/Kyra",
  "id": "59781",
  "description": "Cyropolis/Kyra was an ancient settlement in what is now northern Tajikistan. Tradition holds that Cyrus the Great established the site in 544 BC to mark the boundary of the Persian empire.",
  "bbox": [
    69.004272,
    39.90761,
    69.004272,
    39.90761
  ],
  "reprPoint": [
    69.004272,
    39.90761
  ],
  "names": [
    "Cyropolis",
    "Kyra",
    "Cyreschata"
  ],
  "features": [
    {
      "geometry": {
        "type": "Point",
        "coordinates": [
          69.004272,
          39.90761
        ]
      },
      "id": "darmc-location-19765",
      "type": "Feature",
      "properties": {
        "description": "5M scale point location",
        "location_precision": "precise",
        "title": "DARMC location 19765",
        "link": "http://pleiades.stoa.org/places/59781/darmc-location-19765"
      }
    }
  ]
}