{
  "type": "FeatureCollection",
  "title": "Embolima",
  "id": "59803",
  "bbox": [
    72.79376,
    34.648977,
    72.79376,
    34.648977
  ],
  "description": "An ancient place, cited: BAtlas 6 C3 Embolima",
  "names": [
    "Embolima",
    "Ecbolima"
  ],
  "features": [
    {
      "type": "Feature",
      "geometry": {
        "type": "Point",
        "coordinates": [
          72.79376,
          34.648977
        ]
      },
      "properties": {
        "description": "representative point"
      }
    },
    {
      "geometry": {
        "type": "Point",
        "coordinates": [
          72.79376,
          34.648977
        ]
      },
      "id": "darmc-location-19774",
      "type": "Feature",
      "properties": {
        "description": "5M scale point location",
        "location_precision": "precise",
        "title": "DARMC location 19774",
        "link": "http://pleiades.stoa.org/places/59803/darmc-location-19774"
      }
    }
  ]
}