{
  "type": "FeatureCollection",
  "title": "Eragassa",
  "id": "59807",
  "description": "An ancient place, cited: BAtlas 6 D4 Eragassa",
  "bbox": [
    78.502924,
    25.692849,
    78.502924,
    25.692849
  ],
  "reprPoint": [
    78.502924,
    25.692849
  ],
  "names": [
    "Eragassa"
  ],
  "features": [
    {
      "geometry": {
        "type": "Point",
        "coordinates": [
          78.502924,
          25.692849
        ]
      },
      "id": "darmc-location-12363",
      "type": "Feature",
      "properties": {
        "description": "5M scale point location",
        "location_precision": "precise",
        "title": "DARMC location 12363",
        "link": "http://pleiades.stoa.org/places/59807/darmc-location-12363"
      }
    }
  ]
}