{
  "type": "FeatureCollection",
  "title": "Ganges fl.",
  "id": "59822",
  "description": "The Ganges flows some 2,525 km (1,569 mi) from its sources in the western Himalayas to the Bay of Bengal.",
  "bbox": [
    78.916667,
    22.083333,
    90.833333,
    30.983333
  ],
  "reprPoint": [
    86.5115563333,
    25.621435
  ],
  "names": [
    "Ganges",
    "Padus",
    "Phison",
    "Alibotra"
  ],
  "features": [
    {
      "geometry": {
        "type": "Point",
        "coordinates": [
          78.916667,
          30.983333
        ]
      },
      "id": "location-of-source-of-ganges-fl",
      "type": "Feature",
      "properties": {
        "description": "verified in Google Earth 2013.",
        "location_precision": "precise",
        "title": "location of source of Ganges fl.",
        "link": "http://pleiades.stoa.org/places/59822/location-of-source-of-ganges-fl"
      }
    },
    {
      "geometry": {
        "type": "Point",
        "coordinates": [
          89.784669,
          23.797639
        ]
      },
      "id": "location-of-course-of-Ganges-fl",
      "type": "Feature",
      "properties": {
        "description": "Location based on OpenStreetMap",
        "location_precision": "precise",
        "title": "location of course of Ganges fl.",
        "link": "http://pleiades.stoa.org/places/59822/location-of-course-of-Ganges-fl"
      }
    },
    {
      "geometry": {
        "type": "Point",
        "coordinates": [
          90.833333,
          22.083333
        ]
      },
      "id": "location-of-mouth-of-ganges-fl",
      "type": "Feature",
      "properties": {
        "description": "verified in Google Earth 2013.",
        "location_precision": "precise",
        "title": "location of mouth of Ganges fl.",
        "link": "http://pleiades.stoa.org/places/59822/location-of-mouth-of-ganges-fl"
      }
    }
  ]
}