{
  "type": "FeatureCollection",
  "title": "Platyskinos (settlement)",
  "id": "598359947",
  "bbox": [
    26.073008,
    35.159856,
    26.073008,
    35.159856
  ],
  "description": "Settlement on Crete from the Late Minoan period near Achladia.",
  "connectsWith": [
    "598926917"
  ],
  "features": [
    {
      "type": "Feature",
      "geometry": {
        "type": "Point",
        "coordinates": [
          26.073008,
          35.159856
        ]
      },
      "properties": {
        "description": "representative point"
      }
    },
    {
      "geometry": {
        "type": "Point",
        "coordinates": [
          26.073008,
          35.159856
        ]
      },
      "id": "approximate-imagery-location-of-platyskinos",
      "type": "Feature",
      "properties": {
        "description": "Approximate imagery location based on Google Earth representing Platyskinos after Tsipopoulou 1995.",
        "location_precision": "precise",
        "title": "Approximate imagery location of Platyskinos",
        "link": "http://pleiades.stoa.org/places/598359947/approximate-imagery-location-of-platyskinos"
      }
    }
  ]
}