{
  "type": "FeatureCollection",
  "title": "Kakouthis",
  "id": "59856",
  "description": "An ancient place, cited: BAtlas 6 F4 Kakouthis",
  "bbox": [
    85.052746,
    25.227741,
    85.052746,
    25.227741
  ],
  "reprPoint": [
    85.052746,
    25.227741
  ],
  "names": [
    "Kakouthis"
  ],
  "features": [
    {
      "geometry": {
        "type": "Point",
        "coordinates": [
          85.052746,
          25.227741
        ]
      },
      "id": "darmc-location-19789",
      "type": "Feature",
      "properties": {
        "description": "5M scale point location",
        "location_precision": "precise",
        "title": "DARMC location 19789",
        "link": "http://pleiades.stoa.org/places/59856/darmc-location-19789"
      }
    }
  ]
}