{
  "type": "FeatureCollection",
  "title": "Kamigara",
  "id": "59861",
  "description": "An ancient place, cited: BAtlas 6 B4 Kamigara",
  "bbox": [
    68.849077,
    27.689213,
    68.849077,
    27.689213
  ],
  "reprPoint": [
    68.849077,
    27.689213
  ],
  "names": [
    "Kamigara",
    "Camagora"
  ],
  "features": [
    {
      "geometry": {
        "type": "Point",
        "coordinates": [
          68.849077,
          27.689213
        ]
      },
      "id": "darmc-location-20366",
      "type": "Feature",
      "properties": {
        "description": "5M scale point location",
        "location_precision": "precise",
        "title": "DARMC location 20366",
        "link": "http://pleiades.stoa.org/places/59861/darmc-location-20366"
      }
    }
  ]
}