{
  "type": "FeatureCollection",
  "title": "Katadoupe",
  "id": "59870",
  "description": "An ancient place, cited: BAtlas 6 F5 Katadoupe",
  "bbox": [
    88.132158,
    23.63355,
    88.132158,
    23.63355
  ],
  "reprPoint": [
    88.132158,
    23.63355
  ],
  "names": [
    "Katadoupe"
  ],
  "features": [
    {
      "geometry": {
        "type": "Point",
        "coordinates": [
          88.132158,
          23.63355
        ]
      },
      "id": "darmc-location-19794",
      "type": "Feature",
      "properties": {
        "description": "5M scale point location",
        "location_precision": "precise",
        "title": "DARMC location 19794",
        "link": "http://pleiades.stoa.org/places/59870/darmc-location-19794"
      }
    }
  ]
}