{
  "type": "FeatureCollection",
  "title": "Kabul",
  "id": "59885",
  "bbox": [
    69.1624302,
    34.5197058,
    69.18024,
    34.521818
  ],
  "description": "Pre-modern settlement at and around the area of modern Kabul, Afghanistan has been known by various names in a variety of languages and periods. Excavations begun in the early twenty-first century have significantly extended scholarly understanding established in the early-to-mid 20th century.",
  "connectsWith": [
    "59886"
  ],
  "names": [
    "Kophen",
    "Kōphēn",
    "Ortospana",
    "Kāvul",
    "Čaman Hezārī",
    "Caman-Hazuri",
    "Kaboura",
    "Ortaspana",
    "Kābol",
    "Kābūl",
    "Kabul",
    "Kābul",
    "Kābul",
    "Chaman-i Ḥaz̤ūrī"
  ],
  "features": [
    {
      "type": "Feature",
      "geometry": {
        "type": "Point",
        "coordinates": [
          69.1713351,
          34.5207619
        ]
      },
      "properties": {
        "description": "representative point"
      }
    },
    {
      "geometry": {
        "type": "Point",
        "coordinates": [
          69.18024,
          34.521818
        ]
      },
      "id": "darmc-location-20392",
      "type": "Feature",
      "properties": {
        "description": "5M scale point location",
        "location_precision": "precise",
        "title": "DARMC location 20392",
        "link": "http://pleiades.stoa.org/places/59885/darmc-location-20392"
      }
    },
    {
      "geometry": {
        "type": "Point",
        "coordinates": [
          69.1624302,
          34.5197058
        ]
      },
      "id": "location-of-kabul",
      "type": "Feature",
      "properties": {
        "description": "Location based on OpenStreetMap",
        "location_precision": "precise",
        "title": "OSM location of modern Kabul",
        "link": "http://pleiades.stoa.org/places/59885/location-of-kabul"
      }
    }
  ]
}