{
  "type": "FeatureCollection",
  "title": "Kophen",
  "id": "59885",
  "description": "An ancient place, cited: BAtlas 6 B3 Kophen",
  "bbox": [
    69.1624302,
    34.5197058,
    69.18024,
    34.521818
  ],
  "connectsWith": [
    "59886"
  ],
  "reprPoint": [
    69.1713351,
    34.5207619
  ],
  "names": [
    "Kophen",
    "Kōphēn",
    "Ortospana",
    "Kāvul",
    "Čaman Hezārī",
    "Caman-Hazuri",
    "Kaboura",
    "Ortaspana",
    "Kabul",
    "Kābul",
    "Kābul",
    "Kābol",
    "Kābūl"
  ],
  "features": [
    {
      "geometry": {
        "type": "Point",
        "coordinates": [
          69.18024,
          34.521818
        ]
      },
      "id": "darmc-location-20392",
      "type": "Feature",
      "properties": {
        "description": "5M scale point location",
        "location_precision": "precise",
        "title": "DARMC location 20392",
        "link": "http://pleiades.stoa.org/places/59885/darmc-location-20392"
      }
    }
  ]
}