{
  "type": "FeatureCollection",
  "title": "Naagramma",
  "id": "59940",
  "description": "An ancient place, cited: BAtlas 6 B4 Naagramma",
  "bbox": [
    68.073615,
    26.823941,
    68.073615,
    26.823941
  ],
  "reprPoint": [
    68.073615,
    26.823941
  ],
  "names": [
    "Naagramma"
  ],
  "features": [
    {
      "geometry": {
        "type": "Point",
        "coordinates": [
          68.073615,
          26.823941
        ]
      },
      "id": "darmc-location-10152",
      "type": "Feature",
      "properties": {
        "description": "5M scale point location",
        "location_precision": "precise",
        "title": "DARMC location 10152",
        "link": "http://pleiades.stoa.org/places/59940/darmc-location-10152"
      }
    }
  ]
}