{
  "type": "FeatureCollection",
  "title": "Nautaka",
  "id": "59945",
  "description": "An ancient place, cited: BAtlas 6 B2 Nautaka",
  "bbox": [
    66.82551,
    39.046026,
    66.82551,
    39.046026
  ],
  "reprPoint": [
    66.82551,
    39.046026
  ],
  "names": [
    "Nautaka"
  ],
  "features": [
    {
      "geometry": {
        "type": "Point",
        "coordinates": [
          66.82551,
          39.046026
        ]
      },
      "id": "darmc-location-19827",
      "type": "Feature",
      "properties": {
        "description": "5M scale point location",
        "location_precision": "precise",
        "title": "DARMC location 19827",
        "link": "http://pleiades.stoa.org/places/59945/darmc-location-19827"
      }
    }
  ]
}