{
  "type": "FeatureCollection",
  "title": "Amos",
  "id": "599485",
  "bbox": [
    28.262312,
    36.753438,
    28.266869,
    36.756133
  ],
  "description": "An ancient place, cited: BAtlas 61 G4 Amos",
  "names": [
    "Amos"
  ],
  "features": [
    {
      "type": "Feature",
      "geometry": {
        "type": "Point",
        "coordinates": [
          28.2645905,
          36.7547855
        ]
      },
      "properties": {
        "description": "representative point"
      }
    },
    {
      "geometry": {
        "type": "Point",
        "coordinates": [
          28.262312,
          36.753438
        ]
      },
      "id": "darmc-location-11355",
      "type": "Feature",
      "properties": {
        "description": "1:500,000 scale representative point location digitized from the Barrington Atlas of the Greek and Roman World by the Digital Atlas of Roman and Medieval Civilizations project at Harvard University.",
        "location_precision": "precise",
        "title": "DARMC location 11355",
        "link": "http://pleiades.stoa.org/places/599485/darmc-location-11355"
      }
    },
    {
      "geometry": {
        "type": "Point",
        "coordinates": [
          28.266869,
          36.756133
        ]
      },
      "id": "dare-location",
      "type": "Feature",
      "properties": {
        "description": "Representative point location, site precision",
        "location_precision": "precise",
        "title": "DARE Location",
        "link": "http://pleiades.stoa.org/places/599485/dare-location"
      }
    }
  ]
}