{
  "type": "FeatureCollection",
  "title": "Akrite Ins.",
  "id": "599477",
  "description": "Akrite Ins. (modern Arkoi) is an island of the Dodecanese archipelago.",
  "bbox": [
    26.7185965,
    37.4125411,
    26.7185965,
    37.4125411
  ],
  "reprPoint": [
    26.7185965,
    37.4125411
  ],
  "names": [
    "Akrite"
  ],
  "features": [
    {
      "geometry": {
        "type": "Point",
        "coordinates": [
          26.7185965,
          37.4125411
        ]
      },
      "id": "osm-way-4887778",
      "type": "Feature",
      "properties": {
        "description": "Location based on OpenStreetMap",
        "location_precision": "precise",
        "title": "location of Arkoi",
        "link": "http://pleiades.stoa.org/places/599477/osm-way-4887778"
      }
    }
  ]
}