{
  "type": "FeatureCollection",
  "title": "Colophon",
  "id": "599577",
  "description": "An ancient place, cited: BAtlas 61 E1 Colophon",
  "bbox": [
    27.142647,
    37.997757,
    27.204204,
    38.119933
  ],
  "connectsWith": [
    "735295266"
  ],
  "reprPoint": [
    27.157223,
    38.0908258
  ],
  "names": [
    "Colophon"
  ],
  "features": [
    {
      "geometry": {
        "type": "Point",
        "coordinates": [
          27.14711,
          38.109632
        ]
      },
      "id": "darmc-location-3188",
      "type": "Feature",
      "properties": {
        "description": "500K scale point location",
        "location_precision": "precise",
        "title": "DARMC location 3188",
        "link": "http://pleiades.stoa.org/places/599577/darmc-location-3188"
      }
    },
    {
      "geometry": {
        "type": "Point",
        "coordinates": [
          27.149507,
          38.106874
        ]
      },
      "id": "darmc-location-3189",
      "type": "Feature",
      "properties": {
        "description": "500K scale point location",
        "location_precision": "precise",
        "title": "DARMC location 3189",
        "link": "http://pleiades.stoa.org/places/599577/darmc-location-3189"
      }
    },
    {
      "geometry": {
        "type": "Point",
        "coordinates": [
          27.204204,
          37.997757
        ]
      },
      "id": "darmc-location-3190",
      "type": "Feature",
      "properties": {
        "description": "500K scale point location",
        "location_precision": "precise",
        "title": "DARMC location 3190",
        "link": "http://pleiades.stoa.org/places/599577/darmc-location-3190"
      }
    },
    {
      "geometry": {
        "type": "Point",
        "coordinates": [
          27.142647,
          38.119933
        ]
      },
      "id": "darmc-location-24030",
      "type": "Feature",
      "properties": {
        "description": "1M scale point location",
        "location_precision": "precise",
        "title": "DARMC location 24030",
        "link": "http://pleiades.stoa.org/places/599577/darmc-location-24030"
      }
    },
    {
      "geometry": {
        "type": "Point",
        "coordinates": [
          27.142647,
          38.119933
        ]
      },
      "id": "darmc-location-24031",
      "type": "Feature",
      "properties": {
        "description": "1M scale point location",
        "location_precision": "precise",
        "title": "DARMC location 24031",
        "link": "http://pleiades.stoa.org/places/599577/darmc-location-24031"
      }
    }
  ]
}