{
  "type": "FeatureCollection",
  "title": "Armenokhori",
  "id": "599520",
  "description": "An ancient place, cited: BAtlas 61 C4 Armenokhori",
  "bbox": [
    26.306906,
    36.534254,
    26.306906,
    36.534254
  ],
  "reprPoint": [
    26.306906,
    36.534254
  ],
  "features": [
    {
      "geometry": {
        "type": "Point",
        "coordinates": [
          26.306906,
          36.534254
        ]
      },
      "id": "darmc-location-11504",
      "type": "Feature",
      "properties": {
        "description": "500K scale point location",
        "location_precision": "precise",
        "title": "DARMC location 11504",
        "link": "http://pleiades.stoa.org/places/599520/darmc-location-11504"
      }
    }
  ]
}