{
  "type": "FeatureCollection",
  "title": "Colophon",
  "id": "599577",
  "bbox": [
    27.14711,
    38.106874,
    27.149507,
    38.109632
  ],
  "description": "Colophon was an Ionian city in Lydia, located ca. 13 km north of the harbour of Notion. Its ruins are located near modern Değirmendere.",
  "connectsWith": [
    "735295266",
    "177302800"
  ],
  "names": [
    "Colophon"
  ],
  "features": [
    {
      "type": "Feature",
      "geometry": {
        "type": "Point",
        "coordinates": [
          27.1483085,
          38.108253
        ]
      },
      "properties": {
        "description": "representative point"
      }
    },
    {
      "geometry": {
        "type": "Point",
        "coordinates": [
          27.14711,
          38.109632
        ]
      },
      "id": "darmc-location-3188",
      "type": "Feature",
      "properties": {
        "description": "500K scale point location",
        "location_precision": "precise",
        "title": "DARMC location 3188",
        "link": "http://pleiades.stoa.org/places/599577/darmc-location-3188"
      }
    },
    {
      "geometry": {
        "type": "Point",
        "coordinates": [
          27.149507,
          38.106874
        ]
      },
      "id": "darmc-location-3189",
      "type": "Feature",
      "properties": {
        "description": "500K scale point location",
        "location_precision": "precise",
        "title": "DARMC location 3189",
        "link": "http://pleiades.stoa.org/places/599577/darmc-location-3189"
      }
    }
  ]
}