{
  "type": "FeatureCollection",
  "title": "Apollo Asgelatos, T.",
  "id": "599504",
  "description": "An ancient place, cited: BAtlas 61 B5 Apollo Asgelatos, T.",
  "bbox": [
    25.823783,
    36.361333,
    25.823783,
    36.361333
  ],
  "connectsWith": [
    "599492"
  ],
  "reprPoint": [
    25.823783,
    36.361333
  ],
  "names": [
    "Apollo Asgelatos, T."
  ],
  "features": [
    {
      "geometry": {
        "type": "Point",
        "coordinates": [
          25.823783,
          36.361333
        ]
      },
      "id": "darmc-location-15868",
      "type": "Feature",
      "properties": {
        "description": "500K scale point location",
        "location_precision": "precise",
        "title": "DARMC location 15868",
        "link": "http://pleiades.stoa.org/places/599504/darmc-location-15868"
      }
    }
  ]
}