{
  "type": "FeatureCollection",
  "title": "Bargylia",
  "id": "599550",
  "bbox": [
    27.5891436,
    37.1943528,
    27.589505,
    37.195835
  ],
  "description": "An ancient city of Caria, now known in Turkish as Varvıl. The site is located near the modern Turkish village of Boğaziçi in Muğla province.",
  "connectsWith": [
    "599564"
  ],
  "names": [
    "Bargylia",
    "Varvıl"
  ],
  "features": [
    {
      "type": "Feature",
      "geometry": {
        "type": "Point",
        "coordinates": [
          27.5893243,
          37.1950939
        ]
      },
      "properties": {
        "description": "representative point"
      }
    },
    {
      "geometry": {
        "type": "Point",
        "coordinates": [
          27.589505,
          37.195835
        ]
      },
      "id": "dare-location",
      "type": "Feature",
      "properties": {
        "description": "Representative point location, site precision",
        "location_precision": "precise",
        "title": "DARE Location",
        "link": "http://pleiades.stoa.org/places/599550/dare-location"
      }
    },
    {
      "geometry": {
        "type": "Point",
        "coordinates": [
          27.5891436,
          37.1943528
        ]
      },
      "id": "osm-location-of-bargylia-barbylia",
      "type": "Feature",
      "properties": {
        "description": "Representative location based on OpenStreetMap",
        "location_precision": "precise",
        "title": "OSM location of Bargylia/Barbylia",
        "link": "http://pleiades.stoa.org/places/599550/osm-location-of-bargylia-barbylia"
      }
    }
  ]
}