{
  "type": "FeatureCollection",
  "title": "Arethousa",
  "id": "599513",
  "description": "An ancient place, cited: BAtlas 61 C2 Arethousa",
  "bbox": [
    26.213485,
    37.611568,
    26.213485,
    37.611568
  ],
  "reprPoint": [
    26.213485,
    37.611568
  ],
  "features": [
    {
      "geometry": {
        "type": "Point",
        "coordinates": [
          26.213485,
          37.611568
        ]
      },
      "id": "darmc-location-23465",
      "type": "Feature",
      "properties": {
        "description": "Point location",
        "location_precision": "precise",
        "title": "DARMC location 23465",
        "link": "http://pleiades.stoa.org/places/599513/darmc-location-23465"
      }
    },
    {
      "geometry": {
        "type": "Point",
        "coordinates": [
          26.213485,
          37.611568
        ]
      },
      "id": "darmc-location-23475",
      "type": "Feature",
      "properties": {
        "description": "Point location",
        "location_precision": "precise",
        "title": "DARMC location 23475",
        "link": "http://pleiades.stoa.org/places/599513/darmc-location-23475"
      }
    }
  ]
}