{
  "type": "FeatureCollection",
  "title": "Artemis Tauropolos, T.",
  "id": "599524",
  "description": "An ancient place, cited: BAtlas 61 C2 Artemis Tauropolos, T.",
  "bbox": [
    26.0596359,
    37.6219278,
    26.0596359,
    37.6219278
  ],
  "connectsWith": [
    "599667"
  ],
  "reprPoint": [
    26.0596359,
    37.6219278
  ],
  "names": [
    "Artemis Tauropolos, T."
  ],
  "features": [
    {
      "geometry": {
        "type": "Point",
        "coordinates": [
          26.0596359,
          37.6219278
        ]
      },
      "id": "osm-location",
      "type": "Feature",
      "properties": {
        "description": "Representative location based on OpenStreetMap.",
        "location_precision": "precise",
        "title": "OSM location of Temple Of Artemis",
        "link": "http://pleiades.stoa.org/places/599524/osm-location"
      }
    }
  ]
}