{
  "type": "FeatureCollection",
  "title": "Bargylia",
  "id": "599550",
  "description": "An ancient place, cited: BAtlas 61 F3 Bargylia",
  "bbox": [
    27.589505,
    37.195835,
    27.589505,
    37.195835
  ],
  "reprPoint": [
    27.589505,
    37.195835
  ],
  "names": [
    "Bargylia"
  ],
  "features": [
    {
      "geometry": {
        "type": "Point",
        "coordinates": [
          27.586569,
          37.195722
        ]
      },
      "id": "darmc-location-11659",
      "type": "Feature",
      "properties": {
        "description": "500K scale point location",
        "location_precision": "precise",
        "title": "DARMC location 11659",
        "link": "http://pleiades.stoa.org/places/599550/darmc-location-11659"
      }
    },
    {
      "geometry": {
        "type": "Point",
        "coordinates": [
          27.589505,
          37.195835
        ]
      },
      "id": "dare-location",
      "type": "Feature",
      "properties": {
        "description": "Representative point location, site precision",
        "location_precision": "precise",
        "title": "DARE Location",
        "link": "http://pleiades.stoa.org/places/599550/dare-location"
      }
    }
  ]
}