{
  "type": "FeatureCollection",
  "title": "Artemis Parthenos, T.",
  "id": "599523",
  "description": "An ancient place, cited: BAtlas 61 D3 Artemis Parthenos, T.",
  "bbox": [
    26.803339,
    37.189532,
    26.803339,
    37.189532
  ],
  "connectsWith": [
    "599764"
  ],
  "reprPoint": [
    26.803339,
    37.189532
  ],
  "names": [
    "Artemis Parthenos, T."
  ],
  "features": [
    {
      "geometry": {
        "type": "Point",
        "coordinates": [
          26.803339,
          37.189532
        ]
      },
      "id": "darmc-location-15893",
      "type": "Feature",
      "properties": {
        "description": "500K scale point location",
        "location_precision": "precise",
        "title": "DARMC location 15893",
        "link": "http://pleiades.stoa.org/places/599523/darmc-location-15893"
      }
    }
  ]
}