{
  "type": "FeatureCollection",
  "title": "Astragon",
  "id": "599534",
  "bbox": [
    28.217488,
    37.381718,
    28.217488,
    37.381718
  ],
  "description": "An ancient place, cited: BAtlas 61 G3 Astragon",
  "names": [
    "Astragon"
  ],
  "features": [
    {
      "type": "Feature",
      "geometry": {
        "type": "Point",
        "coordinates": [
          28.217488,
          37.381718
        ]
      },
      "properties": {
        "description": "representative point"
      }
    },
    {
      "geometry": {
        "type": "Point",
        "coordinates": [
          28.217488,
          37.381718
        ]
      },
      "id": "darmc-location-9971",
      "type": "Feature",
      "properties": {
        "description": "1:500,000 scale representative point location digitized from the Barrington Atlas of the Greek and Roman World by the Digital Atlas of Roman and Medieval Civilizations project at Harvard University.",
        "location_precision": "precise",
        "title": "DARMC location 9971",
        "link": "http://pleiades.stoa.org/places/599534/darmc-location-9971"
      }
    }
  ]
}