{
  "type": "FeatureCollection",
  "title": "Artemis Tauropolos, T.",
  "id": "599524",
  "description": "An ancient place, cited: BAtlas 61 C2 Artemis Tauropolos, T.",
  "bbox": [
    26.059426,
    37.621567,
    26.0596359,
    37.6219278
  ],
  "connectsWith": [
    "599667"
  ],
  "reprPoint": [
    26.05953095,
    37.6217474
  ],
  "names": [
    "Artemis Tauropolos, T."
  ],
  "features": [
    {
      "geometry": {
        "type": "Point",
        "coordinates": [
          26.059426,
          37.621567
        ]
      },
      "id": "darmc-location-6591",
      "type": "Feature",
      "properties": {
        "description": "1M scale point location",
        "location_precision": "precise",
        "title": "DARMC location 6591",
        "link": "http://pleiades.stoa.org/places/599524/darmc-location-6591"
      }
    }
  ]
}