{
  "type": "FeatureCollection",
  "title": "Bathos",
  "id": "599553",
  "description": "An ancient place, cited: BAtlas 61 E4 Bathos",
  "bbox": [
    27.025915,
    36.975502,
    27.025915,
    36.975502
  ],
  "reprPoint": [
    27.025915,
    36.975502
  ],
  "features": [
    {
      "geometry": {
        "type": "Point",
        "coordinates": [
          27.025915,
          36.975502
        ]
      },
      "id": "darmc-location-2951",
      "type": "Feature",
      "properties": {
        "description": "500K scale point location",
        "location_precision": "precise",
        "title": "DARMC location 2951",
        "link": "http://pleiades.stoa.org/places/599553/darmc-location-2951"
      }
    }
  ]
}