{
  "type": "FeatureCollection",
  "title": "Dioshieron",
  "id": "599595",
  "bbox": [
    27.08106,
    38.029393,
    27.08106,
    38.029393
  ],
  "description": "An ancient place, cited: BAtlas 61 E1 Dioshieron",
  "names": [
    "Dioshieron"
  ],
  "features": [
    {
      "type": "Feature",
      "geometry": {
        "type": "Point",
        "coordinates": [
          27.08106,
          38.029393
        ]
      },
      "properties": {
        "description": "representative point"
      }
    },
    {
      "geometry": {
        "type": "Point",
        "coordinates": [
          27.08106,
          38.029393
        ]
      },
      "id": "darmc-location-3228",
      "type": "Feature",
      "properties": {
        "description": "1M scale point location",
        "location_precision": "precise",
        "title": "DARMC location 3228",
        "link": "http://pleiades.stoa.org/places/599595/darmc-location-3228"
      }
    }
  ]
}