{
  "type": "FeatureCollection",
  "title": "Drakanon",
  "id": "599598",
  "description": "An ancient place, cited: BAtlas 61 C2 Drakanon",
  "bbox": [
    26.356402,
    37.693867,
    26.356402,
    37.693867
  ],
  "connectsWith": [
    "599667"
  ],
  "reprPoint": [
    26.356402,
    37.693867
  ],
  "names": [
    "Drakanon"
  ],
  "features": [
    {
      "geometry": {
        "type": "Point",
        "coordinates": [
          26.356402,
          37.693867
        ]
      },
      "id": "darmc-location-12258",
      "type": "Feature",
      "properties": {
        "description": "500K scale point location",
        "location_precision": "precise",
        "title": "DARMC location 12258",
        "link": "http://pleiades.stoa.org/places/599598/darmc-location-12258"
      }
    }
  ]
}