{
  "type": "FeatureCollection",
  "title": "Brouzi",
  "id": "599560",
  "bbox": [
    26.855871,
    37.155921,
    26.855871,
    37.155921
  ],
  "description": "An ancient place, cited: BAtlas 61 D3 Brouzi",
  "connectsWith": [
    "599764"
  ],
  "features": [
    {
      "type": "Feature",
      "geometry": {
        "type": "Point",
        "coordinates": [
          26.855871,
          37.155921
        ]
      },
      "properties": {
        "description": "representative point"
      }
    },
    {
      "geometry": {
        "type": "Point",
        "coordinates": [
          26.855871,
          37.155921
        ]
      },
      "id": "darmc-location-23468",
      "type": "Feature",
      "properties": {
        "description": "Point location",
        "location_precision": "precise",
        "title": "DARMC location 23468",
        "link": "http://pleiades.stoa.org/places/599560/darmc-location-23468"
      }
    }
  ]
}