{
  "type": "FeatureCollection",
  "title": "Iasos",
  "id": "599664",
  "description": "Iasos was an ancient Greek city in Caria.",
  "bbox": [
    27.584578,
    37.279525,
    27.584578,
    37.279525
  ],
  "connectsWith": [
    "991381"
  ],
  "reprPoint": [
    27.584578,
    37.279525
  ],
  "names": [
    "Iasos"
  ],
  "features": [
    {
      "geometry": {
        "type": "Point",
        "coordinates": [
          27.585572,
          37.278149
        ]
      },
      "id": "darmc-location-12839",
      "type": "Feature",
      "properties": {
        "description": "500K scale point location",
        "location_precision": "precise",
        "title": "DARMC location 12839",
        "link": "http://pleiades.stoa.org/places/599664/darmc-location-12839"
      }
    },
    {
      "geometry": {
        "type": "Point",
        "coordinates": [
          27.584578,
          37.279525
        ]
      },
      "id": "dare-location",
      "type": "Feature",
      "properties": {
        "description": "Representative point location, site precision",
        "location_precision": "precise",
        "title": "DARE Location",
        "link": "http://pleiades.stoa.org/places/599664/dare-location"
      }
    }
  ]
}