{
  "type": "FeatureCollection",
  "title": "Iasos",
  "id": "599664",
  "bbox": [
    27.584578,
    37.278149,
    27.585572,
    37.279525
  ],
  "description": "Iasos was an ancient Greek city in Caria.",
  "connectsWith": [
    "991381"
  ],
  "names": [
    "Iasos"
  ],
  "features": [
    {
      "type": "Feature",
      "geometry": {
        "type": "Point",
        "coordinates": [
          27.585075,
          37.278837
        ]
      },
      "properties": {
        "description": "representative point"
      }
    },
    {
      "geometry": {
        "type": "Point",
        "coordinates": [
          27.585572,
          37.278149
        ]
      },
      "id": "darmc-location-12839",
      "type": "Feature",
      "properties": {
        "description": "1:500,000 scale representative point location digitized from the Barrington Atlas of the Greek and Roman World by the Digital Atlas of Roman and Medieval Civilizations project at Harvard University.",
        "location_precision": "precise",
        "title": "DARMC location 12839",
        "link": "http://pleiades.stoa.org/places/599664/darmc-location-12839"
      }
    },
    {
      "geometry": {
        "type": "Point",
        "coordinates": [
          27.584578,
          37.279525
        ]
      },
      "id": "dare-location",
      "type": "Feature",
      "properties": {
        "description": "Representative point location, site precision",
        "location_precision": "precise",
        "title": "DARE Location",
        "link": "http://pleiades.stoa.org/places/599664/dare-location"
      }
    }
  ]
}