{
  "type": "FeatureCollection",
  "title": "Kallipolis",
  "id": "599681",
  "bbox": [
    28.4536,
    37.032454,
    28.4536,
    37.032454
  ],
  "description": "A city of the Rhodian Peraea located close to the gulf of Kos.",
  "names": [
    "Kallipolis"
  ],
  "features": [
    {
      "type": "Feature",
      "geometry": {
        "type": "Point",
        "coordinates": [
          28.4536,
          37.032454
        ]
      },
      "properties": {
        "description": "representative point"
      }
    },
    {
      "geometry": {
        "type": "Point",
        "coordinates": [
          28.4536,
          37.032454
        ]
      },
      "id": "darmc-location-3015",
      "type": "Feature",
      "properties": {
        "description": "500K scale point location",
        "location_precision": "precise",
        "title": "DARMC location 3015",
        "link": "http://pleiades.stoa.org/places/599681/darmc-location-3015"
      }
    }
  ]
}