{
  "type": "FeatureCollection",
  "title": "Heraclea ad Latmum/Pleistarcheia",
  "id": "599640",
  "bbox": [
    27.525011,
    37.501842,
    27.525011,
    37.501842
  ],
  "description": "An ancient place, cited: BAtlas 61 F2 Heraclea ad Latmum/Pleistarcheia",
  "names": [
    "Heraclea ad Latmum",
    "Pleistarcheia"
  ],
  "features": [
    {
      "type": "Feature",
      "geometry": {
        "type": "Point",
        "coordinates": [
          27.525011,
          37.501842
        ]
      },
      "properties": {
        "description": "representative point"
      }
    },
    {
      "geometry": {
        "type": "Point",
        "coordinates": [
          27.525011,
          37.501842
        ]
      },
      "id": "dare-location",
      "type": "Feature",
      "properties": {
        "description": "Representative point location, site precision",
        "location_precision": "precise",
        "title": "DARE Location",
        "link": "http://pleiades.stoa.org/places/599640/dare-location"
      }
    }
  ]
}