{
  "type": "FeatureCollection",
  "title": "Euthenai",
  "id": "599617",
  "bbox": [
    28.259418,
    36.935973,
    28.259418,
    36.935973
  ],
  "description": "An ancient place, cited: BAtlas 61 G4 Euthenai",
  "names": [
    "Euthenai"
  ],
  "features": [
    {
      "type": "Feature",
      "geometry": {
        "type": "Point",
        "coordinates": [
          28.259418,
          36.935973
        ]
      },
      "properties": {
        "description": "representative point"
      }
    },
    {
      "geometry": {
        "type": "Point",
        "coordinates": [
          28.259418,
          36.935973
        ]
      },
      "id": "darmc-location-12412",
      "type": "Feature",
      "properties": {
        "description": "500K scale point location",
        "location_precision": "precise",
        "title": "DARMC location 12412",
        "link": "http://pleiades.stoa.org/places/599617/darmc-location-12412"
      }
    }
  ]
}