{
  "type": "FeatureCollection",
  "title": "Heraclea ad Latmum/Pleistarcheia",
  "id": "599640",
  "bbox": [
    27.525011,
    37.501842,
    27.525011,
    37.501842
  ],
  "description": "A town of Caria located 25 km west of Miletos on the Ionian coast, Heraclea was located on the lower slopes of Mt. Latmos. Once a part of the Delian League, the city fell to Mausolos in the fourth century B.C. and his philhellene policy accounts for its change of name.",
  "connectsWith": [
    "599752",
    "48050879",
    "599564"
  ],
  "names": [
    "Heraclea ad Latmum",
    "Pleistarcheia",
    "Herakleia he upo Latmo"
  ],
  "features": [
    {
      "type": "Feature",
      "geometry": {
        "type": "Point",
        "coordinates": [
          27.525011,
          37.501842
        ]
      },
      "properties": {
        "description": "representative point"
      }
    },
    {
      "geometry": {
        "type": "Point",
        "coordinates": [
          27.525011,
          37.501842
        ]
      },
      "id": "dare-location",
      "type": "Feature",
      "properties": {
        "description": "Representative point location, site precision",
        "location_precision": "precise",
        "title": "DARE Location",
        "link": "http://pleiades.stoa.org/places/599640/dare-location"
      }
    }
  ]
}