{
  "type": "FeatureCollection",
  "title": "Klaros",
  "id": "599719",
  "description": "The site of a temple of Apollo administered by Colophonians and active from the seventh century B.C. to the fourth century A.D.",
  "bbox": [
    27.192987,
    38.004725,
    27.192987,
    38.004725
  ],
  "connectsWith": [
    "550597"
  ],
  "reprPoint": [
    27.192987,
    38.004725
  ],
  "names": [
    "Klaros"
  ],
  "features": [
    {
      "geometry": {
        "type": "Point",
        "coordinates": [
          27.192987,
          38.004725
        ]
      },
      "id": "dare-location",
      "type": "Feature",
      "properties": {
        "description": "Representative point location, site precision",
        "location_precision": "precise",
        "title": "DARE Location",
        "link": "http://pleiades.stoa.org/places/599719/dare-location"
      }
    }
  ]
}