{
  "type": "FeatureCollection",
  "title": "*Kleimaka",
  "id": "599721",
  "description": "An ancient place, cited: BAtlas 61 F1 *Kleimaka",
  "bbox": [
    27.893729,
    38.050575,
    27.893729,
    38.050575
  ],
  "reprPoint": [
    27.893729,
    38.050575
  ],
  "names": [
    "Kleimaka"
  ],
  "features": [
    {
      "geometry": {
        "type": "Point",
        "coordinates": [
          27.893729,
          38.050575
        ]
      },
      "id": "darmc-location-10093",
      "type": "Feature",
      "properties": {
        "description": "500K scale point location",
        "location_precision": "precise",
        "title": "DARMC location 10093",
        "link": "http://pleiades.stoa.org/places/599721/darmc-location-10093"
      }
    }
  ]
}