{
  "type": "FeatureCollection",
  "title": "Miletus",
  "id": "599799",
  "bbox": [
    27.2774885,
    37.507952,
    27.279561,
    37.531526
  ],
  "description": "A major ancient city in Caria.",
  "connectsWith": [
    "48050879",
    "981509",
    "735295266",
    "599777",
    "599668",
    "599564"
  ],
  "names": [
    "Millawa(n)da",
    "Miletus",
    "Milet",
    "Palatia",
    "Amtalın",
    "Balat",
    "Balat",
    "Miletos",
    "Milētos",
    "Amṭalin"
  ],
  "features": [
    {
      "type": "Feature",
      "geometry": {
        "type": "Point",
        "coordinates": [
          27.2783168333,
          37.5229047333
        ]
      },
      "properties": {
        "description": "representative point"
      }
    },
    {
      "geometry": {
        "type": "Point",
        "coordinates": [
          27.279561,
          37.531526
        ]
      },
      "id": "darmc-location-4819",
      "type": "Feature",
      "properties": {
        "description": "1:500,000 scale representative point location digitized from the Barrington Atlas of the Greek and Roman World by the Digital Atlas of Roman and Medieval Civilizations project at Harvard University.",
        "location_precision": "precise",
        "title": "DARMC location 4819",
        "link": "http://pleiades.stoa.org/places/599799/darmc-location-4819"
      }
    },
    {
      "geometry": {
        "type": "Point",
        "coordinates": [
          27.277901,
          37.507952
        ]
      },
      "id": "darmc-location-24020",
      "type": "Feature",
      "properties": {
        "description": "1:1 million scale representative point location digitized from the Barrington Atlas of the Greek and Roman World by the Digital Atlas of Roman and Medieval Civilizations project at Harvard University.",
        "location_precision": "precise",
        "title": "DARMC location 24020",
        "link": "http://pleiades.stoa.org/places/599799/darmc-location-24020"
      }
    },
    {
      "geometry": {
        "type": "Point",
        "coordinates": [
          27.2774885,
          37.5292362
        ]
      },
      "id": "dare-location",
      "type": "Feature",
      "properties": {
        "description": "Representative point location, site precision",
        "location_precision": "precise",
        "title": "DARE Location",
        "link": "http://pleiades.stoa.org/places/599799/dare-location"
      }
    }
  ]
}