{
  "type": "FeatureCollection",
  "title": "Korsiai?",
  "id": "599727",
  "bbox": [
    26.479008,
    37.578866,
    26.479008,
    37.578866
  ],
  "description": "An ancient place, cited: BAtlas 61 C2 Korsiai?",
  "connectsWith": [
    "599726"
  ],
  "names": [
    "Korsiai"
  ],
  "features": [
    {
      "type": "Feature",
      "geometry": {
        "type": "Point",
        "coordinates": [
          26.479008,
          37.578866
        ]
      },
      "properties": {
        "description": "representative point"
      }
    },
    {
      "geometry": {
        "type": "Point",
        "coordinates": [
          26.479008,
          37.578866
        ]
      },
      "id": "darmc-location-24063",
      "type": "Feature",
      "properties": {
        "description": "1M scale point location",
        "location_precision": "precise",
        "title": "DARMC location 24063",
        "link": "http://pleiades.stoa.org/places/599727/darmc-location-24063"
      }
    }
  ]
}