{
  "type": "FeatureCollection",
  "title": "Maltezana",
  "id": "599782",
  "bbox": [
    26.382965,
    36.581251,
    26.382965,
    36.581251
  ],
  "description": "An ancient place, cited: BAtlas 61 C4 Maltezana",
  "connectsWith": [
    "599536"
  ],
  "features": [
    {
      "type": "Feature",
      "geometry": {
        "type": "Point",
        "coordinates": [
          26.382965,
          36.581251
        ]
      },
      "properties": {
        "description": "representative point"
      }
    },
    {
      "geometry": {
        "type": "Point",
        "coordinates": [
          26.382965,
          36.581251
        ]
      },
      "id": "darmc-location-9264",
      "type": "Feature",
      "properties": {
        "description": "500K scale point location",
        "location_precision": "precise",
        "title": "DARMC location 9264",
        "link": "http://pleiades.stoa.org/places/599782/darmc-location-9264"
      }
    }
  ]
}