{
  "type": "FeatureCollection",
  "title": "Kys/Kanebion/Palaiapolis",
  "id": "599743",
  "bbox": [
    28.423734,
    37.428882,
    28.423734,
    37.428882
  ],
  "description": "An ancient place, cited: BAtlas 61 G3 Kys/Kanebion/Palaiapolis",
  "names": [
    "Kys",
    "Kanebion",
    "Palaiapolis"
  ],
  "features": [
    {
      "type": "Feature",
      "geometry": {
        "type": "Point",
        "coordinates": [
          28.423734,
          37.428882
        ]
      },
      "properties": {
        "description": "representative point"
      }
    },
    {
      "geometry": {
        "type": "Point",
        "coordinates": [
          28.423734,
          37.428882
        ]
      },
      "id": "darmc-location-13358",
      "type": "Feature",
      "properties": {
        "description": "1:500,000 scale representative point location digitized from the Barrington Atlas of the Greek and Roman World by the Digital Atlas of Roman and Medieval Civilizations project at Harvard University.",
        "location_precision": "precise",
        "title": "DARMC location 13358",
        "link": "http://pleiades.stoa.org/places/599743/darmc-location-13358"
      }
    }
  ]
}