{
  "type": "FeatureCollection",
  "title": "Miletus",
  "id": "599799",
  "description": "A major city in Caria",
  "bbox": [
    27.2756764,
    37.507952,
    27.279561,
    37.531526
  ],
  "connectsWith": [
    "599777",
    "599668"
  ],
  "reprPoint": [
    27.27770558,
    37.52157586
  ],
  "names": [
    "Milet",
    "Miletus",
    "Palatia",
    "Amtalın",
    "Balat",
    "Balat",
    "Miletos",
    "Milētos",
    "Amṭalin"
  ],
  "features": [
    {
      "geometry": {
        "type": "Point",
        "coordinates": [
          27.2756764,
          37.5312131
        ]
      },
      "id": "location-of-theater-of-miletus",
      "type": "Feature",
      "properties": {
        "description": "Location based on OpenStreetMap",
        "location_precision": "precise",
        "title": "location of theater of Miletus",
        "link": "http://pleiades.stoa.org/places/599799/location-of-theater-of-miletus"
      }
    },
    {
      "geometry": {
        "type": "Point",
        "coordinates": [
          27.279561,
          37.531526
        ]
      },
      "id": "darmc-location-4819",
      "type": "Feature",
      "properties": {
        "description": "500K scale point location",
        "location_precision": "precise",
        "title": "DARMC location 4819",
        "link": "http://pleiades.stoa.org/places/599799/darmc-location-4819"
      }
    },
    {
      "geometry": {
        "type": "Point",
        "coordinates": [
          27.277901,
          37.507952
        ]
      },
      "id": "darmc-location-24020",
      "type": "Feature",
      "properties": {
        "description": "1M scale point location",
        "location_precision": "precise",
        "title": "DARMC location 24020",
        "link": "http://pleiades.stoa.org/places/599799/darmc-location-24020"
      }
    },
    {
      "geometry": {
        "type": "Point",
        "coordinates": [
          27.277901,
          37.507952
        ]
      },
      "id": "darmc-location-24087",
      "type": "Feature",
      "properties": {
        "description": "5M scale point location",
        "location_precision": "precise",
        "title": "DARMC location 24087",
        "link": "http://pleiades.stoa.org/places/599799/darmc-location-24087"
      }
    },
    {
      "geometry": {
        "type": "Point",
        "coordinates": [
          27.2774885,
          37.5292362
        ]
      },
      "id": "dare-location",
      "type": "Feature",
      "properties": {
        "description": "Representative point location, site precision",
        "location_precision": "precise",
        "title": "DARE Location",
        "link": "http://pleiades.stoa.org/places/599799/dare-location"
      }
    }
  ]
}