{
  "type": "FeatureCollection",
  "title": "Leros",
  "id": "599763",
  "bbox": [
    26.854663,
    37.158037,
    26.854663,
    37.158037
  ],
  "description": "An ancient place, cited: BAtlas 61 D3 Leros",
  "connectsWith": [
    "599764"
  ],
  "names": [
    "Leros"
  ],
  "features": [
    {
      "type": "Feature",
      "geometry": {
        "type": "Point",
        "coordinates": [
          26.854663,
          37.158037
        ]
      },
      "properties": {
        "description": "representative point"
      }
    },
    {
      "geometry": {
        "type": "Point",
        "coordinates": [
          26.854663,
          37.158037
        ]
      },
      "id": "darmc-location-3826",
      "type": "Feature",
      "properties": {
        "description": "1:500,000 scale representative point location digitized from the Barrington Atlas of the Greek and Roman World by the Digital Atlas of Roman and Medieval Civilizations project at Harvard University.",
        "location_precision": "precise",
        "title": "DARMC location 3826",
        "link": "http://pleiades.stoa.org/places/599763/darmc-location-3826"
      }
    }
  ]
}