{
  "type": "FeatureCollection",
  "title": "Melanes",
  "id": "599791",
  "bbox": [
    25.441833,
    37.086883,
    25.441833,
    37.086883
  ],
  "description": "An ancient place, cited: BAtlas 61 A3 Melanes",
  "connectsWith": [
    "599822"
  ],
  "features": [
    {
      "type": "Feature",
      "geometry": {
        "type": "Point",
        "coordinates": [
          25.441833,
          37.086883
        ]
      },
      "properties": {
        "description": "representative point"
      }
    },
    {
      "geometry": {
        "type": "Point",
        "coordinates": [
          25.441833,
          37.086883
        ]
      },
      "id": "darmc-location-9268",
      "type": "Feature",
      "properties": {
        "description": "500K scale point location",
        "location_precision": "precise",
        "title": "DARMC location 9268",
        "link": "http://pleiades.stoa.org/places/599791/darmc-location-9268"
      }
    }
  ]
}