{
  "type": "FeatureCollection",
  "title": "Korsiai?",
  "id": "599727",
  "bbox": [
    26.479008,
    37.578866,
    26.479008,
    37.578866
  ],
  "description": "The modern town of Fournoi on the largest of the Aegean islands of the same name was likely the principal settlement and harbor of the archipelago, inheriting from them the name Korsiai.",
  "connectsWith": [
    "599726"
  ],
  "names": [
    "Korsiai"
  ],
  "features": [
    {
      "type": "Feature",
      "geometry": {
        "type": "Point",
        "coordinates": [
          26.479008,
          37.578866
        ]
      },
      "properties": {
        "description": "representative point"
      }
    },
    {
      "geometry": {
        "type": "Point",
        "coordinates": [
          26.479008,
          37.578866
        ]
      },
      "id": "darmc-location-24063",
      "type": "Feature",
      "properties": {
        "description": "1:1 million scale representative point location digitized from the Barrington Atlas of the Greek and Roman World by the Digital Atlas of Roman and Medieval Civilizations project at Harvard University.",
        "location_precision": "precise",
        "title": "DARMC location 24063",
        "link": "http://pleiades.stoa.org/places/599727/darmc-location-24063"
      }
    }
  ]
}