{
  "type": "FeatureCollection",
  "title": "Mycale (mountain)",
  "id": "599805",
  "bbox": [
    27.083333,
    37.666667,
    27.083333,
    37.666667
  ],
  "description": "Samsun Dağ.",
  "connectsWith": [
    "599564"
  ],
  "names": [
    "Mycale",
    "Mycale",
    "Dilek Dagi",
    "Samsun Dagi"
  ],
  "features": [
    {
      "type": "Feature",
      "geometry": {
        "type": "Point",
        "coordinates": [
          27.083333,
          37.666667
        ]
      },
      "properties": {
        "description": "representative point"
      }
    },
    {
      "geometry": {
        "type": "Point",
        "coordinates": [
          27.083333,
          37.666667
        ]
      },
      "id": "imagery-location-of-mycale-m",
      "type": "Feature",
      "properties": {
        "description": "verified in Google Earth 2013.",
        "location_precision": "precise",
        "title": "Imagery location of Mycale M.",
        "link": "http://pleiades.stoa.org/places/599805/imagery-location-of-mycale-m"
      }
    }
  ]
}