{
  "type": "FeatureCollection",
  "title": "Ouranion",
  "id": "599842",
  "bbox": [
    27.278841,
    37.093516,
    27.278841,
    37.093516
  ],
  "description": "An ancient place, cited: BAtlas 61 E3 Ouranion",
  "names": [
    "Ouranion"
  ],
  "features": [
    {
      "type": "Feature",
      "geometry": {
        "type": "Point",
        "coordinates": [
          27.278841,
          37.093516
        ]
      },
      "properties": {
        "description": "representative point"
      }
    },
    {
      "geometry": {
        "type": "Point",
        "coordinates": [
          27.278841,
          37.093516
        ]
      },
      "id": "darmc-location-14064",
      "type": "Feature",
      "properties": {
        "description": "500K scale point location",
        "location_precision": "precise",
        "title": "DARMC location 14064",
        "link": "http://pleiades.stoa.org/places/599842/darmc-location-14064"
      }
    }
  ]
}