{
  "type": "FeatureCollection",
  "title": "Nisyros (settlement)",
  "id": "599829",
  "bbox": [
    27.1301861,
    36.583333,
    27.166667,
    36.6060013
  ],
  "description": "The eponymous settlement of the volcanic island of Nisyros in the Aegean Sea.",
  "connectsWith": [
    "599830"
  ],
  "names": [
    "Nisyros"
  ],
  "features": [
    {
      "type": "Feature",
      "geometry": {
        "type": "Point",
        "coordinates": [
          27.1301861,
          36.6060013
        ]
      },
      "properties": {
        "description": "representative point"
      }
    }
  ]
}