{
  "type": "FeatureCollection",
  "title": "Mycale M.",
  "id": "599805",
  "description": "An ancient place, cited: BAtlas 61 E2 Mycale M.",
  "bbox": [
    27.083333,
    37.666667,
    27.083333,
    37.666667
  ],
  "reprPoint": [
    27.083333,
    37.666667
  ],
  "names": [
    "Mycale M."
  ],
  "features": [
    {
      "geometry": {
        "type": "Point",
        "coordinates": [
          27.083333,
          37.666667
        ]
      },
      "id": "location-of-mycale-m",
      "type": "Feature",
      "properties": {
        "description": "verified in Google Earth 2013.",
        "location_precision": "precise",
        "title": "location of Mycale M.",
        "link": "http://pleiades.stoa.org/places/599805/location-of-mycale-m"
      }
    }
  ]
}