{
  "type": "FeatureCollection",
  "title": "Panormos",
  "id": "599861",
  "bbox": [
    26.580316,
    37.321298,
    26.580316,
    37.321298
  ],
  "description": "A bay, sheltered on north, west, and south by the Aegean island of Patmos.",
  "connectsWith": [
    "599872"
  ],
  "names": [
    "Panormos"
  ],
  "features": [
    {
      "type": "Feature",
      "geometry": {
        "type": "Point",
        "coordinates": [
          26.580316,
          37.321298
        ]
      },
      "properties": {
        "description": "representative point"
      }
    },
    {
      "geometry": {
        "type": "Point",
        "coordinates": [
          26.580316,
          37.321298
        ]
      },
      "id": "imagery-location-of-panormos-bay-patmos",
      "type": "Feature",
      "properties": {
        "description": null,
        "location_precision": "precise",
        "title": "Imagery location of Panormos bay (Patmos)",
        "link": "http://pleiades.stoa.org/places/599861/imagery-location-of-panormos-bay-patmos"
      }
    }
  ]
}