{
  "type": "FeatureCollection",
  "title": "Minoa",
  "id": "599800",
  "bbox": [
    25.861108,
    36.821263,
    25.867017,
    36.827112
  ],
  "description": "An ancient place, cited: BAtlas 61 B4 Minoa",
  "names": [
    "Minoa"
  ],
  "features": [
    {
      "type": "Feature",
      "geometry": {
        "type": "Point",
        "coordinates": [
          25.8640625,
          36.8241875
        ]
      },
      "properties": {
        "description": "representative point"
      }
    },
    {
      "geometry": {
        "type": "Point",
        "coordinates": [
          25.867017,
          36.827112
        ]
      },
      "id": "darmc-location-4951",
      "type": "Feature",
      "properties": {
        "description": "1:500,000 scale representative point location digitized from the Barrington Atlas of the Greek and Roman World by the Digital Atlas of Roman and Medieval Civilizations project at Harvard University.",
        "location_precision": "precise",
        "title": "DARMC location 4951",
        "link": "http://pleiades.stoa.org/places/599800/darmc-location-4951"
      }
    },
    {
      "geometry": {
        "type": "Point",
        "coordinates": [
          25.861108,
          36.821263
        ]
      },
      "id": "darmc-location-24088",
      "type": "Feature",
      "properties": {
        "description": "1:1 million scale representative point location digitized from the Barrington Atlas of the Greek and Roman World by the Digital Atlas of Roman and Medieval Civilizations project at Harvard University.",
        "location_precision": "precise",
        "title": "DARMC location 24088",
        "link": "http://pleiades.stoa.org/places/599800/darmc-location-24088"
      }
    }
  ]
}