{
  "type": "FeatureCollection",
  "title": "Orthosia",
  "id": "599839",
  "description": "An ancient place, cited: BAtlas 61 G2 Orthosia",
  "bbox": [
    28.228037,
    37.824122,
    28.252865,
    37.827987
  ],
  "reprPoint": [
    28.240451,
    37.8260545
  ],
  "names": [
    "Orthosia"
  ],
  "features": [
    {
      "geometry": {
        "type": "Point",
        "coordinates": [
          28.252865,
          37.827987
        ]
      },
      "id": "darmc-location-5391",
      "type": "Feature",
      "properties": {
        "description": "500K scale point location",
        "location_precision": "precise",
        "title": "DARMC location 5391",
        "link": "http://pleiades.stoa.org/places/599839/darmc-location-5391"
      }
    },
    {
      "geometry": {
        "type": "Point",
        "coordinates": [
          28.228037,
          37.824122
        ]
      },
      "id": "dare-location",
      "type": "Feature",
      "properties": {
        "description": "Representative point location, site precision",
        "location_precision": "precise",
        "title": "DARE Location",
        "link": "http://pleiades.stoa.org/places/599839/dare-location"
      }
    }
  ]
}