{
  "type": "FeatureCollection",
  "title": "Oia",
  "id": "599834",
  "description": "An ancient place, cited: BAtlas 61 A5 Oia",
  "bbox": [
    25.47724,
    36.364709,
    25.477975,
    36.369955
  ],
  "reprPoint": [
    25.4776075,
    36.367332
  ],
  "names": [
    "Oia"
  ],
  "features": [
    {
      "geometry": {
        "type": "Point",
        "coordinates": [
          25.47724,
          36.369955
        ]
      },
      "id": "darmc-location-13989",
      "type": "Feature",
      "properties": {
        "description": "500K scale point location",
        "location_precision": "precise",
        "title": "DARMC location 13989",
        "link": "http://pleiades.stoa.org/places/599834/darmc-location-13989"
      }
    },
    {
      "geometry": {
        "type": "Point",
        "coordinates": [
          25.477975,
          36.364709
        ]
      },
      "id": "dare-location",
      "type": "Feature",
      "properties": {
        "description": "Representative point location, site precision",
        "location_precision": "precise",
        "title": "DARE Location",
        "link": "http://pleiades.stoa.org/places/599834/dare-location"
      }
    }
  ]
}