{
  "type": "FeatureCollection",
  "title": "Nisyros",
  "id": "599829",
  "description": "An ancient place, cited: BAtlas 61 E4 Nisyros",
  "bbox": [
    27.172056,
    36.587875,
    27.172056,
    36.587875
  ],
  "reprPoint": [
    27.172056,
    36.587875
  ],
  "names": [
    "Nisyros"
  ],
  "features": [
    {
      "geometry": {
        "type": "Point",
        "coordinates": [
          27.172056,
          36.587875
        ]
      },
      "id": "darmc-location-24137",
      "type": "Feature",
      "properties": {
        "description": "1M scale point location",
        "location_precision": "precise",
        "title": "DARMC location 24137",
        "link": "http://pleiades.stoa.org/places/599829/darmc-location-24137"
      }
    }
  ]
}