{
  "type": "FeatureCollection",
  "title": "Polypodousa Ins.",
  "id": "599896",
  "description": "An ancient place, cited: BAtlas 61 F4 Polypodousa Ins.",
  "bbox": [
    27.5092484,
    36.6614292,
    27.5092484,
    36.6614292
  ],
  "reprPoint": [
    27.5092484,
    36.6614292
  ],
  "names": [
    "Polypodousa"
  ],
  "features": [
    {
      "geometry": {
        "type": "Point",
        "coordinates": [
          27.5092484,
          36.6614292
        ]
      },
      "id": "location-of-Polypodousa-Ins",
      "type": "Feature",
      "properties": {
        "description": "Location based on OpenStreetMap",
        "location_precision": "precise",
        "title": "location of Polypodousa Ins.",
        "link": "http://pleiades.stoa.org/places/599896/location-of-Polypodousa-Ins"
      }
    }
  ]
}