{
  "type": "FeatureCollection",
  "title": "Mycale (mountain)",
  "id": "599805",
  "bbox": [
    27.083333,
    37.666667,
    27.083333,
    37.666667
  ],
  "description": "Samsun Dağ.",
  "names": [
    "Mycale"
  ],
  "features": [
    {
      "type": "Feature",
      "geometry": {
        "type": "Point",
        "coordinates": [
          27.083333,
          37.666667
        ]
      },
      "properties": {
        "description": "representative point"
      }
    },
    {
      "geometry": {
        "type": "Point",
        "coordinates": [
          27.083333,
          37.666667
        ]
      },
      "id": "location-of-mycale-m",
      "type": "Feature",
      "properties": {
        "description": "verified in Google Earth 2013.",
        "location_precision": "precise",
        "title": "location of Mycale M.",
        "link": "http://pleiades.stoa.org/places/599805/location-of-mycale-m"
      }
    }
  ]
}