{
  "type": "FeatureCollection",
  "title": "Therma/Asklepieis",
  "id": "599976",
  "bbox": [
    26.319589,
    37.635589,
    26.319589,
    37.635589
  ],
  "description": "An ancient place, cited: BAtlas 61 C2 Therma/Asklepieis",
  "connectsWith": [
    "599667"
  ],
  "names": [
    "Therma",
    "Asklepieis"
  ],
  "features": [
    {
      "type": "Feature",
      "geometry": {
        "type": "Point",
        "coordinates": [
          26.319589,
          37.635589
        ]
      },
      "properties": {
        "description": "representative point"
      }
    },
    {
      "geometry": {
        "type": "Point",
        "coordinates": [
          26.319589,
          37.635589
        ]
      },
      "id": "imagery-location",
      "type": "Feature",
      "properties": {
        "description": "Coordinates following GeoHack",
        "location_precision": "precise",
        "title": "Imagery location",
        "link": "http://pleiades.stoa.org/places/599976/imagery-location"
      }
    }
  ]
}