{
  "type": "FeatureCollection",
  "title": "Skopias? Pr.",
  "id": "599941",
  "bbox": [
    27.263977,
    36.9648658,
    27.263977,
    36.9648658
  ],
  "description": "An ancient place, cited: BAtlas 61 E4 Skopias? Pr.",
  "names": [
    "Skopias Pr."
  ],
  "features": [
    {
      "type": "Feature",
      "geometry": {
        "type": "Point",
        "coordinates": [
          27.263977,
          36.9648658
        ]
      },
      "properties": {
        "description": "representative point"
      }
    },
    {
      "geometry": {
        "type": "Point",
        "coordinates": [
          27.263977,
          36.9648658
        ]
      },
      "id": "osm-location",
      "type": "Feature",
      "properties": {
        "description": "Representative location based on OpenStreetMap.",
        "location_precision": "precise",
        "title": "OSM location of Skopias? Pr.",
        "link": "http://pleiades.stoa.org/places/599941/osm-location"
      }
    }
  ]
}