{
  "type": "FeatureCollection",
  "title": "Rheneia (settlement)",
  "id": "599918",
  "bbox": [
    25.213287,
    37.41206,
    25.213287,
    37.41206
  ],
  "description": "An ancient place, cited: BAtlas 61 A3 Rheneia",
  "connectsWith": [
    "599919"
  ],
  "names": [
    "Rheneia"
  ],
  "features": [
    {
      "type": "Feature",
      "geometry": {
        "type": "Point",
        "coordinates": [
          25.213287,
          37.41206
        ]
      },
      "properties": {
        "description": "representative point"
      }
    },
    {
      "geometry": {
        "type": "Point",
        "coordinates": [
          25.213287,
          37.41206
        ]
      },
      "id": "darmc-location-14497",
      "type": "Feature",
      "properties": {
        "description": "1:500,000 scale representative point location digitized from the Barrington Atlas of the Greek and Roman World by the Digital Atlas of Roman and Medieval Civilizations project at Harvard University.",
        "location_precision": "precise",
        "title": "DARMC location 14497",
        "link": "http://pleiades.stoa.org/places/599918/darmc-location-14497"
      }
    }
  ]
}