{
  "type": "FeatureCollection",
  "title": "Schinoussa (island)",
  "id": "599928",
  "bbox": [
    25.5300178,
    36.8837147,
    25.5300178,
    36.8837147
  ],
  "description": "An ancient place, cited: BAtlas 61 B4 Schinoussa Ins.",
  "names": [
    "Schinoussa"
  ],
  "features": [
    {
      "type": "Feature",
      "geometry": {
        "type": "Point",
        "coordinates": [
          25.5300178,
          36.8837147
        ]
      },
      "properties": {
        "description": "representative point"
      }
    },
    {
      "geometry": {
        "type": "Point",
        "coordinates": [
          25.5300178,
          36.8837147
        ]
      },
      "id": "osm-location",
      "type": "Feature",
      "properties": {
        "description": "Representative modern location based on OpenStreetMap.",
        "location_precision": "precise",
        "title": "OSM location of Σχοινούσα (island)",
        "link": "http://pleiades.stoa.org/places/599928/osm-location"
      }
    }
  ]
}