{
  "type": "FeatureCollection",
  "title": "Sykia",
  "id": "599949",
  "description": "An ancient place, cited: BAtlas 61 D4 Sykia",
  "bbox": [
    26.933023,
    36.992096,
    26.933023,
    36.992096
  ],
  "reprPoint": [
    26.933023,
    36.992096
  ],
  "features": [
    {
      "geometry": {
        "type": "Point",
        "coordinates": [
          26.933023,
          36.992096
        ]
      },
      "id": "darmc-location-14946",
      "type": "Feature",
      "properties": {
        "description": "500K scale point location",
        "location_precision": "precise",
        "title": "DARMC location 14946",
        "link": "http://pleiades.stoa.org/places/599949/darmc-location-14946"
      }
    }
  ]
}