{
  "type": "FeatureCollection",
  "title": "Rheneia",
  "id": "599918",
  "description": "An ancient place, cited: BAtlas 61 A3 Rheneia",
  "bbox": [
    25.213287,
    37.41206,
    25.213287,
    37.41206
  ],
  "reprPoint": [
    25.213287,
    37.41206
  ],
  "names": [
    "Rheneia"
  ],
  "features": [
    {
      "geometry": {
        "type": "Point",
        "coordinates": [
          25.213287,
          37.41206
        ]
      },
      "id": "darmc-location-14497",
      "type": "Feature",
      "properties": {
        "description": "500K scale point location",
        "location_precision": "precise",
        "title": "DARMC location 14497",
        "link": "http://pleiades.stoa.org/places/599918/darmc-location-14497"
      }
    }
  ]
}