{
  "type": "FeatureCollection",
  "title": "Peukelaotis/Kaspatyros?",
  "id": "59993",
  "description": "Peukelaotis/Kaspatyros? was an ancient city in Gandhāra location along the trade route connecting Bactria to India.",
  "bbox": [
    71.616854,
    34.143959,
    71.616854,
    34.143959
  ],
  "reprPoint": [
    71.616854,
    34.143959
  ],
  "names": [
    "Peukelaotis",
    "Kaspatyros",
    "Kaspeira",
    "Spatura",
    "Peucolitae"
  ],
  "features": [
    {
      "geometry": {
        "type": "Point",
        "coordinates": [
          71.616854,
          34.143959
        ]
      },
      "id": "darmc-location-24172",
      "type": "Feature",
      "properties": {
        "description": "5M scale point location",
        "location_precision": "precise",
        "title": "DARMC location 24172",
        "link": "http://pleiades.stoa.org/places/59993/darmc-location-24172"
      }
    }
  ]
}