{
  "type": "FeatureCollection",
  "title": "Sinuri, T.",
  "id": "599936",
  "bbox": [
    27.924663,
    37.266085,
    27.924663,
    37.266085
  ],
  "description": "An ancient place, cited: BAtlas 61 F3 Sinuri, T.",
  "names": [
    "Sinuri, T."
  ],
  "features": [
    {
      "type": "Feature",
      "geometry": {
        "type": "Point",
        "coordinates": [
          27.924663,
          37.266085
        ]
      },
      "properties": {
        "description": "representative point"
      }
    },
    {
      "geometry": {
        "type": "Point",
        "coordinates": [
          27.924663,
          37.266085
        ]
      },
      "id": "darmc-location-16195",
      "type": "Feature",
      "properties": {
        "description": "500K scale point location",
        "location_precision": "precise",
        "title": "DARMC location 16195",
        "link": "http://pleiades.stoa.org/places/599936/darmc-location-16195"
      }
    }
  ]
}