{
  "type": "FeatureCollection",
  "title": "Zeus Melosios, T.",
  "id": "600002",
  "bbox": [
    25.518719,
    37.047029,
    25.518719,
    37.047029
  ],
  "description": "An ancient place, cited: BAtlas 61 B3 Zeus Melosios, T.",
  "connectsWith": [
    "599822"
  ],
  "names": [
    "Zeus Melosios, T."
  ],
  "features": [
    {
      "type": "Feature",
      "geometry": {
        "type": "Point",
        "coordinates": [
          25.518719,
          37.047029
        ]
      },
      "properties": {
        "description": "representative point"
      }
    },
    {
      "geometry": {
        "type": "Point",
        "coordinates": [
          25.518719,
          37.047029
        ]
      },
      "id": "darmc-location-15707",
      "type": "Feature",
      "properties": {
        "description": "500K scale point location",
        "location_precision": "precise",
        "title": "DARMC location 15707",
        "link": "http://pleiades.stoa.org/places/600002/darmc-location-15707"
      }
    }
  ]
}