{
  "type": "FeatureCollection",
  "title": "Puṇḍranagara",
  "id": "60011",
  "description": "An ancient place, cited: BAtlas 6 F5 Puṇḍranagara",
  "bbox": [
    89.371189,
    24.870868,
    89.371189,
    24.870868
  ],
  "reprPoint": [
    89.371189,
    24.870868
  ],
  "names": [
    "Puṇḍranagara"
  ],
  "features": [
    {
      "geometry": {
        "type": "Point",
        "coordinates": [
          89.371189,
          24.870868
        ]
      },
      "id": "darmc-location-13472",
      "type": "Feature",
      "properties": {
        "description": "5M scale point location",
        "location_precision": "precise",
        "title": "DARMC location 13472",
        "link": "http://pleiades.stoa.org/places/60011/darmc-location-13472"
      }
    }
  ]
}