{
  "type": "FeatureCollection",
  "title": "Rhappha?",
  "id": "60018",
  "description": "An ancient place, cited: BAtlas 6 E4 Rhappha?",
  "bbox": [
    84.743581,
    26.045295,
    84.743581,
    26.045295
  ],
  "reprPoint": [
    84.743581,
    26.045295
  ],
  "names": [
    "Rhappha"
  ],
  "features": [
    {
      "geometry": {
        "type": "Point",
        "coordinates": [
          84.743581,
          26.045295
        ]
      },
      "id": "darmc-location-14495",
      "type": "Feature",
      "properties": {
        "description": "5M scale point location",
        "location_precision": "precise",
        "title": "DARMC location 14495",
        "link": "http://pleiades.stoa.org/places/60018/darmc-location-14495"
      }
    }
  ]
}