{
  "type": "FeatureCollection",
  "title": "Taxila",
  "id": "60083",
  "description": "An ancient city with the ruins of the Gandhāran city of Takṣaśilā, an important Hindu and Buddhist center. (cited: BAtlas 6 C3 Taxila)",
  "bbox": [
    72.815207,
    33.745685,
    72.815207,
    33.745685
  ],
  "reprPoint": [
    72.815207,
    33.745685
  ],
  "names": [
    "Taxila",
    "Taxilae"
  ],
  "features": [
    {
      "geometry": {
        "type": "Point",
        "coordinates": [
          72.815207,
          33.745685
        ]
      },
      "id": "darmc-location-3589",
      "type": "Feature",
      "properties": {
        "description": "5M scale point location",
        "location_precision": "precise",
        "title": "DARMC location 3589",
        "link": "http://pleiades.stoa.org/places/60083/darmc-location-3589"
      }
    }
  ]
}