{
  "type": "FeatureCollection",
  "title": "Vidiśā",
  "id": "60099",
  "description": "An ancient place, cited: BAtlas 6 D5 Vidiśā",
  "bbox": [
    77.814463,
    23.523122,
    77.814463,
    23.523122
  ],
  "reprPoint": [
    77.814463,
    23.523122
  ],
  "names": [
    "Vidiśā"
  ],
  "features": [
    {
      "geometry": {
        "type": "Point",
        "coordinates": [
          77.814463,
          23.523122
        ]
      },
      "id": "darmc-location-3709",
      "type": "Feature",
      "properties": {
        "description": "5M scale point location",
        "location_precision": "precise",
        "title": "DARMC location 3709",
        "link": "http://pleiades.stoa.org/places/60099/darmc-location-3709"
      }
    }
  ]
}