{
  "type": "FeatureCollection",
  "title": "Caer Llugwy",
  "id": "601039653",
  "description": "A Roman fort located in a bend of the Afon Llugwy near Capel Curig in Conwy, Wales.",
  "bbox": [
    -3.8742,
    53.0976,
    -3.8742,
    53.0976
  ],
  "reprPoint": [
    -3.8742,
    53.0976
  ],
  "features": [
    {
      "geometry": {
        "type": "Point",
        "coordinates": [
          -3.8742,
          53.0976
        ]
      },
      "id": "location-of-caer-llugwy",
      "type": "Feature",
      "properties": {
        "description": "Coordinates after GeoHack.",
        "location_precision": "precise",
        "title": "location of Caer Llugwy",
        "link": "http://pleiades.stoa.org/places/601039653/location-of-caer-llugwy"
      }
    }
  ]
}