{
  "type": "FeatureCollection",
  "title": "Eadgigi",
  "id": "601157335",
  "bbox": [
    46.1031111,
    30.9612814,
    46.104748,
    30.9624389
  ],
  "description": "The shrine/seat of the god Nusku in the Egipar temple at Ur. The Sumerian ceremonial name Eadgigi means \"House of the Counsellor.\"",
  "connectsWith": [
    "912985",
    "100593150"
  ],
  "names": [
    "Eadgigi"
  ],
  "features": [
    {
      "type": "Feature",
      "geometry": {
        "type": "Point",
        "coordinates": [
          46.1042839449,
          30.9617193234
        ]
      },
      "properties": {
        "description": "representative point"
      }
    }
  ]
}