{
  "type": "FeatureCollection",
  "title": "Monumental complex of Sant'Ilario a Port' Aurea",
  "id": "603993784",
  "bbox": [
    14.781161,
    41.130437,
    14.781161,
    41.130437
  ],
  "description": "An architectural complex associated with the nearby Longobard church of Sant'Ilario. The complex included a monastery and is built atop Roman Imperial remains.",
  "connectsWith": [
    "432721"
  ],
  "features": [
    {
      "type": "Feature",
      "geometry": {
        "type": "Point",
        "coordinates": [
          14.781161,
          41.130437
        ]
      },
      "properties": {
        "description": "representative point"
      }
    }
  ]
}