{
  "type": "FeatureCollection",
  "title": "Nergal Gate",
  "id": "605179374",
  "bbox": [
    43.1477283,
    36.3711319,
    43.1477283,
    36.3711319
  ],
  "description": "The northern city wall of Nineveh had three gates: the Nergal Gate was middle gate. The Neo-Assyrian king Sennacherib constructed it and gave it the Akkadian ceremonial names Erra-mušamqit-ayyābī (\"The God Erra Is the One Who Cuts Down Enemies\") and Erra-šāgiš-zāmânīya (\"The God Erra Is the One Who Cuts Down My Enemies\").\r\n",
  "connectsWith": [
    "874621",
    "882947620",
    "945930916"
  ],
  "names": [
    "abul Nergal",
    "Nergal Gate",
    "Erra-mušamqit-ayyābī",
    "Erra-šāgiš-zāmânīya"
  ],
  "features": [
    {
      "type": "Feature",
      "geometry": {
        "type": "Point",
        "coordinates": [
          43.1477283,
          36.3711319
        ]
      },
      "properties": {
        "description": "representative point"
      }
    },
    {
      "geometry": {
        "type": "Point",
        "coordinates": [
          43.1477283,
          36.3711319
        ]
      },
      "id": "osm-location-of-the-nergal-gate",
      "type": "Feature",
      "properties": {
        "description": "Location based on OpenStreetMap",
        "location_precision": "precise",
        "title": "OSM Location of the Nergal Gate",
        "link": "http://pleiades.stoa.org/places/605179374/osm-location-of-the-nergal-gate"
      }
    }
  ]
}