{
  "type": "FeatureCollection",
  "title": "Roman theater at Libarna",
  "id": "608454005",
  "bbox": [
    8.8649183,
    44.7071097,
    8.8649183,
    44.7071097
  ],
  "description": "The Roman theater at Libarna dates to the first century.",
  "connectsWith": [
    "383694"
  ],
  "features": [
    {
      "type": "Feature",
      "geometry": {
        "type": "Point",
        "coordinates": [
          8.8649183,
          44.7071097
        ]
      },
      "properties": {
        "description": "representative point"
      }
    },
    {
      "geometry": {
        "type": "Point",
        "coordinates": [
          8.8649183,
          44.7071097
        ]
      },
      "id": "location-of-roman-theater",
      "type": "Feature",
      "properties": {
        "description": "Location based on OpenStreetMap",
        "location_precision": "precise",
        "title": "OSM location of Roman theater",
        "link": "http://pleiades.stoa.org/places/608454005/location-of-roman-theater"
      }
    }
  ]
}