{
  "type": "FeatureCollection",
  "title": "Toora-Dash",
  "id": "6086187",
  "bbox": [
    92.190904,
    51.734921,
    92.190904,
    51.734921
  ],
  "description": "Archaeological site at the interfleuve of the Yenisei and Khemchik Rivers in Tuva. The site, which flooded by the construction of the Sayano-Shushenskaya power plant in the mid-1980s, contained artifacts from the Neolithic through the Medieval periods.",
  "names": [
    "Toora-Dash"
  ],
  "features": [
    {
      "type": "Feature",
      "geometry": {
        "type": "Point",
        "coordinates": [
          92.190904,
          51.734921
        ]
      },
      "properties": {
        "description": "representative point"
      }
    },
    {
      "geometry": {
        "type": "Point",
        "coordinates": [
          92.190904,
          51.734921
        ]
      },
      "id": "google-earth-location-of-the-toora-dash-site",
      "type": "Feature",
      "properties": {
        "description": "Point representing the approximate Google Earth location of the Toora-Dash site, after Semenov 2018.",
        "location_precision": "precise",
        "title": "Google Earth location of the Toora-Dash site",
        "link": "http://pleiades.stoa.org/places/6086187/google-earth-location-of-the-toora-dash-site"
      }
    }
  ]
}