{
  "type": "FeatureCollection",
  "title": "Bagis",
  "id": "609336",
  "description": "An ancient place, cited: BAtlas 62 B4 Bagis",
  "bbox": [
    29.157916,
    38.6495284,
    29.1637767,
    38.665537
  ],
  "reprPoint": [
    29.16084635,
    38.6575327
  ],
  "names": [
    "Bagis"
  ],
  "features": [
    {
      "geometry": {
        "type": "Point",
        "coordinates": [
          29.1637767,
          38.6495284
        ]
      },
      "id": "dare-location",
      "type": "Feature",
      "properties": {
        "description": "Representative point location, village precision",
        "location_precision": "precise",
        "title": "DARE Location",
        "link": "http://pleiades.stoa.org/places/609336/dare-location"
      }
    },
    {
      "geometry": {
        "type": "Point",
        "coordinates": [
          29.157916,
          38.665537
        ]
      },
      "id": "darmc-location-11623",
      "type": "Feature",
      "properties": {
        "description": "500K scale point location",
        "location_precision": "precise",
        "title": "DARMC location 11623",
        "link": "http://pleiades.stoa.org/places/609336/darmc-location-11623"
      }
    }
  ]
}