{
  "type": "FeatureCollection",
  "title": "Hasanlar",
  "id": "609399",
  "description": "An ancient place, cited: BAtlas 62 B3 Hasanlar",
  "bbox": [
    29.181245,
    39.257153,
    29.181245,
    39.257153
  ],
  "reprPoint": [
    29.181245,
    39.257153
  ],
  "features": [
    {
      "geometry": {
        "type": "Point",
        "coordinates": [
          29.181245,
          39.257153
        ]
      },
      "id": "darmc-location-12677",
      "type": "Feature",
      "properties": {
        "description": "500K scale point location",
        "location_precision": "precise",
        "title": "DARMC location 12677",
        "link": "http://pleiades.stoa.org/places/609399/darmc-location-12677"
      }
    }
  ]
}