{
  "type": "FeatureCollection",
  "title": "Aragokome",
  "id": "609317",
  "description": "An ancient place, cited: BAtlas 62 D3 Aragokome",
  "bbox": [
    30.169512,
    39.071967,
    30.169512,
    39.071967
  ],
  "reprPoint": [
    30.169512,
    39.071967
  ],
  "names": [
    "Aragokome"
  ],
  "features": [
    {
      "geometry": {
        "type": "Point",
        "coordinates": [
          30.169512,
          39.071967
        ]
      },
      "id": "darmc-location-11458",
      "type": "Feature",
      "properties": {
        "description": "500K scale point location",
        "location_precision": "precise",
        "title": "DARMC location 11458",
        "link": "http://pleiades.stoa.org/places/609317/darmc-location-11458"
      }
    }
  ]
}