{
  "type": "FeatureCollection",
  "title": "Derbent",
  "id": "609358",
  "description": "An ancient place, cited: BAtlas 62 F4 Derbent",
  "bbox": [
    31.022253,
    38.928129,
    31.022253,
    38.928129
  ],
  "reprPoint": [
    31.022253,
    38.928129
  ],
  "features": [
    {
      "geometry": {
        "type": "Point",
        "coordinates": [
          31.022253,
          38.928129
        ]
      },
      "id": "darmc-location-12182",
      "type": "Feature",
      "properties": {
        "description": "500K scale point location",
        "location_precision": "precise",
        "title": "DARMC location 12182",
        "link": "http://pleiades.stoa.org/places/609358/darmc-location-12182"
      }
    }
  ]
}