{
  "type": "FeatureCollection",
  "title": "Eibeos",
  "id": "609370",
  "description": "An ancient place, cited: BAtlas 62 C4 Eibeos",
  "bbox": [
    29.702241,
    38.572242,
    29.724323,
    38.574083
  ],
  "reprPoint": [
    29.713282,
    38.5731625
  ],
  "names": [
    "Eibeos"
  ],
  "features": [
    {
      "geometry": {
        "type": "Point",
        "coordinates": [
          29.724323,
          38.574083
        ]
      },
      "id": "darmc-location-12299",
      "type": "Feature",
      "properties": {
        "description": "500K scale point location",
        "location_precision": "precise",
        "title": "DARMC location 12299",
        "link": "http://pleiades.stoa.org/places/609370/darmc-location-12299"
      }
    },
    {
      "geometry": {
        "type": "Point",
        "coordinates": [
          29.702241,
          38.572242
        ]
      },
      "id": "darmc-location-11824",
      "type": "Feature",
      "properties": {
        "description": "TIB point location",
        "location_precision": "precise",
        "title": "DARMC location 11824",
        "link": "http://pleiades.stoa.org/places/609370/darmc-location-11824"
      }
    }
  ]
}