{
  "type": "FeatureCollection",
  "title": "Aquae Ger(...)",
  "id": "609316",
  "bbox": [
    30.439775,
    38.81864,
    30.439775,
    38.81864
  ],
  "description": "An ancient place, cited: BAtlas 62 D4 Aquae Ger(...)",
  "names": [
    "Aquae Ger(...)"
  ],
  "features": [
    {
      "type": "Feature",
      "geometry": {
        "type": "Point",
        "coordinates": [
          30.439775,
          38.81864
        ]
      },
      "properties": {
        "description": "representative point"
      }
    },
    {
      "geometry": {
        "type": "Point",
        "coordinates": [
          30.439775,
          38.81864
        ]
      },
      "id": "darmc-location-33488",
      "type": "Feature",
      "properties": {
        "description": "representative point location digitized from the Barrington Atlas of the Greek and Roman World by the Digital Atlas of Roman and Medieval Civilizations project at Harvard University.",
        "location_precision": "precise",
        "title": "DARMC location 33488",
        "link": "http://pleiades.stoa.org/places/609316/darmc-location-33488"
      }
    }
  ]
}