{
  "type": "FeatureCollection",
  "title": "Cybele, T.",
  "id": "609353",
  "description": "An ancient place, cited: BAtlas 62 B2 Cybele, T.",
  "bbox": [
    29.385419,
    39.592474,
    29.385419,
    39.592474
  ],
  "reprPoint": [
    29.385419,
    39.592474
  ],
  "names": [
    "Cybele, T."
  ],
  "features": [
    {
      "geometry": {
        "type": "Point",
        "coordinates": [
          29.385419,
          39.592474
        ]
      },
      "id": "darmc-location-6611",
      "type": "Feature",
      "properties": {
        "description": "500K scale point location",
        "location_precision": "precise",
        "title": "DARMC location 6611",
        "link": "http://pleiades.stoa.org/places/609353/darmc-location-6611"
      }
    }
  ]
}