{
  "type": "FeatureCollection",
  "title": "Gelinkaya",
  "id": "609386",
  "description": "An ancient place, cited: BAtlas 62 C3 Gelinkaya",
  "bbox": [
    29.981421,
    39.331397,
    29.981421,
    39.331397
  ],
  "reprPoint": [
    29.981421,
    39.331397
  ],
  "features": [
    {
      "geometry": {
        "type": "Point",
        "coordinates": [
          29.981421,
          39.331397
        ]
      },
      "id": "darmc-location-7273",
      "type": "Feature",
      "properties": {
        "description": "500K scale point location",
        "location_precision": "precise",
        "title": "DARMC location 7273",
        "link": "http://pleiades.stoa.org/places/609386/darmc-location-7273"
      }
    }
  ]
}