{
  "type": "FeatureCollection",
  "title": "Ghaziri",
  "id": "609389",
  "bbox": [
    30.885211,
    38.233389,
    30.885211,
    38.233389
  ],
  "description": "An ancient place, cited: BAtlas 62 E5 Ghaziri",
  "features": [
    {
      "type": "Feature",
      "geometry": {
        "type": "Point",
        "coordinates": [
          30.885211,
          38.233389
        ]
      },
      "properties": {
        "description": "representative point"
      }
    },
    {
      "geometry": {
        "type": "Point",
        "coordinates": [
          30.885211,
          38.233389
        ]
      },
      "id": "darmc-location-15978",
      "type": "Feature",
      "properties": {
        "description": "500K scale point location",
        "location_precision": "precise",
        "title": "DARMC location 15978",
        "link": "http://pleiades.stoa.org/places/609389/darmc-location-15978"
      }
    }
  ]
}