{
  "type": "FeatureCollection",
  "title": "Ilıca",
  "id": "609414",
  "description": "An ancient place, cited: BAtlas 62 D3 Ilıca",
  "bbox": [
    30.018926,
    39.48644,
    30.018926,
    39.48644
  ],
  "reprPoint": [
    30.018926,
    39.48644
  ],
  "features": [
    {
      "geometry": {
        "type": "Point",
        "coordinates": [
          30.018926,
          39.48644
        ]
      },
      "id": "darmc-location-5223",
      "type": "Feature",
      "properties": {
        "description": "500K scale point location",
        "location_precision": "precise",
        "title": "DARMC location 5223",
        "link": "http://pleiades.stoa.org/places/609414/darmc-location-5223"
      }
    }
  ]
}