{
  "type": "FeatureCollection",
  "title": "Fufidianum",
  "id": "609478608",
  "bbox": [
    13.609876,
    41.648422,
    13.609876,
    41.648422
  ],
  "description": "The name of an estate near Arpinum that once belonged to Q. Tullius Cicero.",
  "connectsWith": [
    "432700"
  ],
  "names": [
    "Fufidianum"
  ],
  "features": [
    {
      "type": "Feature",
      "geometry": {
        "type": "Point",
        "coordinates": [
          13.609876,
          41.648422
        ]
      },
      "properties": {
        "description": "representative point"
      }
    }
  ]
}