{
  "type": "FeatureCollection",
  "title": "Katakekaumene",
  "id": "609427",
  "bbox": [
    28.52,
    38.577222,
    28.52,
    38.577222
  ],
  "description": "An area of western Asia Minor characterized by its ashy soil and volcanic rocks.",
  "names": [
    "Katakekaumene",
    "Arima",
    "Maionia"
  ],
  "features": [
    {
      "type": "Feature",
      "geometry": {
        "type": "Point",
        "coordinates": [
          28.52,
          38.577222
        ]
      },
      "properties": {
        "description": "representative point"
      }
    },
    {
      "geometry": {
        "type": "Point",
        "coordinates": [
          28.52,
          38.577222
        ]
      },
      "id": "geohack-location-of-katakekaumene",
      "type": "Feature",
      "properties": {
        "description": "Coordinates following GeoHack.",
        "location_precision": "precise",
        "title": "GeoHack location of Katakekaumene",
        "link": "http://pleiades.stoa.org/places/609427/geohack-location-of-katakekaumene"
      }
    }
  ]
}