{
  "type": "FeatureCollection",
  "title": "*Kaualena",
  "id": "609428",
  "bbox": [
    29.384641,
    38.596028,
    29.384641,
    38.596028
  ],
  "description": "An ancient place, cited: BAtlas 62 B4 *Kaualena",
  "names": [
    "Kaualena"
  ],
  "features": [
    {
      "type": "Feature",
      "geometry": {
        "type": "Point",
        "coordinates": [
          29.384641,
          38.596028
        ]
      },
      "properties": {
        "description": "representative point"
      }
    },
    {
      "geometry": {
        "type": "Point",
        "coordinates": [
          29.384641,
          38.596028
        ]
      },
      "id": "darmc-location-13070",
      "type": "Feature",
      "properties": {
        "description": "500K scale point location",
        "location_precision": "precise",
        "title": "DARMC location 13070",
        "link": "http://pleiades.stoa.org/places/609428/darmc-location-13070"
      }
    }
  ]
}