{
  "type": "FeatureCollection",
  "title": "Penkalas fl.",
  "id": "609496",
  "description": "An ancient place, cited: BAtlas 62 C3 Penkalas fl.",
  "bbox": [
    29.5859461,
    39.1758167,
    29.5859461,
    39.1758167
  ],
  "reprPoint": [
    29.5859461,
    39.1758167
  ],
  "names": [
    "Penkalas"
  ],
  "features": [
    {
      "geometry": {
        "type": "Point",
        "coordinates": [
          29.5859461,
          39.1758167
        ]
      },
      "id": "location-of-Penkalas-fl",
      "type": "Feature",
      "properties": {
        "description": "Location based on OpenStreetMap",
        "location_precision": "precise",
        "title": "location of Penkalas fl.",
        "link": "http://pleiades.stoa.org/places/609496/location-of-Penkalas-fl"
      }
    }
  ]
}