{
  "type": "FeatureCollection",
  "title": "Klaneos?",
  "id": "609435",
  "bbox": [
    31.834923,
    38.623418,
    31.834923,
    38.623418
  ],
  "description": "An ancient place, cited: BAtlas 62 G4 Klaneos?",
  "names": [
    "Klaneos"
  ],
  "features": [
    {
      "type": "Feature",
      "geometry": {
        "type": "Point",
        "coordinates": [
          31.834923,
          38.623418
        ]
      },
      "properties": {
        "description": "representative point"
      }
    },
    {
      "geometry": {
        "type": "Point",
        "coordinates": [
          31.834923,
          38.623418
        ]
      },
      "id": "darmc-location-1262",
      "type": "Feature",
      "properties": {
        "description": "TIB point location",
        "location_precision": "precise",
        "title": "DARMC location 1262",
        "link": "http://pleiades.stoa.org/places/609435/darmc-location-1262"
      }
    }
  ]
}