{
  "type": "FeatureCollection",
  "title": "Nais",
  "id": "609483",
  "bbox": [
    29.211402,
    38.427036,
    29.211402,
    38.427036
  ],
  "description": "An ancient place, cited: BAtlas 62 B5 Nais",
  "names": [
    "Nais"
  ],
  "features": [
    {
      "type": "Feature",
      "geometry": {
        "type": "Point",
        "coordinates": [
          29.211402,
          38.427036
        ]
      },
      "properties": {
        "description": "representative point"
      }
    },
    {
      "geometry": {
        "type": "Point",
        "coordinates": [
          29.211402,
          38.427036
        ]
      },
      "id": "darmc-location-13862",
      "type": "Feature",
      "properties": {
        "description": "500K scale point location",
        "location_precision": "precise",
        "title": "DARMC location 13862",
        "link": "http://pleiades.stoa.org/places/609483/darmc-location-13862"
      }
    }
  ]
}