{
  "type": "FeatureCollection",
  "title": "Meter Arezastis",
  "id": "609465",
  "bbox": [
    30.712999,
    39.218213,
    30.712999,
    39.218213
  ],
  "description": "An ancient place, cited: BAtlas 62 E3 Meter Arezastis",
  "names": [
    "Meter Arezastis"
  ],
  "features": [
    {
      "type": "Feature",
      "geometry": {
        "type": "Point",
        "coordinates": [
          30.712999,
          39.218213
        ]
      },
      "properties": {
        "description": "representative point"
      }
    },
    {
      "geometry": {
        "type": "Point",
        "coordinates": [
          30.712999,
          39.218213
        ]
      },
      "id": "darmc-location-16086",
      "type": "Feature",
      "properties": {
        "description": "500K scale point location",
        "location_precision": "precise",
        "title": "DARMC location 16086",
        "link": "http://pleiades.stoa.org/places/609465/darmc-location-16086"
      }
    }
  ]
}