{
  "type": "FeatureCollection",
  "title": "*Karmena",
  "id": "609424",
  "description": "An ancient place, cited: BAtlas 62 E5 *Karmena",
  "bbox": [
    30.741353,
    38.325884,
    30.741353,
    38.325884
  ],
  "reprPoint": [
    30.741353,
    38.325884
  ],
  "names": [
    "Karmena"
  ],
  "features": [
    {
      "geometry": {
        "type": "Point",
        "coordinates": [
          30.741353,
          38.325884
        ]
      },
      "id": "darmc-location-13025",
      "type": "Feature",
      "properties": {
        "description": "500K scale point location",
        "location_precision": "precise",
        "title": "DARMC location 13025",
        "link": "http://pleiades.stoa.org/places/609424/darmc-location-13025"
      }
    }
  ]
}