{
  "type": "FeatureCollection",
  "title": "Kalabak",
  "id": "609422",
  "description": "An ancient place, cited: BAtlas 62 D2 Kalabak",
  "bbox": [
    30.42012,
    39.534331,
    30.42012,
    39.534331
  ],
  "reprPoint": [
    30.42012,
    39.534331
  ],
  "features": [
    {
      "geometry": {
        "type": "Point",
        "coordinates": [
          30.42012,
          39.534331
        ]
      },
      "id": "darmc-location-16019",
      "type": "Feature",
      "properties": {
        "description": "500K scale point location",
        "location_precision": "precise",
        "title": "DARMC location 16019",
        "link": "http://pleiades.stoa.org/places/609422/darmc-location-16019"
      }
    }
  ]
}