{
  "type": "FeatureCollection",
  "title": "*Soa",
  "id": "609532",
  "description": "An ancient place, cited: BAtlas 62 D3 *Soa",
  "bbox": [
    30.216813,
    39.076771,
    30.216813,
    39.076771
  ],
  "reprPoint": [
    30.216813,
    39.076771
  ],
  "names": [
    "Soa"
  ],
  "features": [
    {
      "geometry": {
        "type": "Point",
        "coordinates": [
          30.216813,
          39.076771
        ]
      },
      "id": "darmc-location-560",
      "type": "Feature",
      "properties": {
        "description": "TIB point location",
        "location_precision": "precise",
        "title": "DARMC location 560",
        "link": "http://pleiades.stoa.org/places/609532/darmc-location-560"
      }
    }
  ]
}