{
  "type": "FeatureCollection",
  "title": "Türkmen Baba",
  "id": "609562",
  "description": "An ancient place, cited: BAtlas 62 D3 Türkmen Baba",
  "bbox": [
    30.406289,
    39.432407,
    30.406289,
    39.432407
  ],
  "reprPoint": [
    30.406289,
    39.432407
  ],
  "features": [
    {
      "geometry": {
        "type": "Point",
        "coordinates": [
          30.406289,
          39.432407
        ]
      },
      "id": "darmc-location-4648",
      "type": "Feature",
      "properties": {
        "description": "500K scale point location",
        "location_precision": "precise",
        "title": "DARMC location 4648",
        "link": "http://pleiades.stoa.org/places/609562/darmc-location-4648"
      }
    }
  ]
}