{
  "type": "FeatureCollection",
  "title": "Tabala",
  "id": "609540",
  "bbox": [
    28.803373,
    38.612168,
    28.803373,
    38.612168
  ],
  "description": "An ancient place, cited: BAtlas 62 A4 Tabala",
  "names": [
    "Tabala"
  ],
  "features": [
    {
      "type": "Feature",
      "geometry": {
        "type": "Point",
        "coordinates": [
          28.803373,
          38.612168
        ]
      },
      "properties": {
        "description": "representative point"
      }
    },
    {
      "geometry": {
        "type": "Point",
        "coordinates": [
          28.803373,
          38.612168
        ]
      },
      "id": "darmc-location-14966",
      "type": "Feature",
      "properties": {
        "description": "500K scale point location",
        "location_precision": "precise",
        "title": "DARMC location 14966",
        "link": "http://pleiades.stoa.org/places/609540/darmc-location-14966"
      }
    }
  ]
}