{
  "type": "FeatureCollection",
  "title": "*Zemmeana",
  "id": "609573",
  "description": "An ancient place, cited: BAtlas 62 D3 *Zemmeana",
  "bbox": [
    30.0826,
    39.108401,
    30.0826,
    39.108401
  ],
  "reprPoint": [
    30.0826,
    39.108401
  ],
  "names": [
    "Zemmeana"
  ],
  "features": [
    {
      "geometry": {
        "type": "Point",
        "coordinates": [
          30.0826,
          39.108401
        ]
      },
      "id": "darmc-location-15522",
      "type": "Feature",
      "properties": {
        "description": "500K scale point location",
        "location_precision": "precise",
        "title": "DARMC location 15522",
        "link": "http://pleiades.stoa.org/places/609573/darmc-location-15522"
      }
    }
  ]
}