{
  "type": "FeatureCollection",
  "title": "Zaferiye",
  "id": "609572",
  "description": "An ancient place, cited: BAtlas 62 H5 Zaferiye",
  "bbox": [
    32.040543,
    38.299133,
    32.040543,
    38.299133
  ],
  "reprPoint": [
    32.040543,
    38.299133
  ],
  "features": [
    {
      "geometry": {
        "type": "Point",
        "coordinates": [
          32.040543,
          38.299133
        ]
      },
      "id": "darmc-location-8459",
      "type": "Feature",
      "properties": {
        "description": "500K scale point location",
        "location_precision": "precise",
        "title": "DARMC location 8459",
        "link": "http://pleiades.stoa.org/places/609572/darmc-location-8459"
      }
    }
  ]
}