{
  "type": "FeatureCollection",
  "title": "Zeus Orkamaneites, T.",
  "id": "609588",
  "description": "An ancient place, cited: BAtlas 62 C4 Zeus Orkamaneites, T.",
  "bbox": [
    29.747816,
    38.714726,
    29.747816,
    38.714726
  ],
  "reprPoint": [
    29.747816,
    38.714726
  ],
  "names": [
    "Zeus Orkamaneites, T."
  ],
  "features": [
    {
      "geometry": {
        "type": "Point",
        "coordinates": [
          29.747816,
          38.714726
        ]
      },
      "id": "darmc-location-16283",
      "type": "Feature",
      "properties": {
        "description": "500K scale point location",
        "location_precision": "precise",
        "title": "DARMC location 16283",
        "link": "http://pleiades.stoa.org/places/609588/darmc-location-16283"
      }
    }
  ]
}