{
  "type": "FeatureCollection",
  "title": "Zeus Thimenos, T.",
  "id": "609592",
  "description": "An ancient place, cited: BAtlas 62 A3 Zeus Thimenos, T.",
  "bbox": [
    28.573658,
    39.403473,
    28.573658,
    39.403473
  ],
  "reprPoint": [
    28.573658,
    39.403473
  ],
  "names": [
    "Zeus Thimenos, T."
  ],
  "features": [
    {
      "geometry": {
        "type": "Point",
        "coordinates": [
          28.573658,
          39.403473
        ]
      },
      "id": "darmc-location-16285",
      "type": "Feature",
      "properties": {
        "description": "500K scale point location",
        "location_precision": "precise",
        "title": "DARMC location 16285",
        "link": "http://pleiades.stoa.org/places/609592/darmc-location-16285"
      }
    }
  ]
}