{
  "type": "FeatureCollection",
  "title": "Zeus Kersoullos, T.",
  "id": "609586",
  "description": "An ancient place, cited: BAtlas 62 B2 Zeus Kersoullos, T.",
  "bbox": [
    29.20155,
    39.874255,
    29.20155,
    39.874255
  ],
  "reprPoint": [
    29.20155,
    39.874255
  ],
  "names": [
    "Zeus Kersoullos, T."
  ],
  "features": [
    {
      "geometry": {
        "type": "Point",
        "coordinates": [
          29.20155,
          39.874255
        ]
      },
      "id": "darmc-location-16278",
      "type": "Feature",
      "properties": {
        "description": "500K scale point location",
        "location_precision": "precise",
        "title": "DARMC location 16278",
        "link": "http://pleiades.stoa.org/places/609586/darmc-location-16278"
      }
    }
  ]
}