{
  "type": "FeatureCollection",
  "title": "Tomb of the Arati",
  "id": "611508454",
  "bbox": [
    12.45531,
    42.3427048,
    12.45531,
    42.3427048
  ],
  "description": "A Faliscan tomb located near Borghetto, Civita Castellana (Viterbo).",
  "features": [
    {
      "type": "Feature",
      "geometry": {
        "type": "Point",
        "coordinates": [
          12.45531,
          42.3427048
        ]
      },
      "properties": {
        "description": "representative point"
      }
    },
    {
      "geometry": {
        "type": "Point",
        "coordinates": [
          12.45531,
          42.3427048
        ]
      },
      "id": "osm-location-of-borghetto",
      "type": "Feature",
      "properties": {
        "description": "Location based on OpenStreetMap",
        "location_precision": "precise",
        "title": "OSM location of Borghetto",
        "link": "http://pleiades.stoa.org/places/611508454/osm-location-of-borghetto"
      }
    }
  ]
}