{
  "type": "FeatureCollection",
  "title": "25",
  "id": "612331",
  "bbox": [
    30.599523,
    38.100219,
    30.599523,
    38.100219
  ],
  "description": "An ancient place, cited: BAtlas 62 E5 no. 25 (E Yassıören)",
  "features": [
    {
      "type": "Feature",
      "geometry": {
        "type": "Point",
        "coordinates": [
          30.599523,
          38.100219
        ]
      },
      "properties": {
        "description": "representative point"
      }
    },
    {
      "geometry": {
        "type": "Point",
        "coordinates": [
          30.599523,
          38.100219
        ]
      },
      "id": "darmc-location-33498",
      "type": "Feature",
      "properties": {
        "description": "representative point location digitized from the Barrington Atlas of the Greek and Roman World by the Digital Atlas of Roman and Medieval Civilizations project at Harvard University.",
        "location_precision": "precise",
        "title": "DARMC location 33498",
        "link": "http://pleiades.stoa.org/places/612331/darmc-location-33498"
      }
    }
  ]
}