{
  "type": "FeatureCollection",
  "title": "Enirgalana",
  "id": "612591680",
  "bbox": [
    45.61715,
    31.318603,
    45.6402127,
    31.3243321
  ],
  "description": "The cella/shrine of the goddess Ištar in the Eanna temple at Uruk. The Sumerian ceremonial name Enirgalana means \"House of the Prince of Heaven.\"",
  "connectsWith": [
    "996877399",
    "912986"
  ],
  "names": [
    "Enirgalana"
  ],
  "features": [
    {
      "type": "Feature",
      "geometry": {
        "type": "Point",
        "coordinates": [
          45.62868135,
          31.32146755
        ]
      },
      "properties": {
        "description": "representative point"
      }
    }
  ]
}