{
  "type": "FeatureCollection",
  "title": "Syreanos",
  "id": "614844",
  "bbox": [
    30.31044,
    39.386076,
    30.31044,
    39.386076
  ],
  "description": "An ancient sanctuary of Zeus attested in inscriptions found on \"the upland plain of Makas Alan between the [Phrygian] cities of Kotiaeion (Kiitahya) and Nakoleia (Seyitgazi)\" in modern Turkey (Drew-Bear). Its precise location cannot be determined today.",
  "connectsWith": [
    "609371"
  ],
  "names": [
    "Syreanos"
  ],
  "features": [
    {
      "type": "Feature",
      "geometry": {
        "type": "Point",
        "coordinates": [
          30.31044,
          39.386076
        ]
      },
      "properties": {
        "description": "representative point"
      }
    },
    {
      "geometry": null,
      "id": "undetermined",
      "type": "Feature",
      "properties": {
        "description": null,
        "location_precision": "unlocated",
        "title": "Undetermined location",
        "link": "http://pleiades.stoa.org/places/614844/undetermined"
      }
    }
  ]
}