{
  "type": "FeatureCollection",
  "title": "Dibbin",
  "id": "616377777",
  "bbox": [
    45.6611,
    31.8977,
    45.6611,
    31.8977
  ],
  "description": "A settlement mound where a cuneiform brick inscription has been found.",
  "features": [
    {
      "type": "Feature",
      "geometry": {
        "type": "Point",
        "coordinates": [
          45.6611,
          31.8977
        ]
      },
      "properties": {
        "description": "representative point"
      }
    },
    {
      "geometry": {
        "type": "Point",
        "coordinates": [
          45.6611,
          31.8977
        ]
      },
      "id": "cigs-location-of-dibbin",
      "type": "Feature",
      "properties": {
        "description": null,
        "location_precision": "precise",
        "title": "CIGS location of Dibbin",
        "link": "http://pleiades.stoa.org/places/616377777/cigs-location-of-dibbin"
      }
    }
  ]
}