{
  "type": "FeatureCollection",
  "title": "Santa Maria Sopra Minerva",
  "id": "617667450",
  "bbox": [
    12.6148196,
    43.0712617,
    12.6148196,
    43.0712617
  ],
  "description": "A first century B.C. temple dedicated to Minerva by Gneus Caestius and Titus Caesius Priscus, who were two of the Assisi's quattuorviri. The temple was converted to the church of Santa Maria Sopra Minerva in 1539.",
  "connectsWith": [
    "413037"
  ],
  "names": [
    "Temple of Minerva"
  ],
  "features": [
    {
      "type": "Feature",
      "geometry": {
        "type": "Point",
        "coordinates": [
          12.6148196,
          43.0712617
        ]
      },
      "properties": {
        "description": "representative point"
      }
    },
    {
      "geometry": {
        "type": "Point",
        "coordinates": [
          12.6148196,
          43.0712617
        ]
      },
      "id": "osm-location-of-santa-maria-sopra-minerva",
      "type": "Feature",
      "properties": {
        "description": "Location based on OpenStreetMap",
        "location_precision": "precise",
        "title": "OSM location of Santa Maria sopra Minerva",
        "link": "http://pleiades.stoa.org/places/617667450/osm-location-of-santa-maria-sopra-minerva"
      }
    }
  ]
}