{
  "type": "FeatureCollection",
  "title": "Spandaryan",
  "id": "618782675",
  "bbox": [
    44.0205,
    40.668,
    44.0205,
    40.668
  ],
  "description": "Find place for cuneiform inscription.",
  "names": [
    "Spandaryan"
  ],
  "features": [
    {
      "type": "Feature",
      "geometry": {
        "type": "Point",
        "coordinates": [
          44.0205,
          40.668
        ]
      },
      "properties": {
        "description": "representative point"
      }
    },
    {
      "geometry": {
        "type": "Point",
        "coordinates": [
          44.0205,
          40.668
        ]
      },
      "id": "cigs-location-of-spandaryan",
      "type": "Feature",
      "properties": {
        "description": "FInd place for cuneiform inscription.",
        "location_precision": "precise",
        "title": "CIGS location of Spandaryan",
        "link": "http://pleiades.stoa.org/places/618782675/cigs-location-of-spandaryan"
      }
    }
  ]
}