{
  "type": "FeatureCollection",
  "title": "Enehil",
  "id": "619155",
  "description": "An ancient place, cited: BAtlas 63 G4 Enehil",
  "bbox": [
    34.837902,
    38.138357,
    34.837902,
    38.138357
  ],
  "reprPoint": [
    34.837902,
    38.138357
  ],
  "features": [
    {
      "geometry": {
        "type": "Point",
        "coordinates": [
          34.837902,
          38.138357
        ]
      },
      "id": "darmc-location-22347",
      "type": "Feature",
      "properties": {
        "description": "500K scale point location",
        "location_precision": "precise",
        "title": "DARMC location 22347",
        "link": "http://pleiades.stoa.org/places/619155/darmc-location-22347"
      }
    }
  ]
}