{
  "type": "FeatureCollection",
  "title": "Keçikalesi",
  "id": "619183",
  "description": "An ancient place, cited: BAtlas 63 E4 Keçikalesi",
  "bbox": [
    34.097176,
    38.076446,
    34.097176,
    38.076446
  ],
  "reprPoint": [
    34.097176,
    38.076446
  ],
  "features": [
    {
      "geometry": {
        "type": "Point",
        "coordinates": [
          34.097176,
          38.076446
        ]
      },
      "id": "darmc-location-13085",
      "type": "Feature",
      "properties": {
        "description": "500K scale point location",
        "location_precision": "precise",
        "title": "DARMC location 13085",
        "link": "http://pleiades.stoa.org/places/619183/darmc-location-13085"
      }
    }
  ]
}