{
  "type": "FeatureCollection",
  "title": "Ancyra",
  "id": "619103",
  "bbox": [
    32.858128,
    39.943198,
    32.860538,
    39.944387
  ],
  "description": "An ancient settlement and later fortified settlement that served as the seat of the koinon of Galatia and capital of the subsequent Roman province. Modern Ankara in Turkey.",
  "connectsWith": [
    "619161"
  ],
  "names": [
    "Ancyra",
    "Angūriyah",
    "Sebastē Tektosagōn",
    "Angūriya",
    "Anqara",
    "Anqara",
    "Anqīra",
    "Ankara",
    "Anḳara",
    "Ankyra",
    "Ankara Z.A.",
    "Ankūrīye",
    "Ankūriya",
    "Angora",
    "Engürü"
  ],
  "features": [
    {
      "type": "Feature",
      "geometry": {
        "type": "Point",
        "coordinates": [
          32.859333,
          39.9437925
        ]
      },
      "properties": {
        "description": "representative point"
      }
    },
    {
      "geometry": {
        "type": "Point",
        "coordinates": [
          32.860538,
          39.943198
        ]
      },
      "id": "darmc-location-3127",
      "type": "Feature",
      "properties": {
        "description": "500K scale point location",
        "location_precision": "precise",
        "title": "DARMC location 3127",
        "link": "http://pleiades.stoa.org/places/619103/darmc-location-3127"
      }
    },
    {
      "geometry": {
        "type": "Point",
        "coordinates": [
          32.858128,
          39.944387
        ]
      },
      "id": "dare-location",
      "type": "Feature",
      "properties": {
        "description": "Representative point location, site precision",
        "location_precision": "precise",
        "title": "DARE Location",
        "link": "http://pleiades.stoa.org/places/619103/dare-location"
      }
    }
  ]
}