{
  "type": "FeatureCollection",
  "title": "Asiana/Osiena",
  "id": "619117",
  "description": "An ancient place, cited: BAtlas 63 E3 Asiana/Osiena",
  "bbox": [
    34.245217,
    38.634092,
    34.259107,
    38.648123
  ],
  "reprPoint": [
    34.252162,
    38.6411075
  ],
  "names": [
    "Asiana",
    "Osiena"
  ],
  "features": [
    {
      "geometry": {
        "type": "Point",
        "coordinates": [
          34.259107,
          38.634092
        ]
      },
      "id": "darmc-location-1194",
      "type": "Feature",
      "properties": {
        "description": "TIB point location",
        "location_precision": "precise",
        "title": "DARMC location 1194",
        "link": "http://pleiades.stoa.org/places/619117/darmc-location-1194"
      }
    },
    {
      "geometry": {
        "type": "Point",
        "coordinates": [
          34.245217,
          38.648123
        ]
      },
      "id": "darmc-location-9727",
      "type": "Feature",
      "properties": {
        "description": "500K scale point location",
        "location_precision": "precise",
        "title": "DARMC location 9727",
        "link": "http://pleiades.stoa.org/places/619117/darmc-location-9727"
      }
    }
  ]
}