{
  "type": "FeatureCollection",
  "title": "Bulduk",
  "id": "619128",
  "description": "An ancient place, cited: BAtlas 63 B3 Bulduk",
  "bbox": [
    32.755936,
    38.953918,
    32.755936,
    38.953918
  ],
  "reprPoint": [
    32.755936,
    38.953918
  ],
  "features": [
    {
      "geometry": {
        "type": "Point",
        "coordinates": [
          32.755936,
          38.953918
        ]
      },
      "id": "darmc-location-11855",
      "type": "Feature",
      "properties": {
        "description": "500K scale point location",
        "location_precision": "precise",
        "title": "DARMC location 11855",
        "link": "http://pleiades.stoa.org/places/619128/darmc-location-11855"
      }
    }
  ]
}