{
  "type": "FeatureCollection",
  "title": "Doara",
  "id": "619151",
  "description": "An ancient place, cited: BAtlas 63 E4 Doara",
  "bbox": [
    34.368077,
    38.203645,
    34.480601,
    38.214142
  ],
  "reprPoint": [
    34.424339,
    38.2088935
  ],
  "names": [
    "Doara"
  ],
  "features": [
    {
      "geometry": {
        "type": "Point",
        "coordinates": [
          34.480601,
          38.203645
        ]
      },
      "id": "darmc-location-565",
      "type": "Feature",
      "properties": {
        "description": "TIB point location",
        "location_precision": "precise",
        "title": "DARMC location 565",
        "link": "http://pleiades.stoa.org/places/619151/darmc-location-565"
      }
    },
    {
      "geometry": {
        "type": "Point",
        "coordinates": [
          34.368077,
          38.214142
        ]
      },
      "id": "darmc-location-843",
      "type": "Feature",
      "properties": {
        "description": "500K scale point location",
        "location_precision": "precise",
        "title": "DARMC location 843",
        "link": "http://pleiades.stoa.org/places/619151/darmc-location-843"
      }
    }
  ]
}