{
  "type": "FeatureCollection",
  "title": "Ancyra",
  "id": "619103",
  "bbox": [
    32.740601,
    39.943198,
    32.860538,
    40.000895
  ],
  "description": "An ancient place, cited: BAtlas 63 B1 Ancyra",
  "names": [
    "Ancyra",
    "Angūriyah",
    "Sebastē Tektosagōn",
    "Angūriya",
    "Anqara",
    "Anqara",
    "Anqīra",
    "Ankara",
    "Anḳara",
    "Ankyra",
    "Ankara Z.A.",
    "Ankūrīye",
    "Ankūriya",
    "Angora",
    "Engürü"
  ],
  "features": [
    {
      "type": "Feature",
      "geometry": {
        "type": "Point",
        "coordinates": [
          32.8197556667,
          39.9628266667
        ]
      },
      "properties": {
        "description": "representative point"
      }
    },
    {
      "geometry": {
        "type": "Point",
        "coordinates": [
          32.860538,
          39.943198
        ]
      },
      "id": "darmc-location-3127",
      "type": "Feature",
      "properties": {
        "description": "500K scale point location",
        "location_precision": "precise",
        "title": "DARMC location 3127",
        "link": "http://pleiades.stoa.org/places/619103/darmc-location-3127"
      }
    },
    {
      "geometry": {
        "type": "Point",
        "coordinates": [
          32.740601,
          40.000895
        ]
      },
      "id": "darmc-location-13126",
      "type": "Feature",
      "properties": {
        "description": "1M scale point location",
        "location_precision": "precise",
        "title": "DARMC location 13126",
        "link": "http://pleiades.stoa.org/places/619103/darmc-location-13126"
      }
    },
    {
      "geometry": {
        "type": "Point",
        "coordinates": [
          32.858128,
          39.944387
        ]
      },
      "id": "dare-location",
      "type": "Feature",
      "properties": {
        "description": "Representative point location, site precision",
        "location_precision": "precise",
        "title": "DARE Location",
        "link": "http://pleiades.stoa.org/places/619103/dare-location"
      }
    }
  ]
}