{
  "type": "FeatureCollection",
  "title": "Nora/Neroassos",
  "id": "619221",
  "bbox": [
    34.319154,
    38.261877,
    34.430027,
    38.28198
  ],
  "description": "An ancient place, cited: BAtlas 63 E4 Nora/Neroassos",
  "names": [
    "Nora",
    "Neroassos",
    "Nanassos"
  ],
  "features": [
    {
      "type": "Feature",
      "geometry": {
        "type": "Point",
        "coordinates": [
          34.3745905,
          38.2719285
        ]
      },
      "properties": {
        "description": "representative point"
      }
    },
    {
      "geometry": {
        "type": "Point",
        "coordinates": [
          34.430027,
          38.261877
        ]
      },
      "id": "darmc-location-597",
      "type": "Feature",
      "properties": {
        "description": "TIB point location",
        "location_precision": "precise",
        "title": "DARMC location 597",
        "link": "http://pleiades.stoa.org/places/619221/darmc-location-597"
      }
    },
    {
      "geometry": {
        "type": "Point",
        "coordinates": [
          34.319154,
          38.28198
        ]
      },
      "id": "darmc-location-3032",
      "type": "Feature",
      "properties": {
        "description": "500K scale point location",
        "location_precision": "precise",
        "title": "DARMC location 3032",
        "link": "http://pleiades.stoa.org/places/619221/darmc-location-3032"
      }
    }
  ]
}