{
  "type": "FeatureCollection",
  "title": "[Sobesos]",
  "id": "619263",
  "description": "An ancient place, cited: BAtlas 63 F4 [Sobesos]",
  "bbox": [
    34.777148,
    38.470121,
    34.965679,
    38.489879
  ],
  "reprPoint": [
    34.8714135,
    38.48
  ],
  "names": [
    "Sobesos"
  ],
  "features": [
    {
      "geometry": {
        "type": "Point",
        "coordinates": [
          34.965679,
          38.470121
        ]
      },
      "id": "darmc-location-2027",
      "type": "Feature",
      "properties": {
        "description": "TIB point location",
        "location_precision": "precise",
        "title": "DARMC location 2027",
        "link": "http://pleiades.stoa.org/places/619263/darmc-location-2027"
      }
    },
    {
      "geometry": {
        "type": "Point",
        "coordinates": [
          34.777148,
          38.489879
        ]
      },
      "id": "darmc-location-5682",
      "type": "Feature",
      "properties": {
        "description": "500K scale point location",
        "location_precision": "precise",
        "title": "DARMC location 5682",
        "link": "http://pleiades.stoa.org/places/619263/darmc-location-5682"
      }
    }
  ]
}