{
  "type": "FeatureCollection",
  "title": "Zoropassos",
  "id": "619288",
  "description": "An ancient place, cited: BAtlas 63 F3 Zoropassos",
  "bbox": [
    34.5136,
    38.741671,
    34.621707,
    38.752169
  ],
  "reprPoint": [
    34.5676535,
    38.74692
  ],
  "names": [
    "Zoropassos"
  ],
  "features": [
    {
      "geometry": {
        "type": "Point",
        "coordinates": [
          34.621707,
          38.741671
        ]
      },
      "id": "darmc-location-126",
      "type": "Feature",
      "properties": {
        "description": "TIB point location",
        "location_precision": "precise",
        "title": "DARMC location 126",
        "link": "http://pleiades.stoa.org/places/619288/darmc-location-126"
      }
    },
    {
      "geometry": {
        "type": "Point",
        "coordinates": [
          34.5136,
          38.752169
        ]
      },
      "id": "darmc-location-1841",
      "type": "Feature",
      "properties": {
        "description": "500K scale point location",
        "location_precision": "precise",
        "title": "DARMC location 1841",
        "link": "http://pleiades.stoa.org/places/619288/darmc-location-1841"
      }
    }
  ]
}