{
  "type": "FeatureCollection",
  "title": "*Zemruta",
  "id": "619286",
  "bbox": [
    32.961372,
    38.211221,
    32.961372,
    38.211221
  ],
  "description": "An ancient place, cited: BAtlas 63 B4 *Zemruta",
  "names": [
    "Zemruta"
  ],
  "features": [
    {
      "type": "Feature",
      "geometry": {
        "type": "Point",
        "coordinates": [
          32.961372,
          38.211221
        ]
      },
      "properties": {
        "description": "representative point"
      }
    },
    {
      "geometry": {
        "type": "Point",
        "coordinates": [
          32.961372,
          38.211221
        ]
      },
      "id": "darmc-location-10266",
      "type": "Feature",
      "properties": {
        "description": "500K scale point location",
        "location_precision": "precise",
        "title": "DARMC location 10266",
        "link": "http://pleiades.stoa.org/places/619286/darmc-location-10266"
      }
    }
  ]
}