{
  "type": "FeatureCollection",
  "title": "[Tamisos]",
  "id": "619266",
  "description": "An ancient place, cited: BAtlas 63 F3 [Tamisos]",
  "bbox": [
    34.737796,
    38.541716,
    34.737796,
    38.541716
  ],
  "reprPoint": [
    34.737796,
    38.541716
  ],
  "names": [
    "Tamisos"
  ],
  "features": [
    {
      "geometry": {
        "type": "Point",
        "coordinates": [
          34.737796,
          38.541716
        ]
      },
      "id": "darmc-location-25554",
      "type": "Feature",
      "properties": {
        "description": "500K scale point location",
        "location_precision": "precise",
        "title": "DARMC location 25554",
        "link": "http://pleiades.stoa.org/places/619266/darmc-location-25554"
      }
    }
  ]
}