{
  "type": "FeatureCollection",
  "title": "Palace of the Shirvanshahs",
  "id": "619239399",
  "bbox": [
    49.833443,
    40.366149,
    49.833443,
    40.366149
  ],
  "description": "A fifteenth-century palace built by the Shirvanshahs in Baku, Azerbaijan.",
  "connectsWith": [
    "46154574"
  ],
  "features": [
    {
      "type": "Feature",
      "geometry": {
        "type": "Point",
        "coordinates": [
          49.833443,
          40.366149
        ]
      },
      "properties": {
        "description": "representative point"
      }
    },
    {
      "geometry": {
        "type": "Point",
        "coordinates": [
          49.833443,
          40.366149
        ]
      },
      "id": "imagery-location-of-palace-of-the-shirvanshahs",
      "type": "Feature",
      "properties": {
        "description": "Coordinates after GeoHack.",
        "location_precision": "precise",
        "title": "Imagery location of Palace of the Shirvanshahs",
        "link": "http://pleiades.stoa.org/places/619239399/imagery-location-of-palace-of-the-shirvanshahs"
      }
    }
  ]
}