{
  "type": "FeatureCollection",
  "title": "Turkdean",
  "id": "620543181",
  "bbox": [
    -1.8578332,
    51.869519,
    -1.8578332,
    51.869519
  ],
  "description": "Site of a major Roman villa complex in Gloucestershire, active from late second century CE until the end of the fourth century.",
  "names": [
    "Turkdean"
  ],
  "features": [
    {
      "type": "Feature",
      "geometry": {
        "type": "Point",
        "coordinates": [
          -1.8578332,
          51.869519
        ]
      },
      "properties": {
        "description": "representative point"
      }
    },
    {
      "geometry": {
        "type": "Point",
        "coordinates": [
          -1.8578332,
          51.869519
        ]
      },
      "id": "osm-location-of-turkdean-roman-villa",
      "type": "Feature",
      "properties": {
        "description": "Representative location based on OpenStreetMap.",
        "location_precision": "precise",
        "title": "OSM Location of Turkdean Roman Villa",
        "link": "http://pleiades.stoa.org/places/620543181/osm-location-of-turkdean-roman-villa"
      }
    }
  ]
}