{
  "type": "FeatureCollection",
  "title": "Ribadiso Roman bridge",
  "id": "623510547",
  "bbox": [
    -8.1303178,
    42.9308198,
    -8.1303178,
    42.9308198
  ],
  "description": "A Roman bridge located in the Provincia da Coruña, Galicia, Spain.",
  "features": [
    {
      "type": "Feature",
      "geometry": {
        "type": "Point",
        "coordinates": [
          -8.1303178,
          42.9308198
        ]
      },
      "properties": {
        "description": "representative point"
      }
    },
    {
      "geometry": {
        "type": "Point",
        "coordinates": [
          -8.1303178,
          42.9308198
        ]
      },
      "id": "osm-location",
      "type": "Feature",
      "properties": {
        "description": "Representative location based on OpenStreetMap.",
        "location_precision": "precise",
        "title": "OSM location of Puente romano de Ribadiso",
        "link": "http://pleiades.stoa.org/places/623510547/osm-location"
      }
    }
  ]
}