{
  "type": "FeatureCollection",
  "title": "Tapah Farukhābād",
  "id": "625383494",
  "bbox": [
    47.2246,
    32.5873,
    47.2246,
    32.5873
  ],
  "description": "Small town mound in Deh Luran Plain.",
  "names": [
    "Tapah Farukhābād"
  ],
  "features": [
    {
      "type": "Feature",
      "geometry": {
        "type": "Point",
        "coordinates": [
          47.2246,
          32.5873
        ]
      },
      "properties": {
        "description": "representative point"
      }
    },
    {
      "geometry": {
        "type": "Point",
        "coordinates": [
          47.2246,
          32.5873
        ]
      },
      "id": "cigs-location-of-tapah-farukhabad",
      "type": "Feature",
      "properties": {
        "description": null,
        "location_precision": "precise",
        "title": "CIGS location of Tapah Farukhābād",
        "link": "http://pleiades.stoa.org/places/625383494/cigs-location-of-tapah-farukhabad"
      }
    }
  ]
}