{
  "type": "FeatureCollection",
  "title": "Temple of Trajan at Italica",
  "id": "627230788",
  "bbox": [
    -6.044551,
    37.4403044,
    -6.044551,
    37.4403044
  ],
  "description": "A sanctuary dedicated to Trajan in the 'urbs nova' of Italica that flourished under the patronage of Hadrian.",
  "connectsWith": [
    "256231"
  ],
  "features": [
    {
      "type": "Feature",
      "geometry": {
        "type": "Point",
        "coordinates": [
          -6.044551,
          37.4403044
        ]
      },
      "properties": {
        "description": "representative point"
      }
    },
    {
      "geometry": {
        "type": "Point",
        "coordinates": [
          -6.044551,
          37.4403044
        ]
      },
      "id": "location-of-temple-of-trajan",
      "type": "Feature",
      "properties": {
        "description": "Location based on OpenStreetMap",
        "location_precision": "precise",
        "title": "OSM location of Temple of Trajan",
        "link": "http://pleiades.stoa.org/places/627230788/location-of-temple-of-trajan"
      }
    }
  ]
}