{
  "type": "FeatureCollection",
  "title": "Church of the Saviour, Thessaloniki",
  "id": "628342669",
  "bbox": [
    22.95,
    40.63,
    22.95,
    40.63
  ],
  "description": "The Church of the Saviour, Thessaloniki is a fourteenth century Byzantine church.",
  "connectsWith": [
    "491741"
  ],
  "features": [
    {
      "type": "Feature",
      "geometry": {
        "type": "Point",
        "coordinates": [
          22.95,
          40.63
        ]
      },
      "properties": {
        "description": "representative point"
      }
    },
    {
      "geometry": {
        "type": "Point",
        "coordinates": [
          22.95,
          40.63
        ]
      },
      "id": "church-of-christ-saviour",
      "type": "Feature",
      "properties": {
        "description": null,
        "location_precision": "precise",
        "title": "Church of Christ Saviour",
        "link": "http://pleiades.stoa.org/places/628342669/church-of-christ-saviour"
      }
    }
  ]
}