{
  "type": "FeatureCollection",
  "title": "Arabissos/Tripotamos",
  "id": "628925",
  "description": "An ancient place, cited: BAtlas 64 D4 Arabissos/Tripotamos",
  "bbox": [
    36.911428,
    38.244033,
    36.911918,
    38.247993
  ],
  "reprPoint": [
    36.911673,
    38.246013
  ],
  "names": [
    "Arabissos",
    "Tripotamos"
  ],
  "features": [
    {
      "geometry": {
        "type": "Point",
        "coordinates": [
          36.911918,
          38.244033
        ]
      },
      "id": "darmc-location-655",
      "type": "Feature",
      "properties": {
        "description": "TIB point location",
        "location_precision": "precise",
        "title": "DARMC location 655",
        "link": "http://pleiades.stoa.org/places/628925/darmc-location-655"
      }
    },
    {
      "geometry": {
        "type": "Point",
        "coordinates": [
          36.911428,
          38.247993
        ]
      },
      "id": "darmc-location-3296",
      "type": "Feature",
      "properties": {
        "description": "500K scale point location",
        "location_precision": "precise",
        "title": "DARMC location 3296",
        "link": "http://pleiades.stoa.org/places/628925/darmc-location-3296"
      }
    }
  ]
}