{
  "type": "FeatureCollection",
  "title": "Anisa",
  "id": "628923",
  "bbox": [
    35.629504,
    38.84724,
    35.634954,
    38.850916
  ],
  "description": "Anisa was an ancient settlement of Cappadocia that was inhabited in Hellenistic, Roman, and Byzantine times.",
  "connectsWith": [
    "58129442"
  ],
  "names": [
    "Anisa",
    "Kaniš",
    "Karahüyük",
    "Kaneš",
    "Kültepe",
    "Kültepe Karahüyük",
    "Neša"
  ],
  "features": [
    {
      "type": "Feature",
      "geometry": {
        "type": "Point",
        "coordinates": [
          35.632229,
          38.849078
        ]
      },
      "properties": {
        "description": "representative point"
      }
    },
    {
      "geometry": {
        "type": "Point",
        "coordinates": [
          35.629504,
          38.84724
        ]
      },
      "id": "darmc-location-11397",
      "type": "Feature",
      "properties": {
        "description": "500K scale point location",
        "location_precision": "precise",
        "title": "DARMC location 11397",
        "link": "http://pleiades.stoa.org/places/628923/darmc-location-11397"
      }
    },
    {
      "geometry": {
        "type": "Point",
        "coordinates": [
          35.634954,
          38.850916
        ]
      },
      "id": "dare-location",
      "type": "Feature",
      "properties": {
        "description": "Representative point location, site precision",
        "location_precision": "precise",
        "title": "DARE Location",
        "link": "http://pleiades.stoa.org/places/628923/dare-location"
      }
    }
  ]
}