{
  "type": "FeatureCollection",
  "title": "Kamisa/Comassa",
  "id": "628997",
  "description": "An ancient place, cited: BAtlas 64 E1 Kamisa/Comassa",
  "bbox": [
    37.401155,
    39.845769,
    37.401155,
    39.845769
  ],
  "reprPoint": [
    37.401155,
    39.845769
  ],
  "names": [
    "Kamisa",
    "Comassa",
    "Eumeis"
  ],
  "features": [
    {
      "geometry": {
        "type": "Point",
        "coordinates": [
          37.401155,
          39.845769
        ]
      },
      "id": "darmc-location-12977",
      "type": "Feature",
      "properties": {
        "description": "500K scale point location",
        "location_precision": "precise",
        "title": "DARMC location 12977",
        "link": "http://pleiades.stoa.org/places/628997/darmc-location-12977"
      }
    }
  ]
}