{
  "type": "FeatureCollection",
  "title": "Euspena",
  "id": "628977",
  "description": "An ancient place, cited: BAtlas 64 E2 Euspena",
  "bbox": [
    37.385969,
    39.235631,
    37.385969,
    39.235631
  ],
  "reprPoint": [
    37.385969,
    39.235631
  ],
  "names": [
    "Euspena"
  ],
  "features": [
    {
      "geometry": {
        "type": "Point",
        "coordinates": [
          37.385969,
          39.235631
        ]
      },
      "id": "darmc-location-12410",
      "type": "Feature",
      "properties": {
        "description": "500K scale point location",
        "location_precision": "precise",
        "title": "DARMC location 12410",
        "link": "http://pleiades.stoa.org/places/628977/darmc-location-12410"
      }
    }
  ]
}