{
  "type": "FeatureCollection",
  "title": "Kabassos",
  "id": "628995",
  "bbox": [
    36.127534,
    38.134602,
    36.127534,
    38.134602
  ],
  "description": "An ancient place, cited: BAtlas 64 C4 Kabassos",
  "names": [
    "Kabassos",
    "Kabissos"
  ],
  "features": [
    {
      "type": "Feature",
      "geometry": {
        "type": "Point",
        "coordinates": [
          36.127534,
          38.134602
        ]
      },
      "properties": {
        "description": "representative point"
      }
    },
    {
      "geometry": {
        "type": "Point",
        "coordinates": [
          36.127534,
          38.134602
        ]
      },
      "id": "darmc-location-10282",
      "type": "Feature",
      "properties": {
        "description": "500K scale point location",
        "location_precision": "precise",
        "title": "DARMC location 10282",
        "link": "http://pleiades.stoa.org/places/628995/darmc-location-10282"
      }
    }
  ]
}