{
  "type": "FeatureCollection",
  "title": "Elegeia",
  "id": "628969",
  "description": "An ancient place, cited: BAtlas 64 H4 Elegeia",
  "bbox": [
    38.827157,
    38.449691,
    38.827157,
    38.449691
  ],
  "reprPoint": [
    38.827157,
    38.449691
  ],
  "names": [
    "Elegeia"
  ],
  "features": [
    {
      "geometry": {
        "type": "Point",
        "coordinates": [
          38.827157,
          38.449691
        ]
      },
      "id": "darmc-location-10277",
      "type": "Feature",
      "properties": {
        "description": "500K scale point location",
        "location_precision": "precise",
        "title": "DARMC location 10277",
        "link": "http://pleiades.stoa.org/places/628969/darmc-location-10277"
      }
    }
  ]
}