{
  "type": "FeatureCollection",
  "title": "Eski Arabkir",
  "id": "628971",
  "description": "An ancient place, cited: BAtlas 64 G2 Eski Arabkir",
  "bbox": [
    38.489809,
    39.058893,
    38.489809,
    39.058893
  ],
  "reprPoint": [
    38.489809,
    39.058893
  ],
  "features": [
    {
      "geometry": {
        "type": "Point",
        "coordinates": [
          38.489809,
          39.058893
        ]
      },
      "id": "darmc-location-12389",
      "type": "Feature",
      "properties": {
        "description": "500K scale point location",
        "location_precision": "precise",
        "title": "DARMC location 12389",
        "link": "http://pleiades.stoa.org/places/628971/darmc-location-12389"
      }
    }
  ]
}