{
  "type": "FeatureCollection",
  "title": "Anisa",
  "id": "628923",
  "description": "An ancient place, cited: BAtlas 64 B3 Anisa",
  "bbox": [
    35.634954,
    38.850916,
    35.634954,
    38.850916
  ],
  "reprPoint": [
    35.634954,
    38.850916
  ],
  "names": [
    "Anisa",
    "Kaniš",
    "Karahüyük",
    "Kaneš",
    "Kültepe",
    "Kültepe Karahüyük",
    "Neša"
  ],
  "features": [
    {
      "geometry": {
        "type": "Point",
        "coordinates": [
          35.634954,
          38.850916
        ]
      },
      "id": "dare-location",
      "type": "Feature",
      "properties": {
        "description": "Representative point location, site precision",
        "location_precision": "precise",
        "title": "DARE Location",
        "link": "http://pleiades.stoa.org/places/628923/dare-location"
      }
    },
    {
      "geometry": {
        "type": "Point",
        "coordinates": [
          35.629504,
          38.84724
        ]
      },
      "id": "darmc-location-11397",
      "type": "Feature",
      "properties": {
        "description": "500K scale point location",
        "location_precision": "precise",
        "title": "DARMC location 11397",
        "link": "http://pleiades.stoa.org/places/628923/darmc-location-11397"
      }
    }
  ]
}