{
  "type": "FeatureCollection",
  "title": "Agranai",
  "id": "628919",
  "bbox": [
    35.838751,
    39.739003,
    35.838751,
    39.739003
  ],
  "description": "An ancient place, cited: BAtlas 64 B1 Agranai",
  "names": [
    "Agranai",
    "Agriane"
  ],
  "features": [
    {
      "type": "Feature",
      "geometry": {
        "type": "Point",
        "coordinates": [
          35.838751,
          39.739003
        ]
      },
      "properties": {
        "description": "representative point"
      }
    },
    {
      "geometry": {
        "type": "Point",
        "coordinates": [
          35.838751,
          39.739003
        ]
      },
      "id": "darmc-location-9931",
      "type": "Feature",
      "properties": {
        "description": "500K scale point location",
        "location_precision": "precise",
        "title": "DARMC location 9931",
        "link": "http://pleiades.stoa.org/places/628919/darmc-location-9931"
      }
    }
  ]
}