{
  "type": "FeatureCollection",
  "title": "Anisa",
  "id": "628923",
  "bbox": [
    35.634954,
    38.850916,
    35.6365,
    38.8518
  ],
  "description": "Anisa was an ancient settlement of Cappadocia that was inhabited in Hellenistic, Roman, and Byzantine times.",
  "connectsWith": [
    "58129442"
  ],
  "names": [
    "Anisa",
    "Kaniš",
    "Karahüyük",
    "Kaneš",
    "Kültepe",
    "Kültepe Karahüyük",
    "Neša",
    "Kültepe"
  ],
  "features": [
    {
      "type": "Feature",
      "geometry": {
        "type": "Point",
        "coordinates": [
          35.635727,
          38.851358
        ]
      },
      "properties": {
        "description": "representative point"
      }
    },
    {
      "geometry": {
        "type": "Point",
        "coordinates": [
          35.634954,
          38.850916
        ]
      },
      "id": "dare-location",
      "type": "Feature",
      "properties": {
        "description": "Representative point location, site precision",
        "location_precision": "precise",
        "title": "DARE Location",
        "link": "http://pleiades.stoa.org/places/628923/dare-location"
      }
    },
    {
      "geometry": {
        "type": "Point",
        "coordinates": [
          35.6365,
          38.8518
        ]
      },
      "id": "cigs-location-of-kultepe",
      "type": "Feature",
      "properties": {
        "description": null,
        "location_precision": "precise",
        "title": "CIGS location of Kültepe",
        "link": "http://pleiades.stoa.org/places/628923/cigs-location-of-kultepe"
      }
    }
  ]
}