{
  "type": "FeatureCollection",
  "title": "Symposion/In Medio?",
  "id": "629088",
  "bbox": [
    36.667723,
    38.933513,
    36.681315,
    38.943202
  ],
  "description": "An ancient place, cited: BAtlas 64 D3 Symposion/In Medio?",
  "names": [
    "Symposion",
    "In Medio"
  ],
  "features": [
    {
      "type": "Feature",
      "geometry": {
        "type": "Point",
        "coordinates": [
          36.674519,
          38.9383575
        ]
      },
      "properties": {
        "description": "representative point"
      }
    },
    {
      "geometry": {
        "type": "Point",
        "coordinates": [
          36.681315,
          38.943202
        ]
      },
      "id": "darmc-location-2025",
      "type": "Feature",
      "properties": {
        "description": "TIB point location",
        "location_precision": "precise",
        "title": "DARMC location 2025",
        "link": "http://pleiades.stoa.org/places/629088/darmc-location-2025"
      }
    },
    {
      "geometry": {
        "type": "Point",
        "coordinates": [
          36.667723,
          38.933513
        ]
      },
      "id": "darmc-location-6108",
      "type": "Feature",
      "properties": {
        "description": "500K scale point location",
        "location_precision": "precise",
        "title": "DARMC location 6108",
        "link": "http://pleiades.stoa.org/places/629088/darmc-location-6108"
      }
    }
  ]
}