{
  "type": "FeatureCollection",
  "title": "Kiakis",
  "id": "629008",
  "bbox": [
    38.375992,
    38.684258,
    38.39808,
    38.684966
  ],
  "description": "An ancient place, cited: BAtlas 64 G3 Kiakis",
  "connectsWith": [
    "628982",
    "522605291",
    "100544804"
  ],
  "names": [
    "Kiakis",
    "Chiaca",
    "Kiaka"
  ],
  "features": [
    {
      "type": "Feature",
      "geometry": {
        "type": "Point",
        "coordinates": [
          38.387036,
          38.684612
        ]
      },
      "properties": {
        "description": "representative point"
      }
    },
    {
      "geometry": {
        "type": "Point",
        "coordinates": [
          38.39808,
          38.684258
        ]
      },
      "id": "darmc-location-1277",
      "type": "Feature",
      "properties": {
        "description": "TIB point location",
        "location_precision": "precise",
        "title": "DARMC location 1277",
        "link": "http://pleiades.stoa.org/places/629008/darmc-location-1277"
      }
    },
    {
      "geometry": {
        "type": "Point",
        "coordinates": [
          38.375992,
          38.684966
        ]
      },
      "id": "darmc-location-6615",
      "type": "Feature",
      "properties": {
        "description": "500K scale point location",
        "location_precision": "precise",
        "title": "DARMC location 6615",
        "link": "http://pleiades.stoa.org/places/629008/darmc-location-6615"
      }
    }
  ]
}