{
  "type": "FeatureCollection",
  "title": "Söğütlü",
  "id": "629085",
  "description": "An ancient place, cited: BAtlas 64 B4 Söğütlü",
  "bbox": [
    35.782775,
    38.308347,
    35.782775,
    38.308347
  ],
  "reprPoint": [
    35.782775,
    38.308347
  ],
  "features": [
    {
      "geometry": {
        "type": "Point",
        "coordinates": [
          35.782775,
          38.308347
        ]
      },
      "id": "darmc-location-14811",
      "type": "Feature",
      "properties": {
        "description": "500K scale point location",
        "location_precision": "precise",
        "title": "DARMC location 14811",
        "link": "http://pleiades.stoa.org/places/629085/darmc-location-14811"
      }
    }
  ]
}