{
  "type": "FeatureCollection",
  "title": "Kötükale",
  "id": "629018",
  "description": "An ancient place, cited: BAtlas 64 F3 Kötükale",
  "bbox": [
    37.556421,
    38.50383,
    37.556421,
    38.50383
  ],
  "reprPoint": [
    37.556421,
    38.50383
  ],
  "features": [
    {
      "geometry": {
        "type": "Point",
        "coordinates": [
          37.556421,
          38.50383
        ]
      },
      "id": "darmc-location-7131",
      "type": "Feature",
      "properties": {
        "description": "500K scale point location",
        "location_precision": "precise",
        "title": "DARMC location 7131",
        "link": "http://pleiades.stoa.org/places/629018/darmc-location-7131"
      }
    }
  ]
}