{
  "type": "FeatureCollection",
  "title": "Leugaisa/‘Lagalasso’",
  "id": "629027",
  "bbox": [
    38.051885,
    38.183297,
    38.051885,
    38.183297
  ],
  "description": "An ancient place, cited: BAtlas 64 G4 Leugaisa/‘Lagalasso’",
  "names": [
    "Leugaisa",
    "Lagalasso"
  ],
  "features": [
    {
      "type": "Feature",
      "geometry": {
        "type": "Point",
        "coordinates": [
          38.051885,
          38.183297
        ]
      },
      "properties": {
        "description": "representative point"
      }
    },
    {
      "geometry": {
        "type": "Point",
        "coordinates": [
          38.051885,
          38.183297
        ]
      },
      "id": "darmc-location-13476",
      "type": "Feature",
      "properties": {
        "description": "500K scale point location",
        "location_precision": "precise",
        "title": "DARMC location 13476",
        "link": "http://pleiades.stoa.org/places/629027/darmc-location-13476"
      }
    }
  ]
}