{
  "type": "FeatureCollection",
  "title": "[Kiskisos]",
  "id": "629009",
  "bbox": [
    35.786827,
    38.15395,
    35.786827,
    38.15395
  ],
  "description": "An ancient place, cited: BAtlas 64 B4 [Kiskisos]",
  "connectsWith": [
    "630437"
  ],
  "names": [
    "Kiskisos"
  ],
  "features": [
    {
      "type": "Feature",
      "geometry": {
        "type": "Point",
        "coordinates": [
          35.786827,
          38.15395
        ]
      },
      "properties": {
        "description": "representative point"
      }
    },
    {
      "geometry": {
        "type": "Point",
        "coordinates": [
          35.786827,
          38.15395
        ]
      },
      "id": "darmc-location-2029",
      "type": "Feature",
      "properties": {
        "description": "TIB point location",
        "location_precision": "precise",
        "title": "DARMC location 2029",
        "link": "http://pleiades.stoa.org/places/629009/darmc-location-2029"
      }
    }
  ]
}