{
  "type": "FeatureCollection",
  "title": "Zabulbar",
  "id": "629104",
  "bbox": [
    38.772098,
    39.007561,
    38.772098,
    39.007561
  ],
  "description": "An ancient place, cited: BAtlas 64 H2 Zabulbar",
  "features": [
    {
      "type": "Feature",
      "geometry": {
        "type": "Point",
        "coordinates": [
          38.772098,
          39.007561
        ]
      },
      "properties": {
        "description": "representative point"
      }
    },
    {
      "geometry": {
        "type": "Point",
        "coordinates": [
          38.772098,
          39.007561
        ]
      },
      "id": "darmc-location-8458",
      "type": "Feature",
      "properties": {
        "description": "500K scale point location",
        "location_precision": "precise",
        "title": "DARMC location 8458",
        "link": "http://pleiades.stoa.org/places/629104/darmc-location-8458"
      }
    }
  ]
}