{
  "type": "FeatureCollection",
  "title": "Ripatransone",
  "id": "629429886",
  "bbox": [
    13.7617959,
    42.9961784,
    13.7617959,
    42.9961784
  ],
  "description": "In antiquity, Ripatransone was a significant Picene center. It now lies in the Province of Ascoli Piceno, in the Italian region Marche.",
  "features": [
    {
      "type": "Feature",
      "geometry": {
        "type": "Point",
        "coordinates": [
          13.7617959,
          42.9961784
        ]
      },
      "properties": {
        "description": "representative point"
      }
    },
    {
      "geometry": {
        "type": "Point",
        "coordinates": [
          13.7617959,
          42.9961784
        ]
      },
      "id": "osm-location-of-ripatransone",
      "type": "Feature",
      "properties": {
        "description": "Location based on OpenStreetMap",
        "location_precision": "precise",
        "title": "OSM location of Ripatransone",
        "link": "http://pleiades.stoa.org/places/629429886/osm-location-of-ripatransone"
      }
    }
  ]
}