{
  "type": "FeatureCollection",
  "title": "Karamagara Bridge",
  "id": "629685",
  "bbox": [
    38.658486,
    38.924961,
    38.658486,
    38.924961
  ],
  "description": "A Roman-era bridge spanning the Arabkir Çay south of Hastek Kale in Turkey. Now submerged and inaccessible.",
  "names": [
    "Karamagara Koprusu",
    "Kara Magara Kopru"
  ],
  "features": [
    {
      "type": "Feature",
      "geometry": {
        "type": "Point",
        "coordinates": [
          38.658486,
          38.924961
        ]
      },
      "properties": {
        "description": "representative point"
      }
    },
    {
      "geometry": {
        "type": "Point",
        "coordinates": [
          38.658486,
          38.924961
        ]
      },
      "id": "wikipedia-location-of-the-karamagara-bridge",
      "type": "Feature",
      "properties": {
        "description": "Matches the BAtlas location. Dates after T.B. Mitford in BAtlas 64.",
        "location_precision": "precise",
        "title": "Wikipedia Location of the Karamagara Bridge",
        "link": "http://pleiades.stoa.org/places/629685/wikipedia-location-of-the-karamagara-bridge"
      }
    }
  ]
}