{
  "type": "FeatureCollection",
  "title": "Saintes-Marie-de-la-Mer Roman Port",
  "id": "631720472",
  "bbox": [
    4.420147,
    43.435109,
    4.444952,
    43.456425
  ],
  "description": "A Roman commercial port near the modern French town of Saintes-Maries-de-la-Mer is attested by over forty Roman-era shipwrecks discovered in the area since the 1990s, most carrying cargoes of metal. The excavators posit in Roman times a significantly different coastline (generally further south) and an old mouth of the Rhone (Ancien Rhône de Saint-Ferréol), located to the east of Saintes-Maries-de-la-Mer (Long 2011, Figure 1).",
  "features": [
    {
      "type": "Feature",
      "geometry": {
        "type": "Point",
        "coordinates": [
          4.43127206667,
          43.4479370333
        ]
      },
      "properties": {
        "description": "representative point"
      }
    },
    {
      "geometry": {
        "type": "Point",
        "coordinates": [
          4.4287172,
          43.4522771
        ]
      },
      "id": "osm-location-of-modern-saintes-maries-de-la-mer",
      "type": "Feature",
      "properties": {
        "description": "Location based on OpenStreetMap, with reference to Gosselin 2023, Figure 1.",
        "location_precision": "precise",
        "title": "OSM Location of modern Saintes-Maries-de-la-Mer",
        "link": "http://pleiades.stoa.org/places/631720472/osm-location-of-modern-saintes-maries-de-la-mer"
      }
    },
    {
      "geometry": {
        "type": "Point",
        "coordinates": [
          4.420147,
          43.435109
        ]
      },
      "id": "imagery-location-approximate-centerpoint-of-wreck-scatter",
      "type": "Feature",
      "properties": {
        "description": "After Gosselin 2023, Figure 1 and Long 2011, Figure 1.",
        "location_precision": "precise",
        "title": "Imagery Location: Approximate Centerpoint of Wreck Scatter",
        "link": "http://pleiades.stoa.org/places/631720472/imagery-location-approximate-centerpoint-of-wreck-scatter"
      }
    },
    {
      "geometry": {
        "type": "Point",
        "coordinates": [
          4.444952,
          43.456425
        ]
      },
      "id": "imagery-location-grau-de-la-fourcade-saintes-maries-de-la-mer",
      "type": "Feature",
      "properties": {
        "description": "The Grau de la Fourcade is the sea channel now occupying the point where the old Saint-Ferréol branch of the Rhone once debouched into the sea, a feature thought by the excavators to have been in place in Roman times.",
        "location_precision": "precise",
        "title": "Imagery Location: Grau de la Fourcade / Saintes-Maries-de-la-Mer",
        "link": "http://pleiades.stoa.org/places/631720472/imagery-location-grau-de-la-fourcade-saintes-maries-de-la-mer"
      }
    }
  ]
}