{
  "type": "FeatureCollection",
  "title": "Verbovskiĭ Mogil'nik",
  "id": "633771263",
  "bbox": [
    41.908704,
    45.069464,
    41.908704,
    45.069464
  ],
  "description": "A burial mound dated to the fourth-third centuries BCE located northwest of the city of Stavropol'.",
  "names": [
    "Verbovskiĭ mogilʹnik"
  ],
  "features": [
    {
      "type": "Feature",
      "geometry": {
        "type": "Point",
        "coordinates": [
          41.908704,
          45.069464
        ]
      },
      "properties": {
        "description": "representative point"
      }
    },
    {
      "geometry": {
        "type": "Point",
        "coordinates": [
          41.908704,
          45.069464
        ]
      },
      "id": "45-069464-41-908704",
      "type": "Feature",
      "properties": {
        "description": "Point representing the location of Verbovskiĭ Mogilʹnik, after Прокопенко 2012.\r\n",
        "location_precision": "precise",
        "title": "Imagery location of Verbovskiĭ Mogilʹnik",
        "link": "http://pleiades.stoa.org/places/633771263/45-069464-41-908704"
      }
    }
  ]
}