{
  "type": "FeatureCollection",
  "title": "Agios Nikolaos (island)",
  "id": "63423309",
  "bbox": [
    25.6899641,
    37.0863475,
    25.6899641,
    37.0863475
  ],
  "description": "An island that is part of the Nikasiai islands (Naxos).",
  "connectsWith": [
    "599827"
  ],
  "features": [
    {
      "type": "Feature",
      "geometry": {
        "type": "Point",
        "coordinates": [
          25.6899641,
          37.0863475
        ]
      },
      "properties": {
        "description": "representative point"
      }
    },
    {
      "geometry": {
        "type": "Point",
        "coordinates": [
          25.6899641,
          37.0863475
        ]
      },
      "id": "osm-location-of-agios-nikolaos",
      "type": "Feature",
      "properties": {
        "description": "Representative location based on OpenStreetMap.",
        "location_precision": "precise",
        "title": "OSM location of Agios Nikolaos",
        "link": "http://pleiades.stoa.org/places/63423309/osm-location-of-agios-nikolaos"
      }
    }
  ]
}