{
  "type": "FeatureCollection",
  "title": "Tell el-'Oueili",
  "id": "636257512",
  "bbox": [
    45.8854399,
    31.2429129,
    45.8854399,
    31.2429129
  ],
  "description": "Tell el-'Oueili is an archaeological site located in the Dhi Qar Governorate of southern Iraq. Occupation at the site predates the occupation levels of Eridu, making Tell el-'Oueili one of the earliest known human settlements of southern Mesopotamia.",
  "names": [
    "Tell el-'Oueili"
  ],
  "features": [
    {
      "type": "Feature",
      "geometry": {
        "type": "Point",
        "coordinates": [
          45.8854399,
          31.2429129
        ]
      },
      "properties": {
        "description": "representative point"
      }
    },
    {
      "geometry": {
        "type": "Point",
        "coordinates": [
          45.8854399,
          31.2429129
        ]
      },
      "id": "osm-location-of-tell-el-oueili",
      "type": "Feature",
      "properties": {
        "description": "Representative location based on OpenStreetMap.",
        "location_precision": "precise",
        "title": "OSM location of Tell el-'Oueili",
        "link": "http://pleiades.stoa.org/places/636257512/osm-location-of-tell-el-oueili"
      }
    }
  ]
}