{
  "type": "FeatureCollection",
  "title": "Aydolin Kale",
  "id": "638787",
  "bbox": [
    31.819965,
    36.737352,
    31.819965,
    36.737352
  ],
  "description": "An ancient place, cited: BAtlas 65 G4 Aydolin Kale",
  "features": [
    {
      "type": "Feature",
      "geometry": {
        "type": "Point",
        "coordinates": [
          31.819965,
          36.737352
        ]
      },
      "properties": {
        "description": "representative point"
      }
    },
    {
      "geometry": {
        "type": "Point",
        "coordinates": [
          31.819965,
          36.737352
        ]
      },
      "id": "darmc-location-11599",
      "type": "Feature",
      "properties": {
        "description": "500K scale point location",
        "location_precision": "precise",
        "title": "DARMC location 11599",
        "link": "http://pleiades.stoa.org/places/638787/darmc-location-11599"
      }
    }
  ]
}