{
  "type": "FeatureCollection",
  "title": "Adada",
  "id": "638733",
  "description": "An ancient place, cited: BAtlas 65 E2 Adada",
  "bbox": [
    30.984032,
    37.577527,
    30.984032,
    37.577527
  ],
  "reprPoint": [
    30.984032,
    37.577527
  ],
  "names": [
    "Adada"
  ],
  "features": [
    {
      "geometry": {
        "type": "Point",
        "coordinates": [
          30.984032,
          37.577527
        ]
      },
      "id": "dare-location",
      "type": "Feature",
      "properties": {
        "description": "Representative point location, site precision",
        "location_precision": "precise",
        "title": "DARE Location",
        "link": "http://pleiades.stoa.org/places/638733/dare-location"
      }
    },
    {
      "geometry": {
        "type": "Point",
        "coordinates": [
          30.976484,
          37.570031
        ]
      },
      "id": "darmc-location-1230",
      "type": "Feature",
      "properties": {
        "description": "TIB point location",
        "location_precision": "precise",
        "title": "DARMC location 1230",
        "link": "http://pleiades.stoa.org/places/638733/darmc-location-1230"
      }
    },
    {
      "geometry": {
        "type": "Point",
        "coordinates": [
          30.989777,
          37.587947
        ]
      },
      "id": "darmc-location-2749",
      "type": "Feature",
      "properties": {
        "description": "500K scale point location",
        "location_precision": "precise",
        "title": "DARMC location 2749",
        "link": "http://pleiades.stoa.org/places/638733/darmc-location-2749"
      }
    }
  ]
}