{
  "type": "FeatureCollection",
  "title": "Artymnissos/Perdikiai",
  "id": "638767",
  "description": "An ancient place, cited: BAtlas 65 B5 Artymnissos/Perdikiai",
  "bbox": [
    29.121492,
    36.4952,
    29.1397,
    36.509319
  ],
  "reprPoint": [
    29.132944,
    36.500354
  ],
  "names": [
    "Artymnissos",
    "Perdikiai"
  ],
  "features": [
    {
      "geometry": {
        "type": "Point",
        "coordinates": [
          29.121492,
          36.509319
        ]
      },
      "id": "darmc-location-12735",
      "type": "Feature",
      "properties": {
        "description": "TIB point location",
        "location_precision": "precise",
        "title": "DARMC location 12735",
        "link": "http://pleiades.stoa.org/places/638767/darmc-location-12735"
      }
    },
    {
      "geometry": {
        "type": "Point",
        "coordinates": [
          29.13764,
          36.496543
        ]
      },
      "id": "darmc-location-11517",
      "type": "Feature",
      "properties": {
        "description": "500K scale point location",
        "location_precision": "precise",
        "title": "DARMC location 11517",
        "link": "http://pleiades.stoa.org/places/638767/darmc-location-11517"
      }
    }
  ]
}