{
  "type": "FeatureCollection",
  "title": "Aydolin Kale",
  "id": "638787",
  "description": "An ancient place, cited: BAtlas 65 G4 Aydolin Kale",
  "bbox": [
    31.819965,
    36.737352,
    31.819965,
    36.737352
  ],
  "reprPoint": [
    31.819965,
    36.737352
  ],
  "features": [
    {
      "geometry": {
        "type": "Point",
        "coordinates": [
          31.8231,
          36.7377
        ]
      },
      "id": "batlas-location",
      "type": "Feature",
      "properties": {
        "description": null,
        "location_precision": "precise",
        "title": "Barrington Atlas map location",
        "link": "http://pleiades.stoa.org/places/638787/batlas-location"
      }
    },
    {
      "geometry": {
        "type": "Point",
        "coordinates": [
          31.819965,
          36.737352
        ]
      },
      "id": "darmc-location-11599",
      "type": "Feature",
      "properties": {
        "description": "500K scale point location",
        "location_precision": "precise",
        "title": "DARMC location 11599",
        "link": "http://pleiades.stoa.org/places/638787/darmc-location-11599"
      }
    }
  ]
}