{
  "type": "FeatureCollection",
  "title": "*Istlada",
  "id": "638874",
  "bbox": [
    29.8876666,
    36.218342,
    29.887844,
    36.2184666
  ],
  "description": "Ruins of an ancient town located in a now-uninhabited forest area near the modern Turkish town of Kapaklı in the Demre district of Antalya province. Its ancient name is known only from fragmentary epigraphic sources of the Hellenistic period, but archaeological investigation has demonstrated occupation and development from the 3rd century BCE through late antiquity, with some modest habitation continuing in the medieval period.",
  "names": [
    "Istlada"
  ],
  "features": [
    {
      "type": "Feature",
      "geometry": {
        "type": "Point",
        "coordinates": [
          29.8877553,
          36.2184043
        ]
      },
      "properties": {
        "description": "representative point"
      }
    },
    {
      "geometry": {
        "type": "Point",
        "coordinates": [
          29.887844,
          36.218342
        ]
      },
      "id": "dare-location",
      "type": "Feature",
      "properties": {
        "description": "Representative point location, site precision",
        "location_precision": "precise",
        "title": "DARE Location",
        "link": "http://pleiades.stoa.org/places/638874/dare-location"
      }
    },
    {
      "geometry": {
        "type": "Point",
        "coordinates": [
          29.8876666,
          36.2184666
        ]
      },
      "id": "osm-location-of-istlada",
      "type": "Feature",
      "properties": {
        "description": "Representative location based on OpenStreetMap. Dates after Marksteiner 2004.",
        "location_precision": "precise",
        "title": "OSM location of Istlada",
        "link": "http://pleiades.stoa.org/places/638874/osm-location-of-istlada"
      }
    }
  ]
}