{
  "type": "FeatureCollection",
  "title": "*Istlada",
  "id": "638874",
  "description": "An ancient place, cited: BAtlas 65 C5 *Istlada",
  "bbox": [
    29.870528,
    36.2074,
    29.889191,
    36.24105
  ],
  "reprPoint": [
    29.88401575,
    36.22066125
  ],
  "names": [
    "Istlada"
  ],
  "features": [
    {
      "geometry": {
        "type": "Point",
        "coordinates": [
          29.887844,
          36.218342
        ]
      },
      "id": "dare-location",
      "type": "Feature",
      "properties": {
        "description": "Representative point location, site precision",
        "location_precision": "precise",
        "title": "DARE Location",
        "link": "http://pleiades.stoa.org/places/638874/dare-location"
      }
    },
    {
      "geometry": {
        "type": "Point",
        "coordinates": [
          29.870528,
          36.24105
        ]
      },
      "id": "darmc-location-2791",
      "type": "Feature",
      "properties": {
        "description": "TIB point location",
        "location_precision": "precise",
        "title": "DARMC location 2791",
        "link": "http://pleiades.stoa.org/places/638874/darmc-location-2791"
      }
    },
    {
      "geometry": {
        "type": "Point",
        "coordinates": [
          29.889191,
          36.215853
        ]
      },
      "id": "darmc-location-12896",
      "type": "Feature",
      "properties": {
        "description": "500K scale point location",
        "location_precision": "precise",
        "title": "DARMC location 12896",
        "link": "http://pleiades.stoa.org/places/638874/darmc-location-12896"
      }
    }
  ]
}