{
  "type": "FeatureCollection",
  "title": "Choma",
  "id": "638803",
  "description": "An ancient place, cited: BAtlas 65 C4 Choma",
  "bbox": [
    29.820042,
    36.6315,
    29.824,
    36.63608
  ],
  "reprPoint": [
    29.822021,
    36.63379
  ],
  "names": [
    "Choma",
    "Hacimusalar"
  ],
  "features": [
    {
      "geometry": {
        "type": "Point",
        "coordinates": [
          29.824,
          36.6315
        ]
      },
      "id": "batlas-location",
      "type": "Feature",
      "properties": {
        "description": null,
        "location_precision": "precise",
        "title": "Barrington Atlas map location",
        "link": "http://pleiades.stoa.org/places/638803/batlas-location"
      }
    },
    {
      "geometry": {
        "type": "Point",
        "coordinates": [
          29.820042,
          36.63608
        ]
      },
      "id": "darmc-location-34858",
      "type": "Feature",
      "properties": {
        "description": "  scale point location",
        "location_precision": "precise",
        "title": "DARMC location 34858",
        "link": "http://pleiades.stoa.org/places/638803/darmc-location-34858"
      }
    }
  ]
}