{
  "type": "FeatureCollection",
  "title": "Hiera Akra",
  "id": "638859",
  "bbox": [
    29.1095284,
    36.3970121,
    29.1095284,
    36.3970121
  ],
  "description": "A promontory at the foot of the Kragos mountains, the modern Yedi Burun on Turkey's southwest coast.",
  "names": [
    "Yedi Burun",
    "Hiera Akra",
    "Kragos Pr."
  ],
  "features": [
    {
      "type": "Feature",
      "geometry": {
        "type": "Point",
        "coordinates": [
          29.1095284,
          36.3970121
        ]
      },
      "properties": {
        "description": "representative point"
      }
    },
    {
      "geometry": {
        "type": "Point",
        "coordinates": [
          29.1095284,
          36.3970121
        ]
      },
      "id": "osm-location-of-yedi-burun",
      "type": "Feature",
      "properties": {
        "description": "Location based on OpenStreetMap",
        "location_precision": "precise",
        "title": "OSM location of Yedi Burun",
        "link": "http://pleiades.stoa.org/places/638859/osm-location-of-yedi-burun"
      }
    }
  ]
}