{
  "type": "FeatureCollection",
  "title": "Choma",
  "id": "638803",
  "bbox": [
    29.820042,
    36.63608,
    29.820042,
    36.63608
  ],
  "description": "An ancient place, cited: BAtlas 65 C4 Choma",
  "names": [
    "Choma",
    "Hacimusalar"
  ],
  "features": [
    {
      "type": "Feature",
      "geometry": {
        "type": "Point",
        "coordinates": [
          29.820042,
          36.63608
        ]
      },
      "properties": {
        "description": "representative point"
      }
    },
    {
      "geometry": {
        "type": "Point",
        "coordinates": [
          29.820042,
          36.63608
        ]
      },
      "id": "darmc-location-34858",
      "type": "Feature",
      "properties": {
        "description": "representative point location digitized from the Barrington Atlas of the Greek and Roman World by the Digital Atlas of Roman and Medieval Civilizations project at Harvard University.",
        "location_precision": "precise",
        "title": "DARMC location 34858",
        "link": "http://pleiades.stoa.org/places/638803/darmc-location-34858"
      }
    }
  ]
}