{
  "type": "FeatureCollection",
  "title": "Hamaxia?",
  "id": "638853",
  "description": "An ancient place, cited: BAtlas 65 G4 Hamaxia?",
  "bbox": [
    31.939322,
    36.566037,
    31.9583,
    36.578674
  ],
  "reprPoint": [
    31.9475726667,
    36.573737
  ],
  "names": [
    "Hamaxia"
  ],
  "features": [
    {
      "geometry": {
        "type": "Point",
        "coordinates": [
          31.939322,
          36.578674
        ]
      },
      "id": "dare-location",
      "type": "Feature",
      "properties": {
        "description": "Representative point location, site precision",
        "location_precision": "precise",
        "title": "DARE Location",
        "link": "http://pleiades.stoa.org/places/638853/dare-location"
      }
    },
    {
      "geometry": {
        "type": "Point",
        "coordinates": [
          31.945096,
          36.566037
        ]
      },
      "id": "darmc-location-1380",
      "type": "Feature",
      "properties": {
        "description": "TIB point location",
        "location_precision": "precise",
        "title": "DARMC location 1380",
        "link": "http://pleiades.stoa.org/places/638853/darmc-location-1380"
      }
    }
  ]
}