{
  "type": "FeatureCollection",
  "title": "Hadrianopolis/Hadriani",
  "id": "638852",
  "description": "An ancient place, cited: BAtlas 65 D3 Hadrianopolis/Hadriani",
  "bbox": [
    30.0122,
    37.4897,
    30.04333,
    37.506828
  ],
  "reprPoint": [
    30.027765,
    37.498264
  ],
  "names": [
    "Hadrianopolis",
    "Hadriani"
  ],
  "features": [
    {
      "geometry": {
        "type": "Point",
        "coordinates": [
          30.0122,
          37.4897
        ]
      },
      "id": "batlas-location",
      "type": "Feature",
      "properties": {
        "description": null,
        "location_precision": "precise",
        "title": "Barrington Atlas map location",
        "link": "http://pleiades.stoa.org/places/638852/batlas-location"
      }
    },
    {
      "geometry": {
        "type": "Point",
        "coordinates": [
          30.04333,
          37.506828
        ]
      },
      "id": "darmc-location-3529",
      "type": "Feature",
      "properties": {
        "description": "500K scale point location",
        "location_precision": "precise",
        "title": "DARMC location 3529",
        "link": "http://pleiades.stoa.org/places/638852/darmc-location-3529"
      }
    }
  ]
}