{
  "type": "FeatureCollection",
  "title": "Idyros?",
  "id": "638866",
  "description": "An ancient place, cited: BAtlas 65 E4 Idyros?",
  "bbox": [
    30.559807,
    36.60261,
    30.559807,
    36.60261
  ],
  "reprPoint": [
    30.559807,
    36.60261
  ],
  "names": [
    "Idyros"
  ],
  "features": [
    {
      "geometry": {
        "type": "Point",
        "coordinates": [
          30.5661,
          36.5906
        ]
      },
      "id": "batlas-location",
      "type": "Feature",
      "properties": {
        "description": null,
        "location_precision": "precise",
        "title": "Barrington Atlas map location",
        "link": "http://pleiades.stoa.org/places/638866/batlas-location"
      }
    },
    {
      "geometry": {
        "type": "Point",
        "coordinates": [
          30.559807,
          36.60261
        ]
      },
      "id": "darmc-location-1389",
      "type": "Feature",
      "properties": {
        "description": "TIB point location",
        "location_precision": "precise",
        "title": "DARMC location 1389",
        "link": "http://pleiades.stoa.org/places/638866/darmc-location-1389"
      }
    }
  ]
}