{
  "type": "FeatureCollection",
  "title": "Kandyba",
  "id": "638892",
  "description": "An ancient place, cited: BAtlas 65 C5 Kandyba",
  "bbox": [
    29.623456,
    36.292387,
    29.6855,
    36.318729
  ],
  "reprPoint": [
    29.6664914,
    36.3083626
  ],
  "names": [
    "Kandyba"
  ],
  "features": [
    {
      "geometry": {
        "type": "Point",
        "coordinates": [
          29.673794,
          36.318729
        ]
      },
      "id": "dare-location",
      "type": "Feature",
      "properties": {
        "description": "Representative point location, site precision",
        "location_precision": "precise",
        "title": "DARE Location",
        "link": "http://pleiades.stoa.org/places/638892/dare-location"
      }
    },
    {
      "geometry": {
        "type": "Point",
        "coordinates": [
          29.664528,
          36.315447
        ]
      },
      "id": "darmc-location-1392",
      "type": "Feature",
      "properties": {
        "description": "TIB point location",
        "location_precision": "precise",
        "title": "DARMC location 1392",
        "link": "http://pleiades.stoa.org/places/638892/darmc-location-1392"
      }
    },
    {
      "geometry": {
        "type": "Point",
        "coordinates": [
          29.623456,
          36.292387
        ]
      },
      "id": "darmc-location-2777",
      "type": "Feature",
      "properties": {
        "description": "TIB point location",
        "location_precision": "precise",
        "title": "DARMC location 2777",
        "link": "http://pleiades.stoa.org/places/638892/darmc-location-2777"
      }
    },
    {
      "geometry": {
        "type": "Point",
        "coordinates": [
          29.685179,
          36.31115
        ]
      },
      "id": "darmc-location-4034",
      "type": "Feature",
      "properties": {
        "description": "500K scale point location",
        "location_precision": "precise",
        "title": "DARMC location 4034",
        "link": "http://pleiades.stoa.org/places/638892/darmc-location-4034"
      }
    }
  ]
}