{
  "type": "FeatureCollection",
  "title": "Idyros?",
  "id": "638866",
  "description": "An ancient place, cited: BAtlas 65 E4 Idyros?",
  "bbox": [
    30.559807,
    36.5906,
    30.5661,
    36.60261
  ],
  "reprPoint": [
    30.5629535,
    36.596605
  ],
  "names": [
    "Idyros"
  ],
  "features": [
    {
      "geometry": {
        "type": "Point",
        "coordinates": [
          30.559807,
          36.60261
        ]
      },
      "id": "darmc-location-1389",
      "type": "Feature",
      "properties": {
        "description": "TIB point location",
        "location_precision": "precise",
        "title": "DARMC location 1389",
        "link": "http://pleiades.stoa.org/places/638866/darmc-location-1389"
      }
    }
  ]
}