{
  "type": "FeatureCollection",
  "title": "Lagussa Ins.",
  "id": "638954",
  "description": "An ancient place, cited: BAtlas 65 B4 Lagussa Ins.",
  "bbox": [
    28.037778,
    36.656944,
    28.037778,
    36.656944
  ],
  "reprPoint": [
    28.037778,
    36.656944
  ],
  "names": [
    "Lagussa"
  ],
  "features": [
    {
      "geometry": {
        "type": "Point",
        "coordinates": [
          28.037778,
          36.656944
        ]
      },
      "id": "location-of-lagussa-ins",
      "type": "Feature",
      "properties": {
        "description": "Coordinates after BAtlas; verified in Google Earth 2013.",
        "location_precision": "precise",
        "title": "location of Lagussa Ins.",
        "link": "http://pleiades.stoa.org/places/638954/location-of-lagussa-ins"
      }
    }
  ]
}