{
  "type": "FeatureCollection",
  "title": "Karmylessos?",
  "id": "638900",
  "bbox": [
    29.090336,
    36.574312,
    29.097095,
    36.579189
  ],
  "description": "An ancient place, cited: BAtlas 65 B4 Karmylessos?",
  "names": [
    "Karmylessos"
  ],
  "features": [
    {
      "type": "Feature",
      "geometry": {
        "type": "Point",
        "coordinates": [
          29.0937155,
          36.5767505
        ]
      },
      "properties": {
        "description": "representative point"
      }
    },
    {
      "geometry": {
        "type": "Point",
        "coordinates": [
          29.097095,
          36.579189
        ]
      },
      "id": "darmc-location-23027",
      "type": "Feature",
      "properties": {
        "description": "500K scale point location",
        "location_precision": "precise",
        "title": "DARMC location 23027",
        "link": "http://pleiades.stoa.org/places/638900/darmc-location-23027"
      }
    },
    {
      "geometry": {
        "type": "Point",
        "coordinates": [
          29.090336,
          36.574312
        ]
      },
      "id": "dare-location",
      "type": "Feature",
      "properties": {
        "description": "Representative point location, site precision",
        "location_precision": "precise",
        "title": "DARE Location",
        "link": "http://pleiades.stoa.org/places/638900/dare-location"
      }
    }
  ]
}