{
  "type": "FeatureCollection",
  "title": "Keretapa?/Diokaisareia?",
  "id": "638914",
  "bbox": [
    29.741952,
    37.436342,
    30.11011,
    37.550986
  ],
  "description": "An ancient place, cited: BAtlas 65 C2 Keretapa?/Diokaisareia?",
  "names": [
    "Keretapa",
    "Diokaisareia"
  ],
  "features": [
    {
      "type": "Feature",
      "geometry": {
        "type": "Point",
        "coordinates": [
          29.926031,
          37.493664
        ]
      },
      "properties": {
        "description": "representative point"
      }
    },
    {
      "geometry": {
        "type": "Point",
        "coordinates": [
          29.741952,
          37.550986
        ]
      },
      "id": "darmc-location-13114",
      "type": "Feature",
      "properties": {
        "description": "500K scale point location",
        "location_precision": "precise",
        "title": "DARMC location 13114",
        "link": "http://pleiades.stoa.org/places/638914/darmc-location-13114"
      }
    },
    {
      "geometry": {
        "type": "Point",
        "coordinates": [
          30.11011,
          37.436342
        ]
      },
      "id": "darmc-location-34958",
      "type": "Feature",
      "properties": {
        "description": "  scale point location",
        "location_precision": "precise",
        "title": "DARMC location 34958",
        "link": "http://pleiades.stoa.org/places/638914/darmc-location-34958"
      }
    }
  ]
}