{
  "type": "FeatureCollection",
  "title": "*Kidrama",
  "id": "638919",
  "description": "An ancient place, cited: BAtlas 65 B3 *Kidrama",
  "bbox": [
    29.1152,
    37.3461,
    29.129469,
    37.354017
  ],
  "reprPoint": [
    29.1223345,
    37.3500585
  ],
  "names": [
    "Kidrama"
  ],
  "features": [
    {
      "geometry": {
        "type": "Point",
        "coordinates": [
          29.129469,
          37.354017
        ]
      },
      "id": "darmc-location-13180",
      "type": "Feature",
      "properties": {
        "description": "500K scale point location",
        "location_precision": "precise",
        "title": "DARMC location 13180",
        "link": "http://pleiades.stoa.org/places/638919/darmc-location-13180"
      }
    }
  ]
}