{
  "type": "FeatureCollection",
  "title": "Kovanlık",
  "id": "638941",
  "description": "An ancient place, cited: BAtlas 65 E3 Kovanlık",
  "bbox": [
    30.602832,
    37.169381,
    30.609,
    37.1702
  ],
  "reprPoint": [
    30.605916,
    37.1697905
  ],
  "features": [
    {
      "geometry": {
        "type": "Point",
        "coordinates": [
          30.602832,
          37.169381
        ]
      },
      "id": "darmc-location-9838",
      "type": "Feature",
      "properties": {
        "description": "500K scale point location",
        "location_precision": "precise",
        "title": "DARMC location 9838",
        "link": "http://pleiades.stoa.org/places/638941/darmc-location-9838"
      }
    }
  ]
}