{
  "type": "FeatureCollection",
  "title": "*Komba",
  "id": "638932",
  "bbox": [
    29.669357,
    36.551265,
    29.669357,
    36.551265
  ],
  "description": "An ancient place, cited: BAtlas 65 C4 *Komba",
  "names": [
    "Komba"
  ],
  "features": [
    {
      "type": "Feature",
      "geometry": {
        "type": "Point",
        "coordinates": [
          29.669357,
          36.551265
        ]
      },
      "properties": {
        "description": "representative point"
      }
    },
    {
      "geometry": {
        "type": "Point",
        "coordinates": [
          29.669357,
          36.551265
        ]
      },
      "id": "darmc-location-1457",
      "type": "Feature",
      "properties": {
        "description": "TIB point location",
        "location_precision": "precise",
        "title": "DARMC location 1457",
        "link": "http://pleiades.stoa.org/places/638932/darmc-location-1457"
      }
    }
  ]
}