{
  "type": "FeatureCollection",
  "title": "Kragos (mountain)",
  "id": "638942",
  "bbox": [
    29.1931181,
    36.35456,
    29.19889,
    36.3804538
  ],
  "description": "Avdancık/Sandak Dağ.",
  "names": [
    "Sandak Dağ",
    "Sandık Dağı",
    "Kragos"
  ],
  "features": [
    {
      "type": "Feature",
      "geometry": {
        "type": "Point",
        "coordinates": [
          29.19600405,
          36.3675069
        ]
      },
      "properties": {
        "description": "representative point"
      }
    },
    {
      "geometry": {
        "type": "Point",
        "coordinates": [
          29.19889,
          36.35456
        ]
      },
      "id": "geonames-location-sandik-dagi",
      "type": "Feature",
      "properties": {
        "description": null,
        "location_precision": "precise",
        "title": "Geonames Location: Sandık Dağı",
        "link": "http://pleiades.stoa.org/places/638942/geonames-location-sandik-dagi"
      }
    },
    {
      "geometry": {
        "type": "Point",
        "coordinates": [
          29.1931181,
          36.3804538
        ]
      },
      "id": "osm-location-of-Kragos-M",
      "type": "Feature",
      "properties": {
        "description": "Location based on OpenStreetMap",
        "location_precision": "precise",
        "title": "OSM location of Kragos M.",
        "link": "http://pleiades.stoa.org/places/638942/osm-location-of-Kragos-M"
      }
    }
  ]
}