{
  "type": "FeatureCollection",
  "title": "Kragos M.",
  "id": "638942",
  "bbox": [
    29.1931181,
    36.3804538,
    29.1931181,
    36.3804538
  ],
  "description": "An ancient place, cited: BAtlas 65 B5 Kragos M.",
  "names": [
    "Kragos M."
  ],
  "features": [
    {
      "type": "Feature",
      "geometry": {
        "type": "Point",
        "coordinates": [
          29.1931181,
          36.3804538
        ]
      },
      "properties": {
        "description": "representative point"
      }
    },
    {
      "geometry": {
        "type": "Point",
        "coordinates": [
          29.1931181,
          36.3804538
        ]
      },
      "id": "location-of-Kragos-M",
      "type": "Feature",
      "properties": {
        "description": "Location based on OpenStreetMap",
        "location_precision": "precise",
        "title": "location of Kragos M.",
        "link": "http://pleiades.stoa.org/places/638942/location-of-Kragos-M"
      }
    }
  ]
}