{
  "type": "FeatureCollection",
  "title": "Salda",
  "id": "639089",
  "description": "An ancient place, cited: BAtlas 65 C2 Salda",
  "bbox": [
    29.6337,
    37.5207,
    29.659222,
    37.535198
  ],
  "reprPoint": [
    29.646461,
    37.527949
  ],
  "features": [
    {
      "geometry": {
        "type": "Point",
        "coordinates": [
          29.659222,
          37.535198
        ]
      },
      "id": "darmc-location-9878",
      "type": "Feature",
      "properties": {
        "description": "500K scale point location",
        "location_precision": "precise",
        "title": "DARMC location 9878",
        "link": "http://pleiades.stoa.org/places/639089/darmc-location-9878"
      }
    }
  ]
}