{
  "type": "FeatureCollection",
  "title": "*Pedaia",
  "id": "639043",
  "bbox": [
    31.873662,
    37.634612,
    31.873662,
    37.634612
  ],
  "description": "An ancient place, cited: BAtlas 65 G2 *Pedaia",
  "names": [
    "Pedaia"
  ],
  "features": [
    {
      "type": "Feature",
      "geometry": {
        "type": "Point",
        "coordinates": [
          31.873662,
          37.634612
        ]
      },
      "properties": {
        "description": "representative point"
      }
    },
    {
      "geometry": {
        "type": "Point",
        "coordinates": [
          31.873662,
          37.634612
        ]
      },
      "id": "darmc-location-10189",
      "type": "Feature",
      "properties": {
        "description": "500K scale point location",
        "location_precision": "precise",
        "title": "DARMC location 10189",
        "link": "http://pleiades.stoa.org/places/639043/darmc-location-10189"
      }
    }
  ]
}