{
  "type": "FeatureCollection",
  "title": "Patara (mountain)",
  "id": "639041",
  "bbox": [
    29.3593733,
    36.2466518,
    29.3593733,
    36.2466518
  ],
  "description": "Eren Tepe.",
  "names": [
    "Patara"
  ],
  "features": [
    {
      "type": "Feature",
      "geometry": {
        "type": "Point",
        "coordinates": [
          29.3593733,
          36.2466518
        ]
      },
      "properties": {
        "description": "representative point"
      }
    },
    {
      "geometry": {
        "type": "Point",
        "coordinates": [
          29.3593733,
          36.2466518
        ]
      },
      "id": "osm-node-310368008",
      "type": "Feature",
      "properties": {
        "description": "Location based on OpenStreetMap.",
        "location_precision": "precise",
        "title": "location of unnamed peak of Patara Mons.",
        "link": "http://pleiades.stoa.org/places/639041/osm-node-310368008"
      }
    }
  ]
}