{
  "type": "FeatureCollection",
  "title": "Morka",
  "id": "639001",
  "bbox": [
    30.79518,
    37.11455,
    30.79518,
    37.11455
  ],
  "description": "An ancient place, cited: BAtlas 65 E3 Morka",
  "names": [
    "Morka"
  ],
  "features": [
    {
      "type": "Feature",
      "geometry": {
        "type": "Point",
        "coordinates": [
          30.79518,
          37.11455
        ]
      },
      "properties": {
        "description": "representative point"
      }
    },
    {
      "geometry": {
        "type": "Point",
        "coordinates": [
          30.79518,
          37.11455
        ]
      },
      "id": "darmc-location-1345",
      "type": "Feature",
      "properties": {
        "description": "TIB point location",
        "location_precision": "precise",
        "title": "DARMC location 1345",
        "link": "http://pleiades.stoa.org/places/639001/darmc-location-1345"
      }
    }
  ]
}