{
  "type": "FeatureCollection",
  "title": "*Orokenda",
  "id": "639024",
  "bbox": [
    31.577604,
    36.86004,
    31.599211,
    36.869584
  ],
  "description": "An ancient place, cited: BAtlas 65 G4 *Orokenda",
  "names": [
    "Orokenda"
  ],
  "features": [
    {
      "type": "Feature",
      "geometry": {
        "type": "Point",
        "coordinates": [
          31.5884075,
          36.864812
        ]
      },
      "properties": {
        "description": "representative point"
      }
    },
    {
      "geometry": {
        "type": "Point",
        "coordinates": [
          31.577604,
          36.869584
        ]
      },
      "id": "darmc-location-1454",
      "type": "Feature",
      "properties": {
        "description": "TIB point location",
        "location_precision": "precise",
        "title": "DARMC location 1454",
        "link": "http://pleiades.stoa.org/places/639024/darmc-location-1454"
      }
    },
    {
      "geometry": {
        "type": "Point",
        "coordinates": [
          31.599211,
          36.86004
        ]
      },
      "id": "darmc-location-5389",
      "type": "Feature",
      "properties": {
        "description": "500K scale point location",
        "location_precision": "precise",
        "title": "DARMC location 5389",
        "link": "http://pleiades.stoa.org/places/639024/darmc-location-5389"
      }
    }
  ]
}