{
  "type": "FeatureCollection",
  "title": "Pedalion/Ankon Pr.",
  "id": "639045",
  "bbox": [
    28.859534,
    36.597739,
    28.859534,
    36.597739
  ],
  "description": "An ancient place, cited: BAtlas 65 A4 Pedalion/Ankon Pr.",
  "names": [
    "Pedalion",
    "Ankon Pr."
  ],
  "features": [
    {
      "type": "Feature",
      "geometry": {
        "type": "Point",
        "coordinates": [
          28.859534,
          36.597739
        ]
      },
      "properties": {
        "description": "representative point"
      }
    },
    {
      "geometry": {
        "type": "Point",
        "coordinates": [
          28.859534,
          36.597739
        ]
      },
      "id": "osm-location",
      "type": "Feature",
      "properties": {
        "description": "Representative location based on OpenStreetMap.",
        "location_precision": "precise",
        "title": "OSM location of Pedalion/Ankon Pr.",
        "link": "http://pleiades.stoa.org/places/639045/osm-location"
      }
    }
  ]
}