{
  "type": "FeatureCollection",
  "title": "Soura",
  "id": "639118",
  "bbox": [
    29.935258,
    36.244938,
    29.944004,
    36.257049
  ],
  "description": "An ancient place, cited: BAtlas 65 C5 Soura",
  "names": [
    "Soura"
  ],
  "features": [
    {
      "type": "Feature",
      "geometry": {
        "type": "Point",
        "coordinates": [
          29.939631,
          36.2509935
        ]
      },
      "properties": {
        "description": "representative point"
      }
    },
    {
      "geometry": {
        "type": "Point",
        "coordinates": [
          29.935258,
          36.257049
        ]
      },
      "id": "darmc-location-2815",
      "type": "Feature",
      "properties": {
        "description": "TIB point location",
        "location_precision": "precise",
        "title": "DARMC location 2815",
        "link": "http://pleiades.stoa.org/places/639118/darmc-location-2815"
      }
    },
    {
      "geometry": {
        "type": "Point",
        "coordinates": [
          29.944004,
          36.244938
        ]
      },
      "id": "dare-location",
      "type": "Feature",
      "properties": {
        "description": "Representative point location, site precision",
        "location_precision": "precise",
        "title": "DARE Location",
        "link": "http://pleiades.stoa.org/places/639118/dare-location"
      }
    }
  ]
}