{
  "type": "FeatureCollection",
  "title": "Tetrapyrgia",
  "id": "639142",
  "bbox": [
    30.8498,
    36.8892,
    30.8498,
    36.8892
  ],
  "description": "An ancient place, cited: BAtlas 65 E4 Tetrapyrgia",
  "names": [
    "Tetrapyrgia"
  ],
  "features": [
    {
      "type": "Feature",
      "geometry": {
        "type": "Point",
        "coordinates": [
          30.8498,
          36.8892
        ]
      },
      "properties": {
        "description": "representative point"
      }
    },
    {
      "geometry": {
        "type": "Point",
        "coordinates": [
          30.8498,
          36.8892
        ]
      },
      "id": "batlas-location",
      "type": "Feature",
      "properties": {
        "description": null,
        "location_precision": "precise",
        "title": "Barrington Atlas map location",
        "link": "http://pleiades.stoa.org/places/639142/batlas-location"
      }
    }
  ]
}