{
  "type": "FeatureCollection",
  "title": "Uzunkale",
  "id": "639162",
  "description": "An ancient place, cited: BAtlas 65 G4 Uzunkale",
  "bbox": [
    31.58734,
    36.7661,
    31.5907,
    36.766255
  ],
  "reprPoint": [
    31.58902,
    36.7661775
  ],
  "features": [
    {
      "geometry": {
        "type": "Point",
        "coordinates": [
          31.58734,
          36.766255
        ]
      },
      "id": "darmc-location-8409",
      "type": "Feature",
      "properties": {
        "description": "500K scale point location",
        "location_precision": "precise",
        "title": "DARMC location 8409",
        "link": "http://pleiades.stoa.org/places/639162/darmc-location-8409"
      }
    }
  ]
}