{
  "type": "FeatureCollection",
  "title": "Xenagori (islands)",
  "id": "639168",
  "description": "An ancient place, cited: BAtlas 65 B5 Xenagori Inss.",
  "bbox": [
    29.347183,
    36.209215,
    29.445966,
    36.21965
  ],
  "reprPoint": [
    29.3882456667,
    36.2149925667
  ],
  "names": [
    "Xenagori"
  ],
  "features": [
    {
      "geometry": {
        "type": "Point",
        "coordinates": [
          29.371588,
          36.21965
        ]
      },
      "id": "mouse-island",
      "type": "Feature",
      "properties": {
        "description": "Representative location based on OpenStreetMap; Part of Xenagori Inss.",
        "location_precision": "precise",
        "title": "OSM location of Mouse island",
        "link": "http://pleiades.stoa.org/places/639168/mouse-island"
      }
    },
    {
      "geometry": {
        "type": "Point",
        "coordinates": [
          29.347183,
          36.209215
        ]
      },
      "id": "snake-island",
      "type": "Feature",
      "properties": {
        "description": "Representative location based on OpenStreetMap. Part of Xenagori Inss.",
        "location_precision": "precise",
        "title": "OSM location of Snake island",
        "link": "http://pleiades.stoa.org/places/639168/snake-island"
      }
    },
    {
      "geometry": {
        "type": "Point",
        "coordinates": [
          29.445966,
          36.2161127
        ]
      },
      "id": "bogazc131k-adas131",
      "type": "Feature",
      "properties": {
        "description": "Representative location based on OpenStreetMap. Part of Xenagori Inss.",
        "location_precision": "precise",
        "title": "OSM location of Boğazcık Adası",
        "link": "http://pleiades.stoa.org/places/639168/bogazc131k-adas131"
      }
    }
  ]
}