{
  "type": "FeatureCollection",
  "title": "Limyra Bridge",
  "id": "640246",
  "bbox": [
    30.21186,
    36.350935,
    30.21186,
    36.350935
  ],
  "description": "A late-Roman bridge, ancient name unknown, located near the ancient city of Limyra in modern Turkey.",
  "names": [
    "Kırk Göz Kemeri"
  ],
  "features": [
    {
      "type": "Feature",
      "geometry": {
        "type": "Point",
        "coordinates": [
          30.21186,
          36.350935
        ]
      },
      "properties": {
        "description": "representative point"
      }
    },
    {
      "geometry": {
        "type": "Point",
        "coordinates": [
          30.21186,
          36.350935
        ]
      },
      "id": "darmc-location-14634",
      "type": "Feature",
      "properties": {
        "description": "500K scale point location",
        "location_precision": "precise",
        "title": "DARMC location 14634",
        "link": "http://pleiades.stoa.org/places/640246/darmc-location-14634"
      }
    }
  ]
}