{
  "type": "FeatureCollection",
  "title": "Avezzano Roman villa",
  "id": "640346165",
  "bbox": [
    13.4065936,
    42.0464996,
    13.4065936,
    42.0464996
  ],
  "description": "A large Roman villa near Alba Fucens that originates in the second century B.C.",
  "features": [
    {
      "type": "Feature",
      "geometry": {
        "type": "Point",
        "coordinates": [
          13.4065936,
          42.0464996
        ]
      },
      "properties": {
        "description": "representative point"
      }
    },
    {
      "geometry": {
        "type": "Point",
        "coordinates": [
          13.4065936,
          42.0464996
        ]
      },
      "id": "osm-location-of-villa",
      "type": "Feature",
      "properties": {
        "description": "Representative location based on OpenStreetMap.",
        "location_precision": "precise",
        "title": "OSM location of Villa romana di Avezzano",
        "link": "http://pleiades.stoa.org/places/640346165/osm-location-of-villa"
      }
    }
  ]
}