{
  "type": "FeatureCollection",
  "title": "Meinarti (island)",
  "id": "640960995",
  "bbox": [
    30.577778,
    21.006944,
    30.577778,
    21.006944
  ],
  "description": "Meinarti Island is located in the Nile River north of the Second Cataract. It lies just upstream of the Sudanese border town of Wadi Halfa.",
  "connectsWith": [
    "727172"
  ],
  "features": [
    {
      "type": "Feature",
      "geometry": {
        "type": "Point",
        "coordinates": [
          30.577778,
          21.006944
        ]
      },
      "properties": {
        "description": "representative point"
      }
    },
    {
      "geometry": {
        "type": "Point",
        "coordinates": [
          30.577778,
          21.006944
        ]
      },
      "id": "osm-location-of-meinarti-island",
      "type": "Feature",
      "properties": {
        "description": "Location based on OpenStreetMap",
        "location_precision": "precise",
        "title": "OSM location of Meinarti Island",
        "link": "http://pleiades.stoa.org/places/640960995/osm-location-of-meinarti-island"
      }
    }
  ]
}