{
  "type": "FeatureCollection",
  "title": "Castromaior",
  "id": "641265240",
  "bbox": [
    -7.7195669,
    42.8335316,
    -7.7195669,
    42.8335316
  ],
  "description": "An Iron Age oppidum.",
  "features": [
    {
      "type": "Feature",
      "geometry": {
        "type": "Point",
        "coordinates": [
          -7.7195669,
          42.8335316
        ]
      },
      "properties": {
        "description": "representative point"
      }
    },
    {
      "geometry": {
        "type": "Point",
        "coordinates": [
          -7.7195669,
          42.8335316
        ]
      },
      "id": "osm-location",
      "type": "Feature",
      "properties": {
        "description": "Representative location based on OpenStreetMap.",
        "location_precision": "precise",
        "title": "OSM location of Castromaior",
        "link": "http://pleiades.stoa.org/places/641265240/osm-location"
      }
    }
  ]
}