{
  "type": "FeatureCollection",
  "title": "Fortifications at Civita di Artena",
  "id": "645857331",
  "bbox": [
    12.9104681,
    41.7281082,
    12.9104681,
    41.7281082
  ],
  "description": "The polygonal masonry fortifications of the ancient settlement now known as Civita di Artena. These fortifications today measure more than 2.5 km in length.",
  "connectsWith": [
    "795348768"
  ],
  "features": [
    {
      "type": "Feature",
      "geometry": {
        "type": "Point",
        "coordinates": [
          12.9104681,
          41.7281082
        ]
      },
      "properties": {
        "description": "representative point"
      }
    },
    {
      "geometry": {
        "type": "Point",
        "coordinates": [
          12.9104681,
          41.7281082
        ]
      },
      "id": "location-of-polygonal-masonry-fortifications",
      "type": "Feature",
      "properties": {
        "description": "Location based on OpenStreetMap",
        "location_precision": "precise",
        "title": "OSM location of polygonal masonry fortifications",
        "link": "http://pleiades.stoa.org/places/645857331/location-of-polygonal-masonry-fortifications"
      }
    }
  ]
}