{
  "type": "FeatureCollection",
  "title": "Dülük Baba Tepesi",
  "id": "647277379",
  "bbox": [
    37.343957,
    37.1281384,
    37.343957,
    37.1281384
  ],
  "description": "A mountain in Türkiye rising to 176 meters (577 feet) above sea level.",
  "features": [
    {
      "type": "Feature",
      "geometry": {
        "type": "Point",
        "coordinates": [
          37.343957,
          37.1281384
        ]
      },
      "properties": {
        "description": "representative point"
      }
    },
    {
      "geometry": {
        "type": "Point",
        "coordinates": [
          37.343957,
          37.1281384
        ]
      },
      "id": "osm-location-of-da1-4la1-4k-baba-tepesi",
      "type": "Feature",
      "properties": {
        "description": "Location based on OpenStreetMap",
        "location_precision": "precise",
        "title": "OSM location of Dülük Baba Tepesi",
        "link": "http://pleiades.stoa.org/places/647277379/osm-location-of-da1-4la1-4k-baba-tepesi"
      }
    }
  ]
}