{
  "type": "FeatureCollection",
  "title": "Ariaramneia/[Rodandos]",
  "id": "648569",
  "description": "An ancient place, cited: BAtlas 66 G1 Ariaramneia/[Rodandos]",
  "bbox": [
    35.450209,
    37.899123,
    35.506572,
    37.915125
  ],
  "reprPoint": [
    35.482917575,
    37.909324225
  ],
  "names": [
    "Ariaramneia",
    "Rodandos"
  ],
  "features": [
    {
      "geometry": {
        "type": "Point",
        "coordinates": [
          35.48985,
          37.908862
        ]
      },
      "id": "darmc-location-2554",
      "type": "Feature",
      "properties": {
        "description": "TIB point location",
        "location_precision": "precise",
        "title": "DARMC location 2554",
        "link": "http://pleiades.stoa.org/places/648569/darmc-location-2554"
      }
    },
    {
      "geometry": {
        "type": "Point",
        "coordinates": [
          35.506572,
          37.915125
        ]
      },
      "id": "darmc-location-3341",
      "type": "Feature",
      "properties": {
        "description": "500K scale point location",
        "location_precision": "precise",
        "title": "DARMC location 3341",
        "link": "http://pleiades.stoa.org/places/648569/darmc-location-3341"
      }
    },
    {
      "geometry": {
        "type": "Point",
        "coordinates": [
          35.450209,
          37.899123
        ]
      },
      "id": "darmc-location-3342",
      "type": "Feature",
      "properties": {
        "description": "500K scale point location",
        "location_precision": "precise",
        "title": "DARMC location 3342",
        "link": "http://pleiades.stoa.org/places/648569/darmc-location-3342"
      }
    },
    {
      "geometry": {
        "type": "Point",
        "coordinates": [
          35.485039299999926,
          37.9141869
        ]
      },
      "id": "dare-location",
      "type": "Feature",
      "properties": {
        "description": "Representative point location, village precision",
        "location_precision": "precise",
        "title": "DARE Location",
        "link": "http://pleiades.stoa.org/places/648569/dare-location"
      }
    }
  ]
}