{
  "type": "FeatureCollection",
  "title": "Antiochia Castellum",
  "id": "648559",
  "description": "An ancient place, cited: BAtlas 66 B3 Antiochia Castellum",
  "bbox": [
    32.992877,
    36.942744,
    32.992877,
    36.942744
  ],
  "reprPoint": [
    32.992877,
    36.942744
  ],
  "names": [
    "Antiochia Castellum"
  ],
  "features": [
    {
      "geometry": {
        "type": "Point",
        "coordinates": [
          32.992877,
          36.942744
        ]
      },
      "id": "darmc-location-6226",
      "type": "Feature",
      "properties": {
        "description": "500K scale point location",
        "location_precision": "precise",
        "title": "DARMC location 6226",
        "link": "http://pleiades.stoa.org/places/648559/darmc-location-6226"
      }
    }
  ]
}