{
  "type": "FeatureCollection",
  "title": "Bıçkıcı Kalesi",
  "id": "648586",
  "description": "An ancient place, cited: BAtlas 66 A4 Bıçkıcı Kalesi",
  "bbox": [
    32.28411,
    36.282346,
    32.28411,
    36.282346
  ],
  "reprPoint": [
    32.28411,
    36.282346
  ],
  "features": [
    {
      "geometry": {
        "type": "Point",
        "coordinates": [
          32.28411,
          36.282346
        ]
      },
      "id": "darmc-location-4999",
      "type": "Feature",
      "properties": {
        "description": "500K scale point location",
        "location_precision": "precise",
        "title": "DARMC location 4999",
        "link": "http://pleiades.stoa.org/places/648586/darmc-location-4999"
      }
    }
  ]
}