{
  "type": "FeatureCollection",
  "title": "Caena",
  "id": "648592",
  "bbox": [
    34.842479,
    37.531389,
    34.842479,
    37.531389
  ],
  "description": "An ancient place, cited: BAtlas 66 F1 Caena",
  "names": [
    "Caena"
  ],
  "features": [
    {
      "type": "Feature",
      "geometry": {
        "type": "Point",
        "coordinates": [
          34.842479,
          37.531389
        ]
      },
      "properties": {
        "description": "representative point"
      }
    },
    {
      "geometry": {
        "type": "Point",
        "coordinates": [
          34.842479,
          37.531389
        ]
      },
      "id": "darmc-location-2856",
      "type": "Feature",
      "properties": {
        "description": "500K scale point location",
        "location_precision": "precise",
        "title": "DARMC location 2856",
        "link": "http://pleiades.stoa.org/places/648592/darmc-location-2856"
      }
    }
  ]
}