{
  "type": "FeatureCollection",
  "title": "Korasion/Kalon Korakesion",
  "id": "648679",
  "description": "An ancient place, cited: BAtlas 66 E4 Korasion/Kalon Korakesion",
  "bbox": [
    34.077331,
    36.414566,
    34.10005,
    36.427489
  ],
  "reprPoint": [
    34.0886905,
    36.4210275
  ],
  "names": [
    "Korasion",
    "Kalon Korakesion"
  ],
  "features": [
    {
      "geometry": {
        "type": "Point",
        "coordinates": [
          34.077331,
          36.414566
        ]
      },
      "id": "darmc-location-1913",
      "type": "Feature",
      "properties": {
        "description": "TIB point location",
        "location_precision": "precise",
        "title": "DARMC location 1913",
        "link": "http://pleiades.stoa.org/places/648679/darmc-location-1913"
      }
    },
    {
      "geometry": {
        "type": "Point",
        "coordinates": [
          34.10005,
          36.427489
        ]
      },
      "id": "darmc-location-4169",
      "type": "Feature",
      "properties": {
        "description": "500K scale point location",
        "location_precision": "precise",
        "title": "DARMC location 4169",
        "link": "http://pleiades.stoa.org/places/648679/darmc-location-4169"
      }
    }
  ]
}