{
  "type": "FeatureCollection",
  "title": "Lamatorma",
  "id": "648689",
  "description": "An ancient place, cited: BAtlas 66 C3 Lamatorma",
  "bbox": [
    32.990007,
    36.699573,
    33.04244,
    36.770169
  ],
  "reprPoint": [
    33.0162235,
    36.734871
  ],
  "names": [
    "Lamatorma"
  ],
  "features": [
    {
      "geometry": {
        "type": "Point",
        "coordinates": [
          33.04244,
          36.699573
        ]
      },
      "id": "darmc-location-6706",
      "type": "Feature",
      "properties": {
        "description": "500K scale point location",
        "location_precision": "precise",
        "title": "DARMC location 6706",
        "link": "http://pleiades.stoa.org/places/648689/darmc-location-6706"
      }
    },
    {
      "geometry": {
        "type": "Point",
        "coordinates": [
          32.990007,
          36.770169
        ]
      },
      "id": "darmc-location-12037",
      "type": "Feature",
      "properties": {
        "description": "TIB point location",
        "location_precision": "precise",
        "title": "DARMC location 12037",
        "link": "http://pleiades.stoa.org/places/648689/darmc-location-12037"
      }
    }
  ]
}