{
  "type": "FeatureCollection",
  "title": "Lauzadeai",
  "id": "648695",
  "description": "An ancient place, cited: BAtlas 66 B3 Lauzadeai",
  "bbox": [
    32.673291,
    36.745013,
    32.722284,
    36.7599
  ],
  "reprPoint": [
    32.6977875,
    36.7524565
  ],
  "names": [
    "Lauzadeai",
    "Lauzados"
  ],
  "features": [
    {
      "geometry": {
        "type": "Point",
        "coordinates": [
          32.673291,
          36.7599
        ]
      },
      "id": "darmc-location-4237",
      "type": "Feature",
      "properties": {
        "description": "TIB point location",
        "location_precision": "precise",
        "title": "DARMC location 4237",
        "link": "http://pleiades.stoa.org/places/648695/darmc-location-4237"
      }
    },
    {
      "geometry": {
        "type": "Point",
        "coordinates": [
          32.722284,
          36.745013
        ]
      },
      "id": "darmc-location-13428",
      "type": "Feature",
      "properties": {
        "description": "500K scale point location",
        "location_precision": "precise",
        "title": "DARMC location 13428",
        "link": "http://pleiades.stoa.org/places/648695/darmc-location-13428"
      }
    }
  ]
}