{
  "type": "FeatureCollection",
  "title": "Selinous/Traianopolis",
  "id": "648772",
  "bbox": [
    32.282734,
    36.258509,
    32.282734,
    36.258509
  ],
  "description": "Selinous/Traianopolis was a city of Cilicia Aspera and counted among the chief coastal cities of Cilicia. It is perhaps best known as the place where Trajan died in A.D. 117 en route to Rome from his campaigns in the East.",
  "names": [
    "Selinous",
    "Traianopolis",
    "Selinitis"
  ],
  "features": [
    {
      "type": "Feature",
      "geometry": {
        "type": "Point",
        "coordinates": [
          32.282734,
          36.258509
        ]
      },
      "properties": {
        "description": "representative point"
      }
    },
    {
      "geometry": {
        "type": "Point",
        "coordinates": [
          32.282734,
          36.258509
        ]
      },
      "id": "dare-location",
      "type": "Feature",
      "properties": {
        "description": "Representative point location, site precision",
        "location_precision": "precise",
        "title": "DARE Location",
        "link": "http://pleiades.stoa.org/places/648772/dare-location"
      }
    }
  ]
}