{
  "type": "FeatureCollection",
  "title": "Thebasa?",
  "id": "648794",
  "description": "An ancient place, cited: BAtlas 66 D2 Thebasa?",
  "bbox": [
    33.836559,
    37.293682,
    33.836559,
    37.293682
  ],
  "reprPoint": [
    33.836559,
    37.293682
  ],
  "names": [
    "Thebasa"
  ],
  "features": [
    {
      "geometry": {
        "type": "Point",
        "coordinates": [
          33.836559,
          37.293682
        ]
      },
      "id": "darmc-location-6313",
      "type": "Feature",
      "properties": {
        "description": "500K scale point location",
        "location_precision": "precise",
        "title": "DARMC location 6313",
        "link": "http://pleiades.stoa.org/places/648794/darmc-location-6313"
      }
    }
  ]
}