{
  "type": "FeatureCollection",
  "title": "Panhormus?/Pylai",
  "id": "648731",
  "bbox": [
    34.793543,
    37.210512,
    34.826894,
    37.269648
  ],
  "description": "An ancient place, cited: BAtlas 66 F2 Panhormus?/Pylai",
  "names": [
    "Panhormus",
    "Pylai"
  ],
  "features": [
    {
      "type": "Feature",
      "geometry": {
        "type": "Point",
        "coordinates": [
          34.8102185,
          37.24008
        ]
      },
      "properties": {
        "description": "representative point"
      }
    },
    {
      "geometry": {
        "type": "Point",
        "coordinates": [
          34.793543,
          37.269648
        ]
      },
      "id": "darmc-location-4476",
      "type": "Feature",
      "properties": {
        "description": "TIB point location",
        "location_precision": "precise",
        "title": "DARMC location 4476",
        "link": "http://pleiades.stoa.org/places/648731/darmc-location-4476"
      }
    },
    {
      "geometry": {
        "type": "Point",
        "coordinates": [
          34.826894,
          37.210512
        ]
      },
      "id": "darmc-location-9691",
      "type": "Feature",
      "properties": {
        "description": "500K scale point location",
        "location_precision": "precise",
        "title": "DARMC location 9691",
        "link": "http://pleiades.stoa.org/places/648731/darmc-location-9691"
      }
    }
  ]
}