{
  "type": "FeatureCollection",
  "title": "Syedra",
  "id": "648783",
  "description": "An ancient place, cited: BAtlas 66 A4 Syedra",
  "bbox": [
    32.145034,
    36.392707,
    32.193497,
    36.44606
  ],
  "reprPoint": [
    32.1620616667,
    36.4272943333
  ],
  "names": [
    "Syedra",
    "Syagra"
  ],
  "features": [
    {
      "geometry": {
        "type": "Point",
        "coordinates": [
          32.145034,
          36.443116
        ]
      },
      "id": "darmc-location-1415",
      "type": "Feature",
      "properties": {
        "description": "TIB point location",
        "location_precision": "precise",
        "title": "DARMC location 1415",
        "link": "http://pleiades.stoa.org/places/648783/darmc-location-1415"
      }
    },
    {
      "geometry": {
        "type": "Point",
        "coordinates": [
          32.193497,
          36.392707
        ]
      },
      "id": "darmc-location-6104",
      "type": "Feature",
      "properties": {
        "description": "500K scale point location",
        "location_precision": "precise",
        "title": "DARMC location 6104",
        "link": "http://pleiades.stoa.org/places/648783/darmc-location-6104"
      }
    },
    {
      "geometry": {
        "type": "Point",
        "coordinates": [
          32.147654,
          36.44606
        ]
      },
      "id": "dare-location",
      "type": "Feature",
      "properties": {
        "description": "Representative point location, site precision",
        "location_precision": "precise",
        "title": "DARE Location",
        "link": "http://pleiades.stoa.org/places/648783/dare-location"
      }
    }
  ]
}