{
  "type": "FeatureCollection",
  "title": "Myous?/Myanda?",
  "id": "648715",
  "bbox": [
    33.291762,
    36.137152,
    33.291762,
    36.137152
  ],
  "description": "An ancient place, cited: BAtlas 66 C4 Myous?/Myanda?",
  "names": [
    "Myous",
    "Myanda"
  ],
  "features": [
    {
      "type": "Feature",
      "geometry": {
        "type": "Point",
        "coordinates": [
          33.291762,
          36.137152
        ]
      },
      "properties": {
        "description": "representative point"
      }
    },
    {
      "geometry": {
        "type": "Point",
        "coordinates": [
          33.291762,
          36.137152
        ]
      },
      "id": "darmc-location-5040",
      "type": "Feature",
      "properties": {
        "description": "500K scale point location",
        "location_precision": "precise",
        "title": "DARMC location 5040",
        "link": "http://pleiades.stoa.org/places/648715/darmc-location-5040"
      }
    }
  ]
}