{
  "type": "FeatureCollection",
  "title": "*Mourisa",
  "id": "648711",
  "bbox": [
    32.375673,
    37.436126,
    32.375673,
    37.436126
  ],
  "description": "An ancient place, cited: BAtlas 66 A2 *Mourisa",
  "names": [
    "Mourisa"
  ],
  "features": [
    {
      "type": "Feature",
      "geometry": {
        "type": "Point",
        "coordinates": [
          32.375673,
          37.436126
        ]
      },
      "properties": {
        "description": "representative point"
      }
    },
    {
      "geometry": {
        "type": "Point",
        "coordinates": [
          32.375673,
          37.436126
        ]
      },
      "id": "darmc-location-13819",
      "type": "Feature",
      "properties": {
        "description": "500K scale point location",
        "location_precision": "precise",
        "title": "DARMC location 13819",
        "link": "http://pleiades.stoa.org/places/648711/darmc-location-13819"
      }
    }
  ]
}