{
  "type": "FeatureCollection",
  "title": "Selinous/Traianopolis",
  "id": "648772",
  "description": "Selinous/Traianopolis was a city of Cilicia Aspera and counted among the chief coastal cities of Cilicia. It is perhaps best known as the place where Trajan died in A.D. 117 en route to Rome from his campaigns in the East.",
  "bbox": [
    32.282734,
    36.258509,
    32.282734,
    36.258509
  ],
  "reprPoint": [
    32.282734,
    36.258509
  ],
  "names": [
    "Selinous",
    "Traianopolis",
    "Selinitis"
  ],
  "features": [
    {
      "geometry": {
        "type": "Point",
        "coordinates": [
          32.308436,
          36.267471
        ]
      },
      "id": "darmc-location-1463",
      "type": "Feature",
      "properties": {
        "description": "TIB point location",
        "location_precision": "precise",
        "title": "DARMC location 1463",
        "link": "http://pleiades.stoa.org/places/648772/darmc-location-1463"
      }
    },
    {
      "geometry": {
        "type": "Point",
        "coordinates": [
          32.290964,
          36.255427
        ]
      },
      "id": "darmc-location-4882",
      "type": "Feature",
      "properties": {
        "description": "500K scale point location",
        "location_precision": "precise",
        "title": "DARMC location 4882",
        "link": "http://pleiades.stoa.org/places/648772/darmc-location-4882"
      }
    },
    {
      "geometry": {
        "type": "Point",
        "coordinates": [
          32.282734,
          36.258509
        ]
      },
      "id": "dare-location",
      "type": "Feature",
      "properties": {
        "description": "Representative point location, site precision",
        "location_precision": "precise",
        "title": "DARE Location",
        "link": "http://pleiades.stoa.org/places/648772/dare-location"
      }
    }
  ]
}