{
  "type": "FeatureCollection",
  "title": "Syedra",
  "id": "648783",
  "description": "A site in Cilicia Aspera near Demirtaş.",
  "bbox": [
    32.147654,
    36.44606,
    32.147654,
    36.44606
  ],
  "reprPoint": [
    32.147654,
    36.44606
  ],
  "names": [
    "Syedra",
    "Syagra"
  ],
  "features": [
    {
      "geometry": {
        "type": "Point",
        "coordinates": [
          32.145034,
          36.443116
        ]
      },
      "id": "darmc-location-1415",
      "type": "Feature",
      "properties": {
        "description": "TIB point location",
        "location_precision": "precise",
        "title": "DARMC location 1415",
        "link": "http://pleiades.stoa.org/places/648783/darmc-location-1415"
      }
    },
    {
      "geometry": {
        "type": "Point",
        "coordinates": [
          32.147654,
          36.44606
        ]
      },
      "id": "dare-location",
      "type": "Feature",
      "properties": {
        "description": "Representative point location, site precision",
        "location_precision": "precise",
        "title": "DARE Location",
        "link": "http://pleiades.stoa.org/places/648783/dare-location"
      }
    }
  ]
}