{
  "type": "FeatureCollection",
  "title": "Pityoussa/Petrossa? (island)",
  "id": "648739",
  "description": "An ancient place, cited: BAtlas 66 D4 Pityoussa/Petrossa? Ins.",
  "bbox": [
    33.769398,
    36.189342,
    33.769398,
    36.189342
  ],
  "reprPoint": [
    33.769398,
    36.189342
  ],
  "names": [
    "Pityoussa",
    "Petrossa"
  ],
  "features": [
    {
      "geometry": {
        "type": "Point",
        "coordinates": [
          33.769398,
          36.189342
        ]
      },
      "id": "dare-location",
      "type": "Feature",
      "properties": {
        "description": "Representative point location, village precision",
        "location_precision": "precise",
        "title": "DARE Location",
        "link": "http://pleiades.stoa.org/places/648739/dare-location"
      }
    }
  ]
}