{
  "type": "FeatureCollection",
  "title": "City Eleusinion at Athens",
  "id": "650003009",
  "description": "The City Eleusinion was one of the most important sanctuaries in the religious life of ancient Athens.  It was the urban “branch” of the sanctuary of Demeter and Kore at Eleusis in use during the Archaic and Classical periods.",
  "bbox": [
    23.7247805,
    37.9728361,
    23.7247805,
    37.9728361
  ],
  "connectsWith": [
    "aef8271177d5afba233b2b97dcb52af4"
  ],
  "reprPoint": [
    23.7247805,
    37.9728361
  ],
  "names": [
    "Eleusinion",
    "Eleusínio en astei",
    "City Eleusinion"
  ],
  "features": [
    {
      "geometry": {
        "type": "Point",
        "coordinates": [
          23.7247805,
          37.9728361
        ]
      },
      "id": "osm-location-of-the-city-eleusinion",
      "type": "Feature",
      "properties": {
        "description": "Representative location based on a way derived from OpenStreetMap. Chronology following Miles 1998.",
        "location_precision": "precise",
        "title": "OSM location of the City Eleusinion",
        "link": "http://pleiades.stoa.org/places/650003009/osm-location-of-the-city-eleusinion"
      }
    }
  ]
}