{
  "type": "FeatureCollection",
  "title": "Untitled",
  "id": "650057",
  "bbox": [
    32.81928,
    36.058178,
    32.81928,
    36.058178
  ],
  "description": "An ancient place, cited: BAtlas 66 B4 unnamed bridge (N Anemurium)",
  "features": [
    {
      "type": "Feature",
      "geometry": {
        "type": "Point",
        "coordinates": [
          32.81928,
          36.058178
        ]
      },
      "properties": {
        "description": "representative point"
      }
    },
    {
      "geometry": {
        "type": "Point",
        "coordinates": [
          32.81928,
          36.058178
        ]
      },
      "id": "darmc-location-14723",
      "type": "Feature",
      "properties": {
        "description": "500K scale point location",
        "location_precision": "precise",
        "title": "DARMC location 14723",
        "link": "http://pleiades.stoa.org/places/650057/darmc-location-14723"
      }
    }
  ]
}