{
  "type": "FeatureCollection",
  "title": "Alişar Höyük",
  "id": "650309285",
  "bbox": [
    35.2614,
    39.6059,
    35.261528,
    39.606111
  ],
  "description": "A settlement with occupation from the Chalcolithic period (fourth millennium B.C.) until the Phrygian period (first millennium B.C.).",
  "connectsWith": [
    "837"
  ],
  "names": [
    "Alişar Hüyük"
  ],
  "features": [
    {
      "type": "Feature",
      "geometry": {
        "type": "Point",
        "coordinates": [
          35.261464,
          39.6060055
        ]
      },
      "properties": {
        "description": "representative point"
      }
    },
    {
      "geometry": {
        "type": "Point",
        "coordinates": [
          35.261528,
          39.606111
        ]
      },
      "id": "alisar-hoeyuk",
      "type": "Feature",
      "properties": {
        "description": "A site occupied from the Chalcolithic period in the fourth millennium BC until the Phrygian period in the first millennium BC.",
        "location_precision": "precise",
        "title": "Alişar Höyük",
        "link": "http://pleiades.stoa.org/places/650309285/alisar-hoeyuk"
      }
    },
    {
      "geometry": {
        "type": "Point",
        "coordinates": [
          35.2614,
          39.6059
        ]
      },
      "id": "cigs-location-of-alisar-huyuk",
      "type": "Feature",
      "properties": {
        "description": null,
        "location_precision": "precise",
        "title": "CIGS location of Alişar Hüyük",
        "link": "http://pleiades.stoa.org/places/650309285/cigs-location-of-alisar-huyuk"
      }
    }
  ]
}