{
  "type": "FeatureCollection",
  "title": "Alişar Höyük",
  "id": "650309285",
  "description": "A settlement with occupation from the Chalcolithic period (fourth millennium BC) until the Phrygian period (first millennium BC)",
  "bbox": [
    35.261528,
    39.606111,
    35.261528,
    39.606111
  ],
  "connectsWith": [
    "837"
  ],
  "reprPoint": [
    35.261528,
    39.606111
  ],
  "features": [
    {
      "geometry": {
        "type": "Point",
        "coordinates": [
          35.261528,
          39.606111
        ]
      },
      "id": "alisar-hoeyuk",
      "type": "Feature",
      "properties": {
        "description": "A site occupied from the Chalcolithic period in the fourth millennium BC until the Phrygian period in the first millennium BC.",
        "location_precision": "precise",
        "title": "Alişar Höyük",
        "link": "http://pleiades.stoa.org/places/650309285/alisar-hoeyuk"
      }
    }
  ]
}