{
  "type": "FeatureCollection",
  "title": "Branston Roman villa",
  "id": "651422974",
  "bbox": [
    -0.497685,
    53.189674,
    -0.497685,
    53.189674
  ],
  "description": "The site of a probable Roman villa, associated with findspot of RIB 3179.",
  "features": [
    {
      "type": "Feature",
      "geometry": {
        "type": "Point",
        "coordinates": [
          -0.497685,
          53.189674
        ]
      },
      "properties": {
        "description": "representative point"
      }
    },
    {
      "geometry": {
        "type": "Point",
        "coordinates": [
          -0.497685,
          53.189674
        ]
      },
      "id": "osm-location-of-branston-roman-villa",
      "type": "Feature",
      "properties": {
        "description": "Representative location based on OpenStreetMap.",
        "location_precision": "precise",
        "title": "OSM location of Branston Roman villa",
        "link": "http://pleiades.stoa.org/places/651422974/osm-location-of-branston-roman-villa"
      }
    }
  ]
}