{
  "type": "FeatureCollection",
  "title": "Unnamed Place",
  "id": "6521781351211310",
  "bbox": [
    31.131,
    37.8135,
    31.131,
    37.8135
  ],
  "description": "An unnamed ancient place",
  "features": [
    {
      "type": "Feature",
      "geometry": {
        "type": "Point",
        "coordinates": [
          31.131,
          37.8135
        ]
      },
      "properties": {
        "description": "representative point"
      }
    },
    {
      "geometry": {
        "type": "Point",
        "coordinates": [
          31.131,
          37.8135
        ]
      },
      "id": "batlas-location",
      "type": "Feature",
      "properties": {
        "description": null,
        "location_precision": "precise",
        "title": "Barrington Atlas map location",
        "link": "http://pleiades.stoa.org/places/6521781351211310/batlas-location"
      }
    }
  ]
}