{
  "type": "FeatureCollection",
  "title": "Kundu/Kyinda",
  "id": "652350",
  "bbox": [
    34.6031761,
    36.8004345,
    35.8163535,
    37.4488715
  ],
  "description": "Kundu is mentioned in Akkadian royal inscriptions of the seventh-century-BC Assyrian king Esarhaddon. In Classical times, Strabo describes Kyinda as a fortress where Macedonian kings deposited treasure. Eumenes reportedly captured the treasure when he revolted against Antigonus. The site is now unlocated.",
  "connectsWith": [
    "648555",
    "652445664",
    "34546779"
  ],
  "names": [
    "Kyinda",
    "Kundu"
  ],
  "features": [
    {
      "type": "Feature",
      "geometry": {
        "type": "Point",
        "coordinates": [
          35.1234508438,
          37.0015916028
        ]
      },
      "properties": {
        "description": "representative point"
      }
    }
  ]
}