{
  "type": "FeatureCollection",
  "title": "Kyinda",
  "id": "652350",
  "bbox": [
    34.6031761,
    36.8004345,
    35.8163535,
    37.4488715
  ],
  "description": "Strabo describes Kyinda as a fortress where Macedonian kings deposited treasure. Eumenes reportedly captured the treasure when he revolted against Antigonus. The site is now unlocated.",
  "connectsWith": [
    "648555",
    "652445664",
    "34546779"
  ],
  "names": [
    "Kyinda",
    "Kundu"
  ],
  "features": [
    {
      "type": "Feature",
      "geometry": {
        "type": "Point",
        "coordinates": [
          35.1234508438,
          37.0015916028
        ]
      },
      "properties": {
        "description": "representative point"
      }
    },
    {
      "geometry": null,
      "id": "undetermined",
      "type": "Feature",
      "properties": {
        "description": null,
        "location_precision": "unlocated",
        "title": "Undetermined location",
        "link": "http://pleiades.stoa.org/places/652350/undetermined"
      }
    }
  ]
}