{
  "type": "FeatureCollection",
  "title": "Tribonum",
  "id": "652497050",
  "description": "An estate formely belonging to Queen Brunhilda, daugther of the Visigoth king Athanagild and married to king Sigebert I",
  "bbox": [
    2.73532,
    44.39783,
    2.73532,
    44.39783
  ],
  "reprPoint": [
    2.73532,
    44.39783
  ],
  "names": [
    "Tribonum"
  ],
  "features": [
    {
      "geometry": {
        "type": "Point",
        "coordinates": [
          2.73532,
          44.39783
        ]
      },
      "id": "trebosc",
      "type": "Feature",
      "properties": {
        "description": "Center point of location Trébosc, France, departement Aveyron, arrondissement Rodez, canton Bozouls, commune Montrozier.",
        "location_precision": "precise",
        "title": "Trébosc",
        "link": "http://pleiades.stoa.org/places/652497050/trebosc"
      }
    }
  ]
}