{
  "type": "FeatureCollection",
  "title": "Khān Ḥaswā",
  "id": "653436097",
  "bbox": [
    44.4016,
    32.8277,
    44.4016,
    32.8277
  ],
  "description": "The findspot of a cylinder with an Old Babylonian funerary inscription.",
  "names": [
    "Khān Ḥaswā"
  ],
  "features": [
    {
      "type": "Feature",
      "geometry": {
        "type": "Point",
        "coordinates": [
          44.4016,
          32.8277
        ]
      },
      "properties": {
        "description": "representative point"
      }
    },
    {
      "geometry": {
        "type": "Point",
        "coordinates": [
          44.4016,
          32.8277
        ]
      },
      "id": "cigs-location-of-khan-haswa",
      "type": "Feature",
      "properties": {
        "description": null,
        "location_precision": "precise",
        "title": "CIGS location of Khān Ḥaswā",
        "link": "http://pleiades.stoa.org/places/653436097/cigs-location-of-khan-haswa"
      }
    }
  ]
}