{
  "type": "FeatureCollection",
  "title": "Duino Mithraeum",
  "id": "655444319",
  "bbox": [
    13.5979462,
    45.7843061,
    13.5979462,
    45.7843061
  ],
  "description": "A Mithraeum near Duino, in the province of Trieste, north-eastern Italy, that is located within a natural cave.",
  "connectsWith": [
    "187588"
  ],
  "names": [
    "La grotta del Mitreo",
    "San Giovanni al Timavo"
  ],
  "features": [
    {
      "type": "Feature",
      "geometry": {
        "type": "Point",
        "coordinates": [
          13.5979462,
          45.7843061
        ]
      },
      "properties": {
        "description": "representative point"
      }
    },
    {
      "geometry": {
        "type": "Point",
        "coordinates": [
          13.5979462,
          45.7843061
        ]
      },
      "id": "osm-location-of-grotta-del-dio-mithra-mitrejeva",
      "type": "Feature",
      "properties": {
        "description": "Representative location based on OpenStreetMap.",
        "location_precision": "precise",
        "title": "OSM location of Grotta del Dio Mithra / Mitrejeva jama",
        "link": "http://pleiades.stoa.org/places/655444319/osm-location-of-grotta-del-dio-mithra-mitrejeva"
      }
    }
  ]
}