{
  "type": "FeatureCollection",
  "title": "Marki Alonia",
  "id": "657559696",
  "bbox": [
    33.3259841,
    35.023638,
    33.3259841,
    35.023638
  ],
  "description": "Marki Alonia is a prehistoric settlement in central Cyprus.",
  "connectsWith": [
    "707498"
  ],
  "features": [
    {
      "type": "Feature",
      "geometry": {
        "type": "Point",
        "coordinates": [
          33.3259841,
          35.023638
        ]
      },
      "properties": {
        "description": "representative point"
      }
    },
    {
      "geometry": {
        "type": "Point",
        "coordinates": [
          33.3259841,
          35.023638
        ]
      },
      "id": "osm-location-of-modern-marki",
      "type": "Feature",
      "properties": {
        "description": "Location based on OpenStreetMap",
        "location_precision": "precise",
        "title": "OSM location of modern Marki",
        "link": "http://pleiades.stoa.org/places/657559696/osm-location-of-modern-marki"
      }
    }
  ]
}