{
  "type": "FeatureCollection",
  "title": "Adatha",
  "id": "658366",
  "description": "An ancient place, cited: BAtlas 67 E1 Adatha",
  "bbox": [
    37.409481,
    37.702358,
    37.442122,
    37.70785
  ],
  "reprPoint": [
    37.4258015,
    37.705104
  ],
  "names": [
    "Adatha"
  ],
  "features": [
    {
      "geometry": {
        "type": "Point",
        "coordinates": [
          37.409481,
          37.702358
        ]
      },
      "id": "darmc-location-1799",
      "type": "Feature",
      "properties": {
        "description": "TIB point location",
        "location_precision": "precise",
        "title": "DARMC location 1799",
        "link": "http://pleiades.stoa.org/places/658366/darmc-location-1799"
      }
    },
    {
      "geometry": {
        "type": "Point",
        "coordinates": [
          37.442122,
          37.70785
        ]
      },
      "id": "darmc-location-11174",
      "type": "Feature",
      "properties": {
        "description": "500K scale point location",
        "location_precision": "precise",
        "title": "DARMC location 11174",
        "link": "http://pleiades.stoa.org/places/658366/darmc-location-11174"
      }
    }
  ]
}