{
  "type": "FeatureCollection",
  "title": "Issicus Sinus",
  "id": "658489",
  "bbox": [
    35.83,
    36.579722,
    35.83,
    36.579722
  ],
  "description": "Issicus Sinus (the Gulf of İskenderun) is a gulf of the Levantine Sea.",
  "connectsWith": [
    "1043"
  ],
  "names": [
    "Issicus Sinus",
    "Kilikios Kolpos",
    "Mariandikos Kolpos"
  ],
  "features": [
    {
      "type": "Feature",
      "geometry": {
        "type": "Point",
        "coordinates": [
          35.83,
          36.579722
        ]
      },
      "properties": {
        "description": "representative point"
      }
    },
    {
      "geometry": {
        "type": "Point",
        "coordinates": [
          35.83,
          36.579722
        ]
      },
      "id": "location-issicus-sinus",
      "type": "Feature",
      "properties": {
        "description": null,
        "location_precision": "precise",
        "title": "location Issicus Sinus",
        "link": "http://pleiades.stoa.org/places/658489/location-issicus-sinus"
      }
    }
  ]
}