{
  "type": "FeatureCollection",
  "title": "Daiara/Thiara",
  "id": "658449",
  "bbox": [
    38.213008,
    36.986278,
    38.213008,
    36.986278
  ],
  "description": "An ancient place, cited: BAtlas 67 G3 Daiara/Thiara",
  "names": [
    "Daiara",
    "Thiara"
  ],
  "features": [
    {
      "type": "Feature",
      "geometry": {
        "type": "Point",
        "coordinates": [
          38.213008,
          36.986278
        ]
      },
      "properties": {
        "description": "representative point"
      }
    },
    {
      "geometry": {
        "type": "Point",
        "coordinates": [
          38.213008,
          36.986278
        ]
      },
      "id": "darmc-location-9656",
      "type": "Feature",
      "properties": {
        "description": "500K scale point location",
        "location_precision": "precise",
        "title": "DARMC location 9656",
        "link": "http://pleiades.stoa.org/places/658449/darmc-location-9656"
      }
    }
  ]
}