{
  "type": "FeatureCollection",
  "title": "Carrhae",
  "id": "658427",
  "bbox": [
    39.028865,
    36.864692,
    39.031492,
    36.866351
  ],
  "description": "Carrhae is a major settlement of Upper Mesopotamia from the Bronze Age onward. The earliest mentions of the site are found in the Ebla tablets (ca. 2300 B.C.). Notably the location of the Battle of Carrhae between the Roman Republic and Parthian Empire in 53 B.C., which proved to be a devastating defeat for the Romans. Modern-day Ḥarrān, Turkey.",
  "names": [
    "Carrhae",
    "Harran"
  ],
  "features": [
    {
      "type": "Feature",
      "geometry": {
        "type": "Point",
        "coordinates": [
          39.0301785,
          36.8655215
        ]
      },
      "properties": {
        "description": "representative point"
      }
    },
    {
      "geometry": {
        "type": "Point",
        "coordinates": [
          39.028865,
          36.866351
        ]
      },
      "id": "darmc-location-30116",
      "type": "Feature",
      "properties": {
        "description": "1:500,000 scale representative point location digitized from the Barrington Atlas of the Greek and Roman World by the Digital Atlas of Roman and Medieval Civilizations project at Harvard University.",
        "location_precision": "precise",
        "title": "DARMC location 30116",
        "link": "http://pleiades.stoa.org/places/658427/darmc-location-30116"
      }
    },
    {
      "geometry": {
        "type": "Point",
        "coordinates": [
          39.031492,
          36.864692
        ]
      },
      "id": "dare-location",
      "type": "Feature",
      "properties": {
        "description": "Representative point location, village precision",
        "location_precision": "precise",
        "title": "DARE Location",
        "link": "http://pleiades.stoa.org/places/658427/dare-location"
      }
    }
  ]
}