{
  "type": "FeatureCollection",
  "title": "Charandama",
  "id": "658435",
  "description": "An ancient place, cited: BAtlas 67 C4 Charandama",
  "bbox": [
    36.181412,
    36.102478,
    36.181412,
    36.102478
  ],
  "reprPoint": [
    36.181412,
    36.102478
  ],
  "names": [
    "Charandama"
  ],
  "features": [
    {
      "geometry": {
        "type": "Point",
        "coordinates": [
          36.181412,
          36.102478
        ]
      },
      "id": "darmc-location-11985",
      "type": "Feature",
      "properties": {
        "description": "500K scale point location",
        "location_precision": "precise",
        "title": "DARMC location 11985",
        "link": "http://pleiades.stoa.org/places/658435/darmc-location-11985"
      }
    }
  ]
}