{
  "type": "FeatureCollection",
  "title": "Cyrrus/Hagioupolis",
  "id": "658446",
  "description": "An ancient city in ancient Syria founded by Seleucus Nicator.",
  "bbox": [
    36.956398,
    36.744679,
    36.956398,
    36.744679
  ],
  "reprPoint": [
    36.956398,
    36.744679
  ],
  "names": [
    "Cyrrus",
    "Hagioupolis"
  ],
  "features": [
    {
      "geometry": {
        "type": "Point",
        "coordinates": [
          36.948956,
          36.734662
        ]
      },
      "id": "darmc-location-20207",
      "type": "Feature",
      "properties": {
        "description": "500K scale point location",
        "location_precision": "precise",
        "title": "DARMC location 20207",
        "link": "http://pleiades.stoa.org/places/658446/darmc-location-20207"
      }
    },
    {
      "geometry": {
        "type": "Point",
        "coordinates": [
          36.956398,
          36.744679
        ]
      },
      "id": "dare-location",
      "type": "Feature",
      "properties": {
        "description": "Representative point location, site precision",
        "location_precision": "precise",
        "title": "DARE Location",
        "link": "http://pleiades.stoa.org/places/658446/dare-location"
      }
    }
  ]
}