{
  "type": "FeatureCollection",
  "title": "Darqita",
  "id": "658452",
  "description": "An ancient place, cited: BAtlas 67 D4 Darqita",
  "bbox": [
    36.683707,
    36.22603,
    36.683707,
    36.22603
  ],
  "reprPoint": [
    36.683707,
    36.22603
  ],
  "features": [
    {
      "geometry": {
        "type": "Point",
        "coordinates": [
          36.683707,
          36.22603
        ]
      },
      "id": "darmc-location-12159",
      "type": "Feature",
      "properties": {
        "description": "500K scale point location",
        "location_precision": "precise",
        "title": "DARMC location 12159",
        "link": "http://pleiades.stoa.org/places/658452/darmc-location-12159"
      }
    }
  ]
}