{
  "type": "FeatureCollection",
  "title": "Carrhae",
  "id": "658427",
  "description": "Carrhae is a major settlement of Upper Mesopotamia from the Bronze Age onward. The earliest mentions of the site are found in the Ebla tablets (ca. 2300 BC).",
  "bbox": [
    39.031492,
    36.864692,
    39.031492,
    36.864692
  ],
  "reprPoint": [
    39.031492,
    36.864692
  ],
  "names": [
    "Carrhae"
  ],
  "features": [
    {
      "geometry": {
        "type": "Point",
        "coordinates": [
          39.031492,
          36.864692
        ]
      },
      "id": "dare-location",
      "type": "Feature",
      "properties": {
        "description": "Representative point location, village precision",
        "location_precision": "precise",
        "title": "DARE Location",
        "link": "http://pleiades.stoa.org/places/658427/dare-location"
      }
    },
    {
      "geometry": {
        "type": "Point",
        "coordinates": [
          39.028865,
          36.866351
        ]
      },
      "id": "darmc-location-30116",
      "type": "Feature",
      "properties": {
        "description": "500K scale point location",
        "location_precision": "precise",
        "title": "DARMC location 30116",
        "link": "http://pleiades.stoa.org/places/658427/darmc-location-30116"
      }
    }
  ]
}