{
  "type": "FeatureCollection",
  "title": "Kanč'",
  "id": "658493",
  "bbox": [
    36.613828,
    37.846261,
    36.613828,
    37.846261
  ],
  "description": "An ancient place, cited: BAtlas 67 D1 Kanč'",
  "names": [
    "Kanč'"
  ],
  "features": [
    {
      "type": "Feature",
      "geometry": {
        "type": "Point",
        "coordinates": [
          36.613828,
          37.846261
        ]
      },
      "properties": {
        "description": "representative point"
      }
    },
    {
      "geometry": {
        "type": "Point",
        "coordinates": [
          36.613828,
          37.846261
        ]
      },
      "id": "darmc-location-4192",
      "type": "Feature",
      "properties": {
        "description": "TIB point location",
        "location_precision": "precise",
        "title": "DARMC location 4192",
        "link": "http://pleiades.stoa.org/places/658493/darmc-location-4192"
      }
    }
  ]
}