{
  "type": "FeatureCollection",
  "title": "Mogiza",
  "id": "658537",
  "description": "An ancient place, cited: BAtlas 67 D4 Mogiza",
  "bbox": [
    36.682801,
    36.180745,
    36.682801,
    36.180745
  ],
  "reprPoint": [
    36.682801,
    36.180745
  ],
  "names": [
    "Mogiza"
  ],
  "features": [
    {
      "geometry": {
        "type": "Point",
        "coordinates": [
          36.682801,
          36.180745
        ]
      },
      "id": "darmc-location-13767",
      "type": "Feature",
      "properties": {
        "description": "500K scale point location",
        "location_precision": "precise",
        "title": "DARMC location 13767",
        "link": "http://pleiades.stoa.org/places/658537/darmc-location-13767"
      }
    }
  ]
}