{
  "type": "FeatureCollection",
  "title": "Kodrigai",
  "id": "658511",
  "bbox": [
    36.220709,
    36.670271,
    36.220709,
    36.670271
  ],
  "description": "An ancient place, cited: BAtlas 67 C3 Kodrigai",
  "names": [
    "Kodrigai"
  ],
  "features": [
    {
      "type": "Feature",
      "geometry": {
        "type": "Point",
        "coordinates": [
          36.220709,
          36.670271
        ]
      },
      "properties": {
        "description": "representative point"
      }
    },
    {
      "geometry": {
        "type": "Point",
        "coordinates": [
          36.220709,
          36.670271
        ]
      },
      "id": "darmc-location-20588",
      "type": "Feature",
      "properties": {
        "description": "500K scale point location",
        "location_precision": "precise",
        "title": "DARMC location 20588",
        "link": "http://pleiades.stoa.org/places/658511/darmc-location-20588"
      }
    }
  ]
}