{
  "type": "FeatureCollection",
  "title": "Sicos Basilisses",
  "id": "658597",
  "bbox": [
    37.330858,
    37.411526,
    37.330858,
    37.411526
  ],
  "description": "An ancient place, cited: BAtlas 67 E2 Sicos Basilisses",
  "names": [
    "Sicos Basilisses"
  ],
  "features": [
    {
      "type": "Feature",
      "geometry": {
        "type": "Point",
        "coordinates": [
          37.330858,
          37.411526
        ]
      },
      "properties": {
        "description": "representative point"
      }
    },
    {
      "geometry": {
        "type": "Point",
        "coordinates": [
          37.330858,
          37.411526
        ]
      },
      "id": "darmc-location-19696",
      "type": "Feature",
      "properties": {
        "description": "500K scale point location",
        "location_precision": "precise",
        "title": "DARMC location 19696",
        "link": "http://pleiades.stoa.org/places/658597/darmc-location-19696"
      }
    }
  ]
}