{
  "type": "FeatureCollection",
  "title": "Oeniandos/Epiphaneia",
  "id": "658556",
  "description": "An ancient place, cited: BAtlas 67 C3 Oeniandos/Epiphaneia",
  "bbox": [
    36.134467,
    36.975624,
    36.134467,
    36.975624
  ],
  "reprPoint": [
    36.134467,
    36.975624
  ],
  "names": [
    "Oeniandos",
    "Epiphaneia"
  ],
  "features": [
    {
      "geometry": {
        "type": "Point",
        "coordinates": [
          36.199705,
          36.955056
        ]
      },
      "id": "darmc-location-1918",
      "type": "Feature",
      "properties": {
        "description": "TIB point location",
        "location_precision": "precise",
        "title": "DARMC location 1918",
        "link": "http://pleiades.stoa.org/places/658556/darmc-location-1918"
      }
    },
    {
      "geometry": {
        "type": "Point",
        "coordinates": [
          36.129072,
          36.954997
        ]
      },
      "id": "darmc-location-3430",
      "type": "Feature",
      "properties": {
        "description": "500K scale point location",
        "location_precision": "precise",
        "title": "DARMC location 3430",
        "link": "http://pleiades.stoa.org/places/658556/darmc-location-3430"
      }
    },
    {
      "geometry": {
        "type": "Point",
        "coordinates": [
          36.134467,
          36.975624
        ]
      },
      "id": "dare-location",
      "type": "Feature",
      "properties": {
        "description": "Representative point location, village precision",
        "location_precision": "precise",
        "title": "DARE Location",
        "link": "http://pleiades.stoa.org/places/658556/dare-location"
      }
    }
  ]
}