{
  "type": "FeatureCollection",
  "title": "Meleagrum",
  "id": "658532",
  "description": "An ancient place, cited: BAtlas 67 C3 Meleagrum",
  "bbox": [
    36.385636,
    36.519966,
    36.385636,
    36.519966
  ],
  "reprPoint": [
    36.385636,
    36.519966
  ],
  "names": [
    "Meleagrum"
  ],
  "features": [
    {
      "geometry": {
        "type": "Point",
        "coordinates": [
          36.385636,
          36.519966
        ]
      },
      "id": "darmc-location-13690",
      "type": "Feature",
      "properties": {
        "description": "500K scale point location",
        "location_precision": "precise",
        "title": "DARMC location 13690",
        "link": "http://pleiades.stoa.org/places/658532/darmc-location-13690"
      }
    }
  ]
}