{
  "type": "FeatureCollection",
  "title": "Nicopolis",
  "id": "658547",
  "bbox": [
    36.631648,
    37.025361,
    36.633389,
    37.027158
  ],
  "description": "An ancient place, cited: BAtlas 67 D2 Nicopolis",
  "names": [
    "Nicopolis"
  ],
  "features": [
    {
      "type": "Feature",
      "geometry": {
        "type": "Point",
        "coordinates": [
          36.6325185,
          37.0262595
        ]
      },
      "properties": {
        "description": "representative point"
      }
    },
    {
      "geometry": {
        "type": "Point",
        "coordinates": [
          36.631648,
          37.025361
        ]
      },
      "id": "darmc-location-7643",
      "type": "Feature",
      "properties": {
        "description": "1:500,000 scale representative point location digitized from the Barrington Atlas of the Greek and Roman World by the Digital Atlas of Roman and Medieval Civilizations project at Harvard University.",
        "location_precision": "precise",
        "title": "DARMC location 7643",
        "link": "http://pleiades.stoa.org/places/658547/darmc-location-7643"
      }
    },
    {
      "geometry": {
        "type": "Point",
        "coordinates": [
          36.633389,
          37.027158
        ]
      },
      "id": "dare-location",
      "type": "Feature",
      "properties": {
        "description": "Representative point location, village precision",
        "location_precision": "precise",
        "title": "DARE Location",
        "link": "http://pleiades.stoa.org/places/658547/dare-location"
      }
    }
  ]
}