{
  "type": "FeatureCollection",
  "title": "Symeon, Mon.",
  "id": "658606",
  "description": "An ancient place, cited: BAtlas 67 D4 Symeon, Mon.",
  "bbox": [
    36.843889,
    36.332786,
    36.844,
    36.334167
  ],
  "reprPoint": [
    36.8439445,
    36.3334765
  ],
  "names": [
    "Symeon, Mon."
  ],
  "features": [
    {
      "geometry": {
        "type": "Point",
        "coordinates": [
          36.844,
          36.332786
        ]
      },
      "id": "darmc-location-6918",
      "type": "Feature",
      "properties": {
        "description": "500K scale point location",
        "location_precision": "precise",
        "title": "DARMC location 6918",
        "link": "http://pleiades.stoa.org/places/658606/darmc-location-6918"
      }
    },
    {
      "geometry": {
        "type": "Point",
        "coordinates": [
          36.843889,
          36.334167
        ]
      },
      "id": "dare-location",
      "type": "Feature",
      "properties": {
        "description": "Representative point location, site precision",
        "location_precision": "precise",
        "title": "DARE Location",
        "link": "http://pleiades.stoa.org/places/658606/dare-location"
      }
    }
  ]
}