{
  "type": "FeatureCollection",
  "title": "Monte Rocche",
  "id": "659022266",
  "description": "A settlement of the Iron Age and Roman period in western Liguria.",
  "bbox": [
    7.8674622,
    43.8484748,
    7.8674622,
    43.8484748
  ],
  "reprPoint": [
    7.8674622,
    43.8484748
  ],
  "names": [
    "Monte Rocche"
  ],
  "features": [
    {
      "geometry": {
        "type": "Point",
        "coordinates": [
          7.8674622,
          43.8484748
        ]
      },
      "id": "monte-rocche",
      "type": "Feature",
      "properties": {
        "description": "Representative point derived from Open Street Map",
        "location_precision": "precise",
        "title": "Monte Rocche",
        "link": "http://pleiades.stoa.org/places/659022266/monte-rocche"
      }
    }
  ]
}