{
  "type": "FeatureCollection",
  "title": "Pons Chabinae",
  "id": "659885",
  "description": "An ancient place, cited: BAtlas 67 H1 unnamed bridge (Pons Chabinae, Cendere Köprüsü, W Arsameia pros Nymphaio)",
  "bbox": [
    38.611801,
    37.933179,
    38.611801,
    37.933179
  ],
  "reprPoint": [
    38.611801,
    37.933179
  ],
  "features": [
    {
      "geometry": {
        "type": "Point",
        "coordinates": [
          38.610599,
          37.937224
        ]
      },
      "id": "darmc-location-27958",
      "type": "Feature",
      "properties": {
        "description": "500K scale point location",
        "location_precision": "precise",
        "title": "DARMC location 27958",
        "link": "http://pleiades.stoa.org/places/659885/darmc-location-27958"
      }
    },
    {
      "geometry": {
        "type": "Point",
        "coordinates": [
          38.611801,
          37.933179
        ]
      },
      "id": "dare-location",
      "type": "Feature",
      "properties": {
        "description": "Representative point location, site precision",
        "location_precision": "precise",
        "title": "DARE Location",
        "link": "http://pleiades.stoa.org/places/659885/dare-location"
      }
    }
  ]
}