{
  "type": "FeatureCollection",
  "title": "Haua Fteah",
  "id": "662332232",
  "bbox": [
    22.0515628,
    32.9001953,
    22.0515628,
    32.9001953
  ],
  "description": "A karstic cave located in northeastern Libya that is a significant site for modern human prehistory. The cave was occupied during the Middle and Upper Paleolithic, the Mesolithic and the Neolithic periods. Evidence for modern human presence in the cave dates back to 200,000 BP.",
  "names": [
    "Haua Fteah Cave"
  ],
  "features": [
    {
      "type": "Feature",
      "geometry": {
        "type": "Point",
        "coordinates": [
          22.0515628,
          32.9001953
        ]
      },
      "properties": {
        "description": "representative point"
      }
    },
    {
      "geometry": {
        "type": "Point",
        "coordinates": [
          22.0515628,
          32.9001953
        ]
      },
      "id": "osm-location-haua-fteah-cave",
      "type": "Feature",
      "properties": {
        "description": "Location based on OpenStreetMap",
        "location_precision": "precise",
        "title": "OSM location Haua Fteah Cave",
        "link": "http://pleiades.stoa.org/places/662332232/osm-location-haua-fteah-cave"
      }
    }
  ]
}