{
  "type": "FeatureCollection",
  "title": "Hellenistic-Roman theater at Sarno",
  "id": "662332234",
  "bbox": [
    14.5970837,
    40.83245,
    14.5970837,
    40.83245
  ],
  "description": "An ancient theater.",
  "connectsWith": [
    "433101"
  ],
  "features": [
    {
      "type": "Feature",
      "geometry": {
        "type": "Point",
        "coordinates": [
          14.5970837,
          40.83245
        ]
      },
      "properties": {
        "description": "representative point"
      }
    },
    {
      "geometry": {
        "type": "Point",
        "coordinates": [
          14.5970837,
          40.83245
        ]
      },
      "id": "location-of-ancient-theater",
      "type": "Feature",
      "properties": {
        "description": "Representative location based on OpenStreetMap",
        "location_precision": "precise",
        "title": "OSM location of teatro antico Greco-Romano",
        "link": "http://pleiades.stoa.org/places/662332234/location-of-ancient-theater"
      }
    }
  ]
}