{
  "type": "FeatureCollection",
  "title": "Coccium?",
  "id": "662928353",
  "bbox": [
    -2.6264624,
    53.5457188,
    -2.6264624,
    53.5457188
  ],
  "description": "A minor Romano-British settlement located at Wigan, Lancashire.",
  "names": [
    "Coccium"
  ],
  "features": [
    {
      "type": "Feature",
      "geometry": {
        "type": "Point",
        "coordinates": [
          -2.6264624,
          53.5457188
        ]
      },
      "properties": {
        "description": "representative point"
      }
    },
    {
      "geometry": {
        "type": "Point",
        "coordinates": [
          -2.6264624,
          53.5457188
        ]
      },
      "id": "osm-location-of-modern-wigan",
      "type": "Feature",
      "properties": {
        "description": "Location based on OpenStreetMap",
        "location_precision": "precise",
        "title": "OSM location of modern Wigan",
        "link": "http://pleiades.stoa.org/places/662928353/osm-location-of-modern-wigan"
      }
    }
  ]
}