{
  "type": "FeatureCollection",
  "title": "Temple of Venus",
  "id": "663121962",
  "bbox": [
    14.4837195,
    40.7484237,
    14.4837195,
    40.7484237
  ],
  "description": "The Temple of Venus (VIII,1) is located adjacent to Pompeii's Porta Marina. The site was cleared in the early years of the colony to make way for the temple. Seriously damaged by the AD 62 earthquake, the sanctuary was still being rebuilt at the time of its ultimate destruction.",
  "connectsWith": [
    "433032",
    "538911200"
  ],
  "names": [
    "Tempio di Venere",
    "Tempel des Empedokles",
    "Aedes of the Ministri Mercurii Maiae",
    "Templum of Augustus",
    "Templum of Venus Pompeiana",
    "Templum of Venus fisica Pompeiana",
    "VIII.1.3"
  ],
  "features": [
    {
      "type": "Feature",
      "geometry": {
        "type": "Point",
        "coordinates": [
          14.4837195,
          40.7484237
        ]
      },
      "properties": {
        "description": "representative point"
      }
    },
    {
      "geometry": {
        "type": "Point",
        "coordinates": [
          14.4837195,
          40.7484237
        ]
      },
      "id": "tempio-di-venere",
      "type": "Feature",
      "properties": {
        "description": "Representative point location based on OpenStreetMap.",
        "location_precision": "precise",
        "title": "OSM location of so-called \"Tempio di Venere\"",
        "link": "http://pleiades.stoa.org/places/663121962/tempio-di-venere"
      }
    }
  ]
}