{
  "type": "FeatureCollection",
  "title": "Arco de los Blanco",
  "id": "663803333",
  "bbox": [
    -6.2929619,
    36.5286396,
    -6.2929619,
    36.5286396
  ],
  "description": "A Roman gateway.",
  "connectsWith": [
    "256177"
  ],
  "features": [
    {
      "type": "Feature",
      "geometry": {
        "type": "Point",
        "coordinates": [
          -6.2929619,
          36.5286396
        ]
      },
      "properties": {
        "description": "representative point"
      }
    },
    {
      "geometry": {
        "type": "Point",
        "coordinates": [
          -6.2929619,
          36.5286396
        ]
      },
      "id": "location-of-arco-de-los-blanco",
      "type": "Feature",
      "properties": {
        "description": "Location based on OpenStreetMap",
        "location_precision": "precise",
        "title": "location of Arco de los Blanco",
        "link": "http://pleiades.stoa.org/places/663803333/location-of-arco-de-los-blanco"
      }
    }
  ]
}