{
  "type": "FeatureCollection",
  "title": "Church of Saint Panteleimon",
  "id": "664535672",
  "bbox": [
    22.9512,
    40.6331,
    22.9512,
    40.6331
  ],
  "description": "The Church of Saint Panteleimon (Thessaloniki) is a late Byzantine church.",
  "connectsWith": [
    "491741"
  ],
  "features": [
    {
      "type": "Feature",
      "geometry": {
        "type": "Point",
        "coordinates": [
          22.9512,
          40.6331
        ]
      },
      "properties": {
        "description": "representative point"
      }
    },
    {
      "geometry": {
        "type": "Point",
        "coordinates": [
          22.9512,
          40.6331
        ]
      },
      "id": "imagery-location",
      "type": "Feature",
      "properties": {
        "description": "a late Byzantine church in Thessaloniki",
        "location_precision": "precise",
        "title": "Imagery Location of Church of Saint Panteleimon",
        "link": "http://pleiades.stoa.org/places/664535672/imagery-location"
      }
    }
  ]
}