{
  "type": "FeatureCollection",
  "title": "Eremo di San Michele (Coli)",
  "id": "664572982",
  "bbox": [
    9.4128938,
    44.7338787,
    9.4128938,
    44.7338787
  ],
  "description": "The cavern of San Michele was a hermit's dwelling place that is located near a cavern known as the \"cave of San Colombano\". This hermitage lies in a relatively solitary area of the valley of the Curiasca di San Michele stream, a tributary of the Trebbia river (Italian municipality of Coli, province of Piacenza).",
  "names": [
    "Eremo di San Michele (Coli)"
  ],
  "features": [
    {
      "type": "Feature",
      "geometry": {
        "type": "Point",
        "coordinates": [
          9.4128938,
          44.7338787
        ]
      },
      "properties": {
        "description": "representative point"
      }
    },
    {
      "geometry": {
        "type": "Point",
        "coordinates": [
          9.4128938,
          44.7338787
        ]
      },
      "id": "osm-location-of-eremo-san-michele",
      "type": "Feature",
      "properties": {
        "description": "Representative location based on OpenStreetMap",
        "location_precision": "precise",
        "title": "OSM location of Eremo San Michele",
        "link": "http://pleiades.stoa.org/places/664572982/osm-location-of-eremo-san-michele"
      }
    }
  ]
}