{
  "type": "FeatureCollection",
  "title": "Ai/Et-Tell",
  "id": "665310877",
  "description": "Ai/Et-Tell was a Canaanite royal city that is mentioned in the Book of Joshua in the Hebrew Bible. The archaeological site of Et-Tell is associated with this ancient place.",
  "bbox": [
    35.2615767,
    31.9166759,
    35.2615767,
    31.9166759
  ],
  "reprPoint": [
    35.2615767,
    31.9166759
  ],
  "names": [
    "Et-Tell",
    "Ai"
  ],
  "features": [
    {
      "geometry": {
        "type": "Point",
        "coordinates": [
          35.2615767,
          31.9166759
        ]
      },
      "id": "osm-location-of-khirbet-tel-ai",
      "type": "Feature",
      "properties": {
        "description": "Representative location based on OpenStreetMap.",
        "location_precision": "precise",
        "title": "OSM location of Khirbet Tel Ai",
        "link": "http://pleiades.stoa.org/places/665310877/osm-location-of-khirbet-tel-ai"
      }
    }
  ]
}