{
  "type": "FeatureCollection",
  "title": "Tell en-Nasbeh",
  "id": "666067876",
  "bbox": [
    35.2164718,
    31.8857713,
    35.2164718,
    31.8857713
  ],
  "description": "Tell en-Naṣbeh is an archaeological site ca. 12 km north of the Old City of Jerusalem. The site is often identified with the biblical Mizpah in Benjamin.",
  "names": [
    "Mizpah in Benjamin"
  ],
  "features": [
    {
      "type": "Feature",
      "geometry": {
        "type": "Point",
        "coordinates": [
          35.2164718,
          31.8857713
        ]
      },
      "properties": {
        "description": "representative point"
      }
    },
    {
      "geometry": {
        "type": "Point",
        "coordinates": [
          35.2164718,
          31.8857713
        ]
      },
      "id": "osm-location-of-tel-a-nasbe",
      "type": "Feature",
      "properties": {
        "description": "Representative location based on a node derived from OpenStreetMap.",
        "location_precision": "precise",
        "title": "OSM location of Tel A-Nasbe",
        "link": "http://pleiades.stoa.org/places/666067876/osm-location-of-tel-a-nasbe"
      }
    }
  ]
}