{
  "type": "FeatureCollection",
  "title": "al-Basiri",
  "id": "668181",
  "description": "An ancient place, cited: BAtlas 68 E5 al-Basiri",
  "bbox": [
    37.607467,
    34.189094,
    37.607467,
    34.189094
  ],
  "reprPoint": [
    37.607467,
    34.189094
  ],
  "features": [
    {
      "geometry": {
        "type": "Point",
        "coordinates": [
          37.607467,
          34.189094
        ]
      },
      "id": "darmc-location-18470",
      "type": "Feature",
      "properties": {
        "description": "500K scale point location",
        "location_precision": "precise",
        "title": "DARMC location 18470",
        "link": "http://pleiades.stoa.org/places/668181/darmc-location-18470"
      }
    }
  ]
}