{
  "type": "FeatureCollection",
  "title": "Aracha/Anatha/‘Harae’",
  "id": "668196",
  "bbox": [
    38.582516,
    34.671287,
    38.582516,
    34.671287
  ],
  "description": "An ancient place, cited: BAtlas 68 G4 Aracha/Anatha/‘Harae’",
  "names": [
    "Aracha",
    "Anatha",
    "Harae"
  ],
  "features": [
    {
      "type": "Feature",
      "geometry": {
        "type": "Point",
        "coordinates": [
          38.582516,
          34.671287
        ]
      },
      "properties": {
        "description": "representative point"
      }
    },
    {
      "geometry": {
        "type": "Point",
        "coordinates": [
          38.582516,
          34.671287
        ]
      },
      "id": "darmc-location-11454",
      "type": "Feature",
      "properties": {
        "description": "500K scale point location",
        "location_precision": "precise",
        "title": "DARMC location 11454",
        "link": "http://pleiades.stoa.org/places/668196/darmc-location-11454"
      }
    }
  ]
}