{
  "type": "FeatureCollection",
  "title": "Betproclis",
  "id": "668212",
  "description": "An ancient place, cited: BAtlas 68 D4 Betproclis",
  "bbox": [
    37.111805,
    34.639874,
    37.111805,
    34.639874
  ],
  "reprPoint": [
    37.111805,
    34.639874
  ],
  "names": [
    "Betproclis"
  ],
  "features": [
    {
      "geometry": {
        "type": "Point",
        "coordinates": [
          37.111805,
          34.639874
        ]
      },
      "id": "darmc-location-9787",
      "type": "Feature",
      "properties": {
        "description": "500K scale point location",
        "location_precision": "precise",
        "title": "DARMC location 9787",
        "link": "http://pleiades.stoa.org/places/668212/darmc-location-9787"
      }
    }
  ]
}