{
  "type": "FeatureCollection",
  "title": "Carne/Karnos",
  "id": "668223",
  "bbox": [
    35.884375,
    34.938844,
    35.884375,
    34.938844
  ],
  "description": "An ancient place, cited: BAtlas 68 A4 Carne/Karnos",
  "names": [
    "Carne",
    "Karnos"
  ],
  "features": [
    {
      "type": "Feature",
      "geometry": {
        "type": "Point",
        "coordinates": [
          35.884375,
          34.938844
        ]
      },
      "properties": {
        "description": "representative point"
      }
    },
    {
      "geometry": {
        "type": "Point",
        "coordinates": [
          35.884375,
          34.938844
        ]
      },
      "id": "darmc-location-11909",
      "type": "Feature",
      "properties": {
        "description": "500K scale point location",
        "location_precision": "precise",
        "title": "DARMC location 11909",
        "link": "http://pleiades.stoa.org/places/668223/darmc-location-11909"
      }
    }
  ]
}