{
  "type": "FeatureCollection",
  "title": "‘Danova’",
  "id": "668236",
  "description": "An ancient place, cited: BAtlas 68 D5 ‘Danova’",
  "bbox": [
    37.074718,
    34.265831,
    37.076564,
    34.275118
  ],
  "reprPoint": [
    37.075641,
    34.2704745
  ],
  "names": [
    "Danova"
  ],
  "features": [
    {
      "geometry": {
        "type": "Point",
        "coordinates": [
          37.076564,
          34.275118
        ]
      },
      "id": "darmc-location-10021",
      "type": "Feature",
      "properties": {
        "description": "500K scale point location",
        "location_precision": "precise",
        "title": "DARMC location 10021",
        "link": "http://pleiades.stoa.org/places/668236/darmc-location-10021"
      }
    },
    {
      "geometry": {
        "type": "Point",
        "coordinates": [
          37.07471799999996,
          34.265831
        ]
      },
      "id": "dare-location",
      "type": "Feature",
      "properties": {
        "description": "Representative point location, village precision",
        "location_precision": "precise",
        "title": "DARE Location",
        "link": "http://pleiades.stoa.org/places/668236/dare-location"
      }
    }
  ]
}