{
  "type": "FeatureCollection",
  "title": "‘Carion’",
  "id": "668222",
  "description": "An ancient place, cited: BAtlas 68 B4 ‘Carion’",
  "bbox": [
    36.316256,
    34.776975,
    36.316256,
    34.776975
  ],
  "reprPoint": [
    36.316256,
    34.776975
  ],
  "names": [
    "Carion"
  ],
  "features": [
    {
      "geometry": {
        "type": "Point",
        "coordinates": [
          36.316256,
          34.776975
        ]
      },
      "id": "darmc-location-9651",
      "type": "Feature",
      "properties": {
        "description": "500K scale point location",
        "location_precision": "precise",
        "title": "DARMC location 9651",
        "link": "http://pleiades.stoa.org/places/668222/darmc-location-9651"
      }
    }
  ]
}