{
  "type": "FeatureCollection",
  "title": "Khirbet el-Bilaas",
  "id": "668285",
  "description": "An ancient place, cited: BAtlas 68 E4 Khirbet el-Bilaas",
  "bbox": [
    37.653739,
    34.964644,
    37.667418,
    34.97057
  ],
  "reprPoint": [
    37.6605785,
    34.967607
  ],
  "features": [
    {
      "geometry": {
        "type": "Point",
        "coordinates": [
          37.653739,
          34.97057
        ]
      },
      "id": "darmc-location-16643",
      "type": "Feature",
      "properties": {
        "description": "500K scale point location",
        "location_precision": "precise",
        "title": "DARMC location 16643",
        "link": "http://pleiades.stoa.org/places/668285/darmc-location-16643"
      }
    },
    {
      "geometry": {
        "type": "Point",
        "coordinates": [
          37.667418,
          34.964644
        ]
      },
      "id": "darmc-location-19608",
      "type": "Feature",
      "properties": {
        "description": "500K scale point location",
        "location_precision": "precise",
        "title": "DARMC location 19608",
        "link": "http://pleiades.stoa.org/places/668285/darmc-location-19608"
      }
    }
  ]
}