{
  "type": "FeatureCollection",
  "title": "Huarte",
  "id": "668266",
  "description": "An ancient place, cited: BAtlas 68 B2 Huarte",
  "bbox": [
    36.458105,
    35.588322,
    36.458105,
    35.588322
  ],
  "reprPoint": [
    36.458105,
    35.588322
  ],
  "features": [
    {
      "geometry": {
        "type": "Point",
        "coordinates": [
          36.458105,
          35.588322
        ]
      },
      "id": "darmc-location-12802",
      "type": "Feature",
      "properties": {
        "description": "500K scale point location",
        "location_precision": "precise",
        "title": "DARMC location 12802",
        "link": "http://pleiades.stoa.org/places/668266/darmc-location-12802"
      }
    }
  ]
}