{
  "type": "FeatureCollection",
  "title": "Hermel",
  "id": "668264",
  "description": "An ancient place, cited: BAtlas 68 B5 Hermel",
  "bbox": [
    36.422188,
    34.379903,
    36.422188,
    34.379903
  ],
  "reprPoint": [
    36.422188,
    34.379903
  ],
  "features": [
    {
      "geometry": {
        "type": "Point",
        "coordinates": [
          36.422188,
          34.379903
        ]
      },
      "id": "darmc-location-26000",
      "type": "Feature",
      "properties": {
        "description": "500K scale point location",
        "location_precision": "precise",
        "title": "DARMC location 26000",
        "link": "http://pleiades.stoa.org/places/668264/darmc-location-26000"
      }
    }
  ]
}