{
  "type": "FeatureCollection",
  "title": "Sabboura",
  "id": "668359",
  "bbox": [
    37.221292,
    35.194282,
    37.221292,
    35.194282
  ],
  "description": "An ancient place, cited: BAtlas 68 D3 Sabboura",
  "features": [
    {
      "type": "Feature",
      "geometry": {
        "type": "Point",
        "coordinates": [
          37.221292,
          35.194282
        ]
      },
      "properties": {
        "description": "representative point"
      }
    },
    {
      "geometry": {
        "type": "Point",
        "coordinates": [
          37.221292,
          35.194282
        ]
      },
      "id": "darmc-location-8259",
      "type": "Feature",
      "properties": {
        "description": "500K scale point location",
        "location_precision": "precise",
        "title": "DARMC location 8259",
        "link": "http://pleiades.stoa.org/places/668359/darmc-location-8259"
      }
    }
  ]
}