{
  "type": "FeatureCollection",
  "title": "Oriza/Oruba/Oresa",
  "id": "668323",
  "description": "An ancient place, cited: BAtlas 68 G3 Oriza/Oruba/Oresa",
  "bbox": [
    38.911148,
    35.074363,
    38.911148,
    35.074363
  ],
  "reprPoint": [
    38.911148,
    35.074363
  ],
  "names": [
    "Oriza",
    "Oruba",
    "Oresa",
    "Orissa"
  ],
  "features": [
    {
      "geometry": {
        "type": "Point",
        "coordinates": [
          38.94342,
          35.124102
        ]
      },
      "id": "darmc-location-8164",
      "type": "Feature",
      "properties": {
        "description": "500K scale point location",
        "location_precision": "precise",
        "title": "DARMC location 8164",
        "link": "http://pleiades.stoa.org/places/668323/darmc-location-8164"
      }
    },
    {
      "geometry": {
        "type": "Point",
        "coordinates": [
          38.911148,
          35.074363
        ]
      },
      "id": "dare-location",
      "type": "Feature",
      "properties": {
        "description": "Representative point location, village precision",
        "location_precision": "precise",
        "title": "DARE Location",
        "link": "http://pleiades.stoa.org/places/668323/dare-location"
      }
    }
  ]
}