{
  "type": "FeatureCollection",
  "title": "Nicephorium/Callinicum/Leontopolis",
  "id": "668318",
  "bbox": [
    39.023783,
    35.929747,
    39.08287,
    35.972501
  ],
  "description": "Nicephorium (modern ar-Raqqa in Syria) was an ancient settlement on the river Euphrates in Syria.",
  "connectsWith": [
    "199032881"
  ],
  "names": [
    "Nicephorium",
    "Callinicum",
    "Leontopolis",
    "ar-Rāfiqa",
    "Kallinikos",
    "Leonopolis",
    "Raqqa",
    "ar-Raqqa",
    "Nikephorion",
    "Nicephorion"
  ],
  "features": [
    {
      "type": "Feature",
      "geometry": {
        "type": "Point",
        "coordinates": [
          39.0569913333,
          35.9500183333
        ]
      },
      "properties": {
        "description": "representative point"
      }
    },
    {
      "geometry": {
        "type": "Point",
        "coordinates": [
          39.08287,
          35.972501
        ]
      },
      "id": "darmc-location-5127",
      "type": "Feature",
      "properties": {
        "description": "1:500,000 scale representative point location digitized from the Barrington Atlas of the Greek and Roman World by the Digital Atlas of Roman and Medieval Civilizations project at Harvard University.",
        "location_precision": "precise",
        "title": "DARMC location 5127",
        "link": "http://pleiades.stoa.org/places/668318/darmc-location-5127"
      }
    },
    {
      "geometry": {
        "type": "Point",
        "coordinates": [
          39.064321,
          35.929747
        ]
      },
      "id": "darmc-location-22365",
      "type": "Feature",
      "properties": {
        "description": "Representative point location digitized from the Barrington Atlas of the Greek and Roman World by the Digital Atlas of Roman and Medieval Civilizations project at Harvard University.",
        "location_precision": "precise",
        "title": "DARMC location 22365",
        "link": "http://pleiades.stoa.org/places/668318/darmc-location-22365"
      }
    },
    {
      "geometry": {
        "type": "Point",
        "coordinates": [
          39.023783,
          35.947807
        ]
      },
      "id": "dare-location",
      "type": "Feature",
      "properties": {
        "description": "Representative point location, village precision",
        "location_precision": "precise",
        "title": "DARE Location",
        "link": "http://pleiades.stoa.org/places/668318/dare-location"
      }
    }
  ]
}