{
  "type": "FeatureCollection",
  "title": "Seriane?",
  "id": "668369",
  "bbox": [
    37.800064,
    35.387685,
    37.800064,
    35.387685
  ],
  "description": "An ancient place, cited: BAtlas 68 E3 Seriane?",
  "names": [
    "Seriane"
  ],
  "features": [
    {
      "type": "Feature",
      "geometry": {
        "type": "Point",
        "coordinates": [
          37.800064,
          35.387685
        ]
      },
      "properties": {
        "description": "representative point"
      }
    },
    {
      "geometry": {
        "type": "Point",
        "coordinates": [
          37.800064,
          35.387685
        ]
      },
      "id": "darmc-location-14688",
      "type": "Feature",
      "properties": {
        "description": "500K scale point location",
        "location_precision": "precise",
        "title": "DARMC location 14688",
        "link": "http://pleiades.stoa.org/places/668369/darmc-location-14688"
      }
    }
  ]
}