{
  "type": "FeatureCollection",
  "title": "Qalaa",
  "id": "668343",
  "bbox": [
    36.056059,
    34.444834,
    36.056059,
    34.444834
  ],
  "description": "An ancient place, cited: BAtlas 68 B5 Qalaa",
  "features": [
    {
      "type": "Feature",
      "geometry": {
        "type": "Point",
        "coordinates": [
          36.056059,
          34.444834
        ]
      },
      "properties": {
        "description": "representative point"
      }
    },
    {
      "geometry": {
        "type": "Point",
        "coordinates": [
          36.056059,
          34.444834
        ]
      },
      "id": "darmc-location-16158",
      "type": "Feature",
      "properties": {
        "description": "500K scale point location",
        "location_precision": "precise",
        "title": "DARMC location 16158",
        "link": "http://pleiades.stoa.org/places/668343/darmc-location-16158"
      }
    }
  ]
}