{
  "type": "FeatureCollection",
  "title": "Tetrapyrgium",
  "id": "668385",
  "description": "An ancient place, cited: BAtlas 68 G2 Tetrapyrgium",
  "bbox": [
    38.813007,
    35.80174,
    38.813007,
    35.80174
  ],
  "reprPoint": [
    38.813007,
    35.80174
  ],
  "names": [
    "Tetrapyrgium"
  ],
  "features": [
    {
      "geometry": {
        "type": "Point",
        "coordinates": [
          38.813007,
          35.80174
        ]
      },
      "id": "darmc-location-8358",
      "type": "Feature",
      "properties": {
        "description": "500K scale point location",
        "location_precision": "precise",
        "title": "DARMC location 8358",
        "link": "http://pleiades.stoa.org/places/668385/darmc-location-8358"
      }
    }
  ]
}