{
  "type": "FeatureCollection",
  "title": "Reccopolis",
  "id": "668575405",
  "bbox": [
    -2.8940678,
    40.3209913,
    -2.8940678,
    40.3209913
  ],
  "description": "Reccopolis is an urban, Visigothic, ex-novo foundation made under king Liuvigild in A.D. 578. The archaeological remains at the site include a palace complex, public area, basilica, walls, and aqueduct. The site is known today by the Spanish version of its Latin name (Recópolis); it is located near the modern village of Zorita de los Canes in the Spanish province of Guadelajara.",
  "connectsWith": [
    "246322",
    "256463"
  ],
  "names": [
    "Recópolis",
    "Reccopolis"
  ],
  "features": [
    {
      "type": "Feature",
      "geometry": {
        "type": "Point",
        "coordinates": [
          -2.8940678,
          40.3209913
        ]
      },
      "properties": {
        "description": "representative point"
      }
    },
    {
      "geometry": {
        "type": "Point",
        "coordinates": [
          -2.8940678,
          40.3209913
        ]
      },
      "id": "osm-location-of-reccopolis",
      "type": "Feature",
      "properties": {
        "description": "Location based on OpenStreetMap",
        "location_precision": "precise",
        "title": "OSM location of Reccopolis",
        "link": "http://pleiades.stoa.org/places/668575405/osm-location-of-reccopolis"
      }
    }
  ]
}