{
  "type": "FeatureCollection",
  "title": "Reccopolis",
  "id": "668575405",
  "description": "Reccopolis is an urban, Visigothic, ex-novo foundation made under king Liuvigild in A.D. 578. The archaeological remains at the site include a palace complex, public area, basilica, walls, and aqueduct. The site is known today by the Spanish version of its Latin name (Recópolis); it is located near the modern village of Zorita de los Canes in the Spanish province of Guadelajara.",
  "bbox": [
    -2.8937871,
    40.321049,
    -2.8937871,
    40.321049
  ],
  "reprPoint": [
    -2.8937871,
    40.321049
  ],
  "names": [
    "Recópolis",
    "Reccopolis",
    "Racubel"
  ],
  "features": [
    {
      "geometry": {
        "type": "Point",
        "coordinates": [
          -2.893,
          40.32
        ]
      },
      "id": "reccopolis",
      "type": "Feature",
      "properties": {
        "description": "Visigothic urban foundation of AD 578 by king Liuvigild. Administrative centre, walls, church, suburbs. It was also a mint and a centre of glass production.",
        "location_precision": "precise",
        "title": "Reccopolis",
        "link": "http://pleiades.stoa.org/places/668575405/reccopolis"
      }
    },
    {
      "geometry": {
        "type": "Point",
        "coordinates": [
          -2.6695178,
          40.4299568
        ]
      },
      "id": "osm-location",
      "type": "Feature",
      "properties": {
        "description": "Location based on OpenStreetMap",
        "location_precision": "precise",
        "title": "OSM location",
        "link": "http://pleiades.stoa.org/places/668575405/osm-location"
      }
    },
    {
      "geometry": {
        "type": "Point",
        "coordinates": [
          -2.8937871,
          40.321049
        ]
      },
      "id": "osm-location-of-reccopolis",
      "type": "Feature",
      "properties": {
        "description": "Location based on OpenStreetMap",
        "location_precision": "precise",
        "title": "OSM location of Reccopolis",
        "link": "http://pleiades.stoa.org/places/668575405/osm-location-of-reccopolis"
      }
    }
  ]
}