{
  "type": "FeatureCollection",
  "title": "Ṭūbzāwah",
  "id": "670767059",
  "bbox": [
    44.6979,
    36.8079,
    44.6979,
    36.8079
  ],
  "description": "Find place for stele with cuneiform inscription.",
  "names": [
    "Ṭūbzāwah"
  ],
  "features": [
    {
      "type": "Feature",
      "geometry": {
        "type": "Point",
        "coordinates": [
          44.6979,
          36.8079
        ]
      },
      "properties": {
        "description": "representative point"
      }
    },
    {
      "geometry": {
        "type": "Point",
        "coordinates": [
          44.6979,
          36.8079
        ]
      },
      "id": "cigs-location-of-tubzawah",
      "type": "Feature",
      "properties": {
        "description": null,
        "location_precision": "precise",
        "title": "CIGS location of Ṭūbzāwah",
        "link": "http://pleiades.stoa.org/places/670767059/cigs-location-of-tubzawah"
      }
    }
  ]
}