{
  "type": "FeatureCollection",
  "title": "Beltany",
  "id": "671053357",
  "description": "At Beltany in County Donegal, Ireland, is a Neolithic stone circle monument comprised of 64 menhirs. The monument dates ca. 1400-800 BC.",
  "bbox": [
    -7.6050202,
    54.8505092,
    -7.6050202,
    54.8505092
  ],
  "connectsWith": [
    "20487"
  ],
  "reprPoint": [
    -7.6050202,
    54.8505092
  ],
  "features": [
    {
      "geometry": {
        "type": "Point",
        "coordinates": [
          -7.6050202,
          54.8505092
        ]
      },
      "id": "location-of-beltany-stone-circle",
      "type": "Feature",
      "properties": {
        "description": "Location based on OpenStreetMap",
        "location_precision": "precise",
        "title": "location of Beltany stone circle",
        "link": "http://pleiades.stoa.org/places/671053357/location-of-beltany-stone-circle"
      }
    }
  ]
}