{
  "type": "FeatureCollection",
  "title": "La Befa, Carcerelle",
  "id": "672896829",
  "bbox": [
    11.40111,
    43.1181826,
    11.40111,
    43.1181826
  ],
  "description": "The Roman villa rustica of La Befa is positioned at the point where the Torrente di Crevoli joins the river Ombrone. Excavation of the site identified a northern sector and a southern sector, both with multiple architectural phases, likely beginning the later first century CE.",
  "connectsWith": [
    "403285"
  ],
  "names": [
    "La Befa"
  ],
  "features": [
    {
      "type": "Feature",
      "geometry": {
        "type": "Point",
        "coordinates": [
          11.40111,
          43.1181826
        ]
      },
      "properties": {
        "description": "representative point"
      }
    },
    {
      "geometry": {
        "type": "Point",
        "coordinates": [
          11.40111,
          43.1181826
        ]
      },
      "id": "osm-location-of-la-befa",
      "type": "Feature",
      "properties": {
        "description": "Location based on OpenStreetMap",
        "location_precision": "precise",
        "title": "OSM location of La Befa",
        "link": "http://pleiades.stoa.org/places/672896829/osm-location-of-la-befa"
      }
    }
  ]
}