{
  "type": "FeatureCollection",
  "title": "Graeco-Roman theater at Oinoanda",
  "id": "673008673",
  "bbox": [
    29.5497418,
    36.8096309,
    29.5497418,
    36.8096309
  ],
  "description": "The theater at Oinoanda is believed to date from the second century B.C. It  sits on the northern fringe of the city.",
  "connectsWith": [
    "639013"
  ],
  "features": [
    {
      "type": "Feature",
      "geometry": {
        "type": "Point",
        "coordinates": [
          29.5497418,
          36.8096309
        ]
      },
      "properties": {
        "description": "representative point"
      }
    },
    {
      "geometry": {
        "type": "Point",
        "coordinates": [
          29.5497418,
          36.8096309
        ]
      },
      "id": "location-of-graeco-roman-theater",
      "type": "Feature",
      "properties": {
        "description": "Representative location based on OpenStreetMap.",
        "location_precision": "precise",
        "title": "OSM location of Graeco-Roman theater",
        "link": "http://pleiades.stoa.org/places/673008673/location-of-graeco-roman-theater"
      }
    }
  ]
}