{
  "type": "FeatureCollection",
  "title": "Compitum Acilii",
  "id": "673471798",
  "bbox": [
    12.486137,
    41.891775,
    12.486137,
    41.891775
  ],
  "description": "The Compitum Acilii was a crossroads in the city of Rome. It was most likely the intersection of the Vicus Cuprius and another street on the Carinae.",
  "connectsWith": [
    "423025",
    "679976755"
  ],
  "names": [
    "Compitum Acilii"
  ],
  "features": [
    {
      "type": "Feature",
      "geometry": {
        "type": "Point",
        "coordinates": [
          12.486137,
          41.891775
        ]
      },
      "properties": {
        "description": "representative point"
      }
    }
  ]
}