{
  "type": "FeatureCollection",
  "title": "Zenodotion",
  "id": "674275",
  "bbox": [
    39.023783,
    35.929747,
    39.08287,
    35.972501
  ],
  "description": "An ancient place, cited: BAtlas 68 unlocated Zenodotion",
  "connectsWith": [
    "668318",
    "658561"
  ],
  "names": [
    "Zenodotion"
  ],
  "features": [
    {
      "type": "Feature",
      "geometry": {
        "type": "Point",
        "coordinates": [
          39.0569913333,
          35.9500183333
        ]
      },
      "properties": {
        "description": "representative point"
      }
    },
    {
      "geometry": null,
      "id": "undetermined",
      "type": "Feature",
      "properties": {
        "description": null,
        "location_precision": "unlocated",
        "title": "Undetermined location",
        "link": "http://pleiades.stoa.org/places/674275/undetermined"
      }
    }
  ]
}