{
  "type": "FeatureCollection",
  "title": "Late Roman Round Building",
  "id": "675812634",
  "bbox": [
    23.72256,
    37.97601,
    23.72256,
    37.97601
  ],
  "description": "A round building constructed in the northwestern corner of the Athenian Agora in the 5th century AD over the Crossroads Enclosure. It was ruined in the late 5th or 6th centuries AD.",
  "connectsWith": [
    "807514119",
    "251170827"
  ],
  "names": [
    "Late Roman Round Building"
  ],
  "features": [
    {
      "type": "Feature",
      "geometry": {
        "type": "Point",
        "coordinates": [
          23.72256,
          37.97601
        ]
      },
      "properties": {
        "description": "representative point"
      }
    },
    {
      "geometry": {
        "type": "Point",
        "coordinates": [
          23.72256,
          37.97601
        ]
      },
      "id": "topostext-location-crossroads-enclosure",
      "type": "Feature",
      "properties": {
        "description": null,
        "location_precision": "precise",
        "title": "ToposText Location: Crossroads Enclosure",
        "link": "http://pleiades.stoa.org/places/675812634/topostext-location-crossroads-enclosure"
      }
    }
  ]
}