{
  "type": "FeatureCollection",
  "title": "Roman theater at Iol Caesarea",
  "id": "677240335",
  "bbox": [
    2.1900063,
    36.6054206,
    2.1900063,
    36.6054206
  ],
  "description": "An important early example of Roman theatral architecture.",
  "connectsWith": [
    "295279"
  ],
  "features": [
    {
      "type": "Feature",
      "geometry": {
        "type": "Point",
        "coordinates": [
          2.1900063,
          36.6054206
        ]
      },
      "properties": {
        "description": "representative point"
      }
    },
    {
      "geometry": {
        "type": "Point",
        "coordinates": [
          2.1900063,
          36.6054206
        ]
      },
      "id": "location-of-roman-theater",
      "type": "Feature",
      "properties": {
        "description": "Location based on OpenStreetMap",
        "location_precision": "precise",
        "title": "OSM location of Roman theater",
        "link": "http://pleiades.stoa.org/places/677240335/location-of-roman-theater"
      }
    }
  ]
}