{
  "type": "FeatureCollection",
  "title": "Abila Dekapoleos/Seleukeia",
  "id": "677992",
  "description": "An ancient place, cited: BAtlas 69 C4 Abila Dekapoleos/Seleukeia",
  "bbox": [
    35.869215,
    32.683121,
    35.869215,
    32.683121
  ],
  "reprPoint": [
    35.869215,
    32.683121
  ],
  "names": [
    "Abila Dekapoleos",
    "Seleukeia"
  ],
  "features": [
    {
      "geometry": {
        "type": "Point",
        "coordinates": [
          35.869215,
          32.683121
        ]
      },
      "id": "darmc-location-19921",
      "type": "Feature",
      "properties": {
        "description": "500K scale point location",
        "location_precision": "precise",
        "title": "DARMC location 19921",
        "link": "http://pleiades.stoa.org/places/677992/darmc-location-19921"
      }
    },
    {
      "geometry": {
        "type": "Point",
        "coordinates": [
          35.732805,
          32.962668
        ]
      },
      "id": "darmc-location-4879",
      "type": "Feature",
      "properties": {
        "description": "500K scale point location",
        "location_precision": "precise",
        "title": "DARMC location 4879",
        "link": "http://pleiades.stoa.org/places/677992/darmc-location-4879"
      }
    }
  ]
}