{
  "type": "FeatureCollection",
  "title": "‘Adarin’",
  "id": "677997",
  "description": "An ancient place, cited: BAtlas 69 E2 ‘Adarin’",
  "bbox": [
    36.5958947,
    33.7393667,
    36.5958947,
    33.7393667
  ],
  "reprPoint": [
    36.5958947,
    33.7393667
  ],
  "names": [
    "Adarin",
    "Atera"
  ],
  "features": [
    {
      "geometry": {
        "type": "Point",
        "coordinates": [
          36.572544,
          33.744486
        ]
      },
      "id": "darmc-location-7956",
      "type": "Feature",
      "properties": {
        "description": "500K scale point location",
        "location_precision": "precise",
        "title": "DARMC location 7956",
        "link": "http://pleiades.stoa.org/places/677997/darmc-location-7956"
      }
    },
    {
      "geometry": {
        "type": "Point",
        "coordinates": [
          36.59589470000003,
          33.7393667
        ]
      },
      "id": "dare-location",
      "type": "Feature",
      "properties": {
        "description": "Representative point location, village precision",
        "location_precision": "precise",
        "title": "DARE Location",
        "link": "http://pleiades.stoa.org/places/677997/dare-location"
      }
    }
  ]
}