{
  "type": "FeatureCollection",
  "title": "Bosana",
  "id": "678071",
  "description": "An ancient place, cited: BAtlas 69 E4 Bosana",
  "bbox": [
    36.790336,
    32.686895,
    36.790336,
    32.686895
  ],
  "reprPoint": [
    36.790336,
    32.686895
  ],
  "names": [
    "Bosana"
  ],
  "features": [
    {
      "geometry": {
        "type": "Point",
        "coordinates": [
          36.790336,
          32.686895
        ]
      },
      "id": "darmc-location-18255",
      "type": "Feature",
      "properties": {
        "description": "500K scale point location",
        "location_precision": "precise",
        "title": "DARMC location 18255",
        "link": "http://pleiades.stoa.org/places/678071/darmc-location-18255"
      }
    }
  ]
}