{
  "type": "FeatureCollection",
  "title": "*Athela",
  "id": "678040",
  "description": "An ancient place, cited: BAtlas 69 E4 *Athela",
  "bbox": [
    36.58284,
    32.760967,
    36.58284,
    32.760967
  ],
  "reprPoint": [
    36.58284,
    32.760967
  ],
  "names": [
    "Athela"
  ],
  "features": [
    {
      "geometry": {
        "type": "Point",
        "coordinates": [
          36.58284,
          32.760967
        ]
      },
      "id": "darmc-location-18220",
      "type": "Feature",
      "properties": {
        "description": "500K scale point location",
        "location_precision": "precise",
        "title": "DARMC location 18220",
        "link": "http://pleiades.stoa.org/places/678040/darmc-location-18220"
      }
    }
  ]
}