{
  "type": "FeatureCollection",
  "title": "Casama",
  "id": "678085",
  "description": "An ancient place, cited: BAtlas 69 E1 Casama",
  "bbox": [
    36.734612,
    34.025421,
    36.734612,
    34.025421
  ],
  "reprPoint": [
    36.734612,
    34.025421
  ],
  "names": [
    "Casama"
  ],
  "features": [
    {
      "geometry": {
        "type": "Point",
        "coordinates": [
          36.700612,
          34.031455
        ]
      },
      "id": "darmc-location-8554",
      "type": "Feature",
      "properties": {
        "description": "500K scale point location",
        "location_precision": "precise",
        "title": "DARMC location 8554",
        "link": "http://pleiades.stoa.org/places/678085/darmc-location-8554"
      }
    },
    {
      "geometry": {
        "type": "Point",
        "coordinates": [
          36.73461199999997,
          34.025421
        ]
      },
      "id": "dare-location",
      "type": "Feature",
      "properties": {
        "description": "Representative point location, village precision",
        "location_precision": "precise",
        "title": "DARE Location",
        "link": "http://pleiades.stoa.org/places/678085/dare-location"
      }
    }
  ]
}