{
  "type": "FeatureCollection",
  "title": "Bethezoba",
  "id": "678064",
  "description": "An ancient place, cited: BAtlas 69 C5 Bethezoba",
  "bbox": [
    35.773767,
    32.43518,
    35.773767,
    32.43518
  ],
  "reprPoint": [
    35.773767,
    32.43518
  ],
  "names": [
    "Bethezoba"
  ],
  "features": [
    {
      "geometry": {
        "type": "Point",
        "coordinates": [
          35.773767,
          32.43518
        ]
      },
      "id": "darmc-location-9986",
      "type": "Feature",
      "properties": {
        "description": "500K scale point location",
        "location_precision": "precise",
        "title": "DARMC location 9986",
        "link": "http://pleiades.stoa.org/places/678064/darmc-location-9986"
      }
    }
  ]
}