{
  "type": "FeatureCollection",
  "title": "Gaba?",
  "id": "678137",
  "bbox": [
    35.106902,
    32.730365,
    35.106902,
    32.730365
  ],
  "description": "An ancient place, cited: BAtlas 69 B4 Gaba?",
  "names": [
    "Gaba"
  ],
  "features": [
    {
      "type": "Feature",
      "geometry": {
        "type": "Point",
        "coordinates": [
          35.106902,
          32.730365
        ]
      },
      "properties": {
        "description": "representative point"
      }
    },
    {
      "geometry": {
        "type": "Point",
        "coordinates": [
          35.106902,
          32.730365
        ]
      },
      "id": "darmc-location-12460",
      "type": "Feature",
      "properties": {
        "description": "500K scale point location",
        "location_precision": "precise",
        "title": "DARMC location 12460",
        "link": "http://pleiades.stoa.org/places/678137/darmc-location-12460"
      }
    }
  ]
}