{
  "type": "FeatureCollection",
  "title": "Gennesar",
  "id": "678155",
  "description": "An ancient place, cited: BAtlas 69 C4 Gennesar",
  "bbox": [
    35.533841,
    32.860267,
    35.533841,
    32.860267
  ],
  "reprPoint": [
    35.533841,
    32.860267
  ],
  "names": [
    "Gennesar"
  ],
  "features": [
    {
      "geometry": {
        "type": "Point",
        "coordinates": [
          35.533841,
          32.860267
        ]
      },
      "id": "darmc-location-12519",
      "type": "Feature",
      "properties": {
        "description": "500K scale point location",
        "location_precision": "precise",
        "title": "DARMC location 12519",
        "link": "http://pleiades.stoa.org/places/678155/darmc-location-12519"
      }
    }
  ]
}