{
  "type": "FeatureCollection",
  "title": "Harran el-Awamid",
  "id": "678174",
  "bbox": [
    36.52955,
    33.448933,
    36.52955,
    33.448933
  ],
  "description": "An ancient place, cited: BAtlas 69 E3 Harran el-Awamid",
  "features": [
    {
      "type": "Feature",
      "geometry": {
        "type": "Point",
        "coordinates": [
          36.52955,
          33.448933
        ]
      },
      "properties": {
        "description": "representative point"
      }
    },
    {
      "geometry": {
        "type": "Point",
        "coordinates": [
          36.52955,
          33.448933
        ]
      },
      "id": "darmc-location-25989",
      "type": "Feature",
      "properties": {
        "description": "500K scale point location",
        "location_precision": "precise",
        "title": "DARMC location 25989",
        "link": "http://pleiades.stoa.org/places/678174/darmc-location-25989"
      }
    }
  ]
}