{
  "type": "FeatureCollection",
  "title": "Horvat 'Erav",
  "id": "678186",
  "bbox": [
    35.219235,
    33.083324,
    35.219235,
    33.083324
  ],
  "description": "An ancient place, cited: BAtlas 69 B3 Horvat 'Erav",
  "features": [
    {
      "type": "Feature",
      "geometry": {
        "type": "Point",
        "coordinates": [
          35.219235,
          33.083324
        ]
      },
      "properties": {
        "description": "representative point"
      }
    },
    {
      "geometry": {
        "type": "Point",
        "coordinates": [
          35.219235,
          33.083324
        ]
      },
      "id": "darmc-location-15219",
      "type": "Feature",
      "properties": {
        "description": "500K scale point location",
        "location_precision": "precise",
        "title": "DARMC location 15219",
        "link": "http://pleiades.stoa.org/places/678186/darmc-location-15219"
      }
    }
  ]
}