{
  "type": "FeatureCollection",
  "title": "Ginai(a)/Gema",
  "id": "678163",
  "description": "An ancient place, cited: BAtlas 69 B5 Ginai(a)/Gema",
  "bbox": [
    35.302465,
    32.461848,
    35.302465,
    32.461848
  ],
  "reprPoint": [
    35.302465,
    32.461848
  ],
  "names": [
    "Ginaia",
    "Ginai",
    "Gema"
  ],
  "features": [
    {
      "geometry": {
        "type": "Point",
        "coordinates": [
          35.302465,
          32.461848
        ]
      },
      "id": "darmc-location-20285",
      "type": "Feature",
      "properties": {
        "description": "500K scale point location",
        "location_precision": "precise",
        "title": "DARMC location 20285",
        "link": "http://pleiades.stoa.org/places/678163/darmc-location-20285"
      }
    }
  ]
}