{
  "type": "FeatureCollection",
  "title": "Iotapata",
  "id": "678201",
  "bbox": [
    35.2775,
    32.832222,
    35.2777328,
    32.8323135
  ],
  "description": "A Hellenistic village that later became a key site during the Great Jewish Revolt.",
  "names": [
    "Iotapata",
    "Yodfat",
    "Jotapata",
    "Yodfat",
    "Jaṭbite"
  ],
  "features": [
    {
      "type": "Feature",
      "geometry": {
        "type": "Point",
        "coordinates": [
          35.2776164,
          32.83226775
        ]
      },
      "properties": {
        "description": "representative point"
      }
    },
    {
      "geometry": {
        "type": "Point",
        "coordinates": [
          35.2775,
          32.832222
        ]
      },
      "id": "dare-location",
      "type": "Feature",
      "properties": {
        "description": "Representative point location, site precision",
        "location_precision": "precise",
        "title": "DARE Location",
        "link": "http://pleiades.stoa.org/places/678201/dare-location"
      }
    },
    {
      "geometry": {
        "type": "Point",
        "coordinates": [
          35.2777328,
          32.8323135
        ]
      },
      "id": "osm-location-of-tel-yodfat",
      "type": "Feature",
      "properties": {
        "description": "Representative location based on OpenStreetMap",
        "location_precision": "precise",
        "title": "OSM location of Tel Yodfat",
        "link": "http://pleiades.stoa.org/places/678201/osm-location-of-tel-yodfat"
      }
    }
  ]
}