{
  "type": "FeatureCollection",
  "title": "Kadasa",
  "id": "678215",
  "description": "An ancient place, cited: BAtlas 69 C3 Kadasa",
  "bbox": [
    35.529938,
    33.1101085,
    35.5309562,
    33.11132
  ],
  "reprPoint": [
    35.5304471,
    33.11071425
  ],
  "names": [
    "Kadasa",
    "Kydissos",
    "Tel Qedesh"
  ],
  "features": [
    {
      "geometry": {
        "type": "Point",
        "coordinates": [
          35.529938,
          33.11132
        ]
      },
      "id": "darmc-location-20357",
      "type": "Feature",
      "properties": {
        "description": "500K scale point location",
        "location_precision": "precise",
        "title": "DARMC location 20357",
        "link": "http://pleiades.stoa.org/places/678215/darmc-location-20357"
      }
    },
    {
      "geometry": {
        "type": "Point",
        "coordinates": [
          35.5309562,
          33.1101085
        ]
      },
      "id": "tel-kedesh",
      "type": "Feature",
      "properties": {
        "description": "Representative location based on a node derived from OpenStreetMap",
        "location_precision": "precise",
        "title": "OSM location of Centerpoint of Tel Kedesh",
        "link": "http://pleiades.stoa.org/places/678215/tel-kedesh"
      }
    }
  ]
}