{
  "type": "FeatureCollection",
  "title": "Krokodeilonpolis",
  "id": "678261",
  "bbox": [
    34.910199,
    32.53493,
    34.910199,
    32.53493
  ],
  "description": "An ancient place, cited: BAtlas 69 A4 Krokodeilonpolis",
  "names": [
    "Krokodeilonpolis"
  ],
  "features": [
    {
      "type": "Feature",
      "geometry": {
        "type": "Point",
        "coordinates": [
          34.910199,
          32.53493
        ]
      },
      "properties": {
        "description": "representative point"
      }
    },
    {
      "geometry": {
        "type": "Point",
        "coordinates": [
          34.910199,
          32.53493
        ]
      },
      "id": "darmc-location-13316",
      "type": "Feature",
      "properties": {
        "description": "500K scale point location",
        "location_precision": "precise",
        "title": "DARMC location 13316",
        "link": "http://pleiades.stoa.org/places/678261/darmc-location-13316"
      }
    }
  ]
}