{
  "type": "FeatureCollection",
  "title": "Nahf",
  "id": "678293",
  "description": "An ancient place, cited: BAtlas 69 B4 Nahf",
  "bbox": [
    35.310513,
    32.930618,
    35.310513,
    32.930618
  ],
  "reprPoint": [
    35.310513,
    32.930618
  ],
  "features": [
    {
      "geometry": {
        "type": "Point",
        "coordinates": [
          35.310513,
          32.930618
        ]
      },
      "id": "darmc-location-13861",
      "type": "Feature",
      "properties": {
        "description": "500K scale point location",
        "location_precision": "precise",
        "title": "DARMC location 13861",
        "link": "http://pleiades.stoa.org/places/678293/darmc-location-13861"
      }
    }
  ]
}