{
  "type": "FeatureCollection",
  "title": "Khirbet Summaqa",
  "id": "678249",
  "description": "An ancient place, cited: BAtlas 69 B4 Khirbet Summaqa",
  "bbox": [
    35.053279,
    32.661186,
    35.053279,
    32.661186
  ],
  "reprPoint": [
    35.053279,
    32.661186
  ],
  "features": [
    {
      "geometry": {
        "type": "Point",
        "coordinates": [
          35.053279,
          32.661186
        ]
      },
      "id": "darmc-location-23140",
      "type": "Feature",
      "properties": {
        "description": "500K scale point location",
        "location_precision": "precise",
        "title": "DARMC location 23140",
        "link": "http://pleiades.stoa.org/places/678249/darmc-location-23140"
      }
    }
  ]
}