{
  "type": "FeatureCollection",
  "title": "Kokhav ha-Yarden",
  "id": "678258",
  "bbox": [
    35.527238,
    32.600211,
    35.527238,
    32.600211
  ],
  "description": "An ancient place, cited: BAtlas 69 C4 Kokhav ha-Yarden",
  "features": [
    {
      "type": "Feature",
      "geometry": {
        "type": "Point",
        "coordinates": [
          35.527238,
          32.600211
        ]
      },
      "properties": {
        "description": "representative point"
      }
    },
    {
      "geometry": {
        "type": "Point",
        "coordinates": [
          35.527238,
          32.600211
        ]
      },
      "id": "darmc-location-23226",
      "type": "Feature",
      "properties": {
        "description": "500K scale point location",
        "location_precision": "precise",
        "title": "DARMC location 23226",
        "link": "http://pleiades.stoa.org/places/678258/darmc-location-23226"
      }
    }
  ]
}