{
  "type": "FeatureCollection",
  "title": "Iotapata",
  "id": "678201",
  "bbox": [
    35.2775,
    32.832222,
    35.286222,
    32.83549
  ],
  "description": "A Hellenistic village that later became a key site during the Great Jewish Revolt.",
  "names": [
    "Iotapata",
    "Yodfat",
    "Jotapata",
    "Yodfat",
    "Jaṭbite"
  ],
  "features": [
    {
      "type": "Feature",
      "geometry": {
        "type": "Point",
        "coordinates": [
          35.281861,
          32.833856
        ]
      },
      "properties": {
        "description": "representative point"
      }
    },
    {
      "geometry": {
        "type": "Point",
        "coordinates": [
          35.286222,
          32.83549
        ]
      },
      "id": "darmc-location-12882",
      "type": "Feature",
      "properties": {
        "description": "1:500,000 scale representative point location digitized from the Barrington Atlas of the Greek and Roman World by the Digital Atlas of Roman and Medieval Civilizations project at Harvard University.",
        "location_precision": "precise",
        "title": "DARMC location 12882",
        "link": "http://pleiades.stoa.org/places/678201/darmc-location-12882"
      }
    },
    {
      "geometry": {
        "type": "Point",
        "coordinates": [
          35.2775,
          32.832222
        ]
      },
      "id": "dare-location",
      "type": "Feature",
      "properties": {
        "description": "Representative point location, site precision",
        "location_precision": "precise",
        "title": "DARE Location",
        "link": "http://pleiades.stoa.org/places/678201/dare-location"
      }
    }
  ]
}