{
  "type": "FeatureCollection",
  "title": "Meser",
  "id": "678286",
  "description": "An ancient place, cited: BAtlas 69 B5 Meser",
  "bbox": [
    35.047491,
    32.440205,
    35.047491,
    32.440205
  ],
  "reprPoint": [
    35.047491,
    32.440205
  ],
  "features": [
    {
      "geometry": {
        "type": "Point",
        "coordinates": [
          35.047491,
          32.440205
        ]
      },
      "id": "darmc-location-13715",
      "type": "Feature",
      "properties": {
        "description": "500K scale point location",
        "location_precision": "precise",
        "title": "DARMC location 13715",
        "link": "http://pleiades.stoa.org/places/678286/darmc-location-13715"
      }
    }
  ]
}