{
  "type": "FeatureCollection",
  "title": "The Sassi and the Park of the Rupestrian Churches of Matera",
  "id": "678263113",
  "bbox": [
    16.6083,
    40.6667,
    16.6083,
    40.6667
  ],
  "description": "A series of rock-cut dwellings and buildings.",
  "connectsWith": [
    "442650"
  ],
  "features": [
    {
      "type": "Feature",
      "geometry": {
        "type": "Point",
        "coordinates": [
          16.6083,
          40.6667
        ]
      },
      "properties": {
        "description": "representative point"
      }
    },
    {
      "geometry": {
        "type": "Point",
        "coordinates": [
          16.6083,
          40.6667
        ]
      },
      "id": "location-of-the-sassi-and-the-park-of-the-rupestrian-churches-of-matera",
      "type": "Feature",
      "properties": {
        "description": "A series of rock-cut dwellings and buildings. Coordinates after Geo-Hack, verified in Google Earth.",
        "location_precision": "precise",
        "title": "Imagery location of The Sassi and the Park of the Rupestrian Churches of Matera",
        "link": "http://pleiades.stoa.org/places/678263113/location-of-the-sassi-and-the-park-of-the-rupestrian-churches-of-matera"
      }
    }
  ]
}