{
  "type": "FeatureCollection",
  "title": "Khirbet et Tira",
  "id": "678244",
  "description": "An ancient place, cited: BAtlas 69 B5 Khirbet et Tira",
  "bbox": [
    35.255049,
    32.158519,
    35.255049,
    32.158519
  ],
  "reprPoint": [
    35.255049,
    32.158519
  ],
  "features": [
    {
      "geometry": {
        "type": "Point",
        "coordinates": [
          35.255049,
          32.158519
        ]
      },
      "id": "darmc-location-23134",
      "type": "Feature",
      "properties": {
        "description": "500K scale point location",
        "location_precision": "precise",
        "title": "DARMC location 23134",
        "link": "http://pleiades.stoa.org/places/678244/darmc-location-23134"
      }
    }
  ]
}