{
  "type": "FeatureCollection",
  "title": "Seia",
  "id": "678381",
  "bbox": [
    36.608748,
    32.735148,
    36.608748,
    32.735148
  ],
  "description": "An ancient place, cited: BAtlas 69 E4 Seia",
  "names": [
    "Seia"
  ],
  "features": [
    {
      "type": "Feature",
      "geometry": {
        "type": "Point",
        "coordinates": [
          36.608748,
          32.735148
        ]
      },
      "properties": {
        "description": "representative point"
      }
    },
    {
      "geometry": {
        "type": "Point",
        "coordinates": [
          36.608748,
          32.735148
        ]
      },
      "id": "darmc-location-980",
      "type": "Feature",
      "properties": {
        "description": "500K scale point location",
        "location_precision": "precise",
        "title": "DARMC location 980",
        "link": "http://pleiades.stoa.org/places/678381/darmc-location-980"
      }
    }
  ]
}