{
  "type": "FeatureCollection",
  "title": "Salem/Salumias",
  "id": "678368",
  "description": "An ancient place, cited: BAtlas 69 C5 Salem/Salumias",
  "bbox": [
    35.528477,
    32.405691,
    35.528477,
    32.405691
  ],
  "reprPoint": [
    35.528477,
    32.405691
  ],
  "names": [
    "Salem",
    "Salumias",
    "Sedima"
  ],
  "features": [
    {
      "geometry": {
        "type": "Point",
        "coordinates": [
          35.528477,
          32.405691
        ]
      },
      "id": "darmc-location-8266",
      "type": "Feature",
      "properties": {
        "description": "500K scale point location",
        "location_precision": "precise",
        "title": "DARMC location 8266",
        "link": "http://pleiades.stoa.org/places/678368/darmc-location-8266"
      }
    }
  ]
}