{
  "type": "FeatureCollection",
  "title": "Nelkomia/Neela?",
  "id": "678305",
  "description": "An ancient place, cited: BAtlas 69 E4 Nelkomia/Neela?",
  "bbox": [
    36.775857,
    32.74287,
    36.775857,
    32.74287
  ],
  "reprPoint": [
    36.775857,
    32.74287
  ],
  "names": [
    "Nelkomia",
    "Neela"
  ],
  "features": [
    {
      "geometry": {
        "type": "Point",
        "coordinates": [
          36.775857,
          32.74287
        ]
      },
      "id": "darmc-location-18691",
      "type": "Feature",
      "properties": {
        "description": "500K scale point location",
        "location_precision": "precise",
        "title": "DARMC location 18691",
        "link": "http://pleiades.stoa.org/places/678305/darmc-location-18691"
      }
    }
  ]
}