{
  "type": "FeatureCollection",
  "title": "Nurith",
  "id": "678311",
  "description": "An ancient place, cited: BAtlas 69 B4 Nurith",
  "bbox": [
    35.366164,
    32.534939,
    35.366164,
    32.534939
  ],
  "reprPoint": [
    35.366164,
    32.534939
  ],
  "features": [
    {
      "geometry": {
        "type": "Point",
        "coordinates": [
          35.366164,
          32.534939
        ]
      },
      "id": "darmc-location-13970",
      "type": "Feature",
      "properties": {
        "description": "500K scale point location",
        "location_precision": "precise",
        "title": "DARMC location 13970",
        "link": "http://pleiades.stoa.org/places/678311/darmc-location-13970"
      }
    }
  ]
}