{
  "type": "FeatureCollection",
  "title": "Oneuatha/*Anabatha",
  "id": "678315",
  "bbox": [
    37.283135,
    34.018825,
    37.283135,
    34.018825
  ],
  "description": "An ancient place, cited: BAtlas 69 F1 Oneuatha/*Anabatha",
  "connectsWith": [
    "743967163"
  ],
  "names": [
    "Oneuatha",
    "Anabatha"
  ],
  "features": [
    {
      "type": "Feature",
      "geometry": {
        "type": "Point",
        "coordinates": [
          37.283135,
          34.018825
        ]
      },
      "properties": {
        "description": "representative point"
      }
    },
    {
      "geometry": {
        "type": "Point",
        "coordinates": [
          37.283135,
          34.018825
        ]
      },
      "id": "darmc-location-8158",
      "type": "Feature",
      "properties": {
        "description": "500K scale point location",
        "location_precision": "precise",
        "title": "DARMC location 8158",
        "link": "http://pleiades.stoa.org/places/678315/darmc-location-8158"
      }
    }
  ]
}