{
  "type": "FeatureCollection",
  "title": "*Selaima",
  "id": "678382",
  "description": "An ancient place, cited: BAtlas 69 E4 *Selaima",
  "bbox": [
    36.553842,
    32.804118,
    36.553842,
    32.804118
  ],
  "reprPoint": [
    36.553842,
    32.804118
  ],
  "names": [
    "Selaima"
  ],
  "features": [
    {
      "geometry": {
        "type": "Point",
        "coordinates": [
          36.553842,
          32.804118
        ]
      },
      "id": "darmc-location-981",
      "type": "Feature",
      "properties": {
        "description": "500K scale point location",
        "location_precision": "precise",
        "title": "DARMC location 981",
        "link": "http://pleiades.stoa.org/places/678382/darmc-location-981"
      }
    }
  ]
}