{
  "type": "FeatureCollection",
  "title": "Ras el-'Ain",
  "id": "678323",
  "bbox": [
    35.219993,
    33.23657,
    35.219993,
    33.23657
  ],
  "description": "An ancient settlement in the southern part of modern Lebanon, known by various names in antiquity.",
  "connectsWith": [
    "678437",
    "678393"
  ],
  "names": [
    "Palaityros",
    "Ušû",
    "Ras el-'Ain"
  ],
  "features": [
    {
      "type": "Feature",
      "geometry": {
        "type": "Point",
        "coordinates": [
          35.219993,
          33.23657
        ]
      },
      "properties": {
        "description": "representative point"
      }
    },
    {
      "geometry": {
        "type": "Point",
        "coordinates": [
          35.219993,
          33.23657
        ]
      },
      "id": "darmc-location-14094",
      "type": "Feature",
      "properties": {
        "description": "1:500,000 scale representative point location digitized from the Barrington Atlas of the Greek and Roman World by the Digital Atlas of Roman and Medieval Civilizations project at Harvard University.",
        "location_precision": "precise",
        "title": "DARMC location 14094",
        "link": "http://pleiades.stoa.org/places/678323/darmc-location-14094"
      }
    }
  ]
}