{
  "type": "FeatureCollection",
  "title": "Qasr el-Ba'iq",
  "id": "678347",
  "bbox": [
    36.338785,
    32.371442,
    36.338785,
    32.371442
  ],
  "description": "An ancient place, cited: BAtlas 69 D5 Qasr el-Ba'iq",
  "features": [
    {
      "type": "Feature",
      "geometry": {
        "type": "Point",
        "coordinates": [
          36.338785,
          32.371442
        ]
      },
      "properties": {
        "description": "representative point"
      }
    },
    {
      "geometry": {
        "type": "Point",
        "coordinates": [
          36.338785,
          32.371442
        ]
      },
      "id": "darmc-location-18219",
      "type": "Feature",
      "properties": {
        "description": "500K scale point location",
        "location_precision": "precise",
        "title": "DARMC location 18219",
        "link": "http://pleiades.stoa.org/places/678347/darmc-location-18219"
      }
    }
  ]
}