{
  "type": "FeatureCollection",
  "title": "Neue",
  "id": "678307",
  "description": "An ancient place, cited: BAtlas 69 D4 Neue",
  "bbox": [
    36.04194,
    32.889346,
    36.04194,
    32.889346
  ],
  "reprPoint": [
    36.04194,
    32.889346
  ],
  "names": [
    "Neue"
  ],
  "features": [
    {
      "geometry": {
        "type": "Point",
        "coordinates": [
          36.042545,
          32.88898
        ]
      },
      "id": "darmc-location-20526",
      "type": "Feature",
      "properties": {
        "description": "500K scale point location",
        "location_precision": "precise",
        "title": "DARMC location 20526",
        "link": "http://pleiades.stoa.org/places/678307/darmc-location-20526"
      }
    },
    {
      "geometry": {
        "type": "Point",
        "coordinates": [
          36.04194,
          32.889346
        ]
      },
      "id": "dare-location",
      "type": "Feature",
      "properties": {
        "description": "Representative point location, village precision",
        "location_precision": "precise",
        "title": "DARE Location",
        "link": "http://pleiades.stoa.org/places/678307/dare-location"
      }
    }
  ]
}