{
  "type": "FeatureCollection",
  "title": "Salem/Salumias",
  "id": "678368",
  "bbox": [
    35.5270805,
    32.3991508,
    35.5270805,
    32.3991508
  ],
  "description": "An ancient place, cited: BAtlas 69 C5 Salem/Salumias",
  "names": [
    "Salem",
    "Salumias",
    "Sedima"
  ],
  "features": [
    {
      "type": "Feature",
      "geometry": {
        "type": "Point",
        "coordinates": [
          35.5270805,
          32.3991508
        ]
      },
      "properties": {
        "description": "representative point"
      }
    },
    {
      "geometry": {
        "type": "Point",
        "coordinates": [
          35.5270805,
          32.3991508
        ]
      },
      "id": "osm-location-of-tel-shalem",
      "type": "Feature",
      "properties": {
        "description": "Representative location based on OpenStreetMap, dates following Barrington Atlas",
        "location_precision": "precise",
        "title": "OSM location of Tel Shalem",
        "link": "http://pleiades.stoa.org/places/678368/osm-location-of-tel-shalem"
      }
    }
  ]
}