{
  "type": "FeatureCollection",
  "title": "Omra",
  "id": "678314",
  "bbox": [
    36.600851,
    32.903344,
    36.600851,
    32.903344
  ],
  "description": "An ancient place, cited: BAtlas 69 E4 Omra",
  "names": [
    "Omra"
  ],
  "features": [
    {
      "type": "Feature",
      "geometry": {
        "type": "Point",
        "coordinates": [
          36.600851,
          32.903344
        ]
      },
      "properties": {
        "description": "representative point"
      }
    },
    {
      "geometry": {
        "type": "Point",
        "coordinates": [
          36.600851,
          32.903344
        ]
      },
      "id": "darmc-location-18122",
      "type": "Feature",
      "properties": {
        "description": "500K scale point location",
        "location_precision": "precise",
        "title": "DARMC location 18122",
        "link": "http://pleiades.stoa.org/places/678314/darmc-location-18122"
      }
    }
  ]
}