{
  "type": "FeatureCollection",
  "title": "Sheikh Miskin",
  "id": "678390",
  "bbox": [
    36.161289,
    32.827563,
    36.161289,
    32.827563
  ],
  "description": "An ancient place, cited: BAtlas 69 D4 Sheikh Miskin",
  "features": [
    {
      "type": "Feature",
      "geometry": {
        "type": "Point",
        "coordinates": [
          36.161289,
          32.827563
        ]
      },
      "properties": {
        "description": "representative point"
      }
    },
    {
      "geometry": {
        "type": "Point",
        "coordinates": [
          36.161289,
          32.827563
        ]
      },
      "id": "darmc-location-3541",
      "type": "Feature",
      "properties": {
        "description": "500K scale point location",
        "location_precision": "precise",
        "title": "DARMC location 3541",
        "link": "http://pleiades.stoa.org/places/678390/darmc-location-3541"
      }
    }
  ]
}