{
  "type": "FeatureCollection",
  "title": "Phaine",
  "id": "678328",
  "description": "An ancient place, cited: BAtlas 69 D3 Phaine",
  "bbox": [
    36.37616,
    33.1287694,
    36.3985493,
    33.133509
  ],
  "reprPoint": [
    36.38735465,
    33.1311392
  ],
  "names": [
    "Phaine"
  ],
  "features": [
    {
      "geometry": {
        "type": "Point",
        "coordinates": [
          36.37616,
          33.133509
        ]
      },
      "id": "darmc-location-18748",
      "type": "Feature",
      "properties": {
        "description": "500K scale point location",
        "location_precision": "precise",
        "title": "DARMC location 18748",
        "link": "http://pleiades.stoa.org/places/678328/darmc-location-18748"
      }
    },
    {
      "geometry": {
        "type": "Point",
        "coordinates": [
          36.39854930000001,
          33.1287694
        ]
      },
      "id": "dare-location",
      "type": "Feature",
      "properties": {
        "description": "Representative point location, village precision",
        "location_precision": "precise",
        "title": "DARE Location",
        "link": "http://pleiades.stoa.org/places/678328/dare-location"
      }
    }
  ]
}