{
  "type": "FeatureCollection",
  "title": "Palaityros",
  "id": "678323",
  "bbox": [
    35.219993,
    33.23657,
    35.219993,
    33.23657
  ],
  "description": "An ancient place, cited: BAtlas 69 B3 Palaityros",
  "names": [
    "Palaityros"
  ],
  "features": [
    {
      "type": "Feature",
      "geometry": {
        "type": "Point",
        "coordinates": [
          35.219993,
          33.23657
        ]
      },
      "properties": {
        "description": "representative point"
      }
    },
    {
      "geometry": {
        "type": "Point",
        "coordinates": [
          35.219993,
          33.23657
        ]
      },
      "id": "darmc-location-14094",
      "type": "Feature",
      "properties": {
        "description": "500K scale point location",
        "location_precision": "precise",
        "title": "DARMC location 14094",
        "link": "http://pleiades.stoa.org/places/678323/darmc-location-14094"
      }
    }
  ]
}