{
  "type": "FeatureCollection",
  "title": "Sennabris/Ginnabris",
  "id": "678386",
  "bbox": [
    35.566036,
    32.709862,
    35.566036,
    32.709862
  ],
  "description": "An ancient place, cited: BAtlas 69 C4 Sennabris/Ginnabris",
  "names": [
    "Sennabris",
    "Ginnabris"
  ],
  "features": [
    {
      "type": "Feature",
      "geometry": {
        "type": "Point",
        "coordinates": [
          35.566036,
          32.709862
        ]
      },
      "properties": {
        "description": "representative point"
      }
    },
    {
      "geometry": {
        "type": "Point",
        "coordinates": [
          35.566036,
          32.709862
        ]
      },
      "id": "darmc-location-14676",
      "type": "Feature",
      "properties": {
        "description": "500K scale point location",
        "location_precision": "precise",
        "title": "DARMC location 14676",
        "link": "http://pleiades.stoa.org/places/678386/darmc-location-14676"
      }
    }
  ]
}