{
  "type": "FeatureCollection",
  "title": "Umtaiyye",
  "id": "678444",
  "bbox": [
    36.295631,
    32.493705,
    36.295631,
    32.493705
  ],
  "description": "An ancient place, cited: BAtlas 69 D5 Umtaiyye",
  "features": [
    {
      "type": "Feature",
      "geometry": {
        "type": "Point",
        "coordinates": [
          36.295631,
          32.493705
        ]
      },
      "properties": {
        "description": "representative point"
      }
    },
    {
      "geometry": {
        "type": "Point",
        "coordinates": [
          36.295631,
          32.493705
        ]
      },
      "id": "darmc-location-15318",
      "type": "Feature",
      "properties": {
        "description": "500K scale point location",
        "location_precision": "precise",
        "title": "DARMC location 15318",
        "link": "http://pleiades.stoa.org/places/678444/darmc-location-15318"
      }
    }
  ]
}