{
  "type": "FeatureCollection",
  "title": "Umm Rihan",
  "id": "678443",
  "bbox": [
    35.141828,
    32.4835623,
    35.141936,
    32.483622
  ],
  "description": "An ancient place, cited: BAtlas 69 B5 Umm Rihan",
  "features": [
    {
      "type": "Feature",
      "geometry": {
        "type": "Point",
        "coordinates": [
          35.141882,
          32.48359215
        ]
      },
      "properties": {
        "description": "representative point"
      }
    },
    {
      "geometry": {
        "type": "Point",
        "coordinates": [
          35.141828,
          32.483622
        ]
      },
      "id": "darmc-location-312",
      "type": "Feature",
      "properties": {
        "description": "500K scale point location",
        "location_precision": "precise",
        "title": "DARMC location 312",
        "link": "http://pleiades.stoa.org/places/678443/darmc-location-312"
      }
    },
    {
      "geometry": {
        "type": "Point",
        "coordinates": [
          35.141936,
          32.4835623
        ]
      },
      "id": "osm-location-of-umm-ar-rihan",
      "type": "Feature",
      "properties": {
        "description": "Location based on OpenStreetMap",
        "location_precision": "precise",
        "title": "OSM location of Umm ar-Rihan",
        "link": "http://pleiades.stoa.org/places/678443/osm-location-of-umm-ar-rihan"
      }
    }
  ]
}