{
  "type": "FeatureCollection",
  "title": "Tyrus/Col. Septimia Severa",
  "id": "678437",
  "bbox": [
    35.1943,
    33.268071,
    35.209358,
    33.2706
  ],
  "description": "The ancient city of Tyre (modern es-Sur on the coast of Lebanon). A UNESCO World Heritage Site, in part because of its \"important archaeological remains, mainly from Roman times.\"",
  "connectsWith": [
    "660988416"
  ],
  "names": [
    "Tyrus",
    "Col. Septimia Severa",
    "Ṭūrā",
    "Ṣūr",
    "Ṭūra",
    "Tyr",
    "Ṣurru",
    "Sur",
    "Tyrus",
    "Tyrus",
    "Colonia Sept. T.",
    "Colonia Septimia T.",
    "Col. Septimia T.",
    "Tyros",
    "Ṣūru",
    "Ṣor",
    "Ṣūrāja",
    "Ṣurrāja",
    "Ṣūr"
  ],
  "features": [
    {
      "type": "Feature",
      "geometry": {
        "type": "Point",
        "coordinates": [
          35.201829,
          33.2693355
        ]
      },
      "properties": {
        "description": "representative point"
      }
    },
    {
      "geometry": {
        "type": "Point",
        "coordinates": [
          35.209358,
          33.268071
        ]
      },
      "id": "dare-location",
      "type": "Feature",
      "properties": {
        "description": "Representative point location, site precision",
        "location_precision": "precise",
        "title": "DARE Location",
        "link": "http://pleiades.stoa.org/places/678437/dare-location"
      }
    },
    {
      "geometry": {
        "type": "Point",
        "coordinates": [
          35.1943,
          33.2706
        ]
      },
      "id": "sur-2",
      "type": "Feature",
      "properties": {
        "description": null,
        "location_precision": "precise",
        "title": "CIGS location of Ṣūr",
        "link": "http://pleiades.stoa.org/places/678437/sur-2"
      }
    }
  ]
}