{
  "type": "FeatureCollection",
  "title": "Umm el-Jimal",
  "id": "678439",
  "description": "Probably a Nabatean foundation, later much expanded in the Roman, Byzantine, and Early Islamic periods, this well-preserved site in the Jordan valley, just south of the Syrian border. Its ancient name is unknown.",
  "bbox": [
    36.366603,
    32.324848,
    36.368638,
    32.326001
  ],
  "reprPoint": [
    36.3676205,
    32.3254245
  ],
  "names": [
    "Umm el-Jimal"
  ],
  "features": [
    {
      "geometry": {
        "type": "Point",
        "coordinates": [
          36.368638,
          32.326001
        ]
      },
      "id": "darmc-location-10311",
      "type": "Feature",
      "properties": {
        "description": "500K scale point location",
        "location_precision": "precise",
        "title": "DARMC location 10311",
        "link": "http://pleiades.stoa.org/places/678439/darmc-location-10311"
      }
    },
    {
      "geometry": {
        "type": "Point",
        "coordinates": [
          36.366603,
          32.324848
        ]
      },
      "id": "dare-location",
      "type": "Feature",
      "properties": {
        "description": "Representative point location, site precision",
        "location_precision": "precise",
        "title": "DARE Location",
        "link": "http://pleiades.stoa.org/places/678439/dare-location"
      }
    }
  ]
}