{
  "type": "FeatureCollection",
  "title": "Tyrus/Col. Septimia Severa",
  "id": "678437",
  "description": "The ancient city of Tyre (modern es-Sur on the coast of Lebanon). A UNESCO World Heritage Site, in part because of its \"important archaeological remains, mainly from Roman times.\"",
  "bbox": [
    35.209358,
    33.268071,
    35.209358,
    33.268071
  ],
  "reprPoint": [
    35.209358,
    33.268071
  ],
  "names": [
    "Tyrus",
    "Col. Septimia Severa",
    "Ṣuru",
    "Ṣūru",
    "Ṭūrā",
    "Ṣūr",
    "Ṭūra",
    "Tyr",
    "Ṣor",
    "Ṣor",
    "Ṣurru",
    "Sur",
    "Tyrus",
    "Tyrus",
    "Colonia Sept. T.",
    "Colonia Septimia T.",
    "Col. Septimia T.",
    "Tyros"
  ],
  "features": [
    {
      "geometry": {
        "type": "Point",
        "coordinates": [
          35.198329,
          33.271624
        ]
      },
      "id": "darmc-location-6402",
      "type": "Feature",
      "properties": {
        "description": "500K scale point location",
        "location_precision": "precise",
        "title": "DARMC location 6402",
        "link": "http://pleiades.stoa.org/places/678437/darmc-location-6402"
      }
    },
    {
      "geometry": {
        "type": "Point",
        "coordinates": [
          35.209358,
          33.268071
        ]
      },
      "id": "dare-location",
      "type": "Feature",
      "properties": {
        "description": "Representative point location, site precision",
        "location_precision": "precise",
        "title": "DARE Location",
        "link": "http://pleiades.stoa.org/places/678437/dare-location"
      }
    }
  ]
}