{
  "type": "FeatureCollection",
  "title": "Umm Rihan",
  "id": "678443",
  "description": "An ancient place, cited: BAtlas 69 B5 Umm Rihan",
  "bbox": [
    35.141828,
    32.483622,
    35.141828,
    32.483622
  ],
  "reprPoint": [
    35.141828,
    32.483622
  ],
  "features": [
    {
      "geometry": {
        "type": "Point",
        "coordinates": [
          35.141828,
          32.483622
        ]
      },
      "id": "darmc-location-312",
      "type": "Feature",
      "properties": {
        "description": "500K scale point location",
        "location_precision": "precise",
        "title": "DARMC location 312",
        "link": "http://pleiades.stoa.org/places/678443/darmc-location-312"
      }
    }
  ]
}