{
  "type": "FeatureCollection",
  "title": "Tell Saidiyeh",
  "id": "678416",
  "description": "An ancient place, cited: BAtlas 69 C5 Tell Saidiyeh",
  "bbox": [
    35.578438,
    32.277741,
    35.578438,
    32.277741
  ],
  "reprPoint": [
    35.578438,
    32.277741
  ],
  "features": [
    {
      "geometry": {
        "type": "Point",
        "coordinates": [
          35.578438,
          32.277741
        ]
      },
      "id": "darmc-location-15057",
      "type": "Feature",
      "properties": {
        "description": "500K scale point location",
        "location_precision": "precise",
        "title": "DARMC location 15057",
        "link": "http://pleiades.stoa.org/places/678416/darmc-location-15057"
      }
    }
  ]
}