{
  "type": "FeatureCollection",
  "title": "Sykamina",
  "id": "678404",
  "bbox": [
    34.9554726,
    32.8246398,
    34.9554726,
    32.8246398
  ],
  "description": "An ancient settlement located near the coast of the modern city of Haifa, Israel.",
  "names": [
    "Sykamina",
    "Tall Abī Ḥuwām",
    "Tall Abī Ḥawām",
    "Porphyreōn",
    "Tall Abū Ḥawām",
    "Tall Abū Hawwām",
    "Caifas",
    "Caifas",
    "Tẹl Šiqmonȧ",
    "Castra Samaritanorum",
    "Calamon",
    "Tall Abū Ḥuwām",
    "Ḥẹfȧ",
    "Ḥẹfa",
    "Ḥēfā",
    "Tall Abū Ḥawwām",
    "Ḥēfā l-ʿAtīqa",
    "Qasṭǝrȧ",
    "Cayphas",
    "Šiqmȧ",
    "Ḥaifā l-ʿAtīqa",
    "Ḫirbat Kafr as-Samīr",
    "Šiqma",
    "Ṣalmonȧ",
    "Salmonȧ",
    "Tall as-Samak",
    "Sykaminon",
    "Sykaminos",
    "Ḥaifā 2",
    "Ḥaifā 1",
    "Ḥaifā 3",
    "Ḥaifā",
    "Ḫaifa",
    "Haifa"
  ],
  "features": [
    {
      "type": "Feature",
      "geometry": {
        "type": "Point",
        "coordinates": [
          34.9554726,
          32.8246398
        ]
      },
      "properties": {
        "description": "representative point"
      }
    },
    {
      "geometry": {
        "type": "Point",
        "coordinates": [
          34.9554726,
          32.8246398
        ]
      },
      "id": "osm-location-of-tel-shikmona",
      "type": "Feature",
      "properties": {
        "description": "Representative location based on OpenStreetMap.",
        "location_precision": "precise",
        "title": "OSM location of Tel Shikmona",
        "link": "http://pleiades.stoa.org/places/678404/osm-location-of-tel-shikmona"
      }
    }
  ]
}