{
  "type": "FeatureCollection",
  "title": "Umm el-Jimal",
  "id": "678439",
  "bbox": [
    36.366603,
    32.324848,
    36.3704669,
    32.3276049
  ],
  "description": "Probably a Nabatean foundation, later much expanded in the Roman, Byzantine, and Early Islamic periods, this well-preserved site is located in the Jordan valley, just south of the Syrian border. Its ancient name is unknown.",
  "names": [
    "Umm el-Jimal"
  ],
  "features": [
    {
      "type": "Feature",
      "geometry": {
        "type": "Point",
        "coordinates": [
          36.3685693,
          32.3261513
        ]
      },
      "properties": {
        "description": "representative point"
      }
    },
    {
      "geometry": {
        "type": "Point",
        "coordinates": [
          36.368638,
          32.326001
        ]
      },
      "id": "darmc-location-10311",
      "type": "Feature",
      "properties": {
        "description": "500K scale point location",
        "location_precision": "precise",
        "title": "DARMC location 10311",
        "link": "http://pleiades.stoa.org/places/678439/darmc-location-10311"
      }
    },
    {
      "geometry": {
        "type": "Point",
        "coordinates": [
          36.366603,
          32.324848
        ]
      },
      "id": "dare-location",
      "type": "Feature",
      "properties": {
        "description": "Representative point location, site precision",
        "location_precision": "precise",
        "title": "DARE Location",
        "link": "http://pleiades.stoa.org/places/678439/dare-location"
      }
    },
    {
      "geometry": {
        "type": "Point",
        "coordinates": [
          36.3704669,
          32.3276049
        ]
      },
      "id": "osm-location-of-um-al-jimal",
      "type": "Feature",
      "properties": {
        "description": "Representative location based on OpenStreetMap.",
        "location_precision": "precise",
        "title": "OSM location of Um Al-Jimal",
        "link": "http://pleiades.stoa.org/places/678439/osm-location-of-um-al-jimal"
      }
    }
  ]
}