{
  "type": "FeatureCollection",
  "title": "Tyrus/Col. Septimia Severa",
  "id": "678437",
  "bbox": [
    35.198329,
    33.268071,
    35.209358,
    33.271624
  ],
  "description": "The ancient city of Tyre (modern es-Sur on the coast of Lebanon). A UNESCO World Heritage Site, in part because of its \"important archaeological remains, mainly from Roman times.\"",
  "names": [
    "Tyrus",
    "Col. Septimia Severa",
    "Ṣuru",
    "Ṣūru",
    "Ṭūrā",
    "Ṣūr",
    "Ṭūra",
    "Tyr",
    "Ṣor",
    "Ṣor",
    "Ṣurru",
    "Sur",
    "Tyrus",
    "Tyrus",
    "Colonia Sept. T.",
    "Colonia Septimia T.",
    "Col. Septimia T.",
    "Tyros"
  ],
  "features": [
    {
      "type": "Feature",
      "geometry": {
        "type": "Point",
        "coordinates": [
          35.2038435,
          33.2698475
        ]
      },
      "properties": {
        "description": "representative point"
      }
    },
    {
      "geometry": {
        "type": "Point",
        "coordinates": [
          35.198329,
          33.271624
        ]
      },
      "id": "darmc-location-6402",
      "type": "Feature",
      "properties": {
        "description": "1:500,000 scale representative point location digitized from the Barrington Atlas of the Greek and Roman World by the Digital Atlas of Roman and Medieval Civilizations project at Harvard University.",
        "location_precision": "precise",
        "title": "DARMC location 6402",
        "link": "http://pleiades.stoa.org/places/678437/darmc-location-6402"
      }
    },
    {
      "geometry": {
        "type": "Point",
        "coordinates": [
          35.209358,
          33.268071
        ]
      },
      "id": "dare-location",
      "type": "Feature",
      "properties": {
        "description": "Representative point location, site precision",
        "location_precision": "precise",
        "title": "DARE Location",
        "link": "http://pleiades.stoa.org/places/678437/dare-location"
      }
    }
  ]
}