{
  "type": "FeatureCollection",
  "title": "Sykamina",
  "id": "678404",
  "description": "An ancient place, cited: BAtlas 69 A4 Sykamina",
  "bbox": [
    34.963823,
    32.817493,
    34.963823,
    32.817493
  ],
  "reprPoint": [
    34.963823,
    32.817493
  ],
  "names": [
    "Tall Abī Ḥuwām",
    "Tall Abī Ḥawām",
    "Porphyreōn",
    "Sykamina",
    "Tall Abū Ḥawām",
    "Tall Abū Hawwām",
    "Caifas",
    "Caifas",
    "Tẹl Šiqmonȧ",
    "Castra Samaritanorum",
    "Calamon",
    "Tall Abū Ḥuwām",
    "Ḥẹfȧ",
    "Ḥẹfa",
    "Ḥēfā",
    "Tall Abū Ḥawwām",
    "Ḥēfā l-ʿAtīqa",
    "Qasṭǝrȧ",
    "Cayphas",
    "Šiqmȧ",
    "Ḥaifā l-ʿAtīqa",
    "Ḫirbat Kafr as-Samīr",
    "Šiqma",
    "Ḥaifā",
    "Ḫaifa",
    "Haifa",
    "Ṣalmonȧ",
    "Salmonȧ",
    "Tall as-Samak",
    "Sykaminon",
    "Sykaminos",
    "Ḥaifā 2",
    "Ḥaifā 1",
    "Ḥaifā 3"
  ],
  "features": [
    {
      "geometry": {
        "type": "Point",
        "coordinates": [
          34.963823,
          32.817493
        ]
      },
      "id": "darmc-location-9895",
      "type": "Feature",
      "properties": {
        "description": "500K scale point location",
        "location_precision": "precise",
        "title": "DARMC location 9895",
        "link": "http://pleiades.stoa.org/places/678404/darmc-location-9895"
      }
    }
  ]
}