{
  "type": "FeatureCollection",
  "title": "Untitled",
  "id": "679506",
  "description": "An ancient place, cited: BAtlas 69 B3 unnamed bridge (Nahr Abu-Assad, S ‘Ad Nonum’)",
  "bbox": [
    35.262168,
    33.372732,
    35.262168,
    33.372732
  ],
  "connectsWith": [
    "a629bbf8140d0801db33fd80f56fead3"
  ],
  "reprPoint": [
    35.262168,
    33.372732
  ],
  "features": [
    {
      "geometry": {
        "type": "Point",
        "coordinates": [
          35.262168,
          33.372732
        ]
      },
      "id": "darmc-location-14779",
      "type": "Feature",
      "properties": {
        "description": "500K scale point location",
        "location_precision": "precise",
        "title": "DARMC location 14779",
        "link": "http://pleiades.stoa.org/places/679506/darmc-location-14779"
      }
    }
  ]
}