{
  "type": "FeatureCollection",
  "title": "Untitled",
  "id": "679506",
  "bbox": [
    35.262168,
    33.372732,
    35.262168,
    33.372732
  ],
  "description": "A Roman bridge located in what is now Lebanon that crosses the Litani River (Leontes). The bridge is located in the vicinity of Nahr Abou Assouad, approximately 10 km north of Tyre.",
  "connectsWith": [
    "678268"
  ],
  "features": [
    {
      "type": "Feature",
      "geometry": {
        "type": "Point",
        "coordinates": [
          35.262168,
          33.372732
        ]
      },
      "properties": {
        "description": "representative point"
      }
    },
    {
      "geometry": {
        "type": "Point",
        "coordinates": [
          35.262168,
          33.372732
        ]
      },
      "id": "darmc-location-14779",
      "type": "Feature",
      "properties": {
        "description": "500K scale point location",
        "location_precision": "precise",
        "title": "DARMC location 14779",
        "link": "http://pleiades.stoa.org/places/679506/darmc-location-14779"
      }
    }
  ]
}