{
  "type": "FeatureCollection",
  "title": "Untitled",
  "id": "679506",
  "bbox": [
    35.2507838,
    33.339524,
    35.2507838,
    33.339524
  ],
  "description": "A Roman bridge located in what is now Lebanon that crosses the Litani River (Leontes). The bridge is located in the vicinity of Nahr Abou Assouad, approximately 10 km north of Tyre.",
  "connectsWith": [
    "678268"
  ],
  "features": [
    {
      "type": "Feature",
      "geometry": {
        "type": "Point",
        "coordinates": [
          35.2507838,
          33.339524
        ]
      },
      "properties": {
        "description": "representative point"
      }
    },
    {
      "geometry": {
        "type": "Point",
        "coordinates": [
          35.2507838,
          33.339524
        ]
      },
      "id": "osm-location",
      "type": "Feature",
      "properties": {
        "description": "Representative location based on OpenStreetMap",
        "location_precision": "precise",
        "title": "OSM location of Leontes Bridge",
        "link": "http://pleiades.stoa.org/places/679506/osm-location"
      }
    }
  ]
}