{
  "type": "FeatureCollection",
  "title": "Assyrian rock relief at Yağmur",
  "id": "680335179",
  "bbox": [
    40.4965813,
    37.4123007,
    40.4965813,
    37.4123007
  ],
  "description": "Inscribed relief, dated to the reign of Tiglath-Pileser I, on a large block near the fortified site of Yağmur in the Tur 'Abdin.",
  "connectsWith": [
    "562639517"
  ],
  "features": [
    {
      "type": "Feature",
      "geometry": {
        "type": "Point",
        "coordinates": [
          40.4965813,
          37.4123007
        ]
      },
      "properties": {
        "description": "representative point"
      }
    },
    {
      "geometry": {
        "type": "Point",
        "coordinates": [
          40.4965813,
          37.4123007
        ]
      },
      "id": "assyrian-rock-relief",
      "type": "Feature",
      "properties": {
        "description": "Point representing the Assyrian rock relief at Yağmur, derived from an OpenStreetMap node after Genç 2023",
        "location_precision": "precise",
        "title": "Assyrian rock relief at Yağmur ",
        "link": "http://pleiades.stoa.org/places/680335179/assyrian-rock-relief"
      }
    }
  ]
}