{
  "type": "FeatureCollection",
  "title": "Adollam",
  "id": "687809",
  "bbox": [
    34.999242,
    31.657354,
    34.999242,
    31.657354
  ],
  "description": "An ancient place, cited: BAtlas 70 G2 Adollam",
  "names": [
    "Adollam"
  ],
  "features": [
    {
      "type": "Feature",
      "geometry": {
        "type": "Point",
        "coordinates": [
          34.999242,
          31.657354
        ]
      },
      "properties": {
        "description": "representative point"
      }
    },
    {
      "geometry": {
        "type": "Point",
        "coordinates": [
          34.999242,
          31.657354
        ]
      },
      "id": "darmc-location-6053",
      "type": "Feature",
      "properties": {
        "description": "500K scale point location",
        "location_precision": "precise",
        "title": "DARMC location 6053",
        "link": "http://pleiades.stoa.org/places/687809/darmc-location-6053"
      }
    }
  ]
}