{
  "type": "FeatureCollection",
  "title": "Betomolachon?",
  "id": "687860",
  "bbox": [
    34.56518,
    31.02993,
    34.56518,
    31.02993
  ],
  "description": "An ancient place, cited: BAtlas 70 F3 Betomolachon?",
  "names": [
    "Betomolachon"
  ],
  "features": [
    {
      "type": "Feature",
      "geometry": {
        "type": "Point",
        "coordinates": [
          34.56518,
          31.02993
        ]
      },
      "properties": {
        "description": "representative point"
      }
    },
    {
      "geometry": {
        "type": "Point",
        "coordinates": [
          34.56518,
          31.02993
        ]
      },
      "id": "geonames-location",
      "type": "Feature",
      "properties": {
        "description": "Representative point location, derived from GeoNames and verified in Google Earth 2016. Dates after BAtlas.",
        "location_precision": "precise",
        "title": "GeoNames Location",
        "link": "http://pleiades.stoa.org/places/687860/geonames-location"
      }
    }
  ]
}