{
  "type": "FeatureCollection",
  "title": "Beer Sheva/Berosaba",
  "id": "687846",
  "description": "An ancient place, cited: BAtlas 70 F3 Beer Sheva/Berosaba",
  "bbox": [
    34.790451,
    31.24509,
    34.840792,
    31.250369
  ],
  "reprPoint": [
    34.8156215,
    31.2477295
  ],
  "names": [
    "Beer Sheva",
    "Berosaba",
    "Bersabe"
  ],
  "features": [
    {
      "geometry": {
        "type": "Point",
        "coordinates": [
          34.790451,
          31.250369
        ]
      },
      "id": "darmc-location-6344",
      "type": "Feature",
      "properties": {
        "description": "500K scale point location",
        "location_precision": "precise",
        "title": "DARMC location 6344",
        "link": "http://pleiades.stoa.org/places/687846/darmc-location-6344"
      }
    },
    {
      "geometry": {
        "type": "Point",
        "coordinates": [
          34.840792,
          31.24509
        ]
      },
      "id": "dare-location",
      "type": "Feature",
      "properties": {
        "description": "Representative point location, site precision",
        "location_precision": "precise",
        "title": "DARE Location",
        "link": "http://pleiades.stoa.org/places/687846/dare-location"
      }
    }
  ]
}