{
  "type": "FeatureCollection",
  "title": "Beer Sheva/Berosaba",
  "id": "687846",
  "bbox": [
    34.840792,
    31.24509,
    34.840792,
    31.24509
  ],
  "description": "Tel Be'er Sheva is an archeological site in southern Israel that is believed to be the location of the remains of the biblical town of Beersheba.",
  "names": [
    "Beer Sheva",
    "Berosaba",
    "Bersabe",
    "Be'er Sheva"
  ],
  "features": [
    {
      "type": "Feature",
      "geometry": {
        "type": "Point",
        "coordinates": [
          34.840792,
          31.24509
        ]
      },
      "properties": {
        "description": "representative point"
      }
    },
    {
      "geometry": {
        "type": "Point",
        "coordinates": [
          34.840792,
          31.24509
        ]
      },
      "id": "dare-location",
      "type": "Feature",
      "properties": {
        "description": "Representative point location, site precision",
        "location_precision": "precise",
        "title": "DARE Location",
        "link": "http://pleiades.stoa.org/places/687846/dare-location"
      }
    }
  ]
}