{
  "type": "FeatureCollection",
  "title": "Betomolachon?",
  "id": "687860",
  "description": "An ancient place, cited: BAtlas 70 F3 Betomolachon?",
  "bbox": [
    34.560022,
    31.037479,
    34.560022,
    31.037479
  ],
  "reprPoint": [
    34.560022,
    31.037479
  ],
  "names": [
    "Betomolachon"
  ],
  "features": [
    {
      "geometry": {
        "type": "Point",
        "coordinates": [
          34.560022,
          31.037479
        ]
      },
      "id": "darmc-location-6365",
      "type": "Feature",
      "properties": {
        "description": "500K scale point location",
        "location_precision": "precise",
        "title": "DARMC location 6365",
        "link": "http://pleiades.stoa.org/places/687860/darmc-location-6365"
      }
    }
  ]
}