{
  "type": "FeatureCollection",
  "title": "Aro'er",
  "id": "687834",
  "description": "An ancient place, cited: BAtlas 70 F3 Aro'er",
  "bbox": [
    34.971244,
    31.161995,
    34.971244,
    31.161995
  ],
  "reprPoint": [
    34.971244,
    31.161995
  ],
  "features": [
    {
      "geometry": {
        "type": "Point",
        "coordinates": [
          34.971244,
          31.161995
        ]
      },
      "id": "darmc-location-6242",
      "type": "Feature",
      "properties": {
        "description": "500K scale point location",
        "location_precision": "precise",
        "title": "DARMC location 6242",
        "link": "http://pleiades.stoa.org/places/687834/darmc-location-6242"
      }
    }
  ]
}