{
  "type": "FeatureCollection",
  "title": "En Boqeq",
  "id": "687892",
  "description": "An ancient place, cited: BAtlas 70 G3 En Boqeq",
  "bbox": [
    35.348111,
    31.2011134,
    35.3588715,
    31.212093
  ],
  "reprPoint": [
    35.35349125,
    31.2066032
  ],
  "features": [
    {
      "geometry": {
        "type": "Point",
        "coordinates": [
          35.348111,
          31.212093
        ]
      },
      "id": "darmc-location-696",
      "type": "Feature",
      "properties": {
        "description": "500K scale point location",
        "location_precision": "precise",
        "title": "DARMC location 696",
        "link": "http://pleiades.stoa.org/places/687892/darmc-location-696"
      }
    }
  ]
}