{
  "type": "FeatureCollection",
  "title": "Caphar Zacharia?",
  "id": "687871",
  "bbox": [
    34.856438,
    31.676232,
    34.943987,
    31.708594
  ],
  "description": "An ancient place, cited: BAtlas 70 F2 Caphar Zacharia?",
  "names": [
    "Caphar Zacharia"
  ],
  "features": [
    {
      "type": "Feature",
      "geometry": {
        "type": "Point",
        "coordinates": [
          34.9002125,
          31.692413
        ]
      },
      "properties": {
        "description": "representative point"
      }
    },
    {
      "geometry": {
        "type": "Point",
        "coordinates": [
          34.856438,
          31.676232
        ]
      },
      "id": "darmc-location-5631",
      "type": "Feature",
      "properties": {
        "description": "500K scale point location",
        "location_precision": "precise",
        "title": "DARMC location 5631",
        "link": "http://pleiades.stoa.org/places/687871/darmc-location-5631"
      }
    },
    {
      "geometry": {
        "type": "Point",
        "coordinates": [
          34.943987,
          31.708594
        ]
      },
      "id": "dare-location",
      "type": "Feature",
      "properties": {
        "description": "Representative point location, village precision",
        "location_precision": "precise",
        "title": "DARE Location",
        "link": "http://pleiades.stoa.org/places/687871/dare-location"
      }
    }
  ]
}