{
  "type": "FeatureCollection",
  "title": "Kapparetaia",
  "id": "687938",
  "description": "An ancient place, cited: BAtlas 70 F1 Kapparetaia",
  "bbox": [
    34.955684,
    32.121572,
    34.962854,
    32.123798
  ],
  "reprPoint": [
    34.959269,
    32.122685
  ],
  "names": [
    "Kapparetaia"
  ],
  "features": [
    {
      "geometry": {
        "type": "Point",
        "coordinates": [
          34.955684,
          32.123798
        ]
      },
      "id": "darmc-location-1652",
      "type": "Feature",
      "properties": {
        "description": "500K scale point location",
        "location_precision": "precise",
        "title": "DARMC location 1652",
        "link": "http://pleiades.stoa.org/places/687938/darmc-location-1652"
      }
    },
    {
      "geometry": {
        "type": "Point",
        "coordinates": [
          34.962854,
          32.121572
        ]
      },
      "id": "darmc-location-4036",
      "type": "Feature",
      "properties": {
        "description": "500K scale point location",
        "location_precision": "precise",
        "title": "DARMC location 4036",
        "link": "http://pleiades.stoa.org/places/687938/darmc-location-4036"
      }
    }
  ]
}