{
  "type": "FeatureCollection",
  "title": "Hadid/Ad(d)ida",
  "id": "687913",
  "description": "An ancient place, cited: BAtlas 70 F2 Hadid/Ad(d)ida",
  "bbox": [
    34.950537,
    31.967821,
    34.950537,
    31.967821
  ],
  "reprPoint": [
    34.950537,
    31.967821
  ],
  "names": [
    "Hadid",
    "Addida",
    "Adida",
    "Aditha"
  ],
  "features": [
    {
      "geometry": {
        "type": "Point",
        "coordinates": [
          34.950537,
          31.967821
        ]
      },
      "id": "darmc-location-6389",
      "type": "Feature",
      "properties": {
        "description": "500K scale point location",
        "location_precision": "precise",
        "title": "DARMC location 6389",
        "link": "http://pleiades.stoa.org/places/687913/darmc-location-6389"
      }
    }
  ]
}