{
  "type": "FeatureCollection",
  "title": "Lobana?",
  "id": "687952",
  "bbox": [
    34.869563,
    31.647111,
    34.869563,
    31.647111
  ],
  "description": "An ancient place, cited: BAtlas 70 F2 Lobana?",
  "names": [
    "Lobana"
  ],
  "features": [
    {
      "type": "Feature",
      "geometry": {
        "type": "Point",
        "coordinates": [
          34.869563,
          31.647111
        ]
      },
      "properties": {
        "description": "representative point"
      }
    },
    {
      "geometry": {
        "type": "Point",
        "coordinates": [
          34.869563,
          31.647111
        ]
      },
      "id": "darmc-location-6698",
      "type": "Feature",
      "properties": {
        "description": "500K scale point location",
        "location_precision": "precise",
        "title": "DARMC location 6698",
        "link": "http://pleiades.stoa.org/places/687952/darmc-location-6698"
      }
    }
  ]
}