{
  "type": "FeatureCollection",
  "title": "Horvat Ma'agurah",
  "id": "687919",
  "description": "An ancient place, cited: BAtlas 70 F4 Horvat Ma'agurah",
  "bbox": [
    34.731491,
    30.870112,
    34.731491,
    30.870112
  ],
  "reprPoint": [
    34.731491,
    30.870112
  ],
  "features": [
    {
      "geometry": {
        "type": "Point",
        "coordinates": [
          34.731491,
          30.870112
        ]
      },
      "id": "darmc-location-18606",
      "type": "Feature",
      "properties": {
        "description": "500K scale point location",
        "location_precision": "precise",
        "title": "DARMC location 18606",
        "link": "http://pleiades.stoa.org/places/687919/darmc-location-18606"
      }
    }
  ]
}