{
  "type": "FeatureCollection",
  "title": "Iethira",
  "id": "687929",
  "description": "An ancient place, cited: BAtlas 70 G3 Iethira",
  "bbox": [
    35.015599,
    31.350745,
    35.015599,
    31.350745
  ],
  "reprPoint": [
    35.015599,
    31.350745
  ],
  "names": [
    "Iethira"
  ],
  "features": [
    {
      "geometry": {
        "type": "Point",
        "coordinates": [
          35.015599,
          31.350745
        ]
      },
      "id": "darmc-location-18046",
      "type": "Feature",
      "properties": {
        "description": "500K scale point location",
        "location_precision": "precise",
        "title": "DARMC location 18046",
        "link": "http://pleiades.stoa.org/places/687929/darmc-location-18046"
      }
    }
  ]
}