{
  "type": "FeatureCollection",
  "title": "Qasrawet",
  "id": "688010",
  "description": "An ancient place, cited: BAtlas 70 B4 Qasrawet",
  "bbox": [
    32.81154,
    30.916609,
    32.81154,
    30.916609
  ],
  "reprPoint": [
    32.81154,
    30.916609
  ],
  "features": [
    {
      "geometry": {
        "type": "Point",
        "coordinates": [
          32.81154,
          30.916609
        ]
      },
      "id": "darmc-location-5303",
      "type": "Feature",
      "properties": {
        "description": "500K scale point location",
        "location_precision": "precise",
        "title": "DARMC location 5303",
        "link": "http://pleiades.stoa.org/places/688010/darmc-location-5303"
      }
    }
  ]
}