{
  "type": "FeatureCollection",
  "title": "Rujm Abu Muheir",
  "id": "688018",
  "bbox": [
    35.39862,
    32.045988,
    35.414902,
    32.051018
  ],
  "description": "An ancient place, cited: BAtlas 70 G1 Rujm Abu Muheir",
  "features": [
    {
      "type": "Feature",
      "geometry": {
        "type": "Point",
        "coordinates": [
          35.406761,
          32.048503
        ]
      },
      "properties": {
        "description": "representative point"
      }
    },
    {
      "geometry": {
        "type": "Point",
        "coordinates": [
          35.414902,
          32.051018
        ]
      },
      "id": "darmc-location-19196",
      "type": "Feature",
      "properties": {
        "description": "500K scale point location",
        "location_precision": "precise",
        "title": "DARMC location 19196",
        "link": "http://pleiades.stoa.org/places/688018/darmc-location-19196"
      }
    },
    {
      "geometry": {
        "type": "Point",
        "coordinates": [
          35.39862,
          32.045988
        ]
      },
      "id": "darmc-location-18252",
      "type": "Feature",
      "properties": {
        "description": "500K scale point location",
        "location_precision": "precise",
        "title": "DARMC location 18252",
        "link": "http://pleiades.stoa.org/places/688018/darmc-location-18252"
      }
    }
  ]
}