{
  "type": "FeatureCollection",
  "title": "Ziph",
  "id": "688047",
  "description": "An ancient place, cited: BAtlas 70 G3 Ziph",
  "bbox": [
    35.140514,
    31.478252,
    35.140514,
    31.478252
  ],
  "reprPoint": [
    35.140514,
    31.478252
  ],
  "names": [
    "Ziph"
  ],
  "features": [
    {
      "geometry": {
        "type": "Point",
        "coordinates": [
          35.140514,
          31.478252
        ]
      },
      "id": "darmc-location-19026",
      "type": "Feature",
      "properties": {
        "description": "500K scale point location",
        "location_precision": "precise",
        "title": "DARMC location 19026",
        "link": "http://pleiades.stoa.org/places/688047/darmc-location-19026"
      }
    }
  ]
}