{
  "type": "FeatureCollection",
  "title": "Bindon Hill",
  "id": "689737512",
  "bbox": [
    -2.23461,
    50.62217,
    -2.23461,
    50.62217
  ],
  "description": "Bindon Hill is the site of extensive Iron Age earthworks on a coastal hill area in Dorset, England.",
  "features": [
    {
      "type": "Feature",
      "geometry": {
        "type": "Point",
        "coordinates": [
          -2.23461,
          50.62217
        ]
      },
      "properties": {
        "description": "representative point"
      }
    },
    {
      "geometry": {
        "type": "Point",
        "coordinates": [
          -2.23461,
          50.62217
        ]
      },
      "id": "location-of-bindon-hill",
      "type": "Feature",
      "properties": {
        "description": "Representative location based on GeoHack.",
        "location_precision": "precise",
        "title": "GeoHack location of Bindon Hill",
        "link": "http://pleiades.stoa.org/places/689737512/location-of-bindon-hill"
      }
    }
  ]
}