{
  "type": "FeatureCollection",
  "title": "Hippades Gate",
  "id": "690970100",
  "bbox": [
    23.7207,
    37.9792,
    23.7207,
    37.9792
  ],
  "description": "A gate in the Themistoklean Wall of Athens, whose name means \"Equestrian Gate.\" It has been identified with archaeological remains (not visible) at Leokoriou and Dipylou Streets.",
  "connectsWith": [
    "579885",
    "830927276"
  ],
  "names": [
    "Eriai Gate",
    "Hippádes púlai",
    "Gate V",
    "Gate at Leokoriou and Dipylou Sts."
  ],
  "features": [
    {
      "type": "Feature",
      "geometry": {
        "type": "Point",
        "coordinates": [
          23.7207,
          37.9792
        ]
      },
      "properties": {
        "description": "representative point"
      }
    },
    {
      "geometry": {
        "type": "Point",
        "coordinates": [
          23.7207,
          37.9792
        ]
      },
      "id": "topostext-location-gate-v-eriai-athens",
      "type": "Feature",
      "properties": {
        "description": null,
        "location_precision": "precise",
        "title": "ToposText Location: Gate V/Eriai (Athens)",
        "link": "http://pleiades.stoa.org/places/690970100/topostext-location-gate-v-eriai-athens"
      }
    }
  ]
}