{
  "type": "FeatureCollection",
  "title": "Catacombs of Trypiti",
  "id": "694364581",
  "bbox": [
    24.4237704,
    36.7373656,
    24.4237704,
    36.7373656
  ],
  "description": "The rock-cut Catacombs of Milos date from the first to fifth centuries.",
  "connectsWith": [
    "570474"
  ],
  "features": [
    {
      "type": "Feature",
      "geometry": {
        "type": "Point",
        "coordinates": [
          24.4237704,
          36.7373656
        ]
      },
      "properties": {
        "description": "representative point"
      }
    },
    {
      "geometry": {
        "type": "Point",
        "coordinates": [
          24.4237704,
          36.7373656
        ]
      },
      "id": "osm-location-of-catacombs-of-trypiti",
      "type": "Feature",
      "properties": {
        "description": "Location based on OpenStreetMap",
        "location_precision": "precise",
        "title": "OSM location of catacombs of Trypiti",
        "link": "http://pleiades.stoa.org/places/694364581/osm-location-of-catacombs-of-trypiti"
      }
    }
  ]
}