{
  "type": "FeatureCollection",
  "title": "La Chapelle-des-Fougeretz",
  "id": "69486",
  "description": "An ancient place, cited: BAtlas 7 E3 La Chapelle-des-Fougeretz",
  "bbox": [
    -1.733453,
    48.177135,
    -1.733453,
    48.177135
  ],
  "reprPoint": [
    -1.733453,
    48.177135
  ],
  "features": [
    {
      "geometry": {
        "type": "Point",
        "coordinates": [
          -1.733453,
          48.177135
        ]
      },
      "id": "darmc-location-23363",
      "type": "Feature",
      "properties": {
        "description": "1M scale point location",
        "location_precision": "precise",
        "title": "DARMC location 23363",
        "link": "http://pleiades.stoa.org/places/69486/darmc-location-23363"
      }
    }
  ]
}