{
  "type": "FeatureCollection",
  "title": "Combourg",
  "id": "69490",
  "description": "An ancient place, cited: BAtlas 7 E3 Combourg",
  "bbox": [
    -1.748985,
    48.409987,
    -1.748985,
    48.409987
  ],
  "reprPoint": [
    -1.748985,
    48.409987
  ],
  "features": [
    {
      "geometry": {
        "type": "Point",
        "coordinates": [
          -1.748985,
          48.409987
        ]
      },
      "id": "darmc-location-12069",
      "type": "Feature",
      "properties": {
        "description": "1M scale point location",
        "location_precision": "precise",
        "title": "DARMC location 12069",
        "link": "http://pleiades.stoa.org/places/69490/darmc-location-12069"
      }
    }
  ]
}