{
  "type": "FeatureCollection",
  "title": "Fanum Martis/Civitas Coriosolitum",
  "id": "69507",
  "description": "Fanum Martis/Civitas Coriosolitum (modern Corseul) was a major Gallo-Roman settlement, closely associated with the extra-urban sanctuary of Mars at Haut Bécherel. Fanum Martis/Civitas Coriosolitum was the chief town of the Coriosolites and was likely founded ca. 10 BC.",
  "bbox": [
    -2.166458,
    48.481442,
    -2.166458,
    48.481442
  ],
  "reprPoint": [
    -2.166458,
    48.481442
  ],
  "names": [
    "Corseul",
    "Fanum Martis",
    "Civitas Coriosolitum",
    "Coriosolitae"
  ],
  "features": [
    {
      "geometry": {
        "type": "Point",
        "coordinates": [
          -2.169599,
          48.48106
        ]
      },
      "id": "darmc-location-3464",
      "type": "Feature",
      "properties": {
        "description": "1M scale point location",
        "location_precision": "precise",
        "title": "DARMC location 3464",
        "link": "http://pleiades.stoa.org/places/69507/darmc-location-3464"
      }
    },
    {
      "geometry": {
        "type": "Point",
        "coordinates": [
          -2.166458,
          48.481442
        ]
      },
      "id": "dare-location",
      "type": "Feature",
      "properties": {
        "description": "Representative point location, site precision",
        "location_precision": "precise",
        "title": "DARE Location",
        "link": "http://pleiades.stoa.org/places/69507/dare-location"
      }
    },
    {
      "geometry": {
        "type": "Point",
        "coordinates": [
          -2.1658756,
          48.4811028
        ]
      },
      "id": "location-of-archaeological-site-of-monterfil",
      "type": "Feature",
      "properties": {
        "description": "Remains of the commercial quarter of the Gallo-Roman settlement. Location based on OpenStreetMap.",
        "location_precision": "precise",
        "title": "location of archaeological site of Monterfil II",
        "link": "http://pleiades.stoa.org/places/69507/location-of-archaeological-site-of-monterfil"
      }
    }
  ]
}