{
  "type": "FeatureCollection",
  "title": "Fanum Martis/Civitas Coriosolitum",
  "id": "69507",
  "bbox": [
    -2.169599,
    48.48106,
    -2.166458,
    48.481442
  ],
  "description": "Fanum Martis/Civitas Coriosolitum (modern Corseul) was a major Gallo-Roman settlement, closely associated with the extra-urban sanctuary of Mars at Haut Bécherel. Fanum Martis/Civitas Coriosolitum was the chief town of the Coriosolites and was likely founded ca. 10 BC.",
  "connectsWith": [
    "70976",
    "70975"
  ],
  "names": [
    "Fanum Martis",
    "Civitas Coriosolitum",
    "Coriosolitae",
    "Corseul"
  ],
  "features": [
    {
      "type": "Feature",
      "geometry": {
        "type": "Point",
        "coordinates": [
          -2.1680285,
          48.481251
        ]
      },
      "properties": {
        "description": "representative point"
      }
    },
    {
      "geometry": {
        "type": "Point",
        "coordinates": [
          -2.169599,
          48.48106
        ]
      },
      "id": "darmc-location-3464",
      "type": "Feature",
      "properties": {
        "description": "1:1 million scale representative point location digitized from the Barrington Atlas of the Greek and Roman World by the Digital Atlas of Roman and Medieval Civilizations project at Harvard University.",
        "location_precision": "precise",
        "title": "DARMC location 3464",
        "link": "http://pleiades.stoa.org/places/69507/darmc-location-3464"
      }
    },
    {
      "geometry": {
        "type": "Point",
        "coordinates": [
          -2.166458,
          48.481442
        ]
      },
      "id": "dare-location",
      "type": "Feature",
      "properties": {
        "description": "Representative point location, site precision",
        "location_precision": "precise",
        "title": "DARE Location",
        "link": "http://pleiades.stoa.org/places/69507/dare-location"
      }
    }
  ]
}