{
  "type": "FeatureCollection",
  "title": "Moulay",
  "id": "69535",
  "description": "An ancient place, cited: BAtlas 7 F3 Moulay",
  "bbox": [
    -0.62899,
    48.270232,
    -0.621725050021,
    48.2754212733
  ],
  "reprPoint": [
    -0.625357525011,
    48.2728266366
  ],
  "features": [
    {
      "geometry": {
        "type": "Point",
        "coordinates": [
          -0.62899,
          48.270232
        ]
      },
      "id": "darmc-location-13816",
      "type": "Feature",
      "properties": {
        "description": "1M scale point location",
        "location_precision": "precise",
        "title": "DARMC location 13816",
        "link": "http://pleiades.stoa.org/places/69535/darmc-location-13816"
      }
    },
    {
      "geometry": {
        "type": "Point",
        "coordinates": [
          -0.621725050021,
          48.2754212733
        ]
      },
      "id": "dare-location",
      "type": "Feature",
      "properties": {
        "description": "Representative point location, site precision",
        "location_precision": "precise",
        "title": "DARE Location",
        "link": "http://pleiades.stoa.org/places/69535/dare-location"
      }
    }
  ]
}