{
  "type": "FeatureCollection",
  "title": "The Nunnery",
  "id": "69542",
  "bbox": [
    -2.176667,
    49.719167,
    -2.17608,
    49.72099
  ],
  "description": "A Roman fort on the island of Alderney in the English Channel. Its ancient name is unknown.",
  "connectsWith": [
    "69557"
  ],
  "features": [
    {
      "type": "Feature",
      "geometry": {
        "type": "Point",
        "coordinates": [
          -2.1763735,
          49.7200785
        ]
      },
      "properties": {
        "description": "representative point"
      }
    },
    {
      "geometry": {
        "type": "Point",
        "coordinates": [
          -2.17608,
          49.72099
        ]
      },
      "id": "darmc-location-8361",
      "type": "Feature",
      "properties": {
        "description": "1M scale point location",
        "location_precision": "precise",
        "title": "DARMC location 8361",
        "link": "http://pleiades.stoa.org/places/69542/darmc-location-8361"
      }
    },
    {
      "geometry": {
        "type": "Point",
        "coordinates": [
          -2.176667,
          49.719167
        ]
      },
      "id": "geohack-location-of-the-nunnery",
      "type": "Feature",
      "properties": {
        "description": "Coordinates following GeoHack",
        "location_precision": "precise",
        "title": "Geohack location of The Nunnery",
        "link": "http://pleiades.stoa.org/places/69542/geohack-location-of-the-nunnery"
      }
    }
  ]
}