{
  "type": "FeatureCollection",
  "title": "Caelius Mons",
  "id": "695491849",
  "bbox": [
    12.486137,
    41.884,
    12.5086818,
    41.891775
  ],
  "description": "The Caelian Hill in Rome.",
  "connectsWith": [
    "423025"
  ],
  "names": [
    "Caelius Mons",
    "Caelian Hill",
    "to Kailion oros",
    "Monte Celio"
  ],
  "features": [
    {
      "type": "Feature",
      "geometry": {
        "type": "Point",
        "coordinates": [
          12.4947085804,
          41.8866169907
        ]
      },
      "properties": {
        "description": "representative point"
      }
    }
  ]
}