{
  "type": "FeatureCollection",
  "title": "Caelius Mons",
  "id": "695491849",
  "bbox": [
    12.4906341,
    41.884,
    12.5089415,
    41.8883327
  ],
  "description": "The Caelian Hill in Rome.",
  "connectsWith": [
    "423025"
  ],
  "names": [
    "Caelius Mons",
    "Caelian Hill",
    "to Kailion oros",
    "Monte Celio"
  ],
  "features": [
    {
      "type": "Feature",
      "geometry": {
        "type": "Point",
        "coordinates": [
          12.5026933599,
          41.8851911411
        ]
      },
      "properties": {
        "description": "representative point"
      }
    }
  ]
}