{
  "type": "FeatureCollection",
  "title": "The Nunnery",
  "id": "69542",
  "description": "An ancient place, cited: BAtlas 7 D2 The Nunnery",
  "bbox": [
    -2.17608,
    49.72099,
    -2.17608,
    49.72099
  ],
  "reprPoint": [
    -2.17608,
    49.72099
  ],
  "features": [
    {
      "geometry": {
        "type": "Point",
        "coordinates": [
          -2.17608,
          49.72099
        ]
      },
      "id": "darmc-location-8361",
      "type": "Feature",
      "properties": {
        "description": "1M scale point location",
        "location_precision": "precise",
        "title": "DARMC location 8361",
        "link": "http://pleiades.stoa.org/places/69542/darmc-location-8361"
      }
    }
  ]
}