{
  "type": "FeatureCollection",
  "title": "Oisseau-Le-Petit",
  "id": "69544",
  "description": "An ancient place, cited: BAtlas 7 G3 Oisseau-Le-Petit",
  "bbox": [
    0.075101,
    48.346449,
    0.086174,
    48.348321
  ],
  "reprPoint": [
    0.0806375,
    48.347385
  ],
  "features": [
    {
      "geometry": {
        "type": "Point",
        "coordinates": [
          0.075101,
          48.346449
        ]
      },
      "id": "dare-location",
      "type": "Feature",
      "properties": {
        "description": "Representative point location, site precision",
        "location_precision": "precise",
        "title": "DARE Location",
        "link": "http://pleiades.stoa.org/places/69544/dare-location"
      }
    },
    {
      "geometry": {
        "type": "Point",
        "coordinates": [
          0.086174,
          48.348321
        ]
      },
      "id": "darmc-location-26122",
      "type": "Feature",
      "properties": {
        "description": "1M scale point location",
        "location_precision": "precise",
        "title": "DARMC location 26122",
        "link": "http://pleiades.stoa.org/places/69544/darmc-location-26122"
      }
    }
  ]
}