{
  "type": "FeatureCollection",
  "title": "Oisseau-Le-Petit",
  "id": "69544",
  "bbox": [
    0.075101,
    48.346449,
    0.075101,
    48.346449
  ],
  "description": "Oisseau-Le-Petit is the site of a Gallo-Roman fanum.",
  "features": [
    {
      "type": "Feature",
      "geometry": {
        "type": "Point",
        "coordinates": [
          0.075101,
          48.346449
        ]
      },
      "properties": {
        "description": "representative point"
      }
    },
    {
      "geometry": {
        "type": "Point",
        "coordinates": [
          0.075101,
          48.346449
        ]
      },
      "id": "dare-location",
      "type": "Feature",
      "properties": {
        "description": "Representative point location, site precision",
        "location_precision": "precise",
        "title": "DARE Location",
        "link": "http://pleiades.stoa.org/places/69544/dare-location"
      }
    }
  ]
}