{
  "type": "FeatureCollection",
  "title": "Titos (river)",
  "id": "69576",
  "bbox": [
    -3.1403757,
    48.6269153,
    -3.1403757,
    48.6269153
  ],
  "description": "Titos fl. (Trieux river) is a river of Brittany.",
  "connectsWith": [
    "20420"
  ],
  "names": [
    "Titos"
  ],
  "features": [
    {
      "type": "Feature",
      "geometry": {
        "type": "Point",
        "coordinates": [
          -3.1403757,
          48.6269153
        ]
      },
      "properties": {
        "description": "representative point"
      }
    },
    {
      "geometry": {
        "type": "Point",
        "coordinates": [
          -3.1403757,
          48.6269153
        ]
      },
      "id": "location-of-Titos-fl",
      "type": "Feature",
      "properties": {
        "description": "Location based on OpenStreetMap",
        "location_precision": "precise",
        "title": "location of Titos fl.",
        "link": "http://pleiades.stoa.org/places/69576/location-of-Titos-fl"
      }
    }
  ]
}