{
  "type": "FeatureCollection",
  "title": "Vorgium",
  "id": "69585",
  "description": "An ancient place, cited: BAtlas 7 C3 Vorgium",
  "bbox": [
    -3.571121,
    48.276532,
    -3.571121,
    48.276532
  ],
  "reprPoint": [
    -3.571121,
    48.276532
  ],
  "names": [
    "Vorgium"
  ],
  "features": [
    {
      "geometry": {
        "type": "Point",
        "coordinates": [
          -3.571121,
          48.276532
        ]
      },
      "id": "darmc-location-15439",
      "type": "Feature",
      "properties": {
        "description": "1M scale point location",
        "location_precision": "precise",
        "title": "DARMC location 15439",
        "link": "http://pleiades.stoa.org/places/69585/darmc-location-15439"
      }
    }
  ]
}