{
  "type": "FeatureCollection",
  "title": "Khirbet el-Fityan",
  "id": "697685",
  "description": "An ancient place, cited: BAtlas 71 B3 Khirbet el-Fityan",
  "bbox": [
    35.84585,
    31.239621,
    35.856658,
    31.242784
  ],
  "reprPoint": [
    35.851254,
    31.2412025
  ],
  "features": [
    {
      "geometry": {
        "type": "Point",
        "coordinates": [
          35.856658,
          31.242784
        ]
      },
      "id": "dare-location",
      "type": "Feature",
      "properties": {
        "description": "Representative point location, site precision",
        "location_precision": "precise",
        "title": "DARE Location",
        "link": "http://pleiades.stoa.org/places/697685/dare-location"
      }
    },
    {
      "geometry": {
        "type": "Point",
        "coordinates": [
          35.84585,
          31.239621
        ]
      },
      "id": "darmc-location-17071",
      "type": "Feature",
      "properties": {
        "description": "500K scale point location",
        "location_precision": "precise",
        "title": "DARMC location 17071",
        "link": "http://pleiades.stoa.org/places/697685/darmc-location-17071"
      }
    }
  ]
}