{
  "type": "FeatureCollection",
  "title": "Lehun",
  "id": "697695",
  "description": "An ancient site located on the northern plateau of the Wadi Mujib in modern Jordan. Under excavation since the 1970s, the site has so far provided evidence for human activity from the prehistoric period through the Islamic.",
  "bbox": [
    35.849951,
    31.459504,
    35.849951,
    31.459504
  ],
  "reprPoint": [
    35.849951,
    31.459504
  ],
  "names": [
    "al-Lahūn"
  ],
  "features": [
    {
      "geometry": {
        "type": "Point",
        "coordinates": [
          35.849951,
          31.459504
        ]
      },
      "id": "darmc-location-20593",
      "type": "Feature",
      "properties": {
        "description": "500K scale point location",
        "location_precision": "precise",
        "title": "DARMC location 20593",
        "link": "http://pleiades.stoa.org/places/697695/darmc-location-20593"
      }
    }
  ]
}