{
  "type": "FeatureCollection",
  "title": "Khirbet el-Muhatta",
  "id": "697686",
  "description": "An ancient place, cited: BAtlas 71 B2 Khirbet el-Muhatta",
  "bbox": [
    35.719701,
    31.790245,
    35.719701,
    31.790245
  ],
  "reprPoint": [
    35.719701,
    31.790245
  ],
  "features": [
    {
      "geometry": {
        "type": "Point",
        "coordinates": [
          35.719701,
          31.790245
        ]
      },
      "id": "darmc-location-17072",
      "type": "Feature",
      "properties": {
        "description": "500K scale point location",
        "location_precision": "precise",
        "title": "DARMC location 17072",
        "link": "http://pleiades.stoa.org/places/697686/darmc-location-17072"
      }
    }
  ]
}