{
  "type": "FeatureCollection",
  "title": "Khirbet ez-Zona",
  "id": "697688",
  "description": "An ancient place, cited: BAtlas 71 B2 Khirbet ez-Zona",
  "bbox": [
    35.973295,
    31.578662,
    35.973295,
    31.578662
  ],
  "reprPoint": [
    35.973295,
    31.578662
  ],
  "features": [
    {
      "geometry": {
        "type": "Point",
        "coordinates": [
          35.973295,
          31.578662
        ]
      },
      "id": "darmc-location-17092",
      "type": "Feature",
      "properties": {
        "description": "500K scale point location",
        "location_precision": "precise",
        "title": "DARMC location 17092",
        "link": "http://pleiades.stoa.org/places/697688/darmc-location-17092"
      }
    }
  ]
}