{
  "type": "FeatureCollection",
  "title": "Khirbet et-Tannur",
  "id": "697687",
  "bbox": [
    35.702957,
    30.907378,
    35.711377,
    30.980157
  ],
  "description": "Located some 70 km from Petra, Khirbet et-Tannur is the site of a well-preserved, open-air Nabataean sanctuary.",
  "connectsWith": [
    "29677"
  ],
  "features": [
    {
      "type": "Feature",
      "geometry": {
        "type": "Point",
        "coordinates": [
          35.707167,
          30.9437675
        ]
      },
      "properties": {
        "description": "representative point"
      }
    },
    {
      "geometry": {
        "type": "Point",
        "coordinates": [
          35.711377,
          30.980157
        ]
      },
      "id": "darmc-location-26031",
      "type": "Feature",
      "properties": {
        "description": "500K scale point location",
        "location_precision": "precise",
        "title": "DARMC location 26031",
        "link": "http://pleiades.stoa.org/places/697687/darmc-location-26031"
      }
    },
    {
      "geometry": {
        "type": "Point",
        "coordinates": [
          35.702957,
          30.907378
        ]
      },
      "id": "dare-location",
      "type": "Feature",
      "properties": {
        "description": "Representative point location, site precision",
        "location_precision": "precise",
        "title": "DARE Location",
        "link": "http://pleiades.stoa.org/places/697687/dare-location"
      }
    }
  ]
}