{
  "type": "FeatureCollection",
  "title": "Castra Mefaa",
  "id": "697646",
  "bbox": [
    35.920133,
    31.500375,
    35.920133,
    31.500375
  ],
  "description": "A site that originated as a Roman castrum and developed into a town from the fifth century onward. Archaeological remains dates from the Roman, Byzantine, and Early Muslim periods.",
  "names": [
    "Castra Mefaa",
    "Umm ar-Rasas"
  ],
  "features": [
    {
      "type": "Feature",
      "geometry": {
        "type": "Point",
        "coordinates": [
          35.920133,
          31.500375
        ]
      },
      "properties": {
        "description": "representative point"
      }
    },
    {
      "geometry": {
        "type": "Point",
        "coordinates": [
          35.920133,
          31.500375
        ]
      },
      "id": "darmc-location-19088",
      "type": "Feature",
      "properties": {
        "description": "500K scale point location",
        "location_precision": "precise",
        "title": "DARMC location 19088",
        "link": "http://pleiades.stoa.org/places/697646/darmc-location-19088"
      }
    }
  ]
}