{
  "type": "FeatureCollection",
  "title": "Betthorus",
  "id": "697643",
  "description": "A Roman castrum of the limes Arabicus. In the fourth century, Legio IV Martia was stationed here.",
  "bbox": [
    35.868542,
    31.237033,
    35.868542,
    31.237033
  ],
  "reprPoint": [
    35.868542,
    31.237033
  ],
  "names": [
    "Betthorus"
  ],
  "features": [
    {
      "geometry": {
        "type": "Point",
        "coordinates": [
          35.86807,
          31.236867
        ]
      },
      "id": "darmc-location-19060",
      "type": "Feature",
      "properties": {
        "description": "500K scale point location",
        "location_precision": "precise",
        "title": "DARMC location 19060",
        "link": "http://pleiades.stoa.org/places/697643/darmc-location-19060"
      }
    },
    {
      "geometry": {
        "type": "Point",
        "coordinates": [
          35.868542,
          31.237033
        ]
      },
      "id": "dare-location",
      "type": "Feature",
      "properties": {
        "description": "Representative point location, site precision",
        "location_precision": "precise",
        "title": "DARE Location",
        "link": "http://pleiades.stoa.org/places/697643/dare-location"
      }
    }
  ]
}