{
  "type": "FeatureCollection",
  "title": "Lehun",
  "id": "697695",
  "bbox": [
    35.847851,
    31.459066,
    35.847851,
    31.459066
  ],
  "description": "An ancient site located on the northern plateau of the Wadi Mujib in modern Jordan. Under excavation since the 1970s, the site has so far provided evidence for human activity from the prehistoric period through the Islamic.",
  "names": [
    "al-Lahūn"
  ],
  "features": [
    {
      "type": "Feature",
      "geometry": {
        "type": "Point",
        "coordinates": [
          35.847851,
          31.459066
        ]
      },
      "properties": {
        "description": "representative point"
      }
    },
    {
      "geometry": {
        "type": "Point",
        "coordinates": [
          35.847851,
          31.459066
        ]
      },
      "id": "vici-org-location-of-lehun",
      "type": "Feature",
      "properties": {
        "description": "coordinates following vici.org",
        "location_precision": "precise",
        "title": "vici.org location of Lehun",
        "link": "http://pleiades.stoa.org/places/697695/vici-org-location-of-lehun"
      }
    }
  ]
}