{
  "type": "FeatureCollection",
  "title": "Dhat Ras",
  "id": "697653",
  "bbox": [
    35.762795,
    31.001818,
    35.762795,
    31.001818
  ],
  "description": "An ancient place, cited: BAtlas 71 B4 Dhat Ras",
  "features": [
    {
      "type": "Feature",
      "geometry": {
        "type": "Point",
        "coordinates": [
          35.762795,
          31.001818
        ]
      },
      "properties": {
        "description": "representative point"
      }
    },
    {
      "geometry": {
        "type": "Point",
        "coordinates": [
          35.762795,
          31.001818
        ]
      },
      "id": "darmc-location-20214",
      "type": "Feature",
      "properties": {
        "description": "500K scale point location",
        "location_precision": "precise",
        "title": "DARMC location 20214",
        "link": "http://pleiades.stoa.org/places/697653/darmc-location-20214"
      }
    }
  ]
}