{
  "type": "FeatureCollection",
  "title": "Tyrus",
  "id": "697757",
  "bbox": [
    35.7538951,
    31.9150722,
    35.7538951,
    31.9150722
  ],
  "description": "Hellenistic and Roman settlement in the Jordan Valley. The site contains a large palace, the Qasr al-Abd, dated to the second century CE.",
  "names": [
    "Tyrus",
    "ʻIrāq al-Amīr"
  ],
  "features": [
    {
      "type": "Feature",
      "geometry": {
        "type": "Point",
        "coordinates": [
          35.7538951,
          31.9150722
        ]
      },
      "properties": {
        "description": "representative point"
      }
    },
    {
      "geometry": {
        "type": "Point",
        "coordinates": [
          35.7538951,
          31.9150722
        ]
      },
      "id": "639631627642-62764464564a631",
      "type": "Feature",
      "properties": {
        "description": "Point representing the approximate centerpoint of the modern town of 'Iraq al-Amir, derived from an OpenStreetMap node.",
        "location_precision": "precise",
        "title": "OSM location of عراق الأمير",
        "link": "http://pleiades.stoa.org/places/697757/639631627642-62764464564a631"
      }
    }
  ]
}