{
  "type": "FeatureCollection",
  "title": "Machairous",
  "id": "697700",
  "description": "An ancient place, cited: BAtlas 71 B2 Machairous",
  "bbox": [
    35.624119,
    31.565925,
    35.633454,
    31.567335
  ],
  "reprPoint": [
    35.6287865,
    31.56663
  ],
  "names": [
    "Machairous"
  ],
  "features": [
    {
      "geometry": {
        "type": "Point",
        "coordinates": [
          35.633454,
          31.565925
        ]
      },
      "id": "darmc-location-7167",
      "type": "Feature",
      "properties": {
        "description": "500K scale point location",
        "location_precision": "precise",
        "title": "DARMC location 7167",
        "link": "http://pleiades.stoa.org/places/697700/darmc-location-7167"
      }
    },
    {
      "geometry": {
        "type": "Point",
        "coordinates": [
          35.624119,
          31.567335
        ]
      },
      "id": "dare-location",
      "type": "Feature",
      "properties": {
        "description": "Representative point location, site precision",
        "location_precision": "precise",
        "title": "DARE Location",
        "link": "http://pleiades.stoa.org/places/697700/dare-location"
      }
    }
  ]
}