{
  "type": "FeatureCollection",
  "title": "er-Ruweihi",
  "id": "697746",
  "description": "An ancient place, cited: BAtlas 71 B4 er-Ruweihi",
  "bbox": [
    35.5124685,
    30.1881885,
    35.910953,
    30.862028
  ],
  "reprPoint": [
    35.71171075,
    30.52510825
  ],
  "features": [
    {
      "geometry": {
        "type": "Point",
        "coordinates": [
          35.910953,
          30.862028
        ]
      },
      "id": "darmc-location-18484",
      "type": "Feature",
      "properties": {
        "description": "500K scale point location",
        "location_precision": "precise",
        "title": "DARMC location 18484",
        "link": "http://pleiades.stoa.org/places/697746/darmc-location-18484"
      }
    }
  ]
}