{
  "type": "FeatureCollection",
  "title": "Roman theater at Cuicul",
  "id": "697765430",
  "bbox": [
    5.7373999,
    36.320874,
    5.7373999,
    36.320874
  ],
  "description": "The Roman theater at Cuicul was built during the reign of Antoninus Pius.",
  "connectsWith": [
    "305068"
  ],
  "features": [
    {
      "type": "Feature",
      "geometry": {
        "type": "Point",
        "coordinates": [
          5.7373999,
          36.320874
        ]
      },
      "properties": {
        "description": "representative point"
      }
    },
    {
      "geometry": {
        "type": "Point",
        "coordinates": [
          5.7373999,
          36.320874
        ]
      },
      "id": "osm-location-of-roman-theater",
      "type": "Feature",
      "properties": {
        "description": "Representative location based on OpenStreetMap",
        "location_precision": "precise",
        "title": "OSM location of Roman theater",
        "link": "http://pleiades.stoa.org/places/697765430/osm-location-of-roman-theater"
      }
    }
  ]
}