{
  "type": "FeatureCollection",
  "title": "Tyrus",
  "id": "697757",
  "description": "An ancient place, cited: BAtlas 71 B2 Tyrus",
  "bbox": [
    35.75154,
    31.907678,
    35.75154,
    31.907678
  ],
  "reprPoint": [
    35.75154,
    31.907678
  ],
  "names": [
    "Tyrus"
  ],
  "features": [
    {
      "geometry": {
        "type": "Point",
        "coordinates": [
          35.75154,
          31.907678
        ]
      },
      "id": "darmc-location-6401",
      "type": "Feature",
      "properties": {
        "description": "500K scale point location",
        "location_precision": "precise",
        "title": "DARMC location 6401",
        "link": "http://pleiades.stoa.org/places/697757/darmc-location-6401"
      }
    }
  ]
}