{
  "type": "FeatureCollection",
  "title": "Zabayir Zahr ed-Diyab",
  "id": "697765",
  "bbox": [
    35.981196,
    31.695585,
    35.981196,
    31.695585
  ],
  "description": "An ancient place, cited: BAtlas 71 B2 Zabayir Zahr ed-Diyab",
  "features": [
    {
      "type": "Feature",
      "geometry": {
        "type": "Point",
        "coordinates": [
          35.981196,
          31.695585
        ]
      },
      "properties": {
        "description": "representative point"
      }
    },
    {
      "geometry": {
        "type": "Point",
        "coordinates": [
          35.981196,
          31.695585
        ]
      },
      "id": "darmc-location-33623",
      "type": "Feature",
      "properties": {
        "description": "representative point location digitized from the Barrington Atlas of the Greek and Roman World by the Digital Atlas of Roman and Medieval Civilizations project at Harvard University.",
        "location_precision": "precise",
        "title": "DARMC location 33623",
        "link": "http://pleiades.stoa.org/places/697765/darmc-location-33623"
      }
    }
  ]
}