{
  "type": "FeatureCollection",
  "title": "Qasr Bayir",
  "id": "697736",
  "description": "An ancient place, cited: BAtlas 71 D4 Qasr Bayir",
  "bbox": [
    36.673887,
    30.762502,
    36.673887,
    30.762502
  ],
  "reprPoint": [
    36.673887,
    30.762502
  ],
  "features": [
    {
      "geometry": {
        "type": "Point",
        "coordinates": [
          36.673887,
          30.762502
        ]
      },
      "id": "darmc-location-19183",
      "type": "Feature",
      "properties": {
        "description": "500K scale point location",
        "location_precision": "precise",
        "title": "DARMC location 19183",
        "link": "http://pleiades.stoa.org/places/697736/darmc-location-19183"
      }
    }
  ]
}