{
  "type": "FeatureCollection",
  "title": "Phaino",
  "id": "697726",
  "description": "An ancient place, cited: BAtlas 71 A4 Phaino",
  "bbox": [
    35.489119,
    30.627038,
    35.489119,
    30.627038
  ],
  "reprPoint": [
    35.489119,
    30.627038
  ],
  "names": [
    "Phaino"
  ],
  "features": [
    {
      "geometry": {
        "type": "Point",
        "coordinates": [
          35.489119,
          30.627038
        ]
      },
      "id": "darmc-location-19415",
      "type": "Feature",
      "properties": {
        "description": "500K scale point location",
        "location_precision": "precise",
        "title": "DARMC location 19415",
        "link": "http://pleiades.stoa.org/places/697726/darmc-location-19415"
      }
    }
  ]
}