{
  "type": "FeatureCollection",
  "title": "Qasr Bayir",
  "id": "697736",
  "bbox": [
    36.6801628,
    30.7619622,
    36.6801628,
    30.7619622
  ],
  "description": "An ancient place, cited: BAtlas 71 D4 Qasr Bayir",
  "features": [
    {
      "type": "Feature",
      "geometry": {
        "type": "Point",
        "coordinates": [
          36.6801628,
          30.7619622
        ]
      },
      "properties": {
        "description": "representative point"
      }
    },
    {
      "geometry": {
        "type": "Point",
        "coordinates": [
          36.6801628,
          30.7619622
        ]
      },
      "id": "osm-location-of-bayir",
      "type": "Feature",
      "properties": {
        "description": "Location based on OpenStreetMap",
        "location_precision": "precise",
        "title": "OSM location of Bayir",
        "link": "http://pleiades.stoa.org/places/697736/osm-location-of-bayir"
      }
    }
  ]
}