{
  "type": "FeatureCollection",
  "title": "Tumulo del Principe etrusco",
  "id": "698136498",
  "bbox": [
    10.3912156,
    43.7339646,
    10.3912156,
    43.7339646
  ],
  "description": "A seventh century B.C. Etruscan tumulus located near Pisa.",
  "connectsWith": [
    "403253"
  ],
  "names": [
    "Tumulo del Principe etrusco"
  ],
  "features": [
    {
      "type": "Feature",
      "geometry": {
        "type": "Point",
        "coordinates": [
          10.3912156,
          43.7339646
        ]
      },
      "properties": {
        "description": "representative point"
      }
    },
    {
      "geometry": {
        "type": "Point",
        "coordinates": [
          10.3912156,
          43.7339646
        ]
      },
      "id": "osm-location",
      "type": "Feature",
      "properties": {
        "description": "Representative location based on OpenStreetMap.",
        "location_precision": "precise",
        "title": "OSM location of Tumulo del Principe Etrusco",
        "link": "http://pleiades.stoa.org/places/698136498/osm-location"
      }
    }
  ]
}