{
  "type": "FeatureCollection",
  "title": "Grotta Corbeddu",
  "id": "70064465",
  "bbox": [
    9.4850745,
    40.2549181,
    9.4850745,
    40.2549181
  ],
  "description": "A cave near Oliena, Sardinia, where evidence for the earliest human occupation of the island of Sardinia has been recovered.",
  "connectsWith": [
    "472014"
  ],
  "features": [
    {
      "type": "Feature",
      "geometry": {
        "type": "Point",
        "coordinates": [
          9.4850745,
          40.2549181
        ]
      },
      "properties": {
        "description": "representative point"
      }
    },
    {
      "geometry": {
        "type": "Point",
        "coordinates": [
          9.4850745,
          40.2549181
        ]
      },
      "id": "osm-location-of-grotta-corbeddu",
      "type": "Feature",
      "properties": {
        "description": "Location based on OpenStreetMap",
        "location_precision": "precise",
        "title": "OSM location of Grotta \"Corbeddu\"",
        "link": "http://pleiades.stoa.org/places/70064465/osm-location-of-grotta-corbeddu"
      }
    }
  ]
}