{
  "type": "FeatureCollection",
  "title": "Villa San Giovanni in Tuscia",
  "id": "702892067",
  "bbox": [
    12.0528028,
    42.2806978,
    12.0528028,
    42.2806978
  ],
  "description": "A Roman villa of the third and fourth centuries A.D.",
  "features": [
    {
      "type": "Feature",
      "geometry": {
        "type": "Point",
        "coordinates": [
          12.0528028,
          42.2806978
        ]
      },
      "properties": {
        "description": "representative point"
      }
    },
    {
      "geometry": {
        "type": "Point",
        "coordinates": [
          12.0528028,
          42.2806978
        ]
      },
      "id": "osm-location-of-villa-san-giovanni-in-tuscia",
      "type": "Feature",
      "properties": {
        "description": "Associated modern location of the village of Villa San Giovanni in Tuscia based on a node derived from OpenStreetMap.",
        "location_precision": "precise",
        "title": "OSM location of Villa San Giovanni in Tuscia",
        "link": "http://pleiades.stoa.org/places/702892067/osm-location-of-villa-san-giovanni-in-tuscia"
      }
    }
  ]
}