{
  "type": "FeatureCollection",
  "title": "Bridgeness Distance Slab",
  "id": "703547396",
  "bbox": [
    -3.5835,
    56.016407,
    -3.5835,
    56.016407
  ],
  "description": "Findspot of the Bridgeness distance slab, near the eastern terminus of the Antonine Wall",
  "connectsWith": [
    "91357"
  ],
  "features": [
    {
      "type": "Feature",
      "geometry": {
        "type": "Point",
        "coordinates": [
          -3.5835,
          56.016407
        ]
      },
      "properties": {
        "description": "representative point"
      }
    },
    {
      "geometry": {
        "type": "Point",
        "coordinates": [
          -3.5835,
          56.016407
        ]
      },
      "id": "findspot-approx",
      "type": "Feature",
      "properties": {
        "description": "Findspot of the Bridgeness Distance slab. The site is marked by a stone plaque embedded in a wall along Harbour Road, marking the slab's discovery 'near this spot'.",
        "location_precision": "precise",
        "title": "Findspot (approx)",
        "link": "http://pleiades.stoa.org/places/703547396/findspot-approx"
      }
    }
  ]
}