{
  "type": "FeatureCollection",
  "title": "Artemis, T.",
  "id": "707486",
  "bbox": [
    33.791481,
    35.057081,
    33.791481,
    35.057081
  ],
  "description": "An ancient place, cited: BAtlas 72 D2 Artemis, T.",
  "names": [
    "Artemis, T.",
    "Kybele, T."
  ],
  "features": [
    {
      "type": "Feature",
      "geometry": {
        "type": "Point",
        "coordinates": [
          33.791481,
          35.057081
        ]
      },
      "properties": {
        "description": "representative point"
      }
    },
    {
      "geometry": {
        "type": "Point",
        "coordinates": [
          33.791481,
          35.057081
        ]
      },
      "id": "darmc-location-6522",
      "type": "Feature",
      "properties": {
        "description": "500K scale point location",
        "location_precision": "precise",
        "title": "DARMC location 6522",
        "link": "http://pleiades.stoa.org/places/707486/darmc-location-6522"
      }
    }
  ]
}