{
  "type": "FeatureCollection",
  "title": "Agrokipia",
  "id": "707452",
  "bbox": [
    33.140868,
    35.044062,
    33.140868,
    35.044062
  ],
  "description": "An ancient place, cited: BAtlas 72 C2 Agrokipia",
  "features": [
    {
      "type": "Feature",
      "geometry": {
        "type": "Point",
        "coordinates": [
          33.140868,
          35.044062
        ]
      },
      "properties": {
        "description": "representative point"
      }
    },
    {
      "geometry": {
        "type": "Point",
        "coordinates": [
          33.140868,
          35.044062
        ]
      },
      "id": "darmc-location-9352",
      "type": "Feature",
      "properties": {
        "description": "500K scale point location",
        "location_precision": "precise",
        "title": "DARMC location 9352",
        "link": "http://pleiades.stoa.org/places/707452/darmc-location-9352"
      }
    }
  ]
}