{
  "type": "FeatureCollection",
  "title": "Aphrodite Paphia, T.",
  "id": "707471",
  "description": "An ancient place, cited: BAtlas 72 C2 Aphrodite Paphia, T.",
  "bbox": [
    33.487926,
    35.25725,
    33.487926,
    35.25725
  ],
  "connectsWith": [
    "707498"
  ],
  "reprPoint": [
    33.487926,
    35.25725
  ],
  "names": [
    "Aphrodite Paphia, T."
  ],
  "features": [
    {
      "geometry": {
        "type": "Point",
        "coordinates": [
          33.487926,
          35.25725
        ]
      },
      "id": "darmc-location-15864",
      "type": "Feature",
      "properties": {
        "description": "500K scale point location",
        "location_precision": "precise",
        "title": "DARMC location 15864",
        "link": "http://pleiades.stoa.org/places/707471/darmc-location-15864"
      }
    }
  ]
}