{
  "type": "FeatureCollection",
  "title": "Ardana",
  "id": "707482",
  "description": "An ancient place, cited: BAtlas 72 D2 Ardana",
  "bbox": [
    33.904939,
    35.321989,
    33.904939,
    35.321989
  ],
  "reprPoint": [
    33.904939,
    35.321989
  ],
  "features": [
    {
      "geometry": {
        "type": "Point",
        "coordinates": [
          33.904939,
          35.321989
        ]
      },
      "id": "darmc-location-11471",
      "type": "Feature",
      "properties": {
        "description": "500K scale point location",
        "location_precision": "precise",
        "title": "DARMC location 11471",
        "link": "http://pleiades.stoa.org/places/707482/darmc-location-11471"
      }
    }
  ]
}