{
  "type": "FeatureCollection",
  "title": "Apollo Melanthios, T.",
  "id": "707478",
  "description": "An ancient place, cited: BAtlas 72 B3 Apollo Melanthios, T.",
  "bbox": [
    32.577772,
    34.829792,
    32.577772,
    34.829792
  ],
  "connectsWith": [
    "707498"
  ],
  "reprPoint": [
    32.577772,
    34.829792
  ],
  "names": [
    "Apollo Melanthios, T.",
    "Opaon Melanthios, T."
  ],
  "features": [
    {
      "geometry": {
        "type": "Point",
        "coordinates": [
          32.577772,
          34.829792
        ]
      },
      "id": "darmc-location-15879",
      "type": "Feature",
      "properties": {
        "description": "500K scale point location",
        "location_precision": "precise",
        "title": "DARMC location 15879",
        "link": "http://pleiades.stoa.org/places/707478/darmc-location-15879"
      }
    }
  ]
}