{
  "type": "FeatureCollection",
  "title": "Laxia tis Skhistis",
  "id": "707557",
  "description": "An ancient place, cited: BAtlas 72 B2 Laxia tis Skhistis",
  "bbox": [
    32.790763,
    35.127665,
    32.790763,
    35.127665
  ],
  "reprPoint": [
    32.790763,
    35.127665
  ],
  "features": [
    {
      "geometry": {
        "type": "Point",
        "coordinates": [
          32.790763,
          35.127665
        ]
      },
      "id": "darmc-location-16055",
      "type": "Feature",
      "properties": {
        "description": "500K scale point location",
        "location_precision": "precise",
        "title": "DARMC location 16055",
        "link": "http://pleiades.stoa.org/places/707557/darmc-location-16055"
      }
    }
  ]
}