{
  "type": "FeatureCollection",
  "title": "Limni",
  "id": "707564",
  "bbox": [
    32.489772,
    35.03481,
    32.489772,
    35.03481
  ],
  "description": "An ancient place, cited: BAtlas 72 A2 Limni",
  "connectsWith": [
    "707498"
  ],
  "features": [
    {
      "type": "Feature",
      "geometry": {
        "type": "Point",
        "coordinates": [
          32.489772,
          35.03481
        ]
      },
      "properties": {
        "description": "representative point"
      }
    },
    {
      "geometry": {
        "type": "Point",
        "coordinates": [
          32.489772,
          35.03481
        ]
      },
      "id": "darmc-location-9257",
      "type": "Feature",
      "properties": {
        "description": "500K scale point location",
        "location_precision": "precise",
        "title": "DARMC location 9257",
        "link": "http://pleiades.stoa.org/places/707564/darmc-location-9257"
      }
    }
  ]
}