{
  "type": "FeatureCollection",
  "title": "Kargaiai? Pr.",
  "id": "707525",
  "bbox": [
    33.0375,
    34.56667,
    33.0375,
    34.56667
  ],
  "description": "The south-eastern cape of the Akrotiri Peninsula on the island of Cyprus.",
  "connectsWith": [
    "325705845"
  ],
  "names": [
    "Kargaiai Pr."
  ],
  "features": [
    {
      "type": "Feature",
      "geometry": {
        "type": "Point",
        "coordinates": [
          33.0375,
          34.56667
        ]
      },
      "properties": {
        "description": "representative point"
      }
    },
    {
      "geometry": {
        "type": "Point",
        "coordinates": [
          33.0375,
          34.56667
        ]
      },
      "id": "location-of-cape-gata",
      "type": "Feature",
      "properties": {
        "description": "coordinates after GeoNames.",
        "location_precision": "precise",
        "title": "location of Cape Gata",
        "link": "http://pleiades.stoa.org/places/707525/location-of-cape-gata"
      }
    }
  ]
}