{
  "type": "FeatureCollection",
  "title": "Mathiatis",
  "id": "707576",
  "bbox": [
    33.341147,
    34.981767,
    33.341147,
    34.981767
  ],
  "description": "An ancient place, cited: BAtlas 72 C3 Mathiatis",
  "connectsWith": [
    "707498"
  ],
  "features": [
    {
      "type": "Feature",
      "geometry": {
        "type": "Point",
        "coordinates": [
          33.341147,
          34.981767
        ]
      },
      "properties": {
        "description": "representative point"
      }
    },
    {
      "geometry": {
        "type": "Point",
        "coordinates": [
          33.341147,
          34.981767
        ]
      },
      "id": "darmc-location-9568",
      "type": "Feature",
      "properties": {
        "description": "500K scale point location",
        "location_precision": "precise",
        "title": "DARMC location 9568",
        "link": "http://pleiades.stoa.org/places/707576/darmc-location-9568"
      }
    }
  ]
}