{
  "type": "FeatureCollection",
  "title": "Lyso",
  "id": "707567",
  "bbox": [
    32.521767,
    35.010847,
    32.521767,
    35.010847
  ],
  "description": "An ancient place, cited: BAtlas 72 B2 Lyso",
  "connectsWith": [
    "707498"
  ],
  "features": [
    {
      "type": "Feature",
      "geometry": {
        "type": "Point",
        "coordinates": [
          32.521767,
          35.010847
        ]
      },
      "properties": {
        "description": "representative point"
      }
    },
    {
      "geometry": {
        "type": "Point",
        "coordinates": [
          32.521767,
          35.010847
        ]
      },
      "id": "darmc-location-9565",
      "type": "Feature",
      "properties": {
        "description": "500K scale point location",
        "location_precision": "precise",
        "title": "DARMC location 9565",
        "link": "http://pleiades.stoa.org/places/707567/darmc-location-9565"
      }
    }
  ]
}