{
  "type": "FeatureCollection",
  "title": "Kouriakon (promontory)",
  "id": "707547",
  "bbox": [
    32.9329679,
    34.5667956,
    32.9329679,
    34.5667956
  ],
  "description": "A promontory of the island of Cyprus, identified tentatively by scholars with the modern Cape Zevgari.",
  "names": [
    "Kouriakon Pr."
  ],
  "features": [
    {
      "type": "Feature",
      "geometry": {
        "type": "Point",
        "coordinates": [
          32.9329679,
          34.5667956
        ]
      },
      "properties": {
        "description": "representative point"
      }
    },
    {
      "geometry": {
        "type": "Point",
        "coordinates": [
          32.9329679,
          34.5667956
        ]
      },
      "id": "location-of-cape-zevgari",
      "type": "Feature",
      "properties": {
        "description": "Location based on OpenStreetMap",
        "location_precision": "precise",
        "title": "OSM location of Cape Zevgari",
        "link": "http://pleiades.stoa.org/places/707547/location-of-cape-zevgari"
      }
    }
  ]
}