{
  "type": "FeatureCollection",
  "title": "Drepanon Pr.",
  "id": "707503",
  "description": "An ancient place, cited: BAtlas 72 A3 Drepanon Pr.",
  "bbox": [
    32.3161058,
    34.8994557,
    32.3161058,
    34.8994557
  ],
  "connectsWith": [
    "707498"
  ],
  "reprPoint": [
    32.3161058,
    34.8994557
  ],
  "names": [
    "Drepanon Pr."
  ],
  "features": [
    {
      "geometry": {
        "type": "Point",
        "coordinates": [
          32.3161058,
          34.8994557
        ]
      },
      "id": "location-of-cape-drepanum",
      "type": "Feature",
      "properties": {
        "description": "Location based on OpenStreetMap",
        "location_precision": "precise",
        "title": "location of Cape Drepanum",
        "link": "http://pleiades.stoa.org/places/707503/location-of-cape-drepanum"
      }
    }
  ]
}