{
  "type": "FeatureCollection",
  "title": "Melabron?",
  "id": "707579",
  "bbox": [
    32.940522,
    35.300538,
    32.941434,
    35.30658
  ],
  "description": "An ancient place, cited: BAtlas 72 B2 Melabron?",
  "connectsWith": [
    "707498"
  ],
  "names": [
    "Melabron"
  ],
  "features": [
    {
      "type": "Feature",
      "geometry": {
        "type": "Point",
        "coordinates": [
          32.940978,
          35.303559
        ]
      },
      "properties": {
        "description": "representative point"
      }
    },
    {
      "geometry": {
        "type": "Point",
        "coordinates": [
          32.941434,
          35.300538
        ]
      },
      "id": "darmc-location-13684",
      "type": "Feature",
      "properties": {
        "description": "1:500,000 scale representative point location digitized from the Barrington Atlas of the Greek and Roman World by the Digital Atlas of Roman and Medieval Civilizations project at Harvard University.",
        "location_precision": "precise",
        "title": "DARMC location 13684",
        "link": "http://pleiades.stoa.org/places/707579/darmc-location-13684"
      }
    },
    {
      "geometry": {
        "type": "Point",
        "coordinates": [
          32.940522,
          35.30658
        ]
      },
      "id": "dare-location",
      "type": "Feature",
      "properties": {
        "description": "Representative point location, village precision",
        "location_precision": "precise",
        "title": "DARE Location",
        "link": "http://pleiades.stoa.org/places/707579/dare-location"
      }
    }
  ]
}