{
  "type": "FeatureCollection",
  "title": "Petrera",
  "id": "707607",
  "bbox": [
    33.60224,
    35.231408,
    33.60224,
    35.231408
  ],
  "description": "An ancient place, cited: BAtlas 72 D2 Petrera",
  "connectsWith": [
    "707498"
  ],
  "features": [
    {
      "type": "Feature",
      "geometry": {
        "type": "Point",
        "coordinates": [
          33.60224,
          35.231408
        ]
      },
      "properties": {
        "description": "representative point"
      }
    },
    {
      "geometry": {
        "type": "Point",
        "coordinates": [
          33.60224,
          35.231408
        ]
      },
      "id": "darmc-location-2200",
      "type": "Feature",
      "properties": {
        "description": "500K scale point location",
        "location_precision": "precise",
        "title": "DARMC location 2200",
        "link": "http://pleiades.stoa.org/places/707607/darmc-location-2200"
      }
    }
  ]
}