{
  "type": "FeatureCollection",
  "title": "Petrera",
  "id": "707608",
  "description": "An ancient place, cited: BAtlas 72 C3 Petrera",
  "bbox": [
    33.362253,
    34.747153,
    33.362253,
    34.747153
  ],
  "connectsWith": [
    "707498"
  ],
  "reprPoint": [
    33.362253,
    34.747153
  ],
  "features": [
    {
      "geometry": {
        "type": "Point",
        "coordinates": [
          33.362253,
          34.747153
        ]
      },
      "id": "darmc-location-2199",
      "type": "Feature",
      "properties": {
        "description": "500K scale point location",
        "location_precision": "precise",
        "title": "DARMC location 2199",
        "link": "http://pleiades.stoa.org/places/707608/darmc-location-2199"
      }
    }
  ]
}