{
  "type": "FeatureCollection",
  "title": "Athenian Treasury at Delphi",
  "id": "707804475",
  "bbox": [
    22.501279,
    38.481828,
    22.501279,
    38.481828
  ],
  "description": "The Athenian Treasury at Delphi, built between 510 and 480 BC, is a building intended to house offerings made to Apollo by the citizens of Athens.",
  "connectsWith": [
    "540726"
  ],
  "names": [
    "Athenian Treasury"
  ],
  "features": [
    {
      "type": "Feature",
      "geometry": {
        "type": "Point",
        "coordinates": [
          22.501279,
          38.481828
        ]
      },
      "properties": {
        "description": "representative point"
      }
    },
    {
      "geometry": {
        "type": "Point",
        "coordinates": [
          22.501279,
          38.481828
        ]
      },
      "id": "athenian-treasury",
      "type": "Feature",
      "properties": {
        "description": "Location for the Athenian Treasury as determined from Google Earth satellite imagery. ",
        "location_precision": "precise",
        "title": "Imagery location of the Athenian Treasury at Delphi",
        "link": "http://pleiades.stoa.org/places/707804475/athenian-treasury"
      }
    }
  ]
}