{
  "type": "FeatureCollection",
  "title": "Via cava del Cavone, Sovana",
  "id": "710805922",
  "bbox": [
    11.6358965,
    42.6608222,
    11.6358965,
    42.6608222
  ],
  "description": "A hollowed roadway created by cutting the natural tufaceous bedrock. These roads link necropoleis and settlements in the area between Sovana, Sorano, and Pitigliano. ",
  "connectsWith": [
    "413323"
  ],
  "features": [
    {
      "type": "Feature",
      "geometry": {
        "type": "Point",
        "coordinates": [
          11.6358965,
          42.6608222
        ]
      },
      "properties": {
        "description": "representative point"
      }
    },
    {
      "geometry": {
        "type": "Point",
        "coordinates": [
          11.6358965,
          42.6608222
        ]
      },
      "id": "via-cava-del-cavone-sovana",
      "type": "Feature",
      "properties": {
        "description": "Location based on OpenStreetMap",
        "location_precision": "precise",
        "title": "Via cava del Cavone, Sovana",
        "link": "http://pleiades.stoa.org/places/710805922/via-cava-del-cavone-sovana"
      }
    }
  ]
}