{
  "type": "FeatureCollection",
  "title": "Temple of Hathor Miskar",
  "id": "71163123",
  "bbox": [
    9.2092383,
    35.8543522,
    9.2092383,
    35.8543522
  ],
  "description": "A Punic temple founded in the first century B.C.",
  "connectsWith": [
    "324774"
  ],
  "features": [
    {
      "type": "Feature",
      "geometry": {
        "type": "Point",
        "coordinates": [
          9.2092383,
          35.8543522
        ]
      },
      "properties": {
        "description": "representative point"
      }
    },
    {
      "geometry": {
        "type": "Point",
        "coordinates": [
          9.2092383,
          35.8543522
        ]
      },
      "id": "location-of-temple-of-hathor-miskar",
      "type": "Feature",
      "properties": {
        "description": "Location based on OpenStreetMap. A Punic temple founded in the first century BC.",
        "location_precision": "precise",
        "title": "OSM location of Temple of Hathor Miskar",
        "link": "http://pleiades.stoa.org/places/71163123/location-of-temple-of-hathor-miskar"
      }
    }
  ]
}