{
  "type": "FeatureCollection",
  "title": "Via Statilia tombs",
  "id": "711765706",
  "description": "Late Republican chamber tombs (ca. 100 B.C.) located at the intersection of the modern Via Statilia and Via di Santa Croce in Rome.",
  "bbox": [
    12.5118411,
    41.8903201,
    12.5118411,
    41.8903201
  ],
  "connectsWith": [
    "423025"
  ],
  "reprPoint": [
    12.5118411,
    41.8903201
  ],
  "features": [
    {
      "geometry": {
        "type": "Point",
        "coordinates": [
          12.5118411,
          41.8903201
        ]
      },
      "id": "location-of-via-statilia-tombs",
      "type": "Feature",
      "properties": {
        "description": "Representative location based on OpenStreetMap.",
        "location_precision": "precise",
        "title": "OSM location of so-called \"Sepolcri repubblicani di Via Statilia\"",
        "link": "http://pleiades.stoa.org/places/711765706/location-of-via-statilia-tombs"
      }
    }
  ]
}