{
  "type": "FeatureCollection",
  "title": "Thrypti",
  "id": "712477009",
  "bbox": [
    25.8754079,
    35.0801117,
    25.8754079,
    35.0801117
  ],
  "description": "Thrypti, a mountain range of eastern Crete.",
  "connectsWith": [
    "589748"
  ],
  "features": [
    {
      "type": "Feature",
      "geometry": {
        "type": "Point",
        "coordinates": [
          25.8754079,
          35.0801117
        ]
      },
      "properties": {
        "description": "representative point"
      }
    },
    {
      "geometry": {
        "type": "Point",
        "coordinates": [
          25.8754079,
          35.0801117
        ]
      },
      "id": "location-of-oros-thriptis",
      "type": "Feature",
      "properties": {
        "description": "Representative modern location based on OpenStreetMap.",
        "location_precision": "precise",
        "title": "OSM location of Oros Thriptis",
        "link": "http://pleiades.stoa.org/places/712477009/location-of-oros-thriptis"
      }
    }
  ]
}