{
  "type": "FeatureCollection",
  "title": "Nuraghe di Sant'Itroxia",
  "id": "71262258",
  "bbox": [
    9.2738527,
    39.3352282,
    9.2738527,
    39.3352282
  ],
  "description": "A Middle Bronze age nuragic site with evidence of a giant's tomb and a nuragic tower.",
  "connectsWith": [
    "472014"
  ],
  "features": [
    {
      "type": "Feature",
      "geometry": {
        "type": "Point",
        "coordinates": [
          9.2738527,
          39.3352282
        ]
      },
      "properties": {
        "description": "representative point"
      }
    },
    {
      "geometry": {
        "type": "Point",
        "coordinates": [
          9.2738527,
          39.3352282
        ]
      },
      "id": "osm-location",
      "type": "Feature",
      "properties": {
        "description": "Location based on OpenStreetMap",
        "location_precision": "precise",
        "title": "OSM location of Nuraghe di Sant'Itroxia",
        "link": "http://pleiades.stoa.org/places/71262258/osm-location"
      }
    }
  ]
}