{
  "type": "FeatureCollection",
  "title": "Roman Theater of Baelo",
  "id": "713816455",
  "bbox": [
    -5.7759514,
    36.0909571,
    -5.7759514,
    36.0909571
  ],
  "description": "A Roman theater in Baelo.",
  "connectsWith": [
    "256005"
  ],
  "features": [
    {
      "type": "Feature",
      "geometry": {
        "type": "Point",
        "coordinates": [
          -5.7759514,
          36.0909571
        ]
      },
      "properties": {
        "description": "representative point"
      }
    },
    {
      "geometry": {
        "type": "Point",
        "coordinates": [
          -5.7759514,
          36.0909571
        ]
      },
      "id": "location-of-roman-theater",
      "type": "Feature",
      "properties": {
        "description": "Representative location based on OpenStreetMap.",
        "location_precision": "precise",
        "title": "OSM location of Roman theater",
        "link": "http://pleiades.stoa.org/places/713816455/location-of-roman-theater"
      }
    }
  ]
}