{
  "type": "FeatureCollection",
  "title": "Luxor Temple",
  "id": "71626430",
  "bbox": [
    32.6380625,
    25.6985252,
    32.6380625,
    25.6985252
  ],
  "description": "An ancient Egyptian temple initially built ca. 1400 B.C.",
  "connectsWith": [
    "786017"
  ],
  "features": [
    {
      "type": "Feature",
      "geometry": {
        "type": "Point",
        "coordinates": [
          32.6380625,
          25.6985252
        ]
      },
      "properties": {
        "description": "representative point"
      }
    },
    {
      "geometry": {
        "type": "Point",
        "coordinates": [
          32.6380625,
          25.6985252
        ]
      },
      "id": "luxor-temple",
      "type": "Feature",
      "properties": {
        "description": "Location based on OpenStreetMap",
        "location_precision": "precise",
        "title": "OSM location of Luxor Temple",
        "link": "http://pleiades.stoa.org/places/71626430/luxor-temple"
      }
    }
  ]
}