{
  "type": "FeatureCollection",
  "title": "Geziret el Marakeb",
  "id": "716560",
  "bbox": [
    23.275971,
    32.220261,
    23.275971,
    32.220261
  ],
  "description": "An ancient place, cited: None",
  "features": [
    {
      "type": "Feature",
      "geometry": {
        "type": "Point",
        "coordinates": [
          23.275971,
          32.220261
        ]
      },
      "properties": {
        "description": "representative point"
      }
    },
    {
      "geometry": {
        "type": "Point",
        "coordinates": [
          23.275971,
          32.220261
        ]
      },
      "id": "darmc-location-15977",
      "type": "Feature",
      "properties": {
        "description": "1M scale point location",
        "location_precision": "precise",
        "title": "DARMC location 15977",
        "link": "http://pleiades.stoa.org/places/716560/darmc-location-15977"
      }
    }
  ]
}