{
  "type": "FeatureCollection",
  "title": "Giarabub",
  "id": "716562",
  "bbox": [
    24.510616,
    29.734968,
    24.510616,
    29.734968
  ],
  "description": "An ancient place, cited: None",
  "features": [
    {
      "type": "Feature",
      "geometry": {
        "type": "Point",
        "coordinates": [
          24.510616,
          29.734968
        ]
      },
      "properties": {
        "description": "representative point"
      }
    },
    {
      "geometry": {
        "type": "Point",
        "coordinates": [
          24.510616,
          29.734968
        ]
      },
      "id": "darmc-location-12543",
      "type": "Feature",
      "properties": {
        "description": "1M scale point location",
        "location_precision": "precise",
        "title": "DARMC location 12543",
        "link": "http://pleiades.stoa.org/places/716562/darmc-location-12543"
      }
    }
  ]
}