{
  "type": "FeatureCollection",
  "title": "‘Comaru’",
  "id": "716546",
  "bbox": [
    28.734397,
    30.966185,
    28.734397,
    30.966185
  ],
  "description": "An ancient place, cited: None",
  "names": [
    "Comaru"
  ],
  "features": [
    {
      "type": "Feature",
      "geometry": {
        "type": "Point",
        "coordinates": [
          28.734397,
          30.966185
        ]
      },
      "properties": {
        "description": "representative point"
      }
    },
    {
      "geometry": {
        "type": "Point",
        "coordinates": [
          28.734397,
          30.966185
        ]
      },
      "id": "darmc-location-9739",
      "type": "Feature",
      "properties": {
        "description": "1M scale point location",
        "location_precision": "precise",
        "title": "DARMC location 9739",
        "link": "http://pleiades.stoa.org/places/716546/darmc-location-9739"
      }
    }
  ]
}