{
  "type": "FeatureCollection",
  "title": "Mandishah",
  "id": "716592",
  "bbox": [
    28.899941,
    28.366464,
    28.899941,
    28.366464
  ],
  "description": "An ancient place, cited: None",
  "features": [
    {
      "type": "Feature",
      "geometry": {
        "type": "Point",
        "coordinates": [
          28.899941,
          28.366464
        ]
      },
      "properties": {
        "description": "representative point"
      }
    },
    {
      "geometry": {
        "type": "Point",
        "coordinates": [
          28.899941,
          28.366464
        ]
      },
      "id": "darmc-location-13616",
      "type": "Feature",
      "properties": {
        "description": "1M scale point location",
        "location_precision": "precise",
        "title": "DARMC location 13616",
        "link": "http://pleiades.stoa.org/places/716592/darmc-location-13616"
      }
    }
  ]
}