{
  "type": "FeatureCollection",
  "title": "Alexandrou Parembole",
  "id": "716518",
  "description": "An ancient place, cited: None",
  "bbox": [
    26.45006,
    29.61606,
    26.45006,
    29.61606
  ],
  "reprPoint": [
    26.45006,
    29.61606
  ],
  "names": [
    "Alexandrou Parembole"
  ],
  "features": [
    {
      "geometry": {
        "type": "Point",
        "coordinates": [
          26.45006,
          29.61606
        ]
      },
      "id": "darmc-location-9946",
      "type": "Feature",
      "properties": {
        "description": "1M scale point location",
        "location_precision": "precise",
        "title": "DARMC location 9946",
        "link": "http://pleiades.stoa.org/places/716518/darmc-location-9946"
      }
    }
  ]
}