{
  "type": "FeatureCollection",
  "title": "Alexandrou Parembole",
  "id": "716518",
  "bbox": [
    26.45006,
    29.61606,
    26.45006,
    29.61606
  ],
  "description": "An ancient place, cited: None",
  "names": [
    "Alexandrou Parembole"
  ],
  "features": [
    {
      "type": "Feature",
      "geometry": {
        "type": "Point",
        "coordinates": [
          26.45006,
          29.61606
        ]
      },
      "properties": {
        "description": "representative point"
      }
    },
    {
      "geometry": {
        "type": "Point",
        "coordinates": [
          26.45006,
          29.61606
        ]
      },
      "id": "darmc-location-9946",
      "type": "Feature",
      "properties": {
        "description": "1:1 million scale representative point location digitized from the Barrington Atlas of the Greek and Roman World by the Digital Atlas of Roman and Medieval Civilizations project at Harvard University.",
        "location_precision": "precise",
        "title": "DARMC location 9946",
        "link": "http://pleiades.stoa.org/places/716518/darmc-location-9946"
      }
    }
  ]
}