{
  "type": "FeatureCollection",
  "title": "Ammon",
  "id": "716520",
  "bbox": [
    25.543375,
    29.205023,
    25.54366,
    29.205389
  ],
  "description": "The Siwa Oasis was, in antiquity, site of the oracular temple of Amun (Zeus Ammon).",
  "names": [
    "Ammon",
    "Ammoniace",
    "Siwa Oasis"
  ],
  "features": [
    {
      "type": "Feature",
      "geometry": {
        "type": "Point",
        "coordinates": [
          25.5435296667,
          29.2051733333
        ]
      },
      "properties": {
        "description": "representative point"
      }
    },
    {
      "geometry": {
        "type": "Point",
        "coordinates": [
          25.543554,
          29.205108
        ]
      },
      "id": "darmc-location-2757",
      "type": "Feature",
      "properties": {
        "description": "1:1 million scale representative point location digitized from the Barrington Atlas of the Greek and Roman World by the Digital Atlas of Roman and Medieval Civilizations project at Harvard University.",
        "location_precision": "precise",
        "title": "DARMC location 2757",
        "link": "http://pleiades.stoa.org/places/716520/darmc-location-2757"
      }
    },
    {
      "geometry": {
        "type": "Point",
        "coordinates": [
          25.54366,
          29.205023
        ]
      },
      "id": "darmc-location-2758",
      "type": "Feature",
      "properties": {
        "description": "5M scale representative point location digitized from the Barrington Atlas of the Greek and Roman World by the Digital Atlas of Roman and Medieval Civilizations project at Harvard University.",
        "location_precision": "precise",
        "title": "DARMC location 2758",
        "link": "http://pleiades.stoa.org/places/716520/darmc-location-2758"
      }
    },
    {
      "geometry": {
        "type": "Point",
        "coordinates": [
          25.543375,
          29.205389
        ]
      },
      "id": "dare-location",
      "type": "Feature",
      "properties": {
        "description": "Representative point location, site precision",
        "location_precision": "precise",
        "title": "DARE Location",
        "link": "http://pleiades.stoa.org/places/716520/dare-location"
      }
    }
  ]
}