{
  "type": "FeatureCollection",
  "title": "Bahrein",
  "id": "716533",
  "description": "An ancient place, cited: None",
  "bbox": [
    26.487423,
    28.680379,
    26.487423,
    28.680379
  ],
  "reprPoint": [
    26.487423,
    28.680379
  ],
  "features": [
    {
      "geometry": {
        "type": "Point",
        "coordinates": [
          26.487423,
          28.680379
        ]
      },
      "id": "darmc-location-23423",
      "type": "Feature",
      "properties": {
        "description": "Point location",
        "location_precision": "precise",
        "title": "DARMC location 23423",
        "link": "http://pleiades.stoa.org/places/716533/darmc-location-23423"
      }
    }
  ]
}