{
  "type": "FeatureCollection",
  "title": "Ain el-Hayz",
  "id": "716510",
  "bbox": [
    28.650122,
    28.033849,
    28.650122,
    28.033849
  ],
  "description": "An ancient place, cited: None",
  "features": [
    {
      "type": "Feature",
      "geometry": {
        "type": "Point",
        "coordinates": [
          28.650122,
          28.033849
        ]
      },
      "properties": {
        "description": "representative point"
      }
    },
    {
      "geometry": {
        "type": "Point",
        "coordinates": [
          28.650122,
          28.033849
        ]
      },
      "id": "darmc-location-21255",
      "type": "Feature",
      "properties": {
        "description": "1M scale point location",
        "location_precision": "precise",
        "title": "DARMC location 21255",
        "link": "http://pleiades.stoa.org/places/716510/darmc-location-21255"
      }
    }
  ]
}