{
  "type": "FeatureCollection",
  "title": "Ain Melfa",
  "id": "716515",
  "bbox": [
    24.835059,
    29.787728,
    24.835059,
    29.787728
  ],
  "description": "An ancient place, cited: None",
  "features": [
    {
      "type": "Feature",
      "geometry": {
        "type": "Point",
        "coordinates": [
          24.835059,
          29.787728
        ]
      },
      "properties": {
        "description": "representative point"
      }
    },
    {
      "geometry": {
        "type": "Point",
        "coordinates": [
          24.835059,
          29.787728
        ]
      },
      "id": "darmc-location-23403",
      "type": "Feature",
      "properties": {
        "description": "Point location",
        "location_precision": "precise",
        "title": "DARMC location 23403",
        "link": "http://pleiades.stoa.org/places/716515/darmc-location-23403"
      }
    }
  ]
}