{
  "type": "FeatureCollection",
  "title": "Pnigeus Akroterion",
  "id": "716625",
  "bbox": [
    27.995411,
    31.085336,
    27.995411,
    31.085336
  ],
  "description": "An ancient place, cited: None",
  "names": [
    "Pnigeus Akroterion"
  ],
  "features": [
    {
      "type": "Feature",
      "geometry": {
        "type": "Point",
        "coordinates": [
          27.995411,
          31.085336
        ]
      },
      "properties": {
        "description": "representative point"
      }
    },
    {
      "geometry": {
        "type": "Point",
        "coordinates": [
          27.995411,
          31.085336
        ]
      },
      "id": "darmc-location-9867",
      "type": "Feature",
      "properties": {
        "description": "1M scale point location",
        "location_precision": "precise",
        "title": "DARMC location 9867",
        "link": "http://pleiades.stoa.org/places/716625/darmc-location-9867"
      }
    }
  ]
}