{
  "type": "FeatureCollection",
  "title": "el-Meyserah",
  "id": "716600",
  "bbox": [
    28.937541,
    28.334403,
    28.937541,
    28.334403
  ],
  "description": "An ancient place, cited: None",
  "features": [
    {
      "type": "Feature",
      "geometry": {
        "type": "Point",
        "coordinates": [
          28.937541,
          28.334403
        ]
      },
      "properties": {
        "description": "representative point"
      }
    },
    {
      "geometry": {
        "type": "Point",
        "coordinates": [
          28.937541,
          28.334403
        ]
      },
      "id": "darmc-location-25586",
      "type": "Feature",
      "properties": {
        "description": "1M scale point location",
        "location_precision": "precise",
        "title": "DARMC location 25586",
        "link": "http://pleiades.stoa.org/places/716600/darmc-location-25586"
      }
    }
  ]
}