{
  "type": "FeatureCollection",
  "title": "Zygris",
  "id": "716656",
  "bbox": [
    26.409102,
    31.506636,
    26.409102,
    31.506636
  ],
  "description": "An ancient place, cited: None",
  "names": [
    "Zygris"
  ],
  "features": [
    {
      "type": "Feature",
      "geometry": {
        "type": "Point",
        "coordinates": [
          26.409102,
          31.506636
        ]
      },
      "properties": {
        "description": "representative point"
      }
    },
    {
      "geometry": {
        "type": "Point",
        "coordinates": [
          26.409102,
          31.506636
        ]
      },
      "id": "darmc-location-830",
      "type": "Feature",
      "properties": {
        "description": "1M scale point location",
        "location_precision": "precise",
        "title": "DARMC location 830",
        "link": "http://pleiades.stoa.org/places/716656/darmc-location-830"
      }
    }
  ]
}