{
  "type": "FeatureCollection",
  "title": "el-Muftella",
  "id": "716602",
  "bbox": [
    28.84717,
    28.357329,
    28.84717,
    28.357329
  ],
  "description": "An ancient place, cited: None",
  "features": [
    {
      "type": "Feature",
      "geometry": {
        "type": "Point",
        "coordinates": [
          28.84717,
          28.357329
        ]
      },
      "properties": {
        "description": "representative point"
      }
    },
    {
      "geometry": {
        "type": "Point",
        "coordinates": [
          28.84717,
          28.357329
        ]
      },
      "id": "darmc-location-26296",
      "type": "Feature",
      "properties": {
        "description": "1M scale point location",
        "location_precision": "precise",
        "title": "DARMC location 26296",
        "link": "http://pleiades.stoa.org/places/716602/darmc-location-26296"
      }
    }
  ]
}