{
  "type": "FeatureCollection",
  "title": "Temple F at Selinus",
  "id": "71706222",
  "description": "Temple F at Selinus is a Doric temple located on the site's so-called \"East Hill\". Dedicated either to Athena or Dionysus, the temple dates to the middle of the sixth century B.C. The non-canonical ground plan of 6 x 14 columns gives the temple an elongated aspect.",
  "bbox": [
    12.8344107,
    37.5874936,
    12.8344107,
    37.5874936
  ],
  "connectsWith": [
    "462489"
  ],
  "reprPoint": [
    12.8344107,
    37.5874936
  ],
  "features": [
    {
      "geometry": {
        "type": "Point",
        "coordinates": [
          12.8344107,
          37.5874936
        ]
      },
      "id": "location-of-temple-f",
      "type": "Feature",
      "properties": {
        "description": "a late Archaic Doric temple. Location based on OpenStreetMap",
        "location_precision": "precise",
        "title": "OSM location of Temple F",
        "link": "http://pleiades.stoa.org/places/71706222/location-of-temple-f"
      }
    }
  ]
}