{
  "type": "FeatureCollection",
  "title": "'Ein-Shadud",
  "id": "720628460",
  "bbox": [
    35.2383508,
    32.6599924,
    35.2383508,
    32.6599924
  ],
  "description": "Small settlement in the Jezreel Valley containing structures dated to the Early Bronze Age I. Salvage excavations were conducted on the site in 1979 prior to its destruction by construction.",
  "names": [
    "'Ein-Shadud"
  ],
  "features": [
    {
      "type": "Feature",
      "geometry": {
        "type": "Point",
        "coordinates": [
          35.2383508,
          32.6599924
        ]
      },
      "properties": {
        "description": "representative point"
      }
    },
    {
      "geometry": {
        "type": "Point",
        "coordinates": [
          35.2383508,
          32.6599924
        ]
      },
      "id": "ein-shadud",
      "type": "Feature",
      "properties": {
        "description": "Point representing the approximate location of the 'Ein-Shadud site prior to its destruction by modern construction, derived from an OpenStreetMap Node after Bruan 1985.",
        "location_precision": "precise",
        "title": "OSM location of 'Ein-Shadud",
        "link": "http://pleiades.stoa.org/places/720628460/ein-shadud"
      }
    }
  ]
}