{
  "type": "FeatureCollection",
  "title": "Ninurta temple (Khorsabad)",
  "id": "72111815",
  "bbox": [
    43.22831,
    36.508702,
    43.22831,
    36.508702
  ],
  "description": "As part of the palatial complex of Dūr-Šarrukīn (modern Khorsabad), the eighth-century-BC Assyrian king Sargon II (r. 721–705 BC) constructed six temples, including one to the god Ninurta.",
  "connectsWith": [
    "874458",
    "237150019",
    "305127729"
  ],
  "names": [
    "Ninurta temple"
  ],
  "features": [
    {
      "type": "Feature",
      "geometry": {
        "type": "Point",
        "coordinates": [
          43.22831,
          36.508702
        ]
      },
      "properties": {
        "description": "representative point"
      }
    },
    {
      "geometry": {
        "type": "Point",
        "coordinates": [
          43.22831,
          36.508702
        ]
      },
      "id": "representative-location-of-the-ninurta-temple",
      "type": "Feature",
      "properties": {
        "description": "Representative point based on the visible remains of the Ninurta temple.",
        "location_precision": "precise",
        "title": "Representative location of the Ninurta temple",
        "link": "http://pleiades.stoa.org/places/72111815/representative-location-of-the-ninurta-temple"
      }
    }
  ]
}