{
  "type": "FeatureCollection",
  "title": "Roman Circus at Mérida",
  "id": "723991750",
  "bbox": [
    -6.332201,
    38.919937,
    -6.332201,
    38.919937
  ],
  "description": "The Roman Circus at Mérida dates ca. 20 B.C.",
  "connectsWith": [
    "256155"
  ],
  "features": [
    {
      "type": "Feature",
      "geometry": {
        "type": "Point",
        "coordinates": [
          -6.332201,
          38.919937
        ]
      },
      "properties": {
        "description": "representative point"
      }
    },
    {
      "geometry": {
        "type": "Point",
        "coordinates": [
          -6.332201,
          38.919937
        ]
      },
      "id": "centerpoint-of-the-roman-circus-at-merida",
      "type": "Feature",
      "properties": {
        "description": "Digitized in Google Earth in July 2012 at an eye altitude of 600m.",
        "location_precision": "precise",
        "title": "Centerpoint of the Roman Circus at Mérida",
        "link": "http://pleiades.stoa.org/places/723991750/centerpoint-of-the-roman-circus-at-merida"
      }
    }
  ]
}