{
  "type": "FeatureCollection",
  "title": "Burgus Szentendre-Dera",
  "id": "725195997",
  "bbox": [
    19.0799,
    47.641344,
    19.0799,
    47.641344
  ],
  "description": "Burgus Szentendre-Dera is a late antique Roman military encampment located along the Hungarian Danube at Szentendre (St. Andrae). The fort secured the Pannonian Limes.",
  "features": [
    {
      "type": "Feature",
      "geometry": {
        "type": "Point",
        "coordinates": [
          19.0799,
          47.641344
        ]
      },
      "properties": {
        "description": "representative point"
      }
    },
    {
      "geometry": {
        "type": "Point",
        "coordinates": [
          19.0799,
          47.641344
        ]
      },
      "id": "burgus-ulcisia-1",
      "type": "Feature",
      "properties": {
        "description": "Coordinates after GeoHack.",
        "location_precision": "precise",
        "title": "Imagery location of Burgus Szentendre-Dera",
        "link": "http://pleiades.stoa.org/places/725195997/burgus-ulcisia-1"
      }
    }
  ]
}