{
  "type": "FeatureCollection",
  "title": "Lusanda",
  "id": "726944833",
  "bbox": [
    37.1139646,
    38.2616336,
    37.1139646,
    38.2616336
  ],
  "description": "Lusanda is a fortified city in Que, probably in the eastern part of the Cilician plain. The city is mentioned with Abarnani and Kisuatni in royal inscriptions of the Assyrian king Shalmaneser III (r. 858-824 BC).",
  "connectsWith": [
    "944349915"
  ],
  "names": [
    "Lusanda"
  ],
  "features": [
    {
      "type": "Feature",
      "geometry": {
        "type": "Point",
        "coordinates": [
          37.1139646,
          38.2616336
        ]
      },
      "properties": {
        "description": "representative point"
      }
    },
    {
      "geometry": {
        "type": "Point",
        "coordinates": [
          37.1139646,
          38.2616336
        ]
      },
      "id": "helsinki-atlas-location-of-lusanda",
      "type": "Feature",
      "properties": {
        "description": "Conjectured, proposed location of Lusanda according to the Helsinki Atlas. The coordinates are for the OSM Node Karahüyük (1417050719).",
        "location_precision": "precise",
        "title": "Helsinki Atlas location of Lusanda",
        "link": "http://pleiades.stoa.org/places/726944833/helsinki-atlas-location-of-lusanda"
      }
    }
  ]
}