{
  "type": "FeatureCollection",
  "title": "Iuliopolis/Nikopolis",
  "id": "727131",
  "bbox": [
    29.950022,
    31.233348,
    29.950022,
    31.233348
  ],
  "description": "An ancient place, cited: BAtlas 74 B2 Iuliopolis/Nikopolis",
  "names": [
    "Iuliopolis",
    "Nikopolis",
    "Sidi Gaber"
  ],
  "features": [
    {
      "type": "Feature",
      "geometry": {
        "type": "Point",
        "coordinates": [
          29.950022,
          31.233348
        ]
      },
      "properties": {
        "description": "representative point"
      }
    },
    {
      "geometry": {
        "type": "Point",
        "coordinates": [
          29.950022,
          31.233348
        ]
      },
      "id": "darmc-location-12905",
      "type": "Feature",
      "properties": {
        "description": "500K scale point location",
        "location_precision": "precise",
        "title": "DARMC location 12905",
        "link": "http://pleiades.stoa.org/places/727131/darmc-location-12905"
      }
    }
  ]
}