{
  "type": "FeatureCollection",
  "title": "Hephaistos",
  "id": "727119",
  "description": "An ancient place, cited: BAtlas 74 G2 Hephaistos",
  "bbox": [
    31.850314,
    31.210588,
    31.850314,
    31.210588
  ],
  "reprPoint": [
    31.850314,
    31.210588
  ],
  "names": [
    "Hephaistos"
  ],
  "features": [
    {
      "geometry": {
        "type": "Point",
        "coordinates": [
          31.850314,
          31.210588
        ]
      },
      "id": "darmc-location-34961",
      "type": "Feature",
      "properties": {
        "description": "scale point location",
        "location_precision": "precise",
        "title": "DARMC location 34961",
        "link": "http://pleiades.stoa.org/places/727119/darmc-location-34961"
      }
    }
  ]
}