{
  "type": "FeatureCollection",
  "title": "Metelis",
  "id": "727163",
  "bbox": [
    30.375411,
    31.12039,
    30.375411,
    31.12039
  ],
  "description": "An ancient place, cited: BAtlas 74 C2 Metelis",
  "names": [
    "Metelis"
  ],
  "features": [
    {
      "type": "Feature",
      "geometry": {
        "type": "Point",
        "coordinates": [
          30.375411,
          31.12039
        ]
      },
      "properties": {
        "description": "representative point"
      }
    },
    {
      "geometry": {
        "type": "Point",
        "coordinates": [
          30.375411,
          31.12039
        ]
      },
      "id": "darmc-location-13721",
      "type": "Feature",
      "properties": {
        "description": "1:500,000 scale representative point location digitized from the Barrington Atlas of the Greek and Roman World by the Digital Atlas of Roman and Medieval Civilizations project at Harvard University.",
        "location_precision": "precise",
        "title": "DARMC location 13721",
        "link": "http://pleiades.stoa.org/places/727163/darmc-location-13721"
      }
    }
  ]
}