{
  "type": "FeatureCollection",
  "title": "Taposiris Megale",
  "id": "727241",
  "description": "A Ptolemaic city and temple built by Ptolemy II between 280 and 270 BC.",
  "bbox": [
    29.518872,
    30.946218,
    29.518872,
    30.946218
  ],
  "reprPoint": [
    29.518872,
    30.946218
  ],
  "names": [
    "Taposiris Megale"
  ],
  "features": [
    {
      "geometry": {
        "type": "Point",
        "coordinates": [
          29.519356,
          30.946035
        ]
      },
      "id": "darmc-location-15004",
      "type": "Feature",
      "properties": {
        "description": "500K scale point location",
        "location_precision": "precise",
        "title": "DARMC location 15004",
        "link": "http://pleiades.stoa.org/places/727241/darmc-location-15004"
      }
    },
    {
      "geometry": {
        "type": "Point",
        "coordinates": [
          29.518872,
          30.946218
        ]
      },
      "id": "dare-location",
      "type": "Feature",
      "properties": {
        "description": "Representative point location, site precision",
        "location_precision": "precise",
        "title": "DARE Location",
        "link": "http://pleiades.stoa.org/places/727241/dare-location"
      }
    }
  ]
}