{
  "type": "FeatureCollection",
  "title": "Sebennytos",
  "id": "727227",
  "bbox": [
    31.239569,
    30.962841,
    31.240395,
    30.965418
  ],
  "description": "Sebennytos was an ancient city of Lower Egypt located on the Sebennytic branch of the Nile river. It was the capital of Lower Egypt's twelfth nome (the Sebennyte nome).",
  "connectsWith": [
    "727092"
  ],
  "names": [
    "Sebennytos"
  ],
  "features": [
    {
      "type": "Feature",
      "geometry": {
        "type": "Point",
        "coordinates": [
          31.239982,
          30.9641295
        ]
      },
      "properties": {
        "description": "representative point"
      }
    },
    {
      "geometry": {
        "type": "Point",
        "coordinates": [
          31.240395,
          30.965418
        ]
      },
      "id": "darmc-location-14645",
      "type": "Feature",
      "properties": {
        "description": "500K scale point location",
        "location_precision": "precise",
        "title": "DARMC location 14645",
        "link": "http://pleiades.stoa.org/places/727227/darmc-location-14645"
      }
    },
    {
      "geometry": {
        "type": "Point",
        "coordinates": [
          31.239569,
          30.962841
        ]
      },
      "id": "dare-location",
      "type": "Feature",
      "properties": {
        "description": "Representative point location, village precision",
        "location_precision": "precise",
        "title": "DARE Location",
        "link": "http://pleiades.stoa.org/places/727227/dare-location"
      }
    }
  ]
}