{
  "type": "FeatureCollection",
  "title": "Thonis",
  "id": "727250",
  "bbox": [
    30.078252,
    31.314035,
    30.078252,
    31.314035
  ],
  "description": "An ancient place, cited: BAtlas 74 C2 Thonis",
  "names": [
    "Thonis"
  ],
  "features": [
    {
      "type": "Feature",
      "geometry": {
        "type": "Point",
        "coordinates": [
          30.078252,
          31.314035
        ]
      },
      "properties": {
        "description": "representative point"
      }
    },
    {
      "geometry": {
        "type": "Point",
        "coordinates": [
          30.078252,
          31.314035
        ]
      },
      "id": "darmc-location-15151",
      "type": "Feature",
      "properties": {
        "description": "1:500,000 scale representative point location digitized from the Barrington Atlas of the Greek and Roman World by the Digital Atlas of Roman and Medieval Civilizations project at Harvard University.",
        "location_precision": "precise",
        "title": "DARMC location 15151",
        "link": "http://pleiades.stoa.org/places/727250/darmc-location-15151"
      }
    }
  ]
}