{
  "type": "FeatureCollection",
  "title": "Thonis",
  "id": "727250",
  "description": "An ancient place, cited: BAtlas 74 C2 Thonis",
  "bbox": [
    30.078252,
    31.314035,
    30.078252,
    31.314035
  ],
  "reprPoint": [
    30.078252,
    31.314035
  ],
  "names": [
    "Thonis"
  ],
  "features": [
    {
      "geometry": {
        "type": "Point",
        "coordinates": [
          30.078252,
          31.314035
        ]
      },
      "id": "darmc-location-15151",
      "type": "Feature",
      "properties": {
        "description": "500K scale point location",
        "location_precision": "precise",
        "title": "DARMC location 15151",
        "link": "http://pleiades.stoa.org/places/727250/darmc-location-15151"
      }
    }
  ]
}