{
  "type": "FeatureCollection",
  "title": "Phragonis",
  "id": "727201",
  "description": "An ancient place, cited: BAtlas 74 D2 Phragonis",
  "bbox": [
    30.934522,
    31.247944,
    30.934522,
    31.247944
  ],
  "reprPoint": [
    30.934522,
    31.247944
  ],
  "names": [
    "Phragonis"
  ],
  "features": [
    {
      "geometry": {
        "type": "Point",
        "coordinates": [
          30.934522,
          31.247944
        ]
      },
      "id": "darmc-location-14265",
      "type": "Feature",
      "properties": {
        "description": "500K scale point location",
        "location_precision": "precise",
        "title": "DARMC location 14265",
        "link": "http://pleiades.stoa.org/places/727201/darmc-location-14265"
      }
    }
  ]
}