{
  "type": "FeatureCollection",
  "title": "Theater at Arykanda",
  "id": "727686421",
  "bbox": [
    30.0599552,
    36.5143106,
    30.0599552,
    36.5143106
  ],
  "description": "The Theater at Arykanda dates to the first century B.C.",
  "connectsWith": [
    "638770"
  ],
  "features": [
    {
      "type": "Feature",
      "geometry": {
        "type": "Point",
        "coordinates": [
          30.0599552,
          36.5143106
        ]
      },
      "properties": {
        "description": "representative point"
      }
    },
    {
      "geometry": {
        "type": "Point",
        "coordinates": [
          30.0599552,
          36.5143106
        ]
      },
      "id": "location-of-theater",
      "type": "Feature",
      "properties": {
        "description": "Representative location based on OpenStreetMap.",
        "location_precision": "precise",
        "title": "OSM location of theater",
        "link": "http://pleiades.stoa.org/places/727686421/location-of-theater"
      }
    }
  ]
}