{
  "type": "FeatureCollection",
  "title": "Dabigu",
  "id": "727743778",
  "bbox": [
    37.2686684,
    36.5400726,
    37.2686684,
    36.5400726
  ],
  "description": "An unwalled city mentioned in Neo-Assyrian sources that is identified with Tell Dābiq.",
  "names": [
    "Dabekon",
    "Tell Dābiq",
    "Dabigu"
  ],
  "features": [
    {
      "type": "Feature",
      "geometry": {
        "type": "Point",
        "coordinates": [
          37.2686684,
          36.5400726
        ]
      },
      "properties": {
        "description": "representative point"
      }
    },
    {
      "geometry": {
        "type": "Point",
        "coordinates": [
          37.2686684,
          36.5400726
        ]
      },
      "id": "osm-location-of-tell-dabiq",
      "type": "Feature",
      "properties": {
        "description": "Location based on OpenStreetMap",
        "location_precision": "precise",
        "title": "OSM location of Tell Dabiq",
        "link": "http://pleiades.stoa.org/places/727743778/osm-location-of-tell-dabiq"
      }
    }
  ]
}