{
  "type": "FeatureCollection",
  "title": "Greolieres Roman Milestone",
  "id": "728329646",
  "bbox": [
    6.9371705,
    43.7957307,
    6.9371705,
    43.7957307
  ],
  "description": "Location of a Roman milestone.",
  "features": [
    {
      "type": "Feature",
      "geometry": {
        "type": "Point",
        "coordinates": [
          6.9371705,
          43.7957307
        ]
      },
      "properties": {
        "description": "representative point"
      }
    },
    {
      "geometry": {
        "type": "Point",
        "coordinates": [
          6.9371705,
          43.7957307
        ]
      },
      "id": "osm-location-of-borne-milliaire",
      "type": "Feature",
      "properties": {
        "description": "Representative location based on OpenStreetMap.",
        "location_precision": "precise",
        "title": "OSM location of Borne milliaire",
        "link": "http://pleiades.stoa.org/places/728329646/osm-location-of-borne-milliaire"
      }
    }
  ]
}