{
  "type": "FeatureCollection",
  "title": "Torre dei Conti",
  "id": "728475463",
  "bbox": [
    12.4879699,
    41.8934315,
    12.4879699,
    41.8934315
  ],
  "description": "A fortified Medieval tower located in Rome, dating to AD 1238, and built by Richard Conti, brother of Pope Innocent III.",
  "connectsWith": [
    "423025"
  ],
  "features": [
    {
      "type": "Feature",
      "geometry": {
        "type": "Point",
        "coordinates": [
          12.4879699,
          41.8934315
        ]
      },
      "properties": {
        "description": "representative point"
      }
    },
    {
      "geometry": {
        "type": "Point",
        "coordinates": [
          12.4879699,
          41.8934315
        ]
      },
      "id": "osm-location",
      "type": "Feature",
      "properties": {
        "description": "Location based on OpenStreetMap",
        "location_precision": "precise",
        "title": "OSM location",
        "link": "http://pleiades.stoa.org/places/728475463/osm-location"
      }
    }
  ]
}