{
  "type": "FeatureCollection",
  "title": "Locmariaquer megaliths",
  "id": "729404980",
  "bbox": [
    -2.9511411,
    47.5724829,
    -2.9511344,
    47.5738634
  ],
  "description": "At Locmariaquer, Brittany, are the remains of a complex of Neolithic structures.",
  "features": [
    {
      "type": "Feature",
      "geometry": {
        "type": "Point",
        "coordinates": [
          -2.9511344,
          47.5724829
        ]
      },
      "properties": {
        "description": "representative point"
      }
    },
    {
      "geometry": {
        "type": "Point",
        "coordinates": [
          -2.9511344,
          47.5724829
        ]
      },
      "id": "location-of-le-grand-menhir-brise",
      "type": "Feature",
      "properties": {
        "description": "Representative location based on OpenStreetMap",
        "location_precision": "precise",
        "title": "OSM location of Le grand menhir brisé",
        "link": "http://pleiades.stoa.org/places/729404980/location-of-le-grand-menhir-brise"
      }
    },
    {
      "geometry": {
        "type": "Point",
        "coordinates": [
          -2.9511411,
          47.5738634
        ]
      },
      "id": "location-of-dolmen-du-mane-lud",
      "type": "Feature",
      "properties": {
        "description": "Representative location based on OpenStreetMap",
        "location_precision": "precise",
        "title": "OSM location of Dolmen du Mané Lud",
        "link": "http://pleiades.stoa.org/places/729404980/location-of-dolmen-du-mane-lud"
      }
    }
  ]
}