{
  "type": "FeatureCollection",
  "title": "Dhaskalio (settlement)",
  "id": "734000266",
  "bbox": [
    25.6041585,
    36.8881154,
    25.6041585,
    36.8881154
  ],
  "description": "An Early Cycladic settlement identified on the island of Daskalio in the Cyclades. This settlement is the most substantial yet known for the Early Bronze Age in the Cyclades.",
  "connectsWith": [
    "212270979"
  ],
  "features": [
    {
      "type": "Feature",
      "geometry": {
        "type": "Point",
        "coordinates": [
          25.6041585,
          36.8881154
        ]
      },
      "properties": {
        "description": "representative point"
      }
    },
    {
      "geometry": {
        "type": "Point",
        "coordinates": [
          25.6041585,
          36.8881154
        ]
      },
      "id": "osm-location-of-iiii-i1i-i-i-i3i1ioii-issiii-i-ii",
      "type": "Feature",
      "properties": {
        "description": "Representative location based on OpenStreetMap.",
        "location_precision": "precise",
        "title": "OSM location of Αρχαιολογικός Χώρος Δασκαλιού Κέρου",
        "link": "http://pleiades.stoa.org/places/734000266/osm-location-of-iiii-i1i-i-i-i3i1ioii-issiii-i-ii"
      }
    }
  ]
}