{
  "type": "FeatureCollection",
  "title": "Tell el-Ajjul",
  "id": "73662437",
  "bbox": [
    34.404297,
    31.467665,
    34.404297,
    31.467665
  ],
  "description": "Tell el-Ajjul was a fortified Bronze Age settlement located in what is now Gaza. Evidence from the site indicates economic interaction with ancient Egypt.",
  "features": [
    {
      "type": "Feature",
      "geometry": {
        "type": "Point",
        "coordinates": [
          34.404297,
          31.467665
        ]
      },
      "properties": {
        "description": "representative point"
      }
    },
    {
      "geometry": {
        "type": "Point",
        "coordinates": [
          34.404297,
          31.467665
        ]
      },
      "id": "imagery-location-of-tell-el-ajjul",
      "type": "Feature",
      "properties": {
        "description": "Imagery location of Tell el-Ajjul based on coordinates derived from GeoHack.",
        "location_precision": "precise",
        "title": "Imagery location of Tell el-Ajjul",
        "link": "http://pleiades.stoa.org/places/73662437/imagery-location-of-tell-el-ajjul"
      }
    }
  ]
}