{
  "type": "FeatureCollection",
  "title": "Akanthonpolis",
  "id": "736884",
  "bbox": [
    31.248329,
    29.511769,
    31.248329,
    29.511769
  ],
  "description": "An ancient place, cited: BAtlas 75 E1 Akanthonpolis",
  "connectsWith": [
    "727172"
  ],
  "names": [
    "Akanthonpolis"
  ],
  "features": [
    {
      "type": "Feature",
      "geometry": {
        "type": "Point",
        "coordinates": [
          31.248329,
          29.511769
        ]
      },
      "properties": {
        "description": "representative point"
      }
    },
    {
      "geometry": {
        "type": "Point",
        "coordinates": [
          31.248329,
          29.511769
        ]
      },
      "id": "darmc-location-11266",
      "type": "Feature",
      "properties": {
        "description": "500K scale point location",
        "location_precision": "precise",
        "title": "DARMC location 11266",
        "link": "http://pleiades.stoa.org/places/736884/darmc-location-11266"
      }
    }
  ]
}