{
  "type": "FeatureCollection",
  "title": "Oxyrhynchus/Pemje",
  "id": "736983",
  "description": "A city of Upper Egypt, Oxyrhynchus/Pemje is particularly well known as an archaeological site that has produced important papyrus manuscripts of ancient texts.",
  "bbox": [
    30.65172,
    28.542574,
    30.65172,
    28.542574
  ],
  "reprPoint": [
    30.65172,
    28.542574
  ],
  "names": [
    "Oxyrhynchus",
    "Pemje"
  ],
  "features": [
    {
      "geometry": {
        "type": "Point",
        "coordinates": [
          30.597609,
          28.808971
        ]
      },
      "id": "darmc-location-5420",
      "type": "Feature",
      "properties": {
        "description": "5M scale point location",
        "location_precision": "precise",
        "title": "DARMC location 5420",
        "link": "http://pleiades.stoa.org/places/736983/darmc-location-5420"
      }
    },
    {
      "geometry": {
        "type": "Point",
        "coordinates": [
          30.654809,
          28.537007
        ]
      },
      "id": "darmc-location-5421",
      "type": "Feature",
      "properties": {
        "description": "500K scale point location",
        "location_precision": "precise",
        "title": "DARMC location 5421",
        "link": "http://pleiades.stoa.org/places/736983/darmc-location-5421"
      }
    },
    {
      "geometry": {
        "type": "Point",
        "coordinates": [
          30.65172,
          28.542574
        ]
      },
      "id": "dare-location",
      "type": "Feature",
      "properties": {
        "description": "Representative point location, site precision",
        "location_precision": "precise",
        "title": "DARE Location",
        "link": "http://pleiades.stoa.org/places/736983/dare-location"
      }
    }
  ]
}