{
  "type": "FeatureCollection",
  "title": "Gebel el-Nur",
  "id": "736914",
  "description": "An ancient place, cited: BAtlas 75 E3 Gebel el-Nur",
  "bbox": [
    31.028491,
    28.953888,
    31.028491,
    28.953888
  ],
  "reprPoint": [
    31.028491,
    28.953888
  ],
  "features": [
    {
      "geometry": {
        "type": "Point",
        "coordinates": [
          31.028491,
          28.953888
        ]
      },
      "id": "darmc-location-22501",
      "type": "Feature",
      "properties": {
        "description": "500K scale point location",
        "location_precision": "precise",
        "title": "DARMC location 22501",
        "link": "http://pleiades.stoa.org/places/736914/darmc-location-22501"
      }
    }
  ]
}