{
  "type": "FeatureCollection",
  "title": "Hwt-nsw",
  "id": "736925",
  "description": "An ancient place, cited: BAtlas 75 D3 Hwt-nsw",
  "bbox": [
    30.851566,
    28.594029,
    30.851566,
    28.594029
  ],
  "reprPoint": [
    30.851566,
    28.594029
  ],
  "names": [
    "Hwt-nsw"
  ],
  "features": [
    {
      "geometry": {
        "type": "Point",
        "coordinates": [
          30.851566,
          28.594029
        ]
      },
      "id": "darmc-location-22809",
      "type": "Feature",
      "properties": {
        "description": "500K scale point location",
        "location_precision": "precise",
        "title": "DARMC location 22809",
        "link": "http://pleiades.stoa.org/places/736925/darmc-location-22809"
      }
    }
  ]
}