{
  "type": "FeatureCollection",
  "title": "Moi(e)thymis",
  "id": "736968",
  "bbox": [
    31.167999,
    29.376311,
    31.167999,
    29.376311
  ],
  "description": "An ancient place, cited: BAtlas 75 E2 Moi(e)thymis",
  "names": [
    " Moiethymis",
    " Moithymis",
    "Meidum"
  ],
  "features": [
    {
      "type": "Feature",
      "geometry": {
        "type": "Point",
        "coordinates": [
          31.167999,
          29.376311
        ]
      },
      "properties": {
        "description": "representative point"
      }
    },
    {
      "geometry": {
        "type": "Point",
        "coordinates": [
          31.167999,
          29.376311
        ]
      },
      "id": "darmc-location-13769",
      "type": "Feature",
      "properties": {
        "description": "500K scale point location",
        "location_precision": "precise",
        "title": "DARMC location 13769",
        "link": "http://pleiades.stoa.org/places/736968/darmc-location-13769"
      }
    }
  ]
}