{
  "type": "FeatureCollection",
  "title": "el-Lahun",
  "id": "736953",
  "description": "An ancient place, cited: BAtlas 75 D2 el-Lahun",
  "bbox": [
    30.966002,
    29.234383,
    30.970699,
    29.236192
  ],
  "reprPoint": [
    30.9683505,
    29.2352875
  ],
  "features": [
    {
      "geometry": {
        "type": "Point",
        "coordinates": [
          30.966002,
          29.234383
        ]
      },
      "id": "darmc-location-26295",
      "type": "Feature",
      "properties": {
        "description": "500K scale point location",
        "location_precision": "precise",
        "title": "DARMC location 26295",
        "link": "http://pleiades.stoa.org/places/736953/darmc-location-26295"
      }
    },
    {
      "geometry": {
        "type": "Point",
        "coordinates": [
          30.970699,
          29.236192
        ]
      },
      "id": "dare-location",
      "type": "Feature",
      "properties": {
        "description": "Representative point location, site precision",
        "location_precision": "precise",
        "title": "DARE Location",
        "link": "http://pleiades.stoa.org/places/736953/dare-location"
      }
    }
  ]
}