{
  "type": "FeatureCollection",
  "title": "Moeris L.",
  "id": "736967",
  "description": "Moeris Lacus (Lake Moeris) was an ancient lake in the northwestern part of the Fayuum Oasis in Egypt; its surviving modern remnant is Birket Qarun.",
  "bbox": [
    30.580833,
    29.453611,
    30.580833,
    29.453611
  ],
  "reprPoint": [
    30.580833,
    29.453611
  ],
  "names": [
    "Moeris L."
  ],
  "features": [
    {
      "geometry": {
        "type": "Point",
        "coordinates": [
          30.580833,
          29.453611
        ]
      },
      "id": "location-of-moeris-l",
      "type": "Feature",
      "properties": {
        "description": "verified in Google Earth 2013.",
        "location_precision": "precise",
        "title": "location of Moeris L.",
        "link": "http://pleiades.stoa.org/places/736967/location-of-moeris-l"
      }
    }
  ]
}