{
  "type": "FeatureCollection",
  "title": "Mouchis",
  "id": "736970",
  "bbox": [
    31.027714,
    29.074883,
    31.027714,
    29.074883
  ],
  "description": "An ancient place, cited: BAtlas 75 E2 Mouchis",
  "connectsWith": [
    "736921"
  ],
  "names": [
    "Mouchis"
  ],
  "features": [
    {
      "type": "Feature",
      "geometry": {
        "type": "Point",
        "coordinates": [
          31.027714,
          29.074883
        ]
      },
      "properties": {
        "description": "representative point"
      }
    },
    {
      "geometry": {
        "type": "Point",
        "coordinates": [
          31.027714,
          29.074883
        ]
      },
      "id": "darmc-location-5000",
      "type": "Feature",
      "properties": {
        "description": "500K scale point location",
        "location_precision": "precise",
        "title": "DARMC location 5000",
        "link": "http://pleiades.stoa.org/places/736970/darmc-location-5000"
      }
    }
  ]
}