{
  "type": "FeatureCollection",
  "title": "Parembole",
  "id": "736993",
  "description": "An ancient place, cited: BAtlas 75 E2 Parembole",
  "bbox": [
    31.238111,
    29.311376,
    31.238111,
    29.311376
  ],
  "reprPoint": [
    31.238111,
    29.311376
  ],
  "names": [
    "Parembole"
  ],
  "features": [
    {
      "geometry": {
        "type": "Point",
        "coordinates": [
          31.238111,
          29.311376
        ]
      },
      "id": "darmc-location-5446",
      "type": "Feature",
      "properties": {
        "description": "500K scale point location",
        "location_precision": "precise",
        "title": "DARMC location 5446",
        "link": "http://pleiades.stoa.org/places/736993/darmc-location-5446"
      }
    }
  ]
}