{
  "type": "FeatureCollection",
  "title": "Euhemereia",
  "id": "736909",
  "description": "An ancient place, cited: BAtlas 75 D2 Euhemereia",
  "bbox": [
    30.533289,
    29.383296,
    30.533289,
    29.383296
  ],
  "reprPoint": [
    30.533289,
    29.383296
  ],
  "names": [
    "Qasr el-Banat",
    "Euhemereia"
  ],
  "features": [
    {
      "geometry": {
        "type": "Point",
        "coordinates": [
          30.533289,
          29.383296
        ]
      },
      "id": "darmc-location-12402",
      "type": "Feature",
      "properties": {
        "description": "500K scale point location",
        "location_precision": "precise",
        "title": "DARMC location 12402",
        "link": "http://pleiades.stoa.org/places/736909/darmc-location-12402"
      }
    }
  ]
}