{
  "type": "FeatureCollection",
  "title": "Panarachthis/Pinarachthis",
  "id": "736989",
  "description": "An ancient place, cited: BAtlas 75 E1 Panarachthis/Pinarachthis",
  "bbox": [
    31.246691,
    29.693885,
    31.246691,
    29.693885
  ],
  "reprPoint": [
    31.246691,
    29.693885
  ],
  "names": [
    "Panarachthis",
    "Pinarachthis"
  ],
  "features": [
    {
      "geometry": {
        "type": "Point",
        "coordinates": [
          31.246691,
          29.693885
        ]
      },
      "id": "darmc-location-14114",
      "type": "Feature",
      "properties": {
        "description": "500K scale point location",
        "location_precision": "precise",
        "title": "DARMC location 14114",
        "link": "http://pleiades.stoa.org/places/736989/darmc-location-14114"
      }
    }
  ]
}