{
  "type": "FeatureCollection",
  "title": "Krokodilopolis/Ptolemais Euergetis",
  "id": "736948",
  "description": "An ancient city in the Heptanomis and the capital of Arsinoites nome. The ancient Egyptian name of the site was Shedyet and in Pharaonic times it was a major cult center for the god Sobek.",
  "bbox": [
    30.835832,
    29.320878,
    30.835832,
    29.320878
  ],
  "reprPoint": [
    30.835832,
    29.320878
  ],
  "names": [
    "Medinet el-Fayum",
    "Krokodeilon polis",
    "Ptolemais Euergetis",
    "Arsinoe",
    "Krialon",
    "Kimān Faris",
    "Mīt Fāris",
    "Arsinoe",
    "šdt",
    "Arsinoitōn polis",
    "Arsinoitēs",
    "Arsinoïtēs",
    "Arsinoitōn Polis",
    "Tpolis Piam",
    "Kīmān Fāris",
    "Arsinoē",
    "Arsinoë",
    "Krokodilopolis",
    "Crocodilopolis",
    "Krokodeilōnpolis",
    "Ptolemais Euergetis",
    "Madīnat al-Fayyūm",
    "al-Fayyum",
    "al-Fayyūm",
    "il-Fayyūm",
    "Sobektempel",
    "Krokodeilōn Polis",
    "Krokodeilōn polis"
  ],
  "features": [
    {
      "geometry": {
        "type": "Point",
        "coordinates": [
          30.844081,
          29.309049
        ]
      },
      "id": "darmc-location-4229",
      "type": "Feature",
      "properties": {
        "description": "500K scale point location",
        "location_precision": "precise",
        "title": "DARMC location 4229",
        "link": "http://pleiades.stoa.org/places/736948/darmc-location-4229"
      }
    },
    {
      "geometry": {
        "type": "Point",
        "coordinates": [
          30.835832,
          29.320878
        ]
      },
      "id": "dare-location",
      "type": "Feature",
      "properties": {
        "description": "Representative point location, village precision",
        "location_precision": "precise",
        "title": "DARE Location",
        "link": "http://pleiades.stoa.org/places/736948/dare-location"
      }
    }
  ]
}