{
  "type": "FeatureCollection",
  "title": "Mnachis",
  "id": "736966",
  "description": "An ancient place, cited: BAtlas 75 D4 Mnachis",
  "bbox": [
    30.71369,
    28.303829,
    30.71369,
    28.303829
  ],
  "reprPoint": [
    30.71369,
    28.303829
  ],
  "names": [
    "Mnachis"
  ],
  "features": [
    {
      "geometry": {
        "type": "Point",
        "coordinates": [
          30.71369,
          28.303829
        ]
      },
      "id": "darmc-location-13763",
      "type": "Feature",
      "properties": {
        "description": "500K scale point location",
        "location_precision": "precise",
        "title": "DARMC location 13763",
        "link": "http://pleiades.stoa.org/places/736966/darmc-location-13763"
      }
    }
  ]
}