{
  "type": "FeatureCollection",
  "title": "Tanis",
  "id": "737069",
  "bbox": [
    31.031412,
    29.393521,
    31.031412,
    29.393521
  ],
  "description": "An ancient settlement of the eastern Fayoum, administratively in the ancient Arsinoite nome, that is well-documented in the papyri. The site has been identified with a village known as Manashinshana at the beginning of the 20th century, which is probably to be identified with a small settlement known locally today as Shanashinshana.",
  "names": [
    "Shinshana",
    "Shana",
    "Tell Shinsana",
    "Manashinshana",
    "Shanashinshana",
    "Tanis"
  ],
  "features": [
    {
      "type": "Feature",
      "geometry": {
        "type": "Point",
        "coordinates": [
          31.031412,
          29.393521
        ]
      },
      "properties": {
        "description": "representative point"
      }
    },
    {
      "geometry": {
        "type": "Point",
        "coordinates": [
          31.031412,
          29.393521
        ]
      },
      "id": "imagery-location-of-modern-shanashinshana",
      "type": "Feature",
      "properties": {
        "description": "After Jensen 2019, pages 132-133",
        "location_precision": "precise",
        "title": "Imagery location of modern Shanashinshana",
        "link": "http://pleiades.stoa.org/places/737069/imagery-location-of-modern-shanashinshana"
      }
    }
  ]
}