{
  "type": "FeatureCollection",
  "title": "Soknopaiou Nesos",
  "id": "737053",
  "description": "An ancient settlement in the Egyptian Fayum, known today as Dime.",
  "bbox": [
    30.668862,
    29.534945,
    30.668862,
    29.534945
  ],
  "reprPoint": [
    30.668862,
    29.534945
  ],
  "names": [
    "Dimeh",
    "Soknopaiou Nesos"
  ],
  "features": [
    {
      "geometry": {
        "type": "Point",
        "coordinates": [
          30.66897,
          29.532004
        ]
      },
      "id": "darmc-location-14814",
      "type": "Feature",
      "properties": {
        "description": "500K scale point location",
        "location_precision": "precise",
        "title": "DARMC location 14814",
        "link": "http://pleiades.stoa.org/places/737053/darmc-location-14814"
      }
    },
    {
      "geometry": {
        "type": "Point",
        "coordinates": [
          30.668862,
          29.534945
        ]
      },
      "id": "dare-location",
      "type": "Feature",
      "properties": {
        "description": "Representative point location, site precision",
        "location_precision": "precise",
        "title": "DARE Location",
        "link": "http://pleiades.stoa.org/places/737053/dare-location"
      }
    }
  ]
}