{
  "type": "FeatureCollection",
  "title": "Perkethaut/Philagris?",
  "id": "737001",
  "bbox": [
    30.607072,
    29.27687,
    30.607072,
    29.27687
  ],
  "description": "An ancient place, cited: BAtlas 75 D2 Perkethaut/Philagris?",
  "names": [
    "Perkethaut",
    "Philagris",
    "Hamuli"
  ],
  "features": [
    {
      "type": "Feature",
      "geometry": {
        "type": "Point",
        "coordinates": [
          30.607072,
          29.27687
        ]
      },
      "properties": {
        "description": "representative point"
      }
    },
    {
      "geometry": {
        "type": "Point",
        "coordinates": [
          30.607072,
          29.27687
        ]
      },
      "id": "darmc-location-14191",
      "type": "Feature",
      "properties": {
        "description": "500K scale point location",
        "location_precision": "precise",
        "title": "DARMC location 14191",
        "link": "http://pleiades.stoa.org/places/737001/darmc-location-14191"
      }
    }
  ]
}