{
  "type": "FeatureCollection",
  "title": "Phentemin",
  "id": "737006",
  "description": "An ancient place, cited: BAtlas 75 D2 Phentemin",
  "bbox": [
    30.777929,
    29.383139,
    30.777929,
    29.383139
  ],
  "reprPoint": [
    30.777929,
    29.383139
  ],
  "names": [
    "Phentemin"
  ],
  "features": [
    {
      "geometry": {
        "type": "Point",
        "coordinates": [
          30.777929,
          29.383139
        ]
      },
      "id": "darmc-location-14238",
      "type": "Feature",
      "properties": {
        "description": "500K scale point location",
        "location_precision": "precise",
        "title": "DARMC location 14238",
        "link": "http://pleiades.stoa.org/places/737006/darmc-location-14238"
      }
    }
  ]
}