{
  "type": "FeatureCollection",
  "title": "Temsiris",
  "id": "737076",
  "bbox": [
    30.694751,
    28.143269,
    30.694751,
    28.143269
  ],
  "description": "An ancient place, cited: BAtlas 75 D4 Temsiris",
  "names": [
    "Temsiris"
  ],
  "features": [
    {
      "type": "Feature",
      "geometry": {
        "type": "Point",
        "coordinates": [
          30.694751,
          28.143269
        ]
      },
      "properties": {
        "description": "representative point"
      }
    },
    {
      "geometry": {
        "type": "Point",
        "coordinates": [
          30.694751,
          28.143269
        ]
      },
      "id": "darmc-location-15070",
      "type": "Feature",
      "properties": {
        "description": "500K scale point location",
        "location_precision": "precise",
        "title": "DARMC location 15070",
        "link": "http://pleiades.stoa.org/places/737076/darmc-location-15070"
      }
    }
  ]
}