{
  "type": "FeatureCollection",
  "title": "Techtho",
  "id": "737073",
  "description": "An ancient place, cited: BAtlas 75 D3 Techtho",
  "bbox": [
    30.91132,
    28.769908,
    30.91132,
    28.769908
  ],
  "reprPoint": [
    30.91132,
    28.769908
  ],
  "names": [
    "Dashtut",
    "Techtho"
  ],
  "features": [
    {
      "geometry": {
        "type": "Point",
        "coordinates": [
          30.91132,
          28.769908
        ]
      },
      "id": "darmc-location-15036",
      "type": "Feature",
      "properties": {
        "description": "500K scale point location",
        "location_precision": "precise",
        "title": "DARMC location 15036",
        "link": "http://pleiades.stoa.org/places/737073/darmc-location-15036"
      }
    }
  ]
}