{
  "type": "FeatureCollection",
  "title": "Baths of the Old Convent, Tharros",
  "id": "737899462",
  "bbox": [
    8.4407676,
    39.8724269,
    8.4407676,
    39.8724269
  ],
  "description": "Roman baths at Tharros known as the \"Baths of the Old Convent\".",
  "connectsWith": [
    "472032"
  ],
  "features": [
    {
      "type": "Feature",
      "geometry": {
        "type": "Point",
        "coordinates": [
          8.4407676,
          39.8724269
        ]
      },
      "properties": {
        "description": "representative point"
      }
    },
    {
      "geometry": {
        "type": "Point",
        "coordinates": [
          8.4407676,
          39.8724269
        ]
      },
      "id": "osm-location-of-thermal-baths-n-2",
      "type": "Feature",
      "properties": {
        "description": "Representative location based on OpenStreetMap",
        "location_precision": "precise",
        "title": "OSM location of thermal baths n. 2",
        "link": "http://pleiades.stoa.org/places/737899462/osm-location-of-thermal-baths-n-2"
      }
    }
  ]
}