{
  "type": "FeatureCollection",
  "title": "Tell ej-Judeideh",
  "id": "738083701",
  "bbox": [
    34.9099784,
    31.6333976,
    34.9099784,
    31.6333976
  ],
  "description": "A tell located southeast of Gath in Israel that has been identified with the biblical Moresheth-Gath.",
  "features": [
    {
      "type": "Feature",
      "geometry": {
        "type": "Point",
        "coordinates": [
          34.9099784,
          31.6333976
        ]
      },
      "properties": {
        "description": "representative point"
      }
    },
    {
      "geometry": {
        "type": "Point",
        "coordinates": [
          34.9099784,
          31.6333976
        ]
      },
      "id": "osm-location-of-goded-mound",
      "type": "Feature",
      "properties": {
        "description": "Representative location based on OpenStreetMap",
        "location_precision": "precise",
        "title": "OSM location of Goded mound",
        "link": "http://pleiades.stoa.org/places/738083701/osm-location-of-goded-mound"
      }
    }
  ]
}