{
  "type": "FeatureCollection",
  "title": "Qaryat al-Lak",
  "id": "741318296",
  "bbox": [
    43.263063,
    36.299303,
    43.263063,
    36.299303
  ],
  "description": "Qaryat al-Lak (formerly called Tulul al-Lak) is a small village in northern Iraq that is located between the Assyrian cities Nimrud and Mosul. The modern village is built on top of the ruin mound.  The ancient name of the settlement is not known.",
  "names": [
    "Tulul al-Lak",
    "Qaryat al-Lak"
  ],
  "features": [
    {
      "type": "Feature",
      "geometry": {
        "type": "Point",
        "coordinates": [
          43.263063,
          36.299303
        ]
      },
      "properties": {
        "description": "representative point"
      }
    },
    {
      "geometry": {
        "type": "Point",
        "coordinates": [
          43.263063,
          36.299303
        ]
      },
      "id": "osm-location-of-qaryat-al-lak",
      "type": "Feature",
      "properties": {
        "description": "Location based on OpenStreetMap",
        "location_precision": "precise",
        "title": "OSM Location of Qaryat al Lak",
        "link": "http://pleiades.stoa.org/places/741318296/osm-location-of-qaryat-al-lak"
      }
    }
  ]
}