{
  "type": "FeatureCollection",
  "title": "Nestou Epoikion",
  "id": "741531",
  "bbox": [
    30.5,
    29.0,
    31.0,
    29.5
  ],
  "description": "An ancient village or region in the Arsinoite nome in Egypt, mentioned in documentary papyri, whose precise location cannot be determined today.",
  "connectsWith": [
    "736893"
  ],
  "names": [
    "Nestou Epoikion"
  ],
  "features": [
    {
      "type": "Feature",
      "geometry": {
        "type": "Point",
        "coordinates": [
          30.75,
          29.25
        ]
      },
      "properties": {
        "description": "representative point"
      }
    }
  ]
}