{
  "type": "FeatureCollection",
  "title": "Pyla-Kokkinokremos",
  "id": "741754494",
  "bbox": [
    33.7026009,
    34.9850468,
    33.7026009,
    34.9850468
  ],
  "description": "A late Bronze Age settlement on Cyprus, abandoned after a brief occupation.",
  "connectsWith": [
    "707498"
  ],
  "features": [
    {
      "type": "Feature",
      "geometry": {
        "type": "Point",
        "coordinates": [
          33.7026009,
          34.9850468
        ]
      },
      "properties": {
        "description": "representative point"
      }
    },
    {
      "geometry": {
        "type": "Point",
        "coordinates": [
          33.7026009,
          34.9850468
        ]
      },
      "id": "pyla-kokkinokremos",
      "type": "Feature",
      "properties": {
        "description": "Point based on an OpenStreetMap node representing Pyla-Kokkinokremos after Wikidata.",
        "location_precision": "precise",
        "title": "OSM location of Pyla-Kokkinokremos",
        "link": "http://pleiades.stoa.org/places/741754494/pyla-kokkinokremos"
      }
    }
  ]
}