{
  "type": "FeatureCollection",
  "title": "Torre del Berrueco",
  "id": "741862948",
  "description": "A Spanish village and castle located in the west of Jaén that belonged to the kingdom of Alfonso X (thirteenth century). The site is now known as El Berrueco, in the municipality of Torredelcampo.",
  "bbox": [
    -3.9389776,
    37.8652854,
    -3.9389776,
    37.8652854
  ],
  "reprPoint": [
    -3.9389776,
    37.8652854
  ],
  "names": [
    "Torre del Berrueco",
    "El Berrueco"
  ],
  "features": [
    {
      "geometry": {
        "type": "Point",
        "coordinates": [
          -3.9389776,
          37.8652854
        ]
      },
      "id": "osm-location-of-modern-el-berrueco",
      "type": "Feature",
      "properties": {
        "description": "Location based on OpenStreetMap",
        "location_precision": "precise",
        "title": "OSM location of modern El Berrueco",
        "link": "http://pleiades.stoa.org/places/741862948/osm-location-of-modern-el-berrueco"
      }
    }
  ]
}