{
  "type": "FeatureCollection",
  "title": "Western necropolis at Egnatia/Gnathia",
  "id": "742996155",
  "bbox": [
    17.3869067,
    40.8853293,
    17.3869067,
    40.8853293
  ],
  "description": "The western necropolis at Egnatia/Gnathia includes some tombs of the Messapian culture dating from the middle of the fourth to the second centuries B.C.",
  "connectsWith": [
    "442573"
  ],
  "features": [
    {
      "type": "Feature",
      "geometry": {
        "type": "Point",
        "coordinates": [
          17.3869067,
          40.8853293
        ]
      },
      "properties": {
        "description": "representative point"
      }
    },
    {
      "geometry": {
        "type": "Point",
        "coordinates": [
          17.3869067,
          40.8853293
        ]
      },
      "id": "location-of-necropolis",
      "type": "Feature",
      "properties": {
        "description": "Representative location based on OpenStreetMap",
        "location_precision": "precise",
        "title": "OSM location of Western Necropolis",
        "link": "http://pleiades.stoa.org/places/742996155/location-of-necropolis"
      }
    }
  ]
}