{
  "type": "FeatureCollection",
  "title": "Ponte di Traiano",
  "id": "746490963",
  "bbox": [
    12.9505568,
    41.5033601,
    12.9505568,
    41.5033601
  ],
  "description": "A Trajanic bridge along the Via Appia that crosses the fosso Striscia.",
  "connectsWith": [
    "356966898"
  ],
  "features": [
    {
      "type": "Feature",
      "geometry": {
        "type": "Point",
        "coordinates": [
          12.9505568,
          41.5033601
        ]
      },
      "properties": {
        "description": "representative point"
      }
    },
    {
      "geometry": {
        "type": "Point",
        "coordinates": [
          12.9505568,
          41.5033601
        ]
      },
      "id": "location-of-roman-bridge",
      "type": "Feature",
      "properties": {
        "description": "Representative location based on OpenStreetMap.",
        "location_precision": "precise",
        "title": "OSM location of Ponte Traiano",
        "link": "http://pleiades.stoa.org/places/746490963/location-of-roman-bridge"
      }
    }
  ]
}