{
  "type": "FeatureCollection",
  "title": "House of the Painters at Work",
  "id": "746630758",
  "bbox": [
    14.4897852,
    40.7512378,
    14.4897852,
    40.7512378
  ],
  "description": "The House of the Painters at Work or Casa dei pittori al lavoro is a ruined domus at Pompeii that was undergoing renovations and repairs at the time of the city's final destruction.",
  "connectsWith": [
    "433032",
    "680072866"
  ],
  "names": [
    "House of the Painters at Work",
    "Casa del Pittori al Lavoro"
  ],
  "features": [
    {
      "type": "Feature",
      "geometry": {
        "type": "Point",
        "coordinates": [
          14.4897852,
          40.7512378
        ]
      },
      "properties": {
        "description": "representative point"
      }
    },
    {
      "geometry": {
        "type": "Point",
        "coordinates": [
          14.4897852,
          40.7512378
        ]
      },
      "id": "osm-location-of-house-of-the-painters-at-work",
      "type": "Feature",
      "properties": {
        "description": "Representative location based on OpenStreetMap",
        "location_precision": "precise",
        "title": "OSM location of House of the Painters at Work",
        "link": "http://pleiades.stoa.org/places/746630758/osm-location-of-house-of-the-painters-at-work"
      }
    }
  ]
}