{
  "type": "FeatureCollection",
  "title": "Ain Nagila",
  "id": "746707",
  "description": "An ancient place, cited: BAtlas 76 D4 Ain Nagila",
  "bbox": [
    33.830398,
    28.69837,
    33.830398,
    28.69837
  ],
  "reprPoint": [
    33.830398,
    28.69837
  ],
  "features": [
    {
      "geometry": {
        "type": "Point",
        "coordinates": [
          33.830398,
          28.69837
        ]
      },
      "id": "darmc-location-4989",
      "type": "Feature",
      "properties": {
        "description": "500K scale point location",
        "location_precision": "precise",
        "title": "DARMC location 4989",
        "link": "http://pleiades.stoa.org/places/746707/darmc-location-4989"
      }
    }
  ]
}