{
  "type": "FeatureCollection",
  "title": "Jebel Serbal",
  "id": "746752",
  "description": "An ancient place, cited: BAtlas 76 D4 Jebel Serbal",
  "bbox": [
    33.645944,
    28.650264,
    33.645944,
    28.650264
  ],
  "reprPoint": [
    33.645944,
    28.650264
  ],
  "features": [
    {
      "geometry": {
        "type": "Point",
        "coordinates": [
          33.645944,
          28.650264
        ]
      },
      "id": "darmc-location-18069",
      "type": "Feature",
      "properties": {
        "description": "500K scale point location",
        "location_precision": "precise",
        "title": "DARMC location 18069",
        "link": "http://pleiades.stoa.org/places/746752/darmc-location-18069"
      }
    }
  ]
}