{
  "type": "FeatureCollection",
  "title": "Fuweileh el-Gharbiyeh",
  "id": "746737",
  "bbox": [
    35.514218,
    30.011393,
    35.514218,
    30.011393
  ],
  "description": "An ancient place, cited: BAtlas 76 G1 Fuweileh el-Gharbiyeh",
  "features": [
    {
      "type": "Feature",
      "geometry": {
        "type": "Point",
        "coordinates": [
          35.514218,
          30.011393
        ]
      },
      "properties": {
        "description": "representative point"
      }
    },
    {
      "geometry": {
        "type": "Point",
        "coordinates": [
          35.514218,
          30.011393
        ]
      },
      "id": "darmc-location-22458",
      "type": "Feature",
      "properties": {
        "description": "500K scale point location",
        "location_precision": "precise",
        "title": "DARMC location 22458",
        "link": "http://pleiades.stoa.org/places/746737/darmc-location-22458"
      }
    }
  ]
}