{
  "type": "FeatureCollection",
  "title": "Deir Umm Butme",
  "id": "746731",
  "bbox": [
    33.848183,
    28.347342,
    33.848183,
    28.347342
  ],
  "description": "An ancient place, cited: BAtlas 76 D5 Deir Umm Butme",
  "features": [
    {
      "type": "Feature",
      "geometry": {
        "type": "Point",
        "coordinates": [
          33.848183,
          28.347342
        ]
      },
      "properties": {
        "description": "representative point"
      }
    },
    {
      "geometry": {
        "type": "Point",
        "coordinates": [
          33.848183,
          28.347342
        ]
      },
      "id": "darmc-location-15193",
      "type": "Feature",
      "properties": {
        "description": "500K scale point location",
        "location_precision": "precise",
        "title": "DARMC location 15193",
        "link": "http://pleiades.stoa.org/places/746731/darmc-location-15193"
      }
    }
  ]
}