{
  "type": "FeatureCollection",
  "title": "Khirbet Umm Ras",
  "id": "746772",
  "description": "An ancient place, cited: BAtlas 76 G1 Khirbet Umm Ras",
  "bbox": [
    35.476977,
    30.101833,
    35.476977,
    30.101833
  ],
  "reprPoint": [
    35.476977,
    30.101833
  ],
  "features": [
    {
      "geometry": {
        "type": "Point",
        "coordinates": [
          35.476977,
          30.101833
        ]
      },
      "id": "darmc-location-20384",
      "type": "Feature",
      "properties": {
        "description": "500K scale point location",
        "location_precision": "precise",
        "title": "DARMC location 20384",
        "link": "http://pleiades.stoa.org/places/746772/darmc-location-20384"
      }
    }
  ]
}