{
  "type": "FeatureCollection",
  "title": "Nuweiba",
  "id": "746788",
  "description": "An ancient place, cited: BAtlas 76 F4 Nuweiba",
  "bbox": [
    34.663554,
    29.036093,
    34.663554,
    29.036093
  ],
  "reprPoint": [
    34.663554,
    29.036093
  ],
  "features": [
    {
      "geometry": {
        "type": "Point",
        "coordinates": [
          34.663554,
          29.036093
        ]
      },
      "id": "darmc-location-20539",
      "type": "Feature",
      "properties": {
        "description": "500K scale point location",
        "location_precision": "precise",
        "title": "DARMC location 20539",
        "link": "http://pleiades.stoa.org/places/746788/darmc-location-20539"
      }
    }
  ]
}