{
  "type": "FeatureCollection",
  "title": "Wadi Nukhaya",
  "id": "746837",
  "description": "An ancient place, cited: BAtlas 76 G1 Wadi Nukhaya",
  "bbox": [
    35.264022,
    30.00071,
    35.264022,
    30.00071
  ],
  "reprPoint": [
    35.264022,
    30.00071
  ],
  "features": [
    {
      "geometry": {
        "type": "Point",
        "coordinates": [
          35.264022,
          30.00071
        ]
      },
      "id": "darmc-location-15457",
      "type": "Feature",
      "properties": {
        "description": "500K scale point location",
        "location_precision": "precise",
        "title": "DARMC location 15457",
        "link": "http://pleiades.stoa.org/places/746837/darmc-location-15457"
      }
    }
  ]
}