{
  "type": "FeatureCollection",
  "title": "Tayyib al-Ism",
  "id": "746818",
  "description": "An ancient place, cited: BAtlas 76 F4 Tayyib al-Ism",
  "bbox": [
    34.815729,
    28.532066,
    34.815729,
    28.532066
  ],
  "reprPoint": [
    34.815729,
    28.532066
  ],
  "features": [
    {
      "geometry": {
        "type": "Point",
        "coordinates": [
          34.815729,
          28.532066
        ]
      },
      "id": "darmc-location-25030",
      "type": "Feature",
      "properties": {
        "description": "500K scale point location",
        "location_precision": "precise",
        "title": "DARMC location 25030",
        "link": "http://pleiades.stoa.org/places/746818/darmc-location-25030"
      }
    }
  ]
}