{
  "type": "FeatureCollection",
  "title": "Victuriacus",
  "id": "749202987",
  "description": "A fortified place mentioned in Gregory of Tours, History of the Franks AD 532",
  "bbox": [
    4.62617,
    48.7462,
    4.62617,
    48.7462
  ],
  "reprPoint": [
    4.62617,
    48.7462
  ],
  "names": [
    "Victuriacus"
  ],
  "features": [
    {
      "geometry": {
        "type": "Point",
        "coordinates": [
          4.62617,
          48.7462
        ]
      },
      "id": "vitry-en-perthois",
      "type": "Feature",
      "properties": {
        "description": "Center point of commune Vitry-en-Perthois: France, departement Marne, arrondissement Vitry-le-François, canton Vitry-le-François-Est. Vitry-en-Perthois is formerly known as Vitry-le-Brûlé.",
        "location_precision": "precise",
        "title": "Vitry-en-Perthois",
        "link": "http://pleiades.stoa.org/places/749202987/vitry-en-perthois"
      }
    }
  ]
}