{
  "type": "FeatureCollection",
  "title": "Via Labicana",
  "id": "74935822",
  "bbox": [
    12.486137,
    41.742213,
    13.158962,
    41.895779
  ],
  "description": "An ancient Roman road connecting Rome and Labicum.",
  "names": [
    "via Labicana"
  ],
  "features": [
    {
      "type": "Feature",
      "geometry": {
        "type": "Point",
        "coordinates": [
          12.73293875,
          41.81788275
        ]
      },
      "properties": {
        "description": "representative point"
      }
    }
  ]
}