{
  "type": "FeatureCollection",
  "title": "Via Labicana",
  "id": "74935822",
  "bbox": [
    12.486137,
    41.742213,
    13.158962,
    41.895779
  ],
  "description": "An ancient Roman road connecting Rome and Labicum.",
  "features": [
    {
      "type": "Feature",
      "geometry": {
        "type": "Point",
        "coordinates": [
          12.7390181019,
          41.8275111685
        ]
      },
      "properties": {
        "description": "representative point"
      }
    }
  ]
}