{
  "type": "FeatureCollection",
  "title": "Tineida",
  "id": "750429666",
  "bbox": [
    29.333603,
    25.501066,
    29.333603,
    25.501066
  ],
  "description": "The ancient village of Tineida, in Egypt's Dakhleh Oasis.",
  "connectsWith": [
    "776172"
  ],
  "features": [
    {
      "type": "Feature",
      "geometry": {
        "type": "Point",
        "coordinates": [
          29.333603,
          25.501066
        ]
      },
      "properties": {
        "description": "representative point"
      }
    },
    {
      "geometry": {
        "type": "Point",
        "coordinates": [
          29.333603,
          25.501066
        ]
      },
      "id": "centerpoint-of-tineida",
      "type": "Feature",
      "properties": {
        "description": null,
        "location_precision": "precise",
        "title": "Centerpoint of Tineida",
        "link": "http://pleiades.stoa.org/places/750429666/centerpoint-of-tineida"
      }
    }
  ]
}