{
  "type": "FeatureCollection",
  "title": "Dam/Khaima Barang",
  "id": "753689707",
  "bbox": [
    61.41899904,
    29.83003745,
    61.41899904,
    29.83003745
  ],
  "description": "An unexcavated Bronze Age site located in the modern Chahar Burjak District of Afghanistan's Nimruz province.",
  "names": [
    "Dam",
    "Khaima Barang"
  ],
  "features": [
    {
      "type": "Feature",
      "geometry": {
        "type": "Point",
        "coordinates": [
          61.41899904,
          29.83003745
        ]
      },
      "properties": {
        "description": "representative point"
      }
    },
    {
      "geometry": {
        "type": "Point",
        "coordinates": [
          61.41899904,
          29.83003745
        ]
      },
      "id": "imagery-location-of-dam-khaima-barang",
      "type": "Feature",
      "properties": {
        "description": "Location from Helmand Sistam Project, verified in Google Earth.",
        "location_precision": "precise",
        "title": "Imagery Location of Dam/Khaima Barang",
        "link": "http://pleiades.stoa.org/places/753689707/imagery-location-of-dam-khaima-barang"
      }
    }
  ]
}