{
  "type": "FeatureCollection",
  "title": "Bompae",
  "id": "756542",
  "description": "An ancient place, cited: BAtlas 77 F3 Bompae",
  "bbox": [
    31.714189,
    26.525085,
    31.714189,
    26.525085
  ],
  "reprPoint": [
    31.714189,
    26.525085
  ],
  "names": [
    "Bompae"
  ],
  "features": [
    {
      "geometry": {
        "type": "Point",
        "coordinates": [
          31.714189,
          26.525085
        ]
      },
      "id": "darmc-location-11790",
      "type": "Feature",
      "properties": {
        "description": "500K scale point location",
        "location_precision": "precise",
        "title": "DARMC location 11790",
        "link": "http://pleiades.stoa.org/places/756542/darmc-location-11790"
      }
    }
  ]
}