{
  "type": "FeatureCollection",
  "title": "[Manlau]",
  "id": "756599",
  "bbox": [
    30.84577,
    27.730769,
    30.84577,
    27.730769
  ],
  "description": "An ancient place, cited: BAtlas 77 D1 [Manlau]",
  "names": [
    "Manlau"
  ],
  "features": [
    {
      "type": "Feature",
      "geometry": {
        "type": "Point",
        "coordinates": [
          30.84577,
          27.730769
        ]
      },
      "properties": {
        "description": "representative point"
      }
    },
    {
      "geometry": {
        "type": "Point",
        "coordinates": [
          30.84577,
          27.730769
        ]
      },
      "id": "darmc-location-13621",
      "type": "Feature",
      "properties": {
        "description": "500K scale point location",
        "location_precision": "precise",
        "title": "DARMC location 13621",
        "link": "http://pleiades.stoa.org/places/756599/darmc-location-13621"
      }
    }
  ]
}