{
  "type": "FeatureCollection",
  "title": "Deir Abu Hennes",
  "id": "756549",
  "bbox": [
    30.906827,
    27.787299,
    30.906827,
    27.787299
  ],
  "description": "An ancient place, cited: BAtlas 77 D1 Deir Abu Hennes",
  "names": [
    "Deir Abu Hennes"
  ],
  "features": [
    {
      "type": "Feature",
      "geometry": {
        "type": "Point",
        "coordinates": [
          30.906827,
          27.787299
        ]
      },
      "properties": {
        "description": "representative point"
      }
    },
    {
      "geometry": {
        "type": "Point",
        "coordinates": [
          30.906827,
          27.787299
        ]
      },
      "id": "darmc-location-5177",
      "type": "Feature",
      "properties": {
        "description": "500K scale point location",
        "location_precision": "precise",
        "title": "DARMC location 5177",
        "link": "http://pleiades.stoa.org/places/756549/darmc-location-5177"
      }
    }
  ]
}