{
  "type": "FeatureCollection",
  "title": "Deir Dronkeh",
  "id": "756555",
  "description": "An ancient place, cited: BAtlas 77 E2 Deir Dronkeh",
  "bbox": [
    31.174295,
    27.131799,
    31.174295,
    27.131799
  ],
  "reprPoint": [
    31.174295,
    27.131799
  ],
  "names": [
    "Deir Dronkeh"
  ],
  "features": [
    {
      "geometry": {
        "type": "Point",
        "coordinates": [
          31.174295,
          27.131799
        ]
      },
      "id": "darmc-location-5184",
      "type": "Feature",
      "properties": {
        "description": "500K scale point location",
        "location_precision": "precise",
        "title": "DARMC location 5184",
        "link": "http://pleiades.stoa.org/places/756555/darmc-location-5184"
      }
    }
  ]
}