{
  "type": "FeatureCollection",
  "title": "Apa Palemon, Mon.",
  "id": "756527",
  "bbox": [
    32.284873,
    26.065227,
    32.284873,
    26.065227
  ],
  "description": "An ancient place, cited: BAtlas 77 G4 Apa Palemon, Mon.",
  "names": [
    "Apa Palemon, Mon."
  ],
  "features": [
    {
      "type": "Feature",
      "geometry": {
        "type": "Point",
        "coordinates": [
          32.284873,
          26.065227
        ]
      },
      "properties": {
        "description": "representative point"
      }
    },
    {
      "geometry": {
        "type": "Point",
        "coordinates": [
          32.284873,
          26.065227
        ]
      },
      "id": "darmc-location-15266",
      "type": "Feature",
      "properties": {
        "description": "500K scale point location",
        "location_precision": "precise",
        "title": "DARMC location 15266",
        "link": "http://pleiades.stoa.org/places/756527/darmc-location-15266"
      }
    }
  ]
}