{
  "type": "FeatureCollection",
  "title": "Houor",
  "id": "756577",
  "description": "An ancient place, cited: BAtlas 77 D1 Houor",
  "bbox": [
    30.730473,
    27.856977,
    30.730473,
    27.856977
  ],
  "reprPoint": [
    30.730473,
    27.856977
  ],
  "names": [
    "Houor"
  ],
  "features": [
    {
      "geometry": {
        "type": "Point",
        "coordinates": [
          30.730473,
          27.856977
        ]
      },
      "id": "darmc-location-12795",
      "type": "Feature",
      "properties": {
        "description": "500K scale point location",
        "location_precision": "precise",
        "title": "DARMC location 12795",
        "link": "http://pleiades.stoa.org/places/756577/darmc-location-12795"
      }
    }
  ]
}