{
  "type": "FeatureCollection",
  "title": "Apa Djoore, Mon.",
  "id": "756524",
  "bbox": [
    31.68881,
    26.668723,
    31.68881,
    26.668723
  ],
  "description": "An ancient place, cited: BAtlas 77 F3 Apa Djoore, Mon.",
  "names": [
    "Apa Djoore, Mon."
  ],
  "features": [
    {
      "type": "Feature",
      "geometry": {
        "type": "Point",
        "coordinates": [
          31.68881,
          26.668723
        ]
      },
      "properties": {
        "description": "representative point"
      }
    },
    {
      "geometry": {
        "type": "Point",
        "coordinates": [
          31.68881,
          26.668723
        ]
      },
      "id": "darmc-location-15263",
      "type": "Feature",
      "properties": {
        "description": "500K scale point location",
        "location_precision": "precise",
        "title": "DARMC location 15263",
        "link": "http://pleiades.stoa.org/places/756524/darmc-location-15263"
      }
    }
  ]
}