{
  "type": "FeatureCollection",
  "title": "Speos Artemidos",
  "id": "756647",
  "description": "An ancient place, cited: BAtlas 77 D1 Speos Artemidos",
  "bbox": [
    30.866656,
    27.899952,
    30.866656,
    27.899952
  ],
  "reprPoint": [
    30.866656,
    27.899952
  ],
  "names": [
    "Speos Artemidos"
  ],
  "features": [
    {
      "geometry": {
        "type": "Point",
        "coordinates": [
          30.866656,
          27.899952
        ]
      },
      "id": "darmc-location-4681",
      "type": "Feature",
      "properties": {
        "description": "500K scale point location",
        "location_precision": "precise",
        "title": "DARMC location 4681",
        "link": "http://pleiades.stoa.org/places/756647/darmc-location-4681"
      }
    }
  ]
}