{
  "type": "FeatureCollection",
  "title": "‘Poisarietemidos’",
  "id": "756625",
  "description": "An ancient place, cited: BAtlas 77 D1 ‘Poisarietemidos’",
  "bbox": [
    30.883298,
    27.933259,
    30.883298,
    27.933259
  ],
  "reprPoint": [
    30.883298,
    27.933259
  ],
  "names": [
    "Poisarietemidos",
    "Peos Artemidos"
  ],
  "features": [
    {
      "geometry": {
        "type": "Point",
        "coordinates": [
          30.883298,
          27.933259
        ]
      },
      "id": "darmc-location-8197",
      "type": "Feature",
      "properties": {
        "description": "500K scale point location",
        "location_precision": "precise",
        "title": "DARMC location 8197",
        "link": "http://pleiades.stoa.org/places/756625/darmc-location-8197"
      }
    }
  ]
}