{
  "type": "FeatureCollection",
  "title": "Selino/Silili",
  "id": "756641",
  "description": "An ancient place, cited: BAtlas 77 F3 Selino/Silili",
  "bbox": [
    31.555114,
    26.779471,
    31.555114,
    26.779471
  ],
  "reprPoint": [
    31.555114,
    26.779471
  ],
  "names": [
    "Selino",
    "Silili"
  ],
  "features": [
    {
      "geometry": {
        "type": "Point",
        "coordinates": [
          31.555114,
          26.779471
        ]
      },
      "id": "darmc-location-14663",
      "type": "Feature",
      "properties": {
        "description": "500K scale point location",
        "location_precision": "precise",
        "title": "DARMC location 14663",
        "link": "http://pleiades.stoa.org/places/756641/darmc-location-14663"
      }
    }
  ]
}