{
  "type": "FeatureCollection",
  "title": "Paphor, Mon.",
  "id": "756615",
  "description": "An ancient place, cited: BAtlas 77 E2 Paphor, Mon.",
  "bbox": [
    31.277036,
    27.164194,
    31.277036,
    27.164194
  ],
  "reprPoint": [
    31.277036,
    27.164194
  ],
  "names": [
    "Paphor, Mon."
  ],
  "features": [
    {
      "geometry": {
        "type": "Point",
        "coordinates": [
          31.277036,
          27.164194
        ]
      },
      "id": "darmc-location-15270",
      "type": "Feature",
      "properties": {
        "description": "500K scale point location",
        "location_precision": "precise",
        "title": "DARMC location 15270",
        "link": "http://pleiades.stoa.org/places/756615/darmc-location-15270"
      }
    }
  ]
}