{
  "type": "FeatureCollection",
  "title": "Thmoo",
  "id": "756660",
  "description": "An ancient place, cited: BAtlas 77 F3 Thmoo",
  "bbox": [
    31.800002,
    26.566654,
    31.800002,
    26.566654
  ],
  "reprPoint": [
    31.800002,
    26.566654
  ],
  "names": [
    "Thmoo",
    "Thomu"
  ],
  "features": [
    {
      "geometry": {
        "type": "Point",
        "coordinates": [
          31.800002,
          26.566654
        ]
      },
      "id": "darmc-location-8367",
      "type": "Feature",
      "properties": {
        "description": "500K scale point location",
        "location_precision": "precise",
        "title": "DARMC location 8367",
        "link": "http://pleiades.stoa.org/places/756660/darmc-location-8367"
      }
    }
  ]
}