{
  "type": "FeatureCollection",
  "title": "Fundus Albianus",
  "id": "757150811",
  "bbox": [
    9.38156898614,
    44.8109064997,
    9.64188202018,
    44.9974562425
  ],
  "description": "An estate located in the Pagus Ambitrebius mentioned on the Tabula alimentaria Traianea.",
  "connectsWith": [
    "383729"
  ],
  "names": [
    "Fundus Albianus"
  ],
  "features": [
    {
      "type": "Feature",
      "geometry": {
        "type": "Point",
        "coordinates": [
          9.51300624372,
          44.8922435392
        ]
      },
      "properties": {
        "description": "representative point"
      }
    }
  ]
}