{
  "type": "FeatureCollection",
  "title": "Fundus Albianus",
  "id": "757150811",
  "bbox": [
    9.0,
    44.5,
    9.5,
    45.0
  ],
  "description": "An estate located in the Pagus Ambitrebius mentioned on the Tabula alimentaria Traianea.",
  "connectsWith": [
    "383729"
  ],
  "names": [
    "Fundus Albianus"
  ],
  "features": [
    {
      "type": "Feature",
      "geometry": {
        "type": "Point",
        "coordinates": [
          9.25,
          44.75
        ]
      },
      "properties": {
        "description": "representative point"
      }
    }
  ]
}