{
  "type": "FeatureCollection",
  "title": "Via Tiberina",
  "id": "759079303",
  "bbox": [
    12.491215,
    42.058824,
    12.596872,
    42.129717
  ],
  "description": "An ancient Roman road.",
  "features": [
    {
      "type": "Feature",
      "geometry": {
        "type": "Point",
        "coordinates": [
          12.5440435,
          42.0942705
        ]
      },
      "properties": {
        "description": "representative point"
      }
    }
  ]
}