{
  "type": "FeatureCollection",
  "title": "Brislington Roman villa",
  "id": "761753444",
  "bbox": [
    -2.55379,
    51.4362,
    -2.55379,
    51.4362
  ],
  "description": "Site of a late third or fourth century winged corridor-type villa first excavated in 1899.",
  "features": [
    {
      "type": "Feature",
      "geometry": {
        "type": "Point",
        "coordinates": [
          -2.55379,
          51.4362
        ]
      },
      "properties": {
        "description": "representative point"
      }
    },
    {
      "geometry": {
        "type": "Point",
        "coordinates": [
          -2.55379,
          51.4362
        ]
      },
      "id": "osm-location-of-brislington-roman-villa",
      "type": "Feature",
      "properties": {
        "description": null,
        "location_precision": "precise",
        "title": "OSM location of Brislington Roman villa",
        "link": "http://pleiades.stoa.org/places/761753444/osm-location-of-brislington-roman-villa"
      }
    }
  ]
}