{
  "type": "FeatureCollection",
  "title": "Theater at Philippi",
  "id": "762595495",
  "bbox": [
    24.2865695,
    41.0130274,
    24.2865695,
    41.0130274
  ],
  "description": "The initial phase of the Theater at Philippi dates to just after 356 B.C. when Philip II conquered the city.",
  "connectsWith": [
    "501482"
  ],
  "features": [
    {
      "type": "Feature",
      "geometry": {
        "type": "Point",
        "coordinates": [
          24.2865695,
          41.0130274
        ]
      },
      "properties": {
        "description": "representative point"
      }
    },
    {
      "geometry": {
        "type": "Point",
        "coordinates": [
          24.2865695,
          41.0130274
        ]
      },
      "id": "osm-location-of-theater",
      "type": "Feature",
      "properties": {
        "description": "Coordinates after OSM; verified in Google Earth 2013.",
        "location_precision": "precise",
        "title": "OSM Location of theater",
        "link": "http://pleiades.stoa.org/places/762595495/osm-location-of-theater"
      }
    }
  ]
}