{
  "type": "FeatureCollection",
  "title": "Minor Acropolis, Norba",
  "id": "76301894",
  "bbox": [
    12.9630436,
    41.5898051,
    12.9630436,
    41.5898051
  ],
  "description": "The so-called Minor Acropolis is located on the hill to the south of the Porta Maggiore. This area is surrounded by the urban enclosure wall and is terraced in polygonal masonry. Two platform temples of unknown assignation are to be found here.",
  "connectsWith": [
    "422987"
  ],
  "names": [
    "Acropoli minore"
  ],
  "features": [
    {
      "type": "Feature",
      "geometry": {
        "type": "Point",
        "coordinates": [
          12.9630436,
          41.5898051
        ]
      },
      "properties": {
        "description": "representative point"
      }
    },
    {
      "geometry": {
        "type": "Point",
        "coordinates": [
          12.9630436,
          41.5898051
        ]
      },
      "id": "location-of-minor-acropolis",
      "type": "Feature",
      "properties": {
        "description": "Location based on OpenStreetMap",
        "location_precision": "precise",
        "title": "OSM location of Minor Acropolis",
        "link": "http://pleiades.stoa.org/places/76301894/location-of-minor-acropolis"
      }
    }
  ]
}