{
  "type": "FeatureCollection",
  "title": "Villa of Manlius Vopiscus",
  "id": "766267487",
  "bbox": [
    12.8000617,
    41.9658812,
    12.8000617,
    41.9658812
  ],
  "description": "A villa site near Tivoli that has long been associated Manlius Vopiscus, who is mentioned by Statius. Excavations were begun in 1825. In 1835 Pope Gregory XVI began construction of his eponymous Villa Gregoriana on the grounds of the Roman villa.",
  "connectsWith": [
    "423081"
  ],
  "names": [
    "Villa di Manlio Vopisco"
  ],
  "features": [
    {
      "type": "Feature",
      "geometry": {
        "type": "Point",
        "coordinates": [
          12.8000617,
          41.9658812
        ]
      },
      "properties": {
        "description": "representative point"
      }
    },
    {
      "geometry": {
        "type": "Point",
        "coordinates": [
          12.8000617,
          41.9658812
        ]
      },
      "id": "osm-location-of-villa-di-manlio-vopisco",
      "type": "Feature",
      "properties": {
        "description": "Point representing the location of the Villa di Manlio Vopisco, derived from an OpenStreetMap node.",
        "location_precision": "precise",
        "title": "OSM location of Villa di Manlio Vopisco",
        "link": "http://pleiades.stoa.org/places/766267487/osm-location-of-villa-di-manlio-vopisco"
      }
    }
  ]
}