{
  "type": "FeatureCollection",
  "title": "Deir el-Atrash",
  "id": "766351",
  "description": "An ancient place, cited: BAtlas 78 C4 Deir el-Atrash",
  "bbox": [
    33.08035,
    26.935516,
    33.0823722,
    26.9359717
  ],
  "reprPoint": [
    33.0813611,
    26.93574385
  ],
  "features": [
    {
      "geometry": {
        "type": "Point",
        "coordinates": [
          33.08035,
          26.935516
        ]
      },
      "id": "darmc-location-31550",
      "type": "Feature",
      "properties": {
        "description": "scale point location",
        "location_precision": "precise",
        "title": "DARMC location 31550",
        "link": "http://pleiades.stoa.org/places/766351/darmc-location-31550"
      }
    }
  ]
}