{
  "type": "FeatureCollection",
  "title": "Porphyrites (mountain)",
  "id": "766391",
  "bbox": [
    33.266667,
    27.216667,
    33.266667,
    27.216667
  ],
  "description": "Porphyrites M. was the site of important quarries that supplied the Roman empire with porphyry.",
  "names": [
    "Porphyrites"
  ],
  "features": [
    {
      "type": "Feature",
      "geometry": {
        "type": "Point",
        "coordinates": [
          33.266667,
          27.216667
        ]
      },
      "properties": {
        "description": "representative point"
      }
    },
    {
      "geometry": {
        "type": "Point",
        "coordinates": [
          33.266667,
          27.216667
        ]
      },
      "id": "location-of-porphyrites-m",
      "type": "Feature",
      "properties": {
        "description": "Coordinates after satelliteviews.net",
        "location_precision": "precise",
        "title": "Imagery location of Porphyrites M.",
        "link": "http://pleiades.stoa.org/places/766391/location-of-porphyrites-m"
      }
    }
  ]
}