{
  "type": "FeatureCollection",
  "title": "Umm Huyut",
  "id": "766415",
  "description": "An ancient place, cited: BAtlas 78 C4 Umm Huyut",
  "bbox": [
    33.476748,
    26.741843,
    33.476748,
    26.741843
  ],
  "reprPoint": [
    33.476748,
    26.741843
  ],
  "features": [
    {
      "geometry": {
        "type": "Point",
        "coordinates": [
          33.476748,
          26.741843
        ]
      },
      "id": "darmc-location-22659",
      "type": "Feature",
      "properties": {
        "description": "Point location",
        "location_precision": "precise",
        "title": "DARMC location 22659",
        "link": "http://pleiades.stoa.org/places/766415/darmc-location-22659"
      }
    }
  ]
}