{
  "type": "FeatureCollection",
  "title": "Umm Sidra",
  "id": "766417",
  "bbox": [
    33.301357,
    27.286051,
    33.301357,
    27.286051
  ],
  "description": "An ancient place, cited: BAtlas 78 C3 Umm Sidra",
  "features": [
    {
      "type": "Feature",
      "geometry": {
        "type": "Point",
        "coordinates": [
          33.301357,
          27.286051
        ]
      },
      "properties": {
        "description": "representative point"
      }
    },
    {
      "geometry": {
        "type": "Point",
        "coordinates": [
          33.301357,
          27.286051
        ]
      },
      "id": "darmc-location-22634",
      "type": "Feature",
      "properties": {
        "description": "Point location",
        "location_precision": "precise",
        "title": "DARMC location 22634",
        "link": "http://pleiades.stoa.org/places/766417/darmc-location-22634"
      }
    }
  ]
}