{
  "type": "FeatureCollection",
  "title": "Wadi Safaga",
  "id": "766428",
  "bbox": [
    33.983069,
    26.605514,
    33.983069,
    26.605514
  ],
  "description": "An ancient place, cited: BAtlas 78 D4 Wadi Safaga",
  "features": [
    {
      "type": "Feature",
      "geometry": {
        "type": "Point",
        "coordinates": [
          33.983069,
          26.605514
        ]
      },
      "properties": {
        "description": "representative point"
      }
    },
    {
      "geometry": {
        "type": "Point",
        "coordinates": [
          33.983069,
          26.605514
        ]
      },
      "id": "darmc-location-22626",
      "type": "Feature",
      "properties": {
        "description": "Point location",
        "location_precision": "precise",
        "title": "DARMC location 22626",
        "link": "http://pleiades.stoa.org/places/766428/darmc-location-22626"
      }
    }
  ]
}