{
  "type": "FeatureCollection",
  "title": "Wadi Saqia",
  "id": "766429",
  "description": "An ancient place, cited: BAtlas 78 D5 Wadi Saqia",
  "bbox": [
    33.665093,
    26.315819,
    33.665093,
    26.315819
  ],
  "reprPoint": [
    33.665093,
    26.315819
  ],
  "features": [
    {
      "geometry": {
        "type": "Point",
        "coordinates": [
          33.665093,
          26.315819
        ]
      },
      "id": "darmc-location-22680",
      "type": "Feature",
      "properties": {
        "description": "Point location",
        "location_precision": "precise",
        "title": "DARMC location 22680",
        "link": "http://pleiades.stoa.org/places/766429/darmc-location-22680"
      }
    }
  ]
}