{
  "type": "FeatureCollection",
  "title": "Wadi Qalt el-Naga",
  "id": "766427",
  "bbox": [
    33.118333,
    26.818833,
    33.118333,
    26.818833
  ],
  "description": "An ancient place, cited: BAtlas 78 C4 Wadi Qalt el-Naga",
  "features": [
    {
      "type": "Feature",
      "geometry": {
        "type": "Point",
        "coordinates": [
          33.118333,
          26.818833
        ]
      },
      "properties": {
        "description": "representative point"
      }
    },
    {
      "geometry": {
        "type": "Point",
        "coordinates": [
          33.118333,
          26.818833
        ]
      },
      "id": "darmc-location-31553",
      "type": "Feature",
      "properties": {
        "description": "representative point location digitized from the Barrington Atlas of the Greek and Roman World by the Digital Atlas of Roman and Medieval Civilizations project at Harvard University.",
        "location_precision": "precise",
        "title": "DARMC location 31553",
        "link": "http://pleiades.stoa.org/places/766427/darmc-location-31553"
      }
    }
  ]
}