{
  "type": "FeatureCollection",
  "title": "Caer y Twr",
  "id": "767060410",
  "bbox": [
    -4.6780633,
    53.317473,
    -4.6780633,
    53.317473
  ],
  "description": "Caer y Twr is the site of a Roman period hill fort in Anglesey, Wales.",
  "connectsWith": [
    "79601"
  ],
  "features": [
    {
      "type": "Feature",
      "geometry": {
        "type": "Point",
        "coordinates": [
          -4.6780633,
          53.317473
        ]
      },
      "properties": {
        "description": "representative point"
      }
    },
    {
      "geometry": {
        "type": "Point",
        "coordinates": [
          -4.6780633,
          53.317473
        ]
      },
      "id": "location-of-caer-y-twr-hill-fort",
      "type": "Feature",
      "properties": {
        "description": "Representative location based on OpenStreetMap.",
        "location_precision": "precise",
        "title": "OSM location of Caer y Twr hill fort",
        "link": "http://pleiades.stoa.org/places/767060410/location-of-caer-y-twr-hill-fort"
      }
    }
  ]
}