{
  "type": "FeatureCollection",
  "title": "Segouiola",
  "id": "768485974",
  "bbox": [
    -6.1966887,
    37.352599,
    -6.1966887,
    37.352599
  ],
  "description": "Segouiola was an old Spanish village located in the west of the province of Sevilla during the kingdom of Alfonso X. Previously, the Arab population called it Boriauenzohar. Afterwards, this place assumed other names, including Torre del Guadiamar. Since the nineteenth century, Torre del Guadiamar county has been part of Benacazón.",
  "names": [
    "Segouiola",
    "Bonauenzohar",
    "Torre de Guadiamar",
    "Benacazon"
  ],
  "features": [
    {
      "type": "Feature",
      "geometry": {
        "type": "Point",
        "coordinates": [
          -6.1966887,
          37.352599
        ]
      },
      "properties": {
        "description": "representative point"
      }
    },
    {
      "geometry": {
        "type": "Point",
        "coordinates": [
          -6.1966887,
          37.352599
        ]
      },
      "id": "osm-location-of-segouiola-modern-benacaza3n",
      "type": "Feature",
      "properties": {
        "description": "Representative point location of modern Becacazón derived from an OpenStreetMap node.",
        "location_precision": "precise",
        "title": "OSM location of modern Benacazón",
        "link": "http://pleiades.stoa.org/places/768485974/osm-location-of-segouiola-modern-benacaza3n"
      }
    }
  ]
}