{
  "type": "FeatureCollection",
  "title": "Sanctae Mariae in Palmis",
  "id": "770702013",
  "bbox": [
    12.5036031,
    41.8664586,
    12.5036031,
    41.8664586
  ],
  "description": "A Medieval Christian sanctuary along the Via Appia, perhaps best known as the Church of Domine Quo Vadis.",
  "connectsWith": [
    "356966898"
  ],
  "names": [
    "Church of Domine Quo Vadis",
    "Santa Maria in Palmis"
  ],
  "features": [
    {
      "type": "Feature",
      "geometry": {
        "type": "Point",
        "coordinates": [
          12.5036031,
          41.8664586
        ]
      },
      "properties": {
        "description": "representative point"
      }
    },
    {
      "geometry": {
        "type": "Point",
        "coordinates": [
          12.5036031,
          41.8664586
        ]
      },
      "id": "location-of-church",
      "type": "Feature",
      "properties": {
        "description": "Representative location based on OpenStreetMap.",
        "location_precision": "precise",
        "title": "OSM location of Chiesa del Domine Quo Vadis",
        "link": "http://pleiades.stoa.org/places/770702013/location-of-church"
      }
    }
  ]
}