{
  "type": "FeatureCollection",
  "title": "Via Valeria",
  "id": "770901484",
  "bbox": [
    12.896194,
    42.018193,
    13.703,
    42.099531
  ],
  "description": "An ancient road from Rome to Corfinium.",
  "names": [
    "Oualeria hodos"
  ],
  "features": [
    {
      "type": "Feature",
      "geometry": {
        "type": "Point",
        "coordinates": [
          13.6257,
          42.05903
        ]
      },
      "properties": {
        "description": "representative point"
      }
    }
  ]
}