{
  "type": "FeatureCollection",
  "title": "Gournia",
  "id": "771100776",
  "bbox": [
    25.792722,
    35.109083,
    25.792722,
    35.109083
  ],
  "description": "A Minoan palace complex and settlement on Crete, finally abandoned ca. 1200 BCE. The original toponym is unknown and the modern name is derived from stone vessels found at the site. ",
  "connectsWith": [
    "589748"
  ],
  "names": [
    "Gournia"
  ],
  "features": [
    {
      "type": "Feature",
      "geometry": {
        "type": "Point",
        "coordinates": [
          25.792722,
          35.109083
        ]
      },
      "properties": {
        "description": "representative point"
      }
    },
    {
      "geometry": {
        "type": "Point",
        "coordinates": [
          25.792722,
          35.109083
        ]
      },
      "id": "town-court-of-gournia",
      "type": "Feature",
      "properties": {
        "description": "Large courtyard in the palace complex at Gournia",
        "location_precision": "precise",
        "title": "\"Town Court\" of Gournia",
        "link": "http://pleiades.stoa.org/places/771100776/town-court-of-gournia"
      }
    }
  ]
}