{
  "type": "FeatureCollection",
  "title": "Aethusa Ins.",
  "id": "772",
  "description": "One of the Pelagie Islands in the Mediterranean Sea, used as a naval base by the Romans during the Punic Wars.",
  "bbox": [
    12.866667,
    35.866667,
    12.866667,
    35.866667
  ],
  "connectsWith": [
    "1043"
  ],
  "reprPoint": [
    12.866667,
    35.866667
  ],
  "names": [
    "Aethusa",
    "Linosa"
  ],
  "features": [
    {
      "geometry": {
        "type": "Point",
        "coordinates": [
          12.866667,
          35.866667
        ]
      },
      "id": "location-of-aethusa-ins",
      "type": "Feature",
      "properties": {
        "description": "verified in Google Earth 2013",
        "location_precision": "precise",
        "title": "location of Aethusa Ins.",
        "link": "http://pleiades.stoa.org/places/772/location-of-aethusa-ins"
      }
    }
  ]
}