{
  "type": "FeatureCollection",
  "title": "Jmr-t",
  "id": "776186",
  "bbox": [
    29.319825,
    25.522623,
    29.319825,
    25.522623
  ],
  "description": "An ancient settlement, centered on the temple to Amun Nakht, located at modern Ain Birbiyeh/Birbibya, in Egypt's Dakhleh Oasis: BAtlas 79 inset Jmr-t",
  "connectsWith": [
    "776172"
  ],
  "names": [
    "Ain Birbiyeh",
    "Jmr-t"
  ],
  "features": [
    {
      "type": "Feature",
      "geometry": {
        "type": "Point",
        "coordinates": [
          29.319825,
          25.522623
        ]
      },
      "properties": {
        "description": "representative point"
      }
    },
    {
      "geometry": {
        "type": "Point",
        "coordinates": [
          29.319825,
          25.522623
        ]
      },
      "id": "centerpoint-of-ain-birbiyeh",
      "type": "Feature",
      "properties": {
        "description": "The centerpoint of the temple at Ain Birbiyeh",
        "location_precision": "precise",
        "title": "Centerpoint of Ain Birbiyeh",
        "link": "http://pleiades.stoa.org/places/776186/centerpoint-of-ain-birbiyeh"
      }
    }
  ]
}