{
  "type": "FeatureCollection",
  "title": "Jmr-t",
  "id": "776186",
  "description": "An ancient settlement, centered on the temple to Amun Nakht, located at modern Ain Birbiyeh/Birbibya, in Egypt's Dakhleh Oasis: BAtlas 79 inset Jmr-t",
  "bbox": [
    29.319825,
    25.522623,
    29.346181,
    25.554827
  ],
  "reprPoint": [
    29.333003,
    25.538725
  ],
  "names": [
    "Ain Birbiyeh",
    "Jmr-t"
  ],
  "features": [
    {
      "geometry": {
        "type": "Point",
        "coordinates": [
          29.319825,
          25.522623
        ]
      },
      "id": "centerpoint-of-ain-birbiyeh",
      "type": "Feature",
      "properties": {
        "description": "The centerpoint of the temple at Ain Birbiyeh",
        "location_precision": "precise",
        "title": "Centerpoint of Ain Birbiyeh",
        "link": "http://pleiades.stoa.org/places/776186/centerpoint-of-ain-birbiyeh"
      }
    },
    {
      "id": "undetermined",
      "type": "Feature",
      "properties": {
        "description": null,
        "location_precision": "unlocated",
        "title": "Undetermined location",
        "link": "http://pleiades.stoa.org/places/776186/undetermined"
      }
    },
    {
      "geometry": {
        "type": "Point",
        "coordinates": [
          29.346181,
          25.554827
        ]
      },
      "id": "darmc-location-22928",
      "type": "Feature",
      "properties": {
        "description": "500K scale point location",
        "location_precision": "precise",
        "title": "DARMC location 22928",
        "link": "http://pleiades.stoa.org/places/776186/darmc-location-22928"
      }
    }
  ]
}