{
  "type": "FeatureCollection",
  "title": "Manawir el-Biyut",
  "id": "776196",
  "description": "An ancient place, cited: BAtlas 79 D4 Manawir el-Biyut",
  "bbox": [
    30.672824,
    24.550981,
    30.672824,
    24.550981
  ],
  "reprPoint": [
    30.672824,
    24.550981
  ],
  "features": [
    {
      "geometry": {
        "type": "Point",
        "coordinates": [
          30.672824,
          24.550981
        ]
      },
      "id": "darmc-location-23614",
      "type": "Feature",
      "properties": {
        "description": "500K scale point location",
        "location_precision": "precise",
        "title": "DARMC location 23614",
        "link": "http://pleiades.stoa.org/places/776196/darmc-location-23614"
      }
    }
  ]
}