{
  "type": "FeatureCollection",
  "title": "Badaran",
  "id": "776155",
  "description": "An ancient place, cited: BAtlas 79 D4 Badaran",
  "bbox": [
    30.657553,
    24.511453,
    30.657553,
    24.511453
  ],
  "reprPoint": [
    30.657553,
    24.511453
  ],
  "features": [
    {
      "geometry": {
        "type": "Point",
        "coordinates": [
          30.657553,
          24.511453
        ]
      },
      "id": "darmc-location-11620",
      "type": "Feature",
      "properties": {
        "description": "500K scale point location",
        "location_precision": "precise",
        "title": "DARMC location 11620",
        "link": "http://pleiades.stoa.org/places/776155/darmc-location-11620"
      }
    }
  ]
}