{
  "type": "FeatureCollection",
  "title": "Ain Marraga",
  "id": "776149",
  "description": "An ancient place, cited: BAtlas 79 D3 Ain Marraga",
  "bbox": [
    30.50529,
    25.355471,
    30.50529,
    25.355471
  ],
  "reprPoint": [
    30.50529,
    25.355471
  ],
  "features": [
    {
      "geometry": {
        "type": "Point",
        "coordinates": [
          30.50529,
          25.355471
        ]
      },
      "id": "darmc-location-11242",
      "type": "Feature",
      "properties": {
        "description": "500K scale point location",
        "location_precision": "precise",
        "title": "DARMC location 11242",
        "link": "http://pleiades.stoa.org/places/776149/darmc-location-11242"
      }
    }
  ]
}