{
  "type": "FeatureCollection",
  "title": "Ain Tauleib",
  "id": "776151",
  "description": "An ancient place, cited: BAtlas 79 D2 Ain Tauleib",
  "bbox": [
    30.624032,
    25.69244,
    30.624032,
    25.69244
  ],
  "reprPoint": [
    30.624032,
    25.69244
  ],
  "features": [
    {
      "geometry": {
        "type": "Point",
        "coordinates": [
          30.624032,
          25.69244
        ]
      },
      "id": "darmc-location-11246",
      "type": "Feature",
      "properties": {
        "description": "500K scale point location",
        "location_precision": "precise",
        "title": "DARMC location 11246",
        "link": "http://pleiades.stoa.org/places/776151/darmc-location-11246"
      }
    }
  ]
}