{
  "type": "FeatureCollection",
  "title": "Someira",
  "id": "776224",
  "bbox": [
    30.600769,
    25.810296,
    30.600769,
    25.810296
  ],
  "description": "An ancient place, cited: BAtlas 79 D2 Someira",
  "features": [
    {
      "type": "Feature",
      "geometry": {
        "type": "Point",
        "coordinates": [
          30.600769,
          25.810296
        ]
      },
      "properties": {
        "description": "representative point"
      }
    },
    {
      "geometry": {
        "type": "Point",
        "coordinates": [
          30.600769,
          25.810296
        ]
      },
      "id": "darmc-location-8327",
      "type": "Feature",
      "properties": {
        "description": "500K scale point location",
        "location_precision": "precise",
        "title": "DARMC location 8327",
        "link": "http://pleiades.stoa.org/places/776224/darmc-location-8327"
      }
    }
  ]
}