{
  "type": "FeatureCollection",
  "title": "*Thenete/Ten(...)",
  "id": "776232",
  "description": "An ancient place, cited: BAtlas 79 inset *Thenete/Ten(...)",
  "bbox": [
    29.371007,
    25.559762,
    29.371007,
    25.559762
  ],
  "reprPoint": [
    29.371007,
    25.559762
  ],
  "names": [
    "Thenete",
    "Ten(...)"
  ],
  "features": [
    {
      "geometry": {
        "type": "Point",
        "coordinates": [
          29.371007,
          25.559762
        ]
      },
      "id": "darmc-location-25127",
      "type": "Feature",
      "properties": {
        "description": "500K scale point location",
        "location_precision": "precise",
        "title": "DARMC location 25127",
        "link": "http://pleiades.stoa.org/places/776232/darmc-location-25127"
      }
    }
  ]
}