{
  "type": "FeatureCollection",
  "title": "el-Qosseir",
  "id": "776221",
  "bbox": [
    30.57787,
    24.5826,
    30.57787,
    24.5826
  ],
  "description": "An ancient place, cited: BAtlas 79 D4 el-Qosseir",
  "features": [
    {
      "type": "Feature",
      "geometry": {
        "type": "Point",
        "coordinates": [
          30.57787,
          24.5826
        ]
      },
      "properties": {
        "description": "representative point"
      }
    },
    {
      "geometry": {
        "type": "Point",
        "coordinates": [
          30.57787,
          24.5826
        ]
      },
      "id": "darmc-location-18483",
      "type": "Feature",
      "properties": {
        "description": "500K scale point location",
        "location_precision": "precise",
        "title": "DARMC location 18483",
        "link": "http://pleiades.stoa.org/places/776221/darmc-location-18483"
      }
    }
  ]
}