{
  "type": "FeatureCollection",
  "title": "Um Dabadib",
  "id": "776237",
  "bbox": [
    30.426489,
    25.731284,
    30.426489,
    25.731284
  ],
  "description": "An ancient place, cited: BAtlas 79 C2 Um Dabadib",
  "features": [
    {
      "type": "Feature",
      "geometry": {
        "type": "Point",
        "coordinates": [
          30.426489,
          25.731284
        ]
      },
      "properties": {
        "description": "representative point"
      }
    },
    {
      "geometry": {
        "type": "Point",
        "coordinates": [
          30.426489,
          25.731284
        ]
      },
      "id": "darmc-location-15312",
      "type": "Feature",
      "properties": {
        "description": "500K scale point location",
        "location_precision": "precise",
        "title": "DARMC location 15312",
        "link": "http://pleiades.stoa.org/places/776237/darmc-location-15312"
      }
    }
  ]
}