{
  "type": "FeatureCollection",
  "title": "Qasr al-Sumayra",
  "id": "776224",
  "bbox": [
    30.600769,
    25.810296,
    30.600769,
    25.810296
  ],
  "description": "A late Roman fort in Egypt's Kharga Oasis.",
  "connectsWith": [
    "776210"
  ],
  "names": [
    "Someira",
    "Qasr al-Sumayra"
  ],
  "features": [
    {
      "type": "Feature",
      "geometry": {
        "type": "Point",
        "coordinates": [
          30.600769,
          25.810296
        ]
      },
      "properties": {
        "description": "representative point"
      }
    },
    {
      "geometry": {
        "type": "Point",
        "coordinates": [
          30.600769,
          25.810296
        ]
      },
      "id": "darmc-location-8327",
      "type": "Feature",
      "properties": {
        "description": "1:500,000 scale representative point location digitized from the Barrington Atlas of the Greek and Roman World by the Digital Atlas of Roman and Medieval Civilizations project at Harvard University.",
        "location_precision": "precise",
        "title": "DARMC location 8327",
        "link": "http://pleiades.stoa.org/places/776224/darmc-location-8327"
      }
    }
  ]
}