{
  "type": "FeatureCollection",
  "title": "[Per-ousekh]",
  "id": "776215",
  "description": "An ancient place, cited: BAtlas 79 D3 [Per-ousekh]",
  "bbox": [
    30.5576705,
    25.282226,
    30.560504,
    25.2869136
  ],
  "reprPoint": [
    30.55908725,
    25.2845698
  ],
  "names": [
    "Per-ousekh"
  ],
  "features": [
    {
      "geometry": {
        "type": "Point",
        "coordinates": [
          30.560504,
          25.282226
        ]
      },
      "id": "darmc-location-26133",
      "type": "Feature",
      "properties": {
        "description": "500K scale point location",
        "location_precision": "precise",
        "title": "DARMC location 26133",
        "link": "http://pleiades.stoa.org/places/776215/darmc-location-26133"
      }
    }
  ]
}