{
  "type": "FeatureCollection",
  "title": "Pege Sykaminia?",
  "id": "776214",
  "description": "An ancient place, cited: BAtlas 79 D4 Pege Sykaminia?",
  "bbox": [
    30.612945,
    24.502678,
    30.612945,
    24.502678
  ],
  "reprPoint": [
    30.612945,
    24.502678
  ],
  "names": [
    "Pege Sykaminia"
  ],
  "features": [
    {
      "geometry": {
        "type": "Point",
        "coordinates": [
          30.612945,
          24.502678
        ]
      },
      "id": "darmc-location-14164",
      "type": "Feature",
      "properties": {
        "description": "500K scale point location",
        "location_precision": "precise",
        "title": "DARMC location 14164",
        "link": "http://pleiades.stoa.org/places/776214/darmc-location-14164"
      }
    }
  ]
}