{
  "type": "FeatureCollection",
  "title": "Temple of the Winged Lions",
  "id": "777218560",
  "bbox": [
    35.4424763,
    30.3292494,
    35.4424763,
    30.3292494
  ],
  "description": "The Temple of the Winged Lions is a colonnaded temple built in Petra in order to honor the Arabian goddess al-Uzza.",
  "connectsWith": [
    "697725"
  ],
  "names": [
    "Temple of the Winged Lions"
  ],
  "features": [
    {
      "type": "Feature",
      "geometry": {
        "type": "Point",
        "coordinates": [
          35.4424763,
          30.3292494
        ]
      },
      "properties": {
        "description": "representative point"
      }
    },
    {
      "geometry": {
        "type": "Point",
        "coordinates": [
          35.4424763,
          30.3292494
        ]
      },
      "id": "location-of-temple-of-the-winged-lions",
      "type": "Feature",
      "properties": {
        "description": "Representative location based on OpenStreetMap.",
        "location_precision": "precise",
        "title": "OSM location of Temple of the Winged Lions",
        "link": "http://pleiades.stoa.org/places/777218560/location-of-temple-of-the-winged-lions"
      }
    }
  ]
}