{
  "type": "FeatureCollection",
  "title": "tribus Voltinia",
  "id": "777690772",
  "bbox": [
    12.486137,
    41.8917,
    12.4862,
    41.891775
  ],
  "description": "The tribus Voltinia (or Votinia) was an older rural tribe of ancient Rome.",
  "connectsWith": [
    "423025",
    "432900"
  ],
  "names": [
    "Voltinia tribus"
  ],
  "features": [
    {
      "type": "Feature",
      "geometry": {
        "type": "Point",
        "coordinates": [
          12.4861685,
          41.8917375
        ]
      },
      "properties": {
        "description": "representative point"
      }
    }
  ]
}