{
  "type": "FeatureCollection",
  "title": "Temple of Apollo",
  "id": "780913480",
  "description": "The Temple of Apollo (VII,7,32) in Pompeii is one of the city's oldest cults, dating to the sixth century BC. The sanctuary assumed its present appearance in the second century BC.",
  "bbox": [
    14.4847266,
    40.7490478,
    14.4847266,
    40.7490478
  ],
  "connectsWith": [
    "7e6d2513bd65076fa2221089e9584825"
  ],
  "reprPoint": [
    14.4847266,
    40.7490478
  ],
  "features": [
    {
      "geometry": {
        "type": "Point",
        "coordinates": [
          14.4847266,
          40.7490478
        ]
      },
      "id": "tempio-di-apollo",
      "type": "Feature",
      "properties": {
        "description": "Location based on OpenStreetMap",
        "location_precision": "precise",
        "title": "OSM location of so-called \"Tempio di Apollo\"",
        "link": "http://pleiades.stoa.org/places/780913480/tempio-di-apollo"
      }
    }
  ]
}