{
  "type": "FeatureCollection",
  "title": "Temple of Apollo",
  "id": "780913480",
  "description": "The Temple of Apollo (VII,7,32) in Pompeii is one of the city's oldest cults, dating to the sixth century BC. The sanctuary assumed its present appearance in the second century BC.",
  "bbox": [
    14.4847266,
    40.7490478,
    14.4847266,
    40.7490478
  ],
  "connectsWith": [
    "433032"
  ],
  "reprPoint": [
    14.4847266,
    40.7490478
  ],
  "names": [
    "Tempio di Apollo",
    "Tempio di Venere Physica Pompeiana",
    "House of the Dwarfs",
    "Tempio ipetero",
    "Tempio di Venere e collegio dei Venerei",
    "Temple of Bacchus",
    "Tempio di Mercurio e Maia",
    "Tempio di Venere Fisica",
    "Aedes of Venus Pompeiana",
    "Tempel der Ceres",
    "Tempel der Ceres und Venus",
    "Aedes of Apollo",
    "VII.7.32"
  ],
  "features": [
    {
      "geometry": {
        "type": "Point",
        "coordinates": [
          14.4847266,
          40.7490478
        ]
      },
      "id": "tempio-di-apollo",
      "type": "Feature",
      "properties": {
        "description": "Location based on OpenStreetMap",
        "location_precision": "precise",
        "title": "OSM location of so-called \"Tempio di Apollo\"",
        "link": "http://pleiades.stoa.org/places/780913480/tempio-di-apollo"
      }
    }
  ]
}