{
  "type": "FeatureCollection",
  "title": "Motroninskoe Gorodishche",
  "id": "78124778",
  "bbox": [
    32.248284,
    49.155224,
    32.248284,
    49.155224
  ],
  "description": "At Motroninskoe Gorodishche in Mielniki (central Ukraine, obl. Cherkassy) an early Iron Age fortified settlement has been identified. The ancient site was a large settlement of the ancient Scythians.",
  "names": [
    "Motroninskoe Gorodishche"
  ],
  "features": [
    {
      "type": "Feature",
      "geometry": {
        "type": "Point",
        "coordinates": [
          32.248284,
          49.155224
        ]
      },
      "properties": {
        "description": "representative point"
      }
    },
    {
      "geometry": {
        "type": "Point",
        "coordinates": [
          32.248284,
          49.155224
        ]
      },
      "id": "imagery-location-of-motroninskoe-gorodishche",
      "type": "Feature",
      "properties": {
        "description": "Representative point location determined via analysis of Google Earth imagery with reference to published site plans.",
        "location_precision": "precise",
        "title": "Imagery location of Motroninskoe Gorodishche",
        "link": "http://pleiades.stoa.org/places/78124778/imagery-location-of-motroninskoe-gorodishche"
      }
    }
  ]
}