{
  "type": "FeatureCollection",
  "title": "Sasso Pisano",
  "id": "784877599",
  "bbox": [
    10.8680796,
    43.1684364,
    10.8680796,
    43.1684364
  ],
  "description": "A sacred Etruscan thermal site.",
  "features": [
    {
      "type": "Feature",
      "geometry": {
        "type": "Point",
        "coordinates": [
          10.8680796,
          43.1684364
        ]
      },
      "properties": {
        "description": "representative point"
      }
    },
    {
      "geometry": {
        "type": "Point",
        "coordinates": [
          10.8680796,
          43.1684364
        ]
      },
      "id": "osm-location-of-lavatoio-del-sasso",
      "type": "Feature",
      "properties": {
        "description": "Representative location based on OpenStreetMap.",
        "location_precision": "precise",
        "title": "OSM location of Lavatoio del Sasso",
        "link": "http://pleiades.stoa.org/places/784877599/osm-location-of-lavatoio-del-sasso"
      }
    }
  ]
}