{
  "type": "FeatureCollection",
  "title": "Abu Hegilig North",
  "id": "785961",
  "description": "An ancient place, cited: BAtlas 80 F5 Abu Hegilig North",
  "bbox": [
    34.9265229,
    24.398183,
    34.939736,
    24.4207681
  ],
  "reprPoint": [
    34.93312945,
    24.40947555
  ],
  "features": [
    {
      "geometry": {
        "type": "Point",
        "coordinates": [
          34.939736,
          24.398183
        ]
      },
      "id": "darmc-location-6999",
      "type": "Feature",
      "properties": {
        "description": "500K scale point location",
        "location_precision": "precise",
        "title": "DARMC location 6999",
        "link": "http://pleiades.stoa.org/places/785961/darmc-location-6999"
      }
    }
  ]
}