{
  "type": "FeatureCollection",
  "title": "Bezah",
  "id": "785987",
  "bbox": [
    34.098712,
    25.115601,
    34.098712,
    25.115601
  ],
  "description": "An ancient place, cited: BAtlas 80 E3 Bezah",
  "features": [
    {
      "type": "Feature",
      "geometry": {
        "type": "Point",
        "coordinates": [
          34.098712,
          25.115601
        ]
      },
      "properties": {
        "description": "representative point"
      }
    },
    {
      "geometry": {
        "type": "Point",
        "coordinates": [
          34.098712,
          25.115601
        ]
      },
      "id": "darmc-location-7355",
      "type": "Feature",
      "properties": {
        "description": "500K scale point location",
        "location_precision": "precise",
        "title": "DARMC location 7355",
        "link": "http://pleiades.stoa.org/places/785987/darmc-location-7355"
      }
    }
  ]
}