{
  "type": "FeatureCollection",
  "title": "Abaton",
  "id": "785957",
  "description": "An ancient site designated as the burial place of Osiris-Serapis.",
  "bbox": [
    32.897895,
    24.041393,
    32.897895,
    24.041393
  ],
  "connectsWith": [
    "727172"
  ],
  "reprPoint": [
    32.897895,
    24.041393
  ],
  "names": [
    "Abaton",
    "Senmet",
    "Jazā’ir Bījah"
  ],
  "features": [
    {
      "geometry": {
        "type": "Point",
        "coordinates": [
          32.897895,
          24.041393
        ]
      },
      "id": "darmc-location-25839",
      "type": "Feature",
      "properties": {
        "description": "500K scale point location",
        "location_precision": "precise",
        "title": "DARMC location 25839",
        "link": "http://pleiades.stoa.org/places/785957/darmc-location-25839"
      }
    }
  ]
}