{
  "type": "FeatureCollection",
  "title": "Aphrodites (Oros)",
  "id": "785971",
  "description": "An ancient place, cited: BAtlas 80 D2 Aphrodites (Oros)",
  "bbox": [
    33.623553,
    25.546178,
    33.633516,
    25.6058972
  ],
  "reprPoint": [
    33.6285345,
    25.5760376
  ],
  "names": [
    "Aphrodites Oros",
    "Aphrodites"
  ],
  "features": [
    {
      "geometry": {
        "type": "Point",
        "coordinates": [
          33.633516,
          25.546178
        ]
      },
      "id": "darmc-location-6228",
      "type": "Feature",
      "properties": {
        "description": "500K scale point location",
        "location_precision": "precise",
        "title": "DARMC location 6228",
        "link": "http://pleiades.stoa.org/places/785971/darmc-location-6228"
      }
    }
  ]
}