{
  "type": "FeatureCollection",
  "title": "Bir Asale",
  "id": "785990",
  "bbox": [
    34.611188,
    25.180106,
    34.611188,
    25.180106
  ],
  "description": "An ancient place, cited: BAtlas 80 F3 Bir Asale",
  "features": [
    {
      "type": "Feature",
      "geometry": {
        "type": "Point",
        "coordinates": [
          34.611188,
          25.180106
        ]
      },
      "properties": {
        "description": "representative point"
      }
    },
    {
      "geometry": {
        "type": "Point",
        "coordinates": [
          34.611188,
          25.180106
        ]
      },
      "id": "darmc-location-23530",
      "type": "Feature",
      "properties": {
        "description": "Point location",
        "location_precision": "precise",
        "title": "DARMC location 23530",
        "link": "http://pleiades.stoa.org/places/785990/darmc-location-23530"
      }
    }
  ]
}