{
  "type": "FeatureCollection",
  "title": "Aphrodites (Oros)",
  "id": "785971",
  "description": "An ancient place, cited: BAtlas 80 D2 Aphrodites (Oros)",
  "bbox": [
    33.623553,
    25.6058972,
    33.623553,
    25.6058972
  ],
  "reprPoint": [
    33.623553,
    25.6058972
  ],
  "names": [
    " Aphrodites Oros",
    " Aphrodites"
  ],
  "features": [
    {
      "geometry": {
        "type": "Point",
        "coordinates": [
          33.623553,
          25.6058972
        ]
      },
      "id": "location-of-aphrodites-oros",
      "type": "Feature",
      "properties": {
        "description": "Representative location based on OpenStreetMap.",
        "location_precision": "precise",
        "title": "OSM location of Aphrodites (Oros)",
        "link": "http://pleiades.stoa.org/places/785971/location-of-aphrodites-oros"
      }
    }
  ]
}