{
  "type": "FeatureCollection",
  "title": "Abu Greiya",
  "id": "785960",
  "bbox": [
    34.704461,
    25.015244,
    34.704461,
    25.015244
  ],
  "description": "An ancient place, cited: BAtlas 80 F3 Abu Greiya",
  "features": [
    {
      "type": "Feature",
      "geometry": {
        "type": "Point",
        "coordinates": [
          34.704461,
          25.015244
        ]
      },
      "properties": {
        "description": "representative point"
      }
    },
    {
      "geometry": {
        "type": "Point",
        "coordinates": [
          34.704461,
          25.015244
        ]
      },
      "id": "darmc-location-9156",
      "type": "Feature",
      "properties": {
        "description": "500K scale point location",
        "location_precision": "precise",
        "title": "DARMC location 9156",
        "link": "http://pleiades.stoa.org/places/785960/darmc-location-9156"
      }
    }
  ]
}