{
  "type": "FeatureCollection",
  "title": "Abaton",
  "id": "785957",
  "description": "An ancient place, cited: BAtlas 80 inset Abaton",
  "bbox": [
    32.897895,
    24.041393,
    32.897895,
    24.041393
  ],
  "connectsWith": [
    "916d0a32739f9ffef352b3ae27582edc"
  ],
  "reprPoint": [
    32.897895,
    24.041393
  ],
  "names": [
    "Abaton",
    "Senmet"
  ],
  "features": [
    {
      "id": "undetermined",
      "type": "Feature",
      "properties": {
        "description": null,
        "location_precision": "unlocated",
        "title": "Undetermined location",
        "link": "http://pleiades.stoa.org/places/785957/undetermined"
      }
    },
    {
      "geometry": {
        "type": "Point",
        "coordinates": [
          32.897895,
          24.041393
        ]
      },
      "id": "darmc-location-25839",
      "type": "Feature",
      "properties": {
        "description": "500K scale point location",
        "location_precision": "precise",
        "title": "DARMC location 25839",
        "link": "http://pleiades.stoa.org/places/785957/darmc-location-25839"
      }
    }
  ]
}