{
  "type": "FeatureCollection",
  "title": "Aristonis",
  "id": "785977",
  "description": "An ancient place, cited: BAtlas 80 E4 Aristonis",
  "bbox": [
    34.2307636,
    24.866976,
    34.250121,
    24.9278957
  ],
  "reprPoint": [
    34.2404423,
    24.89743585
  ],
  "names": [
    "Aristonis"
  ],
  "features": [
    {
      "geometry": {
        "type": "Point",
        "coordinates": [
          34.250121,
          24.866976
        ]
      },
      "id": "darmc-location-6239",
      "type": "Feature",
      "properties": {
        "description": "500K scale point location",
        "location_precision": "precise",
        "title": "DARMC location 6239",
        "link": "http://pleiades.stoa.org/places/785977/darmc-location-6239"
      }
    }
  ]
}