{
  "type": "FeatureCollection",
  "title": "Contra Apollonos",
  "id": "786006",
  "description": "An ancient place, cited: BAtlas 80 B4 Contra Apollonos",
  "bbox": [
    32.884883,
    24.864843,
    32.884883,
    24.864843
  ],
  "reprPoint": [
    32.884883,
    24.864843
  ],
  "names": [
    "Contra Apollonos"
  ],
  "features": [
    {
      "geometry": {
        "type": "Point",
        "coordinates": [
          32.884883,
          24.864843
        ]
      },
      "id": "darmc-location-12083",
      "type": "Feature",
      "properties": {
        "description": "500K scale point location",
        "location_precision": "precise",
        "title": "DARMC location 12083",
        "link": "http://pleiades.stoa.org/places/786006/darmc-location-12083"
      }
    }
  ]
}