{
  "type": "FeatureCollection",
  "title": "Nakheil",
  "id": "786073",
  "bbox": [
    34.12672,
    26.1426,
    34.12672,
    26.1426
  ],
  "description": "An ancient place, cited: BAtlas 80 E1 Nakheil (1)",
  "features": [
    {
      "type": "Feature",
      "geometry": {
        "type": "Point",
        "coordinates": [
          34.12672,
          26.1426
        ]
      },
      "properties": {
        "description": "representative point"
      }
    },
    {
      "geometry": {
        "type": "Point",
        "coordinates": [
          34.12672,
          26.1426
        ]
      },
      "id": "darmc-location-10710",
      "type": "Feature",
      "properties": {
        "description": "500K scale point location",
        "location_precision": "precise",
        "title": "DARMC location 10710",
        "link": "http://pleiades.stoa.org/places/786073/darmc-location-10710"
      }
    }
  ]
}