{
  "type": "FeatureCollection",
  "title": "Albinia Roman villa",
  "id": "786052704",
  "bbox": [
    11.2072722,
    42.4957253,
    11.2072722,
    42.4957253
  ],
  "description": "The remains of a villa rustica near Orbetello, found to have construction in opus latericium.",
  "connectsWith": [
    "375818871"
  ],
  "features": [
    {
      "type": "Feature",
      "geometry": {
        "type": "Point",
        "coordinates": [
          11.2072722,
          42.4957253
        ]
      },
      "properties": {
        "description": "representative point"
      }
    },
    {
      "geometry": {
        "type": "Point",
        "coordinates": [
          11.2072722,
          42.4957253
        ]
      },
      "id": "osm-location-of-villa-romana-di-albinia",
      "type": "Feature",
      "properties": {
        "description": "Representative location based on OpenStreetMap.",
        "location_precision": "precise",
        "title": "OSM location of Villa Romana di Albinia",
        "link": "http://pleiades.stoa.org/places/786052704/osm-location-of-villa-romana-di-albinia"
      }
    }
  ]
}