{
  "type": "FeatureCollection",
  "title": "Nugrus",
  "id": "786077",
  "bbox": [
    34.777677,
    24.591496,
    34.777677,
    24.591496
  ],
  "description": "An ancient place, cited: BAtlas 80 F4 Nugrus",
  "features": [
    {
      "type": "Feature",
      "geometry": {
        "type": "Point",
        "coordinates": [
          34.777677,
          24.591496
        ]
      },
      "properties": {
        "description": "representative point"
      }
    },
    {
      "geometry": {
        "type": "Point",
        "coordinates": [
          34.777677,
          24.591496
        ]
      },
      "id": "darmc-location-13968",
      "type": "Feature",
      "properties": {
        "description": "500K scale point location",
        "location_precision": "precise",
        "title": "DARMC location 13968",
        "link": "http://pleiades.stoa.org/places/786077/darmc-location-13968"
      }
    }
  ]
}