{
  "type": "FeatureCollection",
  "title": "Myos Hormos?",
  "id": "786069",
  "description": "Myos Hormos was a port on the Red Sea built by the Ptolemies in the third century BC.",
  "bbox": [
    34.24401,
    26.156611,
    34.24401,
    26.156611
  ],
  "connectsWith": [
    "39290"
  ],
  "reprPoint": [
    34.24401,
    26.156611
  ],
  "names": [
    "Quseir",
    "Myos Hormos",
    "Muòs Hórmos"
  ],
  "features": [
    {
      "geometry": {
        "type": "Point",
        "coordinates": [
          34.24401,
          26.156611
        ]
      },
      "id": "darmc-location-5037",
      "type": "Feature",
      "properties": {
        "description": "500K scale point location",
        "location_precision": "precise",
        "title": "DARMC location 5037",
        "link": "http://pleiades.stoa.org/places/786069/darmc-location-5037"
      }
    }
  ]
}