{
  "type": "FeatureCollection",
  "title": "Latopolis",
  "id": "786059",
  "description": "An ancient place, cited: BAtlas 80 B3 Latopolis",
  "bbox": [
    32.516438,
    25.213691,
    32.556157,
    25.2936689
  ],
  "reprPoint": [
    32.545454175,
    25.273504425
  ],
  "names": [
    "Esna",
    "Latopolis",
    "Tempel des Chnum und Nebut",
    "[tꜣ]-snj jwnyt",
    "Latopolis",
    "Latōn Polis",
    "Latōn polis",
    "snꜣt",
    "snt",
    "Snē",
    "jwnjjt",
    "jwnjt-rsjt",
    "Isna",
    "Isna",
    "Isna",
    "Isnā",
    "Isnā Site 2",
    "Isnā Site 13",
    "Isnā sites",
    "jwnjt"
  ],
  "features": [
    {
      "geometry": {
        "type": "Point",
        "coordinates": [
          32.5560224,
          25.2935118
        ]
      },
      "id": "temple-of-khnum",
      "type": "Feature",
      "properties": {
        "description": "Location based on OpenStreetMap",
        "location_precision": "precise",
        "title": "Temple of Khnum",
        "link": "http://pleiades.stoa.org/places/786059/temple-of-khnum"
      }
    },
    {
      "geometry": {
        "type": "Point",
        "coordinates": [
          32.5531993,
          25.2936689
        ]
      },
      "id": "location-of-latopolis",
      "type": "Feature",
      "properties": {
        "description": "verified in Google Earth 2013 based on OSM coordinates.",
        "location_precision": "precise",
        "title": "location of Latopolis",
        "link": "http://pleiades.stoa.org/places/786059/location-of-latopolis"
      }
    },
    {
      "geometry": {
        "type": "Point",
        "coordinates": [
          32.516438,
          25.213691
        ]
      },
      "id": "darmc-location-13426",
      "type": "Feature",
      "properties": {
        "description": "500K scale point location",
        "location_precision": "precise",
        "title": "DARMC location 13426",
        "link": "http://pleiades.stoa.org/places/786059/darmc-location-13426"
      }
    },
    {
      "geometry": {
        "type": "Point",
        "coordinates": [
          32.556157,
          25.293146
        ]
      },
      "id": "ptolemaic-temple",
      "type": "Feature",
      "properties": {
        "description": "The most conspicuous remains of the ancient settlement of Latopolis. \r\nA few construction elements (mainly columns) are still visible scattered around in the modern town.",
        "location_precision": "precise",
        "title": "Ptolemaic temple",
        "link": "http://pleiades.stoa.org/places/786059/ptolemaic-temple"
      }
    }
  ]
}