{
  "type": "FeatureCollection",
  "title": "Gebel Zabara",
  "id": "786028",
  "bbox": [
    34.731239,
    24.748949,
    34.731239,
    24.748949
  ],
  "description": "An ancient place, cited: BAtlas 80 F4 Gebel Zabara",
  "features": [
    {
      "type": "Feature",
      "geometry": {
        "type": "Point",
        "coordinates": [
          34.731239,
          24.748949
        ]
      },
      "properties": {
        "description": "representative point"
      }
    },
    {
      "geometry": {
        "type": "Point",
        "coordinates": [
          34.731239,
          24.748949
        ]
      },
      "id": "darmc-location-12500",
      "type": "Feature",
      "properties": {
        "description": "500K scale point location",
        "location_precision": "precise",
        "title": "DARMC location 12500",
        "link": "http://pleiades.stoa.org/places/786028/darmc-location-12500"
      }
    }
  ]
}