{
  "type": "FeatureCollection",
  "title": "Hilal",
  "id": "786038",
  "description": "An ancient place, cited: BAtlas 80 F4 Hilal",
  "bbox": [
    34.600801,
    24.581325,
    34.600801,
    24.581325
  ],
  "reprPoint": [
    34.600801,
    24.581325
  ],
  "features": [
    {
      "geometry": {
        "type": "Point",
        "coordinates": [
          34.600801,
          24.581325
        ]
      },
      "id": "darmc-location-12761",
      "type": "Feature",
      "properties": {
        "description": "500K scale point location",
        "location_precision": "precise",
        "title": "DARMC location 12761",
        "link": "http://pleiades.stoa.org/places/786038/darmc-location-12761"
      }
    }
  ]
}