{
  "type": "FeatureCollection",
  "title": "Daghbag South",
  "id": "786012",
  "bbox": [
    33.838919,
    25.299423,
    33.838919,
    25.299423
  ],
  "description": "An ancient place, cited: BAtlas 80 D3 Daghbag South",
  "features": [
    {
      "type": "Feature",
      "geometry": {
        "type": "Point",
        "coordinates": [
          33.838919,
          25.299423
        ]
      },
      "properties": {
        "description": "representative point"
      }
    },
    {
      "geometry": {
        "type": "Point",
        "coordinates": [
          33.838919,
          25.299423
        ]
      },
      "id": "darmc-location-19808",
      "type": "Feature",
      "properties": {
        "description": "500K scale point location",
        "location_precision": "precise",
        "title": "DARMC location 19808",
        "link": "http://pleiades.stoa.org/places/786012/darmc-location-19808"
      }
    }
  ]
}