{
  "type": "FeatureCollection",
  "title": "Petemout/Kerameia?",
  "id": "786088",
  "bbox": [
    32.704914,
    25.705501,
    32.704914,
    25.705501
  ],
  "description": "An ancient place, cited: BAtlas 80 B2 Petemout/Kerameia?",
  "names": [
    "Petemout",
    "Kerameia",
    "Nag' el-Madamud"
  ],
  "features": [
    {
      "type": "Feature",
      "geometry": {
        "type": "Point",
        "coordinates": [
          32.704914,
          25.705501
        ]
      },
      "properties": {
        "description": "representative point"
      }
    },
    {
      "geometry": {
        "type": "Point",
        "coordinates": [
          32.704914,
          25.705501
        ]
      },
      "id": "darmc-location-14204",
      "type": "Feature",
      "properties": {
        "description": "500K scale point location",
        "location_precision": "precise",
        "title": "DARMC location 14204",
        "link": "http://pleiades.stoa.org/places/786088/darmc-location-14204"
      }
    }
  ]
}