{
  "type": "FeatureCollection",
  "title": "Latopolis",
  "id": "786059",
  "bbox": [
    32.516438,
    25.213691,
    32.5531993,
    25.2936689
  ],
  "description": "An ancient place, cited: BAtlas 80 B3 Latopolis",
  "names": [
    "Latopolis",
    "Esna",
    "Tempel des Chnum und Nebut",
    "[tꜣ]-snj jwnyt",
    "Latopolis",
    "Latōn Polis",
    "Latōn polis",
    "snꜣt",
    "snt",
    "Snē",
    "jwnjjt",
    "jwnjt-rsjt",
    "Isna",
    "Isna",
    "Isna",
    "Isnā",
    "Isnā Site 2",
    "Isnā Site 13",
    "Isnā sites",
    "jwnjt"
  ],
  "features": [
    {
      "type": "Feature",
      "geometry": {
        "type": "Point",
        "coordinates": [
          32.53481865,
          25.25367995
        ]
      },
      "properties": {
        "description": "representative point"
      }
    },
    {
      "geometry": {
        "type": "Point",
        "coordinates": [
          32.516438,
          25.213691
        ]
      },
      "id": "darmc-location-13426",
      "type": "Feature",
      "properties": {
        "description": "500K scale point location",
        "location_precision": "precise",
        "title": "DARMC location 13426",
        "link": "http://pleiades.stoa.org/places/786059/darmc-location-13426"
      }
    },
    {
      "geometry": {
        "type": "Point",
        "coordinates": [
          32.5531993,
          25.2936689
        ]
      },
      "id": "location-of-latopolis",
      "type": "Feature",
      "properties": {
        "description": "verified in Google Earth 2013 based on OSM coordinates.",
        "location_precision": "precise",
        "title": "Imagery location of Latopolis",
        "link": "http://pleiades.stoa.org/places/786059/location-of-latopolis"
      }
    }
  ]
}