{
  "type": "FeatureCollection",
  "title": "Hamesh",
  "id": "786031",
  "description": "An ancient place, cited: BAtlas 80 E4 Hamesh",
  "bbox": [
    34.124479,
    24.594185,
    34.124479,
    24.594185
  ],
  "reprPoint": [
    34.124479,
    24.594185
  ],
  "features": [
    {
      "geometry": {
        "type": "Point",
        "coordinates": [
          34.124479,
          24.594185
        ]
      },
      "id": "darmc-location-9228",
      "type": "Feature",
      "properties": {
        "description": "500K scale point location",
        "location_precision": "precise",
        "title": "DARMC location 9228",
        "link": "http://pleiades.stoa.org/places/786031/darmc-location-9228"
      }
    }
  ]
}