{
  "type": "FeatureCollection",
  "title": "Syene",
  "id": "786123",
  "bbox": [
    32.89804,
    24.081158,
    32.904942,
    24.095991
  ],
  "description": "The ancient city of Swenett in Egypt, called Syene by the Greeks.",
  "connectsWith": [
    "727172"
  ],
  "names": [
    "Syene",
    "Assuan",
    "Suwān",
    "Uswān",
    "Souan",
    "Aswān",
    "Syēnē",
    "Syenē",
    "swnw",
    "Assuan"
  ],
  "features": [
    {
      "type": "Feature",
      "geometry": {
        "type": "Point",
        "coordinates": [
          32.901491,
          24.0885745
        ]
      },
      "properties": {
        "description": "representative point"
      }
    },
    {
      "geometry": {
        "type": "Point",
        "coordinates": [
          32.904942,
          24.095991
        ]
      },
      "id": "darmc-location-16105",
      "type": "Feature",
      "properties": {
        "description": "500K scale point location",
        "location_precision": "precise",
        "title": "DARMC location 16105",
        "link": "http://pleiades.stoa.org/places/786123/darmc-location-16105"
      }
    },
    {
      "geometry": {
        "type": "Point",
        "coordinates": [
          32.89804,
          24.081158
        ]
      },
      "id": "dare-location",
      "type": "Feature",
      "properties": {
        "description": "Representative point location, site precision",
        "location_precision": "precise",
        "title": "DARE Location",
        "link": "http://pleiades.stoa.org/places/786123/dare-location"
      }
    }
  ]
}