{
  "type": "FeatureCollection",
  "title": "Samut 1",
  "id": "786104",
  "bbox": [
    33.94377,
    24.74915,
    33.94377,
    24.74915
  ],
  "description": "An ancient place, cited: BAtlas 80 D4 Samut 1",
  "features": [
    {
      "type": "Feature",
      "geometry": {
        "type": "Point",
        "coordinates": [
          33.94377,
          24.74915
        ]
      },
      "properties": {
        "description": "representative point"
      }
    },
    {
      "geometry": {
        "type": "Point",
        "coordinates": [
          33.94377,
          24.74915
        ]
      },
      "id": "darmc-location-14591",
      "type": "Feature",
      "properties": {
        "description": "500K scale point location",
        "location_precision": "precise",
        "title": "DARMC location 14591",
        "link": "http://pleiades.stoa.org/places/786104/darmc-location-14591"
      }
    }
  ]
}