{
  "type": "FeatureCollection",
  "title": "Umm Kabu",
  "id": "786138",
  "description": "An ancient place, cited: BAtlas 80 F4 Umm Kabu",
  "bbox": [
    34.904044,
    24.57452,
    34.904044,
    24.57452
  ],
  "reprPoint": [
    34.904044,
    24.57452
  ],
  "features": [
    {
      "geometry": {
        "type": "Point",
        "coordinates": [
          34.904044,
          24.57452
        ]
      },
      "id": "darmc-location-9307",
      "type": "Feature",
      "properties": {
        "description": "500K scale point location",
        "location_precision": "precise",
        "title": "DARMC location 9307",
        "link": "http://pleiades.stoa.org/places/786138/darmc-location-9307"
      }
    }
  ]
}