{
  "type": "FeatureCollection",
  "title": "Wadi Umm Qariyeh",
  "id": "786151",
  "bbox": [
    34.55588,
    24.627722,
    34.55588,
    24.627722
  ],
  "description": "An ancient place, cited: BAtlas 80 F4 Wadi Umm Qariyeh",
  "features": [
    {
      "type": "Feature",
      "geometry": {
        "type": "Point",
        "coordinates": [
          34.55588,
          24.627722
        ]
      },
      "properties": {
        "description": "representative point"
      }
    },
    {
      "geometry": {
        "type": "Point",
        "coordinates": [
          34.55588,
          24.627722
        ]
      },
      "id": "darmc-location-15459",
      "type": "Feature",
      "properties": {
        "description": "500K scale point location",
        "location_precision": "precise",
        "title": "DARMC location 15459",
        "link": "http://pleiades.stoa.org/places/786151/darmc-location-15459"
      }
    }
  ]
}