{
  "type": "FeatureCollection",
  "title": "Simiou?",
  "id": "786119",
  "description": "An ancient place, cited: BAtlas 80 D1 Simiou?",
  "bbox": [
    33.941784,
    26.099452,
    33.941784,
    26.099452
  ],
  "reprPoint": [
    33.941784,
    26.099452
  ],
  "names": [
    "Simiou"
  ],
  "features": [
    {
      "geometry": {
        "type": "Point",
        "coordinates": [
          33.941784,
          26.099452
        ]
      },
      "id": "darmc-location-8313",
      "type": "Feature",
      "properties": {
        "description": "500K scale point location",
        "location_precision": "precise",
        "title": "DARMC location 8313",
        "link": "http://pleiades.stoa.org/places/786119/darmc-location-8313"
      }
    }
  ]
}