{
  "type": "FeatureCollection",
  "title": "Chil Zena",
  "id": "787408099",
  "bbox": [
    65.6636369,
    31.6154019,
    65.6636369,
    31.6154019
  ],
  "description": "A mountainous outcropping located to the west of Kandahar, Afghanistan. A flight of forty stone steps leads to the top of the outcropping. The bilingual inscription of the third century BCE known as the Kandahar Bilingual Rock Inscription is found here.",
  "features": [
    {
      "type": "Feature",
      "geometry": {
        "type": "Point",
        "coordinates": [
          65.6636369,
          31.6154019
        ]
      },
      "properties": {
        "description": "representative point"
      }
    },
    {
      "geometry": {
        "type": "Point",
        "coordinates": [
          65.6636369,
          31.6154019
        ]
      },
      "id": "osm-location-of-chilzina-and-the-forty-steps-of",
      "type": "Feature",
      "properties": {
        "description": "Representative location based on OpenStreetMap",
        "location_precision": "precise",
        "title": "OSM location of Chilzina and the Forty Steps of Kandahar",
        "link": "http://pleiades.stoa.org/places/787408099/osm-location-of-chilzina-and-the-forty-steps-of"
      }
    }
  ]
}