{
  "type": "FeatureCollection",
  "title": "Irno (river)",
  "id": "789856352",
  "bbox": [
    14.7762574,
    40.6978018,
    14.7762574,
    40.6978018
  ],
  "description": "The Irno river is a river of Campania that flows into the Tyrrhenian Sea. While its ancient name is unknown, the river valley is the site of first millennium B.C. settlement and also the site of numerous clay beds exploited for pottery production.",
  "connectsWith": [
    "1356"
  ],
  "features": [
    {
      "type": "Feature",
      "geometry": {
        "type": "Point",
        "coordinates": [
          14.7762574,
          40.6978018
        ]
      },
      "properties": {
        "description": "representative point"
      }
    },
    {
      "geometry": {
        "type": "Point",
        "coordinates": [
          14.7762574,
          40.6978018
        ]
      },
      "id": "osm-location-of-fiume-irno",
      "type": "Feature",
      "properties": {
        "description": "Representative modern location of river course based on OpenStreetMap.",
        "location_precision": "precise",
        "title": "OSM location of Fiume Irno",
        "link": "http://pleiades.stoa.org/places/789856352/osm-location-of-fiume-irno"
      }
    }
  ]
}