{
  "type": "FeatureCollection",
  "title": "Woodhouses Hill Fort",
  "id": "792019811",
  "bbox": [
    -2.7356072,
    53.2765045,
    -2.7356072,
    53.2765045
  ],
  "description": "Woodhouses hill fort is an Iron Age hillfort located in Cheshire, England.",
  "features": [
    {
      "type": "Feature",
      "geometry": {
        "type": "Point",
        "coordinates": [
          -2.7356072,
          53.2765045
        ]
      },
      "properties": {
        "description": "representative point"
      }
    },
    {
      "geometry": {
        "type": "Point",
        "coordinates": [
          -2.7356072,
          53.2765045
        ]
      },
      "id": "location-of-woodhouses-hill-fort",
      "type": "Feature",
      "properties": {
        "description": "Location based on OpenStreetMap",
        "location_precision": "precise",
        "title": "location of Woodhouses Hill Fort",
        "link": "http://pleiades.stoa.org/places/792019811/location-of-woodhouses-hill-fort"
      }
    }
  ]
}