{
  "type": "FeatureCollection",
  "title": "Vila Nova de S. Pedro",
  "id": "792786062",
  "bbox": [
    -8.8403982,
    39.2197242,
    -8.8403982,
    39.2197242
  ],
  "description": "A Chalcolithic archaeological site occupied ca. 2600 to 1300 BC. ",
  "features": [
    {
      "type": "Feature",
      "geometry": {
        "type": "Point",
        "coordinates": [
          -8.8403982,
          39.2197242
        ]
      },
      "properties": {
        "description": "representative point"
      }
    },
    {
      "geometry": {
        "type": "Point",
        "coordinates": [
          -8.8403982,
          39.2197242
        ]
      },
      "id": "osm-location",
      "type": "Feature",
      "properties": {
        "description": "Representative location based on OpenStreetMap.",
        "location_precision": "precise",
        "title": "OSM location of Castro de Vila Nova de São Pedro",
        "link": "http://pleiades.stoa.org/places/792786062/osm-location"
      }
    }
  ]
}