{
  "type": "FeatureCollection",
  "title": "Ad Ansam",
  "id": "79283",
  "description": "An ancient place, cited: BAtlas 8 H3 Ad Ansam",
  "bbox": [
    0.901227,
    51.88983,
    0.901227,
    51.88983
  ],
  "reprPoint": [
    0.901227,
    51.88983
  ],
  "names": [
    "Ad Ansam"
  ],
  "features": [
    {
      "geometry": {
        "type": "Point",
        "coordinates": [
          0.901227,
          51.88983
        ]
      },
      "id": "darmc-location-19925",
      "type": "Feature",
      "properties": {
        "description": "1M scale point location",
        "location_precision": "precise",
        "title": "DARMC location 19925",
        "link": "http://pleiades.stoa.org/places/79283/darmc-location-19925"
      }
    }
  ]
}