{
  "type": "FeatureCollection",
  "title": "Aquae *Arnemetiae",
  "id": "79298",
  "description": "An ancient place, cited: BAtlas 8 F1 Aquae *Arnemetiae",
  "bbox": [
    -1.909625,
    53.260551,
    -1.909625,
    53.260551
  ],
  "reprPoint": [
    -1.909625,
    53.260551
  ],
  "names": [
    "Aquae Arnemetiae"
  ],
  "features": [
    {
      "geometry": {
        "type": "Point",
        "coordinates": [
          -1.909625,
          53.260551
        ]
      },
      "id": "darmc-location-33768",
      "type": "Feature",
      "properties": {
        "description": "scale point location",
        "location_precision": "precise",
        "title": "DARMC location 33768",
        "link": "http://pleiades.stoa.org/places/79298/darmc-location-33768"
      }
    }
  ]
}