{
  "type": "FeatureCollection",
  "title": "Alfoldean",
  "id": "79290",
  "bbox": [
    -0.4060552,
    51.085293,
    -0.405216,
    51.085822
  ],
  "description": "An ancient place, cited: BAtlas 8 G3 Alfoldean",
  "connectsWith": [
    "79723"
  ],
  "features": [
    {
      "type": "Feature",
      "geometry": {
        "type": "Point",
        "coordinates": [
          -0.4056356,
          51.0855575
        ]
      },
      "properties": {
        "description": "representative point"
      }
    },
    {
      "geometry": {
        "type": "Point",
        "coordinates": [
          -0.405216,
          51.085822
        ]
      },
      "id": "darmc-location-19954",
      "type": "Feature",
      "properties": {
        "description": "1M scale point location",
        "location_precision": "precise",
        "title": "DARMC location 19954",
        "link": "http://pleiades.stoa.org/places/79290/darmc-location-19954"
      }
    },
    {
      "geometry": {
        "type": "Point",
        "coordinates": [
          -0.4060552,
          51.085293
        ]
      },
      "id": "osm-location-of-roman-station",
      "type": "Feature",
      "properties": {
        "description": "Representative location based on OpenStreetMap",
        "location_precision": "precise",
        "title": "OSM location of Roman Station",
        "link": "http://pleiades.stoa.org/places/79290/osm-location-of-roman-station"
      }
    }
  ]
}