{
  "type": "FeatureCollection",
  "title": "Aquae *Arnemetiae",
  "id": "79298",
  "bbox": [
    -1.909625,
    53.260551,
    -1.909625,
    53.260551
  ],
  "description": "An ancient place, cited: BAtlas 8 F1 Aquae *Arnemetiae",
  "names": [
    "Aquae Arnemetiae"
  ],
  "features": [
    {
      "type": "Feature",
      "geometry": {
        "type": "Point",
        "coordinates": [
          -1.909625,
          53.260551
        ]
      },
      "properties": {
        "description": "representative point"
      }
    },
    {
      "geometry": {
        "type": "Point",
        "coordinates": [
          -1.909625,
          53.260551
        ]
      },
      "id": "darmc-location-33768",
      "type": "Feature",
      "properties": {
        "description": "representative point location digitized from the Barrington Atlas of the Greek and Roman World by the Digital Atlas of Roman and Medieval Civilizations project at Harvard University.",
        "location_precision": "precise",
        "title": "DARMC location 33768",
        "link": "http://pleiades.stoa.org/places/79298/darmc-location-33768"
      }
    }
  ]
}