{
  "type": "FeatureCollection",
  "title": "Apethorpe",
  "id": "79297",
  "bbox": [
    -0.495214,
    52.549985,
    -0.495214,
    52.549985
  ],
  "description": "An ancient place, cited: BAtlas 8 G2 Apethorpe",
  "features": [
    {
      "type": "Feature",
      "geometry": {
        "type": "Point",
        "coordinates": [
          -0.495214,
          52.549985
        ]
      },
      "properties": {
        "description": "representative point"
      }
    },
    {
      "geometry": {
        "type": "Point",
        "coordinates": [
          -0.495214,
          52.549985
        ]
      },
      "id": "darmc-location-20766",
      "type": "Feature",
      "properties": {
        "description": "1M scale point location",
        "location_precision": "precise",
        "title": "DARMC location 20766",
        "link": "http://pleiades.stoa.org/places/79297/darmc-location-20766"
      }
    }
  ]
}