{
  "type": "FeatureCollection",
  "title": "Barnsley Park",
  "id": "79315",
  "description": "A Roman villa occupied between ca. A.D. 140 and the fifth century. It was discovered in 1950.",
  "bbox": [
    -1.890545,
    51.74418,
    -1.890545,
    51.74418
  ],
  "reprPoint": [
    -1.890545,
    51.74418
  ],
  "features": [
    {
      "geometry": {
        "type": "Point",
        "coordinates": [
          -1.890545,
          51.74418
        ]
      },
      "id": "darmc-location-20776",
      "type": "Feature",
      "properties": {
        "description": "1M scale point location",
        "location_precision": "precise",
        "title": "DARMC location 20776",
        "link": "http://pleiades.stoa.org/places/79315/darmc-location-20776"
      }
    }
  ]
}