{
  "type": "FeatureCollection",
  "title": "Bedwyn",
  "id": "79324",
  "description": "An ancient place, cited: BAtlas 8 F3 Bedwyn",
  "bbox": [
    -1.572824,
    51.357254,
    -1.572824,
    51.357254
  ],
  "reprPoint": [
    -1.572824,
    51.357254
  ],
  "features": [
    {
      "geometry": {
        "type": "Point",
        "coordinates": [
          -1.572824,
          51.357254
        ]
      },
      "id": "darmc-location-20784",
      "type": "Feature",
      "properties": {
        "description": "1M scale point location",
        "location_precision": "precise",
        "title": "DARMC location 20784",
        "link": "http://pleiades.stoa.org/places/79324/darmc-location-20784"
      }
    }
  ]
}