{
  "type": "FeatureCollection",
  "title": "Beddington",
  "id": "79323",
  "description": "An ancient place, cited: BAtlas 8 G3 Beddington",
  "bbox": [
    -0.131614,
    51.371568,
    -0.131614,
    51.371568
  ],
  "reprPoint": [
    -0.131614,
    51.371568
  ],
  "features": [
    {
      "geometry": {
        "type": "Point",
        "coordinates": [
          -0.131614,
          51.371568
        ]
      },
      "id": "darmc-location-20783",
      "type": "Feature",
      "properties": {
        "description": "1M scale point location",
        "location_precision": "precise",
        "title": "DARMC location 20783",
        "link": "http://pleiades.stoa.org/places/79323/darmc-location-20783"
      }
    }
  ]
}