{
  "type": "FeatureCollection",
  "title": "Blestium",
  "id": "79333",
  "description": "An ancient place, cited: BAtlas 8 E3 Blestium",
  "bbox": [
    -2.712896,
    51.814232,
    -2.712896,
    51.814232
  ],
  "reprPoint": [
    -2.712896,
    51.814232
  ],
  "names": [
    "Blestium"
  ],
  "features": [
    {
      "geometry": {
        "type": "Point",
        "coordinates": [
          -2.712896,
          51.814232
        ]
      },
      "id": "darmc-location-20057",
      "type": "Feature",
      "properties": {
        "description": "1M scale point location",
        "location_precision": "precise",
        "title": "DARMC location 20057",
        "link": "http://pleiades.stoa.org/places/79333/darmc-location-20057"
      }
    }
  ]
}