{
  "type": "FeatureCollection",
  "title": "Blackwardine",
  "id": "79332",
  "description": "An ancient place, cited: BAtlas 8 E2 Blackwardine",
  "bbox": [
    -2.690621,
    52.203802,
    -2.690621,
    52.203802
  ],
  "reprPoint": [
    -2.690621,
    52.203802
  ],
  "features": [
    {
      "geometry": {
        "type": "Point",
        "coordinates": [
          -2.690621,
          52.203802
        ]
      },
      "id": "darmc-location-20055",
      "type": "Feature",
      "properties": {
        "description": "1M scale point location",
        "location_precision": "precise",
        "title": "DARMC location 20055",
        "link": "http://pleiades.stoa.org/places/79332/darmc-location-20055"
      }
    }
  ]
}