{
  "type": "FeatureCollection",
  "title": "Branogenium",
  "id": "79347",
  "bbox": [
    -2.874516,
    52.361185,
    -2.874516,
    52.361185
  ],
  "description": "An ancient place, cited: BAtlas 8 E2 Branogenium",
  "names": [
    "Branogenium",
    "Bravonium"
  ],
  "features": [
    {
      "type": "Feature",
      "geometry": {
        "type": "Point",
        "coordinates": [
          -2.874516,
          52.361185
        ]
      },
      "properties": {
        "description": "representative point"
      }
    },
    {
      "geometry": {
        "type": "Point",
        "coordinates": [
          -2.874516,
          52.361185
        ]
      },
      "id": "darmc-location-19065",
      "type": "Feature",
      "properties": {
        "description": "1M scale point location",
        "location_precision": "precise",
        "title": "DARMC location 19065",
        "link": "http://pleiades.stoa.org/places/79347/darmc-location-19065"
      }
    }
  ]
}