{
  "type": "FeatureCollection",
  "title": "Caer Gybi",
  "id": "79362",
  "description": "Caer Gybi is the site of a Roman fortlet in Anglesey, Wales.",
  "bbox": [
    -4.6328,
    53.3118,
    -4.6328,
    53.3118
  ],
  "reprPoint": [
    -4.6328,
    53.3118
  ],
  "features": [
    {
      "geometry": {
        "type": "Point",
        "coordinates": [
          -4.633509,
          53.309458
        ]
      },
      "id": "darmc-location-7148",
      "type": "Feature",
      "properties": {
        "description": "1M scale point location",
        "location_precision": "precise",
        "title": "DARMC location 7148",
        "link": "http://pleiades.stoa.org/places/79362/darmc-location-7148"
      }
    },
    {
      "geometry": {
        "type": "Point",
        "coordinates": [
          -4.6328,
          53.3118
        ]
      },
      "id": "dare-location",
      "type": "Feature",
      "properties": {
        "description": "Representative point location, site precision",
        "location_precision": "precise",
        "title": "DARE Location",
        "link": "http://pleiades.stoa.org/places/79362/dare-location"
      }
    }
  ]
}