{
  "type": "FeatureCollection",
  "title": "Caistor",
  "id": "79366",
  "description": "An ancient place, cited: BAtlas 8 G1 Caistor",
  "bbox": [
    -0.315336,
    53.497147,
    -0.315336,
    53.497147
  ],
  "reprPoint": [
    -0.315336,
    53.497147
  ],
  "features": [
    {
      "geometry": {
        "type": "Point",
        "coordinates": [
          -0.315336,
          53.497147
        ]
      },
      "id": "darmc-location-20090",
      "type": "Feature",
      "properties": {
        "description": "1M scale point location",
        "location_precision": "precise",
        "title": "DARMC location 20090",
        "link": "http://pleiades.stoa.org/places/79366/darmc-location-20090"
      }
    }
  ]
}