{
  "type": "FeatureCollection",
  "title": "Caesaromagus",
  "id": "79364",
  "bbox": [
    0.469629,
    51.735893,
    0.469629,
    51.735893
  ],
  "description": "An 8-hectare Romano-British settlement that developed in the 60s AD and continued in use until the fourth century.",
  "names": [
    "Caesaromagus"
  ],
  "features": [
    {
      "type": "Feature",
      "geometry": {
        "type": "Point",
        "coordinates": [
          0.469629,
          51.735893
        ]
      },
      "properties": {
        "description": "representative point"
      }
    },
    {
      "geometry": {
        "type": "Point",
        "coordinates": [
          0.469629,
          51.735893
        ]
      },
      "id": "darmc-location-5318",
      "type": "Feature",
      "properties": {
        "description": "1:1 million scale representative point location digitized from the Barrington Atlas of the Greek and Roman World by the Digital Atlas of Roman and Medieval Civilizations project at Harvard University.",
        "location_precision": "precise",
        "title": "DARMC location 5318",
        "link": "http://pleiades.stoa.org/places/79364/darmc-location-5318"
      }
    }
  ]
}