{
  "type": "FeatureCollection",
  "title": "‘Camborico’?",
  "id": "79369",
  "description": "An ancient place, cited: BAtlas 8 H2 ‘Camborico’?",
  "bbox": [
    0.623598,
    52.3037,
    0.623598,
    52.3037
  ],
  "reprPoint": [
    0.623598,
    52.3037
  ],
  "names": [
    "Camborico"
  ],
  "features": [
    {
      "geometry": {
        "type": "Point",
        "coordinates": [
          0.623598,
          52.3037
        ]
      },
      "id": "darmc-location-20099",
      "type": "Feature",
      "properties": {
        "description": "1M scale point location",
        "location_precision": "precise",
        "title": "DARMC location 20099",
        "link": "http://pleiades.stoa.org/places/79369/darmc-location-20099"
      }
    }
  ]
}