{
  "type": "FeatureCollection",
  "title": "Caesaromagus",
  "id": "79364",
  "description": "An 8 hectare Romano-British settlement that developed beginning in the 60s AD and continued in use at least until the fourth century.",
  "bbox": [
    0.469629,
    51.735893,
    0.469629,
    51.735893
  ],
  "reprPoint": [
    0.469629,
    51.735893
  ],
  "names": [
    "Caesaromagus"
  ],
  "features": [
    {
      "geometry": {
        "type": "Point",
        "coordinates": [
          0.469629,
          51.735893
        ]
      },
      "id": "darmc-location-5318",
      "type": "Feature",
      "properties": {
        "description": "1M scale point location",
        "location_precision": "precise",
        "title": "DARMC location 5318",
        "link": "http://pleiades.stoa.org/places/79364/darmc-location-5318"
      }
    }
  ]
}