{
  "type": "FeatureCollection",
  "title": "Canonium",
  "id": "79373",
  "description": "An ancient place, cited: BAtlas 8 H3 Canonium",
  "bbox": [
    0.703298,
    51.839173,
    0.703298,
    51.839173
  ],
  "reprPoint": [
    0.703298,
    51.839173
  ],
  "names": [
    "Canonium"
  ],
  "features": [
    {
      "geometry": {
        "type": "Point",
        "coordinates": [
          0.703298,
          51.839173
        ]
      },
      "id": "darmc-location-20105",
      "type": "Feature",
      "properties": {
        "description": "1M scale point location",
        "location_precision": "precise",
        "title": "DARMC location 20105",
        "link": "http://pleiades.stoa.org/places/79373/darmc-location-20105"
      }
    }
  ]
}