{
  "type": "FeatureCollection",
  "title": "Col. Lindum",
  "id": "79395",
  "description": "An Pre-Roman Iron Age settlement of Britain that became the site of a Roman colony after AD 71; its full name was Domitiana Lindensium.",
  "bbox": [
    -0.538459,
    53.234785,
    -0.538425,
    53.234856
  ],
  "connectsWith": [
    "656280677",
    "203193875",
    "83055"
  ],
  "reprPoint": [
    -0.538442,
    53.2348205
  ],
  "names": [
    "Col. Lindum"
  ],
  "features": [
    {
      "geometry": {
        "type": "Point",
        "coordinates": [
          -0.5381837,
          53.2371855
        ]
      },
      "id": "location-of-newport-arch-city-gate",
      "type": "Feature",
      "properties": {
        "description": "remains of a third century AD city gate. Location based on OpenStreetMap.",
        "location_precision": "precise",
        "title": "location of Newport Arch city gate",
        "link": "http://pleiades.stoa.org/places/79395/location-of-newport-arch-city-gate"
      }
    },
    {
      "geometry": {
        "type": "Point",
        "coordinates": [
          -0.538459,
          53.234785
        ]
      },
      "id": "darmc-location-20177",
      "type": "Feature",
      "properties": {
        "description": "1M scale point location",
        "location_precision": "precise",
        "title": "DARMC location 20177",
        "link": "http://pleiades.stoa.org/places/79395/darmc-location-20177"
      }
    },
    {
      "geometry": {
        "type": "Point",
        "coordinates": [
          -0.538425,
          53.234856
        ]
      },
      "id": "darmc-location-20182",
      "type": "Feature",
      "properties": {
        "description": "1M scale point location",
        "location_precision": "precise",
        "title": "DARMC location 20182",
        "link": "http://pleiades.stoa.org/places/79395/darmc-location-20182"
      }
    }
  ]
}