{
  "type": "FeatureCollection",
  "title": "Col. Lindum",
  "id": "79395",
  "bbox": [
    -0.538459,
    53.234785,
    -0.538425,
    53.234856
  ],
  "description": "An Pre-Roman Iron Age settlement of Britain that became the site of a Roman colony after A.D. 71; its full name was Domitiana Lindensium.",
  "connectsWith": [
    "83055",
    "203193875",
    "656280677"
  ],
  "names": [
    "Col. Lindum"
  ],
  "features": [
    {
      "type": "Feature",
      "geometry": {
        "type": "Point",
        "coordinates": [
          -0.538442,
          53.2348205
        ]
      },
      "properties": {
        "description": "representative point"
      }
    },
    {
      "geometry": {
        "type": "Point",
        "coordinates": [
          -0.538459,
          53.234785
        ]
      },
      "id": "darmc-location-20177",
      "type": "Feature",
      "properties": {
        "description": "1M scale point location",
        "location_precision": "precise",
        "title": "DARMC location 20177",
        "link": "http://pleiades.stoa.org/places/79395/darmc-location-20177"
      }
    },
    {
      "geometry": {
        "type": "Point",
        "coordinates": [
          -0.538425,
          53.234856
        ]
      },
      "id": "darmc-location-20182",
      "type": "Feature",
      "properties": {
        "description": "1M scale point location",
        "location_precision": "precise",
        "title": "DARMC location 20182",
        "link": "http://pleiades.stoa.org/places/79395/darmc-location-20182"
      }
    }
  ]
}