{
  "type": "FeatureCollection",
  "title": "Ewell",
  "id": "79455",
  "description": "An ancient place, cited: BAtlas 8 G3 Ewell",
  "bbox": [
    -0.249991,
    51.350307,
    -0.249991,
    51.350307
  ],
  "reprPoint": [
    -0.249991,
    51.350307
  ],
  "features": [
    {
      "geometry": {
        "type": "Point",
        "coordinates": [
          -0.249991,
          51.350307
        ]
      },
      "id": "darmc-location-20259",
      "type": "Feature",
      "properties": {
        "description": "1M scale point location",
        "location_precision": "precise",
        "title": "DARMC location 20259",
        "link": "http://pleiades.stoa.org/places/79455/darmc-location-20259"
      }
    }
  ]
}