{
  "type": "FeatureCollection",
  "title": "Folkestone",
  "id": "79467",
  "description": "An ancient place, cited: BAtlas 8 I3 Folkestone",
  "bbox": [
    1.174125,
    51.078741,
    1.174125,
    51.078741
  ],
  "reprPoint": [
    1.174125,
    51.078741
  ],
  "features": [
    {
      "geometry": {
        "type": "Point",
        "coordinates": [
          1.174125,
          51.078741
        ]
      },
      "id": "darmc-location-20868",
      "type": "Feature",
      "properties": {
        "description": "1M scale point location",
        "location_precision": "precise",
        "title": "DARMC location 20868",
        "link": "http://pleiades.stoa.org/places/79467/darmc-location-20868"
      }
    }
  ]
}