{
  "type": "FeatureCollection",
  "title": "‘Gobannio’",
  "id": "79484",
  "bbox": [
    -3.020907,
    51.822,
    -3.018,
    51.824841
  ],
  "description": "An ancient place, cited: BAtlas 8 D3 ‘Gobannio’",
  "names": [
    "Gobannio"
  ],
  "features": [
    {
      "type": "Feature",
      "geometry": {
        "type": "Point",
        "coordinates": [
          -3.0194535,
          51.8234205
        ]
      },
      "properties": {
        "description": "representative point"
      }
    },
    {
      "geometry": {
        "type": "Point",
        "coordinates": [
          -3.020907,
          51.824841
        ]
      },
      "id": "darmc-location-19048",
      "type": "Feature",
      "properties": {
        "description": "1M scale point location",
        "location_precision": "precise",
        "title": "DARMC location 19048",
        "link": "http://pleiades.stoa.org/places/79484/darmc-location-19048"
      }
    },
    {
      "geometry": {
        "type": "Point",
        "coordinates": [
          -3.018,
          51.822
        ]
      },
      "id": "dare-location",
      "type": "Feature",
      "properties": {
        "description": "Representative point location, site precision",
        "location_precision": "precise",
        "title": "DARE Location",
        "link": "http://pleiades.stoa.org/places/79484/dare-location"
      }
    }
  ]
}