{
  "type": "FeatureCollection",
  "title": "Halstock",
  "id": "79499",
  "bbox": [
    -2.654642,
    50.869559,
    -2.654642,
    50.869559
  ],
  "description": "An ancient place, cited: BAtlas 8 E4 Halstock",
  "features": [
    {
      "type": "Feature",
      "geometry": {
        "type": "Point",
        "coordinates": [
          -2.654642,
          50.869559
        ]
      },
      "properties": {
        "description": "representative point"
      }
    },
    {
      "geometry": {
        "type": "Point",
        "coordinates": [
          -2.654642,
          50.869559
        ]
      },
      "id": "darmc-location-20903",
      "type": "Feature",
      "properties": {
        "description": "1M scale point location",
        "location_precision": "precise",
        "title": "DARMC location 20903",
        "link": "http://pleiades.stoa.org/places/79499/darmc-location-20903"
      }
    }
  ]
}