{
  "type": "FeatureCollection",
  "title": "Herakleous Akron",
  "id": "79508",
  "bbox": [
    -4.5270534,
    51.023464,
    -4.5270534,
    51.023464
  ],
  "description": "An ancient place, cited: BAtlas 8 C3 Herakleous Akron",
  "names": [
    "Herakleous Akron"
  ],
  "features": [
    {
      "type": "Feature",
      "geometry": {
        "type": "Point",
        "coordinates": [
          -4.5270534,
          51.023464
        ]
      },
      "properties": {
        "description": "representative point"
      }
    },
    {
      "geometry": {
        "type": "Point",
        "coordinates": [
          -4.5270534,
          51.023464
        ]
      },
      "id": "osm-location",
      "type": "Feature",
      "properties": {
        "description": "Representative modern location based on OpenStreetMap.",
        "location_precision": "precise",
        "title": "OSM location of Hartland Point",
        "link": "http://pleiades.stoa.org/places/79508/osm-location"
      }
    }
  ]
}