{
  "type": "FeatureCollection",
  "title": "Hinton St. Mary",
  "id": "79515",
  "bbox": [
    -2.303091,
    50.946666,
    -2.303091,
    50.946666
  ],
  "description": "An ancient place, cited: BAtlas 8 E4 Hinton St. Mary",
  "features": [
    {
      "type": "Feature",
      "geometry": {
        "type": "Point",
        "coordinates": [
          -2.303091,
          50.946666
        ]
      },
      "properties": {
        "description": "representative point"
      }
    },
    {
      "geometry": {
        "type": "Point",
        "coordinates": [
          -2.303091,
          50.946666
        ]
      },
      "id": "darmc-location-20918",
      "type": "Feature",
      "properties": {
        "description": "1M scale point location",
        "location_precision": "precise",
        "title": "DARMC location 20918",
        "link": "http://pleiades.stoa.org/places/79515/darmc-location-20918"
      }
    }
  ]
}