{
  "type": "FeatureCollection",
  "title": "Icklingham",
  "id": "79525",
  "bbox": [
    0.6155342,
    52.3163198,
    0.6155342,
    52.3163198
  ],
  "description": "Site of a possible Roman Small Town.",
  "features": [
    {
      "type": "Feature",
      "geometry": {
        "type": "Point",
        "coordinates": [
          0.6155342,
          52.3163198
        ]
      },
      "properties": {
        "description": "representative point"
      }
    },
    {
      "geometry": {
        "type": "Point",
        "coordinates": [
          0.6155342,
          52.3163198
        ]
      },
      "id": "osm-location-of-icklingham-roman-settlement",
      "type": "Feature",
      "properties": {
        "description": "Representative location based on OpenStreetMap.",
        "location_precision": "precise",
        "title": "OSM location of Icklingham Roman settlement",
        "link": "http://pleiades.stoa.org/places/79525/osm-location-of-icklingham-roman-settlement"
      }
    }
  ]
}