{
  "type": "FeatureCollection",
  "title": "Icklingham",
  "id": "79525",
  "bbox": [
    0.601859,
    52.324104,
    0.601859,
    52.324104
  ],
  "description": "An ancient place, cited: BAtlas 8 H2 Icklingham",
  "features": [
    {
      "type": "Feature",
      "geometry": {
        "type": "Point",
        "coordinates": [
          0.601859,
          52.324104
        ]
      },
      "properties": {
        "description": "representative point"
      }
    },
    {
      "geometry": {
        "type": "Point",
        "coordinates": [
          0.601859,
          52.324104
        ]
      },
      "id": "darmc-location-20314",
      "type": "Feature",
      "properties": {
        "description": "1M scale point location",
        "location_precision": "precise",
        "title": "DARMC location 20314",
        "link": "http://pleiades.stoa.org/places/79525/darmc-location-20314"
      }
    }
  ]
}