{
  "type": "FeatureCollection",
  "title": "Iping",
  "id": "79529",
  "description": "An ancient place, cited: BAtlas 8 G3 Iping",
  "bbox": [
    -0.785911,
    50.998504,
    -0.785911,
    50.998504
  ],
  "reprPoint": [
    -0.785911,
    50.998504
  ],
  "features": [
    {
      "geometry": {
        "type": "Point",
        "coordinates": [
          -0.785911,
          50.998504
        ]
      },
      "id": "darmc-location-20336",
      "type": "Feature",
      "properties": {
        "description": "1M scale point location",
        "location_precision": "precise",
        "title": "DARMC location 20336",
        "link": "http://pleiades.stoa.org/places/79529/darmc-location-20336"
      }
    }
  ]
}