{
  "type": "FeatureCollection",
  "title": "Huntsham",
  "id": "79521",
  "description": "An ancient place, cited: BAtlas 8 E3 Huntsham",
  "bbox": [
    -2.613981,
    51.87635,
    -2.613981,
    51.87635
  ],
  "reprPoint": [
    -2.613981,
    51.87635
  ],
  "features": [
    {
      "geometry": {
        "type": "Point",
        "coordinates": [
          -2.613981,
          51.87635
        ]
      },
      "id": "darmc-location-20926",
      "type": "Feature",
      "properties": {
        "description": "1M scale point location",
        "location_precision": "precise",
        "title": "DARMC location 20926",
        "link": "http://pleiades.stoa.org/places/79521/darmc-location-20926"
      }
    }
  ]
}