{
  "type": "FeatureCollection",
  "title": "Hucclecote",
  "id": "79520",
  "bbox": [
    -2.191729,
    51.856784,
    -2.191729,
    51.856784
  ],
  "description": "An ancient place, cited: BAtlas 8 E3 Hucclecote",
  "features": [
    {
      "type": "Feature",
      "geometry": {
        "type": "Point",
        "coordinates": [
          -2.191729,
          51.856784
        ]
      },
      "properties": {
        "description": "representative point"
      }
    },
    {
      "geometry": {
        "type": "Point",
        "coordinates": [
          -2.191729,
          51.856784
        ]
      },
      "id": "darmc-location-20923",
      "type": "Feature",
      "properties": {
        "description": "1M scale point location",
        "location_precision": "precise",
        "title": "DARMC location 20923",
        "link": "http://pleiades.stoa.org/places/79520/darmc-location-20923"
      }
    }
  ]
}