{
  "type": "FeatureCollection",
  "title": "Hucclecote",
  "id": "79520",
  "bbox": [
    -2.1801232,
    51.8564958,
    -2.1801232,
    51.8564958
  ],
  "description": "A Roman corridor villa with both bath facilities and mosaics. Excavated in 1911 and 1993 and dated to ca. A.D. 150 to the 5th century.",
  "names": [
    "Hucclecote Roman villa"
  ],
  "features": [
    {
      "type": "Feature",
      "geometry": {
        "type": "Point",
        "coordinates": [
          -2.1801232,
          51.8564958
        ]
      },
      "properties": {
        "description": "representative point"
      }
    },
    {
      "geometry": {
        "type": "Point",
        "coordinates": [
          -2.1801232,
          51.8564958
        ]
      },
      "id": "osm-location-of-hucclecote-roman-villa",
      "type": "Feature",
      "properties": {
        "description": "Representative location based on OpenStreetMap.",
        "location_precision": "precise",
        "title": "OSM location of Hucclecote Roman villa",
        "link": "http://pleiades.stoa.org/places/79520/osm-location-of-hucclecote-roman-villa"
      }
    }
  ]
}