{
  "type": "FeatureCollection",
  "title": "Ixworth",
  "id": "79538",
  "description": "An ancient place, cited: BAtlas 8 H2 Ixworth",
  "bbox": [
    0.831819,
    52.297706,
    0.831819,
    52.297706
  ],
  "reprPoint": [
    0.831819,
    52.297706
  ],
  "features": [
    {
      "geometry": {
        "type": "Point",
        "coordinates": [
          0.831819,
          52.297706
        ]
      },
      "id": "darmc-location-20352",
      "type": "Feature",
      "properties": {
        "description": "1M scale point location",
        "location_precision": "precise",
        "title": "DARMC location 20352",
        "link": "http://pleiades.stoa.org/places/79538/darmc-location-20352"
      }
    }
  ]
}