{
  "type": "FeatureCollection",
  "title": "Jordan Hill Roman Temple",
  "id": "79540",
  "description": "A Romano-Celtic temple dating probably to the fourth century CE. Its ancient name is unknown. The name of the hill on which it sits is spelled \"Jordon\" in some twentieth-century works, including the Barrington Atlas.",
  "bbox": [
    -2.4271767,
    50.637493,
    -2.403449,
    50.664331
  ],
  "reprPoint": [
    -2.41531285,
    50.650912
  ],
  "names": [
    "Jordan Hill Roman Temple"
  ],
  "features": [
    {
      "geometry": {
        "type": "Point",
        "coordinates": [
          -2.4271767,
          50.637493
        ]
      },
      "id": "osm-location",
      "type": "Feature",
      "properties": {
        "description": "Polygonal geometry representing the visible enclosure of the site, derived from an OpenStreetMap way.",
        "location_precision": "precise",
        "title": "OSM Location",
        "link": "http://pleiades.stoa.org/places/79540/osm-location"
      }
    }
  ]
}