{
  "type": "FeatureCollection",
  "title": "Keynsham",
  "id": "79545",
  "description": "An ancient place, cited: BAtlas 8 E3 Keynsham",
  "bbox": [
    -2.498798,
    51.416118,
    -2.498798,
    51.416118
  ],
  "reprPoint": [
    -2.498798,
    51.416118
  ],
  "features": [
    {
      "geometry": {
        "type": "Point",
        "coordinates": [
          -2.498798,
          51.416118
        ]
      },
      "id": "darmc-location-20937",
      "type": "Feature",
      "properties": {
        "description": "1M scale point location",
        "location_precision": "precise",
        "title": "DARMC location 20937",
        "link": "http://pleiades.stoa.org/places/79545/darmc-location-20937"
      }
    }
  ]
}