{
  "type": "FeatureCollection",
  "title": "Jordon Hill",
  "id": "79540",
  "description": "An ancient place, cited: BAtlas 8 E4 Jordon Hill",
  "bbox": [
    -2.4271767,
    50.637493,
    -2.403449,
    50.664331
  ],
  "reprPoint": [
    -2.41531285,
    50.650912
  ],
  "features": [
    {
      "geometry": {
        "type": "Point",
        "coordinates": [
          -2.403449,
          50.664331
        ]
      },
      "id": "darmc-location-20585",
      "type": "Feature",
      "properties": {
        "description": "1M scale point location",
        "location_precision": "precise",
        "title": "DARMC location 20585",
        "link": "http://pleiades.stoa.org/places/79540/darmc-location-20585"
      }
    }
  ]
}