{
  "type": "FeatureCollection",
  "title": "Long Melford",
  "id": "79576",
  "description": "An ancient place, cited: BAtlas 8 H2 Long Melford",
  "bbox": [
    0.720731,
    52.087333,
    0.720731,
    52.087333
  ],
  "reprPoint": [
    0.720731,
    52.087333
  ],
  "features": [
    {
      "geometry": {
        "type": "Point",
        "coordinates": [
          0.720731,
          52.087333
        ]
      },
      "id": "darmc-location-20442",
      "type": "Feature",
      "properties": {
        "description": "1M scale point location",
        "location_precision": "precise",
        "title": "DARMC location 20442",
        "link": "http://pleiades.stoa.org/places/79576/darmc-location-20442"
      }
    }
  ]
}