{
  "type": "FeatureCollection",
  "title": "Ballana",
  "id": "795783",
  "description": "An ancient place, cited: BAtlas 81 B3 Ballana",
  "bbox": [
    31.56667,
    22.266669,
    31.56667,
    22.266669
  ],
  "reprPoint": [
    31.56667,
    22.266669
  ],
  "features": [
    {
      "geometry": {
        "type": "Point",
        "coordinates": [
          31.56667,
          22.266669
        ]
      },
      "id": "darmc-location-21352",
      "type": "Feature",
      "properties": {
        "description": "Point location",
        "location_precision": "precise",
        "title": "DARMC location 21352",
        "link": "http://pleiades.stoa.org/places/795783/darmc-location-21352"
      }
    }
  ]
}