{
  "type": "FeatureCollection",
  "title": "Long Itchington",
  "id": "79575",
  "bbox": [
    -1.392485,
    52.28381,
    -1.392485,
    52.28381
  ],
  "description": "An ancient place, cited: BAtlas 8 F2 Long Itchington",
  "features": [
    {
      "type": "Feature",
      "geometry": {
        "type": "Point",
        "coordinates": [
          -1.392485,
          52.28381
        ]
      },
      "properties": {
        "description": "representative point"
      }
    },
    {
      "geometry": {
        "type": "Point",
        "coordinates": [
          -1.392485,
          52.28381
        ]
      },
      "id": "darmc-location-20972",
      "type": "Feature",
      "properties": {
        "description": "1M scale point location",
        "location_precision": "precise",
        "title": "DARMC location 20972",
        "link": "http://pleiades.stoa.org/places/79575/darmc-location-20972"
      }
    }
  ]
}