{
  "type": "FeatureCollection",
  "title": "Contra Talmis",
  "id": "795797",
  "bbox": [
    32.886004,
    23.561969,
    32.886004,
    23.561969
  ],
  "description": "An ancient place, cited: BAtlas 81 C2 Contra Talmis",
  "names": [
    "Contra Talmis"
  ],
  "features": [
    {
      "type": "Feature",
      "geometry": {
        "type": "Point",
        "coordinates": [
          32.886004,
          23.561969
        ]
      },
      "properties": {
        "description": "representative point"
      }
    },
    {
      "geometry": {
        "type": "Point",
        "coordinates": [
          32.886004,
          23.561969
        ]
      },
      "id": "darmc-location-22010",
      "type": "Feature",
      "properties": {
        "description": "Point location",
        "location_precision": "precise",
        "title": "DARMC location 22010",
        "link": "http://pleiades.stoa.org/places/795797/darmc-location-22010"
      }
    }
  ]
}