{
  "type": "FeatureCollection",
  "title": "Lockleys",
  "id": "79573",
  "bbox": [
    -0.214306,
    51.832741,
    -0.214306,
    51.832741
  ],
  "description": "An ancient place, cited: BAtlas 8 G3 Lockleys",
  "features": [
    {
      "type": "Feature",
      "geometry": {
        "type": "Point",
        "coordinates": [
          -0.214306,
          51.832741
        ]
      },
      "properties": {
        "description": "representative point"
      }
    },
    {
      "geometry": {
        "type": "Point",
        "coordinates": [
          -0.214306,
          51.832741
        ]
      },
      "id": "darmc-location-20968",
      "type": "Feature",
      "properties": {
        "description": "1M scale point location",
        "location_precision": "precise",
        "title": "DARMC location 20968",
        "link": "http://pleiades.stoa.org/places/79573/darmc-location-20968"
      }
    }
  ]
}