{
  "type": "FeatureCollection",
  "title": "Aksha",
  "id": "795775",
  "bbox": [
    31.628525,
    22.367766,
    31.628525,
    22.367766
  ],
  "description": "An ancient place, cited: BAtlas 81 B3 Aksha",
  "features": [
    {
      "type": "Feature",
      "geometry": {
        "type": "Point",
        "coordinates": [
          31.628525,
          22.367766
        ]
      },
      "properties": {
        "description": "representative point"
      }
    },
    {
      "geometry": {
        "type": "Point",
        "coordinates": [
          31.628525,
          22.367766
        ]
      },
      "id": "darmc-location-21349",
      "type": "Feature",
      "properties": {
        "description": "Point location",
        "location_precision": "precise",
        "title": "DARMC location 21349",
        "link": "http://pleiades.stoa.org/places/795775/darmc-location-21349"
      }
    }
  ]
}