{
  "type": "FeatureCollection",
  "title": "Abu Fas",
  "id": "795773",
  "bbox": [
    33.990514,
    22.09553,
    33.990514,
    22.09553
  ],
  "description": "An ancient place, cited: BAtlas 81 D3 Abu Fas",
  "features": [
    {
      "type": "Feature",
      "geometry": {
        "type": "Point",
        "coordinates": [
          33.990514,
          22.09553
        ]
      },
      "properties": {
        "description": "representative point"
      }
    },
    {
      "geometry": {
        "type": "Point",
        "coordinates": [
          33.990514,
          22.09553
        ]
      },
      "id": "darmc-location-22023",
      "type": "Feature",
      "properties": {
        "description": "Point location",
        "location_precision": "precise",
        "title": "DARMC location 22023",
        "link": "http://pleiades.stoa.org/places/795773/darmc-location-22023"
      }
    }
  ]
}