{
  "type": "FeatureCollection",
  "title": "Longstock",
  "id": "79577",
  "description": "An ancient place, cited: BAtlas 8 F3 Longstock",
  "bbox": [
    -1.488242,
    51.131783,
    -1.488242,
    51.131783
  ],
  "reprPoint": [
    -1.488242,
    51.131783
  ],
  "features": [
    {
      "geometry": {
        "type": "Point",
        "coordinates": [
          -1.488242,
          51.131783
        ]
      },
      "id": "darmc-location-20973",
      "type": "Feature",
      "properties": {
        "description": "1M scale point location",
        "location_precision": "precise",
        "title": "DARMC location 20973",
        "link": "http://pleiades.stoa.org/places/79577/darmc-location-20973"
      }
    }
  ]
}