{
  "type": "FeatureCollection",
  "title": "Paptoulis?",
  "id": "795839",
  "bbox": [
    32.9011,
    23.493643,
    32.9011,
    23.493643
  ],
  "description": "An ancient place, cited: BAtlas 81 C2 Paptoulis?",
  "names": [
    "Paptoulis"
  ],
  "features": [
    {
      "type": "Feature",
      "geometry": {
        "type": "Point",
        "coordinates": [
          32.9011,
          23.493643
        ]
      },
      "properties": {
        "description": "representative point"
      }
    },
    {
      "geometry": {
        "type": "Point",
        "coordinates": [
          32.9011,
          23.493643
        ]
      },
      "id": "darmc-location-22008",
      "type": "Feature",
      "properties": {
        "description": "Point location",
        "location_precision": "precise",
        "title": "DARMC location 22008",
        "link": "http://pleiades.stoa.org/places/795839/darmc-location-22008"
      }
    }
  ]
}