{
  "type": "FeatureCollection",
  "title": "Ikhmindi",
  "id": "795820",
  "description": "A sixth century BC settlement on the Nile in Lower Nubia.",
  "bbox": [
    32.635406,
    23.020542,
    32.635406,
    23.020542
  ],
  "connectsWith": [
    "727172"
  ],
  "reprPoint": [
    32.635406,
    23.020542
  ],
  "features": [
    {
      "geometry": {
        "type": "Point",
        "coordinates": [
          32.635406,
          23.020542
        ]
      },
      "id": "darmc-location-21356",
      "type": "Feature",
      "properties": {
        "description": "Point location",
        "location_precision": "precise",
        "title": "DARMC location 21356",
        "link": "http://pleiades.stoa.org/places/795820/darmc-location-21356"
      }
    }
  ]
}