{
  "type": "FeatureCollection",
  "title": "Serra",
  "id": "795857",
  "description": "An ancient place, cited: BAtlas 81 B3 Serra",
  "bbox": [
    31.455513,
    22.124949,
    31.455513,
    22.124949
  ],
  "reprPoint": [
    31.455513,
    22.124949
  ],
  "features": [
    {
      "geometry": {
        "type": "Point",
        "coordinates": [
          31.455513,
          22.124949
        ]
      },
      "id": "darmc-location-21988",
      "type": "Feature",
      "properties": {
        "description": "Point location",
        "location_precision": "precise",
        "title": "DARMC location 21988",
        "link": "http://pleiades.stoa.org/places/795857/darmc-location-21988"
      }
    }
  ]
}