{
  "type": "FeatureCollection",
  "title": "Um Garriat",
  "id": "795878",
  "bbox": [
    33.538448,
    22.511049,
    33.538448,
    22.511049
  ],
  "description": "An ancient place, cited: BAtlas 81 D3 Um Garriat",
  "features": [
    {
      "type": "Feature",
      "geometry": {
        "type": "Point",
        "coordinates": [
          33.538448,
          22.511049
        ]
      },
      "properties": {
        "description": "representative point"
      }
    },
    {
      "geometry": {
        "type": "Point",
        "coordinates": [
          33.538448,
          22.511049
        ]
      },
      "id": "darmc-location-22024",
      "type": "Feature",
      "properties": {
        "description": "Point location",
        "location_precision": "precise",
        "title": "DARMC location 22024",
        "link": "http://pleiades.stoa.org/places/795878/darmc-location-22024"
      }
    }
  ]
}