{
  "type": "FeatureCollection",
  "title": "Tachompso",
  "id": "795866",
  "bbox": [
    32.69612,
    23.079712,
    32.69612,
    23.079712
  ],
  "description": "An ancient place, cited: BAtlas 81 C2 Tachompso",
  "connectsWith": [
    "727172"
  ],
  "names": [
    "Tachompso",
    "Tacompsos"
  ],
  "features": [
    {
      "type": "Feature",
      "geometry": {
        "type": "Point",
        "coordinates": [
          32.69612,
          23.079712
        ]
      },
      "properties": {
        "description": "representative point"
      }
    },
    {
      "geometry": {
        "type": "Point",
        "coordinates": [
          32.69612,
          23.079712
        ]
      },
      "id": "darmc-location-22002",
      "type": "Feature",
      "properties": {
        "description": "Representative point location digitized from the Barrington Atlas of the Greek and Roman World by the Digital Atlas of Roman and Medieval Civilizations project at Harvard University.",
        "location_precision": "precise",
        "title": "DARMC location 22002",
        "link": "http://pleiades.stoa.org/places/795866/darmc-location-22002"
      }
    }
  ]
}