{
  "type": "FeatureCollection",
  "title": "Tachompso",
  "id": "795866",
  "description": "An ancient place, cited: BAtlas 81 C2 Tachompso",
  "bbox": [
    32.69612,
    23.079712,
    32.69612,
    23.079712
  ],
  "connectsWith": [
    "727172"
  ],
  "reprPoint": [
    32.69612,
    23.079712
  ],
  "names": [
    "Tachompso"
  ],
  "features": [
    {
      "geometry": {
        "type": "Point",
        "coordinates": [
          32.69612,
          23.079712
        ]
      },
      "id": "darmc-location-22002",
      "type": "Feature",
      "properties": {
        "description": "Point location",
        "location_precision": "precise",
        "title": "DARMC location 22002",
        "link": "http://pleiades.stoa.org/places/795866/darmc-location-22002"
      }
    }
  ]
}