{
  "type": "FeatureCollection",
  "title": "Forum Cambusis?",
  "id": "795808",
  "bbox": [
    31.60857,
    22.360039,
    31.60857,
    22.360039
  ],
  "description": "An ancient place, cited: BAtlas 81 B3 Forum Cambusis?",
  "names": [
    "Forum Cambusis"
  ],
  "features": [
    {
      "type": "Feature",
      "geometry": {
        "type": "Point",
        "coordinates": [
          31.60857,
          22.360039
        ]
      },
      "properties": {
        "description": "representative point"
      }
    },
    {
      "geometry": {
        "type": "Point",
        "coordinates": [
          31.60857,
          22.360039
        ]
      },
      "id": "darmc-location-21354",
      "type": "Feature",
      "properties": {
        "description": "Point location",
        "location_precision": "precise",
        "title": "DARMC location 21354",
        "link": "http://pleiades.stoa.org/places/795808/darmc-location-21354"
      }
    }
  ]
}