{
  "type": "FeatureCollection",
  "title": "Firka",
  "id": "795807",
  "bbox": [
    30.591101,
    20.894209,
    30.591101,
    20.894209
  ],
  "description": "An ancient place, cited: BAtlas 81 A5 Firka",
  "features": [
    {
      "type": "Feature",
      "geometry": {
        "type": "Point",
        "coordinates": [
          30.591101,
          20.894209
        ]
      },
      "properties": {
        "description": "representative point"
      }
    },
    {
      "geometry": {
        "type": "Point",
        "coordinates": [
          30.591101,
          20.894209
        ]
      },
      "id": "darmc-location-21981",
      "type": "Feature",
      "properties": {
        "description": "Point location",
        "location_precision": "precise",
        "title": "DARMC location 21981",
        "link": "http://pleiades.stoa.org/places/795807/darmc-location-21981"
      }
    }
  ]
}