{
  "type": "FeatureCollection",
  "title": "Maidstone",
  "id": "79589",
  "description": "An ancient place, cited: BAtlas 8 H3 Maidstone",
  "bbox": [
    0.523808,
    51.270273,
    0.523808,
    51.270273
  ],
  "reprPoint": [
    0.523808,
    51.270273
  ],
  "features": [
    {
      "geometry": {
        "type": "Point",
        "coordinates": [
          0.523808,
          51.270273
        ]
      },
      "id": "darmc-location-20986",
      "type": "Feature",
      "properties": {
        "description": "1M scale point location",
        "location_precision": "precise",
        "title": "DARMC location 20986",
        "link": "http://pleiades.stoa.org/places/79589/darmc-location-20986"
      }
    }
  ]
}