{
  "type": "FeatureCollection",
  "title": "Hierasykaminos",
  "id": "795815",
  "description": "An ancient place, cited: BAtlas 81 C2 Hierasykaminos",
  "bbox": [
    32.723056,
    23.054026,
    32.723056,
    23.054026
  ],
  "reprPoint": [
    32.723056,
    23.054026
  ],
  "names": [
    "Hierasykaminos"
  ],
  "features": [
    {
      "geometry": {
        "type": "Point",
        "coordinates": [
          32.683409,
          23.068589
        ]
      },
      "id": "darmc-location-22001",
      "type": "Feature",
      "properties": {
        "description": "Point location",
        "location_precision": "precise",
        "title": "DARMC location 22001",
        "link": "http://pleiades.stoa.org/places/795815/darmc-location-22001"
      }
    },
    {
      "geometry": {
        "type": "Point",
        "coordinates": [
          32.723056,
          23.054026
        ]
      },
      "id": "dare-location",
      "type": "Feature",
      "properties": {
        "description": "Representative point location, village precision",
        "location_precision": "precise",
        "title": "DARE Location",
        "link": "http://pleiades.stoa.org/places/795815/dare-location"
      }
    }
  ]
}