{
  "type": "FeatureCollection",
  "title": "Per-Ptah",
  "id": "795843",
  "bbox": [
    32.889182,
    23.30932,
    32.889182,
    23.30932
  ],
  "description": "The site of Per-Ptah, meaning \"House of Ptah\", lies some 90 km south of Aswan and received a temple dedicated to pharaoh Ramesses II.",
  "names": [
    "Per-Ptah"
  ],
  "features": [
    {
      "type": "Feature",
      "geometry": {
        "type": "Point",
        "coordinates": [
          32.889182,
          23.30932
        ]
      },
      "properties": {
        "description": "representative point"
      }
    },
    {
      "geometry": {
        "type": "Point",
        "coordinates": [
          32.889182,
          23.30932
        ]
      },
      "id": "darmc-location-32006",
      "type": "Feature",
      "properties": {
        "description": "representative point location digitized from the Barrington Atlas of the Greek and Roman World by the Digital Atlas of Roman and Medieval Civilizations project at Harvard University.",
        "location_precision": "precise",
        "title": "DARMC location 32006",
        "link": "http://pleiades.stoa.org/places/795843/darmc-location-32006"
      }
    }
  ]
}