{
  "type": "FeatureCollection",
  "title": "Wadi es Sebua",
  "id": "795885",
  "description": "An ancient place, cited: BAtlas 81 C3 Wadi es Sebua",
  "bbox": [
    32.561719,
    22.798461,
    32.561719,
    22.798461
  ],
  "reprPoint": [
    32.561719,
    22.798461
  ],
  "features": [
    {
      "geometry": {
        "type": "Point",
        "coordinates": [
          32.561719,
          22.798461
        ]
      },
      "id": "darmc-location-22000",
      "type": "Feature",
      "properties": {
        "description": "Point location",
        "location_precision": "precise",
        "title": "DARMC location 22000",
        "link": "http://pleiades.stoa.org/places/795885/darmc-location-22000"
      }
    }
  ]
}