{
  "type": "FeatureCollection",
  "title": "Wadi es Sebua",
  "id": "795885",
  "bbox": [
    32.561719,
    22.798461,
    32.561719,
    22.798461
  ],
  "description": "The Wadi es-Sebua, also known as the Valley of the Lions, is the site of two New Kingdom Egyptian temples. This includes a temple built by Pharaoh Ramesses II (19th Dynasty).",
  "features": [
    {
      "type": "Feature",
      "geometry": {
        "type": "Point",
        "coordinates": [
          32.561719,
          22.798461
        ]
      },
      "properties": {
        "description": "representative point"
      }
    },
    {
      "geometry": {
        "type": "Point",
        "coordinates": [
          32.561719,
          22.798461
        ]
      },
      "id": "darmc-location-22000",
      "type": "Feature",
      "properties": {
        "description": "Point location",
        "location_precision": "precise",
        "title": "DARMC location 22000",
        "link": "http://pleiades.stoa.org/places/795885/darmc-location-22000"
      }
    }
  ]
}