{
  "type": "FeatureCollection",
  "title": "Per-Ptah",
  "id": "795843",
  "bbox": [
    32.889182,
    23.30932,
    32.889182,
    23.30932
  ],
  "description": "An ancient place, cited: BAtlas 81 C2 Per-Ptah",
  "names": [
    "Per-Ptah"
  ],
  "features": [
    {
      "type": "Feature",
      "geometry": {
        "type": "Point",
        "coordinates": [
          32.889182,
          23.30932
        ]
      },
      "properties": {
        "description": "representative point"
      }
    },
    {
      "geometry": {
        "type": "Point",
        "coordinates": [
          32.889182,
          23.30932
        ]
      },
      "id": "darmc-location-32006",
      "type": "Feature",
      "properties": {
        "description": "  scale point location",
        "location_precision": "precise",
        "title": "DARMC location 32006",
        "link": "http://pleiades.stoa.org/places/795843/darmc-location-32006"
      }
    }
  ]
}