{
  "type": "FeatureCollection",
  "title": "Maddle Farm",
  "id": "79585",
  "description": "An ancient place, cited: BAtlas 8 F3 Maddle Farm",
  "bbox": [
    -1.556592,
    51.530386,
    -1.556592,
    51.530386
  ],
  "reprPoint": [
    -1.556592,
    51.530386
  ],
  "features": [
    {
      "geometry": {
        "type": "Point",
        "coordinates": [
          -1.556592,
          51.530386
        ]
      },
      "id": "darmc-location-20985",
      "type": "Feature",
      "properties": {
        "description": "1M scale point location",
        "location_precision": "precise",
        "title": "DARMC location 20985",
        "link": "http://pleiades.stoa.org/places/79585/darmc-location-20985"
      }
    }
  ]
}