{
  "type": "FeatureCollection",
  "title": "Roman Tomb at Mersea",
  "id": "79599",
  "bbox": [
    0.9314015,
    51.7911217,
    0.9314015,
    51.7911217
  ],
  "description": "A Roman barrow tomb on Mersea Island.",
  "connectsWith": [
    "490598212"
  ],
  "features": [
    {
      "type": "Feature",
      "geometry": {
        "type": "Point",
        "coordinates": [
          0.9314015,
          51.7911217
        ]
      },
      "properties": {
        "description": "representative point"
      }
    },
    {
      "geometry": {
        "type": "Point",
        "coordinates": [
          0.9314015,
          51.7911217
        ]
      },
      "id": "osm-location-of-mersea-mount",
      "type": "Feature",
      "properties": {
        "description": "Representative location based on OpenStreetMap.",
        "location_precision": "precise",
        "title": "OSM location of Mersea Mount",
        "link": "http://pleiades.stoa.org/places/79599/osm-location-of-mersea-mount"
      }
    }
  ]
}