{
  "type": "FeatureCollection",
  "title": "‘Mamucio’",
  "id": "79590",
  "description": "An ancient place, cited: BAtlas 8 E1 ‘Mamucio’",
  "bbox": [
    -2.253643,
    53.475624,
    -2.253643,
    53.475624
  ],
  "reprPoint": [
    -2.253643,
    53.475624
  ],
  "names": [
    "Mamucio"
  ],
  "features": [
    {
      "geometry": {
        "type": "Point",
        "coordinates": [
          -2.23438,
          53.480684
        ]
      },
      "id": "darmc-location-19162",
      "type": "Feature",
      "properties": {
        "description": "1M scale point location",
        "location_precision": "precise",
        "title": "DARMC location 19162",
        "link": "http://pleiades.stoa.org/places/79590/darmc-location-19162"
      }
    },
    {
      "geometry": {
        "type": "Point",
        "coordinates": [
          -2.253643,
          53.475624
        ]
      },
      "id": "dare-location",
      "type": "Feature",
      "properties": {
        "description": "Representative point location, site precision",
        "location_precision": "precise",
        "title": "DARE Location",
        "link": "http://pleiades.stoa.org/places/79590/dare-location"
      }
    }
  ]
}