{
  "type": "FeatureCollection",
  "title": "Mersea",
  "id": "79599",
  "description": "An ancient place, cited: BAtlas 8 I3 Mersea",
  "bbox": [
    0.938913,
    51.790439,
    0.938913,
    51.790439
  ],
  "reprPoint": [
    0.938913,
    51.790439
  ],
  "features": [
    {
      "geometry": {
        "type": "Point",
        "coordinates": [
          0.938913,
          51.790439
        ]
      },
      "id": "darmc-location-23659",
      "type": "Feature",
      "properties": {
        "description": "Point location",
        "location_precision": "precise",
        "title": "DARMC location 23659",
        "link": "http://pleiades.stoa.org/places/79599/darmc-location-23659"
      }
    }
  ]
}