{
  "type": "FeatureCollection",
  "title": "Nettleton",
  "id": "79609",
  "description": "An ancient place, cited: BAtlas 8 E3 Nettleton",
  "bbox": [
    -2.259594,
    51.504169,
    -2.259594,
    51.504169
  ],
  "reprPoint": [
    -2.259594,
    51.504169
  ],
  "features": [
    {
      "geometry": {
        "type": "Point",
        "coordinates": [
          -2.259594,
          51.504169
        ]
      },
      "id": "darmc-location-20614",
      "type": "Feature",
      "properties": {
        "description": "1M scale point location",
        "location_precision": "precise",
        "title": "DARMC location 20614",
        "link": "http://pleiades.stoa.org/places/79609/darmc-location-20614"
      }
    }
  ]
}