{
  "type": "FeatureCollection",
  "title": "Netheravon",
  "id": "79608",
  "bbox": [
    -1.792659,
    51.235744,
    -1.792659,
    51.235744
  ],
  "description": "An ancient place, cited: BAtlas 8 F3 Netheravon",
  "features": [
    {
      "type": "Feature",
      "geometry": {
        "type": "Point",
        "coordinates": [
          -1.792659,
          51.235744
        ]
      },
      "properties": {
        "description": "representative point"
      }
    },
    {
      "geometry": {
        "type": "Point",
        "coordinates": [
          -1.792659,
          51.235744
        ]
      },
      "id": "darmc-location-21008",
      "type": "Feature",
      "properties": {
        "description": "1M scale point location",
        "location_precision": "precise",
        "title": "DARMC location 21008",
        "link": "http://pleiades.stoa.org/places/79608/darmc-location-21008"
      }
    }
  ]
}