{
  "type": "FeatureCollection",
  "title": "Navio",
  "id": "79605",
  "description": "An ancient place, cited: BAtlas 8 F1 Navio",
  "bbox": [
    -1.728988,
    53.341381,
    -1.728988,
    53.341381
  ],
  "reprPoint": [
    -1.728988,
    53.341381
  ],
  "names": [
    "Navio"
  ],
  "features": [
    {
      "geometry": {
        "type": "Point",
        "coordinates": [
          -1.728988,
          53.341381
        ]
      },
      "id": "darmc-location-19167",
      "type": "Feature",
      "properties": {
        "description": "1M scale point location",
        "location_precision": "precise",
        "title": "DARMC location 19167",
        "link": "http://pleiades.stoa.org/places/79605/darmc-location-19167"
      }
    }
  ]
}