{
  "type": "FeatureCollection",
  "title": "Navio",
  "id": "79605",
  "bbox": [
    -1.728988,
    53.341381,
    -1.728988,
    53.341381
  ],
  "description": "Navio, located near modern Brough, was a Roman fort of Flavian origin that was abandoned ca. A.D. 120. By 154 it has been rebuilt with a different orientation. There is evidence of continued use in the third and fourth centuries.",
  "names": [
    "Navio"
  ],
  "features": [
    {
      "type": "Feature",
      "geometry": {
        "type": "Point",
        "coordinates": [
          -1.728988,
          53.341381
        ]
      },
      "properties": {
        "description": "representative point"
      }
    },
    {
      "geometry": {
        "type": "Point",
        "coordinates": [
          -1.728988,
          53.341381
        ]
      },
      "id": "darmc-location-19167",
      "type": "Feature",
      "properties": {
        "description": "1M scale point location",
        "location_precision": "precise",
        "title": "DARMC location 19167",
        "link": "http://pleiades.stoa.org/places/79605/darmc-location-19167"
      }
    }
  ]
}