{
  "type": "FeatureCollection",
  "title": "Newton St. Loe",
  "id": "79615",
  "bbox": [
    -2.423606,
    51.380963,
    -2.423606,
    51.380963
  ],
  "description": "An ancient place, cited: BAtlas 8 E3 Newton St. Loe",
  "features": [
    {
      "type": "Feature",
      "geometry": {
        "type": "Point",
        "coordinates": [
          -2.423606,
          51.380963
        ]
      },
      "properties": {
        "description": "representative point"
      }
    },
    {
      "geometry": {
        "type": "Point",
        "coordinates": [
          -2.423606,
          51.380963
        ]
      },
      "id": "darmc-location-21012",
      "type": "Feature",
      "properties": {
        "description": "1M scale point location",
        "location_precision": "precise",
        "title": "DARMC location 21012",
        "link": "http://pleiades.stoa.org/places/79615/darmc-location-21012"
      }
    }
  ]
}