{
  "type": "FeatureCollection",
  "title": "Oktapitaron Akron",
  "id": "79628",
  "bbox": [
    -5.3127212,
    51.9030217,
    -5.3127212,
    51.9030217
  ],
  "description": "A headland located in southwest Wales which marks the divide between the Irish Sea and the Celtic Sea.",
  "names": [
    "Oktapitaron Akron",
    "Penmaen Dewi",
    "St David's Head"
  ],
  "features": [
    {
      "type": "Feature",
      "geometry": {
        "type": "Point",
        "coordinates": [
          -5.3127212,
          51.9030217
        ]
      },
      "properties": {
        "description": "representative point"
      }
    },
    {
      "geometry": {
        "type": "Point",
        "coordinates": [
          -5.3127212,
          51.9030217
        ]
      },
      "id": "osm-location",
      "type": "Feature",
      "properties": {
        "description": "Representative location based on OpenStreetMap.",
        "location_precision": "precise",
        "title": "OSM location of St David's Head",
        "link": "http://pleiades.stoa.org/places/79628/osm-location"
      }
    }
  ]
}