{
  "type": "FeatureCollection",
  "title": "Owmby",
  "id": "79633",
  "description": "An ancient place, cited: BAtlas 8 G1 Owmby",
  "bbox": [
    -0.498618,
    53.374291,
    -0.498618,
    53.374291
  ],
  "reprPoint": [
    -0.498618,
    53.374291
  ],
  "features": [
    {
      "geometry": {
        "type": "Point",
        "coordinates": [
          -0.498618,
          53.374291
        ]
      },
      "id": "darmc-location-898",
      "type": "Feature",
      "properties": {
        "description": "1M scale point location",
        "location_precision": "precise",
        "title": "DARMC location 898",
        "link": "http://pleiades.stoa.org/places/79633/darmc-location-898"
      }
    }
  ]
}