{
  "type": "FeatureCollection",
  "title": "Piddington",
  "id": "79640",
  "bbox": [
    -0.827221,
    52.183328,
    -0.827221,
    52.183328
  ],
  "description": "An ancient place, cited: BAtlas 8 G2 Piddington",
  "features": [
    {
      "type": "Feature",
      "geometry": {
        "type": "Point",
        "coordinates": [
          -0.827221,
          52.183328
        ]
      },
      "properties": {
        "description": "representative point"
      }
    },
    {
      "geometry": {
        "type": "Point",
        "coordinates": [
          -0.827221,
          52.183328
        ]
      },
      "id": "darmc-location-21033",
      "type": "Feature",
      "properties": {
        "description": "1M scale point location",
        "location_precision": "precise",
        "title": "DARMC location 21033",
        "link": "http://pleiades.stoa.org/places/79640/darmc-location-21033"
      }
    }
  ]
}