{
  "type": "FeatureCollection",
  "title": "Piddington",
  "id": "79640",
  "bbox": [
    -0.8348422,
    52.1794013,
    -0.8348422,
    52.1794013
  ],
  "description": "An ancient place, cited: BAtlas 8 G2 Piddington",
  "features": [
    {
      "type": "Feature",
      "geometry": {
        "type": "Point",
        "coordinates": [
          -0.8348422,
          52.1794013
        ]
      },
      "properties": {
        "description": "representative point"
      }
    },
    {
      "geometry": {
        "type": "Point",
        "coordinates": [
          -0.8348422,
          52.1794013
        ]
      },
      "id": "location-of-roman-villa",
      "type": "Feature",
      "properties": {
        "description": "Representative location based on OpenStreetMap.",
        "location_precision": "precise",
        "title": "OSM location of Piddington Roman Villa",
        "link": "http://pleiades.stoa.org/places/79640/location-of-roman-villa"
      }
    }
  ]
}