{
  "type": "FeatureCollection",
  "title": "Regulbium",
  "id": "79654",
  "bbox": [
    1.199796,
    51.379435,
    1.200949,
    51.379537
  ],
  "description": "Regulbium was a Roman 'Saxon Shore' fort.",
  "names": [
    "Regulbium"
  ],
  "features": [
    {
      "type": "Feature",
      "geometry": {
        "type": "Point",
        "coordinates": [
          1.2003725,
          51.379486
        ]
      },
      "properties": {
        "description": "representative point"
      }
    },
    {
      "geometry": {
        "type": "Point",
        "coordinates": [
          1.199796,
          51.379537
        ]
      },
      "id": "darmc-location-19192",
      "type": "Feature",
      "properties": {
        "description": "1M scale point location",
        "location_precision": "precise",
        "title": "DARMC location 19192",
        "link": "http://pleiades.stoa.org/places/79654/darmc-location-19192"
      }
    },
    {
      "geometry": {
        "type": "Point",
        "coordinates": [
          1.200949,
          51.379435
        ]
      },
      "id": "dare-location",
      "type": "Feature",
      "properties": {
        "description": "Representative point location, site precision",
        "location_precision": "precise",
        "title": "DARE Location",
        "link": "http://pleiades.stoa.org/places/79654/dare-location"
      }
    }
  ]
}