{
  "type": "FeatureCollection",
  "title": "Rockbourne",
  "id": "79659",
  "description": "A Roman-style courtyard villa occupied until the fifth century AD.",
  "bbox": [
    -1.839463,
    50.9534708,
    -1.8300565,
    50.96453
  ],
  "reprPoint": [
    -1.83475975,
    50.9590004
  ],
  "features": [
    {
      "geometry": {
        "type": "Point",
        "coordinates": [
          -1.8300565,
          50.9534708
        ]
      },
      "id": "location-of-roman-villa",
      "type": "Feature",
      "properties": {
        "description": "Location based on OpenStreetMap",
        "location_precision": "precise",
        "title": "location of Roman villa",
        "link": "http://pleiades.stoa.org/places/79659/location-of-roman-villa"
      }
    }
  ]
}