{
  "type": "FeatureCollection",
  "title": "Rockbourne",
  "id": "79659",
  "description": "A Roman-style villa occupied until the fifth century AD.",
  "bbox": [
    -1.839463,
    50.96453,
    -1.839463,
    50.96453
  ],
  "reprPoint": [
    -1.839463,
    50.96453
  ],
  "features": [
    {
      "geometry": {
        "type": "Point",
        "coordinates": [
          -1.839463,
          50.96453
        ]
      },
      "id": "darmc-location-21061",
      "type": "Feature",
      "properties": {
        "description": "1M scale point location",
        "location_precision": "precise",
        "title": "DARMC location 21061",
        "link": "http://pleiades.stoa.org/places/79659/darmc-location-21061"
      }
    }
  ]
}