{
  "type": "FeatureCollection",
  "title": "Rougham",
  "id": "79661",
  "bbox": [
    0.796141,
    52.220938,
    0.796141,
    52.220938
  ],
  "description": "An ancient place, cited: BAtlas 8 H2 Rougham",
  "features": [
    {
      "type": "Feature",
      "geometry": {
        "type": "Point",
        "coordinates": [
          0.796141,
          52.220938
        ]
      },
      "properties": {
        "description": "representative point"
      }
    },
    {
      "geometry": {
        "type": "Point",
        "coordinates": [
          0.796141,
          52.220938
        ]
      },
      "id": "darmc-location-21063",
      "type": "Feature",
      "properties": {
        "description": "1M scale point location",
        "location_precision": "precise",
        "title": "DARMC location 21063",
        "link": "http://pleiades.stoa.org/places/79661/darmc-location-21063"
      }
    }
  ]
}