{
  "type": "FeatureCollection",
  "title": "Saunderton",
  "id": "79673",
  "description": "An ancient place, cited: BAtlas 8 G3 Saunderton",
  "bbox": [
    -0.825662,
    51.676078,
    -0.825662,
    51.676078
  ],
  "reprPoint": [
    -0.825662,
    51.676078
  ],
  "features": [
    {
      "geometry": {
        "type": "Point",
        "coordinates": [
          -0.825662,
          51.676078
        ]
      },
      "id": "darmc-location-21089",
      "type": "Feature",
      "properties": {
        "description": "1M scale point location",
        "location_precision": "precise",
        "title": "DARMC location 21089",
        "link": "http://pleiades.stoa.org/places/79673/darmc-location-21089"
      }
    }
  ]
}