{
  "type": "FeatureCollection",
  "title": "Stonham Aspal",
  "id": "79698",
  "description": "An ancient place, cited: BAtlas 8 I2 Stonham Aspal",
  "bbox": [
    1.118105,
    52.193743,
    1.118105,
    52.193743
  ],
  "reprPoint": [
    1.118105,
    52.193743
  ],
  "features": [
    {
      "geometry": {
        "type": "Point",
        "coordinates": [
          1.118105,
          52.193743
        ]
      },
      "id": "darmc-location-21109",
      "type": "Feature",
      "properties": {
        "description": "1M scale point location",
        "location_precision": "precise",
        "title": "DARMC location 21109",
        "link": "http://pleiades.stoa.org/places/79698/darmc-location-21109"
      }
    }
  ]
}