{
  "type": "FeatureCollection",
  "title": "Stroud",
  "id": "79700",
  "description": "An ancient place, cited: BAtlas 8 G3 Stroud",
  "bbox": [
    -0.968211,
    51.008612,
    -0.968211,
    51.008612
  ],
  "reprPoint": [
    -0.968211,
    51.008612
  ],
  "features": [
    {
      "geometry": {
        "type": "Point",
        "coordinates": [
          -0.968211,
          51.008612
        ]
      },
      "id": "darmc-location-21110",
      "type": "Feature",
      "properties": {
        "description": "1M scale point location",
        "location_precision": "precise",
        "title": "DARMC location 21110",
        "link": "http://pleiades.stoa.org/places/79700/darmc-location-21110"
      }
    }
  ]
}