{
  "type": "FeatureCollection",
  "title": "Herculaneum Gate",
  "id": "797109353",
  "bbox": [
    14.4813524,
    40.7517443,
    14.4813524,
    40.7517443
  ],
  "description": "The \"Herculaneum Gate\" was a city gate of Pompeii located at the northern terminus of the Via Consolare. The gate originally incorporated three passageways.",
  "connectsWith": [
    "433032"
  ],
  "features": [
    {
      "type": "Feature",
      "geometry": {
        "type": "Point",
        "coordinates": [
          14.4813524,
          40.7517443
        ]
      },
      "properties": {
        "description": "representative point"
      }
    },
    {
      "geometry": {
        "type": "Point",
        "coordinates": [
          14.4813524,
          40.7517443
        ]
      },
      "id": "porta-di-ercolano-e-cinta-muraria",
      "type": "Feature",
      "properties": {
        "description": "Location based on OpenStreetMap",
        "location_precision": "precise",
        "title": "OSM location of so-called \"Porta di Ercolano e cinta muraria\"",
        "link": "http://pleiades.stoa.org/places/797109353/porta-di-ercolano-e-cinta-muraria"
      }
    }
  ]
}