{
  "type": "FeatureCollection",
  "title": "Tockington",
  "id": "79718",
  "bbox": [
    -2.566262,
    51.575587,
    -2.566262,
    51.575587
  ],
  "description": "An ancient place, cited: BAtlas 8 E3 Tockington",
  "features": [
    {
      "type": "Feature",
      "geometry": {
        "type": "Point",
        "coordinates": [
          -2.566262,
          51.575587
        ]
      },
      "properties": {
        "description": "representative point"
      }
    },
    {
      "geometry": {
        "type": "Point",
        "coordinates": [
          -2.566262,
          51.575587
        ]
      },
      "id": "darmc-location-21121",
      "type": "Feature",
      "properties": {
        "description": "1M scale point location",
        "location_precision": "precise",
        "title": "DARMC location 21121",
        "link": "http://pleiades.stoa.org/places/79718/darmc-location-21121"
      }
    }
  ]
}