{
  "type": "FeatureCollection",
  "title": "Thruxton",
  "id": "79713",
  "description": "An ancient place, cited: BAtlas 8 F3 Thruxton",
  "bbox": [
    -1.584379,
    51.208795,
    -1.584379,
    51.208795
  ],
  "reprPoint": [
    -1.584379,
    51.208795
  ],
  "features": [
    {
      "geometry": {
        "type": "Point",
        "coordinates": [
          -1.584379,
          51.208795
        ]
      },
      "id": "darmc-location-21117",
      "type": "Feature",
      "properties": {
        "description": "1M scale point location",
        "location_precision": "precise",
        "title": "DARMC location 21117",
        "link": "http://pleiades.stoa.org/places/79713/darmc-location-21117"
      }
    }
  ]
}