{
  "type": "FeatureCollection",
  "title": "Uxacona",
  "id": "79727",
  "description": "An ancient place, cited: BAtlas 8 E2 Uxacona",
  "bbox": [
    -2.41121,
    52.69516,
    -2.41121,
    52.69516
  ],
  "connectsWith": [
    "491855883"
  ],
  "reprPoint": [
    -2.41121,
    52.69516
  ],
  "names": [
    "Uxacona"
  ],
  "features": [
    {
      "geometry": {
        "type": "Point",
        "coordinates": [
          -2.402825,
          52.695037
        ]
      },
      "id": "darmc-location-4546",
      "type": "Feature",
      "properties": {
        "description": "1M scale point location",
        "location_precision": "precise",
        "title": "DARMC location 4546",
        "link": "http://pleiades.stoa.org/places/79727/darmc-location-4546"
      }
    },
    {
      "geometry": {
        "type": "Point",
        "coordinates": [
          -2.41121,
          52.69516
        ]
      },
      "id": "dare-location",
      "type": "Feature",
      "properties": {
        "description": "Representative point location, site precision",
        "location_precision": "precise",
        "title": "DARE Location",
        "link": "http://pleiades.stoa.org/places/79727/dare-location"
      }
    }
  ]
}