{
  "type": "FeatureCollection",
  "title": "Venta",
  "id": "79734",
  "description": "An ancient place, cited: BAtlas 8 F3 Venta",
  "bbox": [
    -1.3236537,
    51.063,
    -1.317,
    51.0656286
  ],
  "reprPoint": [
    -1.32032685,
    51.0643143
  ],
  "names": [
    "Venta"
  ],
  "features": [
    {
      "geometry": {
        "type": "Point",
        "coordinates": [
          -1.3236537,
          51.0656286
        ]
      },
      "id": "location-of-orams-arbour",
      "type": "Feature",
      "properties": {
        "description": "Oram's Arbour, now a park, was the site of Iron Age occupation prior to the establishment of Venta. Location based on OpenStreetMap.",
        "location_precision": "precise",
        "title": "location of Oram's Arbour",
        "link": "http://pleiades.stoa.org/places/79734/location-of-orams-arbour"
      }
    },
    {
      "geometry": {
        "type": "Point",
        "coordinates": [
          -1.317,
          51.063
        ]
      },
      "id": "location-of-venta",
      "type": "Feature",
      "properties": {
        "description": "coordinates after GeoHack.",
        "location_precision": "precise",
        "title": "location of Venta",
        "link": "http://pleiades.stoa.org/places/79734/location-of-venta"
      }
    }
  ]
}