{
  "type": "FeatureCollection",
  "title": "Venta",
  "id": "79734",
  "bbox": [
    -1.317,
    51.063,
    -1.317,
    51.063
  ],
  "description": "An ancient place, cited: BAtlas 8 F3 Venta",
  "names": [
    "Venta"
  ],
  "features": [
    {
      "type": "Feature",
      "geometry": {
        "type": "Point",
        "coordinates": [
          -1.317,
          51.063
        ]
      },
      "properties": {
        "description": "representative point"
      }
    },
    {
      "geometry": {
        "type": "Point",
        "coordinates": [
          -1.317,
          51.063
        ]
      },
      "id": "location-of-venta",
      "type": "Feature",
      "properties": {
        "description": "coordinates after GeoHack.",
        "location_precision": "precise",
        "title": "location of Venta",
        "link": "http://pleiades.stoa.org/places/79734/location-of-venta"
      }
    }
  ]
}