{
  "type": "FeatureCollection",
  "title": "Kissonerga-Skalia",
  "id": "797419069",
  "bbox": [
    32.3966814,
    34.8225461,
    32.3966814,
    34.8225461
  ],
  "description": "Kissonerga-Skalia is an archaeological site dating to the Early Middle Cypriot Bronze Age (EM-MC ca. 2400-1650 B.C.) located north of Paphos, Cyprus.",
  "connectsWith": [
    "707498"
  ],
  "features": [
    {
      "type": "Feature",
      "geometry": {
        "type": "Point",
        "coordinates": [
          32.3966814,
          34.8225461
        ]
      },
      "properties": {
        "description": "representative point"
      }
    },
    {
      "geometry": {
        "type": "Point",
        "coordinates": [
          32.3966814,
          34.8225461
        ]
      },
      "id": "location-of-kissonerga-skalia",
      "type": "Feature",
      "properties": {
        "description": "Representative location based on OpenStreetMap.",
        "location_precision": "precise",
        "title": "OSM location of Kissonerga-Skalia",
        "link": "http://pleiades.stoa.org/places/797419069/location-of-kissonerga-skalia"
      }
    }
  ]
}