{
  "type": "FeatureCollection",
  "title": "Wanborough",
  "id": "79746",
  "description": "An ancient place, cited: BAtlas 8 G3 Wanborough",
  "bbox": [
    -0.664466,
    51.23152,
    -0.664466,
    51.23152
  ],
  "reprPoint": [
    -0.664466,
    51.23152
  ],
  "features": [
    {
      "geometry": {
        "type": "Point",
        "coordinates": [
          -0.664466,
          51.23152
        ]
      },
      "id": "darmc-location-20680",
      "type": "Feature",
      "properties": {
        "description": "1M scale point location",
        "location_precision": "precise",
        "title": "DARMC location 20680",
        "link": "http://pleiades.stoa.org/places/79746/darmc-location-20680"
      }
    }
  ]
}