{
  "type": "FeatureCollection",
  "title": "Walton Castle",
  "id": "79744",
  "bbox": [
    1.349271,
    51.961201,
    1.349271,
    51.961201
  ],
  "description": "The site of a Roman Saxon Shore fort known as \"Walton Castle\". The fort was built ca. A.D. 276-285 and was destroyed by sea erosion in the eighteenth century.",
  "features": [
    {
      "type": "Feature",
      "geometry": {
        "type": "Point",
        "coordinates": [
          1.349271,
          51.961201
        ]
      },
      "properties": {
        "description": "representative point"
      }
    },
    {
      "geometry": {
        "type": "Point",
        "coordinates": [
          1.349271,
          51.961201
        ]
      },
      "id": "darmc-location-19227",
      "type": "Feature",
      "properties": {
        "description": "1M scale point location",
        "location_precision": "precise",
        "title": "DARMC location 19227",
        "link": "http://pleiades.stoa.org/places/79744/darmc-location-19227"
      }
    }
  ]
}