{
  "type": "FeatureCollection",
  "title": "Walton Castle",
  "id": "79744",
  "description": "An ancient place, cited: BAtlas 8 I3 Walton Castle",
  "bbox": [
    1.349271,
    51.961201,
    1.349271,
    51.961201
  ],
  "reprPoint": [
    1.349271,
    51.961201
  ],
  "features": [
    {
      "geometry": {
        "type": "Point",
        "coordinates": [
          1.349271,
          51.961201
        ]
      },
      "id": "darmc-location-19227",
      "type": "Feature",
      "properties": {
        "description": "1M scale point location",
        "location_precision": "precise",
        "title": "DARMC location 19227",
        "link": "http://pleiades.stoa.org/places/79744/darmc-location-19227"
      }
    }
  ]
}