{
  "type": "FeatureCollection",
  "title": "Walton Castle",
  "id": "79744",
  "bbox": [
    1.3898991,
    51.9778756,
    1.3898991,
    51.9778756
  ],
  "description": "The site of a Roman Saxon Shore fort known as \"Walton Castle\". The fort was built ca. A.D. 276-285 and was destroyed by sea erosion in the eighteenth century.",
  "features": [
    {
      "type": "Feature",
      "geometry": {
        "type": "Point",
        "coordinates": [
          1.3898991,
          51.9778756
        ]
      },
      "properties": {
        "description": "representative point"
      }
    },
    {
      "geometry": {
        "type": "Point",
        "coordinates": [
          1.3898991,
          51.9778756
        ]
      },
      "id": "osm-location-of-walton-castle-ruin",
      "type": "Feature",
      "properties": {
        "description": "Representative location based on OpenStreetMap",
        "location_precision": "precise",
        "title": "OSM location of Walton Castle (ruin)",
        "link": "http://pleiades.stoa.org/places/79744/osm-location-of-walton-castle-ruin"
      }
    }
  ]
}