{
  "type": "FeatureCollection",
  "title": "West Dean",
  "id": "79751",
  "description": "An ancient place, cited: BAtlas 8 F3 West Dean",
  "bbox": [
    -1.63374,
    51.041175,
    -1.63374,
    51.041175
  ],
  "reprPoint": [
    -1.63374,
    51.041175
  ],
  "features": [
    {
      "geometry": {
        "type": "Point",
        "coordinates": [
          -1.63374,
          51.041175
        ]
      },
      "id": "darmc-location-21157",
      "type": "Feature",
      "properties": {
        "description": "1M scale point location",
        "location_precision": "precise",
        "title": "DARMC location 21157",
        "link": "http://pleiades.stoa.org/places/79751/darmc-location-21157"
      }
    }
  ]
}