{
  "type": "FeatureCollection",
  "title": "Gate at Hag. Dimitrios Loumbardiaris/Gate XIV",
  "id": "799093248",
  "bbox": [
    23.7202,
    37.9699,
    23.7202,
    37.9699
  ],
  "description": "A gate in the Diateichisma wall of Athens, built in the 280s or 270s B.C.",
  "connectsWith": [
    "968858713",
    "579885"
  ],
  "names": [
    "Gate at Hag. Dimitrios Loumbardiaris",
    "Gate XIV",
    "Dipylon-above-the-Gates"
  ],
  "features": [
    {
      "type": "Feature",
      "geometry": {
        "type": "Point",
        "coordinates": [
          23.7202,
          37.9699
        ]
      },
      "properties": {
        "description": "representative point"
      }
    },
    {
      "geometry": {
        "type": "Point",
        "coordinates": [
          23.7202,
          37.9699
        ]
      },
      "id": "topostext-location-gate-xiv-dipylon",
      "type": "Feature",
      "properties": {
        "description": null,
        "location_precision": "precise",
        "title": "ToposText Location: Gate XIV Dipylon",
        "link": "http://pleiades.stoa.org/places/799093248/topostext-location-gate-xiv-dipylon"
      }
    }
  ]
}