{
  "type": "FeatureCollection",
  "title": "Rathgall Hillfort",
  "id": "799667224",
  "bbox": [
    -6.6631296,
    52.8029667,
    -6.6631296,
    52.8029667
  ],
  "description": "Rathgall Hillfort is a multivallate Bronze Age fort located in County Wicklow, Province of Leinster, Ireland.",
  "connectsWith": [
    "20487"
  ],
  "features": [
    {
      "type": "Feature",
      "geometry": {
        "type": "Point",
        "coordinates": [
          -6.6631296,
          52.8029667
        ]
      },
      "properties": {
        "description": "representative point"
      }
    },
    {
      "geometry": {
        "type": "Point",
        "coordinates": [
          -6.6631296,
          52.8029667
        ]
      },
      "id": "osm-location",
      "type": "Feature",
      "properties": {
        "description": "Representative location based on OpenStreetMap.",
        "location_precision": "precise",
        "title": "OSM location of Rathgall Hillfort",
        "link": "http://pleiades.stoa.org/places/799667224/osm-location"
      }
    }
  ]
}