{
  "type": "FeatureCollection",
  "title": "Alana",
  "id": "805590",
  "description": "An ancient place, cited: BAtlas 82 D3 Alana",
  "bbox": [
    33.947411,
    18.239561,
    33.947411,
    18.239561
  ],
  "reprPoint": [
    33.947411,
    18.239561
  ],
  "names": [
    "Alana"
  ],
  "features": [
    {
      "geometry": {
        "type": "Point",
        "coordinates": [
          33.947411,
          18.239561
        ]
      },
      "id": "darmc-location-21396",
      "type": "Feature",
      "properties": {
        "description": "Point location",
        "location_precision": "precise",
        "title": "DARMC location 21396",
        "link": "http://pleiades.stoa.org/places/805590/darmc-location-21396"
      }
    }
  ]
}