{
  "type": "FeatureCollection",
  "title": "Breues",
  "id": "805598",
  "description": "An ancient place, cited: BAtlas 82 A3 Breues",
  "bbox": [
    30.676377,
    18.523605,
    30.676377,
    18.523605
  ],
  "reprPoint": [
    30.676377,
    18.523605
  ],
  "names": [
    "Breues"
  ],
  "features": [
    {
      "geometry": {
        "type": "Point",
        "coordinates": [
          30.676377,
          18.523605
        ]
      },
      "id": "darmc-location-21381",
      "type": "Feature",
      "properties": {
        "description": "Point location",
        "location_precision": "precise",
        "title": "DARMC location 21381",
        "link": "http://pleiades.stoa.org/places/805598/darmc-location-21381"
      }
    }
  ]
}