{
  "type": "FeatureCollection",
  "title": "Abale",
  "id": "805587",
  "description": "An ancient place, cited: BAtlas 82 D4 Abale",
  "bbox": [
    33.975361,
    17.682319,
    33.975361,
    17.682319
  ],
  "reprPoint": [
    33.975361,
    17.682319
  ],
  "names": [
    "Abale"
  ],
  "features": [
    {
      "geometry": {
        "type": "Point",
        "coordinates": [
          33.975361,
          17.682319
        ]
      },
      "id": "darmc-location-21366",
      "type": "Feature",
      "properties": {
        "description": "Point location",
        "location_precision": "precise",
        "title": "DARMC location 21366",
        "link": "http://pleiades.stoa.org/places/805587/darmc-location-21366"
      }
    }
  ]
}