{
  "type": "FeatureCollection",
  "title": "el Kurru",
  "id": "805623",
  "description": "el Kurru is the site of a necropolis used by Nubian royalty. Many of the royal tombs date to the Kushite period.",
  "bbox": [
    31.770152,
    18.408769,
    31.7709239,
    18.4094923
  ],
  "reprPoint": [
    31.77053795,
    18.40913065
  ],
  "features": [
    {
      "geometry": {
        "type": "Point",
        "coordinates": [
          31.770152,
          18.408769
        ]
      },
      "id": "darmc-location-21391",
      "type": "Feature",
      "properties": {
        "description": "Point location",
        "location_precision": "precise",
        "title": "DARMC location 21391",
        "link": "http://pleiades.stoa.org/places/805623/darmc-location-21391"
      }
    }
  ]
}