{
  "type": "FeatureCollection",
  "title": "Omar Kabash",
  "id": "805642",
  "bbox": [
    33.342538,
    20.240402,
    33.342538,
    20.240402
  ],
  "description": "An ancient place, cited: BAtlas 82 D1 Omar Kabash",
  "features": [
    {
      "type": "Feature",
      "geometry": {
        "type": "Point",
        "coordinates": [
          33.342538,
          20.240402
        ]
      },
      "properties": {
        "description": "representative point"
      }
    },
    {
      "geometry": {
        "type": "Point",
        "coordinates": [
          33.342538,
          20.240402
        ]
      },
      "id": "darmc-location-21419",
      "type": "Feature",
      "properties": {
        "description": "Point location",
        "location_precision": "precise",
        "title": "DARMC location 21419",
        "link": "http://pleiades.stoa.org/places/805642/darmc-location-21419"
      }
    }
  ]
}