{
  "type": "FeatureCollection",
  "title": "Nigeim",
  "id": "805637",
  "bbox": [
    34.266666,
    19.483333,
    34.266666,
    19.483333
  ],
  "description": "An ancient place, cited: BAtlas 82 E2 Nigeim",
  "features": [
    {
      "type": "Feature",
      "geometry": {
        "type": "Point",
        "coordinates": [
          34.266666,
          19.483333
        ]
      },
      "properties": {
        "description": "representative point"
      }
    },
    {
      "geometry": {
        "type": "Point",
        "coordinates": [
          34.266666,
          19.483333
        ]
      },
      "id": "darmc-location-21418",
      "type": "Feature",
      "properties": {
        "description": "Point location",
        "location_precision": "precise",
        "title": "DARMC location 21418",
        "link": "http://pleiades.stoa.org/places/805637/darmc-location-21418"
      }
    }
  ]
}