{
  "type": "FeatureCollection",
  "title": "el Kurru",
  "id": "805623",
  "bbox": [
    31.770152,
    18.408769,
    31.7704612,
    18.4089057
  ],
  "description": "El-Kurru is the site of a necropolis used by Nubian royalty. Many of the royal tombs date to the Kushite period.",
  "features": [
    {
      "type": "Feature",
      "geometry": {
        "type": "Point",
        "coordinates": [
          31.7703066,
          18.40883735
        ]
      },
      "properties": {
        "description": "representative point"
      }
    },
    {
      "geometry": {
        "type": "Point",
        "coordinates": [
          31.770152,
          18.408769
        ]
      },
      "id": "darmc-location-21391",
      "type": "Feature",
      "properties": {
        "description": "Point location",
        "location_precision": "precise",
        "title": "DARMC location 21391",
        "link": "http://pleiades.stoa.org/places/805623/darmc-location-21391"
      }
    },
    {
      "geometry": {
        "type": "Point",
        "coordinates": [
          31.7704612,
          18.4089057
        ]
      },
      "id": "osm-location-of-el-kurru",
      "type": "Feature",
      "properties": {
        "description": "Location based on OpenStreetMap",
        "location_precision": "precise",
        "title": "OSM location of El Kurru",
        "link": "http://pleiades.stoa.org/places/805623/osm-location-of-el-kurru"
      }
    }
  ]
}