{
  "type": "FeatureCollection",
  "title": "Napata",
  "id": "805634",
  "description": "Napata was a Nubian city-state located on the west bank of the Nile River and founded in the fifteenth century BC.",
  "bbox": [
    31.853738,
    18.565952,
    31.853738,
    18.565952
  ],
  "connectsWith": [
    "cc1a6a9430d38c6c9bb8bf5f0241b598",
    "916d0a32739f9ffef352b3ae27582edc"
  ],
  "reprPoint": [
    31.853738,
    18.565952
  ],
  "names": [
    "Napata"
  ],
  "features": [
    {
      "geometry": {
        "type": "Point",
        "coordinates": [
          31.853738,
          18.565952
        ]
      },
      "id": "darmc-location-21392",
      "type": "Feature",
      "properties": {
        "description": "Point location",
        "location_precision": "precise",
        "title": "DARMC location 21392",
        "link": "http://pleiades.stoa.org/places/805634/darmc-location-21392"
      }
    }
  ]
}