{
  "type": "FeatureCollection",
  "title": "Napata",
  "id": "805634",
  "bbox": [
    31.853738,
    18.565952,
    31.853738,
    18.565952
  ],
  "description": "Napata was a Nubian city-state located on the west bank of the Nile River and founded in the fifteenth century B.C.",
  "connectsWith": [
    "508356079",
    "727172",
    "827790769"
  ],
  "names": [
    "Napata",
    "Napata"
  ],
  "features": [
    {
      "type": "Feature",
      "geometry": {
        "type": "Point",
        "coordinates": [
          31.853738,
          18.565952
        ]
      },
      "properties": {
        "description": "representative point"
      }
    },
    {
      "geometry": {
        "type": "Point",
        "coordinates": [
          31.853738,
          18.565952
        ]
      },
      "id": "darmc-location-21392",
      "type": "Feature",
      "properties": {
        "description": "Point location",
        "location_precision": "precise",
        "title": "DARMC location 21392",
        "link": "http://pleiades.stoa.org/places/805634/darmc-location-21392"
      }
    }
  ]
}