{
  "type": "FeatureCollection",
  "title": "Segasa",
  "id": "805654",
  "bbox": [
    30.824219,
    18.146555,
    30.824219,
    18.146555
  ],
  "description": "An ancient place, cited: BAtlas 82 A3 Segasa",
  "names": [
    "Segasa",
    "Segusa"
  ],
  "features": [
    {
      "type": "Feature",
      "geometry": {
        "type": "Point",
        "coordinates": [
          30.824219,
          18.146555
        ]
      },
      "properties": {
        "description": "representative point"
      }
    },
    {
      "geometry": {
        "type": "Point",
        "coordinates": [
          30.824219,
          18.146555
        ]
      },
      "id": "darmc-location-21384",
      "type": "Feature",
      "properties": {
        "description": "Point location",
        "location_precision": "precise",
        "title": "DARMC location 21384",
        "link": "http://pleiades.stoa.org/places/805654/darmc-location-21384"
      }
    }
  ]
}