{
  "type": "FeatureCollection",
  "title": "Meroe",
  "id": "805630",
  "bbox": [
    33.70098,
    16.911636,
    33.70098,
    16.911636
  ],
  "description": "Meroë is ancient city on the east bank of the Nile river near Shendi, Sudan. The city was a center of the kingdom of Kush.",
  "connectsWith": [
    "727172"
  ],
  "names": [
    "Meroe"
  ],
  "features": [
    {
      "type": "Feature",
      "geometry": {
        "type": "Point",
        "coordinates": [
          33.70098,
          16.911636
        ]
      },
      "properties": {
        "description": "representative point"
      }
    },
    {
      "geometry": {
        "type": "Point",
        "coordinates": [
          33.70098,
          16.911636
        ]
      },
      "id": "darmc-location-21407",
      "type": "Feature",
      "properties": {
        "description": "Point location",
        "location_precision": "precise",
        "title": "DARMC location 21407",
        "link": "http://pleiades.stoa.org/places/805630/darmc-location-21407"
      }
    }
  ]
}