{
  "type": "FeatureCollection",
  "title": "Zamnes",
  "id": "805666",
  "description": "An ancient place, cited: BAtlas 82 B4 Zamnes",
  "bbox": [
    31.127186,
    17.999997,
    31.127186,
    17.999997
  ],
  "reprPoint": [
    31.127186,
    17.999997
  ],
  "names": [
    "Zamnes"
  ],
  "features": [
    {
      "geometry": {
        "type": "Point",
        "coordinates": [
          31.127186,
          17.999997
        ]
      },
      "id": "darmc-location-21386",
      "type": "Feature",
      "properties": {
        "description": "Point location",
        "location_precision": "precise",
        "title": "DARMC location 21386",
        "link": "http://pleiades.stoa.org/places/805666/darmc-location-21386"
      }
    }
  ]
}