{
  "type": "FeatureCollection",
  "title": "Drepanon Cemetery",
  "id": "807935494",
  "bbox": [
    21.8535539027,
    38.319612879,
    21.8535539027,
    38.319612879
  ],
  "description": "An ancient cemetery at modern Drepano in Greece, uncovered in rescue excavations since the 1970s.",
  "names": [
    "Drepano"
  ],
  "features": [
    {
      "type": "Feature",
      "geometry": {
        "type": "Point",
        "coordinates": [
          21.8535539027,
          38.319612879
        ]
      },
      "properties": {
        "description": "representative point"
      }
    },
    {
      "geometry": {
        "type": "Point",
        "coordinates": [
          21.85355390272261,
          38.319612879048115
        ]
      },
      "id": "imagery-location-of-the-center-of-the-cemetery",
      "type": "Feature",
      "properties": {
        "description": "Point marking the center of the cemetery (the Orthodox church), after Maniaki 2019",
        "location_precision": "precise",
        "title": "Imagery location of the center of the cemetery",
        "link": "http://pleiades.stoa.org/places/807935494/imagery-location-of-the-center-of-the-cemetery"
      }
    }
  ]
}