{
  "type": "FeatureCollection",
  "title": "Santu Misirinu",
  "id": "807933372",
  "bbox": [
    17.8607128,
    40.480012,
    17.8607128,
    40.480012
  ],
  "description": "An octagonal structure covered by a cupola, dating between the second and sixth centuries A.D.",
  "features": [
    {
      "type": "Feature",
      "geometry": {
        "type": "Point",
        "coordinates": [
          17.8607128,
          40.480012
        ]
      },
      "properties": {
        "description": "representative point"
      }
    },
    {
      "geometry": {
        "type": "Point",
        "coordinates": [
          17.8607128,
          40.480012
        ]
      },
      "id": "location-of-temple",
      "type": "Feature",
      "properties": {
        "description": "Representative location based on OpenStreetMap.",
        "location_precision": "precise",
        "title": "OSM location of so-called \"Tempietto di San Miserino\"",
        "link": "http://pleiades.stoa.org/places/807933372/location-of-temple"
      }
    }
  ]
}