{
  "type": "FeatureCollection",
  "title": "Dargues",
  "id": "811686778",
  "bbox": [
    -2.221652,
    55.237716,
    -2.221652,
    55.237716
  ],
  "description": "The remains of the earthworks of a Roman temporary camp.",
  "connectsWith": [
    "82519025"
  ],
  "features": [
    {
      "type": "Feature",
      "geometry": {
        "type": "Point",
        "coordinates": [
          -2.221652,
          55.237716
        ]
      },
      "properties": {
        "description": "representative point"
      }
    },
    {
      "geometry": {
        "type": "Point",
        "coordinates": [
          -2.221652,
          55.237716
        ]
      },
      "id": "location-of-roman-camp",
      "type": "Feature",
      "properties": {
        "description": "Representative location based on OpenStreetMap.",
        "location_precision": "precise",
        "title": "OSM location of Dargues Roman camp",
        "link": "http://pleiades.stoa.org/places/811686778/location-of-roman-camp"
      }
    }
  ]
}