{
  "type": "FeatureCollection",
  "title": "Dun Carloway",
  "id": "814454572",
  "bbox": [
    -6.7939551,
    58.2696017,
    -6.7939551,
    58.2696017
  ],
  "description": "Dun Carloway Broch is a well preserved broch in Scotland that was in use from ca. the first century BC until ca. AD 1300.",
  "features": [
    {
      "type": "Feature",
      "geometry": {
        "type": "Point",
        "coordinates": [
          -6.7939551,
          58.2696017
        ]
      },
      "properties": {
        "description": "representative point"
      }
    },
    {
      "geometry": {
        "type": "Point",
        "coordinates": [
          -6.7939551,
          58.2696017
        ]
      },
      "id": "location-of-dun-carloway",
      "type": "Feature",
      "properties": {
        "description": "Location based on OpenStreetMap",
        "location_precision": "precise",
        "title": "location of Dun Carloway",
        "link": "http://pleiades.stoa.org/places/814454572/location-of-dun-carloway"
      }
    }
  ]
}