{
  "type": "FeatureCollection",
  "title": "Baclanaza",
  "id": "814662",
  "description": "An ancient place, cited: BAtlas 83 B3 Baclanaza",
  "bbox": [
    36.572302,
    28.3857,
    36.573203,
    28.390393
  ],
  "reprPoint": [
    36.5727525,
    28.3880465
  ],
  "names": [
    "Baclanaza",
    "Tabūk",
    "Ostama",
    "Baclanaza"
  ],
  "features": [
    {
      "geometry": {
        "type": "Point",
        "coordinates": [
          36.572302,
          28.3857
        ]
      },
      "id": "darmc-location-20010",
      "type": "Feature",
      "properties": {
        "description": "5M scale point location",
        "location_precision": "precise",
        "title": "DARMC location 20010",
        "link": "http://pleiades.stoa.org/places/814662/darmc-location-20010"
      }
    },
    {
      "geometry": {
        "type": "Point",
        "coordinates": [
          36.573203,
          28.390393
        ]
      },
      "id": "darmc-location-21194",
      "type": "Feature",
      "properties": {
        "description": "Point location",
        "location_precision": "precise",
        "title": "DARMC location 21194",
        "link": "http://pleiades.stoa.org/places/814662/darmc-location-21194"
      }
    }
  ]
}