{
  "type": "FeatureCollection",
  "title": "al-Bada'i'",
  "id": "814663",
  "bbox": [
    38.077748,
    26.506311,
    38.077748,
    26.506311
  ],
  "description": "An ancient place, cited: BAtlas 83 D5 al-Bada'i'",
  "features": [
    {
      "type": "Feature",
      "geometry": {
        "type": "Point",
        "coordinates": [
          38.077748,
          26.506311
        ]
      },
      "properties": {
        "description": "representative point"
      }
    },
    {
      "geometry": {
        "type": "Point",
        "coordinates": [
          38.077748,
          26.506311
        ]
      },
      "id": "darmc-location-32764",
      "type": "Feature",
      "properties": {
        "description": "  scale point location",
        "location_precision": "precise",
        "title": "DARMC location 32764",
        "link": "http://pleiades.stoa.org/places/814663/darmc-location-32764"
      }
    }
  ]
}