{
  "type": "FeatureCollection",
  "title": "Chibanes",
  "id": "81527249",
  "bbox": [
    -8.9176243,
    38.5643375,
    -8.9176243,
    38.5643375
  ],
  "description": "A fortified site in use from the third millennium BC to the Roman period.",
  "features": [
    {
      "type": "Feature",
      "geometry": {
        "type": "Point",
        "coordinates": [
          -8.9176243,
          38.5643375
        ]
      },
      "properties": {
        "description": "representative point"
      }
    },
    {
      "geometry": {
        "type": "Point",
        "coordinates": [
          -8.9176243,
          38.5643375
        ]
      },
      "id": "osm-location",
      "type": "Feature",
      "properties": {
        "description": "Location based on OpenStreetMap",
        "location_precision": "precise",
        "title": "OSM location",
        "link": "http://pleiades.stoa.org/places/81527249/osm-location"
      }
    }
  ]
}