{
  "type": "FeatureCollection",
  "title": "San Pietro a Badia Pozzeveri",
  "id": "81533409",
  "bbox": [
    10.6559363,
    43.8206237,
    10.6559363,
    43.8206237
  ],
  "description": "An abbey with tenth century origins connected to the pilgrimage route known as the Via Francigena.",
  "features": [
    {
      "type": "Feature",
      "geometry": {
        "type": "Point",
        "coordinates": [
          10.6559363,
          43.8206237
        ]
      },
      "properties": {
        "description": "representative point"
      }
    },
    {
      "geometry": {
        "type": "Point",
        "coordinates": [
          10.6559363,
          43.8206237
        ]
      },
      "id": "location-of-san-pietro-a-badia-pozzeveri",
      "type": "Feature",
      "properties": {
        "description": "Location based on OpenStreetMap",
        "location_precision": "precise",
        "title": "location of San Pietro a Badia Pozzeveri",
        "link": "http://pleiades.stoa.org/places/81533409/location-of-san-pietro-a-badia-pozzeveri"
      }
    }
  ]
}