{
  "type": "FeatureCollection",
  "title": "Cahercommaun",
  "id": "815733688",
  "bbox": [
    -9.0703947,
    53.0145498,
    -9.0703947,
    53.0145498
  ],
  "description": "A triple stone ringfort built ca. AD 800.",
  "connectsWith": [
    "20487"
  ],
  "features": [
    {
      "type": "Feature",
      "geometry": {
        "type": "Point",
        "coordinates": [
          -9.0703947,
          53.0145498
        ]
      },
      "properties": {
        "description": "representative point"
      }
    },
    {
      "geometry": {
        "type": "Point",
        "coordinates": [
          -9.0703947,
          53.0145498
        ]
      },
      "id": "osm-location",
      "type": "Feature",
      "properties": {
        "description": "Representative location based on OpenStreetMap.",
        "location_precision": "precise",
        "title": "OSM location of Cahercommaun Ring Fort",
        "link": "http://pleiades.stoa.org/places/815733688/osm-location"
      }
    }
  ]
}