{
  "type": "FeatureCollection",
  "title": "Mikro Kameni",
  "id": "815794667",
  "description": "Mikro Kameni is a non-extant island that was formed in the Santorini caldera some time before 1851, when it was attested in the Admiralty Chart of Robert Graves, HMS Volgae. It was joined to Nea Kameni at some point after this, probably in the major period of volcanic activity in 1866-1870.",
  "bbox": [
    25.407,
    36.411,
    25.407,
    36.411
  ],
  "connectsWith": [
    "808255902"
  ],
  "reprPoint": [
    25.407,
    36.411
  ],
  "features": [
    {
      "geometry": {
        "type": "Point",
        "coordinates": [
          25.407,
          36.411
        ]
      },
      "id": "mikro-kameni",
      "type": "Feature",
      "properties": {
        "description": "Mikro Kameni is a non-extant island that was formed in the Santorini caldera some time before 1851, when it was attested, mapped and named in the Admiralty Chart of Thomas Graves, HMS Volgae. It was joined to Nea Kameni at some point after this, probably in the major period of volcanic activity in 1866-1870.",
        "location_precision": "precise",
        "title": "Mikro Kameni",
        "link": "http://pleiades.stoa.org/places/815794667/mikro-kameni"
      }
    }
  ]
}