{
  "type": "FeatureCollection",
  "title": "Mount Mugh",
  "id": "816647928",
  "bbox": [
    68.273353,
    39.439081,
    68.273353,
    39.439081
  ],
  "description": "Small, remote mountain peak in Tajikistan with a castle used in the 7th-8th centuries CE as a refuge by the Sogdian rulers of Panjakent. The site was the source of a major find of Sogdian documents.",
  "features": [
    {
      "type": "Feature",
      "geometry": {
        "type": "Point",
        "coordinates": [
          68.273353,
          39.439081
        ]
      },
      "properties": {
        "description": "representative point"
      }
    },
    {
      "geometry": {
        "type": "Point",
        "coordinates": [
          68.273353,
          39.439081
        ]
      },
      "id": "approximate-imagery-location-of-mount-mugh",
      "type": "Feature",
      "properties": {
        "description": "Approximate imagery location based on Google Earth representing Mount Mugh after Lurje 2019.",
        "location_precision": "precise",
        "title": "Approximate imagery location of Mount Mugh Fortress",
        "link": "http://pleiades.stoa.org/places/816647928/approximate-imagery-location-of-mount-mugh"
      }
    }
  ]
}