{
  "type": "FeatureCollection",
  "title": "Lucera Castle",
  "id": "817071134",
  "bbox": [
    15.3225689,
    41.5083613,
    15.3225689,
    41.5083613
  ],
  "description": "A castle originally built by Frederick II, Holy Roman Emperor in AD 1233.",
  "connectsWith": [
    "442640"
  ],
  "features": [
    {
      "type": "Feature",
      "geometry": {
        "type": "Point",
        "coordinates": [
          15.3225689,
          41.5083613
        ]
      },
      "properties": {
        "description": "representative point"
      }
    },
    {
      "geometry": {
        "type": "Point",
        "coordinates": [
          15.3225689,
          41.5083613
        ]
      },
      "id": "location-of-lucera-castle",
      "type": "Feature",
      "properties": {
        "description": "A castle originally built by Frederick II, Holy Roman Emperor in AD 1233. Location based on OpenStreetMap.",
        "location_precision": "precise",
        "title": "location of Lucera Castle",
        "link": "http://pleiades.stoa.org/places/817071134/location-of-lucera-castle"
      }
    }
  ]
}