{
  "type": "FeatureCollection",
  "title": "Shunet ez Zebib",
  "id": "819299274",
  "bbox": [
    31.9084936,
    26.1888854,
    31.9084936,
    26.1888854
  ],
  "description": "A large mudbrick structure located at Abydos in Upper Egypt that dates to the Second Dynasty (ca. 2700 B.C.) of ancient Egypt.",
  "connectsWith": [
    "756512"
  ],
  "features": [
    {
      "type": "Feature",
      "geometry": {
        "type": "Point",
        "coordinates": [
          31.9084936,
          26.1888854
        ]
      },
      "properties": {
        "description": "representative point"
      }
    },
    {
      "geometry": {
        "type": "Point",
        "coordinates": [
          31.9084936,
          26.1888854
        ]
      },
      "id": "location-of-shunet-ez-zebib",
      "type": "Feature",
      "properties": {
        "description": "Location based on OpenStreetMap",
        "location_precision": "precise",
        "title": "OSM location of Shunet ez Zebib",
        "link": "http://pleiades.stoa.org/places/819299274/location-of-shunet-ez-zebib"
      }
    }
  ]
}