{
  "type": "FeatureCollection",
  "title": "Porta Consolare",
  "id": "820236688",
  "bbox": [
    12.6729529,
    42.9883445,
    12.6729529,
    42.9883445
  ],
  "description": "The Porta Consolare was likely the primary gateway in Hispellum's Roman-era fortification wall.",
  "connectsWith": [
    "413170"
  ],
  "features": [
    {
      "type": "Feature",
      "geometry": {
        "type": "Point",
        "coordinates": [
          12.6729529,
          42.9883445
        ]
      },
      "properties": {
        "description": "representative point"
      }
    },
    {
      "geometry": {
        "type": "Point",
        "coordinates": [
          12.6729529,
          42.9883445
        ]
      },
      "id": "location-of-porta-consolare",
      "type": "Feature",
      "properties": {
        "description": "Location based on OpenStreetMap",
        "location_precision": "precise",
        "title": "OSM location of Porta Consolare",
        "link": "http://pleiades.stoa.org/places/820236688/location-of-porta-consolare"
      }
    }
  ]
}