{
  "type": "FeatureCollection",
  "title": "Roman amphitheater at Sutri",
  "id": "820932073",
  "bbox": [
    12.2293009,
    42.2393124,
    12.2293009,
    42.2393124
  ],
  "description": "The Roman amphitheater at Sutri likely dates to the reign of Augustus.",
  "connectsWith": [
    "413328"
  ],
  "features": [
    {
      "type": "Feature",
      "geometry": {
        "type": "Point",
        "coordinates": [
          12.2293009,
          42.2393124
        ]
      },
      "properties": {
        "description": "representative point"
      }
    },
    {
      "geometry": {
        "type": "Point",
        "coordinates": [
          12.2293009,
          42.2393124
        ]
      },
      "id": "location-of-roman-amphitheater",
      "type": "Feature",
      "properties": {
        "description": "Location based on OpenStreetMap",
        "location_precision": "precise",
        "title": "OSM location of Roman amphitheater",
        "link": "http://pleiades.stoa.org/places/820932073/location-of-roman-amphitheater"
      }
    }
  ]
}