{
  "type": "FeatureCollection",
  "title": "Colle della Coedra",
  "id": "822068560",
  "bbox": [
    12.843599,
    41.689938,
    12.843599,
    41.689938
  ],
  "description": "A small hill in the Alban Hills that was the site of a protourban settlement of Latium covering some 265 square meters.",
  "connectsWith": [
    "824974027"
  ],
  "names": [
    "Colle della Coedra"
  ],
  "features": [
    {
      "type": "Feature",
      "geometry": {
        "type": "Point",
        "coordinates": [
          12.843599,
          41.689938
        ]
      },
      "properties": {
        "description": "representative point"
      }
    },
    {
      "geometry": {
        "type": "Point",
        "coordinates": [
          12.843599,
          41.689938
        ]
      },
      "id": "imagery-location",
      "type": "Feature",
      "properties": {
        "description": null,
        "location_precision": "precise",
        "title": "Imagery location ",
        "link": "http://pleiades.stoa.org/places/822068560/imagery-location"
      }
    }
  ]
}