{
  "type": "FeatureCollection",
  "title": "Kelsborrow Castle",
  "id": "82240558",
  "bbox": [
    -2.7013641,
    53.2025543,
    -2.7013641,
    53.2025543
  ],
  "description": "Kelsborrow Castle is an Iron Age hill fort located in the county of Cheshire in northern England.",
  "features": [
    {
      "type": "Feature",
      "geometry": {
        "type": "Point",
        "coordinates": [
          -2.7013641,
          53.2025543
        ]
      },
      "properties": {
        "description": "representative point"
      }
    },
    {
      "geometry": {
        "type": "Point",
        "coordinates": [
          -2.7013641,
          53.2025543
        ]
      },
      "id": "location-of-kelsborrow-castle-hill-fort",
      "type": "Feature",
      "properties": {
        "description": "Representative location based on OpenStreetMap.",
        "location_precision": "precise",
        "title": "OSM location of Iron Age Fort Kelsborrow Castle",
        "link": "http://pleiades.stoa.org/places/82240558/location-of-kelsborrow-castle-hill-fort"
      }
    }
  ]
}