{
  "type": "FeatureCollection",
  "title": "Kanī Jūnī",
  "id": "823618978",
  "bbox": [
    47.603,
    33.4982,
    47.603,
    33.4982
  ],
  "description": "Bronze Age site, low mound in Lorestan where cuneiform brick inscription has been found, Kanī Jūnī (II).",
  "names": [
    "Kanī Jūnī"
  ],
  "features": [
    {
      "type": "Feature",
      "geometry": {
        "type": "Point",
        "coordinates": [
          47.603,
          33.4982
        ]
      },
      "properties": {
        "description": "representative point"
      }
    },
    {
      "geometry": {
        "type": "Point",
        "coordinates": [
          47.603,
          33.4982
        ]
      },
      "id": "kani-juni-1",
      "type": "Feature",
      "properties": {
        "description": null,
        "location_precision": "precise",
        "title": "CIGS location of Kanī Jūnī",
        "link": "http://pleiades.stoa.org/places/823618978/kani-juni-1"
      }
    }
  ]
}