{
  "type": "FeatureCollection",
  "title": "Roman amphitheater at Simitthu",
  "id": "823615780",
  "bbox": [
    8.5805396,
    36.4904744,
    8.5805396,
    36.4904744
  ],
  "description": "The poorly preserved remains of an amphitheater that had likely been abandoned by the fifth century.",
  "connectsWith": [
    "315174"
  ],
  "features": [
    {
      "type": "Feature",
      "geometry": {
        "type": "Point",
        "coordinates": [
          8.5805396,
          36.4904744
        ]
      },
      "properties": {
        "description": "representative point"
      }
    },
    {
      "geometry": {
        "type": "Point",
        "coordinates": [
          8.5805396,
          36.4904744
        ]
      },
      "id": "location-of-roman-amphitheater",
      "type": "Feature",
      "properties": {
        "description": "Representative location based on OpenStreetMap.",
        "location_precision": "precise",
        "title": "OSM location of Roman amphitheater",
        "link": "http://pleiades.stoa.org/places/823615780/location-of-roman-amphitheater"
      }
    }
  ]
}