{
  "type": "FeatureCollection",
  "title": "Ishān al-Sama‘a",
  "id": "825039107",
  "bbox": [
    45.4193,
    32.0725,
    45.4193,
    32.0725
  ],
  "description": "Find place for cuneiform inscription.",
  "names": [
    "Ishān al-Sama‘a"
  ],
  "features": [
    {
      "type": "Feature",
      "geometry": {
        "type": "Point",
        "coordinates": [
          45.4193,
          32.0725
        ]
      },
      "properties": {
        "description": "representative point"
      }
    },
    {
      "geometry": {
        "type": "Point",
        "coordinates": [
          45.4193,
          32.0725
        ]
      },
      "id": "cigs-location-of-ishan-al-sama2018a",
      "type": "Feature",
      "properties": {
        "description": null,
        "location_precision": "precise",
        "title": "CIGS location of Ishān al-Sama‘a",
        "link": "http://pleiades.stoa.org/places/825039107/cigs-location-of-ishan-al-sama2018a"
      }
    }
  ]
}