{
  "type": "FeatureCollection",
  "title": "Dere Street",
  "id": "82519025",
  "bbox": [
    -3.565857,
    53.957672,
    -1.082304,
    56.011169
  ],
  "description": "Dere Street is a Roman road in northern Britain and Scotland, also known as the Via Regia. Dere Street connected Eburacum with Veluniate.",
  "features": [
    {
      "type": "Feature",
      "geometry": {
        "type": "Point",
        "coordinates": [
          -2.1470535981,
          55.1298276237
        ]
      },
      "properties": {
        "description": "representative point"
      }
    }
  ]
}