{
  "type": "FeatureCollection",
  "title": "Dere Street",
  "id": "82519025",
  "bbox": [
    -3.575497,
    53.954001,
    -1.07748,
    56.014781
  ],
  "description": "Dere Street is a Roman road in northern Britain and Scotland, also known as the Via Regia. Dere Street connected Eburacum with Veluniate.",
  "features": [
    {
      "type": "Feature",
      "geometry": {
        "type": "Point",
        "coordinates": [
          -2.01954238158,
          54.919333425
        ]
      },
      "properties": {
        "description": "representative point"
      }
    }
  ]
}