{
  "type": "FeatureCollection",
  "title": "Ashamba 3",
  "id": "825230",
  "bbox": [
    37.994904,
    44.610722,
    37.994904,
    44.610722
  ],
  "description": "An ancient place, cited: BAtlas 84 C4 Ashamba 3",
  "features": [
    {
      "type": "Feature",
      "geometry": {
        "type": "Point",
        "coordinates": [
          37.994904,
          44.610722
        ]
      },
      "properties": {
        "description": "representative point"
      }
    },
    {
      "geometry": {
        "type": "Point",
        "coordinates": [
          37.994904,
          44.610722
        ]
      },
      "id": "darmc-location-11526",
      "type": "Feature",
      "properties": {
        "description": "1M scale point location",
        "location_precision": "precise",
        "title": "DARMC location 11526",
        "link": "http://pleiades.stoa.org/places/825230/darmc-location-11526"
      }
    }
  ]
}