{
  "type": "FeatureCollection",
  "title": "Kabardinka 2",
  "id": "825281",
  "description": "An ancient place, cited: BAtlas 84 C4 Kabardinka 2",
  "bbox": [
    37.935882,
    44.635387,
    37.935882,
    44.635387
  ],
  "reprPoint": [
    37.935882,
    44.635387
  ],
  "features": [
    {
      "geometry": {
        "type": "Point",
        "coordinates": [
          37.935882,
          44.635387
        ]
      },
      "id": "darmc-location-12935",
      "type": "Feature",
      "properties": {
        "description": "1M scale point location",
        "location_precision": "precise",
        "title": "DARMC location 12935",
        "link": "http://pleiades.stoa.org/places/825281/darmc-location-12935"
      }
    }
  ]
}