{
  "type": "FeatureCollection",
  "title": "Cherepyanyy Redant",
  "id": "825246",
  "description": "An ancient place, cited: BAtlas 84 D3 Cherepyanyy Redant",
  "bbox": [
    38.395708,
    45.888468,
    38.395708,
    45.888468
  ],
  "reprPoint": [
    38.395708,
    45.888468
  ],
  "features": [
    {
      "geometry": {
        "type": "Point",
        "coordinates": [
          38.395708,
          45.888468
        ]
      },
      "id": "darmc-location-12003",
      "type": "Feature",
      "properties": {
        "description": "1M scale point location",
        "location_precision": "precise",
        "title": "DARMC location 12003",
        "link": "http://pleiades.stoa.org/places/825246/darmc-location-12003"
      }
    }
  ]
}