{
  "type": "FeatureCollection",
  "title": "Kirillovskoye",
  "id": "825295",
  "description": "An ancient place, cited: BAtlas 84 C4 Kirillovskoye",
  "bbox": [
    37.70215,
    44.800395,
    37.70215,
    44.800395
  ],
  "reprPoint": [
    37.70215,
    44.800395
  ],
  "features": [
    {
      "geometry": {
        "type": "Point",
        "coordinates": [
          37.70215,
          44.800395
        ]
      },
      "id": "darmc-location-13191",
      "type": "Feature",
      "properties": {
        "description": "1M scale point location",
        "location_precision": "precise",
        "title": "DARMC location 13191",
        "link": "http://pleiades.stoa.org/places/825295/darmc-location-13191"
      }
    }
  ]
}