{
  "type": "FeatureCollection",
  "title": "Ashamba 5",
  "id": "825232",
  "description": "An ancient place, cited: BAtlas 84 C4 Ashamba 5",
  "bbox": [
    37.989811,
    44.640623,
    37.989811,
    44.640623
  ],
  "reprPoint": [
    37.989811,
    44.640623
  ],
  "features": [
    {
      "geometry": {
        "type": "Point",
        "coordinates": [
          37.989811,
          44.640623
        ]
      },
      "id": "darmc-location-11528",
      "type": "Feature",
      "properties": {
        "description": "1M scale point location",
        "location_precision": "precise",
        "title": "DARMC location 11528",
        "link": "http://pleiades.stoa.org/places/825232/darmc-location-11528"
      }
    }
  ]
}