{
  "type": "FeatureCollection",
  "title": "Sukho-Chaltyrskoye",
  "id": "825393",
  "description": "An ancient place, cited: BAtlas 84 E1 Sukho-Chaltyrskoye",
  "bbox": [
    39.500902,
    47.245648,
    39.500902,
    47.245648
  ],
  "reprPoint": [
    39.500902,
    47.245648
  ],
  "features": [
    {
      "geometry": {
        "type": "Point",
        "coordinates": [
          39.500902,
          47.245648
        ]
      },
      "id": "darmc-location-24929",
      "type": "Feature",
      "properties": {
        "description": "1M scale point location",
        "location_precision": "precise",
        "title": "DARMC location 24929",
        "link": "http://pleiades.stoa.org/places/825393/darmc-location-24929"
      }
    }
  ]
}