{
  "type": "FeatureCollection",
  "title": "Myskhako 2",
  "id": "825333",
  "description": "An ancient place, cited: BAtlas 84 C4 Myskhako 2",
  "bbox": [
    37.747521,
    44.691363,
    37.747521,
    44.691363
  ],
  "reprPoint": [
    37.747521,
    44.691363
  ],
  "features": [
    {
      "geometry": {
        "type": "Point",
        "coordinates": [
          37.747521,
          44.691363
        ]
      },
      "id": "darmc-location-13849",
      "type": "Feature",
      "properties": {
        "description": "1M scale point location",
        "location_precision": "precise",
        "title": "DARMC location 13849",
        "link": "http://pleiades.stoa.org/places/825333/darmc-location-13849"
      }
    }
  ]
}