{
  "type": "FeatureCollection",
  "title": "Nizhne-Gnilovskoye",
  "id": "825337",
  "description": "An ancient place, cited: BAtlas 84 E1 Nizhne-Gnilovskoye",
  "bbox": [
    39.627744,
    47.188901,
    39.627744,
    47.188901
  ],
  "reprPoint": [
    39.627744,
    47.188901
  ],
  "features": [
    {
      "geometry": {
        "type": "Point",
        "coordinates": [
          39.627744,
          47.188901
        ]
      },
      "id": "darmc-location-23941",
      "type": "Feature",
      "properties": {
        "description": "1M scale point location",
        "location_precision": "precise",
        "title": "DARMC location 23941",
        "link": "http://pleiades.stoa.org/places/825337/darmc-location-23941"
      }
    }
  ]
}