{
  "type": "FeatureCollection",
  "title": "Stanitsa Natukhevskaya",
  "id": "825385",
  "description": "An ancient place, cited: BAtlas 84 C4 Stanitsa Natukhevskaya",
  "bbox": [
    37.568427,
    44.912922,
    37.568427,
    44.912922
  ],
  "reprPoint": [
    37.568427,
    44.912922
  ],
  "features": [
    {
      "geometry": {
        "type": "Point",
        "coordinates": [
          37.568427,
          44.912922
        ]
      },
      "id": "darmc-location-23535",
      "type": "Feature",
      "properties": {
        "description": "Point location",
        "location_precision": "precise",
        "title": "DARMC location 23535",
        "link": "http://pleiades.stoa.org/places/825385/darmc-location-23535"
      }
    }
  ]
}