{
  "type": "FeatureCollection",
  "title": "Temirnitskoye",
  "id": "825401",
  "description": "An ancient place, cited: BAtlas 84 E1 Temirnitskoye",
  "bbox": [
    39.672056,
    47.198298,
    39.672056,
    47.198298
  ],
  "reprPoint": [
    39.672056,
    47.198298
  ],
  "features": [
    {
      "geometry": {
        "type": "Point",
        "coordinates": [
          39.672056,
          47.198298
        ]
      },
      "id": "darmc-location-15066",
      "type": "Feature",
      "properties": {
        "description": "1M scale point location",
        "location_precision": "precise",
        "title": "DARMC location 15066",
        "link": "http://pleiades.stoa.org/places/825401/darmc-location-15066"
      }
    }
  ]
}