{
  "type": "FeatureCollection",
  "title": "Shīshīn",
  "id": "825464459",
  "bbox": [
    42.574,
    33.9716,
    42.574,
    33.9716
  ],
  "description": "Find place for cuneiform inscription.",
  "names": [
    "Shīshīn"
  ],
  "features": [
    {
      "type": "Feature",
      "geometry": {
        "type": "Point",
        "coordinates": [
          42.574,
          33.9716
        ]
      },
      "properties": {
        "description": "representative point"
      }
    },
    {
      "geometry": {
        "type": "Point",
        "coordinates": [
          42.574,
          33.9716
        ]
      },
      "id": "cigs-location-of-shishin",
      "type": "Feature",
      "properties": {
        "description": null,
        "location_precision": "precise",
        "title": "CIGS location of Shīshīn",
        "link": "http://pleiades.stoa.org/places/825464459/cigs-location-of-shishin"
      }
    }
  ]
}