{
  "type": "FeatureCollection",
  "title": "Moregine",
  "id": "826462996",
  "bbox": [
    14.4863957,
    40.7398125,
    14.4863957,
    40.7398125
  ],
  "description": "Moregine, immediately to the south of the archaeological site of Pompeii, is the findspot of an important archaeological assemblage buried by seismic activity that preceded that final eruption of Vesuvius in A.D. 79.",
  "connectsWith": [
    "433032"
  ],
  "features": [
    {
      "type": "Feature",
      "geometry": {
        "type": "Point",
        "coordinates": [
          14.4863957,
          40.7398125
        ]
      },
      "properties": {
        "description": "representative point"
      }
    },
    {
      "geometry": {
        "type": "Point",
        "coordinates": [
          14.4863957,
          40.7398125
        ]
      },
      "id": "osm-location-of-modern-hamlet-of-moregine",
      "type": "Feature",
      "properties": {
        "description": "Pointed location of modern hamlet of Moregine based on a node derived from OpenStreetMap. Archaeological excavations in this area have revealed pre-79 A.D. remains.",
        "location_precision": "precise",
        "title": "OSM location of modern hamlet of Moregine",
        "link": "http://pleiades.stoa.org/places/826462996/osm-location-of-modern-hamlet-of-moregine"
      }
    }
  ]
}