{
  "type": "FeatureCollection",
  "title": "Roman amphitheater at Lupia(e)",
  "id": "826967496",
  "bbox": [
    18.1724077,
    40.3527563,
    18.1724077,
    40.3527563
  ],
  "description": "The Roman amphitheater at Lupia(e), modern Lecce, was built in the late first and early second centuries A.D.",
  "connectsWith": [
    "442642"
  ],
  "names": [
    "Anfiteatro Romano Lecce"
  ],
  "features": [
    {
      "type": "Feature",
      "geometry": {
        "type": "Point",
        "coordinates": [
          18.1724077,
          40.3527563
        ]
      },
      "properties": {
        "description": "representative point"
      }
    },
    {
      "geometry": {
        "type": "Point",
        "coordinates": [
          18.1724077,
          40.3527563
        ]
      },
      "id": "location-of-roman-amphitheater",
      "type": "Feature",
      "properties": {
        "description": "Representative location based on OpenStreetMap.",
        "location_precision": "precise",
        "title": "OSM location of Roman amphitheater",
        "link": "http://pleiades.stoa.org/places/826967496/location-of-roman-amphitheater"
      }
    }
  ]
}