{
  "type": "FeatureCollection",
  "title": "Porta Marina tower of Poseidonia/Paestum",
  "id": "828808246",
  "description": "The so-called Porta Marina of Paestum is a gate in the Hellenistic fortifications and is located along a main street axis leading to the port of the city.",
  "bbox": [
    14.9963773,
    40.4211453,
    14.9963773,
    40.4211453
  ],
  "connectsWith": [
    "442733"
  ],
  "reprPoint": [
    14.9963773,
    40.4211453
  ],
  "features": [
    {
      "geometry": {
        "type": "Point",
        "coordinates": [
          14.9963773,
          40.4211453
        ]
      },
      "id": "location-of-tower-at-porta-marina",
      "type": "Feature",
      "properties": {
        "description": "Representative point location based on OpenStreetMap.",
        "location_precision": "precise",
        "title": "OSM location of tower at Porta Marina",
        "link": "http://pleiades.stoa.org/places/828808246/location-of-tower-at-porta-marina"
      }
    }
  ]
}