{
  "type": "FeatureCollection",
  "title": "Caveirac milestone",
  "id": "828895928",
  "bbox": [
    4.2606573,
    43.8259253,
    4.2606573,
    43.8259253
  ],
  "description": "A Roman milestone - (CIL 17-02, no. 256).",
  "features": [
    {
      "type": "Feature",
      "geometry": {
        "type": "Point",
        "coordinates": [
          4.2606573,
          43.8259253
        ]
      },
      "properties": {
        "description": "representative point"
      }
    },
    {
      "geometry": {
        "type": "Point",
        "coordinates": [
          4.2606573,
          43.8259253
        ]
      },
      "id": "osm-location",
      "type": "Feature",
      "properties": {
        "description": "Location based on OpenStreetMap",
        "location_precision": "precise",
        "title": "OSM location of Borne milliaire au nom d'Auguste",
        "link": "http://pleiades.stoa.org/places/828895928/osm-location"
      }
    }
  ]
}