{
  "type": "FeatureCollection",
  "title": "Gymnasium at Akragas",
  "id": "830186655",
  "bbox": [
    13.5866059,
    37.2935577,
    13.5866059,
    37.2935577
  ],
  "description": "An architectural complex in the upper agora of Akragas (modern Agrigento) dedicated to Hermes and Heracles that was probably used as gymnasium. It appears to have been built in Hellenistic time and renovated in the Augustan period.",
  "connectsWith": [
    "462086",
    "499750546"
  ],
  "names": [
    "Gymnasium"
  ],
  "features": [
    {
      "type": "Feature",
      "geometry": {
        "type": "Point",
        "coordinates": [
          13.5866059,
          37.2935577
        ]
      },
      "properties": {
        "description": "representative point"
      }
    },
    {
      "geometry": {
        "type": "Point",
        "coordinates": [
          13.5866059,
          37.2935577
        ]
      },
      "id": "osm-location-of-the-gymnasium-at-akragas",
      "type": "Feature",
      "properties": {
        "description": "Location of the ancient architectural complex in the agora of Agrigento known as \"Gymnasium\", based on a representative point in Open Street Map",
        "location_precision": "precise",
        "title": "OSM location of the Gymnasium at Akragas",
        "link": "http://pleiades.stoa.org/places/830186655/osm-location-of-the-gymnasium-at-akragas"
      }
    }
  ]
}