{
  "type": "FeatureCollection",
  "title": "Tall Ghaḍaiyrīfah",
  "id": "830124755",
  "bbox": [
    44.2649,
    34.1818,
    44.2649,
    34.1818
  ],
  "description": "Find spot (large mound) for an inscribed door socket.",
  "names": [
    "Tall Ghaḍaiyrīfah"
  ],
  "features": [
    {
      "type": "Feature",
      "geometry": {
        "type": "Point",
        "coordinates": [
          44.2649,
          34.1818
        ]
      },
      "properties": {
        "description": "representative point"
      }
    },
    {
      "geometry": {
        "type": "Point",
        "coordinates": [
          44.2649,
          34.1818
        ]
      },
      "id": "cigs-location-of-tall-ghadaiyrifah",
      "type": "Feature",
      "properties": {
        "description": null,
        "location_precision": "precise",
        "title": "CIGS location of Tall Ghaḍaiyrīfah",
        "link": "http://pleiades.stoa.org/places/830124755/cigs-location-of-tall-ghadaiyrifah"
      }
    }
  ]
}