{
  "type": "FeatureCollection",
  "title": "G端zelhisar",
  "id": "831878282",
  "bbox": [
    41.9817,
    39.8283,
    41.9817,
    39.8283
  ],
  "description": "Mosque in the village of G端zelhisar/Avnik where a Urartian inscription was found in 1965.",
  "names": [
    "G端zelhisar",
    "Avnik"
  ],
  "features": [
    {
      "type": "Feature",
      "geometry": {
        "type": "Point",
        "coordinates": [
          41.9817,
          39.8283
        ]
      },
      "properties": {
        "description": "representative point"
      }
    },
    {
      "geometry": {
        "type": "Point",
        "coordinates": [
          41.9817,
          39.8283
        ]
      },
      "id": "cigs-location-of-guzelhisar",
      "type": "Feature",
      "properties": {
        "description": null,
        "location_precision": "precise",
        "title": "CIGS location of G端zelhisar",
        "link": "http://pleiades.stoa.org/places/831878282/cigs-location-of-guzelhisar"
      }
    }
  ]
}