{
  "type": "FeatureCollection",
  "title": "Hellenistic theater at Dion",
  "id": "832363479",
  "bbox": [
    22.491944,
    40.172417,
    22.491944,
    40.172417
  ],
  "description": "The heavily reconstructed remains of the Hellenistic theater at Dion. Parts of the ancient underground stage system are preserved. ",
  "connectsWith": [
    "491572"
  ],
  "features": [
    {
      "type": "Feature",
      "geometry": {
        "type": "Point",
        "coordinates": [
          22.491944,
          40.172417
        ]
      },
      "properties": {
        "description": "representative point"
      }
    },
    {
      "geometry": {
        "type": "Point",
        "coordinates": [
          22.491944,
          40.172417
        ]
      },
      "id": "gps-location-hellenistic-theater",
      "type": "Feature",
      "properties": {
        "description": "The heavily reconstructed remains of the hellenistic theater at Dion. Parts of the ancient underground stage system are preserved. ",
        "location_precision": "precise",
        "title": "GPS Location of Hellenistic theater",
        "link": "http://pleiades.stoa.org/places/832363479/gps-location-hellenistic-theater"
      }
    }
  ]
}