{
  "type": "FeatureCollection",
  "title": "Roman theater of Herculaneum",
  "id": "835972236",
  "bbox": [
    14.3477597,
    40.8082328,
    14.3477597,
    40.8082328
  ],
  "description": "The Roman theater of Herculaneum was constructed during the Augustan period. The theater was discovered first in 1709 while a well was being dug.",
  "connectsWith": [
    "432873"
  ],
  "names": [
    "Teatro romano di Ercolano"
  ],
  "features": [
    {
      "type": "Feature",
      "geometry": {
        "type": "Point",
        "coordinates": [
          14.3477597,
          40.8082328
        ]
      },
      "properties": {
        "description": "representative point"
      }
    },
    {
      "geometry": {
        "type": "Point",
        "coordinates": [
          14.3477597,
          40.8082328
        ]
      },
      "id": "location-of-roman-theater",
      "type": "Feature",
      "properties": {
        "description": "Location based on OpenStreetMap",
        "location_precision": "precise",
        "title": "OSM location of Roman theater",
        "link": "http://pleiades.stoa.org/places/835972236/location-of-roman-theater"
      }
    }
  ]
}