{
  "type": "FeatureCollection",
  "title": "Temple of Ellesyia",
  "id": "837295553",
  "bbox": [
    31.962662,
    22.622568,
    31.962662,
    22.622568
  ],
  "description": "A small rock-cut temple dedicated to Amun, Horus, and Satis dated to the 18th Dynasty. Originally located near Qasr Ibrim/Premis, the temple was relocated to the Museo Egizio in Turin, Italy, in the 1960s prior to the area's flooding beneath the surface of Lake Nasser.",
  "connectsWith": [
    "795845"
  ],
  "features": [
    {
      "type": "Feature",
      "geometry": {
        "type": "Point",
        "coordinates": [
          31.962662,
          22.622568
        ]
      },
      "properties": {
        "description": "representative point"
      }
    },
    {
      "geometry": {
        "type": "Point",
        "coordinates": [
          31.962662,
          22.622568
        ]
      },
      "id": "wikidata-location-of-temple-of-ellesyia",
      "type": "Feature",
      "properties": {
        "description": "Point representing the original location of the Temple of Ellesyia. Coordinates following GeoHack",
        "location_precision": "precise",
        "title": "GeoHack location of Temple of Ellesyia",
        "link": "http://pleiades.stoa.org/places/837295553/wikidata-location-of-temple-of-ellesyia"
      }
    }
  ]
}