{
  "type": "FeatureCollection",
  "title": "Pula Arena (Roman amphitheater)",
  "id": "837713186",
  "bbox": [
    13.8498543,
    44.8737007,
    13.8498543,
    44.8737007
  ],
  "description": "The Pula Arena is a Roman amphitheater dating to the first century.",
  "connectsWith": [
    "197448"
  ],
  "features": [
    {
      "type": "Feature",
      "geometry": {
        "type": "Point",
        "coordinates": [
          13.8498543,
          44.8737007
        ]
      },
      "properties": {
        "description": "representative point"
      }
    },
    {
      "geometry": {
        "type": "Point",
        "coordinates": [
          13.8498543,
          44.8737007
        ]
      },
      "id": "roman-amphitheater",
      "type": "Feature",
      "properties": {
        "description": "Location based on OpenStreetMap",
        "location_precision": "precise",
        "title": "OSM location of Arena Pula (Roman amphitheater)",
        "link": "http://pleiades.stoa.org/places/837713186/roman-amphitheater"
      }
    }
  ]
}