{
  "type": "FeatureCollection",
  "title": "Moridunum",
  "id": "83868",
  "description": "An ancient place, cited: BAtlas 8 unlocated Moridunum",
  "bbox": [
    -2.996888,
    50.771018,
    -2.996888,
    50.771018
  ],
  "reprPoint": [
    -2.996888,
    50.771018
  ],
  "names": [
    "Moridunum"
  ],
  "features": [
    {
      "id": "undetermined",
      "type": "Feature",
      "properties": {
        "description": null,
        "location_precision": "unlocated",
        "title": "Undetermined location",
        "link": "http://pleiades.stoa.org/places/83868/undetermined"
      }
    },
    {
      "geometry": {
        "type": "Point",
        "coordinates": [
          -2.996888,
          50.771018
        ]
      },
      "id": "dare-location",
      "type": "Feature",
      "properties": {
        "description": "Representative point location, site precision",
        "location_precision": "precise",
        "title": "DARE Location",
        "link": "http://pleiades.stoa.org/places/83868/dare-location"
      }
    }
  ]
}