{
  "type": "FeatureCollection",
  "title": "Reycross",
  "id": "842845454",
  "description": "A castra aestivalia perhaps dating from the campaigns of Agricola.",
  "bbox": [
    -2.1554407,
    54.5064554,
    -2.1554407,
    54.5064554
  ],
  "reprPoint": [
    -2.1554407,
    54.5064554
  ],
  "features": [
    {
      "geometry": {
        "type": "Point",
        "coordinates": [
          -2.1554407,
          54.5064554
        ]
      },
      "id": "osm-location",
      "type": "Feature",
      "properties": {
        "description": "Representative point derived from an OpenStreetMap node.",
        "location_precision": "precise",
        "title": "OSM location",
        "link": "http://pleiades.stoa.org/places/842845454/osm-location"
      }
    }
  ]
}