{
  "type": "FeatureCollection",
  "title": "Roman Forts and Camps at Cawthorn",
  "id": "842845453",
  "description": "A series of contiguous Roman forts.",
  "bbox": [
    -0.8005117,
    54.3003672,
    -0.7939553,
    54.3016196
  ],
  "reprPoint": [
    -0.797610633333,
    54.3007931333
  ],
  "features": [
    {
      "geometry": {
        "type": "Point",
        "coordinates": [
          -0.7939553,
          54.3016196
        ]
      },
      "id": "osm-location",
      "type": "Feature",
      "properties": {
        "description": "Geometry following the outline of camps A and B, derived from an  OpenStreetMap way.",
        "location_precision": "precise",
        "title": "OSM location, camps A and B",
        "link": "http://pleiades.stoa.org/places/842845453/osm-location"
      }
    },
    {
      "geometry": {
        "type": "Point",
        "coordinates": [
          -0.7983649,
          54.3003926
        ]
      },
      "id": "osm-location-camp-c",
      "type": "Feature",
      "properties": {
        "description": "Location based on OpenStreetMap",
        "location_precision": "precise",
        "title": "OSM location, camp C",
        "link": "http://pleiades.stoa.org/places/842845453/osm-location-camp-c"
      }
    },
    {
      "geometry": {
        "type": "Point",
        "coordinates": [
          -0.8005117,
          54.3003672
        ]
      },
      "id": "osm-location-camp-d",
      "type": "Feature",
      "properties": {
        "description": "Location based on OpenStreetMap",
        "location_precision": "precise",
        "title": "OSM location, camp D",
        "link": "http://pleiades.stoa.org/places/842845453/osm-location-camp-d"
      }
    }
  ]
}