{
  "type": "FeatureCollection",
  "title": "Ayman Yaylası",
  "id": "844871",
  "bbox": [
    31.600672,
    40.583829,
    31.600672,
    40.583829
  ],
  "description": "An ancient place, cited: BAtlas 86 B3 Ayman Yaylası",
  "features": [
    {
      "type": "Feature",
      "geometry": {
        "type": "Point",
        "coordinates": [
          31.600672,
          40.583829
        ]
      },
      "properties": {
        "description": "representative point"
      }
    },
    {
      "geometry": {
        "type": "Point",
        "coordinates": [
          31.600672,
          40.583829
        ]
      },
      "id": "darmc-location-11600",
      "type": "Feature",
      "properties": {
        "description": "1M scale point location",
        "location_precision": "precise",
        "title": "DARMC location 11600",
        "link": "http://pleiades.stoa.org/places/844871/darmc-location-11600"
      }
    }
  ]
}