{
  "type": "FeatureCollection",
  "title": "*Bonita",
  "id": "844884",
  "bbox": [
    33.125022,
    41.48741,
    33.125022,
    41.48741
  ],
  "description": "An ancient place, cited: BAtlas 86 D2 *Bonita",
  "names": [
    "Bonita"
  ],
  "features": [
    {
      "type": "Feature",
      "geometry": {
        "type": "Point",
        "coordinates": [
          33.125022,
          41.48741
        ]
      },
      "properties": {
        "description": "representative point"
      }
    },
    {
      "geometry": {
        "type": "Point",
        "coordinates": [
          33.125022,
          41.48741
        ]
      },
      "id": "darmc-location-359",
      "type": "Feature",
      "properties": {
        "description": "TIB point location",
        "location_precision": "precise",
        "title": "DARMC location 359",
        "link": "http://pleiades.stoa.org/places/844884/darmc-location-359"
      }
    }
  ]
}