{
  "type": "FeatureCollection",
  "title": "Armene",
  "id": "844865",
  "bbox": [
    35.041878,
    42.049231,
    35.041878,
    42.049231
  ],
  "description": "An ancient place, cited: BAtlas 86 F1 Armene",
  "names": [
    "Armene"
  ],
  "features": [
    {
      "type": "Feature",
      "geometry": {
        "type": "Point",
        "coordinates": [
          35.041878,
          42.049231
        ]
      },
      "properties": {
        "description": "representative point"
      }
    },
    {
      "geometry": {
        "type": "Point",
        "coordinates": [
          35.041878,
          42.049231
        ]
      },
      "id": "darmc-location-11502",
      "type": "Feature",
      "properties": {
        "description": "1:1 million scale representative point location digitized from the Barrington Atlas of the Greek and Roman World by the Digital Atlas of Roman and Medieval Civilizations project at Harvard University.",
        "location_precision": "precise",
        "title": "DARMC location 11502",
        "link": "http://pleiades.stoa.org/places/844865/darmc-location-11502"
      }
    }
  ]
}