{
  "type": "FeatureCollection",
  "title": "Carus Vicus",
  "id": "844886",
  "description": "An ancient place, cited: BAtlas 86 C3 Carus Vicus",
  "bbox": [
    32.155599,
    40.471527,
    32.252751,
    40.493341
  ],
  "reprPoint": [
    32.204175,
    40.482434
  ],
  "names": [
    "Carus Vicus"
  ],
  "features": [
    {
      "geometry": {
        "type": "Point",
        "coordinates": [
          32.155599,
          40.493341
        ]
      },
      "id": "darmc-location-9796",
      "type": "Feature",
      "properties": {
        "description": "1M scale point location",
        "location_precision": "precise",
        "title": "DARMC location 9796",
        "link": "http://pleiades.stoa.org/places/844886/darmc-location-9796"
      }
    },
    {
      "geometry": {
        "type": "Point",
        "coordinates": [
          32.252751,
          40.471527
        ]
      },
      "id": "darmc-location-11541",
      "type": "Feature",
      "properties": {
        "description": "TIB point location",
        "location_precision": "precise",
        "title": "DARMC location 11541",
        "link": "http://pleiades.stoa.org/places/844886/darmc-location-11541"
      }
    }
  ]
}