{
  "type": "FeatureCollection",
  "title": "Acherousias Pr.",
  "id": "844849",
  "description": "Acherousias Pr. (cited BAtlas 86 B2 Acherousias Pr.)",
  "bbox": [
    31.38502,
    41.29822,
    31.38502,
    41.29822
  ],
  "reprPoint": [
    31.38502,
    41.29822
  ],
  "names": [
    "Acherousias Pr."
  ],
  "features": [
    {
      "geometry": {
        "type": "Point",
        "coordinates": [
          31.38502,
          41.29822
        ]
      },
      "id": "awmc-representative-position-for-acherousias-pr",
      "type": "Feature",
      "properties": {
        "description": "AWMC representative point for Acherousias Pr. at 1 : 1 million scale",
        "location_precision": "precise",
        "title": "AWMC Representative position for Acherousias Pr.",
        "link": "http://pleiades.stoa.org/places/844849/awmc-representative-position-for-acherousias-pr"
      }
    }
  ]
}