{
  "type": "FeatureCollection",
  "title": "Akçasu",
  "id": "844855",
  "description": "An ancient place, cited: BAtlas 86 E2 Akçasu",
  "bbox": [
    34.3325,
    41.611992,
    34.3325,
    41.611992
  ],
  "reprPoint": [
    34.3325,
    41.611992
  ],
  "features": [
    {
      "geometry": {
        "type": "Point",
        "coordinates": [
          34.3325,
          41.611992
        ]
      },
      "id": "darmc-location-11268",
      "type": "Feature",
      "properties": {
        "description": "1M scale point location",
        "location_precision": "precise",
        "title": "DARMC location 11268",
        "link": "http://pleiades.stoa.org/places/844855/darmc-location-11268"
      }
    }
  ]
}