{
  "type": "FeatureCollection",
  "title": "Armene",
  "id": "844865",
  "description": "An ancient place, cited: BAtlas 86 F1 Armene",
  "bbox": [
    35.041878,
    42.049231,
    35.041878,
    42.049231
  ],
  "reprPoint": [
    35.041878,
    42.049231
  ],
  "names": [
    "Armene"
  ],
  "features": [
    {
      "geometry": {
        "type": "Point",
        "coordinates": [
          35.041878,
          42.049231
        ]
      },
      "id": "darmc-location-11502",
      "type": "Feature",
      "properties": {
        "description": "1M scale point location",
        "location_precision": "precise",
        "title": "DARMC location 11502",
        "link": "http://pleiades.stoa.org/places/844865/darmc-location-11502"
      }
    }
  ]
}