{
  "type": "FeatureCollection",
  "title": "Karambis",
  "id": "844971",
  "description": "A coastal promontory located northwest of Doğanyurt, Turkey. Modern Kerembe burnu.",
  "bbox": [
    33.3447,
    42.01957,
    33.3447,
    42.01957
  ],
  "reprPoint": [
    33.3447,
    42.01957
  ],
  "names": [
    "Karambis Pr.",
    "Kerembe burnu"
  ],
  "features": [
    {
      "geometry": {
        "type": "Point",
        "coordinates": [
          33.3447,
          42.01957
        ]
      },
      "id": "geonames-location",
      "type": "Feature",
      "properties": {
        "description": "Representative point, derived from GeoNames.",
        "location_precision": "precise",
        "title": "GeoNames Location",
        "link": "http://pleiades.stoa.org/places/844971/geonames-location"
      }
    }
  ]
}