{
  "type": "FeatureCollection",
  "title": "*Endeira",
  "id": "844916",
  "description": "An ancient place, cited: BAtlas 86 C3 *Endeira",
  "bbox": [
    32.606224,
    40.955986,
    32.670911,
    40.979309
  ],
  "reprPoint": [
    32.6385675,
    40.9676475
  ],
  "names": [
    "Endeira"
  ],
  "features": [
    {
      "geometry": {
        "type": "Point",
        "coordinates": [
          32.670911,
          40.955986
        ]
      },
      "id": "darmc-location-514",
      "type": "Feature",
      "properties": {
        "description": "TIB point location",
        "location_precision": "precise",
        "title": "DARMC location 514",
        "link": "http://pleiades.stoa.org/places/844916/darmc-location-514"
      }
    },
    {
      "geometry": {
        "type": "Point",
        "coordinates": [
          32.606224,
          40.979309
        ]
      },
      "id": "darmc-location-3418",
      "type": "Feature",
      "properties": {
        "description": "1M scale point location",
        "location_precision": "precise",
        "title": "DARMC location 3418",
        "link": "http://pleiades.stoa.org/places/844916/darmc-location-3418"
      }
    }
  ]
}