{
  "type": "FeatureCollection",
  "title": "Kastamonu",
  "id": "844974",
  "description": "An ancient place, cited: BAtlas 86 D2 Kastamonu",
  "bbox": [
    33.724146,
    41.376626,
    33.775972,
    41.398749
  ],
  "reprPoint": [
    33.750059,
    41.3876875
  ],
  "names": [
    "Kastamonu",
    "Ḳasṭamonı",
    "Kastamoni",
    "Ḳasṭamoni",
    "Kastamōn",
    "Kıyık Tepesi",
    "Qasṭamūnī",
    "Qasṭamūniya",
    "Qastamuni",
    "Qasṭamoni",
    "Ḳasṭamonu",
    "Qaṣtamūnīya"
  ],
  "features": [
    {
      "geometry": {
        "type": "Point",
        "coordinates": [
          33.724146,
          41.398749
        ]
      },
      "id": "darmc-location-16026",
      "type": "Feature",
      "properties": {
        "description": "1M scale point location",
        "location_precision": "precise",
        "title": "DARMC location 16026",
        "link": "http://pleiades.stoa.org/places/844974/darmc-location-16026"
      }
    },
    {
      "geometry": {
        "type": "Point",
        "coordinates": [
          33.775972,
          41.376626
        ]
      },
      "id": "darmc-location-11907",
      "type": "Feature",
      "properties": {
        "description": "TIB point location",
        "location_precision": "precise",
        "title": "DARMC location 11907",
        "link": "http://pleiades.stoa.org/places/844974/darmc-location-11907"
      }
    }
  ]
}