{
  "type": "FeatureCollection",
  "title": "İlbarut",
  "id": "844953",
  "description": "An ancient place, cited: BAtlas 86 C2 İlbarut",
  "bbox": [
    32.793636,
    41.187761,
    32.793636,
    41.187761
  ],
  "reprPoint": [
    32.793636,
    41.187761
  ],
  "features": [
    {
      "geometry": {
        "type": "Point",
        "coordinates": [
          32.793636,
          41.187761
        ]
      },
      "id": "darmc-location-23486",
      "type": "Feature",
      "properties": {
        "description": "1M scale point location",
        "location_precision": "precise",
        "title": "DARMC location 23486",
        "link": "http://pleiades.stoa.org/places/844953/darmc-location-23486"
      }
    }
  ]
}