{
  "type": "FeatureCollection",
  "title": "Demirciler",
  "id": "844905",
  "bbox": [
    32.031574,
    40.988902,
    32.031574,
    40.988902
  ],
  "description": "An ancient place, cited: BAtlas 86 C3 Demirciler",
  "features": [
    {
      "type": "Feature",
      "geometry": {
        "type": "Point",
        "coordinates": [
          32.031574,
          40.988902
        ]
      },
      "properties": {
        "description": "representative point"
      }
    },
    {
      "geometry": {
        "type": "Point",
        "coordinates": [
          32.031574,
          40.988902
        ]
      },
      "id": "darmc-location-12177",
      "type": "Feature",
      "properties": {
        "description": "1M scale point location",
        "location_precision": "precise",
        "title": "DARMC location 12177",
        "link": "http://pleiades.stoa.org/places/844905/darmc-location-12177"
      }
    }
  ]
}