{
  "type": "FeatureCollection",
  "title": "Garios",
  "id": "844927",
  "description": "An ancient place, cited: BAtlas 86 D2 Garios",
  "bbox": [
    33.564062,
    41.983013,
    33.573952,
    41.994656
  ],
  "reprPoint": [
    33.569007,
    41.9888345
  ],
  "names": [
    "Garios"
  ],
  "features": [
    {
      "geometry": {
        "type": "Point",
        "coordinates": [
          33.564062,
          41.994656
        ]
      },
      "id": "darmc-location-1664",
      "type": "Feature",
      "properties": {
        "description": "TIB point location",
        "location_precision": "precise",
        "title": "DARMC location 1664",
        "link": "http://pleiades.stoa.org/places/844927/darmc-location-1664"
      }
    },
    {
      "geometry": {
        "type": "Point",
        "coordinates": [
          33.573952,
          41.983013
        ]
      },
      "id": "darmc-location-12482",
      "type": "Feature",
      "properties": {
        "description": "1M scale point location",
        "location_precision": "precise",
        "title": "DARMC location 12482",
        "link": "http://pleiades.stoa.org/places/844927/darmc-location-12482"
      }
    }
  ]
}