{
  "type": "FeatureCollection",
  "title": "Dadybra",
  "id": "844903",
  "description": "An ancient place, cited: BAtlas 86 B2 Dadybra",
  "bbox": [
    31.936831,
    41.21889,
    31.954059,
    41.227285
  ],
  "reprPoint": [
    31.945445,
    41.2230875
  ],
  "names": [
    "Dadybra"
  ],
  "features": [
    {
      "geometry": {
        "type": "Point",
        "coordinates": [
          31.954059,
          41.21889
        ]
      },
      "id": "darmc-location-1299",
      "type": "Feature",
      "properties": {
        "description": "TIB point location",
        "location_precision": "precise",
        "title": "DARMC location 1299",
        "link": "http://pleiades.stoa.org/places/844903/darmc-location-1299"
      }
    },
    {
      "geometry": {
        "type": "Point",
        "coordinates": [
          31.936831,
          41.227285
        ]
      },
      "id": "darmc-location-3195",
      "type": "Feature",
      "properties": {
        "description": "1M scale point location",
        "location_precision": "precise",
        "title": "DARMC location 3195",
        "link": "http://pleiades.stoa.org/places/844903/darmc-location-3195"
      }
    }
  ]
}