{
  "type": "FeatureCollection",
  "title": "Karambis",
  "id": "844970",
  "bbox": [
    33.369673,
    42.013625,
    33.369673,
    42.013625
  ],
  "description": "An ancient place, cited: BAtlas 86 D1 Karambis",
  "names": [
    "Karambis"
  ],
  "features": [
    {
      "type": "Feature",
      "geometry": {
        "type": "Point",
        "coordinates": [
          33.369673,
          42.013625
        ]
      },
      "properties": {
        "description": "representative point"
      }
    },
    {
      "geometry": {
        "type": "Point",
        "coordinates": [
          33.369673,
          42.013625
        ]
      },
      "id": "darmc-location-358",
      "type": "Feature",
      "properties": {
        "description": "TIB representative point location digitized from the Barrington Atlas of the Greek and Roman World by the Digital Atlas of Roman and Medieval Civilizations project at Harvard University.",
        "location_precision": "precise",
        "title": "DARMC location 358",
        "link": "http://pleiades.stoa.org/places/844970/darmc-location-358"
      }
    }
  ]
}