{
  "type": "FeatureCollection",
  "title": "Kales fl.",
  "id": "844962",
  "description": "An ancient place, cited: BAtlas 86 B2 Kales fl.",
  "bbox": [
    31.38295,
    41.18133,
    31.38295,
    41.18133
  ],
  "connectsWith": [
    "1224"
  ],
  "reprPoint": [
    31.38295,
    41.18133
  ],
  "names": [
    "Kales"
  ],
  "features": [
    {
      "geometry": {
        "type": "Point",
        "coordinates": [
          31.38295,
          41.18133
        ]
      },
      "id": "awmc-representative-position-for-kales-fl",
      "type": "Feature",
      "properties": {
        "description": "AWMC representative point for the mouth of Kales fl. at 1 : 1 million scale",
        "location_precision": "precise",
        "title": "AWMC Representative Position for Kales fl.",
        "link": "http://pleiades.stoa.org/places/844962/awmc-representative-position-for-kales-fl"
      }
    }
  ]
}