{
  "type": "FeatureCollection",
  "title": "Elaios",
  "id": "844913",
  "description": "An ancient place, cited: BAtlas 86 B2 Elaios",
  "bbox": [
    31.297325,
    41.115693,
    31.297325,
    41.115693
  ],
  "reprPoint": [
    31.297325,
    41.115693
  ],
  "names": [
    "Elaios"
  ],
  "features": [
    {
      "geometry": {
        "type": "Point",
        "coordinates": [
          31.297325,
          41.115693
        ]
      },
      "id": "darmc-location-1296",
      "type": "Feature",
      "properties": {
        "description": "TIB point location",
        "location_precision": "precise",
        "title": "DARMC location 1296",
        "link": "http://pleiades.stoa.org/places/844913/darmc-location-1296"
      }
    }
  ]
}