{
  "type": "FeatureCollection",
  "title": "Mantineion",
  "id": "845012",
  "description": "An ancient place, cited: BAtlas 86 C3 Mantineion",
  "bbox": [
    31.988838,
    40.795684,
    32.049586,
    40.818995
  ],
  "reprPoint": [
    32.019212,
    40.8073395
  ],
  "names": [
    "Mantineion"
  ],
  "features": [
    {
      "geometry": {
        "type": "Point",
        "coordinates": [
          31.988838,
          40.818995
        ]
      },
      "id": "darmc-location-10130",
      "type": "Feature",
      "properties": {
        "description": "1M scale point location",
        "location_precision": "precise",
        "title": "DARMC location 10130",
        "link": "http://pleiades.stoa.org/places/845012/darmc-location-10130"
      }
    },
    {
      "geometry": {
        "type": "Point",
        "coordinates": [
          32.049586,
          40.795684
        ]
      },
      "id": "darmc-location-11540",
      "type": "Feature",
      "properties": {
        "description": "TIB point location",
        "location_precision": "precise",
        "title": "DARMC location 11540",
        "link": "http://pleiades.stoa.org/places/845012/darmc-location-11540"
      }
    }
  ]
}