{
  "type": "FeatureCollection",
  "title": "Mokata?",
  "id": "845023",
  "description": "An ancient place, cited: BAtlas 86 C2 Mokata?",
  "bbox": [
    32.17035,
    41.61294,
    32.17035,
    41.61294
  ],
  "reprPoint": [
    32.17035,
    41.61294
  ],
  "names": [
    "Mokata"
  ],
  "features": [
    {
      "geometry": {
        "type": "Point",
        "coordinates": [
          32.17035,
          41.61294
        ]
      },
      "id": "darmc-location-13770",
      "type": "Feature",
      "properties": {
        "description": "1M scale point location",
        "location_precision": "precise",
        "title": "DARMC location 13770",
        "link": "http://pleiades.stoa.org/places/845023/darmc-location-13770"
      }
    }
  ]
}