{
  "type": "FeatureCollection",
  "title": "Prusias ad Hypium/Kieros",
  "id": "845049",
  "bbox": [
    31.099267,
    40.905988,
    31.148171,
    40.921998
  ],
  "description": "An ancient place, cited: BAtlas 86 B3 Prusias ad Hypium/Kieros",
  "names": [
    "Prusias ad Hypium",
    "Kieros"
  ],
  "features": [
    {
      "type": "Feature",
      "geometry": {
        "type": "Point",
        "coordinates": [
          31.1204086667,
          40.9141913333
        ]
      },
      "properties": {
        "description": "representative point"
      }
    },
    {
      "geometry": {
        "type": "Point",
        "coordinates": [
          31.099267,
          40.921998
        ]
      },
      "id": "darmc-location-2162",
      "type": "Feature",
      "properties": {
        "description": "1M scale point location",
        "location_precision": "precise",
        "title": "DARMC location 2162",
        "link": "http://pleiades.stoa.org/places/845049/darmc-location-2162"
      }
    },
    {
      "geometry": {
        "type": "Point",
        "coordinates": [
          31.113788,
          40.914588
        ]
      },
      "id": "darmc-location-5608",
      "type": "Feature",
      "properties": {
        "description": "1M scale point location",
        "location_precision": "precise",
        "title": "DARMC location 5608",
        "link": "http://pleiades.stoa.org/places/845049/darmc-location-5608"
      }
    },
    {
      "geometry": {
        "type": "Point",
        "coordinates": [
          31.148171,
          40.905988
        ]
      },
      "id": "dare-location",
      "type": "Feature",
      "properties": {
        "description": "Representative point location, site precision",
        "location_precision": "precise",
        "title": "DARE Location",
        "link": "http://pleiades.stoa.org/places/845049/dare-location"
      }
    }
  ]
}