{
  "type": "FeatureCollection",
  "title": "Titus Tunnel",
  "id": "84771631",
  "bbox": [
    35.9226938,
    36.1217286,
    35.9226938,
    36.1217286
  ],
  "description": "A Flavian period channel cut for the purpose of diverting the course of a river.",
  "features": [
    {
      "type": "Feature",
      "geometry": {
        "type": "Point",
        "coordinates": [
          35.9226938,
          36.1217286
        ]
      },
      "properties": {
        "description": "representative point"
      }
    },
    {
      "geometry": {
        "type": "Point",
        "coordinates": [
          35.9226938,
          36.1217286
        ]
      },
      "id": "location-of-titus-tunnel",
      "type": "Feature",
      "properties": {
        "description": "Representative location based on OpenStreetMap.",
        "location_precision": "precise",
        "title": "OSM location of Titus Tunnel",
        "link": "http://pleiades.stoa.org/places/84771631/location-of-titus-tunnel"
      }
    }
  ]
}