{
  "type": "FeatureCollection",
  "title": "Novochigol'skie kurgan",
  "id": "849572079",
  "bbox": [
    40.512562,
    51.222079,
    40.512562,
    51.222079
  ],
  "description": "Cemetery site located on the banks of the Chigla River, near the modern village of Novaya Chigla, Voronezh Oblast. The site contains 28 burials associated with the Srubnaya Culture (Late Bronze Age 1900-1200 BCE) and the Sarmatians (1st-2nd centuries CE).",
  "names": [
    "Novochigol'skie kurgany"
  ],
  "features": [
    {
      "type": "Feature",
      "geometry": {
        "type": "Point",
        "coordinates": [
          40.512562,
          51.222079
        ]
      },
      "properties": {
        "description": "representative point"
      }
    },
    {
      "geometry": {
        "type": "Point",
        "coordinates": [
          40.512562,
          51.222079
        ]
      },
      "id": "imagery-location-of-novochigolskiy-kurgan",
      "type": "Feature",
      "properties": {
        "description": "Point representing the approximate Google Earth centerpoint of the largest kurgan group in the Novochigolskiy Kurgan site, after Berezutskiy 2021.",
        "location_precision": "precise",
        "title": "Imagery location of Novochigolskiy kurgan",
        "link": "http://pleiades.stoa.org/places/849572079/imagery-location-of-novochigolskiy-kurgan"
      }
    }
  ]
}