{
  "type": "FeatureCollection",
  "title": "Wadi Murabba'at",
  "id": "852629977",
  "description": "The Wadi Murabba'at, known also as Nahal Darga, is a ravine in the Judean desert east of Bethlehem. Four cave sites were identified and excavated there in 1952. A fifth cave was identified in 1968.",
  "bbox": [
    35.374098,
    31.585552,
    35.374098,
    31.585552
  ],
  "reprPoint": [
    35.374098,
    31.585552
  ],
  "names": [
    "Wadi Murabba'at",
    "Nahal Darga"
  ],
  "features": [
    {
      "geometry": {
        "type": "Point",
        "coordinates": [
          35.374098,
          31.585552
        ]
      },
      "id": "location-of-wadi-murabbaat",
      "type": "Feature",
      "properties": {
        "description": "Representative location following Benoit, Milik and de Vaux 1961, verified in Google Earth 2016.",
        "location_precision": "precise",
        "title": "Imagery location of Wadi Murabba'at",
        "link": "http://pleiades.stoa.org/places/852629977/location-of-wadi-murabbaat"
      }
    }
  ]
}