{
  "type": "FeatureCollection",
  "title": "Hazine Piri Kapısı",
  "id": "854578361",
  "bbox": [
    43.3045,
    38.4069,
    43.3045,
    38.4069
  ],
  "description": "Place for Urartian rock inscription.",
  "names": [
    "Hazine Piri Kapısı"
  ],
  "features": [
    {
      "type": "Feature",
      "geometry": {
        "type": "Point",
        "coordinates": [
          43.3045,
          38.4069
        ]
      },
      "properties": {
        "description": "representative point"
      }
    },
    {
      "geometry": {
        "type": "Point",
        "coordinates": [
          43.3045,
          38.4069
        ]
      },
      "id": "cigs-location-of-hazine-piri-kapisi",
      "type": "Feature",
      "properties": {
        "description": null,
        "location_precision": "precise",
        "title": "CIGS location of Hazine Piri Kapısı",
        "link": "http://pleiades.stoa.org/places/854578361/cigs-location-of-hazine-piri-kapisi"
      }
    }
  ]
}