{
  "type": "FeatureCollection",
  "title": "Bugaz",
  "id": "854673",
  "description": "An ancient place, cited: BAtlas 87 L2 Bugaz",
  "bbox": [
    36.861334,
    45.114089,
    36.861334,
    45.114089
  ],
  "reprPoint": [
    36.861334,
    45.114089
  ],
  "features": [
    {
      "geometry": {
        "type": "Point",
        "coordinates": [
          36.861334,
          45.114089
        ]
      },
      "id": "darmc-location-11854",
      "type": "Feature",
      "properties": {
        "description": "500K scale point location",
        "location_precision": "precise",
        "title": "DARMC location 11854",
        "link": "http://pleiades.stoa.org/places/854673/darmc-location-11854"
      }
    }
  ]
}