{
  "type": "FeatureCollection",
  "title": "Apatouros Kolpos",
  "id": "854666",
  "bbox": [
    36.783056,
    45.273889,
    36.783056,
    45.273889
  ],
  "description": "Apatouros Kolpos (Taman Bay) is a shallow bay or gulf on the east coast of the Strait of Kerch.",
  "connectsWith": [
    "1224"
  ],
  "names": [
    "Apatouros Kolpos"
  ],
  "features": [
    {
      "type": "Feature",
      "geometry": {
        "type": "Point",
        "coordinates": [
          36.783056,
          45.273889
        ]
      },
      "properties": {
        "description": "representative point"
      }
    },
    {
      "geometry": {
        "type": "Point",
        "coordinates": [
          36.783056,
          45.273889
        ]
      },
      "id": "location-of-apatouros-kolpos",
      "type": "Feature",
      "properties": {
        "description": "coordinates after GeoHack.",
        "location_precision": "precise",
        "title": "Imagery location of Taman Bay",
        "link": "http://pleiades.stoa.org/places/854666/location-of-apatouros-kolpos"
      }
    }
  ]
}