{
  "type": "FeatureCollection",
  "title": "Yubileynoye 2",
  "id": "854748",
  "description": "An ancient place, cited: BAtlas 87 L2 Yubileynoye 2",
  "bbox": [
    36.970217,
    45.344178,
    36.970217,
    45.344178
  ],
  "reprPoint": [
    36.970217,
    45.344178
  ],
  "features": [
    {
      "geometry": {
        "type": "Point",
        "coordinates": [
          36.970217,
          45.344178
        ]
      },
      "id": "darmc-location-17674",
      "type": "Feature",
      "properties": {
        "description": "500K scale point location",
        "location_precision": "precise",
        "title": "DARMC location 17674",
        "link": "http://pleiades.stoa.org/places/854748/darmc-location-17674"
      }
    }
  ]
}