{
  "type": "FeatureCollection",
  "title": "Pantikapaion/Bosp(h)orus",
  "id": "854719",
  "bbox": [
    36.46855,
    45.350981,
    36.471058,
    45.354403
  ],
  "description": "The main city and port of the Kimmerian Bosporus, founded by Miletus in the late seventh or early sixth centuries B.C.",
  "names": [
    "Pantikapaion",
    "Bosphorus",
    "Bosporus",
    "Kaisareia",
    "Apollonia",
    "Apol",
    "Panticapaeum"
  ],
  "features": [
    {
      "type": "Feature",
      "geometry": {
        "type": "Point",
        "coordinates": [
          36.470222,
          45.3532623333
        ]
      },
      "properties": {
        "description": "representative point"
      }
    },
    {
      "geometry": {
        "type": "Point",
        "coordinates": [
          36.471058,
          45.354403
        ]
      },
      "id": "darmc-location-5440",
      "type": "Feature",
      "properties": {
        "description": "1:1 million scale representative point location digitized from the Barrington Atlas of the Greek and Roman World by the Digital Atlas of Roman and Medieval Civilizations project at Harvard University.",
        "location_precision": "precise",
        "title": "DARMC location 5440",
        "link": "http://pleiades.stoa.org/places/854719/darmc-location-5440"
      }
    },
    {
      "geometry": {
        "type": "Point",
        "coordinates": [
          36.471058,
          45.354403
        ]
      },
      "id": "darmc-location-5441",
      "type": "Feature",
      "properties": {
        "description": "1:500,000 scale representative point location digitized from the Barrington Atlas of the Greek and Roman World by the Digital Atlas of Roman and Medieval Civilizations project at Harvard University.",
        "location_precision": "precise",
        "title": "DARMC location 5441",
        "link": "http://pleiades.stoa.org/places/854719/darmc-location-5441"
      }
    },
    {
      "geometry": {
        "type": "Point",
        "coordinates": [
          36.46855,
          45.350981
        ]
      },
      "id": "dare-location",
      "type": "Feature",
      "properties": {
        "description": "Representative point location, site precision",
        "location_precision": "precise",
        "title": "DARE Location",
        "link": "http://pleiades.stoa.org/places/854719/dare-location"
      }
    }
  ]
}