{
  "type": "FeatureCollection",
  "title": "Myrmekion",
  "id": "854710",
  "description": "An ancient place, cited: BAtlas 87 L2 Myrmekion",
  "bbox": [
    36.5213044602,
    45.3532131042,
    36.5213044602,
    45.3532131042
  ],
  "connectsWith": [
    "854711"
  ],
  "reprPoint": [
    36.5213044602,
    45.3532131042
  ],
  "names": [
    "Myrmekion"
  ],
  "features": [
    {
      "geometry": {
        "type": "Point",
        "coordinates": [
          36.536239,
          45.353575
        ]
      },
      "id": "darmc-location-5085",
      "type": "Feature",
      "properties": {
        "description": "1M scale point location",
        "location_precision": "precise",
        "title": "DARMC location 5085",
        "link": "http://pleiades.stoa.org/places/854710/darmc-location-5085"
      }
    },
    {
      "geometry": {
        "type": "Point",
        "coordinates": [
          36.521304460205,
          45.353213104171
        ]
      },
      "id": "dare-location",
      "type": "Feature",
      "properties": {
        "description": "Representative point location, site precision",
        "location_precision": "precise",
        "title": "DARE Location",
        "link": "http://pleiades.stoa.org/places/854710/dare-location"
      }
    }
  ]
}