{
  "type": "FeatureCollection",
  "title": "Salachik",
  "id": "854728",
  "bbox": [
    36.189082,
    45.473642,
    36.189082,
    45.473642
  ],
  "description": "An ancient place, cited: BAtlas 87 K2 Salachik",
  "features": [
    {
      "type": "Feature",
      "geometry": {
        "type": "Point",
        "coordinates": [
          36.189082,
          45.473642
        ]
      },
      "properties": {
        "description": "representative point"
      }
    },
    {
      "geometry": {
        "type": "Point",
        "coordinates": [
          36.189082,
          45.473642
        ]
      },
      "id": "darmc-location-14567",
      "type": "Feature",
      "properties": {
        "description": "500K scale point location",
        "location_precision": "precise",
        "title": "DARMC location 14567",
        "link": "http://pleiades.stoa.org/places/854728/darmc-location-14567"
      }
    }
  ]
}