{
  "type": "FeatureCollection",
  "title": "Marfovka",
  "id": "854707",
  "description": "An ancient place, cited: BAtlas 87 K2 Marfovka",
  "bbox": [
    36.085057,
    45.201364,
    36.085057,
    45.201364
  ],
  "reprPoint": [
    36.085057,
    45.201364
  ],
  "features": [
    {
      "geometry": {
        "type": "Point",
        "coordinates": [
          36.085057,
          45.201364
        ]
      },
      "id": "darmc-location-6506",
      "type": "Feature",
      "properties": {
        "description": "1M scale point location",
        "location_precision": "precise",
        "title": "DARMC location 6506",
        "link": "http://pleiades.stoa.org/places/854707/darmc-location-6506"
      }
    }
  ]
}