{
  "type": "FeatureCollection",
  "title": "Phanagor(e)ia",
  "id": "854724",
  "bbox": [
    36.9584,
    45.2759,
    36.9609365,
    45.2766165
  ],
  "description": "A colony founded by Teos on the Gulf of Taman ca. 540 BC.",
  "names": [
    "Phanagoreia",
    "Phanagoria",
    "Agrippia",
    "Phanagoreion",
    "Phanagorou polis",
    "Phanagouris",
    "Fanagoriya"
  ],
  "features": [
    {
      "type": "Feature",
      "geometry": {
        "type": "Point",
        "coordinates": [
          36.95966825,
          45.27625825
        ]
      },
      "properties": {
        "description": "representative point"
      }
    },
    {
      "geometry": {
        "type": "Point",
        "coordinates": [
          36.9609365,
          45.2766165
        ]
      },
      "id": "location-of-phanagor-e-ia",
      "type": "Feature",
      "properties": {
        "description": "Representative location based on OpenStreetMap",
        "location_precision": "precise",
        "title": "OSM location of Phanagor(e)ia",
        "link": "http://pleiades.stoa.org/places/854724/location-of-phanagor-e-ia"
      }
    },
    {
      "geometry": {
        "type": "Point",
        "coordinates": [
          36.9584,
          45.2759
        ]
      },
      "id": "cigs-location-of-fanagoriia",
      "type": "Feature",
      "properties": {
        "description": null,
        "location_precision": "precise",
        "title": "CIGS location of FanagoriiÍ¡a",
        "link": "http://pleiades.stoa.org/places/854724/cigs-location-of-fanagoriia"
      }
    }
  ]
}