{
  "type": "FeatureCollection",
  "title": "Phanagor(e)ia",
  "id": "854724",
  "description": "A colony founded by Teos on the Gulf of Taman ca. 540 BC.",
  "bbox": [
    36.9609365,
    45.272594,
    36.983964,
    45.2766165
  ],
  "reprPoint": [
    36.97245025,
    45.27460525
  ],
  "names": [
    "Phanagoreia",
    "Phanagoria",
    "Agrippia",
    "Phanagoreion",
    "Phanagorou polis",
    "Phanagouris"
  ],
  "features": [
    {
      "geometry": {
        "type": "Point",
        "coordinates": [
          36.983964,
          45.272594
        ]
      },
      "id": "darmc-location-5495",
      "type": "Feature",
      "properties": {
        "description": "1M scale point location",
        "location_precision": "precise",
        "title": "DARMC location 5495",
        "link": "http://pleiades.stoa.org/places/854724/darmc-location-5495"
      }
    },
    {
      "geometry": {
        "type": "Point",
        "coordinates": [
          36.9609365,
          45.2766165
        ]
      },
      "id": "location-of-phanagor-e-ia",
      "type": "Feature",
      "properties": {
        "description": "Location based on OpenStreetMap",
        "location_precision": "precise",
        "title": "location of Phanagor(e)ia",
        "link": "http://pleiades.stoa.org/places/854724/location-of-phanagor-e-ia"
      }
    }
  ]
}