{
  "type": "FeatureCollection",
  "title": "Via Flavia",
  "id": "855236251",
  "bbox": [
    13.592045,
    44.869567,
    14.46247,
    45.649148
  ],
  "description": "An ancient Roman road that connected Tergeste to Dalmatia and followed the course of the Istrian coast. The road was built during the reign of emperor Vespasian.",
  "features": [
    {
      "type": "Feature",
      "geometry": {
        "type": "Point",
        "coordinates": [
          13.9903385714,
          45.175631
        ]
      },
      "properties": {
        "description": "representative point"
      }
    }
  ]
}