{
  "type": "FeatureCollection",
  "title": "Roman bridge at Ascain",
  "id": "855536858",
  "bbox": [
    -1.6219524,
    43.3500883,
    -1.6219524,
    43.3500883
  ],
  "description": "A fifth century Roman bridge over the river Nivelle at Ascain in France.",
  "features": [
    {
      "type": "Feature",
      "geometry": {
        "type": "Point",
        "coordinates": [
          -1.6219524,
          43.3500883
        ]
      },
      "properties": {
        "description": "representative point"
      }
    },
    {
      "geometry": {
        "type": "Point",
        "coordinates": [
          -1.6219524,
          43.3500883
        ]
      },
      "id": "osm-location",
      "type": "Feature",
      "properties": {
        "description": "Representative location based on OpenStreetMap.",
        "location_precision": "precise",
        "title": "OSM location of the Roman Bridge at Ascain",
        "link": "http://pleiades.stoa.org/places/855536858/osm-location"
      }
    }
  ]
}