{
  "type": "FeatureCollection",
  "title": "Apsaros/Apsyrtos",
  "id": "857032",
  "bbox": [
    41.573576,
    41.559316,
    41.573661,
    41.573247
  ],
  "description": "An ancient place, cited: BAtlas 87 G3 Apsaros/Apsyrtos",
  "names": [
    "Apsaros",
    "Apsyrtos",
    "Absarus",
    "Apsoros",
    "Valentia"
  ],
  "features": [
    {
      "type": "Feature",
      "geometry": {
        "type": "Point",
        "coordinates": [
          41.5736185,
          41.5662815
        ]
      },
      "properties": {
        "description": "representative point"
      }
    },
    {
      "geometry": {
        "type": "Point",
        "coordinates": [
          41.573576,
          41.559316
        ]
      },
      "id": "darmc-location-21439",
      "type": "Feature",
      "properties": {
        "description": "1:1 million scale representative point location digitized from the Barrington Atlas of the Greek and Roman World by the Digital Atlas of Roman and Medieval Civilizations project at Harvard University.",
        "location_precision": "precise",
        "title": "DARMC location 21439",
        "link": "http://pleiades.stoa.org/places/857032/darmc-location-21439"
      }
    },
    {
      "geometry": {
        "type": "Point",
        "coordinates": [
          41.573661,
          41.573247
        ]
      },
      "id": "dare-location",
      "type": "Feature",
      "properties": {
        "description": "Representative point location, site precision",
        "location_precision": "precise",
        "title": "DARE Location",
        "link": "http://pleiades.stoa.org/places/857032/dare-location"
      }
    }
  ]
}