{
  "type": "FeatureCollection",
  "title": "Brouchoi",
  "id": "857071",
  "bbox": [
    40.3352546503,
    43.5259155824,
    40.3352546503,
    43.5259155824
  ],
  "description": "An ancient place, cited: BAtlas 87 F1 Brouchoi",
  "names": [
    "Brouchoi"
  ],
  "features": [
    {
      "type": "Feature",
      "geometry": {
        "type": "Point",
        "coordinates": [
          40.3352546503,
          43.5259155824
        ]
      },
      "properties": {
        "description": "representative point"
      }
    },
    {
      "geometry": {
        "type": "Point",
        "coordinates": [
          40.3352546502688,
          43.5259155824051
        ]
      },
      "id": "awmc-representative-position-for-brouchoi",
      "type": "Feature",
      "properties": {
        "description": "AWMC representative point for the label of the Brouchoi in the BAtlas at 1 : 1 million scale",
        "location_precision": "precise",
        "title": "AWMC Representative Position for Brouchoi",
        "link": "http://pleiades.stoa.org/places/857071/awmc-representative-position-for-brouchoi"
      }
    }
  ]
}