{
  "type": "FeatureCollection",
  "title": "Anniaca",
  "id": "857030",
  "bbox": [
    37.85252,
    40.312587,
    37.85252,
    40.312587
  ],
  "description": "An ancient place, cited: BAtlas 87 C4 Anniaca",
  "names": [
    "Anniaca"
  ],
  "features": [
    {
      "type": "Feature",
      "geometry": {
        "type": "Point",
        "coordinates": [
          37.85252,
          40.312587
        ]
      },
      "properties": {
        "description": "representative point"
      }
    },
    {
      "geometry": {
        "type": "Point",
        "coordinates": [
          37.85252,
          40.312587
        ]
      },
      "id": "darmc-location-21399",
      "type": "Feature",
      "properties": {
        "description": "1M scale point location",
        "location_precision": "precise",
        "title": "DARMC location 21399",
        "link": "http://pleiades.stoa.org/places/857030/darmc-location-21399"
      }
    }
  ]
}