{
  "type": "FeatureCollection",
  "title": "Achaious? (river)",
  "id": "857009",
  "bbox": [
    39.7440084,
    43.6385731,
    39.7440084,
    43.6385731
  ],
  "description": "An ancient place, cited: BAtlas 87 E1 Achaious? fl.",
  "names": [
    "Achaious"
  ],
  "features": [
    {
      "type": "Feature",
      "geometry": {
        "type": "Point",
        "coordinates": [
          39.7440084,
          43.6385731
        ]
      },
      "properties": {
        "description": "representative point"
      }
    },
    {
      "geometry": {
        "type": "Point",
        "coordinates": [
          39.7440084,
          43.6385731
        ]
      },
      "id": "location-of-Achaious-fl",
      "type": "Feature",
      "properties": {
        "description": "Location based on OpenStreetMap",
        "location_precision": "precise",
        "title": "location of Achaious? fl.",
        "link": "http://pleiades.stoa.org/places/857009/location-of-Achaious-fl"
      }
    }
  ]
}