{
  "type": "FeatureCollection",
  "title": "Chadisia",
  "id": "857079",
  "bbox": [
    36.575537,
    41.288083,
    36.575537,
    41.288083
  ],
  "description": "An ancient place, cited: BAtlas 87 B3 Chadisia",
  "names": [
    "Chadisia"
  ],
  "features": [
    {
      "type": "Feature",
      "geometry": {
        "type": "Point",
        "coordinates": [
          36.575537,
          41.288083
        ]
      },
      "properties": {
        "description": "representative point"
      }
    },
    {
      "geometry": {
        "type": "Point",
        "coordinates": [
          36.575537,
          41.288083
        ]
      },
      "id": "darmc-location-19801",
      "type": "Feature",
      "properties": {
        "description": "1M scale point location",
        "location_precision": "precise",
        "title": "DARMC location 19801",
        "link": "http://pleiades.stoa.org/places/857079/darmc-location-19801"
      }
    }
  ]
}