{
  "type": "FeatureCollection",
  "title": "Ad Vincesimum/Magnana",
  "id": "857012",
  "description": "An ancient place, cited: BAtlas 87 E4 Ad Vincesimum/Magnana",
  "bbox": [
    39.617574,
    40.810026,
    39.617574,
    40.810026
  ],
  "reprPoint": [
    39.617574,
    40.810026
  ],
  "names": [
    "Ad Vincesimum",
    "Magnana"
  ],
  "features": [
    {
      "geometry": {
        "type": "Point",
        "coordinates": [
          39.617574,
          40.810026
        ]
      },
      "id": "darmc-location-21172",
      "type": "Feature",
      "properties": {
        "description": "1M scale point location",
        "location_precision": "precise",
        "title": "DARMC location 21172",
        "link": "http://pleiades.stoa.org/places/857012/darmc-location-21172"
      }
    }
  ]
}