{
  "type": "FeatureCollection",
  "title": "Archabis fl.",
  "id": "857039",
  "description": "An ancient place, cited: BAtlas 87 G3 Archabis fl.",
  "bbox": [
    41.3756643,
    41.2768184,
    41.3756643,
    41.2768184
  ],
  "reprPoint": [
    41.3756643,
    41.2768184
  ],
  "names": [
    "Archabis"
  ],
  "features": [
    {
      "geometry": {
        "type": "Point",
        "coordinates": [
          41.3756643,
          41.2768184
        ]
      },
      "id": "location-of-kapistre-deresi",
      "type": "Feature",
      "properties": {
        "description": "Location based on OpenStreetMap",
        "location_precision": "precise",
        "title": "location of Kapistre Deresi",
        "link": "http://pleiades.stoa.org/places/857039/location-of-kapistre-deresi"
      }
    }
  ]
}