{
  "type": "FeatureCollection",
  "title": "Cromen",
  "id": "857096",
  "description": "An ancient place, cited: BAtlas 87 A4 Cromen",
  "bbox": [
    35.536702,
    40.700735,
    35.536702,
    40.700735
  ],
  "reprPoint": [
    35.536702,
    40.700735
  ],
  "names": [
    "Cromen"
  ],
  "features": [
    {
      "geometry": {
        "type": "Point",
        "coordinates": [
          35.536702,
          40.700735
        ]
      },
      "id": "darmc-location-20018",
      "type": "Feature",
      "properties": {
        "description": "1M scale point location",
        "location_precision": "precise",
        "title": "DARMC location 20018",
        "link": "http://pleiades.stoa.org/places/857096/darmc-location-20018"
      }
    }
  ]
}