{
  "type": "FeatureCollection",
  "title": "Apsaros/Apsyrtos",
  "id": "857032",
  "description": "An ancient place, cited: BAtlas 87 G3 Apsaros/Apsyrtos",
  "bbox": [
    41.573661,
    41.573247,
    41.573661,
    41.573247
  ],
  "reprPoint": [
    41.573661,
    41.573247
  ],
  "names": [
    "Apsaros",
    "Apsyrtos",
    "Absarus",
    "Apsoros",
    "Valentia"
  ],
  "features": [
    {
      "geometry": {
        "type": "Point",
        "coordinates": [
          41.573576,
          41.559316
        ]
      },
      "id": "darmc-location-21439",
      "type": "Feature",
      "properties": {
        "description": "1M scale point location",
        "location_precision": "precise",
        "title": "DARMC location 21439",
        "link": "http://pleiades.stoa.org/places/857032/darmc-location-21439"
      }
    },
    {
      "geometry": {
        "type": "Point",
        "coordinates": [
          41.573661,
          41.573247
        ]
      },
      "id": "dare-location",
      "type": "Feature",
      "properties": {
        "description": "Representative point location, site precision",
        "location_precision": "precise",
        "title": "DARE Location",
        "link": "http://pleiades.stoa.org/places/857032/dare-location"
      }
    }
  ]
}