{
  "type": "FeatureCollection",
  "title": "Kainon Chorion",
  "id": "857179",
  "description": "An ancient place, cited: BAtlas 87 B4 Kainon Chorion",
  "bbox": [
    36.851993,
    40.782056,
    36.851993,
    40.782056
  ],
  "reprPoint": [
    36.851993,
    40.782056
  ],
  "names": [
    "Kainon Chorion"
  ],
  "features": [
    {
      "geometry": {
        "type": "Point",
        "coordinates": [
          36.851993,
          40.782056
        ]
      },
      "id": "darmc-location-17856",
      "type": "Feature",
      "properties": {
        "description": "1M scale point location",
        "location_precision": "precise",
        "title": "DARMC location 17856",
        "link": "http://pleiades.stoa.org/places/857179/darmc-location-17856"
      }
    }
  ]
}