{
  "type": "FeatureCollection",
  "title": "Halys (river)",
  "id": "857148",
  "bbox": [
    34.7425505,
    43.0786852,
    34.7425505,
    43.0786852
  ],
  "description": "The Kızılırmak river, the ancient Halys River, is a major river of Asia Minor that flows into the Black Sea.",
  "connectsWith": [
    "1224"
  ],
  "names": [
    "Halys",
    "Maraššant(ij)a",
    "Ḳızıl Irmaḳ",
    "Kizilirmak",
    "Halys",
    "Nahr Ālis",
    "Kizil Irmak",
    "Kızılırmak",
    "Hálys"
  ],
  "features": [
    {
      "type": "Feature",
      "geometry": {
        "type": "Point",
        "coordinates": [
          34.7425505,
          43.0786852
        ]
      },
      "properties": {
        "description": "representative point"
      }
    }
  ]
}