{
  "type": "FeatureCollection",
  "title": "Ibora",
  "id": "857169",
  "bbox": [
    36.5933,
    40.61689,
    36.5933,
    40.61689
  ],
  "description": "An ancient place, cited: BAtlas 87 B4 Ibora",
  "names": [
    "Ibora"
  ],
  "features": [
    {
      "type": "Feature",
      "geometry": {
        "type": "Point",
        "coordinates": [
          36.5933,
          40.61689
        ]
      },
      "properties": {
        "description": "representative point"
      }
    },
    {
      "geometry": {
        "type": "Point",
        "coordinates": [
          36.5933,
          40.61689
        ]
      },
      "id": "osm-location-of-adegverapna1-4",
      "type": "Feature",
      "properties": {
        "description": "Location based on OpenStreetMap",
        "location_precision": "precise",
        "title": "OSM location of İverönü",
        "link": "http://pleiades.stoa.org/places/857169/osm-location-of-adegverapna1-4"
      }
    }
  ]
}