{
  "type": "FeatureCollection",
  "title": "Kabeira/Neocaesarea/Diospolis/Sebaste/Hadriane",
  "id": "857177",
  "description": "An ancient place, cited: BAtlas 87 B4 Kabeira/Neocaesarea/Diospolis/Sebaste/Hadriane",
  "bbox": [
    36.951027,
    40.568442,
    37.089216,
    40.609983
  ],
  "reprPoint": [
    37.0201215,
    40.5892125
  ],
  "names": [
    "Kabeira",
    "Neocaesarea",
    "Diospolis",
    "Sebaste",
    "Hadriane"
  ],
  "features": [
    {
      "geometry": {
        "type": "Point",
        "coordinates": [
          37.089216,
          40.568442
        ]
      },
      "id": "darmc-location-34930",
      "type": "Feature",
      "properties": {
        "description": "scale point location",
        "location_precision": "precise",
        "title": "DARMC location 34930",
        "link": "http://pleiades.stoa.org/places/857177/darmc-location-34930"
      }
    },
    {
      "geometry": {
        "type": "Point",
        "coordinates": [
          36.951027,
          40.609983
        ]
      },
      "id": "darmc-location-22937",
      "type": "Feature",
      "properties": {
        "description": "1M scale point location",
        "location_precision": "precise",
        "title": "DARMC location 22937",
        "link": "http://pleiades.stoa.org/places/857177/darmc-location-22937"
      }
    }
  ]
}