{
  "type": "FeatureCollection",
  "title": "Iris fl.",
  "id": "857171",
  "description": "Iris fl. (Yeşilırmak River) is a river of Asia Minor that flows into the Black Sea.",
  "bbox": [
    36.7190803,
    41.1802622,
    36.7190803,
    41.1802622
  ],
  "connectsWith": [
    "1224"
  ],
  "reprPoint": [
    36.7190803,
    41.1802622
  ],
  "names": [
    "Iris"
  ],
  "features": [
    {
      "geometry": {
        "type": "Point",
        "coordinates": [
          36.7190803,
          41.1802622
        ]
      },
      "id": "location-of-Iris-fl",
      "type": "Feature",
      "properties": {
        "description": "Location based on OpenStreetMap",
        "location_precision": "precise",
        "title": "location of Iris fl.",
        "link": "http://pleiades.stoa.org/places/857171/location-of-Iris-fl"
      }
    }
  ]
}