{
  "type": "FeatureCollection",
  "title": "Ibora",
  "id": "857169",
  "description": "An ancient place, cited: BAtlas 87 B4 Ibora",
  "bbox": [
    36.570874,
    40.622446,
    36.570874,
    40.622446
  ],
  "reprPoint": [
    36.570874,
    40.622446
  ],
  "names": [
    "Ibora"
  ],
  "features": [
    {
      "geometry": {
        "type": "Point",
        "coordinates": [
          36.570874,
          40.622446
        ]
      },
      "id": "darmc-location-22843",
      "type": "Feature",
      "properties": {
        "description": "1M scale point location",
        "location_precision": "precise",
        "title": "DARMC location 22843",
        "link": "http://pleiades.stoa.org/places/857169/darmc-location-22843"
      }
    }
  ]
}