{
  "type": "FeatureCollection",
  "title": "Halys (river)",
  "id": "857148",
  "description": "The Kızılırmak river, the ancient Halys River, is a major river of Asia Minor that flows into the Black Sea.",
  "bbox": [
    35.9295291,
    41.6767598,
    35.9295291,
    41.6767598
  ],
  "connectsWith": [
    "1224"
  ],
  "reprPoint": [
    35.9295291,
    41.6767598
  ],
  "names": [
    "Halys",
    "Halys",
    "Nahr Ālis",
    "Kizil Irmak",
    "Kızılırmak",
    "Maraššant(ij)a",
    "Ḳızıl Irmaḳ",
    "Kizilirmak"
  ],
  "features": [
    {
      "geometry": {
        "type": "Point",
        "coordinates": [
          35.9295291,
          41.6767598
        ]
      },
      "id": "osm-location",
      "type": "Feature",
      "properties": {
        "description": "Location based on OpenStreetMap",
        "location_precision": "precise",
        "title": "OSM location of the Kızılırmak River",
        "link": "http://pleiades.stoa.org/places/857148/osm-location"
      }
    }
  ]
}