{
  "type": "FeatureCollection",
  "title": "Pharangion",
  "id": "857271",
  "description": "An ancient place, cited: BAtlas 87 G4 Pharangion",
  "bbox": [
    41.26869,
    40.556589,
    41.26869,
    40.556589
  ],
  "reprPoint": [
    41.26869,
    40.556589
  ],
  "names": [
    "Pharangion"
  ],
  "features": [
    {
      "geometry": {
        "type": "Point",
        "coordinates": [
          41.26869,
          40.556589
        ]
      },
      "id": "darmc-location-18186",
      "type": "Feature",
      "properties": {
        "description": "1M scale point location",
        "location_precision": "precise",
        "title": "DARMC location 18186",
        "link": "http://pleiades.stoa.org/places/857271/darmc-location-18186"
      }
    }
  ]
}