{
  "type": "FeatureCollection",
  "title": "Onogouris/Ag. Stephanos",
  "id": "857256",
  "bbox": [
    42.279106,
    42.312772,
    42.279106,
    42.312772
  ],
  "description": "An ancient place, cited: BAtlas 87 H2 Onogouris/Ag. Stephanos",
  "names": [
    "Onogouris",
    "Ag. Stephanos"
  ],
  "features": [
    {
      "type": "Feature",
      "geometry": {
        "type": "Point",
        "coordinates": [
          42.279106,
          42.312772
        ]
      },
      "properties": {
        "description": "representative point"
      }
    },
    {
      "geometry": {
        "type": "Point",
        "coordinates": [
          42.279106,
          42.312772
        ]
      },
      "id": "darmc-location-32768",
      "type": "Feature",
      "properties": {
        "description": "representative point location digitized from the Barrington Atlas of the Greek and Roman World by the Digital Atlas of Roman and Medieval Civilizations project at Harvard University.",
        "location_precision": "precise",
        "title": "DARMC location 32768",
        "link": "http://pleiades.stoa.org/places/857256/darmc-location-32768"
      }
    }
  ]
}