{
  "type": "FeatureCollection",
  "title": "Kvemo Chaladidi",
  "id": "857202",
  "bbox": [
    41.782907,
    42.200686,
    41.782907,
    42.200686
  ],
  "description": "An ancient place, cited: BAtlas 87 G2 Kvemo Chaladidi",
  "features": [
    {
      "type": "Feature",
      "geometry": {
        "type": "Point",
        "coordinates": [
          41.782907,
          42.200686
        ]
      },
      "properties": {
        "description": "representative point"
      }
    },
    {
      "geometry": {
        "type": "Point",
        "coordinates": [
          41.782907,
          42.200686
        ]
      },
      "id": "darmc-location-23345",
      "type": "Feature",
      "properties": {
        "description": "1M scale point location",
        "location_precision": "precise",
        "title": "DARMC location 23345",
        "link": "http://pleiades.stoa.org/places/857202/darmc-location-23345"
      }
    }
  ]
}