{
  "type": "FeatureCollection",
  "title": "Morthoula",
  "id": "857238",
  "description": "An ancient place, cited: BAtlas 87 G3 Morthoula",
  "bbox": [
    41.687709,
    41.365197,
    41.687709,
    41.365197
  ],
  "reprPoint": [
    41.687709,
    41.365197
  ],
  "names": [
    "Morthoula"
  ],
  "features": [
    {
      "geometry": {
        "type": "Point",
        "coordinates": [
          41.687709,
          41.365197
        ]
      },
      "id": "darmc-location-23806",
      "type": "Feature",
      "properties": {
        "description": "1M scale point location",
        "location_precision": "precise",
        "title": "DARMC location 23806",
        "link": "http://pleiades.stoa.org/places/857238/darmc-location-23806"
      }
    }
  ]
}