{
  "type": "FeatureCollection",
  "title": "Pityous",
  "id": "857283",
  "description": "An ancient place, cited: BAtlas 87 F1 Pityous",
  "bbox": [
    40.33215,
    43.160265,
    40.334472,
    43.162916
  ],
  "reprPoint": [
    40.333311,
    43.1615905
  ],
  "names": [
    "Pityous",
    "Karteron Teichos",
    "Pithiae"
  ],
  "features": [
    {
      "geometry": {
        "type": "Point",
        "coordinates": [
          40.33215,
          43.160265
        ]
      },
      "id": "dare-location",
      "type": "Feature",
      "properties": {
        "description": "Representative point location, site precision",
        "location_precision": "precise",
        "title": "DARE Location",
        "link": "http://pleiades.stoa.org/places/857283/dare-location"
      }
    },
    {
      "geometry": {
        "type": "Point",
        "coordinates": [
          40.334472,
          43.162916
        ]
      },
      "id": "darmc-location-18196",
      "type": "Feature",
      "properties": {
        "description": "1M scale point location",
        "location_precision": "precise",
        "title": "DARMC location 18196",
        "link": "http://pleiades.stoa.org/places/857283/darmc-location-18196"
      }
    }
  ]
}