{
  "type": "FeatureCollection",
  "title": "Marukh Pass",
  "id": "857227",
  "description": "An ancient place, cited: BAtlas 87 G1 Marukh Pass",
  "bbox": [
    41.4028647524,
    43.3709270964,
    41.4028647524,
    43.3709270964
  ],
  "reprPoint": [
    41.4028647524,
    43.3709270964
  ],
  "features": [
    {
      "geometry": {
        "type": "Point",
        "coordinates": [
          41.4028647523799,
          43.3709270963832
        ]
      },
      "id": "awmc-representative-position-for-marukh-pass",
      "type": "Feature",
      "properties": {
        "description": "AWMC representative point for Marukh Pass at 1 : 1 million scale",
        "location_precision": "precise",
        "title": "AWMC Representative Position for Marukh Pass",
        "link": "http://pleiades.stoa.org/places/857227/awmc-representative-position-for-marukh-pass"
      }
    }
  ]
}