{
  "type": "FeatureCollection",
  "title": "Rhizaion",
  "id": "857297",
  "description": "An ancient place, cited: BAtlas 87 F3 Rhizaion",
  "bbox": [
    40.497928,
    41.03206,
    40.497928,
    41.03206
  ],
  "reprPoint": [
    40.497928,
    41.03206
  ],
  "names": [
    "Rhizaion",
    "Rize",
    "Rize",
    "Rhizaion"
  ],
  "features": [
    {
      "geometry": {
        "type": "Point",
        "coordinates": [
          40.497928,
          41.03206
        ]
      },
      "id": "dare-location",
      "type": "Feature",
      "properties": {
        "description": "Representative point location, site precision",
        "location_precision": "precise",
        "title": "DARE Location",
        "link": "http://pleiades.stoa.org/places/857297/dare-location"
      }
    },
    {
      "geometry": {
        "type": "Point",
        "coordinates": [
          40.508672,
          41.023556
        ]
      },
      "id": "darmc-location-24499",
      "type": "Feature",
      "properties": {
        "description": "1M scale point location",
        "location_precision": "precise",
        "title": "DARMC location 24499",
        "link": "http://pleiades.stoa.org/places/857297/darmc-location-24499"
      }
    }
  ]
}