{
  "type": "FeatureCollection",
  "title": "Skotios",
  "id": "857324",
  "description": "An ancient place, cited: BAtlas 87 A4 Skotios",
  "bbox": [
    35.810125,
    40.349808,
    35.810125,
    40.349808
  ],
  "reprPoint": [
    35.810125,
    40.349808
  ],
  "names": [
    "Skotios"
  ],
  "features": [
    {
      "geometry": {
        "type": "Point",
        "coordinates": [
          35.810125,
          40.349808
        ]
      },
      "id": "darmc-location-18320",
      "type": "Feature",
      "properties": {
        "description": "1M scale point location",
        "location_precision": "precise",
        "title": "DARMC location 18320",
        "link": "http://pleiades.stoa.org/places/857324/darmc-location-18320"
      }
    }
  ]
}