{
  "type": "FeatureCollection",
  "title": "Sidenos (river)",
  "id": "857317",
  "bbox": [
    37.508737,
    40.9933309,
    37.508737,
    40.9933309
  ],
  "description": "The modern Bolaman Irmağı in Turkey, which rises in the Pontic mountains and flows into the Black Sea. ",
  "connectsWith": [
    "1224"
  ],
  "names": [
    "Sidenos",
    "Sidenus"
  ],
  "features": [
    {
      "type": "Feature",
      "geometry": {
        "type": "Point",
        "coordinates": [
          37.508737,
          40.9933309
        ]
      },
      "properties": {
        "description": "representative point"
      }
    },
    {
      "geometry": {
        "type": "Point",
        "coordinates": [
          37.508737,
          40.9933309
        ]
      },
      "id": "osm-location",
      "type": "Feature",
      "properties": {
        "description": "Location based on OpenStreetMap",
        "location_precision": "precise",
        "title": "OSM location of Bolaman Irmağı",
        "link": "http://pleiades.stoa.org/places/857317/osm-location"
      }
    }
  ]
}