{
  "type": "FeatureCollection",
  "title": "Tekke",
  "id": "857346",
  "description": "An ancient place, cited: BAtlas 87 A4 Tekke",
  "bbox": [
    35.105866,
    40.360567,
    35.105866,
    40.360567
  ],
  "reprPoint": [
    35.105866,
    40.360567
  ],
  "features": [
    {
      "geometry": {
        "type": "Point",
        "coordinates": [
          35.105866,
          40.360567
        ]
      },
      "id": "darmc-location-25044",
      "type": "Feature",
      "properties": {
        "description": "1M scale point location",
        "location_precision": "precise",
        "title": "DARMC location 25044",
        "link": "http://pleiades.stoa.org/places/857346/darmc-location-25044"
      }
    }
  ]
}