{
  "type": "FeatureCollection",
  "title": "Verisa",
  "id": "857369",
  "description": "An ancient place, cited: BAtlas 87 B4 Verisa",
  "bbox": [
    36.484083,
    40.102781,
    36.484083,
    40.102781
  ],
  "reprPoint": [
    36.484083,
    40.102781
  ],
  "names": [
    "Verisa"
  ],
  "features": [
    {
      "geometry": {
        "type": "Point",
        "coordinates": [
          36.484083,
          40.102781
        ]
      },
      "id": "darmc-location-25374",
      "type": "Feature",
      "properties": {
        "description": "1M scale point location",
        "location_precision": "precise",
        "title": "DARMC location 25374",
        "link": "http://pleiades.stoa.org/places/857369/darmc-location-25374"
      }
    }
  ]
}