{
  "type": "FeatureCollection",
  "title": "Sagylion",
  "id": "857300",
  "bbox": [
    35.339127,
    41.077969,
    35.339127,
    41.077969
  ],
  "description": "An ancient place, cited: BAtlas 87 A3 Sagylion",
  "names": [
    "Sagylion"
  ],
  "features": [
    {
      "type": "Feature",
      "geometry": {
        "type": "Point",
        "coordinates": [
          35.339127,
          41.077969
        ]
      },
      "properties": {
        "description": "representative point"
      }
    },
    {
      "geometry": {
        "type": "Point",
        "coordinates": [
          35.339127,
          41.077969
        ]
      },
      "id": "darmc-location-18262",
      "type": "Feature",
      "properties": {
        "description": "1M scale point location",
        "location_precision": "precise",
        "title": "DARMC location 18262",
        "link": "http://pleiades.stoa.org/places/857300/darmc-location-18262"
      }
    }
  ]
}