{
  "type": "FeatureCollection",
  "title": "Schamalinichon?",
  "id": "857308",
  "description": "An ancient place, cited: BAtlas 87 E4 Schamalinichon?",
  "bbox": [
    39.632905,
    40.49552,
    39.632905,
    40.49552
  ],
  "reprPoint": [
    39.632905,
    40.49552
  ],
  "names": [
    "Schamalinichon"
  ],
  "features": [
    {
      "geometry": {
        "type": "Point",
        "coordinates": [
          39.632905,
          40.49552
        ]
      },
      "id": "darmc-location-18281",
      "type": "Feature",
      "properties": {
        "description": "1M scale point location",
        "location_precision": "precise",
        "title": "DARMC location 18281",
        "link": "http://pleiades.stoa.org/places/857308/darmc-location-18281"
      }
    }
  ]
}