{
  "type": "FeatureCollection",
  "title": "Stiphane Limne",
  "id": "857335",
  "bbox": [
    36.009078,
    40.906642,
    36.009078,
    40.906642
  ],
  "description": "An ancient place, cited: BAtlas 87 B4 Stiphane Limne",
  "names": [
    "Stiphane Limne"
  ],
  "features": [
    {
      "type": "Feature",
      "geometry": {
        "type": "Point",
        "coordinates": [
          36.009078,
          40.906642
        ]
      },
      "properties": {
        "description": "representative point"
      }
    },
    {
      "geometry": {
        "type": "Point",
        "coordinates": [
          36.009078,
          40.906642
        ]
      },
      "id": "location-of-stiphane-limne",
      "type": "Feature",
      "properties": {
        "description": "Representative location based on Google Earth.",
        "location_precision": "precise",
        "title": "Google Earth imagery location of Stiphane Limne",
        "link": "http://pleiades.stoa.org/places/857335/location-of-stiphane-limne"
      }
    }
  ]
}