{
  "type": "FeatureCollection",
  "title": "Tor de' Schiavi",
  "id": "85815300",
  "bbox": [
    12.5528433,
    41.8951734,
    12.5528433,
    41.8951734
  ],
  "description": "The Tor de' Schiavi is a medieval tower (thirteenth century) built atop the remains of the octagonal hall of the Villa Gordiani.",
  "connectsWith": [
    "422936"
  ],
  "features": [
    {
      "type": "Feature",
      "geometry": {
        "type": "Point",
        "coordinates": [
          12.5528433,
          41.8951734
        ]
      },
      "properties": {
        "description": "representative point"
      }
    },
    {
      "geometry": {
        "type": "Point",
        "coordinates": [
          12.5528433,
          41.8951734
        ]
      },
      "id": "location-of-tor-de-schiavi",
      "type": "Feature",
      "properties": {
        "description": "Representative location based on OpenStreetMap.",
        "location_precision": "precise",
        "title": "OSM location of Tor de' Schiavi",
        "link": "http://pleiades.stoa.org/places/85815300/location-of-tor-de-schiavi"
      }
    }
  ]
}