{
  "type": "FeatureCollection",
  "title": "Castle of Gradara",
  "id": "858581367",
  "bbox": [
    12.7746998,
    43.9425669,
    12.7746998,
    43.9425669
  ],
  "description": "A castle in the Marche built first in the eleventh century.",
  "features": [
    {
      "type": "Feature",
      "geometry": {
        "type": "Point",
        "coordinates": [
          12.7746998,
          43.9425669
        ]
      },
      "properties": {
        "description": "representative point"
      }
    },
    {
      "geometry": {
        "type": "Point",
        "coordinates": [
          12.7746998,
          43.9425669
        ]
      },
      "id": "osm-location",
      "type": "Feature",
      "properties": {
        "description": "Representative location based on OpenStreetMap.",
        "location_precision": "precise",
        "title": "OSM location of Castello di Gradara",
        "link": "http://pleiades.stoa.org/places/858581367/osm-location"
      }
    }
  ]
}