{
  "type": "FeatureCollection",
  "title": "Cadbury Castle",
  "id": "859366031",
  "description": "Cadbury Castle is a hill fort located in South Cadbury, Somerset, England. ",
  "bbox": [
    -2.531285,
    51.0243429,
    -2.531285,
    51.0243429
  ],
  "reprPoint": [
    -2.531285,
    51.0243429
  ],
  "features": [
    {
      "geometry": {
        "type": "Point",
        "coordinates": [
          -2.531285,
          51.0243429
        ]
      },
      "id": "location-of-cadbury-castle",
      "type": "Feature",
      "properties": {
        "description": "Representative location based on OpenStreetMap.",
        "location_precision": "precise",
        "title": "OSM location of Cadbury Castle",
        "link": "http://pleiades.stoa.org/places/859366031/location-of-cadbury-castle"
      }
    }
  ]
}