{
  "type": "FeatureCollection",
  "title": "Ham Hill Hillfort",
  "id": "859366030",
  "bbox": [
    -2.741838,
    50.9497252,
    -2.741838,
    50.9497252
  ],
  "description": "Ham Hill Hill fort is an 85 hectare hillfort in Somerset, England.",
  "features": [
    {
      "type": "Feature",
      "geometry": {
        "type": "Point",
        "coordinates": [
          -2.741838,
          50.9497252
        ]
      },
      "properties": {
        "description": "representative point"
      }
    },
    {
      "geometry": {
        "type": "Point",
        "coordinates": [
          -2.741838,
          50.9497252
        ]
      },
      "id": "location-of-ham-hill-hill-fort",
      "type": "Feature",
      "properties": {
        "description": "Location based on OpenStreetMap",
        "location_precision": "precise",
        "title": "OSM location",
        "link": "http://pleiades.stoa.org/places/859366030/location-of-ham-hill-hill-fort"
      }
    }
  ]
}