{
  "type": "FeatureCollection",
  "title": "‘Ammān al-Madanī civil airport",
  "id": "859811421",
  "bbox": [
    35.9813,
    31.9713,
    35.9813,
    31.9713
  ],
  "description": "Bronze age building located within the civil airport of Amman.",
  "names": [
    "Maṭār ‘Ammān al-Madanī"
  ],
  "features": [
    {
      "type": "Feature",
      "geometry": {
        "type": "Point",
        "coordinates": [
          35.9813,
          31.9713
        ]
      },
      "properties": {
        "description": "representative point"
      }
    },
    {
      "geometry": {
        "type": "Point",
        "coordinates": [
          35.9813,
          31.9713
        ]
      },
      "id": "cigs-location-of-matar-2018amman-al-madani",
      "type": "Feature",
      "properties": {
        "description": null,
        "location_precision": "precise",
        "title": "CIGS location of Maṭār ‘Ammān al-Madanī",
        "link": "http://pleiades.stoa.org/places/859811421/cigs-location-of-matar-2018amman-al-madani"
      }
    }
  ]
}