{
  "type": "FeatureCollection",
  "title": "Abbaye Saint-Pierre de Moissac",
  "id": "862761171",
  "bbox": [
    1.0845822,
    44.1052562,
    1.0845822,
    44.1052562
  ],
  "description": "An important monastery founded probably in the seventh century of the common era.",
  "connectsWith": [
    "246510"
  ],
  "features": [
    {
      "type": "Feature",
      "geometry": {
        "type": "Point",
        "coordinates": [
          1.0845822,
          44.1052562
        ]
      },
      "properties": {
        "description": "representative point"
      }
    },
    {
      "geometry": {
        "type": "Point",
        "coordinates": [
          1.0845822,
          44.1052562
        ]
      },
      "id": "osm-location-of-abbaye-saint-pierre-de-moissac",
      "type": "Feature",
      "properties": {
        "description": "Location based on OpenStreetMap",
        "location_precision": "precise",
        "title": "OSM location of Abbaye Saint-Pierre de Moissac",
        "link": "http://pleiades.stoa.org/places/862761171/osm-location-of-abbaye-saint-pierre-de-moissac"
      }
    }
  ]
}