{
  "type": "FeatureCollection",
  "title": "Gekhadir",
  "id": "863790",
  "description": "An ancient place, cited: BAtlas 88 C4 Gekhadir",
  "bbox": [
    44.501305,
    40.189247,
    44.501305,
    40.189247
  ],
  "reprPoint": [
    44.501305,
    40.189247
  ],
  "features": [
    {
      "geometry": {
        "type": "Point",
        "coordinates": [
          44.501305,
          40.189247
        ]
      },
      "id": "darmc-location-22818",
      "type": "Feature",
      "properties": {
        "description": "Point location",
        "location_precision": "precise",
        "title": "DARMC location 22818",
        "link": "http://pleiades.stoa.org/places/863790/darmc-location-22818"
      }
    }
  ]
}