{
  "type": "FeatureCollection",
  "title": "Eruandavan",
  "id": "863788",
  "bbox": [
    43.775787,
    40.659643,
    43.775787,
    40.659643
  ],
  "description": "An ancient place, cited: BAtlas 88 B4 Eruandavan",
  "features": [
    {
      "type": "Feature",
      "geometry": {
        "type": "Point",
        "coordinates": [
          43.775787,
          40.659643
        ]
      },
      "properties": {
        "description": "representative point"
      }
    },
    {
      "geometry": {
        "type": "Point",
        "coordinates": [
          43.775787,
          40.659643
        ]
      },
      "id": "darmc-location-22781",
      "type": "Feature",
      "properties": {
        "description": "Point location",
        "location_precision": "precise",
        "title": "DARMC location 22781",
        "link": "http://pleiades.stoa.org/places/863788/darmc-location-22781"
      }
    }
  ]
}