{
  "type": "FeatureCollection",
  "title": "Erebuni",
  "id": "863785",
  "description": "Erebuni was a fortified city of the ancient kingdom of Urartu located in what is now Yerevan, Armenia.",
  "bbox": [
    44.53807,
    40.140583,
    44.53807,
    40.140583
  ],
  "reprPoint": [
    44.53807,
    40.140583
  ],
  "names": [
    "Erebuni"
  ],
  "features": [
    {
      "geometry": {
        "type": "Point",
        "coordinates": [
          44.53807,
          40.140583
        ]
      },
      "id": "darmc-location-22157",
      "type": "Feature",
      "properties": {
        "description": "Point location",
        "location_precision": "precise",
        "title": "DARMC location 22157",
        "link": "http://pleiades.stoa.org/places/863785/darmc-location-22157"
      }
    }
  ]
}