{
  "type": "FeatureCollection",
  "title": "Gerros (river)",
  "id": "863791",
  "description": "An ancient place, cited: BAtlas 88 E1 Gerros fl.",
  "bbox": [
    46.8382268,
    43.2062594,
    46.8382268,
    43.2062594
  ],
  "reprPoint": [
    46.8382268,
    43.2062594
  ],
  "names": [
    "Gerros"
  ],
  "features": [
    {
      "geometry": {
        "type": "Point",
        "coordinates": [
          46.8382268,
          43.2062594
        ]
      },
      "id": "location-of-sulak-river",
      "type": "Feature",
      "properties": {
        "description": "Location based on OpenStreetMap",
        "location_precision": "precise",
        "title": "location of Sulak (river)",
        "link": "http://pleiades.stoa.org/places/863791/location-of-sulak-river"
      }
    }
  ]
}