{
  "type": "FeatureCollection",
  "title": "Ad Fontem Felicem",
  "id": "863722",
  "bbox": [
    43.377448,
    41.832999,
    43.377448,
    41.832999
  ],
  "description": "An ancient place, cited: BAtlas 88 B3 Ad Fontem Felicem",
  "names": [
    "Ad Fontem Felicem"
  ],
  "features": [
    {
      "type": "Feature",
      "geometry": {
        "type": "Point",
        "coordinates": [
          43.377448,
          41.832999
        ]
      },
      "properties": {
        "description": "representative point"
      }
    },
    {
      "geometry": {
        "type": "Point",
        "coordinates": [
          43.377448,
          41.832999
        ]
      },
      "id": "darmc-location-22783",
      "type": "Feature",
      "properties": {
        "description": "Point location",
        "location_precision": "precise",
        "title": "DARMC location 22783",
        "link": "http://pleiades.stoa.org/places/863722/darmc-location-22783"
      }
    }
  ]
}