{
  "type": "FeatureCollection",
  "title": "Armaziskhevi",
  "id": "863746",
  "description": "An ancient place, cited: BAtlas 88 C3 Armaziskhevi",
  "bbox": [
    44.658061,
    41.836346,
    44.658061,
    41.836346
  ],
  "reprPoint": [
    44.658061,
    41.836346
  ],
  "features": [
    {
      "geometry": {
        "type": "Point",
        "coordinates": [
          44.658061,
          41.836346
        ]
      },
      "id": "darmc-location-22805",
      "type": "Feature",
      "properties": {
        "description": "Point location",
        "location_precision": "precise",
        "title": "DARMC location 22805",
        "link": "http://pleiades.stoa.org/places/863746/darmc-location-22805"
      }
    }
  ]
}