{
  "type": "FeatureCollection",
  "title": "Ashnak",
  "id": "863748",
  "description": "An ancient place, cited: BAtlas 88 B4 Ashnak",
  "bbox": [
    43.916606,
    40.32737,
    43.916606,
    40.32737
  ],
  "reprPoint": [
    43.916606,
    40.32737
  ],
  "features": [
    {
      "geometry": {
        "type": "Point",
        "coordinates": [
          43.916606,
          40.32737
        ]
      },
      "id": "darmc-location-22142",
      "type": "Feature",
      "properties": {
        "description": "Point location",
        "location_precision": "precise",
        "title": "DARMC location 22142",
        "link": "http://pleiades.stoa.org/places/863748/darmc-location-22142"
      }
    }
  ]
}