{
  "type": "FeatureCollection",
  "title": "Meschistha",
  "id": "863840",
  "description": "Meschistha (modern Mtskheta (Georgian: მცხეთა)) is an ancient city in Georgia and was the capital of the Hellenistic kingdom of Iberia. Meschistha became a UNESCO World Heritage Site in 1994.",
  "bbox": [
    44.706,
    41.839298,
    44.706,
    41.839298
  ],
  "connectsWith": [
    "863807"
  ],
  "reprPoint": [
    44.706,
    41.839298
  ],
  "names": [
    "Mestcheta",
    "Meschistha",
    "Mestleta",
    "Seusamora",
    "Cicamuri",
    "Mc̣ḫeṭa",
    "Mc̣ḫeta"
  ],
  "features": [
    {
      "geometry": {
        "type": "Point",
        "coordinates": [
          44.706,
          41.839298
        ]
      },
      "id": "darmc-location-22169",
      "type": "Feature",
      "properties": {
        "description": "Point location",
        "location_precision": "precise",
        "title": "DARMC location 22169",
        "link": "http://pleiades.stoa.org/places/863840/darmc-location-22169"
      }
    }
  ]
}