{
  "type": "FeatureCollection",
  "title": "Kldeeti",
  "id": "863829",
  "bbox": [
    43.07057,
    42.048415,
    43.07057,
    42.048415
  ],
  "description": "An ancient place, cited: BAtlas 88 B2 Kldeeti",
  "features": [
    {
      "type": "Feature",
      "geometry": {
        "type": "Point",
        "coordinates": [
          43.07057,
          42.048415
        ]
      },
      "properties": {
        "description": "representative point"
      }
    },
    {
      "geometry": {
        "type": "Point",
        "coordinates": [
          43.07057,
          42.048415
        ]
      },
      "id": "darmc-location-22787",
      "type": "Feature",
      "properties": {
        "description": "Point location",
        "location_precision": "precise",
        "title": "DARMC location 22787",
        "link": "http://pleiades.stoa.org/places/863829/darmc-location-22787"
      }
    }
  ]
}