{
  "type": "FeatureCollection",
  "title": "Targu",
  "id": "863902",
  "bbox": [
    47.950361,
    41.925728,
    47.950361,
    41.925728
  ],
  "description": "An ancient place, cited: BAtlas 88 F3 Targu",
  "features": [
    {
      "type": "Feature",
      "geometry": {
        "type": "Point",
        "coordinates": [
          47.950361,
          41.925728
        ]
      },
      "properties": {
        "description": "representative point"
      }
    },
    {
      "geometry": {
        "type": "Point",
        "coordinates": [
          47.950361,
          41.925728
        ]
      },
      "id": "darmc-location-22336",
      "type": "Feature",
      "properties": {
        "description": "Point location",
        "location_precision": "precise",
        "title": "DARMC location 22336",
        "link": "http://pleiades.stoa.org/places/863902/darmc-location-22336"
      }
    }
  ]
}