{
  "type": "FeatureCollection",
  "title": "Untitled",
  "id": "864480",
  "bbox": [
    42.8618381,
    41.8276309,
    42.8618381,
    41.8276309
  ],
  "description": "An ancient place, cited: BAtlas 88 A3 no. 4 (Zekari)",
  "features": [
    {
      "type": "Feature",
      "geometry": {
        "type": "Point",
        "coordinates": [
          42.8618381,
          41.8276309
        ]
      },
      "properties": {
        "description": "representative point"
      }
    },
    {
      "geometry": {
        "type": "Point",
        "coordinates": [
          42.8618381,
          41.8276309
        ]
      },
      "id": "osm-location-of-zekari",
      "type": "Feature",
      "properties": {
        "description": "Location based on OpenStreetMap",
        "location_precision": "precise",
        "title": "OSM location of Zekari",
        "link": "http://pleiades.stoa.org/places/864480/osm-location-of-zekari"
      }
    }
  ]
}