{
  "type": "FeatureCollection",
  "title": "Untitled",
  "id": "864478",
  "bbox": [
    43.330514,
    42.915496,
    43.330514,
    42.915496
  ],
  "description": "An ancient place, cited: BAtlas 88 B2 no. 2 (Sharivtsek)",
  "features": [
    {
      "type": "Feature",
      "geometry": {
        "type": "Point",
        "coordinates": [
          43.330514,
          42.915496
        ]
      },
      "properties": {
        "description": "representative point"
      }
    },
    {
      "geometry": {
        "type": "Point",
        "coordinates": [
          43.330514,
          42.915496
        ]
      },
      "id": "darmc-location-32794",
      "type": "Feature",
      "properties": {
        "description": "  scale point location",
        "location_precision": "precise",
        "title": "DARMC location 32794",
        "link": "http://pleiades.stoa.org/places/864478/darmc-location-32794"
      }
    }
  ]
}