{
  "type": "FeatureCollection",
  "title": "Untitled",
  "id": "864480",
  "bbox": [
    42.763933,
    41.812541,
    42.763933,
    41.812541
  ],
  "description": "An ancient place, cited: BAtlas 88 A3 no. 4 (Zekari)",
  "features": [
    {
      "type": "Feature",
      "geometry": {
        "type": "Point",
        "coordinates": [
          42.763933,
          41.812541
        ]
      },
      "properties": {
        "description": "representative point"
      }
    },
    {
      "geometry": {
        "type": "Point",
        "coordinates": [
          42.763933,
          41.812541
        ]
      },
      "id": "darmc-location-32774",
      "type": "Feature",
      "properties": {
        "description": "representative point location digitized from the Barrington Atlas of the Greek and Roman World by the Digital Atlas of Roman and Medieval Civilizations project at Harvard University.",
        "location_precision": "precise",
        "title": "DARMC location 32774",
        "link": "http://pleiades.stoa.org/places/864480/darmc-location-32774"
      }
    }
  ]
}