{
  "type": "FeatureCollection",
  "title": "Maleme",
  "id": "865194824",
  "bbox": [
    23.8325965,
    35.5234729,
    23.8325965,
    35.5234729
  ],
  "description": "A Mycenaean tholos tomb located to the north of Margarites, Rethymno, Crete.",
  "connectsWith": [
    "589748"
  ],
  "features": [
    {
      "type": "Feature",
      "geometry": {
        "type": "Point",
        "coordinates": [
          23.8325965,
          35.5234729
        ]
      },
      "properties": {
        "description": "representative point"
      }
    },
    {
      "geometry": {
        "type": "Point",
        "coordinates": [
          23.8325965,
          35.5234729
        ]
      },
      "id": "osm-location-of-tholos-tomb-of-maleme",
      "type": "Feature",
      "properties": {
        "description": "Representative location based on OpenStreetMap",
        "location_precision": "precise",
        "title": "OSM location of Tholos Tomb of Maleme",
        "link": "http://pleiades.stoa.org/places/865194824/osm-location-of-tholos-tomb-of-maleme"
      }
    }
  ]
}