{
  "type": "FeatureCollection",
  "title": "Feride Gül Tarla (FGT) excavation sector",
  "id": "867631586",
  "bbox": [
    26.774363,
    38.361435,
    26.774363,
    38.361435
  ],
  "description": "The Feride Gül Tarla (FGT) excavation sector at Klazomenai.",
  "connectsWith": [
    "550650"
  ],
  "features": [
    {
      "type": "Feature",
      "geometry": {
        "type": "Point",
        "coordinates": [
          26.774363,
          38.361435
        ]
      },
      "properties": {
        "description": "representative point"
      }
    },
    {
      "geometry": {
        "type": "Point",
        "coordinates": [
          26.774363,
          38.361435
        ]
      },
      "id": "feride-gul-tarla-fgt-excavation-sector",
      "type": "Feature",
      "properties": {
        "description": null,
        "location_precision": "precise",
        "title": "Feride Gül Tarla (FGT) excavation sector",
        "link": "http://pleiades.stoa.org/places/867631586/feride-gul-tarla-fgt-excavation-sector"
      }
    }
  ]
}