{
  "type": "FeatureCollection",
  "title": "Tomb of Eumachia",
  "id": "869803559",
  "bbox": [
    14.493555,
    40.74898,
    14.493555,
    40.74898
  ],
  "description": "A monumental exedra-type tomb built at the Porta Nocera between ca. A.D 1-30 that served as the tomb for the family of Eumachia.",
  "connectsWith": [
    "11924821",
    "433032"
  ],
  "features": [
    {
      "type": "Feature",
      "geometry": {
        "type": "Point",
        "coordinates": [
          14.493555,
          40.74898
        ]
      },
      "properties": {
        "description": "representative point"
      }
    },
    {
      "geometry": {
        "type": "Point",
        "coordinates": [
          14.493555,
          40.74898
        ]
      },
      "id": "tomb-of-eumachia",
      "type": "Feature",
      "properties": {
        "description": "Representative location of Tomb of Eumachia based on OpenStreetMap.",
        "location_precision": "precise",
        "title": "OSM location of Tomb of Eumachia",
        "link": "http://pleiades.stoa.org/places/869803559/tomb-of-eumachia"
      }
    }
  ]
}