{
  "type": "FeatureCollection",
  "title": "Lobaos",
  "id": "871179047",
  "bbox": [
    8.8521167,
    40.1657806,
    8.8523999,
    40.1665345
  ],
  "description": "The site of two monopteral nuraghi.",
  "connectsWith": [
    "472014"
  ],
  "features": [
    {
      "type": "Feature",
      "geometry": {
        "type": "Point",
        "coordinates": [
          8.8522583,
          40.16615755
        ]
      },
      "properties": {
        "description": "representative point"
      }
    },
    {
      "geometry": {
        "type": "Point",
        "coordinates": [
          8.8521167,
          40.1665345
        ]
      },
      "id": "osm-location-of-nuraghe-lobaos-i",
      "type": "Feature",
      "properties": {
        "description": "Location based on OpenStreetMap",
        "location_precision": "precise",
        "title": "OSM location of Nuraghe Lobaos I",
        "link": "http://pleiades.stoa.org/places/871179047/osm-location-of-nuraghe-lobaos-i"
      }
    },
    {
      "geometry": {
        "type": "Point",
        "coordinates": [
          8.8523999,
          40.1657806
        ]
      },
      "id": "osm-location-of-nuraghe-lobaos-ii",
      "type": "Feature",
      "properties": {
        "description": "Location based on OpenStreetMap",
        "location_precision": "precise",
        "title": "OSM location of Nuraghe Lobaos II",
        "link": "http://pleiades.stoa.org/places/871179047/osm-location-of-nuraghe-lobaos-ii"
      }
    }
  ]
}