{
  "type": "FeatureCollection",
  "title": "Temple of Artemis at Ephesus",
  "id": "873985034",
  "bbox": [
    27.363807,
    37.9497311,
    27.363807,
    37.9497311
  ],
  "description": "The Temple of Artemis, the central element of the extramural sanctuary of Artemis at Ephesus, was considered one of the Seven Wonders of the Ancient World.",
  "connectsWith": [
    "599612"
  ],
  "features": [
    {
      "type": "Feature",
      "geometry": {
        "type": "Point",
        "coordinates": [
          27.363807,
          37.9497311
        ]
      },
      "properties": {
        "description": "representative point"
      }
    },
    {
      "geometry": {
        "type": "Point",
        "coordinates": [
          27.363807,
          37.9497311
        ]
      },
      "id": "temple-of-artemis",
      "type": "Feature",
      "properties": {
        "description": "The Temple of Artemis, the central element of the extramural sanctuary of Artemis at Ephesus, was considered one of the Seven Wonders of the Ancient World.",
        "location_precision": "precise",
        "title": "Temple of Artemis",
        "link": "http://pleiades.stoa.org/places/873985034/temple-of-artemis"
      }
    }
  ]
}