{
  "type": "FeatureCollection",
  "title": "Ad fl. Tigrim",
  "id": "874296",
  "description": "An ancient place, cited: BAtlas 89 E3 Ad fl. Tigrim",
  "bbox": [
    42.190748,
    37.324342,
    42.190748,
    37.324342
  ],
  "reprPoint": [
    42.190748,
    37.324342
  ],
  "names": [
    "Ad fl. Tigrim"
  ],
  "features": [
    {
      "geometry": {
        "type": "Point",
        "coordinates": [
          42.195833,
          37.325
        ]
      },
      "id": "darmc-location-21422",
      "type": "Feature",
      "properties": {
        "description": "Point location",
        "location_precision": "precise",
        "title": "DARMC location 21422",
        "link": "http://pleiades.stoa.org/places/874296/darmc-location-21422"
      }
    },
    {
      "geometry": {
        "type": "Point",
        "coordinates": [
          42.190748,
          37.324342
        ]
      },
      "id": "dare-location",
      "type": "Feature",
      "properties": {
        "description": "Representative point location, village precision",
        "location_precision": "precise",
        "title": "DARE Location",
        "link": "http://pleiades.stoa.org/places/874296/dare-location"
      }
    }
  ]
}