{
  "type": "FeatureCollection",
  "title": "Ad flumen Tigrim",
  "id": "874296",
  "bbox": [
    42.190748,
    37.324342,
    42.1913218,
    37.3259189
  ],
  "description": "An ancient place, cited: BAtlas 89 E3 Ad fl. Tigrim",
  "names": [
    "Ad fl. Tigrim"
  ],
  "features": [
    {
      "type": "Feature",
      "geometry": {
        "type": "Point",
        "coordinates": [
          42.1910349,
          37.32513045
        ]
      },
      "properties": {
        "description": "representative point"
      }
    },
    {
      "geometry": {
        "type": "Point",
        "coordinates": [
          42.190748,
          37.324342
        ]
      },
      "id": "dare-location",
      "type": "Feature",
      "properties": {
        "description": "Representative point location, village precision",
        "location_precision": "precise",
        "title": "DARE Location",
        "link": "http://pleiades.stoa.org/places/874296/dare-location"
      }
    },
    {
      "geometry": {
        "type": "Point",
        "coordinates": [
          42.1913218,
          37.3259189
        ]
      },
      "id": "osm-location-of-modern-cizre-turkey",
      "type": "Feature",
      "properties": {
        "description": "Location of modern associated settlement based on a node derived from OpenStreetMap.",
        "location_precision": "precise",
        "title": "OSM location of modern Cizre, Turkey",
        "link": "http://pleiades.stoa.org/places/874296/osm-location-of-modern-cizre-turkey"
      }
    }
  ]
}