{
  "type": "FeatureCollection",
  "title": "Ani",
  "id": "874322",
  "bbox": [
    39.035555,
    39.602777,
    39.035555,
    39.602777
  ],
  "description": "An ancient place, cited: BAtlas 89 B1 Ani",
  "names": [
    "Ani"
  ],
  "features": [
    {
      "type": "Feature",
      "geometry": {
        "type": "Point",
        "coordinates": [
          39.035555,
          39.602777
        ]
      },
      "properties": {
        "description": "representative point"
      }
    },
    {
      "geometry": {
        "type": "Point",
        "coordinates": [
          39.035555,
          39.602777
        ]
      },
      "id": "darmc-location-21432",
      "type": "Feature",
      "properties": {
        "description": "Point location",
        "location_precision": "precise",
        "title": "DARMC location 21432",
        "link": "http://pleiades.stoa.org/places/874322/darmc-location-21432"
      }
    }
  ]
}