{
  "type": "FeatureCollection",
  "title": "Arzamon/Arxama",
  "id": "874366",
  "description": "An ancient place, cited: BAtlas 89 C3 Arzamon/Arxama",
  "bbox": [
    40.639528,
    37.262483,
    40.639528,
    37.262483
  ],
  "reprPoint": [
    40.639528,
    37.262483
  ],
  "names": [
    "Arzamon",
    "Arxama",
    "Arcamo"
  ],
  "features": [
    {
      "geometry": {
        "type": "Point",
        "coordinates": [
          40.639528,
          37.262483
        ]
      },
      "id": "darmc-location-22620",
      "type": "Feature",
      "properties": {
        "description": "Point location",
        "location_precision": "precise",
        "title": "DARMC location 22620",
        "link": "http://pleiades.stoa.org/places/874366/darmc-location-22620"
      }
    }
  ]
}