{
  "type": "FeatureCollection",
  "title": "Arbela/Arba-ilu",
  "id": "874341",
  "bbox": [
    44.0068677,
    36.1897645,
    44.0116582,
    36.1930506
  ],
  "description": "An ancient Mesopotamian city located between the two Zab rivers (modern Erbel/Erbil in Iraq).",
  "connectsWith": [
    "893935"
  ],
  "names": [
    "Arbela",
    "Arba-ilu",
    "Arbelitis",
    "Artakene",
    "Erbil",
    "Arbil",
    "Alexandriana",
    "Irbīl",
    "Irbil",
    "Irbil",
    "Urbēl",
    "Urbillum",
    "Urbilla",
    "Arbairā",
    "Arbaʾilu",
    "Qaṣrī",
    "Erbil",
    "Arbil",
    "Arbīl",
    "Arbēla",
    "Arbēla",
    "Arbīla",
    "ʾrbl",
    "Alexandreia",
    "Alexandreia in Mygdonia",
    "Alexandreia Mykdonikē",
    "Arbaʾil",
    "Arbailu",
    "Arbail"
  ],
  "features": [
    {
      "type": "Feature",
      "geometry": {
        "type": "Point",
        "coordinates": [
          44.0093823647,
          36.1913213311
        ]
      },
      "properties": {
        "description": "representative point"
      }
    }
  ]
}