{
  "type": "FeatureCollection",
  "title": "Balisbiga/Baioulous",
  "id": "874383",
  "description": "An ancient place, cited: BAtlas 89 B2 Balisbiga/Baioulous",
  "bbox": [
    39.952527,
    38.705472,
    39.952527,
    38.705472
  ],
  "reprPoint": [
    39.952527,
    38.705472
  ],
  "names": [
    "Balisbiga",
    "Baioulous"
  ],
  "features": [
    {
      "geometry": {
        "type": "Point",
        "coordinates": [
          39.952527,
          38.705472
        ]
      },
      "id": "darmc-location-21447",
      "type": "Feature",
      "properties": {
        "description": "Point location",
        "location_precision": "precise",
        "title": "DARMC location 21447",
        "link": "http://pleiades.stoa.org/places/874383/darmc-location-21447"
      }
    }
  ]
}