{
  "type": "FeatureCollection",
  "title": "Akbas",
  "id": "874309",
  "bbox": [
    41.038876,
    38.263455,
    41.038876,
    38.263455
  ],
  "description": "An ancient place, cited: BAtlas 89 D2 Akbas",
  "names": [
    "Akbas"
  ],
  "features": [
    {
      "type": "Feature",
      "geometry": {
        "type": "Point",
        "coordinates": [
          41.038876,
          38.263455
        ]
      },
      "properties": {
        "description": "representative point"
      }
    },
    {
      "geometry": {
        "type": "Point",
        "coordinates": [
          41.038876,
          38.263455
        ]
      },
      "id": "darmc-location-22599",
      "type": "Feature",
      "properties": {
        "description": "Point location",
        "location_precision": "precise",
        "title": "DARMC location 22599",
        "link": "http://pleiades.stoa.org/places/874309/darmc-location-22599"
      }
    }
  ]
}