{
  "type": "FeatureCollection",
  "title": "Balad/Shahrabadh",
  "id": "874379",
  "bbox": [
    42.726566,
    36.514152,
    42.726566,
    36.514152
  ],
  "description": "An ancient place, cited: BAtlas 89 E4 Balad/Shahrabadh",
  "names": [
    "Balad",
    "Shahrabadh"
  ],
  "features": [
    {
      "type": "Feature",
      "geometry": {
        "type": "Point",
        "coordinates": [
          42.726566,
          36.514152
        ]
      },
      "properties": {
        "description": "representative point"
      }
    },
    {
      "geometry": {
        "type": "Point",
        "coordinates": [
          42.726566,
          36.514152
        ]
      },
      "id": "darmc-location-21446",
      "type": "Feature",
      "properties": {
        "description": "Point location",
        "location_precision": "precise",
        "title": "DARMC location 21446",
        "link": "http://pleiades.stoa.org/places/874379/darmc-location-21446"
      }
    }
  ]
}