{
  "type": "FeatureCollection",
  "title": "Anzitene",
  "id": "874328",
  "description": "An ancient place, cited: BAtlas 89 B2 Anzitene",
  "bbox": [
    39.668324,
    38.641856,
    39.668324,
    38.641856
  ],
  "reprPoint": [
    39.668324,
    38.641856
  ],
  "names": [
    "Anzitene"
  ],
  "features": [
    {
      "geometry": {
        "type": "Point",
        "coordinates": [
          39.668324,
          38.641856
        ]
      },
      "id": "darmc-location-34934",
      "type": "Feature",
      "properties": {
        "description": "scale point location",
        "location_precision": "precise",
        "title": "DARMC location 34934",
        "link": "http://pleiades.stoa.org/places/874328/darmc-location-34934"
      }
    }
  ]
}