{
  "type": "FeatureCollection",
  "title": "Arbela/Arba-ilu",
  "id": "874341",
  "description": "An ancient Mesopotamian city located between the two Zab rivers (modern Erbel/Erbil in Iraq): BAtlas 89 G4 Arbela/Arba-ilu.",
  "bbox": [
    44.00924,
    36.191265,
    44.00924,
    36.191265
  ],
  "connectsWith": [
    "893935"
  ],
  "reprPoint": [
    44.00924,
    36.191265
  ],
  "names": [
    "Arbela",
    "Arba-ilu",
    "Arbelitis",
    "Artakene",
    "Erbil",
    "Arbil",
    "Alexandriana",
    "Irbīl",
    "Irbil",
    "Irbil",
    "Urbēl",
    "Urbillum",
    "Urbilla",
    "Arbairā",
    "Arbaʾilu",
    "Qaṣrī",
    "Erbil",
    "Arbil",
    "Arbīl",
    "Arbēla",
    "Arbēla",
    "Arbīla",
    "Alexandreia Mykdonikē",
    "Arbaʾil",
    "Arbailu",
    "Arbail",
    "ʾrbl",
    "Alexandreia",
    "Alexandreia in Mygdonia"
  ],
  "features": [
    {
      "geometry": {
        "type": "Point",
        "coordinates": [
          44.021407,
          36.176805
        ]
      },
      "id": "darmc-location-5298",
      "type": "Feature",
      "properties": {
        "description": "5M scale point location",
        "location_precision": "precise",
        "title": "DARMC location 5298",
        "link": "http://pleiades.stoa.org/places/874341/darmc-location-5298"
      }
    },
    {
      "geometry": {
        "type": "Point",
        "coordinates": [
          44.016666,
          36.166666
        ]
      },
      "id": "darmc-location-21436",
      "type": "Feature",
      "properties": {
        "description": "Point location",
        "location_precision": "precise",
        "title": "DARMC location 21436",
        "link": "http://pleiades.stoa.org/places/874341/darmc-location-21436"
      }
    },
    {
      "geometry": {
        "type": "Point",
        "coordinates": [
          44.00924,
          36.191265
        ]
      },
      "id": "old-town-citadel-of-erbel-in-iraq",
      "type": "Feature",
      "properties": {
        "description": null,
        "location_precision": "precise",
        "title": "Old town (citadel) of Erbel in Iraq",
        "link": "http://pleiades.stoa.org/places/874341/old-town-citadel-of-erbel-in-iraq"
      }
    }
  ]
}