{
  "type": "FeatureCollection",
  "title": "Fakhrikah",
  "id": "874471",
  "description": "An ancient place, cited: BAtlas 89 H4 Fakhrikah",
  "bbox": [
    45.841443,
    36.888117,
    45.841443,
    36.888117
  ],
  "reprPoint": [
    45.841443,
    36.888117
  ],
  "features": [
    {
      "geometry": {
        "type": "Point",
        "coordinates": [
          45.841443,
          36.888117
        ]
      },
      "id": "darmc-location-22841",
      "type": "Feature",
      "properties": {
        "description": "Point location",
        "location_precision": "precise",
        "title": "DARMC location 22841",
        "link": "http://pleiades.stoa.org/places/874471/darmc-location-22841"
      }
    }
  ]
}