{
  "type": "FeatureCollection",
  "title": "Hajestan Qal'eh",
  "id": "874494",
  "description": "An ancient place, cited: BAtlas 89 G1 Hajestan Qal'eh",
  "bbox": [
    44.583547,
    39.518339,
    44.583547,
    39.518339
  ],
  "reprPoint": [
    44.583547,
    39.518339
  ],
  "features": [
    {
      "geometry": {
        "type": "Point",
        "coordinates": [
          44.583547,
          39.518339
        ]
      },
      "id": "darmc-location-22891",
      "type": "Feature",
      "properties": {
        "description": "Point location",
        "location_precision": "precise",
        "title": "DARMC location 22891",
        "link": "http://pleiades.stoa.org/places/874494/darmc-location-22891"
      }
    }
  ]
}