{
  "type": "FeatureCollection",
  "title": "Matzaron",
  "id": "874595",
  "description": "An ancient place, cited: BAtlas 89 C3 Matzaron",
  "bbox": [
    40.957635,
    37.416176,
    40.957635,
    37.416176
  ],
  "reprPoint": [
    40.957635,
    37.416176
  ],
  "names": [
    "Matzaron",
    "Massaron"
  ],
  "features": [
    {
      "geometry": {
        "type": "Point",
        "coordinates": [
          40.957635,
          37.416176
        ]
      },
      "id": "darmc-location-22589",
      "type": "Feature",
      "properties": {
        "description": "Point location",
        "location_precision": "precise",
        "title": "DARMC location 22589",
        "link": "http://pleiades.stoa.org/places/874595/darmc-location-22589"
      }
    }
  ]
}