{
  "type": "FeatureCollection",
  "title": "Ismail Agha Qal'eh",
  "id": "874528",
  "bbox": [
    44.895431,
    37.656884,
    44.895431,
    37.656884
  ],
  "description": "An ancient place, cited: BAtlas 89 G3 Ismail Agha Qal'eh",
  "features": [
    {
      "type": "Feature",
      "geometry": {
        "type": "Point",
        "coordinates": [
          44.895431,
          37.656884
        ]
      },
      "properties": {
        "description": "representative point"
      }
    },
    {
      "geometry": {
        "type": "Point",
        "coordinates": [
          44.895431,
          37.656884
        ]
      },
      "id": "darmc-location-22872",
      "type": "Feature",
      "properties": {
        "description": "Point location",
        "location_precision": "precise",
        "title": "DARMC location 22872",
        "link": "http://pleiades.stoa.org/places/874528/darmc-location-22872"
      }
    }
  ]
}