{
  "type": "FeatureCollection",
  "title": "Horren/Lorne",
  "id": "874513",
  "description": "An ancient place, cited: BAtlas 89 C3 Horren/Lorne",
  "bbox": [
    40.730679,
    37.23023,
    40.730679,
    37.23023
  ],
  "reprPoint": [
    40.730679,
    37.23023
  ],
  "names": [
    "Horren",
    "Lorne"
  ],
  "features": [
    {
      "geometry": {
        "type": "Point",
        "coordinates": [
          40.730679,
          37.23023
        ]
      },
      "id": "darmc-location-22619",
      "type": "Feature",
      "properties": {
        "description": "Point location",
        "location_precision": "precise",
        "title": "DARMC location 22619",
        "link": "http://pleiades.stoa.org/places/874513/darmc-location-22619"
      }
    }
  ]
}