{
  "type": "FeatureCollection",
  "title": "Mar Melki",
  "id": "874582",
  "description": "An ancient place, cited: BAtlas 89 D3 Mar Melki",
  "bbox": [
    41.411144,
    37.231912,
    41.411144,
    37.231912
  ],
  "reprPoint": [
    41.411144,
    37.231912
  ],
  "names": [
    "Mar Melki"
  ],
  "features": [
    {
      "geometry": {
        "type": "Point",
        "coordinates": [
          41.411144,
          37.231912
        ]
      },
      "id": "darmc-location-22583",
      "type": "Feature",
      "properties": {
        "description": "Point location",
        "location_precision": "precise",
        "title": "DARMC location 22583",
        "link": "http://pleiades.stoa.org/places/874582/darmc-location-22583"
      }
    }
  ]
}