{
  "type": "FeatureCollection",
  "title": "Haza/Hassis",
  "id": "874507",
  "bbox": [
    39.333333,
    39.983333,
    39.333333,
    39.983333
  ],
  "description": "An ancient place, cited: BAtlas 89 B1 Haza/Hassis",
  "names": [
    "Haza",
    "Hassis"
  ],
  "features": [
    {
      "type": "Feature",
      "geometry": {
        "type": "Point",
        "coordinates": [
          39.333333,
          39.983333
        ]
      },
      "properties": {
        "description": "representative point"
      }
    },
    {
      "geometry": {
        "type": "Point",
        "coordinates": [
          39.333333,
          39.983333
        ]
      },
      "id": "darmc-location-21464",
      "type": "Feature",
      "properties": {
        "description": "Point location",
        "location_precision": "precise",
        "title": "DARMC location 21464",
        "link": "http://pleiades.stoa.org/places/874507/darmc-location-21464"
      }
    }
  ]
}