{
  "type": "FeatureCollection",
  "title": "Matiane/*Kapauta Limne",
  "id": "874593",
  "bbox": [
    45.2946505,
    37.429713,
    45.2946505,
    37.429713
  ],
  "description": "An ancient place, cited: BAtlas 89 H3 Matiane/*Kapauta Limne",
  "connectsWith": [
    "214160492"
  ],
  "names": [
    "Matiane",
    "Kapauta Limne",
    "Magriane Limne"
  ],
  "features": [
    {
      "type": "Feature",
      "geometry": {
        "type": "Point",
        "coordinates": [
          45.2946505,
          37.429713
        ]
      },
      "properties": {
        "description": "representative point"
      }
    },
    {
      "geometry": {
        "type": "Point",
        "coordinates": [
          45.2946505,
          37.429713
        ]
      },
      "id": "location-of-matiane-kapauta-limne",
      "type": "Feature",
      "properties": {
        "description": "Representative location based on OpenStreetMap.",
        "location_precision": "precise",
        "title": "OSM location of Matiane/*Kapauta Limne",
        "link": "http://pleiades.stoa.org/places/874593/location-of-matiane-kapauta-limne"
      }
    }
  ]
}