{
  "type": "FeatureCollection",
  "title": "Musaifna",
  "id": "874611",
  "bbox": [
    42.651252,
    36.795828,
    42.651252,
    36.795828
  ],
  "description": "Excavations at Tell Museifneh (Eski Mosul) in the 1980s revealed remains of a well-built stone building that was identified as a Christian basilica dating to the seventh century A.D. The apisdal basilica measured ca. 50 x 50 meters.",
  "features": [
    {
      "type": "Feature",
      "geometry": {
        "type": "Point",
        "coordinates": [
          42.651252,
          36.795828
        ]
      },
      "properties": {
        "description": "representative point"
      }
    },
    {
      "geometry": {
        "type": "Point",
        "coordinates": [
          42.651252,
          36.795828
        ]
      },
      "id": "darmc-location-22923",
      "type": "Feature",
      "properties": {
        "description": "Point location",
        "location_precision": "precise",
        "title": "DARMC location 22923",
        "link": "http://pleiades.stoa.org/places/874611/darmc-location-22923"
      }
    }
  ]
}