{
  "type": "FeatureCollection",
  "title": "Musaifna",
  "id": "874611",
  "description": "An ancient place, cited: BAtlas 89 E4 Musaifna",
  "bbox": [
    42.651252,
    36.795828,
    42.651252,
    36.795828
  ],
  "reprPoint": [
    42.651252,
    36.795828
  ],
  "features": [
    {
      "geometry": {
        "type": "Point",
        "coordinates": [
          42.651252,
          36.795828
        ]
      },
      "id": "darmc-location-22923",
      "type": "Feature",
      "properties": {
        "description": "Point location",
        "location_precision": "precise",
        "title": "DARMC location 22923",
        "link": "http://pleiades.stoa.org/places/874611/darmc-location-22923"
      }
    }
  ]
}