{
  "type": "FeatureCollection",
  "title": "Mindon",
  "id": "874604",
  "description": "An ancient place, cited: BAtlas 89 D3 Mindon",
  "bbox": [
    41.789769,
    37.351109,
    41.789769,
    37.351109
  ],
  "reprPoint": [
    41.789769,
    37.351109
  ],
  "names": [
    "Mindon"
  ],
  "features": [
    {
      "geometry": {
        "type": "Point",
        "coordinates": [
          41.789769,
          37.351109
        ]
      },
      "id": "darmc-location-22577",
      "type": "Feature",
      "properties": {
        "description": "Point location",
        "location_precision": "precise",
        "title": "DARMC location 22577",
        "link": "http://pleiades.stoa.org/places/874604/darmc-location-22577"
      }
    }
  ]
}