{
  "type": "FeatureCollection",
  "title": "Shadikanni/Ar(a)ban/(H)Oraba?/*Castellum Arabum",
  "id": "874688",
  "description": "An ancient place, cited: BAtlas 89 C4 Shadikanni/Ar(a)ban/(H)Oraba?/*Castellum Arabum",
  "bbox": [
    40.707477,
    36.244537,
    40.707477,
    36.244537
  ],
  "reprPoint": [
    40.707477,
    36.244537
  ],
  "names": [
    "Shadikanni",
    "Araban",
    "Arban",
    "Horaba",
    "Oraba",
    "Castellum Arabum"
  ],
  "features": [
    {
      "geometry": {
        "type": "Point",
        "coordinates": [
          40.707477,
          36.244537
        ]
      },
      "id": "darmc-location-22932",
      "type": "Feature",
      "properties": {
        "description": "Point location",
        "location_precision": "precise",
        "title": "DARMC location 22932",
        "link": "http://pleiades.stoa.org/places/874688/darmc-location-22932"
      }
    }
  ]
}