{
  "type": "FeatureCollection",
  "title": "Rashgund",
  "id": "874659",
  "description": "An ancient place, cited: BAtlas 89 H3 Rashgund",
  "bbox": [
    45.113057,
    37.207661,
    45.113057,
    37.207661
  ],
  "reprPoint": [
    45.113057,
    37.207661
  ],
  "features": [
    {
      "geometry": {
        "type": "Point",
        "coordinates": [
          45.113057,
          37.207661
        ]
      },
      "id": "darmc-location-22846",
      "type": "Feature",
      "properties": {
        "description": "Point location",
        "location_precision": "precise",
        "title": "DARMC location 22846",
        "link": "http://pleiades.stoa.org/places/874659/darmc-location-22846"
      }
    }
  ]
}