{
  "type": "FeatureCollection",
  "title": "Qalatgah",
  "id": "874652",
  "description": "An ancient place, cited: BAtlas 89 H3 Qalatgah",
  "bbox": [
    45.247586,
    37.026732,
    45.247586,
    37.026732
  ],
  "reprPoint": [
    45.247586,
    37.026732
  ],
  "features": [
    {
      "geometry": {
        "type": "Point",
        "coordinates": [
          45.247586,
          37.026732
        ]
      },
      "id": "darmc-location-22852",
      "type": "Feature",
      "properties": {
        "description": "Point location",
        "location_precision": "precise",
        "title": "DARMC location 22852",
        "link": "http://pleiades.stoa.org/places/874652/darmc-location-22852"
      }
    }
  ]
}