{
  "type": "FeatureCollection",
  "title": "Sareisa",
  "id": "874682",
  "bbox": [
    42.461111,
    37.516388,
    42.461111,
    37.516388
  ],
  "description": "An ancient place, cited: BAtlas 89 E3 Sareisa",
  "names": [
    "Sareisa"
  ],
  "features": [
    {
      "type": "Feature",
      "geometry": {
        "type": "Point",
        "coordinates": [
          42.461111,
          37.516388
        ]
      },
      "properties": {
        "description": "representative point"
      }
    },
    {
      "geometry": {
        "type": "Point",
        "coordinates": [
          42.461111,
          37.516388
        ]
      },
      "id": "darmc-location-21483",
      "type": "Feature",
      "properties": {
        "description": "Point location",
        "location_precision": "precise",
        "title": "DARMC location 21483",
        "link": "http://pleiades.stoa.org/places/874682/darmc-location-21483"
      }
    }
  ]
}