{
  "type": "FeatureCollection",
  "title": "Satalka/Thamanon",
  "id": "874685",
  "description": "An ancient place, cited: BAtlas 89 E3 Satalka/Thamanon",
  "bbox": [
    42.343846,
    37.417929,
    42.343846,
    37.417929
  ],
  "reprPoint": [
    42.343846,
    37.417929
  ],
  "names": [
    "Satalka",
    "Thamanon"
  ],
  "features": [
    {
      "geometry": {
        "type": "Point",
        "coordinates": [
          42.343846,
          37.417929
        ]
      },
      "id": "darmc-location-22551",
      "type": "Feature",
      "properties": {
        "description": "Point location",
        "location_precision": "precise",
        "title": "DARMC location 22551",
        "link": "http://pleiades.stoa.org/places/874685/darmc-location-22551"
      }
    }
  ]
}