{
  "type": "FeatureCollection",
  "title": "‘Naxouana’",
  "id": "874619",
  "bbox": [
    45.366941,
    39.211744,
    45.366941,
    39.211744
  ],
  "description": "An ancient place, cited: BAtlas 89 H1 ‘Naxouana’",
  "names": [
    "Naxouana"
  ],
  "features": [
    {
      "type": "Feature",
      "geometry": {
        "type": "Point",
        "coordinates": [
          45.366941,
          39.211744
        ]
      },
      "properties": {
        "description": "representative point"
      }
    },
    {
      "geometry": {
        "type": "Point",
        "coordinates": [
          45.366941,
          39.211744
        ]
      },
      "id": "darmc-location-22858",
      "type": "Feature",
      "properties": {
        "description": "Point location",
        "location_precision": "precise",
        "title": "DARMC location 22858",
        "link": "http://pleiades.stoa.org/places/874619/darmc-location-22858"
      }
    }
  ]
}