{
  "type": "FeatureCollection",
  "title": "Qalateh Qal'eh",
  "id": "874651",
  "bbox": [
    45.197685,
    37.156592,
    45.197685,
    37.156592
  ],
  "description": "An ancient place, cited: BAtlas 89 H3 Qalateh Qal'eh",
  "features": [
    {
      "type": "Feature",
      "geometry": {
        "type": "Point",
        "coordinates": [
          45.197685,
          37.156592
        ]
      },
      "properties": {
        "description": "representative point"
      }
    },
    {
      "geometry": {
        "type": "Point",
        "coordinates": [
          45.197685,
          37.156592
        ]
      },
      "id": "darmc-location-22848",
      "type": "Feature",
      "properties": {
        "description": "Point location",
        "location_precision": "precise",
        "title": "DARMC location 22848",
        "link": "http://pleiades.stoa.org/places/874651/darmc-location-22848"
      }
    }
  ]
}