{
  "type": "FeatureCollection",
  "title": "Qara Zia Eddin tepe",
  "id": "874654",
  "description": "An ancient place, cited: BAtlas 89 H2 Qara Zia Eddin tepe",
  "bbox": [
    45.00946,
    38.898766,
    45.00946,
    38.898766
  ],
  "reprPoint": [
    45.00946,
    38.898766
  ],
  "features": [
    {
      "geometry": {
        "type": "Point",
        "coordinates": [
          45.00946,
          38.898766
        ]
      },
      "id": "darmc-location-22859",
      "type": "Feature",
      "properties": {
        "description": "Point location",
        "location_precision": "precise",
        "title": "DARMC location 22859",
        "link": "http://pleiades.stoa.org/places/874654/darmc-location-22859"
      }
    }
  ]
}