{
  "type": "FeatureCollection",
  "title": "Vigna Randanini",
  "id": "874652177",
  "description": "A Jewish catacomb along the Via Appia discovered in 1859.",
  "bbox": [
    12.5134707,
    41.8585402,
    12.5134707,
    41.8585402
  ],
  "connectsWith": [
    "356966898"
  ],
  "reprPoint": [
    12.5134707,
    41.8585402
  ],
  "features": [
    {
      "geometry": {
        "type": "Point",
        "coordinates": [
          12.5134707,
          41.8585402
        ]
      },
      "id": "location-of-vigna-randanini",
      "type": "Feature",
      "properties": {
        "description": "Location based on OpenStreetMap",
        "location_precision": "precise",
        "title": "location of Vigna Randanini",
        "link": "http://pleiades.stoa.org/places/874652177/location-of-vigna-randanini"
      }
    }
  ]
}