{
  "type": "FeatureCollection",
  "title": "Tell Aswad Takhtani",
  "id": "874731",
  "bbox": [
    40.717691,
    36.676433,
    40.717691,
    36.676433
  ],
  "description": "An ancient place, cited: BAtlas 89 C4 Tell Aswad Takhtani",
  "features": [
    {
      "type": "Feature",
      "geometry": {
        "type": "Point",
        "coordinates": [
          40.717691,
          36.676433
        ]
      },
      "properties": {
        "description": "representative point"
      }
    },
    {
      "geometry": {
        "type": "Point",
        "coordinates": [
          40.717691,
          36.676433
        ]
      },
      "id": "darmc-location-22938",
      "type": "Feature",
      "properties": {
        "description": "Point location",
        "location_precision": "precise",
        "title": "DARMC location 22938",
        "link": "http://pleiades.stoa.org/places/874731/darmc-location-22938"
      }
    }
  ]
}