{
  "type": "FeatureCollection",
  "title": "Tell Jikan",
  "id": "874747",
  "description": "An ancient place, cited: BAtlas 89 E4 Tell Jikan",
  "bbox": [
    42.882375,
    36.658672,
    42.882375,
    36.658672
  ],
  "reprPoint": [
    42.882375,
    36.658672
  ],
  "features": [
    {
      "geometry": {
        "type": "Point",
        "coordinates": [
          42.882375,
          36.658672
        ]
      },
      "id": "darmc-location-22908",
      "type": "Feature",
      "properties": {
        "description": "Point location",
        "location_precision": "precise",
        "title": "DARMC location 22908",
        "link": "http://pleiades.stoa.org/places/874747/darmc-location-22908"
      }
    }
  ]
}