{
  "type": "FeatureCollection",
  "title": "Tell Deir Situn",
  "id": "874736",
  "bbox": [
    42.953871,
    36.689314,
    42.953871,
    36.689314
  ],
  "description": "An ancient place, cited: BAtlas 89 E4 Tell Deir Situn",
  "features": [
    {
      "type": "Feature",
      "geometry": {
        "type": "Point",
        "coordinates": [
          42.953871,
          36.689314
        ]
      },
      "properties": {
        "description": "representative point"
      }
    },
    {
      "geometry": {
        "type": "Point",
        "coordinates": [
          42.953871,
          36.689314
        ]
      },
      "id": "darmc-location-22911",
      "type": "Feature",
      "properties": {
        "description": "Point location",
        "location_precision": "precise",
        "title": "DARMC location 22911",
        "link": "http://pleiades.stoa.org/places/874736/darmc-location-22911"
      }
    }
  ]
}