{
  "type": "FeatureCollection",
  "title": "Tell Ahmed Agha Kabir",
  "id": "874726",
  "bbox": [
    42.361936,
    36.842209,
    42.361936,
    36.842209
  ],
  "description": "An ancient place, cited: BAtlas 89 E4 Tell Ahmed Agha Kabir",
  "features": [
    {
      "type": "Feature",
      "geometry": {
        "type": "Point",
        "coordinates": [
          42.361936,
          36.842209
        ]
      },
      "properties": {
        "description": "representative point"
      }
    },
    {
      "geometry": {
        "type": "Point",
        "coordinates": [
          42.361936,
          36.842209
        ]
      },
      "id": "darmc-location-22556",
      "type": "Feature",
      "properties": {
        "description": "Point location",
        "location_precision": "precise",
        "title": "DARMC location 22556",
        "link": "http://pleiades.stoa.org/places/874726/darmc-location-22556"
      }
    }
  ]
}