{
  "type": "FeatureCollection",
  "title": "Tell Abu Wajnam",
  "id": "874724",
  "description": "An ancient place, cited: BAtlas 89 E4 Tell Abu Wajnam",
  "bbox": [
    42.603102,
    36.693691,
    42.603102,
    36.693691
  ],
  "reprPoint": [
    42.603102,
    36.693691
  ],
  "features": [
    {
      "geometry": {
        "type": "Point",
        "coordinates": [
          42.603102,
          36.693691
        ]
      },
      "id": "darmc-location-22924",
      "type": "Feature",
      "properties": {
        "description": "Point location",
        "location_precision": "precise",
        "title": "DARMC location 22924",
        "link": "http://pleiades.stoa.org/places/874724/darmc-location-22924"
      }
    }
  ]
}