{
  "type": "FeatureCollection",
  "title": "Tell Brak",
  "id": "874735",
  "description": "An ancient place, cited: BAtlas 89 D4 Tell Brak",
  "reprPoint": [
    40.78481,
    36.620987
  ],
  "names": [
    "Tabite",
    "Nagar",
    "Tall Brāk",
    "Tall Brak",
    "Taidum",
    "Tall Birāk"
  ],
  "features": [
    {
      "geometry": {
        "type": "Point",
        "coordinates": [
          41.070381,
          36.702118
        ]
      },
      "id": "darmc-location-22572",
      "type": "Feature",
      "properties": {
        "description": "Point location",
        "location_precision": "precise",
        "title": "DARMC location 22572",
        "link": "http://pleiades.stoa.org/places/874735/darmc-location-22572"
      }
    },
    {
      "geometry": {
        "type": "Point",
        "coordinates": [
          41.0703913,
          36.6687803
        ]
      },
      "id": "location-of-tell-brak",
      "type": "Feature",
      "properties": {
        "description": "Tell Brak was occupied between the sixth and second millennia BC. Location based on OpenStreetMap.",
        "location_precision": "precise",
        "title": "location of Tell Brak",
        "link": "http://pleiades.stoa.org/places/874735/location-of-tell-brak"
      }
    }
  ]
}