{
  "type": "FeatureCollection",
  "title": "Tell Hassu",
  "id": "874743",
  "description": "An ancient place, cited: BAtlas 89 E4 Tell Hassu",
  "bbox": [
    42.117933,
    36.741243,
    42.117933,
    36.741243
  ],
  "reprPoint": [
    42.117933,
    36.741243
  ],
  "features": [
    {
      "geometry": {
        "type": "Point",
        "coordinates": [
          42.117933,
          36.741243
        ]
      },
      "id": "darmc-location-22558",
      "type": "Feature",
      "properties": {
        "description": "Point location",
        "location_precision": "precise",
        "title": "DARMC location 22558",
        "link": "http://pleiades.stoa.org/places/874743/darmc-location-22558"
      }
    }
  ]
}