{
  "type": "FeatureCollection",
  "title": "Tell Muhammad Kabir",
  "id": "874750",
  "bbox": [
    41.173031,
    36.934341,
    41.173031,
    36.934341
  ],
  "description": "An ancient place, cited: BAtlas 89 D4 Tell Muhammad Kabir",
  "features": [
    {
      "type": "Feature",
      "geometry": {
        "type": "Point",
        "coordinates": [
          41.173031,
          36.934341
        ]
      },
      "properties": {
        "description": "representative point"
      }
    },
    {
      "geometry": {
        "type": "Point",
        "coordinates": [
          41.173031,
          36.934341
        ]
      },
      "id": "darmc-location-22564",
      "type": "Feature",
      "properties": {
        "description": "Point location",
        "location_precision": "precise",
        "title": "DARMC location 22564",
        "link": "http://pleiades.stoa.org/places/874750/darmc-location-22564"
      }
    }
  ]
}