{
  "type": "FeatureCollection",
  "title": "Zarnuqa",
  "id": "874798",
  "description": "An ancient place, cited: BAtlas 89 E3 Zarnuqa",
  "bbox": [
    42.098792,
    37.455792,
    42.098792,
    37.455792
  ],
  "reprPoint": [
    42.098792,
    37.455792
  ],
  "names": [
    "Zarnuqa"
  ],
  "features": [
    {
      "geometry": {
        "type": "Point",
        "coordinates": [
          42.098792,
          37.455792
        ]
      },
      "id": "darmc-location-22552",
      "type": "Feature",
      "properties": {
        "description": "Point location",
        "location_precision": "precise",
        "title": "DARMC location 22552",
        "link": "http://pleiades.stoa.org/places/874798/darmc-location-22552"
      }
    }
  ]
}