{
  "type": "FeatureCollection",
  "title": "Tell Brak",
  "id": "874735",
  "description": "Tell Brak, located in the Upper Khabur of northeastern Syria, was occupied between the sixth and second millennia B.C. The tell stands ca. 40 m tall and cover ca. 130 hectares.",
  "bbox": [
    41.0703913,
    36.6687803,
    41.0703913,
    36.6687803
  ],
  "reprPoint": [
    41.0703913,
    36.6687803
  ],
  "names": [
    "Nagar",
    "Tabite",
    "Tall Brāk",
    "Tall Brak",
    "Taidum",
    "Tall Birāk"
  ],
  "features": [
    {
      "geometry": {
        "type": "Point",
        "coordinates": [
          41.0703913,
          36.6687803
        ]
      },
      "id": "location-of-tell-brak",
      "type": "Feature",
      "properties": {
        "description": "Tell Brak was occupied between the sixth and second millennia BC. Location based on OpenStreetMap.",
        "location_precision": "precise",
        "title": "OSM location of Tell Brak",
        "link": "http://pleiades.stoa.org/places/874735/location-of-tell-brak"
      }
    }
  ]
}