{
  "type": "FeatureCollection",
  "title": "Siraganon",
  "id": "874702",
  "description": "An ancient place, cited: BAtlas 89 G3 Siraganon",
  "bbox": [
    44.970064,
    37.298855,
    44.970064,
    37.298855
  ],
  "reprPoint": [
    44.970064,
    37.298855
  ],
  "names": [
    "Siraganon"
  ],
  "features": [
    {
      "geometry": {
        "type": "Point",
        "coordinates": [
          44.970064,
          37.298855
        ]
      },
      "id": "darmc-location-22843",
      "type": "Feature",
      "properties": {
        "description": "Point location",
        "location_precision": "precise",
        "title": "DARMC location 22843",
        "link": "http://pleiades.stoa.org/places/874702/darmc-location-22843"
      }
    }
  ]
}