{
  "type": "FeatureCollection",
  "title": "Tell Ahmar",
  "id": "874725",
  "bbox": [
    41.047383,
    37.003055,
    41.047383,
    37.003055
  ],
  "description": "An ancient place, cited: BAtlas 89 D4 Tell Ahmar",
  "features": [
    {
      "type": "Feature",
      "geometry": {
        "type": "Point",
        "coordinates": [
          41.047383,
          37.003055
        ]
      },
      "properties": {
        "description": "representative point"
      }
    },
    {
      "geometry": {
        "type": "Point",
        "coordinates": [
          41.047383,
          37.003055
        ]
      },
      "id": "darmc-location-22562",
      "type": "Feature",
      "properties": {
        "description": "Point location",
        "location_precision": "precise",
        "title": "DARMC location 22562",
        "link": "http://pleiades.stoa.org/places/874725/darmc-location-22562"
      }
    }
  ]
}