{
  "type": "FeatureCollection",
  "title": "Tasuk",
  "id": "874718",
  "bbox": [
    45.340677,
    38.315852,
    45.340677,
    38.315852
  ],
  "description": "An ancient place, cited: BAtlas 89 H2 Tasuk",
  "names": [
    "Tasuk"
  ],
  "features": [
    {
      "type": "Feature",
      "geometry": {
        "type": "Point",
        "coordinates": [
          45.340677,
          38.315852
        ]
      },
      "properties": {
        "description": "representative point"
      }
    },
    {
      "geometry": {
        "type": "Point",
        "coordinates": [
          45.340677,
          38.315852
        ]
      },
      "id": "darmc-location-22867",
      "type": "Feature",
      "properties": {
        "description": "Point location",
        "location_precision": "precise",
        "title": "DARMC location 22867",
        "link": "http://pleiades.stoa.org/places/874718/darmc-location-22867"
      }
    }
  ]
}