{
  "type": "FeatureCollection",
  "title": "Untitled",
  "id": "875049",
  "description": "An ancient place, cited: BAtlas 89 C3 unnamed bridge (Ad Tygrem, below Diyarbakır on R. Tigris)",
  "bbox": [
    40.229167,
    37.887222,
    40.243515,
    37.898292
  ],
  "reprPoint": [
    40.232754,
    37.8899895
  ],
  "features": [
    {
      "geometry": {
        "type": "Point",
        "coordinates": [
          40.229167,
          37.887222
        ]
      },
      "id": "ongz-diyarbakir",
      "type": "Feature",
      "properties": {
        "description": "Bridge over Ad Tigren (Amida), constructed c. 485 CE",
        "location_precision": "precise",
        "title": "Ongöz (Diyarbakir)",
        "link": "http://pleiades.stoa.org/places/875049/ongz-diyarbakir"
      }
    },
    {
      "geometry": {
        "type": "Point",
        "coordinates": [
          40.243515,
          37.898292
        ]
      },
      "id": "darmc-location-32610",
      "type": "Feature",
      "properties": {
        "description": "scale point location",
        "location_precision": "precise",
        "title": "DARMC location 32610",
        "link": "http://pleiades.stoa.org/places/875049/darmc-location-32610"
      }
    }
  ]
}