{
  "type": "FeatureCollection",
  "title": "Kouphovouno",
  "id": "875552307",
  "bbox": [
    22.4207,
    37.0568,
    22.4207,
    37.0568
  ],
  "description": "Neolithic and early Helladic site in Greece, located approximately 2.5km southwest of modern Sparta.",
  "features": [
    {
      "type": "Feature",
      "geometry": {
        "type": "Point",
        "coordinates": [
          22.4207,
          37.0568
        ]
      },
      "properties": {
        "description": "representative point"
      }
    },
    {
      "geometry": {
        "type": "Point",
        "coordinates": [
          22.4207,
          37.0568
        ]
      },
      "id": "wikidata-location-of-kouphovouno",
      "type": "Feature",
      "properties": {
        "description": "Point representing the location of Kouphovouno, derived from Wikidata.",
        "location_precision": "precise",
        "title": "Wikidata location of Kouphovouno",
        "link": "http://pleiades.stoa.org/places/875552307/wikidata-location-of-kouphovouno"
      }
    }
  ]
}