{
  "type": "FeatureCollection",
  "title": "Zuqnin, Mon.",
  "id": "876742",
  "bbox": [
    40.23063,
    37.910083,
    40.236259,
    37.914408
  ],
  "description": "An ancient place, cited: BAtlas 89 unlocated Zuqnin, Mon.",
  "connectsWith": [
    "874298"
  ],
  "names": [
    "Zuqnin, Mon."
  ],
  "features": [
    {
      "type": "Feature",
      "geometry": {
        "type": "Point",
        "coordinates": [
          40.2334445,
          37.9122455
        ]
      },
      "properties": {
        "description": "representative point"
      }
    },
    {
      "geometry": null,
      "id": "batlas-location",
      "type": "Feature",
      "properties": {
        "description": null,
        "location_precision": "unlocated",
        "title": "Barrington Atlas location",
        "link": "http://pleiades.stoa.org/places/876742/batlas-location"
      }
    }
  ]
}