{
  "type": "FeatureCollection",
  "title": "Theater of Pergamon",
  "id": "877549424",
  "bbox": [
    27.1832602,
    39.1318438,
    27.1832602,
    39.1318438
  ],
  "description": "The Greek Theater of Pergamon dates ca. 225 -200 B.C.",
  "connectsWith": [
    "550812"
  ],
  "features": [
    {
      "type": "Feature",
      "geometry": {
        "type": "Point",
        "coordinates": [
          27.1832602,
          39.1318438
        ]
      },
      "properties": {
        "description": "representative point"
      }
    },
    {
      "geometry": {
        "type": "Point",
        "coordinates": [
          27.1832602,
          39.1318438
        ]
      },
      "id": "osm-location-of-theater-1",
      "type": "Feature",
      "properties": {
        "description": "Representative location based on OpenStreetMap",
        "location_precision": "precise",
        "title": "OSM location of Theater",
        "link": "http://pleiades.stoa.org/places/877549424/osm-location-of-theater-1"
      }
    }
  ]
}