{
  "type": "FeatureCollection",
  "title": "Theater of Pergamon",
  "id": "877549424",
  "bbox": [
    27.1830282,
    39.1319456,
    27.1830282,
    39.1319456
  ],
  "description": "The Greek Theater of Pergamon dates ca. 225 -200 B.C.",
  "connectsWith": [
    "550812"
  ],
  "features": [
    {
      "type": "Feature",
      "geometry": {
        "type": "Point",
        "coordinates": [
          27.1830282,
          39.1319456
        ]
      },
      "properties": {
        "description": "representative point"
      }
    },
    {
      "geometry": {
        "type": "Point",
        "coordinates": [
          27.1830282,
          39.1319456
        ]
      },
      "id": "osm-location-of-theater",
      "type": "Feature",
      "properties": {
        "description": "Location based on OpenStreetMap",
        "location_precision": "precise",
        "title": "OSM Location of theater",
        "link": "http://pleiades.stoa.org/places/877549424/osm-location-of-theater"
      }
    }
  ]
}