{
  "type": "FeatureCollection",
  "title": "Tel Arad",
  "id": "87764825",
  "bbox": [
    35.1255017,
    31.2799119,
    35.1255017,
    31.2799119
  ],
  "description": "A multi-period settlement with occupation stretching from the Chalcolithic period to the second century A.D.",
  "names": [
    "Beit Yahweh"
  ],
  "features": [
    {
      "type": "Feature",
      "geometry": {
        "type": "Point",
        "coordinates": [
          35.1255017,
          31.2799119
        ]
      },
      "properties": {
        "description": "representative point"
      }
    },
    {
      "geometry": {
        "type": "Point",
        "coordinates": [
          35.1255017,
          31.2799119
        ]
      },
      "id": "location-of-tel-arad",
      "type": "Feature",
      "properties": {
        "description": "Representative ocation based on OpenStreetMap.",
        "location_precision": "precise",
        "title": "OSM location of Tel Arad",
        "link": "http://pleiades.stoa.org/places/87764825/location-of-tel-arad"
      }
    }
  ]
}