{
  "type": "FeatureCollection",
  "title": "Sorgenti della Nova",
  "id": "87797229",
  "bbox": [
    11.685037,
    42.595495,
    11.685037,
    42.595495
  ],
  "description": "An eleventh and tenth century B.C. settlement in south Etruria.",
  "connectsWith": [
    "748685357"
  ],
  "names": [
    "Sorgenti della Nova"
  ],
  "features": [
    {
      "type": "Feature",
      "geometry": {
        "type": "Point",
        "coordinates": [
          11.685037,
          42.595495
        ]
      },
      "properties": {
        "description": "representative point"
      }
    },
    {
      "geometry": {
        "type": "Point",
        "coordinates": [
          11.685037,
          42.595495
        ]
      },
      "id": "osm-location-of-sorgenti-della-nova-castle",
      "type": "Feature",
      "properties": {
        "description": "Associated location based on OpenStreetMap. The castle occupies the same hilltop that was once the site of the protohistoric settlement.",
        "location_precision": "precise",
        "title": "OSM location of Sorgenti della Nova (castle)",
        "link": "http://pleiades.stoa.org/places/87797229/osm-location-of-sorgenti-della-nova-castle"
      }
    }
  ]
}