{
  "type": "FeatureCollection",
  "title": "Meher Kap覺s覺",
  "id": "878177649",
  "bbox": [
    43.3875,
    38.5182,
    43.3875,
    38.5182
  ],
  "description": "Urartian inscribed rock niche.",
  "features": [
    {
      "type": "Feature",
      "geometry": {
        "type": "Point",
        "coordinates": [
          43.3875,
          38.5182
        ]
      },
      "properties": {
        "description": "representative point"
      }
    },
    {
      "geometry": {
        "type": "Point",
        "coordinates": [
          43.3875,
          38.5182
        ]
      },
      "id": "cigs-location-of-meher-kapisi",
      "type": "Feature",
      "properties": {
        "description": null,
        "location_precision": "precise",
        "title": "CIGS location of Meher Kap覺s覺",
        "link": "http://pleiades.stoa.org/places/878177649/cigs-location-of-meher-kapisi"
      }
    }
  ]
}