{
  "type": "FeatureCollection",
  "title": "Temple of Iuno Sospita, Lanuvium",
  "id": "879109673",
  "bbox": [
    12.6988018,
    41.6779167,
    12.6988018,
    41.6779167
  ],
  "description": "A celebrated cult-place sacred to Iuno Sospita that retained its sacred significance even after a cult to the same divinity was dedicated in the Forum Holitorium in Rome in 194 BCE.",
  "connectsWith": [
    "422956"
  ],
  "features": [
    {
      "type": "Feature",
      "geometry": {
        "type": "Point",
        "coordinates": [
          12.6988018,
          41.6779167
        ]
      },
      "properties": {
        "description": "representative point"
      }
    },
    {
      "geometry": {
        "type": "Point",
        "coordinates": [
          12.6988018,
          41.6779167
        ]
      },
      "id": "osm-location-of-tempio-di-giunone-sospita",
      "type": "Feature",
      "properties": {
        "description": "Representative location based on OpenStreetMap",
        "location_precision": "precise",
        "title": "OSM location of Tempio di Giunone Sospita",
        "link": "http://pleiades.stoa.org/places/879109673/osm-location-of-tempio-di-giunone-sospita"
      }
    }
  ]
}