{
  "type": "FeatureCollection",
  "title": "Amol",
  "id": "884116",
  "bbox": [
    52.356944,
    36.466943,
    52.356944,
    36.466943
  ],
  "description": "An ancient place, cited: BAtlas 90 H4 Amol",
  "names": [
    "Amol"
  ],
  "features": [
    {
      "type": "Feature",
      "geometry": {
        "type": "Point",
        "coordinates": [
          52.356944,
          36.466943
        ]
      },
      "properties": {
        "description": "representative point"
      }
    },
    {
      "geometry": {
        "type": "Point",
        "coordinates": [
          52.356944,
          36.466943
        ]
      },
      "id": "darmc-location-22116",
      "type": "Feature",
      "properties": {
        "description": "Point location",
        "location_precision": "precise",
        "title": "DARMC location 22116",
        "link": "http://pleiades.stoa.org/places/884116/darmc-location-22116"
      }
    }
  ]
}