{
  "type": "FeatureCollection",
  "title": "Dizli",
  "id": "884142",
  "description": "An ancient place, cited: BAtlas 90 B2 Dizli",
  "bbox": [
    46.921196,
    38.543395,
    46.921196,
    38.543395
  ],
  "reprPoint": [
    46.921196,
    38.543395
  ],
  "features": [
    {
      "geometry": {
        "type": "Point",
        "coordinates": [
          46.921196,
          38.543395
        ]
      },
      "id": "darmc-location-22088",
      "type": "Feature",
      "properties": {
        "description": "Point location",
        "location_precision": "precise",
        "title": "DARMC location 22088",
        "link": "http://pleiades.stoa.org/places/884142/darmc-location-22088"
      }
    }
  ]
}