{
  "type": "FeatureCollection",
  "title": "Adjalu",
  "id": "884108",
  "description": "An ancient place, cited: BAtlas 90 B4 Adjalu",
  "bbox": [
    46.359347,
    36.835529,
    46.359347,
    36.835529
  ],
  "reprPoint": [
    46.359347,
    36.835529
  ],
  "features": [
    {
      "geometry": {
        "type": "Point",
        "coordinates": [
          46.359347,
          36.835529
        ]
      },
      "id": "darmc-location-22104",
      "type": "Feature",
      "properties": {
        "description": "Point location",
        "location_precision": "precise",
        "title": "DARMC location 22104",
        "link": "http://pleiades.stoa.org/places/884108/darmc-location-22104"
      }
    }
  ]
}