{
  "type": "FeatureCollection",
  "title": "Laclac Gaisi",
  "id": "884175",
  "description": "An ancient place, cited: BAtlas 90 B4 Laclac Gaisi",
  "bbox": [
    46.114411,
    36.740595,
    46.114411,
    36.740595
  ],
  "reprPoint": [
    46.114411,
    36.740595
  ],
  "features": [
    {
      "geometry": {
        "type": "Point",
        "coordinates": [
          46.114411,
          36.740595
        ]
      },
      "id": "darmc-location-22111",
      "type": "Feature",
      "properties": {
        "description": "Point location",
        "location_precision": "precise",
        "title": "DARMC location 22111",
        "link": "http://pleiades.stoa.org/places/884175/darmc-location-22111"
      }
    }
  ]
}