{
  "type": "FeatureCollection",
  "title": "Aganzana",
  "id": "884110",
  "bbox": [
    48.485111,
    36.67094,
    48.485111,
    36.67094
  ],
  "description": "An ancient place, cited: BAtlas 90 D4 Aganzana",
  "names": [
    "Aganzana"
  ],
  "features": [
    {
      "type": "Feature",
      "geometry": {
        "type": "Point",
        "coordinates": [
          48.485111,
          36.67094
        ]
      },
      "properties": {
        "description": "representative point"
      }
    },
    {
      "geometry": {
        "type": "Point",
        "coordinates": [
          48.485111,
          36.67094
        ]
      },
      "id": "darmc-location-22117",
      "type": "Feature",
      "properties": {
        "description": "Point location",
        "location_precision": "precise",
        "title": "DARMC location 22117",
        "link": "http://pleiades.stoa.org/places/884110/darmc-location-22117"
      }
    }
  ]
}