{
  "type": "FeatureCollection",
  "title": "Dashkasen",
  "id": "884139",
  "bbox": [
    46.517617,
    38.535444,
    46.517617,
    38.535444
  ],
  "description": "An ancient place, cited: BAtlas 90 B2 Dashkasen",
  "features": [
    {
      "type": "Feature",
      "geometry": {
        "type": "Point",
        "coordinates": [
          46.517617,
          38.535444
        ]
      },
      "properties": {
        "description": "representative point"
      }
    },
    {
      "geometry": {
        "type": "Point",
        "coordinates": [
          46.517617,
          38.535444
        ]
      },
      "id": "darmc-location-22093",
      "type": "Feature",
      "properties": {
        "description": "Point location",
        "location_precision": "precise",
        "title": "DARMC location 22093",
        "link": "http://pleiades.stoa.org/places/884139/darmc-location-22093"
      }
    }
  ]
}