{
  "type": "FeatureCollection",
  "title": "Parachoatras/Choatras M./Padishxvargar",
  "id": "884905",
  "description": "A mountainous area in the vicinity of the Caspian, possibly to be associated with the Alburz and Talish mountains.",
  "bbox": [
    48.3,
    36.075833,
    51.796111,
    38.7
  ],
  "reprPoint": [
    50.0480555,
    37.3879165
  ],
  "names": [
    "Parachoatras",
    "Choatras M.",
    "Padishxvargar"
  ],
  "features": [
    {
      "geometry": {
        "type": "Point",
        "coordinates": [
          48.3,
          38.7
        ]
      },
      "id": "location-of-talysh-mountains",
      "type": "Feature",
      "properties": {
        "description": "coordinates after GeoHack.",
        "location_precision": "precise",
        "title": "location of Talysh Mountains",
        "link": "http://pleiades.stoa.org/places/884905/location-of-talysh-mountains"
      }
    },
    {
      "geometry": {
        "type": "Point",
        "coordinates": [
          51.796111,
          36.075833
        ]
      },
      "id": "location-of-mount-alborz",
      "type": "Feature",
      "properties": {
        "description": "coordinates after GeoHack.",
        "location_precision": "precise",
        "title": "location of Mount Alborz",
        "link": "http://pleiades.stoa.org/places/884905/location-of-mount-alborz"
      }
    }
  ]
}