{
  "type": "FeatureCollection",
  "title": "Garn Fadryn",
  "id": "886371212",
  "bbox": [
    -4.557763,
    52.8857103,
    -4.557763,
    52.8857103
  ],
  "description": "A 5 ha Iron Age hill fort located in Wales.",
  "features": [
    {
      "type": "Feature",
      "geometry": {
        "type": "Point",
        "coordinates": [
          -4.557763,
          52.8857103
        ]
      },
      "properties": {
        "description": "representative point"
      }
    },
    {
      "geometry": {
        "type": "Point",
        "coordinates": [
          -4.557763,
          52.8857103
        ]
      },
      "id": "location-of-garn-fadryn-hill-fort",
      "type": "Feature",
      "properties": {
        "description": "Location based on OpenStreetMap",
        "location_precision": "precise",
        "title": "location of Garn Fadryn hill fort",
        "link": "http://pleiades.stoa.org/places/886371212/location-of-garn-fadryn-hill-fort"
      }
    }
  ]
}