{
  "type": "FeatureCollection",
  "title": "Kaymakçı",
  "id": "886756147",
  "bbox": [
    27.929806,
    38.623692,
    27.929806,
    38.623692
  ],
  "description": "A large Bronze Age settlement on the western shore of Lake Marmara in western Anatolia, overlooking the central Gediz river valley. The site is composed of an 8-hectare fortified citadel situated on a ridge, with evidence of a larger lower town below on the surrounding plain.",
  "connectsWith": [
    "415460394"
  ],
  "names": [
    "Kaymakçı"
  ],
  "features": [
    {
      "type": "Feature",
      "geometry": {
        "type": "Point",
        "coordinates": [
          27.929806,
          38.623692
        ]
      },
      "properties": {
        "description": "representative point"
      }
    },
    {
      "geometry": {
        "type": "Point",
        "coordinates": [
          27.929806,
          38.623692
        ]
      },
      "id": "kaymakc131",
      "type": "Feature",
      "properties": {
        "description": "the lower ridge of Gür Dağ, west of Lake Marmara",
        "location_precision": "precise",
        "title": "Kaymakçı ridge",
        "link": "http://pleiades.stoa.org/places/886756147/kaymakc131"
      }
    }
  ]
}