{
  "type": "FeatureCollection",
  "title": "vicus vitrarius",
  "id": "88851260",
  "bbox": [
    12.486137,
    41.891775,
    12.486137,
    41.891775
  ],
  "description": "A street in Regio I known only from the Regionary Catalogues.",
  "connectsWith": [
    "423025",
    "307963010"
  ],
  "names": [
    "vicus vitrarius"
  ],
  "features": [
    {
      "type": "Feature",
      "geometry": {
        "type": "Point",
        "coordinates": [
          12.486137,
          41.891775
        ]
      },
      "properties": {
        "description": "representative point"
      }
    }
  ]
}