{
  "type": "FeatureCollection",
  "title": "Le Peu (Charente)",
  "id": "888830080",
  "bbox": [
    0.1138505,
    45.9502838,
    0.1138505,
    45.9502838
  ],
  "description": "The archaeological site at Le Peu (Charente) dates originally to the mid-fifth millennium BCE and preserves evidence of a fortified Middle Neolithic settlement with timber structures. The ditch and palisade fortifications and the timber structures represent the earliest evidence of such architecture in Atlantic Europe. The fortified site is located close to the monumental Tusson tumuli.",
  "connectsWith": [
    "47784683"
  ],
  "names": [
    "Le Peu (Charente)"
  ],
  "features": [
    {
      "type": "Feature",
      "geometry": {
        "type": "Point",
        "coordinates": [
          0.1138505,
          45.9502838
        ]
      },
      "properties": {
        "description": "representative point"
      }
    },
    {
      "geometry": {
        "type": "Point",
        "coordinates": [
          0.1138505,
          45.9502838
        ]
      },
      "id": "osm-location-of-modern-village-of-charma-c",
      "type": "Feature",
      "properties": {
        "description": "Location based on OpenStreetMap",
        "location_precision": "precise",
        "title": "OSM location of modern village of Charmé",
        "link": "http://pleiades.stoa.org/places/888830080/osm-location-of-modern-village-of-charma-c"
      }
    }
  ]
}