{
  "type": "FeatureCollection",
  "title": "Kalhu Archive 14",
  "id": "889344378",
  "bbox": [
    43.330672,
    36.096925,
    43.330672,
    36.096925
  ],
  "description": "The remains of a library containing about 280 clay tablets were found in and around Room NT12 the Nabû Temple (Ezida). These text date from 800 BC to 614 BC. The majority of the texts assigned to this archive repository were discovered in Room NT12 and the adjoining courtyard. Some texts, including fragments of seven wooden and ivory writing boards, were found in Rooms NT13 and NT14. This Neo-Assyrian ‘library’ house omen texts (79 tablets), incantation and medical texts (75 tablets), lexical lists (37 tablets), as well as some administrative texts, epics, hemerological texts, hymns, prayers, rituals, and royal inscriptions.",
  "connectsWith": [
    "894019",
    "242008148"
  ],
  "names": [
    "Kalhu Archive 14"
  ],
  "features": [
    {
      "type": "Feature",
      "geometry": {
        "type": "Point",
        "coordinates": [
          43.330672,
          36.096925
        ]
      },
      "properties": {
        "description": "representative point"
      }
    },
    {
      "geometry": {
        "type": "Point",
        "coordinates": [
          43.330672,
          36.096925
        ]
      },
      "id": "plan-location-of-kalhu-archive-14",
      "type": "Feature",
      "properties": {
        "description": "Representative locations of the Neo-Assyrian archive at Kalhu on the basis of Pedersén 1987 Plan(s) 66 and 70.",
        "location_precision": "precise",
        "title": "Plan location of Kalhu Archive 14",
        "link": "http://pleiades.stoa.org/places/889344378/plan-location-of-kalhu-archive-14"
      }
    }
  ]
}