{
  "type": "FeatureCollection",
  "title": "Gal'adi",
  "id": "889522883",
  "bbox": [
    35.7908645,
    32.0954515,
    35.7908645,
    32.0954515
  ],
  "description": "A town mentioned in Neo-Assyrian sources; the modern site is Khirbet Ǧalʿad.",
  "names": [
    "Khirbet Gal'ad",
    "*Galʾadi"
  ],
  "features": [
    {
      "type": "Feature",
      "geometry": {
        "type": "Point",
        "coordinates": [
          35.7908645,
          32.0954515
        ]
      },
      "properties": {
        "description": "representative point"
      }
    },
    {
      "geometry": {
        "type": "Point",
        "coordinates": [
          35.7908645,
          32.0954515
        ]
      },
      "id": "osm-location-of-khirbet-galad",
      "type": "Feature",
      "properties": {
        "description": "Location based on OpenStreetMap",
        "location_precision": "precise",
        "title": "OSM location of Khirbet Gal'ad",
        "link": "http://pleiades.stoa.org/places/889522883/osm-location-of-khirbet-galad"
      }
    }
  ]
}