{
  "type": "FeatureCollection",
  "title": "Alauna",
  "id": "89099",
  "description": "An ancient place, cited: BAtlas 9 F5 Alauna",
  "bbox": [
    -1.820411,
    55.396463,
    -1.820411,
    55.396463
  ],
  "reprPoint": [
    -1.820411,
    55.396463
  ],
  "names": [
    "Alauna"
  ],
  "features": [
    {
      "geometry": {
        "type": "Point",
        "coordinates": [
          -1.820411,
          55.396463
        ]
      },
      "id": "darmc-location-6250",
      "type": "Feature",
      "properties": {
        "description": "1M scale point location",
        "location_precision": "precise",
        "title": "DARMC location 6250",
        "link": "http://pleiades.stoa.org/places/89099/darmc-location-6250"
      }
    }
  ]
}