{
  "type": "FeatureCollection",
  "title": "B(r)ibra?",
  "id": "89125",
  "bbox": [
    -3.418604,
    54.826122,
    -3.418604,
    54.826122
  ],
  "description": "Roman fort at present-day Beckfoot. Part of the Cumbrian coastal defenses.",
  "connectsWith": [
    "579047271"
  ],
  "names": [
    "Bibra",
    "Beckfoot Roman Fort",
    "Bribra"
  ],
  "features": [
    {
      "type": "Feature",
      "geometry": {
        "type": "Point",
        "coordinates": [
          -3.418604,
          54.826122
        ]
      },
      "properties": {
        "description": "representative point"
      }
    },
    {
      "geometry": {
        "type": "Point",
        "coordinates": [
          -3.418604,
          54.826122
        ]
      },
      "id": "centerpoint-of-the-ancient-site",
      "type": "Feature",
      "properties": {
        "description": null,
        "location_precision": "precise",
        "title": "Centerpoint of the ancient site",
        "link": "http://pleiades.stoa.org/places/89125/centerpoint-of-the-ancient-site"
      }
    }
  ]
}