{
  "type": "FeatureCollection",
  "title": "B(r)ibra?",
  "id": "89125",
  "description": "Roman fort at present-day Beckfoot. Part of the Cumbrian coastal defenses.",
  "bbox": [
    -3.418604,
    54.826122,
    -3.411477,
    54.83536
  ],
  "reprPoint": [
    -3.4150405,
    54.830741
  ],
  "names": [
    "Beckfoot Roman Fort",
    "Bribra",
    "Bibra"
  ],
  "features": [
    {
      "geometry": {
        "type": "Point",
        "coordinates": [
          -3.418604,
          54.826122
        ]
      },
      "id": "centerpoint-of-the-ancient-site",
      "type": "Feature",
      "properties": {
        "description": null,
        "location_precision": "precise",
        "title": "Centerpoint of the ancient site",
        "link": "http://pleiades.stoa.org/places/89125/centerpoint-of-the-ancient-site"
      }
    }
  ]
}