{
  "type": "FeatureCollection",
  "title": "[Derventio] (river)",
  "id": "89167",
  "description": "An ancient place, cited: BAtlas 9 G7 [Derventio] fl.",
  "bbox": [
    -1.4416236,
    52.9144126,
    -1.4416236,
    52.9144126
  ],
  "reprPoint": [
    -1.4416236,
    52.9144126
  ],
  "names": [
    "[Derventio]"
  ],
  "features": [
    {
      "geometry": {
        "type": "Point",
        "coordinates": [
          -1.4416236,
          52.9144126
        ]
      },
      "id": "osm-location",
      "type": "Feature",
      "properties": {
        "description": "Representative location based on OpenStreetMap.",
        "location_precision": "precise",
        "title": "OSM location of River Derwent",
        "link": "http://pleiades.stoa.org/places/89167/osm-location"
      }
    }
  ]
}