{
  "type": "FeatureCollection",
  "title": "Deoua (river)",
  "id": "89164",
  "bbox": [
    -2.9138769,
    57.0674547,
    -2.9138769,
    57.0674547
  ],
  "description": "An ancient place, cited: BAtlas 9 E3 Deoua fl.",
  "names": [
    "Deoua"
  ],
  "features": [
    {
      "type": "Feature",
      "geometry": {
        "type": "Point",
        "coordinates": [
          -2.9138769,
          57.0674547
        ]
      },
      "properties": {
        "description": "representative point"
      }
    },
    {
      "geometry": {
        "type": "Point",
        "coordinates": [
          -2.9138769,
          57.0674547
        ]
      },
      "id": "osm-location",
      "type": "Feature",
      "properties": {
        "description": "Representative location based on OpenStreetMap.",
        "location_precision": "precise",
        "title": "OSM location of River Dee",
        "link": "http://pleiades.stoa.org/places/89164/osm-location"
      }
    }
  ]
}