{
  "type": "FeatureCollection",
  "title": "Derventio (river)",
  "id": "89167",
  "bbox": [
    -1.4416236,
    52.9144126,
    -1.4416236,
    52.9144126
  ],
  "description": "Known today as the Derwent, the Derventio river is in the UK.",
  "names": [
    "Derventio"
  ],
  "features": [
    {
      "type": "Feature",
      "geometry": {
        "type": "Point",
        "coordinates": [
          -1.4416236,
          52.9144126
        ]
      },
      "properties": {
        "description": "representative point"
      }
    },
    {
      "geometry": {
        "type": "Point",
        "coordinates": [
          -1.4416236,
          52.9144126
        ]
      },
      "id": "osm-location",
      "type": "Feature",
      "properties": {
        "description": "Representative location based on OpenStreetMap.",
        "location_precision": "precise",
        "title": "OSM location of River Derwent",
        "link": "http://pleiades.stoa.org/places/89167/osm-location"
      }
    }
  ]
}