{
  "type": "FeatureCollection",
  "title": "Gabrosentum",
  "id": "89189",
  "description": "A Roman fort at present-day Moresby, cited: BAtlas 9 D6 Gabrosentum. Part of Cumbrian coastal defenses.",
  "bbox": [
    -3.576289,
    54.573931,
    -3.557333,
    54.578812
  ],
  "reprPoint": [
    -3.566811,
    54.5763715
  ],
  "names": [
    "Moresby",
    "Gabrosentum"
  ],
  "features": [
    {
      "geometry": {
        "type": "Point",
        "coordinates": [
          -3.576289,
          54.573931
        ]
      },
      "id": "centerpoint-of-the-ancient-site",
      "type": "Feature",
      "properties": {
        "description": null,
        "location_precision": "precise",
        "title": "Centerpoint of the ancient site",
        "link": "http://pleiades.stoa.org/places/89189/centerpoint-of-the-ancient-site"
      }
    }
  ]
}