{
  "type": "FeatureCollection",
  "title": "Victoria?",
  "id": "89206",
  "bbox": [
    -3.424,
    56.525841,
    -3.399193,
    56.541
  ],
  "description": "A Roman fort probably to be identified with modern day Dalginross.",
  "names": [
    "Victoria",
    "Dalginross"
  ],
  "features": [
    {
      "type": "Feature",
      "geometry": {
        "type": "Point",
        "coordinates": [
          -3.4115965,
          56.5334205
        ]
      },
      "properties": {
        "description": "representative point"
      }
    },
    {
      "geometry": {
        "type": "Point",
        "coordinates": [
          -3.399193,
          56.525841
        ]
      },
      "id": "darmc-location-19220",
      "type": "Feature",
      "properties": {
        "description": "1M scale point location",
        "location_precision": "precise",
        "title": "DARMC location 19220",
        "link": "http://pleiades.stoa.org/places/89206/darmc-location-19220"
      }
    },
    {
      "geometry": {
        "type": "Point",
        "coordinates": [
          -3.424,
          56.541
        ]
      },
      "id": "dare-location",
      "type": "Feature",
      "properties": {
        "description": "Representative point location, site precision",
        "location_precision": "precise",
        "title": "DARE Location",
        "link": "http://pleiades.stoa.org/places/89206/dare-location"
      }
    }
  ]
}