{
  "type": "FeatureCollection",
  "title": "Huntcliff",
  "id": "89202",
  "description": "An ancient place, cited: BAtlas 9 G6 Huntcliff",
  "bbox": [
    -0.932836,
    54.5718,
    -0.932836,
    54.5718
  ],
  "reprPoint": [
    -0.932836,
    54.5718
  ],
  "features": [
    {
      "geometry": {
        "type": "Point",
        "coordinates": [
          -0.932836,
          54.5718
        ]
      },
      "id": "darmc-location-19132",
      "type": "Feature",
      "properties": {
        "description": "1M scale point location",
        "location_precision": "precise",
        "title": "DARMC location 19132",
        "link": "http://pleiades.stoa.org/places/89202/darmc-location-19132"
      }
    }
  ]
}