{
  "type": "FeatureCollection",
  "title": "Isurium",
  "id": "89209",
  "bbox": [
    -1.380761,
    54.09191,
    -1.380761,
    54.09191
  ],
  "description": "Isurium (modern Aldborough) was a Roman settlement - and likely fort - along Dere Street.",
  "connectsWith": [
    "89126",
    "82519025"
  ],
  "names": [
    "Isurium"
  ],
  "features": [
    {
      "type": "Feature",
      "geometry": {
        "type": "Point",
        "coordinates": [
          -1.380761,
          54.09191
        ]
      },
      "properties": {
        "description": "representative point"
      }
    },
    {
      "geometry": {
        "type": "Point",
        "coordinates": [
          -1.380761,
          54.09191
        ]
      },
      "id": "dare-location",
      "type": "Feature",
      "properties": {
        "description": "Representative point location, village precision",
        "location_precision": "precise",
        "title": "DARE Location",
        "link": "http://pleiades.stoa.org/places/89209/dare-location"
      }
    }
  ]
}