{
  "type": "FeatureCollection",
  "title": "Isurium",
  "id": "89209",
  "description": "Isurium (modern Aldborough) was a Roman settlement - and likely fort - along Dere Street.",
  "bbox": [
    -1.380761,
    54.09191,
    -1.380761,
    54.09191
  ],
  "connectsWith": [
    "82519025"
  ],
  "reprPoint": [
    -1.380761,
    54.09191
  ],
  "names": [
    "Isurium"
  ],
  "features": [
    {
      "geometry": {
        "type": "Point",
        "coordinates": [
          -1.3796296,
          54.0881157
        ]
      },
      "id": "possible-location-of-roman-amphitheater",
      "type": "Feature",
      "properties": {
        "description": "Archaeological remains at 'Aldborough Studforth Hill' site. Location based on OpenStreetMap.",
        "location_precision": "precise",
        "title": "possible location of Roman amphitheater",
        "link": "http://pleiades.stoa.org/places/89209/possible-location-of-roman-amphitheater"
      }
    },
    {
      "geometry": {
        "type": "Point",
        "coordinates": [
          -1.380761,
          54.09191
        ]
      },
      "id": "dare-location",
      "type": "Feature",
      "properties": {
        "description": "Representative point location, village precision",
        "location_precision": "precise",
        "title": "DARE Location",
        "link": "http://pleiades.stoa.org/places/89209/dare-location"
      }
    }
  ]
}