{
  "type": "FeatureCollection",
  "title": "Kirk Sink",
  "id": "89217",
  "bbox": [
    -2.0944722,
    53.9790012,
    -2.0944722,
    53.9790012
  ],
  "description": "An ancient place, cited: BAtlas 9 E7 Kirk Sink",
  "features": [
    {
      "type": "Feature",
      "geometry": {
        "type": "Point",
        "coordinates": [
          -2.0944722,
          53.9790012
        ]
      },
      "properties": {
        "description": "representative point"
      }
    },
    {
      "geometry": {
        "type": "Point",
        "coordinates": [
          -2.0944722,
          53.9790012
        ]
      },
      "id": "location-of-kirk-sink-roman-villa",
      "type": "Feature",
      "properties": {
        "description": "Representative location based on OpenStreetMap.",
        "location_precision": "precise",
        "title": "OSM location of Kirk Sink Roman villa",
        "link": "http://pleiades.stoa.org/places/89217/location-of-kirk-sink-roman-villa"
      }
    }
  ]
}