{
  "type": "FeatureCollection",
  "title": "Kirk Sink",
  "id": "89217",
  "bbox": [
    -2.10313,
    53.9790012,
    -2.0944722,
    53.981909
  ],
  "description": "An ancient place, cited: BAtlas 9 E7 Kirk Sink",
  "features": [
    {
      "type": "Feature",
      "geometry": {
        "type": "Point",
        "coordinates": [
          -2.0988011,
          53.9804551
        ]
      },
      "properties": {
        "description": "representative point"
      }
    },
    {
      "geometry": {
        "type": "Point",
        "coordinates": [
          -2.10313,
          53.981909
        ]
      },
      "id": "darmc-location-20939",
      "type": "Feature",
      "properties": {
        "description": "1M scale point location",
        "location_precision": "precise",
        "title": "DARMC location 20939",
        "link": "http://pleiades.stoa.org/places/89217/darmc-location-20939"
      }
    },
    {
      "geometry": {
        "type": "Point",
        "coordinates": [
          -2.0944722,
          53.9790012
        ]
      },
      "id": "location-of-kirk-sink-roman-villa",
      "type": "Feature",
      "properties": {
        "description": "Location based on OpenStreetMap",
        "location_precision": "precise",
        "title": "location of Kirk Sink Roman villa",
        "link": "http://pleiades.stoa.org/places/89217/location-of-kirk-sink-roman-villa"
      }
    }
  ]
}