{
  "type": "FeatureCollection",
  "title": "Lindon?",
  "id": "89226",
  "bbox": [
    -4.453567,
    56.063365,
    -4.453567,
    56.063365
  ],
  "description": "An ancient place, cited: BAtlas 9 C4 Lindon?",
  "names": [
    "Lindon"
  ],
  "features": [
    {
      "type": "Feature",
      "geometry": {
        "type": "Point",
        "coordinates": [
          -4.453567,
          56.063365
        ]
      },
      "properties": {
        "description": "representative point"
      }
    },
    {
      "geometry": {
        "type": "Point",
        "coordinates": [
          -4.453567,
          56.063365
        ]
      },
      "id": "darmc-location-19151",
      "type": "Feature",
      "properties": {
        "description": "1M scale point location",
        "location_precision": "precise",
        "title": "DARMC location 19151",
        "link": "http://pleiades.stoa.org/places/89226/darmc-location-19151"
      }
    }
  ]
}