{
  "type": "FeatureCollection",
  "title": "Old Durham",
  "id": "89258",
  "bbox": [
    -1.559667,
    54.778678,
    -1.559667,
    54.778678
  ],
  "description": "An ancient place, cited: BAtlas 9 F6 Old Durham",
  "features": [
    {
      "type": "Feature",
      "geometry": {
        "type": "Point",
        "coordinates": [
          -1.559667,
          54.778678
        ]
      },
      "properties": {
        "description": "representative point"
      }
    },
    {
      "geometry": {
        "type": "Point",
        "coordinates": [
          -1.559667,
          54.778678
        ]
      },
      "id": "darmc-location-21021",
      "type": "Feature",
      "properties": {
        "description": "1M scale point location",
        "location_precision": "precise",
        "title": "DARMC location 21021",
        "link": "http://pleiades.stoa.org/places/89258/darmc-location-21021"
      }
    }
  ]
}