{
  "type": "FeatureCollection",
  "title": "Oueroubioum Akron",
  "id": "89267",
  "description": "An ancient place, cited: BAtlas 9 D2 Oueroubioum Akron",
  "bbox": [
    -3.051004,
    58.4795685,
    -3.051004,
    58.4795685
  ],
  "reprPoint": [
    -3.051004,
    58.4795685
  ],
  "names": [
    "Oueroubioum Akron"
  ],
  "features": [
    {
      "geometry": {
        "type": "Point",
        "coordinates": [
          -3.051004,
          58.4795685
        ]
      },
      "id": "location-of-oueroubioum-akron",
      "type": "Feature",
      "properties": {
        "description": "Location based on OpenStreetMap",
        "location_precision": "precise",
        "title": "location of Oueroubioum Akron",
        "link": "http://pleiades.stoa.org/places/89267/location-of-oueroubioum-akron"
      }
    }
  ]
}