{
  "type": "FeatureCollection",
  "title": "Scarborough",
  "id": "89285",
  "description": "An ancient place, cited: BAtlas 9 G6 Scarborough",
  "bbox": [
    -0.402424,
    54.280123,
    -0.3860551,
    54.2895333
  ],
  "reprPoint": [
    -0.392004066667,
    54.2856747667
  ],
  "features": [
    {
      "geometry": {
        "type": "Point",
        "coordinates": [
          -0.402424,
          54.280123
        ]
      },
      "id": "darmc-location-19199",
      "type": "Feature",
      "properties": {
        "description": "1M scale point location",
        "location_precision": "precise",
        "title": "DARMC location 19199",
        "link": "http://pleiades.stoa.org/places/89285/darmc-location-19199"
      }
    }
  ]
}