{
  "type": "FeatureCollection",
  "title": "Scarborough",
  "id": "89285",
  "description": "On Castle Hill, Scarborough, a Roman signal station was established ca. A.D. 370 that remained in use until the early fifth century.",
  "bbox": [
    -0.4090339,
    54.280123,
    -0.402424,
    54.2847601
  ],
  "reprPoint": [
    -0.40572895,
    54.28244155
  ],
  "features": [
    {
      "geometry": {
        "type": "Point",
        "coordinates": [
          -0.402424,
          54.280123
        ]
      },
      "id": "darmc-location-19199",
      "type": "Feature",
      "properties": {
        "description": "1M scale point location",
        "location_precision": "precise",
        "title": "DARMC location 19199",
        "link": "http://pleiades.stoa.org/places/89285/darmc-location-19199"
      }
    },
    {
      "geometry": {
        "type": "Point",
        "coordinates": [
          -0.4090339,
          54.2847601
        ]
      },
      "id": "osm-location-for-centerpoint-of-scarborough",
      "type": "Feature",
      "properties": {
        "description": "Location based on OpenStreetMap",
        "location_precision": "precise",
        "title": "OSM location for Centerpoint of modern Scarborough",
        "link": "http://pleiades.stoa.org/places/89285/osm-location-for-centerpoint-of-scarborough"
      }
    }
  ]
}