{
  "type": "FeatureCollection",
  "title": "Scarborough",
  "id": "89285",
  "description": "On Castle Hill, Scarborough, a Roman signal station was established ca. A.D. 370 that remained in use until the early fifth century.",
  "bbox": [
    -0.402424,
    54.280123,
    -0.3860551,
    54.287368
  ],
  "reprPoint": [
    -0.39423955,
    54.2837455
  ],
  "features": [
    {
      "geometry": {
        "type": "Point",
        "coordinates": [
          -0.402424,
          54.280123
        ]
      },
      "id": "darmc-location-19199",
      "type": "Feature",
      "properties": {
        "description": "1M scale point location",
        "location_precision": "precise",
        "title": "DARMC location 19199",
        "link": "http://pleiades.stoa.org/places/89285/darmc-location-19199"
      }
    },
    {
      "geometry": {
        "type": "Point",
        "coordinates": [
          -0.3860551,
          54.287368
        ]
      },
      "id": "osm-location-of-roman-signal-station",
      "type": "Feature",
      "properties": {
        "description": "Location based on OpenStreetMap",
        "location_precision": "precise",
        "title": "OSM location of Roman signal station",
        "link": "http://pleiades.stoa.org/places/89285/osm-location-of-roman-signal-station"
      }
    }
  ]
}