{
  "type": "FeatureCollection",
  "title": "Scarborough",
  "id": "89285",
  "bbox": [
    -0.4090339,
    54.2847601,
    -0.4090339,
    54.2847601
  ],
  "description": "On Castle Hill, Scarborough, a Roman signal station was established ca. A.D. 370 that remained in use until the early fifth century. A medieval castle was established ca. A.D. 1135.",
  "features": [
    {
      "type": "Feature",
      "geometry": {
        "type": "Point",
        "coordinates": [
          -0.4090339,
          54.2847601
        ]
      },
      "properties": {
        "description": "representative point"
      }
    },
    {
      "geometry": {
        "type": "Point",
        "coordinates": [
          -0.4090339,
          54.2847601
        ]
      },
      "id": "osm-location-for-centerpoint-of-scarborough",
      "type": "Feature",
      "properties": {
        "description": "Location based on OpenStreetMap",
        "location_precision": "precise",
        "title": "OSM location for Centerpoint of modern Scarborough",
        "link": "http://pleiades.stoa.org/places/89285/osm-location-for-centerpoint-of-scarborough"
      }
    }
  ]
}