{
  "type": "FeatureCollection",
  "title": "Trimontium",
  "id": "89304",
  "bbox": [
    -2.699279,
    55.59958,
    -2.699279,
    55.59958
  ],
  "description": "An ancient place, cited: BAtlas 9 E5 Trimontium",
  "connectsWith": [
    "82519025"
  ],
  "names": [
    "Trimontium"
  ],
  "features": [
    {
      "type": "Feature",
      "geometry": {
        "type": "Point",
        "coordinates": [
          -2.699279,
          55.59958
        ]
      },
      "properties": {
        "description": "representative point"
      }
    },
    {
      "geometry": {
        "type": "Point",
        "coordinates": [
          -2.699279,
          55.59958
        ]
      },
      "id": "darmc-location-19213",
      "type": "Feature",
      "properties": {
        "description": "1M scale point location",
        "location_precision": "precise",
        "title": "DARMC location 19213",
        "link": "http://pleiades.stoa.org/places/89304/darmc-location-19213"
      }
    }
  ]
}