{
  "type": "FeatureCollection",
  "title": "Roman amphitheatre, Charterhouse",
  "id": "893570731",
  "bbox": [
    -2.7206451,
    51.3054023,
    -2.7206451,
    51.3054023
  ],
  "description": "An amphitheater stood to the west of the lead mining settlement at Charterhouse Roman Town.",
  "connectsWith": [
    "79534"
  ],
  "features": [
    {
      "type": "Feature",
      "geometry": {
        "type": "Point",
        "coordinates": [
          -2.7206451,
          51.3054023
        ]
      },
      "properties": {
        "description": "representative point"
      }
    },
    {
      "geometry": {
        "type": "Point",
        "coordinates": [
          -2.7206451,
          51.3054023
        ]
      },
      "id": "location-of-roman-amphitheater",
      "type": "Feature",
      "properties": {
        "description": "Representative location based on OpenStreetMap.",
        "location_precision": "precise",
        "title": "OSM location of Roman amphitheater",
        "link": "http://pleiades.stoa.org/places/893570731/location-of-roman-amphitheater"
      }
    }
  ]
}