{
  "type": "FeatureCollection",
  "title": "Gallo-Roman theater at Alba Helviorum",
  "id": "89384567",
  "bbox": [
    4.602191,
    44.5595398,
    4.602191,
    44.5595398
  ],
  "description": "A third and fourth century theater at Alba Helviorum.",
  "connectsWith": [
    "167629"
  ],
  "features": [
    {
      "type": "Feature",
      "geometry": {
        "type": "Point",
        "coordinates": [
          4.602191,
          44.5595398
        ]
      },
      "properties": {
        "description": "representative point"
      }
    },
    {
      "geometry": {
        "type": "Point",
        "coordinates": [
          4.602191,
          44.5595398
        ]
      },
      "id": "osm-location-of-theater",
      "type": "Feature",
      "properties": {
        "description": "Representative location based on OpenStreetMap.",
        "location_precision": "precise",
        "title": "OSM location of Théatre Antique",
        "link": "http://pleiades.stoa.org/places/89384567/osm-location-of-theater"
      }
    }
  ]
}