{
  "type": "FeatureCollection",
  "title": "Abu Taraichiya",
  "id": "893932",
  "bbox": [
    44.826059,
    32.557584,
    44.826059,
    32.557584
  ],
  "description": "An ancient place, cited: BAtlas 91 F5 Abu Taraichiya",
  "features": [
    {
      "type": "Feature",
      "geometry": {
        "type": "Point",
        "coordinates": [
          44.826059,
          32.557584
        ]
      },
      "properties": {
        "description": "representative point"
      }
    },
    {
      "geometry": {
        "type": "Point",
        "coordinates": [
          44.826059,
          32.557584
        ]
      },
      "id": "darmc-location-22501",
      "type": "Feature",
      "properties": {
        "description": "Point location",
        "location_precision": "precise",
        "title": "DARMC location 22501",
        "link": "http://pleiades.stoa.org/places/893932/darmc-location-22501"
      }
    }
  ]
}