{
  "type": "FeatureCollection",
  "title": "Arrapha/Karkha de Beth Seluk",
  "id": "893941",
  "description": "An ancient place, cited: BAtlas 91 F2 Arrapha/Karkha de Beth Seluk",
  "bbox": [
    44.3953,
    35.468099,
    44.3953,
    35.468099
  ],
  "reprPoint": [
    44.3953,
    35.468099
  ],
  "names": [
    "Qalʿat Kirkūk",
    "Arrapḫa",
    "Arrapḫum",
    "Arrapḫu",
    "Arrapḫi",
    "Kirkuk",
    "Kirkūk",
    "Arrapha",
    "Karkha de Beth Seluk",
    "Arrapachitis"
  ],
  "features": [
    {
      "geometry": {
        "type": "Point",
        "coordinates": [
          44.3953,
          35.468099
        ]
      },
      "id": "darmc-location-22425",
      "type": "Feature",
      "properties": {
        "description": "Point location",
        "location_precision": "precise",
        "title": "DARMC location 22425",
        "link": "http://pleiades.stoa.org/places/893941/darmc-location-22425"
      }
    }
  ]
}