{
  "type": "FeatureCollection",
  "title": "Abu Jilaj",
  "id": "893930",
  "description": "An ancient place, cited: BAtlas 91 F4 Abu Jilaj",
  "bbox": [
    44.817362,
    33.260584,
    44.817362,
    33.260584
  ],
  "reprPoint": [
    44.817362,
    33.260584
  ],
  "features": [
    {
      "geometry": {
        "type": "Point",
        "coordinates": [
          44.817362,
          33.260584
        ]
      },
      "id": "darmc-location-22482",
      "type": "Feature",
      "properties": {
        "description": "Point location",
        "location_precision": "precise",
        "title": "DARMC location 22482",
        "link": "http://pleiades.stoa.org/places/893930/darmc-location-22482"
      }
    }
  ]
}