{
  "type": "FeatureCollection",
  "title": "Ishan al-Khara",
  "id": "894009",
  "description": "An ancient place, cited: BAtlas 91 F5 Ishan al-Khara",
  "bbox": [
    44.78311,
    32.538977,
    44.78311,
    32.538977
  ],
  "reprPoint": [
    44.78311,
    32.538977
  ],
  "features": [
    {
      "geometry": {
        "type": "Point",
        "coordinates": [
          44.78311,
          32.538977
        ]
      },
      "id": "darmc-location-32495",
      "type": "Feature",
      "properties": {
        "description": "scale point location",
        "location_precision": "precise",
        "title": "DARMC location 32495",
        "link": "http://pleiades.stoa.org/places/894009/darmc-location-32495"
      }
    }
  ]
}