{
  "type": "FeatureCollection",
  "title": "Khirbet Qubr Ibn Naif",
  "id": "894024",
  "description": "An ancient place, cited: BAtlas 91 E2 Khirbet Qubr Ibn Naif",
  "bbox": [
    42.946049,
    35.879143,
    42.946049,
    35.879143
  ],
  "reprPoint": [
    42.946049,
    35.879143
  ],
  "features": [
    {
      "geometry": {
        "type": "Point",
        "coordinates": [
          42.946049,
          35.879143
        ]
      },
      "id": "darmc-location-22420",
      "type": "Feature",
      "properties": {
        "description": "Point location",
        "location_precision": "precise",
        "title": "DARMC location 22420",
        "link": "http://pleiades.stoa.org/places/894024/darmc-location-22420"
      }
    }
  ]
}