{
  "type": "FeatureCollection",
  "title": "Paikuli",
  "id": "894058",
  "description": "An ancient place, cited: BAtlas 91 G2 Paikuli",
  "bbox": [
    45.711981,
    35.118595,
    45.711981,
    35.118595
  ],
  "reprPoint": [
    45.711981,
    35.118595
  ],
  "features": [
    {
      "geometry": {
        "type": "Point",
        "coordinates": [
          45.711981,
          35.118595
        ]
      },
      "id": "darmc-location-22432",
      "type": "Feature",
      "properties": {
        "description": "Point location",
        "location_precision": "precise",
        "title": "DARMC location 22432",
        "link": "http://pleiades.stoa.org/places/894058/darmc-location-22432"
      }
    }
  ]
}