{
  "type": "FeatureCollection",
  "title": "Karastel/Artemita?",
  "id": "894020",
  "description": "An ancient place, cited: BAtlas 91 F4 Karastel/Artemita?",
  "bbox": [
    44.822085,
    33.88109,
    44.822085,
    33.88109
  ],
  "reprPoint": [
    44.822085,
    33.88109
  ],
  "names": [
    "Artemita",
    "Chalasar"
  ],
  "features": [
    {
      "geometry": {
        "type": "Point",
        "coordinates": [
          44.822085,
          33.88109
        ]
      },
      "id": "darmc-location-32447",
      "type": "Feature",
      "properties": {
        "description": "scale point location",
        "location_precision": "precise",
        "title": "DARMC location 32447",
        "link": "http://pleiades.stoa.org/places/894020/darmc-location-32447"
      }
    }
  ]
}