{
  "type": "FeatureCollection",
  "title": "Karastel/Artemita?",
  "id": "894020",
  "bbox": [
    44.822085,
    33.88109,
    44.822085,
    33.88109
  ],
  "description": "A city in Sittakene and/or Babylonia, located on the Silla River.",
  "connectsWith": [
    "893939",
    "894084",
    "912816"
  ],
  "names": [
    "Artemita",
    "Chalasar"
  ],
  "features": [
    {
      "type": "Feature",
      "geometry": {
        "type": "Point",
        "coordinates": [
          44.822085,
          33.88109
        ]
      },
      "properties": {
        "description": "representative point"
      }
    },
    {
      "geometry": {
        "type": "Point",
        "coordinates": [
          44.822085,
          33.88109
        ]
      },
      "id": "darmc-location-32447",
      "type": "Feature",
      "properties": {
        "description": "representative point location digitized from the Barrington Atlas of the Greek and Roman World by the Digital Atlas of Roman and Medieval Civilizations project at Harvard University.",
        "location_precision": "precise",
        "title": "DARMC location 32447",
        "link": "http://pleiades.stoa.org/places/894020/darmc-location-32447"
      }
    }
  ]
}