{
  "type": "FeatureCollection",
  "title": "Ishan Rishayd",
  "id": "894011",
  "bbox": [
    44.800243,
    32.758335,
    44.800243,
    32.758335
  ],
  "description": "An ancient place, cited: BAtlas 91 F5 Ishan Rishayd",
  "features": [
    {
      "type": "Feature",
      "geometry": {
        "type": "Point",
        "coordinates": [
          44.800243,
          32.758335
        ]
      },
      "properties": {
        "description": "representative point"
      }
    },
    {
      "geometry": {
        "type": "Point",
        "coordinates": [
          44.800243,
          32.758335
        ]
      },
      "id": "darmc-location-22492",
      "type": "Feature",
      "properties": {
        "description": "Point location",
        "location_precision": "precise",
        "title": "DARMC location 22492",
        "link": "http://pleiades.stoa.org/places/894011/darmc-location-22492"
      }
    }
  ]
}