{
  "type": "FeatureCollection",
  "title": "[Jalula]",
  "id": "894013",
  "description": "An ancient place, cited: BAtlas 91 G3 [Jalula]",
  "bbox": [
    45.118333,
    34.186388,
    45.118333,
    34.186388
  ],
  "reprPoint": [
    45.118333,
    34.186388
  ],
  "names": [
    "Jalula"
  ],
  "features": [
    {
      "geometry": {
        "type": "Point",
        "coordinates": [
          45.118333,
          34.186388
        ]
      },
      "id": "darmc-location-22435",
      "type": "Feature",
      "properties": {
        "description": "Point location",
        "location_precision": "precise",
        "title": "DARMC location 22435",
        "link": "http://pleiades.stoa.org/places/894013/darmc-location-22435"
      }
    }
  ]
}