{
  "type": "FeatureCollection",
  "title": "[Nuzi]",
  "id": "894054",
  "description": "Nuzi was an ancient city of Mesopotamia located southwest of Arrapha.",
  "bbox": [
    44.208201,
    35.381241,
    44.208201,
    35.381241
  ],
  "reprPoint": [
    44.208201,
    35.381241
  ],
  "names": [
    "Nuzi"
  ],
  "features": [
    {
      "geometry": {
        "type": "Point",
        "coordinates": [
          44.208201,
          35.381241
        ]
      },
      "id": "darmc-location-22428",
      "type": "Feature",
      "properties": {
        "description": "Point location",
        "location_precision": "precise",
        "title": "DARMC location 22428",
        "link": "http://pleiades.stoa.org/places/894054/darmc-location-22428"
      }
    }
  ]
}