{
  "type": "FeatureCollection",
  "title": "Tulul Abu Jawan",
  "id": "894161",
  "bbox": [
    44.80519,
    33.130959,
    44.80519,
    33.130959
  ],
  "description": "An ancient place, cited: BAtlas 91 F4 Tulul Abu Jawan",
  "features": [
    {
      "type": "Feature",
      "geometry": {
        "type": "Point",
        "coordinates": [
          44.80519,
          33.130959
        ]
      },
      "properties": {
        "description": "representative point"
      }
    },
    {
      "geometry": {
        "type": "Point",
        "coordinates": [
          44.80519,
          33.130959
        ]
      },
      "id": "darmc-location-22478",
      "type": "Feature",
      "properties": {
        "description": "Point location",
        "location_precision": "precise",
        "title": "DARMC location 22478",
        "link": "http://pleiades.stoa.org/places/894161/darmc-location-22478"
      }
    }
  ]
}