{
  "type": "FeatureCollection",
  "title": "Tell Bismaya",
  "id": "894129",
  "description": "An ancient place, cited: BAtlas 91 G5 Tell Bismaya",
  "bbox": [
    45.650976,
    32.4093,
    45.650976,
    32.4093
  ],
  "reprPoint": [
    45.650976,
    32.4093
  ],
  "features": [
    {
      "geometry": {
        "type": "Point",
        "coordinates": [
          45.650976,
          32.4093
        ]
      },
      "id": "darmc-location-22515",
      "type": "Feature",
      "properties": {
        "description": "Point location",
        "location_precision": "precise",
        "title": "DARMC location 22515",
        "link": "http://pleiades.stoa.org/places/894129/darmc-location-22515"
      }
    }
  ]
}