{
  "type": "FeatureCollection",
  "title": "Tell Katluma",
  "id": "894143",
  "description": "An ancient place, cited: BAtlas 91 B2 Tell Katluma",
  "bbox": [
    40.529301,
    35.253855,
    40.529301,
    35.253855
  ],
  "reprPoint": [
    40.529301,
    35.253855
  ],
  "features": [
    {
      "geometry": {
        "type": "Point",
        "coordinates": [
          40.529301,
          35.253855
        ]
      },
      "id": "darmc-location-22384",
      "type": "Feature",
      "properties": {
        "description": "Point location",
        "location_precision": "precise",
        "title": "DARMC location 22384",
        "link": "http://pleiades.stoa.org/places/894143/darmc-location-22384"
      }
    }
  ]
}