{
  "type": "FeatureCollection",
  "title": "Tell Mahuz",
  "id": "894148",
  "bbox": [
    43.8365989,
    35.4923435,
    43.8365989,
    35.4923435
  ],
  "description": "The site of Tell Mahuz site in northern Iraq was occupied from the fourth millennium B.C. to the Early Islamic Period.",
  "connectsWith": [
    "894184"
  ],
  "names": [
    "Tursana"
  ],
  "features": [
    {
      "type": "Feature",
      "geometry": {
        "type": "Point",
        "coordinates": [
          43.8365989,
          35.4923435
        ]
      },
      "properties": {
        "description": "representative point"
      }
    },
    {
      "geometry": {
        "type": "Point",
        "coordinates": [
          43.8365989,
          35.4923435
        ]
      },
      "id": "osm-location-of-tall-mahuz",
      "type": "Feature",
      "properties": {
        "description": "Location based on OpenStreetMap",
        "location_precision": "precise",
        "title": "OSM location of  Tall Mahuz",
        "link": "http://pleiades.stoa.org/places/894148/osm-location-of-tall-mahuz"
      }
    }
  ]
}