{
  "type": "FeatureCollection",
  "title": "Tell Hussain",
  "id": "894137",
  "description": "An ancient place, cited: BAtlas 91 B2 Tell Hussain",
  "bbox": [
    40.71494,
    35.643074,
    40.71494,
    35.643074
  ],
  "reprPoint": [
    40.71494,
    35.643074
  ],
  "features": [
    {
      "geometry": {
        "type": "Point",
        "coordinates": [
          40.71494,
          35.643074
        ]
      },
      "id": "darmc-location-22379",
      "type": "Feature",
      "properties": {
        "description": "Point location",
        "location_precision": "precise",
        "title": "DARMC location 22379",
        "link": "http://pleiades.stoa.org/places/894137/darmc-location-22379"
      }
    }
  ]
}