{
  "type": "FeatureCollection",
  "title": "Tell Itwayba",
  "id": "894140",
  "description": "An ancient place, cited: BAtlas 91 F5 Tell Itwayba",
  "bbox": [
    44.475273,
    32.801115,
    44.475273,
    32.801115
  ],
  "reprPoint": [
    44.475273,
    32.801115
  ],
  "features": [
    {
      "geometry": {
        "type": "Point",
        "coordinates": [
          44.475273,
          32.801115
        ]
      },
      "id": "darmc-location-22487",
      "type": "Feature",
      "properties": {
        "description": "Point location",
        "location_precision": "precise",
        "title": "DARMC location 22487",
        "link": "http://pleiades.stoa.org/places/894140/darmc-location-22487"
      }
    }
  ]
}