{
  "type": "FeatureCollection",
  "title": "Wiranshehir",
  "id": "894181",
  "description": "An ancient place, cited: BAtlas 91 F2 Wiranshehir",
  "bbox": [
    44.156541,
    35.415621,
    44.156541,
    35.415621
  ],
  "reprPoint": [
    44.156541,
    35.415621
  ],
  "features": [
    {
      "geometry": {
        "type": "Point",
        "coordinates": [
          44.156541,
          35.415621
        ]
      },
      "id": "darmc-location-22427",
      "type": "Feature",
      "properties": {
        "description": "Point location",
        "location_precision": "precise",
        "title": "DARMC location 22427",
        "link": "http://pleiades.stoa.org/places/894181/darmc-location-22427"
      }
    }
  ]
}