{
  "type": "FeatureCollection",
  "title": "Vologesias?",
  "id": "894179",
  "description": "An ancient place, cited: BAtlas 91 F4 Vologesias?",
  "bbox": [
    44.118536,
    33.045979,
    44.580481,
    33.125398
  ],
  "reprPoint": [
    44.3495085,
    33.0856885
  ],
  "names": [
    "Vologesias"
  ],
  "features": [
    {
      "geometry": {
        "type": "Point",
        "coordinates": [
          44.118536,
          33.125398
        ]
      },
      "id": "darmc-location-15434",
      "type": "Feature",
      "properties": {
        "description": "5M scale point location",
        "location_precision": "precise",
        "title": "DARMC location 15434",
        "link": "http://pleiades.stoa.org/places/894179/darmc-location-15434"
      }
    },
    {
      "geometry": {
        "type": "Point",
        "coordinates": [
          44.580481,
          33.045979
        ]
      },
      "id": "darmc-location-22503",
      "type": "Feature",
      "properties": {
        "description": "Point location",
        "location_precision": "precise",
        "title": "DARMC location 22503",
        "link": "http://pleiades.stoa.org/places/894179/darmc-location-22503"
      }
    }
  ]
}