{
  "type": "FeatureCollection",
  "title": "Tell al-Mas'ud",
  "id": "894121",
  "description": "An ancient place, cited: BAtlas 91 F4 Tell al-Mas'ud",
  "bbox": [
    44.332001,
    33.717241,
    44.332001,
    33.717241
  ],
  "reprPoint": [
    44.332001,
    33.717241
  ],
  "features": [
    {
      "geometry": {
        "type": "Point",
        "coordinates": [
          44.332001,
          33.717241
        ]
      },
      "id": "darmc-location-32451",
      "type": "Feature",
      "properties": {
        "description": "scale point location",
        "location_precision": "precise",
        "title": "DARMC location 32451",
        "link": "http://pleiades.stoa.org/places/894121/darmc-location-32451"
      }
    }
  ]
}