{
  "type": "FeatureCollection",
  "title": "Tell Mahuz",
  "id": "894148",
  "description": "An ancient place, cited: BAtlas 91 F2 Tell Mahuz",
  "bbox": [
    43.830277,
    35.498888,
    43.830277,
    35.498888
  ],
  "reprPoint": [
    43.830277,
    35.498888
  ],
  "features": [
    {
      "geometry": {
        "type": "Point",
        "coordinates": [
          43.830277,
          35.498888
        ]
      },
      "id": "darmc-location-22403",
      "type": "Feature",
      "properties": {
        "description": "Point location",
        "location_precision": "precise",
        "title": "DARMC location 22403",
        "link": "http://pleiades.stoa.org/places/894148/darmc-location-22403"
      }
    }
  ]
}