{
  "type": "FeatureCollection",
  "title": "Tell al-Mas'ud",
  "id": "894121",
  "bbox": [
    44.332001,
    33.717241,
    44.332001,
    33.717241
  ],
  "description": "An ancient place, cited: BAtlas 91 F4 Tell al-Mas'ud",
  "features": [
    {
      "type": "Feature",
      "geometry": {
        "type": "Point",
        "coordinates": [
          44.332001,
          33.717241
        ]
      },
      "properties": {
        "description": "representative point"
      }
    },
    {
      "geometry": {
        "type": "Point",
        "coordinates": [
          44.332001,
          33.717241
        ]
      },
      "id": "darmc-location-32451",
      "type": "Feature",
      "properties": {
        "description": "representative point location digitized from the Barrington Atlas of the Greek and Roman World by the Digital Atlas of Roman and Medieval Civilizations project at Harvard University.",
        "location_precision": "precise",
        "title": "DARMC location 32451",
        "link": "http://pleiades.stoa.org/places/894121/darmc-location-32451"
      }
    }
  ]
}