{
  "type": "FeatureCollection",
  "title": "Tell al-Hafa'ir",
  "id": "894117",
  "description": "An ancient place, cited: BAtlas 91 G3 Tell al-Hafa'ir",
  "bbox": [
    45.205254,
    34.00767,
    45.205254,
    34.00767
  ],
  "reprPoint": [
    45.205254,
    34.00767
  ],
  "features": [
    {
      "geometry": {
        "type": "Point",
        "coordinates": [
          45.205254,
          34.00767
        ]
      },
      "id": "darmc-location-32442",
      "type": "Feature",
      "properties": {
        "description": "scale point location",
        "location_precision": "precise",
        "title": "DARMC location 32442",
        "link": "http://pleiades.stoa.org/places/894117/darmc-location-32442"
      }
    }
  ]
}