{
  "type": "FeatureCollection",
  "title": "Zabas Mikros/Kapros?/Zerbis? (river)",
  "id": "894184",
  "description": "Zabas Mikros/Kapros?/Zerbis? fl. (Little Zab River) flows from the Zagros Mountains to the Tigris river.",
  "bbox": [
    44.7915335,
    35.8572581,
    44.7915335,
    35.8572581
  ],
  "connectsWith": [
    "29816",
    "912964"
  ],
  "reprPoint": [
    44.7915335,
    35.8572581
  ],
  "names": [
    "Zāb-e Aṣġar",
    "Zāb-e Kūček",
    "Rūd-e Zāb-e Kūček",
    "Kapros",
    "Zabu-šupalû",
    "Zāb al-Asfal",
    "az-Zāb aṣ-Saġīr",
    "Kleiner Zaw",
    "Kleiner Zāb",
    "az-Zab aṣ-Saġīr",
    "Kleiner Zab",
    "az-Zāb aṣ-Ṣaġīr",
    "az-Zāb al-Asfal",
    "Zaba Šaplû",
    "Unterer Zab",
    "Zabas Mikros",
    "Kapros",
    "Zerbis"
  ],
  "features": [
    {
      "geometry": {
        "type": "Point",
        "coordinates": [
          44.7915335,
          35.8572581
        ]
      },
      "id": "location-of-Zabas-Mikros-Kapros-Zerbis-fl",
      "type": "Feature",
      "properties": {
        "description": "Location based on OpenStreetMap",
        "location_precision": "precise",
        "title": "location of Zabas Mikros/Kapros?/Zerbis? fl.",
        "link": "http://pleiades.stoa.org/places/894184/location-of-Zabas-Mikros-Kapros-Zerbis-fl"
      }
    }
  ]
}