{
  "type": "FeatureCollection",
  "title": "Necropoli del Fusco",
  "id": "895916364",
  "bbox": [
    15.2590759,
    37.0750458,
    15.2590759,
    37.0750458
  ],
  "description": "The Fusco necropolis is the largest and oldest burial area in Greek Syracuse. Located within contrada Canalicchio, the site was excavated by Paolo Orsi in 1893.",
  "connectsWith": [
    "462503"
  ],
  "names": [
    "Necropoli del Fusco"
  ],
  "features": [
    {
      "type": "Feature",
      "geometry": {
        "type": "Point",
        "coordinates": [
          15.2590759,
          37.0750458
        ]
      },
      "properties": {
        "description": "representative point"
      }
    },
    {
      "geometry": {
        "type": "Point",
        "coordinates": [
          15.2590759,
          37.0750458
        ]
      },
      "id": "osm-location-of-the-necropoli-del-fusco",
      "type": "Feature",
      "properties": {
        "description": "Representative location of the ancient burial area called Necropoli del Fusco in Syracuse, near the modern War Cemetery, based on a representative point derived from an OpenStreetMap node.",
        "location_precision": "precise",
        "title": "OSM location of the Necropoli del Fusco",
        "link": "http://pleiades.stoa.org/places/895916364/osm-location-of-the-necropoli-del-fusco"
      }
    }
  ]
}