{
  "type": "FeatureCollection",
  "title": "Wall of Media",
  "id": "896945",
  "bbox": [
    44.2698,
    33.1216,
    44.2698,
    33.1216
  ],
  "description": "The Wall of Media, also known as Mēdías teîchos or the Wall of Semiramis, at Habl as-Sahr is mentioned by Xenophon in the Anabasis as a defensive ditch at the Euphrates built on the orders of Artaxerxes in the fifth century BC.",
  "names": [
    "Semirámidos diateíchisma",
    "Medias kaloumenon teichos (to)",
    "Ḥabl al-Ṣakhar"
  ],
  "features": [
    {
      "type": "Feature",
      "geometry": {
        "type": "Point",
        "coordinates": [
          44.2698,
          33.1216
        ]
      },
      "properties": {
        "description": "representative point"
      }
    },
    {
      "geometry": {
        "type": "Point",
        "coordinates": [
          44.2698,
          33.1216
        ]
      },
      "id": "cigs-location-of-habl-al-sakhar",
      "type": "Feature",
      "properties": {
        "description": null,
        "location_precision": "precise",
        "title": "CIGS location of Ḥabl al-Ṣakhar",
        "link": "http://pleiades.stoa.org/places/896945/cigs-location-of-habl-al-sakhar"
      }
    }
  ]
}