{
  "type": "FeatureCollection",
  "title": "Khosr River",
  "id": "897975989",
  "bbox": [
    43.1592036,
    36.3586329,
    43.1592036,
    36.3586329
  ],
  "description": "The Khosr River was a tributary of the Tigris River that ran directly through the center of the Assyrian city Nineveh. The Neo-Assyrian king Sennacherib reinforced its banks with large stone blocks to prevent it from flooding or damaging the citadel wall.",
  "connectsWith": [
    "874621",
    "882947620",
    "945930916",
    "897975988"
  ],
  "names": [
    "Khosr River",
    "Nahr al-Khosr",
    "Husur"
  ],
  "features": [
    {
      "type": "Feature",
      "geometry": {
        "type": "Point",
        "coordinates": [
          43.1592036,
          36.3586329
        ]
      },
      "properties": {
        "description": "representative point"
      }
    },
    {
      "geometry": {
        "type": "Point",
        "coordinates": [
          43.1592036,
          36.3586329
        ]
      },
      "id": "osm-representative-point-for-alkhosr",
      "type": "Feature",
      "properties": {
        "description": "Location based on OpenStreetMap node is a representative point for the river",
        "location_precision": "precise",
        "title": "OSM representative point for Alkhosr ",
        "link": "http://pleiades.stoa.org/places/897975989/osm-representative-point-for-alkhosr"
      }
    }
  ]
}