{
  "type": "FeatureCollection",
  "title": "Ojasar-Ilandağ",
  "id": "901571869",
  "bbox": [
    45.6251,
    39.137,
    45.6251,
    39.137
  ],
  "description": "Place for Urartian rock inscription.",
  "features": [
    {
      "type": "Feature",
      "geometry": {
        "type": "Point",
        "coordinates": [
          45.6251,
          39.137
        ]
      },
      "properties": {
        "description": "representative point"
      }
    },
    {
      "geometry": {
        "type": "Point",
        "coordinates": [
          45.6251,
          39.137
        ]
      },
      "id": "cigs-location-of-ojasar-ilandag",
      "type": "Feature",
      "properties": {
        "description": null,
        "location_precision": "precise",
        "title": "CIGS location of Ojasar-Ilandağ",
        "link": "http://pleiades.stoa.org/places/901571869/cigs-location-of-ojasar-ilandag"
      }
    }
  ]
}