{
  "type": "FeatureCollection",
  "title": "Ain Diwar",
  "id": "90199885",
  "bbox": [
    42.2158069,
    37.314535,
    42.2158069,
    37.314535
  ],
  "description": "A ruined Roman bridge near Ain Diwar, Syria, that once crossed the Tigris river.",
  "features": [
    {
      "type": "Feature",
      "geometry": {
        "type": "Point",
        "coordinates": [
          42.2158069,
          37.314535
        ]
      },
      "properties": {
        "description": "representative point"
      }
    },
    {
      "geometry": {
        "type": "Point",
        "coordinates": [
          42.2158069,
          37.314535
        ]
      },
      "id": "osm-location",
      "type": "Feature",
      "properties": {
        "description": "Representative location based on OpenStreetMap.",
        "location_precision": "precise",
        "title": "OSM location of Ain Diwar Bridge",
        "link": "http://pleiades.stoa.org/places/90199885/osm-location"
      }
    }
  ]
}