{
  "type": "FeatureCollection",
  "title": "Tanella Angori",
  "id": "902458924",
  "bbox": [
    11.9793152,
    43.2731321,
    11.9793152,
    43.2731321
  ],
  "description": "A circular Hellenistic tomb of the second century BC.",
  "connectsWith": [
    "413106"
  ],
  "features": [
    {
      "type": "Feature",
      "geometry": {
        "type": "Point",
        "coordinates": [
          11.9793152,
          43.2731321
        ]
      },
      "properties": {
        "description": "representative point"
      }
    },
    {
      "geometry": {
        "type": "Point",
        "coordinates": [
          11.9793152,
          43.2731321
        ]
      },
      "id": "osm-location-of-tanella-angori",
      "type": "Feature",
      "properties": {
        "description": "Representative location based on OpenStreetMap.",
        "location_precision": "precise",
        "title": "OSM location of Tanella Angori",
        "link": "http://pleiades.stoa.org/places/902458924/osm-location-of-tanella-angori"
      }
    }
  ]
}