{
  "type": "FeatureCollection",
  "title": "Lang-i Rud",
  "id": "903072",
  "bbox": [
    51.000769,
    34.52229,
    51.000769,
    34.52229
  ],
  "description": "An ancient place, cited: BAtlas 92 G2 Lang-i Rud",
  "features": [
    {
      "type": "Feature",
      "geometry": {
        "type": "Point",
        "coordinates": [
          51.000769,
          34.52229
        ]
      },
      "properties": {
        "description": "representative point"
      }
    },
    {
      "geometry": {
        "type": "Point",
        "coordinates": [
          51.000769,
          34.52229
        ]
      },
      "id": "darmc-location-31930",
      "type": "Feature",
      "properties": {
        "description": "  scale point location",
        "location_precision": "precise",
        "title": "DARMC location 31930",
        "link": "http://pleiades.stoa.org/places/903072/darmc-location-31930"
      }
    }
  ]
}