{
  "type": "FeatureCollection",
  "title": "Ivan-i Karkheh/Eran-Khurra-(kard-) Shapur?/Karkha de Ladan",
  "id": "903047",
  "bbox": [
    48.149253,
    32.314998,
    48.149253,
    32.314998
  ],
  "description": "An ancient place, cited: BAtlas 92 D4 Ivan-i Karkheh/Eran-Khurra-(kard-) Shapur?/Karkha de Ladan",
  "names": [
    "Eran-khurra-kard- Shapur",
    "Eran-khurra- Shapur",
    "Karkha de Ladan"
  ],
  "features": [
    {
      "type": "Feature",
      "geometry": {
        "type": "Point",
        "coordinates": [
          48.149253,
          32.314998
        ]
      },
      "properties": {
        "description": "representative point"
      }
    },
    {
      "geometry": {
        "type": "Point",
        "coordinates": [
          48.149253,
          32.314998
        ]
      },
      "id": "darmc-location-30351",
      "type": "Feature",
      "properties": {
        "description": "5M scale point location",
        "location_precision": "precise",
        "title": "DARMC location 30351",
        "link": "http://pleiades.stoa.org/places/903047/darmc-location-30351"
      }
    }
  ]
}