{
  "type": "FeatureCollection",
  "title": "Khurmal/Syarazur?/Siasouron?",
  "id": "903063",
  "description": "An ancient place, cited: BAtlas 92 B1 Khurmal/Syarazur?/Siasouron?",
  "bbox": [
    46.03589,
    35.299481,
    46.03589,
    35.299481
  ],
  "reprPoint": [
    46.03589,
    35.299481
  ],
  "names": [
    "Syarazur",
    "Siasouron"
  ],
  "features": [
    {
      "geometry": {
        "type": "Point",
        "coordinates": [
          46.03589,
          35.299481
        ]
      },
      "id": "darmc-location-21540",
      "type": "Feature",
      "properties": {
        "description": "Point location",
        "location_precision": "precise",
        "title": "DARMC location 21540",
        "link": "http://pleiades.stoa.org/places/903063/darmc-location-21540"
      }
    }
  ]
}