{
  "type": "FeatureCollection",
  "title": "Taq-i Girra",
  "id": "903127",
  "bbox": [
    46.07918,
    34.433054,
    46.07918,
    34.433054
  ],
  "description": "An ancient place, cited: BAtlas 92 B2 Taq-i Girra",
  "features": [
    {
      "type": "Feature",
      "geometry": {
        "type": "Point",
        "coordinates": [
          46.07918,
          34.433054
        ]
      },
      "properties": {
        "description": "representative point"
      }
    },
    {
      "geometry": {
        "type": "Point",
        "coordinates": [
          46.07918,
          34.433054
        ]
      },
      "id": "darmc-location-31935",
      "type": "Feature",
      "properties": {
        "description": "  scale point location",
        "location_precision": "precise",
        "title": "DARMC location 31935",
        "link": "http://pleiades.stoa.org/places/903127/darmc-location-31935"
      }
    }
  ]
}