{
  "type": "FeatureCollection",
  "title": "Untitled",
  "id": "903737",
  "bbox": [
    45.946555,
    35.134714,
    45.946555,
    35.134714
  ],
  "description": "An ancient place, cited: BAtlas 92 A1 no. 1 (Pird-i Kinachan, near Halabja)",
  "features": [
    {
      "type": "Feature",
      "geometry": {
        "type": "Point",
        "coordinates": [
          45.946555,
          35.134714
        ]
      },
      "properties": {
        "description": "representative point"
      }
    },
    {
      "geometry": {
        "type": "Point",
        "coordinates": [
          45.946555,
          35.134714
        ]
      },
      "id": "darmc-location-31936",
      "type": "Feature",
      "properties": {
        "description": "representative point location digitized from the Barrington Atlas of the Greek and Roman World by the Digital Atlas of Roman and Medieval Civilizations project at Harvard University.",
        "location_precision": "precise",
        "title": "DARMC location 31936",
        "link": "http://pleiades.stoa.org/places/903737/darmc-location-31936"
      }
    }
  ]
}