{
  "type": "FeatureCollection",
  "title": "Baths of Antoninus at Carthage",
  "id": "907258688",
  "bbox": [
    10.3313849,
    36.8546945,
    10.3313849,
    36.8546945
  ],
  "description": "The Baths of Antoninus at Carthage date to the middle of the second century and are the largest of the Roman public bath complexes in North Africa.",
  "connectsWith": [
    "314921"
  ],
  "names": [
    "Thermes d'Antonin"
  ],
  "features": [
    {
      "type": "Feature",
      "geometry": {
        "type": "Point",
        "coordinates": [
          10.3313849,
          36.8546945
        ]
      },
      "properties": {
        "description": "representative point"
      }
    },
    {
      "geometry": {
        "type": "Point",
        "coordinates": [
          10.3313849,
          36.8546945
        ]
      },
      "id": "thermes-dantonin",
      "type": "Feature",
      "properties": {
        "description": "French: Thermes d'Antonin. Representative location based on OpenStreetMap.",
        "location_precision": "precise",
        "title": "OSM location of Baths of Antoninus",
        "link": "http://pleiades.stoa.org/places/907258688/thermes-dantonin"
      }
    }
  ]
}