{
  "type": "FeatureCollection",
  "title": "[Girsu]/Tello(h)",
  "id": "912855",
  "description": "A Sumerian city-state.",
  "bbox": [
    46.175712,
    31.576909,
    46.205633,
    31.592135
  ],
  "reprPoint": [
    46.1906725,
    31.584522
  ],
  "names": [
    "Girsu"
  ],
  "features": [
    {
      "geometry": {
        "type": "Point",
        "coordinates": [
          46.205633,
          31.592135
        ]
      },
      "id": "darmc-location-31508",
      "type": "Feature",
      "properties": {
        "description": "scale point location",
        "location_precision": "precise",
        "title": "DARMC location 31508",
        "link": "http://pleiades.stoa.org/places/912855/darmc-location-31508"
      }
    }
  ]
}