{
  "type": "FeatureCollection",
  "title": "Hung-i Yar-i 'Alivand",
  "id": "912864",
  "description": "An ancient place, cited: BAtlas 93 F2 Hung-i Yar-i 'Alivand",
  "bbox": [
    49.81782,
    31.932829,
    49.81782,
    31.932829
  ],
  "reprPoint": [
    49.81782,
    31.932829
  ],
  "features": [
    {
      "geometry": {
        "type": "Point",
        "coordinates": [
          49.81782,
          31.932829
        ]
      },
      "id": "darmc-location-31872",
      "type": "Feature",
      "properties": {
        "description": "scale point location",
        "location_precision": "precise",
        "title": "DARMC location 31872",
        "link": "http://pleiades.stoa.org/places/912864/darmc-location-31872"
      }
    }
  ]
}