{
  "type": "FeatureCollection",
  "title": "Arakia? Ins.",
  "id": "912810",
  "description": "An ancient place, cited: BAtlas 93 G4 Arakia? Ins.",
  "bbox": [
    50.3080741,
    29.2126438,
    50.3080741,
    29.2126438
  ],
  "connectsWith": [
    "29713"
  ],
  "reprPoint": [
    50.3080741,
    29.2126438
  ],
  "names": [
    "Arakia",
    "Alexandrou"
  ],
  "features": [
    {
      "geometry": {
        "type": "Point",
        "coordinates": [
          50.3080741,
          29.2126438
        ]
      },
      "id": "location-of-Arakia-Ins",
      "type": "Feature",
      "properties": {
        "description": "Location based on OpenStreetMap",
        "location_precision": "precise",
        "title": "location of Arakia? Ins.",
        "link": "http://pleiades.stoa.org/places/912810/location-of-Arakia-Ins"
      }
    }
  ]
}