{
  "type": "FeatureCollection",
  "title": "[Girsu]/Tello(h)",
  "id": "912855",
  "bbox": [
    46.175712,
    31.576909,
    46.175712,
    31.576909
  ],
  "description": "A Sumerian city-state.",
  "names": [
    "Girsu"
  ],
  "features": [
    {
      "type": "Feature",
      "geometry": {
        "type": "Point",
        "coordinates": [
          46.175712,
          31.576909
        ]
      },
      "properties": {
        "description": "representative point"
      }
    },
    {
      "geometry": {
        "type": "Point",
        "coordinates": [
          46.175712,
          31.576909
        ]
      },
      "id": "osm-location",
      "type": "Feature",
      "properties": {
        "description": "Representative location based on OpenStreetMap.",
        "location_precision": "precise",
        "title": "OSM location of Girsu (Tell Telloh)",
        "link": "http://pleiades.stoa.org/places/912855/osm-location"
      }
    }
  ]
}