{
  "type": "FeatureCollection",
  "title": "Hurmizd Ardashir/[Suq al-Ahwaz]",
  "id": "912865",
  "bbox": [
    48.68438,
    31.316712,
    48.68438,
    31.316712
  ],
  "description": "An ancient place, cited: BAtlas 93 E2 Hurmizd Ardashir/[Suq al-Ahwaz]",
  "names": [
    "Hurmizd Ardashir",
    "Suq al-Ahwaz",
    "Tareiana",
    "Sūq al-Ahwāz",
    "Ahvāz",
    "Ahwāz",
    "al-Ahwāz",
    "Hormizd Ardašīr",
    "Ohurmazd-Artaḫšēr",
    "Ohurmazd-Artaḫšēr",
    "Ohurmazd-Artaḫšēr"
  ],
  "features": [
    {
      "type": "Feature",
      "geometry": {
        "type": "Point",
        "coordinates": [
          48.68438,
          31.316712
        ]
      },
      "properties": {
        "description": "representative point"
      }
    },
    {
      "geometry": {
        "type": "Point",
        "coordinates": [
          48.68438,
          31.316712
        ]
      },
      "id": "darmc-location-21501",
      "type": "Feature",
      "properties": {
        "description": "Point location",
        "location_precision": "precise",
        "title": "DARMC location 21501",
        "link": "http://pleiades.stoa.org/places/912865/darmc-location-21501"
      }
    }
  ]
}