{
  "type": "FeatureCollection",
  "title": "[Jundishapur]/Veh-Andiyok-Shapur/Beth Lapat/Bendosaboron",
  "id": "912873",
  "description": "An ancient place, cited: BAtlas 93 E1 [Jundishapur]/Veh-Andiyok-Shapur/Beth Lapat/Bendosaboron",
  "bbox": [
    48.516471,
    32.277313,
    48.518906,
    32.283618
  ],
  "reprPoint": [
    48.5176885,
    32.2804655
  ],
  "names": [
    "Jundishapur",
    "Veh-Andiyok-Shapur",
    "Beth Lapat",
    "Bendosaboron"
  ],
  "features": [
    {
      "geometry": {
        "type": "Point",
        "coordinates": [
          48.516471,
          32.283618
        ]
      },
      "id": "darmc-location-20356",
      "type": "Feature",
      "properties": {
        "description": "5M scale point location",
        "location_precision": "precise",
        "title": "DARMC location 20356",
        "link": "http://pleiades.stoa.org/places/912873/darmc-location-20356"
      }
    },
    {
      "geometry": {
        "type": "Point",
        "coordinates": [
          48.518906,
          32.277313
        ]
      },
      "id": "darmc-location-31889",
      "type": "Feature",
      "properties": {
        "description": "scale point location",
        "location_precision": "precise",
        "title": "DARMC location 31889",
        "link": "http://pleiades.stoa.org/places/912873/darmc-location-31889"
      }
    }
  ]
}