{
  "type": "FeatureCollection",
  "title": "[Girsu]/Tello(h)",
  "id": "912855",
  "bbox": [
    46.175712,
    31.5591,
    46.1776,
    31.576909
  ],
  "description": "A Sumerian city-state.",
  "connectsWith": [
    "202833934"
  ],
  "names": [
    "Girsu",
    "Tell Telloh",
    "Tall Tīlūh",
    "Jīrsū"
  ],
  "features": [
    {
      "type": "Feature",
      "geometry": {
        "type": "Point",
        "coordinates": [
          46.176656,
          31.5680045
        ]
      },
      "properties": {
        "description": "representative point"
      }
    },
    {
      "geometry": {
        "type": "Point",
        "coordinates": [
          46.175712,
          31.576909
        ]
      },
      "id": "osm-location",
      "type": "Feature",
      "properties": {
        "description": "Representative location based on OpenStreetMap.",
        "location_precision": "precise",
        "title": "OSM location of Girsu (Tell Telloh)",
        "link": "http://pleiades.stoa.org/places/912855/osm-location"
      }
    },
    {
      "geometry": {
        "type": "Point",
        "coordinates": [
          46.1776,
          31.5591
        ]
      },
      "id": "imagery-location-of-tall-tiluh",
      "type": "Feature",
      "properties": {
        "description": null,
        "location_precision": "precise",
        "title": "CIGS location of Tall Tīlūh",
        "link": "http://pleiades.stoa.org/places/912855/imagery-location-of-tall-tiluh"
      }
    }
  ]
}