{
  "type": "FeatureCollection",
  "title": "Tell Laham",
  "id": "912959",
  "description": "An ancient place, cited: BAtlas 93 B1 Tell Laham",
  "bbox": [
    45.406123,
    32.04884,
    45.406123,
    32.04884
  ],
  "reprPoint": [
    45.406123,
    32.04884
  ],
  "features": [
    {
      "geometry": {
        "type": "Point",
        "coordinates": [
          45.406123,
          32.04884
        ]
      },
      "id": "darmc-location-21901",
      "type": "Feature",
      "properties": {
        "description": "Point location",
        "location_precision": "precise",
        "title": "DARMC location 21901",
        "link": "http://pleiades.stoa.org/places/912959/darmc-location-21901"
      }
    }
  ]
}