{
  "type": "FeatureCollection",
  "title": "Qal'a Huwaysh al-Pasha",
  "id": "912924",
  "bbox": [
    45.640387,
    31.760594,
    45.640387,
    31.760594
  ],
  "description": "An ancient place, cited: BAtlas 93 B2 Qal'a Huwaysh al-Pasha",
  "features": [
    {
      "type": "Feature",
      "geometry": {
        "type": "Point",
        "coordinates": [
          45.640387,
          31.760594
        ]
      },
      "properties": {
        "description": "representative point"
      }
    },
    {
      "geometry": {
        "type": "Point",
        "coordinates": [
          45.640387,
          31.760594
        ]
      },
      "id": "darmc-location-31919",
      "type": "Feature",
      "properties": {
        "description": "representative point location digitized from the Barrington Atlas of the Greek and Roman World by the Digital Atlas of Roman and Medieval Civilizations project at Harvard University.",
        "location_precision": "precise",
        "title": "DARMC location 31919",
        "link": "http://pleiades.stoa.org/places/912924/darmc-location-31919"
      }
    }
  ]
}