{
  "type": "FeatureCollection",
  "title": "Tell Nahr 'Umar",
  "id": "912961",
  "bbox": [
    47.62361,
    30.772672,
    47.62361,
    30.772672
  ],
  "description": "An ancient place, cited: BAtlas 93 D3 Tell Nahr 'Umar",
  "features": [
    {
      "type": "Feature",
      "geometry": {
        "type": "Point",
        "coordinates": [
          47.62361,
          30.772672
        ]
      },
      "properties": {
        "description": "representative point"
      }
    },
    {
      "geometry": {
        "type": "Point",
        "coordinates": [
          47.62361,
          30.772672
        ]
      },
      "id": "darmc-location-31862",
      "type": "Feature",
      "properties": {
        "description": "  scale point location",
        "location_precision": "precise",
        "title": "DARMC location 31862",
        "link": "http://pleiades.stoa.org/places/912961/darmc-location-31862"
      }
    }
  ]
}