{
  "type": "FeatureCollection",
  "title": "Tell Laham",
  "id": "912959",
  "bbox": [
    45.4062,
    32.051,
    45.4062,
    32.051
  ],
  "description": "An ancient place, cited: BAtlas 93 B1 Tell Laham",
  "names": [
    "Tall al-Laḥam"
  ],
  "features": [
    {
      "type": "Feature",
      "geometry": {
        "type": "Point",
        "coordinates": [
          45.4062,
          32.051
        ]
      },
      "properties": {
        "description": "representative point"
      }
    },
    {
      "geometry": {
        "type": "Point",
        "coordinates": [
          45.4062,
          32.051
        ]
      },
      "id": "tall-al-laham",
      "type": "Feature",
      "properties": {
        "description": null,
        "location_precision": "precise",
        "title": "CIGS location of Tall al-Laḥam",
        "link": "http://pleiades.stoa.org/places/912959/tall-al-laham"
      }
    }
  ]
}