{
  "type": "FeatureCollection",
  "title": "Tulul Abu Fatas",
  "id": "912966",
  "description": "An ancient place, cited: BAtlas 93 B2 Tulul Abu Fatas",
  "bbox": [
    45.694613,
    31.973662,
    45.694613,
    31.973662
  ],
  "reprPoint": [
    45.694613,
    31.973662
  ],
  "features": [
    {
      "geometry": {
        "type": "Point",
        "coordinates": [
          45.694613,
          31.973662
        ]
      },
      "id": "darmc-location-21910",
      "type": "Feature",
      "properties": {
        "description": "Point location",
        "location_precision": "precise",
        "title": "DARMC location 21910",
        "link": "http://pleiades.stoa.org/places/912966/darmc-location-21910"
      }
    }
  ]
}