{
  "type": "FeatureCollection",
  "title": "U045",
  "id": "912970",
  "bbox": [
    45.553629,
    31.723911,
    45.553629,
    31.723911
  ],
  "description": "An ancient place, cited: BAtlas 93 B2 U045",
  "features": [
    {
      "type": "Feature",
      "geometry": {
        "type": "Point",
        "coordinates": [
          45.553629,
          31.723911
        ]
      },
      "properties": {
        "description": "representative point"
      }
    },
    {
      "geometry": {
        "type": "Point",
        "coordinates": [
          45.553629,
          31.723911
        ]
      },
      "id": "darmc-location-21916",
      "type": "Feature",
      "properties": {
        "description": "Point location",
        "location_precision": "precise",
        "title": "DARMC location 21916",
        "link": "http://pleiades.stoa.org/places/912970/darmc-location-21916"
      }
    }
  ]
}