{
  "type": "FeatureCollection",
  "title": "Tarr Steps",
  "id": "913465647",
  "bbox": [
    -3.6177347,
    51.0771786,
    -3.6177347,
    51.0771786
  ],
  "description": "Tarr Steps is a prehistoric bridge over the River Barle in England. The current phase dates to the Medieval period, although the original phase of the bridge is dated ca. 1000 BC.",
  "features": [
    {
      "type": "Feature",
      "geometry": {
        "type": "Point",
        "coordinates": [
          -3.6177347,
          51.0771786
        ]
      },
      "properties": {
        "description": "representative point"
      }
    },
    {
      "geometry": {
        "type": "Point",
        "coordinates": [
          -3.6177347,
          51.0771786
        ]
      },
      "id": "location-of-tarr-steps",
      "type": "Feature",
      "properties": {
        "description": "Location based on OpenStreetMap",
        "location_precision": "precise",
        "title": "OSM location of Tarr Steps",
        "link": "http://pleiades.stoa.org/places/913465647/location-of-tarr-steps"
      }
    }
  ]
}