{
  "type": "FeatureCollection",
  "title": "Untitled",
  "id": "915063",
  "description": "An ancient place, cited: BAtlas 93 F2 unnamed dam (Ja Nishin)",
  "bbox": [
    49.432028,
    30.998195,
    49.432028,
    30.998195
  ],
  "reprPoint": [
    49.432028,
    30.998195
  ],
  "features": [
    {
      "geometry": {
        "type": "Point",
        "coordinates": [
          49.432028,
          30.998195
        ]
      },
      "id": "darmc-location-31866",
      "type": "Feature",
      "properties": {
        "description": "scale point location",
        "location_precision": "precise",
        "title": "DARMC location 31866",
        "link": "http://pleiades.stoa.org/places/915063/darmc-location-31866"
      }
    }
  ]
}