{
  "type": "FeatureCollection",
  "title": "Tulūl al-Hummar",
  "id": "916091377",
  "bbox": [
    45.4998,
    31.6166,
    45.4998,
    31.6166
  ],
  "description": "Mound where stamped bricks have been found.",
  "features": [
    {
      "type": "Feature",
      "geometry": {
        "type": "Point",
        "coordinates": [
          45.4998,
          31.6166
        ]
      },
      "properties": {
        "description": "representative point"
      }
    },
    {
      "geometry": {
        "type": "Point",
        "coordinates": [
          45.4998,
          31.6166
        ]
      },
      "id": "cigs-location-of-tulul-al-hummar",
      "type": "Feature",
      "properties": {
        "description": null,
        "location_precision": "precise",
        "title": "CIGS location of Tulūl al-Hummar",
        "link": "http://pleiades.stoa.org/places/916091377/cigs-location-of-tulul-al-hummar"
      }
    }
  ]
}