{
  "type": "FeatureCollection",
  "title": "Temple of Augustales at Centuripae",
  "id": "916046175",
  "bbox": [
    14.741437,
    37.621971,
    14.741437,
    37.621971
  ],
  "description": "An early Imperial (first to third centuries) temple at Centuripae that has been associated with the priestly college of the Augustales.",
  "connectsWith": [
    "462153"
  ],
  "features": [
    {
      "type": "Feature",
      "geometry": {
        "type": "Point",
        "coordinates": [
          14.741437,
          37.621971
        ]
      },
      "properties": {
        "description": "representative point"
      }
    },
    {
      "geometry": {
        "type": "Point",
        "coordinates": [
          14.741437,
          37.621971
        ]
      },
      "id": "osm-location-of-temple-of-augustales",
      "type": "Feature",
      "properties": {
        "description": "Location based on OpenStreetMap",
        "location_precision": "precise",
        "title": "OSM location of Temple of Augustales",
        "link": "http://pleiades.stoa.org/places/916046175/osm-location-of-temple-of-augustales"
      }
    }
  ]
}