{
  "type": "FeatureCollection",
  "title": "Mastaba of Kagemni",
  "id": "916778615",
  "bbox": [
    31.2211256,
    29.8758796,
    31.2211256,
    29.8758796
  ],
  "description": "The 6th Dynasty vizier Kagemni was buried in a large limestone mastaba at Saqqara. It Is the largest mastaba in the Teti cemetery. Its relief program includes well-preserved depictions of quotidian life in ancient Egypt.",
  "connectsWith": [
    "796289136"
  ],
  "features": [
    {
      "type": "Feature",
      "geometry": {
        "type": "Point",
        "coordinates": [
          31.2211256,
          29.8758796
        ]
      },
      "properties": {
        "description": "representative point"
      }
    },
    {
      "geometry": {
        "type": "Point",
        "coordinates": [
          31.2211256,
          29.8758796
        ]
      },
      "id": "osm-location-of-mastaba-of-kagemni",
      "type": "Feature",
      "properties": {
        "description": "Location based on OpenStreetMap",
        "location_precision": "precise",
        "title": "OSM location of Mastaba of Kagemni",
        "link": "http://pleiades.stoa.org/places/916778615/osm-location-of-mastaba-of-kagemni"
      }
    }
  ]
}