{
  "type": "FeatureCollection",
  "title": "Ani city wall",
  "id": "916890383",
  "bbox": [
    43.5705326,
    40.5122171,
    43.5705326,
    40.5122171
  ],
  "description": "Defensive walls attributed to King Smbat in the tenth centuries.",
  "connectsWith": [
    "863739"
  ],
  "features": [
    {
      "type": "Feature",
      "geometry": {
        "type": "Point",
        "coordinates": [
          43.5705326,
          40.5122171
        ]
      },
      "properties": {
        "description": "representative point"
      }
    },
    {
      "geometry": {
        "type": "Point",
        "coordinates": [
          43.5705326,
          40.5122171
        ]
      },
      "id": "osm-location-of-city-wall",
      "type": "Feature",
      "properties": {
        "description": "Representative location based on OpenStreetMap.",
        "location_precision": "precise",
        "title": "OSM location of city wall",
        "link": "http://pleiades.stoa.org/places/916890383/osm-location-of-city-wall"
      }
    }
  ]
}