{
  "type": "FeatureCollection",
  "title": "Mausoleum of Romulus",
  "id": "916973546",
  "bbox": [
    12.5185,
    41.8551,
    12.5185,
    41.8551
  ],
  "description": "Tomb of Valerius Romulus (ca. AD 292/295 – 309), son of Maxentius, along the Via Appia.",
  "connectsWith": [
    "356966898",
    "423129"
  ],
  "features": [
    {
      "type": "Feature",
      "geometry": {
        "type": "Point",
        "coordinates": [
          12.5185,
          41.8551
        ]
      },
      "properties": {
        "description": "representative point"
      }
    },
    {
      "geometry": {
        "type": "Point",
        "coordinates": [
          12.5185,
          41.8551
        ]
      },
      "id": "location-of-mausoleum-of-romulus",
      "type": "Feature",
      "properties": {
        "description": "verified in Google Earth 2013.",
        "location_precision": "precise",
        "title": "Imagery location of Mausoleum of Romulus",
        "link": "http://pleiades.stoa.org/places/916973546/location-of-mausoleum-of-romulus"
      }
    }
  ]
}