{
  "type": "FeatureCollection",
  "title": "San Potito Sannitico",
  "id": "917618128",
  "bbox": [
    14.3929016,
    41.337736,
    14.3929016,
    41.337736
  ],
  "description": "A Roman villa in the locality of Torelle at San Potito Sannitico.",
  "features": [
    {
      "type": "Feature",
      "geometry": {
        "type": "Point",
        "coordinates": [
          14.3929016,
          41.337736
        ]
      },
      "properties": {
        "description": "representative point"
      }
    },
    {
      "geometry": {
        "type": "Point",
        "coordinates": [
          14.3929016,
          41.337736
        ]
      },
      "id": "osm-location-of-san-potito-sannitico",
      "type": "Feature",
      "properties": {
        "description": "Associated modern location based on OpenStreetMap",
        "location_precision": "precise",
        "title": "OSM location of San Potito Sannitico",
        "link": "http://pleiades.stoa.org/places/917618128/osm-location-of-san-potito-sannitico"
      }
    }
  ]
}