{
  "type": "FeatureCollection",
  "title": "Kouloures at Phaistos",
  "id": "920460659",
  "bbox": [
    24.81377,
    35.05123,
    24.81377,
    35.05123
  ],
  "description": "Circular, stone, pit-like structures built into the ground at the edge of the West Court of the Minoan palace at Phaistos.",
  "connectsWith": [
    "589987"
  ],
  "features": [
    {
      "type": "Feature",
      "geometry": {
        "type": "Point",
        "coordinates": [
          24.81377,
          35.05123
        ]
      },
      "properties": {
        "description": "representative point"
      }
    },
    {
      "geometry": {
        "type": "Point",
        "coordinates": [
          24.81377,
          35.05123
        ]
      },
      "id": "the-kouloures-at-phaistos",
      "type": "Feature",
      "properties": {
        "description": "Circular, stone, pit-like structures built into the ground at the edge of the West Court of the Minoan palace at Phaistos.",
        "location_precision": "precise",
        "title": "Kouloures at Phaistos",
        "link": "http://pleiades.stoa.org/places/920460659/the-kouloures-at-phaistos"
      }
    }
  ]
}