{
  "type": "FeatureCollection",
  "title": "Tepeköy Höyük",
  "id": "92232873",
  "bbox": [
    41.505851,
    39.093299,
    41.505851,
    39.093299
  ],
  "description": "Settlement in eastern Turkey containing signs of inhabitation dated to the Early Bronze Age. Rescue excavations were conducted at the site prior to its inundation by the Alpaslan-2 Reservoir in 2021.",
  "names": [
    "Tepekoy Hoyuk"
  ],
  "features": [
    {
      "type": "Feature",
      "geometry": {
        "type": "Point",
        "coordinates": [
          41.505851,
          39.093299
        ]
      },
      "properties": {
        "description": "representative point"
      }
    },
    {
      "geometry": {
        "type": "Point",
        "coordinates": [
          41.505851,
          39.093299
        ]
      },
      "id": "google-earth-location-of-tepekoy-hoyuk",
      "type": "Feature",
      "properties": {
        "description": "Point representing the approximate centerpoint of the Tepeköy Höyük site prior to its inundation, after Erdoğan 2023.",
        "location_precision": "precise",
        "title": "Google Earth location of Tepeköy Höyük",
        "link": "http://pleiades.stoa.org/places/92232873/google-earth-location-of-tepekoy-hoyuk"
      }
    }
  ]
}