{
  "type": "FeatureCollection",
  "title": "Gur-i Shapur",
  "id": "922653",
  "bbox": [
    51.614238,
    29.779161,
    51.614238,
    29.779161
  ],
  "description": "The so-called \"Shapur cave\" in the Zagros Mountains contains a colossal statue of Shapur I, the second ruler of the Sasanid Empire.",
  "connectsWith": [
    "410216617",
    "922740"
  ],
  "features": [
    {
      "type": "Feature",
      "geometry": {
        "type": "Point",
        "coordinates": [
          51.614238,
          29.779161
        ]
      },
      "properties": {
        "description": "representative point"
      }
    },
    {
      "geometry": {
        "type": "Point",
        "coordinates": [
          51.614238,
          29.779161
        ]
      },
      "id": "darmc-location-32534",
      "type": "Feature",
      "properties": {
        "description": "  scale point location",
        "location_precision": "precise",
        "title": "DARMC location 32534",
        "link": "http://pleiades.stoa.org/places/922653/darmc-location-32534"
      }
    }
  ]
}