{
  "type": "FeatureCollection",
  "title": "Gur-i Shapur",
  "id": "922653",
  "bbox": [
    51.6118028,
    29.8076618,
    51.6118028,
    29.8076618
  ],
  "description": "The so-called \"Shapur cave\" in the Zagros Mountains contains a colossal statue of Shapur I, the second ruler of the Sasanid Empire.",
  "connectsWith": [
    "410216617",
    "922740"
  ],
  "features": [
    {
      "type": "Feature",
      "geometry": {
        "type": "Point",
        "coordinates": [
          51.6118028,
          29.8076618
        ]
      },
      "properties": {
        "description": "representative point"
      }
    },
    {
      "geometry": {
        "type": "Point",
        "coordinates": [
          51.6118028,
          29.8076618
        ]
      },
      "id": "osm-location-of-shahpur-sasani-cave",
      "type": "Feature",
      "properties": {
        "description": "Representative location based on OpenStreetMap.",
        "location_precision": "precise",
        "title": "OSM location of Shahpur Sasani Cave",
        "link": "http://pleiades.stoa.org/places/922653/osm-location-of-shahpur-sasani-cave"
      }
    }
  ]
}