{
  "type": "FeatureCollection",
  "title": "Persides?/Susidae? Pylae",
  "id": "922697",
  "description": "An ancient place, cited: BAtlas 94 B3 Persides?/Susidae? Pylae",
  "bbox": [
    51.909909,
    30.093233,
    51.909909,
    30.093233
  ],
  "reprPoint": [
    51.909909,
    30.093233
  ],
  "names": [
    "Persides",
    "Susidae Pylae"
  ],
  "features": [
    {
      "geometry": {
        "type": "Point",
        "coordinates": [
          51.909909,
          30.093233
        ]
      },
      "id": "darmc-location-22295",
      "type": "Feature",
      "properties": {
        "description": "Point location",
        "location_precision": "precise",
        "title": "DARMC location 22295",
        "link": "http://pleiades.stoa.org/places/922697/darmc-location-22295"
      }
    }
  ]
}