{
  "type": "FeatureCollection",
  "title": "Naqsh-i Rajab",
  "id": "922684",
  "description": "An ancient place, cited: BAtlas 94 C4 Naqsh-i Rajab",
  "bbox": [
    52.887043,
    29.966486,
    52.920562,
    29.979412
  ],
  "reprPoint": [
    52.9038025,
    29.972949
  ],
  "features": [
    {
      "geometry": {
        "type": "Point",
        "coordinates": [
          52.887043,
          29.966486
        ]
      },
      "id": "dare-location",
      "type": "Feature",
      "properties": {
        "description": "Representative point location, site precision",
        "location_precision": "precise",
        "title": "DARE Location",
        "link": "http://pleiades.stoa.org/places/922684/dare-location"
      }
    },
    {
      "geometry": {
        "type": "Point",
        "coordinates": [
          52.920562,
          29.979412
        ]
      },
      "id": "darmc-location-32186",
      "type": "Feature",
      "properties": {
        "description": "scale point location",
        "location_precision": "precise",
        "title": "DARMC location 32186",
        "link": "http://pleiades.stoa.org/places/922684/darmc-location-32186"
      }
    }
  ]
}