{
  "type": "FeatureCollection",
  "title": "Gur-i Dukhtar",
  "id": "922652",
  "description": "An ancient place, cited: BAtlas 94 B4 Gur-i Dukhtar",
  "bbox": [
    51.633061,
    29.217325,
    51.633061,
    29.217325
  ],
  "reprPoint": [
    51.633061,
    29.217325
  ],
  "features": [
    {
      "geometry": {
        "type": "Point",
        "coordinates": [
          51.633061,
          29.217325
        ]
      },
      "id": "darmc-location-32332",
      "type": "Feature",
      "properties": {
        "description": "scale point location",
        "location_precision": "precise",
        "title": "DARMC location 32332",
        "link": "http://pleiades.stoa.org/places/922652/darmc-location-32332"
      }
    }
  ]
}