{
  "type": "FeatureCollection",
  "title": "Naqsh-i Rustam",
  "id": "922685",
  "description": "An ancient necropolis located northwest of Persepolis.",
  "bbox": [
    52.874722,
    29.988889,
    52.874722,
    29.988889
  ],
  "reprPoint": [
    52.874722,
    29.988889
  ],
  "features": [
    {
      "geometry": {
        "type": "Point",
        "coordinates": [
          52.874722,
          29.988889
        ]
      },
      "id": "dare-location",
      "type": "Feature",
      "properties": {
        "description": "Representative point location, site precision",
        "location_precision": "precise",
        "title": "DARE Location",
        "link": "http://pleiades.stoa.org/places/922685/dare-location"
      }
    },
    {
      "geometry": {
        "type": "Point",
        "coordinates": [
          52.935221,
          29.9774
        ]
      },
      "id": "darmc-location-32187",
      "type": "Feature",
      "properties": {
        "description": "scale point location",
        "location_precision": "precise",
        "title": "DARMC location 32187",
        "link": "http://pleiades.stoa.org/places/922685/darmc-location-32187"
      }
    }
  ]
}