{
  "type": "FeatureCollection",
  "title": "Muk",
  "id": "922681",
  "description": "An ancient place, cited: BAtlas 94 C4 Muk",
  "bbox": [
    52.655808,
    29.096565,
    52.655808,
    29.096565
  ],
  "reprPoint": [
    52.655808,
    29.096565
  ],
  "features": [
    {
      "geometry": {
        "type": "Point",
        "coordinates": [
          52.655808,
          29.096565
        ]
      },
      "id": "darmc-location-22315",
      "type": "Feature",
      "properties": {
        "description": "Point location",
        "location_precision": "precise",
        "title": "DARMC location 22315",
        "link": "http://pleiades.stoa.org/places/922681/darmc-location-22315"
      }
    }
  ]
}