{
  "type": "FeatureCollection",
  "title": "Tal-i Malyan/[Anzan]",
  "id": "922729",
  "bbox": [
    52.407778,
    29.98608,
    52.410901,
    30.011667
  ],
  "description": "An ancient place, cited: BAtlas 94 C3 Tal-i Malyan/[Anzan]",
  "names": [
    "Anzan"
  ],
  "features": [
    {
      "type": "Feature",
      "geometry": {
        "type": "Point",
        "coordinates": [
          52.4093395,
          29.9988735
        ]
      },
      "properties": {
        "description": "representative point"
      }
    },
    {
      "geometry": {
        "type": "Point",
        "coordinates": [
          52.410901,
          29.98608
        ]
      },
      "id": "darmc-location-32304",
      "type": "Feature",
      "properties": {
        "description": "  scale point location",
        "location_precision": "precise",
        "title": "DARMC location 32304",
        "link": "http://pleiades.stoa.org/places/922729/darmc-location-32304"
      }
    },
    {
      "geometry": {
        "type": "Point",
        "coordinates": [
          52.407778,
          30.011667
        ]
      },
      "id": "dare-location",
      "type": "Feature",
      "properties": {
        "description": "Representative point location, site precision",
        "location_precision": "precise",
        "title": "DARE Location",
        "link": "http://pleiades.stoa.org/places/922729/dare-location"
      }
    }
  ]
}