{
  "type": "FeatureCollection",
  "title": "Tal-i Baiza",
  "id": "922726",
  "description": "An ancient place, cited: BAtlas 94 C4 Tal-i Baiza",
  "bbox": [
    52.444364,
    29.961872,
    52.444364,
    29.961872
  ],
  "reprPoint": [
    52.444364,
    29.961872
  ],
  "features": [
    {
      "geometry": {
        "type": "Point",
        "coordinates": [
          52.444364,
          29.961872
        ]
      },
      "id": "darmc-location-32305",
      "type": "Feature",
      "properties": {
        "description": "scale point location",
        "location_precision": "precise",
        "title": "DARMC location 32305",
        "link": "http://pleiades.stoa.org/places/922726/darmc-location-32305"
      }
    }
  ]
}