{
  "type": "FeatureCollection",
  "title": "Tal-i Malyan/[Anzan]",
  "id": "922729",
  "bbox": [
    52.407778,
    29.98608,
    52.4124,
    30.0119
  ],
  "description": "An ancient place, cited: BAtlas 94 C3 Tal-i Malyan/[Anzan]",
  "names": [
    "Anzan",
    "Tal-I Malyān"
  ],
  "features": [
    {
      "type": "Feature",
      "geometry": {
        "type": "Point",
        "coordinates": [
          52.4103596667,
          30.0032156667
        ]
      },
      "properties": {
        "description": "representative point"
      }
    },
    {
      "geometry": {
        "type": "Point",
        "coordinates": [
          52.410901,
          29.98608
        ]
      },
      "id": "darmc-location-32304",
      "type": "Feature",
      "properties": {
        "description": "representative point location digitized from the Barrington Atlas of the Greek and Roman World by the Digital Atlas of Roman and Medieval Civilizations project at Harvard University.",
        "location_precision": "precise",
        "title": "DARMC location 32304",
        "link": "http://pleiades.stoa.org/places/922729/darmc-location-32304"
      }
    },
    {
      "geometry": {
        "type": "Point",
        "coordinates": [
          52.407778,
          30.011667
        ]
      },
      "id": "dare-location",
      "type": "Feature",
      "properties": {
        "description": "Representative point location, site precision",
        "location_precision": "precise",
        "title": "DARE Location",
        "link": "http://pleiades.stoa.org/places/922729/dare-location"
      }
    },
    {
      "geometry": {
        "type": "Point",
        "coordinates": [
          52.4124,
          30.0119
        ]
      },
      "id": "imagery-location-of-tal-i-malyan",
      "type": "Feature",
      "properties": {
        "description": "Centre point location extracted from polygon drawn around entire site as identified on Google Earth base imagery in QGIS 3.x.",
        "location_precision": "precise",
        "title": "CIGS location of Tal-I Malyān",
        "link": "http://pleiades.stoa.org/places/922729/imagery-location-of-tal-i-malyan"
      }
    }
  ]
}