{
  "type": "FeatureCollection",
  "title": "Poggio all'Aglione",
  "id": "923771661",
  "bbox": [
    10.9235416,
    43.5353184,
    10.9235416,
    43.5353184
  ],
  "description": "A cistern likely connected with a Roman villa.",
  "features": [
    {
      "type": "Feature",
      "geometry": {
        "type": "Point",
        "coordinates": [
          10.9235416,
          43.5353184
        ]
      },
      "properties": {
        "description": "representative point"
      }
    },
    {
      "geometry": {
        "type": "Point",
        "coordinates": [
          10.9235416,
          43.5353184
        ]
      },
      "id": "osm-location",
      "type": "Feature",
      "properties": {
        "description": "Location based on OpenStreetMap",
        "location_precision": "precise",
        "title": "OSM location of Cisterna Romana",
        "link": "http://pleiades.stoa.org/places/923771661/osm-location"
      }
    }
  ]
}