{
  "type": "FeatureCollection",
  "title": "Untitled",
  "id": "924123",
  "bbox": [
    51.280998,
    30.285271,
    51.280998,
    30.285271
  ],
  "description": "An ancient place, cited: BAtlas 94 B3 unnamed bridge (Pol-e Brin, SW Da u Dukhtar)",
  "features": [
    {
      "type": "Feature",
      "geometry": {
        "type": "Point",
        "coordinates": [
          51.280998,
          30.285271
        ]
      },
      "properties": {
        "description": "representative point"
      }
    },
    {
      "geometry": {
        "type": "Point",
        "coordinates": [
          51.280998,
          30.285271
        ]
      },
      "id": "darmc-location-32291",
      "type": "Feature",
      "properties": {
        "description": "  scale point location",
        "location_precision": "precise",
        "title": "DARMC location 32291",
        "link": "http://pleiades.stoa.org/places/924123/darmc-location-32291"
      }
    }
  ]
}