{
  "type": "FeatureCollection",
  "title": "Tel Batash (Timnah)",
  "id": "925655548",
  "bbox": [
    34.9115833,
    31.785337,
    34.9115833,
    31.785337
  ],
  "description": "Tel Batash, an archaeological site located in the Sorek Valley of modern Israel, lies northwest of Beit Shemesh. This site has been identified as the ancient Timnath or Timnah, a Philistine city in Canaan.",
  "names": [
    "Timnah",
    "Tel Batash",
    "Tel Batash"
  ],
  "features": [
    {
      "type": "Feature",
      "geometry": {
        "type": "Point",
        "coordinates": [
          34.9115833,
          31.785337
        ]
      },
      "properties": {
        "description": "representative point"
      }
    },
    {
      "geometry": {
        "type": "Point",
        "coordinates": [
          34.9115833,
          31.785337
        ]
      },
      "id": "osm-location-of-tel-batash",
      "type": "Feature",
      "properties": {
        "description": "Representative location based on OpenStreetMap",
        "location_precision": "precise",
        "title": "OSM location of Tel Batash",
        "link": "http://pleiades.stoa.org/places/925655548/osm-location-of-tel-batash"
      }
    }
  ]
}