{
  "type": "FeatureCollection",
  "title": "Salve necropolis",
  "id": "9269628",
  "bbox": [
    18.2339541,
    39.8467611,
    18.2339541,
    39.8467611
  ],
  "description": "A Chalcolithic necropolis with tumulus-type tombs.",
  "features": [
    {
      "type": "Feature",
      "geometry": {
        "type": "Point",
        "coordinates": [
          18.2339541,
          39.8467611
        ]
      },
      "properties": {
        "description": "representative point"
      }
    },
    {
      "geometry": {
        "type": "Point",
        "coordinates": [
          18.2339541,
          39.8467611
        ]
      },
      "id": "osm-location-of-necropoli-a-tumuli-di-salve",
      "type": "Feature",
      "properties": {
        "description": "Representative location based on OpenStreetMap",
        "location_precision": "precise",
        "title": "OSM location of Necropoli a Tumuli di Salve",
        "link": "http://pleiades.stoa.org/places/9269628/osm-location-of-necropoli-a-tumuli-di-salve"
      }
    }
  ]
}