{
  "type": "FeatureCollection",
  "title": "Tall Imlīḥiyah",
  "id": "928982900",
  "bbox": [
    45.003,
    34.1961,
    45.003,
    34.1961
  ],
  "description": "A settlement mound now submerged in the Hamrin basin; a findspot for cuneiform inscriptions.",
  "names": [
    "Tall Imlīḥiyah"
  ],
  "features": [
    {
      "type": "Feature",
      "geometry": {
        "type": "Point",
        "coordinates": [
          45.003,
          34.1961
        ]
      },
      "properties": {
        "description": "representative point"
      }
    },
    {
      "geometry": {
        "type": "Point",
        "coordinates": [
          45.003,
          34.1961
        ]
      },
      "id": "cigs-location-of-tall-imlihiyah",
      "type": "Feature",
      "properties": {
        "description": null,
        "location_precision": "precise",
        "title": "CIGS location of Tall Imlīḥiyah",
        "link": "http://pleiades.stoa.org/places/928982900/cigs-location-of-tall-imlihiyah"
      }
    }
  ]
}