{
  "type": "FeatureCollection",
  "title": "Tanagra",
  "id": "930250",
  "description": "An ancient place, cited: BAtlas 94 unlocated Tanagra",
  "reprPoint": [
    0.0,
    0.0
  ],
  "names": [
    "Tanagra",
    "Tanagra"
  ],
  "features": [
    {
      "id": "batlas-location",
      "type": "Feature",
      "properties": {
        "description": null,
        "location_precision": "unlocated",
        "title": "Barrington Atlas location",
        "link": "http://pleiades.stoa.org/places/930250/batlas-location"
      }
    },
    {
      "geometry": {
        "type": "Point",
        "coordinates": [
          20.0,
          35.0
        ]
      },
      "id": "modern-tanagra",
      "type": "Feature",
      "properties": {
        "description": "Modern Tanagra, close  (within 1 mile) to ancient Tanagra",
        "location_precision": "precise",
        "title": "Modern Tanagra",
        "link": "http://pleiades.stoa.org/places/930250/modern-tanagra"
      }
    },
    {
      "geometry": {
        "type": "Point",
        "coordinates": [
          20.0,
          35.0
        ]
      },
      "id": "tanagra-1",
      "type": "Feature",
      "properties": {
        "description": "Modern Tanagra, close  (within 1 mile) to ancient Tanagra",
        "location_precision": "precise",
        "title": "Tanagra",
        "link": "http://pleiades.stoa.org/places/930250/tanagra-1"
      }
    },
    {
      "geometry": {
        "type": "Point",
        "coordinates": [
          23.52523,
          38.236583
        ]
      },
      "id": "modern-tanagra-1",
      "type": "Feature",
      "properties": {
        "description": "Ancient Tanagra is within a mile from modern Tanagra",
        "location_precision": "precise",
        "title": "Modern Tanagra, per Google Earth",
        "link": "http://pleiades.stoa.org/places/930250/modern-tanagra-1"
      }
    }
  ]
}