{
  "type": "FeatureCollection",
  "title": "Gerraicus? Sinus",
  "id": "932455",
  "bbox": [
    49.68752,
    27.02883,
    49.68752,
    27.02883
  ],
  "description": "A portion of the Persian Gulf mentioned by Pliny who places it between the Sinus Capeus on the north and the Regio Attene to the south.",
  "names": [
    "Gerraicus Sinus"
  ],
  "features": [
    {
      "type": "Feature",
      "geometry": {
        "type": "Point",
        "coordinates": [
          49.68752,
          27.02883
        ]
      },
      "properties": {
        "description": "representative point"
      }
    },
    {
      "geometry": {
        "type": "Point",
        "coordinates": [
          49.68752,
          27.02883
        ]
      },
      "id": "imagery-location-of-al-jubayl-commercial-port",
      "type": "Feature",
      "properties": {
        "description": "Coordinates following GeoNames",
        "location_precision": "precise",
        "title": "Imagery location of Al Jubayl Commercial Port",
        "link": "http://pleiades.stoa.org/places/932455/imagery-location-of-al-jubayl-commercial-port"
      }
    }
  ]
}