{
  "type": "FeatureCollection",
  "title": "Darin",
  "id": "932448",
  "bbox": [
    50.078134,
    26.543416,
    50.078134,
    26.543416
  ],
  "description": "An ancient place, cited: BAtlas 95 C3 Darin",
  "features": [
    {
      "type": "Feature",
      "geometry": {
        "type": "Point",
        "coordinates": [
          50.078134,
          26.543416
        ]
      },
      "properties": {
        "description": "representative point"
      }
    },
    {
      "geometry": {
        "type": "Point",
        "coordinates": [
          50.078134,
          26.543416
        ]
      },
      "id": "darmc-location-22207",
      "type": "Feature",
      "properties": {
        "description": "Point location",
        "location_precision": "precise",
        "title": "DARMC location 22207",
        "link": "http://pleiades.stoa.org/places/932448/darmc-location-22207"
      }
    }
  ]
}