{
  "type": "FeatureCollection",
  "title": "Via Annia",
  "id": "932949218",
  "bbox": [
    11.876975,
    45.0577,
    13.371044,
    45.769742
  ],
  "description": "The Via Annia was a Roman consular road in Cisalpine Gaul that connected (H)Atria to Aquileia. The praetor Titus Annius Rufus constructed the road in 131 BC.",
  "features": [
    {
      "type": "Feature",
      "geometry": {
        "type": "Point",
        "coordinates": [
          12.5074226,
          45.51010228
        ]
      },
      "properties": {
        "description": "representative point"
      }
    }
  ]
}