{
  "type": "FeatureCollection",
  "title": "Via Annia",
  "id": "932949218",
  "bbox": [
    11.876975,
    45.0577,
    13.370946,
    45.769631
  ],
  "description": "The Via Annia was a Roman consular road in Cisalpine Gaul that connected (H)Atria to Aquileia. The praetor Titus Annius Rufus constructed the road in 131 BC.",
  "features": [
    {
      "type": "Feature",
      "geometry": {
        "type": "Point",
        "coordinates": [
          12.5072045667,
          45.5100491467
        ]
      },
      "properties": {
        "description": "representative point"
      }
    }
  ]
}