{
  "type": "FeatureCollection",
  "title": "Stoke Hill",
  "id": "93334047",
  "bbox": [
    -3.5273732,
    50.7474408,
    -3.5273732,
    50.7474408
  ],
  "description": "The site of a possible Roman signal station.",
  "features": [
    {
      "type": "Feature",
      "geometry": {
        "type": "Point",
        "coordinates": [
          -3.5273732,
          50.7474408
        ]
      },
      "properties": {
        "description": "representative point"
      }
    },
    {
      "geometry": {
        "type": "Point",
        "coordinates": [
          -3.5273732,
          50.7474408
        ]
      },
      "id": "osm-location-of-roman-signal-station",
      "type": "Feature",
      "properties": {
        "description": "Representative location based on OpenStreetMap.",
        "location_precision": "precise",
        "title": "OSM location of Roman Signal Station",
        "link": "http://pleiades.stoa.org/places/93334047/osm-location-of-roman-signal-station"
      }
    }
  ]
}