{
  "type": "FeatureCollection",
  "title": "Roman amphitheater at Santa Maria Capua Vetere",
  "id": "93820013",
  "description": "Sometimes referred to as the \"Anfiteatro Campano\", the Roman amphitheater at Santa Maria Capua Vetere is the second largest in the Roman world. Begun under Augustus, it was further renovated under Hadrian and Antoninus Pius.",
  "bbox": [
    14.2494471,
    41.0866016,
    14.2494471,
    41.0866016
  ],
  "connectsWith": [
    "3676ccf7c04c7afb46e2ae8365395edc"
  ],
  "reprPoint": [
    14.2494471,
    41.0866016
  ],
  "names": [
    "Anfiteatro Campano"
  ],
  "features": [
    {
      "geometry": {
        "type": "Point",
        "coordinates": [
          14.2494471,
          41.0866016
        ]
      },
      "id": "osm-location-of-roman-amphitheater",
      "type": "Feature",
      "properties": {
        "description": "Representative location based on OpenStreetMap.",
        "location_precision": "precise",
        "title": "OSM location of Roman amphitheater",
        "link": "http://pleiades.stoa.org/places/93820013/osm-location-of-roman-amphitheater"
      }
    }
  ]
}