{
  "type": "FeatureCollection",
  "title": "Gourimadi Prehistoric Settlement",
  "id": "941807582",
  "bbox": [
    24.3576899171,
    38.039724075,
    24.3576899171,
    38.039724075
  ],
  "description": "Survey and site excavation have provided evidence for a likely prehistoric settlement (possibly fortified) on the Gourimadi hill in the Katsaronio plain in the Karystia, southern Euboea, Greece.",
  "names": [
    "Gourimadi"
  ],
  "features": [
    {
      "type": "Feature",
      "geometry": {
        "type": "Point",
        "coordinates": [
          24.3576899171,
          38.039724075
        ]
      },
      "properties": {
        "description": "representative point"
      }
    },
    {
      "geometry": {
        "type": "Point",
        "coordinates": [
          24.3576899171,
          38.039724075
        ]
      },
      "id": "imagery-location-of-gourimadi-excavation",
      "type": "Feature",
      "properties": {
        "description": "Coordinates from Chronique, verified in Tankosić 2021a and against Google Earth (imagery date 8/8/2019). Dates after Tankosić 2021a.",
        "location_precision": "precise",
        "title": "Imagery Location of Gourimadi excavation",
        "link": "http://pleiades.stoa.org/places/941807582/imagery-location-of-gourimadi-excavation"
      }
    }
  ]
}