{
  "type": "FeatureCollection",
  "title": "Qal'eh Kharabeh",
  "id": "942304",
  "description": "An ancient place, cited: BAtlas 96 C2 Qal'eh Kharabeh",
  "bbox": [
    54.41742,
    37.087259,
    54.41742,
    37.087259
  ],
  "reprPoint": [
    54.41742,
    37.087259
  ],
  "features": [
    {
      "geometry": {
        "type": "Point",
        "coordinates": [
          54.41742,
          37.087259
        ]
      },
      "id": "darmc-location-22277",
      "type": "Feature",
      "properties": {
        "description": "Point location",
        "location_precision": "precise",
        "title": "DARMC location 22277",
        "link": "http://pleiades.stoa.org/places/942304/darmc-location-22277"
      }
    }
  ]
}