{
  "type": "FeatureCollection",
  "title": "Qal'eh Gug",
  "id": "942301",
  "description": "An ancient place, cited: BAtlas 96 D2 Qal'eh Gug",
  "bbox": [
    55.148651,
    37.20616,
    55.148651,
    37.20616
  ],
  "reprPoint": [
    55.148651,
    37.20616
  ],
  "features": [
    {
      "geometry": {
        "type": "Point",
        "coordinates": [
          55.148651,
          37.20616
        ]
      },
      "id": "darmc-location-22285",
      "type": "Feature",
      "properties": {
        "description": "Point location",
        "location_precision": "precise",
        "title": "DARMC location 22285",
        "link": "http://pleiades.stoa.org/places/942301/darmc-location-22285"
      }
    }
  ]
}