{
  "type": "FeatureCollection",
  "title": "Qal'eh Yasaqi",
  "id": "942309",
  "description": "An ancient place, cited: BAtlas 96 C3 Qal'eh Yasaqi",
  "bbox": [
    54.334066,
    36.828941,
    54.334066,
    36.828941
  ],
  "reprPoint": [
    54.334066,
    36.828941
  ],
  "features": [
    {
      "geometry": {
        "type": "Point",
        "coordinates": [
          54.334066,
          36.828941
        ]
      },
      "id": "darmc-location-22274",
      "type": "Feature",
      "properties": {
        "description": "Point location",
        "location_precision": "precise",
        "title": "DARMC location 22274",
        "link": "http://pleiades.stoa.org/places/942309/darmc-location-22274"
      }
    }
  ]
}