{
  "type": "FeatureCollection",
  "title": "The Theater of Larissa",
  "id": "942647940",
  "description": "The theater at Larissa was a large stone theater built around the end of the third century BC and used for dramatic performances and as a political meeting place.",
  "bbox": [
    22.415256,
    39.640315,
    22.415256,
    39.640315
  ],
  "connectsWith": [
    "2ba8d674e32e1c432d6888ef56fe8308"
  ],
  "reprPoint": [
    22.415256,
    39.640315
  ],
  "names": [
    "The Theater of Larissa",
    "First Ancient Theater of Larissa"
  ],
  "features": [
    {
      "geometry": {
        "type": "Point",
        "coordinates": [
          22.415256,
          39.640315
        ]
      },
      "id": "the-theater-of-larissa",
      "type": "Feature",
      "properties": {
        "description": "Based on Google Earth 2015.",
        "location_precision": "precise",
        "title": "Imagery location for the Theater of Larissa",
        "link": "http://pleiades.stoa.org/places/942647940/the-theater-of-larissa"
      }
    }
  ]
}