{
  "type": "FeatureCollection",
  "title": "Judeideh",
  "id": "945906724",
  "bbox": [
    42.028552,
    34.3887,
    42.028552,
    34.3887
  ],
  "description": "Judeideh (also Jedīdē, Judaide) is a site in the middle Euphrates region in what was part of the ancient kingdom of Suhu. The city was situated on the east bank of the Euphrates, about ten kilometers downstream of Anat (Anatho). Like many towns and cities of the ancient kingdom of Suhu, Judeideh is now underwater; the area was flooded after the construction of the Haditha dam. Its ancient name is not known.",
  "connectsWith": [
    "893936",
    "945906723",
    "912849"
  ],
  "names": [
    "Judeideh"
  ],
  "features": [
    {
      "type": "Feature",
      "geometry": {
        "type": "Point",
        "coordinates": [
          42.028552,
          34.3887
        ]
      },
      "properties": {
        "description": "representative point"
      }
    },
    {
      "geometry": {
        "type": "Point",
        "coordinates": [
          42.028552,
          34.3887
        ]
      },
      "id": "judeideh",
      "type": "Feature",
      "properties": {
        "description": "Estimated, representative coordinates based on location of Sur Jureh shown in Map 2 of Iraq 45 (1981-82) and on Corona satellite imagery (1102-1025Fore [Dec 11, 1967]).",
        "location_precision": "precise",
        "title": "Imagery Location of Judeideh",
        "link": "http://pleiades.stoa.org/places/945906724/judeideh"
      }
    }
  ]
}