{
  "type": "FeatureCollection",
  "title": "Qamişvan/Değirmendüzü",
  "id": "946658103",
  "bbox": [
    42.9647167,
    39.210255,
    42.9647167,
    39.210255
  ],
  "description": "Değirmendüzü (formerly Qamişvan/Kamişvan) is a modern village situated ca. 8 km in the east of Pathos (Aznavurtepe / Anzavurtepe) in the Ağrı Province in eastern Turkey. Here a column base with an inscription of the Urartian king Minua, son of Išpuini (9th/8th century BCE) has been found (CTU I A 5-70)",
  "connectsWith": [
    "214160492"
  ],
  "names": [
    "Qamişvan",
    "Değirmendüzü"
  ],
  "features": [
    {
      "type": "Feature",
      "geometry": {
        "type": "Point",
        "coordinates": [
          42.9647167,
          39.210255
        ]
      },
      "properties": {
        "description": "representative point"
      }
    },
    {
      "geometry": {
        "type": "Point",
        "coordinates": [
          42.9647167,
          39.210255
        ]
      },
      "id": "osm-location",
      "type": "Feature",
      "properties": {
        "description": "Location based on OpenStreetMap",
        "location_precision": "precise",
        "title": "OSM Location of Değirmendüzü",
        "link": "http://pleiades.stoa.org/places/946658103/osm-location"
      }
    }
  ]
}