{
  "type": "FeatureCollection",
  "title": "Temple of Jupiter",
  "id": "949315840",
  "bbox": [
    14.6177482,
    41.4329867,
    14.6177482,
    41.4329867
  ],
  "description": "A temple dedicated to the Capitoline triad is located on the forum of Saepinum.",
  "connectsWith": [
    "433073"
  ],
  "features": [
    {
      "type": "Feature",
      "geometry": {
        "type": "Point",
        "coordinates": [
          14.6177482,
          41.4329867
        ]
      },
      "properties": {
        "description": "representative point"
      }
    },
    {
      "geometry": {
        "type": "Point",
        "coordinates": [
          14.6177482,
          41.4329867
        ]
      },
      "id": "location-of-temple-of-jupiter",
      "type": "Feature",
      "properties": {
        "description": "Location based on OpenStreetMap",
        "location_precision": "precise",
        "title": "OSM location of Temple of Jupiter",
        "link": "http://pleiades.stoa.org/places/949315840/location-of-temple-of-jupiter"
      }
    }
  ]
}