{
  "type": "FeatureCollection",
  "title": "Roman amphitheater at Egnatia/Gnathia",
  "id": "95066748",
  "bbox": [
    17.3912795,
    40.8880492,
    17.3912795,
    40.8880492
  ],
  "description": "The so-called Roman amphitheater at Egnatia/Gnathia dates to the Iulio-Claudian period. It is an elliptical structure with walls in opus Africanum that were revetted with painted plaster.",
  "connectsWith": [
    "442573"
  ],
  "features": [
    {
      "type": "Feature",
      "geometry": {
        "type": "Point",
        "coordinates": [
          17.3912795,
          40.8880492
        ]
      },
      "properties": {
        "description": "representative point"
      }
    },
    {
      "geometry": {
        "type": "Point",
        "coordinates": [
          17.3912795,
          40.8880492
        ]
      },
      "id": "location-of-roman-amphitheater",
      "type": "Feature",
      "properties": {
        "description": "Representative location based on OpenStreetMap.",
        "location_precision": "precise",
        "title": "OSM location of Roman amphitheater",
        "link": "http://pleiades.stoa.org/places/95066748/location-of-roman-amphitheater"
      }
    }
  ]
}