{
  "type": "FeatureCollection",
  "title": "[(A)Bivard]/Apauarktike",
  "id": "952058",
  "description": "An ancient place, cited: BAtlas 97 E2 [(A)Bivard]/Apauarktike",
  "bbox": [
    59.670091,
    37.519088,
    59.670091,
    37.519088
  ],
  "reprPoint": [
    59.670091,
    37.519088
  ],
  "names": [
    "Abivard",
    "Bivard",
    "Apauarktike"
  ],
  "features": [
    {
      "geometry": {
        "type": "Point",
        "coordinates": [
          59.670091,
          37.519088
        ]
      },
      "id": "darmc-location-21839",
      "type": "Feature",
      "properties": {
        "description": "Point location",
        "location_precision": "precise",
        "title": "DARMC location 21839",
        "link": "http://pleiades.stoa.org/places/952058/darmc-location-21839"
      }
    }
  ]
}