{
  "type": "FeatureCollection",
  "title": "Tumbus (Nubia)",
  "id": "952615577",
  "bbox": [
    30.393826,
    19.711147,
    30.393826,
    19.711147
  ],
  "description": "An archaeological site in northern Sudan that includes Tombos Island and the adjacent riverbank. The site is located at the Third Cataract of the Nile River and was occupied form the mid-18th Dynasty of Egypt and through the 25th Dynasty.",
  "connectsWith": [
    "727172",
    "805602"
  ],
  "features": [
    {
      "type": "Feature",
      "geometry": {
        "type": "Point",
        "coordinates": [
          30.393826,
          19.711147
        ]
      },
      "properties": {
        "description": "representative point"
      }
    },
    {
      "geometry": {
        "type": "Point",
        "coordinates": [
          30.393826,
          19.711147
        ]
      },
      "id": "osm-location-of-tombos",
      "type": "Feature",
      "properties": {
        "description": "Representative location based on OpenStreetMap",
        "location_precision": "precise",
        "title": "OSM location of Tombos",
        "link": "http://pleiades.stoa.org/places/952615577/osm-location-of-tombos"
      }
    }
  ]
}