{
  "type": "FeatureCollection",
  "title": "Arch of Trajan",
  "id": "952600989",
  "bbox": [
    9.2078824,
    35.853336,
    9.2078824,
    35.853336
  ],
  "description": "The Arch of Trajan at Maktar.",
  "connectsWith": [
    "324774",
    "329343086"
  ],
  "features": [
    {
      "type": "Feature",
      "geometry": {
        "type": "Point",
        "coordinates": [
          9.2078824,
          35.853336
        ]
      },
      "properties": {
        "description": "representative point"
      }
    },
    {
      "geometry": {
        "type": "Point",
        "coordinates": [
          9.2078824,
          35.853336
        ]
      },
      "id": "location-of-arch-of-trajan",
      "type": "Feature",
      "properties": {
        "description": "Location based on OpenStreetMap",
        "location_precision": "precise",
        "title": "OSM location of Arch of Trajan",
        "link": "http://pleiades.stoa.org/places/952600989/location-of-arch-of-trajan"
      }
    }
  ]
}