{
  "type": "FeatureCollection",
  "title": "Ponte di Pietra",
  "id": "952774737",
  "bbox": [
    7.3299824,
    45.7397954,
    7.3299824,
    45.7397954
  ],
  "description": "A Roman segmental stone arch bridge located near Augusta Praetoria.",
  "connectsWith": [
    "383579"
  ],
  "features": [
    {
      "type": "Feature",
      "geometry": {
        "type": "Point",
        "coordinates": [
          7.3299824,
          45.7397954
        ]
      },
      "properties": {
        "description": "representative point"
      }
    },
    {
      "geometry": {
        "type": "Point",
        "coordinates": [
          7.3299824,
          45.7397954
        ]
      },
      "id": "location-of-ponte-di-pietra",
      "type": "Feature",
      "properties": {
        "description": "Location based on OpenStreetMap",
        "location_precision": "precise",
        "title": "location of Ponte di Pietra",
        "link": "http://pleiades.stoa.org/places/952774737/location-of-ponte-di-pietra"
      }
    }
  ]
}