{
  "type": "FeatureCollection",
  "title": "Pagliano Roman port",
  "id": "952976544",
  "bbox": [
    12.1921804,
    42.6959763,
    12.1921804,
    42.6959763
  ],
  "description": "A riverine port near the confluence of the Tiber and Paglia rivers.",
  "connectsWith": [
    "423080",
    "413243"
  ],
  "features": [
    {
      "type": "Feature",
      "geometry": {
        "type": "Point",
        "coordinates": [
          12.1921804,
          42.6959763
        ]
      },
      "properties": {
        "description": "representative point"
      }
    },
    {
      "geometry": {
        "type": "Point",
        "coordinates": [
          12.1921804,
          42.6959763
        ]
      },
      "id": "location-of-archaeological-area",
      "type": "Feature",
      "properties": {
        "description": "Representative location based on OpenStreetMap.",
        "location_precision": "precise",
        "title": "OSM location of Porto Romano di Pagliano",
        "link": "http://pleiades.stoa.org/places/952976544/location-of-archaeological-area"
      }
    }
  ]
}