{
  "type": "FeatureCollection",
  "title": "Mount Juktas",
  "id": "953163789",
  "bbox": [
    25.1409222,
    35.2325318,
    25.1409222,
    35.2325318
  ],
  "description": "Mount Juktas is mountain of north-central Crete, noted for being the location of an important Minoan peak sanctuary.",
  "connectsWith": [
    "589748"
  ],
  "names": [
    "Mount Juktas"
  ],
  "features": [
    {
      "type": "Feature",
      "geometry": {
        "type": "Point",
        "coordinates": [
          25.1409222,
          35.2325318
        ]
      },
      "properties": {
        "description": "representative point"
      }
    },
    {
      "geometry": {
        "type": "Point",
        "coordinates": [
          25.1409222,
          35.2325318
        ]
      },
      "id": "location-of-mount-juktas",
      "type": "Feature",
      "properties": {
        "description": "Representative location based on OpenStreetMap",
        "location_precision": "precise",
        "title": "OSM location of Mount Juktas",
        "link": "http://pleiades.stoa.org/places/953163789/location-of-mount-juktas"
      }
    }
  ]
}