{
  "type": "FeatureCollection",
  "title": "Voley Castle",
  "id": "954446705",
  "bbox": [
    -3.9257802,
    51.1996882,
    -3.9257802,
    51.1996882
  ],
  "description": "Voley Castle is an Iron Age hill fort located in Devon, England, on a promontory on Heale Down.",
  "features": [
    {
      "type": "Feature",
      "geometry": {
        "type": "Point",
        "coordinates": [
          -3.9257802,
          51.1996882
        ]
      },
      "properties": {
        "description": "representative point"
      }
    },
    {
      "geometry": {
        "type": "Point",
        "coordinates": [
          -3.9257802,
          51.1996882
        ]
      },
      "id": "location-of-voley-castle",
      "type": "Feature",
      "properties": {
        "description": "Representative location based on OpenStreetMap.",
        "location_precision": "precise",
        "title": "OSM location of Voley Castle (Settlement)",
        "link": "http://pleiades.stoa.org/places/954446705/location-of-voley-castle"
      }
    }
  ]
}