{
  "type": "FeatureCollection",
  "title": "Belevi Tumulus",
  "id": "957064614",
  "bbox": [
    27.469106,
    38.014405,
    27.469106,
    38.014405
  ],
  "description": "The Belevi tumulus may date to the early Hellenistic period.",
  "features": [
    {
      "type": "Feature",
      "geometry": {
        "type": "Point",
        "coordinates": [
          27.469106,
          38.014405
        ]
      },
      "properties": {
        "description": "representative point"
      }
    },
    {
      "geometry": {
        "type": "Point",
        "coordinates": [
          27.469106,
          38.014405
        ]
      },
      "id": "imagery-location-of-belevi-tumulus",
      "type": "Feature",
      "properties": {
        "description": null,
        "location_precision": "precise",
        "title": "Imagery Location of Belevi Tumulus",
        "link": "http://pleiades.stoa.org/places/957064614/imagery-location-of-belevi-tumulus"
      }
    }
  ]
}