{
  "type": "FeatureCollection",
  "title": "Agora of Corinth",
  "id": "958275306",
  "description": "The Agora of ancient Corinth.",
  "bbox": [
    22.8793472,
    37.9049161,
    22.8793472,
    37.9049161
  ],
  "connectsWith": [
    "570182"
  ],
  "reprPoint": [
    22.8793472,
    37.9049161
  ],
  "features": [
    {
      "geometry": {
        "type": "Point",
        "coordinates": [
          22.8793472,
          37.9049161
        ]
      },
      "id": "location-of-agora",
      "type": "Feature",
      "properties": {
        "description": "Representative Location based on OpenStreetMap",
        "location_precision": "precise",
        "title": "OSM location of the ancient agora at Corinth",
        "link": "http://pleiades.stoa.org/places/958275306/location-of-agora"
      }
    }
  ]
}