{
  "type": "FeatureCollection",
  "title": "Theater at Stymphalos",
  "id": "958299306",
  "bbox": [
    22.4628726,
    37.8606852,
    22.4628726,
    37.8606852
  ],
  "description": "The remains of a rock-cut theater at Stymphalos.",
  "connectsWith": [
    "570696"
  ],
  "features": [
    {
      "type": "Feature",
      "geometry": {
        "type": "Point",
        "coordinates": [
          22.4628726,
          37.8606852
        ]
      },
      "properties": {
        "description": "representative point"
      }
    },
    {
      "geometry": {
        "type": "Point",
        "coordinates": [
          22.4628726,
          37.8606852
        ]
      },
      "id": "location-of-ancient-theater",
      "type": "Feature",
      "properties": {
        "description": "Representative location based on OpenStreetMap.",
        "location_precision": "precise",
        "title": "OSM location of ancient theater",
        "link": "http://pleiades.stoa.org/places/958299306/location-of-ancient-theater"
      }
    }
  ]
}