{
  "type": "FeatureCollection",
  "title": "Porta Asinaria",
  "id": "958548506",
  "bbox": [
    12.5086818,
    41.8856879,
    12.5086818,
    41.8856879
  ],
  "description": "The Porta Asinaria is a gate of the Aurelian Walls on the Caelian Hill, located immediately southwest of the Porta S. Giovanni.",
  "connectsWith": [
    "423025",
    "695491849",
    "529700371"
  ],
  "names": [
    "Porta Asinaria",
    "Porta Asinaria Lateranensis",
    "Porta San Giovanni"
  ],
  "features": [
    {
      "type": "Feature",
      "geometry": {
        "type": "Point",
        "coordinates": [
          12.5086818,
          41.8856879
        ]
      },
      "properties": {
        "description": "representative point"
      }
    },
    {
      "geometry": {
        "type": "Point",
        "coordinates": [
          12.5086818,
          41.8856879
        ]
      },
      "id": "osm-location",
      "type": "Feature",
      "properties": {
        "description": "Representative location based on a node derived from OpenStreetMap.",
        "location_precision": "precise",
        "title": "OSM location of  Porta Asinaria",
        "link": "http://pleiades.stoa.org/places/958548506/osm-location"
      }
    }
  ]
}