{
  "type": "FeatureCollection",
  "title": "Lagash",
  "id": "959120263",
  "bbox": [
    46.40836,
    31.4182,
    46.411,
    31.420485
  ],
  "description": "Lagash was an important Sumerian city of the late third millennium B.C.",
  "connectsWith": [
    "202833934"
  ],
  "names": [
    "Tall al Hibā",
    "Lagash"
  ],
  "features": [
    {
      "type": "Feature",
      "geometry": {
        "type": "Point",
        "coordinates": [
          46.40968,
          31.4193425
        ]
      },
      "properties": {
        "description": "representative point"
      }
    },
    {
      "geometry": {
        "type": "Point",
        "coordinates": [
          46.40836,
          31.420485
        ]
      },
      "id": "osm-location-of-tall-al-hiba",
      "type": "Feature",
      "properties": {
        "description": "Point representing the location of Tall al Hiba/Lagash, derived from an OSM node.",
        "location_precision": "precise",
        "title": "OSM location of Tall al Hiba",
        "link": "http://pleiades.stoa.org/places/959120263/osm-location-of-tall-al-hiba"
      }
    },
    {
      "geometry": {
        "type": "Point",
        "coordinates": [
          46.411,
          31.4182
        ]
      },
      "id": "cigs-location-of-tall-al-hiba",
      "type": "Feature",
      "properties": {
        "description": null,
        "location_precision": "precise",
        "title": "CIGS location of Tall al-Hibā",
        "link": "http://pleiades.stoa.org/places/959120263/cigs-location-of-tall-al-hiba"
      }
    }
  ]
}