{
  "type": "FeatureCollection",
  "title": "Kyrk tepe",
  "id": "961931",
  "description": "An ancient place, cited: BAtlas 98 C1 Kyrk tepe",
  "bbox": [
    62.185366,
    37.656669,
    62.185366,
    37.656669
  ],
  "reprPoint": [
    62.185366,
    37.656669
  ],
  "features": [
    {
      "geometry": {
        "type": "Point",
        "coordinates": [
          62.185366,
          37.656669
        ]
      },
      "id": "darmc-location-21208",
      "type": "Feature",
      "properties": {
        "description": "Point location",
        "location_precision": "precise",
        "title": "DARMC location 21208",
        "link": "http://pleiades.stoa.org/places/961931/darmc-location-21208"
      }
    }
  ]
}