{
  "type": "FeatureCollection",
  "title": "Serakhs",
  "id": "961963",
  "description": "An ancient place, cited: BAtlas 98 B2 Serakhs",
  "bbox": [
    61.149993,
    36.53333,
    61.149993,
    36.53333
  ],
  "reprPoint": [
    61.149993,
    36.53333
  ],
  "features": [
    {
      "geometry": {
        "type": "Point",
        "coordinates": [
          61.149993,
          36.53333
        ]
      },
      "id": "darmc-location-21216",
      "type": "Feature",
      "properties": {
        "description": "Point location",
        "location_precision": "precise",
        "title": "DARMC location 21216",
        "link": "http://pleiades.stoa.org/places/961963/darmc-location-21216"
      }
    }
  ]
}