{
  "type": "FeatureCollection",
  "title": "Palgird tepe",
  "id": "961950",
  "description": "An ancient place, cited: BAtlas 98 B4 Palgird tepe",
  "bbox": [
    61.272486,
    34.288468,
    61.272486,
    34.288468
  ],
  "reprPoint": [
    61.272486,
    34.288468
  ],
  "features": [
    {
      "geometry": {
        "type": "Point",
        "coordinates": [
          61.272486,
          34.288468
        ]
      },
      "id": "darmc-location-22984",
      "type": "Feature",
      "properties": {
        "description": "Point location",
        "location_precision": "precise",
        "title": "DARMC location 22984",
        "link": "http://pleiades.stoa.org/places/961950/darmc-location-22984"
      }
    }
  ]
}