{
  "type": "FeatureCollection",
  "title": "Pir-i Surkh",
  "id": "961952",
  "description": "An ancient place, cited: BAtlas 98 C4 Pir-i Surkh",
  "bbox": [
    62.401033,
    34.070519,
    62.401033,
    34.070519
  ],
  "reprPoint": [
    62.401033,
    34.070519
  ],
  "features": [
    {
      "geometry": {
        "type": "Point",
        "coordinates": [
          62.401033,
          34.070519
        ]
      },
      "id": "darmc-location-31213",
      "type": "Feature",
      "properties": {
        "description": "scale point location",
        "location_precision": "precise",
        "title": "DARMC location 31213",
        "link": "http://pleiades.stoa.org/places/961952/darmc-location-31213"
      }
    }
  ]
}