{
  "type": "FeatureCollection",
  "title": "Deshikli tepe",
  "id": "961900",
  "description": "An ancient place, cited: BAtlas 98 F1 Deshikli tepe",
  "bbox": [
    65.572855,
    37.573634,
    65.572855,
    37.573634
  ],
  "reprPoint": [
    65.572855,
    37.573634
  ],
  "features": [
    {
      "geometry": {
        "type": "Point",
        "coordinates": [
          65.572855,
          37.573634
        ]
      },
      "id": "darmc-location-22972",
      "type": "Feature",
      "properties": {
        "description": "Point location",
        "location_precision": "precise",
        "title": "DARMC location 22972",
        "link": "http://pleiades.stoa.org/places/961900/darmc-location-22972"
      }
    }
  ]
}