{
  "type": "FeatureCollection",
  "title": "Unnamed villa",
  "id": "963101202",
  "bbox": [
    14.725542,
    32.163878,
    14.725542,
    32.163878
  ],
  "description": "An unnamed villa of Tripolitana",
  "features": [
    {
      "type": "Feature",
      "geometry": {
        "type": "Point",
        "coordinates": [
          14.725542,
          32.163878
        ]
      },
      "properties": {
        "description": "representative point"
      }
    },
    {
      "geometry": {
        "type": "Point",
        "coordinates": [
          14.725542,
          32.163878
        ]
      },
      "id": "darmc-location-27008",
      "type": "Feature",
      "properties": {
        "description": "500K scale point location",
        "location_precision": "precise",
        "title": "DARMC location 27008",
        "link": "http://pleiades.stoa.org/places/963101202/darmc-location-27008"
      }
    }
  ]
}