{
  "type": "FeatureCollection",
  "title": "Unnamed villa",
  "id": "963101240",
  "bbox": [
    10.444693,
    33.152674,
    10.444693,
    33.152674
  ],
  "description": "An unnamed villa of Tripolitana",
  "features": [
    {
      "type": "Feature",
      "geometry": {
        "type": "Point",
        "coordinates": [
          10.444693,
          33.152674
        ]
      },
      "properties": {
        "description": "representative point"
      }
    },
    {
      "geometry": {
        "type": "Point",
        "coordinates": [
          10.444693,
          33.152674
        ]
      },
      "id": "darmc-location-26846",
      "type": "Feature",
      "properties": {
        "description": "500K scale point location",
        "location_precision": "precise",
        "title": "DARMC location 26846",
        "link": "http://pleiades.stoa.org/places/963101240/darmc-location-26846"
      }
    }
  ]
}