{
  "type": "FeatureCollection",
  "title": "Unnamed villa",
  "id": "963101283",
  "bbox": [
    10.515639,
    33.467614,
    10.515639,
    33.467614
  ],
  "description": "An unnamed villa of Tripolitana",
  "features": [
    {
      "type": "Feature",
      "geometry": {
        "type": "Point",
        "coordinates": [
          10.515639,
          33.467614
        ]
      },
      "properties": {
        "description": "representative point"
      }
    },
    {
      "geometry": {
        "type": "Point",
        "coordinates": [
          10.515639,
          33.467614
        ]
      },
      "id": "darmc-location-26854",
      "type": "Feature",
      "properties": {
        "description": "500K scale point location",
        "location_precision": "precise",
        "title": "DARMC location 26854",
        "link": "http://pleiades.stoa.org/places/963101283/darmc-location-26854"
      }
    }
  ]
}