{
  "type": "FeatureCollection",
  "title": "Fort at Great Wall of Gorgan",
  "id": "963101069",
  "bbox": [
    54.95516,
    37.238799,
    54.95516,
    37.238799
  ],
  "description": "One of the integral forts spaced along the wall",
  "features": [
    {
      "type": "Feature",
      "geometry": {
        "type": "Point",
        "coordinates": [
          54.95516,
          37.238799
        ]
      },
      "properties": {
        "description": "representative point"
      }
    },
    {
      "geometry": {
        "type": "Point",
        "coordinates": [
          54.95516,
          37.238799
        ]
      },
      "id": "darmc-location-32251",
      "type": "Feature",
      "properties": {
        "description": "  scale point location",
        "location_precision": "precise",
        "title": "DARMC location 32251",
        "link": "http://pleiades.stoa.org/places/963101069/darmc-location-32251"
      }
    }
  ]
}