{
  "type": "FeatureCollection",
  "title": "Unnamed villa",
  "id": "963100981",
  "description": "An unnamed villa from the Boreum region",
  "bbox": [
    19.723926,
    30.433596,
    19.723926,
    30.433596
  ],
  "reprPoint": [
    19.723926,
    30.433596
  ],
  "features": [
    {
      "geometry": {
        "type": "Point",
        "coordinates": [
          19.723926,
          30.433596
        ]
      },
      "id": "darmc-location-27055",
      "type": "Feature",
      "properties": {
        "description": "500K scale point location",
        "location_precision": "precise",
        "title": "DARMC location 27055",
        "link": "http://pleiades.stoa.org/places/963100981/darmc-location-27055"
      }
    }
  ]
}