{
  "type": "FeatureCollection",
  "title": "Mine of Laureion",
  "id": "963101151",
  "description": "An Athenian lead or silver mine",
  "bbox": [
    24.020489,
    37.730287,
    24.020489,
    37.730287
  ],
  "reprPoint": [
    24.020489,
    37.730287
  ],
  "features": [
    {
      "geometry": {
        "type": "Point",
        "coordinates": [
          24.020489,
          37.730287
        ]
      },
      "id": "darmc-location-31617",
      "type": "Feature",
      "properties": {
        "description": "scale point location",
        "location_precision": "precise",
        "title": "DARMC location 31617",
        "link": "http://pleiades.stoa.org/places/963101151/darmc-location-31617"
      }
    }
  ]
}