{
  "type": "FeatureCollection",
  "title": "Fort at Great Wall of Gorgan",
  "id": "963101062",
  "bbox": [
    54.514585,
    37.096402,
    54.514585,
    37.096402
  ],
  "description": "One of the interval forts spaced along the wall.",
  "connectsWith": [
    "942998"
  ],
  "features": [
    {
      "type": "Feature",
      "geometry": {
        "type": "Point",
        "coordinates": [
          54.514585,
          37.096402
        ]
      },
      "properties": {
        "description": "representative point"
      }
    },
    {
      "geometry": {
        "type": "Point",
        "coordinates": [
          54.514585,
          37.096402
        ]
      },
      "id": "darmc-location-32261",
      "type": "Feature",
      "properties": {
        "description": "representative point location digitized from the Barrington Atlas of the Greek and Roman World by the Digital Atlas of Roman and Medieval Civilizations project at Harvard University.",
        "location_precision": "precise",
        "title": "DARMC location 32261",
        "link": "http://pleiades.stoa.org/places/963101062/darmc-location-32261"
      }
    }
  ]
}