{
  "type": "FeatureCollection",
  "title": "Mine of Laureion",
  "id": "963101145",
  "description": "An Athenian lead or silver mine",
  "bbox": [
    24.059021,
    37.749797,
    24.059021,
    37.749797
  ],
  "reprPoint": [
    24.059021,
    37.749797
  ],
  "features": [
    {
      "geometry": {
        "type": "Point",
        "coordinates": [
          24.059021,
          37.749797
        ]
      },
      "id": "darmc-location-31607",
      "type": "Feature",
      "properties": {
        "description": "scale point location",
        "location_precision": "precise",
        "title": "DARMC location 31607",
        "link": "http://pleiades.stoa.org/places/963101145/darmc-location-31607"
      }
    }
  ]
}