{
  "type": "FeatureCollection",
  "title": "Unnamed place",
  "id": "963101001",
  "bbox": [
    16.522778,
    31.093273,
    16.522778,
    31.093273
  ],
  "description": "An unnamed monument, settlement, or villa of Syrtica",
  "features": [
    {
      "type": "Feature",
      "geometry": {
        "type": "Point",
        "coordinates": [
          16.522778,
          31.093273
        ]
      },
      "properties": {
        "description": "representative point"
      }
    },
    {
      "geometry": {
        "type": "Point",
        "coordinates": [
          16.522778,
          31.093273
        ]
      },
      "id": "darmc-location-27046",
      "type": "Feature",
      "properties": {
        "description": "500K scale point location",
        "location_precision": "precise",
        "title": "DARMC location 27046",
        "link": "http://pleiades.stoa.org/places/963101001/darmc-location-27046"
      }
    }
  ]
}