{
  "type": "FeatureCollection",
  "title": "Unnamed villa",
  "id": "963101397",
  "bbox": [
    20.088029,
    31.884864,
    20.088029,
    31.884864
  ],
  "description": "An unnamed villa of Cyrenaica",
  "features": [
    {
      "type": "Feature",
      "geometry": {
        "type": "Point",
        "coordinates": [
          20.088029,
          31.884864
        ]
      },
      "properties": {
        "description": "representative point"
      }
    },
    {
      "geometry": {
        "type": "Point",
        "coordinates": [
          20.088029,
          31.884864
        ]
      },
      "id": "darmc-location-27063",
      "type": "Feature",
      "properties": {
        "description": "500K scale point location",
        "location_precision": "precise",
        "title": "DARMC location 27063",
        "link": "http://pleiades.stoa.org/places/963101397/darmc-location-27063"
      }
    }
  ]
}