{
  "type": "FeatureCollection",
  "title": "Mine of Laureion",
  "id": "963101148",
  "description": "An Athenian lead or silver mine",
  "bbox": [
    24.034005,
    37.73085,
    24.034005,
    37.73085
  ],
  "reprPoint": [
    24.034005,
    37.73085
  ],
  "features": [
    {
      "geometry": {
        "type": "Point",
        "coordinates": [
          24.034005,
          37.73085
        ]
      },
      "id": "darmc-location-31614",
      "type": "Feature",
      "properties": {
        "description": "scale point location",
        "location_precision": "precise",
        "title": "DARMC location 31614",
        "link": "http://pleiades.stoa.org/places/963101148/darmc-location-31614"
      }
    }
  ]
}