{
  "type": "FeatureCollection",
  "title": "Unnamed villa",
  "id": "963101254",
  "bbox": [
    14.134671,
    32.281188,
    14.134671,
    32.281188
  ],
  "description": "An unnamed villa of Tripolitana",
  "features": [
    {
      "type": "Feature",
      "geometry": {
        "type": "Point",
        "coordinates": [
          14.134671,
          32.281188
        ]
      },
      "properties": {
        "description": "representative point"
      }
    },
    {
      "geometry": {
        "type": "Point",
        "coordinates": [
          14.134671,
          32.281188
        ]
      },
      "id": "darmc-location-26992",
      "type": "Feature",
      "properties": {
        "description": "500K scale point location",
        "location_precision": "precise",
        "title": "DARMC location 26992",
        "link": "http://pleiades.stoa.org/places/963101254/darmc-location-26992"
      }
    }
  ]
}