{
  "type": "FeatureCollection",
  "title": "Fort at Great Wall of Gorgan",
  "id": "963101060",
  "description": "One of the integral forts spaced along the wall",
  "bbox": [
    54.181021,
    37.133425,
    54.181021,
    37.133425
  ],
  "reprPoint": [
    54.181021,
    37.133425
  ],
  "features": [
    {
      "geometry": {
        "type": "Point",
        "coordinates": [
          54.181021,
          37.133425
        ]
      },
      "id": "darmc-location-32268",
      "type": "Feature",
      "properties": {
        "description": "scale point location",
        "location_precision": "precise",
        "title": "DARMC location 32268",
        "link": "http://pleiades.stoa.org/places/963101060/darmc-location-32268"
      }
    }
  ]
}