{
  "type": "FeatureCollection",
  "title": "Unnamed villa",
  "id": "963101208",
  "description": "An unnamed villa of Tripolitana",
  "bbox": [
    14.155222,
    32.707643,
    14.155222,
    32.707643
  ],
  "reprPoint": [
    14.155222,
    32.707643
  ],
  "features": [
    {
      "geometry": {
        "type": "Point",
        "coordinates": [
          14.155222,
          32.707643
        ]
      },
      "id": "darmc-location-27002",
      "type": "Feature",
      "properties": {
        "description": "500K scale point location",
        "location_precision": "precise",
        "title": "DARMC location 27002",
        "link": "http://pleiades.stoa.org/places/963101208/darmc-location-27002"
      }
    }
  ]
}