{
  "type": "FeatureCollection",
  "title": "Unnamed villa",
  "id": "963101246",
  "description": "An unnamed villa of Tripolitana",
  "bbox": [
    13.573437,
    31.390568,
    13.573437,
    31.390568
  ],
  "reprPoint": [
    13.573437,
    31.390568
  ],
  "features": [
    {
      "geometry": {
        "type": "Point",
        "coordinates": [
          13.573437,
          31.390568
        ]
      },
      "id": "darmc-location-26924",
      "type": "Feature",
      "properties": {
        "description": "500K scale point location",
        "location_precision": "precise",
        "title": "DARMC location 26924",
        "link": "http://pleiades.stoa.org/places/963101246/darmc-location-26924"
      }
    }
  ]
}