{
  "type": "FeatureCollection",
  "title": "Cemetery of the Garamantes",
  "id": "963101089",
  "bbox": [
    13.381442,
    26.53369,
    13.381442,
    26.53369
  ],
  "description": "Unnamed cemetery in the el-Agial escarpment",
  "features": [
    {
      "type": "Feature",
      "geometry": {
        "type": "Point",
        "coordinates": [
          13.381442,
          26.53369
        ]
      },
      "properties": {
        "description": "representative point"
      }
    },
    {
      "geometry": {
        "type": "Point",
        "coordinates": [
          13.381442,
          26.53369
        ]
      },
      "id": "darmc-location-33030",
      "type": "Feature",
      "properties": {
        "description": "  scale point location",
        "location_precision": "precise",
        "title": "DARMC location 33030",
        "link": "http://pleiades.stoa.org/places/963101089/darmc-location-33030"
      }
    }
  ]
}