{
  "type": "FeatureCollection",
  "title": "Unnamed villa",
  "id": "963101214",
  "bbox": [
    13.778204,
    31.699029,
    13.778204,
    31.699029
  ],
  "description": "An unnamed villa of Tripolitana",
  "features": [
    {
      "type": "Feature",
      "geometry": {
        "type": "Point",
        "coordinates": [
          13.778204,
          31.699029
        ]
      },
      "properties": {
        "description": "representative point"
      }
    },
    {
      "geometry": {
        "type": "Point",
        "coordinates": [
          13.778204,
          31.699029
        ]
      },
      "id": "darmc-location-26973",
      "type": "Feature",
      "properties": {
        "description": "500K scale point location",
        "location_precision": "precise",
        "title": "DARMC location 26973",
        "link": "http://pleiades.stoa.org/places/963101214/darmc-location-26973"
      }
    }
  ]
}