{
  "type": "FeatureCollection",
  "title": "Unnamed settlement",
  "id": "963100990",
  "description": "An unnamed settlement on Cercina or Cercinits islands",
  "bbox": [
    11.224399,
    34.781993,
    11.224399,
    34.781993
  ],
  "reprPoint": [
    11.224399,
    34.781993
  ],
  "features": [
    {
      "geometry": {
        "type": "Point",
        "coordinates": [
          11.224399,
          34.781993
        ]
      },
      "id": "darmc-location-20412",
      "type": "Feature",
      "properties": {
        "description": "500K scale point location",
        "location_precision": "precise",
        "title": "DARMC location 20412",
        "link": "http://pleiades.stoa.org/places/963100990/darmc-location-20412"
      }
    }
  ]
}