{
  "type": "FeatureCollection",
  "title": "Tower in R. Nestos Valley",
  "id": "963101026",
  "bbox": [
    24.586721,
    41.250488,
    24.586721,
    41.250488
  ],
  "description": "One of many towers or forts",
  "features": [
    {
      "type": "Feature",
      "geometry": {
        "type": "Point",
        "coordinates": [
          24.586721,
          41.250488
        ]
      },
      "properties": {
        "description": "representative point"
      }
    },
    {
      "geometry": {
        "type": "Point",
        "coordinates": [
          24.586721,
          41.250488
        ]
      },
      "id": "darmc-location-16658",
      "type": "Feature",
      "properties": {
        "description": "500K scale point location",
        "location_precision": "precise",
        "title": "DARMC location 16658",
        "link": "http://pleiades.stoa.org/places/963101026/darmc-location-16658"
      }
    }
  ]
}