{
  "type": "FeatureCollection",
  "title": "Unnamed villa",
  "id": "963101187",
  "bbox": [
    13.772976,
    32.669847,
    13.772976,
    32.669847
  ],
  "description": "An unnamed villa of Tripolitana",
  "features": [
    {
      "type": "Feature",
      "geometry": {
        "type": "Point",
        "coordinates": [
          13.772976,
          32.669847
        ]
      },
      "properties": {
        "description": "representative point"
      }
    },
    {
      "geometry": {
        "type": "Point",
        "coordinates": [
          13.772976,
          32.669847
        ]
      },
      "id": "darmc-location-26947",
      "type": "Feature",
      "properties": {
        "description": "500K scale point location",
        "location_precision": "precise",
        "title": "DARMC location 26947",
        "link": "http://pleiades.stoa.org/places/963101187/darmc-location-26947"
      }
    }
  ]
}