{
  "type": "FeatureCollection",
  "title": "Unnamed villa",
  "id": "963101273",
  "description": "An unnamed villa of Tripolitana",
  "bbox": [
    13.918535,
    32.501614,
    13.918535,
    32.501614
  ],
  "reprPoint": [
    13.918535,
    32.501614
  ],
  "features": [
    {
      "geometry": {
        "type": "Point",
        "coordinates": [
          13.918535,
          32.501614
        ]
      },
      "id": "darmc-location-26964",
      "type": "Feature",
      "properties": {
        "description": "500K scale point location",
        "location_precision": "precise",
        "title": "DARMC location 26964",
        "link": "http://pleiades.stoa.org/places/963101273/darmc-location-26964"
      }
    }
  ]
}