{
  "type": "FeatureCollection",
  "title": "Unnamed villa",
  "id": "963101239",
  "description": "An unnamed villa of Tripolitana",
  "bbox": [
    10.522032,
    33.131463,
    10.522032,
    33.131463
  ],
  "reprPoint": [
    10.522032,
    33.131463
  ],
  "features": [
    {
      "geometry": {
        "type": "Point",
        "coordinates": [
          10.522032,
          33.131463
        ]
      },
      "id": "darmc-location-26847",
      "type": "Feature",
      "properties": {
        "description": "500K scale point location",
        "location_precision": "precise",
        "title": "DARMC location 26847",
        "link": "http://pleiades.stoa.org/places/963101239/darmc-location-26847"
      }
    }
  ]
}