{
  "type": "FeatureCollection",
  "title": "Unnamed place",
  "id": "963101012",
  "description": "An unnamed monument, settlement, or villa of Syrtica",
  "bbox": [
    17.278424,
    30.79963,
    17.278424,
    30.79963
  ],
  "reprPoint": [
    17.278424,
    30.79963
  ],
  "features": [
    {
      "geometry": {
        "type": "Point",
        "coordinates": [
          17.278424,
          30.79963
        ]
      },
      "id": "darmc-location-20716",
      "type": "Feature",
      "properties": {
        "description": "500K scale point location",
        "location_precision": "precise",
        "title": "DARMC location 20716",
        "link": "http://pleiades.stoa.org/places/963101012/darmc-location-20716"
      }
    }
  ]
}