{
  "type": "FeatureCollection",
  "title": "Tower in R. Nestos Valley",
  "id": "963101035",
  "bbox": [
    24.718547,
    41.165168,
    24.718547,
    41.165168
  ],
  "description": "One of many towers or forts",
  "features": [
    {
      "type": "Feature",
      "geometry": {
        "type": "Point",
        "coordinates": [
          24.718547,
          41.165168
        ]
      },
      "properties": {
        "description": "representative point"
      }
    },
    {
      "geometry": {
        "type": "Point",
        "coordinates": [
          24.718547,
          41.165168
        ]
      },
      "id": "darmc-location-16664",
      "type": "Feature",
      "properties": {
        "description": "500K scale point location",
        "location_precision": "precise",
        "title": "DARMC location 16664",
        "link": "http://pleiades.stoa.org/places/963101035/darmc-location-16664"
      }
    }
  ]
}