{
  "type": "FeatureCollection",
  "title": "Unnamed villa",
  "id": "963101398",
  "description": "An unnamed villa of Cyrenaica",
  "bbox": [
    20.043114,
    31.873767,
    20.043114,
    31.873767
  ],
  "reprPoint": [
    20.043114,
    31.873767
  ],
  "features": [
    {
      "geometry": {
        "type": "Point",
        "coordinates": [
          20.043114,
          31.873767
        ]
      },
      "id": "darmc-location-27064",
      "type": "Feature",
      "properties": {
        "description": "500K scale point location",
        "location_precision": "precise",
        "title": "DARMC location 27064",
        "link": "http://pleiades.stoa.org/places/963101398/darmc-location-27064"
      }
    }
  ]
}