{
  "type": "FeatureCollection",
  "title": "Pass of the Alpes Graiae",
  "id": "963101022",
  "bbox": [
    6.0,
    45.21055,
    6.876693,
    45.216035
  ],
  "description": "A pass west of Segusio",
  "features": [
    {
      "type": "Feature",
      "geometry": {
        "type": "Point",
        "coordinates": [
          6.4383465,
          45.2132925
        ]
      },
      "properties": {
        "description": "representative point"
      }
    },
    {
      "geometry": {
        "type": "Point",
        "coordinates": [
          6.876693,
          45.216035
        ]
      },
      "id": "darmc-location-19587",
      "type": "Feature",
      "properties": {
        "description": "500K scale point location",
        "location_precision": "precise",
        "title": "DARMC location 19587",
        "link": "http://pleiades.stoa.org/places/963101022/darmc-location-19587"
      }
    },
    {
      "geometry": {
        "type": "Point",
        "coordinates": [
          6,
          45.21055
        ]
      },
      "id": "geohack-location-of-col-du-petit-mont-cenis",
      "type": "Feature",
      "properties": {
        "description": "Representative location following GeoHack",
        "location_precision": "precise",
        "title": "GeoHack location of Col du Petit Mont-Cenis",
        "link": "http://pleiades.stoa.org/places/963101022/geohack-location-of-col-du-petit-mont-cenis"
      }
    }
  ]
}