{
  "type": "FeatureCollection",
  "title": "Pass of the Alpes Graiae",
  "id": "963101022",
  "description": "A pass west of Segusio",
  "bbox": [
    6.876693,
    45.216035,
    6.876693,
    45.216035
  ],
  "reprPoint": [
    6.876693,
    45.216035
  ],
  "features": [
    {
      "geometry": {
        "type": "Point",
        "coordinates": [
          6.876693,
          45.216035
        ]
      },
      "id": "darmc-location-19587",
      "type": "Feature",
      "properties": {
        "description": "500K scale point location",
        "location_precision": "precise",
        "title": "DARMC location 19587",
        "link": "http://pleiades.stoa.org/places/963101022/darmc-location-19587"
      }
    }
  ]
}