{
  "type": "FeatureCollection",
  "title": "Unnamed villa",
  "id": "963101236",
  "description": "An unnamed villa of Tripolitana",
  "bbox": [
    10.074569,
    33.6993,
    10.074569,
    33.6993
  ],
  "reprPoint": [
    10.074569,
    33.6993
  ],
  "features": [
    {
      "geometry": {
        "type": "Point",
        "coordinates": [
          10.074569,
          33.6993
        ]
      },
      "id": "darmc-location-26842",
      "type": "Feature",
      "properties": {
        "description": "500K scale point location",
        "location_precision": "precise",
        "title": "DARMC location 26842",
        "link": "http://pleiades.stoa.org/places/963101236/darmc-location-26842"
      }
    }
  ]
}