{
  "type": "FeatureCollection",
  "title": "Unnamed villa",
  "id": "963101216",
  "description": "An unnamed villa of Tripolitana",
  "bbox": [
    14.060415,
    31.670373,
    14.060415,
    31.670373
  ],
  "reprPoint": [
    14.060415,
    31.670373
  ],
  "features": [
    {
      "geometry": {
        "type": "Point",
        "coordinates": [
          14.060415,
          31.670373
        ]
      },
      "id": "darmc-location-26975",
      "type": "Feature",
      "properties": {
        "description": "500K scale point location",
        "location_precision": "precise",
        "title": "DARMC location 26975",
        "link": "http://pleiades.stoa.org/places/963101216/darmc-location-26975"
      }
    }
  ]
}