{
  "type": "FeatureCollection",
  "title": "Unnamed villa",
  "id": "963101350",
  "bbox": [
    10.255832,
    33.672914,
    10.255832,
    33.672914
  ],
  "description": "An unnamed villa of Tripolitana",
  "features": [
    {
      "type": "Feature",
      "geometry": {
        "type": "Point",
        "coordinates": [
          10.255832,
          33.672914
        ]
      },
      "properties": {
        "description": "representative point"
      }
    },
    {
      "geometry": {
        "type": "Point",
        "coordinates": [
          10.255832,
          33.672914
        ]
      },
      "id": "darmc-location-26861",
      "type": "Feature",
      "properties": {
        "description": "500K scale point location",
        "location_precision": "precise",
        "title": "DARMC location 26861",
        "link": "http://pleiades.stoa.org/places/963101350/darmc-location-26861"
      }
    }
  ]
}