{
  "type": "FeatureCollection",
  "title": "Hafir near Meroe or Araba",
  "id": "963101117",
  "description": "A waterhole essential to the ancient Sudanese pastoral economy",
  "bbox": [
    33.290186,
    16.562993,
    33.290186,
    16.562993
  ],
  "reprPoint": [
    33.290186,
    16.562993
  ],
  "features": [
    {
      "geometry": {
        "type": "Point",
        "coordinates": [
          33.290186,
          16.562993
        ]
      },
      "id": "darmc-location-32344",
      "type": "Feature",
      "properties": {
        "description": "scale point location",
        "location_precision": "precise",
        "title": "DARMC location 32344",
        "link": "http://pleiades.stoa.org/places/963101117/darmc-location-32344"
      }
    }
  ]
}