{
  "type": "FeatureCollection",
  "title": "Unnamed villa",
  "id": "963101253",
  "description": "An unnamed villa of Tripolitana",
  "bbox": [
    14.235752,
    32.361372,
    14.235752,
    32.361372
  ],
  "reprPoint": [
    14.235752,
    32.361372
  ],
  "features": [
    {
      "geometry": {
        "type": "Point",
        "coordinates": [
          14.235752,
          32.361372
        ]
      },
      "id": "darmc-location-26993",
      "type": "Feature",
      "properties": {
        "description": "500K scale point location",
        "location_precision": "precise",
        "title": "DARMC location 26993",
        "link": "http://pleiades.stoa.org/places/963101253/darmc-location-26993"
      }
    }
  ]
}