{
  "type": "FeatureCollection",
  "title": "Unnamed villa",
  "id": "963101238",
  "bbox": [
    10.156599,
    33.697744,
    10.156599,
    33.697744
  ],
  "description": "An unnamed villa of Tripolitana",
  "features": [
    {
      "type": "Feature",
      "geometry": {
        "type": "Point",
        "coordinates": [
          10.156599,
          33.697744
        ]
      },
      "properties": {
        "description": "representative point"
      }
    },
    {
      "geometry": {
        "type": "Point",
        "coordinates": [
          10.156599,
          33.697744
        ]
      },
      "id": "darmc-location-26844",
      "type": "Feature",
      "properties": {
        "description": "500K scale point location",
        "location_precision": "precise",
        "title": "DARMC location 26844",
        "link": "http://pleiades.stoa.org/places/963101238/darmc-location-26844"
      }
    }
  ]
}