{
  "type": "FeatureCollection",
  "title": "Pass of the Alpes Graiae",
  "id": "963101023",
  "description": "A pass west of Segusio",
  "bbox": [
    6.651634,
    45.116858,
    6.651634,
    45.116858
  ],
  "reprPoint": [
    6.651634,
    45.116858
  ],
  "features": [
    {
      "geometry": {
        "type": "Point",
        "coordinates": [
          6.651634,
          45.116858
        ]
      },
      "id": "darmc-location-19582",
      "type": "Feature",
      "properties": {
        "description": "500K scale point location",
        "location_precision": "precise",
        "title": "DARMC location 19582",
        "link": "http://pleiades.stoa.org/places/963101023/darmc-location-19582"
      }
    }
  ]
}