{
  "type": "FeatureCollection",
  "title": "Unnamed villa",
  "id": "963101309",
  "description": "An unnamed villa of Tripolitana",
  "bbox": [
    14.478192,
    31.223659,
    14.478192,
    31.223659
  ],
  "reprPoint": [
    14.478192,
    31.223659
  ],
  "features": [
    {
      "geometry": {
        "type": "Point",
        "coordinates": [
          14.478192,
          31.223659
        ]
      },
      "id": "darmc-location-27026",
      "type": "Feature",
      "properties": {
        "description": "500K scale point location",
        "location_precision": "precise",
        "title": "DARMC location 27026",
        "link": "http://pleiades.stoa.org/places/963101309/darmc-location-27026"
      }
    }
  ]
}