{
  "type": "FeatureCollection",
  "title": "Mine of Laureion",
  "id": "963101164",
  "bbox": [
    24.031414,
    37.716263,
    24.031414,
    37.716263
  ],
  "description": "An Athenian lead or silver mine",
  "features": [
    {
      "type": "Feature",
      "geometry": {
        "type": "Point",
        "coordinates": [
          24.031414,
          37.716263
        ]
      },
      "properties": {
        "description": "representative point"
      }
    },
    {
      "geometry": {
        "type": "Point",
        "coordinates": [
          24.031414,
          37.716263
        ]
      },
      "id": "darmc-location-31626",
      "type": "Feature",
      "properties": {
        "description": "  scale point location",
        "location_precision": "precise",
        "title": "DARMC location 31626",
        "link": "http://pleiades.stoa.org/places/963101164/darmc-location-31626"
      }
    }
  ]
}