{
  "type": "FeatureCollection",
  "title": "Mine of Laureion",
  "id": "963101166",
  "description": "An Athenian lead or silver mine",
  "bbox": [
    24.026008,
    37.724655,
    24.026008,
    37.724655
  ],
  "reprPoint": [
    24.026008,
    37.724655
  ],
  "features": [
    {
      "geometry": {
        "type": "Point",
        "coordinates": [
          24.026008,
          37.724655
        ]
      },
      "id": "darmc-location-31620",
      "type": "Feature",
      "properties": {
        "description": "scale point location",
        "location_precision": "precise",
        "title": "DARMC location 31620",
        "link": "http://pleiades.stoa.org/places/963101166/darmc-location-31620"
      }
    }
  ]
}