{
  "type": "FeatureCollection",
  "title": "Unnamed villa",
  "id": "963101351",
  "description": "An unnamed villa of Tripolitana",
  "bbox": [
    10.516354,
    33.631538,
    10.516354,
    33.631538
  ],
  "reprPoint": [
    10.516354,
    33.631538
  ],
  "features": [
    {
      "geometry": {
        "type": "Point",
        "coordinates": [
          10.516354,
          33.631538
        ]
      },
      "id": "darmc-location-26860",
      "type": "Feature",
      "properties": {
        "description": "500K scale point location",
        "location_precision": "precise",
        "title": "DARMC location 26860",
        "link": "http://pleiades.stoa.org/places/963101351/darmc-location-26860"
      }
    }
  ]
}