{
  "type": "FeatureCollection",
  "title": "Unnamed villa",
  "id": "963101384",
  "description": "An unnamed villa of Cyrenaica",
  "bbox": [
    20.669945,
    32.525829,
    20.669945,
    32.525829
  ],
  "reprPoint": [
    20.669945,
    32.525829
  ],
  "features": [
    {
      "geometry": {
        "type": "Point",
        "coordinates": [
          20.669945,
          32.525829
        ]
      },
      "id": "darmc-location-27078",
      "type": "Feature",
      "properties": {
        "description": "500K scale point location",
        "location_precision": "precise",
        "title": "DARMC location 27078",
        "link": "http://pleiades.stoa.org/places/963101384/darmc-location-27078"
      }
    }
  ]
}