{
  "type": "FeatureCollection",
  "title": "Cemetery of the Garamantes",
  "id": "963101093",
  "bbox": [
    13.03516,
    26.629329,
    13.03516,
    26.629329
  ],
  "description": "Unnamed cemetery in the el-Agial escarpment",
  "features": [
    {
      "type": "Feature",
      "geometry": {
        "type": "Point",
        "coordinates": [
          13.03516,
          26.629329
        ]
      },
      "properties": {
        "description": "representative point"
      }
    },
    {
      "geometry": {
        "type": "Point",
        "coordinates": [
          13.03516,
          26.629329
        ]
      },
      "id": "darmc-location-33027",
      "type": "Feature",
      "properties": {
        "description": "  scale point location",
        "location_precision": "precise",
        "title": "DARMC location 33027",
        "link": "http://pleiades.stoa.org/places/963101093/darmc-location-33027"
      }
    }
  ]
}