{
  "type": "FeatureCollection",
  "title": "Unnamed villa",
  "id": "963101251",
  "description": "An unnamed villa of Tripolitana",
  "bbox": [
    13.447251,
    31.293993,
    13.447251,
    31.293993
  ],
  "reprPoint": [
    13.447251,
    31.293993
  ],
  "features": [
    {
      "geometry": {
        "type": "Point",
        "coordinates": [
          13.447251,
          31.293993
        ]
      },
      "id": "darmc-location-26921",
      "type": "Feature",
      "properties": {
        "description": "500K scale point location",
        "location_precision": "precise",
        "title": "DARMC location 26921",
        "link": "http://pleiades.stoa.org/places/963101251/darmc-location-26921"
      }
    }
  ]
}