{
  "type": "FeatureCollection",
  "title": "Mine of Laureion",
  "id": "963101158",
  "description": "An Athenian lead or silver mine",
  "bbox": [
    24.019835,
    37.706041,
    24.019835,
    37.706041
  ],
  "reprPoint": [
    24.019835,
    37.706041
  ],
  "features": [
    {
      "geometry": {
        "type": "Point",
        "coordinates": [
          24.019835,
          37.706041
        ]
      },
      "id": "darmc-location-19341",
      "type": "Feature",
      "properties": {
        "description": "500K scale point location",
        "location_precision": "precise",
        "title": "DARMC location 19341",
        "link": "http://pleiades.stoa.org/places/963101158/darmc-location-19341"
      }
    }
  ]
}