{
  "type": "FeatureCollection",
  "title": "Untitled",
  "id": "963101134",
  "bbox": [
    23.870608,
    38.080671,
    23.870608,
    38.080671
  ],
  "description": "An mine or quarry from a group on Pentelikon M.",
  "features": [
    {
      "type": "Feature",
      "geometry": {
        "type": "Point",
        "coordinates": [
          23.870608,
          38.080671
        ]
      },
      "properties": {
        "description": "representative point"
      }
    },
    {
      "geometry": {
        "type": "Point",
        "coordinates": [
          23.870608,
          38.080671
        ]
      },
      "id": "darmc-location-31565",
      "type": "Feature",
      "properties": {
        "description": "  scale point location",
        "location_precision": "precise",
        "title": "DARMC location 31565",
        "link": "http://pleiades.stoa.org/places/963101134/darmc-location-31565"
      }
    }
  ]
}