{
  "type": "FeatureCollection",
  "title": "Unnamed place",
  "id": "963101013",
  "description": "An unnamed monument, settlement, or villa of Syrtica",
  "bbox": [
    17.27419,
    30.893397,
    17.27419,
    30.893397
  ],
  "reprPoint": [
    17.27419,
    30.893397
  ],
  "features": [
    {
      "geometry": {
        "type": "Point",
        "coordinates": [
          17.27419,
          30.893397
        ]
      },
      "id": "darmc-location-20715",
      "type": "Feature",
      "properties": {
        "description": "500K scale point location",
        "location_precision": "precise",
        "title": "DARMC location 20715",
        "link": "http://pleiades.stoa.org/places/963101013/darmc-location-20715"
      }
    }
  ]
}