{
  "type": "FeatureCollection",
  "title": "Unnamed villa",
  "id": "963101281",
  "description": "An unnamed villa of Tripolitana",
  "bbox": [
    10.297761,
    33.546112,
    10.297761,
    33.546112
  ],
  "reprPoint": [
    10.297761,
    33.546112
  ],
  "features": [
    {
      "geometry": {
        "type": "Point",
        "coordinates": [
          10.297761,
          33.546112
        ]
      },
      "id": "darmc-location-26856",
      "type": "Feature",
      "properties": {
        "description": "500K scale point location",
        "location_precision": "precise",
        "title": "DARMC location 26856",
        "link": "http://pleiades.stoa.org/places/963101281/darmc-location-26856"
      }
    }
  ]
}