{
  "type": "FeatureCollection",
  "title": "Mine of Laureion",
  "id": "963101156",
  "bbox": [
    24.007198,
    37.729498,
    24.007198,
    37.729498
  ],
  "description": "An Athenian lead or silver mine",
  "features": [
    {
      "type": "Feature",
      "geometry": {
        "type": "Point",
        "coordinates": [
          24.007198,
          37.729498
        ]
      },
      "properties": {
        "description": "representative point"
      }
    },
    {
      "geometry": {
        "type": "Point",
        "coordinates": [
          24.007198,
          37.729498
        ]
      },
      "id": "darmc-location-31618",
      "type": "Feature",
      "properties": {
        "description": "  scale point location",
        "location_precision": "precise",
        "title": "DARMC location 31618",
        "link": "http://pleiades.stoa.org/places/963101156/darmc-location-31618"
      }
    }
  ]
}