{
  "type": "FeatureCollection",
  "title": "Unnamed villa",
  "id": "963101371",
  "description": "An unnamed villa of Tripolitana",
  "bbox": [
    11.002524,
    33.757443,
    11.002524,
    33.757443
  ],
  "reprPoint": [
    11.002524,
    33.757443
  ],
  "features": [
    {
      "geometry": {
        "type": "Point",
        "coordinates": [
          11.002524,
          33.757443
        ]
      },
      "id": "darmc-location-26892",
      "type": "Feature",
      "properties": {
        "description": "500K scale point location",
        "location_precision": "precise",
        "title": "DARMC location 26892",
        "link": "http://pleiades.stoa.org/places/963101371/darmc-location-26892"
      }
    }
  ]
}