{
  "type": "FeatureCollection",
  "title": "Unnamed villa",
  "id": "963101338",
  "bbox": [
    13.248589,
    31.969327,
    13.248589,
    31.969327
  ],
  "description": "An unnamed villa of Tripolitana",
  "features": [
    {
      "type": "Feature",
      "geometry": {
        "type": "Point",
        "coordinates": [
          13.248589,
          31.969327
        ]
      },
      "properties": {
        "description": "representative point"
      }
    },
    {
      "geometry": {
        "type": "Point",
        "coordinates": [
          13.248589,
          31.969327
        ]
      },
      "id": "darmc-location-26905",
      "type": "Feature",
      "properties": {
        "description": "500K scale point location",
        "location_precision": "precise",
        "title": "DARMC location 26905",
        "link": "http://pleiades.stoa.org/places/963101338/darmc-location-26905"
      }
    }
  ]
}