{
  "type": "FeatureCollection",
  "title": "Unnamed villa",
  "id": "963101315",
  "description": "An unnamed villa of Tripolitana",
  "bbox": [
    14.442316,
    31.123155,
    14.442316,
    31.123155
  ],
  "reprPoint": [
    14.442316,
    31.123155
  ],
  "features": [
    {
      "geometry": {
        "type": "Point",
        "coordinates": [
          14.442316,
          31.123155
        ]
      },
      "id": "darmc-location-27028",
      "type": "Feature",
      "properties": {
        "description": "500K scale point location",
        "location_precision": "precise",
        "title": "DARMC location 27028",
        "link": "http://pleiades.stoa.org/places/963101315/darmc-location-27028"
      }
    }
  ]
}