{
  "type": "FeatureCollection",
  "title": "Unnamed villa",
  "id": "963101235",
  "description": "An unnamed villa of Tripolitana",
  "bbox": [
    10.048216,
    33.639439,
    10.048216,
    33.639439
  ],
  "reprPoint": [
    10.048216,
    33.639439
  ],
  "features": [
    {
      "geometry": {
        "type": "Point",
        "coordinates": [
          10.048216,
          33.639439
        ]
      },
      "id": "darmc-location-26843",
      "type": "Feature",
      "properties": {
        "description": "500K scale point location",
        "location_precision": "precise",
        "title": "DARMC location 26843",
        "link": "http://pleiades.stoa.org/places/963101235/darmc-location-26843"
      }
    }
  ]
}