{
  "type": "FeatureCollection",
  "title": "Unnamed villa",
  "id": "963101231",
  "description": "An unnamed villa of Tripolitana",
  "bbox": [
    13.289893,
    31.70409,
    13.289893,
    31.70409
  ],
  "reprPoint": [
    13.289893,
    31.70409
  ],
  "features": [
    {
      "geometry": {
        "type": "Point",
        "coordinates": [
          13.289893,
          31.70409
        ]
      },
      "id": "darmc-location-26908",
      "type": "Feature",
      "properties": {
        "description": "500K scale point location",
        "location_precision": "precise",
        "title": "DARMC location 26908",
        "link": "http://pleiades.stoa.org/places/963101231/darmc-location-26908"
      }
    }
  ]
}