{
  "type": "FeatureCollection",
  "title": "Fort at Great Wall of Gorgan",
  "id": "963101062",
  "description": "One of the integral forts spaced along the wall",
  "bbox": [
    54.514585,
    37.096402,
    54.514585,
    37.096402
  ],
  "reprPoint": [
    54.514585,
    37.096402
  ],
  "features": [
    {
      "geometry": {
        "type": "Point",
        "coordinates": [
          54.514585,
          37.096402
        ]
      },
      "id": "darmc-location-32261",
      "type": "Feature",
      "properties": {
        "description": "scale point location",
        "location_precision": "precise",
        "title": "DARMC location 32261",
        "link": "http://pleiades.stoa.org/places/963101062/darmc-location-32261"
      }
    }
  ]
}