{
  "type": "FeatureCollection",
  "title": "Unnamed villa",
  "id": "963101198",
  "description": "An unnamed villa of Tripolitana",
  "bbox": [
    13.413393,
    31.760237,
    13.413393,
    31.760237
  ],
  "reprPoint": [
    13.413393,
    31.760237
  ],
  "features": [
    {
      "geometry": {
        "type": "Point",
        "coordinates": [
          13.413393,
          31.760237
        ]
      },
      "id": "darmc-location-26931",
      "type": "Feature",
      "properties": {
        "description": "500K scale point location",
        "location_precision": "precise",
        "title": "DARMC location 26931",
        "link": "http://pleiades.stoa.org/places/963101198/darmc-location-26931"
      }
    }
  ]
}