{
  "type": "FeatureCollection",
  "title": "Unnamed Mine",
  "id": "963101127",
  "description": "An unnamed mine in the Midlands",
  "bbox": [
    -0.391964,
    52.70956,
    -0.391964,
    52.70956
  ],
  "reprPoint": [
    -0.391964,
    52.70956
  ],
  "features": [
    {
      "geometry": {
        "type": "Point",
        "coordinates": [
          -0.391964,
          52.70956
        ]
      },
      "id": "darmc-location-29446",
      "type": "Feature",
      "properties": {
        "description": "500K scale point location",
        "location_precision": "precise",
        "title": "DARMC location 29446",
        "link": "http://pleiades.stoa.org/places/963101127/darmc-location-29446"
      }
    }
  ]
}