{
  "type": "FeatureCollection",
  "title": "Untitled",
  "id": "963101132",
  "bbox": [
    23.874413,
    38.075264,
    23.874413,
    38.075264
  ],
  "description": "An mine or quarry from a group on Pentelikon M.",
  "connectsWith": [
    "580065"
  ],
  "features": [
    {
      "type": "Feature",
      "geometry": {
        "type": "Point",
        "coordinates": [
          23.874413,
          38.075264
        ]
      },
      "properties": {
        "description": "representative point"
      }
    },
    {
      "geometry": {
        "type": "Point",
        "coordinates": [
          23.874413,
          38.075264
        ]
      },
      "id": "darmc-location-31567",
      "type": "Feature",
      "properties": {
        "description": "representative point location digitized from the Barrington Atlas of the Greek and Roman World by the Digital Atlas of Roman and Medieval Civilizations project at Harvard University.",
        "location_precision": "precise",
        "title": "DARMC location 31567",
        "link": "http://pleiades.stoa.org/places/963101132/darmc-location-31567"
      }
    }
  ]
}