{
  "type": "FeatureCollection",
  "title": "tribus Poblilia",
  "id": "964333742",
  "bbox": [
    12.486137,
    41.8917,
    12.4862,
    41.891775
  ],
  "description": "Tribus Poblilia was a later rural tribe of Rome, which was established in 358 B.C.",
  "connectsWith": [
    "432900",
    "423025"
  ],
  "names": [
    "Publilia"
  ],
  "features": [
    {
      "type": "Feature",
      "geometry": {
        "type": "Point",
        "coordinates": [
          12.4861685,
          41.8917375
        ]
      },
      "properties": {
        "description": "representative point"
      }
    }
  ]
}