{
  "type": "FeatureCollection",
  "title": "Sapinuwa",
  "id": "964671598",
  "description": "Bronze Age Hittite city at the location of modern Ortaköy, Turkey",
  "bbox": [
    35.25,
    40.266667,
    35.25,
    40.266667
  ],
  "reprPoint": [
    35.25,
    40.266667
  ],
  "features": [
    {
      "geometry": {
        "type": "Point",
        "coordinates": [
          35.25,
          40.266667
        ]
      },
      "id": "sapinuwa",
      "type": "Feature",
      "properties": {
        "description": "After Wikipedia, which places the site to the south of the modern city of Ortaköy. Verified in Google Earth, wherein it should be noticed, there are no obvious archaeological remains to be seen in the vicinity of the point.",
        "location_precision": "precise",
        "title": "Location of Sapinuwa",
        "link": "http://pleiades.stoa.org/places/964671598/sapinuwa"
      }
    }
  ]
}