{
  "type": "FeatureCollection",
  "title": "Arapsu Bridge",
  "id": "965247252",
  "bbox": [
    30.659346,
    36.880906,
    30.659346,
    36.880906
  ],
  "description": "A Roman bridge near Antalya, Turkey.",
  "features": [
    {
      "type": "Feature",
      "geometry": {
        "type": "Point",
        "coordinates": [
          30.659346,
          36.880906
        ]
      },
      "properties": {
        "description": "representative point"
      }
    },
    {
      "geometry": {
        "type": "Point",
        "coordinates": [
          30.659346,
          36.880906
        ]
      },
      "id": "location-of-arapsu-bridge",
      "type": "Feature",
      "properties": {
        "description": "Representative location based on GeoHack.",
        "location_precision": "precise",
        "title": "GeoHack location of Arapsu Bridge",
        "link": "http://pleiades.stoa.org/places/965247252/location-of-arapsu-bridge"
      }
    }
  ]
}