{
  "type": "FeatureCollection",
  "title": "Varaha Cave",
  "id": "965370150",
  "bbox": [
    80.1922234,
    12.6180857,
    80.1922234,
    12.6180857
  ],
  "description": "The modern name of a seventh-century Pallava cave temple in Mahābalipuram.",
  "connectsWith": [
    "835093310"
  ],
  "names": [
    "Varaha Cave"
  ],
  "features": [
    {
      "type": "Feature",
      "geometry": {
        "type": "Point",
        "coordinates": [
          80.1922234,
          12.6180857
        ]
      },
      "properties": {
        "description": "representative point"
      }
    },
    {
      "geometry": {
        "type": "Point",
        "coordinates": [
          80.1922234,
          12.6180857
        ]
      },
      "id": "representative-point-derived-from-an-openstreetmap",
      "type": "Feature",
      "properties": {
        "description": "Location based on OpenStreetMap",
        "location_precision": "precise",
        "title": "Representative point derived from an OpenStreetMap node",
        "link": "http://pleiades.stoa.org/places/965370150/representative-point-derived-from-an-openstreetmap"
      }
    }
  ]
}