{
  "type": "FeatureCollection",
  "title": "Korucutepe",
  "id": "966705384",
  "bbox": [
    39.53657,
    38.636943,
    39.53657,
    38.636943
  ],
  "description": "An ancient settlement in the Altınova plain (eastern Anatolia). The site was flooded by the construction of the Keban Dam in 1974.",
  "names": [
    "Korucutepe"
  ],
  "features": [
    {
      "type": "Feature",
      "geometry": {
        "type": "Point",
        "coordinates": [
          39.53657,
          38.636943
        ]
      },
      "properties": {
        "description": "representative point"
      }
    },
    {
      "geometry": {
        "type": "Point",
        "coordinates": [
          39.53657,
          38.636943
        ]
      },
      "id": "location-of-korucutepe",
      "type": "Feature",
      "properties": {
        "description": "Approximate, representative location of the site of Korucutepe prior to its flooding, after van Loon 1975-1980. ",
        "location_precision": "precise",
        "title": "Approximate representative location of Korucutepe",
        "link": "http://pleiades.stoa.org/places/966705384/location-of-korucutepe"
      }
    }
  ]
}