{
  "type": "FeatureCollection",
  "title": "Milecastle 5 (Quarry House)",
  "id": "967060354",
  "bbox": [
    -1.62898,
    54.971409,
    -1.62898,
    54.971409
  ],
  "description": "A milecastle situated on Hadrian's Wall.",
  "connectsWith": [
    "91358"
  ],
  "features": [
    {
      "type": "Feature",
      "geometry": {
        "type": "Point",
        "coordinates": [
          -1.62898,
          54.971409
        ]
      },
      "properties": {
        "description": "representative point"
      }
    },
    {
      "geometry": {
        "type": "Point",
        "coordinates": [
          -1.62898,
          54.971409
        ]
      },
      "id": "center-point-of-the-ancient-site",
      "type": "Feature",
      "properties": {
        "description": null,
        "location_precision": "precise",
        "title": "Center point of the ancient site",
        "link": "http://pleiades.stoa.org/places/967060354/center-point-of-the-ancient-site"
      }
    }
  ]
}