{
  "type": "FeatureCollection",
  "title": "Milecastle 12 (Heddon)",
  "id": "967060410",
  "bbox": [
    -1.789823,
    54.996999,
    -1.789823,
    54.996999
  ],
  "description": "A milecastle situated on Hadrian's Wall.",
  "connectsWith": [
    "91358"
  ],
  "features": [
    {
      "type": "Feature",
      "geometry": {
        "type": "Point",
        "coordinates": [
          -1.789823,
          54.996999
        ]
      },
      "properties": {
        "description": "representative point"
      }
    },
    {
      "geometry": {
        "type": "Point",
        "coordinates": [
          -1.789823,
          54.996999
        ]
      },
      "id": "center-point-of-the-ancient-site",
      "type": "Feature",
      "properties": {
        "description": null,
        "location_precision": "precise",
        "title": "Center point of the ancient site",
        "link": "http://pleiades.stoa.org/places/967060410/center-point-of-the-ancient-site"
      }
    }
  ]
}