{
  "type": "FeatureCollection",
  "title": "Turret 55B (Townhead Croft)",
  "id": "967060245",
  "bbox": [
    -2.740968,
    54.971377,
    -2.740968,
    54.971377
  ],
  "description": "A turret situated on Hadrian's Wall.",
  "connectsWith": [
    "91358"
  ],
  "features": [
    {
      "type": "Feature",
      "geometry": {
        "type": "Point",
        "coordinates": [
          -2.740968,
          54.971377
        ]
      },
      "properties": {
        "description": "representative point"
      }
    },
    {
      "geometry": {
        "type": "Point",
        "coordinates": [
          -2.740968,
          54.971377
        ]
      },
      "id": "center-point-of-the-ancient-site",
      "type": "Feature",
      "properties": {
        "description": null,
        "location_precision": "precise",
        "title": "Center point of the ancient site",
        "link": "http://pleiades.stoa.org/places/967060245/center-point-of-the-ancient-site"
      }
    }
  ]
}