{
  "type": "FeatureCollection",
  "title": "Turret 47A (Foultown)",
  "id": "967060338",
  "description": "A turret situated on Hadrian's Wall.",
  "bbox": [
    -2.557659,
    54.988711,
    -2.557659,
    54.988711
  ],
  "reprPoint": [
    -2.557659,
    54.988711
  ],
  "features": [
    {
      "geometry": {
        "type": "Point",
        "coordinates": [
          -2.557659,
          54.988711
        ]
      },
      "id": "center-point-of-the-ancient-site",
      "type": "Feature",
      "properties": {
        "description": null,
        "location_precision": "precise",
        "title": "Center point of the ancient site",
        "link": "http://pleiades.stoa.org/places/967060338/center-point-of-the-ancient-site"
      }
    }
  ]
}