{
  "type": "FeatureCollection",
  "title": "Turret 1B",
  "id": "967060288",
  "bbox": [
    -1.56325,
    54.9808,
    -1.56325,
    54.9808
  ],
  "description": "A turret situated on Hadrian's Wall.",
  "connectsWith": [
    "91358"
  ],
  "features": [
    {
      "type": "Feature",
      "geometry": {
        "type": "Point",
        "coordinates": [
          -1.56325,
          54.9808
        ]
      },
      "properties": {
        "description": "representative point"
      }
    },
    {
      "geometry": {
        "type": "Point",
        "coordinates": [
          -1.56325,
          54.9808
        ]
      },
      "id": "center-point-of-the-ancient-site",
      "type": "Feature",
      "properties": {
        "description": null,
        "location_precision": "precise",
        "title": "Center point of the ancient site",
        "link": "http://pleiades.stoa.org/places/967060288/center-point-of-the-ancient-site"
      }
    }
  ]
}