{
  "type": "FeatureCollection",
  "title": "Milecastle 65 (Tarraby)",
  "id": "967060434",
  "description": "A milecastle situated on Hadrian's Wall.",
  "bbox": [
    -2.92411,
    54.912609,
    -2.92411,
    54.912609
  ],
  "reprPoint": [
    -2.92411,
    54.912609
  ],
  "features": [
    {
      "geometry": {
        "type": "Point",
        "coordinates": [
          -2.92411,
          54.912609
        ]
      },
      "id": "center-point-of-the-ancient-site",
      "type": "Feature",
      "properties": {
        "description": null,
        "location_precision": "precise",
        "title": "Center point of the ancient site",
        "link": "http://pleiades.stoa.org/places/967060434/center-point-of-the-ancient-site"
      }
    }
  ]
}