{
  "type": "FeatureCollection",
  "title": "Turret 46B (Wallend)",
  "id": "967060340",
  "bbox": [
    -2.541861,
    54.987704,
    -2.541861,
    54.987704
  ],
  "description": "A turret situated on Hadrian's Wall.",
  "connectsWith": [
    "91358"
  ],
  "features": [
    {
      "type": "Feature",
      "geometry": {
        "type": "Point",
        "coordinates": [
          -2.541861,
          54.987704
        ]
      },
      "properties": {
        "description": "representative point"
      }
    },
    {
      "geometry": {
        "type": "Point",
        "coordinates": [
          -2.541861,
          54.987704
        ]
      },
      "id": "center-point-of-the-ancient-site",
      "type": "Feature",
      "properties": {
        "description": null,
        "location_precision": "precise",
        "title": "Center point of the ancient site",
        "link": "http://pleiades.stoa.org/places/967060340/center-point-of-the-ancient-site"
      }
    }
  ]
}