{
  "type": "FeatureCollection",
  "title": "Turret 58B",
  "id": "967060263",
  "description": "A turret situated on Hadrian's Wall.",
  "bbox": [
    -2.797387,
    54.949003,
    -2.797387,
    54.949003
  ],
  "reprPoint": [
    -2.797387,
    54.949003
  ],
  "features": [
    {
      "geometry": {
        "type": "Point",
        "coordinates": [
          -2.797387,
          54.949003
        ]
      },
      "id": "center-point-of-the-ancient-site",
      "type": "Feature",
      "properties": {
        "description": null,
        "location_precision": "precise",
        "title": "Center point of the ancient site",
        "link": "http://pleiades.stoa.org/places/967060263/center-point-of-the-ancient-site"
      }
    }
  ]
}