{
  "type": "FeatureCollection",
  "title": "Milecastle 50 (Turf Wall) (High House)",
  "id": "967060310",
  "description": "A milecastle situated on Hadrian's Wall.",
  "bbox": [
    -2.615434,
    54.985556,
    -2.615434,
    54.985556
  ],
  "reprPoint": [
    -2.615434,
    54.985556
  ],
  "features": [
    {
      "geometry": {
        "type": "Point",
        "coordinates": [
          -2.615434,
          54.985556
        ]
      },
      "id": "center-point-of-the-ancient-site",
      "type": "Feature",
      "properties": {
        "description": null,
        "location_precision": "precise",
        "title": "Center point of the ancient site",
        "link": "http://pleiades.stoa.org/places/967060310/center-point-of-the-ancient-site"
      }
    }
  ]
}