{
  "type": "FeatureCollection",
  "title": "Turret 49B (Turf Wall)",
  "id": "967060308",
  "bbox": [
    -2.608748,
    54.987747,
    -2.608748,
    54.987747
  ],
  "description": "A turret situated on Hadrian's Wall.",
  "connectsWith": [
    "91358"
  ],
  "features": [
    {
      "type": "Feature",
      "geometry": {
        "type": "Point",
        "coordinates": [
          -2.608748,
          54.987747
        ]
      },
      "properties": {
        "description": "representative point"
      }
    },
    {
      "geometry": {
        "type": "Point",
        "coordinates": [
          -2.608748,
          54.987747
        ]
      },
      "id": "center-point-of-the-ancient-site",
      "type": "Feature",
      "properties": {
        "description": null,
        "location_precision": "precise",
        "title": "Center point of the ancient site",
        "link": "http://pleiades.stoa.org/places/967060308/center-point-of-the-ancient-site"
      }
    }
  ]
}