{
  "type": "FeatureCollection",
  "title": "Turret 14B",
  "id": "967060402",
  "bbox": [
    -1.849516,
    55.004693,
    -1.849516,
    55.004693
  ],
  "description": "A turret situated on Hadrian's Wall.",
  "connectsWith": [
    "91358"
  ],
  "features": [
    {
      "type": "Feature",
      "geometry": {
        "type": "Point",
        "coordinates": [
          -1.849516,
          55.004693
        ]
      },
      "properties": {
        "description": "representative point"
      }
    },
    {
      "geometry": {
        "type": "Point",
        "coordinates": [
          -1.849516,
          55.004693
        ]
      },
      "id": "center-point-of-the-ancient-site",
      "type": "Feature",
      "properties": {
        "description": null,
        "location_precision": "precise",
        "title": "Center point of the ancient site",
        "link": "http://pleiades.stoa.org/places/967060402/center-point-of-the-ancient-site"
      }
    }
  ]
}