{
  "type": "FeatureCollection",
  "title": "Milecastle 6 (Benwell Grove)",
  "id": "967060357",
  "description": "A milecastle situated on Hadrian's Wall.",
  "bbox": [
    -1.652321,
    54.975308,
    -1.652321,
    54.975308
  ],
  "reprPoint": [
    -1.652321,
    54.975308
  ],
  "features": [
    {
      "geometry": {
        "type": "Point",
        "coordinates": [
          -1.652321,
          54.975308
        ]
      },
      "id": "center-point-of-the-ancient-site",
      "type": "Feature",
      "properties": {
        "description": null,
        "location_precision": "precise",
        "title": "Center point of the ancient site",
        "link": "http://pleiades.stoa.org/places/967060357/center-point-of-the-ancient-site"
      }
    }
  ]
}