{
  "type": "FeatureCollection",
  "title": "Turret 55A (Dovecote)",
  "id": "967060236",
  "description": "A turret situated on Hadrian's Wall.",
  "bbox": [
    -2.734101,
    54.971688,
    -2.734101,
    54.971688
  ],
  "reprPoint": [
    -2.734101,
    54.971688
  ],
  "features": [
    {
      "geometry": {
        "type": "Point",
        "coordinates": [
          -2.734101,
          54.971688
        ]
      },
      "id": "center-point-of-the-ancient-site",
      "type": "Feature",
      "properties": {
        "description": null,
        "location_precision": "precise",
        "title": "Center point of the ancient site",
        "link": "http://pleiades.stoa.org/places/967060236/center-point-of-the-ancient-site"
      }
    }
  ]
}