{
  "type": "FeatureCollection",
  "title": "Milecastle 7 (Benwell Bank)",
  "id": "967060352",
  "description": "A milecastle situated on Hadrian's Wall.",
  "bbox": [
    -1.676078,
    54.980295,
    -1.676078,
    54.980295
  ],
  "reprPoint": [
    -1.676078,
    54.980295
  ],
  "features": [
    {
      "geometry": {
        "type": "Point",
        "coordinates": [
          -1.676078,
          54.980295
        ]
      },
      "id": "center-point-of-the-ancient-site",
      "type": "Feature",
      "properties": {
        "description": null,
        "location_precision": "precise",
        "title": "Center point of the ancient site",
        "link": "http://pleiades.stoa.org/places/967060352/center-point-of-the-ancient-site"
      }
    }
  ]
}