{
  "type": "FeatureCollection",
  "title": "Milecastle 41 (Melkridge)",
  "id": "967060392",
  "description": "A milecastle situated on Hadrian's Wall.",
  "bbox": [
    -2.423193,
    54.997341,
    -2.423193,
    54.997341
  ],
  "reprPoint": [
    -2.423193,
    54.997341
  ],
  "features": [
    {
      "geometry": {
        "type": "Point",
        "coordinates": [
          -2.423193,
          54.997341
        ]
      },
      "id": "center-point-of-the-ancient-site",
      "type": "Feature",
      "properties": {
        "description": null,
        "location_precision": "precise",
        "title": "Center point of the ancient site",
        "link": "http://pleiades.stoa.org/places/967060392/center-point-of-the-ancient-site"
      }
    }
  ]
}