{
  "type": "FeatureCollection",
  "title": "Milecastle 3 (Ouseburn)",
  "id": "967060312",
  "description": "A milecastle situated on Hadrian's Wall.",
  "bbox": [
    -1.589022,
    54.975908,
    -1.589022,
    54.975908
  ],
  "reprPoint": [
    -1.589022,
    54.975908
  ],
  "features": [
    {
      "geometry": {
        "type": "Point",
        "coordinates": [
          -1.589022,
          54.975908
        ]
      },
      "id": "center-point-of-the-ancient-site",
      "type": "Feature",
      "properties": {
        "description": null,
        "location_precision": "precise",
        "title": "Center point of the ancient site",
        "link": "http://pleiades.stoa.org/places/967060312/center-point-of-the-ancient-site"
      }
    }
  ]
}