{
  "type": "FeatureCollection",
  "title": "Turret 40A (Winshields)",
  "id": "967060400",
  "description": "A turret situated on Hadrian's Wall.",
  "bbox": [
    -2.40776,
    55.001527,
    -2.40776,
    55.001527
  ],
  "reprPoint": [
    -2.40776,
    55.001527
  ],
  "features": [
    {
      "geometry": {
        "type": "Point",
        "coordinates": [
          -2.40776,
          55.001527
        ]
      },
      "id": "center-point-of-the-ancient-site",
      "type": "Feature",
      "properties": {
        "description": null,
        "location_precision": "precise",
        "title": "Center point of the ancient site",
        "link": "http://pleiades.stoa.org/places/967060400/center-point-of-the-ancient-site"
      }
    }
  ]
}