{
  "type": "FeatureCollection",
  "title": "Milecastle 77 (Raven Bank)",
  "id": "967060324",
  "description": "A milecastle situated on Hadrian's Wall.",
  "bbox": [
    -3.161714,
    54.935283,
    -3.161714,
    54.935283
  ],
  "reprPoint": [
    -3.161714,
    54.935283
  ],
  "features": [
    {
      "geometry": {
        "type": "Point",
        "coordinates": [
          -3.161714,
          54.935283
        ]
      },
      "id": "center-point-of-the-ancient-site",
      "type": "Feature",
      "properties": {
        "description": null,
        "location_precision": "precise",
        "title": "Center point of the ancient site",
        "link": "http://pleiades.stoa.org/places/967060324/center-point-of-the-ancient-site"
      }
    }
  ]
}