{
  "type": "FeatureCollection",
  "title": "Turret 19B (West Clarewood)",
  "id": "967060223",
  "description": "A turret situated on Hadrian's Wall.",
  "bbox": [
    -1.964405,
    55.012361,
    -1.964405,
    55.012361
  ],
  "reprPoint": [
    -1.964405,
    55.012361
  ],
  "features": [
    {
      "geometry": {
        "type": "Point",
        "coordinates": [
          -1.964405,
          55.012361
        ]
      },
      "id": "center-point-of-the-ancient-site",
      "type": "Feature",
      "properties": {
        "description": null,
        "location_precision": "precise",
        "title": "Center point of the ancient site",
        "link": "http://pleiades.stoa.org/places/967060223/center-point-of-the-ancient-site"
      }
    }
  ]
}