{
  "type": "FeatureCollection",
  "title": "Turret 76A (Drumburgh)",
  "id": "967060323",
  "bbox": [
    -3.153106,
    54.928984,
    -3.153106,
    54.928984
  ],
  "description": "A turret situated on Hadrian's Wall.",
  "connectsWith": [
    "91358"
  ],
  "features": [
    {
      "type": "Feature",
      "geometry": {
        "type": "Point",
        "coordinates": [
          -3.153106,
          54.928984
        ]
      },
      "properties": {
        "description": "representative point"
      }
    },
    {
      "geometry": {
        "type": "Point",
        "coordinates": [
          -3.153106,
          54.928984
        ]
      },
      "id": "center-point-of-the-ancient-site",
      "type": "Feature",
      "properties": {
        "description": null,
        "location_precision": "precise",
        "title": "Center point of the ancient site",
        "link": "http://pleiades.stoa.org/places/967060323/center-point-of-the-ancient-site"
      }
    }
  ]
}