{
  "type": "FeatureCollection",
  "title": "Milecastle 21 (Down Hill)",
  "id": "967060215",
  "bbox": [
    -1.99474,
    55.011198,
    -1.99474,
    55.011198
  ],
  "description": "A milecastle situated on Hadrian's Wall.",
  "connectsWith": [
    "91358"
  ],
  "features": [
    {
      "type": "Feature",
      "geometry": {
        "type": "Point",
        "coordinates": [
          -1.99474,
          55.011198
        ]
      },
      "properties": {
        "description": "representative point"
      }
    },
    {
      "geometry": {
        "type": "Point",
        "coordinates": [
          -1.99474,
          55.011198
        ]
      },
      "id": "center-point-of-the-ancient-site",
      "type": "Feature",
      "properties": {
        "description": null,
        "location_precision": "precise",
        "title": "Center point of the ancient site",
        "link": "http://pleiades.stoa.org/places/967060215/center-point-of-the-ancient-site"
      }
    }
  ]
}