{
  "type": "FeatureCollection",
  "title": "Ponte d'Augusto",
  "id": "967100965",
  "bbox": [
    12.5636292,
    44.0639023,
    12.5636292,
    44.0639023
  ],
  "description": "A Iulio-Claudian bridge located in Ariminum.",
  "connectsWith": [
    "393379"
  ],
  "features": [
    {
      "type": "Feature",
      "geometry": {
        "type": "Point",
        "coordinates": [
          12.5636292,
          44.0639023
        ]
      },
      "properties": {
        "description": "representative point"
      }
    },
    {
      "geometry": {
        "type": "Point",
        "coordinates": [
          12.5636292,
          44.0639023
        ]
      },
      "id": "location-of-roman-bridge",
      "type": "Feature",
      "properties": {
        "description": "Location based on OpenStreetMap",
        "location_precision": "precise",
        "title": "OSM location of Ponte di Tiberio",
        "link": "http://pleiades.stoa.org/places/967100965/location-of-roman-bridge"
      }
    }
  ]
}