{
  "type": "FeatureCollection",
  "title": "Grimde",
  "id": "968039984",
  "bbox": [
    4.9583639,
    50.7995153,
    4.9583639,
    50.7995153
  ],
  "description": "Grimde is the site of three Gallo-Roman tumuli.",
  "features": [
    {
      "type": "Feature",
      "geometry": {
        "type": "Point",
        "coordinates": [
          4.9583639,
          50.7995153
        ]
      },
      "properties": {
        "description": "representative point"
      }
    },
    {
      "geometry": {
        "type": "Point",
        "coordinates": [
          4.9583639,
          50.7995153
        ]
      },
      "id": "location-of-tumuli",
      "type": "Feature",
      "properties": {
        "description": "Representative location based on OpenStreetMap",
        "location_precision": "precise",
        "title": "OSM location of De drie tumuli",
        "link": "http://pleiades.stoa.org/places/968039984/location-of-tumuli"
      }
    }
  ]
}