{
  "type": "FeatureCollection",
  "title": "Karaul tepe",
  "id": "971784",
  "description": "An ancient place, cited: BAtlas 99 B1 Karaul tepe",
  "bbox": [
    67.934061,
    38.481375,
    67.934061,
    38.481375
  ],
  "reprPoint": [
    67.934061,
    38.481375
  ],
  "features": [
    {
      "geometry": {
        "type": "Point",
        "coordinates": [
          67.934061,
          38.481375
        ]
      },
      "id": "darmc-location-21668",
      "type": "Feature",
      "properties": {
        "description": "Point location",
        "location_precision": "precise",
        "title": "DARMC location 21668",
        "link": "http://pleiades.stoa.org/places/971784/darmc-location-21668"
      }
    }
  ]
}