{
  "type": "FeatureCollection",
  "title": "Kalai-Shodmoi",
  "id": "971777",
  "bbox": [
    68.98259,
    38.571663,
    68.98259,
    38.571663
  ],
  "description": "An ancient place, cited: BAtlas 99 D1 Kalai-Shodmoi",
  "features": [
    {
      "type": "Feature",
      "geometry": {
        "type": "Point",
        "coordinates": [
          68.98259,
          38.571663
        ]
      },
      "properties": {
        "description": "representative point"
      }
    },
    {
      "geometry": {
        "type": "Point",
        "coordinates": [
          68.98259,
          38.571663
        ]
      },
      "id": "darmc-location-31682",
      "type": "Feature",
      "properties": {
        "description": "representative point location digitized from the Barrington Atlas of the Greek and Roman World by the Digital Atlas of Roman and Medieval Civilizations project at Harvard University.",
        "location_precision": "precise",
        "title": "DARMC location 31682",
        "link": "http://pleiades.stoa.org/places/971777/darmc-location-31682"
      }
    }
  ]
}