{
  "type": "FeatureCollection",
  "title": "Khatta tepe",
  "id": "971794",
  "description": "An ancient place, cited: BAtlas 99 B2 Khatta tepe",
  "bbox": [
    67.093732,
    37.569843,
    67.093732,
    37.569843
  ],
  "reprPoint": [
    67.093732,
    37.569843
  ],
  "features": [
    {
      "geometry": {
        "type": "Point",
        "coordinates": [
          67.093732,
          37.569843
        ]
      },
      "id": "darmc-location-21808",
      "type": "Feature",
      "properties": {
        "description": "Point location",
        "location_precision": "precise",
        "title": "DARMC location 21808",
        "link": "http://pleiades.stoa.org/places/971794/darmc-location-21808"
      }
    }
  ]
}