{
  "type": "FeatureCollection",
  "title": "Chehel Dukhtaran",
  "id": "971729",
  "bbox": [
    68.860709,
    36.730138,
    68.860709,
    36.730138
  ],
  "description": "An ancient place, cited: BAtlas 99 C3 Chehel Dukhtaran",
  "features": [
    {
      "type": "Feature",
      "geometry": {
        "type": "Point",
        "coordinates": [
          68.860709,
          36.730138
        ]
      },
      "properties": {
        "description": "representative point"
      }
    },
    {
      "geometry": {
        "type": "Point",
        "coordinates": [
          68.860709,
          36.730138
        ]
      },
      "id": "darmc-location-21720",
      "type": "Feature",
      "properties": {
        "description": "Point location",
        "location_precision": "precise",
        "title": "DARMC location 21720",
        "link": "http://pleiades.stoa.org/places/971729/darmc-location-21720"
      }
    }
  ]
}