{
  "type": "FeatureCollection",
  "title": "Khatyn-Rabad",
  "id": "971795",
  "description": "An ancient place, cited: BAtlas 99 B2 Khatyn-Rabad",
  "bbox": [
    67.778491,
    37.21987,
    67.778491,
    37.21987
  ],
  "reprPoint": [
    67.778491,
    37.21987
  ],
  "features": [
    {
      "geometry": {
        "type": "Point",
        "coordinates": [
          67.778491,
          37.21987
        ]
      },
      "id": "darmc-location-31794",
      "type": "Feature",
      "properties": {
        "description": "scale point location",
        "location_precision": "precise",
        "title": "DARMC location 31794",
        "link": "http://pleiades.stoa.org/places/971795/darmc-location-31794"
      }
    }
  ]
}