{
  "type": "FeatureCollection",
  "title": "Bactria (region)",
  "id": "971705",
  "bbox": [
    61.8760451,
    34.9528864,
    67.1565297,
    37.5616804
  ],
  "description": "An historic region at the eastern limits of the Iranian plateau connected with the Oxus civilization (Bactria–Margiana Archaeological Complex).",
  "names": [
    "Bactria",
    "Aseni",
    "Baktrioi",
    "Bactriani",
    "Zariaspai"
  ],
  "features": [
    {
      "type": "Feature",
      "geometry": {
        "type": "Point",
        "coordinates": [
          67.1536516955,
          37.4104997452
        ]
      },
      "properties": {
        "description": "representative point"
      }
    }
  ]
}