{
  "type": "FeatureCollection",
  "title": "Khairabad tepe",
  "id": "971789",
  "description": "An ancient place, cited: BAtlas 99 B2 Khairabad tepe",
  "bbox": [
    67.152272,
    37.445802,
    67.152272,
    37.445802
  ],
  "reprPoint": [
    67.152272,
    37.445802
  ],
  "features": [
    {
      "geometry": {
        "type": "Point",
        "coordinates": [
          67.152272,
          37.445802
        ]
      },
      "id": "darmc-location-21807",
      "type": "Feature",
      "properties": {
        "description": "Point location",
        "location_precision": "precise",
        "title": "DARMC location 21807",
        "link": "http://pleiades.stoa.org/places/971789/darmc-location-21807"
      }
    }
  ]
}