{
  "type": "FeatureCollection",
  "title": "Chul-i Abdan",
  "id": "971736",
  "bbox": [
    68.856279,
    36.804816,
    68.856279,
    36.804816
  ],
  "description": "An ancient place, cited: BAtlas 99 C3 Chul-i Abdan",
  "features": [
    {
      "type": "Feature",
      "geometry": {
        "type": "Point",
        "coordinates": [
          68.856279,
          36.804816
        ]
      },
      "properties": {
        "description": "representative point"
      }
    },
    {
      "geometry": {
        "type": "Point",
        "coordinates": [
          68.856279,
          36.804816
        ]
      },
      "id": "darmc-location-31726",
      "type": "Feature",
      "properties": {
        "description": "  scale point location",
        "location_precision": "precise",
        "title": "DARMC location 31726",
        "link": "http://pleiades.stoa.org/places/971736/darmc-location-31726"
      }
    }
  ]
}