{
  "type": "FeatureCollection",
  "title": "Bish Kapa",
  "id": "971718",
  "description": "An ancient place, cited: BAtlas 99 D3 Bish Kapa",
  "bbox": [
    69.379384,
    36.610211,
    69.379384,
    36.610211
  ],
  "reprPoint": [
    69.379384,
    36.610211
  ],
  "features": [
    {
      "geometry": {
        "type": "Point",
        "coordinates": [
          69.379384,
          36.610211
        ]
      },
      "id": "darmc-location-21712",
      "type": "Feature",
      "properties": {
        "description": "Point location",
        "location_precision": "precise",
        "title": "DARMC location 21712",
        "link": "http://pleiades.stoa.org/places/971718/darmc-location-21712"
      }
    }
  ]
}