{
  "type": "FeatureCollection",
  "title": "Ishan Tup",
  "id": "971763",
  "bbox": [
    69.069871,
    36.604198,
    69.069871,
    36.604198
  ],
  "description": "An ancient place, cited: BAtlas 99 D3 Ishan Tup",
  "features": [
    {
      "type": "Feature",
      "geometry": {
        "type": "Point",
        "coordinates": [
          69.069871,
          36.604198
        ]
      },
      "properties": {
        "description": "representative point"
      }
    },
    {
      "geometry": {
        "type": "Point",
        "coordinates": [
          69.069871,
          36.604198
        ]
      },
      "id": "darmc-location-21715",
      "type": "Feature",
      "properties": {
        "description": "Point location",
        "location_precision": "precise",
        "title": "DARMC location 21715",
        "link": "http://pleiades.stoa.org/places/971763/darmc-location-21715"
      }
    }
  ]
}