{
  "type": "FeatureCollection",
  "title": "Drapsaka",
  "id": "971746",
  "description": "Drapsaka (modern Kunduz) was an ancient settlement in central Asia.",
  "bbox": [
    68.853748,
    36.711785,
    68.867739,
    36.722088
  ],
  "reprPoint": [
    68.8607435,
    36.7169365
  ],
  "names": [
    "Drapsaka",
    "Adrapsa",
    "Darapsa",
    "Drepsa"
  ],
  "features": [
    {
      "geometry": {
        "type": "Point",
        "coordinates": [
          68.867739,
          36.722088
        ]
      },
      "id": "darmc-location-20221",
      "type": "Feature",
      "properties": {
        "description": "5M scale point location",
        "location_precision": "precise",
        "title": "DARMC location 20221",
        "link": "http://pleiades.stoa.org/places/971746/darmc-location-20221"
      }
    },
    {
      "geometry": {
        "type": "Point",
        "coordinates": [
          68.853748,
          36.711785
        ]
      },
      "id": "darmc-location-21721",
      "type": "Feature",
      "properties": {
        "description": "Point location",
        "location_precision": "precise",
        "title": "DARMC location 21721",
        "link": "http://pleiades.stoa.org/places/971746/darmc-location-21721"
      }
    }
  ]
}