{
  "type": "FeatureCollection",
  "title": "Katta-dzhelail",
  "id": "971786",
  "bbox": [
    68.443305,
    38.549724,
    68.443305,
    38.549724
  ],
  "description": "An ancient place, cited: BAtlas 99 C1 Katta-dzhelail",
  "features": [
    {
      "type": "Feature",
      "geometry": {
        "type": "Point",
        "coordinates": [
          68.443305,
          38.549724
        ]
      },
      "properties": {
        "description": "representative point"
      }
    },
    {
      "geometry": {
        "type": "Point",
        "coordinates": [
          68.443305,
          38.549724
        ]
      },
      "id": "darmc-location-31674",
      "type": "Feature",
      "properties": {
        "description": "  scale point location",
        "location_precision": "precise",
        "title": "DARMC location 31674",
        "link": "http://pleiades.stoa.org/places/971786/darmc-location-31674"
      }
    }
  ]
}