{
  "type": "FeatureCollection",
  "title": "Shur tepe",
  "id": "971872",
  "description": "An ancient place, cited: BAtlas 99 C2 Shur tepe",
  "bbox": [
    68.516857,
    37.465183,
    68.516857,
    37.465183
  ],
  "reprPoint": [
    68.516857,
    37.465183
  ],
  "features": [
    {
      "geometry": {
        "type": "Point",
        "coordinates": [
          68.516857,
          37.465183
        ]
      },
      "id": "darmc-location-21823",
      "type": "Feature",
      "properties": {
        "description": "Point location",
        "location_precision": "precise",
        "title": "DARMC location 21823",
        "link": "http://pleiades.stoa.org/places/971872/darmc-location-21823"
      }
    }
  ]
}