{
  "type": "FeatureCollection",
  "title": "Tamosho tepe",
  "id": "971885",
  "description": "An ancient place, cited: BAtlas 99 C1 Tamosho tepe",
  "bbox": [
    68.911709,
    38.271264,
    68.911709,
    38.271264
  ],
  "reprPoint": [
    68.911709,
    38.271264
  ],
  "features": [
    {
      "geometry": {
        "type": "Point",
        "coordinates": [
          68.911709,
          38.271264
        ]
      },
      "id": "darmc-location-21681",
      "type": "Feature",
      "properties": {
        "description": "Point location",
        "location_precision": "precise",
        "title": "DARMC location 21681",
        "link": "http://pleiades.stoa.org/places/971885/darmc-location-21681"
      }
    }
  ]
}