{
  "type": "FeatureCollection",
  "title": "Panjiri",
  "id": "971838",
  "description": "An ancient place, cited: BAtlas 99 D3 Panjiri",
  "bbox": [
    69.347036,
    36.305803,
    69.347036,
    36.305803
  ],
  "reprPoint": [
    69.347036,
    36.305803
  ],
  "features": [
    {
      "geometry": {
        "type": "Point",
        "coordinates": [
          69.347036,
          36.305803
        ]
      },
      "id": "darmc-location-21704",
      "type": "Feature",
      "properties": {
        "description": "Point location",
        "location_precision": "precise",
        "title": "DARMC location 21704",
        "link": "http://pleiades.stoa.org/places/971838/darmc-location-21704"
      }
    }
  ]
}