{
  "type": "FeatureCollection",
  "title": "Uljatu",
  "id": "971898",
  "description": "An ancient place, cited: BAtlas 99 B3 Uljatu",
  "bbox": [
    67.655181,
    36.752605,
    67.655181,
    36.752605
  ],
  "reprPoint": [
    67.655181,
    36.752605
  ],
  "features": [
    {
      "geometry": {
        "type": "Point",
        "coordinates": [
          67.655181,
          36.752605
        ]
      },
      "id": "darmc-location-21741",
      "type": "Feature",
      "properties": {
        "description": "Point location",
        "location_precision": "precise",
        "title": "DARMC location 21741",
        "link": "http://pleiades.stoa.org/places/971898/darmc-location-21741"
      }
    }
  ]
}