{
  "type": "FeatureCollection",
  "title": "Shor tepe",
  "id": "971869",
  "description": "An ancient place, cited: BAtlas 99 C2 Shor tepe",
  "bbox": [
    68.653429,
    37.776236,
    68.653429,
    37.776236
  ],
  "reprPoint": [
    68.653429,
    37.776236
  ],
  "features": [
    {
      "geometry": {
        "type": "Point",
        "coordinates": [
          68.653429,
          37.776236
        ]
      },
      "id": "darmc-location-21829",
      "type": "Feature",
      "properties": {
        "description": "Point location",
        "location_precision": "precise",
        "title": "DARMC location 21829",
        "link": "http://pleiades.stoa.org/places/971869/darmc-location-21829"
      }
    }
  ]
}