{
  "type": "FeatureCollection",
  "title": "Takht-i Sangin",
  "id": "971882",
  "bbox": [
    59.1285597,
    36.9229988,
    73.5725,
    44.108333
  ],
  "description": "Takht-i Sangin is an ancient settlement located near the confluence of the Vakhsh and Panj rivers. It may be the source of the so-called \"Oxus Treasure\".",
  "connectsWith": [
    "59969"
  ],
  "features": [
    {
      "type": "Feature",
      "geometry": {
        "type": "Point",
        "coordinates": [
          66.9025360113,
          38.4775102617
        ]
      },
      "properties": {
        "description": "representative point"
      }
    }
  ]
}