{
  "type": "FeatureCollection",
  "title": "Sina",
  "id": "971875",
  "description": "An ancient place, cited: BAtlas 99 B1 Sina",
  "bbox": [
    67.447829,
    38.462811,
    67.447829,
    38.462811
  ],
  "reprPoint": [
    67.447829,
    38.462811
  ],
  "features": [
    {
      "geometry": {
        "type": "Point",
        "coordinates": [
          67.447829,
          38.462811
        ]
      },
      "id": "darmc-location-21655",
      "type": "Feature",
      "properties": {
        "description": "Point location",
        "location_precision": "precise",
        "title": "DARMC location 21655",
        "link": "http://pleiades.stoa.org/places/971875/darmc-location-21655"
      }
    }
  ]
}