{
  "type": "FeatureCollection",
  "title": "Takht-i Sangin",
  "id": "971882",
  "bbox": [
    68.2846781,
    37.0988705,
    68.2846781,
    37.0988705
  ],
  "description": "Takht-i Sangin is an ancient settlement located near the confluence of the Vakhsh and Panj rivers. It may be the source of the so-called \"Oxus Treasure\".",
  "connectsWith": [
    "59969"
  ],
  "features": [
    {
      "type": "Feature",
      "geometry": {
        "type": "Point",
        "coordinates": [
          68.2846781,
          37.0988705
        ]
      },
      "properties": {
        "description": "representative point"
      }
    }
  ]
}