{
  "type": "FeatureCollection",
  "title": "Khush bai",
  "id": "971803",
  "description": "An ancient place, cited: BAtlas 99 D3 Khush bai",
  "bbox": [
    69.550292,
    36.722228,
    69.550292,
    36.722228
  ],
  "reprPoint": [
    69.550292,
    36.722228
  ],
  "features": [
    {
      "geometry": {
        "type": "Point",
        "coordinates": [
          69.550292,
          36.722228
        ]
      },
      "id": "darmc-location-21731",
      "type": "Feature",
      "properties": {
        "description": "Point location",
        "location_precision": "precise",
        "title": "DARMC location 21731",
        "link": "http://pleiades.stoa.org/places/971803/darmc-location-21731"
      }
    }
  ]
}