{
  "type": "FeatureCollection",
  "title": "Sar Rustaq",
  "id": "971859",
  "description": "An ancient place, cited: BAtlas 99 D2 Sar Rustaq",
  "bbox": [
    69.934237,
    37.108064,
    69.934237,
    37.108064
  ],
  "reprPoint": [
    69.934237,
    37.108064
  ],
  "features": [
    {
      "geometry": {
        "type": "Point",
        "coordinates": [
          69.934237,
          37.108064
        ]
      },
      "id": "darmc-location-21758",
      "type": "Feature",
      "properties": {
        "description": "Point location",
        "location_precision": "precise",
        "title": "DARMC location 21758",
        "link": "http://pleiades.stoa.org/places/971859/darmc-location-21758"
      }
    }
  ]
}