{
  "type": "FeatureCollection",
  "title": "Pushing",
  "id": "971842",
  "description": "An ancient place, cited: BAtlas 99 D1 Pushing",
  "bbox": [
    69.465048,
    38.24834,
    69.465048,
    38.24834
  ],
  "reprPoint": [
    69.465048,
    38.24834
  ],
  "features": [
    {
      "geometry": {
        "type": "Point",
        "coordinates": [
          69.465048,
          38.24834
        ]
      },
      "id": "darmc-location-21687",
      "type": "Feature",
      "properties": {
        "description": "Point location",
        "location_precision": "precise",
        "title": "DARMC location 21687",
        "link": "http://pleiades.stoa.org/places/971842/darmc-location-21687"
      }
    }
  ]
}