{
  "type": "FeatureCollection",
  "title": "Takht-i Sangin",
  "id": "971882",
  "description": "An ancient place, cited: BAtlas 99 C2 Takht-i Sangin",
  "bbox": [
    67.758081,
    37.480633,
    67.758081,
    37.480633
  ],
  "reprPoint": [
    67.758081,
    37.480633
  ],
  "features": [
    {
      "geometry": {
        "type": "Point",
        "coordinates": [
          67.758081,
          37.480633
        ]
      },
      "id": "darmc-location-24982",
      "type": "Feature",
      "properties": {
        "description": "5M scale point location",
        "location_precision": "precise",
        "title": "DARMC location 24982",
        "link": "http://pleiades.stoa.org/places/971882/darmc-location-24982"
      }
    }
  ]
}