{
  "type": "FeatureCollection",
  "title": "Uzbekon tepe",
  "id": "971903",
  "description": "An ancient place, cited: BAtlas 99 C1 Uzbekon tepe",
  "bbox": [
    68.091011,
    38.47378,
    68.091011,
    38.47378
  ],
  "reprPoint": [
    68.091011,
    38.47378
  ],
  "features": [
    {
      "geometry": {
        "type": "Point",
        "coordinates": [
          68.091011,
          38.47378
        ]
      },
      "id": "darmc-location-21669",
      "type": "Feature",
      "properties": {
        "description": "Point location",
        "location_precision": "precise",
        "title": "DARMC location 21669",
        "link": "http://pleiades.stoa.org/places/971903/darmc-location-21669"
      }
    }
  ]
}