{
  "type": "FeatureCollection",
  "title": "Urta Buz",
  "id": "971901",
  "bbox": [
    68.662922,
    37.647132,
    68.662922,
    37.647132
  ],
  "description": "A site located on a natural promontory in Takhar Province near the Taluqan River. The settlement mound includes occupation horizons ranging from the Bronze Age (second millennium B.C.) to the Hellenistic period with some Kushan and Islamic material as well.",
  "features": [
    {
      "type": "Feature",
      "geometry": {
        "type": "Point",
        "coordinates": [
          68.662922,
          37.647132
        ]
      },
      "properties": {
        "description": "representative point"
      }
    },
    {
      "geometry": {
        "type": "Point",
        "coordinates": [
          68.662922,
          37.647132
        ]
      },
      "id": "darmc-location-21826",
      "type": "Feature",
      "properties": {
        "description": "Point location",
        "location_precision": "precise",
        "title": "DARMC location 21826",
        "link": "http://pleiades.stoa.org/places/971901/darmc-location-21826"
      }
    }
  ]
}