{
  "type": "FeatureCollection",
  "title": "Urta Buz",
  "id": "971901",
  "description": "An ancient place, cited: BAtlas 99 C2 Urta Buz",
  "bbox": [
    68.662922,
    37.647132,
    68.662922,
    37.647132
  ],
  "reprPoint": [
    68.662922,
    37.647132
  ],
  "features": [
    {
      "geometry": {
        "type": "Point",
        "coordinates": [
          68.662922,
          37.647132
        ]
      },
      "id": "darmc-location-21826",
      "type": "Feature",
      "properties": {
        "description": "Point location",
        "location_precision": "precise",
        "title": "DARMC location 21826",
        "link": "http://pleiades.stoa.org/places/971901/darmc-location-21826"
      }
    }
  ]
}