{
  "type": "FeatureCollection",
  "title": "Zulm",
  "id": "971913",
  "description": "An ancient place, cited: BAtlas 99 D2 Zulm",
  "bbox": [
    69.519521,
    37.165232,
    69.519521,
    37.165232
  ],
  "reprPoint": [
    69.519521,
    37.165232
  ],
  "features": [
    {
      "geometry": {
        "type": "Point",
        "coordinates": [
          69.519521,
          37.165232
        ]
      },
      "id": "darmc-location-21763",
      "type": "Feature",
      "properties": {
        "description": "Point location",
        "location_precision": "precise",
        "title": "DARMC location 21763",
        "link": "http://pleiades.stoa.org/places/971913/darmc-location-21763"
      }
    }
  ]
}