{
  "type": "FeatureCollection",
  "title": "Withdrawn: House of the Tragic Poet",
  "id": "973204924",
  "description": "This place resource is a duplicate for http://pleiades.stoa.org/places/912505596 and was erroneously created and published. It has been withdrawn and moved to errata.",
  "reprPoint": [
    0.0,
    0.0
  ],
  "names": [
    "Casa di Omero",
    "Haus der Iphigenia",
    "Casa del poeta drammatico",
    "Domus of Aninius",
    "VI.8.3",
    "Casa di Glauco",
    "Casa del concerto drammatico",
    "Casa del poeta",
    "Casa col Cave canem",
    "Domus of M. P. Cepius",
    "Casa omerica",
    "Casa del Poeta Tragico"
  ],
  "features": [
    {
      "geometry": {
        "type": "Point",
        "coordinates": [
          14.4836286,
          40.7507916
        ]
      },
      "id": "casa-del-poeta-tragico",
      "type": "Feature",
      "properties": {
        "description": "Location based on OpenStreetMap",
        "location_precision": "precise",
        "title": "Casa del Poeta Tragico",
        "link": "http://pleiades.stoa.org/errata/973204924/casa-del-poeta-tragico"
      }
    },
    {
      "geometry": {
        "type": "Point",
        "coordinates": [
          14.4836286,
          40.7507916
        ]
      },
      "id": "copy_of_casa-del-poeta-tragico",
      "type": "Feature",
      "properties": {
        "description": "Location based on OpenStreetMap",
        "location_precision": "precise",
        "title": "OSM location of so-called \"Casa del Poeta Tragico\"",
        "link": "http://pleiades.stoa.org/errata/973204924/copy_of_casa-del-poeta-tragico"
      }
    }
  ]
}