{
  "type": "FeatureCollection",
  "title": "Laqê",
  "id": "973646284",
  "bbox": [
    40.674133,
    34.71904,
    40.674133,
    34.71904
  ],
  "description": "A land situated on the middle Euphrates, to north and west of the kingdom of Suhu and to the south of the land Bit-Halupê. Eleven of its cities are mentioned in Assyrian inscriptions of the first millennium B.C.",
  "names": [
    "Lāqê"
  ],
  "features": [
    {
      "type": "Feature",
      "geometry": {
        "type": "Point",
        "coordinates": [
          40.674133,
          34.71904
        ]
      },
      "properties": {
        "description": "representative point"
      }
    },
    {
      "geometry": {
        "type": "Point",
        "coordinates": [
          40.674133,
          34.71904
        ]
      },
      "id": "tavo-location-of-laqe",
      "type": "Feature",
      "properties": {
        "description": "Estimated, representative centerpoint based on location of Laqê shown in the Helsinki Atlas of the Ancient Near East in the Neo-Assyrian Period and in Bagg 2017 (RGTC 7/2-2).",
        "location_precision": "precise",
        "title": "Representative centerpoint of Laqê",
        "link": "http://pleiades.stoa.org/places/973646284/tavo-location-of-laqe"
      }
    }
  ]
}