{
  "type": "FeatureCollection",
  "title": "Old Burrow",
  "id": "975884600",
  "bbox": [
    -3.7377062,
    51.2307607,
    -3.7377062,
    51.2307607
  ],
  "description": "A first century Roman fortlet measuring 44 by 85 meters. ",
  "features": [
    {
      "type": "Feature",
      "geometry": {
        "type": "Point",
        "coordinates": [
          -3.7377062,
          51.2307607
        ]
      },
      "properties": {
        "description": "representative point"
      }
    },
    {
      "geometry": {
        "type": "Point",
        "coordinates": [
          -3.7377062,
          51.2307607
        ]
      },
      "id": "osm-location",
      "type": "Feature",
      "properties": {
        "description": "Representative location based on OpenStreetMap.",
        "location_precision": "precise",
        "title": "OSM location of Old Burrow fortlet",
        "link": "http://pleiades.stoa.org/places/975884600/osm-location"
      }
    }
  ]
}