{
  "type": "FeatureCollection",
  "title": "Lucus Stimulae",
  "id": "978725164",
  "bbox": [
    12.483333,
    41.883333,
    12.486137,
    41.891775
  ],
  "description": "A grove sacred to Stimula, located at the southwestern foot of the Aventine hill.",
  "connectsWith": [
    "865014139",
    "423025"
  ],
  "names": [
    "Lucus Stimulae"
  ],
  "features": [
    {
      "type": "Feature",
      "geometry": {
        "type": "Point",
        "coordinates": [
          12.484735,
          41.887554
        ]
      },
      "properties": {
        "description": "representative point"
      }
    }
  ]
}