{
  "type": "FeatureCollection",
  "title": "Atlit Yam",
  "id": "97875559",
  "bbox": [
    34.93515,
    32.710828,
    34.93515,
    32.710828
  ],
  "description": "Atlit Yam is the site of an ancient submerged Neolithic village off the coast of Atlit, Israel, occupied during the final Pre-Pottery Neolithic B period.",
  "features": [
    {
      "type": "Feature",
      "geometry": {
        "type": "Point",
        "coordinates": [
          34.93515,
          32.710828
        ]
      },
      "properties": {
        "description": "representative point"
      }
    },
    {
      "geometry": {
        "type": "Point",
        "coordinates": [
          34.93515,
          32.710828
        ]
      },
      "id": "location-of-atlit-yam",
      "type": "Feature",
      "properties": {
        "description": "coordinates after GeoHack.",
        "location_precision": "precise",
        "title": "location of Atlit Yam",
        "link": "http://pleiades.stoa.org/places/97875559/location-of-atlit-yam"
      }
    }
  ]
}