{
  "type": "FeatureCollection",
  "title": "La Hougue Bie",
  "id": "982326584",
  "bbox": [
    -2.0635778,
    49.2000813,
    -2.0635778,
    49.2000813
  ],
  "description": "A Neolithic ritual site that includes a passage grave dating ca. 4000-3500 BCE.",
  "connectsWith": [
    "69465"
  ],
  "names": [
    "La Hougue Bie"
  ],
  "features": [
    {
      "type": "Feature",
      "geometry": {
        "type": "Point",
        "coordinates": [
          -2.0635778,
          49.2000813
        ]
      },
      "properties": {
        "description": "representative point"
      }
    },
    {
      "geometry": {
        "type": "Point",
        "coordinates": [
          -2.0635778,
          49.2000813
        ]
      },
      "id": "location-of-la-houge-bie",
      "type": "Feature",
      "properties": {
        "description": "Representative location based on OpenStreetMap",
        "location_precision": "precise",
        "title": "OSM location of La Houge Bie",
        "link": "http://pleiades.stoa.org/places/982326584/location-of-la-houge-bie"
      }
    }
  ]
}