{
  "type": "FeatureCollection",
  "title": "Ṭarṭūs",
  "id": "9832296",
  "bbox": [
    35.885167,
    34.8936225,
    35.8866,
    34.8958
  ],
  "description": "Find place for cuneiform inscription.",
  "names": [
    "Ṭarṭūs"
  ],
  "features": [
    {
      "type": "Feature",
      "geometry": {
        "type": "Point",
        "coordinates": [
          35.8858835,
          34.89471125
        ]
      },
      "properties": {
        "description": "representative point"
      }
    },
    {
      "geometry": {
        "type": "Point",
        "coordinates": [
          35.885167,
          34.8936225
        ]
      },
      "id": "637631637648633",
      "type": "Feature",
      "properties": {
        "description": "Location based on OpenStreetMap",
        "location_precision": "precise",
        "title": "OSM location of طرطوس",
        "link": "http://pleiades.stoa.org/places/9832296/637631637648633"
      }
    },
    {
      "geometry": {
        "type": "Point",
        "coordinates": [
          35.8866,
          34.8958
        ]
      },
      "id": "cigs-location-of-tartus",
      "type": "Feature",
      "properties": {
        "description": null,
        "location_precision": "precise",
        "title": "CIGS location of Ṭarṭūs",
        "link": "http://pleiades.stoa.org/places/9832296/cigs-location-of-tartus"
      }
    }
  ]
}