{
  "type": "FeatureCollection",
  "title": "Theater at Alinda/Alexandria ad Latmum",
  "id": "983828927",
  "bbox": [
    27.8267113,
    37.5587066,
    27.8267113,
    37.5587066
  ],
  "description": "The Roman Theater at Alinda could accommodate about 5,000 spectators.",
  "connectsWith": [
    "599480"
  ],
  "features": [
    {
      "type": "Feature",
      "geometry": {
        "type": "Point",
        "coordinates": [
          27.8267113,
          37.5587066
        ]
      },
      "properties": {
        "description": "representative point"
      }
    },
    {
      "geometry": {
        "type": "Point",
        "coordinates": [
          27.8267113,
          37.5587066
        ]
      },
      "id": "osm-location-of-theater",
      "type": "Feature",
      "properties": {
        "description": "Representative location based on OpenStreetMap",
        "location_precision": "precise",
        "title": "OSM location of theater",
        "link": "http://pleiades.stoa.org/places/983828927/osm-location-of-theater"
      }
    }
  ]
}