{
  "type": "FeatureCollection",
  "title": "Regio IV, Pompeii",
  "id": "984330149",
  "bbox": [
    14.485429,
    40.74941,
    14.485429,
    40.74941
  ],
  "description": "The so-called Regio IV is a largely unexcavated archaeological subdivision located in the northeastern section of Pompeii.",
  "connectsWith": [
    "433032"
  ],
  "names": [
    "Regio IV degli scavi archeologici di Pompei"
  ],
  "features": [
    {
      "type": "Feature",
      "geometry": {
        "type": "Point",
        "coordinates": [
          14.485429,
          40.74941
        ]
      },
      "properties": {
        "description": "representative point"
      }
    }
  ]
}