{
  "type": "FeatureCollection",
  "title": "Regio V, Pompeii",
  "id": "984330150",
  "bbox": [
    14.485429,
    40.74941,
    14.4884573,
    40.7529254
  ],
  "description": "The so-called Regio V, a largely unexcavated archaeological subdivision located in the northern section of Pompeii, contains a mixture of commercial and domestic structures, including a gladiators' barracks.",
  "connectsWith": [
    "433032"
  ],
  "names": [
    "Regio V degli scavi archeologici di Pompei"
  ],
  "features": [
    {
      "type": "Feature",
      "geometry": {
        "type": "Point",
        "coordinates": [
          14.48822775,
          40.752885
        ]
      },
      "properties": {
        "description": "representative point"
      }
    }
  ]
}