{
  "type": "FeatureCollection",
  "title": "Theban Tomb 320",
  "id": "986129163",
  "bbox": [
    32.605036,
    25.7368,
    32.605036,
    25.7368
  ],
  "description": "Theban Tomb 320, known as the \"Royal Cache,\" was constructed during the 18th Dynasty near Deir el-Bahari. It was used as a secondary burial site for over 50 royal and noble mummies during the New Kingdom period.",
  "connectsWith": [
    "836839127"
  ],
  "names": [
    "TT 320"
  ],
  "features": [
    {
      "type": "Feature",
      "geometry": {
        "type": "Point",
        "coordinates": [
          32.605036,
          25.7368
        ]
      },
      "properties": {
        "description": "representative point"
      }
    },
    {
      "geometry": {
        "type": "Point",
        "coordinates": [
          32.605036,
          25.7368
        ]
      },
      "id": "wikidata-location-of-tt-320",
      "type": "Feature",
      "properties": {
        "description": "Point representing the location of the entrance to TT 320.",
        "location_precision": "precise",
        "title": "Wikidata location of TT 320",
        "link": "http://pleiades.stoa.org/places/986129163/wikidata-location-of-tt-320"
      }
    }
  ]
}