{
  "type": "FeatureCollection",
  "title": "Tomb of Marcus Servilius Quartus ",
  "id": "98709290",
  "bbox": [
    12.532156,
    41.841589,
    12.532156,
    41.841589
  ],
  "description": "A Roman tomb on the Via Appia dating ca. A.D. 100.",
  "connectsWith": [
    "356966898"
  ],
  "features": [
    {
      "type": "Feature",
      "geometry": {
        "type": "Point",
        "coordinates": [
          12.532156,
          41.841589
        ]
      },
      "properties": {
        "description": "representative point"
      }
    },
    {
      "geometry": {
        "type": "Point",
        "coordinates": [
          12.532156,
          41.841589
        ]
      },
      "id": "osm-location-of-tomba-di-marco-servilio-quarto",
      "type": "Feature",
      "properties": {
        "description": "Representative location based on OpenStreetMap",
        "location_precision": "precise",
        "title": "OSM location of Tomba di Marco Servilio Quarto",
        "link": "http://pleiades.stoa.org/places/98709290/osm-location-of-tomba-di-marco-servilio-quarto"
      }
    }
  ]
}