{
  "type": "FeatureCollection",
  "title": "Nuraghe Sa Jua",
  "id": "987440325",
  "bbox": [
    8.8527249,
    40.1711527,
    8.8527249,
    40.1711527
  ],
  "description": "A monopteral nuraghe. ",
  "connectsWith": [
    "472014"
  ],
  "features": [
    {
      "type": "Feature",
      "geometry": {
        "type": "Point",
        "coordinates": [
          8.8527249,
          40.1711527
        ]
      },
      "properties": {
        "description": "representative point"
      }
    },
    {
      "geometry": {
        "type": "Point",
        "coordinates": [
          8.8527249,
          40.1711527
        ]
      },
      "id": "osm-location-of-nuraghe-sa-jua",
      "type": "Feature",
      "properties": {
        "description": "Location based on OpenStreetMap",
        "location_precision": "precise",
        "title": "OSM location of Nuraghe Sa Jua",
        "link": "http://pleiades.stoa.org/places/987440325/osm-location-of-nuraghe-sa-jua"
      }
    }
  ]
}