{
  "type": "FeatureCollection",
  "title": "Ellibir",
  "id": "988674926",
  "bbox": [
    37.241604,
    38.718471,
    37.273376,
    38.727385
  ],
  "description": "A fortress in the vicinity of Til-garimmu fortified by the Assyrian king Sargon II (r. 721-705 BC) against Kasku.",
  "connectsWith": [
    "319432673",
    "628982",
    "270123727"
  ],
  "names": [
    "Ellibir"
  ],
  "features": [
    {
      "type": "Feature",
      "geometry": {
        "type": "Point",
        "coordinates": [
          37.25749,
          38.722928
        ]
      },
      "properties": {
        "description": "representative point"
      }
    }
  ]
}