{
  "type": "FeatureCollection",
  "title": "Monte Rovello",
  "id": "989027460",
  "bbox": [
    11.9038323,
    42.156218,
    11.9038323,
    42.156218
  ],
  "description": "Monte Rovello was an important Etruscan settlement covering ca. 5 hectares with occupation stretching from the Bronze Age to the Hellenistic period.",
  "features": [
    {
      "type": "Feature",
      "geometry": {
        "type": "Point",
        "coordinates": [
          11.9038323,
          42.156218
        ]
      },
      "properties": {
        "description": "representative point"
      }
    },
    {
      "geometry": {
        "type": "Point",
        "coordinates": [
          11.9038323,
          42.156218
        ]
      },
      "id": "allumiere",
      "type": "Feature",
      "properties": {
        "description": "Representative location of the modern comune based on OpenStreetMap.",
        "location_precision": "precise",
        "title": "OSM location of Allumiere",
        "link": "http://pleiades.stoa.org/places/989027460/allumiere"
      }
    }
  ]
}