{
  "type": "FeatureCollection",
  "title": "Amisia (river)",
  "id": "98910",
  "bbox": [
    7.4499802,
    52.2730841,
    7.4499802,
    52.2730841
  ],
  "description": "An ancient place, cited: BAtlas 10 D3 Amisia fl.",
  "names": [
    "Amisia"
  ],
  "features": [
    {
      "type": "Feature",
      "geometry": {
        "type": "Point",
        "coordinates": [
          7.4499802,
          52.2730841
        ]
      },
      "properties": {
        "description": "representative point"
      }
    },
    {
      "geometry": {
        "type": "Point",
        "coordinates": [
          7.4499802,
          52.2730841
        ]
      },
      "id": "location-of-Amisia-fl",
      "type": "Feature",
      "properties": {
        "description": "Location based on OpenStreetMap",
        "location_precision": "precise",
        "title": "location of Amisia fl.",
        "link": "http://pleiades.stoa.org/places/98910/location-of-Amisia-fl"
      }
    }
  ]
}