{
  "type": "FeatureCollection",
  "title": "Bornstein",
  "id": "98927",
  "description": "An ancient place, cited: BAtlas 10 F2 Bornstein",
  "bbox": [
    9.930574,
    54.416751,
    9.930574,
    54.416751
  ],
  "reprPoint": [
    9.930574,
    54.416751
  ],
  "features": [
    {
      "geometry": {
        "type": "Point",
        "coordinates": [
          9.930574,
          54.416751
        ]
      },
      "id": "darmc-location-23643",
      "type": "Feature",
      "properties": {
        "description": "Point location",
        "location_precision": "precise",
        "title": "DARMC location 23643",
        "link": "http://pleiades.stoa.org/places/98927/darmc-location-23643"
      }
    }
  ]
}