{
  "type": "FeatureCollection",
  "title": "Ezinge",
  "id": "98953",
  "description": "An ancient place, cited: BAtlas 10 C3 Ezinge",
  "bbox": [
    6.439244,
    53.311169,
    6.439244,
    53.311169
  ],
  "reprPoint": [
    6.439244,
    53.311169
  ],
  "features": [
    {
      "geometry": {
        "type": "Point",
        "coordinates": [
          6.439244,
          53.311169
        ]
      },
      "id": "darmc-location-12419",
      "type": "Feature",
      "properties": {
        "description": "1M scale point location",
        "location_precision": "precise",
        "title": "DARMC location 12419",
        "link": "http://pleiades.stoa.org/places/98953/darmc-location-12419"
      }
    }
  ]
}