{
  "type": "FeatureCollection",
  "title": "Feddersen Wierde",
  "id": "98957",
  "description": "An ancient place, cited: BAtlas 10 E3 Feddersen Wierde",
  "bbox": [
    8.54315,
    53.665868,
    8.54315,
    53.665868
  ],
  "reprPoint": [
    8.54315,
    53.665868
  ],
  "features": [
    {
      "geometry": {
        "type": "Point",
        "coordinates": [
          8.54315,
          53.665868
        ]
      },
      "id": "darmc-location-12422",
      "type": "Feature",
      "properties": {
        "description": "1M scale point location",
        "location_precision": "precise",
        "title": "DARMC location 12422",
        "link": "http://pleiades.stoa.org/places/98957/darmc-location-12422"
      }
    }
  ]
}