{
  "type": "FeatureCollection",
  "title": "Gristede",
  "id": "98968",
  "bbox": [
    8.053076,
    53.223203,
    8.053076,
    53.223203
  ],
  "description": "An ancient place, cited: BAtlas 10 E3 Gristede",
  "features": [
    {
      "type": "Feature",
      "geometry": {
        "type": "Point",
        "coordinates": [
          8.053076,
          53.223203
        ]
      },
      "properties": {
        "description": "representative point"
      }
    },
    {
      "geometry": {
        "type": "Point",
        "coordinates": [
          8.053076,
          53.223203
        ]
      },
      "id": "darmc-location-12604",
      "type": "Feature",
      "properties": {
        "description": "1M scale point location",
        "location_precision": "precise",
        "title": "DARMC location 12604",
        "link": "http://pleiades.stoa.org/places/98968/darmc-location-12604"
      }
    }
  ]
}