{
  "type": "FeatureCollection",
  "title": "Jever",
  "id": "98989",
  "description": "An ancient place, cited: BAtlas 10 D3 Jever",
  "bbox": [
    7.900281,
    53.575688,
    7.900281,
    53.575688
  ],
  "reprPoint": [
    7.900281,
    53.575688
  ],
  "features": [
    {
      "geometry": {
        "type": "Point",
        "coordinates": [
          7.900281,
          53.575688
        ]
      },
      "id": "darmc-location-12926",
      "type": "Feature",
      "properties": {
        "description": "1M scale point location",
        "location_precision": "precise",
        "title": "DARMC location 12926",
        "link": "http://pleiades.stoa.org/places/98989/darmc-location-12926"
      }
    }
  ]
}