{
  "type": "FeatureCollection",
  "title": "Hoby",
  "id": "98983",
  "description": "An ancient place, cited: BAtlas 10 H2 Hoby",
  "bbox": [
    11.230919,
    54.740603,
    11.230919,
    54.740603
  ],
  "reprPoint": [
    11.230919,
    54.740603
  ],
  "features": [
    {
      "geometry": {
        "type": "Point",
        "coordinates": [
          11.230919,
          54.740603
        ]
      },
      "id": "darmc-location-23647",
      "type": "Feature",
      "properties": {
        "description": "Point location",
        "location_precision": "precise",
        "title": "DARMC location 23647",
        "link": "http://pleiades.stoa.org/places/98983/darmc-location-23647"
      }
    }
  ]
}