{
  "type": "FeatureCollection",
  "title": "Juellinge",
  "id": "98990",
  "description": "An ancient place, cited: BAtlas 10 I1 Juellinge",
  "bbox": [
    12.234436,
    55.305106,
    12.234436,
    55.305106
  ],
  "reprPoint": [
    12.234436,
    55.305106
  ],
  "features": [
    {
      "geometry": {
        "type": "Point",
        "coordinates": [
          12.234436,
          55.305106
        ]
      },
      "id": "darmc-location-23651",
      "type": "Feature",
      "properties": {
        "description": "Point location",
        "location_precision": "precise",
        "title": "DARMC location 23651",
        "link": "http://pleiades.stoa.org/places/98990/darmc-location-23651"
      }
    }
  ]
}