{
  "type": "FeatureCollection",
  "title": "Loo-Loowaard",
  "id": "99002",
  "description": "An ancient place, cited: BAtlas 10 C5 Loo-Loowaard",
  "bbox": [
    5.9875,
    51.920833,
    5.9875,
    51.920833
  ],
  "reprPoint": [
    5.9875,
    51.920833
  ],
  "features": [
    {
      "geometry": {
        "type": "Point",
        "coordinates": [
          5.9875,
          51.920833
        ]
      },
      "id": "dare-location",
      "type": "Feature",
      "properties": {
        "description": "Representative point location, site precision",
        "location_precision": "precise",
        "title": "DARE Location",
        "link": "http://pleiades.stoa.org/places/99002/dare-location"
      }
    },
    {
      "geometry": {
        "type": "Point",
        "coordinates": [
          5.989303,
          51.930287
        ]
      },
      "id": "darmc-location-17917",
      "type": "Feature",
      "properties": {
        "description": "1M scale point location",
        "location_precision": "precise",
        "title": "DARMC location 17917",
        "link": "http://pleiades.stoa.org/places/99002/darmc-location-17917"
      }
    }
  ]
}