{
  "type": "FeatureCollection",
  "title": "Rullstorf",
  "id": "99030",
  "description": "An ancient place, cited: BAtlas 10 G3 Rullstorf",
  "bbox": [
    10.529762,
    53.286333,
    10.529762,
    53.286333
  ],
  "reprPoint": [
    10.529762,
    53.286333
  ],
  "features": [
    {
      "geometry": {
        "type": "Point",
        "coordinates": [
          10.529762,
          53.286333
        ]
      },
      "id": "darmc-location-14534",
      "type": "Feature",
      "properties": {
        "description": "1M scale point location",
        "location_precision": "precise",
        "title": "DARMC location 14534",
        "link": "http://pleiades.stoa.org/places/99030/darmc-location-14534"
      }
    }
  ]
}