{
  "type": "FeatureCollection",
  "title": "Wiebendorf",
  "id": "99064",
  "description": "An ancient place, cited: BAtlas 10 G3 Wiebendorf",
  "bbox": [
    10.821529,
    53.403543,
    10.821529,
    53.403543
  ],
  "reprPoint": [
    10.821529,
    53.403543
  ],
  "features": [
    {
      "geometry": {
        "type": "Point",
        "coordinates": [
          10.821529,
          53.403543
        ]
      },
      "id": "darmc-location-23638",
      "type": "Feature",
      "properties": {
        "description": "Point location",
        "location_precision": "precise",
        "title": "DARMC location 23638",
        "link": "http://pleiades.stoa.org/places/99064/darmc-location-23638"
      }
    }
  ]
}