{
  "type": "FeatureCollection",
  "title": "Tall al-Disim",
  "id": "992018312",
  "bbox": [
    45.3929,
    32.1415,
    45.3929,
    32.1415
  ],
  "description": "Mound where cuneiform inscription has been found.",
  "features": [
    {
      "type": "Feature",
      "geometry": {
        "type": "Point",
        "coordinates": [
          45.3929,
          32.1415
        ]
      },
      "properties": {
        "description": "representative point"
      }
    },
    {
      "geometry": {
        "type": "Point",
        "coordinates": [
          45.3929,
          32.1415
        ]
      },
      "id": "cigs-location-of-tall-al-disim",
      "type": "Feature",
      "properties": {
        "description": null,
        "location_precision": "precise",
        "title": "CIGS location of Tall al-Disim",
        "link": "http://pleiades.stoa.org/places/992018312/cigs-location-of-tall-al-disim"
      }
    }
  ]
}