{
  "type": "FeatureCollection",
  "title": "Punta della Vipera Etruscan temple",
  "id": "99313926",
  "bbox": [
    11.8256075,
    42.0463351,
    11.8256075,
    42.0463351
  ],
  "description": "A coastal Etruscan sanctuary that dates ca. 540-530 B.C. with additional architectural phases dating to the fourth through second centuries B.C.",
  "features": [
    {
      "type": "Feature",
      "geometry": {
        "type": "Point",
        "coordinates": [
          11.8256075,
          42.0463351
        ]
      },
      "properties": {
        "description": "representative point"
      }
    },
    {
      "geometry": {
        "type": "Point",
        "coordinates": [
          11.8256075,
          42.0463351
        ]
      },
      "id": "osm-location-of-tempio-etrusco-punta-della-vipera",
      "type": "Feature",
      "properties": {
        "description": "Representative location based on OpenStreetMap.",
        "location_precision": "precise",
        "title": "OSM location of Tempio Etrusco Punta della Vipera",
        "link": "http://pleiades.stoa.org/places/99313926/osm-location-of-tempio-etrusco-punta-della-vipera"
      }
    }
  ]
}