{
  "type": "FeatureCollection",
  "title": "Puig de Castellet",
  "id": "996799901",
  "bbox": [
    2.8480864,
    41.7160823,
    2.8480864,
    41.7160823
  ],
  "description": "A pre-Roman oppidum located in the municipality of Lloret de Mar and occupied by the Ausetani. The site was short-lived and abandoned after the Roman conquest.",
  "connectsWith": [
    "246211"
  ],
  "features": [
    {
      "type": "Feature",
      "geometry": {
        "type": "Point",
        "coordinates": [
          2.8480864,
          41.7160823
        ]
      },
      "properties": {
        "description": "representative point"
      }
    },
    {
      "geometry": {
        "type": "Point",
        "coordinates": [
          2.8480864,
          41.7160823
        ]
      },
      "id": "location-of-puig-de-castellet",
      "type": "Feature",
      "properties": {
        "description": "Representative location based on OpenStreetMap.",
        "location_precision": "precise",
        "title": "OSM location of Puig de Castellet",
        "link": "http://pleiades.stoa.org/places/996799901/location-of-puig-de-castellet"
      }
    }
  ]
}