{
  "type": "FeatureCollection",
  "title": "Roman amphitheater at Bern",
  "id": "997994574",
  "bbox": [
    7.451176,
    46.975706,
    7.451176,
    46.975706
  ],
  "description": "The remains of a small Roman amphitheater at Bern, measuring ca. 27.5 x 25.3 meters, are visible on satellite images.",
  "connectsWith": [
    "177471"
  ],
  "features": [
    {
      "type": "Feature",
      "geometry": {
        "type": "Point",
        "coordinates": [
          7.451176,
          46.975706
        ]
      },
      "properties": {
        "description": "representative point"
      }
    },
    {
      "geometry": {
        "type": "Point",
        "coordinates": [
          7.451176,
          46.975706
        ]
      },
      "id": "center-point-of-roman-amfitheather",
      "type": "Feature",
      "properties": {
        "description": "Small amphitheater (27.5 x 25.3 m) visible on satellite images.",
        "location_precision": "precise",
        "title": "Imagery location of Roman amphitheater",
        "link": "http://pleiades.stoa.org/places/997994574/center-point-of-roman-amfitheather"
      }
    }
  ]
}